{
  "comments": [
    "I\u0027ve installed version 3.0.1 from the version 3.0 of the platform using the \nautomatic upgrade functionality from the eclipse 3.0 platform.\nAfter downloading and installing all components of this new version,\nthe platform asks to restart the platform.\nAfter restarting the platform an exception is thrown and the platform does not\nshow up.\n\nI would very much like to know how I can solve this problem quickly or \nreverse the upgrade in a simple manner, in order not to have to reinstall the \nplatform version 3.0.\n\nkind regards,\n\n\nP.S. the log file indicating the exception contains the following:\n\n!SESSION Sep 24, 2004 13:30:58.562 ---------------------------------------------\neclipse.buildId\u003dI200406251208\njava.version\u003d1.4.2_05\njava.vendor\u003dSun Microsystems Inc.\nBootLoader constants: OS\u003dwin32, ARCH\u003dx86, WS\u003dwin32, NL\u003den_US\n\n!ENTRY org.eclipse.osgi Sep 24, 2004 13:30:58.562\n!MESSAGE Application error\n!STACK 1\njava.lang.RuntimeException: No application id has been found.\n\tat org.eclipse.core.internal.runtime.PlatformActivator$1.run\n(PlatformActivator.java:313)\n\tat org.eclipse.core.runtime.adaptor.EclipseStarter.run\n(EclipseStarter.java:273)\n\tat org.eclipse.core.runtime.adaptor.EclipseStarter.run\n(EclipseStarter.java:129)\n\tat sun.reflect.NativeMethodAccessorImpl.invoke0(Native Method)\n\tat sun.reflect.NativeMethodAccessorImpl.invoke(Unknown Source)\n\tat sun.reflect.DelegatingMethodAccessorImpl.invoke(Unknown Source)\n\tat java.lang.reflect.Method.invoke(Unknown Source)\n\tat org.eclipse.core.launcher.Main.basicRun(Main.java:183)\n\tat org.eclipse.core.launcher.Main.run(Main.java:644)\n\tat org.eclipse.core.launcher.Main.main(Main.java:628)\n\n!ENTRY org.eclipse.osgi Sep 24, 2004 13:30:58.578\n!MESSAGE Bundle update@/c:/work/programming tools/eclipse \n3.0/plugins/org.eclipse.update.core.win32_3.0.0/ [3] was not resolved.\n\n!ENTRY org.eclipse.osgi Sep 24, 2004 13:30:58.578\n!MESSAGE Bundle update@/c:/work/programming tools/eclipse \n3.0/plugins/org.eclipse.update.scheduler_3.0.0/ [4] was not resolved.\n\n!ENTRY org.eclipse.osgi Sep 24, 2004 13:30:58.578\n!MESSAGE Bundle update@/c:/work/programming tools/eclipse \n3.0/plugins/org.eclipse.ui.views_3.0.0/ [23] was not resolved.\n\n!ENTRY org.eclipse.osgi Sep 24, 2004 13:30:58.578\n!MESSAGE Bundle update@/c:/work/programming tools/eclipse \n3.0/plugins/org.eclipse.core.resources.win32_3.0.0/ [24] was not resolved.\n\n!ENTRY org.eclipse.osgi Sep 24, 2004 13:30:58.578\n!MESSAGE Bundle update@/c:/work/programming tools/eclipse \n3.0/plugins/org.eclipse.help.ide_3.0.0/ [33] was not resolved.\n\n!ENTRY org.eclipse.osgi Sep 24, 2004 13:30:58.593\n!MESSAGE Bundle update@/c:/work/programming tools/eclipse \n3.0/plugins/org.eclipse.team.cvs.ssh_3.0.0/ [36] was not resolved.\n\n!ENTRY org.eclipse.osgi Sep 24, 2004 13:30:58.593\n!MESSAGE Bundle update@/c:/work/programming tools/eclipse \n3.0/plugins/org.eclipse.compare_3.0.0/ [40] was not resolved.\n\n!ENTRY org.eclipse.osgi Sep 24, 2004 13:30:58.593\n!MESSAGE Bundle update@/c:/work/programming tools/eclipse \n3.0/plugins/org.eclipse.jface_3.0.0/ [41] was not resolved.\n\n!ENTRY org.eclipse.osgi Sep 24, 2004 13:30:58.593\n!MESSAGE Bundle update@/c:/work/programming tools/eclipse \n3.0/plugins/org.eclipse.team.cvs.ssh2_3.0.0/ [50] was not resolved.\n\n!ENTRY org.eclipse.osgi Sep 24, 2004 13:30:58.593\n!MESSAGE Bundle update@/c:/work/programming tools/eclipse \n3.0/plugins/org.eclipse.help.ui_3.0.0/ [51] was not resolved.\n\n!ENTRY org.eclipse.osgi Sep 24, 2004 13:30:58.593\n!MESSAGE Bundle update@/c:/work/programming tools/eclipse \n3.0/plugins/org.eclipse.ui.console_3.0.0/ [56] was not resolved.\n\n!ENTRY org.eclipse.osgi Sep 24, 2004 13:30:58.593\n!MESSAGE Bundle update@/c:/work/programming tools/eclipse \n3.0/plugins/org.eclipse.tomcat_4.1.30/ [64] was not resolved.\n\n!ENTRY org.eclipse.osgi Sep 24, 2004 13:30:58.609\n!MESSAGE Bundle update@/c:/work/programming tools/eclipse \n3.0/plugins/org.eclipse.team.core_3.0.0/ [78] was not resolved.\n\n!ENTRY org.eclipse.osgi Sep 24, 2004 13:30:58.609\n!MESSAGE Bundle update@/c:/work/programming tools/eclipse \n3.0/plugins/org.eclipse.ui.workbench.compatibility_3.0.0/ [83] was not resolved.\n\n!ENTRY org.eclipse.osgi Sep 24, 2004 13:30:58.609\n!MESSAGE Bundle update@/c:/work/programming tools/eclipse \n3.0/plugins/org.eclipse.ui.forms_3.0.0/ [86] was not resolved.\n\n!ENTRY org.eclipse.osgi Sep 24, 2004 13:30:58.609\n!MESSAGE Bundle update@/c:/work/programming tools/eclipse \n3.0/plugins/org.eclipse.ajdt.ui_1.1.12/ [92] was not resolved.\n\n!ENTRY org.eclipse.osgi Sep 24, 2004 13:30:58.609\n!MESSAGE Bundle update@/c:/work/programming tools/eclipse \n3.0/plugins/org.eclipse.ajdt.examples_1.1.12/ [93] was not resolved.\n\n!ENTRY org.eclipse.osgi Sep 24, 2004 13:30:58.609\n!MESSAGE Bundle update@/c:/work/programming tools/eclipse \n3.0/plugins/org.eclipse.contribution.visualiser_2.0.1/ [94] was not resolved.\n\n!ENTRY org.eclipse.osgi Sep 24, 2004 13:30:58.609\n!MESSAGE Bundle update@/c:/work/programming tools/eclipse \n3.0/plugins/org.eclipse.platform.doc.isv_3.0.1/ [96] was not resolved.\n!SUBENTRY 1 org.eclipse.osgi Sep 24, 2004 13:30:58.609\n!MESSAGE Missing required bundle org.eclipse.ui_0.0.0.\n\n!ENTRY org.eclipse.osgi Sep 24, 2004 13:30:58.609\n!MESSAGE Bundle update@/c:/work/programming tools/eclipse \n3.0/plugins/org.eclipse.jdt_3.0.1/ [99] was not resolved.\n!SUBENTRY 1 org.eclipse.osgi Sep 24, 2004 13:30:58.609\n!MESSAGE Missing required bundle org.eclipse.ui.intro_0.0.0.\n!SUBENTRY 1 org.eclipse.osgi Sep 24, 2004 13:30:58.609\n!MESSAGE Missing required bundle org.eclipse.ui.cheatsheets_0.0.0.\n\n!ENTRY org.eclipse.osgi Sep 24, 2004 13:30:58.625\n!MESSAGE Bundle update@/c:/work/programming tools/eclipse \n3.0/plugins/org.eclipse.ant.ui_3.0.1/ [100] was not resolved.\n!SUBENTRY 1 org.eclipse.osgi Sep 24, 2004 13:30:58.625\n!MESSAGE Missing optionally required bundle org.eclipse.ui.ide_0.0.0.\n!SUBENTRY 1 org.eclipse.osgi Sep 24, 2004 13:30:58.625\n!MESSAGE Missing optionally required bundle org.eclipse.ui.views_0.0.0.\n!SUBENTRY 1 org.eclipse.osgi Sep 24, 2004 13:30:58.625\n!MESSAGE Missing optionally required bundle org.eclipse.jface.text_0.0.0.\n!SUBENTRY 1 org.eclipse.osgi Sep 24, 2004 13:30:58.625\n!MESSAGE Missing optionally required bundle \norg.eclipse.ui.workbench.texteditor_0.0.0.\n!SUBENTRY 1 org.eclipse.osgi Sep 24, 2004 13:30:58.625\n!MESSAGE Missing optionally required bundle org.eclipse.ui.editors_0.0.0.\n!SUBENTRY 1 org.eclipse.osgi Sep 24, 2004 13:30:58.625\n!MESSAGE Missing required bundle org.apache.ant_0.0.0.\n!SUBENTRY 1 org.eclipse.osgi Sep 24, 2004 13:30:58.625\n!MESSAGE Missing required bundle org.eclipse.core.resources_0.0.0.\n!SUBENTRY 1 org.eclipse.osgi Sep 24, 2004 13:30:58.625\n!MESSAGE Missing required bundle org.eclipse.core.filebuffers_0.0.0.\n!SUBENTRY 1 org.eclipse.osgi Sep 24, 2004 13:30:58.625\n!MESSAGE Missing required bundle org.eclipse.ui.externaltools_0.0.0.\n!SUBENTRY 1 org.eclipse.osgi Sep 24, 2004 13:30:58.625\n!MESSAGE Missing required bundle org.eclipse.ui_0.0.0.\n!SUBENTRY 1 org.eclipse.osgi Sep 24, 2004 13:30:58.625\n!MESSAGE Missing required bundle org.eclipse.ui.console_0.0.0.\n!SUBENTRY 1 org.eclipse.osgi Sep 24, 2004 13:30:58.625\n!MESSAGE Missing required bundle org.eclipse.debug.core_0.0.0.\n!SUBENTRY 1 org.eclipse.osgi Sep 24, 2004 13:30:58.625\n!MESSAGE Missing required bundle org.eclipse.debug.ui_0.0.0.\n!SUBENTRY 1 org.eclipse.osgi Sep 24, 2004 13:30:58.625\n!MESSAGE Missing required bundle org.eclipse.jdt.ui_0.0.0.\n!SUBENTRY 1 org.eclipse.osgi Sep 24, 2004 13:30:58.625\n!MESSAGE Missing required bundle org.eclipse.jdt.debug.ui_0.0.0.\n!SUBENTRY 1 org.eclipse.osgi Sep 24, 2004 13:30:58.625\n!MESSAGE Missing required bundle org.eclipse.jdt.launching_0.0.0.\n!SUBENTRY 1 org.eclipse.osgi Sep 24, 2004 13:30:58.625\n!MESSAGE Missing required bundle org.eclipse.jdt.core_0.0.0.\n\n!ENTRY org.eclipse.osgi Sep 24, 2004 13:30:58.625\n!MESSAGE Bundle update@/c:/work/programming tools/eclipse \n3.0/plugins/org.eclipse.ltk.core.refactoring_3.0.1/ [101] was not resolved.\n!SUBENTRY 1 org.eclipse.osgi Sep 24, 2004 13:30:58.625\n!MESSAGE Missing required bundle org.eclipse.core.filebuffers_0.0.0.\n!SUBENTRY 1 org.eclipse.osgi Sep 24, 2004 13:30:58.625\n!MESSAGE Missing required bundle org.eclipse.core.resources_0.0.0.\n!SUBENTRY 1 org.eclipse.osgi Sep 24, 2004 13:30:58.625\n!MESSAGE Missing required bundle org.eclipse.text_0.0.0.\n\n!ENTRY org.eclipse.osgi Sep 24, 2004 13:30:58.625\n!MESSAGE Bundle update@/c:/work/programming tools/eclipse \n3.0/plugins/org.eclipse.ltk.ui.refactoring_3.0.1/ [102] was not resolved.\n!SUBENTRY 1 org.eclipse.osgi Sep 24, 2004 13:30:58.625\n!MESSAGE Missing required bundle org.eclipse.core.filebuffers_0.0.0.\n!SUBENTRY 1 org.eclipse.osgi Sep 24, 2004 13:30:58.625\n!MESSAGE Missing required bundle org.eclipse.core.resources_0.0.0.\n!SUBENTRY 1 org.eclipse.osgi Sep 24, 2004 13:30:58.625\n!MESSAGE Missing required bundle org.eclipse.text_0.0.0.\n!SUBENTRY 1 org.eclipse.osgi Sep 24, 2004 13:30:58.625\n!MESSAGE Missing required bundle org.eclipse.ltk.core.refactoring_0.0.0.\n!SUBENTRY 1 org.eclipse.osgi Sep 24, 2004 13:30:58.625\n!MESSAGE Missing required bundle org.eclipse.jdt.core_0.0.0.\n!SUBENTRY 1 org.eclipse.osgi Sep 24, 2004 13:30:58.625\n!MESSAGE Missing required bundle org.eclipse.jface.text_0.0.0.\n!SUBENTRY 1 org.eclipse.osgi Sep 24, 2004 13:30:58.625\n!MESSAGE Missing required bundle org.eclipse.ui_0.0.0.\n!SUBENTRY 1 org.eclipse.osgi Sep 24, 2004 13:30:58.625\n!MESSAGE Missing required bundle org.eclipse.compare_0.0.0.\n!SUBENTRY 1 org.eclipse.osgi Sep 24, 2004 13:30:58.625\n!MESSAGE Missing required bundle org.eclipse.ui.workbench.texteditor_0.0.0.\n\n!ENTRY org.eclipse.osgi Sep 24, 2004 13:30:58.640\n!MESSAGE Bundle update@/c:/work/programming tools/eclipse \n3.0/plugins/org.eclipse.jdt.core_3.0.1/ [103] was not resolved.\n!SUBENTRY 1 org.eclipse.osgi Sep 24, 2004 13:30:58.640\n!MESSAGE Missing required bundle org.eclipse.core.resources_0.0.0.\n!SUBENTRY 1 org.eclipse.osgi Sep 24, 2004 13:30:58.640\n!MESSAGE Missing required bundle org.eclipse.text_0.0.0.\n!SUBENTRY 1 org.eclipse.osgi Sep 24, 2004 13:30:58.640\n!MESSAGE Missing optionally required bundle org.apache.ant_0.0.0.\n!SUBENTRY 1 org.eclipse.osgi Sep 24, 2004 13:30:58.640\n!MESSAGE Missing optionally required bundle org.eclipse.team.core_0.0.0.\n\n!ENTRY org.eclipse.osgi Sep 24, 2004 13:30:58.640\n!MESSAGE Bundle update@/c:/work/programming tools/eclipse \n3.0/plugins/org.eclipse.jdt.debug.ui_3.0.1/ [104] was not resolved.\n!SUBENTRY 1 org.eclipse.osgi Sep 24, 2004 13:30:58.640\n!MESSAGE Missing required bundle org.eclipse.ui.ide_0.0.0.\n!SUBENTRY 1 org.eclipse.osgi Sep 24, 2004 13:30:58.640\n!MESSAGE Missing required bundle org.eclipse.jface.text_0.0.0.\n!SUBENTRY 1 org.eclipse.osgi Sep 24, 2004 13:30:58.640\n!MESSAGE Missing required bundle org.eclipse.ui.workbench.texteditor_0.0.0.\n!SUBENTRY 1 org.eclipse.osgi Sep 24, 2004 13:30:58.640\n!MESSAGE Missing required bundle org.eclipse.ui.editors_0.0.0.\n!SUBENTRY 1 org.eclipse.osgi Sep 24, 2004 13:30:58.640\n!MESSAGE Missing required bundle org.eclipse.ui_0.0.0.\n!SUBENTRY 1 org.eclipse.osgi Sep 24, 2004 13:30:58.640\n!MESSAGE Missing required bundle org.eclipse.core.filebuffers_0.0.0.\n!SUBENTRY 1 org.eclipse.osgi Sep 24, 2004 13:30:58.640\n!MESSAGE Missing required bundle org.eclipse.core.resources_0.0.0.\n!SUBENTRY 1 org.eclipse.osgi Sep 24, 2004 13:30:58.640\n!MESSAGE Missing required bundle org.eclipse.jdt.core_0.0.0.\n!SUBENTRY 1 org.eclipse.osgi Sep 24, 2004 13:30:58.640\n!MESSAGE Missing required bundle org.eclipse.debug.core_0.0.0.\n!SUBENTRY 1 org.eclipse.osgi Sep 24, 2004 13:30:58.640\n!MESSAGE Missing required bundle org.eclipse.debug.ui_0.0.0.\n!SUBENTRY 1 org.eclipse.osgi Sep 24, 2004 13:30:58.640\n!MESSAGE Missing required bundle org.eclipse.jdt.debug_0.0.0.\n!SUBENTRY 1 org.eclipse.osgi Sep 24, 2004 13:30:58.640\n!MESSAGE Missing required bundle org.eclipse.jdt.launching_0.0.0.\n!SUBENTRY 1 org.eclipse.osgi Sep 24, 2004 13:30:58.640\n!MESSAGE Missing required bundle org.eclipse.jdt.ui_0.0.0.\n!SUBENTRY 1 org.eclipse.osgi Sep 24, 2004 13:30:58.640\n!MESSAGE Missing required bundle org.eclipse.ltk.core.refactoring_0.0.0.\n\n!ENTRY org.eclipse.osgi Sep 24, 2004 13:30:58.640\n!MESSAGE Bundle update@/c:/work/programming tools/eclipse \n3.0/plugins/org.eclipse.jdt.debug_3.0.1/ [105] was not resolved.\n!SUBENTRY 1 org.eclipse.osgi Sep 24, 2004 13:30:58.640\n!MESSAGE Missing required bundle org.eclipse.core.resources_0.0.0.\n!SUBENTRY 1 org.eclipse.osgi Sep 24, 2004 13:30:58.656\n!MESSAGE Missing required bundle org.eclipse.debug.core_0.0.0.\n!SUBENTRY 1 org.eclipse.osgi Sep 24, 2004 13:30:58.656\n!MESSAGE Missing required bundle org.eclipse.jdt.core_0.0.0.\n\n!ENTRY org.eclipse.osgi Sep 24, 2004 13:30:58.656\n!MESSAGE Bundle update@/c:/work/programming tools/eclipse \n3.0/plugins/org.eclipse.jdt.junit_3.0.1/ [106] was not resolved.\n!SUBENTRY 1 org.eclipse.osgi Sep 24, 2004 13:30:58.656\n!MESSAGE Missing required bundle org.eclipse.ui.ide_0.0.0.\n!SUBENTRY 1 org.eclipse.osgi Sep 24, 2004 13:30:58.656\n!MESSAGE Missing required bundle org.eclipse.ui.views_0.0.0.\n!SUBENTRY 1 org.eclipse.osgi Sep 24, 2004 13:30:58.656\n!MESSAGE Missing required bundle org.eclipse.jface.text_0.0.0.\n!SUBENTRY 1 org.eclipse.osgi Sep 24, 2004 13:30:58.656\n!MESSAGE Missing required bundle org.eclipse.ui.workbench.texteditor_0.0.0.\n!SUBENTRY 1 org.eclipse.osgi Sep 24, 2004 13:30:58.656\n!MESSAGE Missing required bundle org.eclipse.ui.editors_0.0.0.\n!SUBENTRY 1 org.eclipse.osgi Sep 24, 2004 13:30:58.656\n!MESSAGE Missing required bundle org.eclipse.ui_0.0.0.\n!SUBENTRY 1 org.eclipse.osgi Sep 24, 2004 13:30:58.656\n!MESSAGE Missing required bundle org.eclipse.core.resources_0.0.0.\n!SUBENTRY 1 org.eclipse.osgi Sep 24, 2004 13:30:58.656\n!MESSAGE Missing required bundle org.eclipse.debug.core_0.0.0.\n!SUBENTRY 1 org.eclipse.osgi Sep 24, 2004 13:30:58.656\n!MESSAGE Missing required bundle org.eclipse.debug.ui_0.0.0.\n!SUBENTRY 1 org.eclipse.osgi Sep 24, 2004 13:30:58.656\n!MESSAGE Missing required bundle org.eclipse.jdt.core_0.0.0.\n!SUBENTRY 1 org.eclipse.osgi Sep 24, 2004 13:30:58.656\n!MESSAGE Missing required bundle org.eclipse.jdt.ui_0.0.0.\n!SUBENTRY 1 org.eclipse.osgi Sep 24, 2004 13:30:58.656\n!MESSAGE Missing required bundle org.eclipse.jdt.launching_0.0.0.\n!SUBENTRY 1 org.eclipse.osgi Sep 24, 2004 13:30:58.656\n!MESSAGE Missing required bundle org.eclipse.jdt.debug.ui_0.0.0.\n!SUBENTRY 1 org.eclipse.osgi Sep 24, 2004 13:30:58.656\n!MESSAGE Missing required bundle org.eclipse.compare_0.0.0.\n!SUBENTRY 1 org.eclipse.osgi Sep 24, 2004 13:30:58.656\n!MESSAGE Missing required bundle org.eclipse.ltk.core.refactoring_0.0.0.\n\n!ENTRY org.eclipse.osgi Sep 24, 2004 13:30:58.671\n!MESSAGE Bundle update@/c:/work/programming tools/eclipse \n3.0/plugins/org.eclipse.jdt.launching_3.0.1/ [107] was not resolved.\n!SUBENTRY 1 org.eclipse.osgi Sep 24, 2004 13:30:58.671\n!MESSAGE Missing required bundle org.eclipse.core.resources_0.0.0.\n!SUBENTRY 1 org.eclipse.osgi Sep 24, 2004 13:30:58.671\n!MESSAGE Missing required bundle org.eclipse.jdt.core_0.0.0.\n!SUBENTRY 1 org.eclipse.osgi Sep 24, 2004 13:30:58.671\n!MESSAGE Missing required bundle org.eclipse.debug.core_0.0.0.\n!SUBENTRY 1 org.eclipse.osgi Sep 24, 2004 13:30:58.671\n!MESSAGE Missing required bundle org.eclipse.jdt.debug_0.0.0.\n\n!ENTRY org.eclipse.osgi Sep 24, 2004 13:30:58.671\n!MESSAGE Bundle update@/c:/work/programming tools/eclipse \n3.0/plugins/org.eclipse.jdt.ui_3.0.1/ [108] was not resolved.\n!SUBENTRY 1 org.eclipse.osgi Sep 24, 2004 13:30:58.671\n!MESSAGE Missing required bundle org.eclipse.ui_0.0.0.\n!SUBENTRY 1 org.eclipse.osgi Sep 24, 2004 13:30:58.671\n!MESSAGE Missing required bundle org.eclipse.ui.console_0.0.0.\n!SUBENTRY 1 org.eclipse.osgi Sep 24, 2004 13:30:58.671\n!MESSAGE Missing required bundle org.eclipse.core.resources_0.0.0.\n!SUBENTRY 1 org.eclipse.osgi Sep 24, 2004 13:30:58.671\n!MESSAGE Missing required bundle org.eclipse.jdt.core_0.0.0.\n!SUBENTRY 1 org.eclipse.osgi Sep 24, 2004 13:30:58.671\n!MESSAGE Missing required bundle org.eclipse.search_0.0.0.\n!SUBENTRY 1 org.eclipse.osgi Sep 24, 2004 13:30:58.671\n!MESSAGE Missing required bundle org.eclipse.debug.core_0.0.0.\n!SUBENTRY 1 org.eclipse.osgi Sep 24, 2004 13:30:58.671\n!MESSAGE Missing required bundle org.eclipse.debug.ui_0.0.0.\n!SUBENTRY 1 org.eclipse.osgi Sep 24, 2004 13:30:58.671\n!MESSAGE Missing required bundle org.eclipse.jdt.launching_0.0.0.\n!SUBENTRY 1 org.eclipse.osgi Sep 24, 2004 13:30:58.671\n!MESSAGE Missing required bundle org.eclipse.compare_0.0.0.\n!SUBENTRY 1 org.eclipse.osgi Sep 24, 2004 13:30:58.671\n!MESSAGE Missing required bundle org.eclipse.team.core_0.0.0.\n!SUBENTRY 1 org.eclipse.osgi Sep 24, 2004 13:30:58.671\n!MESSAGE Missing required bundle org.eclipse.core.filebuffers_0.0.0.\n!SUBENTRY 1 org.eclipse.osgi Sep 24, 2004 13:30:58.671\n!MESSAGE Missing required bundle org.eclipse.jface.text_0.0.0.\n!SUBENTRY 1 org.eclipse.osgi Sep 24, 2004 13:30:58.671\n!MESSAGE Missing required bundle org.eclipse.ui.workbench.texteditor_0.0.0.\n!SUBENTRY 1 org.eclipse.osgi Sep 24, 2004 13:30:58.671\n!MESSAGE Missing required bundle org.eclipse.ui.ide_0.0.0.\n!SUBENTRY 1 org.eclipse.osgi Sep 24, 2004 13:30:58.671\n!MESSAGE Missing required bundle org.eclipse.ui.views_0.0.0.\n!SUBENTRY 1 org.eclipse.osgi Sep 24, 2004 13:30:58.671\n!MESSAGE Missing required bundle org.eclipse.ui.editors_0.0.0.\n!SUBENTRY 1 org.eclipse.osgi Sep 24, 2004 13:30:58.671\n!MESSAGE Missing required bundle org.eclipse.ltk.core.refactoring_0.0.0.\n!SUBENTRY 1 org.eclipse.osgi Sep 24, 2004 13:30:58.671\n!MESSAGE Missing required bundle org.eclipse.ltk.ui.refactoring_0.0.0.\n\n!ENTRY org.eclipse.osgi Sep 24, 2004 13:30:58.671\n!MESSAGE Bundle update@/c:/work/programming tools/eclipse \n3.0/plugins/org.eclipse.pde_3.0.1/ [112] was not resolved.\n!SUBENTRY 1 org.eclipse.osgi Sep 24, 2004 13:30:58.671\n!MESSAGE Missing required bundle org.eclipse.pde.core_0.0.0.\n!SUBENTRY 1 org.eclipse.osgi Sep 24, 2004 13:30:58.671\n!MESSAGE Missing required bundle org.eclipse.core.resources_0.0.0.\n!SUBENTRY 1 org.eclipse.osgi Sep 24, 2004 13:30:58.671\n!MESSAGE Missing required bundle org.eclipse.jdt.core_0.0.0.\n!SUBENTRY 1 org.eclipse.osgi Sep 24, 2004 13:30:58.671\n!MESSAGE Missing required bundle org.eclipse.text_0.0.0.\n!SUBENTRY 1 org.eclipse.osgi Sep 24, 2004 13:30:58.671\n!MESSAGE Missing optionally required bundle org.eclipse.ui.intro_0.0.0.\n!SUBENTRY 1 org.eclipse.osgi Sep 24, 2004 13:30:58.671\n!MESSAGE Missing optionally required bundle org.eclipse.ui.cheatsheets_0.0.0.\n\n!ENTRY org.eclipse.osgi Sep 24, 2004 13:30:58.671\n!MESSAGE Bundle update@/c:/work/programming tools/eclipse \n3.0/plugins/org.eclipse.pde.build_3.0.1/ [113] was not resolved.\n!SUBENTRY 1 org.eclipse.osgi Sep 24, 2004 13:30:58.671\n!MESSAGE Missing required bundle org.eclipse.update.core_0.0.0.\n!SUBENTRY 1 org.eclipse.osgi Sep 24, 2004 13:30:58.671\n!MESSAGE Missing required bundle org.apache.ant_0.0.0.\n\n!ENTRY org.eclipse.osgi Sep 24, 2004 13:30:58.671\n!MESSAGE Bundle update@/c:/work/programming tools/eclipse \n3.0/plugins/org.eclipse.pde.core_3.0.1/ [114] was not resolved.\n!SUBENTRY 1 org.eclipse.osgi Sep 24, 2004 13:30:58.671\n!MESSAGE Missing required bundle org.eclipse.core.resources_0.0.0.\n!SUBENTRY 1 org.eclipse.osgi Sep 24, 2004 13:30:58.671\n!MESSAGE Missing required bundle org.eclipse.jdt.core_0.0.0.\n!SUBENTRY 1 org.eclipse.osgi Sep 24, 2004 13:30:58.687\n!MESSAGE Missing required bundle org.eclipse.team.core_0.0.0.\n\n!ENTRY org.eclipse.osgi Sep 24, 2004 13:30:58.687\n!MESSAGE Bundle update@/c:/work/programming tools/eclipse \n3.0/plugins/org.eclipse.pde.runtime_3.0.1/ [115] was not resolved.\n!SUBENTRY 1 org.eclipse.osgi Sep 24, 2004 13:30:58.687\n!MESSAGE Missing required bundle org.eclipse.ui_0.0.0.\n!SUBENTRY 1 org.eclipse.osgi Sep 24, 2004 13:30:58.687\n!MESSAGE Missing required bundle org.eclipse.ui.views_0.0.0.\n\n!ENTRY org.eclipse.osgi Sep 24, 2004 13:30:58.687\n!MESSAGE Bundle update@/c:/work/programming tools/eclipse \n3.0/plugins/org.eclipse.pde.ui_3.0.1/ [116] was not resolved.\n!SUBENTRY 1 org.eclipse.osgi Sep 24, 2004 13:30:58.687\n!MESSAGE Missing required bundle org.eclipse.ui.ide_0.0.0.\n!SUBENTRY 1 org.eclipse.osgi Sep 24, 2004 13:30:58.687\n!MESSAGE Missing required bundle org.eclipse.ui.views_0.0.0.\n!SUBENTRY 1 org.eclipse.osgi Sep 24, 2004 13:30:58.687\n!MESSAGE Missing required bundle org.eclipse.jface.text_0.0.0.\n!SUBENTRY 1 org.eclipse.osgi Sep 24, 2004 13:30:58.687\n!MESSAGE Missing required bundle org.eclipse.ui.workbench.texteditor_0.0.0.\n!SUBENTRY 1 org.eclipse.osgi Sep 24, 2004 13:30:58.687\n!MESSAGE Missing required bundle org.eclipse.ui.editors_0.0.0.\n!SUBENTRY 1 org.eclipse.osgi Sep 24, 2004 13:30:58.687\n!MESSAGE Missing required bundle org.eclipse.core.resources_0.0.0.\n!SUBENTRY 1 org.eclipse.osgi Sep 24, 2004 13:30:58.687\n!MESSAGE Missing required bundle org.eclipse.debug.core_0.0.0.\n!SUBENTRY 1 org.eclipse.osgi Sep 24, 2004 13:30:58.687\n!MESSAGE Missing required bundle org.eclipse.debug.ui_0.0.0.\n!SUBENTRY 1 org.eclipse.osgi Sep 24, 2004 13:30:58.687\n!MESSAGE Missing required bundle org.eclipse.help.base_0.0.0.\n!SUBENTRY 1 org.eclipse.osgi Sep 24, 2004 13:30:58.687\n!MESSAGE Missing required bundle org.eclipse.jdt.core_0.0.0.\n!SUBENTRY 1 org.eclipse.osgi Sep 24, 2004 13:30:58.687\n!MESSAGE Missing required bundle org.eclipse.jdt.debug.ui_0.0.0.\n!SUBENTRY 1 org.eclipse.osgi Sep 24, 2004 13:30:58.687\n!MESSAGE Missing required bundle org.eclipse.jdt.launching_0.0.0.\n!SUBENTRY 1 org.eclipse.osgi Sep 24, 2004 13:30:58.687\n!MESSAGE Missing required bundle org.eclipse.jdt.ui_0.0.0.\n!SUBENTRY 1 org.eclipse.osgi Sep 24, 2004 13:30:58.687\n!MESSAGE Missing required bundle org.eclipse.pde_0.0.0.\n!SUBENTRY 1 org.eclipse.osgi Sep 24, 2004 13:30:58.687\n!MESSAGE Missing required bundle org.eclipse.pde.build_0.0.0.\n!SUBENTRY 1 org.eclipse.osgi Sep 24, 2004 13:30:58.687\n!MESSAGE Missing required bundle org.eclipse.search_0.0.0.\n!SUBENTRY 1 org.eclipse.osgi Sep 24, 2004 13:30:58.687\n!MESSAGE Missing required bundle org.eclipse.team.core_0.0.0.\n!SUBENTRY 1 org.eclipse.osgi Sep 24, 2004 13:30:58.687\n!MESSAGE Missing required bundle org.eclipse.ui_0.0.0.\n!SUBENTRY 1 org.eclipse.osgi Sep 24, 2004 13:30:58.687\n!MESSAGE Missing required bundle org.eclipse.update.core_0.0.0.\n!SUBENTRY 1 org.eclipse.osgi Sep 24, 2004 13:30:58.687\n!MESSAGE Missing required bundle org.eclipse.ui.forms_0.0.0.\n!SUBENTRY 1 org.eclipse.osgi Sep 24, 2004 13:30:58.687\n!MESSAGE Missing required bundle org.eclipse.ant.ui_0.0.0.\n!SUBENTRY 1 org.eclipse.osgi Sep 24, 2004 13:30:58.687\n!MESSAGE Missing required bundle org.eclipse.jdt.junit_0.0.0.\n!SUBENTRY 1 org.eclipse.osgi Sep 24, 2004 13:30:58.687\n!MESSAGE Missing required bundle org.eclipse.ui.intro_0.0.0.\n!SUBENTRY 1 org.eclipse.osgi Sep 24, 2004 13:30:58.687\n!MESSAGE Missing required bundle org.eclipse.ui.cheatsheets_0.0.0.\n\n!ENTRY org.eclipse.osgi Sep 24, 2004 13:30:58.687\n!MESSAGE Bundle update@/c:/work/programming tools/eclipse \n3.0/plugins/org.eclipse.sdk_3.0.1/ [118] was not resolved.\n!SUBENTRY 1 org.eclipse.osgi Sep 24, 2004 13:30:58.687\n!MESSAGE Missing required bundle org.eclipse.ui_0.0.0.",
    "\n\n*** This bug has been marked as a duplicate of 74624 ***"
  ],
  "commentCreationDates": [
    "2004-09-24T13:47:21+02:00",
    "2004-09-24T15:53:55+02:00"
  ],
  "traces": [
    {
      "exceptionType": "java.lang.RuntimeException",
      "message": "No application id has been found.",
      "elements": [
        {
          "method": "org.eclipse.core.internal.runtime.PlatformActivator$1.run",
          "source": "PlatformActivator.java:313"
        },
        {
          "method": "org.eclipse.core.runtime.adaptor.EclipseStarter.run",
          "source": "EclipseStarter.java:273"
        },
        {
          "method": "org.eclipse.core.runtime.adaptor.EclipseStarter.run",
          "source": "EclipseStarter.java:129"
        },
        {
          "method": "sun.reflect.NativeMethodAccessorImpl.invoke0",
          "source": "Native Method"
        },
        {
          "method": "sun.reflect.NativeMethodAccessorImpl.invoke",
          "source": "Unknown Source"
        },
        {
          "method": "sun.reflect.DelegatingMethodAccessorImpl.invoke",
          "source": "Unknown Source"
        },
        {
          "method": "java.lang.reflect.Method.invoke",
          "source": "Unknown Source"
        },
        {
          "method": "org.eclipse.core.launcher.Main.basicRun",
          "source": "Main.java:183"
        },
        {
          "method": "org.eclipse.core.launcher.Main.run",
          "source": "Main.java:644"
        },
        {
          "method": "org.eclipse.core.launcher.Main.main",
          "source": "Main.java:628"
        }
      ],
      "number": 0,
      "commentIndex": 0,
      "bugId": "74941",
      "duplicateId": "74624",
      "date": "2004-09-24T13:47:21+02:00",
      "product": "Platform",
      "component": "Runtime",
      "severity": "critical"
    }
  ],
  "groupId": "74624",
  "bugId": "74941",
  "duplicateId": "74624",
  "date": "2004-09-24T13:47:21+02:00",
  "product": "Platform",
  "component": "Runtime",
  "severity": "critical"
}