{
  "comments": [
    "After the update has retrieved all the software I can not start eclipse. I get \nan error occured see log file message.\n\nI looked at the log file but this is not helping me. How can I get eclipse up \nand running again.\n\nHere is the content of the log file:\n!SESSION okt 02, 2004 12:38:37.718 --------------------------------------------\n-\neclipse.buildId\u003dI200406251208\njava.version\u003d1.4.2_05\njava.vendor\u003dSun Microsystems Inc.\nBootLoader constants: OS\u003dwin32, ARCH\u003dx86, WS\u003dwin32, NL\u003dnl_NL\n\n!ENTRY org.eclipse.osgi okt 02, 2004 12:38:37.734\n!MESSAGE Application error\n!STACK 1\njava.lang.RuntimeException: No application id has been found.\n\tat org.eclipse.core.internal.runtime.PlatformActivator$1.run\n(PlatformActivator.java:313)\n\tat org.eclipse.core.runtime.adaptor.EclipseStarter.run\n(EclipseStarter.java:273)\n\tat org.eclipse.core.runtime.adaptor.EclipseStarter.run\n(EclipseStarter.java:129)\n\tat sun.reflect.NativeMethodAccessorImpl.invoke0(Native Method)\n\tat sun.reflect.NativeMethodAccessorImpl.invoke(Unknown Source)\n\tat sun.reflect.DelegatingMethodAccessorImpl.invoke(Unknown Source)\n\tat java.lang.reflect.Method.invoke(Unknown Source)\n\tat org.eclipse.core.launcher.Main.basicRun(Main.java:183)\n\tat org.eclipse.core.launcher.Main.run(Main.java:644)\n\tat org.eclipse.core.launcher.Main.main(Main.java:628)\n\n!ENTRY org.eclipse.osgi okt 02, 2004 12:38:37.750\n!MESSAGE Bundle update@/c:/Program \nFiles/eclipse/plugins/org.eclipse.compare_3.0.0/ [7] was not resolved.\n\n!ENTRY org.eclipse.osgi okt 02, 2004 12:38:37.750\n!MESSAGE Bundle update@/c:/Program \nFiles/eclipse/plugins/org.eclipse.core.resources.win32_3.0.0/ [11] was not \nresolved.\n\n!ENTRY org.eclipse.osgi okt 02, 2004 12:38:37.765\n!MESSAGE Bundle update@/c:/Program \nFiles/eclipse/plugins/org.eclipse.help.ide_3.0.0/ [20] was not resolved.\n\n!ENTRY org.eclipse.osgi okt 02, 2004 12:38:37.781\n!MESSAGE Bundle update@/c:/Program \nFiles/eclipse/plugins/org.eclipse.help.ui_3.0.0/ [21] was not resolved.\n\n!ENTRY org.eclipse.osgi okt 02, 2004 12:38:37.781\n!MESSAGE Bundle update@/c:/Program \nFiles/eclipse/plugins/org.eclipse.jface_3.0.0/ [36] was not resolved.\n\n!ENTRY org.eclipse.osgi okt 02, 2004 12:38:37.796\n!MESSAGE Bundle update@/c:/Program \nFiles/eclipse/plugins/org.eclipse.team.core_3.0.0/ [59] was not resolved.\n\n!ENTRY org.eclipse.osgi okt 02, 2004 12:38:37.812\n!MESSAGE Bundle update@/c:/Program \nFiles/eclipse/plugins/org.eclipse.team.cvs.ssh2_3.0.0/ [61] was not resolved.\n\n!ENTRY org.eclipse.osgi okt 02, 2004 12:38:37.812\n!MESSAGE Bundle update@/c:/Program \nFiles/eclipse/plugins/org.eclipse.team.cvs.ssh_3.0.0/ [62] was not resolved.\n\n!ENTRY org.eclipse.osgi okt 02, 2004 12:38:37.828\n!MESSAGE Bundle update@/c:/Program \nFiles/eclipse/plugins/org.eclipse.tomcat_4.1.30/ [66] was not resolved.\n\n!ENTRY org.eclipse.osgi okt 02, 2004 12:38:37.828\n!MESSAGE Bundle update@/c:/Program \nFiles/eclipse/plugins/org.eclipse.ui.console_3.0.0/ [68] was not resolved.\n\n!ENTRY org.eclipse.osgi okt 02, 2004 12:38:37.843\n!MESSAGE Bundle update@/c:/Program \nFiles/eclipse/plugins/org.eclipse.ui.forms_3.0.0/ [71] was not resolved.\n\n!ENTRY org.eclipse.osgi okt 02, 2004 12:38:37.843\n!MESSAGE Bundle update@/c:/Program \nFiles/eclipse/plugins/org.eclipse.ui.views_3.0.0/ [75] was not resolved.\n\n!ENTRY org.eclipse.osgi okt 02, 2004 12:38:37.859\n!MESSAGE Bundle update@/c:/Program \nFiles/eclipse/plugins/org.eclipse.ui.workbench.compatibility_3.0.0/ [77] was \nnot resolved.\n\n!ENTRY org.eclipse.osgi okt 02, 2004 12:38:37.875\n!MESSAGE Bundle update@/c:/Program \nFiles/eclipse/plugins/org.eclipse.update.core.win32_3.0.0/ [82] was not \nresolved.\n\n!ENTRY org.eclipse.osgi okt 02, 2004 12:38:37.875\n!MESSAGE Bundle update@/c:/Program \nFiles/eclipse/plugins/org.eclipse.update.scheduler_3.0.0/ [84] was not \nresolved.\n\n!ENTRY org.eclipse.osgi okt 02, 2004 12:38:37.890\n!MESSAGE Bundle update@/c:/Program \nFiles/eclipse/plugins/org.eclipse.compare.examples.xml_3.0.0/ [87] was not \nresolved.\n\n!ENTRY org.eclipse.osgi okt 02, 2004 12:38:37.906\n!MESSAGE Bundle update@/c:/Program \nFiles/eclipse/plugins/org.eclipse.compare.examples_3.0.0/ [88] was not \nresolved.\n\n!ENTRY org.eclipse.osgi okt 02, 2004 12:38:37.921\n!MESSAGE Bundle update@/c:/Program \nFiles/eclipse/plugins/org.eclipse.draw2d_3.0.0/ [91] was not resolved.\n\n!ENTRY org.eclipse.osgi okt 02, 2004 12:38:37.921\n!MESSAGE Bundle update@/c:/Program \nFiles/eclipse/plugins/org.eclipse.gef.doc.isv_3.0.0/ [92] was not resolved.\n\n!ENTRY org.eclipse.osgi okt 02, 2004 12:38:37.937\n!MESSAGE Bundle update@/c:/Program \nFiles/eclipse/plugins/org.eclipse.gef.examples.flow_3.0.0/ [93] was not \nresolved.\n\n!ENTRY org.eclipse.osgi okt 02, 2004 12:38:37.953\n!MESSAGE Bundle update@/c:/Program \nFiles/eclipse/plugins/org.eclipse.gef.examples.logic_3.0.0/ [94] was not \nresolved.\n\n!ENTRY org.eclipse.osgi okt 02, 2004 12:38:37.953\n!MESSAGE Bundle update@/c:/Program \nFiles/eclipse/plugins/org.eclipse.gef_3.0.0/ [97] was not resolved.\n\n!ENTRY org.eclipse.osgi okt 02, 2004 12:38:37.968\n!MESSAGE Bundle update@/c:/Program \nFiles/eclipse/plugins/org.eclipse.jdt.ui.examples.projects_3.0.0/ [99] was not \nresolved.\n\n!ENTRY org.eclipse.osgi okt 02, 2004 12:38:37.984\n!MESSAGE Bundle update@/c:/Program \nFiles/eclipse/plugins/org.eclipse.swt.examples.browser_3.0.0/ [104] was not \nresolved.\n\n!ENTRY org.eclipse.osgi okt 02, 2004 12:38:37.984\n!MESSAGE Bundle update@/c:/Program \nFiles/eclipse/plugins/org.eclipse.swt.examples.controls_3.0.0/ [105] was not \nresolved.\n\n!ENTRY org.eclipse.osgi okt 02, 2004 12:38:38.00\n!MESSAGE Bundle update@/c:/Program \nFiles/eclipse/plugins/org.eclipse.swt.examples.launcher_3.0.0/ [106] was not \nresolved.\n\n!ENTRY org.eclipse.osgi okt 02, 2004 12:38:38.15\n!MESSAGE Bundle update@/c:/Program \nFiles/eclipse/plugins/org.eclipse.swt.examples.layouts_3.0.0/ [107] was not \nresolved.\n\n!ENTRY org.eclipse.osgi okt 02, 2004 12:38:38.31\n!MESSAGE Bundle update@/c:/Program \nFiles/eclipse/plugins/org.eclipse.swt.examples.ole.win32_3.0.0/ [108] was not \nresolved.\n\n!ENTRY org.eclipse.osgi okt 02, 2004 12:38:38.31\n!MESSAGE Bundle update@/c:/Program \nFiles/eclipse/plugins/org.eclipse.swt.examples.paint_3.0.0/ [109] was not \nresolved.\n\n!ENTRY org.eclipse.osgi okt 02, 2004 12:38:38.46\n!MESSAGE Bundle update@/c:/Program \nFiles/eclipse/plugins/org.eclipse.swt.examples_3.0.0/ [110] was not resolved.\n\n!ENTRY org.eclipse.osgi okt 02, 2004 12:38:38.62\n!MESSAGE Bundle update@/c:/Program \nFiles/eclipse/plugins/org.eclipse.team.examples.filesystem_3.0.0/ [111] was \nnot resolved.\n\n!ENTRY org.eclipse.osgi okt 02, 2004 12:38:38.62\n!MESSAGE Bundle update@/c:/Program \nFiles/eclipse/plugins/org.eclipse.team.ftp_3.0.0/ [114] was not resolved.\n\n!ENTRY org.eclipse.osgi okt 02, 2004 12:38:38.78\n!MESSAGE Bundle update@/c:/Program \nFiles/eclipse/plugins/org.eclipse.team.webdav_3.0.0/ [115] was not resolved.\n\n!ENTRY org.eclipse.osgi okt 02, 2004 12:38:38.93\n!MESSAGE Bundle update@/c:/Program \nFiles/eclipse/plugins/org.eclipse.ui.examples.javaeditor_3.0.0/ [116] was not \nresolved.\n\n!ENTRY org.eclipse.osgi okt 02, 2004 12:38:38.93\n!MESSAGE Bundle update@/c:/Program \nFiles/eclipse/plugins/org.eclipse.ui.examples.multipageeditor_2.1.0/ [117] was \nnot resolved.\n\n!ENTRY org.eclipse.osgi okt 02, 2004 12:38:38.109\n!MESSAGE Bundle update@/c:/Program \nFiles/eclipse/plugins/org.eclipse.ui.examples.propertysheet_2.1.0/ [118] was \nnot resolved.\n\n!ENTRY org.eclipse.osgi okt 02, 2004 12:38:38.125\n!MESSAGE Bundle update@/c:/Program \nFiles/eclipse/plugins/org.eclipse.ui.examples.readmetool_2.1.0/ [119] was not \nresolved.\n\n!ENTRY org.eclipse.osgi okt 02, 2004 12:38:38.140\n!MESSAGE Bundle update@/c:/Program \nFiles/eclipse/plugins/org.eclipse.ant.ui_3.0.1/ [163] was not resolved.\n!SUBENTRY 1 org.eclipse.osgi okt 02, 2004 12:38:38.140\n!MESSAGE Missing optionally required bundle org.eclipse.ui.ide_0.0.0.\n!SUBENTRY 1 org.eclipse.osgi okt 02, 2004 12:38:38.140\n!MESSAGE Missing optionally required bundle org.eclipse.ui.views_0.0.0.\n!SUBENTRY 1 org.eclipse.osgi okt 02, 2004 12:38:38.140\n!MESSAGE Missing optionally required bundle org.eclipse.jface.text_0.0.0.\n!SUBENTRY 1 org.eclipse.osgi okt 02, 2004 12:38:38.140\n!MESSAGE Missing optionally required bundle \norg.eclipse.ui.workbench.texteditor_0.0.0.\n!SUBENTRY 1 org.eclipse.osgi okt 02, 2004 12:38:38.140\n!MESSAGE Missing optionally required bundle org.eclipse.ui.editors_0.0.0.\n!SUBENTRY 1 org.eclipse.osgi okt 02, 2004 12:38:38.140\n!MESSAGE Missing required bundle org.apache.ant_0.0.0.\n!SUBENTRY 1 org.eclipse.osgi okt 02, 2004 12:38:38.140\n!MESSAGE Missing required bundle org.eclipse.core.resources_0.0.0.\n!SUBENTRY 1 org.eclipse.osgi okt 02, 2004 12:38:38.140\n!MESSAGE Missing required bundle org.eclipse.core.filebuffers_0.0.0.\n!SUBENTRY 1 org.eclipse.osgi okt 02, 2004 12:38:38.140\n!MESSAGE Missing required bundle org.eclipse.ui.externaltools_0.0.0.\n!SUBENTRY 1 org.eclipse.osgi okt 02, 2004 12:38:38.140\n!MESSAGE Missing required bundle org.eclipse.ui_0.0.0.\n!SUBENTRY 1 org.eclipse.osgi okt 02, 2004 12:38:38.140\n!MESSAGE Missing required bundle org.eclipse.ui.console_0.0.0.\n!SUBENTRY 1 org.eclipse.osgi okt 02, 2004 12:38:38.140\n!MESSAGE Missing required bundle org.eclipse.debug.core_0.0.0.\n!SUBENTRY 1 org.eclipse.osgi okt 02, 2004 12:38:38.140\n!MESSAGE Missing required bundle org.eclipse.debug.ui_0.0.0.\n!SUBENTRY 1 org.eclipse.osgi okt 02, 2004 12:38:38.140\n!MESSAGE Missing required bundle org.eclipse.jdt.ui_0.0.0.\n!SUBENTRY 1 org.eclipse.osgi okt 02, 2004 12:38:38.140\n!MESSAGE Missing required bundle org.eclipse.jdt.debug.ui_0.0.0.\n!SUBENTRY 1 org.eclipse.osgi okt 02, 2004 12:38:38.140\n!MESSAGE Missing required bundle org.eclipse.jdt.launching_0.0.0.\n!SUBENTRY 1 org.eclipse.osgi okt 02, 2004 12:38:38.140\n!MESSAGE Missing required bundle org.eclipse.jdt.core_0.0.0.\n\n!ENTRY org.eclipse.osgi okt 02, 2004 12:38:38.156\n!MESSAGE Bundle update@/c:/Program \nFiles/eclipse/plugins/org.eclipse.jdt.core_3.0.1/ [164] was not resolved.\n!SUBENTRY 1 org.eclipse.osgi okt 02, 2004 12:38:38.156\n!MESSAGE Missing required bundle org.eclipse.core.resources_0.0.0.\n!SUBENTRY 1 org.eclipse.osgi okt 02, 2004 12:38:38.156\n!MESSAGE Missing required bundle org.eclipse.text_0.0.0.\n!SUBENTRY 1 org.eclipse.osgi okt 02, 2004 12:38:38.171\n!MESSAGE Missing optionally required bundle org.apache.ant_0.0.0.\n!SUBENTRY 1 org.eclipse.osgi okt 02, 2004 12:38:38.171\n!MESSAGE Missing optionally required bundle org.eclipse.team.core_0.0.0.\n\n!ENTRY org.eclipse.osgi okt 02, 2004 12:38:38.187\n!MESSAGE Bundle update@/c:/Program \nFiles/eclipse/plugins/org.eclipse.jdt.debug.ui_3.0.1/ [165] was not resolved.\n!SUBENTRY 1 org.eclipse.osgi okt 02, 2004 12:38:38.187\n!MESSAGE Missing required bundle org.eclipse.ui.ide_0.0.0.\n!SUBENTRY 1 org.eclipse.osgi okt 02, 2004 12:38:38.187\n!MESSAGE Missing required bundle org.eclipse.jface.text_0.0.0.\n!SUBENTRY 1 org.eclipse.osgi okt 02, 2004 12:38:38.187\n!MESSAGE Missing required bundle org.eclipse.ui.workbench.texteditor_0.0.0.\n!SUBENTRY 1 org.eclipse.osgi okt 02, 2004 12:38:38.187\n!MESSAGE Missing required bundle org.eclipse.ui.editors_0.0.0.\n!SUBENTRY 1 org.eclipse.osgi okt 02, 2004 12:38:38.187\n!MESSAGE Missing required bundle org.eclipse.ui_0.0.0.\n!SUBENTRY 1 org.eclipse.osgi okt 02, 2004 12:38:38.187\n!MESSAGE Missing required bundle org.eclipse.core.filebuffers_0.0.0.\n!SUBENTRY 1 org.eclipse.osgi okt 02, 2004 12:38:38.187\n!MESSAGE Missing required bundle org.eclipse.core.resources_0.0.0.\n!SUBENTRY 1 org.eclipse.osgi okt 02, 2004 12:38:38.187\n!MESSAGE Missing required bundle org.eclipse.jdt.core_0.0.0.\n!SUBENTRY 1 org.eclipse.osgi okt 02, 2004 12:38:38.187\n!MESSAGE Missing required bundle org.eclipse.debug.core_0.0.0.\n!SUBENTRY 1 org.eclipse.osgi okt 02, 2004 12:38:38.187\n!MESSAGE Missing required bundle org.eclipse.debug.ui_0.0.0.\n!SUBENTRY 1 org.eclipse.osgi okt 02, 2004 12:38:38.187\n!MESSAGE Missing required bundle org.eclipse.jdt.debug_0.0.0.\n!SUBENTRY 1 org.eclipse.osgi okt 02, 2004 12:38:38.187\n!MESSAGE Missing required bundle org.eclipse.jdt.launching_0.0.0.\n!SUBENTRY 1 org.eclipse.osgi okt 02, 2004 12:38:38.187\n!MESSAGE Missing required bundle org.eclipse.jdt.ui_0.0.0.\n!SUBENTRY 1 org.eclipse.osgi okt 02, 2004 12:38:38.187\n!MESSAGE Missing required bundle org.eclipse.ltk.core.refactoring_0.0.0.\n\n!ENTRY org.eclipse.osgi okt 02, 2004 12:38:38.203\n!MESSAGE Bundle update@/c:/Program \nFiles/eclipse/plugins/org.eclipse.jdt.debug_3.0.1/ [166] was not resolved.\n!SUBENTRY 1 org.eclipse.osgi okt 02, 2004 12:38:38.203\n!MESSAGE Missing required bundle org.eclipse.core.resources_0.0.0.\n!SUBENTRY 1 org.eclipse.osgi okt 02, 2004 12:38:38.203\n!MESSAGE Missing required bundle org.eclipse.debug.core_0.0.0.\n!SUBENTRY 1 org.eclipse.osgi okt 02, 2004 12:38:38.203\n!MESSAGE Missing required bundle org.eclipse.jdt.core_0.0.0.\n\n!ENTRY org.eclipse.osgi okt 02, 2004 12:38:38.218\n!MESSAGE Bundle update@/c:/Program \nFiles/eclipse/plugins/org.eclipse.jdt.junit_3.0.1/ [169] was not resolved.\n!SUBENTRY 1 org.eclipse.osgi okt 02, 2004 12:38:38.218\n!MESSAGE Missing required bundle org.eclipse.ui.ide_0.0.0.\n!SUBENTRY 1 org.eclipse.osgi okt 02, 2004 12:38:38.218\n!MESSAGE Missing required bundle org.eclipse.ui.views_0.0.0.\n!SUBENTRY 1 org.eclipse.osgi okt 02, 2004 12:38:38.218\n!MESSAGE Missing required bundle org.eclipse.jface.text_0.0.0.\n!SUBENTRY 1 org.eclipse.osgi okt 02, 2004 12:38:38.218\n!MESSAGE Missing required bundle org.eclipse.ui.workbench.texteditor_0.0.0.\n!SUBENTRY 1 org.eclipse.osgi okt 02, 2004 12:38:38.218\n!MESSAGE Missing required bundle org.eclipse.ui.editors_0.0.0.\n!SUBENTRY 1 org.eclipse.osgi okt 02, 2004 12:38:38.218\n!MESSAGE Missing required bundle org.eclipse.ui_0.0.0.\n!SUBENTRY 1 org.eclipse.osgi okt 02, 2004 12:38:38.218\n!MESSAGE Missing required bundle org.eclipse.core.resources_0.0.0.\n!SUBENTRY 1 org.eclipse.osgi okt 02, 2004 12:38:38.218\n!MESSAGE Missing required bundle org.eclipse.debug.core_0.0.0.\n!SUBENTRY 1 org.eclipse.osgi okt 02, 2004 12:38:38.218\n!MESSAGE Missing required bundle org.eclipse.debug.ui_0.0.0.\n!SUBENTRY 1 org.eclipse.osgi okt 02, 2004 12:38:38.218\n!MESSAGE Missing required bundle org.eclipse.jdt.core_0.0.0.\n!SUBENTRY 1 org.eclipse.osgi okt 02, 2004 12:38:38.218\n!MESSAGE Missing required bundle org.eclipse.jdt.ui_0.0.0.\n!SUBENTRY 1 org.eclipse.osgi okt 02, 2004 12:38:38.218\n!MESSAGE Missing required bundle org.eclipse.jdt.launching_0.0.0.\n!SUBENTRY 1 org.eclipse.osgi okt 02, 2004 12:38:38.218\n!MESSAGE Missing required bundle org.eclipse.jdt.debug.ui_0.0.0.\n!SUBENTRY 1 org.eclipse.osgi okt 02, 2004 12:38:38.218\n!MESSAGE Missing required bundle org.eclipse.compare_0.0.0.\n!SUBENTRY 1 org.eclipse.osgi okt 02, 2004 12:38:38.218\n!MESSAGE Missing required bundle org.eclipse.ltk.core.refactoring_0.0.0.\n\n!ENTRY org.eclipse.osgi okt 02, 2004 12:38:38.234\n!MESSAGE Bundle update@/c:/Program \nFiles/eclipse/plugins/org.eclipse.jdt.launching_3.0.1/ [170] was not resolved.\n!SUBENTRY 1 org.eclipse.osgi okt 02, 2004 12:38:38.234\n!MESSAGE Missing required bundle org.eclipse.core.resources_0.0.0.\n!SUBENTRY 1 org.eclipse.osgi okt 02, 2004 12:38:38.234\n!MESSAGE Missing required bundle org.eclipse.jdt.core_0.0.0.\n!SUBENTRY 1 org.eclipse.osgi okt 02, 2004 12:38:38.265\n!MESSAGE Missing required bundle org.eclipse.debug.core_0.0.0.\n!SUBENTRY 1 org.eclipse.osgi okt 02, 2004 12:38:38.265\n!MESSAGE Missing required bundle org.eclipse.jdt.debug_0.0.0.\n\n!ENTRY org.eclipse.osgi okt 02, 2004 12:38:38.281\n!MESSAGE Bundle update@/c:/Program \nFiles/eclipse/plugins/org.eclipse.jdt.ui_3.0.1/ [172] was not resolved.\n!SUBENTRY 1 org.eclipse.osgi okt 02, 2004 12:38:38.281\n!MESSAGE Missing required bundle org.eclipse.ui_0.0.0.\n!SUBENTRY 1 org.eclipse.osgi okt 02, 2004 12:38:38.281\n!MESSAGE Missing required bundle org.eclipse.ui.console_0.0.0.\n!SUBENTRY 1 org.eclipse.osgi okt 02, 2004 12:38:38.281\n!MESSAGE Missing required bundle org.eclipse.core.resources_0.0.0.\n!SUBENTRY 1 org.eclipse.osgi okt 02, 2004 12:38:38.281\n!MESSAGE Missing required bundle org.eclipse.jdt.core_0.0.0.\n!SUBENTRY 1 org.eclipse.osgi okt 02, 2004 12:38:38.281\n!MESSAGE Missing required bundle org.eclipse.search_0.0.0.\n!SUBENTRY 1 org.eclipse.osgi okt 02, 2004 12:38:38.281\n!MESSAGE Missing required bundle org.eclipse.debug.core_0.0.0.\n!SUBENTRY 1 org.eclipse.osgi okt 02, 2004 12:38:38.281\n!MESSAGE Missing required bundle org.eclipse.debug.ui_0.0.0.\n!SUBENTRY 1 org.eclipse.osgi okt 02, 2004 12:38:38.281\n!MESSAGE Missing required bundle org.eclipse.jdt.launching_0.0.0.\n!SUBENTRY 1 org.eclipse.osgi okt 02, 2004 12:38:38.281\n!MESSAGE Missing required bundle org.eclipse.compare_0.0.0.\n!SUBENTRY 1 org.eclipse.osgi okt 02, 2004 12:38:38.281\n!MESSAGE Missing required bundle org.eclipse.team.core_0.0.0.\n!SUBENTRY 1 org.eclipse.osgi okt 02, 2004 12:38:38.281\n!MESSAGE Missing required bundle org.eclipse.core.filebuffers_0.0.0.\n!SUBENTRY 1 org.eclipse.osgi okt 02, 2004 12:38:38.281\n!MESSAGE Missing required bundle org.eclipse.jface.text_0.0.0.\n!SUBENTRY 1 org.eclipse.osgi okt 02, 2004 12:38:38.281\n!MESSAGE Missing required bundle org.eclipse.ui.workbench.texteditor_0.0.0.\n!SUBENTRY 1 org.eclipse.osgi okt 02, 2004 12:38:38.281\n!MESSAGE Missing required bundle org.eclipse.ui.ide_0.0.0.\n!SUBENTRY 1 org.eclipse.osgi okt 02, 2004 12:38:38.281\n!MESSAGE Missing required bundle org.eclipse.ui.views_0.0.0.\n!SUBENTRY 1 org.eclipse.osgi okt 02, 2004 12:38:38.281\n!MESSAGE Missing required bundle org.eclipse.ui.editors_0.0.0.\n!SUBENTRY 1 org.eclipse.osgi okt 02, 2004 12:38:38.281\n!MESSAGE Missing required bundle org.eclipse.ltk.core.refactoring_0.0.0.\n!SUBENTRY 1 org.eclipse.osgi okt 02, 2004 12:38:38.281\n!MESSAGE Missing required bundle org.eclipse.ltk.ui.refactoring_0.0.0.\n\n!ENTRY org.eclipse.osgi okt 02, 2004 12:38:38.296\n!MESSAGE Bundle update@/c:/Program \nFiles/eclipse/plugins/org.eclipse.jdt_3.0.1/ [173] was not resolved.\n!SUBENTRY 1 org.eclipse.osgi okt 02, 2004 12:38:38.296\n!MESSAGE Missing required bundle org.eclipse.ui.intro_0.0.0.\n!SUBENTRY 1 org.eclipse.osgi okt 02, 2004 12:38:38.296\n!MESSAGE Missing required bundle org.eclipse.ui.cheatsheets_0.0.0.\n\n!ENTRY org.eclipse.osgi okt 02, 2004 12:38:38.328\n!MESSAGE Bundle update@/c:/Program \nFiles/eclipse/plugins/org.eclipse.ltk.core.refactoring_3.0.1/ [174] was not \nresolved.\n!SUBENTRY 1 org.eclipse.osgi okt 02, 2004 12:38:38.328\n!MESSAGE Missing required bundle org.eclipse.core.filebuffers_0.0.0.\n!SUBENTRY 1 org.eclipse.osgi okt 02, 2004 12:38:38.328\n!MESSAGE Missing required bundle org.eclipse.core.resources_0.0.0.\n!SUBENTRY 1 org.eclipse.osgi okt 02, 2004 12:38:38.328\n!MESSAGE Missing required bundle org.eclipse.text_0.0.0.\n\n!ENTRY org.eclipse.osgi okt 02, 2004 12:38:38.328\n!MESSAGE Bundle update@/c:/Program \nFiles/eclipse/plugins/org.eclipse.ltk.ui.refactoring_3.0.1/ [175] was not \nresolved.\n!SUBENTRY 1 org.eclipse.osgi okt 02, 2004 12:38:38.328\n!MESSAGE Missing required bundle org.eclipse.core.filebuffers_0.0.0.\n!SUBENTRY 1 org.eclipse.osgi okt 02, 2004 12:38:38.343\n!MESSAGE Missing required bundle org.eclipse.core.resources_0.0.0.\n!SUBENTRY 1 org.eclipse.osgi okt 02, 2004 12:38:38.343\n!MESSAGE Missing required bundle org.eclipse.text_0.0.0.\n!SUBENTRY 1 org.eclipse.osgi okt 02, 2004 12:38:38.343\n!MESSAGE Missing required bundle org.eclipse.ltk.core.refactoring_0.0.0.\n!SUBENTRY 1 org.eclipse.osgi okt 02, 2004 12:38:38.343\n!MESSAGE Missing required bundle org.eclipse.jdt.core_0.0.0.\n!SUBENTRY 1 org.eclipse.osgi okt 02, 2004 12:38:38.343\n!MESSAGE Missing required bundle org.eclipse.jface.text_0.0.0.\n!SUBENTRY 1 org.eclipse.osgi okt 02, 2004 12:38:38.343\n!MESSAGE Missing required bundle org.eclipse.ui_0.0.0.\n!SUBENTRY 1 org.eclipse.osgi okt 02, 2004 12:38:38.343\n!MESSAGE Missing required bundle org.eclipse.compare_0.0.0.\n!SUBENTRY 1 org.eclipse.osgi okt 02, 2004 12:38:38.343\n!MESSAGE Missing required bundle org.eclipse.ui.workbench.texteditor_0.0.0.\n\n!ENTRY org.eclipse.osgi okt 02, 2004 12:38:38.343\n!MESSAGE Bundle update@/c:/Program \nFiles/eclipse/plugins/org.eclipse.pde.build_3.0.1/ [176] was not resolved.\n!SUBENTRY 1 org.eclipse.osgi okt 02, 2004 12:38:38.343\n!MESSAGE Missing required bundle org.eclipse.update.core_0.0.0.\n!SUBENTRY 1 org.eclipse.osgi okt 02, 2004 12:38:38.343\n!MESSAGE Missing required bundle org.apache.ant_0.0.0.\n\n!ENTRY org.eclipse.osgi okt 02, 2004 12:38:38.375\n!MESSAGE Bundle update@/c:/Program \nFiles/eclipse/plugins/org.eclipse.pde.core_3.0.1/ [177] was not resolved.\n!SUBENTRY 1 org.eclipse.osgi okt 02, 2004 12:38:38.375\n!MESSAGE Missing required bundle org.eclipse.core.resources_0.0.0.\n!SUBENTRY 1 org.eclipse.osgi okt 02, 2004 12:38:38.375\n!MESSAGE Missing required bundle org.eclipse.jdt.core_0.0.0.\n!SUBENTRY 1 org.eclipse.osgi okt 02, 2004 12:38:38.375\n!MESSAGE Missing required bundle org.eclipse.team.core_0.0.0.\n\n!ENTRY org.eclipse.osgi okt 02, 2004 12:38:38.390\n!MESSAGE Bundle update@/c:/Program \nFiles/eclipse/plugins/org.eclipse.pde.runtime_3.0.1/ [178] was not resolved.\n!SUBENTRY 1 org.eclipse.osgi okt 02, 2004 12:38:38.390\n!MESSAGE Missing required bundle org.eclipse.ui_0.0.0.\n!SUBENTRY 1 org.eclipse.osgi okt 02, 2004 12:38:38.390\n!MESSAGE Missing required bundle org.eclipse.ui.views_0.0.0.\n\n!ENTRY org.eclipse.osgi okt 02, 2004 12:38:38.406\n!MESSAGE Bundle update@/c:/Program \nFiles/eclipse/plugins/org.eclipse.pde.ui_3.0.1/ [180] was not resolved.\n!SUBENTRY 1 org.eclipse.osgi okt 02, 2004 12:38:38.406\n!MESSAGE Missing required bundle org.eclipse.ui.ide_0.0.0.\n!SUBENTRY 1 org.eclipse.osgi okt 02, 2004 12:38:38.406\n!MESSAGE Missing required bundle org.eclipse.ui.views_0.0.0.\n!SUBENTRY 1 org.eclipse.osgi okt 02, 2004 12:38:38.406\n!MESSAGE Missing required bundle org.eclipse.jface.text_0.0.0.\n!SUBENTRY 1 org.eclipse.osgi okt 02, 2004 12:38:38.437\n!MESSAGE Missing required bundle org.eclipse.ui.workbench.texteditor_0.0.0.\n!SUBENTRY 1 org.eclipse.osgi okt 02, 2004 12:38:38.437\n!MESSAGE Missing required bundle org.eclipse.ui.editors_0.0.0.\n!SUBENTRY 1 org.eclipse.osgi okt 02, 2004 12:38:38.437\n!MESSAGE Missing required bundle org.eclipse.core.resources_0.0.0.\n!SUBENTRY 1 org.eclipse.osgi okt 02, 2004 12:38:38.437\n!MESSAGE Missing required bundle org.eclipse.debug.core_0.0.0.\n!SUBENTRY 1 org.eclipse.osgi okt 02, 2004 12:38:38.437\n!MESSAGE Missing required bundle org.eclipse.debug.ui_0.0.0.\n!SUBENTRY 1 org.eclipse.osgi okt 02, 2004 12:38:38.437\n!MESSAGE Missing required bundle org.eclipse.help.base_0.0.0.\n!SUBENTRY 1 org.eclipse.osgi okt 02, 2004 12:38:38.437\n!MESSAGE Missing required bundle org.eclipse.jdt.core_0.0.0.\n!SUBENTRY 1 org.eclipse.osgi okt 02, 2004 12:38:38.437\n!MESSAGE Missing required bundle org.eclipse.jdt.debug.ui_0.0.0.\n!SUBENTRY 1 org.eclipse.osgi okt 02, 2004 12:38:38.437\n!MESSAGE Missing required bundle org.eclipse.jdt.launching_0.0.0.\n!SUBENTRY 1 org.eclipse.osgi okt 02, 2004 12:38:38.437\n!MESSAGE Missing required bundle org.eclipse.jdt.ui_0.0.0.\n!SUBENTRY 1 org.eclipse.osgi okt 02, 2004 12:38:38.437\n!MESSAGE Missing required bundle org.eclipse.pde_0.0.0.\n!SUBENTRY 1 org.eclipse.osgi okt 02, 2004 12:38:38.437\n!MESSAGE Missing required bundle org.eclipse.pde.build_0.0.0.\n!SUBENTRY 1 org.eclipse.osgi okt 02, 2004 12:38:38.437\n!MESSAGE Missing required bundle org.eclipse.search_0.0.0.\n!SUBENTRY 1 org.eclipse.osgi okt 02, 2004 12:38:38.437\n!MESSAGE Missing required bundle org.eclipse.team.core_0.0.0.\n!SUBENTRY 1 org.eclipse.osgi okt 02, 2004 12:38:38.437\n!MESSAGE Missing required bundle org.eclipse.ui_0.0.0.\n!SUBENTRY 1 org.eclipse.osgi okt 02, 2004 12:38:38.437\n!MESSAGE Missing required bundle org.eclipse.update.core_0.0.0.\n!SUBENTRY 1 org.eclipse.osgi okt 02, 2004 12:38:38.437\n!MESSAGE Missing required bundle org.eclipse.ui.forms_0.0.0.\n!SUBENTRY 1 org.eclipse.osgi okt 02, 2004 12:38:38.437\n!MESSAGE Missing required bundle org.eclipse.ant.ui_0.0.0.\n!SUBENTRY 1 org.eclipse.osgi okt 02, 2004 12:38:38.437\n!MESSAGE Missing required bundle org.eclipse.jdt.junit_0.0.0.\n!SUBENTRY 1 org.eclipse.osgi okt 02, 2004 12:38:38.437\n!MESSAGE Missing required bundle org.eclipse.ui.intro_0.0.0.\n!SUBENTRY 1 org.eclipse.osgi okt 02, 2004 12:38:38.437\n!MESSAGE Missing required bundle org.eclipse.ui.cheatsheets_0.0.0.\n\n!ENTRY org.eclipse.osgi okt 02, 2004 12:38:38.453\n!MESSAGE Bundle update@/c:/Program \nFiles/eclipse/plugins/org.eclipse.pde_3.0.1/ [181] was not resolved.\n!SUBENTRY 1 org.eclipse.osgi okt 02, 2004 12:38:38.453\n!MESSAGE Missing required bundle org.eclipse.pde.core_0.0.0.\n!SUBENTRY 1 org.eclipse.osgi okt 02, 2004 12:38:38.453\n!MESSAGE Missing required bundle org.eclipse.core.resources_0.0.0.\n!SUBENTRY 1 org.eclipse.osgi okt 02, 2004 12:38:38.453\n!MESSAGE Missing required bundle org.eclipse.jdt.core_0.0.0.\n!SUBENTRY 1 org.eclipse.osgi okt 02, 2004 12:38:38.453\n!MESSAGE Missing required bundle org.eclipse.text_0.0.0.\n!SUBENTRY 1 org.eclipse.osgi okt 02, 2004 12:38:38.453\n!MESSAGE Missing optionally required bundle org.eclipse.ui.intro_0.0.0.\n!SUBENTRY 1 org.eclipse.osgi okt 02, 2004 12:38:38.453\n!MESSAGE Missing optionally required bundle org.eclipse.ui.cheatsheets_0.0.0.\n\n!ENTRY org.eclipse.osgi okt 02, 2004 12:38:38.468\n!MESSAGE Bundle update@/c:/Program \nFiles/eclipse/plugins/org.eclipse.platform.doc.isv_3.0.1/ [182] was not \nresolved.\n!SUBENTRY 1 org.eclipse.osgi okt 02, 2004 12:38:38.468\n!MESSAGE Missing required bundle org.eclipse.ui_0.0.0.\n\n!ENTRY org.eclipse.osgi okt 02, 2004 12:38:38.484\n!MESSAGE Bundle update@/c:/Program \nFiles/eclipse/plugins/org.eclipse.sdk_3.0.1/ [185] was not resolved.\n!SUBENTRY 1 org.eclipse.osgi okt 02, 2004 12:38:38.484\n!MESSAGE Missing required bundle org.eclipse.ui_0.0.0.",
    "dup of bug 74624 \n\nTry installing the 3.0.1 sdk zip file on top, and restart with -clean.\n\n*** This bug has been marked as a duplicate of 74624 ***"
  ],
  "commentCreationDates": [
    "2004-10-02T12:59:21+02:00",
    "2004-10-02T19:06:06+02:00"
  ],
  "traces": [
    {
      "exceptionType": "java.lang.RuntimeException",
      "message": "No application id has been found.",
      "elements": [
        {
          "method": "org.eclipse.core.internal.runtime.PlatformActivator$1.run",
          "source": "PlatformActivator.java:313"
        },
        {
          "method": "org.eclipse.core.runtime.adaptor.EclipseStarter.run",
          "source": "EclipseStarter.java:273"
        },
        {
          "method": "org.eclipse.core.runtime.adaptor.EclipseStarter.run",
          "source": "EclipseStarter.java:129"
        },
        {
          "method": "sun.reflect.NativeMethodAccessorImpl.invoke0",
          "source": "Native Method"
        },
        {
          "method": "sun.reflect.NativeMethodAccessorImpl.invoke",
          "source": "Unknown Source"
        },
        {
          "method": "sun.reflect.DelegatingMethodAccessorImpl.invoke",
          "source": "Unknown Source"
        },
        {
          "method": "java.lang.reflect.Method.invoke",
          "source": "Unknown Source"
        },
        {
          "method": "org.eclipse.core.launcher.Main.basicRun",
          "source": "Main.java:183"
        },
        {
          "method": "org.eclipse.core.launcher.Main.run",
          "source": "Main.java:644"
        },
        {
          "method": "org.eclipse.core.launcher.Main.main",
          "source": "Main.java:628"
        }
      ],
      "number": 0,
      "commentIndex": 0,
      "bugId": "75515",
      "duplicateId": "74624",
      "date": "2004-10-02T12:59:21+02:00",
      "product": "Platform",
      "component": "Update",
      "severity": "normal"
    }
  ],
  "groupId": "74624",
  "bugId": "75515",
  "duplicateId": "74624",
  "date": "2004-10-02T12:59:21+02:00",
  "product": "Platform",
  "component": "Update",
  "severity": "normal"
}