{
  "comments": [
    "I\u0027m running Eclipse 3.0 final release and I tried to update it to 3.0.1 via the \nsoftware updates option in the help menu. It downloaded the jars, installed \nthem and then asked me if I wanted to restart Eclipse. On restart, an error \nwindow popped up and a logfile was generated in C:\\eclipse\\configuration:\n\n-----------------------------------------------------\n\n!SESSION Nov 04, 2004 15:34:03.88 ----------------------------------------------\neclipse.buildId\u003dI200406251208\njava.version\u003d1.4.2_04\njava.vendor\u003dSun Microsystems Inc.\nBootLoader constants: OS\u003dwin32, ARCH\u003dx86, WS\u003dwin32, NL\u003den_US\n\n!ENTRY org.eclipse.osgi Nov 04, 2004 15:34:03.88\n!MESSAGE Application error\n!STACK 1\njava.lang.RuntimeException: No application id has been found.\n\tat org.eclipse.core.internal.runtime.PlatformActivator$1.run\n(PlatformActivator.java:313)\n\tat org.eclipse.core.runtime.adaptor.EclipseStarter.run\n(EclipseStarter.java:273)\n\tat org.eclipse.core.runtime.adaptor.EclipseStarter.run\n(EclipseStarter.java:129)\n\tat sun.reflect.NativeMethodAccessorImpl.invoke0(Native Method)\n\tat sun.reflect.NativeMethodAccessorImpl.invoke\n(NativeMethodAccessorImpl.java:39)\n\tat sun.reflect.DelegatingMethodAccessorImpl.invoke\n(DelegatingMethodAccessorImpl.java:25)\n\tat java.lang.reflect.Method.invoke(Method.java:324)\n\tat org.eclipse.core.launcher.Main.basicRun(Main.java:183)\n\tat org.eclipse.core.launcher.Main.run(Main.java:644)\n\tat org.eclipse.core.launcher.Main.main(Main.java:628)\n\n!ENTRY org.eclipse.osgi Nov 04, 2004 15:34:03.99\n!MESSAGE Bundle update@/c:/eclipse/plugins/org.eclipse.compare_3.0.0/ [7] was \nnot resolved.\n\n!ENTRY org.eclipse.osgi Nov 04, 2004 15:34:03.99\n!MESSAGE Bundle \nupdate@/c:/eclipse/plugins/org.eclipse.core.resources.win32_3.0.0/ [11] was not \nresolved.\n\n!ENTRY org.eclipse.osgi Nov 04, 2004 15:34:03.99\n!MESSAGE Bundle update@/c:/eclipse/plugins/org.eclipse.help.ide_3.0.0/ [20] was \nnot resolved.\n\n!ENTRY org.eclipse.osgi Nov 04, 2004 15:34:03.109\n!MESSAGE Bundle update@/c:/eclipse/plugins/org.eclipse.help.ui_3.0.0/ [21] was \nnot resolved.\n\n!ENTRY org.eclipse.osgi Nov 04, 2004 15:34:03.119\n!MESSAGE Bundle update@/c:/eclipse/plugins/org.eclipse.jface_3.0.0/ [36] was \nnot resolved.\n\n!ENTRY org.eclipse.osgi Nov 04, 2004 15:34:03.119\n!MESSAGE Bundle update@/c:/eclipse/plugins/org.eclipse.team.core_3.0.0/ [59] \nwas not resolved.\n\n!ENTRY org.eclipse.osgi Nov 04, 2004 15:34:03.119\n!MESSAGE Bundle update@/c:/eclipse/plugins/org.eclipse.team.cvs.ssh2_3.0.0/ \n[61] was not resolved.\n\n!ENTRY org.eclipse.osgi Nov 04, 2004 15:34:03.119\n!MESSAGE Bundle update@/c:/eclipse/plugins/org.eclipse.team.cvs.ssh_3.0.0/ [62] \nwas not resolved.\n\n!ENTRY org.eclipse.osgi Nov 04, 2004 15:34:03.119\n!MESSAGE Bundle update@/c:/eclipse/plugins/org.eclipse.tomcat_4.1.30/ [66] was \nnot resolved.\n\n!ENTRY org.eclipse.osgi Nov 04, 2004 15:34:03.119\n!MESSAGE Bundle update@/c:/eclipse/plugins/org.eclipse.ui.console_3.0.0/ [68] \nwas not resolved.\n\n!ENTRY org.eclipse.osgi Nov 04, 2004 15:34:03.119\n!MESSAGE Bundle update@/c:/eclipse/plugins/org.eclipse.ui.forms_3.0.0/ [71] was \nnot resolved.\n\n!ENTRY org.eclipse.osgi Nov 04, 2004 15:34:03.119\n!MESSAGE Bundle update@/c:/eclipse/plugins/org.eclipse.ui.views_3.0.0/ [75] was \nnot resolved.\n\n!ENTRY org.eclipse.osgi Nov 04, 2004 15:34:03.119\n!MESSAGE Bundle \nupdate@/c:/eclipse/plugins/org.eclipse.ui.workbench.compatibility_3.0.0/ [77] \nwas not resolved.\n\n!ENTRY org.eclipse.osgi Nov 04, 2004 15:34:03.129\n!MESSAGE Bundle update@/c:/eclipse/plugins/org.eclipse.update.core.win32_3.0.0/ \n[82] was not resolved.\n\n!ENTRY org.eclipse.osgi Nov 04, 2004 15:34:03.129\n!MESSAGE Bundle update@/c:/eclipse/plugins/org.eclipse.update.scheduler_3.0.0/ \n[84] was not resolved.\n\n!ENTRY org.eclipse.osgi Nov 04, 2004 15:34:03.129\n!MESSAGE Bundle update@/c:/eclipse/plugins/net.sf.commonclipse_1.1.0/ [91] was \nnot resolved.\n\n!ENTRY org.eclipse.osgi Nov 04, 2004 15:34:03.139\n!MESSAGE Bundle update@/c:/eclipse/plugins/org.eclipse.pde.build_3.0.1/ [97] \nwas not resolved.\n!SUBENTRY 1 org.eclipse.osgi Nov 04, 2004 15:34:03.139\n!MESSAGE Missing required bundle org.eclipse.update.core_0.0.0.\n!SUBENTRY 1 org.eclipse.osgi Nov 04, 2004 15:34:03.139\n!MESSAGE Missing required bundle org.apache.ant_0.0.0.\n\n!ENTRY org.eclipse.osgi Nov 04, 2004 15:34:03.139\n!MESSAGE Bundle update@/c:/eclipse/plugins/org.eclipse.pde.core_3.0.1/ [98] was \nnot resolved.\n!SUBENTRY 1 org.eclipse.osgi Nov 04, 2004 15:34:03.139\n!MESSAGE Missing required bundle org.eclipse.core.resources_0.0.0.\n!SUBENTRY 1 org.eclipse.osgi Nov 04, 2004 15:34:03.139\n!MESSAGE Missing required bundle org.eclipse.jdt.core_0.0.0.\n!SUBENTRY 1 org.eclipse.osgi Nov 04, 2004 15:34:03.139\n!MESSAGE Missing required bundle org.eclipse.team.core_0.0.0.\n\n!ENTRY org.eclipse.osgi Nov 04, 2004 15:34:03.139\n!MESSAGE Bundle update@/c:/eclipse/plugins/org.eclipse.pde.runtime_3.0.1/ [99] \nwas not resolved.\n!SUBENTRY 1 org.eclipse.osgi Nov 04, 2004 15:34:03.139\n!MESSAGE Missing required bundle org.eclipse.ui_0.0.0.\n!SUBENTRY 1 org.eclipse.osgi Nov 04, 2004 15:34:03.139\n!MESSAGE Missing required bundle org.eclipse.ui.views_0.0.0.\n\n!ENTRY org.eclipse.osgi Nov 04, 2004 15:34:03.149\n!MESSAGE Bundle update@/c:/eclipse/plugins/org.eclipse.pde.ui_3.0.1/ [101] was \nnot resolved.\n!SUBENTRY 1 org.eclipse.osgi Nov 04, 2004 15:34:03.149\n!MESSAGE Missing required bundle org.eclipse.ui.ide_0.0.0.\n!SUBENTRY 1 org.eclipse.osgi Nov 04, 2004 15:34:03.149\n!MESSAGE Missing required bundle org.eclipse.ui.views_0.0.0.\n!SUBENTRY 1 org.eclipse.osgi Nov 04, 2004 15:34:03.149\n!MESSAGE Missing required bundle org.eclipse.jface.text_0.0.0.\n!SUBENTRY 1 org.eclipse.osgi Nov 04, 2004 15:34:03.149\n!MESSAGE Missing required bundle org.eclipse.ui.workbench.texteditor_0.0.0.\n!SUBENTRY 1 org.eclipse.osgi Nov 04, 2004 15:34:03.149\n!MESSAGE Missing required bundle org.eclipse.ui.editors_0.0.0.\n!SUBENTRY 1 org.eclipse.osgi Nov 04, 2004 15:34:03.149\n!MESSAGE Missing required bundle org.eclipse.core.resources_0.0.0.\n!SUBENTRY 1 org.eclipse.osgi Nov 04, 2004 15:34:03.149\n!MESSAGE Missing required bundle org.eclipse.debug.core_0.0.0.\n!SUBENTRY 1 org.eclipse.osgi Nov 04, 2004 15:34:03.149\n!MESSAGE Missing required bundle org.eclipse.debug.ui_0.0.0.\n!SUBENTRY 1 org.eclipse.osgi Nov 04, 2004 15:34:03.149\n!MESSAGE Missing required bundle org.eclipse.help.base_0.0.0.\n!SUBENTRY 1 org.eclipse.osgi Nov 04, 2004 15:34:03.149\n!MESSAGE Missing required bundle org.eclipse.jdt.core_0.0.0.\n!SUBENTRY 1 org.eclipse.osgi Nov 04, 2004 15:34:03.149\n!MESSAGE Missing required bundle org.eclipse.jdt.debug.ui_0.0.0.\n!SUBENTRY 1 org.eclipse.osgi Nov 04, 2004 15:34:03.149\n!MESSAGE Missing required bundle org.eclipse.jdt.launching_0.0.0.\n!SUBENTRY 1 org.eclipse.osgi Nov 04, 2004 15:34:03.149\n!MESSAGE Missing required bundle org.eclipse.jdt.ui_0.0.0.\n!SUBENTRY 1 org.eclipse.osgi Nov 04, 2004 15:34:03.149\n!MESSAGE Missing required bundle org.eclipse.pde_0.0.0.\n!SUBENTRY 1 org.eclipse.osgi Nov 04, 2004 15:34:03.149\n!MESSAGE Missing required bundle org.eclipse.pde.build_0.0.0.\n!SUBENTRY 1 org.eclipse.osgi Nov 04, 2004 15:34:03.149\n!MESSAGE Missing required bundle org.eclipse.search_0.0.0.\n!SUBENTRY 1 org.eclipse.osgi Nov 04, 2004 15:34:03.149\n!MESSAGE Missing required bundle org.eclipse.team.core_0.0.0.\n!SUBENTRY 1 org.eclipse.osgi Nov 04, 2004 15:34:03.149\n!MESSAGE Missing required bundle org.eclipse.ui_0.0.0.\n!SUBENTRY 1 org.eclipse.osgi Nov 04, 2004 15:34:03.149\n!MESSAGE Missing required bundle org.eclipse.update.core_0.0.0.\n!SUBENTRY 1 org.eclipse.osgi Nov 04, 2004 15:34:03.149\n!MESSAGE Missing required bundle org.eclipse.ui.forms_0.0.0.\n!SUBENTRY 1 org.eclipse.osgi Nov 04, 2004 15:34:03.149\n!MESSAGE Missing required bundle org.eclipse.ant.ui_0.0.0.\n!SUBENTRY 1 org.eclipse.osgi Nov 04, 2004 15:34:03.149\n!MESSAGE Missing required bundle org.eclipse.jdt.junit_0.0.0.\n!SUBENTRY 1 org.eclipse.osgi Nov 04, 2004 15:34:03.149\n!MESSAGE Missing required bundle org.eclipse.ui.intro_0.0.0.\n!SUBENTRY 1 org.eclipse.osgi Nov 04, 2004 15:34:03.149\n!MESSAGE Missing required bundle org.eclipse.ui.cheatsheets_0.0.0.\n\n!ENTRY org.eclipse.osgi Nov 04, 2004 15:34:03.149\n!MESSAGE Bundle update@/c:/eclipse/plugins/org.eclipse.pde_3.0.1/ [102] was not \nresolved.\n!SUBENTRY 1 org.eclipse.osgi Nov 04, 2004 15:34:03.149\n!MESSAGE Missing required bundle org.eclipse.pde.core_0.0.0.\n!SUBENTRY 1 org.eclipse.osgi Nov 04, 2004 15:34:03.149\n!MESSAGE Missing required bundle org.eclipse.core.resources_0.0.0.\n!SUBENTRY 1 org.eclipse.osgi Nov 04, 2004 15:34:03.149\n!MESSAGE Missing required bundle org.eclipse.jdt.core_0.0.0.\n!SUBENTRY 1 org.eclipse.osgi Nov 04, 2004 15:34:03.159\n!MESSAGE Missing required bundle org.eclipse.text_0.0.0.\n!SUBENTRY 1 org.eclipse.osgi Nov 04, 2004 15:34:03.159\n!MESSAGE Missing optionally required bundle org.eclipse.ui.intro_0.0.0.\n!SUBENTRY 1 org.eclipse.osgi Nov 04, 2004 15:34:03.159\n!MESSAGE Missing optionally required bundle org.eclipse.ui.cheatsheets_0.0.0.\n\n!ENTRY org.eclipse.osgi Nov 04, 2004 15:34:03.159\n!MESSAGE Bundle update@/c:/eclipse/plugins/org.eclipse.sdk_3.0.1/ [103] was not \nresolved.\n!SUBENTRY 1 org.eclipse.osgi Nov 04, 2004 15:34:03.159\n!MESSAGE Missing required bundle org.eclipse.ui_0.0.0.\n\n\n-----------------------------------------------------\n\nIt seems that some libraries have not come through the update?",
    "dup of bug 74624 (fixed in 3.1 and 3.0.2)\n\nTry downloading the 3.0.1 SDK and unzip it on top of the (corrupted) 3.0 \ninstall. Then restart with -clean.\n\n*** This bug has been marked as a duplicate of 74624 ***"
  ],
  "commentCreationDates": [
    "2004-11-04T20:59:21+01:00",
    "2004-11-04T21:19:26+01:00"
  ],
  "traces": [
    {
      "exceptionType": "java.lang.RuntimeException",
      "message": "No application id has been found.",
      "elements": [
        {
          "method": "org.eclipse.core.internal.runtime.PlatformActivator$1.run",
          "source": "PlatformActivator.java:313"
        },
        {
          "method": "org.eclipse.core.runtime.adaptor.EclipseStarter.run",
          "source": "EclipseStarter.java:273"
        },
        {
          "method": "org.eclipse.core.runtime.adaptor.EclipseStarter.run",
          "source": "EclipseStarter.java:129"
        },
        {
          "method": "sun.reflect.NativeMethodAccessorImpl.invoke0",
          "source": "Native Method"
        },
        {
          "method": "sun.reflect.NativeMethodAccessorImpl.invoke",
          "source": "NativeMethodAccessorImpl.java:39"
        },
        {
          "method": "sun.reflect.DelegatingMethodAccessorImpl.invoke",
          "source": "DelegatingMethodAccessorImpl.java:25"
        },
        {
          "method": "java.lang.reflect.Method.invoke",
          "source": "Method.java:324"
        },
        {
          "method": "org.eclipse.core.launcher.Main.basicRun",
          "source": "Main.java:183"
        },
        {
          "method": "org.eclipse.core.launcher.Main.run",
          "source": "Main.java:644"
        },
        {
          "method": "org.eclipse.core.launcher.Main.main",
          "source": "Main.java:628"
        }
      ],
      "number": 0,
      "commentIndex": 0,
      "bugId": "77897",
      "duplicateId": "74624",
      "date": "2004-11-04T20:59:21+01:00",
      "product": "Platform",
      "component": "Update",
      "severity": "critical"
    }
  ],
  "groupId": "74624",
  "bugId": "77897",
  "duplicateId": "74624",
  "date": "2004-11-04T20:59:21+01:00",
  "product": "Platform",
  "component": "Update",
  "severity": "critical"
}