{
  "comments": [
    "I asked to rename a class from MetaDataObject to MetaData.  It looks like it \nsucceeded but I received the following exceptions when it was completed.\n\njava.lang.NullPointerException\n        at \norg.eclipse.jdt.internal.core.search.indexing.AbstractIndexer.addMeth\nodReference(AbstractIndexer.java(Compiled Code))\n        at \norg.eclipse.jdt.internal.core.search.indexing.SourceIndexerRequestor.\nacceptMethodReference(SourceIndexerRequestor.java:69)\n        at \norg.eclipse.jdt.internal.compiler.SourceElementParser.consumeMethodIn\nvocationName(SourceElementParser.java(Compiled Code))\n        at org.eclipse.jdt.internal.compiler.parser.Parser.consumeRule\n(Parser.ja\nva(Compiled Code))\n        at org.eclipse.jdt.internal.compiler.parser.Parser.parse(Parser.java\n(Com\npiled Code))\n        at org.eclipse.jdt.internal.compiler.parser.Parser.parse\n(Parser.java:694\n6)\n        at \norg.eclipse.jdt.internal.compiler.SourceElementParser.parseCompilatio\nnUnit(SourceElementParser.java:968)\n        at \norg.eclipse.jdt.internal.core.search.indexing.SourceIndexer.indexFile\n(SourceIndexer.java:66)\n        at org.eclipse.jdt.internal.core.search.indexing.AbstractIndexer.index\n(A\nbstractIndexer.java:558)\n        at org.eclipse.jdt.internal.core.index.impl.Index.add(Index.java:88)\n        at \norg.eclipse.jdt.internal.core.search.indexing.AddCompilationUnitToInd\nex.execute(AddCompilationUnitToIndex.java:54)\n        at org.eclipse.jdt.internal.core.search.processing.JobManager.run\n(JobMan\nager.java(Compiled Code))\n        at java.lang.Thread.run(Thread.java:512)\njava.lang.ClassCastException\n        at \norg.eclipse.jdt.internal.core.search.indexing.AbstractIndexer.addMeth\nodReference(AbstractIndexer.java(Compiled Code))\n        at \norg.eclipse.jdt.internal.core.search.indexing.AbstractIndexer.addMeth\nodReference(AbstractIndexer.java(Compiled Code))\n        at \norg.eclipse.jdt.internal.core.search.indexing.AbstractIndexer.addMeth\nodReference(AbstractIndexer.java(Compiled Code))\n        at \norg.eclipse.jdt.internal.core.search.indexing.AbstractIndexer.addMeth\nodReference(AbstractIndexer.java(Compiled Code))\n        at \norg.eclipse.jdt.internal.core.search.indexing.SourceIndexerRequestor.\nacceptMethodReference(SourceIndexerRequestor.java:69)\n        at \norg.eclipse.jdt.internal.compiler.SourceElementParser.consumeMethodIn\nvocationName(SourceElementParser.java(Compiled Code))\n        at org.eclipse.jdt.internal.compiler.parser.Parser.consumeRule\n(Parser.ja\nva(Compiled Code))\n        at org.eclipse.jdt.internal.compiler.parser.Parser.parse(Parser.java\n(Com\npiled Code))\n        at org.eclipse.jdt.internal.compiler.parser.Parser.parse\n(Parser.java:694\n6)\n        at \norg.eclipse.jdt.internal.compiler.SourceElementParser.parseCompilatio\nnUnit(SourceElementParser.java:968)\n        at \norg.eclipse.jdt.internal.core.search.indexing.SourceIndexer.indexFile\n(SourceIndexer.java:66)\n        at org.eclipse.jdt.internal.core.search.indexing.AbstractIndexer.index\n(A\nbstractIndexer.java:558)\n        at org.eclipse.jdt.internal.core.index.impl.Index.add(Index.java:88)\n        at \norg.eclipse.jdt.internal.core.search.indexing.AddCompilationUnitToInd\nex.execute(AddCompilationUnitToIndex.java:54)\n        at org.eclipse.jdt.internal.core.search.processing.JobManager.run\n(JobMan\nager.java(Compiled Code))\n        at java.lang.Thread.run(Thread.java:512)\njava.lang.ClassCastException\n        at \norg.eclipse.jdt.internal.core.search.indexing.AbstractIndexer.addMeth\nodReference(AbstractIndexer.java(Compiled Code))\n        at \norg.eclipse.jdt.internal.core.search.indexing.AbstractIndexer.addMeth\nodReference(AbstractIndexer.java(Compiled Code))\n        at \norg.eclipse.jdt.internal.core.search.indexing.AbstractIndexer.addMeth\nodReference(AbstractIndexer.java(Compiled Code))\n        at \norg.eclipse.jdt.internal.core.search.indexing.AbstractIndexer.addMeth\nodReference(AbstractIndexer.java(Compiled Code))\n        at \norg.eclipse.jdt.internal.core.search.indexing.SourceIndexerRequestor.\nacceptMethodReference(SourceIndexerRequestor.java:69)\n        at \norg.eclipse.jdt.internal.compiler.SourceElementParser.consumeMethodIn\nvocationName(SourceElementParser.java(Compiled Code))\n        at org.eclipse.jdt.internal.compiler.parser.Parser.consumeRule\n(Parser.ja\nva(Compiled Code))\n        at org.eclipse.jdt.internal.compiler.parser.Parser.parse(Parser.java\n(Com\npiled Code))\n        at org.eclipse.jdt.internal.compiler.parser.Parser.parse\n(Parser.java:694\n6)\n        at \norg.eclipse.jdt.internal.compiler.SourceElementParser.parseCompilatio\nnUnit(SourceElementParser.java:968)\n        at \norg.eclipse.jdt.internal.core.search.indexing.SourceIndexer.indexFile\n(SourceIndexer.java:66)\n        at org.eclipse.jdt.internal.core.search.indexing.AbstractIndexer.index\n(A\nbstractIndexer.java:558)\n        at org.eclipse.jdt.internal.core.index.impl.Index.add(Index.java:88)\n        at \norg.eclipse.jdt.internal.core.search.indexing.AddCompilationUnitToInd\nex.execute(AddCompilationUnitToIndex.java:54)\n        at org.eclipse.jdt.internal.core.search.processing.JobManager.run\n(JobMan\nager.java(Compiled Code))\n        at java.lang.Thread.run(Thread.java:512)\njava.lang.NullPointerException\n        at \norg.eclipse.jdt.internal.core.index.impl.SimpleIndexInput.moveToNextW\nordEntry(SimpleIndexInput.java(Compiled Code))\n        at \norg.eclipse.jdt.internal.core.index.impl.MergeFactory.mergeReferences\n(MergeFactory.java(Compiled Code))\n        at org.eclipse.jdt.internal.core.index.impl.MergeFactory.merge\n(MergeFact\nory.java:79)\n        at org.eclipse.jdt.internal.core.index.impl.Index.merge(Index.java:231)\n        at \norg.eclipse.jdt.internal.core.search.indexing.IndexManager.saveIndexe\ns(IndexManager.java(Compiled Code))\n        at \norg.eclipse.jdt.internal.core.search.indexing.IndexManager.saveIndexe\ns(IndexManager.java(Compiled Code))\n        at \norg.eclipse.jdt.internal.core.search.indexing.IndexManager.notifyIdle\n(IndexManager.java(Compiled Code))\n        at org.eclipse.jdt.internal.core.search.processing.JobManager.run\n(JobMan\nager.java(Compiled Code))\n        at java.lang.Thread.run(Thread.java:512)",
    "Could you please attach or send me the source of the offending compilation \nunit ?",
    "Test case received, but could not reproduce.\nSeems like an internal index error occurred, and from thereon the indexer was \ninconsistent.\n\n",
    "Which build did it occur in ?",
    "Stable 20020214",
    "Closing, was never reproduced. Sounds like a VM/JIT bug."
  ],
  "commentCreationDates": [
    "2002-02-19T19:03:48+01:00",
    "2002-02-20T00:12:14+01:00",
    "2002-02-25T22:26:00+01:00",
    "2002-03-04T13:33:47+01:00",
    "2002-03-04T13:59:10+01:00",
    "2002-06-04T16:14:33+02:00"
  ],
  "traces": [
    {
      "exceptionType": "java.lang.NullPointerException",
      "elements": [
        {
          "method": "org.eclipse.jdt.internal.core.search.indexing.AbstractIndexer.addMethodReference",
          "source": "AbstractIndexer.java(Compiled Code)"
        },
        {
          "method": "org.eclipse.jdt.internal.core.search.indexing.SourceIndexerRequestor.acceptMethodReference",
          "source": "SourceIndexerRequestor.java:69"
        },
        {
          "method": "org.eclipse.jdt.internal.compiler.SourceElementParser.consumeMethodInvocationName",
          "source": "SourceElementParser.java(Compiled Code)"
        },
        {
          "method": "org.eclipse.jdt.internal.compiler.parser.Parser.consumeRule",
          "source": "Parser.ja va(Compiled Code)"
        },
        {
          "method": "org.eclipse.jdt.internal.compiler.parser.Parser.parse",
          "source": "Parser.java (Com piled Code)"
        },
        {
          "method": "org.eclipse.jdt.internal.compiler.parser.Parser.parse",
          "source": "Parser.java:694 6"
        },
        {
          "method": "org.eclipse.jdt.internal.compiler.SourceElementParser.parseCompilationUnit",
          "source": "SourceElementParser.java:968"
        },
        {
          "method": "org.eclipse.jdt.internal.core.search.indexing.SourceIndexer.indexFile",
          "source": "SourceIndexer.java:66"
        },
        {
          "method": "org.eclipse.jdt.internal.core.search.indexing.AbstractIndexer.index",
          "source": "A bstractIndexer.java:558"
        },
        {
          "method": "org.eclipse.jdt.internal.core.index.impl.Index.add",
          "source": "Index.java:88"
        },
        {
          "method": "org.eclipse.jdt.internal.core.search.indexing.AddCompilationUnitToIndex.execute",
          "source": "AddCompilationUnitToIndex.java:54"
        },
        {
          "method": "org.eclipse.jdt.internal.core.search.processing.JobManager.run",
          "source": "JobMan ager.java(Compiled Code)"
        },
        {
          "method": "java.lang.Thread.run",
          "source": "Thread.java:512"
        }
      ],
      "number": 0,
      "commentIndex": 0,
      "bugId": "10007",
      "date": "2002-02-19T19:03:48+01:00",
      "product": "JDT",
      "component": "Core",
      "severity": "normal"
    },
    {
      "exceptionType": "java.lang.ClassCastException",
      "elements": [
        {
          "method": "org.eclipse.jdt.internal.core.search.indexing.AbstractIndexer.addMethodReference",
          "source": "AbstractIndexer.java(Compiled Code)"
        },
        {
          "method": "org.eclipse.jdt.internal.core.search.indexing.AbstractIndexer.addMethodReference",
          "source": "AbstractIndexer.java(Compiled Code)"
        },
        {
          "method": "org.eclipse.jdt.internal.core.search.indexing.AbstractIndexer.addMethodReference",
          "source": "AbstractIndexer.java(Compiled Code)"
        },
        {
          "method": "org.eclipse.jdt.internal.core.search.indexing.AbstractIndexer.addMethodReference",
          "source": "AbstractIndexer.java(Compiled Code)"
        },
        {
          "method": "org.eclipse.jdt.internal.core.search.indexing.SourceIndexerRequestor.acceptMethodReference",
          "source": "SourceIndexerRequestor.java:69"
        },
        {
          "method": "org.eclipse.jdt.internal.compiler.SourceElementParser.consumeMethodInvocationName",
          "source": "SourceElementParser.java(Compiled Code)"
        },
        {
          "method": "org.eclipse.jdt.internal.compiler.parser.Parser.consumeRule",
          "source": "Parser.ja va(Compiled Code)"
        },
        {
          "method": "org.eclipse.jdt.internal.compiler.parser.Parser.parse",
          "source": "Parser.java (Com piled Code)"
        },
        {
          "method": "org.eclipse.jdt.internal.compiler.parser.Parser.parse",
          "source": "Parser.java:694 6"
        },
        {
          "method": "org.eclipse.jdt.internal.compiler.SourceElementParser.parseCompilationUnit",
          "source": "SourceElementParser.java:968"
        },
        {
          "method": "org.eclipse.jdt.internal.core.search.indexing.SourceIndexer.indexFile",
          "source": "SourceIndexer.java:66"
        },
        {
          "method": "org.eclipse.jdt.internal.core.search.indexing.AbstractIndexer.index",
          "source": "A bstractIndexer.java:558"
        },
        {
          "method": "org.eclipse.jdt.internal.core.index.impl.Index.add",
          "source": "Index.java:88"
        },
        {
          "method": "org.eclipse.jdt.internal.core.search.indexing.AddCompilationUnitToIndex.execute",
          "source": "AddCompilationUnitToIndex.java:54"
        },
        {
          "method": "org.eclipse.jdt.internal.core.search.processing.JobManager.run",
          "source": "JobMan ager.java(Compiled Code)"
        },
        {
          "method": "java.lang.Thread.run",
          "source": "Thread.java:512"
        }
      ],
      "number": 1,
      "commentIndex": 0,
      "bugId": "10007",
      "date": "2002-02-19T19:03:48+01:00",
      "product": "JDT",
      "component": "Core",
      "severity": "normal"
    },
    {
      "exceptionType": "java.lang.ClassCastException",
      "elements": [
        {
          "method": "org.eclipse.jdt.internal.core.search.indexing.AbstractIndexer.addMethodReference",
          "source": "AbstractIndexer.java(Compiled Code)"
        },
        {
          "method": "org.eclipse.jdt.internal.core.search.indexing.AbstractIndexer.addMethodReference",
          "source": "AbstractIndexer.java(Compiled Code)"
        },
        {
          "method": "org.eclipse.jdt.internal.core.search.indexing.AbstractIndexer.addMethodReference",
          "source": "AbstractIndexer.java(Compiled Code)"
        },
        {
          "method": "org.eclipse.jdt.internal.core.search.indexing.AbstractIndexer.addMethodReference",
          "source": "AbstractIndexer.java(Compiled Code)"
        },
        {
          "method": "org.eclipse.jdt.internal.core.search.indexing.SourceIndexerRequestor.acceptMethodReference",
          "source": "SourceIndexerRequestor.java:69"
        },
        {
          "method": "org.eclipse.jdt.internal.compiler.SourceElementParser.consumeMethodInvocationName",
          "source": "SourceElementParser.java(Compiled Code)"
        },
        {
          "method": "org.eclipse.jdt.internal.compiler.parser.Parser.consumeRule",
          "source": "Parser.ja va(Compiled Code)"
        },
        {
          "method": "org.eclipse.jdt.internal.compiler.parser.Parser.parse",
          "source": "Parser.java (Com piled Code)"
        },
        {
          "method": "org.eclipse.jdt.internal.compiler.parser.Parser.parse",
          "source": "Parser.java:694 6"
        },
        {
          "method": "org.eclipse.jdt.internal.compiler.SourceElementParser.parseCompilationUnit",
          "source": "SourceElementParser.java:968"
        },
        {
          "method": "org.eclipse.jdt.internal.core.search.indexing.SourceIndexer.indexFile",
          "source": "SourceIndexer.java:66"
        },
        {
          "method": "org.eclipse.jdt.internal.core.search.indexing.AbstractIndexer.index",
          "source": "A bstractIndexer.java:558"
        },
        {
          "method": "org.eclipse.jdt.internal.core.index.impl.Index.add",
          "source": "Index.java:88"
        },
        {
          "method": "org.eclipse.jdt.internal.core.search.indexing.AddCompilationUnitToIndex.execute",
          "source": "AddCompilationUnitToIndex.java:54"
        },
        {
          "method": "org.eclipse.jdt.internal.core.search.processing.JobManager.run",
          "source": "JobMan ager.java(Compiled Code)"
        },
        {
          "method": "java.lang.Thread.run",
          "source": "Thread.java:512"
        }
      ],
      "number": 2,
      "commentIndex": 0,
      "bugId": "10007",
      "date": "2002-02-19T19:03:48+01:00",
      "product": "JDT",
      "component": "Core",
      "severity": "normal"
    },
    {
      "exceptionType": "java.lang.NullPointerException",
      "elements": [
        {
          "method": "org.eclipse.jdt.internal.core.index.impl.SimpleIndexInput.moveToNextWordEntry",
          "source": "SimpleIndexInput.java(Compiled Code)"
        },
        {
          "method": "org.eclipse.jdt.internal.core.index.impl.MergeFactory.mergeReferences",
          "source": "MergeFactory.java(Compiled Code)"
        },
        {
          "method": "org.eclipse.jdt.internal.core.index.impl.MergeFactory.merge",
          "source": "MergeFact ory.java:79"
        },
        {
          "method": "org.eclipse.jdt.internal.core.index.impl.Index.merge",
          "source": "Index.java:231"
        },
        {
          "method": "org.eclipse.jdt.internal.core.search.indexing.IndexManager.saveIndexes",
          "source": "IndexManager.java(Compiled Code)"
        },
        {
          "method": "org.eclipse.jdt.internal.core.search.indexing.IndexManager.saveIndexes",
          "source": "IndexManager.java(Compiled Code)"
        },
        {
          "method": "org.eclipse.jdt.internal.core.search.indexing.IndexManager.notifyIdle",
          "source": "IndexManager.java(Compiled Code)"
        },
        {
          "method": "org.eclipse.jdt.internal.core.search.processing.JobManager.run",
          "source": "JobMan ager.java(Compiled Code)"
        },
        {
          "method": "java.lang.Thread.run",
          "source": "Thread.java:512"
        }
      ],
      "number": 3,
      "commentIndex": 0,
      "bugId": "10007",
      "date": "2002-02-19T19:03:48+01:00",
      "product": "JDT",
      "component": "Core",
      "severity": "normal"
    }
  ],
  "groupId": "10007",
  "bugId": "10007",
  "date": "2002-02-19T19:03:48+01:00",
  "product": "JDT",
  "component": "Core",
  "severity": "normal"
}