{
  "comments": [
    "I am getting this problem only in 3.1 versions. When I run ant build, I am\ngetting this error.\n\n!ENTRY org.eclipse.core.runtime 4 2 2005-06-14 10:53:55.774\n!MESSAGE An internal error occurred during: \"Match Job\".\n!STACK 0\njava.lang.NumberFormatException: For input string: \" warning\"\n\tat java.lang.NumberFormatException.forInputString(NumberFormatException.java:48)\n\tat java.lang.Integer.parseInt(Integer.java:447)\n\tat java.lang.Integer.parseInt(Integer.java:497)\n\tat\norg.eclipse.ant.internal.ui.console.JavacPatternMatcher.matchFound(JavacPatternMatcher.java:63)\n\tat\norg.eclipse.ui.internal.console.PatternMatchListener.matchFound(PatternMatchListener.java:47)\n\tat\norg.eclipse.ui.internal.console.ConsolePatternMatcher$MatchJob.run(ConsolePatternMatcher.java:130)\n\tat org.eclipse.core.internal.jobs.Worker.run(Worker.java:76)\n\nI found out that the problem is being cased by the deprecation warning in the\nsource. \nFollowing is the java compiler warning.\n [javac] C:{path}AuthenticationFilter.java:65: warning: [deprecation]\ngetRealPath(java.lang.String) in javax.servlet.ServletRequest has been deprecated\n    [javac] public String getRemoteUser() { return username; }\n    [javac] ^\n    [javac] C:{path}/AuthenticationFilter.java:65: warning: [deprecation]\nisRequestedSessionIdFromUrl() in javax.servlet.http.HttpServletRequest has been\ndeprecated\n    [javac] public String getRemoteUser() { return username; }\n    [javac] ^\n    [javac] C:\\{path}/AuthenticationFilter.java:65: warning: [deprecation]\ngetRealPath(java.lang.String) in javax.servlet.ServletRequest has been deprecated\n    [javac] public String getRemoteUser() { return username; }\n    [javac] ^\n    [javac] 3 warnings",
    "\n\n*** This bug has been marked as a duplicate of 99499 ***"
  ],
  "commentCreationDates": [
    "2005-06-14T22:00:14+02:00",
    "2005-06-14T22:05:14+02:00"
  ],
  "traces": [
    {
      "exceptionType": "java.lang.NumberFormatException",
      "message": "For input string: \" warning\"",
      "elements": [
        {
          "method": "java.lang.NumberFormatException.forInputString",
          "source": "NumberFormatException.java:48"
        },
        {
          "method": "java.lang.Integer.parseInt",
          "source": "Integer.java:447"
        },
        {
          "method": "java.lang.Integer.parseInt",
          "source": "Integer.java:497"
        },
        {
          "method": "org.eclipse.ant.internal.ui.console.JavacPatternMatcher.matchFound",
          "source": "JavacPatternMatcher.java:63"
        },
        {
          "method": "org.eclipse.ui.internal.console.PatternMatchListener.matchFound",
          "source": "PatternMatchListener.java:47"
        },
        {
          "method": "org.eclipse.ui.internal.console.ConsolePatternMatcher$MatchJob.run",
          "source": "ConsolePatternMatcher.java:130"
        },
        {
          "method": "org.eclipse.core.internal.jobs.Worker.run",
          "source": "Worker.java:76"
        }
      ],
      "number": 0,
      "commentIndex": 0,
      "bugId": "100063",
      "duplicateId": "99499",
      "date": "2005-06-14T22:00:14+02:00",
      "product": "Platform",
      "component": "Ant",
      "severity": "normal"
    }
  ],
  "groupId": "99499",
  "bugId": "100063",
  "duplicateId": "99499",
  "date": "2005-06-14T22:00:14+02:00",
  "product": "Platform",
  "component": "Ant",
  "severity": "normal"
}