{
  "comments": [
    "I have installed I20050617 from scratch (but re-used my old workspace).\n\nI have two servers defined (Tomcat 5.5 and Tomcat 4.1).\n\nWhen creating a new Dynamic Web Project the \"Target server\" dropdown box only\nshows Tomcat 5.5. The \"New...\" button just does nothing.\n\nI have also tried setting \"Module version\" to 2.3, since Tomcat 4.1 is a 2.3\ncontainer.",
    "Could not reproduce in Windows XP environment, please attach the error \nfrom .log  file\n",
    "There is no .log at all.\n\nI just tried again:\n\n- downloaded the latest I20050617 again (noticing that there was a new one in\nthe meantime)\n- installed everything from scratch again\n- this time, created a new workspace\n- in addition to the already installed JDK 1.5.0_03, I added a JDK 1.4.2_08\nruntime (\"Installed JREs\") \n- added the two Server Runtimes Tomcat 5.5 (using JRE 1.5) and 4.1 (using JRE\n1.4) , in this order (\"Installed Server Runtime Environments\")\n- added the Servers view to my Java perspective (don\u0027t like the J2EE perspective)\n- added two Servers Tomcat 5.5 and 4.1 to the Servers view, in this order\n- File-\u003eNew-\u003eProject-\u003e(expand Web)-\u003eJ2EE Web Project-\u003e(expand \"Hide Advanced\")\n\nTry to change Tomcat 5.5. This is not possible, because this is the only Server\nin the List.",
    "Ok, sorry, there is a log, but it does not contain anything suspicious:\n\n!SESSION 2005-06-18 10:49:55.841 -----------------------------------------------\neclipse.buildId\u003dI20050610-1757\njava.version\u003d1.5.0_03\njava.vendor\u003dSun Microsystems Inc.\nBootLoader constants: OS\u003dlinux, ARCH\u003dx86, WS\u003dgtk, NL\u003den_US\nCommand-line arguments:  -os linux -ws gtk -arch x86\n\n!ENTRY org.eclipse.osgi 2 1 2005-06-18 10:50:09.796\n!MESSAGE NLS unused message: viewStatusStarting in:\norg.eclipse.wst.server.ui.internal.Messages\n\n!ENTRY org.eclipse.osgi 2 1 2005-06-18 10:50:09.798\n!MESSAGE NLS unused message: viewStatusStopping in:\norg.eclipse.wst.server.ui.internal.Messages\n\n!ENTRY org.eclipse.osgi 2 1 2005-06-18 10:50:09.798\n!MESSAGE NLS unused message: viewStatusUnsupported in:\norg.eclipse.wst.server.ui.internal.Messages\n\n!ENTRY org.eclipse.osgi 2 1 2005-06-18 10:50:09.798\n!MESSAGE NLS unused message: actionStart2 in:\norg.eclipse.wst.server.ui.internal.Messages\n\n!ENTRY org.eclipse.osgi 2 1 2005-06-18 10:50:09.799\n!MESSAGE NLS unused message: actionStartToolTip2 in:\norg.eclipse.wst.server.ui.internal.Messages\n\n!ENTRY org.eclipse.osgi 2 1 2005-06-18 10:50:09.799\n!MESSAGE NLS unused message: actionDebug2 in:\norg.eclipse.wst.server.ui.internal.Messages\n\n!ENTRY org.eclipse.osgi 2 1 2005-06-18 10:50:09.801\n!MESSAGE NLS unused message: actionDebugToolTip2 in:\norg.eclipse.wst.server.ui.internal.Messages\n\n!ENTRY org.eclipse.osgi 2 1 2005-06-18 10:50:09.801\n!MESSAGE NLS unused message: actionProfile2 in:\norg.eclipse.wst.server.ui.internal.Messages\n\n!ENTRY org.eclipse.osgi 2 1 2005-06-18 10:50:09.801\n!MESSAGE NLS unused message: actionProfileToolTip2 in:\norg.eclipse.wst.server.ui.internal.Messages\n\n!ENTRY org.eclipse.osgi 2 1 2005-06-18 10:50:09.802\n!MESSAGE NLS unused message: actionRestart2 in:\norg.eclipse.wst.server.ui.internal.Messages\n\n!ENTRY org.eclipse.osgi 2 1 2005-06-18 10:50:09.802\n!MESSAGE NLS unused message: actionRestartToolTip2 in:\norg.eclipse.wst.server.ui.internal.Messages\n\n!ENTRY org.eclipse.osgi 2 1 2005-06-18 10:50:09.802\n!MESSAGE NLS unused message: actionPublish2 in:\norg.eclipse.wst.server.ui.internal.Messages\n\n!ENTRY org.eclipse.osgi 2 1 2005-06-18 10:50:09.803\n!MESSAGE NLS unused message: actionPublishToolTip2 in:\norg.eclipse.wst.server.ui.internal.Messages\n\n!ENTRY org.eclipse.osgi 2 1 2005-06-18 10:50:09.803\n!MESSAGE NLS unused message: viewStatusStartedDebug2 in:\norg.eclipse.wst.server.ui.internal.Messages\n\n!ENTRY org.eclipse.osgi 2 1 2005-06-18 10:50:09.804\n!MESSAGE NLS unused message: viewStatusUnsupported2 in:\norg.eclipse.wst.server.ui.internal.Messages\n\n!ENTRY org.eclipse.osgi 2 1 2005-06-18 10:50:09.804\n!MESSAGE NLS unused message: viewStatusStartedProfile2 in:\norg.eclipse.wst.server.ui.internal.Messages\n",
    "Did you try again to set \"Module Version\" to 2.3, as mentioned  in your \noriginal defect statement, since the default is 2.4 and Tomcat 4.1 doesn\u0027t \nsupport 2.4",
    "I just tried around some more, including some more switching between Module\nversions.\n\nThe key is, you have to change the Module version twice for Tomcat 4.1 to show\nup. So, if you set it from 2.4 to 2.2, nothing changes. If you then set it from\n2.2 to 2.3, everything is okay and both Tomcat 4.1 and 5.5 are contained in the\nlist.\n\nThis is showing up in the console:\n\nUnhandled event loop exception\nReason:\njava.lang.String\n\nAnd this in the .log:\n\n!ENTRY org.eclipse.ui 4 4 2005-06-20 16:25:22.118\n!MESSAGE Unhandled event loop exception\n\n!ENTRY org.eclipse.ui 4 0 2005-06-20 16:25:22.118\n!MESSAGE java.lang.String\n!STACK 0\njava.lang.ClassCastException: java.lang.String\n        at\norg.eclipse.wst.common.frameworks.internal.datamodel.DataModelImpl.getIntProperty(DataModelImpl.java:136)\n        at\norg.eclipse.wst.common.frameworks.datamodel.AbstractDataModelProvider.getIntProperty(AbstractDataModelProvider.java:286)\n        at\norg.eclipse.jst.j2ee.application.internal.operations.J2EEComponentCreationDataModelProvider.getJ2EEVersion(J2EEComponentCreationDataModelProvider.java:555)\n        at\norg.eclipse.jst.j2ee.application.internal.operations.J2EEComponentCreationDataModelProvider.propertySet(J2EEComponentCreationDataModelProvider.java:116)\n        at\norg.eclipse.jst.j2ee.internal.web.archive.operations.WebComponentCreationDataModelProvider.propertySet(WebComponentCreationDataModelProvider.java:76)\n        at\norg.eclipse.wst.common.frameworks.internal.datamodel.DataModelImpl.internalSetProperty(DataModelImpl.java:176)\n        at\norg.eclipse.wst.common.frameworks.internal.datamodel.DataModelImpl.setProperty(DataModelImpl.java:166)\n        at\norg.eclipse.wst.common.frameworks.internal.datamodel.ui.DataModelSynchHelper.setProperty(DataModelSynchHelper.java:178)\n        at\norg.eclipse.wst.common.frameworks.internal.datamodel.ui.DataModelSynchHelper$ComboListener.modifyText(DataModelSynchHelper.java:96)\n        at org.eclipse.swt.widgets.TypedListener.handleEvent(TypedListener.java:187)\n        at org.eclipse.swt.widgets.EventTable.sendEvent(EventTable.java:66)\n        at org.eclipse.swt.widgets.Widget.sendEvent(Widget.java:1021)\n        at org.eclipse.swt.widgets.Widget.sendEvent(Widget.java:1045)\n        at org.eclipse.swt.widgets.Widget.sendEvent(Widget.java:1026)\n        at org.eclipse.swt.widgets.Combo.gtk_changed(Combo.java:859)\n        at org.eclipse.swt.widgets.Widget.windowProc(Widget.java:1315)\n        at org.eclipse.swt.widgets.Display.windowProc(Display.java:3380)\n        at org.eclipse.swt.internal.gtk.OS._gtk_main_do_event(Native Method)\n        at org.eclipse.swt.internal.gtk.OS.gtk_main_do_event(OS.java:4759)\n        at org.eclipse.swt.widgets.Display.eventProc(Display.java:1026)\n        at org.eclipse.swt.internal.gtk.OS._g_main_context_iteration(Native Method)\n        at org.eclipse.swt.internal.gtk.OS.g_main_context_iteration(OS.java:1149)\n        at org.eclipse.swt.widgets.Display.readAndDispatch(Display.java:2528)\n        at org.eclipse.jface.window.Window.runEventLoop(Window.java:809)\n        at org.eclipse.jface.window.Window.open(Window.java:787)\n        at org.eclipse.ui.actions.NewProjectAction.run(NewProjectAction.java:114)\n        at org.eclipse.jface.action.Action.runWithEvent(Action.java:996)\n        at\norg.eclipse.jface.action.ActionContributionItem.handleWidgetSelection(ActionContributionItem.java:538)\n[...]",
    "Derek, sending your way, since  you are more familiar with this code.",
    "The bug is still reproducable on I20050621 (18:03).",
    "This is not reproducable in Windows.  We can take a look in linux environment.",
    "Wiht M5 closing down this will be looked at early m6",
    "M6",
    "Duping against 103066\n\n*** This bug has been marked as a duplicate of 103066 ***",
    "This does now work on 0.7 RC2. Thanks!",
    "Closing already verified defects"
  ],
  "commentCreationDates": [
    "2005-06-17T08:58:01+02:00",
    "2005-06-17T17:50:27+02:00",
    "2005-06-18T10:05:17+02:00",
    "2005-06-18T10:52:32+02:00",
    "2005-06-20T15:38:56+02:00",
    "2005-06-20T16:28:41+02:00",
    "2005-06-20T17:04:32+02:00",
    "2005-06-21T20:13:50+02:00",
    "2005-06-23T21:58:46+02:00",
    "2005-06-28T17:47:43+02:00",
    "2005-06-28T17:48:58+02:00",
    "2005-07-07T22:23:07+02:00",
    "2005-07-24T15:09:11+02:00",
    "2005-07-26T20:11:17+02:00"
  ],
  "traces": [
    {
      "exceptionType": "java.lang.ClassCastException",
      "message": "java.lang.String",
      "elements": [
        {
          "method": "org.eclipse.wst.common.frameworks.internal.datamodel.DataModelImpl.getIntProperty",
          "source": "DataModelImpl.java:136"
        },
        {
          "method": "org.eclipse.wst.common.frameworks.datamodel.AbstractDataModelProvider.getIntProperty",
          "source": "AbstractDataModelProvider.java:286"
        },
        {
          "method": "org.eclipse.jst.j2ee.application.internal.operations.J2EEComponentCreationDataModelProvider.getJ2EEVersion",
          "source": "J2EEComponentCreationDataModelProvider.java:555"
        },
        {
          "method": "org.eclipse.jst.j2ee.application.internal.operations.J2EEComponentCreationDataModelProvider.propertySet",
          "source": "J2EEComponentCreationDataModelProvider.java:116"
        },
        {
          "method": "org.eclipse.jst.j2ee.internal.web.archive.operations.WebComponentCreationDataModelProvider.propertySet",
          "source": "WebComponentCreationDataModelProvider.java:76"
        },
        {
          "method": "org.eclipse.wst.common.frameworks.internal.datamodel.DataModelImpl.internalSetProperty",
          "source": "DataModelImpl.java:176"
        },
        {
          "method": "org.eclipse.wst.common.frameworks.internal.datamodel.DataModelImpl.setProperty",
          "source": "DataModelImpl.java:166"
        },
        {
          "method": "org.eclipse.wst.common.frameworks.internal.datamodel.ui.DataModelSynchHelper.setProperty",
          "source": "DataModelSynchHelper.java:178"
        },
        {
          "method": "org.eclipse.wst.common.frameworks.internal.datamodel.ui.DataModelSynchHelper$ComboListener.modifyText",
          "source": "DataModelSynchHelper.java:96"
        },
        {
          "method": "org.eclipse.swt.widgets.TypedListener.handleEvent",
          "source": "TypedListener.java:187"
        },
        {
          "method": "org.eclipse.swt.widgets.EventTable.sendEvent",
          "source": "EventTable.java:66"
        },
        {
          "method": "org.eclipse.swt.widgets.Widget.sendEvent",
          "source": "Widget.java:1021"
        },
        {
          "method": "org.eclipse.swt.widgets.Widget.sendEvent",
          "source": "Widget.java:1045"
        },
        {
          "method": "org.eclipse.swt.widgets.Widget.sendEvent",
          "source": "Widget.java:1026"
        },
        {
          "method": "org.eclipse.swt.widgets.Combo.gtk_changed",
          "source": "Combo.java:859"
        },
        {
          "method": "org.eclipse.swt.widgets.Widget.windowProc",
          "source": "Widget.java:1315"
        },
        {
          "method": "org.eclipse.swt.widgets.Display.windowProc",
          "source": "Display.java:3380"
        },
        {
          "method": "org.eclipse.swt.internal.gtk.OS._gtk_main_do_event",
          "source": "Native Method"
        },
        {
          "method": "org.eclipse.swt.internal.gtk.OS.gtk_main_do_event",
          "source": "OS.java:4759"
        },
        {
          "method": "org.eclipse.swt.widgets.Display.eventProc",
          "source": "Display.java:1026"
        },
        {
          "method": "org.eclipse.swt.internal.gtk.OS._g_main_context_iteration",
          "source": "Native Method"
        },
        {
          "method": "org.eclipse.swt.internal.gtk.OS.g_main_context_iteration",
          "source": "OS.java:1149"
        },
        {
          "method": "org.eclipse.swt.widgets.Display.readAndDispatch",
          "source": "Display.java:2528"
        },
        {
          "method": "org.eclipse.jface.window.Window.runEventLoop",
          "source": "Window.java:809"
        },
        {
          "method": "org.eclipse.jface.window.Window.open",
          "source": "Window.java:787"
        },
        {
          "method": "org.eclipse.ui.actions.NewProjectAction.run",
          "source": "NewProjectAction.java:114"
        },
        {
          "method": "org.eclipse.jface.action.Action.runWithEvent",
          "source": "Action.java:996"
        },
        {
          "method": "org.eclipse.jface.action.ActionContributionItem.handleWidgetSelection",
          "source": "ActionContributionItem.java:538"
        }
      ],
      "number": 0,
      "commentIndex": 5,
      "bugId": "100520",
      "duplicateId": "103066",
      "date": "2005-06-20T16:28:41+02:00",
      "product": "Web Tools",
      "component": "jst.j2ee",
      "severity": "major"
    }
  ],
  "groupId": "93290",
  "bugId": "100520",
  "duplicateId": "103066",
  "date": "2005-06-17T08:58:01+02:00",
  "product": "Web Tools",
  "component": "jst.j2ee",
  "severity": "major"
}