{
  "comments": [
    "I found an NPE in my console but i don\u0027t know how to reproduce it and i have no\ntest case.\n\n!ENTRY org.eclipse.jdt.ui 4 0 2005-06-17 17:06:30.296\n!MESSAGE Error in JDT Core during reconcile\n!STACK 0\njava.lang.NullPointerException\n        at\norg.eclipse.jdt.internal.compiler.lookup.TypeVariableBinding.genericSignature(TypeVariableBinding.java:271)\n        at\norg.eclipse.jdt.internal.compiler.lookup.MethodBinding.genericSignature(MethodBinding.java:364)\n        at\norg.eclipse.jdt.internal.compiler.lookup.MethodBinding.computeUniqueKey(MethodBinding.java:321)\n        at\norg.eclipse.jdt.internal.compiler.lookup.MethodBinding.computeUniqueKey(MethodBinding.java:310)\n        at\norg.eclipse.jdt.internal.compiler.lookup.TypeVariableBinding.computeUniqueKey(TypeVariableBinding.java:242)\n        at\norg.eclipse.jdt.internal.compiler.lookup.Binding.computeUniqueKey(Binding.java:45)\n        at org.eclipse.jdt.core.dom.TypeBinding.getKey(TypeBinding.java:455)\n        at\norg.eclipse.jdt.core.dom.DefaultBindingResolver.resolveTypeParameter(DefaultBindingResolver.java:1399)\n        at\norg.eclipse.jdt.core.dom.TypeParameter.resolveBinding(TypeParameter.java:201)\n        at org.eclipse.jdt.core.dom.ASTConverter.convert(ASTConverter.java:2525)\n        at org.eclipse.jdt.core.dom.ASTConverter.convert(ASTConverter.java:546)\n        at\norg.eclipse.jdt.core.dom.ASTConverter.buildBodyDeclarations(ASTConverter.java:178)\n        at org.eclipse.jdt.core.dom.ASTConverter.convert(ASTConverter.java:2486)\n        at org.eclipse.jdt.core.dom.ASTConverter.convert(ASTConverter.java:1162)\n        at org.eclipse.jdt.core.dom.AST.convertCompilationUnit(AST.java:261)\n        at\norg.eclipse.jdt.internal.core.ReconcileWorkingCopyOperation.executeOperation(ReconcileWorkingCopyOperation.java:84)\n        at\norg.eclipse.jdt.internal.core.JavaModelOperation.run(JavaModelOperation.java:718)\n        at\norg.eclipse.jdt.internal.core.JavaModelOperation.runOperation(JavaModelOperation.java:777)\n        at\norg.eclipse.jdt.internal.core.CompilationUnit.reconcile(CompilationUnit.java:1081)\n        at\norg.eclipse.jdt.internal.ui.text.java.JavaReconcilingStrategy$1.run(JavaReconcilingStrategy.java:98)\n        at\norg.eclipse.core.internal.runtime.InternalPlatform.run(InternalPlatform.java:1044)\n        at org.eclipse.core.runtime.Platform.run(Platform.java:783)\n        at\norg.eclipse.jdt.internal.ui.text.java.JavaReconcilingStrategy.reconcile(JavaReconcilingStrategy.java:82)\n        at\norg.eclipse.jdt.internal.ui.text.java.JavaReconcilingStrategy.reconcile(JavaReconcilingStrategy.java:147)\n        at\norg.eclipse.jdt.internal.ui.text.CompositeReconcilingStrategy.reconcile(CompositeReconcilingStrategy.java:86)\n        at\norg.eclipse.jdt.internal.ui.text.JavaCompositeReconcilingStrategy.reconcile(JavaCompositeReconcilingStrategy.java:94)\n        at\norg.eclipse.jface.text.reconciler.MonoReconciler.process(MonoReconciler.java:75)\n        at\norg.eclipse.jdt.internal.ui.text.JavaReconciler.process(JavaReconciler.java:339)\n        at\norg.eclipse.jface.text.reconciler.AbstractReconciler$BackgroundThread.run(AbstractReconciler.java:204)",
    "Reduced test case (from David)\n\npublic class X {\n\tvoid bar() throws BinSub {\n\t}\n\t\u003cT\u003e void foo() {\n\t}\n}",
    "where BinSub is a binary type with missing superclass (manually deleted\nclassfile for supertype in classfolder).",
    "Kent - what about initializing type variable superInterfaces to\nNoSuperInterfaces when creating them ? We may never get a chance to connect them.",
    "But then, what about other sort of types... maybe null checks are preferrable in\nvarious places where it gets used.",
    "We cannot initialize them before since its part of the cycle detection that \nthey are null.\n\nI think this case needs a null check.",
    "According to David, an AbortCompilation is thrown, but we catch it in the\nASTConverter and still attempt to return a DOM AST with resolved bindings. We\nmight consider not returning bindings at all in this case.",
    "Unfortunately, the AbortCompilation is not caught in the ASTConverter, but in\nthe CompilationUnitProblemFinder (subclass of Compiler).\n\nSo the best thing we can do is to add a null check.",
    "Created an attachment (id\u003d26299)\nNull checks added\n",
    "Created an attachment (id\u003d26300)\nRegression test\n",
    "+1 for 3.1.1",
    "Released fix and regression test (renamed to test0197()) in both HEAD and\nR3_1_maintenance branch.",
    "Verified in I20050920-0010 for 3.2M2",
    "Verified for 3.1.1 using M20050923-1430."
  ],
  "commentCreationDates": [
    "2005-06-17T18:17:43+02:00",
    "2005-06-23T18:34:06+02:00",
    "2005-06-23T18:34:47+02:00",
    "2005-06-23T18:37:32+02:00",
    "2005-06-23T18:40:55+02:00",
    "2005-06-23T19:09:26+02:00",
    "2005-06-24T12:11:24+02:00",
    "2005-08-19T16:47:08+02:00",
    "2005-08-19T17:02:42+02:00",
    "2005-08-19T17:03:04+02:00",
    "2005-09-01T12:11:12+02:00",
    "2005-09-01T15:35:46+02:00",
    "2005-09-21T13:33:50+02:00",
    "2005-09-26T16:13:59+02:00"
  ],
  "traces": [
    {
      "exceptionType": "java.lang.NullPointerException",
      "elements": [
        {
          "method": "org.eclipse.jdt.internal.compiler.lookup.TypeVariableBinding.genericSignature",
          "source": "TypeVariableBinding.java:271"
        },
        {
          "method": "org.eclipse.jdt.internal.compiler.lookup.MethodBinding.genericSignature",
          "source": "MethodBinding.java:364"
        },
        {
          "method": "org.eclipse.jdt.internal.compiler.lookup.MethodBinding.computeUniqueKey",
          "source": "MethodBinding.java:321"
        },
        {
          "method": "org.eclipse.jdt.internal.compiler.lookup.MethodBinding.computeUniqueKey",
          "source": "MethodBinding.java:310"
        },
        {
          "method": "org.eclipse.jdt.internal.compiler.lookup.TypeVariableBinding.computeUniqueKey",
          "source": "TypeVariableBinding.java:242"
        },
        {
          "method": "org.eclipse.jdt.internal.compiler.lookup.Binding.computeUniqueKey",
          "source": "Binding.java:45"
        },
        {
          "method": "org.eclipse.jdt.core.dom.TypeBinding.getKey",
          "source": "TypeBinding.java:455"
        },
        {
          "method": "org.eclipse.jdt.core.dom.DefaultBindingResolver.resolveTypeParameter",
          "source": "DefaultBindingResolver.java:1399"
        },
        {
          "method": "org.eclipse.jdt.core.dom.TypeParameter.resolveBinding",
          "source": "TypeParameter.java:201"
        },
        {
          "method": "org.eclipse.jdt.core.dom.ASTConverter.convert",
          "source": "ASTConverter.java:2525"
        },
        {
          "method": "org.eclipse.jdt.core.dom.ASTConverter.convert",
          "source": "ASTConverter.java:546"
        },
        {
          "method": "org.eclipse.jdt.core.dom.ASTConverter.buildBodyDeclarations",
          "source": "ASTConverter.java:178"
        },
        {
          "method": "org.eclipse.jdt.core.dom.ASTConverter.convert",
          "source": "ASTConverter.java:2486"
        },
        {
          "method": "org.eclipse.jdt.core.dom.ASTConverter.convert",
          "source": "ASTConverter.java:1162"
        },
        {
          "method": "org.eclipse.jdt.core.dom.AST.convertCompilationUnit",
          "source": "AST.java:261"
        },
        {
          "method": "org.eclipse.jdt.internal.core.ReconcileWorkingCopyOperation.executeOperation",
          "source": "ReconcileWorkingCopyOperation.java:84"
        },
        {
          "method": "org.eclipse.jdt.internal.core.JavaModelOperation.run",
          "source": "JavaModelOperation.java:718"
        },
        {
          "method": "org.eclipse.jdt.internal.core.JavaModelOperation.runOperation",
          "source": "JavaModelOperation.java:777"
        },
        {
          "method": "org.eclipse.jdt.internal.core.CompilationUnit.reconcile",
          "source": "CompilationUnit.java:1081"
        },
        {
          "method": "org.eclipse.jdt.internal.ui.text.java.JavaReconcilingStrategy$1.run",
          "source": "JavaReconcilingStrategy.java:98"
        },
        {
          "method": "org.eclipse.core.internal.runtime.InternalPlatform.run",
          "source": "InternalPlatform.java:1044"
        },
        {
          "method": "org.eclipse.core.runtime.Platform.run",
          "source": "Platform.java:783"
        },
        {
          "method": "org.eclipse.jdt.internal.ui.text.java.JavaReconcilingStrategy.reconcile",
          "source": "JavaReconcilingStrategy.java:82"
        },
        {
          "method": "org.eclipse.jdt.internal.ui.text.java.JavaReconcilingStrategy.reconcile",
          "source": "JavaReconcilingStrategy.java:147"
        },
        {
          "method": "org.eclipse.jdt.internal.ui.text.CompositeReconcilingStrategy.reconcile",
          "source": "CompositeReconcilingStrategy.java:86"
        },
        {
          "method": "org.eclipse.jdt.internal.ui.text.JavaCompositeReconcilingStrategy.reconcile",
          "source": "JavaCompositeReconcilingStrategy.java:94"
        },
        {
          "method": "org.eclipse.jface.text.reconciler.MonoReconciler.process",
          "source": "MonoReconciler.java:75"
        },
        {
          "method": "org.eclipse.jdt.internal.ui.text.JavaReconciler.process",
          "source": "JavaReconciler.java:339"
        },
        {
          "method": "org.eclipse.jface.text.reconciler.AbstractReconciler$BackgroundThread.run",
          "source": "AbstractReconciler.java:204"
        }
      ],
      "number": 0,
      "commentIndex": 0,
      "bugId": "100606",
      "date": "2005-06-17T18:17:43+02:00",
      "product": "JDT",
      "component": "Core",
      "severity": "normal"
    }
  ],
  "groupId": "100606",
  "bugId": "100606",
  "date": "2005-06-17T18:17:43+02:00",
  "product": "JDT",
  "component": "Core",
  "severity": "normal"
}