{
  "comments": [
    "I was trying to open the EAR Import dialog using File -\u003e Import -\u003e EAR File -\u003e\nNext and got the following propery not found exception.\n\nbuild used N0620\n\n\n!ENTRY org.eclipse.ui 4 0 2005-06-20 11:04:38.957\n!MESSAGE Property not located:ServerTargetDataModel.RUNTIME_TARGET_ID\n!STACK 0\njava.lang.RuntimeException: Property not located:ServerTargetDataModel.RUNTIME_T\nARGET_ID\n        at org.eclipse.wst.common.frameworks.internal.datamodel.DataModelImpl.ch\neckValidPropertyName(DataModelImpl.java:94)\n        at org.eclipse.wst.common.frameworks.internal.datamodel.DataModelImpl.ge\ntOwningDataModel(DataModelImpl.java:99)\n        at org.eclipse.wst.common.frameworks.internal.datamodel.DataModelImpl.ge\ntValidPropertyDescriptors(DataModelImpl.java:313)\n        at org.eclipse.wst.common.frameworks.internal.datamodel.ui.DataModelSync\nhHelper.setWidgetValue(DataModelSynchHelper.java:291)\n        at org.eclipse.wst.common.frameworks.internal.datamodel.ui.DataModelSync\nhHelper.synchUIWithModel(DataModelSynchHelper.java:210)\n        at org.eclipse.wst.common.frameworks.internal.datamodel.ui.DataModelSync\nhHelper.synchComposite(DataModelSynchHelper.java:428)\n        at org.eclipse.wst.common.frameworks.internal.datamodel.ui.DataModelSync\nhHelper.synchCombo(DataModelSynchHelper.java:465)\n        at org.eclipse.jst.j2ee.internal.wizard.EARComponentImportPage.createSer\nverTargetComposite(EARComponentImportPage.java:126)\n        at org.eclipse.jst.j2ee.internal.wizard.J2EEImportPage.createProjectName\nComposite(J2EEImportPage.java:106)\n        at org.eclipse.jst.j2ee.internal.wizard.EARComponentImportPage.createTop\nLevelComposite(EARComponentImportPage.java:70)\n        at org.eclipse.wst.common.frameworks.internal.datamodel.ui.DataModelWiza\nrdPage.createControl(DataModelWizardPage.java:91)\n        at org.eclipse.wst.common.frameworks.internal.datamodel.ui.DataModelWiza\nrd.createPageControls(DataModelWizard.java:83)\n        at org.eclipse.jface.wizard.WizardDialog.createPageControls(WizardDialog\n.java:611)\n        at org.eclipse.jface.wizard.WizardDialog.setWizard(WizardDialog.java:965\n)\n        at org.eclipse.jface.wizard.WizardDialog.updateForPage(WizardDialog.java\n:1016)\n        at org.eclipse.jface.wizard.WizardDialog.access$2(WizardDialog.java:1013\n)\n        at org.eclipse.jface.wizard.WizardDialog$4.run(WizardDialog.java:1003)\n        at org.eclipse.swt.custom.BusyIndicator.showWhile(BusyIndicator.java:69)\n\n        at org.eclipse.jface.wizard.WizardDialog.showPage(WizardDialog.java:1001\n)\n        at org.eclipse.jface.wizard.WizardDialog.nextPressed(WizardDialog.java:7\n53)\n        at org.eclipse.jface.wizard.WizardDialog.buttonPressed(WizardDialog.java\n:345)\n        at org.eclipse.jface.dialogs.Dialog$2.widgetSelected(Dialog.java:556)\n        at org.eclipse.swt.widgets.TypedListener.handleEvent(TypedListener.java:\n89)\n        at org.eclipse.swt.widgets.EventTable.sendEvent(EventTable.java:66)\n        at org.eclipse.swt.widgets.Widget.sendEvent(Widget.java:844)\n        at org.eclipse.swt.widgets.Display.runDeferredEvents(Display.java:3058)\n        at org.eclipse.swt.widgets.Display.readAndDispatch(Display.java:2691)\n        at org.eclipse.jface.window.Window.runEventLoop(Window.java:809)\n        at org.eclipse.jface.window.Window.open(Window.java:787)\n        at org.eclipse.ui.actions.ImportResourcesAction.run(ImportResourcesActio\nn.java:159)\n        at org.eclipse.ui.actions.BaseSelectionListenerAction.runWithEvent(BaseS\nelectionListenerAction.java:167)\n        at org.eclipse.jface.action.ActionContributionItem.handleWidgetSelection\n(ActionContributionItem.java:538)\n        at org.eclipse.jface.action.ActionContributionItem.access$2(ActionContri\nbutionItem.java:488)\n        at org.eclipse.jface.action.ActionContributionItem$5.handleEvent(ActionC\nontributionItem.java:400)\n        at org.eclipse.swt.widgets.EventTable.sendEvent(EventTable.java:66)\n        at org.eclipse.swt.widgets.Widget.sendEvent(Widget.java:844)\n        at org.eclipse.swt.widgets.Display.runDeferredEvents(Display.java:3058)\n        at org.eclipse.swt.widgets.Display.readAndDispatch(Display.java:2691)\n        at org.eclipse.ui.internal.Workbench.runEventLoop(Workbench.java:1716)\n        at org.eclipse.ui.internal.Workbench.runUI(Workbench.java:1680)\n        at org.eclipse.ui.internal.Workbench.createAndRunWorkbench(Workbench.jav\na:365)\n        at org.eclipse.ui.PlatformUI.createAndRunWorkbench(PlatformUI.java:143)\n        at org.eclipse.ui.internal.ide.IDEApplication.run(IDEApplication.java:10\n3)\n        at org.eclipse.core.internal.runtime.PlatformActivator$1.run(PlatformAct\nivator.java:226)\n        at org.eclipse.core.runtime.adaptor.EclipseStarter.run(EclipseStarter.ja\nva:376)\n        at org.eclipse.core.runtime.adaptor.EclipseStarter.run(EclipseStarter.ja\nva:163)\n        at sun.reflect.NativeMethodAccessorImpl.invoke0(Native Method)\n        at sun.reflect.NativeMethodAccessorImpl.invoke(Unknown Source)\n        at sun.reflect.DelegatingMethodAccessorImpl.invoke(Unknown Source)\n        at java.lang.reflect.Method.invoke(Unknown Source)\n        at org.eclipse.core.launcher.Main.invokeFramework(Main.java:334)\n        at org.eclipse.core.launcher.Main.basicRun(Main.java:278)\n        at org.eclipse.core.launcher.Main.run(Main.java:973)\n        at org.eclipse.core.launcher.Main.main(Main.java:948)\nProperty not located:ServerTargetDataModel.RUNTIME_TARGET_ID",
    "code in cvs",
    "verified on 06/22 wtp driver"
  ],
  "commentCreationDates": [
    "2005-06-20T17:15:03+02:00",
    "2005-06-20T22:22:30+02:00",
    "2005-06-22T16:19:12+02:00"
  ],
  "traces": [
    {
      "exceptionType": "java.lang.RuntimeException",
      "message": "Property not located:ServerTargetDataModel.RUNTIME_T ARGET_ID",
      "elements": [
        {
          "method": "org.eclipse.wst.common.frameworks.internal.datamodel.DataModelImpl.checkValidPropertyName",
          "source": "DataModelImpl.java:94"
        },
        {
          "method": "org.eclipse.wst.common.frameworks.internal.datamodel.DataModelImpl.getOwningDataModel",
          "source": "DataModelImpl.java:99"
        },
        {
          "method": "org.eclipse.wst.common.frameworks.internal.datamodel.DataModelImpl.getValidPropertyDescriptors",
          "source": "DataModelImpl.java:313"
        },
        {
          "method": "org.eclipse.wst.common.frameworks.internal.datamodel.ui.DataModelSynchHelper.setWidgetValue",
          "source": "DataModelSynchHelper.java:291"
        },
        {
          "method": "org.eclipse.wst.common.frameworks.internal.datamodel.ui.DataModelSynchHelper.synchUIWithModel",
          "source": "DataModelSynchHelper.java:210"
        },
        {
          "method": "org.eclipse.wst.common.frameworks.internal.datamodel.ui.DataModelSynchHelper.synchComposite",
          "source": "DataModelSynchHelper.java:428"
        },
        {
          "method": "org.eclipse.wst.common.frameworks.internal.datamodel.ui.DataModelSynchHelper.synchCombo",
          "source": "DataModelSynchHelper.java:465"
        },
        {
          "method": "org.eclipse.jst.j2ee.internal.wizard.EARComponentImportPage.createServerTargetComposite",
          "source": "EARComponentImportPage.java:126"
        },
        {
          "method": "org.eclipse.jst.j2ee.internal.wizard.J2EEImportPage.createProjectNameComposite",
          "source": "J2EEImportPage.java:106"
        },
        {
          "method": "org.eclipse.jst.j2ee.internal.wizard.EARComponentImportPage.createTopLevelComposite",
          "source": "EARComponentImportPage.java:70"
        },
        {
          "method": "org.eclipse.wst.common.frameworks.internal.datamodel.ui.DataModelWizardPage.createControl",
          "source": "DataModelWizardPage.java:91"
        },
        {
          "method": "org.eclipse.wst.common.frameworks.internal.datamodel.ui.DataModelWizard.createPageControls",
          "source": "DataModelWizard.java:83"
        },
        {
          "method": "org.eclipse.jface.wizard.WizardDialog.createPageControls",
          "source": "WizardDialog .java:611"
        },
        {
          "method": "org.eclipse.jface.wizard.WizardDialog.setWizard",
          "source": "WizardDialog.java:965 "
        },
        {
          "method": "org.eclipse.jface.wizard.WizardDialog.updateForPage",
          "source": "WizardDialog.java :1016"
        },
        {
          "method": "org.eclipse.jface.wizard.WizardDialog.access$2",
          "source": "WizardDialog.java:1013 "
        },
        {
          "method": "org.eclipse.jface.wizard.WizardDialog$4.run",
          "source": "WizardDialog.java:1003"
        },
        {
          "method": "org.eclipse.swt.custom.BusyIndicator.showWhile",
          "source": "BusyIndicator.java:69"
        },
        {
          "method": "org.eclipse.jface.wizard.WizardDialog.showPage",
          "source": "WizardDialog.java:1001 "
        },
        {
          "method": "org.eclipse.jface.wizard.WizardDialog.nextPressed",
          "source": "WizardDialog.java:7 53"
        },
        {
          "method": "org.eclipse.jface.wizard.WizardDialog.buttonPressed",
          "source": "WizardDialog.java :345"
        },
        {
          "method": "org.eclipse.jface.dialogs.Dialog$2.widgetSelected",
          "source": "Dialog.java:556"
        },
        {
          "method": "org.eclipse.swt.widgets.TypedListener.handleEvent",
          "source": "TypedListener.java: 89"
        },
        {
          "method": "org.eclipse.swt.widgets.EventTable.sendEvent",
          "source": "EventTable.java:66"
        },
        {
          "method": "org.eclipse.swt.widgets.Widget.sendEvent",
          "source": "Widget.java:844"
        },
        {
          "method": "org.eclipse.swt.widgets.Display.runDeferredEvents",
          "source": "Display.java:3058"
        },
        {
          "method": "org.eclipse.swt.widgets.Display.readAndDispatch",
          "source": "Display.java:2691"
        },
        {
          "method": "org.eclipse.jface.window.Window.runEventLoop",
          "source": "Window.java:809"
        },
        {
          "method": "org.eclipse.jface.window.Window.open",
          "source": "Window.java:787"
        },
        {
          "method": "org.eclipse.ui.actions.ImportResourcesAction.run",
          "source": "ImportResourcesActio n.java:159"
        },
        {
          "method": "org.eclipse.ui.actions.BaseSelectionListenerAction.runWithEvent",
          "source": "BaseS electionListenerAction.java:167"
        },
        {
          "method": "org.eclipse.jface.action.ActionContributionItem.handleWidgetSelection",
          "source": "ActionContributionItem.java:538"
        },
        {
          "method": "org.eclipse.jface.action.ActionContributionItem.access$2",
          "source": "ActionContri butionItem.java:488"
        },
        {
          "method": "org.eclipse.jface.action.ActionContributionItem$5.handleEvent",
          "source": "ActionC ontributionItem.java:400"
        },
        {
          "method": "org.eclipse.swt.widgets.EventTable.sendEvent",
          "source": "EventTable.java:66"
        },
        {
          "method": "org.eclipse.swt.widgets.Widget.sendEvent",
          "source": "Widget.java:844"
        },
        {
          "method": "org.eclipse.swt.widgets.Display.runDeferredEvents",
          "source": "Display.java:3058"
        },
        {
          "method": "org.eclipse.swt.widgets.Display.readAndDispatch",
          "source": "Display.java:2691"
        },
        {
          "method": "org.eclipse.ui.internal.Workbench.runEventLoop",
          "source": "Workbench.java:1716"
        },
        {
          "method": "org.eclipse.ui.internal.Workbench.runUI",
          "source": "Workbench.java:1680"
        },
        {
          "method": "org.eclipse.ui.internal.Workbench.createAndRunWorkbench",
          "source": "Workbench.jav a:365"
        },
        {
          "method": "org.eclipse.ui.PlatformUI.createAndRunWorkbench",
          "source": "PlatformUI.java:143"
        },
        {
          "method": "org.eclipse.ui.internal.ide.IDEApplication.run",
          "source": "IDEApplication.java:10 3"
        },
        {
          "method": "org.eclipse.core.internal.runtime.PlatformActivator$1.run",
          "source": "PlatformAct ivator.java:226"
        },
        {
          "method": "org.eclipse.core.runtime.adaptor.EclipseStarter.run",
          "source": "EclipseStarter.ja va:376"
        },
        {
          "method": "org.eclipse.core.runtime.adaptor.EclipseStarter.run",
          "source": "EclipseStarter.ja va:163"
        },
        {
          "method": "sun.reflect.NativeMethodAccessorImpl.invoke0",
          "source": "Native Method"
        },
        {
          "method": "sun.reflect.NativeMethodAccessorImpl.invoke",
          "source": "Unknown Source"
        },
        {
          "method": "sun.reflect.DelegatingMethodAccessorImpl.invoke",
          "source": "Unknown Source"
        },
        {
          "method": "java.lang.reflect.Method.invoke",
          "source": "Unknown Source"
        },
        {
          "method": "org.eclipse.core.launcher.Main.invokeFramework",
          "source": "Main.java:334"
        },
        {
          "method": "org.eclipse.core.launcher.Main.basicRun",
          "source": "Main.java:278"
        },
        {
          "method": "org.eclipse.core.launcher.Main.run",
          "source": "Main.java:973"
        },
        {
          "method": "org.eclipse.core.launcher.Main.main",
          "source": "Main.java:948"
        }
      ],
      "number": 0,
      "commentIndex": 0,
      "bugId": "100847",
      "date": "2005-06-20T17:15:03+02:00",
      "product": "Web Tools",
      "component": "jst.j2ee",
      "severity": "blocker"
    }
  ],
  "groupId": "100847",
  "bugId": "100847",
  "date": "2005-06-20T17:15:03+02:00",
  "product": "Web Tools",
  "component": "jst.j2ee",
  "severity": "blocker"
}