{
  "comments": [
    "The following validation error is being thrown on War import. Looks like the War\nvalidator is trying to load the DD before it is actually created. This looks to\nbe a timing issue that i have seen on the ejb validator too. \n\n*** ERROR ***: Mon Jun 20 10:45:06 EDT 2005    org.eclipse.jst.j2ee.commonarchiv\necore.internal.exception.OpenFailureException: IWAE0006E Archive is not a valid\nWAR File because the deployment descriptor can not be found (case sensitive): WE\nB-INF/web.xml\n        at org.eclipse.jst.j2ee.commonarchivecore.internal.impl.CommonarchiveFac\ntoryImpl.openSpecificArchive(CommonarchiveFactoryImpl.java:793)\n        at org.eclipse.jst.j2ee.commonarchivecore.internal.impl.CommonarchiveFac\ntoryImpl.openWARFile(CommonarchiveFactoryImpl.java:829)\n        at org.eclipse.jst.j2ee.web.componentcore.util.WebArtifactEdit.asArchive\n(WebArtifactEdit.java:599)\n        at org.eclipse.jst.j2ee.internal.web.validation.WarHelper.loadWarFile(Wa\nrHelper.java:110)\n        at sun.reflect.NativeMethodAccessorImpl.invoke0(Native Method)\n        at sun.reflect.NativeMethodAccessorImpl.invoke(Unknown Source)\n        at sun.reflect.DelegatingMethodAccessorImpl.invoke(Unknown Source)\n        at java.lang.reflect.Method.invoke(Unknown Source)\n        at org.eclipse.wst.validation.internal.operations.WorkbenchContext.loadM\nodel(WorkbenchContext.java:585)\n        at org.eclipse.wst.validation.internal.operations.WorkbenchContext.loadM\nodel(WorkbenchContext.java:567)\n        at org.eclipse.jst.j2ee.model.internal.validation.WarValidator.validate(\nWarValidator.java:252)\n        at org.eclipse.jst.j2ee.internal.web.validation.UIWarValidator.validate(\nUIWarValidator.java:92)\n        at org.eclipse.wst.validation.internal.core.ValidatorLauncher.start(Vali\ndatorLauncher.java:90)\n        at org.eclipse.wst.validation.internal.operations.ValidationOperation.la\nunchValidator(ValidationOperation.java:1196)\n        at org.eclipse.wst.validation.internal.operations.ValidationOperation.in\nternalValidate(ValidationOperation.java:1022)\n        at org.eclipse.wst.validation.internal.operations.ValidationOperation.va\nlidate(ValidationOperation.java:928)\n        at org.eclipse.wst.validation.internal.operations.ValidationOperation.ru\nn(ValidationOperation.java:639)\n        at org.eclipse.wst.validation.internal.operations.ValidationBuilder.perf\normFullBuild(ValidationBuilder.java:262)\n        at org.eclipse.wst.validation.internal.operations.ValidationBuilder.perf\normFullBuild(ValidationBuilder.java:254)\n        at org.eclipse.wst.validation.internal.operations.ValidationBuilder.buil\nd(ValidationBuilder.java:195)\n        at org.eclipse.core.internal.events.BuildManager$2.run(BuildManager.java\n:593)\n        at org.eclipse.core.internal.runtime.InternalPlatform.run(InternalPlatfo\nrm.java:1038)\n        at org.eclipse.core.runtime.Platform.run(Platform.java:775)\n        at org.eclipse.core.internal.events.BuildManager.basicBuild(BuildManager\n.java:168)\n        at org.eclipse.core.internal.events.BuildManager.basicBuild(BuildManager\n.java:202)\n        at org.eclipse.core.internal.events.BuildManager$1.run(BuildManager.java\n:231)\n        at org.eclipse.core.internal.runtime.InternalPlatform.run(InternalPlatfo\nrm.java:1038)\n        at org.eclipse.core.runtime.Platform.run(Platform.java:775)\n        at org.eclipse.core.internal.events.BuildManager.basicBuild(BuildManager\n.java:234)\n        at org.eclipse.core.internal.events.BuildManager.basicBuildLoop(BuildMan\nager.java:253)\n        at org.eclipse.core.internal.events.BuildManager.build(BuildManager.java\n:282)\n        at org.eclipse.core.internal.events.AutoBuildJob.doBuild(AutoBuildJob.ja\nva:139)\n        at org.eclipse.core.internal.events.AutoBuildJob.run(AutoBuildJob.java:2\n00)\n        at org.eclipse.core.internal.jobs.Worker.run(Worker.java:76)",
    "Fixed, validation code looks for exsiting DD before validating but in my \nopinion we should design validation framework so that validation is not kicked \noff until creation is completed.\n",
    "Verified in M5 build"
  ],
  "commentCreationDates": [
    "2005-06-20T16:52:19+02:00",
    "2005-06-20T17:59:30+02:00",
    "2005-07-06T23:25:18+02:00"
  ],
  "traces": [
    {
      "exceptionType": "ecore.internal.exception.OpenFailureException",
      "message": "IWAE0006E Archive is not a valid WAR File because the deployment descriptor can not be found (case sensitive): WE B-INF/web.xml",
      "elements": [
        {
          "method": "org.eclipse.jst.j2ee.commonarchivecore.internal.impl.CommonarchiveFactoryImpl.openSpecificArchive",
          "source": "CommonarchiveFactoryImpl.java:793"
        },
        {
          "method": "org.eclipse.jst.j2ee.commonarchivecore.internal.impl.CommonarchiveFactoryImpl.openWARFile",
          "source": "CommonarchiveFactoryImpl.java:829"
        },
        {
          "method": "org.eclipse.jst.j2ee.web.componentcore.util.WebArtifactEdit.asArchive",
          "source": "WebArtifactEdit.java:599"
        },
        {
          "method": "org.eclipse.jst.j2ee.internal.web.validation.WarHelper.loadWarFile",
          "source": "Wa rHelper.java:110"
        },
        {
          "method": "sun.reflect.NativeMethodAccessorImpl.invoke0",
          "source": "Native Method"
        },
        {
          "method": "sun.reflect.NativeMethodAccessorImpl.invoke",
          "source": "Unknown Source"
        },
        {
          "method": "sun.reflect.DelegatingMethodAccessorImpl.invoke",
          "source": "Unknown Source"
        },
        {
          "method": "java.lang.reflect.Method.invoke",
          "source": "Unknown Source"
        },
        {
          "method": "org.eclipse.wst.validation.internal.operations.WorkbenchContext.loadModel",
          "source": "WorkbenchContext.java:585"
        },
        {
          "method": "org.eclipse.wst.validation.internal.operations.WorkbenchContext.loadModel",
          "source": "WorkbenchContext.java:567"
        },
        {
          "method": "org.eclipse.jst.j2ee.model.internal.validation.WarValidator.validate",
          "source": " WarValidator.java:252"
        },
        {
          "method": "org.eclipse.jst.j2ee.internal.web.validation.UIWarValidator.validate",
          "source": " UIWarValidator.java:92"
        },
        {
          "method": "org.eclipse.wst.validation.internal.core.ValidatorLauncher.start",
          "source": "Vali datorLauncher.java:90"
        },
        {
          "method": "org.eclipse.wst.validation.internal.operations.ValidationOperation.launchValidator",
          "source": "ValidationOperation.java:1196"
        },
        {
          "method": "org.eclipse.wst.validation.internal.operations.ValidationOperation.internalValidate",
          "source": "ValidationOperation.java:1022"
        },
        {
          "method": "org.eclipse.wst.validation.internal.operations.ValidationOperation.validate",
          "source": "ValidationOperation.java:928"
        },
        {
          "method": "org.eclipse.wst.validation.internal.operations.ValidationOperation.run",
          "source": "ValidationOperation.java:639"
        },
        {
          "method": "org.eclipse.wst.validation.internal.operations.ValidationBuilder.performFullBuild",
          "source": "ValidationBuilder.java:262"
        },
        {
          "method": "org.eclipse.wst.validation.internal.operations.ValidationBuilder.performFullBuild",
          "source": "ValidationBuilder.java:254"
        },
        {
          "method": "org.eclipse.wst.validation.internal.operations.ValidationBuilder.build",
          "source": "ValidationBuilder.java:195"
        },
        {
          "method": "org.eclipse.core.internal.events.BuildManager$2.run",
          "source": "BuildManager.java :593"
        },
        {
          "method": "org.eclipse.core.internal.runtime.InternalPlatform.run",
          "source": "InternalPlatfo rm.java:1038"
        },
        {
          "method": "org.eclipse.core.runtime.Platform.run",
          "source": "Platform.java:775"
        },
        {
          "method": "org.eclipse.core.internal.events.BuildManager.basicBuild",
          "source": "BuildManager .java:168"
        },
        {
          "method": "org.eclipse.core.internal.events.BuildManager.basicBuild",
          "source": "BuildManager .java:202"
        },
        {
          "method": "org.eclipse.core.internal.events.BuildManager$1.run",
          "source": "BuildManager.java :231"
        },
        {
          "method": "org.eclipse.core.internal.runtime.InternalPlatform.run",
          "source": "InternalPlatfo rm.java:1038"
        },
        {
          "method": "org.eclipse.core.runtime.Platform.run",
          "source": "Platform.java:775"
        },
        {
          "method": "org.eclipse.core.internal.events.BuildManager.basicBuild",
          "source": "BuildManager .java:234"
        },
        {
          "method": "org.eclipse.core.internal.events.BuildManager.basicBuildLoop",
          "source": "BuildMan ager.java:253"
        },
        {
          "method": "org.eclipse.core.internal.events.BuildManager.build",
          "source": "BuildManager.java :282"
        },
        {
          "method": "org.eclipse.core.internal.events.AutoBuildJob.doBuild",
          "source": "AutoBuildJob.ja va:139"
        },
        {
          "method": "org.eclipse.core.internal.events.AutoBuildJob.run",
          "source": "AutoBuildJob.java:2 00"
        },
        {
          "method": "org.eclipse.core.internal.jobs.Worker.run",
          "source": "Worker.java:76"
        }
      ],
      "number": 0,
      "commentIndex": 0,
      "bugId": "100833",
      "date": "2005-06-20T16:52:19+02:00",
      "product": "Web Tools",
      "component": "jst.j2ee",
      "severity": "blocker"
    }
  ],
  "groupId": "100833",
  "bugId": "100833",
  "date": "2005-06-20T16:52:19+02:00",
  "product": "Web Tools",
  "component": "jst.j2ee",
  "severity": "blocker"
}