{
  "comments": [
    "I am testing 2005/06/20 build. \nStep to reproduce:\n1. With a fresh workspace, create an J2EE EJB project. Type name as Ejb1.\n2. Click the Browse... button for Project location, and select am empty \nfolder, like D:\\temp.\n3. Expand Advanced toggle button, and click New.. button for Target server, \nand select JonAS4.1.4.\n4. Accept all other default settings. Click Finish.\nStack Trace:\n*** ERROR ***: Mon Jun 20 14:40:40 EDT 2005    \norg.eclipse.jst.j2ee.commonarchiv\necore.internal.exception.OpenFailureException: IWAE0006E Archive is not a valid\nEJB JAR File because the deployment descriptor can not be found (case \nsensitive)\n: META-INF/ejb-jar.xml\n        at \norg.eclipse.jst.j2ee.commonarchivecore.internal.impl.CommonarchiveFac\ntoryImpl.openSpecificArchive(CommonarchiveFactoryImpl.java:793)\n        at \norg.eclipse.jst.j2ee.commonarchivecore.internal.impl.CommonarchiveFac\ntoryImpl.openSpecificArchive(CommonarchiveFactoryImpl.java:804)\n        at \norg.eclipse.jst.j2ee.commonarchivecore.internal.impl.CommonarchiveFac\ntoryImpl.openEJBJarFile(CommonarchiveFactoryImpl.java:681)\n        at \norg.eclipse.jst.j2ee.ejb.componentcore.util.EJBArtifactEdit.asArchive\n(EJBArtifactEdit.java:501)\n        at \norg.eclipse.jst.j2ee.internal.ejb.workbench.validation.UIEjbValidator\n.validate(UIEjbValidator.java:56)\n        at org.eclipse.wst.validation.internal.core.ValidatorLauncher.start\n(Vali\ndatorLauncher.java:90)\n        at \norg.eclipse.wst.validation.internal.operations.ValidationOperation.la\nunchValidator(ValidationOperation.java:1196)\n        at \norg.eclipse.wst.validation.internal.operations.ValidationOperation.in\nternalValidate(ValidationOperation.java:1022)\n        at \norg.eclipse.wst.validation.internal.operations.ValidationOperation.va\nlidate(ValidationOperation.java:928)\n        at \norg.eclipse.wst.validation.internal.operations.ValidationOperation.ru\nn(ValidationOperation.java:639)\n        at \norg.eclipse.wst.validation.internal.operations.ValidationBuilder.perf\normFullBuild(ValidationBuilder.java:262)\n        at \norg.eclipse.wst.validation.internal.operations.ValidationBuilder.perf\normFullBuild(ValidationBuilder.java:254)\n        at \norg.eclipse.wst.validation.internal.operations.ValidationBuilder.buil\nd(ValidationBuilder.java:195)\n        at org.eclipse.core.internal.events.BuildManager$2.run\n(BuildManager.java\n:593)\n        at org.eclipse.core.internal.runtime.InternalPlatform.run\n(InternalPlatfo\nrm.java:1038)\n        at org.eclipse.core.runtime.Platform.run(Platform.java:775)\n        at org.eclipse.core.internal.events.BuildManager.basicBuild\n(BuildManager\n.java:168)\n        at org.eclipse.core.internal.events.BuildManager.basicBuild\n(BuildManager\n.java:202)\n        at org.eclipse.core.internal.events.BuildManager$1.run\n(BuildManager.java\n:231)\n        at org.eclipse.core.internal.runtime.InternalPlatform.run\n(InternalPlatfo\nrm.java:1038)\n        at org.eclipse.core.runtime.Platform.run(Platform.java:775)\n        at org.eclipse.core.internal.events.BuildManager.basicBuild\n(BuildManager\n.java:234)\n        at org.eclipse.core.internal.events.BuildManager.basicBuildLoop\n(BuildMan\nager.java:253)\n        at org.eclipse.core.internal.events.BuildManager.build\n(BuildManager.java\n:282)\n        at org.eclipse.core.internal.events.AutoBuildJob.doBuild\n(AutoBuildJob.ja\nva:139)\n        at org.eclipse.core.internal.events.AutoBuildJob.run\n(AutoBuildJob.java:2\n00)\n        at org.eclipse.core.internal.jobs.Worker.run(Worker.java:76)\n\n*** ERROR ***: Mon Jun 20 14:40:40 EDT 2005    \norg.eclipse.jst.j2ee.commonarchiv\necore.internal.exception.OpenFailureException: IWAE0006E Archive is not a valid\nEJB JAR File because the deployment descriptor can not be found (case \nsensitive)\n: META-INF/ejb-jar.xml\n        at \norg.eclipse.jst.j2ee.commonarchivecore.internal.impl.CommonarchiveFac\ntoryImpl.openSpecificArchive(CommonarchiveFactoryImpl.java:793)\n        at \norg.eclipse.jst.j2ee.commonarchivecore.internal.impl.CommonarchiveFac\ntoryImpl.openSpecificArchive(CommonarchiveFactoryImpl.java:804)\n        at \norg.eclipse.jst.j2ee.commonarchivecore.internal.impl.CommonarchiveFac\ntoryImpl.openEJBJarFile(CommonarchiveFactoryImpl.java:681)\n        at \norg.eclipse.jst.j2ee.ejb.componentcore.util.EJBArtifactEdit.asArchive\n(EJBArtifactEdit.java:501)\n        at \norg.eclipse.jst.j2ee.internal.ejb.workbench.validation.EJBHelper.load\nEjbModel(EJBHelper.java:564)\n        at sun.reflect.NativeMethodAccessorImpl.invoke0(Native Method)\n        at sun.reflect.NativeMethodAccessorImpl.invoke(Unknown Source)\n        at sun.reflect.DelegatingMethodAccessorImpl.invoke(Unknown Source)\n        at java.lang.reflect.Method.invoke(Unknown Source)\n        at \norg.eclipse.wst.validation.internal.operations.WorkbenchContext.loadM\nodel(WorkbenchContext.java:585)\n        at \norg.eclipse.jst.j2ee.internal.ejb.workbench.validation.EJBHelper.load\nModel(EJBHelper.java:294)\n        at \norg.eclipse.wst.validation.internal.operations.WorkbenchContext.loadM\nodel(WorkbenchContext.java:567)\n        at \norg.eclipse.jst.j2ee.model.internal.validation.EJBValidationContext.l\noadModel(EJBValidationContext.java:116)\n        at \norg.eclipse.jst.j2ee.model.internal.validation.EJBValidator.fullValid\nate(EJBValidator.java:363)\n        at org.eclipse.jst.j2ee.model.internal.validation.EJBValidator.validate\n(\nEJBValidator.java:79)\n        at \norg.eclipse.jst.j2ee.internal.ejb.workbench.validation.UIEjbValidator\n.validate(UIEjbValidator.java:65)\n        at org.eclipse.wst.validation.internal.core.ValidatorLauncher.start\n(Vali\ndatorLauncher.java:90)\n        at \norg.eclipse.wst.validation.internal.operations.ValidationOperation.la\nunchValidator(ValidationOperation.java:1196)\n        at \norg.eclipse.wst.validation.internal.operations.ValidationOperation.in\nternalValidate(ValidationOperation.java:1022)\n        at \norg.eclipse.wst.validation.internal.operations.ValidationOperation.va\nlidate(ValidationOperation.java:928)\n        at \norg.eclipse.wst.validation.internal.operations.ValidationOperation.ru\nn(ValidationOperation.java:639)\n        at \norg.eclipse.wst.validation.internal.operations.ValidationBuilder.perf\normFullBuild(ValidationBuilder.java:262)\n        at \norg.eclipse.wst.validation.internal.operations.ValidationBuilder.perf\normFullBuild(ValidationBuilder.java:254)\n        at \norg.eclipse.wst.validation.internal.operations.ValidationBuilder.buil\nd(ValidationBuilder.java:195)\n        at org.eclipse.core.internal.events.BuildManager$2.run\n(BuildManager.java\n:593)\n        at org.eclipse.core.internal.runtime.InternalPlatform.run\n(InternalPlatfo\nrm.java:1038)\n        at org.eclipse.core.runtime.Platform.run(Platform.java:775)\n        at org.eclipse.core.internal.events.BuildManager.basicBuild\n(BuildManager\n.java:168)\n        at org.eclipse.core.internal.events.BuildManager.basicBuild\n(BuildManager\n.java:202)\n        at org.eclipse.core.internal.events.BuildManager$1.run\n(BuildManager.java\n:231)\n        at org.eclipse.core.internal.runtime.InternalPlatform.run\n(InternalPlatfo\nrm.java:1038)\n        at org.eclipse.core.runtime.Platform.run(Platform.java:775)\n        at org.eclipse.core.internal.events.BuildManager.basicBuild\n(BuildManager\n.java:234)\n        at org.eclipse.core.internal.events.BuildManager.basicBuildLoop\n(BuildMan\nager.java:253)\n        at org.eclipse.core.internal.events.BuildManager.build\n(BuildManager.java\n:282)\n        at org.eclipse.core.internal.events.AutoBuildJob.doBuild\n(AutoBuildJob.ja\nva:139)\n        at org.eclipse.core.internal.events.AutoBuildJob.run\n(AutoBuildJob.java:2\n00)\n        at org.eclipse.core.internal.jobs.Worker.run(Worker.java:76)",
    "This defect has been fixed on 6/20",
    "ok."
  ],
  "commentCreationDates": [
    "2005-06-20T20:49:20+02:00",
    "2005-06-22T15:34:49+02:00",
    "2005-07-11T19:22:52+02:00"
  ],
  "traces": [
    {
      "exceptionType": "ecore.internal.exception.OpenFailureException",
      "message": "IWAE0006E Archive is not a valid EJB JAR File because the deployment descriptor can not be found (case  sensitive) : META-INF/ejb-jar.xml",
      "elements": [
        {
          "method": "org.eclipse.jst.j2ee.commonarchivecore.internal.impl.CommonarchiveFactoryImpl.openSpecificArchive",
          "source": "CommonarchiveFactoryImpl.java:793"
        },
        {
          "method": "org.eclipse.jst.j2ee.commonarchivecore.internal.impl.CommonarchiveFactoryImpl.openSpecificArchive",
          "source": "CommonarchiveFactoryImpl.java:804"
        },
        {
          "method": "org.eclipse.jst.j2ee.commonarchivecore.internal.impl.CommonarchiveFactoryImpl.openEJBJarFile",
          "source": "CommonarchiveFactoryImpl.java:681"
        },
        {
          "method": "org.eclipse.jst.j2ee.ejb.componentcore.util.EJBArtifactEdit.asArchive",
          "source": "EJBArtifactEdit.java:501"
        },
        {
          "method": "org.eclipse.jst.j2ee.internal.ejb.workbench.validation.UIEjbValidator.validate",
          "source": "UIEjbValidator.java:56"
        },
        {
          "method": "org.eclipse.wst.validation.internal.core.ValidatorLauncher.start",
          "source": "Vali datorLauncher.java:90"
        },
        {
          "method": "org.eclipse.wst.validation.internal.operations.ValidationOperation.launchValidator",
          "source": "ValidationOperation.java:1196"
        },
        {
          "method": "org.eclipse.wst.validation.internal.operations.ValidationOperation.internalValidate",
          "source": "ValidationOperation.java:1022"
        },
        {
          "method": "org.eclipse.wst.validation.internal.operations.ValidationOperation.validate",
          "source": "ValidationOperation.java:928"
        },
        {
          "method": "org.eclipse.wst.validation.internal.operations.ValidationOperation.run",
          "source": "ValidationOperation.java:639"
        },
        {
          "method": "org.eclipse.wst.validation.internal.operations.ValidationBuilder.performFullBuild",
          "source": "ValidationBuilder.java:262"
        },
        {
          "method": "org.eclipse.wst.validation.internal.operations.ValidationBuilder.performFullBuild",
          "source": "ValidationBuilder.java:254"
        },
        {
          "method": "org.eclipse.wst.validation.internal.operations.ValidationBuilder.build",
          "source": "ValidationBuilder.java:195"
        },
        {
          "method": "org.eclipse.core.internal.events.BuildManager$2.run",
          "source": "BuildManager.java :593"
        },
        {
          "method": "org.eclipse.core.internal.runtime.InternalPlatform.run",
          "source": "InternalPlatfo rm.java:1038"
        },
        {
          "method": "org.eclipse.core.runtime.Platform.run",
          "source": "Platform.java:775"
        },
        {
          "method": "org.eclipse.core.internal.events.BuildManager.basicBuild",
          "source": "BuildManager .java:168"
        },
        {
          "method": "org.eclipse.core.internal.events.BuildManager.basicBuild",
          "source": "BuildManager .java:202"
        },
        {
          "method": "org.eclipse.core.internal.events.BuildManager$1.run",
          "source": "BuildManager.java :231"
        },
        {
          "method": "org.eclipse.core.internal.runtime.InternalPlatform.run",
          "source": "InternalPlatfo rm.java:1038"
        },
        {
          "method": "org.eclipse.core.runtime.Platform.run",
          "source": "Platform.java:775"
        },
        {
          "method": "org.eclipse.core.internal.events.BuildManager.basicBuild",
          "source": "BuildManager .java:234"
        },
        {
          "method": "org.eclipse.core.internal.events.BuildManager.basicBuildLoop",
          "source": "BuildMan ager.java:253"
        },
        {
          "method": "org.eclipse.core.internal.events.BuildManager.build",
          "source": "BuildManager.java :282"
        },
        {
          "method": "org.eclipse.core.internal.events.AutoBuildJob.doBuild",
          "source": "AutoBuildJob.ja va:139"
        },
        {
          "method": "org.eclipse.core.internal.events.AutoBuildJob.run",
          "source": "AutoBuildJob.java:2 00"
        },
        {
          "method": "org.eclipse.core.internal.jobs.Worker.run",
          "source": "Worker.java:76"
        }
      ],
      "number": 0,
      "commentIndex": 0,
      "bugId": "100933",
      "date": "2005-06-20T20:49:20+02:00",
      "product": "Web Tools",
      "component": "jst.j2ee",
      "severity": "major"
    },
    {
      "exceptionType": "ecore.internal.exception.OpenFailureException",
      "message": "IWAE0006E Archive is not a valid EJB JAR File because the deployment descriptor can not be found (case  sensitive) : META-INF/ejb-jar.xml",
      "elements": [
        {
          "method": "org.eclipse.jst.j2ee.commonarchivecore.internal.impl.CommonarchiveFactoryImpl.openSpecificArchive",
          "source": "CommonarchiveFactoryImpl.java:793"
        },
        {
          "method": "org.eclipse.jst.j2ee.commonarchivecore.internal.impl.CommonarchiveFactoryImpl.openSpecificArchive",
          "source": "CommonarchiveFactoryImpl.java:804"
        },
        {
          "method": "org.eclipse.jst.j2ee.commonarchivecore.internal.impl.CommonarchiveFactoryImpl.openEJBJarFile",
          "source": "CommonarchiveFactoryImpl.java:681"
        },
        {
          "method": "org.eclipse.jst.j2ee.ejb.componentcore.util.EJBArtifactEdit.asArchive",
          "source": "EJBArtifactEdit.java:501"
        },
        {
          "method": "org.eclipse.jst.j2ee.internal.ejb.workbench.validation.EJBHelper.loadEjbModel",
          "source": "EJBHelper.java:564"
        },
        {
          "method": "sun.reflect.NativeMethodAccessorImpl.invoke0",
          "source": "Native Method"
        },
        {
          "method": "sun.reflect.NativeMethodAccessorImpl.invoke",
          "source": "Unknown Source"
        },
        {
          "method": "sun.reflect.DelegatingMethodAccessorImpl.invoke",
          "source": "Unknown Source"
        },
        {
          "method": "java.lang.reflect.Method.invoke",
          "source": "Unknown Source"
        },
        {
          "method": "org.eclipse.wst.validation.internal.operations.WorkbenchContext.loadModel",
          "source": "WorkbenchContext.java:585"
        },
        {
          "method": "org.eclipse.jst.j2ee.internal.ejb.workbench.validation.EJBHelper.loadModel",
          "source": "EJBHelper.java:294"
        },
        {
          "method": "org.eclipse.wst.validation.internal.operations.WorkbenchContext.loadModel",
          "source": "WorkbenchContext.java:567"
        },
        {
          "method": "org.eclipse.jst.j2ee.model.internal.validation.EJBValidationContext.loadModel",
          "source": "EJBValidationContext.java:116"
        },
        {
          "method": "org.eclipse.jst.j2ee.model.internal.validation.EJBValidator.fullValidate",
          "source": "EJBValidator.java:363"
        },
        {
          "method": "org.eclipse.jst.j2ee.model.internal.validation.EJBValidator.validate",
          "source": " EJBValidator.java:79"
        },
        {
          "method": "org.eclipse.jst.j2ee.internal.ejb.workbench.validation.UIEjbValidator.validate",
          "source": "UIEjbValidator.java:65"
        },
        {
          "method": "org.eclipse.wst.validation.internal.core.ValidatorLauncher.start",
          "source": "Vali datorLauncher.java:90"
        },
        {
          "method": "org.eclipse.wst.validation.internal.operations.ValidationOperation.launchValidator",
          "source": "ValidationOperation.java:1196"
        },
        {
          "method": "org.eclipse.wst.validation.internal.operations.ValidationOperation.internalValidate",
          "source": "ValidationOperation.java:1022"
        },
        {
          "method": "org.eclipse.wst.validation.internal.operations.ValidationOperation.validate",
          "source": "ValidationOperation.java:928"
        },
        {
          "method": "org.eclipse.wst.validation.internal.operations.ValidationOperation.run",
          "source": "ValidationOperation.java:639"
        },
        {
          "method": "org.eclipse.wst.validation.internal.operations.ValidationBuilder.performFullBuild",
          "source": "ValidationBuilder.java:262"
        },
        {
          "method": "org.eclipse.wst.validation.internal.operations.ValidationBuilder.performFullBuild",
          "source": "ValidationBuilder.java:254"
        },
        {
          "method": "org.eclipse.wst.validation.internal.operations.ValidationBuilder.build",
          "source": "ValidationBuilder.java:195"
        },
        {
          "method": "org.eclipse.core.internal.events.BuildManager$2.run",
          "source": "BuildManager.java :593"
        },
        {
          "method": "org.eclipse.core.internal.runtime.InternalPlatform.run",
          "source": "InternalPlatfo rm.java:1038"
        },
        {
          "method": "org.eclipse.core.runtime.Platform.run",
          "source": "Platform.java:775"
        },
        {
          "method": "org.eclipse.core.internal.events.BuildManager.basicBuild",
          "source": "BuildManager .java:168"
        },
        {
          "method": "org.eclipse.core.internal.events.BuildManager.basicBuild",
          "source": "BuildManager .java:202"
        },
        {
          "method": "org.eclipse.core.internal.events.BuildManager$1.run",
          "source": "BuildManager.java :231"
        },
        {
          "method": "org.eclipse.core.internal.runtime.InternalPlatform.run",
          "source": "InternalPlatfo rm.java:1038"
        },
        {
          "method": "org.eclipse.core.runtime.Platform.run",
          "source": "Platform.java:775"
        },
        {
          "method": "org.eclipse.core.internal.events.BuildManager.basicBuild",
          "source": "BuildManager .java:234"
        },
        {
          "method": "org.eclipse.core.internal.events.BuildManager.basicBuildLoop",
          "source": "BuildMan ager.java:253"
        },
        {
          "method": "org.eclipse.core.internal.events.BuildManager.build",
          "source": "BuildManager.java :282"
        },
        {
          "method": "org.eclipse.core.internal.events.AutoBuildJob.doBuild",
          "source": "AutoBuildJob.ja va:139"
        },
        {
          "method": "org.eclipse.core.internal.events.AutoBuildJob.run",
          "source": "AutoBuildJob.java:2 00"
        },
        {
          "method": "org.eclipse.core.internal.jobs.Worker.run",
          "source": "Worker.java:76"
        }
      ],
      "number": 1,
      "commentIndex": 0,
      "bugId": "100933",
      "date": "2005-06-20T20:49:20+02:00",
      "product": "Web Tools",
      "component": "jst.j2ee",
      "severity": "major"
    }
  ],
  "groupId": "100933",
  "bugId": "100933",
  "date": "2005-06-20T20:49:20+02:00",
  "product": "Web Tools",
  "component": "jst.j2ee",
  "severity": "major"
}