{
  "comments": [
    "With a current N-build, in a fresh workspace, create a new Tomcat 5.0 runtime \nand server and a new J2EE Web project.  If I use Run As -\u003e Run on Server and \nclick Next to reach the \"Add and Remove Projects\" page, the Next button is \nstill enabled, which I believe should not be enabled (I\u0027m not aware of another \npage to be displayed).  Clicking nexts results in:\n\njava.lang.IllegalArgumentException: Argument cannot be null\n\tat org.eclipse.swt.SWT.error(SWT.java:2924)\n\tat org.eclipse.swt.SWT.error(SWT.java:2863)\n\tat org.eclipse.swt.SWT.error(SWT.java:2834)\n\tat org.eclipse.swt.widgets.Widget.error(Widget.java:395)\n\tat org.eclipse.swt.widgets.Button.setText(Button.java:751)\n\tat \norg.eclipse.wst.server.ui.internal.wizard.page.TasksComposite.createControl\n(TasksComposite.java:95)\n\tat \norg.eclipse.wst.server.ui.internal.wizard.fragment.TasksWizardFragment.enter\n(TasksWizardFragment.java:93)\n\tat \norg.eclipse.wst.server.ui.internal.wizard.TaskWizard.switchWizardFragment\n(TaskWizard.java:280)\n...",
    "Problem was caused by a faulty Tomcat publish operation + an NPE in the wizard\npage because of a null label \u0026 description. Fixed both problems \u0026 removed the\noperation from the plugin.xml as well since it is experimental at this stage.\nFix dropped to HEAD and will be tagged for weekly I-build.",
    "I was incorrect about the need for the Next button.  I have verified that the \nexception does not occur in M5.",
    "Closing."
  ],
  "commentCreationDates": [
    "2005-06-21T17:00:33+02:00",
    "2005-06-21T17:27:43+02:00",
    "2005-07-11T18:56:56+02:00",
    "2005-07-12T21:07:24+02:00"
  ],
  "traces": [
    {
      "exceptionType": "java.lang.IllegalArgumentException",
      "message": "Argument cannot be null",
      "elements": [
        {
          "method": "org.eclipse.swt.SWT.error",
          "source": "SWT.java:2924"
        },
        {
          "method": "org.eclipse.swt.SWT.error",
          "source": "SWT.java:2863"
        },
        {
          "method": "org.eclipse.swt.SWT.error",
          "source": "SWT.java:2834"
        },
        {
          "method": "org.eclipse.swt.widgets.Widget.error",
          "source": "Widget.java:395"
        },
        {
          "method": "org.eclipse.swt.widgets.Button.setText",
          "source": "Button.java:751"
        },
        {
          "method": "org.eclipse.wst.server.ui.internal.wizard.page.TasksComposite.createControl",
          "source": "TasksComposite.java:95"
        },
        {
          "method": "org.eclipse.wst.server.ui.internal.wizard.fragment.TasksWizardFragment.enter",
          "source": "TasksWizardFragment.java:93"
        },
        {
          "method": "org.eclipse.wst.server.ui.internal.wizard.TaskWizard.switchWizardFragment",
          "source": "TaskWizard.java:280"
        }
      ],
      "number": 0,
      "commentIndex": 0,
      "bugId": "101063",
      "date": "2005-06-21T17:00:33+02:00",
      "product": "Web Tools",
      "component": "wst.server",
      "severity": "normal"
    }
  ],
  "groupId": "101063",
  "bugId": "101063",
  "date": "2005-06-21T17:00:33+02:00",
  "product": "Web Tools",
  "component": "wst.server",
  "severity": "normal"
}