{
  "comments": [
    "bring up the new Connector wizard and type asdf/ for the project name.\n\n!ENTRY org.eclipse.ui 4 0 2005-06-22 16:07:44.983\n!MESSAGE Path for project must have only one segment.\n!STACK 0\njava.lang.IllegalArgumentException: Path for project must have only one segment.\n        at org.eclipse.core.internal.utils.Assert.isLegal(Assert.java(Inlined\nCompiled Code))\n        at\norg.eclipse.core.internal.resources.WorkspaceRoot.getProject(WorkspaceRoot.java(Compiled\nCode))\n        at\norg.eclipse.jem.util.emf.workbench.ProjectUtilities.getProject(ProjectUtilities.java:728)\n        at\norg.eclipse.jst.j2ee.application.internal.operations.J2EEComponentCreationDataModelProvider.computeEARHandle(\nJ2EEComponentCreationDataModelProvider.java:139)\n        at\norg.eclipse.jst.j2ee.application.internal.operations.J2EEComponentCreationDataModelProvider.propertySet(J2EEC\nomponentCreationDataModelProvider.java:108)\n        at\norg.eclipse.wst.common.frameworks.internal.datamodel.DataModelImpl.internalSetProperty(DataModelImpl.java:176\n)\n        at\norg.eclipse.wst.common.frameworks.internal.datamodel.DataModelImpl.setProperty(DataModelImpl.java:166)\n        at\norg.eclipse.wst.common.frameworks.internal.datamodel.ui.DataModelSynchHelper.setProperty(DataModelSynchHelper\n.java:178)\n        at\norg.eclipse.wst.common.frameworks.internal.datamodel.ui.DataModelSynchHelper$ModifyTextListener.modifyText(Da\ntaModelSynchHelper.java:71)\n        at org.eclipse.swt.widgets.TypedListener.handleEvent(TypedListener.java:187)\n        at org.eclipse.swt.widgets.EventTable.sendEvent(EventTable.java(Compiled\nCode))\n        at org.eclipse.swt.widgets.Widget.sendEvent(Widget.java(Inlined Compiled\nCode))\n        at org.eclipse.swt.widgets.Widget.sendEvent(Widget.java(Compiled Code))\n        at org.eclipse.swt.widgets.Widget.sendEvent(Widget.java(Compiled Code))\n        at org.eclipse.swt.widgets.Text.wmCommandChild(Text.java:2027)\n        at org.eclipse.swt.widgets.Control.WM_COMMAND(Control.java:3163)\n        at org.eclipse.swt.widgets.Control.windowProc(Control.java(Compiled Code))\n        at org.eclipse.swt.widgets.Display.windowProc(Display.java(Compiled Code))\n        at org.eclipse.swt.internal.win32.OS.CallWindowProcW(Native Method)\n        at org.eclipse.swt.internal.win32.OS.CallWindowProc(OS.java(Compiled Code))\n        at org.eclipse.swt.widgets.Text.callWindowProc(Text.java:127)\n        at org.eclipse.swt.widgets.Control.windowProc(Control.java(Compiled Code))\n        at org.eclipse.swt.widgets.Text.windowProc(Text.java:1743)\n        at org.eclipse.swt.widgets.Display.windowProc(Display.java(Compiled Code))\n        at org.eclipse.swt.internal.win32.OS.DispatchMessageW(Native Method)\n        at org.eclipse.swt.internal.win32.OS.DispatchMessage(OS.java(Inlined\nCompiled Code))\n        at org.eclipse.swt.widgets.Display.readAndDispatch(Display.java(Compiled\nCode))\n        at org.eclipse.jface.window.Window.runEventLoop(Window.java(Compiled Code))\n        at org.eclipse.jface.window.Window.open(Window.java:787)\n        at org.eclipse.ui.actions.NewWizardAction.run(NewWizardAction.java:181)\n        at org.eclipse.jface.action.Action.runWithEvent(Action.java:996)\n        at\norg.eclipse.jface.action.ActionContributionItem.handleWidgetSelection(ActionContributionItem.java:538)\n        at\norg.eclipse.jface.action.ActionContributionItem.access$2(ActionContributionItem.java:488)\n        at\norg.eclipse.jface.action.ActionContributionItem$5.handleEvent(ActionContributionItem.java:400)\n        at org.eclipse.swt.widgets.EventTable.sendEvent(EventTable.java(Compiled\nCode))\n        at org.eclipse.swt.widgets.Widget.sendEvent(Widget.java(Inlined Compiled\nCode))\n        at\norg.eclipse.swt.widgets.Display.runDeferredEvents(Display.java(Compiled Code))\n        at org.eclipse.swt.widgets.Display.readAndDispatch(Display.java(Compiled\nCode))\n        at\norg.eclipse.ui.internal.Workbench.runEventLoop(Workbench.java(Compiled Code))\n        at org.eclipse.ui.internal.Workbench.runUI(Workbench.java:1663)\n        at\norg.eclipse.ui.internal.Workbench.createAndRunWorkbench(Workbench.java:367)\n        at org.eclipse.ui.PlatformUI.createAndRunWorkbench(PlatformUI.java:143)\n        at org.eclipse.ui.internal.ide.IDEApplication.run(IDEApplication.java:103)\n        at\norg.eclipse.core.internal.runtime.PlatformActivator$1.run(PlatformActivator.java:226)\n        at\norg.eclipse.core.runtime.adaptor.EclipseStarter.run(EclipseStarter.java:376)\n        at\norg.eclipse.core.runtime.adaptor.EclipseStarter.run(EclipseStarter.java:163)\n        at sun.reflect.NativeMethodAccessorImpl.invoke0(Native Method)\n        at\nsun.reflect.NativeMethodAccessorImpl.invoke(NativeMethodAccessorImpl.java:85)\n        at\nsun.reflect.NativeMethodAccessorImpl.invoke(NativeMethodAccessorImpl.java:58)\n        at\nsun.reflect.DelegatingMethodAccessorImpl.invoke(DelegatingMethodAccessorImpl.java:60)\n        at java.lang.reflect.Method.invoke(Method.java:391)\n        at org.eclipse.core.launcher.Main.invokeFramework(Main.java:334)\n        at org.eclipse.core.launcher.Main.basicRun(Main.java:278)\n        at org.eclipse.core.launcher.Main.run(Main.java:973)\n        at org.eclipse.core.launcher.Main.main(Main.java:948)\nPath for project must have only one segment.",
    "fix dropped 6.29",
    "verified"
  ],
  "commentCreationDates": [
    "2005-06-22T22:08:44+02:00",
    "2005-06-29T16:27:36+02:00",
    "2005-07-11T16:35:25+02:00"
  ],
  "traces": [
    {
      "exceptionType": "java.lang.IllegalArgumentException",
      "message": "Path for project must have only one segment.",
      "elements": [
        {
          "method": "org.eclipse.core.internal.utils.Assert.isLegal",
          "source": "Assert.java(Inlined Compiled Code)"
        },
        {
          "method": "org.eclipse.core.internal.resources.WorkspaceRoot.getProject",
          "source": "WorkspaceRoot.java(Compiled Code)"
        },
        {
          "method": "org.eclipse.jem.util.emf.workbench.ProjectUtilities.getProject",
          "source": "ProjectUtilities.java:728"
        },
        {
          "method": "org.eclipse.jst.j2ee.application.internal.operations.J2EEComponentCreationDataModelProvider.computeEARHandle",
          "source": " J2EEComponentCreationDataModelProvider.java:139"
        },
        {
          "method": "org.eclipse.jst.j2ee.application.internal.operations.J2EEComponentCreationDataModelProvider.propertySet",
          "source": "J2EEC omponentCreationDataModelProvider.java:108"
        },
        {
          "method": "org.eclipse.wst.common.frameworks.internal.datamodel.DataModelImpl.internalSetProperty",
          "source": "DataModelImpl.java:176 "
        },
        {
          "method": "org.eclipse.wst.common.frameworks.internal.datamodel.DataModelImpl.setProperty",
          "source": "DataModelImpl.java:166"
        },
        {
          "method": "org.eclipse.wst.common.frameworks.internal.datamodel.ui.DataModelSynchHelper.setProperty",
          "source": "DataModelSynchHelper .java:178"
        },
        {
          "method": "org.eclipse.wst.common.frameworks.internal.datamodel.ui.DataModelSynchHelper$ModifyTextListener.modifyText",
          "source": "Da taModelSynchHelper.java:71"
        },
        {
          "method": "org.eclipse.swt.widgets.TypedListener.handleEvent",
          "source": "TypedListener.java:187"
        },
        {
          "method": "org.eclipse.swt.widgets.EventTable.sendEvent",
          "source": "EventTable.java(Compiled Code)"
        },
        {
          "method": "org.eclipse.swt.widgets.Widget.sendEvent",
          "source": "Widget.java(Inlined Compiled Code)"
        },
        {
          "method": "org.eclipse.swt.widgets.Widget.sendEvent",
          "source": "Widget.java(Compiled Code)"
        },
        {
          "method": "org.eclipse.swt.widgets.Widget.sendEvent",
          "source": "Widget.java(Compiled Code)"
        },
        {
          "method": "org.eclipse.swt.widgets.Text.wmCommandChild",
          "source": "Text.java:2027"
        },
        {
          "method": "org.eclipse.swt.widgets.Control.WM_COMMAND",
          "source": "Control.java:3163"
        },
        {
          "method": "org.eclipse.swt.widgets.Control.windowProc",
          "source": "Control.java(Compiled Code)"
        },
        {
          "method": "org.eclipse.swt.widgets.Display.windowProc",
          "source": "Display.java(Compiled Code)"
        },
        {
          "method": "org.eclipse.swt.internal.win32.OS.CallWindowProcW",
          "source": "Native Method"
        },
        {
          "method": "org.eclipse.swt.internal.win32.OS.CallWindowProc",
          "source": "OS.java(Compiled Code)"
        },
        {
          "method": "org.eclipse.swt.widgets.Text.callWindowProc",
          "source": "Text.java:127"
        },
        {
          "method": "org.eclipse.swt.widgets.Control.windowProc",
          "source": "Control.java(Compiled Code)"
        },
        {
          "method": "org.eclipse.swt.widgets.Text.windowProc",
          "source": "Text.java:1743"
        },
        {
          "method": "org.eclipse.swt.widgets.Display.windowProc",
          "source": "Display.java(Compiled Code)"
        },
        {
          "method": "org.eclipse.swt.internal.win32.OS.DispatchMessageW",
          "source": "Native Method"
        },
        {
          "method": "org.eclipse.swt.internal.win32.OS.DispatchMessage",
          "source": "OS.java(Inlined Compiled Code)"
        },
        {
          "method": "org.eclipse.swt.widgets.Display.readAndDispatch",
          "source": "Display.java(Compiled Code)"
        },
        {
          "method": "org.eclipse.jface.window.Window.runEventLoop",
          "source": "Window.java(Compiled Code)"
        },
        {
          "method": "org.eclipse.jface.window.Window.open",
          "source": "Window.java:787"
        },
        {
          "method": "org.eclipse.ui.actions.NewWizardAction.run",
          "source": "NewWizardAction.java:181"
        },
        {
          "method": "org.eclipse.jface.action.Action.runWithEvent",
          "source": "Action.java:996"
        },
        {
          "method": "org.eclipse.jface.action.ActionContributionItem.handleWidgetSelection",
          "source": "ActionContributionItem.java:538"
        },
        {
          "method": "org.eclipse.jface.action.ActionContributionItem.access$2",
          "source": "ActionContributionItem.java:488"
        },
        {
          "method": "org.eclipse.jface.action.ActionContributionItem$5.handleEvent",
          "source": "ActionContributionItem.java:400"
        },
        {
          "method": "org.eclipse.swt.widgets.EventTable.sendEvent",
          "source": "EventTable.java(Compiled Code)"
        },
        {
          "method": "org.eclipse.swt.widgets.Widget.sendEvent",
          "source": "Widget.java(Inlined Compiled Code)"
        },
        {
          "method": "org.eclipse.swt.widgets.Display.runDeferredEvents",
          "source": "Display.java(Compiled Code)"
        },
        {
          "method": "org.eclipse.swt.widgets.Display.readAndDispatch",
          "source": "Display.java(Compiled Code)"
        },
        {
          "method": "org.eclipse.ui.internal.Workbench.runEventLoop",
          "source": "Workbench.java(Compiled Code)"
        },
        {
          "method": "org.eclipse.ui.internal.Workbench.runUI",
          "source": "Workbench.java:1663"
        },
        {
          "method": "org.eclipse.ui.internal.Workbench.createAndRunWorkbench",
          "source": "Workbench.java:367"
        },
        {
          "method": "org.eclipse.ui.PlatformUI.createAndRunWorkbench",
          "source": "PlatformUI.java:143"
        },
        {
          "method": "org.eclipse.ui.internal.ide.IDEApplication.run",
          "source": "IDEApplication.java:103"
        },
        {
          "method": "org.eclipse.core.internal.runtime.PlatformActivator$1.run",
          "source": "PlatformActivator.java:226"
        },
        {
          "method": "org.eclipse.core.runtime.adaptor.EclipseStarter.run",
          "source": "EclipseStarter.java:376"
        },
        {
          "method": "org.eclipse.core.runtime.adaptor.EclipseStarter.run",
          "source": "EclipseStarter.java:163"
        },
        {
          "method": "sun.reflect.NativeMethodAccessorImpl.invoke0",
          "source": "Native Method"
        },
        {
          "method": "sun.reflect.NativeMethodAccessorImpl.invoke",
          "source": "NativeMethodAccessorImpl.java:85"
        },
        {
          "method": "sun.reflect.NativeMethodAccessorImpl.invoke",
          "source": "NativeMethodAccessorImpl.java:58"
        },
        {
          "method": "sun.reflect.DelegatingMethodAccessorImpl.invoke",
          "source": "DelegatingMethodAccessorImpl.java:60"
        },
        {
          "method": "java.lang.reflect.Method.invoke",
          "source": "Method.java:391"
        },
        {
          "method": "org.eclipse.core.launcher.Main.invokeFramework",
          "source": "Main.java:334"
        },
        {
          "method": "org.eclipse.core.launcher.Main.basicRun",
          "source": "Main.java:278"
        },
        {
          "method": "org.eclipse.core.launcher.Main.run",
          "source": "Main.java:973"
        },
        {
          "method": "org.eclipse.core.launcher.Main.main",
          "source": "Main.java:948"
        }
      ],
      "number": 0,
      "commentIndex": 0,
      "bugId": "101347",
      "date": "2005-06-22T22:08:44+02:00",
      "product": "Web Tools",
      "component": "jst.j2ee",
      "severity": "normal"
    }
  ],
  "groupId": "101347",
  "bugId": "101347",
  "date": "2005-06-22T22:08:44+02:00",
  "product": "Web Tools",
  "component": "jst.j2ee",
  "severity": "normal"
}