{
  "comments": [
    "This error occours while running Eclipse SDK 3.0.2 (gtk-amd64 build) on the\nUbuntu Linux/amd64 OS (clean install/new workspace/Sun JDK 5.0 64bits). \n\nWhen I try to invoke the \"Installed JRE\u0027s\" dialog I get an error message saying\n\"The currently displayed page contains invalid values\". \n\n.log:\n!SESSION Jun 24, 2005 08:30:01.58 ----------------------------------------------\neclipse.buildId\u003dM200503110845\njava.version\u003d1.5.0_03\njava.vendor\u003dSun Microsystems Inc.\nBootLoader constants: OS\u003dlinux, ARCH\u003damd64, WS\u003dgtk, NL\u003den_US\n\n!ENTRY org.eclipse.core.runtime 4 2 Jun 24, 2005 08:30:01.59\n!MESSAGE Problems occurred when invoking code from plug-in:\n\"org.eclipse.core.runtime\".\n!STACK 0\njava.lang.UnsatisfiedLinkError: gtk_tree_view_column_get_fixed_width\n        at\norg.eclipse.swt.internal.gtk.OS.gtk_tree_view_column_get_fixed_width(Native Method)\n        at org.eclipse.swt.widgets.TableColumn.getWidth(TableColumn.java:261)\n        at\norg.eclipse.jdt.internal.debug.ui.jres.InstalledJREsBlock.resizeTable(InstalledJREsBlock.java:541)\n        at\norg.eclipse.jdt.internal.debug.ui.jres.InstalledJREsBlock.access$9(InstalledJREsBlock.java:503)\n        at\norg.eclipse.jdt.internal.debug.ui.jres.InstalledJREsBlock$15.controlResized(InstalledJREsBlock.java:478)\n        at org.eclipse.swt.widgets.TypedListener.handleEvent(TypedListener.java:148)\n        at org.eclipse.swt.widgets.EventTable.sendEvent(EventTable.java:82)\n        at org.eclipse.swt.widgets.Widget.sendEvent(Widget.java:954)\n        at org.eclipse.swt.widgets.Widget.sendEvent(Widget.java:978)\n        at org.eclipse.swt.widgets.Widget.sendEvent(Widget.java:959)\n        at org.eclipse.swt.widgets.Control.setBounds(Control.java:538)\n        at org.eclipse.swt.widgets.Composite.setBounds(Composite.java:693)\n        at org.eclipse.swt.widgets.Control.setBounds(Control.java:461)\n        at org.eclipse.swt.layout.GridLayout.layout(GridLayout.java:684)\n        at org.eclipse.swt.widgets.Composite.layout(Composite.java:565)\n        at\norg.eclipse.jface.preference.PreferencePage.doComputeSize(PreferencePage.java:328)\n        at\norg.eclipse.jface.preference.PreferencePage.computeSize(PreferencePage.java:150)\n        at\norg.eclipse.jface.preference.PreferenceDialog$13.run(PreferenceDialog.java:1027)\n        at\norg.eclipse.core.internal.runtime.InternalPlatform.run(InternalPlatform.java:616)\n        at org.eclipse.core.runtime.Platform.run(Platform.java:747)\n        at\norg.eclipse.jface.preference.PreferenceDialog.showPage(PreferenceDialog.java:1022)\n        at\norg.eclipse.jface.preference.PreferenceDialog$8.selectionChanged(PreferenceDialog.java:529)\n        at\norg.eclipse.jface.viewers.StructuredViewer$3.run(StructuredViewer.java:450)\n        at\norg.eclipse.core.internal.runtime.InternalPlatform.run(InternalPlatform.java:616)\n        at org.eclipse.core.runtime.Platform.run(Platform.java:747)\n        at\norg.eclipse.jface.viewers.StructuredViewer.firePostSelectionChanged(StructuredViewer.java:448)\n        at\norg.eclipse.jface.viewers.StructuredViewer.handlePostSelect(StructuredViewer.java:708)\n        at\norg.eclipse.jface.viewers.StructuredViewer$5.widgetSelected(StructuredViewer.java:726)\n        at\norg.eclipse.jface.util.OpenStrategy.firePostSelectionEvent(OpenStrategy.java:200)\n        at org.eclipse.jface.util.OpenStrategy.access$4(OpenStrategy.java:195)\n        at org.eclipse.jface.util.OpenStrategy$3.run(OpenStrategy.java:349)\n        at org.eclipse.swt.widgets.RunnableLock.run(RunnableLock.java:35)\n        at\norg.eclipse.swt.widgets.Synchronizer.runAsyncMessages(Synchronizer.java:106)\n        at org.eclipse.swt.widgets.Display.runAsyncMessages(Display.java:2572)\n        at org.eclipse.swt.widgets.Display.readAndDispatch(Display.java:2301)\n        at org.eclipse.jface.window.Window.runEventLoop(Window.java:668)\n        at org.eclipse.jface.window.Window.open(Window.java:648)\n        at\norg.eclipse.ui.internal.OpenPreferencesAction.run(OpenPreferencesAction.java:72)\n        at org.eclipse.jface.action.Action.runWithEvent(Action.java:881)\n        at\norg.eclipse.jface.action.ActionContributionItem.handleWidgetSelection(ActionContributionItem.java:915)\n        at\norg.eclipse.jface.action.ActionContributionItem.access$2(ActionContributionItem.java:866)\n        at\norg.eclipse.jface.action.ActionContributionItem$7.handleEvent(ActionContributionItem.java:785)\n        at org.eclipse.swt.widgets.EventTable.sendEvent(EventTable.java:82)\n        at org.eclipse.swt.widgets.Widget.sendEvent(Widget.java:954)\n        at org.eclipse.swt.widgets.Display.runDeferredEvents(Display.java:2595)\n        at org.eclipse.swt.widgets.Display.readAndDispatch(Display.java:2298)\n        at org.eclipse.ui.internal.Workbench.runEventLoop(Workbench.java:1377)\n        at org.eclipse.ui.internal.Workbench.runUI(Workbench.java:1348)\n        at\norg.eclipse.ui.internal.Workbench.createAndRunWorkbench(Workbench.java:254)\n        at org.eclipse.ui.PlatformUI.createAndRunWorkbench(PlatformUI.java:141)\n        at org.eclipse.ui.internal.ide.IDEApplication.run(IDEApplication.java:96)\n        at\norg.eclipse.core.internal.runtime.PlatformActivator$1.run(PlatformActivator.java:335)\n        at\norg.eclipse.core.runtime.adaptor.EclipseStarter.run(EclipseStarter.java:273)\n        at\norg.eclipse.core.runtime.adaptor.EclipseStarter.run(EclipseStarter.java:129)\n        at sun.reflect.NativeMethodAccessorImpl.invoke0(Native Method)\n        at\nsun.reflect.NativeMethodAccessorImpl.invoke(NativeMethodAccessorImpl.java:39)\n        at\nsun.reflect.DelegatingMethodAccessorImpl.invoke(DelegatingMethodAccessorImpl.java:25)\n        at java.lang.reflect.Method.invoke(Method.java:585)\n        at org.eclipse.core.launcher.Main.basicRun(Main.java:185)\n        at org.eclipse.core.launcher.Main.run(Main.java:704)\n        at org.eclipse.core.launcher.Main.main(Main.java:688)",
    "The 3.0.2 build of eclipse had an incorrect library attached to it for amd64. \nSee the attachment and steps in bug 89911.  :(\n\n*** This bug has been marked as a duplicate of 89911 ***"
  ],
  "commentCreationDates": [
    "2005-06-24T08:45:26+02:00",
    "2005-06-24T14:32:23+02:00"
  ],
  "traces": [
    {
      "exceptionType": "java.lang.UnsatisfiedLinkError",
      "message": "gtk_tree_view_column_get_fixed_width",
      "elements": [
        {
          "method": "org.eclipse.swt.internal.gtk.OS.gtk_tree_view_column_get_fixed_width",
          "source": "Native Method"
        },
        {
          "method": "org.eclipse.swt.widgets.TableColumn.getWidth",
          "source": "TableColumn.java:261"
        },
        {
          "method": "org.eclipse.jdt.internal.debug.ui.jres.InstalledJREsBlock.resizeTable",
          "source": "InstalledJREsBlock.java:541"
        },
        {
          "method": "org.eclipse.jdt.internal.debug.ui.jres.InstalledJREsBlock.access$9",
          "source": "InstalledJREsBlock.java:503"
        },
        {
          "method": "org.eclipse.jdt.internal.debug.ui.jres.InstalledJREsBlock$15.controlResized",
          "source": "InstalledJREsBlock.java:478"
        },
        {
          "method": "org.eclipse.swt.widgets.TypedListener.handleEvent",
          "source": "TypedListener.java:148"
        },
        {
          "method": "org.eclipse.swt.widgets.EventTable.sendEvent",
          "source": "EventTable.java:82"
        },
        {
          "method": "org.eclipse.swt.widgets.Widget.sendEvent",
          "source": "Widget.java:954"
        },
        {
          "method": "org.eclipse.swt.widgets.Widget.sendEvent",
          "source": "Widget.java:978"
        },
        {
          "method": "org.eclipse.swt.widgets.Widget.sendEvent",
          "source": "Widget.java:959"
        },
        {
          "method": "org.eclipse.swt.widgets.Control.setBounds",
          "source": "Control.java:538"
        },
        {
          "method": "org.eclipse.swt.widgets.Composite.setBounds",
          "source": "Composite.java:693"
        },
        {
          "method": "org.eclipse.swt.widgets.Control.setBounds",
          "source": "Control.java:461"
        },
        {
          "method": "org.eclipse.swt.layout.GridLayout.layout",
          "source": "GridLayout.java:684"
        },
        {
          "method": "org.eclipse.swt.widgets.Composite.layout",
          "source": "Composite.java:565"
        },
        {
          "method": "org.eclipse.jface.preference.PreferencePage.doComputeSize",
          "source": "PreferencePage.java:328"
        },
        {
          "method": "org.eclipse.jface.preference.PreferencePage.computeSize",
          "source": "PreferencePage.java:150"
        },
        {
          "method": "org.eclipse.jface.preference.PreferenceDialog$13.run",
          "source": "PreferenceDialog.java:1027"
        },
        {
          "method": "org.eclipse.core.internal.runtime.InternalPlatform.run",
          "source": "InternalPlatform.java:616"
        },
        {
          "method": "org.eclipse.core.runtime.Platform.run",
          "source": "Platform.java:747"
        },
        {
          "method": "org.eclipse.jface.preference.PreferenceDialog.showPage",
          "source": "PreferenceDialog.java:1022"
        },
        {
          "method": "org.eclipse.jface.preference.PreferenceDialog$8.selectionChanged",
          "source": "PreferenceDialog.java:529"
        },
        {
          "method": "org.eclipse.jface.viewers.StructuredViewer$3.run",
          "source": "StructuredViewer.java:450"
        },
        {
          "method": "org.eclipse.core.internal.runtime.InternalPlatform.run",
          "source": "InternalPlatform.java:616"
        },
        {
          "method": "org.eclipse.core.runtime.Platform.run",
          "source": "Platform.java:747"
        },
        {
          "method": "org.eclipse.jface.viewers.StructuredViewer.firePostSelectionChanged",
          "source": "StructuredViewer.java:448"
        },
        {
          "method": "org.eclipse.jface.viewers.StructuredViewer.handlePostSelect",
          "source": "StructuredViewer.java:708"
        },
        {
          "method": "org.eclipse.jface.viewers.StructuredViewer$5.widgetSelected",
          "source": "StructuredViewer.java:726"
        },
        {
          "method": "org.eclipse.jface.util.OpenStrategy.firePostSelectionEvent",
          "source": "OpenStrategy.java:200"
        },
        {
          "method": "org.eclipse.jface.util.OpenStrategy.access$4",
          "source": "OpenStrategy.java:195"
        },
        {
          "method": "org.eclipse.jface.util.OpenStrategy$3.run",
          "source": "OpenStrategy.java:349"
        },
        {
          "method": "org.eclipse.swt.widgets.RunnableLock.run",
          "source": "RunnableLock.java:35"
        },
        {
          "method": "org.eclipse.swt.widgets.Synchronizer.runAsyncMessages",
          "source": "Synchronizer.java:106"
        },
        {
          "method": "org.eclipse.swt.widgets.Display.runAsyncMessages",
          "source": "Display.java:2572"
        },
        {
          "method": "org.eclipse.swt.widgets.Display.readAndDispatch",
          "source": "Display.java:2301"
        },
        {
          "method": "org.eclipse.jface.window.Window.runEventLoop",
          "source": "Window.java:668"
        },
        {
          "method": "org.eclipse.jface.window.Window.open",
          "source": "Window.java:648"
        },
        {
          "method": "org.eclipse.ui.internal.OpenPreferencesAction.run",
          "source": "OpenPreferencesAction.java:72"
        },
        {
          "method": "org.eclipse.jface.action.Action.runWithEvent",
          "source": "Action.java:881"
        },
        {
          "method": "org.eclipse.jface.action.ActionContributionItem.handleWidgetSelection",
          "source": "ActionContributionItem.java:915"
        },
        {
          "method": "org.eclipse.jface.action.ActionContributionItem.access$2",
          "source": "ActionContributionItem.java:866"
        },
        {
          "method": "org.eclipse.jface.action.ActionContributionItem$7.handleEvent",
          "source": "ActionContributionItem.java:785"
        },
        {
          "method": "org.eclipse.swt.widgets.EventTable.sendEvent",
          "source": "EventTable.java:82"
        },
        {
          "method": "org.eclipse.swt.widgets.Widget.sendEvent",
          "source": "Widget.java:954"
        },
        {
          "method": "org.eclipse.swt.widgets.Display.runDeferredEvents",
          "source": "Display.java:2595"
        },
        {
          "method": "org.eclipse.swt.widgets.Display.readAndDispatch",
          "source": "Display.java:2298"
        },
        {
          "method": "org.eclipse.ui.internal.Workbench.runEventLoop",
          "source": "Workbench.java:1377"
        },
        {
          "method": "org.eclipse.ui.internal.Workbench.runUI",
          "source": "Workbench.java:1348"
        },
        {
          "method": "org.eclipse.ui.internal.Workbench.createAndRunWorkbench",
          "source": "Workbench.java:254"
        },
        {
          "method": "org.eclipse.ui.PlatformUI.createAndRunWorkbench",
          "source": "PlatformUI.java:141"
        },
        {
          "method": "org.eclipse.ui.internal.ide.IDEApplication.run",
          "source": "IDEApplication.java:96"
        },
        {
          "method": "org.eclipse.core.internal.runtime.PlatformActivator$1.run",
          "source": "PlatformActivator.java:335"
        },
        {
          "method": "org.eclipse.core.runtime.adaptor.EclipseStarter.run",
          "source": "EclipseStarter.java:273"
        },
        {
          "method": "org.eclipse.core.runtime.adaptor.EclipseStarter.run",
          "source": "EclipseStarter.java:129"
        },
        {
          "method": "sun.reflect.NativeMethodAccessorImpl.invoke0",
          "source": "Native Method"
        },
        {
          "method": "sun.reflect.NativeMethodAccessorImpl.invoke",
          "source": "NativeMethodAccessorImpl.java:39"
        },
        {
          "method": "sun.reflect.DelegatingMethodAccessorImpl.invoke",
          "source": "DelegatingMethodAccessorImpl.java:25"
        },
        {
          "method": "java.lang.reflect.Method.invoke",
          "source": "Method.java:585"
        },
        {
          "method": "org.eclipse.core.launcher.Main.basicRun",
          "source": "Main.java:185"
        },
        {
          "method": "org.eclipse.core.launcher.Main.run",
          "source": "Main.java:704"
        },
        {
          "method": "org.eclipse.core.launcher.Main.main",
          "source": "Main.java:688"
        }
      ],
      "number": 0,
      "commentIndex": 0,
      "bugId": "101594",
      "duplicateId": "89911",
      "date": "2005-06-24T08:45:26+02:00",
      "product": "Platform",
      "component": "SWT",
      "severity": "normal"
    }
  ],
  "groupId": "89911",
  "bugId": "101594",
  "duplicateId": "89911",
  "date": "2005-06-24T08:45:26+02:00",
  "product": "Platform",
  "component": "SWT",
  "severity": "normal"
}