{
  "comments": [
    "Build 20020214\n\nOn project org.eclipse.jdt.core.tests, opening the Debugger Source Lookup \nproperties results in the following JavaModelException:\n\n4 org.eclipse.jdt.debug.ui 150 Internal Error\norg.eclipse.jdt.core.JavaModelException[985]: java.util.zip.ZipException: The \nsystem cannot find the file specified\n        at java.util.zip.ZipFile.open(Native Method)\n        at java.util.zip.ZipFile.\u003cinit\u003e(ZipFile.java:110)\n        at java.util.zip.ZipFile.\u003cinit\u003e(ZipFile.java:75)\n        at \norg.eclipse.jdt.launching.sourcelookup.ArchiveSourceLocation.getZipFile\n(ArchiveSourceLocation.java:52)\n        at org.eclipse.jdt.launching.sourcelookup.ArchiveSourceLocation.\u003cinit\u003e\n(ArchiveSourceLocation.java:99)\n        at \norg.eclipse.jdt.launching.sourcelookup.JavaSourceLocator.getDefaultSourceLocatio\nns(JavaSourceLocator.java:194)\n        at \norg.eclipse.jdt.internal.debug.ui.launcher.SourceLookupBlock.initializeFields\n(SourceLookupBlock.java:167)\n        at org.eclipse.jdt.internal.debug.ui.launcher.SourceLookupBlock.\u003cinit\u003e\n(SourceLookupBlock.java:151)\n        at \norg.eclipse.jdt.internal.debug.ui.launcher.SourceLookupPropertyPage.createJavaCo\nntents(SourceLookupPropertyPage.java:25)\n        at \norg.eclipse.jdt.internal.debug.ui.launcher.JavaProjectPropertyPage.createContent\ns(JavaProjectPropertyPage.java:30)\n        at org.eclipse.jface.preference.PreferencePage.createControl\n(PreferencePage.java:194)\n        at org.eclipse.jface.preference.PreferenceDialog.showPage\n(PreferenceDialog.java:793)\n        at org.eclipse.jface.preference.PreferenceDialog$6.run\n(PreferenceDialog.java:400)\n        at org.eclipse.swt.custom.BusyIndicator.showWhile(BusyIndicator.java:56)\n        at org.eclipse.jface.preference.PreferenceDialog$5.widgetSelected\n(PreferenceDialog.java:392)\n        at org.eclipse.swt.widgets.TypedListener.handleEvent\n(TypedListener.java:85)\n        at org.eclipse.swt.widgets.EventTable.sendEvent(EventTable.java:74)\n        at org.eclipse.swt.widgets.Widget.notifyListeners(Widget.java:637)\n        at org.eclipse.swt.widgets.Display.runDeferredEvents(Display.java:1413)\n        at org.eclipse.swt.widgets.Display.readAndDispatch(Display.java:1205)\n        at org.eclipse.jface.window.Window.runEventLoop(Window.java:538)\n        at org.eclipse.jface.window.Window.open(Window.java:525)\n        at org.eclipse.ui.dialogs.PropertyDialogAction.run\n(PropertyDialogAction.java:150)\n        at org.eclipse.jface.action.Action.runWithEvent(Action.java:452)\n        at org.eclipse.jface.action.ActionContributionItem.handleWidgetSelection\n(ActionContributionItem.java:407)\n        at org.eclipse.jface.action.ActionContributionItem.handleWidgetEvent\n(ActionContributionItem.java:361)\n        at org.eclipse.jface.action.ActionContributionItem.access$0\n(ActionContributionItem.java:352)\n        at \norg.eclipse.jface.action.ActionContributionItem$ActionListener.handleEvent\n(ActionContributionItem.java:47)\n        at org.eclipse.swt.widgets.EventTable.sendEvent(EventTable.java:74)\n        at org.eclipse.swt.widgets.Widget.notifyListeners(Widget.java:637)\n        at org.eclipse.swt.widgets.Display.runDeferredEvents(Display.java:1413)\n        at org.eclipse.swt.widgets.Display.readAndDispatch(Display.java:1205)\n        at org.eclipse.ui.internal.Workbench.runEventLoop(Workbench.java:788)\n        at org.eclipse.ui.internal.Workbench.run(Workbench.java:771)\n        at org.eclipse.core.internal.boot.InternalBootLoader.run\n(InternalBootLoader.java:777)\n        at org.eclipse.core.boot.BootLoader.run(BootLoader.java:319)\n        at java.lang.reflect.Method.invoke(Native Method)\n        at org.eclipse.core.launcher.Main.basicRun(Main.java:151)\n        at org.eclipse.core.launcher.Main.run(Main.java:502)\n        at org.eclipse.core.launcher.UIMain.main(UIMain.java:52)",
    "Additional info: this happened after I upgraded my jdk1.4 on disk. It appears \nthat the new version of jdk1.4 I\u0027m using doesn\u0027t contain a src.jar as the old \none did. As I didn\u0027t change the \u0027Installed JRE\u0027 itself, it was assuming that \nthe src.jar was still present.",
    "moving to JDT Debug",
    "\n\n*** This bug has been marked as a duplicate of 10096 ***"
  ],
  "commentCreationDates": [
    "2002-02-25T11:36:03+01:00",
    "2002-02-25T12:06:32+01:00",
    "2002-02-27T23:55:05+01:00",
    "2002-03-12T17:12:02+01:00"
  ],
  "traces": [
    {
      "exceptionType": "java.util.zip.ZipException",
      "message": "The  system cannot find the file specified",
      "elements": [
        {
          "method": "java.util.zip.ZipFile.open",
          "source": "Native Method"
        },
        {
          "method": "java.util.zip.ZipFile.\u003cinit\u003e",
          "source": "ZipFile.java:110"
        },
        {
          "method": "java.util.zip.ZipFile.\u003cinit\u003e",
          "source": "ZipFile.java:75"
        },
        {
          "method": "org.eclipse.jdt.launching.sourcelookup.ArchiveSourceLocation.getZipFile",
          "source": "ArchiveSourceLocation.java:52"
        },
        {
          "method": "org.eclipse.jdt.launching.sourcelookup.ArchiveSourceLocation.\u003cinit\u003e",
          "source": "ArchiveSourceLocation.java:99"
        },
        {
          "method": "org.eclipse.jdt.launching.sourcelookup.JavaSourceLocator.getDefaultSourceLocations",
          "source": "JavaSourceLocator.java:194"
        },
        {
          "method": "org.eclipse.jdt.internal.debug.ui.launcher.SourceLookupBlock.initializeFields",
          "source": "SourceLookupBlock.java:167"
        },
        {
          "method": "org.eclipse.jdt.internal.debug.ui.launcher.SourceLookupBlock.\u003cinit\u003e",
          "source": "SourceLookupBlock.java:151"
        },
        {
          "method": "org.eclipse.jdt.internal.debug.ui.launcher.SourceLookupPropertyPage.createJavaContents",
          "source": "SourceLookupPropertyPage.java:25"
        },
        {
          "method": "org.eclipse.jdt.internal.debug.ui.launcher.JavaProjectPropertyPage.createContents",
          "source": "JavaProjectPropertyPage.java:30"
        },
        {
          "method": "org.eclipse.jface.preference.PreferencePage.createControl",
          "source": "PreferencePage.java:194"
        },
        {
          "method": "org.eclipse.jface.preference.PreferenceDialog.showPage",
          "source": "PreferenceDialog.java:793"
        },
        {
          "method": "org.eclipse.jface.preference.PreferenceDialog$6.run",
          "source": "PreferenceDialog.java:400"
        },
        {
          "method": "org.eclipse.swt.custom.BusyIndicator.showWhile",
          "source": "BusyIndicator.java:56"
        },
        {
          "method": "org.eclipse.jface.preference.PreferenceDialog$5.widgetSelected",
          "source": "PreferenceDialog.java:392"
        },
        {
          "method": "org.eclipse.swt.widgets.TypedListener.handleEvent",
          "source": "TypedListener.java:85"
        },
        {
          "method": "org.eclipse.swt.widgets.EventTable.sendEvent",
          "source": "EventTable.java:74"
        },
        {
          "method": "org.eclipse.swt.widgets.Widget.notifyListeners",
          "source": "Widget.java:637"
        },
        {
          "method": "org.eclipse.swt.widgets.Display.runDeferredEvents",
          "source": "Display.java:1413"
        },
        {
          "method": "org.eclipse.swt.widgets.Display.readAndDispatch",
          "source": "Display.java:1205"
        },
        {
          "method": "org.eclipse.jface.window.Window.runEventLoop",
          "source": "Window.java:538"
        },
        {
          "method": "org.eclipse.jface.window.Window.open",
          "source": "Window.java:525"
        },
        {
          "method": "org.eclipse.ui.dialogs.PropertyDialogAction.run",
          "source": "PropertyDialogAction.java:150"
        },
        {
          "method": "org.eclipse.jface.action.Action.runWithEvent",
          "source": "Action.java:452"
        },
        {
          "method": "org.eclipse.jface.action.ActionContributionItem.handleWidgetSelection",
          "source": "ActionContributionItem.java:407"
        },
        {
          "method": "org.eclipse.jface.action.ActionContributionItem.handleWidgetEvent",
          "source": "ActionContributionItem.java:361"
        },
        {
          "method": "org.eclipse.jface.action.ActionContributionItem.access$0",
          "source": "ActionContributionItem.java:352"
        },
        {
          "method": "org.eclipse.jface.action.ActionContributionItem$ActionListener.handleEvent",
          "source": "ActionContributionItem.java:47"
        },
        {
          "method": "org.eclipse.swt.widgets.EventTable.sendEvent",
          "source": "EventTable.java:74"
        },
        {
          "method": "org.eclipse.swt.widgets.Widget.notifyListeners",
          "source": "Widget.java:637"
        },
        {
          "method": "org.eclipse.swt.widgets.Display.runDeferredEvents",
          "source": "Display.java:1413"
        },
        {
          "method": "org.eclipse.swt.widgets.Display.readAndDispatch",
          "source": "Display.java:1205"
        },
        {
          "method": "org.eclipse.ui.internal.Workbench.runEventLoop",
          "source": "Workbench.java:788"
        },
        {
          "method": "org.eclipse.ui.internal.Workbench.run",
          "source": "Workbench.java:771"
        },
        {
          "method": "org.eclipse.core.internal.boot.InternalBootLoader.run",
          "source": "InternalBootLoader.java:777"
        },
        {
          "method": "org.eclipse.core.boot.BootLoader.run",
          "source": "BootLoader.java:319"
        },
        {
          "method": "java.lang.reflect.Method.invoke",
          "source": "Native Method"
        },
        {
          "method": "org.eclipse.core.launcher.Main.basicRun",
          "source": "Main.java:151"
        },
        {
          "method": "org.eclipse.core.launcher.Main.run",
          "source": "Main.java:502"
        },
        {
          "method": "org.eclipse.core.launcher.UIMain.main",
          "source": "UIMain.java:52"
        }
      ],
      "number": 0,
      "commentIndex": 0,
      "bugId": "10151",
      "duplicateId": "10096",
      "date": "2002-02-25T11:36:03+01:00",
      "product": "JDT",
      "component": "Debug",
      "severity": "normal"
    }
  ],
  "groupId": "10096",
  "bugId": "10151",
  "duplicateId": "10096",
  "date": "2002-02-25T11:36:03+01:00",
  "product": "JDT",
  "component": "Debug",
  "severity": "normal"
}