{
  "comments": [
    "I\u0027ve installed 3.1\nI get this error when starting it as a \u0027regular\u0027 user\n\n\"An error has occurred. See the log file\n/usr/local/eclipse/configuration/1120086080617.log.\"\n\nThere is no file by this name in this directory.\nI am able to start 3.1 as root.\nMy old installation 3.02 still works for root and user.\n\nUsing SuSe Linux 9.2",
    "How did you install Eclipse 3.1? Extracted it to an empty dir or on top of a\nprevious install? \n\nPlease open a shell and run Eclipse as user with the given command line:\n\n\u003ceclipse-install\u003e/eclipse -debug -consolelog \n\nAnd attach the resulting output to this PR. Thanks.\n\n",
    "output from the command is below.\nit shows that it can\u0027t write to /usr/local/eclipse/configuration/...\nso i did this (as root):\n# cd /usr/local/eclipse/configuration\n# chmod +777 -R *\nand it now works.\n\n---------------------------------------------\n\u003e ./eclipse -debug -consolelog\nStart VM: /usr/bin/java\n-Xms40m\n-Xmx256m\n-jar /usr/local/eclipse/./startup.jar\n-os linux\n-ws gtk\n-arch x86\n-launcher /usr/local/eclipse/./eclipse\n-name Eclipse\n-showsplash 600\n-exitdata 110004\n-debug\n-consolelog\n-vm /usr/bin/java\n-vmargs\n-Xms40m\n-Xmx256m\n-jar /usr/local/eclipse/./startup.jar\nInstall location:\n    file:/usr/local/eclipse/\nConfiguration file:\n    file:/usr/local/eclipse/configuration/config.ini loaded\nConfiguration location:\n    file:/usr/local/eclipse/configuration/\nFramework located:\n    file:/usr/local/eclipse/plugins/org.eclipse.osgi_3.1.0.jar\nFramework classpath:\n    file:/usr/local/eclipse/plugins/org.eclipse.osgi_3.1.0.jar\nSplash location:\n    /usr/local/eclipse/plugins/org.eclipse.platform_3.1.0/splash.bmp\nrunCommand:\n   \n\u003c/usr/local/eclipse/./eclipse\u003e\u003c-name\u003e\u003cEclipse\u003e\u003c-showsplash\u003e\u003c600\u003e\u003c/usr/local/eclipse/plugins/org.eclipse.platform_3.1.0/splash.bmp\u003e\nDebug options:\n    file:/usr/local/eclipse/.options not found\n!SESSION 2005-06-30 10:52:08.476 -----------------------------------------------\neclipse.buildId\u003dI20050627-1435\njava.version\u003d1.4.2_06\njava.vendor\u003dSun Microsystems Inc.\nBootLoader constants: OS\u003dlinux, ARCH\u003dx86, WS\u003dgtk, NL\u003den_US\nCommand-line arguments:  -os linux -ws gtk -arch x86 -debug -consolelog\n\n!ENTRY org.eclipse.osgi 2005-06-30 10:52:09.354\n!MESSAGE Error reading configuration:\n/usr/local/eclipse/configuration/org.eclipse.osgi/.manager/.fileTableLock\n(Permission denied)\n!STACK 0\njava.io.FileNotFoundException:\n/usr/local/eclipse/configuration/org.eclipse.osgi/.manager/.fileTableLock\n(Permission denied)\n        at java.io.FileOutputStream.openAppend(Native Method)\n        at java.io.FileOutputStream.\u003cinit\u003e(FileOutputStream.java:177)\n        at\norg.eclipse.core.runtime.internal.adaptor.Locker_JavaNio.lock(Locker_JavaNio.java:34)\n        at org.eclipse.core.runtime.adaptor.FileManager.lock(FileManager.java:361)\n        at org.eclipse.core.runtime.adaptor.FileManager.open(FileManager.java:658)\n        at\norg.eclipse.core.runtime.adaptor.EclipseAdaptor.initFileManager(EclipseAdaptor.java:809)\n        at\norg.eclipse.core.runtime.adaptor.EclipseAdaptor.initialize(EclipseAdaptor.java:139)\n        at\norg.eclipse.osgi.framework.internal.core.Framework.initialize(Framework.java:126)\n        at\norg.eclipse.osgi.framework.internal.core.Framework.\u003cinit\u003e(Framework.java:104)\n        at\norg.eclipse.osgi.framework.internal.core.OSGi.createFramework(OSGi.java:90)\n        at org.eclipse.osgi.framework.internal.core.OSGi.\u003cinit\u003e(OSGi.java:31)\n        at\norg.eclipse.core.runtime.adaptor.EclipseStarter.startup(EclipseStarter.java:272)\n        at\norg.eclipse.core.runtime.adaptor.EclipseStarter.run(EclipseStarter.java:159)\n        at sun.reflect.NativeMethodAccessorImpl.invoke0(Native Method)\n        at\nsun.reflect.NativeMethodAccessorImpl.invoke(NativeMethodAccessorImpl.java:39)\n        at\nsun.reflect.DelegatingMethodAccessorImpl.invoke(DelegatingMethodAccessorImpl.java:25)\n        at java.lang.reflect.Method.invoke(Method.java:324)\n        at org.eclipse.core.launcher.Main.invokeFramework(Main.java:334)\n        at org.eclipse.core.launcher.Main.basicRun(Main.java:278)\n        at org.eclipse.core.launcher.Main.run(Main.java:973)\n        at org.eclipse.core.launcher.Main.main(Main.java:948)\n!SESSION 2005-06-30 10:52:08.476 -----------------------------------------------\neclipse.buildId\u003dI20050627-1435\njava.version\u003d1.4.2_06\njava.vendor\u003dSun Microsystems Inc.\nBootLoader constants: OS\u003dlinux, ARCH\u003dx86, WS\u003dgtk, NL\u003den_US\nCommand-line arguments:  -os linux -ws gtk -arch x86 -debug -consolelog\n\n!ENTRY org.eclipse.osgi 2005-06-30 10:52:09.354\n!MESSAGE Error reading configuration:\n/usr/local/eclipse/configuration/org.eclipse.osgi/.manager/.fileTableLock\n(Permission denied)\n!STACK 0\njava.io.FileNotFoundException:\n/usr/local/eclipse/configuration/org.eclipse.osgi/.manager/.fileTableLock\n(Permission denied)\n        at java.io.FileOutputStream.openAppend(Native Method)\n        at java.io.FileOutputStream.\u003cinit\u003e(FileOutputStream.java:177)\n        at\norg.eclipse.core.runtime.internal.adaptor.Locker_JavaNio.lock(Locker_JavaNio.java:34)\n        at org.eclipse.core.runtime.adaptor.FileManager.lock(FileManager.java:361)\n        at org.eclipse.core.runtime.adaptor.FileManager.open(FileManager.java:658)\n        at\norg.eclipse.core.runtime.adaptor.EclipseAdaptor.initFileManager(EclipseAdaptor.java:809)\n        at\norg.eclipse.core.runtime.adaptor.EclipseAdaptor.initialize(EclipseAdaptor.java:139)\n        at\norg.eclipse.osgi.framework.internal.core.Framework.initialize(Framework.java:126)\n        at\norg.eclipse.osgi.framework.internal.core.Framework.\u003cinit\u003e(Framework.java:104)\n        at\norg.eclipse.osgi.framework.internal.core.OSGi.createFramework(OSGi.java:90)\n        at org.eclipse.osgi.framework.internal.core.OSGi.\u003cinit\u003e(OSGi.java:31)\n        at\norg.eclipse.core.runtime.adaptor.EclipseStarter.startup(EclipseStarter.java:272)\n        at\norg.eclipse.core.runtime.adaptor.EclipseStarter.run(EclipseStarter.java:159)\n        at sun.reflect.NativeMethodAccessorImpl.invoke0(Native Method)\n        at\nsun.reflect.NativeMethodAccessorImpl.invoke(NativeMethodAccessorImpl.java:39)\n        at\nsun.reflect.DelegatingMethodAccessorImpl.invoke(DelegatingMethodAccessorImpl.java:25)\n        at java.lang.reflect.Method.invoke(Method.java:324)\n        at org.eclipse.core.launcher.Main.invokeFramework(Main.java:334)\n        at org.eclipse.core.launcher.Main.basicRun(Main.java:278)\n        at org.eclipse.core.launcher.Main.run(Main.java:973)\n        at org.eclipse.core.launcher.Main.main(Main.java:948)\nTime to load bundles: 172\n\n!ENTRY initial@reference:file:plugins/org.eclipse.core.runtime_3.1.0.jar/ 0 0\n2005-06-30 10:52:10.581\n!MESSAGE FrameworkEvent.ERROR\n!STACK 0\norg.osgi.framework.BundleException: Exception in\norg.eclipse.core.internal.runtime.PlatformActivator.start() of bundle\norg.eclipse.core.runtime.\n        at\norg.eclipse.osgi.framework.internal.core.BundleContextImpl.startActivator(BundleContextImpl.java:1013)\n        at\norg.eclipse.osgi.framework.internal.core.BundleContextImpl.start(BundleContextImpl.java:969)\n        at\norg.eclipse.osgi.framework.internal.core.BundleHost.startWorker(BundleHost.java:321)\n        at\norg.eclipse.osgi.framework.internal.core.AbstractBundle.resume(AbstractBundle.java:339)\n        at\norg.eclipse.osgi.framework.internal.core.Framework.resumeBundle(Framework.java:1024)\n        at\norg.eclipse.osgi.framework.internal.core.StartLevelManager.resumeBundles(StartLevelManager.java:576)\n        at\norg.eclipse.osgi.framework.internal.core.StartLevelManager.incFWSL(StartLevelManager.java:498)\n        at\norg.eclipse.osgi.framework.internal.core.StartLevelManager.doSetStartLevel(StartLevelManager.java:275)\n        at\norg.eclipse.osgi.framework.internal.core.StartLevelManager.dispatchEvent(StartLevelManager.java:458)\n        at\norg.eclipse.osgi.framework.eventmgr.EventManager.dispatchEvent(EventManager.java:189)\n        at\norg.eclipse.osgi.framework.eventmgr.EventManager$EventThread.run(EventManager.java:291)\nCaused by: java.io.FileNotFoundException:\n/usr/local/eclipse/configuration/org.eclipse.core.runtime/.manager/.fileTableLock\n(Permission denied)\n        at java.io.FileOutputStream.openAppend(Native Method)\n        at java.io.FileOutputStream.\u003cinit\u003e(FileOutputStream.java:177)\n        at\norg.eclipse.core.runtime.internal.adaptor.Locker_JavaNio.lock(Locker_JavaNio.java:34)\n        at org.eclipse.core.runtime.adaptor.FileManager.lock(FileManager.java:361)\n        at org.eclipse.core.runtime.adaptor.FileManager.open(FileManager.java:658)\n        at\norg.eclipse.core.internal.runtime.InternalPlatform.initializeRuntimeFileManager(InternalPlatform.java:786)\n        at\norg.eclipse.core.internal.runtime.InternalPlatform.start(InternalPlatform.java:1086)\n        at\norg.eclipse.core.internal.runtime.PlatformActivator.startInternalPlatform(PlatformActivator.java:141)\n        at\norg.eclipse.core.internal.runtime.PlatformActivator.start(PlatformActivator.java:57)\n        at\norg.eclipse.osgi.framework.internal.core.BundleContextImpl$2.run(BundleContextImpl.java:994)\n        at java.security.AccessController.doPrivileged(Native Method)\n        at\norg.eclipse.osgi.framework.internal.core.BundleContextImpl.startActivator(BundleContextImpl.java:988)\n        ... 10 more\nRoot exception:\njava.io.FileNotFoundException:\n/usr/local/eclipse/configuration/org.eclipse.core.runtime/.manager/.fileTableLock\n(Permission denied)\n        at java.io.FileOutputStream.openAppend(Native Method)\n        at java.io.FileOutputStream.\u003cinit\u003e(FileOutputStream.java:177)\n        at\norg.eclipse.core.runtime.internal.adaptor.Locker_JavaNio.lock(Locker_JavaNio.java:34)\n        at org.eclipse.core.runtime.adaptor.FileManager.lock(FileManager.java:361)\n        at org.eclipse.core.runtime.adaptor.FileManager.open(FileManager.java:658)\n        at\norg.eclipse.core.internal.runtime.InternalPlatform.initializeRuntimeFileManager(InternalPlatform.java:786)\n        at\norg.eclipse.core.internal.runtime.InternalPlatform.start(InternalPlatform.java:1086)\n        at\norg.eclipse.core.internal.runtime.PlatformActivator.startInternalPlatform(PlatformActivator.java:141)\n        at\norg.eclipse.core.internal.runtime.PlatformActivator.start(PlatformActivator.java:57)\n        at\norg.eclipse.osgi.framework.internal.core.BundleContextImpl$2.run(BundleContextImpl.java:994)\n        at java.security.AccessController.doPrivileged(Native Method)\n        at\norg.eclipse.osgi.framework.internal.core.BundleContextImpl.startActivator(BundleContextImpl.java:988)\n        at\norg.eclipse.osgi.framework.internal.core.BundleContextImpl.start(BundleContextImpl.java:969)\n        at\norg.eclipse.osgi.framework.internal.core.BundleHost.startWorker(BundleHost.java:321)\n        at\norg.eclipse.osgi.framework.internal.core.AbstractBundle.resume(AbstractBundle.java:339)\n        at\norg.eclipse.osgi.framework.internal.core.Framework.resumeBundle(Framework.java:1024)\n        at\norg.eclipse.osgi.framework.internal.core.StartLevelManager.resumeBundles(StartLevelManager.java:576)\n        at\norg.eclipse.osgi.framework.internal.core.StartLevelManager.incFWSL(StartLevelManager.java:498)\n        at\norg.eclipse.osgi.framework.internal.core.StartLevelManager.doSetStartLevel(StartLevelManager.java:275)\n        at\norg.eclipse.osgi.framework.internal.core.StartLevelManager.dispatchEvent(StartLevelManager.java:458)\n        at\norg.eclipse.osgi.framework.eventmgr.EventManager.dispatchEvent(EventManager.java:189)\n        at\norg.eclipse.osgi.framework.eventmgr.EventManager$EventThread.run(EventManager.java:291)\n\n!ENTRY initial@reference:file:plugins/org.eclipse.update.configurator_3.1.0.jar/\n0 0 2005-06-30 10:52:10.666\n!MESSAGE FrameworkEvent.ERROR\n!STACK 0\norg.osgi.framework.BundleException: Exception in\norg.eclipse.update.internal.configurator.ConfigurationActivator.start() of\nbundle org.eclipse.update.configurator.\n        at\norg.eclipse.osgi.framework.internal.core.BundleContextImpl.startActivator(BundleContextImpl.java:1013)\n        at\norg.eclipse.osgi.framework.internal.core.BundleContextImpl.start(BundleContextImpl.java:969)\n        at\norg.eclipse.osgi.framework.internal.core.BundleHost.startWorker(BundleHost.java:321)\n        at\norg.eclipse.osgi.framework.internal.core.AbstractBundle.resume(AbstractBundle.java:339)\n        at\norg.eclipse.osgi.framework.internal.core.Framework.resumeBundle(Framework.java:1024)\n        at\norg.eclipse.osgi.framework.internal.core.StartLevelManager.resumeBundles(StartLevelManager.java:576)\n        at\norg.eclipse.osgi.framework.internal.core.StartLevelManager.incFWSL(StartLevelManager.java:498)\n        at\norg.eclipse.osgi.framework.internal.core.StartLevelManager.doSetStartLevel(StartLevelManager.java:275)\n        at\norg.eclipse.osgi.framework.internal.core.StartLevelManager.dispatchEvent(StartLevelManager.java:458)\n        at\norg.eclipse.osgi.framework.eventmgr.EventManager.dispatchEvent(EventManager.java:189)\n        at\norg.eclipse.osgi.framework.eventmgr.EventManager$EventThread.run(EventManager.java:291)\nCaused by: java.lang.Exception: Cannot initialize the Update Configurator\n        at\norg.eclipse.update.internal.configurator.ConfigurationActivator.initialize(ConfigurationActivator.java:89)\n        at\norg.eclipse.update.internal.configurator.ConfigurationActivator.start(ConfigurationActivator.java:67)\n        at\norg.eclipse.osgi.framework.internal.core.BundleContextImpl$2.run(BundleContextImpl.java:994)\n        at java.security.AccessController.doPrivileged(Native Method)\n        at\norg.eclipse.osgi.framework.internal.core.BundleContextImpl.startActivator(BundleContextImpl.java:988)\n        ... 10 more\nRoot exception:\njava.lang.Exception: Cannot initialize the Update Configurator\n        at\norg.eclipse.update.internal.configurator.ConfigurationActivator.initialize(ConfigurationActivator.java:89)\n        at\norg.eclipse.update.internal.configurator.ConfigurationActivator.start(ConfigurationActivator.java:67)\n        at\norg.eclipse.osgi.framework.internal.core.BundleContextImpl$2.run(BundleContextImpl.java:994)\n        at java.security.AccessController.doPrivileged(Native Method)\n        at\norg.eclipse.osgi.framework.internal.core.BundleContextImpl.startActivator(BundleContextImpl.java:988)\n        at\norg.eclipse.osgi.framework.internal.core.BundleContextImpl.start(BundleContextImpl.java:969)\n        at\norg.eclipse.osgi.framework.internal.core.BundleHost.startWorker(BundleHost.java:321)\n        at\norg.eclipse.osgi.framework.internal.core.AbstractBundle.resume(AbstractBundle.java:339)\n        at\norg.eclipse.osgi.framework.internal.core.Framework.resumeBundle(Framework.java:1024)\n        at\norg.eclipse.osgi.framework.internal.core.StartLevelManager.resumeBundles(StartLevelManager.java:576)\n        at\norg.eclipse.osgi.framework.internal.core.StartLevelManager.incFWSL(StartLevelManager.java:498)\n        at\norg.eclipse.osgi.framework.internal.core.StartLevelManager.doSetStartLevel(StartLevelManager.java:275)\n        at\norg.eclipse.osgi.framework.internal.core.StartLevelManager.dispatchEvent(StartLevelManager.java:458)\n        at\norg.eclipse.osgi.framework.eventmgr.EventManager.dispatchEvent(EventManager.java:189)\n        at\norg.eclipse.osgi.framework.eventmgr.EventManager$EventThread.run(EventManager.java:291)\n\n!ENTRY org.eclipse.osgi 2005-06-30 10:52:10.679\n!MESSAGE Startup error\n!STACK 1\njava.lang.IllegalStateException: Bundle\ninitial@reference:file:plugins/org.eclipse.core.runtime_3.1.0.jar/ [1] is not\nactive.\n        at\norg.eclipse.core.runtime.adaptor.EclipseStarter.ensureBundlesActive(EclipseStarter.java:410)\n        at\norg.eclipse.core.runtime.adaptor.EclipseStarter.startup(EclipseStarter.java:297)\n        at\norg.eclipse.core.runtime.adaptor.EclipseStarter.run(EclipseStarter.java:159)\n        at sun.reflect.NativeMethodAccessorImpl.invoke0(Native Method)\n        at\nsun.reflect.NativeMethodAccessorImpl.invoke(NativeMethodAccessorImpl.java:39)\n        at\nsun.reflect.DelegatingMethodAccessorImpl.invoke(DelegatingMethodAccessorImpl.java:25)\n        at java.lang.reflect.Method.invoke(Method.java:324)\n        at org.eclipse.core.launcher.Main.invokeFramework(Main.java:334)\n        at org.eclipse.core.launcher.Main.basicRun(Main.java:278)\n        at org.eclipse.core.launcher.Main.run(Main.java:973)\n        at org.eclipse.core.launcher.Main.main(Main.java:948)\nrunCommand:\n    \u003c/usr/local/eclipse/./eclipse\u003e\u003c-name\u003e\u003cEclipse\u003e\u003c-exitdata\u003e\u003c110004\u003e\u003cAn error\nhas occurred. See the log file\n/usr/local/eclipse/configuration/1120150328846.log.\u003e\n",
    "Might be dup of bug 101892.\n\nYou should not make the install configuration directory writable. The whole\ninstall should be write protected to any users (except root), and Eclipse should\njut work fine.\n\nWould you be willing to trash that install location and unpack Eclipse 3.1 again\nso we can investigate the problem? You would have to delete the\n~/.eclipse/org.eclipse.platform_3.1.0 directory as well.\n\nThanks.",
    "I now get an error:\nCan\u0027t save periodic table\n\nSo i have to change permissions somewhere.\nWhere is this?",
    "Please see my comment 3 above. You are not expected/supposed to change any\npermissions to be able to run Eclipse.",
    "I don\u0027t think this is an eclipse bug, in retrospect.\nI installed as root, which is apparently not the thing to do.\n",
    "No, that is perfectly fine. You can install as root and run as a regular user.\nThis is how a single Eclipse install can be shared by multiple users.",
    "So here is how I installed (as root)\n\nMy existing 3.02 was in /usr/local/eclipse/\n\nI copied everything under this to /usr/local/eclipse_3.02/\nthen i deleted everything under/usr/local/eclipse/\nHaving unzipped the downloaded 3.1 file in /root/, i moved the contents to\n/usr/local/eclipse/.  \nThen i copied plugins (cdt, photran, metrics, log4j) from\n/usr/local/eclipse_3.02/plugins/ to /usr/local/eclipse/plugins/\n\n",
    "Could you try installing Eclipse 3.1 as root again and before installing any\nplug-ins, running it as regular user?",
    "This might be a dup of bug 101892 (see bug 101892 comment 12 and following\ncomments). \n\nMickey, what are the permissions for the Eclipse install directory\n(/usr/local/eclipse)? They should be \"drwxr-xr-x\".",
    "drwxrwxrwx   7 root      root      488 2005-07-05 07:22 eclipse/\n\n",
    "Ok, that explains it. It should be as described in comment 10 above (this is how\nEclipse is shipped). By the way you said you installed the other products\n(comment 8), this is *not* a duplicate of bug 101892, just has the same effects.\nYou probably tweaked the permissions for the install directory manually leaving\nit in an invalid state (install root has full permissions, configuration under\ninstall has restricted permissions).\n\nPlease reopen if that does not fix your problem.",
    "I removed eclipse and then\n1. As root, installed into /usr/local/eclipse\n2. Started as regular user with no problems\n3. As root once again, copied plugins from old eclipse folder to new\n4. Started as regular user with no problems, again\n\nI think the mistake i made the first time was that i ran eclipse as root.  \nI think this caused permissions to change such that it wouldn\u0027t work for a\nregular user because that user didn\u0027t have permissions to write to certain areas."
  ],
  "commentCreationDates": [
    "2005-06-30T15:05:24+02:00",
    "2005-06-30T18:41:48+02:00",
    "2005-06-30T18:55:12+02:00",
    "2005-06-30T19:06:20+02:00",
    "2005-06-30T19:08:43+02:00",
    "2005-06-30T19:16:58+02:00",
    "2005-06-30T19:21:23+02:00",
    "2005-06-30T19:22:56+02:00",
    "2005-06-30T19:31:13+02:00",
    "2005-06-30T19:42:31+02:00",
    "2005-07-05T16:53:07+02:00",
    "2005-07-05T18:04:35+02:00",
    "2005-07-05T18:48:22+02:00",
    "2005-07-07T23:00:11+02:00"
  ],
  "traces": [
    {
      "exceptionType": "java.io.FileNotFoundException",
      "message": "/usr/local/eclipse/configuration/org.eclipse.osgi/.manager/.fileTableLock (Permission denied)",
      "elements": [
        {
          "method": "java.io.FileOutputStream.openAppend",
          "source": "Native Method"
        },
        {
          "method": "java.io.FileOutputStream.\u003cinit\u003e",
          "source": "FileOutputStream.java:177"
        },
        {
          "method": "org.eclipse.core.runtime.internal.adaptor.Locker_JavaNio.lock",
          "source": "Locker_JavaNio.java:34"
        },
        {
          "method": "org.eclipse.core.runtime.adaptor.FileManager.lock",
          "source": "FileManager.java:361"
        },
        {
          "method": "org.eclipse.core.runtime.adaptor.FileManager.open",
          "source": "FileManager.java:658"
        },
        {
          "method": "org.eclipse.core.runtime.adaptor.EclipseAdaptor.initFileManager",
          "source": "EclipseAdaptor.java:809"
        },
        {
          "method": "org.eclipse.core.runtime.adaptor.EclipseAdaptor.initialize",
          "source": "EclipseAdaptor.java:139"
        },
        {
          "method": "org.eclipse.osgi.framework.internal.core.Framework.initialize",
          "source": "Framework.java:126"
        },
        {
          "method": "org.eclipse.osgi.framework.internal.core.Framework.\u003cinit\u003e",
          "source": "Framework.java:104"
        },
        {
          "method": "org.eclipse.osgi.framework.internal.core.OSGi.createFramework",
          "source": "OSGi.java:90"
        },
        {
          "method": "org.eclipse.osgi.framework.internal.core.OSGi.\u003cinit\u003e",
          "source": "OSGi.java:31"
        },
        {
          "method": "org.eclipse.core.runtime.adaptor.EclipseStarter.startup",
          "source": "EclipseStarter.java:272"
        },
        {
          "method": "org.eclipse.core.runtime.adaptor.EclipseStarter.run",
          "source": "EclipseStarter.java:159"
        },
        {
          "method": "sun.reflect.NativeMethodAccessorImpl.invoke0",
          "source": "Native Method"
        },
        {
          "method": "sun.reflect.NativeMethodAccessorImpl.invoke",
          "source": "NativeMethodAccessorImpl.java:39"
        },
        {
          "method": "sun.reflect.DelegatingMethodAccessorImpl.invoke",
          "source": "DelegatingMethodAccessorImpl.java:25"
        },
        {
          "method": "java.lang.reflect.Method.invoke",
          "source": "Method.java:324"
        },
        {
          "method": "org.eclipse.core.launcher.Main.invokeFramework",
          "source": "Main.java:334"
        },
        {
          "method": "org.eclipse.core.launcher.Main.basicRun",
          "source": "Main.java:278"
        },
        {
          "method": "org.eclipse.core.launcher.Main.run",
          "source": "Main.java:973"
        },
        {
          "method": "org.eclipse.core.launcher.Main.main",
          "source": "Main.java:948"
        }
      ],
      "number": 0,
      "commentIndex": 2,
      "bugId": "102311",
      "date": "2005-06-30T18:55:12+02:00",
      "product": "Platform",
      "component": "Runtime",
      "severity": "normal"
    },
    {
      "exceptionType": "java.io.FileNotFoundException",
      "message": "/usr/local/eclipse/configuration/org.eclipse.osgi/.manager/.fileTableLock (Permission denied)",
      "elements": [
        {
          "method": "java.io.FileOutputStream.openAppend",
          "source": "Native Method"
        },
        {
          "method": "java.io.FileOutputStream.\u003cinit\u003e",
          "source": "FileOutputStream.java:177"
        },
        {
          "method": "org.eclipse.core.runtime.internal.adaptor.Locker_JavaNio.lock",
          "source": "Locker_JavaNio.java:34"
        },
        {
          "method": "org.eclipse.core.runtime.adaptor.FileManager.lock",
          "source": "FileManager.java:361"
        },
        {
          "method": "org.eclipse.core.runtime.adaptor.FileManager.open",
          "source": "FileManager.java:658"
        },
        {
          "method": "org.eclipse.core.runtime.adaptor.EclipseAdaptor.initFileManager",
          "source": "EclipseAdaptor.java:809"
        },
        {
          "method": "org.eclipse.core.runtime.adaptor.EclipseAdaptor.initialize",
          "source": "EclipseAdaptor.java:139"
        },
        {
          "method": "org.eclipse.osgi.framework.internal.core.Framework.initialize",
          "source": "Framework.java:126"
        },
        {
          "method": "org.eclipse.osgi.framework.internal.core.Framework.\u003cinit\u003e",
          "source": "Framework.java:104"
        },
        {
          "method": "org.eclipse.osgi.framework.internal.core.OSGi.createFramework",
          "source": "OSGi.java:90"
        },
        {
          "method": "org.eclipse.osgi.framework.internal.core.OSGi.\u003cinit\u003e",
          "source": "OSGi.java:31"
        },
        {
          "method": "org.eclipse.core.runtime.adaptor.EclipseStarter.startup",
          "source": "EclipseStarter.java:272"
        },
        {
          "method": "org.eclipse.core.runtime.adaptor.EclipseStarter.run",
          "source": "EclipseStarter.java:159"
        },
        {
          "method": "sun.reflect.NativeMethodAccessorImpl.invoke0",
          "source": "Native Method"
        },
        {
          "method": "sun.reflect.NativeMethodAccessorImpl.invoke",
          "source": "NativeMethodAccessorImpl.java:39"
        },
        {
          "method": "sun.reflect.DelegatingMethodAccessorImpl.invoke",
          "source": "DelegatingMethodAccessorImpl.java:25"
        },
        {
          "method": "java.lang.reflect.Method.invoke",
          "source": "Method.java:324"
        },
        {
          "method": "org.eclipse.core.launcher.Main.invokeFramework",
          "source": "Main.java:334"
        },
        {
          "method": "org.eclipse.core.launcher.Main.basicRun",
          "source": "Main.java:278"
        },
        {
          "method": "org.eclipse.core.launcher.Main.run",
          "source": "Main.java:973"
        },
        {
          "method": "org.eclipse.core.launcher.Main.main",
          "source": "Main.java:948"
        }
      ],
      "number": 1,
      "commentIndex": 2,
      "bugId": "102311",
      "date": "2005-06-30T18:55:12+02:00",
      "product": "Platform",
      "component": "Runtime",
      "severity": "normal"
    },
    {
      "exceptionType": "org.osgi.framework.BundleException",
      "message": "Exception in org.eclipse.core.internal.runtime.PlatformActivator.start() of bundle org.eclipse.core.runtime.",
      "elements": [
        {
          "method": "org.eclipse.osgi.framework.internal.core.BundleContextImpl.startActivator",
          "source": "BundleContextImpl.java:1013"
        },
        {
          "method": "org.eclipse.osgi.framework.internal.core.BundleContextImpl.start",
          "source": "BundleContextImpl.java:969"
        },
        {
          "method": "org.eclipse.osgi.framework.internal.core.BundleHost.startWorker",
          "source": "BundleHost.java:321"
        },
        {
          "method": "org.eclipse.osgi.framework.internal.core.AbstractBundle.resume",
          "source": "AbstractBundle.java:339"
        },
        {
          "method": "org.eclipse.osgi.framework.internal.core.Framework.resumeBundle",
          "source": "Framework.java:1024"
        },
        {
          "method": "org.eclipse.osgi.framework.internal.core.StartLevelManager.resumeBundles",
          "source": "StartLevelManager.java:576"
        },
        {
          "method": "org.eclipse.osgi.framework.internal.core.StartLevelManager.incFWSL",
          "source": "StartLevelManager.java:498"
        },
        {
          "method": "org.eclipse.osgi.framework.internal.core.StartLevelManager.doSetStartLevel",
          "source": "StartLevelManager.java:275"
        },
        {
          "method": "org.eclipse.osgi.framework.internal.core.StartLevelManager.dispatchEvent",
          "source": "StartLevelManager.java:458"
        },
        {
          "method": "org.eclipse.osgi.framework.eventmgr.EventManager.dispatchEvent",
          "source": "EventManager.java:189"
        },
        {
          "method": "org.eclipse.osgi.framework.eventmgr.EventManager$EventThread.run",
          "source": "EventManager.java:291"
        }
      ],
      "causedBy": {
        "exceptionType": "java.io.FileNotFoundException",
        "message": "/usr/local/eclipse/configuration/org.eclipse.core.runtime/.manager/.fileTableLock (Permission denied)",
        "elements": [
          {
            "method": "java.io.FileOutputStream.openAppend",
            "source": "Native Method"
          },
          {
            "method": "java.io.FileOutputStream.\u003cinit\u003e",
            "source": "FileOutputStream.java:177"
          },
          {
            "method": "org.eclipse.core.runtime.internal.adaptor.Locker_JavaNio.lock",
            "source": "Locker_JavaNio.java:34"
          },
          {
            "method": "org.eclipse.core.runtime.adaptor.FileManager.lock",
            "source": "FileManager.java:361"
          },
          {
            "method": "org.eclipse.core.runtime.adaptor.FileManager.open",
            "source": "FileManager.java:658"
          },
          {
            "method": "org.eclipse.core.internal.runtime.InternalPlatform.initializeRuntimeFileManager",
            "source": "InternalPlatform.java:786"
          },
          {
            "method": "org.eclipse.core.internal.runtime.InternalPlatform.start",
            "source": "InternalPlatform.java:1086"
          },
          {
            "method": "org.eclipse.core.internal.runtime.PlatformActivator.startInternalPlatform",
            "source": "PlatformActivator.java:141"
          },
          {
            "method": "org.eclipse.core.internal.runtime.PlatformActivator.start",
            "source": "PlatformActivator.java:57"
          },
          {
            "method": "org.eclipse.osgi.framework.internal.core.BundleContextImpl$2.run",
            "source": "BundleContextImpl.java:994"
          },
          {
            "method": "java.security.AccessController.doPrivileged",
            "source": "Native Method"
          },
          {
            "method": "org.eclipse.osgi.framework.internal.core.BundleContextImpl.startActivator",
            "source": "BundleContextImpl.java:988"
          }
        ],
        "number": 0,
        "commentIndex": 0
      },
      "number": 2,
      "commentIndex": 2,
      "bugId": "102311",
      "date": "2005-06-30T18:55:12+02:00",
      "product": "Platform",
      "component": "Runtime",
      "severity": "normal"
    },
    {
      "exceptionType": "java.io.FileNotFoundException",
      "message": "/usr/local/eclipse/configuration/org.eclipse.core.runtime/.manager/.fileTableLock (Permission denied)",
      "elements": [
        {
          "method": "java.io.FileOutputStream.openAppend",
          "source": "Native Method"
        },
        {
          "method": "java.io.FileOutputStream.\u003cinit\u003e",
          "source": "FileOutputStream.java:177"
        },
        {
          "method": "org.eclipse.core.runtime.internal.adaptor.Locker_JavaNio.lock",
          "source": "Locker_JavaNio.java:34"
        },
        {
          "method": "org.eclipse.core.runtime.adaptor.FileManager.lock",
          "source": "FileManager.java:361"
        },
        {
          "method": "org.eclipse.core.runtime.adaptor.FileManager.open",
          "source": "FileManager.java:658"
        },
        {
          "method": "org.eclipse.core.internal.runtime.InternalPlatform.initializeRuntimeFileManager",
          "source": "InternalPlatform.java:786"
        },
        {
          "method": "org.eclipse.core.internal.runtime.InternalPlatform.start",
          "source": "InternalPlatform.java:1086"
        },
        {
          "method": "org.eclipse.core.internal.runtime.PlatformActivator.startInternalPlatform",
          "source": "PlatformActivator.java:141"
        },
        {
          "method": "org.eclipse.core.internal.runtime.PlatformActivator.start",
          "source": "PlatformActivator.java:57"
        },
        {
          "method": "org.eclipse.osgi.framework.internal.core.BundleContextImpl$2.run",
          "source": "BundleContextImpl.java:994"
        },
        {
          "method": "java.security.AccessController.doPrivileged",
          "source": "Native Method"
        },
        {
          "method": "org.eclipse.osgi.framework.internal.core.BundleContextImpl.startActivator",
          "source": "BundleContextImpl.java:988"
        },
        {
          "method": "org.eclipse.osgi.framework.internal.core.BundleContextImpl.start",
          "source": "BundleContextImpl.java:969"
        },
        {
          "method": "org.eclipse.osgi.framework.internal.core.BundleHost.startWorker",
          "source": "BundleHost.java:321"
        },
        {
          "method": "org.eclipse.osgi.framework.internal.core.AbstractBundle.resume",
          "source": "AbstractBundle.java:339"
        },
        {
          "method": "org.eclipse.osgi.framework.internal.core.Framework.resumeBundle",
          "source": "Framework.java:1024"
        },
        {
          "method": "org.eclipse.osgi.framework.internal.core.StartLevelManager.resumeBundles",
          "source": "StartLevelManager.java:576"
        },
        {
          "method": "org.eclipse.osgi.framework.internal.core.StartLevelManager.incFWSL",
          "source": "StartLevelManager.java:498"
        },
        {
          "method": "org.eclipse.osgi.framework.internal.core.StartLevelManager.doSetStartLevel",
          "source": "StartLevelManager.java:275"
        },
        {
          "method": "org.eclipse.osgi.framework.internal.core.StartLevelManager.dispatchEvent",
          "source": "StartLevelManager.java:458"
        },
        {
          "method": "org.eclipse.osgi.framework.eventmgr.EventManager.dispatchEvent",
          "source": "EventManager.java:189"
        },
        {
          "method": "org.eclipse.osgi.framework.eventmgr.EventManager$EventThread.run",
          "source": "EventManager.java:291"
        }
      ],
      "number": 3,
      "commentIndex": 2,
      "bugId": "102311",
      "date": "2005-06-30T18:55:12+02:00",
      "product": "Platform",
      "component": "Runtime",
      "severity": "normal"
    },
    {
      "exceptionType": "org.osgi.framework.BundleException",
      "message": "Exception in org.eclipse.update.internal.configurator.ConfigurationActivator.start() of bundle org.eclipse.update.configurator.",
      "elements": [
        {
          "method": "org.eclipse.osgi.framework.internal.core.BundleContextImpl.startActivator",
          "source": "BundleContextImpl.java:1013"
        },
        {
          "method": "org.eclipse.osgi.framework.internal.core.BundleContextImpl.start",
          "source": "BundleContextImpl.java:969"
        },
        {
          "method": "org.eclipse.osgi.framework.internal.core.BundleHost.startWorker",
          "source": "BundleHost.java:321"
        },
        {
          "method": "org.eclipse.osgi.framework.internal.core.AbstractBundle.resume",
          "source": "AbstractBundle.java:339"
        },
        {
          "method": "org.eclipse.osgi.framework.internal.core.Framework.resumeBundle",
          "source": "Framework.java:1024"
        },
        {
          "method": "org.eclipse.osgi.framework.internal.core.StartLevelManager.resumeBundles",
          "source": "StartLevelManager.java:576"
        },
        {
          "method": "org.eclipse.osgi.framework.internal.core.StartLevelManager.incFWSL",
          "source": "StartLevelManager.java:498"
        },
        {
          "method": "org.eclipse.osgi.framework.internal.core.StartLevelManager.doSetStartLevel",
          "source": "StartLevelManager.java:275"
        },
        {
          "method": "org.eclipse.osgi.framework.internal.core.StartLevelManager.dispatchEvent",
          "source": "StartLevelManager.java:458"
        },
        {
          "method": "org.eclipse.osgi.framework.eventmgr.EventManager.dispatchEvent",
          "source": "EventManager.java:189"
        },
        {
          "method": "org.eclipse.osgi.framework.eventmgr.EventManager$EventThread.run",
          "source": "EventManager.java:291"
        }
      ],
      "causedBy": {
        "exceptionType": "java.lang.Exception",
        "message": "Cannot initialize the Update Configurator",
        "elements": [
          {
            "method": "org.eclipse.update.internal.configurator.ConfigurationActivator.initialize",
            "source": "ConfigurationActivator.java:89"
          },
          {
            "method": "org.eclipse.update.internal.configurator.ConfigurationActivator.start",
            "source": "ConfigurationActivator.java:67"
          },
          {
            "method": "org.eclipse.osgi.framework.internal.core.BundleContextImpl$2.run",
            "source": "BundleContextImpl.java:994"
          },
          {
            "method": "java.security.AccessController.doPrivileged",
            "source": "Native Method"
          },
          {
            "method": "org.eclipse.osgi.framework.internal.core.BundleContextImpl.startActivator",
            "source": "BundleContextImpl.java:988"
          }
        ],
        "number": 0,
        "commentIndex": 0
      },
      "number": 4,
      "commentIndex": 2,
      "bugId": "102311",
      "date": "2005-06-30T18:55:12+02:00",
      "product": "Platform",
      "component": "Runtime",
      "severity": "normal"
    },
    {
      "exceptionType": "java.lang.Exception",
      "message": "Cannot initialize the Update Configurator",
      "elements": [
        {
          "method": "org.eclipse.update.internal.configurator.ConfigurationActivator.initialize",
          "source": "ConfigurationActivator.java:89"
        },
        {
          "method": "org.eclipse.update.internal.configurator.ConfigurationActivator.start",
          "source": "ConfigurationActivator.java:67"
        },
        {
          "method": "org.eclipse.osgi.framework.internal.core.BundleContextImpl$2.run",
          "source": "BundleContextImpl.java:994"
        },
        {
          "method": "java.security.AccessController.doPrivileged",
          "source": "Native Method"
        },
        {
          "method": "org.eclipse.osgi.framework.internal.core.BundleContextImpl.startActivator",
          "source": "BundleContextImpl.java:988"
        },
        {
          "method": "org.eclipse.osgi.framework.internal.core.BundleContextImpl.start",
          "source": "BundleContextImpl.java:969"
        },
        {
          "method": "org.eclipse.osgi.framework.internal.core.BundleHost.startWorker",
          "source": "BundleHost.java:321"
        },
        {
          "method": "org.eclipse.osgi.framework.internal.core.AbstractBundle.resume",
          "source": "AbstractBundle.java:339"
        },
        {
          "method": "org.eclipse.osgi.framework.internal.core.Framework.resumeBundle",
          "source": "Framework.java:1024"
        },
        {
          "method": "org.eclipse.osgi.framework.internal.core.StartLevelManager.resumeBundles",
          "source": "StartLevelManager.java:576"
        },
        {
          "method": "org.eclipse.osgi.framework.internal.core.StartLevelManager.incFWSL",
          "source": "StartLevelManager.java:498"
        },
        {
          "method": "org.eclipse.osgi.framework.internal.core.StartLevelManager.doSetStartLevel",
          "source": "StartLevelManager.java:275"
        },
        {
          "method": "org.eclipse.osgi.framework.internal.core.StartLevelManager.dispatchEvent",
          "source": "StartLevelManager.java:458"
        },
        {
          "method": "org.eclipse.osgi.framework.eventmgr.EventManager.dispatchEvent",
          "source": "EventManager.java:189"
        },
        {
          "method": "org.eclipse.osgi.framework.eventmgr.EventManager$EventThread.run",
          "source": "EventManager.java:291"
        }
      ],
      "number": 5,
      "commentIndex": 2,
      "bugId": "102311",
      "date": "2005-06-30T18:55:12+02:00",
      "product": "Platform",
      "component": "Runtime",
      "severity": "normal"
    },
    {
      "exceptionType": "java.lang.IllegalStateException",
      "message": "Bundle initial@reference:file:plugins/org.eclipse.core.runtime_3.1.0.jar/ [1] is not active.",
      "elements": [
        {
          "method": "org.eclipse.core.runtime.adaptor.EclipseStarter.ensureBundlesActive",
          "source": "EclipseStarter.java:410"
        },
        {
          "method": "org.eclipse.core.runtime.adaptor.EclipseStarter.startup",
          "source": "EclipseStarter.java:297"
        },
        {
          "method": "org.eclipse.core.runtime.adaptor.EclipseStarter.run",
          "source": "EclipseStarter.java:159"
        },
        {
          "method": "sun.reflect.NativeMethodAccessorImpl.invoke0",
          "source": "Native Method"
        },
        {
          "method": "sun.reflect.NativeMethodAccessorImpl.invoke",
          "source": "NativeMethodAccessorImpl.java:39"
        },
        {
          "method": "sun.reflect.DelegatingMethodAccessorImpl.invoke",
          "source": "DelegatingMethodAccessorImpl.java:25"
        },
        {
          "method": "java.lang.reflect.Method.invoke",
          "source": "Method.java:324"
        },
        {
          "method": "org.eclipse.core.launcher.Main.invokeFramework",
          "source": "Main.java:334"
        },
        {
          "method": "org.eclipse.core.launcher.Main.basicRun",
          "source": "Main.java:278"
        },
        {
          "method": "org.eclipse.core.launcher.Main.run",
          "source": "Main.java:973"
        },
        {
          "method": "org.eclipse.core.launcher.Main.main",
          "source": "Main.java:948"
        }
      ],
      "number": 6,
      "commentIndex": 2,
      "bugId": "102311",
      "date": "2005-06-30T18:55:12+02:00",
      "product": "Platform",
      "component": "Runtime",
      "severity": "normal"
    }
  ],
  "groupId": "102311",
  "bugId": "102311",
  "date": "2005-06-30T15:05:24+02:00",
  "product": "Platform",
  "component": "Runtime",
  "severity": "normal"
}