{
  "comments": [
    "I installed CDT3.0 on Eclipse3.1 and created a standard make C++ Project.\nI compiled the project and got the following exceptions:\n\njava.lang.ClassCastException: \norg.eclipse.cdt.internal.core.dom.parser.cpp.CPPClassType$CPPClassTypeProblem\n        at \norg.eclipse.cdt.internal.core.dom.parser.cpp.CPPSemantics.getLookupScope\n(CPPSemantics.java:888)\n        at org.eclipse.cdt.internal.core.dom.parser.cpp.CPPSemantics.lookup(CPPS\n\nemantics.java:962)\n        at \norg.eclipse.cdt.internal.core.dom.parser.cpp.CPPSemantics.resolveBinding\n(CPPSemantics.java:603)\n        at \norg.eclipse.cdt.internal.core.dom.parser.cpp.CPPVisitor.resolveBinding\n(CPPVisitor.java:924)\n        at org.eclipse.cdt.internal.core.dom.parser.cpp.CPPVisitor.createBinding\n(CPPVisitor.java:184)\n        at \norg.eclipse.cdt.internal.core.dom.parser.cpp.CPPASTName.resolveBinding\n(CPPASTName.java:52)\n        at \norg.eclipse.cdt.internal.core.index.domsourceindexer.CPPGenerateIndexVisitor.pro\ncessName(\n\nCPPGenerateIndexVisitor.java:148)\n        at \norg.eclipse.cdt.internal.core.index.domsourceindexer.CPPGenerateIndexVisitor.vis\nit(\n\nCPPGenerateIndexVisitor.java:112)\n        at org.eclipse.cdt.internal.core.dom.parser.cpp.CPPASTName.accept\n(CPPASTName.java:90)\n        at \norg.eclipse.cdt.internal.core.dom.parser.cpp.CPPASTFieldReference.accept\n(CPPASTFieldReference.java\n\n:97)\n        at \norg.eclipse.cdt.internal.core.dom.parser.cpp.CPPASTFunctionCallExpression.accept\n(\n\nCPPASTFunctionCallExpression.java:64)\n        at \norg.eclipse.cdt.internal.core.dom.parser.cpp.CPPASTBinaryExpression.accept\n(CPPASTBinaryExpression.\n\njava:81)\n        at \norg.eclipse.cdt.internal.core.dom.parser.cpp.CPPASTExpressionStatement.accept(\n\nCPPASTExpressionStatement.java:48)\n        at org.eclipse.cdt.internal.core.dom.parser.cpp.CPPASTCompoundStatement.\naccept(CPPASTCompoundStatement.java:66)\n        at \norg.eclipse.cdt.internal.core.dom.parser.cpp.CPPASTFunctionDefinition.accept(\n\nCPPASTFunctionDefinition.java:93)\n        at \norg.eclipse.cdt.internal.core.dom.parser.cpp.CPPASTCompositeTypeSpecifier.accept\n(\n\nCPPASTCompositeTypeSpecifier.java:136)\n        at \norg.eclipse.cdt.internal.core.dom.parser.cpp.CPPASTSimpleDeclaration.accept(\n\nCPPASTSimpleDeclaration.java:71)\n        at \norg.eclipse.cdt.internal.core.dom.parser.cpp.CPPASTTranslationUnit.accept\n(CPPASTTranslationUnit.\n\njava:520)\n        at \norg.eclipse.cdt.internal.core.index.domsourceindexer.DOMSourceIndexerRunner.inde\nxFile(\n\nDOMSourceIndexerRunner.java:133)\n        at \norg.eclipse.cdt.internal.core.index.domsourceindexer.AbstractIndexerRunner.index\n(\n\nAbstractIndexerRunner.java:76)\n        at org.eclipse.cdt.internal.core.index.cindexstorage.Index.add\n(Index.java:110)\n        at \norg.eclipse.cdt.internal.core.index.domsourceindexer.DOMAddCompilationUnitToInde\nx.indexDocument(\n\nDOMAddCompilationUnitToIndex.java:29)\n        at \norg.eclipse.cdt.internal.core.index.domsourceindexer.DOMAddFileToIndex.execute\n(DOMAddFileToIndex.\n\njava:60)\n        at org.eclipse.cdt.internal.core.search.processing.JobManager.run\n(JobManager.java:466)\n        at java.lang.Thread.run(Thread.java:534)\njava.lang.ClassCastException: \norg.eclipse.cdt.internal.core.dom.parser.cpp.CPPClassType$CPPClassTypeProblem\n       at \norg.eclipse.cdt.internal.core.dom.parser.cpp.CPPSemantics.getLookupScope\n(CPPSemantics.java:888)\n        at org.eclipse.cdt.internal.core.dom.parser.cpp.CPPSemantics.lookup\n(CPPSemantics.java:962)\n        at \norg.eclipse.cdt.internal.core.dom.parser.cpp.CPPSemantics.resolveBinding\n(CPPSemantics.java:603)\n        at \norg.eclipse.cdt.internal.core.dom.parser.cpp.CPPVisitor.resolveBinding\n(CPPVisitor.java:924)\n        at org.eclipse.cdt.internal.core.dom.parser.cpp.CPPVisitor.createBinding\n(CPPVisitor.java:184)\n        at \norg.eclipse.cdt.internal.core.dom.parser.cpp.CPPASTName.resolveBinding\n(CPPASTName.java:52)\n        at \norg.eclipse.cdt.internal.core.index.domsourceindexer.CPPGenerateIndexVisitor.pro\ncessName(\n\nCPPGenerateIndexVisitor.java:148)\n        at \norg.eclipse.cdt.internal.core.index.domsourceindexer.CPPGenerateIndexVisitor.vis\nit(\n\nCPPGenerateIndexVisitor.java:112)\n        at org.eclipse.cdt.internal.core.dom.parser.cpp.CPPASTName.accept\n(CPPASTName.java:90)\n        at \norg.eclipse.cdt.internal.core.dom.parser.cpp.CPPASTFieldReference.accept\n(CPPASTFieldReference.java\n\n:97)\n        at \norg.eclipse.cdt.internal.core.dom.parser.cpp.CPPASTFunctionCallExpression.accept\n(\n\nCPPASTFunctionCallExpression.java:64)\n        at \norg.eclipse.cdt.internal.core.dom.parser.cpp.CPPASTBinaryExpression.accept\n(CPPASTBinaryExpression.\n\njava:81)\n      at \norg.eclipse.cdt.internal.core.dom.parser.cpp.CPPASTExpressionStatement.accept(\n\nCPPASTExpressionStatement.java:48)\n        at \norg.eclipse.cdt.internal.core.dom.parser.cpp.CPPASTCompoundStatement.accept(\n\nCPPASTCompoundStatement.java:66)\n        at \norg.eclipse.cdt.internal.core.dom.parser.cpp.CPPASTFunctionDefinition.accept(\n\nCPPASTFunctionDefinition.java:93)\n        at \norg.eclipse.cdt.internal.core.dom.parser.cpp.CPPASTCompositeTypeSpecifier.accept\n(\n\nCPPASTCompositeTypeSpecifier.java:136)\n        at \norg.eclipse.cdt.internal.core.dom.parser.cpp.CPPASTSimpleDeclaration.accept(\n\nCPPASTSimpleDeclaration.java:71)\n        at \norg.eclipse.cdt.internal.core.dom.parser.cpp.CPPASTTranslationUnit.accept\n(CPPASTTranslationUnit.\n\njava:520)\n        at \norg.eclipse.cdt.internal.core.index.domsourceindexer.DOMSourceIndexerRunner.inde\nxFile(\n\nDOMSourceIndexerRunner.java:133)\n        at \norg.eclipse.cdt.internal.core.index.domsourceindexer.AbstractIndexerRunner.index\n(\n\nAbstractIndexerRunner.java:76)\n        at org.eclipse.cdt.internal.core.index.cindexstorage.Index.add\n(Index.java:110)\n        at \norg.eclipse.cdt.internal.core.index.domsourceindexer.DOMAddCompilationUnitToInde\nx.indexDocument(\n\nDOMAddCompilationUnitToIndex.java:29)\n        at \norg.eclipse.cdt.internal.core.index.domsourceindexer.DOMAddFileToIndex.execute\n(DOMAddFileToIndex.\n\njava:60)\n        at org.eclipse.cdt.internal.core.search.processing.JobManager.run\n(JobManager.java:466)\n  at java.lang.Thread.run(Thread.java:534)\njava.lang.ClassCastException: \norg.eclipse.cdt.internal.core.dom.parser.cpp.CPPClassType$CPPClassTypeProblem\n        at \norg.eclipse.cdt.internal.core.dom.parser.cpp.CPPSemantics.getLookupScope\n(CPPSemantics.java:888)\n        at org.eclipse.cdt.internal.core.dom.parser.cpp.CPPSemantics.lookup\n(CPPSemantics.java:962)\n        at \norg.eclipse.cdt.internal.core.dom.parser.cpp.CPPSemantics.resolveBinding\n(CPPSemantics.java:603)\n        at \norg.eclipse.cdt.internal.core.dom.parser.cpp.CPPVisitor.resolveBinding\n(CPPVisitor.java:924)\n        at org.eclipse.cdt.internal.core.dom.parser.cpp.CPPVisitor.createBinding\n(CPPVisitor.java:184)\n        at \norg.eclipse.cdt.internal.core.dom.parser.cpp.CPPASTName.resolveBinding\n(CPPASTName.java:52)\n        at \norg.eclipse.cdt.internal.core.index.domsourceindexer.CPPGenerateIndexVisitor.pro\ncessName(\n\nCPPGenerateIndexVisitor.java:148)\n        at \norg.eclipse.cdt.internal.core.index.domsourceindexer.CPPGenerateIndexVisitor.vis\nit(\n\nCPPGenerateIndexVisitor.java:112)\n        at org.eclipse.cdt.internal.core.dom.parser.cpp.CPPASTName.accept\n(CPPASTName.java:90)\n        at \norg.eclipse.cdt.internal.core.dom.parser.cpp.CPPASTFieldReference.accept\n(CPPASTFieldReference.java\n\n:97)\n        at org.eclipse.cdt.internal.core.dom.parser.cpp.CPPASTFunctionCallExpres\nsion.accept(CPPASTFunctionCallExpression.java:64)\n        at \norg.eclipse.cdt.internal.core.dom.parser.cpp.CPPASTBinaryExpression.accept\n(CPPASTBinaryExpression.\n\njava:81)\n        at \norg.eclipse.cdt.internal.core.dom.parser.cpp.CPPASTExpressionStatement.accept(\n\nCPPASTExpressionStatement.java:48)\n        at \norg.eclipse.cdt.internal.core.dom.parser.cpp.CPPASTCompoundStatement.accept(\n\nCPPASTCompoundStatement.java:66)\n        at \norg.eclipse.cdt.internal.core.dom.parser.cpp.CPPASTFunctionDefinition.accept(\n\nCPPASTFunctionDefinition.java:93)\n        at \norg.eclipse.cdt.internal.core.dom.parser.cpp.CPPASTCompositeTypeSpecifier.accept\n(\n\nCPPASTCompositeTypeSpecifier.java:136)\n        at \norg.eclipse.cdt.internal.core.dom.parser.cpp.CPPASTSimpleDeclaration.accept(\n\nCPPASTSimpleDeclaration.java:71)\n        at \norg.eclipse.cdt.internal.core.dom.parser.cpp.CPPASTTranslationUnit.accept\n(CPPASTTranslationUnit.\n\njava:520)\n        at \norg.eclipse.cdt.internal.core.index.domsourceindexer.DOMSourceIndexerRunner.inde\nxFile(\n\nDOMSourceIndexerRunner.java:133)\n        at \norg.eclipse.cdt.internal.core.index.domsourceindexer.AbstractIndexerRunner.index\n(\n\nAbstractIndexerRunner.java:76)\n        at org.eclipse.cdt.internal.core.index.cindexstorage.Index.add\n(Index.java:110)\n        at \norg.eclipse.cdt.internal.core.index.domsourceindexer.DOMAddCompilationUnitToInde\nx.indexDocument(\n\nDOMAddCompilationUnitToIndex.java:29)\n        at \norg.eclipse.cdt.internal.core.index.domsourceindexer.DOMAddFileToIndex.execute\n(DOMAddFileToIndex.\n\njava:60)\n        at org.eclipse.cdt.internal.core.search.processing.JobManager.run\n(JobManager.java:466)\n        at java.lang.Thread.run(Thread.java:534)\njava.lang.ClassCastException: \norg.eclipse.cdt.internal.core.dom.parser.cpp.CPPClassType$CPPClassTypeProblem\n        at \norg.eclipse.cdt.internal.core.dom.parser.cpp.CPPSemantics.getLookupScope\n(CPPSemantics.java:888)\n        at org.eclipse.cdt.internal.core.dom.parser.cpp.CPPSemantics.lookup\n(CPPSemantics.java:962)\n        at \norg.eclipse.cdt.internal.core.dom.parser.cpp.CPPSemantics.resolveBinding\n(CPPSemantics.java:603)\n        at \norg.eclipse.cdt.internal.core.dom.parser.cpp.CPPVisitor.resolveBinding\n(CPPVisitor.java:924)\n        at org.eclipse.cdt.internal.core.dom.parser.cpp.CPPVisitor.createBinding\n(CPPVisitor.java:184)\n        at \norg.eclipse.cdt.internal.core.dom.parser.cpp.CPPASTName.resolveBinding\n(CPPASTName.java:52)\n        at \norg.eclipse.cdt.internal.core.index.domsourceindexer.CPPGenerateIndexVisitor.pro\ncessName(\n\nCPPGenerateIndexVisitor.java:148)\n        at \norg.eclipse.cdt.internal.core.index.domsourceindexer.CPPGenerateIndexVisitor.vis\nit(\n\nCPPGenerateIndexVisitor.java:112)\n        at org.eclipse.cdt.internal.core.dom.parser.cpp.CPPASTName.accept\n(CPPASTName.java:90)\n        at \norg.eclipse.cdt.internal.core.dom.parser.cpp.CPPASTFieldReference.accept\n(CPPASTFieldReference.java\n\n:97)\n        at \norg.eclipse.cdt.internal.core.dom.parser.cpp.CPPASTFunctionCallExpression.accept\n(\n\nCPPASTFunctionCallExpression.java:64)\n        at \norg.eclipse.cdt.internal.core.dom.parser.cpp.CPPASTBinaryExpression.accept\n(CPPASTBinaryExpression.\n\njava:81)\n        at \norg.eclipse.cdt.internal.core.dom.parser.cpp.CPPASTExpressionStatement.accept(\n\nCPPASTExpressionStatement.java:48)\n        at \norg.eclipse.cdt.internal.core.dom.parser.cpp.CPPASTCompoundStatement.accept(\n\nCPPASTCompoundStatement.java:66)\n        at \norg.eclipse.cdt.internal.core.dom.parser.cpp.CPPASTFunctionDefinition.accept(\n\nCPPASTFunctionDefinition.java:93)\n        at \norg.eclipse.cdt.internal.core.dom.parser.cpp.CPPASTCompositeTypeSpecifier.accept\n(\n\nCPPASTCompositeTypeSpecifier.java:136)\n        at \norg.eclipse.cdt.internal.core.dom.parser.cpp.CPPASTSimpleDeclaration.accept(\n\nCPPASTSimpleDeclaration.java:71)\n        at \norg.eclipse.cdt.internal.core.dom.parser.cpp.CPPASTTranslationUnit.accept\n(CPPASTTranslationUnit.\n\njava:520)\n        at \norg.eclipse.cdt.internal.core.index.domsourceindexer.DOMSourceIndexerRunner.inde\nxFile(\n\nDOMSourceIndexerRunner.java:133)\n        at \norg.eclipse.cdt.internal.core.index.domsourceindexer.AbstractIndexerRunner.index\n(\n\nAbstractIndexerRunner.java:76)\n        at org.eclipse.cdt.internal.core.index.cindexstorage.Index.add\n(Index.java:110)\n at \norg.eclipse.cdt.internal.core.index.domsourceindexer.DOMAddCompilationUnitToInde\nx.indexDocument(\n\nDOMAddCompilationUnitToIndex.java:29)\n        at \norg.eclipse.cdt.internal.core.index.domsourceindexer.DOMAddFileToIndex.execute\n(DOMAddFileToIndex.\n\njava:60)\n        at org.eclipse.cdt.internal.core.search.processing.JobManager.run\n(JobManager.java:466)\n        at java.lang.Thread.run(Thread.java:534)\njava.lang.ClassCastException: \norg.eclipse.cdt.internal.core.dom.parser.cpp.CPPClassType$CPPClassTypeProblem\n        at \norg.eclipse.cdt.internal.core.dom.parser.cpp.CPPSemantics.getLookupScope\n(CPPSemantics.java:888)\n        at org.eclipse.cdt.internal.core.dom.parser.cpp.CPPSemantics.lookup\n(CPPSemantics.java:962)\n        at org.eclipse.cdt.internal.core.dom.parser.cpp.CPPSemantics.resolveBind\ning(CPPSemantics.java:603)\n        at \norg.eclipse.cdt.internal.core.dom.parser.cpp.CPPVisitor.resolveBinding\n(CPPVisitor.java:924)\n        at org.eclipse.cdt.internal.core.dom.parser.cpp.CPPVisitor.createBinding\n(CPPVisitor.java:184)\n        at \norg.eclipse.cdt.internal.core.dom.parser.cpp.CPPASTName.resolveBinding\n(CPPASTName.java:52)\n        at \norg.eclipse.cdt.internal.core.index.domsourceindexer.CPPGenerateIndexVisitor.pro\ncessName(\n\nCPPGenerateIndexVisitor.java:148)\n        at \norg.eclipse.cdt.internal.core.index.domsourceindexer.CPPGenerateIndexVisitor.vis\nit(\n\nCPPGenerateIndexVisitor.java:112)\n        at org.eclipse.cdt.internal.core.dom.parser.cpp.CPPASTName.accept\n(CPPASTName.java:90)\n        at \norg.eclipse.cdt.internal.core.dom.parser.cpp.CPPASTFieldReference.accept\n(CPPASTFieldReference.java\n\n:97)\n        at \norg.eclipse.cdt.internal.core.dom.parser.cpp.CPPASTFunctionCallExpression.accept\n(\n\nCPPASTFunctionCallExpression.java:64)\n        at \norg.eclipse.cdt.internal.core.dom.parser.cpp.CPPASTBinaryExpression.accept\n(CPPASTBinaryExpression.\n\njava:81)\n        at \norg.eclipse.cdt.internal.core.dom.parser.cpp.CPPASTExpressionStatement.accept(\n\nCPPASTExpressionStatement.java:48)\n        at \norg.eclipse.cdt.internal.core.dom.parser.cpp.CPPASTCompoundStatement.accept(\n\nCPPASTCompoundStatement.java:66)\n        at org.eclipse.cdt.internal.core.dom.parser.cpp.CPPASTFunctionDefinition\n.accept(CPPASTFunctionDefinition.java:93)\n        at \norg.eclipse.cdt.internal.core.dom.parser.cpp.CPPASTCompositeTypeSpecifier.accept\n(\n\nCPPASTCompositeTypeSpecifier.java:136)\n        at \norg.eclipse.cdt.internal.core.dom.parser.cpp.CPPASTSimpleDeclaration.accept(\n\nCPPASTSimpleDeclaration.java:71)\n        at \norg.eclipse.cdt.internal.core.dom.parser.cpp.CPPASTTranslationUnit.accept\n(CPPASTTranslationUnit.\n\njava:520)\n        at \norg.eclipse.cdt.internal.core.index.domsourceindexer.DOMSourceIndexerRunner.inde\nxFile(\n\nDOMSourceIndexerRunner.java:133)\n        at \norg.eclipse.cdt.internal.core.index.domsourceindexer.AbstractIndexerRunner.index\n(\n\nAbstractIndexerRunner.java:76)\n        at org.eclipse.cdt.internal.core.index.cindexstorage.Index.add\n(Index.java:110)\n        at \norg.eclipse.cdt.internal.core.index.domsourceindexer.DOMAddCompilationUnitToInde\nx.indexDocument(\n\nDOMAddCompilationUnitToIndex.java:29)\n        at \norg.eclipse.cdt.internal.core.index.domsourceindexer.DOMAddFileToIndex.execute\n(DOMAddFileToIndex.\n\njava:60)\n        at org.eclipse.cdt.internal.core.search.processing.JobManager.run\n(JobManager.java:466)\n        at java.lang.Thread.run(Thread.java:534)\neclipseLinuxjava.lang.ClassCastException: \norg.eclipse.cdt.internal.core.dom.parser.cpp.\n\nCPPClassType$CPPClassTypeProblem\n        at \norg.eclipse.cdt.internal.core.dom.parser.cpp.CPPSemantics.getLookupScope\n(CPPSemantics.java:888)\n\n       at org.eclipse.cdt.internal.core.dom.parser.cpp.CPPSemantics.lookup\n(CPPSemantics.java:962)\n        at \norg.eclipse.cdt.internal.core.dom.parser.cpp.CPPSemantics.resolveBinding\n(CPPSemantics.java:603)\n        at \norg.eclipse.cdt.internal.core.dom.parser.cpp.CPPVisitor.resolveBinding\n(CPPVisitor.java:924)\n        at org.eclipse.cdt.internal.core.dom.parser.cpp.CPPVisitor.createBinding\n(CPPVisitor.java:184)\n        at \norg.eclipse.cdt.internal.core.dom.parser.cpp.CPPASTName.resolveBinding\n(CPPASTName.java:52)\n        at \norg.eclipse.cdt.internal.core.index.domsourceindexer.CPPGenerateIndexVisitor.pro\ncessName(\n\nCPPGenerateIndexVisitor.java:148)\n        at \norg.eclipse.cdt.internal.core.index.domsourceindexer.CPPGenerateIndexVisitor.vis\nit(\n\nCPPGenerateIndexVisitor.java:112)\n        at org.eclipse.cdt.internal.core.dom.parser.cpp.CPPASTName.accept\n(CPPASTName.java:90)\n        at \norg.eclipse.cdt.internal.core.dom.parser.cpp.CPPASTFieldReference.accept\n(CPPASTFieldReference.java\n\n:97)\n        at \norg.eclipse.cdt.internal.core.dom.parser.cpp.CPPASTFunctionCallExpression.accept\n(\n\nCPPASTFunctionCallExpression.java:64)\n        at \norg.eclipse.cdt.internal.core.dom.parser.cpp.CPPASTBinaryExpression.accept\n(CPPASTBinaryExpression.\n\njava:81)\n        at \norg.eclipse.cdt.internal.core.dom.parser.cpp.CPPASTExpressionStatement.accept(\n\nCPPASTExpressionStatement.java:48)\n   at \norg.eclipse.cdt.internal.core.dom.parser.cpp.CPPASTCompoundStatement.accept\n(CPPASTCompoundStatement.\n\njava:66)\n        at \norg.eclipse.cdt.internal.core.dom.parser.cpp.CPPASTFunctionDefinition.accept(\n\nCPPASTFunctionDefinition.java:93)\n        at \norg.eclipse.cdt.internal.core.dom.parser.cpp.CPPASTCompositeTypeSpecifier.accept\n(\n\nCPPASTCompositeTypeSpecifier.java:136)\n        at \norg.eclipse.cdt.internal.core.dom.parser.cpp.CPPASTSimpleDeclaration.accept(\n\nCPPASTSimpleDeclaration.java:71)\n        at \norg.eclipse.cdt.internal.core.dom.parser.cpp.CPPASTTranslationUnit.accept\n(CPPASTTranslationUnit.\n\njava:520)\n        at \norg.eclipse.cdt.internal.core.index.domsourceindexer.DOMSourceIndexerRunner.inde\nxFile(\n\nDOMSourceIndexerRunner.java:133)\n        at \norg.eclipse.cdt.internal.core.index.domsourceindexer.AbstractIndexerRunner.index\n(\n\nAbstractIndexerRunner.java:76)\n        at org.eclipse.cdt.internal.core.index.cindexstorage.Index.add\n(Index.java:110)\n        at \norg.eclipse.cdt.internal.core.index.domsourceindexer.DOMAddCompilationUnitToInde\nx.indexDocument(\n\nDOMAddCompilationUnitToIndex.java:29)\n        at \norg.eclipse.cdt.internal.core.index.domsourceindexer.DOMAddFileToIndex.execute\n(DOMAddFileToIndex.\n\njava:60)\n        at org.eclipse.cdt.internal.core.search.processing.JobManager.run\n(JobManager.java:466)\n        at java.lang.Thread.run(Thread.java:534)",
    "Changing component to cdt-core.",
    "The CCE in getLookupScope was fixed in RC2 with bug 102764.\n\nI can\u0027t address the reason for getting a problem instead of a scope without an\nexample."
  ],
  "commentCreationDates": [
    "2005-07-12T12:16:46+02:00",
    "2005-07-12T14:48:38+02:00",
    "2005-07-12T16:25:49+02:00"
  ],
  "traces": [
    {
      "exceptionType": "java.lang.ClassCastException",
      "message": "org.eclipse.cdt.internal.core.dom.parser.cpp.CPPClassType$CPPClassTypeProblem",
      "elements": [
        {
          "method": "org.eclipse.cdt.internal.core.dom.parser.cpp.CPPSemantics.getLookupScope",
          "source": "CPPSemantics.java:888"
        },
        {
          "method": "org.eclipse.cdt.internal.core.dom.parser.cpp.CPPSemantics.lookup",
          "source": "CPPS  emantics.java:962"
        },
        {
          "method": "org.eclipse.cdt.internal.core.dom.parser.cpp.CPPSemantics.resolveBinding",
          "source": "CPPSemantics.java:603"
        },
        {
          "method": "org.eclipse.cdt.internal.core.dom.parser.cpp.CPPVisitor.resolveBinding",
          "source": "CPPVisitor.java:924"
        },
        {
          "method": "org.eclipse.cdt.internal.core.dom.parser.cpp.CPPVisitor.createBinding",
          "source": "CPPVisitor.java:184"
        },
        {
          "method": "org.eclipse.cdt.internal.core.dom.parser.cpp.CPPASTName.resolveBinding",
          "source": "CPPASTName.java:52"
        },
        {
          "method": "org.eclipse.cdt.internal.core.index.domsourceindexer.CPPGenerateIndexVisitor.processName",
          "source": "  CPPGenerateIndexVisitor.java:148"
        },
        {
          "method": "org.eclipse.cdt.internal.core.index.domsourceindexer.CPPGenerateIndexVisitor.visit",
          "source": "  CPPGenerateIndexVisitor.java:112"
        },
        {
          "method": "org.eclipse.cdt.internal.core.dom.parser.cpp.CPPASTName.accept",
          "source": "CPPASTName.java:90"
        },
        {
          "method": "org.eclipse.cdt.internal.core.dom.parser.cpp.CPPASTFieldReference.accept",
          "source": "CPPASTFieldReference.java  :97"
        },
        {
          "method": "org.eclipse.cdt.internal.core.dom.parser.cpp.CPPASTFunctionCallExpression.accept",
          "source": "  CPPASTFunctionCallExpression.java:64"
        },
        {
          "method": "org.eclipse.cdt.internal.core.dom.parser.cpp.CPPASTBinaryExpression.accept",
          "source": "CPPASTBinaryExpression.  java:81"
        },
        {
          "method": "org.eclipse.cdt.internal.core.dom.parser.cpp.CPPASTExpressionStatement.accept",
          "source": "  CPPASTExpressionStatement.java:48"
        },
        {
          "method": "org.eclipse.cdt.internal.core.dom.parser.cpp.CPPASTCompoundStatement.accept",
          "source": "CPPASTCompoundStatement.java:66"
        },
        {
          "method": "org.eclipse.cdt.internal.core.dom.parser.cpp.CPPASTFunctionDefinition.accept",
          "source": "  CPPASTFunctionDefinition.java:93"
        },
        {
          "method": "org.eclipse.cdt.internal.core.dom.parser.cpp.CPPASTCompositeTypeSpecifier.accept",
          "source": "  CPPASTCompositeTypeSpecifier.java:136"
        },
        {
          "method": "org.eclipse.cdt.internal.core.dom.parser.cpp.CPPASTSimpleDeclaration.accept",
          "source": "  CPPASTSimpleDeclaration.java:71"
        },
        {
          "method": "org.eclipse.cdt.internal.core.dom.parser.cpp.CPPASTTranslationUnit.accept",
          "source": "CPPASTTranslationUnit.  java:520"
        },
        {
          "method": "org.eclipse.cdt.internal.core.index.domsourceindexer.DOMSourceIndexerRunner.indexFile",
          "source": "  DOMSourceIndexerRunner.java:133"
        },
        {
          "method": "org.eclipse.cdt.internal.core.index.domsourceindexer.AbstractIndexerRunner.index",
          "source": "  AbstractIndexerRunner.java:76"
        },
        {
          "method": "org.eclipse.cdt.internal.core.index.cindexstorage.Index.add",
          "source": "Index.java:110"
        },
        {
          "method": "org.eclipse.cdt.internal.core.index.domsourceindexer.DOMAddCompilationUnitToIndex.indexDocument",
          "source": "  DOMAddCompilationUnitToIndex.java:29"
        },
        {
          "method": "org.eclipse.cdt.internal.core.index.domsourceindexer.DOMAddFileToIndex.execute",
          "source": "DOMAddFileToIndex.  java:60"
        },
        {
          "method": "org.eclipse.cdt.internal.core.search.processing.JobManager.run",
          "source": "JobManager.java:466"
        },
        {
          "method": "java.lang.Thread.run",
          "source": "Thread.java:534"
        }
      ],
      "number": 0,
      "commentIndex": 0,
      "bugId": "103468",
      "date": "2005-07-12T12:16:46+02:00",
      "product": "CDT",
      "component": "cdt-core",
      "severity": "normal"
    },
    {
      "exceptionType": "java.lang.ClassCastException",
      "message": "org.eclipse.cdt.internal.core.dom.parser.cpp.CPPClassType$CPPClassTypeProblem",
      "elements": [
        {
          "method": "org.eclipse.cdt.internal.core.dom.parser.cpp.CPPSemantics.getLookupScope",
          "source": "CPPSemantics.java:888"
        },
        {
          "method": "org.eclipse.cdt.internal.core.dom.parser.cpp.CPPSemantics.lookup",
          "source": "CPPSemantics.java:962"
        },
        {
          "method": "org.eclipse.cdt.internal.core.dom.parser.cpp.CPPSemantics.resolveBinding",
          "source": "CPPSemantics.java:603"
        },
        {
          "method": "org.eclipse.cdt.internal.core.dom.parser.cpp.CPPVisitor.resolveBinding",
          "source": "CPPVisitor.java:924"
        },
        {
          "method": "org.eclipse.cdt.internal.core.dom.parser.cpp.CPPVisitor.createBinding",
          "source": "CPPVisitor.java:184"
        },
        {
          "method": "org.eclipse.cdt.internal.core.dom.parser.cpp.CPPASTName.resolveBinding",
          "source": "CPPASTName.java:52"
        },
        {
          "method": "org.eclipse.cdt.internal.core.index.domsourceindexer.CPPGenerateIndexVisitor.processName",
          "source": "  CPPGenerateIndexVisitor.java:148"
        },
        {
          "method": "org.eclipse.cdt.internal.core.index.domsourceindexer.CPPGenerateIndexVisitor.visit",
          "source": "  CPPGenerateIndexVisitor.java:112"
        },
        {
          "method": "org.eclipse.cdt.internal.core.dom.parser.cpp.CPPASTName.accept",
          "source": "CPPASTName.java:90"
        },
        {
          "method": "org.eclipse.cdt.internal.core.dom.parser.cpp.CPPASTFieldReference.accept",
          "source": "CPPASTFieldReference.java  :97"
        },
        {
          "method": "org.eclipse.cdt.internal.core.dom.parser.cpp.CPPASTFunctionCallExpression.accept",
          "source": "  CPPASTFunctionCallExpression.java:64"
        },
        {
          "method": "org.eclipse.cdt.internal.core.dom.parser.cpp.CPPASTBinaryExpression.accept",
          "source": "CPPASTBinaryExpression.  java:81"
        },
        {
          "method": "org.eclipse.cdt.internal.core.dom.parser.cpp.CPPASTExpressionStatement.accept",
          "source": "  CPPASTExpressionStatement.java:48"
        },
        {
          "method": "org.eclipse.cdt.internal.core.dom.parser.cpp.CPPASTCompoundStatement.accept",
          "source": "  CPPASTCompoundStatement.java:66"
        },
        {
          "method": "org.eclipse.cdt.internal.core.dom.parser.cpp.CPPASTFunctionDefinition.accept",
          "source": "  CPPASTFunctionDefinition.java:93"
        },
        {
          "method": "org.eclipse.cdt.internal.core.dom.parser.cpp.CPPASTCompositeTypeSpecifier.accept",
          "source": "  CPPASTCompositeTypeSpecifier.java:136"
        },
        {
          "method": "org.eclipse.cdt.internal.core.dom.parser.cpp.CPPASTSimpleDeclaration.accept",
          "source": "  CPPASTSimpleDeclaration.java:71"
        },
        {
          "method": "org.eclipse.cdt.internal.core.dom.parser.cpp.CPPASTTranslationUnit.accept",
          "source": "CPPASTTranslationUnit.  java:520"
        },
        {
          "method": "org.eclipse.cdt.internal.core.index.domsourceindexer.DOMSourceIndexerRunner.indexFile",
          "source": "  DOMSourceIndexerRunner.java:133"
        },
        {
          "method": "org.eclipse.cdt.internal.core.index.domsourceindexer.AbstractIndexerRunner.index",
          "source": "  AbstractIndexerRunner.java:76"
        },
        {
          "method": "org.eclipse.cdt.internal.core.index.cindexstorage.Index.add",
          "source": "Index.java:110"
        },
        {
          "method": "org.eclipse.cdt.internal.core.index.domsourceindexer.DOMAddCompilationUnitToIndex.indexDocument",
          "source": "  DOMAddCompilationUnitToIndex.java:29"
        },
        {
          "method": "org.eclipse.cdt.internal.core.index.domsourceindexer.DOMAddFileToIndex.execute",
          "source": "DOMAddFileToIndex.  java:60"
        },
        {
          "method": "org.eclipse.cdt.internal.core.search.processing.JobManager.run",
          "source": "JobManager.java:466"
        },
        {
          "method": "java.lang.Thread.run",
          "source": "Thread.java:534"
        }
      ],
      "number": 1,
      "commentIndex": 0,
      "bugId": "103468",
      "date": "2005-07-12T12:16:46+02:00",
      "product": "CDT",
      "component": "cdt-core",
      "severity": "normal"
    },
    {
      "exceptionType": "java.lang.ClassCastException",
      "message": "org.eclipse.cdt.internal.core.dom.parser.cpp.CPPClassType$CPPClassTypeProblem",
      "elements": [
        {
          "method": "org.eclipse.cdt.internal.core.dom.parser.cpp.CPPSemantics.getLookupScope",
          "source": "CPPSemantics.java:888"
        },
        {
          "method": "org.eclipse.cdt.internal.core.dom.parser.cpp.CPPSemantics.lookup",
          "source": "CPPSemantics.java:962"
        },
        {
          "method": "org.eclipse.cdt.internal.core.dom.parser.cpp.CPPSemantics.resolveBinding",
          "source": "CPPSemantics.java:603"
        },
        {
          "method": "org.eclipse.cdt.internal.core.dom.parser.cpp.CPPVisitor.resolveBinding",
          "source": "CPPVisitor.java:924"
        },
        {
          "method": "org.eclipse.cdt.internal.core.dom.parser.cpp.CPPVisitor.createBinding",
          "source": "CPPVisitor.java:184"
        },
        {
          "method": "org.eclipse.cdt.internal.core.dom.parser.cpp.CPPASTName.resolveBinding",
          "source": "CPPASTName.java:52"
        },
        {
          "method": "org.eclipse.cdt.internal.core.index.domsourceindexer.CPPGenerateIndexVisitor.processName",
          "source": "  CPPGenerateIndexVisitor.java:148"
        },
        {
          "method": "org.eclipse.cdt.internal.core.index.domsourceindexer.CPPGenerateIndexVisitor.visit",
          "source": "  CPPGenerateIndexVisitor.java:112"
        },
        {
          "method": "org.eclipse.cdt.internal.core.dom.parser.cpp.CPPASTName.accept",
          "source": "CPPASTName.java:90"
        },
        {
          "method": "org.eclipse.cdt.internal.core.dom.parser.cpp.CPPASTFieldReference.accept",
          "source": "CPPASTFieldReference.java  :97"
        },
        {
          "method": "org.eclipse.cdt.internal.core.dom.parser.cpp.CPPASTFunctionCallExpression.accept",
          "source": "CPPASTFunctionCallExpression.java:64"
        },
        {
          "method": "org.eclipse.cdt.internal.core.dom.parser.cpp.CPPASTBinaryExpression.accept",
          "source": "CPPASTBinaryExpression.  java:81"
        },
        {
          "method": "org.eclipse.cdt.internal.core.dom.parser.cpp.CPPASTExpressionStatement.accept",
          "source": "  CPPASTExpressionStatement.java:48"
        },
        {
          "method": "org.eclipse.cdt.internal.core.dom.parser.cpp.CPPASTCompoundStatement.accept",
          "source": "  CPPASTCompoundStatement.java:66"
        },
        {
          "method": "org.eclipse.cdt.internal.core.dom.parser.cpp.CPPASTFunctionDefinition.accept",
          "source": "  CPPASTFunctionDefinition.java:93"
        },
        {
          "method": "org.eclipse.cdt.internal.core.dom.parser.cpp.CPPASTCompositeTypeSpecifier.accept",
          "source": "  CPPASTCompositeTypeSpecifier.java:136"
        },
        {
          "method": "org.eclipse.cdt.internal.core.dom.parser.cpp.CPPASTSimpleDeclaration.accept",
          "source": "  CPPASTSimpleDeclaration.java:71"
        },
        {
          "method": "org.eclipse.cdt.internal.core.dom.parser.cpp.CPPASTTranslationUnit.accept",
          "source": "CPPASTTranslationUnit.  java:520"
        },
        {
          "method": "org.eclipse.cdt.internal.core.index.domsourceindexer.DOMSourceIndexerRunner.indexFile",
          "source": "  DOMSourceIndexerRunner.java:133"
        },
        {
          "method": "org.eclipse.cdt.internal.core.index.domsourceindexer.AbstractIndexerRunner.index",
          "source": "  AbstractIndexerRunner.java:76"
        },
        {
          "method": "org.eclipse.cdt.internal.core.index.cindexstorage.Index.add",
          "source": "Index.java:110"
        },
        {
          "method": "org.eclipse.cdt.internal.core.index.domsourceindexer.DOMAddCompilationUnitToIndex.indexDocument",
          "source": "  DOMAddCompilationUnitToIndex.java:29"
        },
        {
          "method": "org.eclipse.cdt.internal.core.index.domsourceindexer.DOMAddFileToIndex.execute",
          "source": "DOMAddFileToIndex.  java:60"
        },
        {
          "method": "org.eclipse.cdt.internal.core.search.processing.JobManager.run",
          "source": "JobManager.java:466"
        },
        {
          "method": "java.lang.Thread.run",
          "source": "Thread.java:534"
        }
      ],
      "number": 2,
      "commentIndex": 0,
      "bugId": "103468",
      "date": "2005-07-12T12:16:46+02:00",
      "product": "CDT",
      "component": "cdt-core",
      "severity": "normal"
    },
    {
      "exceptionType": "java.lang.ClassCastException",
      "message": "org.eclipse.cdt.internal.core.dom.parser.cpp.CPPClassType$CPPClassTypeProblem",
      "elements": [
        {
          "method": "org.eclipse.cdt.internal.core.dom.parser.cpp.CPPSemantics.getLookupScope",
          "source": "CPPSemantics.java:888"
        },
        {
          "method": "org.eclipse.cdt.internal.core.dom.parser.cpp.CPPSemantics.lookup",
          "source": "CPPSemantics.java:962"
        },
        {
          "method": "org.eclipse.cdt.internal.core.dom.parser.cpp.CPPSemantics.resolveBinding",
          "source": "CPPSemantics.java:603"
        },
        {
          "method": "org.eclipse.cdt.internal.core.dom.parser.cpp.CPPVisitor.resolveBinding",
          "source": "CPPVisitor.java:924"
        },
        {
          "method": "org.eclipse.cdt.internal.core.dom.parser.cpp.CPPVisitor.createBinding",
          "source": "CPPVisitor.java:184"
        },
        {
          "method": "org.eclipse.cdt.internal.core.dom.parser.cpp.CPPASTName.resolveBinding",
          "source": "CPPASTName.java:52"
        },
        {
          "method": "org.eclipse.cdt.internal.core.index.domsourceindexer.CPPGenerateIndexVisitor.processName",
          "source": "  CPPGenerateIndexVisitor.java:148"
        },
        {
          "method": "org.eclipse.cdt.internal.core.index.domsourceindexer.CPPGenerateIndexVisitor.visit",
          "source": "  CPPGenerateIndexVisitor.java:112"
        },
        {
          "method": "org.eclipse.cdt.internal.core.dom.parser.cpp.CPPASTName.accept",
          "source": "CPPASTName.java:90"
        },
        {
          "method": "org.eclipse.cdt.internal.core.dom.parser.cpp.CPPASTFieldReference.accept",
          "source": "CPPASTFieldReference.java  :97"
        },
        {
          "method": "org.eclipse.cdt.internal.core.dom.parser.cpp.CPPASTFunctionCallExpression.accept",
          "source": "  CPPASTFunctionCallExpression.java:64"
        },
        {
          "method": "org.eclipse.cdt.internal.core.dom.parser.cpp.CPPASTBinaryExpression.accept",
          "source": "CPPASTBinaryExpression.  java:81"
        },
        {
          "method": "org.eclipse.cdt.internal.core.dom.parser.cpp.CPPASTExpressionStatement.accept",
          "source": "  CPPASTExpressionStatement.java:48"
        },
        {
          "method": "org.eclipse.cdt.internal.core.dom.parser.cpp.CPPASTCompoundStatement.accept",
          "source": "  CPPASTCompoundStatement.java:66"
        },
        {
          "method": "org.eclipse.cdt.internal.core.dom.parser.cpp.CPPASTFunctionDefinition.accept",
          "source": "  CPPASTFunctionDefinition.java:93"
        },
        {
          "method": "org.eclipse.cdt.internal.core.dom.parser.cpp.CPPASTCompositeTypeSpecifier.accept",
          "source": "  CPPASTCompositeTypeSpecifier.java:136"
        },
        {
          "method": "org.eclipse.cdt.internal.core.dom.parser.cpp.CPPASTSimpleDeclaration.accept",
          "source": "  CPPASTSimpleDeclaration.java:71"
        },
        {
          "method": "org.eclipse.cdt.internal.core.dom.parser.cpp.CPPASTTranslationUnit.accept",
          "source": "CPPASTTranslationUnit.  java:520"
        },
        {
          "method": "org.eclipse.cdt.internal.core.index.domsourceindexer.DOMSourceIndexerRunner.indexFile",
          "source": "  DOMSourceIndexerRunner.java:133"
        },
        {
          "method": "org.eclipse.cdt.internal.core.index.domsourceindexer.AbstractIndexerRunner.index",
          "source": "  AbstractIndexerRunner.java:76"
        },
        {
          "method": "org.eclipse.cdt.internal.core.index.cindexstorage.Index.add",
          "source": "Index.java:110"
        },
        {
          "method": "org.eclipse.cdt.internal.core.index.domsourceindexer.DOMAddCompilationUnitToIndex.indexDocument",
          "source": "  DOMAddCompilationUnitToIndex.java:29"
        },
        {
          "method": "org.eclipse.cdt.internal.core.index.domsourceindexer.DOMAddFileToIndex.execute",
          "source": "DOMAddFileToIndex.  java:60"
        },
        {
          "method": "org.eclipse.cdt.internal.core.search.processing.JobManager.run",
          "source": "JobManager.java:466"
        },
        {
          "method": "java.lang.Thread.run",
          "source": "Thread.java:534"
        }
      ],
      "number": 3,
      "commentIndex": 0,
      "bugId": "103468",
      "date": "2005-07-12T12:16:46+02:00",
      "product": "CDT",
      "component": "cdt-core",
      "severity": "normal"
    },
    {
      "exceptionType": "java.lang.ClassCastException",
      "message": "org.eclipse.cdt.internal.core.dom.parser.cpp.CPPClassType$CPPClassTypeProblem",
      "elements": [
        {
          "method": "org.eclipse.cdt.internal.core.dom.parser.cpp.CPPSemantics.getLookupScope",
          "source": "CPPSemantics.java:888"
        },
        {
          "method": "org.eclipse.cdt.internal.core.dom.parser.cpp.CPPSemantics.lookup",
          "source": "CPPSemantics.java:962"
        },
        {
          "method": "org.eclipse.cdt.internal.core.dom.parser.cpp.CPPSemantics.resolveBinding",
          "source": "CPPSemantics.java:603"
        },
        {
          "method": "org.eclipse.cdt.internal.core.dom.parser.cpp.CPPVisitor.resolveBinding",
          "source": "CPPVisitor.java:924"
        },
        {
          "method": "org.eclipse.cdt.internal.core.dom.parser.cpp.CPPVisitor.createBinding",
          "source": "CPPVisitor.java:184"
        },
        {
          "method": "org.eclipse.cdt.internal.core.dom.parser.cpp.CPPASTName.resolveBinding",
          "source": "CPPASTName.java:52"
        },
        {
          "method": "org.eclipse.cdt.internal.core.index.domsourceindexer.CPPGenerateIndexVisitor.processName",
          "source": "  CPPGenerateIndexVisitor.java:148"
        },
        {
          "method": "org.eclipse.cdt.internal.core.index.domsourceindexer.CPPGenerateIndexVisitor.visit",
          "source": "  CPPGenerateIndexVisitor.java:112"
        },
        {
          "method": "org.eclipse.cdt.internal.core.dom.parser.cpp.CPPASTName.accept",
          "source": "CPPASTName.java:90"
        },
        {
          "method": "org.eclipse.cdt.internal.core.dom.parser.cpp.CPPASTFieldReference.accept",
          "source": "CPPASTFieldReference.java  :97"
        },
        {
          "method": "org.eclipse.cdt.internal.core.dom.parser.cpp.CPPASTFunctionCallExpression.accept",
          "source": "  CPPASTFunctionCallExpression.java:64"
        },
        {
          "method": "org.eclipse.cdt.internal.core.dom.parser.cpp.CPPASTBinaryExpression.accept",
          "source": "CPPASTBinaryExpression.  java:81"
        },
        {
          "method": "org.eclipse.cdt.internal.core.dom.parser.cpp.CPPASTExpressionStatement.accept",
          "source": "  CPPASTExpressionStatement.java:48"
        },
        {
          "method": "org.eclipse.cdt.internal.core.dom.parser.cpp.CPPASTCompoundStatement.accept",
          "source": "  CPPASTCompoundStatement.java:66"
        },
        {
          "method": "org.eclipse.cdt.internal.core.dom.parser.cpp.CPPASTFunctionDefinition.accept",
          "source": "CPPASTFunctionDefinition.java:93"
        },
        {
          "method": "org.eclipse.cdt.internal.core.dom.parser.cpp.CPPASTCompositeTypeSpecifier.accept",
          "source": "  CPPASTCompositeTypeSpecifier.java:136"
        },
        {
          "method": "org.eclipse.cdt.internal.core.dom.parser.cpp.CPPASTSimpleDeclaration.accept",
          "source": "  CPPASTSimpleDeclaration.java:71"
        },
        {
          "method": "org.eclipse.cdt.internal.core.dom.parser.cpp.CPPASTTranslationUnit.accept",
          "source": "CPPASTTranslationUnit.  java:520"
        },
        {
          "method": "org.eclipse.cdt.internal.core.index.domsourceindexer.DOMSourceIndexerRunner.indexFile",
          "source": "  DOMSourceIndexerRunner.java:133"
        },
        {
          "method": "org.eclipse.cdt.internal.core.index.domsourceindexer.AbstractIndexerRunner.index",
          "source": "  AbstractIndexerRunner.java:76"
        },
        {
          "method": "org.eclipse.cdt.internal.core.index.cindexstorage.Index.add",
          "source": "Index.java:110"
        },
        {
          "method": "org.eclipse.cdt.internal.core.index.domsourceindexer.DOMAddCompilationUnitToIndex.indexDocument",
          "source": "  DOMAddCompilationUnitToIndex.java:29"
        },
        {
          "method": "org.eclipse.cdt.internal.core.index.domsourceindexer.DOMAddFileToIndex.execute",
          "source": "DOMAddFileToIndex.  java:60"
        },
        {
          "method": "org.eclipse.cdt.internal.core.search.processing.JobManager.run",
          "source": "JobManager.java:466"
        },
        {
          "method": "java.lang.Thread.run",
          "source": "Thread.java:534"
        }
      ],
      "number": 4,
      "commentIndex": 0,
      "bugId": "103468",
      "date": "2005-07-12T12:16:46+02:00",
      "product": "CDT",
      "component": "cdt-core",
      "severity": "normal"
    },
    {
      "exceptionType": "eclipseLinuxjava.lang.ClassCastException",
      "message": "org.eclipse.cdt.internal.core.dom.parser.cpp.  CPPClassType$CPPClassTypeProblem",
      "elements": [
        {
          "method": "org.eclipse.cdt.internal.core.dom.parser.cpp.CPPSemantics.getLookupScope",
          "source": "CPPSemantics.java:888"
        },
        {
          "method": "org.eclipse.cdt.internal.core.dom.parser.cpp.CPPSemantics.lookup",
          "source": "CPPSemantics.java:962"
        },
        {
          "method": "org.eclipse.cdt.internal.core.dom.parser.cpp.CPPSemantics.resolveBinding",
          "source": "CPPSemantics.java:603"
        },
        {
          "method": "org.eclipse.cdt.internal.core.dom.parser.cpp.CPPVisitor.resolveBinding",
          "source": "CPPVisitor.java:924"
        },
        {
          "method": "org.eclipse.cdt.internal.core.dom.parser.cpp.CPPVisitor.createBinding",
          "source": "CPPVisitor.java:184"
        },
        {
          "method": "org.eclipse.cdt.internal.core.dom.parser.cpp.CPPASTName.resolveBinding",
          "source": "CPPASTName.java:52"
        },
        {
          "method": "org.eclipse.cdt.internal.core.index.domsourceindexer.CPPGenerateIndexVisitor.processName",
          "source": "  CPPGenerateIndexVisitor.java:148"
        },
        {
          "method": "org.eclipse.cdt.internal.core.index.domsourceindexer.CPPGenerateIndexVisitor.visit",
          "source": "  CPPGenerateIndexVisitor.java:112"
        },
        {
          "method": "org.eclipse.cdt.internal.core.dom.parser.cpp.CPPASTName.accept",
          "source": "CPPASTName.java:90"
        },
        {
          "method": "org.eclipse.cdt.internal.core.dom.parser.cpp.CPPASTFieldReference.accept",
          "source": "CPPASTFieldReference.java  :97"
        },
        {
          "method": "org.eclipse.cdt.internal.core.dom.parser.cpp.CPPASTFunctionCallExpression.accept",
          "source": "  CPPASTFunctionCallExpression.java:64"
        },
        {
          "method": "org.eclipse.cdt.internal.core.dom.parser.cpp.CPPASTBinaryExpression.accept",
          "source": "CPPASTBinaryExpression.  java:81"
        },
        {
          "method": "org.eclipse.cdt.internal.core.dom.parser.cpp.CPPASTExpressionStatement.accept",
          "source": "  CPPASTExpressionStatement.java:48"
        },
        {
          "method": "org.eclipse.cdt.internal.core.dom.parser.cpp.CPPASTCompoundStatement.accept",
          "source": "CPPASTCompoundStatement.  java:66"
        },
        {
          "method": "org.eclipse.cdt.internal.core.dom.parser.cpp.CPPASTFunctionDefinition.accept",
          "source": "  CPPASTFunctionDefinition.java:93"
        },
        {
          "method": "org.eclipse.cdt.internal.core.dom.parser.cpp.CPPASTCompositeTypeSpecifier.accept",
          "source": "  CPPASTCompositeTypeSpecifier.java:136"
        },
        {
          "method": "org.eclipse.cdt.internal.core.dom.parser.cpp.CPPASTSimpleDeclaration.accept",
          "source": "  CPPASTSimpleDeclaration.java:71"
        },
        {
          "method": "org.eclipse.cdt.internal.core.dom.parser.cpp.CPPASTTranslationUnit.accept",
          "source": "CPPASTTranslationUnit.  java:520"
        },
        {
          "method": "org.eclipse.cdt.internal.core.index.domsourceindexer.DOMSourceIndexerRunner.indexFile",
          "source": "  DOMSourceIndexerRunner.java:133"
        },
        {
          "method": "org.eclipse.cdt.internal.core.index.domsourceindexer.AbstractIndexerRunner.index",
          "source": "  AbstractIndexerRunner.java:76"
        },
        {
          "method": "org.eclipse.cdt.internal.core.index.cindexstorage.Index.add",
          "source": "Index.java:110"
        },
        {
          "method": "org.eclipse.cdt.internal.core.index.domsourceindexer.DOMAddCompilationUnitToIndex.indexDocument",
          "source": "  DOMAddCompilationUnitToIndex.java:29"
        },
        {
          "method": "org.eclipse.cdt.internal.core.index.domsourceindexer.DOMAddFileToIndex.execute",
          "source": "DOMAddFileToIndex.  java:60"
        },
        {
          "method": "org.eclipse.cdt.internal.core.search.processing.JobManager.run",
          "source": "JobManager.java:466"
        },
        {
          "method": "java.lang.Thread.run",
          "source": "Thread.java:534"
        }
      ],
      "number": 5,
      "commentIndex": 0,
      "bugId": "103468",
      "date": "2005-07-12T12:16:46+02:00",
      "product": "CDT",
      "component": "cdt-core",
      "severity": "normal"
    }
  ],
  "groupId": "103468",
  "bugId": "103468",
  "date": "2005-07-12T12:16:46+02:00",
  "product": "CDT",
  "component": "cdt-core",
  "severity": "normal"
}