{
  "comments": [
    "Eclipse refuses to start and logs: \n \n!SESSION 2005-07-13 13:50:38.742 \n----------------------------------------------- \neclipse.buildId\u003dI20050627-1435 \njava.fullversion\u003dJ2RE 1.4.2 IBM build cxp641420ifx-20040722 (142GA+75755) (JIT \ne \nnabled: jitc) \nBootLoader constants: OS\u003dlinux, ARCH\u003dppc, WS\u003dgtk, NL\u003den_US \nCommand-line arguments:  -os linux -ws gtk -arch ppc \n \n!ENTRY org.eclipse.osgi 2005-07-13 13:50:40.775 \n!MESSAGE Application error \n!STACK 1 \njava.lang.UnsatisfiedLinkError: /suse/skh/eclipse-ppc/eclipse/configuration/org. \neclipse.osgi/bundles/71/1/.cp/libswt-pi-gtk-3138.so: /suse/skh/eclipse-ppc/eclip \nse/configuration/org.eclipse.osgi/bundles/71/1/.cp/libswt-pi-gtk-3138.so: \ncannot \n open shared object file: No such file or directory \n        at java.lang.ClassLoader$NativeLibrary.load(Native Method) \n        at java.lang.ClassLoader.loadLibrary0(ClassLoader.java:2120) \n        at java.lang.ClassLoader.loadLibrary(ClassLoader.java:1968) \n        at java.lang.Runtime.loadLibrary0(Runtime.java:824) \n        at java.lang.System.loadLibrary(System.java:908) \n        at org.eclipse.swt.internal.Library.loadLibrary(Library.java:123) \n        at org.eclipse.swt.internal.gtk.OS.\u003cclinit\u003e(OS.java:19) \n        at org.eclipse.swt.internal.Converter.wcsToMbcs(Converter.java:63) \n        at org.eclipse.swt.internal.Converter.wcsToMbcs(Converter.java:54) \n        at org.eclipse.swt.widgets.Display.\u003cclinit\u003e(Display.java:122) \n        at org.eclipse.ui.internal.Workbench.createDisplay(Workbench.java:381) \n        at org.eclipse.ui.PlatformUI.createDisplay(PlatformUI.java:155) \n        at \norg.eclipse.ui.internal.ide.IDEApplication.createDisplay(IDEApplicati \non.java:128) \n        at \norg.eclipse.ui.internal.ide.IDEApplication.run(IDEApplication.java:79 \n) \n        at \norg.eclipse.core.internal.runtime.PlatformActivator$1.run(PlatformAct \nivator.java:226) \n        at \norg.eclipse.core.runtime.adaptor.EclipseStarter.run(EclipseStarter.ja \nva:376) \n        at \norg.eclipse.core.runtime.adaptor.EclipseStarter.run(EclipseStarter.ja \nva:163) \n        at sun.reflect.NativeMethodAccessorImpl.invoke0(Native Method) \n        at \nsun.reflect.NativeMethodAccessorImpl.invoke(NativeMethodAccessorImpl. \njava:85) \n        at \nsun.reflect.NativeMethodAccessorImpl.invoke(NativeMethodAccessorImpl. \njava:58) \n        at \nsun.reflect.DelegatingMethodAccessorImpl.invoke(DelegatingMethodAcces \nsorImpl.java:60) \n        at java.lang.reflect.Method.invoke(Method.java:391) \n        at org.eclipse.core.launcher.Main.invokeFramework(Main.java:334) \n        at org.eclipse.core.launcher.Main.basicRun(Main.java:278) \n        at org.eclipse.core.launcher.Main.run(Main.java:973) \n        at org.eclipse.core.launcher.Main.main(Main.java:948) \n \nThe file exists: \nskh@xxxxxxxx:~/eclipse-ppc/eclipse\u003e ls -l \nconfiguration/org.eclipse.osgi/bundles/71/1/.cp/libswt-pi-gtk-3138.so \n-rw-r--r--  1 skh suse 319964 2005-07-13 13:44 \nconfiguration/org.eclipse.osgi/bundles/71/1/.cp/libswt-pi-gtk-3138.so \n \nThis happens both with the binary distribution \n(eclipse-SDK-3.1-linux-gtk-ppc.tar.gz downloaded today, 2005-07-13) and with a \nversion compiled from the 3.1 final source zip.",
    "What is the output of this command:\n\n\u0027ldd\n/suse/skh/eclipse-ppc/eclipse/configuration/org.eclipse.osgi/bundles/71/1/.cp/libswt-pi-gtk-3138.so\u0027",
    " \nskh@xxxxxxxx:~\u003e \nldd /suse/skh/eclipse-ppc/eclipse/configuration/org.eclipse.osgi/ \nbundles/71/1/.cp/libswt-pi-gtk-3138.so \nldd: warning: you do not have execution permission for \n`/suse/skh/eclipse-ppc/eclipse/configuration/org.eclipse.osgi/bundles/71/1/.cp/libswt-pi-gtk-3138.so\u0027 \n        libgtk-x11-2.0.so.0 \u003d\u003e /opt/gnome/lib/libgtk-x11-2.0.so.0 (0x6fcd4000) \n        libgthread-2.0.so.0 \u003d\u003e /opt/gnome/lib/libgthread-2.0.so.0 (0x6fcaf000) \n        libXtst.so.6 \u003d\u003e /usr/X11R6/lib/libXtst.so.6 (0x6fc88000) \n        libc.so.6 \u003d\u003e /lib/tls/libc.so.6 (0x6fb41000) \n        libgdk_pixbuf-2.0.so.0 \u003d\u003e /opt/gnome/lib/libgdk_pixbuf-2.0.so.0 \n(0x6fb0c000) \n        libgdk-x11-2.0.so.0 \u003d\u003e /opt/gnome/lib/libgdk-x11-2.0.so.0 (0x6fa70000) \n        libX11.so.6 \u003d\u003e /usr/X11R6/lib/libX11.so.6 (0x6f941000) \n        libpangoxft-1.0.so.0 \u003d\u003e /opt/gnome/lib/libpangoxft-1.0.so.0 \n(0x6f900000) \n        libpangox-1.0.so.0 \u003d\u003e /opt/gnome/lib/libpangox-1.0.so.0 (0x6f8d2000) \n        libpango-1.0.so.0 \u003d\u003e /opt/gnome/lib/libpango-1.0.so.0 (0x6f878000) \n        libatk-1.0.so.0 \u003d\u003e /opt/gnome/lib/libatk-1.0.so.0 (0x6f837000) \n        libgobject-2.0.so.0 \u003d\u003e /opt/gnome/lib/libgobject-2.0.so.0 (0x6f7d9000) \n        libgmodule-2.0.so.0 \u003d\u003e /opt/gnome/lib/libgmodule-2.0.so.0 (0x6f7b5000) \n        libdl.so.2 \u003d\u003e /lib/libdl.so.2 (0x6f792000) \n        libglib-2.0.so.0 \u003d\u003e /opt/gnome/lib/libglib-2.0.so.0 (0x6f6f8000) \n        libm.so.6 \u003d\u003e /lib/tls/libm.so.6 (0x6f663000) \n        libpthread.so.0 \u003d\u003e /lib/tls/libpthread.so.0 (0x6f640000) \n        libXext.so.6 \u003d\u003e /usr/X11R6/lib/libXext.so.6 (0x6f60d000) \n        /lib/ld.so.1 \u003d\u003e /lib/ld.so.1 (0x08000000) \n        libXrandr.so.2 \u003d\u003e /usr/X11R6/lib/libXrandr.so.2 (0x6f5e9000) \n        libXi.so.6 \u003d\u003e /usr/X11R6/lib/libXi.so.6 (0x6f5bf000) \n        libXft.so.2 \u003d\u003e /usr/X11R6/lib/libXft.so.2 (0x6f58b000) \n        libXrender.so.1 \u003d\u003e /usr/X11R6/lib/libXrender.so.1 (0x6f561000) \n        libfontconfig.so.1 \u003d\u003e /usr/lib/libfontconfig.so.1 (0x6f510000) \n        libfreetype.so.6 \u003d\u003e /usr/lib/libfreetype.so.6 (0x6f47b000) \n        libexpat.so.0 \u003d\u003e /usr/lib/libexpat.so.0 (0x6f435000) \n \n(The file is copied as non-executable there by eclipse. Making it executable \ndoesn\u0027t change the original error, I had already checked that.) \n \n \n ",
    "Linux doesn\u0027t require that shared libraries be marked executable (although I\nthought for sure the osgi stuff did so, I\u0027ll look into that).\n\nThe error \"No such file or directory\" when the library exists usually occurs\nbecause a dependency cannot be found, so I expected to see some unsatisfied link\nerrors.  It looks like everything is found though.  Are you maybe using a 64-bit\nVM, but using a 32-bit eclipse?  This would cause it to use a different runtime\nlinker...",
    "Yes, it is. I called it with powerpc32 so I thought it wouldn\u0027t matter, but  \nthe VM of course stays 64bit.  \n  \nI guess this is INVALID, then? \n \n ",
    "Do you have a 32 bit VM to try with?  Is Eclipse working for you yet? :)\n\nI am not as familiar with the ppc systems.  For x86-64, some users have both 32\nbit and 64 bit versions of GTK+ installed, and can use either the 64 or 32 bit\nversions of Eclipse.  The application, VM, and libraries all must be the same\nfor things to work.  Bug 73839 is requesting that we do a build of Eclipse for\n64 bit PPC.  I am not sure how common this is, it seems that most Linux-PPC\ndistros are 32 bit.\n\nThoughts?",
    "With a 32bit VM the binary version is working.  \n  \nThanks for your help. "
  ],
  "commentCreationDates": [
    "2005-07-13T13:59:18+02:00",
    "2005-07-13T14:49:24+02:00",
    "2005-07-13T15:18:36+02:00",
    "2005-07-13T17:45:29+02:00",
    "2005-07-13T17:51:49+02:00",
    "2005-07-13T18:21:23+02:00",
    "2005-07-14T12:24:08+02:00"
  ],
  "traces": [
    {
      "exceptionType": "java.lang.UnsatisfiedLinkError",
      "message": "/suse/skh/eclipse-ppc/eclipse/configuration/org.  eclipse.osgi/bundles/71/1/.cp/libswt-pi-gtk-3138.so: /suse/skh/eclipse-ppc/eclip  se/configuration/org.eclipse.osgi/bundles/71/1/.cp/libswt-pi-gtk-3138.so:  cannot   open shared object file: No such file or directory",
      "elements": [
        {
          "method": "java.lang.ClassLoader$NativeLibrary.load",
          "source": "Native Method"
        },
        {
          "method": "java.lang.ClassLoader.loadLibrary0",
          "source": "ClassLoader.java:2120"
        },
        {
          "method": "java.lang.ClassLoader.loadLibrary",
          "source": "ClassLoader.java:1968"
        },
        {
          "method": "java.lang.Runtime.loadLibrary0",
          "source": "Runtime.java:824"
        },
        {
          "method": "java.lang.System.loadLibrary",
          "source": "System.java:908"
        },
        {
          "method": "org.eclipse.swt.internal.Library.loadLibrary",
          "source": "Library.java:123"
        },
        {
          "method": "org.eclipse.swt.internal.gtk.OS.\u003cclinit\u003e",
          "source": "OS.java:19"
        },
        {
          "method": "org.eclipse.swt.internal.Converter.wcsToMbcs",
          "source": "Converter.java:63"
        },
        {
          "method": "org.eclipse.swt.internal.Converter.wcsToMbcs",
          "source": "Converter.java:54"
        },
        {
          "method": "org.eclipse.swt.widgets.Display.\u003cclinit\u003e",
          "source": "Display.java:122"
        },
        {
          "method": "org.eclipse.ui.internal.Workbench.createDisplay",
          "source": "Workbench.java:381"
        },
        {
          "method": "org.eclipse.ui.PlatformUI.createDisplay",
          "source": "PlatformUI.java:155"
        },
        {
          "method": "org.eclipse.ui.internal.ide.IDEApplication.createDisplay",
          "source": "IDEApplicati  on.java:128"
        },
        {
          "method": "org.eclipse.ui.internal.ide.IDEApplication.run",
          "source": "IDEApplication.java:79  "
        },
        {
          "method": "org.eclipse.core.internal.runtime.PlatformActivator$1.run",
          "source": "PlatformAct  ivator.java:226"
        },
        {
          "method": "org.eclipse.core.runtime.adaptor.EclipseStarter.run",
          "source": "EclipseStarter.ja  va:376"
        },
        {
          "method": "org.eclipse.core.runtime.adaptor.EclipseStarter.run",
          "source": "EclipseStarter.ja  va:163"
        },
        {
          "method": "sun.reflect.NativeMethodAccessorImpl.invoke0",
          "source": "Native Method"
        },
        {
          "method": "sun.reflect.NativeMethodAccessorImpl.invoke",
          "source": "NativeMethodAccessorImpl.  java:85"
        },
        {
          "method": "sun.reflect.NativeMethodAccessorImpl.invoke",
          "source": "NativeMethodAccessorImpl.  java:58"
        },
        {
          "method": "sun.reflect.DelegatingMethodAccessorImpl.invoke",
          "source": "DelegatingMethodAcces  sorImpl.java:60"
        },
        {
          "method": "java.lang.reflect.Method.invoke",
          "source": "Method.java:391"
        },
        {
          "method": "org.eclipse.core.launcher.Main.invokeFramework",
          "source": "Main.java:334"
        },
        {
          "method": "org.eclipse.core.launcher.Main.basicRun",
          "source": "Main.java:278"
        },
        {
          "method": "org.eclipse.core.launcher.Main.run",
          "source": "Main.java:973"
        },
        {
          "method": "org.eclipse.core.launcher.Main.main",
          "source": "Main.java:948"
        }
      ],
      "number": 0,
      "commentIndex": 0,
      "bugId": "103640",
      "date": "2005-07-13T13:59:18+02:00",
      "product": "Platform",
      "component": "SWT",
      "severity": "major"
    }
  ],
  "groupId": "103640",
  "bugId": "103640",
  "date": "2005-07-13T13:59:18+02:00",
  "product": "Platform",
  "component": "SWT",
  "severity": "major"
}