{
  "comments": [
    "Running Ant build for J2ME project crashes while calling Antenna(0.9.13)\nwtkpreverify. Runs without error when executed from cmd line via Ant directly.\n\nStack trace (from console when Eclipse started from cmd line):\n\nException in thread \"Ant Build Server Connection\"\njava.lang.StringIndexOutOfBoundsException: String index out of range: -1\n        at java.lang.String.substring(String.java:1768)\n        at org.eclipse.ant.internal.ui.AntUtil.getLocationLink(AntUtil.java:491)\n        at\norg.eclipse.ant.internal.ui.launchConfigurations.RemoteAntBuildListener.generateLink(RemoteAntBuildListener.java:255)\n        at\norg.eclipse.ant.internal.ui.launchConfigurations.RemoteAntBuildListener.receiveTaskMessage(RemoteAntBuildListener.java:243)\n        at\norg.eclipse.ant.internal.ui.launchConfigurations.RemoteAntBuildListener.receiveMessage(RemoteAntBuildListener.java:173)\n        at\norg.eclipse.ant.internal.ui.launchConfigurations.RemoteAntBuildListener$ServerConnection.run(RemoteAntBuildListener.java:104)",
    "Moving to Platform/Ant.",
    "\n\n*** This bug has been marked as a duplicate of 102300 ***"
  ],
  "commentCreationDates": [
    "2005-07-18T15:55:16+02:00",
    "2005-07-18T18:48:44+02:00",
    "2005-07-18T19:06:58+02:00"
  ],
  "traces": [
    {
      "exceptionType": "java.lang.StringIndexOutOfBoundsException",
      "message": "String index out of range: -1",
      "elements": [
        {
          "method": "java.lang.String.substring",
          "source": "String.java:1768"
        },
        {
          "method": "org.eclipse.ant.internal.ui.AntUtil.getLocationLink",
          "source": "AntUtil.java:491"
        },
        {
          "method": "org.eclipse.ant.internal.ui.launchConfigurations.RemoteAntBuildListener.generateLink",
          "source": "RemoteAntBuildListener.java:255"
        },
        {
          "method": "org.eclipse.ant.internal.ui.launchConfigurations.RemoteAntBuildListener.receiveTaskMessage",
          "source": "RemoteAntBuildListener.java:243"
        },
        {
          "method": "org.eclipse.ant.internal.ui.launchConfigurations.RemoteAntBuildListener.receiveMessage",
          "source": "RemoteAntBuildListener.java:173"
        },
        {
          "method": "org.eclipse.ant.internal.ui.launchConfigurations.RemoteAntBuildListener$ServerConnection.run",
          "source": "RemoteAntBuildListener.java:104"
        }
      ],
      "number": 0,
      "commentIndex": 0,
      "bugId": "104217",
      "duplicateId": "102300",
      "date": "2005-07-18T15:55:16+02:00",
      "product": "Platform",
      "component": "Ant",
      "severity": "critical"
    }
  ],
  "groupId": "102300",
  "bugId": "104217",
  "duplicateId": "102300",
  "date": "2005-07-18T15:55:16+02:00",
  "product": "Platform",
  "component": "Ant",
  "severity": "critical"
}