{
  "comments": [
    "Cannot bring up the create EJB wizard from the context menu on the bean, or from\nNEW menu, ie, new-\u003eOther-\u003eEJB-Enterprise Java Bean (RAD)\n\nI can bring it up from the DD Editor, by clicking ADD bean.\nHere is the stack trace:\n\njava.lang.NoClassDefFoundError: org.eclipse.jst.common.internal.annotations.cont\nroller.AnnotationsControllerManager\n        at org.eclipse.jst.j2ee.internal.wizard.AnnotationsStandaloneGroup.setEn\nablement(AnnotationsStandaloneGroup.java:171)\n        at com.ibm.etools.ejb.creation.model.wizard.EJBBasicPropertiesComposite.\ncreateAnnotationsGroup(EJBBasicPropertiesComposite.java:142)\n        at com.ibm.etools.ejb.creation.model.wizard.EJBBasicPropertiesComposite.\ncreateContents(EJBBasicPropertiesComposite.java:82)\n        at com.ibm.etools.ejb.creation.model.wizard.EJBBasicPropertiesComposite.\n\u003cinit\u003e(EJBBasicPropertiesComposite.java:70)\n        at com.ibm.etools.ejb.creation.model.wizard.EJBTypeSelectionPage.createN\namesComposite(EJBTypeSelectionPage.java:200)\n        at com.ibm.etools.ejb.creation.model.wizard.EJBTypeSelectionPage.createT\nopLevelComposite(EJBTypeSelectionPage.java:173)\n        at org.eclipse.wst.common.frameworks.internal.datamodel.ui.DataModelWiza\nrdPage.createControl(DataModelWizardPage.java:91)\n        at org.eclipse.wst.common.frameworks.internal.datamodel.ui.DataModelWiza\nrd.createPageControls(DataModelWizard.java:83)\n        at org.eclipse.jface.wizard.WizardDialog.createPageControls(WizardDialog\n.java:611)\n        at org.eclipse.jface.wizard.WizardDialog.setWizard(WizardDialog.java:965\n)\n        at org.eclipse.jface.wizard.WizardDialog.updateForPage(WizardDialog.java\n:1016)\n        at org.eclipse.jface.wizard.WizardDialog.access$2(WizardDialog.java:1013\n)\n        at org.eclipse.jface.wizard.WizardDialog$4.run(WizardDialog.java:1003)\n        at org.eclipse.swt.custom.BusyIndicator.showWhile(BusyIndicator.java:69)\n\n        at org.eclipse.jface.wizard.WizardDialog.showPage(WizardDialog.java:1001\n)\n        at org.eclipse.jface.wizard.WizardDialog.nextPressed(WizardDialog.java:7\n53)\n        at org.eclipse.jface.wizard.WizardDialog.buttonPressed(WizardDialog.java\n:345)\n        at org.eclipse.jface.dialogs.Dialog$2.widgetSelected(Dialog.java:556)\n        at org.eclipse.swt.widgets.TypedListener.handleEvent(TypedListener.java:\n90)\n        at org.eclipse.swt.widgets.EventTable.sendEvent(EventTable.java:66)\n        at org.eclipse.swt.widgets.Widget.sendEvent(Widget.java:843)\n        at org.eclipse.swt.widgets.Display.runDeferredEvents(Display.java:3080)\n        at org.eclipse.swt.widgets.Display.readAndDispatch(Display.java:2713)\n        at org.eclipse.jface.window.Window.runEventLoop(Window.java:809)\n        at org.eclipse.jface.window.Window.open(Window.java:787)\n        at org.eclipse.ui.actions.NewWizardAction.run(NewWizardAction.java:181)\n        at org.eclipse.jface.action.Action.runWithEvent(Action.java:996)\n        at org.eclipse.jface.action.ActionContributionItem.handleWidgetSelection",
    "Please open product specific defects on IBM\u0027s product bug tracking system",
    "Closing."
  ],
  "commentCreationDates": [
    "2005-07-18T20:53:50+02:00",
    "2005-07-18T22:01:23+02:00",
    "2006-09-26T16:03:37+02:00"
  ],
  "traces": [
    {
      "exceptionType": "java.lang.NoClassDefFoundError",
      "message": "org.eclipse.jst.common.internal.annotations.cont roller.AnnotationsControllerManager",
      "elements": [
        {
          "method": "org.eclipse.jst.j2ee.internal.wizard.AnnotationsStandaloneGroup.setEnablement",
          "source": "AnnotationsStandaloneGroup.java:171"
        },
        {
          "method": "com.ibm.etools.ejb.creation.model.wizard.EJBBasicPropertiesComposite.createAnnotationsGroup",
          "source": "EJBBasicPropertiesComposite.java:142"
        },
        {
          "method": "com.ibm.etools.ejb.creation.model.wizard.EJBBasicPropertiesComposite.createContents",
          "source": "EJBBasicPropertiesComposite.java:82"
        },
        {
          "method": "com.ibm.etools.ejb.creation.model.wizard.EJBBasicPropertiesComposite.\u003cinit\u003e",
          "source": "EJBBasicPropertiesComposite.java:70"
        },
        {
          "method": "com.ibm.etools.ejb.creation.model.wizard.EJBTypeSelectionPage.createNamesComposite",
          "source": "EJBTypeSelectionPage.java:200"
        },
        {
          "method": "com.ibm.etools.ejb.creation.model.wizard.EJBTypeSelectionPage.createTopLevelComposite",
          "source": "EJBTypeSelectionPage.java:173"
        },
        {
          "method": "org.eclipse.wst.common.frameworks.internal.datamodel.ui.DataModelWizardPage.createControl",
          "source": "DataModelWizardPage.java:91"
        },
        {
          "method": "org.eclipse.wst.common.frameworks.internal.datamodel.ui.DataModelWizard.createPageControls",
          "source": "DataModelWizard.java:83"
        },
        {
          "method": "org.eclipse.jface.wizard.WizardDialog.createPageControls",
          "source": "WizardDialog .java:611"
        },
        {
          "method": "org.eclipse.jface.wizard.WizardDialog.setWizard",
          "source": "WizardDialog.java:965 "
        },
        {
          "method": "org.eclipse.jface.wizard.WizardDialog.updateForPage",
          "source": "WizardDialog.java :1016"
        },
        {
          "method": "org.eclipse.jface.wizard.WizardDialog.access$2",
          "source": "WizardDialog.java:1013 "
        },
        {
          "method": "org.eclipse.jface.wizard.WizardDialog$4.run",
          "source": "WizardDialog.java:1003"
        },
        {
          "method": "org.eclipse.swt.custom.BusyIndicator.showWhile",
          "source": "BusyIndicator.java:69"
        },
        {
          "method": "org.eclipse.jface.wizard.WizardDialog.showPage",
          "source": "WizardDialog.java:1001 "
        },
        {
          "method": "org.eclipse.jface.wizard.WizardDialog.nextPressed",
          "source": "WizardDialog.java:7 53"
        },
        {
          "method": "org.eclipse.jface.wizard.WizardDialog.buttonPressed",
          "source": "WizardDialog.java :345"
        },
        {
          "method": "org.eclipse.jface.dialogs.Dialog$2.widgetSelected",
          "source": "Dialog.java:556"
        },
        {
          "method": "org.eclipse.swt.widgets.TypedListener.handleEvent",
          "source": "TypedListener.java: 90"
        },
        {
          "method": "org.eclipse.swt.widgets.EventTable.sendEvent",
          "source": "EventTable.java:66"
        },
        {
          "method": "org.eclipse.swt.widgets.Widget.sendEvent",
          "source": "Widget.java:843"
        },
        {
          "method": "org.eclipse.swt.widgets.Display.runDeferredEvents",
          "source": "Display.java:3080"
        },
        {
          "method": "org.eclipse.swt.widgets.Display.readAndDispatch",
          "source": "Display.java:2713"
        },
        {
          "method": "org.eclipse.jface.window.Window.runEventLoop",
          "source": "Window.java:809"
        },
        {
          "method": "org.eclipse.jface.window.Window.open",
          "source": "Window.java:787"
        },
        {
          "method": "org.eclipse.ui.actions.NewWizardAction.run",
          "source": "NewWizardAction.java:181"
        },
        {
          "method": "org.eclipse.jface.action.Action.runWithEvent",
          "source": "Action.java:996"
        }
      ],
      "number": 0,
      "commentIndex": 0,
      "bugId": "104258",
      "date": "2005-07-18T20:53:50+02:00",
      "product": "Web Tools",
      "component": "jst.j2ee",
      "severity": "blocker"
    }
  ],
  "groupId": "104258",
  "bugId": "104258",
  "date": "2005-07-18T20:53:50+02:00",
  "product": "Web Tools",
  "component": "jst.j2ee",
  "severity": "blocker"
}