{
  "comments": [
    "Hello All,\n\n \n\nI did the Data Set operation, tested the connection also.  It works fine.\n\n \n\nWhile editing Data Source, I did preview the results to make sure that data is\nfetched from the database and it works great.\n\n \n\nBut when I try preview the reportdesign, it throws error saying:\n\n \n\nError0 : odaconsumer.CannotOpenConnection(1 time)\n\ndetail: Cannot open the connection for the driver\n(org.eclipse.birt.report.data.oda.jdbc).\n\nFailed to get Connection\n\nFailed to start database\n\u0027D:\\rajesh.gheware\\projects\\automatedbuild\\build\\I.TestBuild\\Arena\\db\\networkManager\u0027,\nsee the next exception for details.\n\nFailed to get Connection\n\nFailed to start database\n\u0027D:\\rajesh.gheware\\projects\\automatedbuild\\build\\I.TestBuild\\Arena\\db\\networkManager\u0027,\nsee the next exception for details.\n\nFailed to start database\n\u0027D:\\rajesh.gheware\\projects\\automatedbuild\\build\\I.TestBuild\\Arena\\db\\networkManager\u0027,\nsee the next exception for details.\n\n \n\n \n\n \n\nWhen I try to peak into\n?\\eclipse\\plugins\\org.eclipse.birt.report.viewer_1.0.0\\birt\\logs directory, I\nsee the following:\n\nJul 13, 2005 8:00:00 PM org.eclipse.birt.core.util.BirtTimer logTimeTaken\n\nINFO: Engine startup takes 566 Milliseconds.\n\nJul 13, 2005 8:00:01 PM org.eclipse.birt.data.engine.impl.DataEngineImpl \u003cinit\u003e\n\nINFO: Data Engine starts up\n\nJul 13, 2005 8:00:01 PM org.eclipse.birt.data.engine.impl.DataEngineImpl \u003cinit\u003e\n\nINFO: Data Engine starts up\n\nJul 13, 2005 8:00:01 PM\norg.eclipse.birt.report.engine.content.impl.MasterPageContent initSimpleMasterPage\n\nINFO: The property HeaderHeight is not set. Use Default 1 cm.\n\nJul 13, 2005 8:00:01 PM\norg.eclipse.birt.report.engine.content.impl.MasterPageContent initSimpleMasterPage\n\nINFO: The property FooterHeight is not set. Use default 1 cm.\n\nJul 13, 2005 8:00:01 PM org.eclipse.birt.report.data.oda.jdbc.JDBCDriverManager\nloadDriverExtensions\n\nINFO: Found JDBC driverinfo extension: driverClass\u003dsun.jdbc.odbc.JdbcOdbcDriver,\nconnectionFactory\u003dnull\n\nJul 13, 2005 8:00:01 PM org.eclipse.birt.report.data.oda.jdbc.JDBCDriverManager\nloadDriverExtensions\n\nINFO: Found JDBC driverinfo extension:\ndriverClass\u003dorg.apache.derby.jdbc.EmbeddedDriver, connectionFactory\u003dnull\n\nJul 13, 2005 8:00:01 PM org.eclipse.birt.report.data.oda.jdbc.JDBCDriverManager\nloadAndRegisterDriver\n\nINFO: Loading JDBC driver class: org.apache.derby.jdbc.EmbeddedDriver\n\nJul 13, 2005 8:00:01 PM org.eclipse.birt.report.data.oda.jdbc.JDBCDriverManager\nloadAndRegisterDriver\n\nINFO: Loaded JDBC driver class in class path: org.apache.derby.jdbc.EmbeddedDriver\n\nJul 13, 2005 8:00:01 PM\norg.eclipse.birt.data.engine.odaconsumer.ConnectionManager openConnection\n\nSEVERE: Cannot open connection.\n\norg.eclipse.birt.report.data.oda.jdbc.JDBCException: Failed to get Connection\n\nFailed to start database\n\u0027D:\\rajesh.gheware\\projects\\automatedbuild\\build\\I.TestBuild\\Arena\\db\\networkManager\u0027,\nsee the next exception for details.\n\n            at\norg.eclipse.birt.report.data.oda.jdbc.Connection.connectByUrl(Connection.java:223)\n\n            at\norg.eclipse.birt.report.data.oda.jdbc.Connection.open(Connection.java:179)\n\n            at\norg.eclipse.birt.data.engine.odaconsumer.manager.OdaConnection.open(OdaConnection.java:221)\n\n            at\norg.eclipse.birt.data.engine.odaconsumer.ConnectionManager.openConnection(ConnectionManager.java:89)\n\n            at\norg.eclipse.birt.data.engine.executor.DataSource.newConnection(DataSource.java:147)\n\n            at\norg.eclipse.birt.data.engine.executor.DataSource.open(DataSource.java:140)\n\n            at\norg.eclipse.birt.data.engine.impl.DataSourceRuntime.openOdiDataSource(DataSourceRuntime.java:137)\n\n            at\norg.eclipse.birt.data.engine.impl.PreparedQuery$Executor.openDataSource(PreparedQuery.java:642)\n\n            at\norg.eclipse.birt.data.engine.impl.PreparedQuery$Executor.prepareExecution(PreparedQuery.java:454)\n\n            at\norg.eclipse.birt.data.engine.impl.PreparedQuery$Executor.access$000(PreparedQuery.java:379)\n\n            at\norg.eclipse.birt.data.engine.impl.PreparedQuery.doPrepare(PreparedQuery.java:171)\n\n            at\norg.eclipse.birt.data.engine.impl.PreparedDataSourceQuery.execute(PreparedDataSourceQuery.java:137)\n\n            at\norg.eclipse.birt.report.engine.data.dte.DteDataEngine.execute(DteDataEngine.java:216)\n\n            at\norg.eclipse.birt.report.engine.executor.ReportItemExecutor.openResultSet(ReportItemExecutor.java:140)\n\n            at\norg.eclipse.birt.report.engine.executor.ListItemExecutor.execute(ListItemExecutor.java:79)\n\n            at\norg.eclipse.birt.report.engine.executor.ReportExecutorVisitor.visitListItem(ReportExecutorVisitor.java:256)\n\n            at\norg.eclipse.birt.report.engine.ir.ListItemDesign.accept(ListItemDesign.java:151)\n\n            at\norg.eclipse.birt.report.engine.executor.ReportExecutor.execute(ReportExecutor.java:163)\n\n            at\norg.eclipse.birt.report.engine.api.impl.RunAndRenderTask.run(RunAndRenderTask.java:152)\n\n            at\norg.eclipse.birt.report.viewer.aggregation.layout.EngineFragment.doService(Unknown\nSource)\n\n            at\norg.eclipse.birt.report.viewer.aggregation.BaseFragment.service(Unknown Source)\n\n            at\norg.eclipse.birt.report.viewer.servlets.ViewerServlet.doPost(Unknown Source)\n\n            at\norg.eclipse.birt.report.viewer.servlets.ViewerServlet.doGet(Unknown Source)\n\n            at javax.servlet.http.HttpServlet.service(HttpServlet.java:740)\n\n            at javax.servlet.http.HttpServlet.service(HttpServlet.java:853)\n\n            at\norg.apache.catalina.core.ApplicationFilterChain.internalDoFilter(ApplicationFilterChain.java:247)\n\n            at\norg.apache.catalina.core.ApplicationFilterChain.doFilter(ApplicationFilterChain.java:193)\n\n            at\norg.apache.catalina.core.StandardWrapperValve.invoke(StandardWrapperValve.java:256)\n\n            at\norg.apache.catalina.core.StandardPipeline$StandardPipelineValveContext.invokeNext(StandardPipeline.java:643)\n\n            at\norg.apache.catalina.core.StandardPipeline.invoke(StandardPipeline.java:480)\n\n            at org.apache.catalina.core.ContainerBase.invoke(ContainerBase.java:995)\n\n            at\norg.apache.catalina.core.StandardContextValve.invoke(StandardContextValve.java:191)\n\n            at\norg.apache.catalina.core.StandardPipeline$StandardPipelineValveContext.invokeNext(StandardPipeline.java:643)\n\n            at\norg.apache.catalina.valves.CertificatesValve.invoke(CertificatesValve.java:246)\n\n            at\norg.apache.catalina.core.StandardPipeline$StandardPipelineValveContext.invokeNext(StandardPipeline.java:641)\n\n            at\norg.apache.catalina.core.StandardPipeline.invoke(StandardPipeline.java:480)\n\n            at org.apache.catalina.core.ContainerBase.invoke(ContainerBase.java:995)\n\n            at\norg.apache.catalina.core.StandardContext.invoke(StandardContext.java:2422)\n\n            at\norg.apache.catalina.core.StandardHostValve.invoke(StandardHostValve.java:180)\n\n            at\norg.apache.catalina.core.StandardPipeline$StandardPipelineValveContext.invokeNext(StandardPipeline.java:643)\n\n            at\norg.apache.catalina.valves.ErrorDispatcherValve.invoke(ErrorDispatcherValve.java:171)\n\n            at\norg.apache.catalina.core.StandardPipeline$StandardPipelineValveContext.invokeNext(StandardPipeline.java:641)\n\n            at\norg.eclipse.tomcat.internal.EclipseErrorReportValve.invoke(EclipseErrorReportValve.java:153)\n\n            at\norg.apache.catalina.core.StandardPipeline$StandardPipelineValveContext.invokeNext(StandardPipeline.java:641)\n\n            at\norg.apache.catalina.core.StandardPipeline.invoke(StandardPipeline.java:480)\n\n            at org.apache.catalina.core.ContainerBase.invoke(ContainerBase.java:995)\n\n            at\norg.apache.catalina.core.StandardEngineValve.invoke(StandardEngineValve.java:174)\n\n            at\norg.apache.catalina.core.StandardPipeline$StandardPipelineValveContext.invokeNext(StandardPipeline.java:643)\n\n            at\norg.apache.catalina.core.StandardPipeline.invoke(StandardPipeline.java:480)\n\n            at org.apache.catalina.core.ContainerBase.invoke(ContainerBase.java:995)\n\n            at\norg.apache.coyote.tomcat4.CoyoteAdapter.service(CoyoteAdapter.java:199)\n\n            at\norg.apache.coyote.http11.Http11Processor.process(Http11Processor.java:828)\n\n            at\norg.apache.coyote.http11.Http11Protocol$Http11ConnectionHandler.processConnection(Http11Protocol.java:700)\n\n            at\norg.apache.tomcat.util.net.TcpWorkerThread.runIt(PoolTcpEndpoint.java:584)\n\n            at\norg.apache.tomcat.util.threads.ThreadPool$ControlRunnable.run(ThreadPool.java:683)\n\n            at java.lang.Thread.run(Unknown Source)\n\nCaused by: SQL Exception: Failed to start database\n\u0027D:\\rajesh.gheware\\projects\\automatedbuild\\build\\I.TestBuild\\Arena\\db\\networkManager\u0027,\nsee the next exception for details.\n\n            at org.apache.derby.impl.jdbc.Util.newEmbedSQLException(Util.java)\n\n            at org.apache.derby.impl.jdbc.Util.newEmbedSQLException(Util.java)\n\n            at org.apache.derby.impl.jdbc.Util.generateCsSQLException(Util.java)\n\n            at\norg.apache.derby.impl.jdbc.EmbedConnection.newSQLException(EmbedConnection.java)\n\n            at\norg.apache.derby.impl.jdbc.EmbedConnection.bootDatabase(EmbedConnection.java)\n\n            at\norg.apache.derby.impl.jdbc.EmbedConnection.\u003cinit\u003e(EmbedConnection.java)\n\n            at\norg.apache.derby.impl.jdbc.EmbedConnection20.\u003cinit\u003e(EmbedConnection20.java)\n\n            at\norg.apache.derby.impl.jdbc.EmbedConnection30.\u003cinit\u003e(EmbedConnection30.java)\n\n            at org.apache.derby.jdbc.Driver30.getNewEmbedConnection(Driver30.java)\n\n            at org.apache.derby.jdbc.Driver169.connect(Driver169.java)\n\n            at java.sql.DriverManager.getConnection(Unknown Source)\n\n            at java.sql.DriverManager.getConnection(Unknown Source)\n\n            at\norg.eclipse.birt.report.data.oda.jdbc.JDBCDriverManager.doConnect(JDBCDriverManager.java:146)\n\n            at\norg.eclipse.birt.report.data.oda.jdbc.JDBCDriverManager.getConnection(JDBCDriverManager.java:92)\n\n            at\norg.eclipse.birt.report.data.oda.jdbc.Connection.connectByUrl(Connection.java:218)\n\n            ... 55 more\n\nJul 13, 2005 8:00:01 PM org.eclipse.birt.report.engine.data.dte.DteDataEngine\nexecute\n\nSEVERE: Cannot open the connection for the driver\n(org.eclipse.birt.report.data.oda.jdbc).\n\n \n\nAny ideas, what could be wrong?.?\n\n \n\nBy the way, I am using Eclipse 3.1, BIRT 1.0.0 and Hibernate database?.\n\n \n\n \n\nThanks in advance?\n\n \n\nBest Regards,\nRajesh V. Gheware\nJava Developer Lead",
    "Can you tell me following informatin?\n1: which database you use (hibernate is only data layer, not database)\n2: which Driver Class is used (you can know it from data source editor page)\n\nThanks,",
    "(In reply to comment #1)\n\u003e Can you tell me following informatin?\n\u003e 1: which database you use (hibernate is only data layer, not database)\nDatabase is: Apache Derby. Following info is taken from Manifest.mf file in case\nany more details can be used..\nBundle-Vendor: Apache Software Foundation\nBundle-Activator: org.apache.derby.osgi.EmbeddedActivator\nBundle-Name: Apache Derby 10.0\nBundle-Version: 10.0.2000001\nImport-Package: java.sql\nDynamicImport-Package: *\nExport-Package: org.apache.derby.authentication,org.apache.derby.datab\n ase,org.apache.derby.io,org.apache.derby.jdbc,org.apache.derby.vti\n\n\u003e 2: which Driver Class is used (you can know it from data source editor page)\norg.apache.derby.jdbc.EmbeddedDriver (Apache Derby Embedded Driver v10.0)\n\nand the URL that I am using is:\njdbc:derby:D:\\\\rajesh.gheware\\\\projects\\\\automatedbuild\\\\build\\\\I.TestBuild\\\\Arena\\\\db\\\\networkManager\n\nAnd when I tested the Connection, dialog says Connection Successful \n\u003e \n\u003e Thanks,\n\nThanks to you for responding so quickly.",
    "This is indeed a bug. I need more time to investigate it, now I give you a work \naround way to bypass it temporarily.\n\nJar your database, and connect this jar file. An example is,\nFolder name: c:/dbexample\nJar name: c:/dbexample.jar (it includes dbexample folder)\nConnection url is: jdbc:derby:jar:(c:/dbexample.jar)dbexample\n\nThanks,",
    "*** Bug 105787 has been marked as a duplicate of this bug. ***",
    "It seems this bug can not be solved without the change of BIRT framework in \ndesigning and viewing. \n\nDerby driver can not be loaded into the same JVM by two different ClassLoader, \nbut current framework needs to use it. Refer to bug105787.",
    "This bug is resolved after viewer does not use another class loader to load all plugins.",
    "Verified in the build 20051220"
  ],
  "commentCreationDates": [
    "2005-07-19T13:26:46+02:00",
    "2005-07-20T04:15:03+02:00",
    "2005-07-20T07:58:38+02:00",
    "2005-07-20T08:53:32+02:00",
    "2005-09-16T07:49:03+02:00",
    "2005-09-26T03:58:36+02:00",
    "2005-11-24T06:43:33+01:00",
    "2005-12-20T08:08:46+01:00"
  ],
  "traces": [
    {
      "exceptionType": "org.eclipse.birt.report.data.oda.jdbc.JDBCException",
      "message": "Failed to get Connection  Failed to start database \u0027D:\\rajesh.gheware\\projects\\automatedbuild\\build\\I.TestBuild\\Arena\\db\\networkManager\u0027, see the next exception for details.",
      "elements": [
        {
          "method": "org.eclipse.birt.report.data.oda.jdbc.Connection.connectByUrl",
          "source": "Connection.java:223"
        },
        {
          "method": "org.eclipse.birt.report.data.oda.jdbc.Connection.open",
          "source": "Connection.java:179"
        },
        {
          "method": "org.eclipse.birt.data.engine.odaconsumer.manager.OdaConnection.open",
          "source": "OdaConnection.java:221"
        },
        {
          "method": "org.eclipse.birt.data.engine.odaconsumer.ConnectionManager.openConnection",
          "source": "ConnectionManager.java:89"
        },
        {
          "method": "org.eclipse.birt.data.engine.executor.DataSource.newConnection",
          "source": "DataSource.java:147"
        },
        {
          "method": "org.eclipse.birt.data.engine.executor.DataSource.open",
          "source": "DataSource.java:140"
        },
        {
          "method": "org.eclipse.birt.data.engine.impl.DataSourceRuntime.openOdiDataSource",
          "source": "DataSourceRuntime.java:137"
        },
        {
          "method": "org.eclipse.birt.data.engine.impl.PreparedQuery$Executor.openDataSource",
          "source": "PreparedQuery.java:642"
        },
        {
          "method": "org.eclipse.birt.data.engine.impl.PreparedQuery$Executor.prepareExecution",
          "source": "PreparedQuery.java:454"
        },
        {
          "method": "org.eclipse.birt.data.engine.impl.PreparedQuery$Executor.access$000",
          "source": "PreparedQuery.java:379"
        },
        {
          "method": "org.eclipse.birt.data.engine.impl.PreparedQuery.doPrepare",
          "source": "PreparedQuery.java:171"
        },
        {
          "method": "org.eclipse.birt.data.engine.impl.PreparedDataSourceQuery.execute",
          "source": "PreparedDataSourceQuery.java:137"
        },
        {
          "method": "org.eclipse.birt.report.engine.data.dte.DteDataEngine.execute",
          "source": "DteDataEngine.java:216"
        },
        {
          "method": "org.eclipse.birt.report.engine.executor.ReportItemExecutor.openResultSet",
          "source": "ReportItemExecutor.java:140"
        },
        {
          "method": "org.eclipse.birt.report.engine.executor.ListItemExecutor.execute",
          "source": "ListItemExecutor.java:79"
        },
        {
          "method": "org.eclipse.birt.report.engine.executor.ReportExecutorVisitor.visitListItem",
          "source": "ReportExecutorVisitor.java:256"
        },
        {
          "method": "org.eclipse.birt.report.engine.ir.ListItemDesign.accept",
          "source": "ListItemDesign.java:151"
        },
        {
          "method": "org.eclipse.birt.report.engine.executor.ReportExecutor.execute",
          "source": "ReportExecutor.java:163"
        },
        {
          "method": "org.eclipse.birt.report.engine.api.impl.RunAndRenderTask.run",
          "source": "RunAndRenderTask.java:152"
        },
        {
          "method": "org.eclipse.birt.report.viewer.aggregation.layout.EngineFragment.doService",
          "source": "Unknown Source"
        },
        {
          "method": "org.eclipse.birt.report.viewer.aggregation.BaseFragment.service",
          "source": "Unknown Source"
        },
        {
          "method": "org.eclipse.birt.report.viewer.servlets.ViewerServlet.doPost",
          "source": "Unknown Source"
        },
        {
          "method": "org.eclipse.birt.report.viewer.servlets.ViewerServlet.doGet",
          "source": "Unknown Source"
        },
        {
          "method": "javax.servlet.http.HttpServlet.service",
          "source": "HttpServlet.java:740"
        },
        {
          "method": "javax.servlet.http.HttpServlet.service",
          "source": "HttpServlet.java:853"
        },
        {
          "method": "org.apache.catalina.core.ApplicationFilterChain.internalDoFilter",
          "source": "ApplicationFilterChain.java:247"
        },
        {
          "method": "org.apache.catalina.core.ApplicationFilterChain.doFilter",
          "source": "ApplicationFilterChain.java:193"
        },
        {
          "method": "org.apache.catalina.core.StandardWrapperValve.invoke",
          "source": "StandardWrapperValve.java:256"
        },
        {
          "method": "org.apache.catalina.core.StandardPipeline$StandardPipelineValveContext.invokeNext",
          "source": "StandardPipeline.java:643"
        },
        {
          "method": "org.apache.catalina.core.StandardPipeline.invoke",
          "source": "StandardPipeline.java:480"
        },
        {
          "method": "org.apache.catalina.core.ContainerBase.invoke",
          "source": "ContainerBase.java:995"
        },
        {
          "method": "org.apache.catalina.core.StandardContextValve.invoke",
          "source": "StandardContextValve.java:191"
        },
        {
          "method": "org.apache.catalina.core.StandardPipeline$StandardPipelineValveContext.invokeNext",
          "source": "StandardPipeline.java:643"
        },
        {
          "method": "org.apache.catalina.valves.CertificatesValve.invoke",
          "source": "CertificatesValve.java:246"
        },
        {
          "method": "org.apache.catalina.core.StandardPipeline$StandardPipelineValveContext.invokeNext",
          "source": "StandardPipeline.java:641"
        },
        {
          "method": "org.apache.catalina.core.StandardPipeline.invoke",
          "source": "StandardPipeline.java:480"
        },
        {
          "method": "org.apache.catalina.core.ContainerBase.invoke",
          "source": "ContainerBase.java:995"
        },
        {
          "method": "org.apache.catalina.core.StandardContext.invoke",
          "source": "StandardContext.java:2422"
        },
        {
          "method": "org.apache.catalina.core.StandardHostValve.invoke",
          "source": "StandardHostValve.java:180"
        },
        {
          "method": "org.apache.catalina.core.StandardPipeline$StandardPipelineValveContext.invokeNext",
          "source": "StandardPipeline.java:643"
        },
        {
          "method": "org.apache.catalina.valves.ErrorDispatcherValve.invoke",
          "source": "ErrorDispatcherValve.java:171"
        },
        {
          "method": "org.apache.catalina.core.StandardPipeline$StandardPipelineValveContext.invokeNext",
          "source": "StandardPipeline.java:641"
        },
        {
          "method": "org.eclipse.tomcat.internal.EclipseErrorReportValve.invoke",
          "source": "EclipseErrorReportValve.java:153"
        },
        {
          "method": "org.apache.catalina.core.StandardPipeline$StandardPipelineValveContext.invokeNext",
          "source": "StandardPipeline.java:641"
        },
        {
          "method": "org.apache.catalina.core.StandardPipeline.invoke",
          "source": "StandardPipeline.java:480"
        },
        {
          "method": "org.apache.catalina.core.ContainerBase.invoke",
          "source": "ContainerBase.java:995"
        },
        {
          "method": "org.apache.catalina.core.StandardEngineValve.invoke",
          "source": "StandardEngineValve.java:174"
        },
        {
          "method": "org.apache.catalina.core.StandardPipeline$StandardPipelineValveContext.invokeNext",
          "source": "StandardPipeline.java:643"
        },
        {
          "method": "org.apache.catalina.core.StandardPipeline.invoke",
          "source": "StandardPipeline.java:480"
        },
        {
          "method": "org.apache.catalina.core.ContainerBase.invoke",
          "source": "ContainerBase.java:995"
        },
        {
          "method": "org.apache.coyote.tomcat4.CoyoteAdapter.service",
          "source": "CoyoteAdapter.java:199"
        },
        {
          "method": "org.apache.coyote.http11.Http11Processor.process",
          "source": "Http11Processor.java:828"
        },
        {
          "method": "org.apache.coyote.http11.Http11Protocol$Http11ConnectionHandler.processConnection",
          "source": "Http11Protocol.java:700"
        },
        {
          "method": "org.apache.tomcat.util.net.TcpWorkerThread.runIt",
          "source": "PoolTcpEndpoint.java:584"
        },
        {
          "method": "org.apache.tomcat.util.threads.ThreadPool$ControlRunnable.run",
          "source": "ThreadPool.java:683"
        },
        {
          "method": "java.lang.Thread.run",
          "source": "Unknown Source"
        }
      ],
      "number": 0,
      "commentIndex": 0,
      "bugId": "104338",
      "date": "2005-07-19T13:26:46+02:00",
      "product": "BIRT",
      "component": "Data",
      "severity": "major"
    }
  ],
  "groupId": "104338",
  "bugId": "104338",
  "date": "2005-07-19T13:26:46+02:00",
  "product": "BIRT",
  "component": "Data",
  "severity": "major"
}