{
  "comments": [
    "I created a module that had a dependancy on another module. After deleting the\ndependant module manually from the resource navigator and continuing to use WTP,\nseveral internal errors occurred in different parts of the product. I managed to\ncatch two of them below - one during validation and the other in the component\nbuilder. It looks like the module code needs some hardening when modules don\u0027t\nexist or go missing. Normally I would mark this as major given the number of\nexceptions, the fact that the errors happen on every build, and the bad user\nexperience, but given how close 0.7 is I\u0027ll leave this as \u0027normal\u0027 for now.\n\n\n*** ERROR ***: Sun Jul 24 18:29:01 EDT 2005    java.lang.NullPointerException\n        at\norg.eclipse.wst.common.componentcore.ModuleCoreNature.getModuleCoreNature(ModuleCoreNature.java:152)\n        at\norg.eclipse.wst.common.componentcore.internal.StructureEdit.getStructureEditForRead(StructureEdit.java:115)\n        at\norg.eclipse.wst.common.componentcore.internal.resources.VirtualComponent.getComponentTypeId(VirtualComponent.\njava:88)\n        at\norg.eclipse.jst.j2ee.componentcore.util.EARArtifactEdit.getComponentReferences(EARArtifactEdit.java:483)\n        at\norg.eclipse.jst.j2ee.componentcore.util.EARArtifactEdit.getJ2EEModuleReferences(EARArtifactEdit.java:459)\n        at\norg.eclipse.jst.j2ee.componentcore.util.EARArtifactEdit.getModule(EARArtifactEdit.java:435)\n        at\norg.eclipse.jst.j2ee.componentcore.util.EARArtifactEdit.getModuleURI(EARArtifactEdit.java:408)\n        at\norg.eclipse.jst.j2ee.internal.archive.operations.EARComponentLoadStrategyImpl.addModulesAndUtilities(EARCompo\nnentLoadStrategyImpl.java:58)\n        at\norg.eclipse.jst.j2ee.internal.archive.operations.EARComponentLoadStrategyImpl.getFiles(EARComponentLoadStrate\ngyImpl.java:40)\n        at\norg.eclipse.jst.j2ee.commonarchivecore.internal.strategy.LoadStrategyImpl.collectFiles(LoadStrategyImpl.java:\n274)\n        at\norg.eclipse.jst.j2ee.commonarchivecore.internal.impl.ContainerImpl.getFiles(ContainerImpl.java:239)\n        at\norg.eclipse.jst.j2ee.commonarchivecore.internal.impl.EARFileImpl.getModuleFiles(EARFileImpl.java:501)\n        at\norg.eclipse.jst.j2ee.model.internal.validation.EarValidator.validateSpecLevel(EarValidator.java:673)\n        at\norg.eclipse.jst.j2ee.model.internal.validation.EarValidator.validate(EarValidator.java:114)\n        at\norg.eclipse.jst.j2ee.model.internal.validation.EarValidator.validate(EarValidator.java:128)\n        at\norg.eclipse.jst.j2ee.internal.validation.UIEarValidator.validate(UIEarValidator.java:212)\n        at\norg.eclipse.wst.validation.internal.core.ValidatorLauncher.start(ValidatorLauncher.java:90)\n        at\norg.eclipse.wst.validation.internal.operations.ValidationOperation.launchValidator(ValidationOperation.java:1\n196)\n        at\norg.eclipse.wst.validation.internal.operations.ValidationOperation.internalValidate(ValidationOperation.java:\n1022)\n        at\norg.eclipse.wst.validation.internal.operations.ValidationOperation.validate(ValidationOperation.java:928)\n        at\norg.eclipse.wst.validation.internal.operations.ValidationOperation.run(ValidationOperation.java:639)\n        at\norg.eclipse.wst.validation.internal.operations.ValidationBuilder.build(ValidationBuilder.java:209)\n\n\n!SUBENTRY 1 org.eclipse.wst.common.modulecore 2 75 2005-07-24 18:29:04.258\n!MESSAGE Errors running builder \"Component Structural Dependency Resolver\" on\nproject echoEAR.\n!SUBENTRY 1 org.eclipse.wst.common.modulecore 2 75 2005-07-24 18:29:04.258\n!MESSAGE java.lang.NullPointerException encountered while running Component\nStructural Dependency Resolver.\n!STACK 0\njava.lang.NullPointerException\n        at\norg.eclipse.wst.common.componentcore.internal.StructureEdit.getOutputContainerRoot(StructureEdit.java:287)\n        at\norg.eclipse.wst.common.componentcore.internal.builder.ReferencedComponentBuilderOperation.getAbsoluteInputCon\ntainer(ReferencedComponentBuilderOperation.java:284)\n        at\norg.eclipse.wst.common.componentcore.internal.builder.ReferencedComponentBuilderOperation.execute(ReferencedC\nomponentBuilderOperation.java:97)\n        at\norg.eclipse.wst.common.frameworks.internal.datamodel.ExtendableOperationImpl.doExecute(ExtendableOperationImp\nl.java:129)\n        at\norg.eclipse.wst.common.frameworks.internal.datamodel.ExtendableOperationImpl$1.run(ExtendableOperationImpl.ja\nva:109)\n        at org.eclipse.core.internal.resources.Workspace.run(Workspace.java:1719)\n        at org.eclipse.core.internal.resources.Workspace.run(Workspace.java:1739)\n        at\norg.eclipse.wst.common.frameworks.internal.datamodel.ExtendableOperationImpl.execute(ExtendableOperationImpl.\njava:115)\n        at\norg.eclipse.wst.common.componentcore.internal.builder.ComponentStructuralBuilderDependencyResolver.build(Comp\nonentStructuralBuilderDependencyResolver.java:53)\n        at\norg.eclipse.core.internal.events.BuildManager$2.run(BuildManager.java:593)\n        at\norg.eclipse.core.internal.runtime.InternalPlatform.run(InternalPlatform.java:1044)\n        at org.eclipse.core.runtime.Platform.run(Platform.java:783)\n        at\norg.eclipse.core.internal.events.BuildManager.basicBuild(BuildManager.java:168)\n        at\norg.eclipse.core.internal.events.BuildManager.basicBuild(BuildManager.java:202)\n        at\norg.eclipse.core.internal.events.BuildManager$1.run(BuildManager.java:231)\n        at\norg.eclipse.core.internal.runtime.InternalPlatform.run(InternalPlatform.java:1044)\n        at org.eclipse.core.runtime.Platform.run(Platform.java:783)\n        at\norg.eclipse.core.internal.events.BuildManager.basicBuild(BuildManager.java:234)\n        at\norg.eclipse.core.internal.events.BuildManager.basicBuildLoop(BuildManager.java:253)\n        at\norg.eclipse.core.internal.events.BuildManager.build(BuildManager.java:282)\n        at\norg.eclipse.core.internal.events.AutoBuildJob.doBuild(AutoBuildJob.java:139)\n        at org.eclipse.core.internal.events.AutoBuildJob.run(AutoBuildJob.java:200)\n        at org.eclipse.core.internal.jobs.Worker.run(Worker.java:76)",
    "I think fixes went in on Friday the 22nd to catch most of the more common errors.",
    "Reducing priority, and deferring to M8",
    "This should go away once the \"Refactoring\" actions are implememted",
    "\n\n*** This bug has been marked as a duplicate of 91967 ***",
    "Closing"
  ],
  "commentCreationDates": [
    "2005-07-25T00:37:21+02:00",
    "2005-07-25T15:31:16+02:00",
    "2005-07-26T21:22:56+02:00",
    "2005-08-02T19:39:57+02:00",
    "2005-08-02T19:57:10+02:00",
    "2005-11-23T16:17:40+01:00"
  ],
  "traces": [
    {
      "exceptionType": "java.lang.NullPointerException",
      "elements": [
        {
          "method": "org.eclipse.wst.common.componentcore.ModuleCoreNature.getModuleCoreNature",
          "source": "ModuleCoreNature.java:152"
        },
        {
          "method": "org.eclipse.wst.common.componentcore.internal.StructureEdit.getStructureEditForRead",
          "source": "StructureEdit.java:115"
        },
        {
          "method": "org.eclipse.wst.common.componentcore.internal.resources.VirtualComponent.getComponentTypeId",
          "source": "VirtualComponent. java:88"
        },
        {
          "method": "org.eclipse.jst.j2ee.componentcore.util.EARArtifactEdit.getComponentReferences",
          "source": "EARArtifactEdit.java:483"
        },
        {
          "method": "org.eclipse.jst.j2ee.componentcore.util.EARArtifactEdit.getJ2EEModuleReferences",
          "source": "EARArtifactEdit.java:459"
        },
        {
          "method": "org.eclipse.jst.j2ee.componentcore.util.EARArtifactEdit.getModule",
          "source": "EARArtifactEdit.java:435"
        },
        {
          "method": "org.eclipse.jst.j2ee.componentcore.util.EARArtifactEdit.getModuleURI",
          "source": "EARArtifactEdit.java:408"
        },
        {
          "method": "org.eclipse.jst.j2ee.internal.archive.operations.EARComponentLoadStrategyImpl.addModulesAndUtilities",
          "source": "EARCompo nentLoadStrategyImpl.java:58"
        },
        {
          "method": "org.eclipse.jst.j2ee.internal.archive.operations.EARComponentLoadStrategyImpl.getFiles",
          "source": "EARComponentLoadStrate gyImpl.java:40"
        },
        {
          "method": "org.eclipse.jst.j2ee.commonarchivecore.internal.strategy.LoadStrategyImpl.collectFiles",
          "source": "LoadStrategyImpl.java: 274"
        },
        {
          "method": "org.eclipse.jst.j2ee.commonarchivecore.internal.impl.ContainerImpl.getFiles",
          "source": "ContainerImpl.java:239"
        },
        {
          "method": "org.eclipse.jst.j2ee.commonarchivecore.internal.impl.EARFileImpl.getModuleFiles",
          "source": "EARFileImpl.java:501"
        },
        {
          "method": "org.eclipse.jst.j2ee.model.internal.validation.EarValidator.validateSpecLevel",
          "source": "EarValidator.java:673"
        },
        {
          "method": "org.eclipse.jst.j2ee.model.internal.validation.EarValidator.validate",
          "source": "EarValidator.java:114"
        },
        {
          "method": "org.eclipse.jst.j2ee.model.internal.validation.EarValidator.validate",
          "source": "EarValidator.java:128"
        },
        {
          "method": "org.eclipse.jst.j2ee.internal.validation.UIEarValidator.validate",
          "source": "UIEarValidator.java:212"
        },
        {
          "method": "org.eclipse.wst.validation.internal.core.ValidatorLauncher.start",
          "source": "ValidatorLauncher.java:90"
        },
        {
          "method": "org.eclipse.wst.validation.internal.operations.ValidationOperation.launchValidator",
          "source": "ValidationOperation.java:1 196"
        },
        {
          "method": "org.eclipse.wst.validation.internal.operations.ValidationOperation.internalValidate",
          "source": "ValidationOperation.java: 1022"
        },
        {
          "method": "org.eclipse.wst.validation.internal.operations.ValidationOperation.validate",
          "source": "ValidationOperation.java:928"
        },
        {
          "method": "org.eclipse.wst.validation.internal.operations.ValidationOperation.run",
          "source": "ValidationOperation.java:639"
        },
        {
          "method": "org.eclipse.wst.validation.internal.operations.ValidationBuilder.build",
          "source": "ValidationBuilder.java:209"
        }
      ],
      "number": 0,
      "commentIndex": 0,
      "bugId": "104954",
      "duplicateId": "91967",
      "date": "2005-07-25T00:37:21+02:00",
      "product": "Web Tools",
      "component": "wst.common",
      "severity": "major"
    },
    {
      "exceptionType": "java.lang.NullPointerException",
      "elements": [
        {
          "method": "org.eclipse.wst.common.componentcore.internal.StructureEdit.getOutputContainerRoot",
          "source": "StructureEdit.java:287"
        },
        {
          "method": "org.eclipse.wst.common.componentcore.internal.builder.ReferencedComponentBuilderOperation.getAbsoluteInputContainer",
          "source": "ReferencedComponentBuilderOperation.java:284"
        },
        {
          "method": "org.eclipse.wst.common.componentcore.internal.builder.ReferencedComponentBuilderOperation.execute",
          "source": "ReferencedC omponentBuilderOperation.java:97"
        },
        {
          "method": "org.eclipse.wst.common.frameworks.internal.datamodel.ExtendableOperationImpl.doExecute",
          "source": "ExtendableOperationImp l.java:129"
        },
        {
          "method": "org.eclipse.wst.common.frameworks.internal.datamodel.ExtendableOperationImpl$1.run",
          "source": "ExtendableOperationImpl.ja va:109"
        },
        {
          "method": "org.eclipse.core.internal.resources.Workspace.run",
          "source": "Workspace.java:1719"
        },
        {
          "method": "org.eclipse.core.internal.resources.Workspace.run",
          "source": "Workspace.java:1739"
        },
        {
          "method": "org.eclipse.wst.common.frameworks.internal.datamodel.ExtendableOperationImpl.execute",
          "source": "ExtendableOperationImpl. java:115"
        },
        {
          "method": "org.eclipse.wst.common.componentcore.internal.builder.ComponentStructuralBuilderDependencyResolver.build",
          "source": "Comp onentStructuralBuilderDependencyResolver.java:53"
        },
        {
          "method": "org.eclipse.core.internal.events.BuildManager$2.run",
          "source": "BuildManager.java:593"
        },
        {
          "method": "org.eclipse.core.internal.runtime.InternalPlatform.run",
          "source": "InternalPlatform.java:1044"
        },
        {
          "method": "org.eclipse.core.runtime.Platform.run",
          "source": "Platform.java:783"
        },
        {
          "method": "org.eclipse.core.internal.events.BuildManager.basicBuild",
          "source": "BuildManager.java:168"
        },
        {
          "method": "org.eclipse.core.internal.events.BuildManager.basicBuild",
          "source": "BuildManager.java:202"
        },
        {
          "method": "org.eclipse.core.internal.events.BuildManager$1.run",
          "source": "BuildManager.java:231"
        },
        {
          "method": "org.eclipse.core.internal.runtime.InternalPlatform.run",
          "source": "InternalPlatform.java:1044"
        },
        {
          "method": "org.eclipse.core.runtime.Platform.run",
          "source": "Platform.java:783"
        },
        {
          "method": "org.eclipse.core.internal.events.BuildManager.basicBuild",
          "source": "BuildManager.java:234"
        },
        {
          "method": "org.eclipse.core.internal.events.BuildManager.basicBuildLoop",
          "source": "BuildManager.java:253"
        },
        {
          "method": "org.eclipse.core.internal.events.BuildManager.build",
          "source": "BuildManager.java:282"
        },
        {
          "method": "org.eclipse.core.internal.events.AutoBuildJob.doBuild",
          "source": "AutoBuildJob.java:139"
        },
        {
          "method": "org.eclipse.core.internal.events.AutoBuildJob.run",
          "source": "AutoBuildJob.java:200"
        },
        {
          "method": "org.eclipse.core.internal.jobs.Worker.run",
          "source": "Worker.java:76"
        }
      ],
      "number": 1,
      "commentIndex": 0,
      "bugId": "104954",
      "duplicateId": "91967",
      "date": "2005-07-25T00:37:21+02:00",
      "product": "Web Tools",
      "component": "wst.common",
      "severity": "major"
    }
  ],
  "groupId": "92426",
  "bugId": "104954",
  "duplicateId": "91967",
  "date": "2005-07-25T00:37:21+02:00",
  "product": "Web Tools",
  "component": "wst.common",
  "severity": "major"
}