{
  "comments": [
    "Every time I click on something in the \"Project Explorer\" view I get the\nfollowing in my eclipse log file:\n\n!MESSAGE Problems occurred when invoking code from plug-in: \"org.eclipse.jface\".\n!STACK 0\njava.lang.NoSuchFieldError: BuildAction_label\n        at\norg.eclipse.jst.common.navigator.internal.actions.ProjectMgmtActionsExtension.init(ProjectMgmtActionsExtension.java:77)\n        at\norg.eclipse.wst.common.navigator.internal.provisional.views.NavigatorActionService.initialize(NavigatorActionService.java:379)\n        at\norg.eclipse.wst.common.navigator.internal.provisional.views.NavigatorActionService.getActionProviderInstance(NavigatorActionService.java:280)\n        at\norg.eclipse.wst.common.navigator.internal.provisional.views.NavigatorActionService.fillActionBars(NavigatorActionService.java:229)\n        at\norg.eclipse.wst.common.navigator.internal.provisional.views.CommonNavigatorManager.selectionChanged(CommonNavigatorManager.java:98)\n        at org.eclipse.jface.viewers.Viewer$2.run(Viewer.java:162)\n        at\norg.eclipse.core.internal.runtime.InternalPlatform.run(InternalPlatform.java:1021)\n        at org.eclipse.core.runtime.Platform.run(Platform.java:757)\n        at org.eclipse.ui.internal.JFaceUtil$1.run(JFaceUtil.java:40)\n        at org.eclipse.jface.util.SafeRunnable.run(SafeRunnable.java:148)\n        at org.eclipse.jface.viewers.Viewer.fireSelectionChanged(Viewer.java:160)\n        at\norg.eclipse.jface.viewers.StructuredViewer.updateSelection(StructuredViewer.java:1691)\n        at\norg.eclipse.jface.viewers.StructuredViewer.handleSelect(StructuredViewer.java:934)\n        at\norg.eclipse.jface.viewers.StructuredViewer$4.widgetSelected(StructuredViewer.java:960)\n        at\norg.eclipse.jface.util.OpenStrategy.fireSelectionEvent(OpenStrategy.java:209)\n        at org.eclipse.jface.util.OpenStrategy.access$3(OpenStrategy.java:204)\n        at org.eclipse.jface.util.OpenStrategy$1.handleEvent(OpenStrategy.java:364)\n        at org.eclipse.swt.widgets.EventTable.sendEvent(EventTable.java:82)\n        at org.eclipse.swt.widgets.Widget.sendEvent(Widget.java:740)\n        at org.eclipse.swt.widgets.Display.runDeferredEvents(Display.java:3003)\n        at org.eclipse.swt.widgets.Display.readAndDispatch(Display.java:2703)\n        at org.eclipse.ui.internal.Workbench.runEventLoop(Workbench.java:1570)\n        at org.eclipse.ui.internal.Workbench.runUI(Workbench.java:1534)\n        at\norg.eclipse.ui.internal.Workbench.createAndRunWorkbench(Workbench.java:306)\n        at org.eclipse.ui.PlatformUI.createAndRunWorkbench(PlatformUI.java:143)\n        at org.eclipse.ui.internal.ide.IDEApplication.run(IDEApplication.java:103)\n        at\norg.eclipse.core.internal.runtime.PlatformActivator$1.run(PlatformActivator.java:228)\n        at\norg.eclipse.core.runtime.adaptor.EclipseStarter.run(EclipseStarter.java:344)\n        at\norg.eclipse.core.runtime.adaptor.EclipseStarter.run(EclipseStarter.java:156)\n        at sun.reflect.NativeMethodAccessorImpl.invoke0(Native Method)\n        at\nsun.reflect.NativeMethodAccessorImpl.invoke(NativeMethodAccessorImpl.java:39)\n        at\nsun.reflect.DelegatingMethodAccessorImpl.invoke(DelegatingMethodAccessorImpl.java:25)\n        at java.lang.reflect.Method.invoke(Method.java:585)\n        at org.eclipse.core.launcher.Main.invokeFramework(Main.java:315)\n        at org.eclipse.core.launcher.Main.basicRun(Main.java:268)\n        at org.eclipse.core.launcher.Main.run(Main.java:942)\n        at org.eclipse.core.launcher.Main.main(Main.java:926)",
    "What version of the Eclipse base are you using? Can you confirm that it is 3.1?",
    "(In reply to comment #1)\n\u003e What version of the Eclipse base are you using? Can you confirm that it is 3.1?\n\nYes. I\u0027m using the 3.1.0 version, with wtp 0.7.\nBefore I was using the eclipse 3.1RC3 with wtp 1.0M5, and it was working properly.",
    "Part of a mass update. Based on 9/22/2005 development review meeting, it\u0027s \ndetermined this was an open bug/enhancement with tartget mistakenly set to M8. \nSince this will not be in M8, I am changing to \"unspecified\". \n\nIf this is an error, please correct (for example the bug really has been fixed\nin M8, change back to M8, and \"fixed\".)\n",
    "\nThis works for me in the current build. Cannot reproduce. ",
    "This bug was moved to \u0027closed\u0027 state, since it is so old is is assumed its dup, invalid, or worksforme resolution is no longer in qustion and the bugzilla needs no further attention. Feel free to re-open, or open a new bug, if this semi-automatic processing was done in error in this case. "
  ],
  "commentCreationDates": [
    "2005-07-25T19:47:40+02:00",
    "2005-07-25T21:44:52+02:00",
    "2005-07-26T13:25:10+02:00",
    "2005-09-23T05:16:48+02:00",
    "2005-11-05T22:43:21+01:00",
    "2006-09-25T09:04:39+02:00"
  ],
  "traces": [
    {
      "exceptionType": "java.lang.NoSuchFieldError",
      "message": "BuildAction_label",
      "elements": [
        {
          "method": "org.eclipse.jst.common.navigator.internal.actions.ProjectMgmtActionsExtension.init",
          "source": "ProjectMgmtActionsExtension.java:77"
        },
        {
          "method": "org.eclipse.wst.common.navigator.internal.provisional.views.NavigatorActionService.initialize",
          "source": "NavigatorActionService.java:379"
        },
        {
          "method": "org.eclipse.wst.common.navigator.internal.provisional.views.NavigatorActionService.getActionProviderInstance",
          "source": "NavigatorActionService.java:280"
        },
        {
          "method": "org.eclipse.wst.common.navigator.internal.provisional.views.NavigatorActionService.fillActionBars",
          "source": "NavigatorActionService.java:229"
        },
        {
          "method": "org.eclipse.wst.common.navigator.internal.provisional.views.CommonNavigatorManager.selectionChanged",
          "source": "CommonNavigatorManager.java:98"
        },
        {
          "method": "org.eclipse.jface.viewers.Viewer$2.run",
          "source": "Viewer.java:162"
        },
        {
          "method": "org.eclipse.core.internal.runtime.InternalPlatform.run",
          "source": "InternalPlatform.java:1021"
        },
        {
          "method": "org.eclipse.core.runtime.Platform.run",
          "source": "Platform.java:757"
        },
        {
          "method": "org.eclipse.ui.internal.JFaceUtil$1.run",
          "source": "JFaceUtil.java:40"
        },
        {
          "method": "org.eclipse.jface.util.SafeRunnable.run",
          "source": "SafeRunnable.java:148"
        },
        {
          "method": "org.eclipse.jface.viewers.Viewer.fireSelectionChanged",
          "source": "Viewer.java:160"
        },
        {
          "method": "org.eclipse.jface.viewers.StructuredViewer.updateSelection",
          "source": "StructuredViewer.java:1691"
        },
        {
          "method": "org.eclipse.jface.viewers.StructuredViewer.handleSelect",
          "source": "StructuredViewer.java:934"
        },
        {
          "method": "org.eclipse.jface.viewers.StructuredViewer$4.widgetSelected",
          "source": "StructuredViewer.java:960"
        },
        {
          "method": "org.eclipse.jface.util.OpenStrategy.fireSelectionEvent",
          "source": "OpenStrategy.java:209"
        },
        {
          "method": "org.eclipse.jface.util.OpenStrategy.access$3",
          "source": "OpenStrategy.java:204"
        },
        {
          "method": "org.eclipse.jface.util.OpenStrategy$1.handleEvent",
          "source": "OpenStrategy.java:364"
        },
        {
          "method": "org.eclipse.swt.widgets.EventTable.sendEvent",
          "source": "EventTable.java:82"
        },
        {
          "method": "org.eclipse.swt.widgets.Widget.sendEvent",
          "source": "Widget.java:740"
        },
        {
          "method": "org.eclipse.swt.widgets.Display.runDeferredEvents",
          "source": "Display.java:3003"
        },
        {
          "method": "org.eclipse.swt.widgets.Display.readAndDispatch",
          "source": "Display.java:2703"
        },
        {
          "method": "org.eclipse.ui.internal.Workbench.runEventLoop",
          "source": "Workbench.java:1570"
        },
        {
          "method": "org.eclipse.ui.internal.Workbench.runUI",
          "source": "Workbench.java:1534"
        },
        {
          "method": "org.eclipse.ui.internal.Workbench.createAndRunWorkbench",
          "source": "Workbench.java:306"
        },
        {
          "method": "org.eclipse.ui.PlatformUI.createAndRunWorkbench",
          "source": "PlatformUI.java:143"
        },
        {
          "method": "org.eclipse.ui.internal.ide.IDEApplication.run",
          "source": "IDEApplication.java:103"
        },
        {
          "method": "org.eclipse.core.internal.runtime.PlatformActivator$1.run",
          "source": "PlatformActivator.java:228"
        },
        {
          "method": "org.eclipse.core.runtime.adaptor.EclipseStarter.run",
          "source": "EclipseStarter.java:344"
        },
        {
          "method": "org.eclipse.core.runtime.adaptor.EclipseStarter.run",
          "source": "EclipseStarter.java:156"
        },
        {
          "method": "sun.reflect.NativeMethodAccessorImpl.invoke0",
          "source": "Native Method"
        },
        {
          "method": "sun.reflect.NativeMethodAccessorImpl.invoke",
          "source": "NativeMethodAccessorImpl.java:39"
        },
        {
          "method": "sun.reflect.DelegatingMethodAccessorImpl.invoke",
          "source": "DelegatingMethodAccessorImpl.java:25"
        },
        {
          "method": "java.lang.reflect.Method.invoke",
          "source": "Method.java:585"
        },
        {
          "method": "org.eclipse.core.launcher.Main.invokeFramework",
          "source": "Main.java:315"
        },
        {
          "method": "org.eclipse.core.launcher.Main.basicRun",
          "source": "Main.java:268"
        },
        {
          "method": "org.eclipse.core.launcher.Main.run",
          "source": "Main.java:942"
        },
        {
          "method": "org.eclipse.core.launcher.Main.main",
          "source": "Main.java:926"
        }
      ],
      "number": 0,
      "commentIndex": 0,
      "bugId": "105057",
      "date": "2005-07-25T19:47:40+02:00",
      "product": "Web Tools",
      "component": "wst.common",
      "severity": "major"
    }
  ],
  "groupId": "105057",
  "bugId": "105057",
  "date": "2005-07-25T19:47:40+02:00",
  "product": "Web Tools",
  "component": "wst.common",
  "severity": "major"
}