{
  "comments": [
    "Steps to repro: \n\n1- Create a new project\n2- Create a new Java file that contains annotations (like from a template, or\nrefreshing the project after a was file copied into the project)\n3- Immediately delete the project after creating the file (before the APT\nprocessing is complete).\n\nThe result is a JavaModelException:\n\nJava Model Exception: Java Model Status [Project3 does not exist]\n\n            at\norg.eclipse.jdt.internal.core.JavaElement.newNotPresentException(JavaElement.java:468)\n\n            at\norg.eclipse.jdt.internal.core.JavaModelManager.getPerProjectInfoCheckExistence(JavaModelManager.java:1353)\n\n            at\norg.eclipse.jdt.internal.core.JavaProject.getPerProjectInfo(JavaProject.java:1785)\n\n            at\norg.eclipse.jdt.internal.core.JavaProject.getResolvedClasspath(JavaProject.java:1923)\n\n            at\norg.eclipse.jdt.internal.core.JavaProject.getResolvedClasspath(JavaProject.java:1888)\n\n            at\norg.eclipse.jdt.apt.core.util.AptConfig.getProcessorOptions(AptConfig.java:138)\n\n            at\norg.eclipse.jdt.apt.core.internal.env.ProcessorEnvImpl.initOptions(ProcessorEnvImpl.java:226)\n\n            at\norg.eclipse.jdt.apt.core.internal.env.ProcessorEnvImpl.\u003cinit\u003e(ProcessorEnvImpl.java:208)\n\n            at\norg.eclipse.jdt.apt.core.internal.env.ProcessorEnvImpl.newProcessorEnvironmentForReconcile(ProcessorEnvImpl.java:155)\n\n            at\norg.eclipse.jdt.apt.core.internal.APTDispatchRunnable.run(APTDispatchRunnable.java:136)\n\n            at\norg.eclipse.core.internal.resources.Workspace.run(Workspace.java:1719)\n\n            at\norg.eclipse.jdt.apt.core.internal.APTDispatch.runAPT(APTDispatch.java:79)\n\n            at\norg.eclipse.jdt.apt.core.internal.APTDispatch.runAPTDuringReconcile(APTDispatch.java:55)\n\n            at\norg.eclipse.jdt.apt.core.internal.AptCompilationParticipant.postReconcileNotify(AptCompilationParticipant.java:168)\n\n            at\norg.eclipse.jdt.apt.core.internal.AptCompilationParticipant.notify(AptCompilationParticipant.java:77)\n\n            at\norg.eclipse.jdt.internal.core.ReconcileWorkingCopyOperation.notifyCompilationParticipants(ReconcileWorkingCopyOperation.java:145)\n\n            at\norg.eclipse.jdt.internal.core.ReconcileWorkingCopyOperation.executeOperation(ReconcileWorkingCopyOperation.java:59)\n\n            at\norg.eclipse.jdt.internal.core.JavaModelOperation.run(JavaModelOperation.java:718)\n\n            at\norg.eclipse.jdt.internal.core.JavaModelOperation.runOperation(JavaModelOperation.java:777)\n\n            at\norg.eclipse.jdt.internal.core.CompilationUnit.reconcile(CompilationUnit.java:1081)\n\n            at\norg.eclipse.jdt.internal.ui.text.java.JavaReconcilingStrategy$1.run(JavaReconcilingStrategy.java:98)\n\n            at\norg.eclipse.core.internal.runtime.InternalPlatform.run(InternalPlatform.java:1044)\n\n            at org.eclipse.core.runtime.Platform.run(Platform.java:783)\n\n            at\norg.eclipse.jdt.internal.ui.text.java.JavaReconcilingStrategy.reconcile(JavaReconcilingStrategy.java:82)\n\n            at\norg.eclipse.jdt.internal.ui.text.java.JavaReconcilingStrategy.reconcile(JavaReconcilingStrategy.java:147)\n\n            at\norg.eclipse.jdt.internal.ui.text.CompositeReconcilingStrategy.reconcile(CompositeReconcilingStrategy.java:86)",
    "John - is the exception reported anywhere but in STDERR/STDOUT? The message\nshould be harmless, and is just there to log possible failures. In this case,\nit\u0027s expected that we should fail since the project has been deleted.",
    "I think the exception is getting bubbled up to the default eclipse exception\nhandler.  The exception definitely appears in the Error Log view as a logged\nexception (meaning that the stack trace is visible from the logged event\u0027s\nproperties and is logged with severity, ERROR).  \n\nOff the top of my head, I think that an error dialog was popped, too. \"An\ninternal error has occurred. See the log for more details\" kind of a thing, but\nI\u0027ll repro to be 100% sure that it really is showing up.",
    "Just tried this out. I don\u0027t get a dialog, but I do get the error logged to the\nError Log. I think this is okay, as the user deleted the project mid-build, and\nwe\u0027d rather not have the possibility of ignoring valuable errors that might look\nlike this one.\n\nThe stack trace to the console will be removed before we ship, tracked with bug\n101322:\n\nhttps://bugs.eclipse.org/bugs/show_bug.cgi?id\u003d101322\n"
  ],
  "commentCreationDates": [
    "2005-07-26T18:12:54+02:00",
    "2005-07-26T22:14:32+02:00",
    "2005-07-26T22:36:34+02:00",
    "2005-07-29T23:51:40+02:00"
  ],
  "traces": [
    {
      "exceptionType": "JavaModelException",
      "message": "Java Model Exception: Java Model Status [Project3 does not exist]",
      "elements": [
        {
          "method": "org.eclipse.jdt.internal.core.JavaElement.newNotPresentException",
          "source": "JavaElement.java:468"
        },
        {
          "method": "org.eclipse.jdt.internal.core.JavaModelManager.getPerProjectInfoCheckExistence",
          "source": "JavaModelManager.java:1353"
        },
        {
          "method": "org.eclipse.jdt.internal.core.JavaProject.getPerProjectInfo",
          "source": "JavaProject.java:1785"
        },
        {
          "method": "org.eclipse.jdt.internal.core.JavaProject.getResolvedClasspath",
          "source": "JavaProject.java:1923"
        },
        {
          "method": "org.eclipse.jdt.internal.core.JavaProject.getResolvedClasspath",
          "source": "JavaProject.java:1888"
        },
        {
          "method": "org.eclipse.jdt.apt.core.util.AptConfig.getProcessorOptions",
          "source": "AptConfig.java:138"
        },
        {
          "method": "org.eclipse.jdt.apt.core.internal.env.ProcessorEnvImpl.initOptions",
          "source": "ProcessorEnvImpl.java:226"
        },
        {
          "method": "org.eclipse.jdt.apt.core.internal.env.ProcessorEnvImpl.\u003cinit\u003e",
          "source": "ProcessorEnvImpl.java:208"
        },
        {
          "method": "org.eclipse.jdt.apt.core.internal.env.ProcessorEnvImpl.newProcessorEnvironmentForReconcile",
          "source": "ProcessorEnvImpl.java:155"
        },
        {
          "method": "org.eclipse.jdt.apt.core.internal.APTDispatchRunnable.run",
          "source": "APTDispatchRunnable.java:136"
        },
        {
          "method": "org.eclipse.core.internal.resources.Workspace.run",
          "source": "Workspace.java:1719"
        },
        {
          "method": "org.eclipse.jdt.apt.core.internal.APTDispatch.runAPT",
          "source": "APTDispatch.java:79"
        },
        {
          "method": "org.eclipse.jdt.apt.core.internal.APTDispatch.runAPTDuringReconcile",
          "source": "APTDispatch.java:55"
        },
        {
          "method": "org.eclipse.jdt.apt.core.internal.AptCompilationParticipant.postReconcileNotify",
          "source": "AptCompilationParticipant.java:168"
        },
        {
          "method": "org.eclipse.jdt.apt.core.internal.AptCompilationParticipant.notify",
          "source": "AptCompilationParticipant.java:77"
        },
        {
          "method": "org.eclipse.jdt.internal.core.ReconcileWorkingCopyOperation.notifyCompilationParticipants",
          "source": "ReconcileWorkingCopyOperation.java:145"
        },
        {
          "method": "org.eclipse.jdt.internal.core.ReconcileWorkingCopyOperation.executeOperation",
          "source": "ReconcileWorkingCopyOperation.java:59"
        },
        {
          "method": "org.eclipse.jdt.internal.core.JavaModelOperation.run",
          "source": "JavaModelOperation.java:718"
        },
        {
          "method": "org.eclipse.jdt.internal.core.JavaModelOperation.runOperation",
          "source": "JavaModelOperation.java:777"
        },
        {
          "method": "org.eclipse.jdt.internal.core.CompilationUnit.reconcile",
          "source": "CompilationUnit.java:1081"
        },
        {
          "method": "org.eclipse.jdt.internal.ui.text.java.JavaReconcilingStrategy$1.run",
          "source": "JavaReconcilingStrategy.java:98"
        },
        {
          "method": "org.eclipse.core.internal.runtime.InternalPlatform.run",
          "source": "InternalPlatform.java:1044"
        },
        {
          "method": "org.eclipse.core.runtime.Platform.run",
          "source": "Platform.java:783"
        },
        {
          "method": "org.eclipse.jdt.internal.ui.text.java.JavaReconcilingStrategy.reconcile",
          "source": "JavaReconcilingStrategy.java:82"
        },
        {
          "method": "org.eclipse.jdt.internal.ui.text.java.JavaReconcilingStrategy.reconcile",
          "source": "JavaReconcilingStrategy.java:147"
        },
        {
          "method": "org.eclipse.jdt.internal.ui.text.CompositeReconcilingStrategy.reconcile",
          "source": "CompositeReconcilingStrategy.java:86"
        }
      ],
      "number": 0,
      "commentIndex": 0,
      "bugId": "105175",
      "date": "2005-07-26T18:12:54+02:00",
      "product": "JDT",
      "component": "APT",
      "severity": "normal"
    }
  ],
  "groupId": "105175",
  "bugId": "105175",
  "date": "2005-07-26T18:12:54+02:00",
  "product": "JDT",
  "component": "APT",
  "severity": "normal"
}