{
  "comments": [
    "Sometimes while doing a lot of \"step intos\" the step into button (in Eclipse\n3.1.0) will become disabled. If I click on the thread in the Debug view and\nclick on the top of the stack (the activation record of the method I\u0027m currently\nin) suddenly the step into button will become enabled, and then I can click on it.\n\nThus, either the button is being disabled when it shouldn\u0027t (note that step over\nis always enabled), or is being enabled when it shouldn\u0027t. Definitely a bug.",
    "Any related exception in the .log file? I wonder if this is related to bug \n105095?",
    "Here is something from that day in my .log. I\u0027m not sure if it\u0027s related or not.\n\n!SESSION 2005-07-27 12:19:34.39 ------------------------------------------------\neclipse.buildId\u003dI20050627-1435\njava.version\u003d1.5.0_04\njava.vendor\u003dSun Microsystems Inc.\nBootLoader constants: OS\u003dwin32, ARCH\u003dx86, WS\u003dwin32, NL\u003den_US\nCommand-line arguments:  -os win32 -ws win32 -arch x86 -data C:\\EclipseWorkspace\n\n!ENTRY org.eclipse.jdt.debug 4 120 2005-07-27 12:59:24.767\n!MESSAGE Internal error logged from JDI Debug: \n!STACK 0\norg.eclipse.jdi.TimeoutException: Timeout occurred while waiting for packet 1231\n.\n        at org.eclipse.jdi.internal.connect.PacketReceiveManager.getReply(Packet\nReceiveManager.java:174)\n        at org.eclipse.jdi.internal.connect.PacketReceiveManager.getReply(Packet\nReceiveManager.java:184)\n        at org.eclipse.jdi.internal.MirrorImpl.requestVM(MirrorImpl.java:174)\n        at org.eclipse.jdi.internal.MirrorImpl.requestVM(MirrorImpl.java:192)\n        at org.eclipse.jdi.internal.MirrorImpl.requestVM(MirrorImpl.java:207)\n        at org.eclipse.jdi.internal.ThreadReferenceImpl.status(ThreadReferenceIm\npl.java:345)\n        at org.eclipse.jdt.internal.debug.core.model.JDIThread.initialize(JDIThr\nead.java:249)\n        at org.eclipse.jdt.internal.debug.core.model.JDIThread.\u003cinit\u003e(JDIThread.\njava:211)\n        at org.eclipse.jdt.internal.debug.core.model.JDIDebugTarget.createThread\n(JDIDebugTarget.java:447)\n        at org.eclipse.jdt.internal.debug.core.model.JDIDebugTarget$ThreadStartH\nandler.handleEvent(JDIDebugTarget.java:1739)\n        at org.eclipse.jdt.internal.debug.core.EventDispatcher.dispatch(EventDis\npatcher.java:140)\n        at org.eclipse.jdt.internal.debug.core.EventDispatcher.run(EventDispatch\ner.java:232)\n        at java.lang.Thread.run(Unknown Source)",
    "The exception in the log looks like a dup of bug 94452. Not likely the cause \nof the described problem.",
    "The step actions are re-written in 3.2, and a similar problem has been fixed. See bug 124160.\n\n*** This bug has been marked as a duplicate of 124160 ***"
  ],
  "commentCreationDates": [
    "2005-07-27T22:20:12+02:00",
    "2005-07-29T17:11:37+02:00",
    "2005-07-29T20:30:57+02:00",
    "2005-07-29T23:41:20+02:00",
    "2006-01-27T20:41:36+01:00"
  ],
  "traces": [
    {
      "exceptionType": "org.eclipse.jdi.TimeoutException",
      "message": "Timeout occurred while waiting for packet 1231 .",
      "elements": [
        {
          "method": "org.eclipse.jdi.internal.connect.PacketReceiveManager.getReply",
          "source": "Packet ReceiveManager.java:174"
        },
        {
          "method": "org.eclipse.jdi.internal.connect.PacketReceiveManager.getReply",
          "source": "Packet ReceiveManager.java:184"
        },
        {
          "method": "org.eclipse.jdi.internal.MirrorImpl.requestVM",
          "source": "MirrorImpl.java:174"
        },
        {
          "method": "org.eclipse.jdi.internal.MirrorImpl.requestVM",
          "source": "MirrorImpl.java:192"
        },
        {
          "method": "org.eclipse.jdi.internal.MirrorImpl.requestVM",
          "source": "MirrorImpl.java:207"
        },
        {
          "method": "org.eclipse.jdi.internal.ThreadReferenceImpl.status",
          "source": "ThreadReferenceIm pl.java:345"
        },
        {
          "method": "org.eclipse.jdt.internal.debug.core.model.JDIThread.initialize",
          "source": "JDIThr ead.java:249"
        },
        {
          "method": "org.eclipse.jdt.internal.debug.core.model.JDIThread.\u003cinit\u003e",
          "source": "JDIThread. java:211"
        },
        {
          "method": "org.eclipse.jdt.internal.debug.core.model.JDIDebugTarget.createThread",
          "source": "JDIDebugTarget.java:447"
        },
        {
          "method": "org.eclipse.jdt.internal.debug.core.model.JDIDebugTarget$ThreadStartHandler.handleEvent",
          "source": "JDIDebugTarget.java:1739"
        },
        {
          "method": "org.eclipse.jdt.internal.debug.core.EventDispatcher.dispatch",
          "source": "EventDis patcher.java:140"
        },
        {
          "method": "org.eclipse.jdt.internal.debug.core.EventDispatcher.run",
          "source": "EventDispatch er.java:232"
        },
        {
          "method": "java.lang.Thread.run",
          "source": "Unknown Source"
        }
      ],
      "number": 0,
      "commentIndex": 2,
      "bugId": "105374",
      "duplicateId": "124160",
      "date": "2005-07-29T20:30:57+02:00",
      "product": "JDT",
      "component": "Debug",
      "severity": "normal"
    }
  ],
  "groupId": "124160",
  "bugId": "105374",
  "duplicateId": "124160",
  "date": "2005-07-27T22:20:12+02:00",
  "product": "JDT",
  "component": "Debug",
  "severity": "normal"
}