{
  "comments": [
    "Hi All:\nI\u0027ve some ui code work fine with eclipse3.0.2.\nbut when i run these code on eclipse3.1 release, there\u0027s some critical problem.\ni use gridlayout to layout out my widgets and use jre1.5.04 in these two \nsituation.\nThanks.",
    "Created an attachment (id\u003d25453)\nwork fine on eclipse 3.0.2 with jre1.5.04\n",
    "Created an attachment (id\u003d25454)\ncan layout correctly on eclipse 3.1 release with jre1.5.04\n",
    "Can you please provide a code snippet that shows the problem?",
    "This is probably bug (???)  maybe not in GridLayout (maybe in another layout , too)\n\nWe have (in more method getData,layout,flushCache) next construction :\n\nGridData data \u003d (GridData) control.getLayoutData ();\n\nIt throw exception (ClassCastException) when user set GridData to non GridLayout\nUser can do it and it has worked in eclipse \u003c 3.1\n\nIt can be user bug, but eclipse can check it and do nothing or return friendly\nexception like \u0027you set XXXData to YYYLayout\u0027\n\nPeco",
    "jre \u003d 1.5.0_04\n\neverything\u0027s fine with SWT \u003c 3.1\n\nBut... SWT \u003e\u003d 3.1 I get :\n\njava.lang.ClassCastException: org.eclipse.swt.layout.GridData\n        at org.eclipse.swt.layout.FillLayout.computeChildSize\n(FillLayout.java:141)\n        at org.eclipse.swt.layout.FillLayout.computeSize(FillLayout.java:119)\n        at org.eclipse.swt.widgets.Composite.computeSize(Composite.java:213)\n        at org.eclipse.swt.custom.SashFormLayout.computeSize\n(SashFormLayout.java:46)\n        at org.eclipse.swt.widgets.Composite.computeSize(Composite.java:213)\n        at org.eclipse.swt.layout.FormData.computeSize(FormData.java:127)\n        at org.eclipse.swt.layout.FormLayout.layout(FormLayout.java:318)\n        at org.eclipse.swt.layout.FormLayout.computeSize(FormLayout.java:239)\n        at org.eclipse.swt.widgets.Composite.computeSize(Composite.java:213)\n        at org.eclipse.swt.widgets.Group.computeSize(Group.java:150)\n        at org.eclipse.swt.layout.FormData.computeSize(FormData.java:116)\n        at org.eclipse.swt.layout.FormData.getWidth(FormData.java:145)\n        at org.eclipse.swt.layout.FormData.getRightAttachment(FormData.java:247)\n        at org.eclipse.swt.layout.FormLayout.layout(FormLayout.java:305)\n        at org.eclipse.swt.layout.FormLayout.layout(FormLayout.java:284)\n        at org.eclipse.swt.widgets.Composite.updateLayout(Composite.java:869)\n        at org.eclipse.swt.widgets.Composite.WM_SIZE(Composite.java:1248)\n        at org.eclipse.swt.widgets.Control.windowProc(Control.java:3107)\n        at org.eclipse.swt.widgets.Display.windowProc(Display.java:3706)\n        at org.eclipse.swt.internal.win32.OS.DefWindowProcW(Native Method)\n        at org.eclipse.swt.internal.win32.OS.DefWindowProc(OS.java:1651)\n        at org.eclipse.swt.widgets.Scrollable.callWindowProc(Scrollable.java:77)\n        at org.eclipse.swt.widgets.Control.windowProc(Control.java:3123)\n        at org.eclipse.swt.widgets.Display.windowProc(Display.java:3706)\n        at org.eclipse.swt.internal.win32.OS.SetWindowPos(Native Method)\n        at org.eclipse.swt.widgets.Widget.SetWindowPos(Widget.java:1140)\n        at org.eclipse.swt.widgets.Control.setBounds(Control.java:1952)\n        at org.eclipse.swt.widgets.Control.setBounds(Control.java:1933)\n        at org.eclipse.swt.widgets.Control.setBounds(Control.java:1929)\n        at org.eclipse.swt.layout.FillLayout.layout(FillLayout.java:198)\n        at org.eclipse.swt.widgets.Composite.updateLayout(Composite.java:869)\n        at org.eclipse.swt.widgets.Composite.layout(Composite.java:493)\n        at org.eclipse.swt.widgets.Composite.layout(Composite.java:458)\n        at org.eclipse.swt.widgets.Composite.layout(Composite.java:428)\n        at org.ies.ui.UIPanel.init(UIPanel.java:207)\n        at org.ies.ui.UIWindow.createUIPanelInstance(UIWindow.java:142)\n        at org.ies.ui.UIFrame.createCTabItem(UIFrame.java:374)\n        at org.ies.ui.UIFrame.init(UIFrame.java:146)\n        at org.ies.ui.UIApplication.showUIFrame(UIApplication.java:263)\n        at MainClass.UIFrame_Test_1(MainClass.java:194)\n        at MainClass.main(MainClass.java:208)\n\n\n\n\n",
    "(In reply to comment #5)\n\nyou add GridData to any FillLayout (probably SashForm)\n\nyou acn be your bug, but eclipse can return better error message\nor exception",
    "\n\n*** This bug has been marked as a duplicate of 98493 ***"
  ],
  "commentCreationDates": [
    "2005-07-29T04:27:21+02:00",
    "2005-07-29T04:28:28+02:00",
    "2005-07-29T04:29:21+02:00",
    "2005-08-11T17:42:57+02:00",
    "2005-10-07T18:38:46+02:00",
    "2005-10-23T01:24:58+02:00",
    "2005-10-23T03:06:16+02:00",
    "2005-10-25T17:32:49+02:00"
  ],
  "traces": [
    {
      "exceptionType": "java.lang.ClassCastException",
      "message": "org.eclipse.swt.layout.GridData",
      "elements": [
        {
          "method": "org.eclipse.swt.layout.FillLayout.computeChildSize",
          "source": "FillLayout.java:141"
        },
        {
          "method": "org.eclipse.swt.layout.FillLayout.computeSize",
          "source": "FillLayout.java:119"
        },
        {
          "method": "org.eclipse.swt.widgets.Composite.computeSize",
          "source": "Composite.java:213"
        },
        {
          "method": "org.eclipse.swt.custom.SashFormLayout.computeSize",
          "source": "SashFormLayout.java:46"
        },
        {
          "method": "org.eclipse.swt.widgets.Composite.computeSize",
          "source": "Composite.java:213"
        },
        {
          "method": "org.eclipse.swt.layout.FormData.computeSize",
          "source": "FormData.java:127"
        },
        {
          "method": "org.eclipse.swt.layout.FormLayout.layout",
          "source": "FormLayout.java:318"
        },
        {
          "method": "org.eclipse.swt.layout.FormLayout.computeSize",
          "source": "FormLayout.java:239"
        },
        {
          "method": "org.eclipse.swt.widgets.Composite.computeSize",
          "source": "Composite.java:213"
        },
        {
          "method": "org.eclipse.swt.widgets.Group.computeSize",
          "source": "Group.java:150"
        },
        {
          "method": "org.eclipse.swt.layout.FormData.computeSize",
          "source": "FormData.java:116"
        },
        {
          "method": "org.eclipse.swt.layout.FormData.getWidth",
          "source": "FormData.java:145"
        },
        {
          "method": "org.eclipse.swt.layout.FormData.getRightAttachment",
          "source": "FormData.java:247"
        },
        {
          "method": "org.eclipse.swt.layout.FormLayout.layout",
          "source": "FormLayout.java:305"
        },
        {
          "method": "org.eclipse.swt.layout.FormLayout.layout",
          "source": "FormLayout.java:284"
        },
        {
          "method": "org.eclipse.swt.widgets.Composite.updateLayout",
          "source": "Composite.java:869"
        },
        {
          "method": "org.eclipse.swt.widgets.Composite.WM_SIZE",
          "source": "Composite.java:1248"
        },
        {
          "method": "org.eclipse.swt.widgets.Control.windowProc",
          "source": "Control.java:3107"
        },
        {
          "method": "org.eclipse.swt.widgets.Display.windowProc",
          "source": "Display.java:3706"
        },
        {
          "method": "org.eclipse.swt.internal.win32.OS.DefWindowProcW",
          "source": "Native Method"
        },
        {
          "method": "org.eclipse.swt.internal.win32.OS.DefWindowProc",
          "source": "OS.java:1651"
        },
        {
          "method": "org.eclipse.swt.widgets.Scrollable.callWindowProc",
          "source": "Scrollable.java:77"
        },
        {
          "method": "org.eclipse.swt.widgets.Control.windowProc",
          "source": "Control.java:3123"
        },
        {
          "method": "org.eclipse.swt.widgets.Display.windowProc",
          "source": "Display.java:3706"
        },
        {
          "method": "org.eclipse.swt.internal.win32.OS.SetWindowPos",
          "source": "Native Method"
        },
        {
          "method": "org.eclipse.swt.widgets.Widget.SetWindowPos",
          "source": "Widget.java:1140"
        },
        {
          "method": "org.eclipse.swt.widgets.Control.setBounds",
          "source": "Control.java:1952"
        },
        {
          "method": "org.eclipse.swt.widgets.Control.setBounds",
          "source": "Control.java:1933"
        },
        {
          "method": "org.eclipse.swt.widgets.Control.setBounds",
          "source": "Control.java:1929"
        },
        {
          "method": "org.eclipse.swt.layout.FillLayout.layout",
          "source": "FillLayout.java:198"
        },
        {
          "method": "org.eclipse.swt.widgets.Composite.updateLayout",
          "source": "Composite.java:869"
        },
        {
          "method": "org.eclipse.swt.widgets.Composite.layout",
          "source": "Composite.java:493"
        },
        {
          "method": "org.eclipse.swt.widgets.Composite.layout",
          "source": "Composite.java:458"
        },
        {
          "method": "org.eclipse.swt.widgets.Composite.layout",
          "source": "Composite.java:428"
        },
        {
          "method": "org.ies.ui.UIPanel.init",
          "source": "UIPanel.java:207"
        },
        {
          "method": "org.ies.ui.UIWindow.createUIPanelInstance",
          "source": "UIWindow.java:142"
        },
        {
          "method": "org.ies.ui.UIFrame.createCTabItem",
          "source": "UIFrame.java:374"
        },
        {
          "method": "org.ies.ui.UIFrame.init",
          "source": "UIFrame.java:146"
        },
        {
          "method": "org.ies.ui.UIApplication.showUIFrame",
          "source": "UIApplication.java:263"
        },
        {
          "method": "MainClass.UIFrame_Test_1",
          "source": "MainClass.java:194"
        },
        {
          "method": "MainClass.main",
          "source": "MainClass.java:208"
        }
      ],
      "number": 0,
      "commentIndex": 5,
      "bugId": "105544",
      "duplicateId": "98493",
      "date": "2005-10-23T01:24:58+02:00",
      "product": "Platform",
      "component": "SWT",
      "severity": "blocker"
    }
  ],
  "groupId": "98493",
  "bugId": "105544",
  "duplicateId": "98493",
  "date": "2005-07-29T04:27:21+02:00",
  "product": "Platform",
  "component": "SWT",
  "severity": "blocker"
}