{
  "comments": [
    "Version 0.7\n\n!ENTRY org.eclipse.wst.sse.core 4 4 2005-08-03 14:58:36.686\n!MESSAGE Resource /org.eclipse.search.tests is not open.\n!STACK 1\norg.eclipse.core.internal.resources.ResourceException: Resource\n/org.eclipse.search.tests is not open.\n        at\norg.eclipse.core.internal.resources.Project.checkAccessible(Project.java:127)\n        at org.eclipse.core.internal.resources.Container.members(Container.java:180)\n        at org.eclipse.core.internal.resources.Container.members(Container.java:163)\n        at\norg.eclipse.wst.sse.core.internal.tasks.WorkspaceTaskScanner.scan(WorkspaceTaskScanner.java:309)\n        at\norg.eclipse.wst.sse.core.internal.tasks.TaskScanningJob.run(TaskScanningJob.java:155)\n        at org.eclipse.core.internal.jobs.Worker.run(Worker.java:76)\n!SUBENTRY 1 org.eclipse.core.resources 4 372 2005-08-03 14:58:36.686\n!MESSAGE Resource /org.eclipse.search.tests is not open.",
    "Fixed in HEAD.  Thanks.",
    "This bug was moved to \u0027closed\u0027 state, since it is so old and it is assumed really fixed and no longer useful or need further attention. Feel free to re-open, or open a new bug, if this semi-automatic processing was done in error. "
  ],
  "commentCreationDates": [
    "2005-08-03T15:33:09+02:00",
    "2005-08-03T15:51:45+02:00",
    "2006-09-25T08:43:12+02:00"
  ],
  "traces": [
    {
      "exceptionType": "org.eclipse.core.internal.resources.ResourceException",
      "message": "Resource /org.eclipse.search.tests is not open.",
      "elements": [
        {
          "method": "org.eclipse.core.internal.resources.Project.checkAccessible",
          "source": "Project.java:127"
        },
        {
          "method": "org.eclipse.core.internal.resources.Container.members",
          "source": "Container.java:180"
        },
        {
          "method": "org.eclipse.core.internal.resources.Container.members",
          "source": "Container.java:163"
        },
        {
          "method": "org.eclipse.wst.sse.core.internal.tasks.WorkspaceTaskScanner.scan",
          "source": "WorkspaceTaskScanner.java:309"
        },
        {
          "method": "org.eclipse.wst.sse.core.internal.tasks.TaskScanningJob.run",
          "source": "TaskScanningJob.java:155"
        },
        {
          "method": "org.eclipse.core.internal.jobs.Worker.run",
          "source": "Worker.java:76"
        }
      ],
      "number": 0,
      "commentIndex": 0,
      "bugId": "105907",
      "date": "2005-08-03T15:33:09+02:00",
      "product": "Web Tools",
      "component": "wst.sse",
      "severity": "normal"
    }
  ],
  "groupId": "105907",
  "bugId": "105907",
  "date": "2005-08-03T15:33:09+02:00",
  "product": "Web Tools",
  "component": "wst.sse",
  "severity": "normal"
}