{
  "comments": [
    "Build id: I20050808-2000\n\ngo to windows-\u003epreferences-\u003egeneral-\u003eKeys (experimental)\nselect the \"Show All Commands\" check box.\nNote the table stop drawing, probably the code call Table.setRedraw(false),\nsomething bad happens, the code returns and never call Table.setRedraw(true) to\nturn redraw back on.\ntested on gtk and motif.",
    "Experimental. ",
    "walkback:\n!ENTRY org.eclipse.ui 4 0 2005-08-09 14:43:05.712\n!MESSAGE org.eclipse.core.commands.ParameterizedCommand\n!STACK 0\njava.lang.ClassCastException: org.eclipse.core.commands.ParameterizedCommand\n        at\norg.eclipse.ui.internal.keys.NewKeysPreferencePage$BindingSorter.compare(NewKeysPreferencePage.java:309)\n        at org.eclipse.jface.viewers.ViewerSorter$1.compare(ViewerSorter.java:177)\n        at java.util.Arrays.mergeSort(Arrays.java:1278)\n        at java.util.Arrays.mergeSort(Arrays.java:1289)\n        at java.util.Arrays.mergeSort(Arrays.java:1289)\n        at java.util.Arrays.mergeSort(Arrays.java:1290)\n        at java.util.Arrays.mergeSort(Arrays.java:1289)\n        at java.util.Arrays.mergeSort(Arrays.java:1289)\n        at java.util.Arrays.mergeSort(Arrays.java:1290)\n        at java.util.Arrays.mergeSort(Arrays.java:1289)\n        at java.util.Arrays.sort(Arrays.java:1219)\n        at org.eclipse.jface.viewers.ViewerSorter.sort(ViewerSorter.java:175)\n        at\norg.eclipse.jface.viewers.StructuredViewer.getSortedChildren(StructuredViewer.java:909)\n        at\norg.eclipse.jface.viewers.AbstractTreeViewer$1.run(AbstractTreeViewer.java:512)\n        at org.eclipse.swt.custom.BusyIndicator.showWhile(BusyIndicator.java:69)\n        at\norg.eclipse.jface.viewers.AbstractTreeViewer.createChildren(AbstractTreeViewer.java:494)\n        at\norg.eclipse.jface.viewers.AbstractTreeViewer$5.run(AbstractTreeViewer.java:983)\n        at\norg.eclipse.jface.viewers.StructuredViewer.preservingSelection(StructuredViewer.java:1201)\n        at\norg.eclipse.jface.viewers.AbstractTreeViewer.inputChanged(AbstractTreeViewer.java:973)\n        at org.eclipse.jface.viewers.ContentViewer.setInput(ContentViewer.java:248)\n        at\norg.eclipse.jface.viewers.StructuredViewer.setInput(StructuredViewer.java:1417)\n        at\norg.eclipse.ui.internal.keys.NewKeysPreferencePage.updateTree(NewKeysPreferencePage.java:1173)\n        at\norg.eclipse.ui.internal.keys.NewKeysPreferencePage.access$8(NewKeysPreferencePage.java:1041)\n        at\norg.eclipse.ui.internal.keys.NewKeysPreferencePage$5.widgetSelected(NewKeysPreferencePage.java:833)\n        at org.eclipse.swt.widgets.TypedListener.handleEvent(TypedListener.java:90)\n        at org.eclipse.swt.widgets.EventTable.sendEvent(EventTable.java:66)\n        at org.eclipse.swt.widgets.Widget.sendEvent(Widget.java:1036)\n        at org.eclipse.swt.widgets.Display.runDeferredEvents(Display.java:2863)\n        at org.eclipse.swt.widgets.Display.readAndDispatch(Display.java:2568)\n        at org.eclipse.jface.window.Window.runEventLoop(Window.java:809)\n        at org.eclipse.jface.window.Window.open(Window.java:787)\n        at\norg.eclipse.ui.internal.OpenPreferencesAction.run(OpenPreferencesAction.java:66)\n        at org.eclipse.jface.action.Action.runWithEvent(Action.java:996)\n        at\norg.eclipse.jface.action.ActionContributionItem.handleWidgetSelection(ActionContributionItem.java:538)\n        at\norg.eclipse.jface.action.ActionContributionItem.access$2(ActionContributionItem.java:488)\n        at\norg.eclipse.jface.action.ActionContributionItem$5.handleEvent(ActionContributionItem.java:400)\n        at org.eclipse.swt.widgets.EventTable.sendEvent(EventTable.java:66)\n        at org.eclipse.swt.widgets.Widget.sendEvent(Widget.java:1036)\n        at org.eclipse.swt.widgets.Display.runDeferredEvents(Display.java:2863)\n        at org.eclipse.swt.widgets.Display.readAndDispatch(Display.java:2568)\n        at org.eclipse.ui.internal.Workbench.runEventLoop(Workbench.java:1734)\n        at org.eclipse.ui.internal.Workbench.runUI(Workbench.java:1698)\n        at\norg.eclipse.ui.internal.Workbench.createAndRunWorkbench(Workbench.java:367)\n        at org.eclipse.ui.PlatformUI.createAndRunWorkbench(PlatformUI.java:143)\n        at org.eclipse.ui.internal.ide.IDEApplication.run(IDEApplication.java:103)\n        at\norg.eclipse.core.internal.runtime.PlatformActivator$1.run(PlatformActivator.java:226)\n        at\norg.eclipse.core.runtime.adaptor.EclipseStarter.run(EclipseStarter.java:376)\n        at\norg.eclipse.core.runtime.adaptor.EclipseStarter.run(EclipseStarter.java:163)\n        at sun.reflect.NativeMethodAccessorImpl.invoke0(Native Method)\n        at\nsun.reflect.NativeMethodAccessorImpl.invoke(NativeMethodAccessorImpl.java:39)\n        at\nsun.reflect.DelegatingMethodAccessorImpl.invoke(DelegatingMethodAccessorImpl.java:25)\n        at java.lang.reflect.Method.invoke(Method.java:324)\n        at org.eclipse.core.launcher.Main.invokeFramework(Main.java:338)\n        at org.eclipse.core.launcher.Main.basicRun(Main.java:282)\n        at org.eclipse.core.launcher.Main.run(Main.java:977)\n        at org.eclipse.core.launcher.Main.main(Main.java:952)\n",
    "This probably was the fastest bug open, assigned, and closed ever..."
  ],
  "commentCreationDates": [
    "2005-08-09T20:36:25+02:00",
    "2005-08-09T20:39:18+02:00",
    "2005-08-09T20:40:24+02:00",
    "2005-08-09T20:41:34+02:00"
  ],
  "traces": [
    {
      "exceptionType": "java.lang.ClassCastException",
      "message": "org.eclipse.core.commands.ParameterizedCommand",
      "elements": [
        {
          "method": "org.eclipse.ui.internal.keys.NewKeysPreferencePage$BindingSorter.compare",
          "source": "NewKeysPreferencePage.java:309"
        },
        {
          "method": "org.eclipse.jface.viewers.ViewerSorter$1.compare",
          "source": "ViewerSorter.java:177"
        },
        {
          "method": "java.util.Arrays.mergeSort",
          "source": "Arrays.java:1278"
        },
        {
          "method": "java.util.Arrays.mergeSort",
          "source": "Arrays.java:1289"
        },
        {
          "method": "java.util.Arrays.mergeSort",
          "source": "Arrays.java:1289"
        },
        {
          "method": "java.util.Arrays.mergeSort",
          "source": "Arrays.java:1290"
        },
        {
          "method": "java.util.Arrays.mergeSort",
          "source": "Arrays.java:1289"
        },
        {
          "method": "java.util.Arrays.mergeSort",
          "source": "Arrays.java:1289"
        },
        {
          "method": "java.util.Arrays.mergeSort",
          "source": "Arrays.java:1290"
        },
        {
          "method": "java.util.Arrays.mergeSort",
          "source": "Arrays.java:1289"
        },
        {
          "method": "java.util.Arrays.sort",
          "source": "Arrays.java:1219"
        },
        {
          "method": "org.eclipse.jface.viewers.ViewerSorter.sort",
          "source": "ViewerSorter.java:175"
        },
        {
          "method": "org.eclipse.jface.viewers.StructuredViewer.getSortedChildren",
          "source": "StructuredViewer.java:909"
        },
        {
          "method": "org.eclipse.jface.viewers.AbstractTreeViewer$1.run",
          "source": "AbstractTreeViewer.java:512"
        },
        {
          "method": "org.eclipse.swt.custom.BusyIndicator.showWhile",
          "source": "BusyIndicator.java:69"
        },
        {
          "method": "org.eclipse.jface.viewers.AbstractTreeViewer.createChildren",
          "source": "AbstractTreeViewer.java:494"
        },
        {
          "method": "org.eclipse.jface.viewers.AbstractTreeViewer$5.run",
          "source": "AbstractTreeViewer.java:983"
        },
        {
          "method": "org.eclipse.jface.viewers.StructuredViewer.preservingSelection",
          "source": "StructuredViewer.java:1201"
        },
        {
          "method": "org.eclipse.jface.viewers.AbstractTreeViewer.inputChanged",
          "source": "AbstractTreeViewer.java:973"
        },
        {
          "method": "org.eclipse.jface.viewers.ContentViewer.setInput",
          "source": "ContentViewer.java:248"
        },
        {
          "method": "org.eclipse.jface.viewers.StructuredViewer.setInput",
          "source": "StructuredViewer.java:1417"
        },
        {
          "method": "org.eclipse.ui.internal.keys.NewKeysPreferencePage.updateTree",
          "source": "NewKeysPreferencePage.java:1173"
        },
        {
          "method": "org.eclipse.ui.internal.keys.NewKeysPreferencePage.access$8",
          "source": "NewKeysPreferencePage.java:1041"
        },
        {
          "method": "org.eclipse.ui.internal.keys.NewKeysPreferencePage$5.widgetSelected",
          "source": "NewKeysPreferencePage.java:833"
        },
        {
          "method": "org.eclipse.swt.widgets.TypedListener.handleEvent",
          "source": "TypedListener.java:90"
        },
        {
          "method": "org.eclipse.swt.widgets.EventTable.sendEvent",
          "source": "EventTable.java:66"
        },
        {
          "method": "org.eclipse.swt.widgets.Widget.sendEvent",
          "source": "Widget.java:1036"
        },
        {
          "method": "org.eclipse.swt.widgets.Display.runDeferredEvents",
          "source": "Display.java:2863"
        },
        {
          "method": "org.eclipse.swt.widgets.Display.readAndDispatch",
          "source": "Display.java:2568"
        },
        {
          "method": "org.eclipse.jface.window.Window.runEventLoop",
          "source": "Window.java:809"
        },
        {
          "method": "org.eclipse.jface.window.Window.open",
          "source": "Window.java:787"
        },
        {
          "method": "org.eclipse.ui.internal.OpenPreferencesAction.run",
          "source": "OpenPreferencesAction.java:66"
        },
        {
          "method": "org.eclipse.jface.action.Action.runWithEvent",
          "source": "Action.java:996"
        },
        {
          "method": "org.eclipse.jface.action.ActionContributionItem.handleWidgetSelection",
          "source": "ActionContributionItem.java:538"
        },
        {
          "method": "org.eclipse.jface.action.ActionContributionItem.access$2",
          "source": "ActionContributionItem.java:488"
        },
        {
          "method": "org.eclipse.jface.action.ActionContributionItem$5.handleEvent",
          "source": "ActionContributionItem.java:400"
        },
        {
          "method": "org.eclipse.swt.widgets.EventTable.sendEvent",
          "source": "EventTable.java:66"
        },
        {
          "method": "org.eclipse.swt.widgets.Widget.sendEvent",
          "source": "Widget.java:1036"
        },
        {
          "method": "org.eclipse.swt.widgets.Display.runDeferredEvents",
          "source": "Display.java:2863"
        },
        {
          "method": "org.eclipse.swt.widgets.Display.readAndDispatch",
          "source": "Display.java:2568"
        },
        {
          "method": "org.eclipse.ui.internal.Workbench.runEventLoop",
          "source": "Workbench.java:1734"
        },
        {
          "method": "org.eclipse.ui.internal.Workbench.runUI",
          "source": "Workbench.java:1698"
        },
        {
          "method": "org.eclipse.ui.internal.Workbench.createAndRunWorkbench",
          "source": "Workbench.java:367"
        },
        {
          "method": "org.eclipse.ui.PlatformUI.createAndRunWorkbench",
          "source": "PlatformUI.java:143"
        },
        {
          "method": "org.eclipse.ui.internal.ide.IDEApplication.run",
          "source": "IDEApplication.java:103"
        },
        {
          "method": "org.eclipse.core.internal.runtime.PlatformActivator$1.run",
          "source": "PlatformActivator.java:226"
        },
        {
          "method": "org.eclipse.core.runtime.adaptor.EclipseStarter.run",
          "source": "EclipseStarter.java:376"
        },
        {
          "method": "org.eclipse.core.runtime.adaptor.EclipseStarter.run",
          "source": "EclipseStarter.java:163"
        },
        {
          "method": "sun.reflect.NativeMethodAccessorImpl.invoke0",
          "source": "Native Method"
        },
        {
          "method": "sun.reflect.NativeMethodAccessorImpl.invoke",
          "source": "NativeMethodAccessorImpl.java:39"
        },
        {
          "method": "sun.reflect.DelegatingMethodAccessorImpl.invoke",
          "source": "DelegatingMethodAccessorImpl.java:25"
        },
        {
          "method": "java.lang.reflect.Method.invoke",
          "source": "Method.java:324"
        },
        {
          "method": "org.eclipse.core.launcher.Main.invokeFramework",
          "source": "Main.java:338"
        },
        {
          "method": "org.eclipse.core.launcher.Main.basicRun",
          "source": "Main.java:282"
        },
        {
          "method": "org.eclipse.core.launcher.Main.run",
          "source": "Main.java:977"
        },
        {
          "method": "org.eclipse.core.launcher.Main.main",
          "source": "Main.java:952"
        }
      ],
      "number": 0,
      "commentIndex": 2,
      "bugId": "106538",
      "date": "2005-08-09T20:40:24+02:00",
      "product": "Platform",
      "component": "UI",
      "severity": "normal"
    }
  ],
  "groupId": "106538",
  "bugId": "106538",
  "date": "2005-08-09T20:36:25+02:00",
  "product": "Platform",
  "component": "UI",
  "severity": "normal"
}