{
  "comments": [
    "Reported by Tim Munro\n--\n\n!ENTRY org.eclipse.jface 4 2 2005-08-09 11:25:52.314\n\n!MESSAGE Problems occurred when invoking code from plug-in: \"org.eclipse.jface\".\n\n!STACK 0\n\njava.lang.NoSuchMethodError:\norg.eclipse.mylar.core.internal.MylarContextManager.actionObserved(Lorg/eclipse/jface/action/IAction;Ljava/lang/String;)V\n\n      at\norg.eclipse.mylar.tasklist.ui.actions.TaskActivateAction.run(TaskActivateAction.java:34)\n\n      at\norg.eclipse.mylar.tasklist.ui.views.TaskListView$TaskListCellModifier.modify(TaskListView.java:581)\n\n      at\norg.eclipse.jface.viewers.TreeEditorImpl.saveEditorValue(TreeEditorImpl.java:310)\n\n      at\norg.eclipse.jface.viewers.TreeEditorImpl.applyEditorValue(TreeEditorImpl.java:161)\n\n      at\norg.eclipse.jface.viewers.TreeEditorImpl$3.applyEditorValue(TreeEditorImpl.java:286)\n\n      at org.eclipse.jface.viewers.CellEditor$1.run(CellEditor.java:304)\n\n      at\norg.eclipse.core.internal.runtime.InternalPlatform.run(InternalPlatform.java:1044)\n\n      at org.eclipse.core.runtime.Platform.run(Platform.java:783)\n\n      at org.eclipse.ui.internal.JFaceUtil$1.run(JFaceUtil.java:44)\n\n      at org.eclipse.jface.util.SafeRunnable.run(SafeRunnable.java:148)\n\n      at\norg.eclipse.jface.viewers.CellEditor.fireApplyEditorValue(CellEditor.java:302)\n\n      at\norg.eclipse.jface.viewers.CheckboxCellEditor.activate(CheckboxCellEditor.java:84)\n\n      at\norg.eclipse.jface.viewers.TreeEditorImpl.activateCellEditor(TreeEditorImpl.java:83)\n\n      at\norg.eclipse.jface.viewers.TreeEditorImpl.activateCellEditor(TreeEditorImpl.java:145)\n\n      at\norg.eclipse.jface.viewers.TreeEditorImpl.handleMouseDown(TreeEditorImpl.java:271)\n\n      at org.eclipse.jface.viewers.TreeViewer$1.mouseDown(TreeViewer.java:435)\n\n      at org.eclipse.swt.widgets.TypedListener.handleEvent(TypedListener.java:133)\n\n      at org.eclipse.swt.widgets.EventTable.sendEvent(EventTable.java:66)\n\n      at org.eclipse.swt.widgets.Widget.sendEvent(Widget.java:843)\n\n      at org.eclipse.swt.widgets.Display.runDeferredEvents(Display.java:3080)\n\n      at org.eclipse.swt.widgets.Display.readAndDispatch(Display.java:2713)\n\n      at org.eclipse.ui.internal.Workbench.runEventLoop(Workbench.java:1699)\n\n      at org.eclipse.ui.internal.Workbench.runUI(Workbench.java:1663)\n\n      at org.eclipse.ui.internal.Workbench.createAndRunWorkbench(Workbench.java:367)\n\n      at org.eclipse.ui.PlatformUI.createAndRunWorkbench(PlatformUI.java:143)\n\n      at org.eclipse.ui.internal.ide.IDEApplication.run(IDEApplication.java:103)\n\n      at\norg.eclipse.core.internal.runtime.PlatformActivator$1.run(PlatformActivator.java:226)\n\n      at\norg.eclipse.core.runtime.adaptor.EclipseStarter.run(EclipseStarter.java:376)\n\n      at\norg.eclipse.core.runtime.adaptor.EclipseStarter.run(EclipseStarter.java:163)\n\n      at sun.reflect.NativeMethodAccessorImpl.invoke0(Native Method)\n\n      at\nsun.reflect.NativeMethodAccessorImpl.invoke(NativeMethodAccessorImpl.java:39)\n\n      at\nsun.reflect.DelegatingMethodAccessorImpl.invoke(DelegatingMethodAccessorImpl.java:25)\n\n      at java.lang.reflect.Method.invoke(Method.java:585)\n\n      at org.eclipse.core.launcher.Main.invokeFramework(Main.java:334)\n\n      at org.eclipse.core.launcher.Main.basicRun(Main.java:278)\n\n      at org.eclipse.core.launcher.Main.run(Main.java:973)\n\n      at org.eclipse.core.launcher.Main.main(Main.java:948)",
    "The only way that this should happen is if there is an old version of\norg.eclipse.mylar.core laying around, which doesn?t have that actionObserved\nmethod, or installing the core failed somehow.\n\nPlease try the following in the Manage Configuration dialog:\n1.\tRight-click to disable all of the visible mylar features and allow Eclipse to\nrestart\n2.\tRight-click each of the visible Mylar features to uninstall it (make sure\nthat the ?Show Disabled Features? toolbar button is pressed).  You only need to\nrestart after the last one is uninstalled.\n3.\tRe-install Mylar from the update site",
    "Fixed by following steps above.  This should not happen, but for now we will\nassume that the problem is not on our end.\n"
  ],
  "commentCreationDates": [
    "2005-08-10T16:32:28+02:00",
    "2005-08-10T16:51:08+02:00",
    "2005-08-10T18:20:39+02:00"
  ],
  "traces": [
    {
      "exceptionType": "java.lang.NoSuchMethodError",
      "message": "org.eclipse.mylar.core.internal.MylarContextManager.actionObserved(Lorg/eclipse/jface/action/IAction;Ljava/lang/String;)V",
      "elements": [
        {
          "method": "org.eclipse.mylar.tasklist.ui.actions.TaskActivateAction.run",
          "source": "TaskActivateAction.java:34"
        },
        {
          "method": "org.eclipse.mylar.tasklist.ui.views.TaskListView$TaskListCellModifier.modify",
          "source": "TaskListView.java:581"
        },
        {
          "method": "org.eclipse.jface.viewers.TreeEditorImpl.saveEditorValue",
          "source": "TreeEditorImpl.java:310"
        },
        {
          "method": "org.eclipse.jface.viewers.TreeEditorImpl.applyEditorValue",
          "source": "TreeEditorImpl.java:161"
        },
        {
          "method": "org.eclipse.jface.viewers.TreeEditorImpl$3.applyEditorValue",
          "source": "TreeEditorImpl.java:286"
        },
        {
          "method": "org.eclipse.jface.viewers.CellEditor$1.run",
          "source": "CellEditor.java:304"
        },
        {
          "method": "org.eclipse.core.internal.runtime.InternalPlatform.run",
          "source": "InternalPlatform.java:1044"
        },
        {
          "method": "org.eclipse.core.runtime.Platform.run",
          "source": "Platform.java:783"
        },
        {
          "method": "org.eclipse.ui.internal.JFaceUtil$1.run",
          "source": "JFaceUtil.java:44"
        },
        {
          "method": "org.eclipse.jface.util.SafeRunnable.run",
          "source": "SafeRunnable.java:148"
        },
        {
          "method": "org.eclipse.jface.viewers.CellEditor.fireApplyEditorValue",
          "source": "CellEditor.java:302"
        },
        {
          "method": "org.eclipse.jface.viewers.CheckboxCellEditor.activate",
          "source": "CheckboxCellEditor.java:84"
        },
        {
          "method": "org.eclipse.jface.viewers.TreeEditorImpl.activateCellEditor",
          "source": "TreeEditorImpl.java:83"
        },
        {
          "method": "org.eclipse.jface.viewers.TreeEditorImpl.activateCellEditor",
          "source": "TreeEditorImpl.java:145"
        },
        {
          "method": "org.eclipse.jface.viewers.TreeEditorImpl.handleMouseDown",
          "source": "TreeEditorImpl.java:271"
        },
        {
          "method": "org.eclipse.jface.viewers.TreeViewer$1.mouseDown",
          "source": "TreeViewer.java:435"
        },
        {
          "method": "org.eclipse.swt.widgets.TypedListener.handleEvent",
          "source": "TypedListener.java:133"
        },
        {
          "method": "org.eclipse.swt.widgets.EventTable.sendEvent",
          "source": "EventTable.java:66"
        },
        {
          "method": "org.eclipse.swt.widgets.Widget.sendEvent",
          "source": "Widget.java:843"
        },
        {
          "method": "org.eclipse.swt.widgets.Display.runDeferredEvents",
          "source": "Display.java:3080"
        },
        {
          "method": "org.eclipse.swt.widgets.Display.readAndDispatch",
          "source": "Display.java:2713"
        },
        {
          "method": "org.eclipse.ui.internal.Workbench.runEventLoop",
          "source": "Workbench.java:1699"
        },
        {
          "method": "org.eclipse.ui.internal.Workbench.runUI",
          "source": "Workbench.java:1663"
        },
        {
          "method": "org.eclipse.ui.internal.Workbench.createAndRunWorkbench",
          "source": "Workbench.java:367"
        },
        {
          "method": "org.eclipse.ui.PlatformUI.createAndRunWorkbench",
          "source": "PlatformUI.java:143"
        },
        {
          "method": "org.eclipse.ui.internal.ide.IDEApplication.run",
          "source": "IDEApplication.java:103"
        },
        {
          "method": "org.eclipse.core.internal.runtime.PlatformActivator$1.run",
          "source": "PlatformActivator.java:226"
        },
        {
          "method": "org.eclipse.core.runtime.adaptor.EclipseStarter.run",
          "source": "EclipseStarter.java:376"
        },
        {
          "method": "org.eclipse.core.runtime.adaptor.EclipseStarter.run",
          "source": "EclipseStarter.java:163"
        },
        {
          "method": "sun.reflect.NativeMethodAccessorImpl.invoke0",
          "source": "Native Method"
        },
        {
          "method": "sun.reflect.NativeMethodAccessorImpl.invoke",
          "source": "NativeMethodAccessorImpl.java:39"
        },
        {
          "method": "sun.reflect.DelegatingMethodAccessorImpl.invoke",
          "source": "DelegatingMethodAccessorImpl.java:25"
        },
        {
          "method": "java.lang.reflect.Method.invoke",
          "source": "Method.java:585"
        },
        {
          "method": "org.eclipse.core.launcher.Main.invokeFramework",
          "source": "Main.java:334"
        },
        {
          "method": "org.eclipse.core.launcher.Main.basicRun",
          "source": "Main.java:278"
        },
        {
          "method": "org.eclipse.core.launcher.Main.run",
          "source": "Main.java:973"
        },
        {
          "method": "org.eclipse.core.launcher.Main.main",
          "source": "Main.java:948"
        }
      ],
      "number": 0,
      "commentIndex": 0,
      "bugId": "106629",
      "date": "2005-08-10T16:32:28+02:00",
      "product": "Mylyn",
      "component": "Core",
      "severity": "blocker"
    }
  ],
  "groupId": "106629",
  "bugId": "106629",
  "date": "2005-08-10T16:32:28+02:00",
  "product": "Mylyn",
  "component": "Core",
  "severity": "blocker"
}