{
  "comments": [
    "I downloaded org.eclipse.cdt-3.0.0-I200508081313-linux.x86.tar.gz\nand created a new C++ project.\nDuring the creation and building of the project I got the following Java \nexceptions: \njava.lang.ClassCastException\n        at \norg.eclipse.cdt.internal.core.dom.parser.cpp.CPPClassScope.createImplicitMembers\n(CPPClassScope.\n\njava:85)\n        at org.eclipse.cdt.internal.core.dom.parser.cpp.CPPClassScope.\u003cinit\u003e\n(CPPClassScope.java:60)\n        at \norg.eclipse.cdt.internal.core.dom.parser.cpp.CPPASTCompositeTypeSpecifier.getSco\npe(\n\nCPPASTCompositeTypeSpecifier.java:112)\n        at \norg.eclipse.cdt.internal.core.dom.parser.cpp.CPPVisitor.getContainingScope\n(CPPVisitor.java:668)\n        at \norg.eclipse.cdt.internal.core.dom.parser.cpp.CPPVisitor.getContainingScope\n(CPPVisitor.java:835)\n        at \norg.eclipse.cdt.internal.core.dom.parser.cpp.CPPVisitor.getContainingScope\n(CPPVisitor.java:657)\n  at org.eclipse.cdt.internal.core.dom.parser.cpp.CPPVisitor.createBinding\n(CPPVisitor.java:481)\n        at org.eclipse.cdt.internal.core.dom.parser.cpp.CPPVisitor.createBinding\n(CPPVisitor.java:188)\n        at \norg.eclipse.cdt.internal.core.dom.parser.cpp.CPPASTName.resolveBinding\n(CPPASTName.java:52)\n        at \norg.eclipse.cdt.internal.core.index.domsourceindexer.CPPGenerateIndexVisitor.pro\ncessName(\n\nCPPGenerateIndexVisitor.java:148)\n        at \norg.eclipse.cdt.internal.core.index.domsourceindexer.CPPGenerateIndexVisitor.vis\nit(\n\nCPPGenerateIndexVisitor.java:112)\n        at org.eclipse.cdt.internal.core.dom.parser.cpp.CPPASTName.accept\n(CPPASTName.java:90)\n        at org.eclipse.cdt.internal.core.dom.parser.cpp.CPPASTDeclarator.accept\n(CPPASTDeclarator.java:126)\n        at \norg.eclipse.cdt.internal.core.dom.parser.cpp.CPPASTSimpleDeclaration.accept(\n\nCPPASTSimpleDeclaration.java:74)\n        at \norg.eclipse.cdt.internal.core.dom.parser.cpp.CPPASTCompositeTypeSpecifier.accept\n(\n\nCPPASTCompositeTypeSpecifier.java:136)\n        at \norg.eclipse.cdt.internal.core.dom.parser.cpp.CPPASTSimpleDeclaration.accept(\n\nCPPASTSimpleDeclaration.java:71)\n        at \norg.eclipse.cdt.internal.core.dom.parser.cpp.CPPASTTemplateDeclaration.accept(\n\nCPPASTTemplateDeclaration.java:95)\n        at \norg.eclipse.cdt.internal.core.dom.parser.cpp.CPPASTTranslationUnit.accept\n(CPPASTTranslationUnit.\n\njava:520)\n        at \norg.eclipse.cdt.internal.core.index.domsourceindexer.DOMSourceIndexerRunner.inde\nxFile(\n\nDOMSourceIndexerRunner.java:133)\n        at \norg.eclipse.cdt.internal.core.index.domsourceindexer.AbstractIndexerRunner.index\n(\n\nAbstractIndexerRunner.java:76)\n        at org.eclipse.cdt.internal.core.index.cindexstorage.Index.add\n(Index.java:110)\n        at \norg.eclipse.cdt.internal.core.index.domsourceindexer.DOMAddCompilationUnitToInde\nx.indexDocument(\n\nDOMAddCompilationUnitToIndex.java:29)\n        at \norg.eclipse.cdt.internal.core.index.domsourceindexer.DOMAddFileToIndex.execute\n(DOMAddFileToIndex.\n\njava:60)\n        at org.eclipse.cdt.internal.core.search.processing.JobManager.run\n(JobManager.java:466)\n        at java.lang.Thread.run(Thread.java:534)\njava.lang.ClassCastException\n        at \norg.eclipse.cdt.internal.core.dom.parser.cpp.CPPClassScope.createImplicitMembers\n(CPPClassScope.\n\njava:85)\n        at org.eclipse.cdt.internal.core.dom.parser.cpp.CPPClassScope.\u003cinit\u003e\n(CPPClassScope.java:60)\n        at \norg.eclipse.cdt.internal.core.dom.parser.cpp.CPPASTCompositeTypeSpecifier.getSco\npe(\n\nCPPASTCompositeTypeSpecifier.java:112)\n        at \norg.eclipse.cdt.internal.core.dom.parser.cpp.CPPVisitor.getContainingScope\n(CPPVisitor.java:668)\n        at \norg.eclipse.cdt.internal.core.dom.parser.cpp.CPPVisitor.getContainingScope\n(CPPVisitor.java:835)\n        at \norg.eclipse.cdt.internal.core.dom.parser.cpp.CPPSemantics.getLookupScope\n(CPPSemantics.java:907)\n        at org.eclipse.cdt.internal.core.dom.parser.cpp.CPPSemantics.lookup\n(CPPSemantics.java:987)\n        at \norg.eclipse.cdt.internal.core.dom.parser.cpp.CPPSemantics.resolveBinding\n(CPPSemantics.java:610)\n        at org.eclipse.cdt.internal.core.dom.parser.cpp.CPPVisitor.createBinding\n(CPPVisitor.java:164)\n        at \norg.eclipse.cdt.internal.core.dom.parser.cpp.CPPASTName.resolveBinding\n(CPPASTName.java:52)\n        at \norg.eclipse.cdt.internal.core.dom.parser.cpp.CPPTemplates.createClassSpecializat\nion(CPPTemplates.\n\njava:297)\n        at \norg.eclipse.cdt.internal.core.dom.parser.cpp.CPPTemplates.createBinding\n(CPPTemplates.java:224)\n        at \norg.eclipse.cdt.internal.core.dom.parser.cpp.CPPASTTemplateId.resolveBinding\n(CPPASTTemplateId.java\n\n:74)\n        at \norg.eclipse.cdt.internal.core.index.domsourceindexer.CPPGenerateIndexVisitor.add\nFriendDeclarations\n\n(CPPGenerateIndexVisitor.java:426)\n        at \norg.eclipse.cdt.internal.core.index.domsourceindexer.CPPGenerateIndexVisitor.pro\ncessNameBinding(\n\nCPPGenerateIndexVisitor.java:235)\n        at \norg.eclipse.cdt.internal.core.index.domsourceindexer.CPPGenerateIndexVisitor.pro\ncessName(\n\nCPPGenerateIndexVisitor.java:169)\n        at \norg.eclipse.cdt.internal.core.index.domsourceindexer.CPPGenerateIndexVisitor.vis\nit(\n\nCPPGenerateIndexVisitor.java:112)\n        at org.eclipse.cdt.internal.core.dom.parser.cpp.CPPASTName.accept\n(CPPASTName.java:90)\n        at \norg.eclipse.cdt.internal.core.dom.parser.cpp.CPPASTCompositeTypeSpecifier.accept\n(\n\nCPPASTCompositeTypeSpecifier.java:129)\n        at \norg.eclipse.cdt.internal.core.dom.parser.cpp.CPPASTSimpleDeclaration.accept(\n\nCPPASTSimpleDeclaration.java:71)\n        at \norg.eclipse.cdt.internal.core.dom.parser.cpp.CPPASTTemplateDeclaration.accept(\n\nCPPASTTemplateDeclaration.java:95)\n        at \norg.eclipse.cdt.internal.core.dom.parser.cpp.CPPASTTranslationUnit.accept\n(CPPASTTranslationUnit.\n\njava:520)\n        at \norg.eclipse.cdt.internal.core.index.domsourceindexer.DOMSourceIndexerRunner.inde\nxFile(\n\nDOMSourceIndexerRunner.java:133)\n        at \norg.eclipse.cdt.internal.core.index.domsourceindexer.AbstractIndexerRunner.index\n(\n\nAbstractIndexerRunner.java:76)\n        at org.eclipse.cdt.internal.core.index.cindexstorage.Index.add\n(Index.java:110)\n        at \norg.eclipse.cdt.internal.core.index.domsourceindexer.DOMAddCompilationUnitToInde\nx.indexDocument(\n\nDOMAddCompilationUnitToIndex.java:29)\n        at \norg.eclipse.cdt.internal.core.index.domsourceindexer.DOMAddFileToIndex.execute\n(DOMAddFileToIndex.\n\njava:60)\n        at org.eclipse.cdt.internal.core.search.processing.JobManager.run\n(JobManager.java:466)\n        at java.lang.Thread.run(Thread.java:534)\n\n22 gmilman on ~\u003ejava.lang.ClassCastException: \norg.eclipse.cdt.internal.core.dom.parser.cpp.\n\nCPPTemplateDefinition$CPPTemplateProblem\n  at \norg.eclipse.cdt.internal.core.dom.parser.cpp.CPPClassScope.createImplicitMembers\n(CPPClassScope.java:85)\n        at org.eclipse.cdt.internal.core.dom.parser.cpp.CPPClassScope.\u003cinit\u003e\n(CPPClassScope.java:60)\n        at \norg.eclipse.cdt.internal.core.dom.parser.cpp.CPPASTCompositeTypeSpecifier.getSco\npe(\n\nCPPASTCompositeTypeSpecifier.java:112)\n        at \norg.eclipse.cdt.internal.core.dom.parser.cpp.CPPVisitor.getContainingScope\n(CPPVisitor.java:668)\n        at \norg.eclipse.cdt.internal.core.dom.parser.cpp.CPPVisitor.getContainingScope\n(CPPVisitor.java:835)\n        at \norg.eclipse.cdt.internal.core.dom.parser.cpp.CPPVisitor.getContainingScope\n(CPPVisitor.java:657)\n        at org.eclipse.cdt.internal.core.dom.parser.cpp.CPPVisitor.createBinding\n(CPPVisitor.java:481)\n        at org.eclipse.cdt.internal.core.dom.parser.cpp.CPPVisitor.createBinding\n(CPPVisitor.java:188)\n        at \norg.eclipse.cdt.internal.core.dom.parser.cpp.CPPASTName.resolveBinding\n(CPPASTName.java:52)\n        at \norg.eclipse.cdt.internal.core.index.domsourceindexer.CPPGenerateIndexVisitor.pro\ncessName(\n\nCPPGenerateIndexVisitor.java:148)\n        at \norg.eclipse.cdt.internal.core.index.domsourceindexer.CPPGenerateIndexVisitor.vis\nit(\n\nCPPGenerateIndexVisitor.java:112)\n        at org.eclipse.cdt.internal.core.dom.parser.cpp.CPPASTName.accept\n(CPPASTName.java:90)\n        at org.eclipse.cdt.internal.core.dom.parser.cpp.CPPASTDeclarator.accept\n(CPPASTDeclarator.java:126)\n        at \norg.eclipse.cdt.internal.core.dom.parser.cpp.CPPASTSimpleDeclaration.accept(\n\nCPPASTSimpleDeclaration.java:74)\n        at \norg.eclipse.cdt.internal.core.dom.parser.cpp.CPPASTCompositeTypeSpecifier.accept\n(\n\nCPPASTCompositeTypeSpecifier.java:136)\n        at \norg.eclipse.cdt.internal.core.dom.parser.cpp.CPPASTSimpleDeclaration.accept(\n\nCPPASTSimpleDeclaration.java:71)\n  at \norg.eclipse.cdt.internal.core.dom.parser.cpp.CPPASTTemplateDeclaration.accept\n(CPPASTTemplateDeclaration.\n\njava:95)\n        at \norg.eclipse.cdt.internal.core.dom.parser.cpp.CPPASTTranslationUnit.accept\n(CPPASTTranslationUnit.\n\njava:520)\n        at \norg.eclipse.cdt.internal.core.index.domsourceindexer.DOMSourceIndexerRunner.inde\nxFile(\n\nDOMSourceIndexerRunner.java:133)\n        at \norg.eclipse.cdt.internal.core.index.domsourceindexer.AbstractIndexerRunner.index\n(\n\nAbstractIndexerRunner.java:76)\n        at org.eclipse.cdt.internal.core.index.cindexstorage.Index.add\n(Index.java:110)\n        at \norg.eclipse.cdt.internal.core.index.domsourceindexer.DOMAddCompilationUnitToInde\nx.indexDocument(\n\nDOMAddCompilationUnitToIndex.java:29)\n        at \norg.eclipse.cdt.internal.core.index.domsourceindexer.DOMAddFileToIndex.execute\n(DOMAddFileToIndex.\n\njava:60)\n        at org.eclipse.cdt.internal.core.search.processing.JobManager.run\n(JobManager.java:466)\n        at java.lang.Thread.run(Thread.java:534)\njava.lang.ClassCastException: org.eclipse.cdt.internal.core.dom.parser.cpp.\n\nCPPTemplateDefinition$CPPTemplateProblem\n        at \norg.eclipse.cdt.internal.core.dom.parser.cpp.CPPSemantics.getTargetParameterType\ns(CPPSemantics.\n\njava:2141)\n        at \norg.eclipse.cdt.internal.core.dom.parser.cpp.CPPSemantics.resolveFunction\n(CPPSemantics.java:2219)\n        at \norg.eclipse.cdt.internal.core.dom.parser.cpp.CPPSemantics.resolveAmbiguities\n(CPPSemantics.java:\n\n1993)\n        at \norg.eclipse.cdt.internal.core.dom.parser.cpp.CPPSemantics.resolveBinding\n(CPPSemantics.java:621)\n        at \norg.eclipse.cdt.internal.core.dom.parser.cpp.CPPVisitor.resolveBinding\n(CPPVisitor.java:927)\n        at org.eclipse.cdt.internal.core.dom.parser.cpp.CPPVisitor.createBinding\n(CPPVisitor.java:182)\n        at \norg.eclipse.cdt.internal.core.dom.parser.cpp.CPPASTName.resolveBinding\n(CPPASTName.java:52)\n        at \norg.eclipse.cdt.internal.core.index.domsourceindexer.CPPGenerateIndexVisitor.pro\ncessName(\n\nCPPGenerateIndexVisitor.java:148)\n        at \norg.eclipse.cdt.internal.core.index.domsourceindexer.CPPGenerateIndexVisitor.vis\nit(\n\nCPPGenerateIndexVisitor.java:112)\n        at org.eclipse.cdt.internal.core.dom.parser.cpp.CPPASTName.accept\n(CPPASTName.java:90)\n        at \norg.eclipse.cdt.internal.core.dom.parser.cpp.CPPASTIdExpression.accept\n(CPPASTIdExpression.java:46)\n  at \norg.eclipse.cdt.internal.core.dom.parser.cpp.CPPASTFunctionCallExpression.accept\n(\n\nCPPASTFunctionCallExpression.java:64)\n        at \norg.eclipse.cdt.internal.core.dom.parser.cpp.CPPASTInitializerExpression.accept(\n\nCPPASTInitializerExpression.java:49)\n        at \norg.eclipse.cdt.internal.core.dom.parser.cpp.CPPASTDeclarator.postAccept\n(CPPASTDeclarator.java:135)\n        at org.eclipse.cdt.internal.core.dom.parser.cpp.CPPASTDeclarator.accept\n(CPPASTDeclarator.java:131)\n        at \norg.eclipse.cdt.internal.core.dom.parser.cpp.CPPASTSimpleDeclaration.accept(\n\nCPPASTSimpleDeclaration.java:74)\n        at \norg.eclipse.cdt.internal.core.dom.parser.cpp.CPPASTDeclarationStatement.accept(\n\nCPPASTDeclarationStatement.java:49)\n        at \norg.eclipse.cdt.internal.core.dom.parser.cpp.CPPASTCompoundStatement.accept(\n\nCPPASTCompoundStatement.java:66)\n        at \norg.eclipse.cdt.internal.core.dom.parser.cpp.CPPASTFunctionDefinition.accept(\n\nCPPASTFunctionDefinition.java:93)\n        at \norg.eclipse.cdt.internal.core.dom.parser.cpp.CPPASTTemplateDeclaration.accept(\n\nCPPASTTemplateDeclaration.java:95)\n        at \norg.eclipse.cdt.internal.core.dom.parser.cpp.CPPASTTranslationUnit.accept\n(CPPASTTranslationUnit.\n\njava:520)\n        at \norg.eclipse.cdt.internal.core.index.domsourceindexer.DOMSourceIndexerRunner.inde\nxFile(\n\nDOMSourceIndexerRunner.java:133)\n        at \norg.eclipse.cdt.internal.core.index.domsourceindexer.AbstractIndexerRunner.index\n(\n\nAbstractIndexerRunner.java:76)\n        at org.eclipse.cdt.internal.core.index.cindexstorage.Index.add\n(Index.java:110)\n        at \norg.eclipse.cdt.internal.core.index.domsourceindexer.DOMAddCompilationUnitToInde\nx.indexDocument(\n\nDOMAddCompilationUnitToIndex.java:29)\n        at \norg.eclipse.cdt.internal.core.index.domsourceindexer.DOMAddFileToIndex.execute\n(DOMAddFileToIndex.\n\njava:60)\n        at org.eclipse.cdt.internal.core.search.processing.JobManager.run\n(JobManager.java:466)\n  at java.lang.Thread.run(Thread.java:534)\n\n22 gmilman on ~\u003e\n22 gmilman on ~\u003ejava.lang.ClassCastException: \norg.eclipse.cdt.internal.core.dom.parser.cpp.\n\nCPPTemplateDefinition$CPPTemplateProblem\n        at \norg.eclipse.cdt.internal.core.dom.parser.cpp.CPPClassScope.createImplicitMembers\n(CPPClassScope.\n\njava:85)\n        at org.eclipse.cdt.internal.core.dom.parser.cpp.CPPClassScope.\u003cinit\u003e\n(CPPClassScope.java:60)\n        at \norg.eclipse.cdt.internal.core.dom.parser.cpp.CPPASTCompositeTypeSpecifier.getSco\npe(\n\nCPPASTCompositeTypeSpecifier.java:112)\n        at \norg.eclipse.cdt.internal.core.dom.parser.cpp.CPPVisitor.getContainingScope\n(CPPVisitor.java:668)\n        at \norg.eclipse.cdt.internal.core.dom.parser.cpp.CPPVisitor.getContainingScope\n(CPPVisitor.java:835)\n        at \norg.eclipse.cdt.internal.core.dom.parser.cpp.CPPVisitor.getContainingScope\n(CPPVisitor.java:657)\n        at org.eclipse.cdt.internal.core.dom.parser.cpp.CPPVisitor.createBinding\n(CPPVisitor.java:481)\n        at org.eclipse.cdt.internal.core.dom.parser.cpp.CPPVisitor.createBinding\n(CPPVisitor.java:188)\n        at \norg.eclipse.cdt.internal.core.dom.parser.cpp.CPPASTName.resolveBinding\n(CPPASTName.java:52)\n        at \norg.eclipse.cdt.internal.core.index.domsourceindexer.CPPGenerateIndexVisitor.pro\ncessName(\n\nCPPGenerateIndexVisitor.java:148)\n        at \norg.eclipse.cdt.internal.core.index.domsourceindexer.CPPGenerateIndexVisitor.vis\nit(\n\nCPPGenerateIndexVisitor.java:112)\n        at org.eclipse.cdt.internal.core.dom.parser.cpp.CPPASTName.accept\n(CPPASTName.java:90)\n        at org.eclipse.cdt.internal.core.dom.parser.cpp.CPPASTDeclarator.accept\n(CPPASTDeclarator.java:126)\n        at \norg.eclipse.cdt.internal.core.dom.parser.cpp.CPPASTSimpleDeclaration.accept(\n\nCPPASTSimpleDeclaration.java:74)\n        at \norg.eclipse.cdt.internal.core.dom.parser.cpp.CPPASTCompositeTypeSpecifier.accept\n(\n\nCPPASTCompositeTypeSpecifier.java:136)\n        at \norg.eclipse.cdt.internal.core.dom.parser.cpp.CPPASTSimpleDeclaration.accept(\n\nCPPASTSimpleDeclaration.java:71)\n        at \norg.eclipse.cdt.internal.core.dom.parser.cpp.CPPASTTemplateDeclaration.accept(\n\nCPPASTTemplateDeclaration.java:95)\n        at \norg.eclipse.cdt.internal.core.dom.parser.cpp.CPPASTTranslationUnit.accept\n(CPPASTTranslationUnit.\n\njava:520)\n        at \norg.eclipse.cdt.internal.core.index.domsourceindexer.DOMSourceIndexerRunner.inde\nxFile(\n\nDOMSourceIndexerRunner.java:133)\n        at \norg.eclipse.cdt.internal.core.index.domsourceindexer.AbstractIndexerRunner.index\n(\n\nAbstractIndexerRunner.java:76)\n        at org.eclipse.cdt.internal.core.index.cindexstorage.Index.add\n(Index.java:110)\n        at \norg.eclipse.cdt.internal.core.index.domsourceindexer.DOMAddCompilationUnitToInde\nx.indexDocument(\n\nDOMAddCompilationUnitToIndex.java:29)\n        at \norg.eclipse.cdt.internal.core.index.domsourceindexer.DOMAddFileToIndex.execute\n(DOMAddFileToIndex.\n\njava:60)\n        at org.eclipse.cdt.internal.core.search.processing.JobManager.run\n(JobManager.java:466)\n        at java.lang.Thread.run(Thread.java:534)\njava.lang.ClassCastException: org.eclipse.cdt.internal.core.dom.parser.cpp.\n\nCPPTemplateDefinition$CPPTemplateProblem\n        at \norg.eclipse.cdt.internal.core.dom.parser.cpp.CPPClassScope.createImplicitMembers\n(CPPClassScope.\n\njava:85)\n        at org.eclipse.cdt.internal.core.dom.parser.cpp.CPPClassScope.\u003cinit\u003e\n(CPPClassScope.java:60)\n        at \norg.eclipse.cdt.internal.core.dom.parser.cpp.CPPASTCompositeTypeSpecifier.getSco\npe(\n\nCPPASTCompositeTypeSpecifier.java:112)\n        at \norg.eclipse.cdt.internal.core.dom.parser.cpp.CPPVisitor.getContainingScope\n(CPPVisitor.java:668)\n        at \norg.eclipse.cdt.internal.core.dom.parser.cpp.CPPVisitor.getContainingScope\n(CPPVisitor.java:835)\n        at \norg.eclipse.cdt.internal.core.dom.parser.cpp.CPPSemantics.getLookupScope\n(CPPSemantics.java:907)\n        at org.eclipse.cdt.internal.core.dom.parser.cpp.CPPSemantics.lookup\n(CPPSemantics.java:987)\n        at \norg.eclipse.cdt.internal.core.dom.parser.cpp.CPPSemantics.resolveBinding\n(CPPSemantics.java:610)\n        at org.eclipse.cdt.internal.core.dom.parser.cpp.CPPVisitor.createBinding\n(CPPVisitor.java:164)\n        at \norg.eclipse.cdt.internal.core.dom.parser.cpp.CPPASTName.resolveBinding\n(CPPASTName.java:52)\n        at \norg.eclipse.cdt.internal.core.dom.parser.cpp.CPPTemplates.createClassSpecializat\nion(CPPTemplates.\n\njava:297)\n        at \norg.eclipse.cdt.internal.core.dom.parser.cpp.CPPTemplates.createBinding\n(CPPTemplates.java:224)\n        at \norg.eclipse.cdt.internal.core.dom.parser.cpp.CPPASTTemplateId.resolveBinding\n(CPPASTTemplateId.java\n\n:74)\n        at \norg.eclipse.cdt.internal.core.index.domsourceindexer.CPPGenerateIndexVisitor.add\nFriendDeclarations\n\n(CPPGenerateIndexVisitor.java:426)\n        at \norg.eclipse.cdt.internal.core.index.domsourceindexer.CPPGenerateIndexVisitor.pro\ncessNameBinding(\n\nCPPGenerateIndexVisitor.java:235)\n        at \norg.eclipse.cdt.internal.core.index.domsourceindexer.CPPGenerateIndexVisitor.pro\ncessName(\n\nCPPGenerateIndexVisitor.java:169)\n        at \norg.eclipse.cdt.internal.core.index.domsourceindexer.CPPGenerateIndexVisitor.vis\nit(\n\nCPPGenerateIndexVisitor.java:112)\n        at org.eclipse.cdt.internal.core.dom.parser.cpp.CPPASTName.accept\n(CPPASTName.java:90)\n        at \norg.eclipse.cdt.internal.core.dom.parser.cpp.CPPASTCompositeTypeSpecifier.accept\n(\n\nCPPASTCompositeTypeSpecifier.java:129)\n        at \norg.eclipse.cdt.internal.core.dom.parser.cpp.CPPASTSimpleDeclaration.accept(\n\nCPPASTSimpleDeclaration.java:71)\n        at \norg.eclipse.cdt.internal.core.dom.parser.cpp.CPPASTTemplateDeclaration.accept(\n\nCPPASTTemplateDeclaration.java:95)\n        at \norg.eclipse.cdt.internal.core.dom.parser.cpp.CPPASTTranslationUnit.accept\n(CPPASTTranslationUnit.\n\njava:520)\n        at \norg.eclipse.cdt.internal.core.index.domsourceindexer.DOMSourceIndexerRunner.inde\nxFile(\n\nDOMSourceIndexerRunner.java:133)\n        at \norg.eclipse.cdt.internal.core.index.domsourceindexer.AbstractIndexerRunner.index\n(\n\nAbstractIndexerRunner.java:76)\n        at org.eclipse.cdt.internal.core.index.cindexstorage.Index.add\n(Index.java:110)\n        at \norg.eclipse.cdt.internal.core.index.domsourceindexer.DOMAddCompilationUnitToInde\nx.indexDocument(\n\nDOMAddCompilationUnitToIndex.java:29)\n        at \norg.eclipse.cdt.internal.core.index.domsourceindexer.DOMAddFileToIndex.execute\n(DOMAddFileToIndex.\n\njava:60)\n        at org.eclipse.cdt.internal.core.search.processing.JobManager.run\n(JobManager.java:466)\n        at java.lang.Thread.run(Thread.java:534)\njava.lang.ClassCastException: org.eclipse.cdt.internal.core.dom.parser.cpp.\n\nCPPTemplateDefinition$CPPTemplateProblem\n        at \norg.eclipse.cdt.internal.core.dom.parser.cpp.CPPClassScope.createImplicitMembers\n(CPPClassScope.\n\njava:85)\n        at org.eclipse.cdt.internal.core.dom.parser.cpp.CPPClassScope.\u003cinit\u003e\n(CPPClassScope.java:60)\n        at \norg.eclipse.cdt.internal.core.dom.parser.cpp.CPPASTCompositeTypeSpecifier.getSco\npe(\n\nCPPASTCompositeTypeSpecifier.java:112)\n        at \norg.eclipse.cdt.internal.core.dom.parser.cpp.CPPVisitor.getContainingScope\n(CPPVisitor.java:668)\n        at \norg.eclipse.cdt.internal.core.dom.parser.cpp.CPPVisitor.getContainingScope\n(CPPVisitor.java:835)\n        at \norg.eclipse.cdt.internal.core.dom.parser.cpp.CPPVisitor.getContainingScope\n(CPPVisitor.java:657)\n        at org.eclipse.cdt.internal.core.dom.parser.cpp.CPPVisitor.createBinding\n(CPPVisitor.java:481)\n        at org.eclipse.cdt.internal.core.dom.parser.cpp.CPPVisitor.createBinding\n(CPPVisitor.java:188)\n        at \norg.eclipse.cdt.internal.core.dom.parser.cpp.CPPASTName.resolveBinding\n(CPPASTName.java:52)\n        at \norg.eclipse.cdt.internal.core.index.domsourceindexer.CPPGenerateIndexVisitor.pro\ncessName(\n\nCPPGenerateIndexVisitor.java:148)\n        at \norg.eclipse.cdt.internal.core.index.domsourceindexer.CPPGenerateIndexVisitor.vis\nit(\n\nCPPGenerateIndexVisitor.java:112)\n        at org.eclipse.cdt.internal.core.dom.parser.cpp.CPPASTName.accept\n(CPPASTName.java:90)\n        at org.eclipse.cdt.internal.core.dom.parser.cpp.CPPASTDeclarator.accept\n(CPPASTDeclarator.java:126)\n        at \norg.eclipse.cdt.internal.core.dom.parser.cpp.CPPASTSimpleDeclaration.accept(\n\nCPPASTSimpleDeclaration.java:74)\n        at \norg.eclipse.cdt.internal.core.dom.parser.cpp.CPPASTCompositeTypeSpecifier.accept\n(\n\nCPPASTCompositeTypeSpecifier.java:136)\n        at \norg.eclipse.cdt.internal.core.dom.parser.cpp.CPPASTSimpleDeclaration.accept(\n\nCPPASTSimpleDeclaration.java:71)\n        at \norg.eclipse.cdt.internal.core.dom.parser.cpp.CPPASTTemplateDeclaration.accept(\n\nCPPASTTemplateDeclaration.java:95)\n        at \norg.eclipse.cdt.internal.core.dom.parser.cpp.CPPASTTranslationUnit.accept\n(CPPASTTranslationUnit.\n\njava:520)\n        at \norg.eclipse.cdt.internal.core.index.domsourceindexer.DOMSourceIndexerRunner.inde\nxFile(\n\nDOMSourceIndexerRunner.java:133)\n        at \norg.eclipse.cdt.internal.core.index.domsourceindexer.AbstractIndexerRunner.index\n(\n\nAbstractIndexerRunner.java:76)\n        at org.eclipse.cdt.internal.core.index.cindexstorage.Index.add\n(Index.java:110)\n        at \norg.eclipse.cdt.internal.core.index.domsourceindexer.DOMAddCompilationUnitToInde\nx.indexDocument(\n\nDOMAddCompilationUnitToIndex.java:29)\n        at \norg.eclipse.cdt.internal.core.index.domsourceindexer.DOMAddFileToIndex.execute\n(DOMAddFileToIndex.\n\njava:60)\n        at org.eclipse.cdt.internal.core.search.processing.JobManager.run\n(JobManager.java:466)  at java.lang.\n\nThread.run(Thread.java:534)\njava.lang.ClassCastException: org.eclipse.cdt.internal.core.dom.parser.cpp.\n\nCPPTemplateDefinition$CPPTemplateProblem\n        at \norg.eclipse.cdt.internal.core.dom.parser.cpp.CPPSemantics.getTargetParameterType\ns(CPPSemantics.\n\njava:2141)\n        at \norg.eclipse.cdt.internal.core.dom.parser.cpp.CPPSemantics.resolveFunction\n(CPPSemantics.java:2219)\n        at \norg.eclipse.cdt.internal.core.dom.parser.cpp.CPPSemantics.resolveAmbiguities\n(CPPSemantics.java:\n\n1993)\n        at \norg.eclipse.cdt.internal.core.dom.parser.cpp.CPPSemantics.resolveBinding\n(CPPSemantics.java:621)\n        at \norg.eclipse.cdt.internal.core.dom.parser.cpp.CPPVisitor.resolveBinding\n(CPPVisitor.java:927)\n        at org.eclipse.cdt.internal.core.dom.parser.cpp.CPPVisitor.createBinding\n(CPPVisitor.java:182)\n        at \norg.eclipse.cdt.internal.core.dom.parser.cpp.CPPASTName.resolveBinding\n(CPPASTName.java:52)\n        at \norg.eclipse.cdt.internal.core.index.domsourceindexer.CPPGenerateIndexVisitor.pro\ncessName(\n\nCPPGenerateIndexVisitor.java:148)\n        at \norg.eclipse.cdt.internal.core.index.domsourceindexer.CPPGenerateIndexVisitor.vis\nit(\n\nCPPGenerateIndexVisitor.java:112)\n        at org.eclipse.cdt.internal.core.dom.parser.cpp.CPPASTName.accept\n(CPPASTName.java:90)\n        at \norg.eclipse.cdt.internal.core.dom.parser.cpp.CPPASTIdExpression.accept\n(CPPASTIdExpression.java:46)\n        at \norg.eclipse.cdt.internal.core.dom.parser.cpp.CPPASTFunctionCallExpression.accept\n(\n\nCPPASTFunctionCallExpression.java:64)\n        at \norg.eclipse.cdt.internal.core.dom.parser.cpp.CPPASTInitializerExpression.accept(\n\nCPPASTInitializerExpression.java:49)\n        at \norg.eclipse.cdt.internal.core.dom.parser.cpp.CPPASTDeclarator.postAccept\n(CPPASTDeclarator.java:135)\n  at org.eclipse.cdt.internal.core.dom.parser.cpp.CPPASTDeclarator.accept\n(CPPASTDeclarator.java:131)\n        at \norg.eclipse.cdt.internal.core.dom.parser.cpp.CPPASTSimpleDeclaration.accept(\n\nCPPASTSimpleDeclaration.java:74)\n        at \norg.eclipse.cdt.internal.core.dom.parser.cpp.CPPASTDeclarationStatement.accept(\n\nCPPASTDeclarationStatement.java:49)\n        at \norg.eclipse.cdt.internal.core.dom.parser.cpp.CPPASTCompoundStatement.accept(\n\nCPPASTCompoundStatement.java:66)\n        at \norg.eclipse.cdt.internal.core.dom.parser.cpp.CPPASTFunctionDefinition.accept(\n\nCPPASTFunctionDefinition.java:93)\n        at \norg.eclipse.cdt.internal.core.dom.parser.cpp.CPPASTTemplateDeclaration.accept(\n\nCPPASTTemplateDeclaration.java:95)\n        at \norg.eclipse.cdt.internal.core.dom.parser.cpp.CPPASTTranslationUnit.accept\n(CPPASTTranslationUnit.\n\njava:520)\n        at \norg.eclipse.cdt.internal.core.index.domsourceindexer.DOMSourceIndexerRunner.inde\nxFile(\n\nDOMSourceIndexerRunner.java:133)\n        at \norg.eclipse.cdt.internal.core.index.domsourceindexer.AbstractIndexerRunner.index\n(\n\nAbstractIndexerRunner.java:76)\n        at org.eclipse.cdt.internal.core.index.cindexstorage.Index.add\n(Index.java:110)\n        at \norg.eclipse.cdt.internal.core.index.domsourceindexer.DOMAddCompilationUnitToInde\nx.indexDocument(\n\nDOMAddCompilationUnitToIndex.java:29)\n        at \norg.eclipse.cdt.internal.core.index.domsourceindexer.DOMAddFileToIndex.execute\n(DOMAddFileToIndex.\n\njava:60)\n        at org.eclipse.cdt.internal.core.search.processing.JobManager.run\n(JobManager.java:466)\n        at java.lang.Thread.run(Thread.java:534)\nGConf Error: Failed to contact configuration server; some possible causes are \nthat you need to enable TCP/IP \n\nnetworking for ORBit, or you have stale NFS locks due to a system crash. See \nhttp://www.gnome.org/projects/\n\ngconf/ for information. (Details -  1: IOR \nfile \u0027/users/gmilman/.gconfd/lock/ior\u0027 not opened successfully, no \n\ngconfd located: No such file or directory 2: IOR \nfile \u0027/users/gmilman/.gconfd/lock/ior\u0027 not opened \n\nsuccessfully, no gconfd located: No such file or directory)\nGConf Error: Failed to contact configuration server; some possible causes are \nthat you need to enable TCP/IP \n\nnetworking for ORBit, or you have stale NFS locks due to a system crash. See \nhttp://www.gnome.org/projects/\n\ngconf/ for information. (Details -  1: IOR \nfile \u0027/users/gmilman/.gconfd/lock/ior\u0027 not opened successfully, no \n\ngconfd located: No such file or directory 2: IOR \nfile \u0027/users/gmilman/.gconfd/lock/ior\u0027 not opened successfully, no gconfd \nlocated: No such file or directory)",
    "*** Bug 106716 has been marked as a duplicate of this bug. ***",
    "I get the same exception when trying to import the inkscape project with cdt-3.0.2",
    "This problem is also seen when any closed CDT Project is attemted to be opened."
  ],
  "commentCreationDates": [
    "2005-08-11T09:00:03+02:00",
    "2006-01-13T15:41:20+01:00",
    "2006-02-18T15:04:19+01:00",
    "2006-07-03T09:37:51+02:00"
  ],
  "traces": [
    {
      "exceptionType": "java.lang.ClassCastException",
      "elements": [
        {
          "method": "org.eclipse.cdt.internal.core.dom.parser.cpp.CPPClassScope.createImplicitMembers",
          "source": "CPPClassScope.  java:85"
        },
        {
          "method": "org.eclipse.cdt.internal.core.dom.parser.cpp.CPPClassScope.\u003cinit\u003e",
          "source": "CPPClassScope.java:60"
        },
        {
          "method": "org.eclipse.cdt.internal.core.dom.parser.cpp.CPPASTCompositeTypeSpecifier.getScope",
          "source": "  CPPASTCompositeTypeSpecifier.java:112"
        },
        {
          "method": "org.eclipse.cdt.internal.core.dom.parser.cpp.CPPVisitor.getContainingScope",
          "source": "CPPVisitor.java:668"
        },
        {
          "method": "org.eclipse.cdt.internal.core.dom.parser.cpp.CPPVisitor.getContainingScope",
          "source": "CPPVisitor.java:835"
        },
        {
          "method": "org.eclipse.cdt.internal.core.dom.parser.cpp.CPPVisitor.getContainingScope",
          "source": "CPPVisitor.java:657"
        },
        {
          "method": "org.eclipse.cdt.internal.core.dom.parser.cpp.CPPVisitor.createBinding",
          "source": "CPPVisitor.java:481"
        },
        {
          "method": "org.eclipse.cdt.internal.core.dom.parser.cpp.CPPVisitor.createBinding",
          "source": "CPPVisitor.java:188"
        },
        {
          "method": "org.eclipse.cdt.internal.core.dom.parser.cpp.CPPASTName.resolveBinding",
          "source": "CPPASTName.java:52"
        },
        {
          "method": "org.eclipse.cdt.internal.core.index.domsourceindexer.CPPGenerateIndexVisitor.processName",
          "source": "  CPPGenerateIndexVisitor.java:148"
        },
        {
          "method": "org.eclipse.cdt.internal.core.index.domsourceindexer.CPPGenerateIndexVisitor.visit",
          "source": "  CPPGenerateIndexVisitor.java:112"
        },
        {
          "method": "org.eclipse.cdt.internal.core.dom.parser.cpp.CPPASTName.accept",
          "source": "CPPASTName.java:90"
        },
        {
          "method": "org.eclipse.cdt.internal.core.dom.parser.cpp.CPPASTDeclarator.accept",
          "source": "CPPASTDeclarator.java:126"
        },
        {
          "method": "org.eclipse.cdt.internal.core.dom.parser.cpp.CPPASTSimpleDeclaration.accept",
          "source": "  CPPASTSimpleDeclaration.java:74"
        },
        {
          "method": "org.eclipse.cdt.internal.core.dom.parser.cpp.CPPASTCompositeTypeSpecifier.accept",
          "source": "  CPPASTCompositeTypeSpecifier.java:136"
        },
        {
          "method": "org.eclipse.cdt.internal.core.dom.parser.cpp.CPPASTSimpleDeclaration.accept",
          "source": "  CPPASTSimpleDeclaration.java:71"
        },
        {
          "method": "org.eclipse.cdt.internal.core.dom.parser.cpp.CPPASTTemplateDeclaration.accept",
          "source": "  CPPASTTemplateDeclaration.java:95"
        },
        {
          "method": "org.eclipse.cdt.internal.core.dom.parser.cpp.CPPASTTranslationUnit.accept",
          "source": "CPPASTTranslationUnit.  java:520"
        },
        {
          "method": "org.eclipse.cdt.internal.core.index.domsourceindexer.DOMSourceIndexerRunner.indexFile",
          "source": "  DOMSourceIndexerRunner.java:133"
        },
        {
          "method": "org.eclipse.cdt.internal.core.index.domsourceindexer.AbstractIndexerRunner.index",
          "source": "  AbstractIndexerRunner.java:76"
        },
        {
          "method": "org.eclipse.cdt.internal.core.index.cindexstorage.Index.add",
          "source": "Index.java:110"
        },
        {
          "method": "org.eclipse.cdt.internal.core.index.domsourceindexer.DOMAddCompilationUnitToIndex.indexDocument",
          "source": "  DOMAddCompilationUnitToIndex.java:29"
        },
        {
          "method": "org.eclipse.cdt.internal.core.index.domsourceindexer.DOMAddFileToIndex.execute",
          "source": "DOMAddFileToIndex.  java:60"
        },
        {
          "method": "org.eclipse.cdt.internal.core.search.processing.JobManager.run",
          "source": "JobManager.java:466"
        },
        {
          "method": "java.lang.Thread.run",
          "source": "Thread.java:534"
        }
      ],
      "number": 0,
      "commentIndex": 0,
      "bugId": "106715",
      "date": "2005-08-11T09:00:03+02:00",
      "product": "CDT",
      "component": "cdt-core",
      "severity": "trivial"
    },
    {
      "exceptionType": "java.lang.ClassCastException",
      "elements": [
        {
          "method": "org.eclipse.cdt.internal.core.dom.parser.cpp.CPPClassScope.createImplicitMembers",
          "source": "CPPClassScope.  java:85"
        },
        {
          "method": "org.eclipse.cdt.internal.core.dom.parser.cpp.CPPClassScope.\u003cinit\u003e",
          "source": "CPPClassScope.java:60"
        },
        {
          "method": "org.eclipse.cdt.internal.core.dom.parser.cpp.CPPASTCompositeTypeSpecifier.getScope",
          "source": "  CPPASTCompositeTypeSpecifier.java:112"
        },
        {
          "method": "org.eclipse.cdt.internal.core.dom.parser.cpp.CPPVisitor.getContainingScope",
          "source": "CPPVisitor.java:668"
        },
        {
          "method": "org.eclipse.cdt.internal.core.dom.parser.cpp.CPPVisitor.getContainingScope",
          "source": "CPPVisitor.java:835"
        },
        {
          "method": "org.eclipse.cdt.internal.core.dom.parser.cpp.CPPSemantics.getLookupScope",
          "source": "CPPSemantics.java:907"
        },
        {
          "method": "org.eclipse.cdt.internal.core.dom.parser.cpp.CPPSemantics.lookup",
          "source": "CPPSemantics.java:987"
        },
        {
          "method": "org.eclipse.cdt.internal.core.dom.parser.cpp.CPPSemantics.resolveBinding",
          "source": "CPPSemantics.java:610"
        },
        {
          "method": "org.eclipse.cdt.internal.core.dom.parser.cpp.CPPVisitor.createBinding",
          "source": "CPPVisitor.java:164"
        },
        {
          "method": "org.eclipse.cdt.internal.core.dom.parser.cpp.CPPASTName.resolveBinding",
          "source": "CPPASTName.java:52"
        },
        {
          "method": "org.eclipse.cdt.internal.core.dom.parser.cpp.CPPTemplates.createClassSpecialization",
          "source": "CPPTemplates.  java:297"
        },
        {
          "method": "org.eclipse.cdt.internal.core.dom.parser.cpp.CPPTemplates.createBinding",
          "source": "CPPTemplates.java:224"
        },
        {
          "method": "org.eclipse.cdt.internal.core.dom.parser.cpp.CPPASTTemplateId.resolveBinding",
          "source": "CPPASTTemplateId.java  :74"
        },
        {
          "method": "org.eclipse.cdt.internal.core.index.domsourceindexer.CPPGenerateIndexVisitor.addFriendDeclarations",
          "source": "CPPGenerateIndexVisitor.java:426"
        },
        {
          "method": "org.eclipse.cdt.internal.core.index.domsourceindexer.CPPGenerateIndexVisitor.processNameBinding",
          "source": "  CPPGenerateIndexVisitor.java:235"
        },
        {
          "method": "org.eclipse.cdt.internal.core.index.domsourceindexer.CPPGenerateIndexVisitor.processName",
          "source": "  CPPGenerateIndexVisitor.java:169"
        },
        {
          "method": "org.eclipse.cdt.internal.core.index.domsourceindexer.CPPGenerateIndexVisitor.visit",
          "source": "  CPPGenerateIndexVisitor.java:112"
        },
        {
          "method": "org.eclipse.cdt.internal.core.dom.parser.cpp.CPPASTName.accept",
          "source": "CPPASTName.java:90"
        },
        {
          "method": "org.eclipse.cdt.internal.core.dom.parser.cpp.CPPASTCompositeTypeSpecifier.accept",
          "source": "  CPPASTCompositeTypeSpecifier.java:129"
        },
        {
          "method": "org.eclipse.cdt.internal.core.dom.parser.cpp.CPPASTSimpleDeclaration.accept",
          "source": "  CPPASTSimpleDeclaration.java:71"
        },
        {
          "method": "org.eclipse.cdt.internal.core.dom.parser.cpp.CPPASTTemplateDeclaration.accept",
          "source": "  CPPASTTemplateDeclaration.java:95"
        },
        {
          "method": "org.eclipse.cdt.internal.core.dom.parser.cpp.CPPASTTranslationUnit.accept",
          "source": "CPPASTTranslationUnit.  java:520"
        },
        {
          "method": "org.eclipse.cdt.internal.core.index.domsourceindexer.DOMSourceIndexerRunner.indexFile",
          "source": "  DOMSourceIndexerRunner.java:133"
        },
        {
          "method": "org.eclipse.cdt.internal.core.index.domsourceindexer.AbstractIndexerRunner.index",
          "source": "  AbstractIndexerRunner.java:76"
        },
        {
          "method": "org.eclipse.cdt.internal.core.index.cindexstorage.Index.add",
          "source": "Index.java:110"
        },
        {
          "method": "org.eclipse.cdt.internal.core.index.domsourceindexer.DOMAddCompilationUnitToIndex.indexDocument",
          "source": "  DOMAddCompilationUnitToIndex.java:29"
        },
        {
          "method": "org.eclipse.cdt.internal.core.index.domsourceindexer.DOMAddFileToIndex.execute",
          "source": "DOMAddFileToIndex.  java:60"
        },
        {
          "method": "org.eclipse.cdt.internal.core.search.processing.JobManager.run",
          "source": "JobManager.java:466"
        },
        {
          "method": "java.lang.Thread.run",
          "source": "Thread.java:534"
        }
      ],
      "number": 1,
      "commentIndex": 0,
      "bugId": "106715",
      "date": "2005-08-11T09:00:03+02:00",
      "product": "CDT",
      "component": "cdt-core",
      "severity": "trivial"
    },
    {
      "exceptionType": "java.lang.ClassCastException",
      "message": "org.eclipse.cdt.internal.core.dom.parser.cpp.  CPPTemplateDefinition$CPPTemplateProblem",
      "elements": [
        {
          "method": "org.eclipse.cdt.internal.core.dom.parser.cpp.CPPClassScope.createImplicitMembers",
          "source": "CPPClassScope.java:85"
        },
        {
          "method": "org.eclipse.cdt.internal.core.dom.parser.cpp.CPPClassScope.\u003cinit\u003e",
          "source": "CPPClassScope.java:60"
        },
        {
          "method": "org.eclipse.cdt.internal.core.dom.parser.cpp.CPPASTCompositeTypeSpecifier.getScope",
          "source": "  CPPASTCompositeTypeSpecifier.java:112"
        },
        {
          "method": "org.eclipse.cdt.internal.core.dom.parser.cpp.CPPVisitor.getContainingScope",
          "source": "CPPVisitor.java:668"
        },
        {
          "method": "org.eclipse.cdt.internal.core.dom.parser.cpp.CPPVisitor.getContainingScope",
          "source": "CPPVisitor.java:835"
        },
        {
          "method": "org.eclipse.cdt.internal.core.dom.parser.cpp.CPPVisitor.getContainingScope",
          "source": "CPPVisitor.java:657"
        },
        {
          "method": "org.eclipse.cdt.internal.core.dom.parser.cpp.CPPVisitor.createBinding",
          "source": "CPPVisitor.java:481"
        },
        {
          "method": "org.eclipse.cdt.internal.core.dom.parser.cpp.CPPVisitor.createBinding",
          "source": "CPPVisitor.java:188"
        },
        {
          "method": "org.eclipse.cdt.internal.core.dom.parser.cpp.CPPASTName.resolveBinding",
          "source": "CPPASTName.java:52"
        },
        {
          "method": "org.eclipse.cdt.internal.core.index.domsourceindexer.CPPGenerateIndexVisitor.processName",
          "source": "  CPPGenerateIndexVisitor.java:148"
        },
        {
          "method": "org.eclipse.cdt.internal.core.index.domsourceindexer.CPPGenerateIndexVisitor.visit",
          "source": "  CPPGenerateIndexVisitor.java:112"
        },
        {
          "method": "org.eclipse.cdt.internal.core.dom.parser.cpp.CPPASTName.accept",
          "source": "CPPASTName.java:90"
        },
        {
          "method": "org.eclipse.cdt.internal.core.dom.parser.cpp.CPPASTDeclarator.accept",
          "source": "CPPASTDeclarator.java:126"
        },
        {
          "method": "org.eclipse.cdt.internal.core.dom.parser.cpp.CPPASTSimpleDeclaration.accept",
          "source": "  CPPASTSimpleDeclaration.java:74"
        },
        {
          "method": "org.eclipse.cdt.internal.core.dom.parser.cpp.CPPASTCompositeTypeSpecifier.accept",
          "source": "  CPPASTCompositeTypeSpecifier.java:136"
        },
        {
          "method": "org.eclipse.cdt.internal.core.dom.parser.cpp.CPPASTSimpleDeclaration.accept",
          "source": "  CPPASTSimpleDeclaration.java:71"
        },
        {
          "method": "org.eclipse.cdt.internal.core.dom.parser.cpp.CPPASTTemplateDeclaration.accept",
          "source": "CPPASTTemplateDeclaration.  java:95"
        },
        {
          "method": "org.eclipse.cdt.internal.core.dom.parser.cpp.CPPASTTranslationUnit.accept",
          "source": "CPPASTTranslationUnit.  java:520"
        },
        {
          "method": "org.eclipse.cdt.internal.core.index.domsourceindexer.DOMSourceIndexerRunner.indexFile",
          "source": "  DOMSourceIndexerRunner.java:133"
        },
        {
          "method": "org.eclipse.cdt.internal.core.index.domsourceindexer.AbstractIndexerRunner.index",
          "source": "  AbstractIndexerRunner.java:76"
        },
        {
          "method": "org.eclipse.cdt.internal.core.index.cindexstorage.Index.add",
          "source": "Index.java:110"
        },
        {
          "method": "org.eclipse.cdt.internal.core.index.domsourceindexer.DOMAddCompilationUnitToIndex.indexDocument",
          "source": "  DOMAddCompilationUnitToIndex.java:29"
        },
        {
          "method": "org.eclipse.cdt.internal.core.index.domsourceindexer.DOMAddFileToIndex.execute",
          "source": "DOMAddFileToIndex.  java:60"
        },
        {
          "method": "org.eclipse.cdt.internal.core.search.processing.JobManager.run",
          "source": "JobManager.java:466"
        },
        {
          "method": "java.lang.Thread.run",
          "source": "Thread.java:534"
        }
      ],
      "number": 2,
      "commentIndex": 0,
      "bugId": "106715",
      "date": "2005-08-11T09:00:03+02:00",
      "product": "CDT",
      "component": "cdt-core",
      "severity": "trivial"
    },
    {
      "exceptionType": "java.lang.ClassCastException",
      "message": "org.eclipse.cdt.internal.core.dom.parser.cpp.  CPPTemplateDefinition$CPPTemplateProblem",
      "elements": [
        {
          "method": "org.eclipse.cdt.internal.core.dom.parser.cpp.CPPSemantics.getTargetParameterTypes",
          "source": "CPPSemantics.  java:2141"
        },
        {
          "method": "org.eclipse.cdt.internal.core.dom.parser.cpp.CPPSemantics.resolveFunction",
          "source": "CPPSemantics.java:2219"
        },
        {
          "method": "org.eclipse.cdt.internal.core.dom.parser.cpp.CPPSemantics.resolveAmbiguities",
          "source": "CPPSemantics.java:  1993"
        },
        {
          "method": "org.eclipse.cdt.internal.core.dom.parser.cpp.CPPSemantics.resolveBinding",
          "source": "CPPSemantics.java:621"
        },
        {
          "method": "org.eclipse.cdt.internal.core.dom.parser.cpp.CPPVisitor.resolveBinding",
          "source": "CPPVisitor.java:927"
        },
        {
          "method": "org.eclipse.cdt.internal.core.dom.parser.cpp.CPPVisitor.createBinding",
          "source": "CPPVisitor.java:182"
        },
        {
          "method": "org.eclipse.cdt.internal.core.dom.parser.cpp.CPPASTName.resolveBinding",
          "source": "CPPASTName.java:52"
        },
        {
          "method": "org.eclipse.cdt.internal.core.index.domsourceindexer.CPPGenerateIndexVisitor.processName",
          "source": "  CPPGenerateIndexVisitor.java:148"
        },
        {
          "method": "org.eclipse.cdt.internal.core.index.domsourceindexer.CPPGenerateIndexVisitor.visit",
          "source": "  CPPGenerateIndexVisitor.java:112"
        },
        {
          "method": "org.eclipse.cdt.internal.core.dom.parser.cpp.CPPASTName.accept",
          "source": "CPPASTName.java:90"
        },
        {
          "method": "org.eclipse.cdt.internal.core.dom.parser.cpp.CPPASTIdExpression.accept",
          "source": "CPPASTIdExpression.java:46"
        },
        {
          "method": "org.eclipse.cdt.internal.core.dom.parser.cpp.CPPASTFunctionCallExpression.accept",
          "source": "  CPPASTFunctionCallExpression.java:64"
        },
        {
          "method": "org.eclipse.cdt.internal.core.dom.parser.cpp.CPPASTInitializerExpression.accept",
          "source": "  CPPASTInitializerExpression.java:49"
        },
        {
          "method": "org.eclipse.cdt.internal.core.dom.parser.cpp.CPPASTDeclarator.postAccept",
          "source": "CPPASTDeclarator.java:135"
        },
        {
          "method": "org.eclipse.cdt.internal.core.dom.parser.cpp.CPPASTDeclarator.accept",
          "source": "CPPASTDeclarator.java:131"
        },
        {
          "method": "org.eclipse.cdt.internal.core.dom.parser.cpp.CPPASTSimpleDeclaration.accept",
          "source": "  CPPASTSimpleDeclaration.java:74"
        },
        {
          "method": "org.eclipse.cdt.internal.core.dom.parser.cpp.CPPASTDeclarationStatement.accept",
          "source": "  CPPASTDeclarationStatement.java:49"
        },
        {
          "method": "org.eclipse.cdt.internal.core.dom.parser.cpp.CPPASTCompoundStatement.accept",
          "source": "  CPPASTCompoundStatement.java:66"
        },
        {
          "method": "org.eclipse.cdt.internal.core.dom.parser.cpp.CPPASTFunctionDefinition.accept",
          "source": "  CPPASTFunctionDefinition.java:93"
        },
        {
          "method": "org.eclipse.cdt.internal.core.dom.parser.cpp.CPPASTTemplateDeclaration.accept",
          "source": "  CPPASTTemplateDeclaration.java:95"
        },
        {
          "method": "org.eclipse.cdt.internal.core.dom.parser.cpp.CPPASTTranslationUnit.accept",
          "source": "CPPASTTranslationUnit.  java:520"
        },
        {
          "method": "org.eclipse.cdt.internal.core.index.domsourceindexer.DOMSourceIndexerRunner.indexFile",
          "source": "  DOMSourceIndexerRunner.java:133"
        },
        {
          "method": "org.eclipse.cdt.internal.core.index.domsourceindexer.AbstractIndexerRunner.index",
          "source": "  AbstractIndexerRunner.java:76"
        },
        {
          "method": "org.eclipse.cdt.internal.core.index.cindexstorage.Index.add",
          "source": "Index.java:110"
        },
        {
          "method": "org.eclipse.cdt.internal.core.index.domsourceindexer.DOMAddCompilationUnitToIndex.indexDocument",
          "source": "  DOMAddCompilationUnitToIndex.java:29"
        },
        {
          "method": "org.eclipse.cdt.internal.core.index.domsourceindexer.DOMAddFileToIndex.execute",
          "source": "DOMAddFileToIndex.  java:60"
        },
        {
          "method": "org.eclipse.cdt.internal.core.search.processing.JobManager.run",
          "source": "JobManager.java:466"
        },
        {
          "method": "java.lang.Thread.run",
          "source": "Thread.java:534"
        }
      ],
      "number": 3,
      "commentIndex": 0,
      "bugId": "106715",
      "date": "2005-08-11T09:00:03+02:00",
      "product": "CDT",
      "component": "cdt-core",
      "severity": "trivial"
    },
    {
      "exceptionType": "java.lang.ClassCastException",
      "message": "org.eclipse.cdt.internal.core.dom.parser.cpp.  CPPTemplateDefinition$CPPTemplateProblem",
      "elements": [
        {
          "method": "org.eclipse.cdt.internal.core.dom.parser.cpp.CPPClassScope.createImplicitMembers",
          "source": "CPPClassScope.  java:85"
        },
        {
          "method": "org.eclipse.cdt.internal.core.dom.parser.cpp.CPPClassScope.\u003cinit\u003e",
          "source": "CPPClassScope.java:60"
        },
        {
          "method": "org.eclipse.cdt.internal.core.dom.parser.cpp.CPPASTCompositeTypeSpecifier.getScope",
          "source": "  CPPASTCompositeTypeSpecifier.java:112"
        },
        {
          "method": "org.eclipse.cdt.internal.core.dom.parser.cpp.CPPVisitor.getContainingScope",
          "source": "CPPVisitor.java:668"
        },
        {
          "method": "org.eclipse.cdt.internal.core.dom.parser.cpp.CPPVisitor.getContainingScope",
          "source": "CPPVisitor.java:835"
        },
        {
          "method": "org.eclipse.cdt.internal.core.dom.parser.cpp.CPPVisitor.getContainingScope",
          "source": "CPPVisitor.java:657"
        },
        {
          "method": "org.eclipse.cdt.internal.core.dom.parser.cpp.CPPVisitor.createBinding",
          "source": "CPPVisitor.java:481"
        },
        {
          "method": "org.eclipse.cdt.internal.core.dom.parser.cpp.CPPVisitor.createBinding",
          "source": "CPPVisitor.java:188"
        },
        {
          "method": "org.eclipse.cdt.internal.core.dom.parser.cpp.CPPASTName.resolveBinding",
          "source": "CPPASTName.java:52"
        },
        {
          "method": "org.eclipse.cdt.internal.core.index.domsourceindexer.CPPGenerateIndexVisitor.processName",
          "source": "  CPPGenerateIndexVisitor.java:148"
        },
        {
          "method": "org.eclipse.cdt.internal.core.index.domsourceindexer.CPPGenerateIndexVisitor.visit",
          "source": "  CPPGenerateIndexVisitor.java:112"
        },
        {
          "method": "org.eclipse.cdt.internal.core.dom.parser.cpp.CPPASTName.accept",
          "source": "CPPASTName.java:90"
        },
        {
          "method": "org.eclipse.cdt.internal.core.dom.parser.cpp.CPPASTDeclarator.accept",
          "source": "CPPASTDeclarator.java:126"
        },
        {
          "method": "org.eclipse.cdt.internal.core.dom.parser.cpp.CPPASTSimpleDeclaration.accept",
          "source": "  CPPASTSimpleDeclaration.java:74"
        },
        {
          "method": "org.eclipse.cdt.internal.core.dom.parser.cpp.CPPASTCompositeTypeSpecifier.accept",
          "source": "  CPPASTCompositeTypeSpecifier.java:136"
        },
        {
          "method": "org.eclipse.cdt.internal.core.dom.parser.cpp.CPPASTSimpleDeclaration.accept",
          "source": "  CPPASTSimpleDeclaration.java:71"
        },
        {
          "method": "org.eclipse.cdt.internal.core.dom.parser.cpp.CPPASTTemplateDeclaration.accept",
          "source": "  CPPASTTemplateDeclaration.java:95"
        },
        {
          "method": "org.eclipse.cdt.internal.core.dom.parser.cpp.CPPASTTranslationUnit.accept",
          "source": "CPPASTTranslationUnit.  java:520"
        },
        {
          "method": "org.eclipse.cdt.internal.core.index.domsourceindexer.DOMSourceIndexerRunner.indexFile",
          "source": "  DOMSourceIndexerRunner.java:133"
        },
        {
          "method": "org.eclipse.cdt.internal.core.index.domsourceindexer.AbstractIndexerRunner.index",
          "source": "  AbstractIndexerRunner.java:76"
        },
        {
          "method": "org.eclipse.cdt.internal.core.index.cindexstorage.Index.add",
          "source": "Index.java:110"
        },
        {
          "method": "org.eclipse.cdt.internal.core.index.domsourceindexer.DOMAddCompilationUnitToIndex.indexDocument",
          "source": "  DOMAddCompilationUnitToIndex.java:29"
        },
        {
          "method": "org.eclipse.cdt.internal.core.index.domsourceindexer.DOMAddFileToIndex.execute",
          "source": "DOMAddFileToIndex.  java:60"
        },
        {
          "method": "org.eclipse.cdt.internal.core.search.processing.JobManager.run",
          "source": "JobManager.java:466"
        },
        {
          "method": "java.lang.Thread.run",
          "source": "Thread.java:534"
        }
      ],
      "number": 4,
      "commentIndex": 0,
      "bugId": "106715",
      "date": "2005-08-11T09:00:03+02:00",
      "product": "CDT",
      "component": "cdt-core",
      "severity": "trivial"
    },
    {
      "exceptionType": "java.lang.ClassCastException",
      "message": "org.eclipse.cdt.internal.core.dom.parser.cpp.  CPPTemplateDefinition$CPPTemplateProblem",
      "elements": [
        {
          "method": "org.eclipse.cdt.internal.core.dom.parser.cpp.CPPClassScope.createImplicitMembers",
          "source": "CPPClassScope.  java:85"
        },
        {
          "method": "org.eclipse.cdt.internal.core.dom.parser.cpp.CPPClassScope.\u003cinit\u003e",
          "source": "CPPClassScope.java:60"
        },
        {
          "method": "org.eclipse.cdt.internal.core.dom.parser.cpp.CPPASTCompositeTypeSpecifier.getScope",
          "source": "  CPPASTCompositeTypeSpecifier.java:112"
        },
        {
          "method": "org.eclipse.cdt.internal.core.dom.parser.cpp.CPPVisitor.getContainingScope",
          "source": "CPPVisitor.java:668"
        },
        {
          "method": "org.eclipse.cdt.internal.core.dom.parser.cpp.CPPVisitor.getContainingScope",
          "source": "CPPVisitor.java:835"
        },
        {
          "method": "org.eclipse.cdt.internal.core.dom.parser.cpp.CPPSemantics.getLookupScope",
          "source": "CPPSemantics.java:907"
        },
        {
          "method": "org.eclipse.cdt.internal.core.dom.parser.cpp.CPPSemantics.lookup",
          "source": "CPPSemantics.java:987"
        },
        {
          "method": "org.eclipse.cdt.internal.core.dom.parser.cpp.CPPSemantics.resolveBinding",
          "source": "CPPSemantics.java:610"
        },
        {
          "method": "org.eclipse.cdt.internal.core.dom.parser.cpp.CPPVisitor.createBinding",
          "source": "CPPVisitor.java:164"
        },
        {
          "method": "org.eclipse.cdt.internal.core.dom.parser.cpp.CPPASTName.resolveBinding",
          "source": "CPPASTName.java:52"
        },
        {
          "method": "org.eclipse.cdt.internal.core.dom.parser.cpp.CPPTemplates.createClassSpecialization",
          "source": "CPPTemplates.  java:297"
        },
        {
          "method": "org.eclipse.cdt.internal.core.dom.parser.cpp.CPPTemplates.createBinding",
          "source": "CPPTemplates.java:224"
        },
        {
          "method": "org.eclipse.cdt.internal.core.dom.parser.cpp.CPPASTTemplateId.resolveBinding",
          "source": "CPPASTTemplateId.java  :74"
        },
        {
          "method": "org.eclipse.cdt.internal.core.index.domsourceindexer.CPPGenerateIndexVisitor.addFriendDeclarations",
          "source": "CPPGenerateIndexVisitor.java:426"
        },
        {
          "method": "org.eclipse.cdt.internal.core.index.domsourceindexer.CPPGenerateIndexVisitor.processNameBinding",
          "source": "  CPPGenerateIndexVisitor.java:235"
        },
        {
          "method": "org.eclipse.cdt.internal.core.index.domsourceindexer.CPPGenerateIndexVisitor.processName",
          "source": "  CPPGenerateIndexVisitor.java:169"
        },
        {
          "method": "org.eclipse.cdt.internal.core.index.domsourceindexer.CPPGenerateIndexVisitor.visit",
          "source": "  CPPGenerateIndexVisitor.java:112"
        },
        {
          "method": "org.eclipse.cdt.internal.core.dom.parser.cpp.CPPASTName.accept",
          "source": "CPPASTName.java:90"
        },
        {
          "method": "org.eclipse.cdt.internal.core.dom.parser.cpp.CPPASTCompositeTypeSpecifier.accept",
          "source": "  CPPASTCompositeTypeSpecifier.java:129"
        },
        {
          "method": "org.eclipse.cdt.internal.core.dom.parser.cpp.CPPASTSimpleDeclaration.accept",
          "source": "  CPPASTSimpleDeclaration.java:71"
        },
        {
          "method": "org.eclipse.cdt.internal.core.dom.parser.cpp.CPPASTTemplateDeclaration.accept",
          "source": "  CPPASTTemplateDeclaration.java:95"
        },
        {
          "method": "org.eclipse.cdt.internal.core.dom.parser.cpp.CPPASTTranslationUnit.accept",
          "source": "CPPASTTranslationUnit.  java:520"
        },
        {
          "method": "org.eclipse.cdt.internal.core.index.domsourceindexer.DOMSourceIndexerRunner.indexFile",
          "source": "  DOMSourceIndexerRunner.java:133"
        },
        {
          "method": "org.eclipse.cdt.internal.core.index.domsourceindexer.AbstractIndexerRunner.index",
          "source": "  AbstractIndexerRunner.java:76"
        },
        {
          "method": "org.eclipse.cdt.internal.core.index.cindexstorage.Index.add",
          "source": "Index.java:110"
        },
        {
          "method": "org.eclipse.cdt.internal.core.index.domsourceindexer.DOMAddCompilationUnitToIndex.indexDocument",
          "source": "  DOMAddCompilationUnitToIndex.java:29"
        },
        {
          "method": "org.eclipse.cdt.internal.core.index.domsourceindexer.DOMAddFileToIndex.execute",
          "source": "DOMAddFileToIndex.  java:60"
        },
        {
          "method": "org.eclipse.cdt.internal.core.search.processing.JobManager.run",
          "source": "JobManager.java:466"
        },
        {
          "method": "java.lang.Thread.run",
          "source": "Thread.java:534"
        }
      ],
      "number": 5,
      "commentIndex": 0,
      "bugId": "106715",
      "date": "2005-08-11T09:00:03+02:00",
      "product": "CDT",
      "component": "cdt-core",
      "severity": "trivial"
    },
    {
      "exceptionType": "java.lang.ClassCastException",
      "message": "org.eclipse.cdt.internal.core.dom.parser.cpp.  CPPTemplateDefinition$CPPTemplateProblem",
      "elements": [
        {
          "method": "org.eclipse.cdt.internal.core.dom.parser.cpp.CPPClassScope.createImplicitMembers",
          "source": "CPPClassScope.  java:85"
        },
        {
          "method": "org.eclipse.cdt.internal.core.dom.parser.cpp.CPPClassScope.\u003cinit\u003e",
          "source": "CPPClassScope.java:60"
        },
        {
          "method": "org.eclipse.cdt.internal.core.dom.parser.cpp.CPPASTCompositeTypeSpecifier.getScope",
          "source": "  CPPASTCompositeTypeSpecifier.java:112"
        },
        {
          "method": "org.eclipse.cdt.internal.core.dom.parser.cpp.CPPVisitor.getContainingScope",
          "source": "CPPVisitor.java:668"
        },
        {
          "method": "org.eclipse.cdt.internal.core.dom.parser.cpp.CPPVisitor.getContainingScope",
          "source": "CPPVisitor.java:835"
        },
        {
          "method": "org.eclipse.cdt.internal.core.dom.parser.cpp.CPPVisitor.getContainingScope",
          "source": "CPPVisitor.java:657"
        },
        {
          "method": "org.eclipse.cdt.internal.core.dom.parser.cpp.CPPVisitor.createBinding",
          "source": "CPPVisitor.java:481"
        },
        {
          "method": "org.eclipse.cdt.internal.core.dom.parser.cpp.CPPVisitor.createBinding",
          "source": "CPPVisitor.java:188"
        },
        {
          "method": "org.eclipse.cdt.internal.core.dom.parser.cpp.CPPASTName.resolveBinding",
          "source": "CPPASTName.java:52"
        },
        {
          "method": "org.eclipse.cdt.internal.core.index.domsourceindexer.CPPGenerateIndexVisitor.processName",
          "source": "  CPPGenerateIndexVisitor.java:148"
        },
        {
          "method": "org.eclipse.cdt.internal.core.index.domsourceindexer.CPPGenerateIndexVisitor.visit",
          "source": "  CPPGenerateIndexVisitor.java:112"
        },
        {
          "method": "org.eclipse.cdt.internal.core.dom.parser.cpp.CPPASTName.accept",
          "source": "CPPASTName.java:90"
        },
        {
          "method": "org.eclipse.cdt.internal.core.dom.parser.cpp.CPPASTDeclarator.accept",
          "source": "CPPASTDeclarator.java:126"
        },
        {
          "method": "org.eclipse.cdt.internal.core.dom.parser.cpp.CPPASTSimpleDeclaration.accept",
          "source": "  CPPASTSimpleDeclaration.java:74"
        },
        {
          "method": "org.eclipse.cdt.internal.core.dom.parser.cpp.CPPASTCompositeTypeSpecifier.accept",
          "source": "  CPPASTCompositeTypeSpecifier.java:136"
        },
        {
          "method": "org.eclipse.cdt.internal.core.dom.parser.cpp.CPPASTSimpleDeclaration.accept",
          "source": "  CPPASTSimpleDeclaration.java:71"
        },
        {
          "method": "org.eclipse.cdt.internal.core.dom.parser.cpp.CPPASTTemplateDeclaration.accept",
          "source": "  CPPASTTemplateDeclaration.java:95"
        },
        {
          "method": "org.eclipse.cdt.internal.core.dom.parser.cpp.CPPASTTranslationUnit.accept",
          "source": "CPPASTTranslationUnit.  java:520"
        },
        {
          "method": "org.eclipse.cdt.internal.core.index.domsourceindexer.DOMSourceIndexerRunner.indexFile",
          "source": "  DOMSourceIndexerRunner.java:133"
        },
        {
          "method": "org.eclipse.cdt.internal.core.index.domsourceindexer.AbstractIndexerRunner.index",
          "source": "  AbstractIndexerRunner.java:76"
        },
        {
          "method": "org.eclipse.cdt.internal.core.index.cindexstorage.Index.add",
          "source": "Index.java:110"
        },
        {
          "method": "org.eclipse.cdt.internal.core.index.domsourceindexer.DOMAddCompilationUnitToIndex.indexDocument",
          "source": "  DOMAddCompilationUnitToIndex.java:29"
        },
        {
          "method": "org.eclipse.cdt.internal.core.index.domsourceindexer.DOMAddFileToIndex.execute",
          "source": "DOMAddFileToIndex.  java:60"
        },
        {
          "method": "org.eclipse.cdt.internal.core.search.processing.JobManager.run",
          "source": "JobManager.java:466"
        }
      ],
      "number": 6,
      "commentIndex": 0,
      "bugId": "106715",
      "date": "2005-08-11T09:00:03+02:00",
      "product": "CDT",
      "component": "cdt-core",
      "severity": "trivial"
    },
    {
      "exceptionType": "java.lang.ClassCastException",
      "message": "org.eclipse.cdt.internal.core.dom.parser.cpp.  CPPTemplateDefinition$CPPTemplateProblem",
      "elements": [
        {
          "method": "org.eclipse.cdt.internal.core.dom.parser.cpp.CPPSemantics.getTargetParameterTypes",
          "source": "CPPSemantics.  java:2141"
        },
        {
          "method": "org.eclipse.cdt.internal.core.dom.parser.cpp.CPPSemantics.resolveFunction",
          "source": "CPPSemantics.java:2219"
        },
        {
          "method": "org.eclipse.cdt.internal.core.dom.parser.cpp.CPPSemantics.resolveAmbiguities",
          "source": "CPPSemantics.java:  1993"
        },
        {
          "method": "org.eclipse.cdt.internal.core.dom.parser.cpp.CPPSemantics.resolveBinding",
          "source": "CPPSemantics.java:621"
        },
        {
          "method": "org.eclipse.cdt.internal.core.dom.parser.cpp.CPPVisitor.resolveBinding",
          "source": "CPPVisitor.java:927"
        },
        {
          "method": "org.eclipse.cdt.internal.core.dom.parser.cpp.CPPVisitor.createBinding",
          "source": "CPPVisitor.java:182"
        },
        {
          "method": "org.eclipse.cdt.internal.core.dom.parser.cpp.CPPASTName.resolveBinding",
          "source": "CPPASTName.java:52"
        },
        {
          "method": "org.eclipse.cdt.internal.core.index.domsourceindexer.CPPGenerateIndexVisitor.processName",
          "source": "  CPPGenerateIndexVisitor.java:148"
        },
        {
          "method": "org.eclipse.cdt.internal.core.index.domsourceindexer.CPPGenerateIndexVisitor.visit",
          "source": "  CPPGenerateIndexVisitor.java:112"
        },
        {
          "method": "org.eclipse.cdt.internal.core.dom.parser.cpp.CPPASTName.accept",
          "source": "CPPASTName.java:90"
        },
        {
          "method": "org.eclipse.cdt.internal.core.dom.parser.cpp.CPPASTIdExpression.accept",
          "source": "CPPASTIdExpression.java:46"
        },
        {
          "method": "org.eclipse.cdt.internal.core.dom.parser.cpp.CPPASTFunctionCallExpression.accept",
          "source": "  CPPASTFunctionCallExpression.java:64"
        },
        {
          "method": "org.eclipse.cdt.internal.core.dom.parser.cpp.CPPASTInitializerExpression.accept",
          "source": "  CPPASTInitializerExpression.java:49"
        },
        {
          "method": "org.eclipse.cdt.internal.core.dom.parser.cpp.CPPASTDeclarator.postAccept",
          "source": "CPPASTDeclarator.java:135"
        },
        {
          "method": "org.eclipse.cdt.internal.core.dom.parser.cpp.CPPASTDeclarator.accept",
          "source": "CPPASTDeclarator.java:131"
        },
        {
          "method": "org.eclipse.cdt.internal.core.dom.parser.cpp.CPPASTSimpleDeclaration.accept",
          "source": "  CPPASTSimpleDeclaration.java:74"
        },
        {
          "method": "org.eclipse.cdt.internal.core.dom.parser.cpp.CPPASTDeclarationStatement.accept",
          "source": "  CPPASTDeclarationStatement.java:49"
        },
        {
          "method": "org.eclipse.cdt.internal.core.dom.parser.cpp.CPPASTCompoundStatement.accept",
          "source": "  CPPASTCompoundStatement.java:66"
        },
        {
          "method": "org.eclipse.cdt.internal.core.dom.parser.cpp.CPPASTFunctionDefinition.accept",
          "source": "  CPPASTFunctionDefinition.java:93"
        },
        {
          "method": "org.eclipse.cdt.internal.core.dom.parser.cpp.CPPASTTemplateDeclaration.accept",
          "source": "  CPPASTTemplateDeclaration.java:95"
        },
        {
          "method": "org.eclipse.cdt.internal.core.dom.parser.cpp.CPPASTTranslationUnit.accept",
          "source": "CPPASTTranslationUnit.  java:520"
        },
        {
          "method": "org.eclipse.cdt.internal.core.index.domsourceindexer.DOMSourceIndexerRunner.indexFile",
          "source": "  DOMSourceIndexerRunner.java:133"
        },
        {
          "method": "org.eclipse.cdt.internal.core.index.domsourceindexer.AbstractIndexerRunner.index",
          "source": "  AbstractIndexerRunner.java:76"
        },
        {
          "method": "org.eclipse.cdt.internal.core.index.cindexstorage.Index.add",
          "source": "Index.java:110"
        },
        {
          "method": "org.eclipse.cdt.internal.core.index.domsourceindexer.DOMAddCompilationUnitToIndex.indexDocument",
          "source": "  DOMAddCompilationUnitToIndex.java:29"
        },
        {
          "method": "org.eclipse.cdt.internal.core.index.domsourceindexer.DOMAddFileToIndex.execute",
          "source": "DOMAddFileToIndex.  java:60"
        },
        {
          "method": "org.eclipse.cdt.internal.core.search.processing.JobManager.run",
          "source": "JobManager.java:466"
        },
        {
          "method": "java.lang.Thread.run",
          "source": "Thread.java:534"
        }
      ],
      "number": 7,
      "commentIndex": 0,
      "bugId": "106715",
      "date": "2005-08-11T09:00:03+02:00",
      "product": "CDT",
      "component": "cdt-core",
      "severity": "trivial"
    }
  ],
  "groupId": "106715",
  "bugId": "106715",
  "date": "2005-08-11T09:00:03+02:00",
  "product": "CDT",
  "component": "cdt-core",
  "severity": "trivial"
}