{
  "comments": [
    "I downloaded org.eclipse.cdt-3.0.0-I200508081313-linux.x86.tar.gz\nand created a new C++ project.\nDuring the creation and building of the project I got the following Java \nexceptions: \njava.lang.ClassCastException\n        at \norg.eclipse.cdt.internal.core.dom.parser.cpp.CPPClassScope.createImplicitMembers\n(CPPClassScope.\n\njava:85)\n        at org.eclipse.cdt.internal.core.dom.parser.cpp.CPPClassScope.\u003cinit\u003e\n(CPPClassScope.java:60)\n        at \norg.eclipse.cdt.internal.core.dom.parser.cpp.CPPASTCompositeTypeSpecifier.getSco\npe(\n\nCPPASTCompositeTypeSpecifier.java:112)\n        at \norg.eclipse.cdt.internal.core.dom.parser.cpp.CPPVisitor.getContainingScope\n(CPPVisitor.java:668)\n        at \norg.eclipse.cdt.internal.core.dom.parser.cpp.CPPVisitor.getContainingScope\n(CPPVisitor.java:835)\n        at \norg.eclipse.cdt.internal.core.dom.parser.cpp.CPPVisitor.getContainingScope\n(CPPVisitor.java:657)\n  at org.eclipse.cdt.internal.core.dom.parser.cpp.CPPVisitor.createBinding\n(CPPVisitor.java:481)\n        at org.eclipse.cdt.internal.core.dom.parser.cpp.CPPVisitor.createBinding\n(CPPVisitor.java:188)\n        at \norg.eclipse.cdt.internal.core.dom.parser.cpp.CPPASTName.resolveBinding\n(CPPASTName.java:52)\n        at \norg.eclipse.cdt.internal.core.index.domsourceindexer.CPPGenerateIndexVisitor.pro\ncessName(\n\nCPPGenerateIndexVisitor.java:148)\n        at \norg.eclipse.cdt.internal.core.index.domsourceindexer.CPPGenerateIndexVisitor.vis\nit(\n\nCPPGenerateIndexVisitor.java:112)\n        at org.eclipse.cdt.internal.core.dom.parser.cpp.CPPASTName.accept\n(CPPASTName.java:90)\n        at org.eclipse.cdt.internal.core.dom.parser.cpp.CPPASTDeclarator.accept\n(CPPASTDeclarator.java:126)\n        at \norg.eclipse.cdt.internal.core.dom.parser.cpp.CPPASTSimpleDeclaration.accept(\n\nCPPASTSimpleDeclaration.java:74)\n        at \norg.eclipse.cdt.internal.core.dom.parser.cpp.CPPASTCompositeTypeSpecifier.accept\n(\n\nCPPASTCompositeTypeSpecifier.java:136)\n        at \norg.eclipse.cdt.internal.core.dom.parser.cpp.CPPASTSimpleDeclaration.accept(\n\nCPPASTSimpleDeclaration.java:71)\n        at \norg.eclipse.cdt.internal.core.dom.parser.cpp.CPPASTTemplateDeclaration.accept(\n\nCPPASTTemplateDeclaration.java:95)\n        at \norg.eclipse.cdt.internal.core.dom.parser.cpp.CPPASTTranslationUnit.accept\n(CPPASTTranslationUnit.\n\njava:520)\n        at \norg.eclipse.cdt.internal.core.index.domsourceindexer.DOMSourceIndexerRunner.inde\nxFile(\n\nDOMSourceIndexerRunner.java:133)\n        at \norg.eclipse.cdt.internal.core.index.domsourceindexer.AbstractIndexerRunner.index\n(\n\nAbstractIndexerRunner.java:76)\n        at org.eclipse.cdt.internal.core.index.cindexstorage.Index.add\n(Index.java:110)\n        at \norg.eclipse.cdt.internal.core.index.domsourceindexer.DOMAddCompilationUnitToInde\nx.indexDocument(\n\nDOMAddCompilationUnitToIndex.java:29)\n        at \norg.eclipse.cdt.internal.core.index.domsourceindexer.DOMAddFileToIndex.execute\n(DOMAddFileToIndex.\n\njava:60)\n        at org.eclipse.cdt.internal.core.search.processing.JobManager.run\n(JobManager.java:466)\n        at java.lang.Thread.run(Thread.java:534)\njava.lang.ClassCastException\n        at \norg.eclipse.cdt.internal.core.dom.parser.cpp.CPPClassScope.createImplicitMembers\n(CPPClassScope.\n\njava:85)\n        at org.eclipse.cdt.internal.core.dom.parser.cpp.CPPClassScope.\u003cinit\u003e\n(CPPClassScope.java:60)\n        at \norg.eclipse.cdt.internal.core.dom.parser.cpp.CPPASTCompositeTypeSpecifier.getSco\npe(\n\nCPPASTCompositeTypeSpecifier.java:112)\n        at \norg.eclipse.cdt.internal.core.dom.parser.cpp.CPPVisitor.getContainingScope\n(CPPVisitor.java:668)\n        at \norg.eclipse.cdt.internal.core.dom.parser.cpp.CPPVisitor.getContainingScope\n(CPPVisitor.java:835)\n        at \norg.eclipse.cdt.internal.core.dom.parser.cpp.CPPSemantics.getLookupScope\n(CPPSemantics.java:907)\n        at org.eclipse.cdt.internal.core.dom.parser.cpp.CPPSemantics.lookup\n(CPPSemantics.java:987)\n        at \norg.eclipse.cdt.internal.core.dom.parser.cpp.CPPSemantics.resolveBinding\n(CPPSemantics.java:610)\n        at org.eclipse.cdt.internal.core.dom.parser.cpp.CPPVisitor.createBinding\n(CPPVisitor.java:164)\n        at \norg.eclipse.cdt.internal.core.dom.parser.cpp.CPPASTName.resolveBinding\n(CPPASTName.java:52)\n        at \norg.eclipse.cdt.internal.core.dom.parser.cpp.CPPTemplates.createClassSpecializat\nion(CPPTemplates.\n\njava:297)\n        at \norg.eclipse.cdt.internal.core.dom.parser.cpp.CPPTemplates.createBinding\n(CPPTemplates.java:224)\n        at \norg.eclipse.cdt.internal.core.dom.parser.cpp.CPPASTTemplateId.resolveBinding\n(CPPASTTemplateId.java\n\n:74)\n        at \norg.eclipse.cdt.internal.core.index.domsourceindexer.CPPGenerateIndexVisitor.add\nFriendDeclarations\n\n(CPPGenerateIndexVisitor.java:426)\n        at \norg.eclipse.cdt.internal.core.index.domsourceindexer.CPPGenerateIndexVisitor.pro\ncessNameBinding(\n\nCPPGenerateIndexVisitor.java:235)\n        at \norg.eclipse.cdt.internal.core.index.domsourceindexer.CPPGenerateIndexVisitor.pro\ncessName(\n\nCPPGenerateIndexVisitor.java:169)\n        at \norg.eclipse.cdt.internal.core.index.domsourceindexer.CPPGenerateIndexVisitor.vis\nit(\n\nCPPGenerateIndexVisitor.java:112)\n        at org.eclipse.cdt.internal.core.dom.parser.cpp.CPPASTName.accept\n(CPPASTName.java:90)\n        at \norg.eclipse.cdt.internal.core.dom.parser.cpp.CPPASTCompositeTypeSpecifier.accept\n(\n\nCPPASTCompositeTypeSpecifier.java:129)\n        at \norg.eclipse.cdt.internal.core.dom.parser.cpp.CPPASTSimpleDeclaration.accept(\n\nCPPASTSimpleDeclaration.java:71)\n        at \norg.eclipse.cdt.internal.core.dom.parser.cpp.CPPASTTemplateDeclaration.accept(\n\nCPPASTTemplateDeclaration.java:95)\n        at \norg.eclipse.cdt.internal.core.dom.parser.cpp.CPPASTTranslationUnit.accept\n(CPPASTTranslationUnit.\n\njava:520)\n        at \norg.eclipse.cdt.internal.core.index.domsourceindexer.DOMSourceIndexerRunner.inde\nxFile(\n\nDOMSourceIndexerRunner.java:133)\n        at \norg.eclipse.cdt.internal.core.index.domsourceindexer.AbstractIndexerRunner.index\n(\n\nAbstractIndexerRunner.java:76)\n        at org.eclipse.cdt.internal.core.index.cindexstorage.Index.add\n(Index.java:110)\n        at \norg.eclipse.cdt.internal.core.index.domsourceindexer.DOMAddCompilationUnitToInde\nx.indexDocument(\n\nDOMAddCompilationUnitToIndex.java:29)\n        at \norg.eclipse.cdt.internal.core.index.domsourceindexer.DOMAddFileToIndex.execute\n(DOMAddFileToIndex.\n\njava:60)\n        at org.eclipse.cdt.internal.core.search.processing.JobManager.run\n(JobManager.java:466)\n        at java.lang.Thread.run(Thread.java:534)\n\n22 gmilman on ~\u003ejava.lang.ClassCastException: \norg.eclipse.cdt.internal.core.dom.parser.cpp.\n\nCPPTemplateDefinition$CPPTemplateProblem\n  at \norg.eclipse.cdt.internal.core.dom.parser.cpp.CPPClassScope.createImplicitMembers\n(CPPClassScope.java:85)\n        at org.eclipse.cdt.internal.core.dom.parser.cpp.CPPClassScope.\u003cinit\u003e\n(CPPClassScope.java:60)\n        at \norg.eclipse.cdt.internal.core.dom.parser.cpp.CPPASTCompositeTypeSpecifier.getSco\npe(\n\nCPPASTCompositeTypeSpecifier.java:112)\n        at \norg.eclipse.cdt.internal.core.dom.parser.cpp.CPPVisitor.getContainingScope\n(CPPVisitor.java:668)\n        at \norg.eclipse.cdt.internal.core.dom.parser.cpp.CPPVisitor.getContainingScope\n(CPPVisitor.java:835)\n        at \norg.eclipse.cdt.internal.core.dom.parser.cpp.CPPVisitor.getContainingScope\n(CPPVisitor.java:657)\n        at org.eclipse.cdt.internal.core.dom.parser.cpp.CPPVisitor.createBinding\n(CPPVisitor.java:481)\n        at org.eclipse.cdt.internal.core.dom.parser.cpp.CPPVisitor.createBinding\n(CPPVisitor.java:188)\n        at \norg.eclipse.cdt.internal.core.dom.parser.cpp.CPPASTName.resolveBinding\n(CPPASTName.java:52)\n        at \norg.eclipse.cdt.internal.core.index.domsourceindexer.CPPGenerateIndexVisitor.pro\ncessName(\n\nCPPGenerateIndexVisitor.java:148)\n        at \norg.eclipse.cdt.internal.core.index.domsourceindexer.CPPGenerateIndexVisitor.vis\nit(\n\nCPPGenerateIndexVisitor.java:112)\n        at org.eclipse.cdt.internal.core.dom.parser.cpp.CPPASTName.accept\n(CPPASTName.java:90)\n        at org.eclipse.cdt.internal.core.dom.parser.cpp.CPPASTDeclarator.accept\n(CPPASTDeclarator.java:126)\n        at \norg.eclipse.cdt.internal.core.dom.parser.cpp.CPPASTSimpleDeclaration.accept(\n\nCPPASTSimpleDeclaration.java:74)\n        at \norg.eclipse.cdt.internal.core.dom.parser.cpp.CPPASTCompositeTypeSpecifier.accept\n(\n\nCPPASTCompositeTypeSpecifier.java:136)\n        at \norg.eclipse.cdt.internal.core.dom.parser.cpp.CPPASTSimpleDeclaration.accept(\n\nCPPASTSimpleDeclaration.java:71)\n  at \norg.eclipse.cdt.internal.core.dom.parser.cpp.CPPASTTemplateDeclaration.accept\n(CPPASTTemplateDeclaration.\n\njava:95)\n        at \norg.eclipse.cdt.internal.core.dom.parser.cpp.CPPASTTranslationUnit.accept\n(CPPASTTranslationUnit.\n\njava:520)\n        at \norg.eclipse.cdt.internal.core.index.domsourceindexer.DOMSourceIndexerRunner.inde\nxFile(\n\nDOMSourceIndexerRunner.java:133)\n        at \norg.eclipse.cdt.internal.core.index.domsourceindexer.AbstractIndexerRunner.index\n(\n\nAbstractIndexerRunner.java:76)\n        at org.eclipse.cdt.internal.core.index.cindexstorage.Index.add\n(Index.java:110)\n        at \norg.eclipse.cdt.internal.core.index.domsourceindexer.DOMAddCompilationUnitToInde\nx.indexDocument(\n\nDOMAddCompilationUnitToIndex.java:29)\n        at \norg.eclipse.cdt.internal.core.index.domsourceindexer.DOMAddFileToIndex.execute\n(DOMAddFileToIndex.\n\njava:60)\n        at org.eclipse.cdt.internal.core.search.processing.JobManager.run\n(JobManager.java:466)\n        at java.lang.Thread.run(Thread.java:534)\njava.lang.ClassCastException: org.eclipse.cdt.internal.core.dom.parser.cpp.\n\nCPPTemplateDefinition$CPPTemplateProblem\n        at \norg.eclipse.cdt.internal.core.dom.parser.cpp.CPPSemantics.getTargetParameterType\ns(CPPSemantics.\n\njava:2141)\n        at \norg.eclipse.cdt.internal.core.dom.parser.cpp.CPPSemantics.resolveFunction\n(CPPSemantics.java:2219)\n        at \norg.eclipse.cdt.internal.core.dom.parser.cpp.CPPSemantics.resolveAmbiguities\n(CPPSemantics.java:\n\n1993)\n        at \norg.eclipse.cdt.internal.core.dom.parser.cpp.CPPSemantics.resolveBinding\n(CPPSemantics.java:621)\n        at \norg.eclipse.cdt.internal.core.dom.parser.cpp.CPPVisitor.resolveBinding\n(CPPVisitor.java:927)\n        at org.eclipse.cdt.internal.core.dom.parser.cpp.CPPVisitor.createBinding\n(CPPVisitor.java:182)\n        at \norg.eclipse.cdt.internal.core.dom.parser.cpp.CPPASTName.resolveBinding\n(CPPASTName.java:52)\n        at \norg.eclipse.cdt.internal.core.index.domsourceindexer.CPPGenerateIndexVisitor.pro\ncessName(\n\nCPPGenerateIndexVisitor.java:148)\n        at \norg.eclipse.cdt.internal.core.index.domsourceindexer.CPPGenerateIndexVisitor.vis\nit(\n\nCPPGenerateIndexVisitor.java:112)\n        at org.eclipse.cdt.internal.core.dom.parser.cpp.CPPASTName.accept\n(CPPASTName.java:90)\n        at \norg.eclipse.cdt.internal.core.dom.parser.cpp.CPPASTIdExpression.accept\n(CPPASTIdExpression.java:46)\n  at \norg.eclipse.cdt.internal.core.dom.parser.cpp.CPPASTFunctionCallExpression.accept\n(\n\nCPPASTFunctionCallExpression.java:64)\n        at \norg.eclipse.cdt.internal.core.dom.parser.cpp.CPPASTInitializerExpression.accept(\n\nCPPASTInitializerExpression.java:49)\n        at \norg.eclipse.cdt.internal.core.dom.parser.cpp.CPPASTDeclarator.postAccept\n(CPPASTDeclarator.java:135)\n        at org.eclipse.cdt.internal.core.dom.parser.cpp.CPPASTDeclarator.accept\n(CPPASTDeclarator.java:131)\n        at \norg.eclipse.cdt.internal.core.dom.parser.cpp.CPPASTSimpleDeclaration.accept(\n\nCPPASTSimpleDeclaration.java:74)\n        at \norg.eclipse.cdt.internal.core.dom.parser.cpp.CPPASTDeclarationStatement.accept(\n\nCPPASTDeclarationStatement.java:49)\n        at \norg.eclipse.cdt.internal.core.dom.parser.cpp.CPPASTCompoundStatement.accept(\n\nCPPASTCompoundStatement.java:66)\n        at \norg.eclipse.cdt.internal.core.dom.parser.cpp.CPPASTFunctionDefinition.accept(\n\nCPPASTFunctionDefinition.java:93)\n        at \norg.eclipse.cdt.internal.core.dom.parser.cpp.CPPASTTemplateDeclaration.accept(\n\nCPPASTTemplateDeclaration.java:95)\n        at \norg.eclipse.cdt.internal.core.dom.parser.cpp.CPPASTTranslationUnit.accept\n(CPPASTTranslationUnit.\n\njava:520)\n        at \norg.eclipse.cdt.internal.core.index.domsourceindexer.DOMSourceIndexerRunner.inde\nxFile(\n\nDOMSourceIndexerRunner.java:133)\n        at \norg.eclipse.cdt.internal.core.index.domsourceindexer.AbstractIndexerRunner.index\n(\n\nAbstractIndexerRunner.java:76)\n        at org.eclipse.cdt.internal.core.index.cindexstorage.Index.add\n(Index.java:110)\n        at \norg.eclipse.cdt.internal.core.index.domsourceindexer.DOMAddCompilationUnitToInde\nx.indexDocument(\n\nDOMAddCompilationUnitToIndex.java:29)\n        at \norg.eclipse.cdt.internal.core.index.domsourceindexer.DOMAddFileToIndex.execute\n(DOMAddFileToIndex.\n\njava:60)\n        at org.eclipse.cdt.internal.core.search.processing.JobManager.run\n(JobManager.java:466)\n  at java.lang.Thread.run(Thread.java:534)\n\n22 gmilman on ~\u003e\n22 gmilman on ~\u003ejava.lang.ClassCastException: \norg.eclipse.cdt.internal.core.dom.parser.cpp.\n\nCPPTemplateDefinition$CPPTemplateProblem\n        at \norg.eclipse.cdt.internal.core.dom.parser.cpp.CPPClassScope.createImplicitMembers\n(CPPClassScope.\n\njava:85)\n        at org.eclipse.cdt.internal.core.dom.parser.cpp.CPPClassScope.\u003cinit\u003e\n(CPPClassScope.java:60)\n        at \norg.eclipse.cdt.internal.core.dom.parser.cpp.CPPASTCompositeTypeSpecifier.getSco\npe(\n\nCPPASTCompositeTypeSpecifier.java:112)\n        at \norg.eclipse.cdt.internal.core.dom.parser.cpp.CPPVisitor.getContainingScope\n(CPPVisitor.java:668)\n        at \norg.eclipse.cdt.internal.core.dom.parser.cpp.CPPVisitor.getContainingScope\n(CPPVisitor.java:835)\n        at \norg.eclipse.cdt.internal.core.dom.parser.cpp.CPPVisitor.getContainingScope\n(CPPVisitor.java:657)\n        at org.eclipse.cdt.internal.core.dom.parser.cpp.CPPVisitor.createBinding\n(CPPVisitor.java:481)\n        at org.eclipse.cdt.internal.core.dom.parser.cpp.CPPVisitor.createBinding\n(CPPVisitor.java:188)\n        at \norg.eclipse.cdt.internal.core.dom.parser.cpp.CPPASTName.resolveBinding\n(CPPASTName.java:52)\n        at \norg.eclipse.cdt.internal.core.index.domsourceindexer.CPPGenerateIndexVisitor.pro\ncessName(\n\nCPPGenerateIndexVisitor.java:148)\n        at \norg.eclipse.cdt.internal.core.index.domsourceindexer.CPPGenerateIndexVisitor.vis\nit(\n\nCPPGenerateIndexVisitor.java:112)\n        at org.eclipse.cdt.internal.core.dom.parser.cpp.CPPASTName.accept\n(CPPASTName.java:90)\n        at org.eclipse.cdt.internal.core.dom.parser.cpp.CPPASTDeclarator.accept\n(CPPASTDeclarator.java:126)\n        at \norg.eclipse.cdt.internal.core.dom.parser.cpp.CPPASTSimpleDeclaration.accept(\n\nCPPASTSimpleDeclaration.java:74)\n        at \norg.eclipse.cdt.internal.core.dom.parser.cpp.CPPASTCompositeTypeSpecifier.accept\n(\n\nCPPASTCompositeTypeSpecifier.java:136)\n        at \norg.eclipse.cdt.internal.core.dom.parser.cpp.CPPASTSimpleDeclaration.accept(\n\nCPPASTSimpleDeclaration.java:71)\n        at \norg.eclipse.cdt.internal.core.dom.parser.cpp.CPPASTTemplateDeclaration.accept(\n\nCPPASTTemplateDeclaration.java:95)\n        at \norg.eclipse.cdt.internal.core.dom.parser.cpp.CPPASTTranslationUnit.accept\n(CPPASTTranslationUnit.\n\njava:520)\n        at \norg.eclipse.cdt.internal.core.index.domsourceindexer.DOMSourceIndexerRunner.inde\nxFile(\n\nDOMSourceIndexerRunner.java:133)\n        at \norg.eclipse.cdt.internal.core.index.domsourceindexer.AbstractIndexerRunner.index\n(\n\nAbstractIndexerRunner.java:76)\n        at org.eclipse.cdt.internal.core.index.cindexstorage.Index.add\n(Index.java:110)\n        at \norg.eclipse.cdt.internal.core.index.domsourceindexer.DOMAddCompilationUnitToInde\nx.indexDocument(\n\nDOMAddCompilationUnitToIndex.java:29)\n        at \norg.eclipse.cdt.internal.core.index.domsourceindexer.DOMAddFileToIndex.execute\n(DOMAddFileToIndex.\n\njava:60)\n        at org.eclipse.cdt.internal.core.search.processing.JobManager.run\n(JobManager.java:466)\n        at java.lang.Thread.run(Thread.java:534)\njava.lang.ClassCastException: org.eclipse.cdt.internal.core.dom.parser.cpp.\n\nCPPTemplateDefinition$CPPTemplateProblem\n        at \norg.eclipse.cdt.internal.core.dom.parser.cpp.CPPClassScope.createImplicitMembers\n(CPPClassScope.\n\njava:85)\n        at org.eclipse.cdt.internal.core.dom.parser.cpp.CPPClassScope.\u003cinit\u003e\n(CPPClassScope.java:60)\n        at \norg.eclipse.cdt.internal.core.dom.parser.cpp.CPPASTCompositeTypeSpecifier.getSco\npe(\n\nCPPASTCompositeTypeSpecifier.java:112)\n        at \norg.eclipse.cdt.internal.core.dom.parser.cpp.CPPVisitor.getContainingScope\n(CPPVisitor.java:668)\n        at \norg.eclipse.cdt.internal.core.dom.parser.cpp.CPPVisitor.getContainingScope\n(CPPVisitor.java:835)\n        at \norg.eclipse.cdt.internal.core.dom.parser.cpp.CPPSemantics.getLookupScope\n(CPPSemantics.java:907)\n        at org.eclipse.cdt.internal.core.dom.parser.cpp.CPPSemantics.lookup\n(CPPSemantics.java:987)\n        at \norg.eclipse.cdt.internal.core.dom.parser.cpp.CPPSemantics.resolveBinding\n(CPPSemantics.java:610)\n        at org.eclipse.cdt.internal.core.dom.parser.cpp.CPPVisitor.createBinding\n(CPPVisitor.java:164)\n        at \norg.eclipse.cdt.internal.core.dom.parser.cpp.CPPASTName.resolveBinding\n(CPPASTName.java:52)\n        at \norg.eclipse.cdt.internal.core.dom.parser.cpp.CPPTemplates.createClassSpecializat\nion(CPPTemplates.\n\njava:297)\n        at \norg.eclipse.cdt.internal.core.dom.parser.cpp.CPPTemplates.createBinding\n(CPPTemplates.java:224)\n        at \norg.eclipse.cdt.internal.core.dom.parser.cpp.CPPASTTemplateId.resolveBinding\n(CPPASTTemplateId.java\n\n:74)\n        at \norg.eclipse.cdt.internal.core.index.domsourceindexer.CPPGenerateIndexVisitor.add\nFriendDeclarations\n\n(CPPGenerateIndexVisitor.java:426)\n        at \norg.eclipse.cdt.internal.core.index.domsourceindexer.CPPGenerateIndexVisitor.pro\ncessNameBinding(\n\nCPPGenerateIndexVisitor.java:235)\n        at \norg.eclipse.cdt.internal.core.index.domsourceindexer.CPPGenerateIndexVisitor.pro\ncessName(\n\nCPPGenerateIndexVisitor.java:169)\n        at \norg.eclipse.cdt.internal.core.index.domsourceindexer.CPPGenerateIndexVisitor.vis\nit(\n\nCPPGenerateIndexVisitor.java:112)\n        at org.eclipse.cdt.internal.core.dom.parser.cpp.CPPASTName.accept\n(CPPASTName.java:90)\n        at \norg.eclipse.cdt.internal.core.dom.parser.cpp.CPPASTCompositeTypeSpecifier.accept\n(\n\nCPPASTCompositeTypeSpecifier.java:129)\n        at \norg.eclipse.cdt.internal.core.dom.parser.cpp.CPPASTSimpleDeclaration.accept(\n\nCPPASTSimpleDeclaration.java:71)\n        at \norg.eclipse.cdt.internal.core.dom.parser.cpp.CPPASTTemplateDeclaration.accept(\n\nCPPASTTemplateDeclaration.java:95)\n        at \norg.eclipse.cdt.internal.core.dom.parser.cpp.CPPASTTranslationUnit.accept\n(CPPASTTranslationUnit.\n\njava:520)\n        at \norg.eclipse.cdt.internal.core.index.domsourceindexer.DOMSourceIndexerRunner.inde\nxFile(\n\nDOMSourceIndexerRunner.java:133)\n        at \norg.eclipse.cdt.internal.core.index.domsourceindexer.AbstractIndexerRunner.index\n(\n\nAbstractIndexerRunner.java:76)\n        at org.eclipse.cdt.internal.core.index.cindexstorage.Index.add\n(Index.java:110)\n        at \norg.eclipse.cdt.internal.core.index.domsourceindexer.DOMAddCompilationUnitToInde\nx.indexDocument(\n\nDOMAddCompilationUnitToIndex.java:29)\n        at \norg.eclipse.cdt.internal.core.index.domsourceindexer.DOMAddFileToIndex.execute\n(DOMAddFileToIndex.\n\njava:60)\n        at org.eclipse.cdt.internal.core.search.processing.JobManager.run\n(JobManager.java:466)\n        at java.lang.Thread.run(Thread.java:534)\njava.lang.ClassCastException: org.eclipse.cdt.internal.core.dom.parser.cpp.\n\nCPPTemplateDefinition$CPPTemplateProblem\n        at \norg.eclipse.cdt.internal.core.dom.parser.cpp.CPPClassScope.createImplicitMembers\n(CPPClassScope.\n\njava:85)\n        at org.eclipse.cdt.internal.core.dom.parser.cpp.CPPClassScope.\u003cinit\u003e\n(CPPClassScope.java:60)\n        at \norg.eclipse.cdt.internal.core.dom.parser.cpp.CPPASTCompositeTypeSpecifier.getSco\npe(\n\nCPPASTCompositeTypeSpecifier.java:112)\n        at \norg.eclipse.cdt.internal.core.dom.parser.cpp.CPPVisitor.getContainingScope\n(CPPVisitor.java:668)\n        at \norg.eclipse.cdt.internal.core.dom.parser.cpp.CPPVisitor.getContainingScope\n(CPPVisitor.java:835)\n        at \norg.eclipse.cdt.internal.core.dom.parser.cpp.CPPVisitor.getContainingScope\n(CPPVisitor.java:657)\n        at org.eclipse.cdt.internal.core.dom.parser.cpp.CPPVisitor.createBinding\n(CPPVisitor.java:481)\n        at org.eclipse.cdt.internal.core.dom.parser.cpp.CPPVisitor.createBinding\n(CPPVisitor.java:188)\n        at \norg.eclipse.cdt.internal.core.dom.parser.cpp.CPPASTName.resolveBinding\n(CPPASTName.java:52)\n        at \norg.eclipse.cdt.internal.core.index.domsourceindexer.CPPGenerateIndexVisitor.pro\ncessName(\n\nCPPGenerateIndexVisitor.java:148)\n        at \norg.eclipse.cdt.internal.core.index.domsourceindexer.CPPGenerateIndexVisitor.vis\nit(\n\nCPPGenerateIndexVisitor.java:112)\n        at org.eclipse.cdt.internal.core.dom.parser.cpp.CPPASTName.accept\n(CPPASTName.java:90)\n        at org.eclipse.cdt.internal.core.dom.parser.cpp.CPPASTDeclarator.accept\n(CPPASTDeclarator.java:126)\n        at \norg.eclipse.cdt.internal.core.dom.parser.cpp.CPPASTSimpleDeclaration.accept(\n\nCPPASTSimpleDeclaration.java:74)\n        at \norg.eclipse.cdt.internal.core.dom.parser.cpp.CPPASTCompositeTypeSpecifier.accept\n(\n\nCPPASTCompositeTypeSpecifier.java:136)\n        at \norg.eclipse.cdt.internal.core.dom.parser.cpp.CPPASTSimpleDeclaration.accept(\n\nCPPASTSimpleDeclaration.java:71)\n        at \norg.eclipse.cdt.internal.core.dom.parser.cpp.CPPASTTemplateDeclaration.accept(\n\nCPPASTTemplateDeclaration.java:95)\n        at \norg.eclipse.cdt.internal.core.dom.parser.cpp.CPPASTTranslationUnit.accept\n(CPPASTTranslationUnit.\n\njava:520)\n        at \norg.eclipse.cdt.internal.core.index.domsourceindexer.DOMSourceIndexerRunner.inde\nxFile(\n\nDOMSourceIndexerRunner.java:133)\n        at \norg.eclipse.cdt.internal.core.index.domsourceindexer.AbstractIndexerRunner.index\n(\n\nAbstractIndexerRunner.java:76)\n        at org.eclipse.cdt.internal.core.index.cindexstorage.Index.add\n(Index.java:110)\n        at \norg.eclipse.cdt.internal.core.index.domsourceindexer.DOMAddCompilationUnitToInde\nx.indexDocument(\n\nDOMAddCompilationUnitToIndex.java:29)\n        at \norg.eclipse.cdt.internal.core.index.domsourceindexer.DOMAddFileToIndex.execute\n(DOMAddFileToIndex.\n\njava:60)\n        at org.eclipse.cdt.internal.core.search.processing.JobManager.run\n(JobManager.java:466)  at java.lang.\n\nThread.run(Thread.java:534)\njava.lang.ClassCastException: org.eclipse.cdt.internal.core.dom.parser.cpp.\n\nCPPTemplateDefinition$CPPTemplateProblem\n        at \norg.eclipse.cdt.internal.core.dom.parser.cpp.CPPSemantics.getTargetParameterType\ns(CPPSemantics.\n\njava:2141)\n        at \norg.eclipse.cdt.internal.core.dom.parser.cpp.CPPSemantics.resolveFunction\n(CPPSemantics.java:2219)\n        at \norg.eclipse.cdt.internal.core.dom.parser.cpp.CPPSemantics.resolveAmbiguities\n(CPPSemantics.java:\n\n1993)\n        at \norg.eclipse.cdt.internal.core.dom.parser.cpp.CPPSemantics.resolveBinding\n(CPPSemantics.java:621)\n        at \norg.eclipse.cdt.internal.core.dom.parser.cpp.CPPVisitor.resolveBinding\n(CPPVisitor.java:927)\n        at org.eclipse.cdt.internal.core.dom.parser.cpp.CPPVisitor.createBinding\n(CPPVisitor.java:182)\n        at \norg.eclipse.cdt.internal.core.dom.parser.cpp.CPPASTName.resolveBinding\n(CPPASTName.java:52)\n        at \norg.eclipse.cdt.internal.core.index.domsourceindexer.CPPGenerateIndexVisitor.pro\ncessName(\n\nCPPGenerateIndexVisitor.java:148)\n        at \norg.eclipse.cdt.internal.core.index.domsourceindexer.CPPGenerateIndexVisitor.vis\nit(\n\nCPPGenerateIndexVisitor.java:112)\n        at org.eclipse.cdt.internal.core.dom.parser.cpp.CPPASTName.accept\n(CPPASTName.java:90)\n        at \norg.eclipse.cdt.internal.core.dom.parser.cpp.CPPASTIdExpression.accept\n(CPPASTIdExpression.java:46)\n        at \norg.eclipse.cdt.internal.core.dom.parser.cpp.CPPASTFunctionCallExpression.accept\n(\n\nCPPASTFunctionCallExpression.java:64)\n        at \norg.eclipse.cdt.internal.core.dom.parser.cpp.CPPASTInitializerExpression.accept(\n\nCPPASTInitializerExpression.java:49)\n        at \norg.eclipse.cdt.internal.core.dom.parser.cpp.CPPASTDeclarator.postAccept\n(CPPASTDeclarator.java:135)\n  at org.eclipse.cdt.internal.core.dom.parser.cpp.CPPASTDeclarator.accept\n(CPPASTDeclarator.java:131)\n        at \norg.eclipse.cdt.internal.core.dom.parser.cpp.CPPASTSimpleDeclaration.accept(\n\nCPPASTSimpleDeclaration.java:74)\n        at \norg.eclipse.cdt.internal.core.dom.parser.cpp.CPPASTDeclarationStatement.accept(\n\nCPPASTDeclarationStatement.java:49)\n        at \norg.eclipse.cdt.internal.core.dom.parser.cpp.CPPASTCompoundStatement.accept(\n\nCPPASTCompoundStatement.java:66)\n        at \norg.eclipse.cdt.internal.core.dom.parser.cpp.CPPASTFunctionDefinition.accept(\n\nCPPASTFunctionDefinition.java:93)\n        at \norg.eclipse.cdt.internal.core.dom.parser.cpp.CPPASTTemplateDeclaration.accept(\n\nCPPASTTemplateDeclaration.java:95)\n        at \norg.eclipse.cdt.internal.core.dom.parser.cpp.CPPASTTranslationUnit.accept\n(CPPASTTranslationUnit.\n\njava:520)\n        at \norg.eclipse.cdt.internal.core.index.domsourceindexer.DOMSourceIndexerRunner.inde\nxFile(\n\nDOMSourceIndexerRunner.java:133)\n        at \norg.eclipse.cdt.internal.core.index.domsourceindexer.AbstractIndexerRunner.index\n(\n\nAbstractIndexerRunner.java:76)\n        at org.eclipse.cdt.internal.core.index.cindexstorage.Index.add\n(Index.java:110)\n        at \norg.eclipse.cdt.internal.core.index.domsourceindexer.DOMAddCompilationUnitToInde\nx.indexDocument(\n\nDOMAddCompilationUnitToIndex.java:29)\n        at \norg.eclipse.cdt.internal.core.index.domsourceindexer.DOMAddFileToIndex.execute\n(DOMAddFileToIndex.\n\njava:60)\n        at org.eclipse.cdt.internal.core.search.processing.JobManager.run\n(JobManager.java:466)\n        at java.lang.Thread.run(Thread.java:534)\nGConf Error: Failed to contact configuration server; some possible causes are \nthat you need to enable TCP/IP \n\nnetworking for ORBit, or you have stale NFS locks due to a system crash. See \nhttp://www.gnome.org/projects/\n\ngconf/ for information. (Details -  1: IOR \nfile \u0027/users/gmilman/.gconfd/lock/ior\u0027 not opened successfully, no \n\ngconfd located: No such file or directory 2: IOR \nfile \u0027/users/gmilman/.gconfd/lock/ior\u0027 not opened \n\nsuccessfully, no gconfd located: No such file or directory)\nGConf Error: Failed to contact configuration server; some possible causes are \nthat you need to enable TCP/IP \n\nnetworking for ORBit, or you have stale NFS locks due to a system crash. See \nhttp://www.gnome.org/projects/\n\ngconf/ for information. (Details -  1: IOR \nfile \u0027/users/gmilman/.gconfd/lock/ior\u0027 not opened successfully, no \n\ngconfd located: No such file or directory 2: IOR \nfile \u0027/users/gmilman/.gconfd/lock/ior\u0027 not opened successfully, no gconfd \nlocated: No such file or directory)",
    "Hello, Can you attach to the PR the file causing this ... if possible.\nIt looks like, at first glance, a template parsing problem.\n\nThanks",
    "I don\u0027t know what is the file that cause this.\nCan you be more specific? \n\nGuy",
    "(In reply to comment #2)\n\u003e I don\u0027t know what is the file that cause this.\n\u003e Can you be more specific? \n\u003e \n\nThe exception is cause by the DOM C++ parser, so if we have the C++\nfile or if you know the C++ construct semantic that the parser can not grok\nthat will be of a tremondous help.  We could also add this to our regression\ntesting.",
    "Hi,\nAfter many efforts I succeeded to isolate at least one of the problems (I\u0027m not \nsure it is the only one) - an include to the ACE file SOCK_Stream.h \n(ACE_wrappers/ace/SOCK_Stream.h) that was added to one of the files caused the \nexceptions.\nHere is the file content:\n\n#ident \"@(#)\\051Netology: $Id: /mvobs/ACE/Linux.i686.g++-\n323/ACE_wrappers/ace/SOCK_Stream.h /main/integ_ace51_5.1c/1 29.02.04 17:42:57 \ninteg_base Exp $\"\n/* -*- C++ -*- */\n// SOCK_Stream.h,v 4.15 2000/01/05 15:54:31 levine Exp\n\n// \u003d\u003d\u003d\u003d\u003d\u003d\u003d\u003d\u003d\u003d\u003d\u003d\u003d\u003d\u003d\u003d\u003d\u003d\u003d\u003d\u003d\u003d\u003d\u003d\u003d\u003d\u003d\u003d\u003d\u003d\u003d\u003d\u003d\u003d\u003d\u003d\u003d\u003d\u003d\u003d\u003d\u003d\u003d\u003d\u003d\u003d\u003d\u003d\u003d\u003d\u003d\u003d\u003d\u003d\u003d\u003d\u003d\u003d\u003d\u003d\u003d\u003d\u003d\u003d\u003d\u003d\u003d\u003d\u003d\u003d\u003d\u003d\u003d\u003d\u003d\u003d\n//\n// \u003d LIBRARY\n//    ace\n//\n// \u003d FILENAME\n//    SOCK_Stream.h\n//\n// \u003d AUTHOR\n//    Doug Schmidt\n//\n// \u003d\u003d\u003d\u003d\u003d\u003d\u003d\u003d\u003d\u003d\u003d\u003d\u003d\u003d\u003d\u003d\u003d\u003d\u003d\u003d\u003d\u003d\u003d\u003d\u003d\u003d\u003d\u003d\u003d\u003d\u003d\u003d\u003d\u003d\u003d\u003d\u003d\u003d\u003d\u003d\u003d\u003d\u003d\u003d\u003d\u003d\u003d\u003d\u003d\u003d\u003d\u003d\u003d\u003d\u003d\u003d\u003d\u003d\u003d\u003d\u003d\u003d\u003d\u003d\u003d\u003d\u003d\u003d\u003d\u003d\u003d\u003d\u003d\u003d\u003d\u003d\n\n#ifndef ACE_SOCK_STREAM_H\n/*\n *  Name.......     /mvobs/ACE/Linux.i686.g++-323/ACE_wrappers/ace/SOCK_Stream.h\n *  Description..\n *  Author... integ_base \n *\n *\n *\n *\n *  Revisions.... \n *  \n *  Revision /main/integ_ace51_5.1c/1 29.02.04 17:42:57 integ_base from \ninteg_base_infra_3.0.5_view\n *  INFRA Linux port. gcc 3.2.3\n *\n */\n#define ACE_SOCK_STREAM_H\n\n#include \"ace/SOCK_IO.h\"\n\n#if !defined (ACE_LACKS_PRAGMA_ONCE)\n# pragma once\n#endif /* ACE_LACKS_PRAGMA_ONCE */\n\n#include \"ace/INET_Addr.h\"\n\nclass ACE_Export ACE_SOCK_Stream : public ACE_SOCK_IO\n{\n  // \u003d TITLE\n  //     Defines the methods in the \u003cACE_SOCK_Stream\u003e abstraction.\n  //\n  // \u003d DESCRIPTION\n  //     This adds additional wrapper methods atop the \u003cACE_SOCK_IO\u003e\n  //     class.\n  //\n  // \u003d NOTES\n  //\n  //     The \"_n\" I/O methods keep looping until all the data has been\n  //     transferred.  These methods also work for sockets in\n  //     non-blocking mode i.e., they keep looping on EWOULDBLOCK.\n  //     \u003ctimeout\u003e is used to make sure we keep making progress, i.e.,\n  //     the same timeout value is used for every I/O operation in the\n  //     loop and the timeout is not counted down.  If the transfer\n  //     times out, the number of bytes transferred so far are\n  //     returned.\n  //\n  //     Errors are reported by -1 and 0 return values.\n  //\n  //     Methods with the extra \u003cflags\u003e argument will always result in\n  //     \u003csend\u003e getting called. Methods without the extra \u003cflags\u003e\n  //     argument will result in \u003csend\u003e getting called on Win32\n  //     platforms, and \u003cwrite\u003e getting called on non-Win32 platforms.\n  //\npublic:\n  // Initialization and termination methods.\n  ACE_SOCK_Stream (void);\n  // Constructor.\n\n  ACE_SOCK_Stream (ACE_HANDLE h);\n  // Constructor (sets the underlying \u003cACE_HANDLE\u003e with \u003ch\u003e).\n\n  ~ACE_SOCK_Stream (void);\n  // Destructor.\n\n  // \u003d I/O functions.\n\n  ssize_t recv_n (void *buf,\n                  size_t len,\n                  int flags,\n                  const ACE_Time_Value *timeout \u003d 0) const;\n  // Try to recv exactly \u003clen\u003e bytes into \u003cbuf\u003e from \u003chandle\u003e.\n\n  ssize_t recv_n (void *buf,\n                  size_t len,\n                  const ACE_Time_Value *timeout \u003d 0) const;\n  // Try to recv exactly \u003clen\u003e bytes into \u003cbuf\u003e from \u003chandle\u003e.\n\n  ssize_t recvv_n (iovec iov[],\n                   size_t iovcnt,\n                   const ACE_Time_Value *timeout \u003d 0) const;\n  // Receive an \u003ciovec\u003e of size \u003ciovcnt\u003e to the connected socket.\n\n  ssize_t send_n (const void *buf,\n                  size_t len,\n                  int flags,\n                  const ACE_Time_Value *timeout \u003d 0) const;\n  // Try to send exactly \u003clen\u003e bytes into \u003cbuf\u003e from \u003chandle\u003e.\n\n  ssize_t send_n (const void *buf,\n                  size_t len,\n                  const ACE_Time_Value *timeout \u003d 0) const;\n  // Try to send exactly \u003clen\u003e bytes into \u003cbuf\u003e from \u003chandle\u003e.\n\n  ssize_t sendv_n (const iovec iov[],\n                   size_t iovcnt,\n                   const ACE_Time_Value *timeout \u003d 0) const;\n  // Send an \u003ciovec\u003e of size \u003ciovcnt\u003e to the connected socket.\n\n  // \u003d Send/receive ``urgent\u0027\u0027 data (see TCP specs...).\n  ssize_t send_urg (const void *ptr,\n                    size_t len \u003d sizeof (char),\n                    const ACE_Time_Value *timeout \u003d 0) const;\n\n  ssize_t recv_urg (void *ptr,\n                    size_t len \u003d sizeof (char),\n                    const ACE_Time_Value *timeout \u003d 0) const;\n\n  // \u003d Selectively close endpoints.\n  int close_reader (void);\n  // Close down the reader.\n  int close_writer (void);\n  // Close down the writer.\n\n  int close (void);\n  // Close down the socket (we need this to make things work correctly\n  // on Win32, which requires use to do a \u003cclose_writer\u003e before doing\n  // the close to avoid losing data).\n\n  // \u003d Meta-type info\n  typedef ACE_INET_Addr PEER_ADDR;\n\n  void dump (void) const;\n  // Dump the state of an object.\n\n  ACE_ALLOC_HOOK_DECLARE;\n  // Declare the dynamic allocation hooks.\n};\n\n#if !defined (ACE_LACKS_INLINE_FUNCTIONS)\n#include \"ace/SOCK_Stream.i\"\n#endif\n\n#endif /* ACE_SOCK_STREAM_H */\n",
    "Hi,\nThe file I found as a problematic isn\u0027t the only problem - the project continue \nto crash. I think that the reason is ACE files (I found out that the file \nACE_wrappers/ace/SSL/SSL_SOCK_Connector.h is also problematic) but I can\u0027t tell \nthat these files are the only reason.",
    "\n\n*** This bug has been marked as a duplicate of 106715 ***"
  ],
  "commentCreationDates": [
    "2005-08-11T09:00:16+02:00",
    "2005-08-11T15:57:41+02:00",
    "2005-08-14T07:58:46+02:00",
    "2005-08-15T16:08:43+02:00",
    "2005-08-31T07:56:36+02:00",
    "2005-08-31T14:25:13+02:00",
    "2006-01-13T15:41:20+01:00"
  ],
  "traces": [
    {
      "exceptionType": "java.lang.ClassCastException",
      "elements": [
        {
          "method": "org.eclipse.cdt.internal.core.dom.parser.cpp.CPPClassScope.createImplicitMembers",
          "source": "CPPClassScope.  java:85"
        },
        {
          "method": "org.eclipse.cdt.internal.core.dom.parser.cpp.CPPClassScope.\u003cinit\u003e",
          "source": "CPPClassScope.java:60"
        },
        {
          "method": "org.eclipse.cdt.internal.core.dom.parser.cpp.CPPASTCompositeTypeSpecifier.getScope",
          "source": "  CPPASTCompositeTypeSpecifier.java:112"
        },
        {
          "method": "org.eclipse.cdt.internal.core.dom.parser.cpp.CPPVisitor.getContainingScope",
          "source": "CPPVisitor.java:668"
        },
        {
          "method": "org.eclipse.cdt.internal.core.dom.parser.cpp.CPPVisitor.getContainingScope",
          "source": "CPPVisitor.java:835"
        },
        {
          "method": "org.eclipse.cdt.internal.core.dom.parser.cpp.CPPVisitor.getContainingScope",
          "source": "CPPVisitor.java:657"
        },
        {
          "method": "org.eclipse.cdt.internal.core.dom.parser.cpp.CPPVisitor.createBinding",
          "source": "CPPVisitor.java:481"
        },
        {
          "method": "org.eclipse.cdt.internal.core.dom.parser.cpp.CPPVisitor.createBinding",
          "source": "CPPVisitor.java:188"
        },
        {
          "method": "org.eclipse.cdt.internal.core.dom.parser.cpp.CPPASTName.resolveBinding",
          "source": "CPPASTName.java:52"
        },
        {
          "method": "org.eclipse.cdt.internal.core.index.domsourceindexer.CPPGenerateIndexVisitor.processName",
          "source": "  CPPGenerateIndexVisitor.java:148"
        },
        {
          "method": "org.eclipse.cdt.internal.core.index.domsourceindexer.CPPGenerateIndexVisitor.visit",
          "source": "  CPPGenerateIndexVisitor.java:112"
        },
        {
          "method": "org.eclipse.cdt.internal.core.dom.parser.cpp.CPPASTName.accept",
          "source": "CPPASTName.java:90"
        },
        {
          "method": "org.eclipse.cdt.internal.core.dom.parser.cpp.CPPASTDeclarator.accept",
          "source": "CPPASTDeclarator.java:126"
        },
        {
          "method": "org.eclipse.cdt.internal.core.dom.parser.cpp.CPPASTSimpleDeclaration.accept",
          "source": "  CPPASTSimpleDeclaration.java:74"
        },
        {
          "method": "org.eclipse.cdt.internal.core.dom.parser.cpp.CPPASTCompositeTypeSpecifier.accept",
          "source": "  CPPASTCompositeTypeSpecifier.java:136"
        },
        {
          "method": "org.eclipse.cdt.internal.core.dom.parser.cpp.CPPASTSimpleDeclaration.accept",
          "source": "  CPPASTSimpleDeclaration.java:71"
        },
        {
          "method": "org.eclipse.cdt.internal.core.dom.parser.cpp.CPPASTTemplateDeclaration.accept",
          "source": "  CPPASTTemplateDeclaration.java:95"
        },
        {
          "method": "org.eclipse.cdt.internal.core.dom.parser.cpp.CPPASTTranslationUnit.accept",
          "source": "CPPASTTranslationUnit.  java:520"
        },
        {
          "method": "org.eclipse.cdt.internal.core.index.domsourceindexer.DOMSourceIndexerRunner.indexFile",
          "source": "  DOMSourceIndexerRunner.java:133"
        },
        {
          "method": "org.eclipse.cdt.internal.core.index.domsourceindexer.AbstractIndexerRunner.index",
          "source": "  AbstractIndexerRunner.java:76"
        },
        {
          "method": "org.eclipse.cdt.internal.core.index.cindexstorage.Index.add",
          "source": "Index.java:110"
        },
        {
          "method": "org.eclipse.cdt.internal.core.index.domsourceindexer.DOMAddCompilationUnitToIndex.indexDocument",
          "source": "  DOMAddCompilationUnitToIndex.java:29"
        },
        {
          "method": "org.eclipse.cdt.internal.core.index.domsourceindexer.DOMAddFileToIndex.execute",
          "source": "DOMAddFileToIndex.  java:60"
        },
        {
          "method": "org.eclipse.cdt.internal.core.search.processing.JobManager.run",
          "source": "JobManager.java:466"
        },
        {
          "method": "java.lang.Thread.run",
          "source": "Thread.java:534"
        }
      ],
      "number": 0,
      "commentIndex": 0,
      "bugId": "106716",
      "duplicateId": "106715",
      "date": "2005-08-11T09:00:16+02:00",
      "product": "CDT",
      "component": "cdt-core",
      "severity": "trivial"
    },
    {
      "exceptionType": "java.lang.ClassCastException",
      "elements": [
        {
          "method": "org.eclipse.cdt.internal.core.dom.parser.cpp.CPPClassScope.createImplicitMembers",
          "source": "CPPClassScope.  java:85"
        },
        {
          "method": "org.eclipse.cdt.internal.core.dom.parser.cpp.CPPClassScope.\u003cinit\u003e",
          "source": "CPPClassScope.java:60"
        },
        {
          "method": "org.eclipse.cdt.internal.core.dom.parser.cpp.CPPASTCompositeTypeSpecifier.getScope",
          "source": "  CPPASTCompositeTypeSpecifier.java:112"
        },
        {
          "method": "org.eclipse.cdt.internal.core.dom.parser.cpp.CPPVisitor.getContainingScope",
          "source": "CPPVisitor.java:668"
        },
        {
          "method": "org.eclipse.cdt.internal.core.dom.parser.cpp.CPPVisitor.getContainingScope",
          "source": "CPPVisitor.java:835"
        },
        {
          "method": "org.eclipse.cdt.internal.core.dom.parser.cpp.CPPSemantics.getLookupScope",
          "source": "CPPSemantics.java:907"
        },
        {
          "method": "org.eclipse.cdt.internal.core.dom.parser.cpp.CPPSemantics.lookup",
          "source": "CPPSemantics.java:987"
        },
        {
          "method": "org.eclipse.cdt.internal.core.dom.parser.cpp.CPPSemantics.resolveBinding",
          "source": "CPPSemantics.java:610"
        },
        {
          "method": "org.eclipse.cdt.internal.core.dom.parser.cpp.CPPVisitor.createBinding",
          "source": "CPPVisitor.java:164"
        },
        {
          "method": "org.eclipse.cdt.internal.core.dom.parser.cpp.CPPASTName.resolveBinding",
          "source": "CPPASTName.java:52"
        },
        {
          "method": "org.eclipse.cdt.internal.core.dom.parser.cpp.CPPTemplates.createClassSpecialization",
          "source": "CPPTemplates.  java:297"
        },
        {
          "method": "org.eclipse.cdt.internal.core.dom.parser.cpp.CPPTemplates.createBinding",
          "source": "CPPTemplates.java:224"
        },
        {
          "method": "org.eclipse.cdt.internal.core.dom.parser.cpp.CPPASTTemplateId.resolveBinding",
          "source": "CPPASTTemplateId.java  :74"
        },
        {
          "method": "org.eclipse.cdt.internal.core.index.domsourceindexer.CPPGenerateIndexVisitor.addFriendDeclarations",
          "source": "CPPGenerateIndexVisitor.java:426"
        },
        {
          "method": "org.eclipse.cdt.internal.core.index.domsourceindexer.CPPGenerateIndexVisitor.processNameBinding",
          "source": "  CPPGenerateIndexVisitor.java:235"
        },
        {
          "method": "org.eclipse.cdt.internal.core.index.domsourceindexer.CPPGenerateIndexVisitor.processName",
          "source": "  CPPGenerateIndexVisitor.java:169"
        },
        {
          "method": "org.eclipse.cdt.internal.core.index.domsourceindexer.CPPGenerateIndexVisitor.visit",
          "source": "  CPPGenerateIndexVisitor.java:112"
        },
        {
          "method": "org.eclipse.cdt.internal.core.dom.parser.cpp.CPPASTName.accept",
          "source": "CPPASTName.java:90"
        },
        {
          "method": "org.eclipse.cdt.internal.core.dom.parser.cpp.CPPASTCompositeTypeSpecifier.accept",
          "source": "  CPPASTCompositeTypeSpecifier.java:129"
        },
        {
          "method": "org.eclipse.cdt.internal.core.dom.parser.cpp.CPPASTSimpleDeclaration.accept",
          "source": "  CPPASTSimpleDeclaration.java:71"
        },
        {
          "method": "org.eclipse.cdt.internal.core.dom.parser.cpp.CPPASTTemplateDeclaration.accept",
          "source": "  CPPASTTemplateDeclaration.java:95"
        },
        {
          "method": "org.eclipse.cdt.internal.core.dom.parser.cpp.CPPASTTranslationUnit.accept",
          "source": "CPPASTTranslationUnit.  java:520"
        },
        {
          "method": "org.eclipse.cdt.internal.core.index.domsourceindexer.DOMSourceIndexerRunner.indexFile",
          "source": "  DOMSourceIndexerRunner.java:133"
        },
        {
          "method": "org.eclipse.cdt.internal.core.index.domsourceindexer.AbstractIndexerRunner.index",
          "source": "  AbstractIndexerRunner.java:76"
        },
        {
          "method": "org.eclipse.cdt.internal.core.index.cindexstorage.Index.add",
          "source": "Index.java:110"
        },
        {
          "method": "org.eclipse.cdt.internal.core.index.domsourceindexer.DOMAddCompilationUnitToIndex.indexDocument",
          "source": "  DOMAddCompilationUnitToIndex.java:29"
        },
        {
          "method": "org.eclipse.cdt.internal.core.index.domsourceindexer.DOMAddFileToIndex.execute",
          "source": "DOMAddFileToIndex.  java:60"
        },
        {
          "method": "org.eclipse.cdt.internal.core.search.processing.JobManager.run",
          "source": "JobManager.java:466"
        },
        {
          "method": "java.lang.Thread.run",
          "source": "Thread.java:534"
        }
      ],
      "number": 1,
      "commentIndex": 0,
      "bugId": "106716",
      "duplicateId": "106715",
      "date": "2005-08-11T09:00:16+02:00",
      "product": "CDT",
      "component": "cdt-core",
      "severity": "trivial"
    },
    {
      "exceptionType": "java.lang.ClassCastException",
      "message": "org.eclipse.cdt.internal.core.dom.parser.cpp.  CPPTemplateDefinition$CPPTemplateProblem",
      "elements": [
        {
          "method": "org.eclipse.cdt.internal.core.dom.parser.cpp.CPPClassScope.createImplicitMembers",
          "source": "CPPClassScope.java:85"
        },
        {
          "method": "org.eclipse.cdt.internal.core.dom.parser.cpp.CPPClassScope.\u003cinit\u003e",
          "source": "CPPClassScope.java:60"
        },
        {
          "method": "org.eclipse.cdt.internal.core.dom.parser.cpp.CPPASTCompositeTypeSpecifier.getScope",
          "source": "  CPPASTCompositeTypeSpecifier.java:112"
        },
        {
          "method": "org.eclipse.cdt.internal.core.dom.parser.cpp.CPPVisitor.getContainingScope",
          "source": "CPPVisitor.java:668"
        },
        {
          "method": "org.eclipse.cdt.internal.core.dom.parser.cpp.CPPVisitor.getContainingScope",
          "source": "CPPVisitor.java:835"
        },
        {
          "method": "org.eclipse.cdt.internal.core.dom.parser.cpp.CPPVisitor.getContainingScope",
          "source": "CPPVisitor.java:657"
        },
        {
          "method": "org.eclipse.cdt.internal.core.dom.parser.cpp.CPPVisitor.createBinding",
          "source": "CPPVisitor.java:481"
        },
        {
          "method": "org.eclipse.cdt.internal.core.dom.parser.cpp.CPPVisitor.createBinding",
          "source": "CPPVisitor.java:188"
        },
        {
          "method": "org.eclipse.cdt.internal.core.dom.parser.cpp.CPPASTName.resolveBinding",
          "source": "CPPASTName.java:52"
        },
        {
          "method": "org.eclipse.cdt.internal.core.index.domsourceindexer.CPPGenerateIndexVisitor.processName",
          "source": "  CPPGenerateIndexVisitor.java:148"
        },
        {
          "method": "org.eclipse.cdt.internal.core.index.domsourceindexer.CPPGenerateIndexVisitor.visit",
          "source": "  CPPGenerateIndexVisitor.java:112"
        },
        {
          "method": "org.eclipse.cdt.internal.core.dom.parser.cpp.CPPASTName.accept",
          "source": "CPPASTName.java:90"
        },
        {
          "method": "org.eclipse.cdt.internal.core.dom.parser.cpp.CPPASTDeclarator.accept",
          "source": "CPPASTDeclarator.java:126"
        },
        {
          "method": "org.eclipse.cdt.internal.core.dom.parser.cpp.CPPASTSimpleDeclaration.accept",
          "source": "  CPPASTSimpleDeclaration.java:74"
        },
        {
          "method": "org.eclipse.cdt.internal.core.dom.parser.cpp.CPPASTCompositeTypeSpecifier.accept",
          "source": "  CPPASTCompositeTypeSpecifier.java:136"
        },
        {
          "method": "org.eclipse.cdt.internal.core.dom.parser.cpp.CPPASTSimpleDeclaration.accept",
          "source": "  CPPASTSimpleDeclaration.java:71"
        },
        {
          "method": "org.eclipse.cdt.internal.core.dom.parser.cpp.CPPASTTemplateDeclaration.accept",
          "source": "CPPASTTemplateDeclaration.  java:95"
        },
        {
          "method": "org.eclipse.cdt.internal.core.dom.parser.cpp.CPPASTTranslationUnit.accept",
          "source": "CPPASTTranslationUnit.  java:520"
        },
        {
          "method": "org.eclipse.cdt.internal.core.index.domsourceindexer.DOMSourceIndexerRunner.indexFile",
          "source": "  DOMSourceIndexerRunner.java:133"
        },
        {
          "method": "org.eclipse.cdt.internal.core.index.domsourceindexer.AbstractIndexerRunner.index",
          "source": "  AbstractIndexerRunner.java:76"
        },
        {
          "method": "org.eclipse.cdt.internal.core.index.cindexstorage.Index.add",
          "source": "Index.java:110"
        },
        {
          "method": "org.eclipse.cdt.internal.core.index.domsourceindexer.DOMAddCompilationUnitToIndex.indexDocument",
          "source": "  DOMAddCompilationUnitToIndex.java:29"
        },
        {
          "method": "org.eclipse.cdt.internal.core.index.domsourceindexer.DOMAddFileToIndex.execute",
          "source": "DOMAddFileToIndex.  java:60"
        },
        {
          "method": "org.eclipse.cdt.internal.core.search.processing.JobManager.run",
          "source": "JobManager.java:466"
        },
        {
          "method": "java.lang.Thread.run",
          "source": "Thread.java:534"
        }
      ],
      "number": 2,
      "commentIndex": 0,
      "bugId": "106716",
      "duplicateId": "106715",
      "date": "2005-08-11T09:00:16+02:00",
      "product": "CDT",
      "component": "cdt-core",
      "severity": "trivial"
    },
    {
      "exceptionType": "java.lang.ClassCastException",
      "message": "org.eclipse.cdt.internal.core.dom.parser.cpp.  CPPTemplateDefinition$CPPTemplateProblem",
      "elements": [
        {
          "method": "org.eclipse.cdt.internal.core.dom.parser.cpp.CPPSemantics.getTargetParameterTypes",
          "source": "CPPSemantics.  java:2141"
        },
        {
          "method": "org.eclipse.cdt.internal.core.dom.parser.cpp.CPPSemantics.resolveFunction",
          "source": "CPPSemantics.java:2219"
        },
        {
          "method": "org.eclipse.cdt.internal.core.dom.parser.cpp.CPPSemantics.resolveAmbiguities",
          "source": "CPPSemantics.java:  1993"
        },
        {
          "method": "org.eclipse.cdt.internal.core.dom.parser.cpp.CPPSemantics.resolveBinding",
          "source": "CPPSemantics.java:621"
        },
        {
          "method": "org.eclipse.cdt.internal.core.dom.parser.cpp.CPPVisitor.resolveBinding",
          "source": "CPPVisitor.java:927"
        },
        {
          "method": "org.eclipse.cdt.internal.core.dom.parser.cpp.CPPVisitor.createBinding",
          "source": "CPPVisitor.java:182"
        },
        {
          "method": "org.eclipse.cdt.internal.core.dom.parser.cpp.CPPASTName.resolveBinding",
          "source": "CPPASTName.java:52"
        },
        {
          "method": "org.eclipse.cdt.internal.core.index.domsourceindexer.CPPGenerateIndexVisitor.processName",
          "source": "  CPPGenerateIndexVisitor.java:148"
        },
        {
          "method": "org.eclipse.cdt.internal.core.index.domsourceindexer.CPPGenerateIndexVisitor.visit",
          "source": "  CPPGenerateIndexVisitor.java:112"
        },
        {
          "method": "org.eclipse.cdt.internal.core.dom.parser.cpp.CPPASTName.accept",
          "source": "CPPASTName.java:90"
        },
        {
          "method": "org.eclipse.cdt.internal.core.dom.parser.cpp.CPPASTIdExpression.accept",
          "source": "CPPASTIdExpression.java:46"
        },
        {
          "method": "org.eclipse.cdt.internal.core.dom.parser.cpp.CPPASTFunctionCallExpression.accept",
          "source": "  CPPASTFunctionCallExpression.java:64"
        },
        {
          "method": "org.eclipse.cdt.internal.core.dom.parser.cpp.CPPASTInitializerExpression.accept",
          "source": "  CPPASTInitializerExpression.java:49"
        },
        {
          "method": "org.eclipse.cdt.internal.core.dom.parser.cpp.CPPASTDeclarator.postAccept",
          "source": "CPPASTDeclarator.java:135"
        },
        {
          "method": "org.eclipse.cdt.internal.core.dom.parser.cpp.CPPASTDeclarator.accept",
          "source": "CPPASTDeclarator.java:131"
        },
        {
          "method": "org.eclipse.cdt.internal.core.dom.parser.cpp.CPPASTSimpleDeclaration.accept",
          "source": "  CPPASTSimpleDeclaration.java:74"
        },
        {
          "method": "org.eclipse.cdt.internal.core.dom.parser.cpp.CPPASTDeclarationStatement.accept",
          "source": "  CPPASTDeclarationStatement.java:49"
        },
        {
          "method": "org.eclipse.cdt.internal.core.dom.parser.cpp.CPPASTCompoundStatement.accept",
          "source": "  CPPASTCompoundStatement.java:66"
        },
        {
          "method": "org.eclipse.cdt.internal.core.dom.parser.cpp.CPPASTFunctionDefinition.accept",
          "source": "  CPPASTFunctionDefinition.java:93"
        },
        {
          "method": "org.eclipse.cdt.internal.core.dom.parser.cpp.CPPASTTemplateDeclaration.accept",
          "source": "  CPPASTTemplateDeclaration.java:95"
        },
        {
          "method": "org.eclipse.cdt.internal.core.dom.parser.cpp.CPPASTTranslationUnit.accept",
          "source": "CPPASTTranslationUnit.  java:520"
        },
        {
          "method": "org.eclipse.cdt.internal.core.index.domsourceindexer.DOMSourceIndexerRunner.indexFile",
          "source": "  DOMSourceIndexerRunner.java:133"
        },
        {
          "method": "org.eclipse.cdt.internal.core.index.domsourceindexer.AbstractIndexerRunner.index",
          "source": "  AbstractIndexerRunner.java:76"
        },
        {
          "method": "org.eclipse.cdt.internal.core.index.cindexstorage.Index.add",
          "source": "Index.java:110"
        },
        {
          "method": "org.eclipse.cdt.internal.core.index.domsourceindexer.DOMAddCompilationUnitToIndex.indexDocument",
          "source": "  DOMAddCompilationUnitToIndex.java:29"
        },
        {
          "method": "org.eclipse.cdt.internal.core.index.domsourceindexer.DOMAddFileToIndex.execute",
          "source": "DOMAddFileToIndex.  java:60"
        },
        {
          "method": "org.eclipse.cdt.internal.core.search.processing.JobManager.run",
          "source": "JobManager.java:466"
        },
        {
          "method": "java.lang.Thread.run",
          "source": "Thread.java:534"
        }
      ],
      "number": 3,
      "commentIndex": 0,
      "bugId": "106716",
      "duplicateId": "106715",
      "date": "2005-08-11T09:00:16+02:00",
      "product": "CDT",
      "component": "cdt-core",
      "severity": "trivial"
    },
    {
      "exceptionType": "java.lang.ClassCastException",
      "message": "org.eclipse.cdt.internal.core.dom.parser.cpp.  CPPTemplateDefinition$CPPTemplateProblem",
      "elements": [
        {
          "method": "org.eclipse.cdt.internal.core.dom.parser.cpp.CPPClassScope.createImplicitMembers",
          "source": "CPPClassScope.  java:85"
        },
        {
          "method": "org.eclipse.cdt.internal.core.dom.parser.cpp.CPPClassScope.\u003cinit\u003e",
          "source": "CPPClassScope.java:60"
        },
        {
          "method": "org.eclipse.cdt.internal.core.dom.parser.cpp.CPPASTCompositeTypeSpecifier.getScope",
          "source": "  CPPASTCompositeTypeSpecifier.java:112"
        },
        {
          "method": "org.eclipse.cdt.internal.core.dom.parser.cpp.CPPVisitor.getContainingScope",
          "source": "CPPVisitor.java:668"
        },
        {
          "method": "org.eclipse.cdt.internal.core.dom.parser.cpp.CPPVisitor.getContainingScope",
          "source": "CPPVisitor.java:835"
        },
        {
          "method": "org.eclipse.cdt.internal.core.dom.parser.cpp.CPPVisitor.getContainingScope",
          "source": "CPPVisitor.java:657"
        },
        {
          "method": "org.eclipse.cdt.internal.core.dom.parser.cpp.CPPVisitor.createBinding",
          "source": "CPPVisitor.java:481"
        },
        {
          "method": "org.eclipse.cdt.internal.core.dom.parser.cpp.CPPVisitor.createBinding",
          "source": "CPPVisitor.java:188"
        },
        {
          "method": "org.eclipse.cdt.internal.core.dom.parser.cpp.CPPASTName.resolveBinding",
          "source": "CPPASTName.java:52"
        },
        {
          "method": "org.eclipse.cdt.internal.core.index.domsourceindexer.CPPGenerateIndexVisitor.processName",
          "source": "  CPPGenerateIndexVisitor.java:148"
        },
        {
          "method": "org.eclipse.cdt.internal.core.index.domsourceindexer.CPPGenerateIndexVisitor.visit",
          "source": "  CPPGenerateIndexVisitor.java:112"
        },
        {
          "method": "org.eclipse.cdt.internal.core.dom.parser.cpp.CPPASTName.accept",
          "source": "CPPASTName.java:90"
        },
        {
          "method": "org.eclipse.cdt.internal.core.dom.parser.cpp.CPPASTDeclarator.accept",
          "source": "CPPASTDeclarator.java:126"
        },
        {
          "method": "org.eclipse.cdt.internal.core.dom.parser.cpp.CPPASTSimpleDeclaration.accept",
          "source": "  CPPASTSimpleDeclaration.java:74"
        },
        {
          "method": "org.eclipse.cdt.internal.core.dom.parser.cpp.CPPASTCompositeTypeSpecifier.accept",
          "source": "  CPPASTCompositeTypeSpecifier.java:136"
        },
        {
          "method": "org.eclipse.cdt.internal.core.dom.parser.cpp.CPPASTSimpleDeclaration.accept",
          "source": "  CPPASTSimpleDeclaration.java:71"
        },
        {
          "method": "org.eclipse.cdt.internal.core.dom.parser.cpp.CPPASTTemplateDeclaration.accept",
          "source": "  CPPASTTemplateDeclaration.java:95"
        },
        {
          "method": "org.eclipse.cdt.internal.core.dom.parser.cpp.CPPASTTranslationUnit.accept",
          "source": "CPPASTTranslationUnit.  java:520"
        },
        {
          "method": "org.eclipse.cdt.internal.core.index.domsourceindexer.DOMSourceIndexerRunner.indexFile",
          "source": "  DOMSourceIndexerRunner.java:133"
        },
        {
          "method": "org.eclipse.cdt.internal.core.index.domsourceindexer.AbstractIndexerRunner.index",
          "source": "  AbstractIndexerRunner.java:76"
        },
        {
          "method": "org.eclipse.cdt.internal.core.index.cindexstorage.Index.add",
          "source": "Index.java:110"
        },
        {
          "method": "org.eclipse.cdt.internal.core.index.domsourceindexer.DOMAddCompilationUnitToIndex.indexDocument",
          "source": "  DOMAddCompilationUnitToIndex.java:29"
        },
        {
          "method": "org.eclipse.cdt.internal.core.index.domsourceindexer.DOMAddFileToIndex.execute",
          "source": "DOMAddFileToIndex.  java:60"
        },
        {
          "method": "org.eclipse.cdt.internal.core.search.processing.JobManager.run",
          "source": "JobManager.java:466"
        },
        {
          "method": "java.lang.Thread.run",
          "source": "Thread.java:534"
        }
      ],
      "number": 4,
      "commentIndex": 0,
      "bugId": "106716",
      "duplicateId": "106715",
      "date": "2005-08-11T09:00:16+02:00",
      "product": "CDT",
      "component": "cdt-core",
      "severity": "trivial"
    },
    {
      "exceptionType": "java.lang.ClassCastException",
      "message": "org.eclipse.cdt.internal.core.dom.parser.cpp.  CPPTemplateDefinition$CPPTemplateProblem",
      "elements": [
        {
          "method": "org.eclipse.cdt.internal.core.dom.parser.cpp.CPPClassScope.createImplicitMembers",
          "source": "CPPClassScope.  java:85"
        },
        {
          "method": "org.eclipse.cdt.internal.core.dom.parser.cpp.CPPClassScope.\u003cinit\u003e",
          "source": "CPPClassScope.java:60"
        },
        {
          "method": "org.eclipse.cdt.internal.core.dom.parser.cpp.CPPASTCompositeTypeSpecifier.getScope",
          "source": "  CPPASTCompositeTypeSpecifier.java:112"
        },
        {
          "method": "org.eclipse.cdt.internal.core.dom.parser.cpp.CPPVisitor.getContainingScope",
          "source": "CPPVisitor.java:668"
        },
        {
          "method": "org.eclipse.cdt.internal.core.dom.parser.cpp.CPPVisitor.getContainingScope",
          "source": "CPPVisitor.java:835"
        },
        {
          "method": "org.eclipse.cdt.internal.core.dom.parser.cpp.CPPSemantics.getLookupScope",
          "source": "CPPSemantics.java:907"
        },
        {
          "method": "org.eclipse.cdt.internal.core.dom.parser.cpp.CPPSemantics.lookup",
          "source": "CPPSemantics.java:987"
        },
        {
          "method": "org.eclipse.cdt.internal.core.dom.parser.cpp.CPPSemantics.resolveBinding",
          "source": "CPPSemantics.java:610"
        },
        {
          "method": "org.eclipse.cdt.internal.core.dom.parser.cpp.CPPVisitor.createBinding",
          "source": "CPPVisitor.java:164"
        },
        {
          "method": "org.eclipse.cdt.internal.core.dom.parser.cpp.CPPASTName.resolveBinding",
          "source": "CPPASTName.java:52"
        },
        {
          "method": "org.eclipse.cdt.internal.core.dom.parser.cpp.CPPTemplates.createClassSpecialization",
          "source": "CPPTemplates.  java:297"
        },
        {
          "method": "org.eclipse.cdt.internal.core.dom.parser.cpp.CPPTemplates.createBinding",
          "source": "CPPTemplates.java:224"
        },
        {
          "method": "org.eclipse.cdt.internal.core.dom.parser.cpp.CPPASTTemplateId.resolveBinding",
          "source": "CPPASTTemplateId.java  :74"
        },
        {
          "method": "org.eclipse.cdt.internal.core.index.domsourceindexer.CPPGenerateIndexVisitor.addFriendDeclarations",
          "source": "CPPGenerateIndexVisitor.java:426"
        },
        {
          "method": "org.eclipse.cdt.internal.core.index.domsourceindexer.CPPGenerateIndexVisitor.processNameBinding",
          "source": "  CPPGenerateIndexVisitor.java:235"
        },
        {
          "method": "org.eclipse.cdt.internal.core.index.domsourceindexer.CPPGenerateIndexVisitor.processName",
          "source": "  CPPGenerateIndexVisitor.java:169"
        },
        {
          "method": "org.eclipse.cdt.internal.core.index.domsourceindexer.CPPGenerateIndexVisitor.visit",
          "source": "  CPPGenerateIndexVisitor.java:112"
        },
        {
          "method": "org.eclipse.cdt.internal.core.dom.parser.cpp.CPPASTName.accept",
          "source": "CPPASTName.java:90"
        },
        {
          "method": "org.eclipse.cdt.internal.core.dom.parser.cpp.CPPASTCompositeTypeSpecifier.accept",
          "source": "  CPPASTCompositeTypeSpecifier.java:129"
        },
        {
          "method": "org.eclipse.cdt.internal.core.dom.parser.cpp.CPPASTSimpleDeclaration.accept",
          "source": "  CPPASTSimpleDeclaration.java:71"
        },
        {
          "method": "org.eclipse.cdt.internal.core.dom.parser.cpp.CPPASTTemplateDeclaration.accept",
          "source": "  CPPASTTemplateDeclaration.java:95"
        },
        {
          "method": "org.eclipse.cdt.internal.core.dom.parser.cpp.CPPASTTranslationUnit.accept",
          "source": "CPPASTTranslationUnit.  java:520"
        },
        {
          "method": "org.eclipse.cdt.internal.core.index.domsourceindexer.DOMSourceIndexerRunner.indexFile",
          "source": "  DOMSourceIndexerRunner.java:133"
        },
        {
          "method": "org.eclipse.cdt.internal.core.index.domsourceindexer.AbstractIndexerRunner.index",
          "source": "  AbstractIndexerRunner.java:76"
        },
        {
          "method": "org.eclipse.cdt.internal.core.index.cindexstorage.Index.add",
          "source": "Index.java:110"
        },
        {
          "method": "org.eclipse.cdt.internal.core.index.domsourceindexer.DOMAddCompilationUnitToIndex.indexDocument",
          "source": "  DOMAddCompilationUnitToIndex.java:29"
        },
        {
          "method": "org.eclipse.cdt.internal.core.index.domsourceindexer.DOMAddFileToIndex.execute",
          "source": "DOMAddFileToIndex.  java:60"
        },
        {
          "method": "org.eclipse.cdt.internal.core.search.processing.JobManager.run",
          "source": "JobManager.java:466"
        },
        {
          "method": "java.lang.Thread.run",
          "source": "Thread.java:534"
        }
      ],
      "number": 5,
      "commentIndex": 0,
      "bugId": "106716",
      "duplicateId": "106715",
      "date": "2005-08-11T09:00:16+02:00",
      "product": "CDT",
      "component": "cdt-core",
      "severity": "trivial"
    },
    {
      "exceptionType": "java.lang.ClassCastException",
      "message": "org.eclipse.cdt.internal.core.dom.parser.cpp.  CPPTemplateDefinition$CPPTemplateProblem",
      "elements": [
        {
          "method": "org.eclipse.cdt.internal.core.dom.parser.cpp.CPPClassScope.createImplicitMembers",
          "source": "CPPClassScope.  java:85"
        },
        {
          "method": "org.eclipse.cdt.internal.core.dom.parser.cpp.CPPClassScope.\u003cinit\u003e",
          "source": "CPPClassScope.java:60"
        },
        {
          "method": "org.eclipse.cdt.internal.core.dom.parser.cpp.CPPASTCompositeTypeSpecifier.getScope",
          "source": "  CPPASTCompositeTypeSpecifier.java:112"
        },
        {
          "method": "org.eclipse.cdt.internal.core.dom.parser.cpp.CPPVisitor.getContainingScope",
          "source": "CPPVisitor.java:668"
        },
        {
          "method": "org.eclipse.cdt.internal.core.dom.parser.cpp.CPPVisitor.getContainingScope",
          "source": "CPPVisitor.java:835"
        },
        {
          "method": "org.eclipse.cdt.internal.core.dom.parser.cpp.CPPVisitor.getContainingScope",
          "source": "CPPVisitor.java:657"
        },
        {
          "method": "org.eclipse.cdt.internal.core.dom.parser.cpp.CPPVisitor.createBinding",
          "source": "CPPVisitor.java:481"
        },
        {
          "method": "org.eclipse.cdt.internal.core.dom.parser.cpp.CPPVisitor.createBinding",
          "source": "CPPVisitor.java:188"
        },
        {
          "method": "org.eclipse.cdt.internal.core.dom.parser.cpp.CPPASTName.resolveBinding",
          "source": "CPPASTName.java:52"
        },
        {
          "method": "org.eclipse.cdt.internal.core.index.domsourceindexer.CPPGenerateIndexVisitor.processName",
          "source": "  CPPGenerateIndexVisitor.java:148"
        },
        {
          "method": "org.eclipse.cdt.internal.core.index.domsourceindexer.CPPGenerateIndexVisitor.visit",
          "source": "  CPPGenerateIndexVisitor.java:112"
        },
        {
          "method": "org.eclipse.cdt.internal.core.dom.parser.cpp.CPPASTName.accept",
          "source": "CPPASTName.java:90"
        },
        {
          "method": "org.eclipse.cdt.internal.core.dom.parser.cpp.CPPASTDeclarator.accept",
          "source": "CPPASTDeclarator.java:126"
        },
        {
          "method": "org.eclipse.cdt.internal.core.dom.parser.cpp.CPPASTSimpleDeclaration.accept",
          "source": "  CPPASTSimpleDeclaration.java:74"
        },
        {
          "method": "org.eclipse.cdt.internal.core.dom.parser.cpp.CPPASTCompositeTypeSpecifier.accept",
          "source": "  CPPASTCompositeTypeSpecifier.java:136"
        },
        {
          "method": "org.eclipse.cdt.internal.core.dom.parser.cpp.CPPASTSimpleDeclaration.accept",
          "source": "  CPPASTSimpleDeclaration.java:71"
        },
        {
          "method": "org.eclipse.cdt.internal.core.dom.parser.cpp.CPPASTTemplateDeclaration.accept",
          "source": "  CPPASTTemplateDeclaration.java:95"
        },
        {
          "method": "org.eclipse.cdt.internal.core.dom.parser.cpp.CPPASTTranslationUnit.accept",
          "source": "CPPASTTranslationUnit.  java:520"
        },
        {
          "method": "org.eclipse.cdt.internal.core.index.domsourceindexer.DOMSourceIndexerRunner.indexFile",
          "source": "  DOMSourceIndexerRunner.java:133"
        },
        {
          "method": "org.eclipse.cdt.internal.core.index.domsourceindexer.AbstractIndexerRunner.index",
          "source": "  AbstractIndexerRunner.java:76"
        },
        {
          "method": "org.eclipse.cdt.internal.core.index.cindexstorage.Index.add",
          "source": "Index.java:110"
        },
        {
          "method": "org.eclipse.cdt.internal.core.index.domsourceindexer.DOMAddCompilationUnitToIndex.indexDocument",
          "source": "  DOMAddCompilationUnitToIndex.java:29"
        },
        {
          "method": "org.eclipse.cdt.internal.core.index.domsourceindexer.DOMAddFileToIndex.execute",
          "source": "DOMAddFileToIndex.  java:60"
        },
        {
          "method": "org.eclipse.cdt.internal.core.search.processing.JobManager.run",
          "source": "JobManager.java:466"
        }
      ],
      "number": 6,
      "commentIndex": 0,
      "bugId": "106716",
      "duplicateId": "106715",
      "date": "2005-08-11T09:00:16+02:00",
      "product": "CDT",
      "component": "cdt-core",
      "severity": "trivial"
    },
    {
      "exceptionType": "java.lang.ClassCastException",
      "message": "org.eclipse.cdt.internal.core.dom.parser.cpp.  CPPTemplateDefinition$CPPTemplateProblem",
      "elements": [
        {
          "method": "org.eclipse.cdt.internal.core.dom.parser.cpp.CPPSemantics.getTargetParameterTypes",
          "source": "CPPSemantics.  java:2141"
        },
        {
          "method": "org.eclipse.cdt.internal.core.dom.parser.cpp.CPPSemantics.resolveFunction",
          "source": "CPPSemantics.java:2219"
        },
        {
          "method": "org.eclipse.cdt.internal.core.dom.parser.cpp.CPPSemantics.resolveAmbiguities",
          "source": "CPPSemantics.java:  1993"
        },
        {
          "method": "org.eclipse.cdt.internal.core.dom.parser.cpp.CPPSemantics.resolveBinding",
          "source": "CPPSemantics.java:621"
        },
        {
          "method": "org.eclipse.cdt.internal.core.dom.parser.cpp.CPPVisitor.resolveBinding",
          "source": "CPPVisitor.java:927"
        },
        {
          "method": "org.eclipse.cdt.internal.core.dom.parser.cpp.CPPVisitor.createBinding",
          "source": "CPPVisitor.java:182"
        },
        {
          "method": "org.eclipse.cdt.internal.core.dom.parser.cpp.CPPASTName.resolveBinding",
          "source": "CPPASTName.java:52"
        },
        {
          "method": "org.eclipse.cdt.internal.core.index.domsourceindexer.CPPGenerateIndexVisitor.processName",
          "source": "  CPPGenerateIndexVisitor.java:148"
        },
        {
          "method": "org.eclipse.cdt.internal.core.index.domsourceindexer.CPPGenerateIndexVisitor.visit",
          "source": "  CPPGenerateIndexVisitor.java:112"
        },
        {
          "method": "org.eclipse.cdt.internal.core.dom.parser.cpp.CPPASTName.accept",
          "source": "CPPASTName.java:90"
        },
        {
          "method": "org.eclipse.cdt.internal.core.dom.parser.cpp.CPPASTIdExpression.accept",
          "source": "CPPASTIdExpression.java:46"
        },
        {
          "method": "org.eclipse.cdt.internal.core.dom.parser.cpp.CPPASTFunctionCallExpression.accept",
          "source": "  CPPASTFunctionCallExpression.java:64"
        },
        {
          "method": "org.eclipse.cdt.internal.core.dom.parser.cpp.CPPASTInitializerExpression.accept",
          "source": "  CPPASTInitializerExpression.java:49"
        },
        {
          "method": "org.eclipse.cdt.internal.core.dom.parser.cpp.CPPASTDeclarator.postAccept",
          "source": "CPPASTDeclarator.java:135"
        },
        {
          "method": "org.eclipse.cdt.internal.core.dom.parser.cpp.CPPASTDeclarator.accept",
          "source": "CPPASTDeclarator.java:131"
        },
        {
          "method": "org.eclipse.cdt.internal.core.dom.parser.cpp.CPPASTSimpleDeclaration.accept",
          "source": "  CPPASTSimpleDeclaration.java:74"
        },
        {
          "method": "org.eclipse.cdt.internal.core.dom.parser.cpp.CPPASTDeclarationStatement.accept",
          "source": "  CPPASTDeclarationStatement.java:49"
        },
        {
          "method": "org.eclipse.cdt.internal.core.dom.parser.cpp.CPPASTCompoundStatement.accept",
          "source": "  CPPASTCompoundStatement.java:66"
        },
        {
          "method": "org.eclipse.cdt.internal.core.dom.parser.cpp.CPPASTFunctionDefinition.accept",
          "source": "  CPPASTFunctionDefinition.java:93"
        },
        {
          "method": "org.eclipse.cdt.internal.core.dom.parser.cpp.CPPASTTemplateDeclaration.accept",
          "source": "  CPPASTTemplateDeclaration.java:95"
        },
        {
          "method": "org.eclipse.cdt.internal.core.dom.parser.cpp.CPPASTTranslationUnit.accept",
          "source": "CPPASTTranslationUnit.  java:520"
        },
        {
          "method": "org.eclipse.cdt.internal.core.index.domsourceindexer.DOMSourceIndexerRunner.indexFile",
          "source": "  DOMSourceIndexerRunner.java:133"
        },
        {
          "method": "org.eclipse.cdt.internal.core.index.domsourceindexer.AbstractIndexerRunner.index",
          "source": "  AbstractIndexerRunner.java:76"
        },
        {
          "method": "org.eclipse.cdt.internal.core.index.cindexstorage.Index.add",
          "source": "Index.java:110"
        },
        {
          "method": "org.eclipse.cdt.internal.core.index.domsourceindexer.DOMAddCompilationUnitToIndex.indexDocument",
          "source": "  DOMAddCompilationUnitToIndex.java:29"
        },
        {
          "method": "org.eclipse.cdt.internal.core.index.domsourceindexer.DOMAddFileToIndex.execute",
          "source": "DOMAddFileToIndex.  java:60"
        },
        {
          "method": "org.eclipse.cdt.internal.core.search.processing.JobManager.run",
          "source": "JobManager.java:466"
        },
        {
          "method": "java.lang.Thread.run",
          "source": "Thread.java:534"
        }
      ],
      "number": 7,
      "commentIndex": 0,
      "bugId": "106716",
      "duplicateId": "106715",
      "date": "2005-08-11T09:00:16+02:00",
      "product": "CDT",
      "component": "cdt-core",
      "severity": "trivial"
    }
  ],
  "groupId": "106715",
  "bugId": "106716",
  "duplicateId": "106715",
  "date": "2005-08-11T09:00:16+02:00",
  "product": "CDT",
  "component": "cdt-core",
  "severity": "trivial"
}