{
  "comments": [
    "I develope a plugin for automated debugging of java programs for eclipse. My\nplugin launches several tests in an additional vm and use the tools of eclipse\nto set breakpoints etc.\n\nDuring the execution of my tool i get the following error:\n\n--------------------------\n!ENTRY org.eclipse.ui 4 0 2005-08-12 17:08:52.535\n!MESSAGE Failed to execute runnable\n(org.eclipse.jface.util.Assert$AssertionFailedException: null argument;)\n!STACK 0\norg.eclipse.swt.SWTException: Failed to execute runnable\n(org.eclipse.jface.util.Assert$AssertionFailedException: null argument;)\n    at org.eclipse.swt.SWT.error(SWT.java:2942)\n    at org.eclipse.swt.SWT.error(SWT.java:2865)\n    at org.eclipse.swt.widgets.Synchronizer.runAsyncMessages(Synchronizer.java:126)\n    at org.eclipse.swt.widgets.Display.runAsyncMessages(Display.java:2844)\n    at org.eclipse.swt.widgets.Display.readAndDispatch(Display.java:2575)\n    at org.eclipse.ui.internal.Workbench.runEventLoop(Workbench.java:1699)\n    at org.eclipse.ui.internal.Workbench.runUI(Workbench.java:1663)\n    at org.eclipse.ui.internal.Workbench.createAndRunWorkbench(Workbench.java:367)\n    at org.eclipse.ui.PlatformUI.createAndRunWorkbench(PlatformUI.java:143)\n    at org.eclipse.ui.internal.ide.IDEApplication.run(IDEApplication.java:103)\n    at\norg.eclipse.core.internal.runtime.PlatformActivator$1.run(PlatformActivator.java:226)\n    at org.eclipse.core.runtime.adaptor.EclipseStarter.run(EclipseStarter.java:376)\n    at org.eclipse.core.runtime.adaptor.EclipseStarter.run(EclipseStarter.java:163)\n    at sun.reflect.NativeMethodAccessorImpl.invoke0(Native Method)\n    at sun.reflect.NativeMethodAccessorImpl.invoke(NativeMethodAccessorImpl.java:39)\n    at\nsun.reflect.DelegatingMethodAccessorImpl.invoke(DelegatingMethodAccessorImpl.java:25)\n    at java.lang.reflect.Method.invoke(Method.java:324)\n    at org.eclipse.core.launcher.Main.invokeFramework(Main.java:334)\n    at org.eclipse.core.launcher.Main.basicRun(Main.java:278)\n    at org.eclipse.core.launcher.Main.run(Main.java:973)\n    at org.eclipse.core.launcher.Main.main(Main.java:948)\nCaused by: org.eclipse.jface.util.Assert$AssertionFailedException: null argument;\n    at org.eclipse.jface.util.Assert.isNotNull(Assert.java:149)\n    at org.eclipse.jface.util.Assert.isNotNull(Assert.java:125)\n    at\norg.eclipse.jface.viewers.StructuredSelection.\u003cinit\u003e(StructuredSelection.java:66)\n    at\norg.eclipse.jdt.internal.debug.ui.actions.ShowSystemThreadsAction$1.run(ShowSystemThreadsAction.java:103)\n    at org.eclipse.swt.widgets.RunnableLock.run(RunnableLock.java:35)\n    at org.eclipse.swt.widgets.Synchronizer.runAsyncMessages(Synchronizer.java:123)\n    ... 18 more\n--------------------------\n\nI debugged the application and found that in ShowSystemThreadsAction at line 102\nthe top stack frame of the current thread will assigned to the variable tos.\nAfter that this frame should present to the user with a StructuredSelection. But\nunfortunately the method getTopStackFrame can return null. This cause an\nAssertionFailedException in the constructor of the StructuredSelection.\n               \nCode snippet from ShowSystemThreadsAction (line 102-103):\n  tos \u003d thread.getTopStackFrame();\n  getStructuredViewer().setSelection(new StructuredSelection(tos));\n\nIt is necessary to check that the top stack frame is not null before the\nStructuredSelction will be initialised?\n\nThe consequence of this exception is still an unhandeld event loop exception\nwhich will already logged in the error log.\n\nI\u0027m sorry but i cannot provide a special test case yet because my plugin is not\nyet public.",
    "Fixed in ShowSystemThreadsAction.",
    "Please verify, Kevin.",
    "verified"
  ],
  "commentCreationDates": [
    "2005-08-12T18:10:32+02:00",
    "2006-04-04T20:49:13+02:00",
    "2006-04-04T20:49:24+02:00",
    "2006-04-06T17:23:36+02:00"
  ],
  "traces": [
    {
      "exceptionType": "org.eclipse.jface.util.Assert$AssertionFailedException",
      "message": "null argument;)",
      "elements": [
        {
          "method": "org.eclipse.swt.SWT.error",
          "source": "SWT.java:2942"
        },
        {
          "method": "org.eclipse.swt.SWT.error",
          "source": "SWT.java:2865"
        },
        {
          "method": "org.eclipse.swt.widgets.Synchronizer.runAsyncMessages",
          "source": "Synchronizer.java:126"
        },
        {
          "method": "org.eclipse.swt.widgets.Display.runAsyncMessages",
          "source": "Display.java:2844"
        },
        {
          "method": "org.eclipse.swt.widgets.Display.readAndDispatch",
          "source": "Display.java:2575"
        },
        {
          "method": "org.eclipse.ui.internal.Workbench.runEventLoop",
          "source": "Workbench.java:1699"
        },
        {
          "method": "org.eclipse.ui.internal.Workbench.runUI",
          "source": "Workbench.java:1663"
        },
        {
          "method": "org.eclipse.ui.internal.Workbench.createAndRunWorkbench",
          "source": "Workbench.java:367"
        },
        {
          "method": "org.eclipse.ui.PlatformUI.createAndRunWorkbench",
          "source": "PlatformUI.java:143"
        },
        {
          "method": "org.eclipse.ui.internal.ide.IDEApplication.run",
          "source": "IDEApplication.java:103"
        },
        {
          "method": "org.eclipse.core.internal.runtime.PlatformActivator$1.run",
          "source": "PlatformActivator.java:226"
        },
        {
          "method": "org.eclipse.core.runtime.adaptor.EclipseStarter.run",
          "source": "EclipseStarter.java:376"
        },
        {
          "method": "org.eclipse.core.runtime.adaptor.EclipseStarter.run",
          "source": "EclipseStarter.java:163"
        },
        {
          "method": "sun.reflect.NativeMethodAccessorImpl.invoke0",
          "source": "Native Method"
        },
        {
          "method": "sun.reflect.NativeMethodAccessorImpl.invoke",
          "source": "NativeMethodAccessorImpl.java:39"
        },
        {
          "method": "sun.reflect.DelegatingMethodAccessorImpl.invoke",
          "source": "DelegatingMethodAccessorImpl.java:25"
        },
        {
          "method": "java.lang.reflect.Method.invoke",
          "source": "Method.java:324"
        },
        {
          "method": "org.eclipse.core.launcher.Main.invokeFramework",
          "source": "Main.java:334"
        },
        {
          "method": "org.eclipse.core.launcher.Main.basicRun",
          "source": "Main.java:278"
        },
        {
          "method": "org.eclipse.core.launcher.Main.run",
          "source": "Main.java:973"
        },
        {
          "method": "org.eclipse.core.launcher.Main.main",
          "source": "Main.java:948"
        }
      ],
      "causedBy": {
        "exceptionType": "org.eclipse.jface.util.Assert$AssertionFailedException",
        "message": "null argument;",
        "elements": [
          {
            "method": "org.eclipse.jface.util.Assert.isNotNull",
            "source": "Assert.java:149"
          },
          {
            "method": "org.eclipse.jface.util.Assert.isNotNull",
            "source": "Assert.java:125"
          },
          {
            "method": "org.eclipse.jface.viewers.StructuredSelection.\u003cinit\u003e",
            "source": "StructuredSelection.java:66"
          },
          {
            "method": "org.eclipse.jdt.internal.debug.ui.actions.ShowSystemThreadsAction$1.run",
            "source": "ShowSystemThreadsAction.java:103"
          },
          {
            "method": "org.eclipse.swt.widgets.RunnableLock.run",
            "source": "RunnableLock.java:35"
          },
          {
            "method": "org.eclipse.swt.widgets.Synchronizer.runAsyncMessages",
            "source": "Synchronizer.java:123"
          }
        ],
        "number": 0,
        "commentIndex": 0
      },
      "number": 0,
      "commentIndex": 0,
      "bugId": "106871",
      "date": "2005-08-12T18:10:32+02:00",
      "product": "JDT",
      "component": "Debug",
      "severity": "normal"
    }
  ],
  "groupId": "106871",
  "bugId": "106871",
  "date": "2005-08-12T18:10:32+02:00",
  "product": "JDT",
  "component": "Debug",
  "severity": "normal"
}