{
  "comments": [
    "Using R2(20020125):\n- Create a REMOTE project and set the \"parse include path\" to /usr/include\n- After Parsing the project go to the \"Parsed Files\" and change the filter so\nthat \"Included Source\" files are visible. Attempt to open one of the \"Included\nSource\" files by double-clicking on them. An internal error would occur.\n-----------------------Here is the log-----------------------------\njava.lang.NumberFormatException: Exception\n        at java.lang.Long.parseLong(Long.java:311)\n        at java.lang.Long.\u003cinit\u003e(Long.java:522)\n        at\norg.eclipse.cdt.dstore.ui.resource.ResourceElement.getModificationStamp(ResourceElement.java:489)\n        at\norg.eclipse.ui.editors.text.FileDocumentProvider.computeModificationStamp(FileDocumentProvider.java:256)\n        at\norg.eclipse.cdt.cpp.ui.internal.editor.CppDocumentProvider.createElementInfo(CppDocumentProvider.java:116)\n        at\norg.eclipse.ui.texteditor.AbstractDocumentProvider.connect(AbstractDocumentProvider.java:244)\n        at\ncom.ibm.lpex.alef.LpexAbstractTextEditor.doSetInput(LpexAbstractTextEditor.java:1175)\n        at\ncom.ibm.lpex.alef.LpexAbstractTextEditor.init(LpexAbstractTextEditor.java:897)\n        at org.eclipse.ui.internal.EditorManager$2.run(EditorManager.java:452)\n        at org.eclipse.swt.custom.BusyIndicator.showWhile(BusyIndicator.java:56)\n        at\norg.eclipse.ui.internal.EditorManager.openInternalEditor(EditorManager.java:447)\n        at\norg.eclipse.ui.internal.EditorManager.openInternalEditor(EditorManager.java:498)\n        at\norg.eclipse.ui.internal.EditorManager.openEditor(EditorManager.java:372)\n        at\norg.eclipse.ui.internal.EditorManager.openEditor(EditorManager.java:269)\n        at\norg.eclipse.ui.internal.WorkbenchPage.openEditor(WorkbenchPage.java:1167)\n        at\norg.eclipse.ui.internal.WorkbenchPage.openEditor(WorkbenchPage.java:1063)\n        at\norg.eclipse.cdt.cpp.ui.internal.actions.OpenEditorAction.performGoto(OpenEditorAction.java:285)\n        at\norg.eclipse.cdt.cpp.ui.internal.actions.OpenEditorAction.run(OpenEditorAction.java:98)\n        at\norg.eclipse.cdt.dstore.ui.widgets.DataElementTableViewer.handleDoubleSelect(DataElementTableViewer.java:712)\n        at\norg.eclipse.jface.viewers.TableViewer$1.widgetDefaultSelected(TableViewer.java:302)\n        at\norg.eclipse.swt.widgets.TypedListener.handleEvent(TypedListener.java:92)\n        at org.eclipse.swt.widgets.Widget.notifyListeners(Widget.java(Compiled\nCode))\n        at org.eclipse.swt.widgets.Widget.notifyListeners(Widget.java(Compiled\nCode))\n        at org.eclipse.swt.widgets.Table.columnMouseDoubleClick(Table.java:243)\n        at org.eclipse.swt.widgets.Table.handleEvents(Table.java:1244)\n        at\norg.eclipse.swt.widgets.SelectableItemWidget$1.handleEvent(SelectableItemWidget.java:1190)\n        at org.eclipse.swt.widgets.Widget.notifyListeners(Widget.java(Compiled\nCode))\n        at org.eclipse.swt.widgets.Widget.notifyListeners(Widget.java(Compiled\nCode))\n        at\norg.eclipse.swt.widgets.Display.runDeferredEvents(Display.java(Compiled Code))\n        at org.eclipse.swt.widgets.Display.readAndDispatch(Display.java(Compiled\nCode))\n        at\norg.eclipse.ui.internal.Workbench.runEventLoop(Workbench.java(Compiled Code))\n        at org.eclipse.ui.internal.Workbench.run(Workbench.java:827)\n        at\norg.eclipse.core.internal.boot.InternalBootLoader.run(InternalBootLoader.java:878)\n        at org.eclipse.core.boot.BootLoader.run(BootLoader.java:321)\n        at java.lang.reflect.Method.invoke(Native Method)\n        at org.eclipse.core.launcher.Main.basicRun(Main.java:151)\n        at org.eclipse.core.launcher.Main.run(Main.java:502)\n        at org.eclipse.core.launcher.Main.main(Main.java:362)",
    "The problem is that, when we create a FileResourceElement for the editor to \nencapsulate the remote project, we need to also create a file DataElement.  The \nelement exists locally but not on the server side.  We need to call set object \non the DataElement so that FS miner has a real subject to work with."
  ],
  "commentCreationDates": [
    "2002-03-04T21:40:14+01:00",
    "2002-03-04T23:38:15+01:00"
  ],
  "traces": [
    {
      "exceptionType": "java.lang.NumberFormatException",
      "message": "Exception",
      "elements": [
        {
          "method": "java.lang.Long.parseLong",
          "source": "Long.java:311"
        },
        {
          "method": "java.lang.Long.\u003cinit\u003e",
          "source": "Long.java:522"
        },
        {
          "method": "org.eclipse.cdt.dstore.ui.resource.ResourceElement.getModificationStamp",
          "source": "ResourceElement.java:489"
        },
        {
          "method": "org.eclipse.ui.editors.text.FileDocumentProvider.computeModificationStamp",
          "source": "FileDocumentProvider.java:256"
        },
        {
          "method": "org.eclipse.cdt.cpp.ui.internal.editor.CppDocumentProvider.createElementInfo",
          "source": "CppDocumentProvider.java:116"
        },
        {
          "method": "org.eclipse.ui.texteditor.AbstractDocumentProvider.connect",
          "source": "AbstractDocumentProvider.java:244"
        },
        {
          "method": "com.ibm.lpex.alef.LpexAbstractTextEditor.doSetInput",
          "source": "LpexAbstractTextEditor.java:1175"
        },
        {
          "method": "com.ibm.lpex.alef.LpexAbstractTextEditor.init",
          "source": "LpexAbstractTextEditor.java:897"
        },
        {
          "method": "org.eclipse.ui.internal.EditorManager$2.run",
          "source": "EditorManager.java:452"
        },
        {
          "method": "org.eclipse.swt.custom.BusyIndicator.showWhile",
          "source": "BusyIndicator.java:56"
        },
        {
          "method": "org.eclipse.ui.internal.EditorManager.openInternalEditor",
          "source": "EditorManager.java:447"
        },
        {
          "method": "org.eclipse.ui.internal.EditorManager.openInternalEditor",
          "source": "EditorManager.java:498"
        },
        {
          "method": "org.eclipse.ui.internal.EditorManager.openEditor",
          "source": "EditorManager.java:372"
        },
        {
          "method": "org.eclipse.ui.internal.EditorManager.openEditor",
          "source": "EditorManager.java:269"
        },
        {
          "method": "org.eclipse.ui.internal.WorkbenchPage.openEditor",
          "source": "WorkbenchPage.java:1167"
        },
        {
          "method": "org.eclipse.ui.internal.WorkbenchPage.openEditor",
          "source": "WorkbenchPage.java:1063"
        },
        {
          "method": "org.eclipse.cdt.cpp.ui.internal.actions.OpenEditorAction.performGoto",
          "source": "OpenEditorAction.java:285"
        },
        {
          "method": "org.eclipse.cdt.cpp.ui.internal.actions.OpenEditorAction.run",
          "source": "OpenEditorAction.java:98"
        },
        {
          "method": "org.eclipse.cdt.dstore.ui.widgets.DataElementTableViewer.handleDoubleSelect",
          "source": "DataElementTableViewer.java:712"
        },
        {
          "method": "org.eclipse.jface.viewers.TableViewer$1.widgetDefaultSelected",
          "source": "TableViewer.java:302"
        },
        {
          "method": "org.eclipse.swt.widgets.TypedListener.handleEvent",
          "source": "TypedListener.java:92"
        },
        {
          "method": "org.eclipse.swt.widgets.Widget.notifyListeners",
          "source": "Widget.java(Compiled Code)"
        },
        {
          "method": "org.eclipse.swt.widgets.Widget.notifyListeners",
          "source": "Widget.java(Compiled Code)"
        },
        {
          "method": "org.eclipse.swt.widgets.Table.columnMouseDoubleClick",
          "source": "Table.java:243"
        },
        {
          "method": "org.eclipse.swt.widgets.Table.handleEvents",
          "source": "Table.java:1244"
        },
        {
          "method": "org.eclipse.swt.widgets.SelectableItemWidget$1.handleEvent",
          "source": "SelectableItemWidget.java:1190"
        },
        {
          "method": "org.eclipse.swt.widgets.Widget.notifyListeners",
          "source": "Widget.java(Compiled Code)"
        },
        {
          "method": "org.eclipse.swt.widgets.Widget.notifyListeners",
          "source": "Widget.java(Compiled Code)"
        },
        {
          "method": "org.eclipse.swt.widgets.Display.runDeferredEvents",
          "source": "Display.java(Compiled Code)"
        },
        {
          "method": "org.eclipse.swt.widgets.Display.readAndDispatch",
          "source": "Display.java(Compiled Code)"
        },
        {
          "method": "org.eclipse.ui.internal.Workbench.runEventLoop",
          "source": "Workbench.java(Compiled Code)"
        },
        {
          "method": "org.eclipse.ui.internal.Workbench.run",
          "source": "Workbench.java:827"
        },
        {
          "method": "org.eclipse.core.internal.boot.InternalBootLoader.run",
          "source": "InternalBootLoader.java:878"
        },
        {
          "method": "org.eclipse.core.boot.BootLoader.run",
          "source": "BootLoader.java:321"
        },
        {
          "method": "java.lang.reflect.Method.invoke",
          "source": "Native Method"
        },
        {
          "method": "org.eclipse.core.launcher.Main.basicRun",
          "source": "Main.java:151"
        },
        {
          "method": "org.eclipse.core.launcher.Main.run",
          "source": "Main.java:502"
        },
        {
          "method": "org.eclipse.core.launcher.Main.main",
          "source": "Main.java:362"
        }
      ],
      "number": 0,
      "commentIndex": 0,
      "bugId": "10727",
      "date": "2002-03-04T21:40:14+01:00",
      "product": "CDT",
      "component": "UI",
      "severity": "normal"
    }
  ],
  "groupId": "10727",
  "bugId": "10727",
  "date": "2002-03-04T21:40:14+01:00",
  "product": "CDT",
  "component": "UI",
  "severity": "normal"
}