{
  "comments": [
    "I am using Eclipse 3.1 and GEF 3.1 on Windows 98 SE.\nI am attempting to drag and drop a template from the palette onto the \nFigureCanvas.\nI get the following exception:\n\njava.lang.NumberFormatException: For input string: \"1124479904260   \"\n        at java.lang.NumberFormatException.forInputString\n(NumberFormatException.java:48)\n        at java.lang.Long.parseLong(Long.java:403)\n        at java.lang.Long.parseLong(Long.java:452)\n        at org.eclipse.gef.dnd.SimpleObjectTransfer.nativeToJava\n(SimpleObjectTransfer.java:57)\n        at org.eclipse.swt.dnd.DropTarget.Drop(DropTarget.java:394)\n        at org.eclipse.swt.dnd.DropTarget.access$7(DropTarget.java:350)\n        at org.eclipse.swt.dnd.DropTarget$3.method6(DropTarget.java:236)\n        at org.eclipse.swt.internal.ole.win32.COMObject.callback6\n(COMObject.java:117)\n        at org.eclipse.swt.internal.ole.win32.COM.DoDragDrop(Native Method)\n        at org.eclipse.swt.dnd.DragSource.drag(DragSource.java:277)\n        at org.eclipse.swt.dnd.DragSource.access$0(DragSource.java:267)\n        at org.eclipse.swt.dnd.DragSource$1.handleEvent(DragSource.java:161)\n        at org.eclipse.swt.widgets.EventTable.sendEvent(EventTable.java:66)\n        at org.eclipse.swt.widgets.Widget.sendEvent(Widget.java:843)\n        at org.eclipse.swt.widgets.Display.runDeferredEvents(Display.java:3080)\n        at org.eclipse.swt.widgets.Display.readAndDispatch(Display.java:2713)\n        at org.eclipse.ui.internal.Workbench.runEventLoop(Workbench.java:1699)\n        at org.eclipse.ui.internal.Workbench.runUI(Workbench.java:1663)\n        at org.eclipse.ui.internal.Workbench.createAndRunWorkbench\n(Workbench.java:367)\n        at org.eclipse.ui.PlatformUI.createAndRunWorkbench(PlatformUI.java:143)\n        at org.eclipse.ui.internal.ide.IDEApplication.run\n(IDEApplication.java:103)\n        at org.eclipse.core.internal.runtime.PlatformActivator$1.run\n(PlatformActivator.java:226)\n        at org.eclipse.core.runtime.adaptor.EclipseStarter.run\n(EclipseStarter.java:376)\n        at org.eclipse.core.runtime.adaptor.EclipseStarter.run\n(EclipseStarter.java:163)\n        at sun.reflect.NativeMethodAccessorImpl.invoke0(Native Method)\n        at sun.reflect.NativeMethodAccessorImpl.invoke\n(NativeMethodAccessorImpl.java:39)\n        at sun.reflect.DelegatingMethodAccessorImpl.invoke\n(DelegatingMethodAccessorImpl.java:25)\n        at java.lang.reflect.Method.invoke(Method.java:324)\n        at org.eclipse.core.launcher.Main.invokeFramework(Main.java:334)\n        at org.eclipse.core.launcher.Main.basicRun(Main.java:278)\n        at org.eclipse.core.launcher.Main.run(Main.java:973)\n        at org.eclipse.core.launcher.Main.main(Main.java:948)",
    "The spaces after the 1124479904260 are actually unprintable characters.",
    "Our javaToNative code looks like this:\npublic void javaToNative(Object object, TransferData transferData) {\n\tsetObject(object);\n\tstartTime \u003d System.currentTimeMillis();\n\tif (transferData !\u003d null)\n\t\tsuper.javaToNative(String.valueOf(startTime).getBytes(), \ntransferData);\n}\n\nSo, it looks like an issue with win98 that results in extra bogus bytes getting \ntransfered. Maybe SWT knows of a workaround.",
    "The trailing bytes are null characters (ascii code 0).\nPerhaps the nativeToJava and javaToNative only deal with words (or dwords) and\npad with the extra null bytes to complete the word/dword."
  ],
  "commentCreationDates": [
    "2005-08-19T21:42:20+02:00",
    "2005-08-19T21:50:09+02:00",
    "2005-08-19T22:03:11+02:00",
    "2005-08-20T05:00:22+02:00"
  ],
  "traces": [
    {
      "exceptionType": "java.lang.NumberFormatException",
      "message": "For input string: \"1124479904260   \"",
      "elements": [
        {
          "method": "java.lang.NumberFormatException.forInputString",
          "source": "NumberFormatException.java:48"
        },
        {
          "method": "java.lang.Long.parseLong",
          "source": "Long.java:403"
        },
        {
          "method": "java.lang.Long.parseLong",
          "source": "Long.java:452"
        },
        {
          "method": "org.eclipse.gef.dnd.SimpleObjectTransfer.nativeToJava",
          "source": "SimpleObjectTransfer.java:57"
        },
        {
          "method": "org.eclipse.swt.dnd.DropTarget.Drop",
          "source": "DropTarget.java:394"
        },
        {
          "method": "org.eclipse.swt.dnd.DropTarget.access$7",
          "source": "DropTarget.java:350"
        },
        {
          "method": "org.eclipse.swt.dnd.DropTarget$3.method6",
          "source": "DropTarget.java:236"
        },
        {
          "method": "org.eclipse.swt.internal.ole.win32.COMObject.callback6",
          "source": "COMObject.java:117"
        },
        {
          "method": "org.eclipse.swt.internal.ole.win32.COM.DoDragDrop",
          "source": "Native Method"
        },
        {
          "method": "org.eclipse.swt.dnd.DragSource.drag",
          "source": "DragSource.java:277"
        },
        {
          "method": "org.eclipse.swt.dnd.DragSource.access$0",
          "source": "DragSource.java:267"
        },
        {
          "method": "org.eclipse.swt.dnd.DragSource$1.handleEvent",
          "source": "DragSource.java:161"
        },
        {
          "method": "org.eclipse.swt.widgets.EventTable.sendEvent",
          "source": "EventTable.java:66"
        },
        {
          "method": "org.eclipse.swt.widgets.Widget.sendEvent",
          "source": "Widget.java:843"
        },
        {
          "method": "org.eclipse.swt.widgets.Display.runDeferredEvents",
          "source": "Display.java:3080"
        },
        {
          "method": "org.eclipse.swt.widgets.Display.readAndDispatch",
          "source": "Display.java:2713"
        },
        {
          "method": "org.eclipse.ui.internal.Workbench.runEventLoop",
          "source": "Workbench.java:1699"
        },
        {
          "method": "org.eclipse.ui.internal.Workbench.runUI",
          "source": "Workbench.java:1663"
        },
        {
          "method": "org.eclipse.ui.internal.Workbench.createAndRunWorkbench",
          "source": "Workbench.java:367"
        },
        {
          "method": "org.eclipse.ui.PlatformUI.createAndRunWorkbench",
          "source": "PlatformUI.java:143"
        },
        {
          "method": "org.eclipse.ui.internal.ide.IDEApplication.run",
          "source": "IDEApplication.java:103"
        },
        {
          "method": "org.eclipse.core.internal.runtime.PlatformActivator$1.run",
          "source": "PlatformActivator.java:226"
        },
        {
          "method": "org.eclipse.core.runtime.adaptor.EclipseStarter.run",
          "source": "EclipseStarter.java:376"
        },
        {
          "method": "org.eclipse.core.runtime.adaptor.EclipseStarter.run",
          "source": "EclipseStarter.java:163"
        },
        {
          "method": "sun.reflect.NativeMethodAccessorImpl.invoke0",
          "source": "Native Method"
        },
        {
          "method": "sun.reflect.NativeMethodAccessorImpl.invoke",
          "source": "NativeMethodAccessorImpl.java:39"
        },
        {
          "method": "sun.reflect.DelegatingMethodAccessorImpl.invoke",
          "source": "DelegatingMethodAccessorImpl.java:25"
        },
        {
          "method": "java.lang.reflect.Method.invoke",
          "source": "Method.java:324"
        },
        {
          "method": "org.eclipse.core.launcher.Main.invokeFramework",
          "source": "Main.java:334"
        },
        {
          "method": "org.eclipse.core.launcher.Main.basicRun",
          "source": "Main.java:278"
        },
        {
          "method": "org.eclipse.core.launcher.Main.run",
          "source": "Main.java:973"
        },
        {
          "method": "org.eclipse.core.launcher.Main.main",
          "source": "Main.java:948"
        }
      ],
      "number": 0,
      "commentIndex": 0,
      "bugId": "107469",
      "date": "2005-08-19T21:42:20+02:00",
      "product": "Platform",
      "component": "SWT",
      "severity": "normal"
    }
  ],
  "groupId": "107469",
  "bugId": "107469",
  "date": "2005-08-19T21:42:20+02:00",
  "product": "Platform",
  "component": "SWT",
  "severity": "normal"
}