{
  "comments": [
    "I downloaded the sourcebuild of Eclipse 3.1. I wanted to create the build for\nSolaris-gtk-x86 but there\u0027s an error which i don\u0027t know how to fix.\n\nThe following is displayed in my terminal after he has done something:\n\nBUILD SUCCESSFUL\nTotal time: 1 minute 15 seconds\nAssuming RHEL CLASSPATH compatible.\n     [echo] TARGET: compiler2\n     [echo] compilerArg -encoding ISO-8859-1\n     [echo] build compiler org.eclipse.jdt.core.JDTCompilerAdapter\n\nBUILD FAILED\n/Desktop/eclipse/jdtcoresrc/compilejdtcore.xml:47: Compiler Adapter\n\u0027org.eclipse.jdt.core.JDTCompilerAdapter\u0027 can\u0027t be found.\n\nTotal time: 5 seconds\nAssuming RHEL CLASSPATH compatible.\n\nBUILD FAILED\n/Desktop/eclipse/build.xml:238: The Eclipse compiler (ecj.jar) cannot be found.\n\nTotal time: 4 seconds \n\n\nIch hope you can help me.",
    "I have the same problem on another platform, debian (sarge), j2sdk 1.4.2, and\nant 1.6.2. Build is ran for linux,gtk,x86.\n\nIt sounds like a more apt summary for this bug would be along the lines, \"\nEclipse can not get compiler from CompilerAdapterFactory\". It is also not\nspecific to Solaris-GTK. (Assuming we are seeing the same bug.)\n\ncompilelog2.txt:\n\n    [javac] Compiling 297 source files to\n/home/chris/school/archive/grad/1/spring/cs239-4/eclipse/jdtcoresrc/compiler2\n\nBUILD FAILED\n\n/home/chris/school/archive/grad/1/spring/cs239-4/eclipse/jdtcoresrc/compilejdtcore.xml:47:\nCompiler Adapter org.eclipse.jdt.core.JDTCompilerAdapter caused an interesting\nexception.\n        at\norg.apache.tools.ant.taskdefs.compilers.CompilerAdapterFactory.resolveClassName(CompilerAdapterFactory.java:173)\n        at\norg.apache.tools.ant.taskdefs.compilers.CompilerAdapterFactory.getCompiler(CompilerAdapterFactory.java:130)\n        at org.apache.tools.ant.taskdefs.Javac.compile(Javac.java:929)\n        at org.apache.tools.ant.taskdefs.Javac.execute(Javac.java:758)\n        at org.apache.tools.ant.UnknownElement.execute(UnknownElement.java:275)\n        at org.apache.tools.ant.Task.perform(Task.java:364)\n        at org.apache.tools.ant.Target.execute(Target.java:341)\n        at org.apache.tools.ant.Target.performTasks(Target.java:369)\n        at org.apache.tools.ant.Project.executeTarget(Project.java:1214)\n        at org.apache.tools.ant.Project.executeTargets(Project.java:1062)\n        at org.apache.tools.ant.Main.runBuild(Main.java:673)\n        at org.apache.tools.ant.Main.startAnt(Main.java:188)\n        at org.apache.tools.ant.launch.Launcher.run(Launcher.java:196)\n        at org.apache.tools.ant.launch.Launcher.main(Launcher.java:55)\nCaused by: java.lang.NoClassDefFoundError:\norg/apache/tools/ant/taskdefs/compilers/DefaultCompilerAdapter\n        at java.lang.ClassLoader.defineClass0(Native Method)\n        at java.lang.ClassLoader.defineClass(ClassLoader.java:537)\n        at java.security.SecureClassLoader.defineClass(SecureClassLoader.java:123)\n        at java.net.URLClassLoader.defineClass(URLClassLoader.java:251)\n        at java.net.URLClassLoader.access$100(URLClassLoader.java:55)\n        at java.net.URLClassLoader$1.run(URLClassLoader.java:194)\n        at java.security.AccessController.doPrivileged(Native Method)\n        at java.net.URLClassLoader.findClass(URLClassLoader.java:187)\n        at java.lang.ClassLoader.loadClass(ClassLoader.java:289)\n        at sun.misc.Launcher$AppClassLoader.loadClass(Launcher.java:274)\n        at java.lang.ClassLoader.loadClass(ClassLoader.java:282)\n        at java.lang.ClassLoader.loadClass(ClassLoader.java:235)\n        at java.lang.ClassLoader.loadClassInternal(ClassLoader.java:302)\n        at java.lang.Class.forName0(Native Method)\n        at java.lang.Class.forName(Class.java:141)\n        at\norg.apache.tools.ant.taskdefs.compilers.CompilerAdapterFactory.resolveClassName(CompilerAdapterFactory.java:162)\n        ... 13 more\n--- Nested Exception ---\njava.lang.NoClassDefFoundError:\norg/apache/tools/ant/taskdefs/compilers/DefaultCompilerAdapter\n        at java.lang.ClassLoader.defineClass0(Native Method)\n        at java.lang.ClassLoader.defineClass(ClassLoader.java:537)\n        at java.security.SecureClassLoader.defineClass(SecureClassLoader.java:123)\n        at java.net.URLClassLoader.defineClass(URLClassLoader.java:251)\n        at java.net.URLClassLoader.access$100(URLClassLoader.java:55)\n        at java.net.URLClassLoader$1.run(URLClassLoader.java:194)\n        at java.security.AccessController.doPrivileged(Native Method)\n        at java.net.URLClassLoader.findClass(URLClassLoader.java:187)\n        at java.lang.ClassLoader.loadClass(ClassLoader.java:289)\n        at sun.misc.Launcher$AppClassLoader.loadClass(Launcher.java:274)\n        at java.lang.ClassLoader.loadClass(ClassLoader.java:282)\n        at java.lang.ClassLoader.loadClass(ClassLoader.java:235)\n        at java.lang.ClassLoader.loadClassInternal(ClassLoader.java:302)\n        at java.lang.Class.forName0(Native Method)\n        at java.lang.Class.forName(Class.java:141)\n        at\norg.apache.tools.ant.taskdefs.compilers.CompilerAdapterFactory.resolveClassName(CompilerAdapterFactory.java:162)\n        at\norg.apache.tools.ant.taskdefs.compilers.CompilerAdapterFactory.getCompiler(CompilerAdapterFactory.java:130)\n        at org.apache.tools.ant.taskdefs.Javac.compile(Javac.java:929)\n        at org.apache.tools.ant.taskdefs.Javac.execute(Javac.java:758)\n        at org.apache.tools.ant.UnknownElement.execute(UnknownElement.java:275)\n        at org.apache.tools.ant.Task.perform(Task.java:364)\n        at org.apache.tools.ant.Target.execute(Target.java:341)\n        at org.apache.tools.ant.Target.performTasks(Target.java:369)\n        at org.apache.tools.ant.Project.executeTarget(Project.java:1214)\n        at org.apache.tools.ant.Project.executeTargets(Project.java:1062)\n        at org.apache.tools.ant.Main.runBuild(Main.java:673)\n        at org.apache.tools.ant.Main.startAnt(Main.java:188)\n        at org.apache.tools.ant.launch.Launcher.run(Launcher.java:196)\n        at org.apache.tools.ant.launch.Launcher.main(Launcher.java:55)",
    "Same problem with j2sdk1.5 on Debian Linux GTK. I changed the build.xml file to\njavacSource\u003d1.4 as instructed.",
    "I have had this problem with Solaris Express 8/05, j2sdk1.5.0_01 and ant 1.6.5.\nIt is apparently caused by ant not finding the ecj.jar when it builds the\necj.jar with itself (the jdtcoresrc/compiler2 stuff). I managed to get past that\npoint with the build with a simple trick:\n\nFirst unpack the eclipse SDK 3.1 sources in some directory $ECLIPSE_SRC. If you\nare building for Solaris x86, you will have to create the file structure for it\njust like the sparc structure that is already there.\n\nFrom here use the following commands:\ncd $ECLIPSE_SRC/jdtcoresrc\nant -buildfile compilejdtcorewithjavac.xml\nCLASSPATH\u003d./ecj.jar ant -buildfile compilejdtcore.xml\ncd ..\nCLASSPATH\u003d./ecj.jar ./build -os solaris -ws gtk -arch i386 -compilelibs\nCLASSPATH\u003d./ecj.jar ./build -os solaris -ws motif -arch i386 -compilelibs\n\nI have tested this on Solaris, but in principle any Unix-like platform will work\naccordingly. I also got lots of compilation warnings but I guess this is caused\nby the JDK 1.5.0 I am using.\n\nNow someone who knows one\u0027s way through ant could fix this small classpath\nproblem and save us all this trouble.\n\nDoug",
    "Thanks Doug.\nTrying this on the platform I mentioned (but with jdk 1.5 instead of 1.4.2), it\nappears that the ./build still goes to generate ecj.jar and fails. The failure\ndoes seem to be a bit different, some output from compilelog.txt:\n\nbuild.jars:\n\nproperties:\n\ninit:\n\n@dot:\n    [mkdir] Created dir:\n/home/chris/school/archive/grad/1/spring/cs239-4/eclipse/plugins/org.eclipse.osgi/temp.folder/@dot.bin\n    [javac] Compiling 261 source files to\n/home/chris/school/archive/grad/1/spring/cs239-4/eclipse/plugins/org.eclipse.osgi/temp.folder/@dot.bin\n\nBUILD FAILED\n\n/home/chris/school/archive/grad/1/spring/cs239-4/eclipse/build.xml:37: The\nfollowing error occurred while executing this line:\n/home/chris/school/archive/grad/1/spring/cs239-4/eclipse/build.xml:8: The\nfollowing error occurred while executing this line:\n/home/chris/school/archive/grad/1/spring/cs239-4/eclipse/features/org.eclipse.sdk/build.xml:35:\nThe following error occurred while executing this line:\n/home/chris/school/archive/grad/1/spring/cs239-4/eclipse/features/org.eclipse.sdk/build.xml:17:\nThe following error occurred while executing this line:\n/home/chris/school/archive/grad/1/spring/cs239-4/eclipse/features/org.eclipse.platform/build.xml:305:\nThe following error occurred while executing this line:\n/home/chris/school/archive/grad/1/spring/cs239-4/eclipse/features/org.eclipse.platform/build.xml:292:\nThe following error occurred while executing this line:\n/home/chris/school/archive/grad/1/spring/cs239-4/eclipse/features/org.eclipse.rcp/build.xml:144:\nThe following error occurred while executing this line:\n/home/chris/school/archive/grad/1/spring/cs239-4/eclipse/features/org.eclipse.rcp/build.xml:15:\nThe following error occurred while executing this line:\n/home/chris/school/archive/grad/1/spring/cs239-4/eclipse/plugins/org.eclipse.osgi/build.xml:100:\nThe following error occurred while executing this line:\n/home/chris/school/archive/grad/1/spring/cs239-4/eclipse/plugins/org.eclipse.osgi/build.xml:56:\nCompiler Adapter org.eclipse.jdt.core.JDTCompilerAdapter caused an interesting\nexception.\n        at\norg.apache.tools.ant.ProjectHelper.addLocationToBuildException(ProjectHelper.java:539)\n        at org.apache.tools.ant.taskdefs.Ant.execute(Ant.java:388)\n        at org.apache.tools.ant.taskdefs.CallTarget.execute(CallTarget.java:106)\n        at org.apache.tools.ant.UnknownElement.execute(UnknownElement.java:275)\n        at org.apache.tools.ant.Task.perform(Task.java:364)\n        at org.apache.tools.ant.Target.execute(Target.java:341)\n        at org.apache.tools.ant.Target.performTasks(Target.java:369)\n        at org.apache.tools.ant.Project.executeTarget(Project.java:1214)\n        at org.apache.tools.ant.Project.executeTargets(Project.java:1062)\n        at org.apache.tools.ant.Main.runBuild(Main.java:673)\n        at org.apache.tools.ant.Main.startAnt(Main.java:188)\n        at org.apache.tools.ant.launch.Launcher.run(Launcher.java:196)\n        at org.apache.tools.ant.launch.Launcher.main(Launcher.java:55)\n\n\nDozens more org.eclipse.jdt.core.JDTCompilerAdapter exceptions are generated\nfollowing this one.",
    "Chris,\nI don?t have the code right here (I?m at work now) but I?ll look into it later.\nMaybe you can take a look at the build.xml line 37 to try to figure out what the\nscript was trying to do when it issued the first error.\nBTW, I just forgot to mention yesterday. I defined the following variable in my\nshell before trying to build the ecj.jar as the build would fail right at the\nbeginning because of memory exhaustion:\nANT_OPTS\u003d-Xmx1024m;export ANT_OPTS\nMaybe this will solve your problem before we try to look into the build scripts.\nCheers,\nDoug",
    "build.xml:37 is an antcall for allElements\u0027s build.jars. The exception bottoms\nout doing a javac for the @dot target at plugins/org.eclipse.osgi/build.xml:56.\n\n(thanks again for the help)",
    "Solaris 10-gtk-x86 is not a supported platform for eclipse 3.1\n\nhttp://www.eclipse.org/eclipse/development/eclipse_project_plan_3_1.html#TargetOperatingEnvironments\n\nIf you would like this architecture to be added to the source build scripts for\nthe 3.2 stream, please provide a patch. We are not adding additional platform\nsupport to 3.1.1 stream builds.\n",
    "The majority of comments in this bug occur on the linux platform. As this bug is\nmarked for solaris and this configuration of solaris is not yet supported, I\nhave created bug #109351 for these build problems on linux.",
    "\n\n*** This bug has been marked as a duplicate of 84344 ***"
  ],
  "commentCreationDates": [
    "2005-08-24T16:27:38+02:00",
    "2005-08-25T17:14:55+02:00",
    "2005-09-06T09:52:11+02:00",
    "2005-09-08T06:29:08+02:00",
    "2005-09-08T07:00:44+02:00",
    "2005-09-08T14:53:21+02:00",
    "2005-09-11T19:08:38+02:00",
    "2005-09-13T03:29:51+02:00",
    "2005-09-13T05:38:13+02:00",
    "2005-09-16T17:54:30+02:00"
  ],
  "traces": [
    {
      "exceptionType": "java.lang.NoClassDefFoundError",
      "message": "org/apache/tools/ant/taskdefs/compilers/DefaultCompilerAdapter",
      "elements": [
        {
          "method": "java.lang.ClassLoader.defineClass0",
          "source": "Native Method"
        },
        {
          "method": "java.lang.ClassLoader.defineClass",
          "source": "ClassLoader.java:537"
        },
        {
          "method": "java.security.SecureClassLoader.defineClass",
          "source": "SecureClassLoader.java:123"
        },
        {
          "method": "java.net.URLClassLoader.defineClass",
          "source": "URLClassLoader.java:251"
        },
        {
          "method": "java.net.URLClassLoader.access$100",
          "source": "URLClassLoader.java:55"
        },
        {
          "method": "java.net.URLClassLoader$1.run",
          "source": "URLClassLoader.java:194"
        },
        {
          "method": "java.security.AccessController.doPrivileged",
          "source": "Native Method"
        },
        {
          "method": "java.net.URLClassLoader.findClass",
          "source": "URLClassLoader.java:187"
        },
        {
          "method": "java.lang.ClassLoader.loadClass",
          "source": "ClassLoader.java:289"
        },
        {
          "method": "sun.misc.Launcher$AppClassLoader.loadClass",
          "source": "Launcher.java:274"
        },
        {
          "method": "java.lang.ClassLoader.loadClass",
          "source": "ClassLoader.java:282"
        },
        {
          "method": "java.lang.ClassLoader.loadClass",
          "source": "ClassLoader.java:235"
        },
        {
          "method": "java.lang.ClassLoader.loadClassInternal",
          "source": "ClassLoader.java:302"
        },
        {
          "method": "java.lang.Class.forName0",
          "source": "Native Method"
        },
        {
          "method": "java.lang.Class.forName",
          "source": "Class.java:141"
        },
        {
          "method": "org.apache.tools.ant.taskdefs.compilers.CompilerAdapterFactory.resolveClassName",
          "source": "CompilerAdapterFactory.java:162"
        }
      ],
      "number": 0,
      "commentIndex": 1,
      "bugId": "107852",
      "duplicateId": "84344",
      "date": "2005-08-25T17:14:55+02:00",
      "product": "Platform",
      "component": "Releng",
      "severity": "normal"
    },
    {
      "exceptionType": "java.lang.NoClassDefFoundError",
      "message": "org/apache/tools/ant/taskdefs/compilers/DefaultCompilerAdapter",
      "elements": [
        {
          "method": "java.lang.ClassLoader.defineClass0",
          "source": "Native Method"
        },
        {
          "method": "java.lang.ClassLoader.defineClass",
          "source": "ClassLoader.java:537"
        },
        {
          "method": "java.security.SecureClassLoader.defineClass",
          "source": "SecureClassLoader.java:123"
        },
        {
          "method": "java.net.URLClassLoader.defineClass",
          "source": "URLClassLoader.java:251"
        },
        {
          "method": "java.net.URLClassLoader.access$100",
          "source": "URLClassLoader.java:55"
        },
        {
          "method": "java.net.URLClassLoader$1.run",
          "source": "URLClassLoader.java:194"
        },
        {
          "method": "java.security.AccessController.doPrivileged",
          "source": "Native Method"
        },
        {
          "method": "java.net.URLClassLoader.findClass",
          "source": "URLClassLoader.java:187"
        },
        {
          "method": "java.lang.ClassLoader.loadClass",
          "source": "ClassLoader.java:289"
        },
        {
          "method": "sun.misc.Launcher$AppClassLoader.loadClass",
          "source": "Launcher.java:274"
        },
        {
          "method": "java.lang.ClassLoader.loadClass",
          "source": "ClassLoader.java:282"
        },
        {
          "method": "java.lang.ClassLoader.loadClass",
          "source": "ClassLoader.java:235"
        },
        {
          "method": "java.lang.ClassLoader.loadClassInternal",
          "source": "ClassLoader.java:302"
        },
        {
          "method": "java.lang.Class.forName0",
          "source": "Native Method"
        },
        {
          "method": "java.lang.Class.forName",
          "source": "Class.java:141"
        },
        {
          "method": "org.apache.tools.ant.taskdefs.compilers.CompilerAdapterFactory.resolveClassName",
          "source": "CompilerAdapterFactory.java:162"
        },
        {
          "method": "org.apache.tools.ant.taskdefs.compilers.CompilerAdapterFactory.getCompiler",
          "source": "CompilerAdapterFactory.java:130"
        },
        {
          "method": "org.apache.tools.ant.taskdefs.Javac.compile",
          "source": "Javac.java:929"
        },
        {
          "method": "org.apache.tools.ant.taskdefs.Javac.execute",
          "source": "Javac.java:758"
        },
        {
          "method": "org.apache.tools.ant.UnknownElement.execute",
          "source": "UnknownElement.java:275"
        },
        {
          "method": "org.apache.tools.ant.Task.perform",
          "source": "Task.java:364"
        },
        {
          "method": "org.apache.tools.ant.Target.execute",
          "source": "Target.java:341"
        },
        {
          "method": "org.apache.tools.ant.Target.performTasks",
          "source": "Target.java:369"
        },
        {
          "method": "org.apache.tools.ant.Project.executeTarget",
          "source": "Project.java:1214"
        },
        {
          "method": "org.apache.tools.ant.Project.executeTargets",
          "source": "Project.java:1062"
        },
        {
          "method": "org.apache.tools.ant.Main.runBuild",
          "source": "Main.java:673"
        },
        {
          "method": "org.apache.tools.ant.Main.startAnt",
          "source": "Main.java:188"
        },
        {
          "method": "org.apache.tools.ant.launch.Launcher.run",
          "source": "Launcher.java:196"
        },
        {
          "method": "org.apache.tools.ant.launch.Launcher.main",
          "source": "Launcher.java:55"
        }
      ],
      "number": 1,
      "commentIndex": 1,
      "bugId": "107852",
      "duplicateId": "84344",
      "date": "2005-08-25T17:14:55+02:00",
      "product": "Platform",
      "component": "Releng",
      "severity": "normal"
    }
  ],
  "groupId": "84344",
  "bugId": "107852",
  "duplicateId": "84344",
  "date": "2005-08-24T16:27:38+02:00",
  "product": "Platform",
  "component": "Releng",
  "severity": "normal"
}