{
  "comments": [
    "I am attempting to run Eclipse v.3.1 on an AMD Athlon64 with kernel 2.6.13-rc5\nand Gentoo.  I have attempted to run both the Sun JDK 1.5.0 and 1.6.0 beta (both\n64 bit versions), and both exhibit the same behavior.  The most noticeable\nproblem for me is that I receive a typical \"Out of Memory\" dialog after building\na few times.  When this happens, I also receive the message posted at the end of\nthis report.  I have attempted a few different sets of vmargs, and all behave\nsimilarly.  Most recently, I have run it with the args:\n\n-vmargs\n-Xms1024m\n-Xmx1024m\n-d64\n\n(I also tried this omitting the -d64 flag)\n\nI even doubled my RAM to 2GB to see if the problem would go away.  Good excuse\nfor a RAM upgrade I guess. :-)\n\njava.lang.UnsatisfiedLinkError: no spawner in java.library.path\n        at java.lang.ClassLoader.loadLibrary(ClassLoader.java:1682)\n        at java.lang.Runtime.loadLibrary0(Runtime.java:821)\n        at java.lang.System.loadLibrary(System.java:992)\n        at\norg.eclipse.cdt.utils.spawner.ProcessFactory.\u003cinit\u003e(ProcessFactory.java:35)\n        at\norg.eclipse.cdt.utils.spawner.ProcessFactory.getFactory(ProcessFactory.java:47)\n        at\norg.eclipse.cdt.utils.spawner.EnvironmentReader.getEnvVars(EnvironmentReader.java:49)\n        at\norg.eclipse.cdt.core.CommandLauncher.getEnvironment(CommandLauncher.java:67)\n        at org.eclipse.cdt.make.core.MakeBuilder.invokeMake(MakeBuilder.java:147)\n        at org.eclipse.cdt.make.core.MakeBuilder.build(MakeBuilder.java:76)\n        at\norg.eclipse.core.internal.events.BuildManager$2.run(BuildManager.java:593)\n        at\norg.eclipse.core.internal.runtime.InternalPlatform.run(InternalPlatform.java:1044)\n        at org.eclipse.core.runtime.Platform.run(Platform.java:783)\n        at\norg.eclipse.core.internal.events.BuildManager.basicBuild(BuildManager.java:168)\n        at\norg.eclipse.core.internal.events.BuildManager.basicBuild(BuildManager.java:202)\n        at\norg.eclipse.core.internal.events.BuildManager$1.run(BuildManager.java:231)\n        at\norg.eclipse.core.internal.runtime.InternalPlatform.run(InternalPlatform.java:1044)\n        at org.eclipse.core.runtime.Platform.run(Platform.java:783)\n        at\norg.eclipse.core.internal.events.BuildManager.basicBuild(BuildManager.java:234)\n        at\norg.eclipse.core.internal.events.BuildManager.basicBuildLoop(BuildManager.java:253)\n        at\norg.eclipse.core.internal.events.BuildManager.build(BuildManager.java:282)\n        at\norg.eclipse.core.internal.events.AutoBuildJob.doBuild(AutoBuildJob.java:139)\n        at org.eclipse.core.internal.events.AutoBuildJob.run(AutoBuildJob.java:200)\n        at org.eclipse.core.internal.jobs.Worker.run(Worker.java:76)\nWarning: Could not get charToByteConverterClass!\nUnhandled event loop exception\nReason:\nunable to create new native thread",
    "I apologize, I somehow ended up pairing up too old a version of CDT with Eclipse\n3.1.  I\u0027ll reopen this if the problem reoccurs.",
    "This bug is still present in v.3.0 of CDT.  The only difference is that I now\nreceive this message immediately upon startup:\n\nWarning: Could not get charToByteConverterClass!\n\nAnd, the message I receive after the out of memory condition has been shortened\nto this:\n\nUnhandled event loop exception\nReason:\nunable to create new native thread\n",
    "If someone has a 64-bit x86 box and wants to test and debug this we could use the help.  Otherwise I don\u0027t think this will be resolved any time soon."
  ],
  "commentCreationDates": [
    "2005-08-28T03:06:16+02:00",
    "2005-08-28T03:16:54+02:00",
    "2005-08-28T03:48:14+02:00",
    "2007-05-15T22:19:14+02:00"
  ],
  "traces": [
    {
      "exceptionType": "java.lang.UnsatisfiedLinkError",
      "message": "no spawner in java.library.path",
      "elements": [
        {
          "method": "java.lang.ClassLoader.loadLibrary",
          "source": "ClassLoader.java:1682"
        },
        {
          "method": "java.lang.Runtime.loadLibrary0",
          "source": "Runtime.java:821"
        },
        {
          "method": "java.lang.System.loadLibrary",
          "source": "System.java:992"
        },
        {
          "method": "org.eclipse.cdt.utils.spawner.ProcessFactory.\u003cinit\u003e",
          "source": "ProcessFactory.java:35"
        },
        {
          "method": "org.eclipse.cdt.utils.spawner.ProcessFactory.getFactory",
          "source": "ProcessFactory.java:47"
        },
        {
          "method": "org.eclipse.cdt.utils.spawner.EnvironmentReader.getEnvVars",
          "source": "EnvironmentReader.java:49"
        },
        {
          "method": "org.eclipse.cdt.core.CommandLauncher.getEnvironment",
          "source": "CommandLauncher.java:67"
        },
        {
          "method": "org.eclipse.cdt.make.core.MakeBuilder.invokeMake",
          "source": "MakeBuilder.java:147"
        },
        {
          "method": "org.eclipse.cdt.make.core.MakeBuilder.build",
          "source": "MakeBuilder.java:76"
        },
        {
          "method": "org.eclipse.core.internal.events.BuildManager$2.run",
          "source": "BuildManager.java:593"
        },
        {
          "method": "org.eclipse.core.internal.runtime.InternalPlatform.run",
          "source": "InternalPlatform.java:1044"
        },
        {
          "method": "org.eclipse.core.runtime.Platform.run",
          "source": "Platform.java:783"
        },
        {
          "method": "org.eclipse.core.internal.events.BuildManager.basicBuild",
          "source": "BuildManager.java:168"
        },
        {
          "method": "org.eclipse.core.internal.events.BuildManager.basicBuild",
          "source": "BuildManager.java:202"
        },
        {
          "method": "org.eclipse.core.internal.events.BuildManager$1.run",
          "source": "BuildManager.java:231"
        },
        {
          "method": "org.eclipse.core.internal.runtime.InternalPlatform.run",
          "source": "InternalPlatform.java:1044"
        },
        {
          "method": "org.eclipse.core.runtime.Platform.run",
          "source": "Platform.java:783"
        },
        {
          "method": "org.eclipse.core.internal.events.BuildManager.basicBuild",
          "source": "BuildManager.java:234"
        },
        {
          "method": "org.eclipse.core.internal.events.BuildManager.basicBuildLoop",
          "source": "BuildManager.java:253"
        },
        {
          "method": "org.eclipse.core.internal.events.BuildManager.build",
          "source": "BuildManager.java:282"
        },
        {
          "method": "org.eclipse.core.internal.events.AutoBuildJob.doBuild",
          "source": "AutoBuildJob.java:139"
        },
        {
          "method": "org.eclipse.core.internal.events.AutoBuildJob.run",
          "source": "AutoBuildJob.java:200"
        },
        {
          "method": "org.eclipse.core.internal.jobs.Worker.run",
          "source": "Worker.java:76"
        }
      ],
      "number": 0,
      "commentIndex": 0,
      "bugId": "108207",
      "date": "2005-08-28T03:06:16+02:00",
      "product": "CDT",
      "component": "cdt-build",
      "severity": "major"
    }
  ],
  "groupId": "108207",
  "bugId": "108207",
  "date": "2005-08-28T03:06:16+02:00",
  "product": "CDT",
  "component": "cdt-build",
  "severity": "major"
}