{
  "comments": [
    "Eclipse 3.1, Mozilla 1.7.10-1.5.1 (FC4)\n\n1. Open a .html file in the internal web browser.\n2. Rename the file in the package explorer using Refactor \u003e Rename.\n3. Hit reload in the browser.\n\nEclipse dies with this message:\n\nUnhandled event loop exception\nReason:\nXPCOM error -2142109678\n\n!ENTRY org.eclipse.ui 4 0 2005-08-31 15:33:17.810\n!MESSAGE XPCOM error -2142109678\n!STACK 0\norg.eclipse.swt.SWTError: XPCOM error -2142109678\n        at org.eclipse.swt.browser.Browser.error(Browser.java:983)\n        at org.eclipse.swt.browser.Browser.refresh(Browser.java:1109)\n        at\norg.eclipse.ui.internal.browser.BrowserViewer.refresh(BrowserViewer.java:636)\n        at\norg.eclipse.ui.internal.browser.BrowserViewer$15.widgetSelected(BrowserViewer.java:805)\n        at org.eclipse.swt.widgets.TypedListener.handleEvent(TypedListener.java:90)\n        at org.eclipse.swt.widgets.EventTable.sendEvent(EventTable.java:66)\n        at org.eclipse.swt.widgets.Widget.sendEvent(Widget.java:1021)\n        at org.eclipse.swt.widgets.Display.runDeferredEvents(Display.java:2867)\n        at org.eclipse.swt.widgets.Display.readAndDispatch(Display.java:2572)\n        at org.eclipse.ui.internal.Workbench.runEventLoop(Workbench.java:1699)\n        at org.eclipse.ui.internal.Workbench.runUI(Workbench.java:1663)\n        at\norg.eclipse.ui.internal.Workbench.createAndRunWorkbench(Workbench.java:367)\n        at org.eclipse.ui.PlatformUI.createAndRunWorkbench(PlatformUI.java:143)\n        at org.eclipse.ui.internal.ide.IDEApplication.run(IDEApplication.java:103)\n        at\norg.eclipse.core.internal.runtime.PlatformActivator$1.run(PlatformActivator.java:226)\n        at\norg.eclipse.core.runtime.adaptor.EclipseStarter.run(EclipseStarter.java:376)\n        at\norg.eclipse.core.runtime.adaptor.EclipseStarter.run(EclipseStarter.java:163)\n        at sun.reflect.NativeMethodAccessorImpl.invoke0(Native Method)\n        at\nsun.reflect.NativeMethodAccessorImpl.invoke(NativeMethodAccessorImpl.java:39)\n        at\nsun.reflect.DelegatingMethodAccessorImpl.invoke(DelegatingMethodAccessorImpl.java:25)\n        at java.lang.reflect.Method.invoke(Method.java:324)\n        at org.eclipse.core.launcher.Main.invokeFramework(Main.java:334)\n        at org.eclipse.core.launcher.Main.basicRun(Main.java:278)\n        at org.eclipse.core.launcher.Main.run(Main.java:973)\n        at org.eclipse.core.launcher.Main.main(Main.java:948)",
    "fixed on gtk and motif \u003e 0908\n"
  ],
  "commentCreationDates": [
    "2005-08-31T21:28:46+02:00",
    "2005-09-08T16:43:03+02:00"
  ],
  "traces": [
    {
      "exceptionType": "org.eclipse.swt.SWTError",
      "message": "XPCOM error -2142109678",
      "elements": [
        {
          "method": "org.eclipse.swt.browser.Browser.error",
          "source": "Browser.java:983"
        },
        {
          "method": "org.eclipse.swt.browser.Browser.refresh",
          "source": "Browser.java:1109"
        },
        {
          "method": "org.eclipse.ui.internal.browser.BrowserViewer.refresh",
          "source": "BrowserViewer.java:636"
        },
        {
          "method": "org.eclipse.ui.internal.browser.BrowserViewer$15.widgetSelected",
          "source": "BrowserViewer.java:805"
        },
        {
          "method": "org.eclipse.swt.widgets.TypedListener.handleEvent",
          "source": "TypedListener.java:90"
        },
        {
          "method": "org.eclipse.swt.widgets.EventTable.sendEvent",
          "source": "EventTable.java:66"
        },
        {
          "method": "org.eclipse.swt.widgets.Widget.sendEvent",
          "source": "Widget.java:1021"
        },
        {
          "method": "org.eclipse.swt.widgets.Display.runDeferredEvents",
          "source": "Display.java:2867"
        },
        {
          "method": "org.eclipse.swt.widgets.Display.readAndDispatch",
          "source": "Display.java:2572"
        },
        {
          "method": "org.eclipse.ui.internal.Workbench.runEventLoop",
          "source": "Workbench.java:1699"
        },
        {
          "method": "org.eclipse.ui.internal.Workbench.runUI",
          "source": "Workbench.java:1663"
        },
        {
          "method": "org.eclipse.ui.internal.Workbench.createAndRunWorkbench",
          "source": "Workbench.java:367"
        },
        {
          "method": "org.eclipse.ui.PlatformUI.createAndRunWorkbench",
          "source": "PlatformUI.java:143"
        },
        {
          "method": "org.eclipse.ui.internal.ide.IDEApplication.run",
          "source": "IDEApplication.java:103"
        },
        {
          "method": "org.eclipse.core.internal.runtime.PlatformActivator$1.run",
          "source": "PlatformActivator.java:226"
        },
        {
          "method": "org.eclipse.core.runtime.adaptor.EclipseStarter.run",
          "source": "EclipseStarter.java:376"
        },
        {
          "method": "org.eclipse.core.runtime.adaptor.EclipseStarter.run",
          "source": "EclipseStarter.java:163"
        },
        {
          "method": "sun.reflect.NativeMethodAccessorImpl.invoke0",
          "source": "Native Method"
        },
        {
          "method": "sun.reflect.NativeMethodAccessorImpl.invoke",
          "source": "NativeMethodAccessorImpl.java:39"
        },
        {
          "method": "sun.reflect.DelegatingMethodAccessorImpl.invoke",
          "source": "DelegatingMethodAccessorImpl.java:25"
        },
        {
          "method": "java.lang.reflect.Method.invoke",
          "source": "Method.java:324"
        },
        {
          "method": "org.eclipse.core.launcher.Main.invokeFramework",
          "source": "Main.java:334"
        },
        {
          "method": "org.eclipse.core.launcher.Main.basicRun",
          "source": "Main.java:278"
        },
        {
          "method": "org.eclipse.core.launcher.Main.run",
          "source": "Main.java:973"
        },
        {
          "method": "org.eclipse.core.launcher.Main.main",
          "source": "Main.java:948"
        }
      ],
      "number": 0,
      "commentIndex": 0,
      "bugId": "108511",
      "date": "2005-08-31T21:28:46+02:00",
      "product": "Platform",
      "component": "SWT",
      "severity": "normal"
    }
  ],
  "groupId": "108511",
  "bugId": "108511",
  "date": "2005-08-31T21:28:46+02:00",
  "product": "Platform",
  "component": "SWT",
  "severity": "normal"
}