{
  "comments": [
    "Exception in thread \"main\" java.lang.ClassCastException:\norg.eclipse.swt.layout.GridData\n        at org.eclipse.swt.layout.FillLayout.computeChildSize(FillLayout.java:141)\n        at org.eclipse.swt.layout.FillLayout.computeSize(FillLayout.java:119)\n        at org.eclipse.swt.widgets.Composite.computeSize(Composite.java:192)\n        at org.eclipse.swt.layout.GridData.computeSize(GridData.java:478)\n        at org.eclipse.swt.layout.GridLayout.layout(GridLayout.java:207)\n        at org.eclipse.swt.layout.GridLayout.computeSize(GridLayout.java:155)\n        at org.eclipse.swt.widgets.Composite.computeSize(Composite.java:192)\n        at org.eclipse.swt.layout.GridData.computeSize(GridData.java:478)\n        at org.eclipse.swt.layout.GridLayout.layout(GridLayout.java:207)\n        at org.eclipse.swt.layout.GridLayout.layout(GridLayout.java:186)\n        at org.eclipse.swt.widgets.Composite.updateLayout(Composite.java:1133)\n        at org.eclipse.swt.widgets.Shell.resizeBounds(Shell.java:1071)\n        at org.eclipse.swt.widgets.Shell.gtk_size_allocate(Shell.java:876)\n        at org.eclipse.swt.widgets.Widget.windowProc(Widget.java:1375)\n        at org.eclipse.swt.widgets.Display.windowProc(Display.java:3442)\n        at org.eclipse.swt.internal.gtk.OS._gtk_widget_show(Native Method)\n        at org.eclipse.swt.internal.gtk.OS.gtk_widget_show(OS.java:7262)\n        at org.eclipse.swt.widgets.Shell.setVisible(Shell.java:1382)\n        at org.eclipse.swt.widgets.Shell.open(Shell.java:948)\n        at MySWT4.go(Unknown Source)\n        at MySWT4.main(Unknown Source)\n\nI will attach a sample that demonstrates the bug.",
    "Created an attachment (id\u003d26738)\nn Exception under Linux with Eclipse 3.1\n\nStandalone SWT application that works fine under Windows Eclipse 3.0 but throws\na\nn Exception under Linux with Eclipse 3.1",
    "\n\n*** This bug has been marked as a duplicate of 92803 ***",
    "See bug 92803 comment 8"
  ],
  "commentCreationDates": [
    "2005-08-31T22:34:01+02:00",
    "2005-08-31T22:37:01+02:00",
    "2005-08-31T22:48:22+02:00",
    "2005-09-01T15:59:09+02:00"
  ],
  "traces": [
    {
      "exceptionType": "java.lang.ClassCastException",
      "message": "org.eclipse.swt.layout.GridData",
      "elements": [
        {
          "method": "org.eclipse.swt.layout.FillLayout.computeChildSize",
          "source": "FillLayout.java:141"
        },
        {
          "method": "org.eclipse.swt.layout.FillLayout.computeSize",
          "source": "FillLayout.java:119"
        },
        {
          "method": "org.eclipse.swt.widgets.Composite.computeSize",
          "source": "Composite.java:192"
        },
        {
          "method": "org.eclipse.swt.layout.GridData.computeSize",
          "source": "GridData.java:478"
        },
        {
          "method": "org.eclipse.swt.layout.GridLayout.layout",
          "source": "GridLayout.java:207"
        },
        {
          "method": "org.eclipse.swt.layout.GridLayout.computeSize",
          "source": "GridLayout.java:155"
        },
        {
          "method": "org.eclipse.swt.widgets.Composite.computeSize",
          "source": "Composite.java:192"
        },
        {
          "method": "org.eclipse.swt.layout.GridData.computeSize",
          "source": "GridData.java:478"
        },
        {
          "method": "org.eclipse.swt.layout.GridLayout.layout",
          "source": "GridLayout.java:207"
        },
        {
          "method": "org.eclipse.swt.layout.GridLayout.layout",
          "source": "GridLayout.java:186"
        },
        {
          "method": "org.eclipse.swt.widgets.Composite.updateLayout",
          "source": "Composite.java:1133"
        },
        {
          "method": "org.eclipse.swt.widgets.Shell.resizeBounds",
          "source": "Shell.java:1071"
        },
        {
          "method": "org.eclipse.swt.widgets.Shell.gtk_size_allocate",
          "source": "Shell.java:876"
        },
        {
          "method": "org.eclipse.swt.widgets.Widget.windowProc",
          "source": "Widget.java:1375"
        },
        {
          "method": "org.eclipse.swt.widgets.Display.windowProc",
          "source": "Display.java:3442"
        },
        {
          "method": "org.eclipse.swt.internal.gtk.OS._gtk_widget_show",
          "source": "Native Method"
        },
        {
          "method": "org.eclipse.swt.internal.gtk.OS.gtk_widget_show",
          "source": "OS.java:7262"
        },
        {
          "method": "org.eclipse.swt.widgets.Shell.setVisible",
          "source": "Shell.java:1382"
        },
        {
          "method": "org.eclipse.swt.widgets.Shell.open",
          "source": "Shell.java:948"
        },
        {
          "method": "MySWT4.go",
          "source": "Unknown Source"
        },
        {
          "method": "MySWT4.main",
          "source": "Unknown Source"
        }
      ],
      "number": 0,
      "commentIndex": 0,
      "bugId": "108519",
      "duplicateId": "92803",
      "date": "2005-08-31T22:34:01+02:00",
      "product": "Platform",
      "component": "SWT",
      "severity": "normal"
    }
  ],
  "groupId": "92803",
  "bugId": "108519",
  "duplicateId": "92803",
  "date": "2005-08-31T22:34:01+02:00",
  "product": "Platform",
  "component": "SWT",
  "severity": "normal"
}