{
  "comments": [
    "Interface with a method returning a typed collection and taking two boolean args\nnext to each other (try playing with order) produces error message at bottom\nThis might be duplicate of bug 86903.  Compiler is from today\u0027s (9/1 9:30am\nPacific time) cvs checkout.\n\n/*\n * GenericsError.java\n *\n * Created on September 1, 2005, 9:36 AM\n *\n */\n\nimport java.util.Collection;\n\npublic interface GenericsError {\n  public Collection\u003cString\u003e test(\n      boolean arg1,\n      boolean arg2,\n      Object arg3) ;\n}\n\n\n/*\n * GenericsErrorImpl.java\n *\n * Created on September 1, 2005, 9:37 AM\n *\n */\n\nimport java.util.Collection;\n\npublic class GenericsErrorImpl implements GenericsError {\n\n  public Collection\u003cString\u003e test(\n      boolean arg1,\n      boolean arg2,\n      Object arg3)  { return null; }\n \n}\n\ntrouble in:\npublic class GenericsErrorImpl extends java.lang.Object implements GenericsError:\n  public void \u003cinit\u003e():\n                    ALOAD_0     // GenericsErrorImpl this   (line 19)\n                    INVOKESPECIAL java.lang.Object.\u003cinit\u003e ()V\n    constructor-execution(void GenericsErrorImpl.\u003cinit\u003e())\n    |               RETURN\n    constructor-execution(void GenericsErrorImpl.\u003cinit\u003e())\n  end public void \u003cinit\u003e()\n\n  public java.util.Collection test(boolean, boolean, Object):\n    method-execution(java.util.Collection GenericsErrorImpl.test(boolean,\nboolean, java.lang.Object))\n    |               ACONST_NULL   (line 25)\n    |               ARETURN\n    method-execution(java.util.Collection GenericsErrorImpl.test(boolean,\nboolean, java.lang.Object))\n  end public java.util.Collection test(boolean, boolean, Object)\n\nend public class GenericsErrorImpl\nABORT\n       \nException thrown from AspectJ DEVELOPMENT\n\nThis might be logged as a bug already -- find current bugs at\n  http://bugs.eclipse.org/bugs/buglist.cgi?product\u003dAspectJ\u0026component\u003dCompiler\n\nBugs for exceptions thrown have titles File:line from the top stack,\ne.g., \"SomeFile.java:243\"\n\nIf you don\u0027t find the exception below in a bug, please add a new bug\nat http://bugs.eclipse.org/bugs/enter_bug.cgi?product\u003dAspectJ\nTo make the bug a priority, please include a test program\nthat can reproduce this exception.\nBad type signature /\nBad type signature /\norg.aspectj.weaver.BCException: Bad type signature /\n        at org.aspectj.weaver.UnresolvedType.forSignature(UnresolvedType.java:425)\n        at\norg.aspectj.weaver.bcel.BcelGenericSignatureToTypeXConverter.typeSignature2TypeX(BcelGenericSignatureToTypeXConverter.java:202)\n        at\norg.aspectj.weaver.bcel.BcelGenericSignatureToTypeXConverter.typeSignature2TypeX(BcelGenericSignatureToTypeXConverter.java:189)\n        at\norg.aspectj.weaver.bcel.BcelMethod.unpackGenericSignature(BcelMethod.java:298)\n        at\norg.aspectj.weaver.bcel.BcelMethod.getGenericParameterTypes(BcelMethod.java:257)\n        at\norg.aspectj.weaver.ResolvedMemberImpl.matches(ResolvedMemberImpl.java:650)\n        at\norg.aspectj.weaver.ResolvedType.lookupResolvedMember(ResolvedType.java:350)\n        at\norg.aspectj.weaver.ResolvedMemberImpl.accumulateMembersMatching(ResolvedMemberImpl.java:212)\n        at\norg.aspectj.weaver.ResolvedMemberImpl.getJoinPointSignatures(ResolvedMemberImpl.java:166)\n        at org.aspectj.weaver.MemberImpl.getJoinPointSignatures(MemberImpl.java:917)\n        at\norg.aspectj.weaver.patterns.SignaturePattern.matches(SignaturePattern.java:150)\n        at\norg.aspectj.weaver.patterns.KindedPointcut.matchInternal(KindedPointcut.java:111)\n        at org.aspectj.weaver.patterns.Pointcut.match(Pointcut.java:151)\n        at\norg.aspectj.weaver.patterns.AndPointcut.matchInternal(AndPointcut.java:63)\n        at org.aspectj.weaver.patterns.Pointcut.match(Pointcut.java:151)\n        at\norg.aspectj.weaver.patterns.AndPointcut.matchInternal(AndPointcut.java:61)\n        at org.aspectj.weaver.patterns.Pointcut.match(Pointcut.java:151)\n        at\norg.aspectj.weaver.patterns.AndPointcut.matchInternal(AndPointcut.java:61)\n        at org.aspectj.weaver.patterns.Pointcut.match(Pointcut.java:151)\n        at org.aspectj.weaver.ShadowMunger.match(ShadowMunger.java:62)\n        at org.aspectj.weaver.Advice.match(Advice.java:101)\n        at org.aspectj.weaver.bcel.BcelClassWeaver.match(BcelClassWeaver.java:1727)\n        at org.aspectj.weaver.bcel.BcelClassWeaver.match(BcelClassWeaver.java:1360)\n        at org.aspectj.weaver.bcel.BcelClassWeaver.weave(BcelClassWeaver.java:381)\n        at org.aspectj.weaver.bcel.BcelClassWeaver.weave(BcelClassWeaver.java:96)\n        at org.aspectj.weaver.bcel.BcelWeaver.weave(BcelWeaver.java:1372)\n        at org.aspectj.weaver.bcel.BcelWeaver.weaveWithoutDump(BcelWeaver.java:1337)\n        at org.aspectj.weaver.bcel.BcelWeaver.weaveAndNotify(BcelWeaver.java:1114)\n        at org.aspectj.weaver.bcel.BcelWeaver.weave(BcelWeaver.java:1001)\n        at\norg.aspectj.ajdt.internal.compiler.AjCompilerAdapter.weave(AjCompilerAdapter.java:286)\n        at\norg.aspectj.ajdt.internal.compiler.AjCompilerAdapter.afterCompiling(AjCompilerAdapter.java:165)\n        at\norg.aspectj.ajdt.internal.compiler.CompilerAdapter.ajc$afterReturning$org_aspectj_ajdt_internal_compiler_CompilerAdapter$2$f9cc9ca0(CompilerAdapter.aj:70)\n        at\norg.aspectj.org.eclipse.jdt.internal.compiler.Compiler.compile(Compiler.java:367)\n        at\norg.aspectj.ajdt.internal.core.builder.AjBuildManager.performCompilation(AjBuildManager.java:728)\n        at\norg.aspectj.ajdt.internal.core.builder.AjBuildManager.doBuild(AjBuildManager.java:206)\n        at\norg.aspectj.ajdt.internal.core.builder.AjBuildManager.batchBuild(AjBuildManager.java:140)\n        at org.aspectj.ajdt.ajc.AjdtCommand.doCommand(AjdtCommand.java:112)\n        at org.aspectj.ajdt.ajc.AjdtCommand.runCommand(AjdtCommand.java:60)\n        at org.aspectj.tools.ajc.Main.run(Main.java:324)\n        at org.aspectj.tools.ajc.Main.runMain(Main.java:238)\n        at org.aspectj.tools.ajc.Main.main(Main.java:82)\n\n\n1 fail|abort",
    "thanks for the clear bug report, I\u0027ll look into this tomorrow.\nRgds, Adrian.",
    "fix for this has now been committed into tree, will be available from AJ\ndownloads page in the next published build.\n\n"
  ],
  "commentCreationDates": [
    "2005-09-01T19:25:41+02:00",
    "2005-09-01T20:22:29+02:00",
    "2005-09-02T11:37:03+02:00"
  ],
  "traces": [
    {
      "exceptionType": "org.aspectj.weaver.BCException",
      "message": "Bad type signature /",
      "elements": [
        {
          "method": "org.aspectj.weaver.UnresolvedType.forSignature",
          "source": "UnresolvedType.java:425"
        },
        {
          "method": "org.aspectj.weaver.bcel.BcelGenericSignatureToTypeXConverter.typeSignature2TypeX",
          "source": "BcelGenericSignatureToTypeXConverter.java:202"
        },
        {
          "method": "org.aspectj.weaver.bcel.BcelGenericSignatureToTypeXConverter.typeSignature2TypeX",
          "source": "BcelGenericSignatureToTypeXConverter.java:189"
        },
        {
          "method": "org.aspectj.weaver.bcel.BcelMethod.unpackGenericSignature",
          "source": "BcelMethod.java:298"
        },
        {
          "method": "org.aspectj.weaver.bcel.BcelMethod.getGenericParameterTypes",
          "source": "BcelMethod.java:257"
        },
        {
          "method": "org.aspectj.weaver.ResolvedMemberImpl.matches",
          "source": "ResolvedMemberImpl.java:650"
        },
        {
          "method": "org.aspectj.weaver.ResolvedType.lookupResolvedMember",
          "source": "ResolvedType.java:350"
        },
        {
          "method": "org.aspectj.weaver.ResolvedMemberImpl.accumulateMembersMatching",
          "source": "ResolvedMemberImpl.java:212"
        },
        {
          "method": "org.aspectj.weaver.ResolvedMemberImpl.getJoinPointSignatures",
          "source": "ResolvedMemberImpl.java:166"
        },
        {
          "method": "org.aspectj.weaver.MemberImpl.getJoinPointSignatures",
          "source": "MemberImpl.java:917"
        },
        {
          "method": "org.aspectj.weaver.patterns.SignaturePattern.matches",
          "source": "SignaturePattern.java:150"
        },
        {
          "method": "org.aspectj.weaver.patterns.KindedPointcut.matchInternal",
          "source": "KindedPointcut.java:111"
        },
        {
          "method": "org.aspectj.weaver.patterns.Pointcut.match",
          "source": "Pointcut.java:151"
        },
        {
          "method": "org.aspectj.weaver.patterns.AndPointcut.matchInternal",
          "source": "AndPointcut.java:63"
        },
        {
          "method": "org.aspectj.weaver.patterns.Pointcut.match",
          "source": "Pointcut.java:151"
        },
        {
          "method": "org.aspectj.weaver.patterns.AndPointcut.matchInternal",
          "source": "AndPointcut.java:61"
        },
        {
          "method": "org.aspectj.weaver.patterns.Pointcut.match",
          "source": "Pointcut.java:151"
        },
        {
          "method": "org.aspectj.weaver.patterns.AndPointcut.matchInternal",
          "source": "AndPointcut.java:61"
        },
        {
          "method": "org.aspectj.weaver.patterns.Pointcut.match",
          "source": "Pointcut.java:151"
        },
        {
          "method": "org.aspectj.weaver.ShadowMunger.match",
          "source": "ShadowMunger.java:62"
        },
        {
          "method": "org.aspectj.weaver.Advice.match",
          "source": "Advice.java:101"
        },
        {
          "method": "org.aspectj.weaver.bcel.BcelClassWeaver.match",
          "source": "BcelClassWeaver.java:1727"
        },
        {
          "method": "org.aspectj.weaver.bcel.BcelClassWeaver.match",
          "source": "BcelClassWeaver.java:1360"
        },
        {
          "method": "org.aspectj.weaver.bcel.BcelClassWeaver.weave",
          "source": "BcelClassWeaver.java:381"
        },
        {
          "method": "org.aspectj.weaver.bcel.BcelClassWeaver.weave",
          "source": "BcelClassWeaver.java:96"
        },
        {
          "method": "org.aspectj.weaver.bcel.BcelWeaver.weave",
          "source": "BcelWeaver.java:1372"
        },
        {
          "method": "org.aspectj.weaver.bcel.BcelWeaver.weaveWithoutDump",
          "source": "BcelWeaver.java:1337"
        },
        {
          "method": "org.aspectj.weaver.bcel.BcelWeaver.weaveAndNotify",
          "source": "BcelWeaver.java:1114"
        },
        {
          "method": "org.aspectj.weaver.bcel.BcelWeaver.weave",
          "source": "BcelWeaver.java:1001"
        },
        {
          "method": "org.aspectj.ajdt.internal.compiler.AjCompilerAdapter.weave",
          "source": "AjCompilerAdapter.java:286"
        },
        {
          "method": "org.aspectj.ajdt.internal.compiler.AjCompilerAdapter.afterCompiling",
          "source": "AjCompilerAdapter.java:165"
        },
        {
          "method": "org.aspectj.ajdt.internal.compiler.CompilerAdapter.ajc$afterReturning$org_aspectj_ajdt_internal_compiler_CompilerAdapter$2$f9cc9ca0",
          "source": "CompilerAdapter.aj:70"
        },
        {
          "method": "org.aspectj.org.eclipse.jdt.internal.compiler.Compiler.compile",
          "source": "Compiler.java:367"
        },
        {
          "method": "org.aspectj.ajdt.internal.core.builder.AjBuildManager.performCompilation",
          "source": "AjBuildManager.java:728"
        },
        {
          "method": "org.aspectj.ajdt.internal.core.builder.AjBuildManager.doBuild",
          "source": "AjBuildManager.java:206"
        },
        {
          "method": "org.aspectj.ajdt.internal.core.builder.AjBuildManager.batchBuild",
          "source": "AjBuildManager.java:140"
        },
        {
          "method": "org.aspectj.ajdt.ajc.AjdtCommand.doCommand",
          "source": "AjdtCommand.java:112"
        },
        {
          "method": "org.aspectj.ajdt.ajc.AjdtCommand.runCommand",
          "source": "AjdtCommand.java:60"
        },
        {
          "method": "org.aspectj.tools.ajc.Main.run",
          "source": "Main.java:324"
        },
        {
          "method": "org.aspectj.tools.ajc.Main.runMain",
          "source": "Main.java:238"
        },
        {
          "method": "org.aspectj.tools.ajc.Main.main",
          "source": "Main.java:82"
        }
      ],
      "number": 0,
      "commentIndex": 0,
      "bugId": "108602",
      "date": "2005-09-01T19:25:41+02:00",
      "product": "AspectJ",
      "component": "Compiler",
      "severity": "normal"
    }
  ],
  "groupId": "108602",
  "bugId": "108602",
  "date": "2005-09-01T19:25:41+02:00",
  "product": "AspectJ",
  "component": "Compiler",
  "severity": "normal"
}