{
  "comments": [
    "The following is a valid AspectJ program, that should compile and run without \ninfinite recursion. It does so with AspectJ 1.2.1. AspectJ 1.5.0 Development \n(but not M3a) chokes on it.\n\nSample Code:\naspect BadAdvice {\n    after(Object controller) returning (Object foo): \n      cflow(adviceexecution() \u0026\u0026 args(controller, ..) \u0026\u0026 this(BadAdvice)) \u0026\u0026 \ncall(Bar+.new(..)) {\n    }    \n    Object around(Object controller) : call(* whoKnows()) \u0026\u0026 target(controller) \n{\n        return new Bar();\n    }\n    public static void main(String args[]) {\n        (new Bar()).whoKnows();\n    }\n}\n\nclass Bar {\n    void whoKnows() {}\n}\n\nNow look at the horrid output:\nC:\\devel\\scratch\\recurse\u003eajc BadAdvice.aj\ntrouble in:\npublic class BadAdvice extends java.lang.Object:\n  private static Throwable ajc$initFailureCause\n  public static final BadAdvice ajc$perSingletonInstance\n  public static final org.aspectj.runtime.internal.CFlowStack ajc$cflowStack$0\n  static void \u003cclinit\u003e():\n                    INVOKESTATIC BadAdvice.ajc$preClinit ()V\n    staticinitialization(void BadAdvice.\u003cclinit\u003e())\n    | catch java.lang.Throwable -\u003e E0\n    | |             INVOKESTATIC BadAdvice.ajc$postClinit ()V   (line 1)\n    | catch java.lang.Throwable -\u003e E0\n    |               GOTO L0\n    |           E0: ASTORE_0\n    |               ALOAD_0\n    |               PUTSTATIC BadAdvice.ajc$initFailureCause Ljava/lang/Throwabl\ne;\n    |           L0: RETURN\n    staticinitialization(void BadAdvice.\u003cclinit\u003e())\n  end static void \u003cclinit\u003e()\n\n  void \u003cinit\u003e():\n                    ALOAD_0     // BadAdvice this   (line 1)\n                    INVOKESPECIAL java.lang.Object.\u003cinit\u003e ()V\n    constructor-execution(void BadAdvice.\u003cinit\u003e())\n    |               RETURN\n    constructor-execution(void BadAdvice.\u003cinit\u003e())\n  end void \u003cinit\u003e()\n\n  public void ajc$afterReturning$BadAdvice$1$97dc015a(Object, Object)    AdviceA\nttribute(afterReturning, (cflow((execution(* *) \u0026\u0026 (args(BindingTypePattern(java\n.lang.Object, 0), ..) \u0026\u0026 this(BadAdvice)))) \u0026\u0026 call(Bar+.new(..))), 1, 24)\n:\n                    ALOAD_1\n                    ASTORE_3\n                    ALOAD_2\n                    ASTORE 4\n    advice-execution(void BadAdvice.ajc$afterReturning$BadAdvice$1$97dc015a(java\n.lang.Object, java.lang.Object))\n    |               BIPUSH 1\n    |               ANEWARRAY java.lang.Object\n    |               ASTORE 6\n    |               ALOAD 6\n    |               BIPUSH 0\n    |               ALOAD_3\n    |               AASTORE\n    |               GETSTATIC BadAdvice.ajc$cflowStack$0 Lorg/aspectj/runtime/in\nternal/CFlowStack;\n    |               ALOAD 6\n    |               INVOKEVIRTUAL org.aspectj.runtime.internal.CFlowStack.push (\n[Ljava/lang/Object;)V\n    | catch java.lang.Throwable -\u003e E0\n    | |             GOTO L0   (line 4)\n    | catch java.lang.Throwable -\u003e E0\n    |           E0: ASTORE 7\n    |               GETSTATIC BadAdvice.ajc$cflowStack$0 Lorg/aspectj/runtime/in\nternal/CFlowStack;\n    |               INVOKEVIRTUAL org.aspectj.runtime.internal.CFlowStack.pop ()\nV\n    |               ALOAD 7\n    |               ATHROW\n    |           L0: GETSTATIC BadAdvice.ajc$cflowStack$0 Lorg/aspectj/runtime/in\nternal/CFlowStack;\n    |               INVOKEVIRTUAL org.aspectj.runtime.internal.CFlowStack.pop ()\nV\n    |               RETURN\n    advice-execution(void BadAdvice.ajc$afterReturning$BadAdvice$1$97dc015a(java\n.lang.Object, java.lang.Object))\n  end public void ajc$afterReturning$BadAdvice$1$97dc015a(Object, Object)\n\n  public Object ajc$around$BadAdvice$2$ef382b2d(Object, org.aspectj.runtime.inte\nrnal.AroundClosure)    AdviceAttribute(around, (call(* whoKnows()) \u0026\u0026 target(Bin\ndingTypePattern(java.lang.Object, 0))), 1, 196)\n:\n    advice-execution(java.lang.Object BadAdvice.ajc$around$BadAdvice$2$ef382b2d(\njava.lang.Object, org.aspectj.runtime.internal.AroundClosure))\n    | constructor-call(void Bar.\u003cinit\u003e())\n    | |             NEW Bar\n    | |             DUP\n    | |             INVOKESPECIAL Bar.\u003cinit\u003e ()V   (line 6)\n    | |             DUP\n    | |             ASTORE_3\n    | |             GETSTATIC BadAdvice.ajc$cflowStack$0 Lorg/aspectj/runtime/in\nternal/CFlowStack;\n    | |             INVOKEVIRTUAL org.aspectj.runtime.internal.CFlowStack.isVali\nd ()Z\n    | |             IFEQ L0\n    | |             INVOKESTATIC BadAdvice.aspectOf ()LBadAdvice;\n    | |             GETSTATIC BadAdvice.ajc$cflowStack$0 Lorg/aspectj/runtime/in\nternal/CFlowStack;\n    | |             BIPUSH 0\n    | |             INVOKEVIRTUAL org.aspectj.runtime.internal.CFlowStack.get (I\n)Ljava/lang/Object;\n    | |             ALOAD_3\n    | |             INVOKEVIRTUAL BadAdvice.ajc$afterReturning$BadAdvice$1$97dc0\n15a (Ljava/lang/Object;Ljava/lang/Object;)V\n    | |         L0: NOP\n    | constructor-call(void Bar.\u003cinit\u003e())\n    |               ARETURN\n    advice-execution(java.lang.Object BadAdvice.ajc$around$BadAdvice$2$ef382b2d(\njava.lang.Object, org.aspectj.runtime.internal.AroundClosure))\n  end public Object ajc$around$BadAdvice$2$ef382b2d(Object, org.aspectj.runtime.\ninternal.AroundClosure)\n\n  static Object ajc$around$BadAdvice$2$ef382b2dproceed(Object, org.aspectj.runti\nme.internal.AroundClosure) throws java.lang.Throwable    org.aspectj.weaver.AjAt\ntribute$AjSynthetic@3feb61\n:\n                    ALOAD_1\n                    ICONST_1\n                    ANEWARRAY java.lang.Object\n                    DUP\n                    ICONST_0\n                    ALOAD_0     // BadAdvice this\n                    AASTORE\n                    INVOKEVIRTUAL org.aspectj.runtime.internal.AroundClosure.run\n ([Ljava/lang/Object;)Ljava/lang/Object;\n                    CHECKCAST java.lang.Object\n                    ARETURN\n  end static Object ajc$around$BadAdvice$2$ef382b2dproceed(Object, org.aspectj.r\nuntime.internal.AroundClosure) throws java.lang.Throwable\n\n  public static BadAdvice aspectOf()    org.aspectj.weaver.AjAttribute$AjSynthet\nic@3ff616\n:\n                    GETSTATIC BadAdvice.ajc$perSingletonInstance LBadAdvice;\n                    IFNONNULL L0\n                    NEW org.aspectj.lang.NoAspectBoundException\n                    DUP\n                    LDC \"BadAdvice\"\n                    GETSTATIC BadAdvice.ajc$initFailureCause Ljava/lang/Throwabl\ne;\n                    INVOKESPECIAL org.aspectj.lang.NoAspectBoundException.\u003cinit\u003e\n (Ljava/lang/String;Ljava/lang/Throwable;)V\n                    ATHROW\n                L0: GETSTATIC BadAdvice.ajc$perSingletonInstance LBadAdvice;\n                    ARETURN\n  end public static BadAdvice aspectOf()\n\n  public static boolean hasAspect()    org.aspectj.weaver.AjAttribute$AjSyntheti\nc@400021\n:\n                    GETSTATIC BadAdvice.ajc$perSingletonInstance LBadAdvice;\n                    IFNULL L0\n                    ICONST_1\n                    IRETURN\n                L0: ICONST_0\n                    IRETURN\n  end public static boolean hasAspect()\n\n  private static void ajc$postClinit()    org.aspectj.weaver.AjAttribute$AjSynth\netic@400662\n:\n                    NEW BadAdvice\n                    DUP\n                    INVOKESPECIAL BadAdvice.\u003cinit\u003e ()V\n                    PUTSTATIC BadAdvice.ajc$perSingletonInstance LBadAdvice;\n                    RETURN\n  end private static void ajc$postClinit()\n\n  static void ajc$preClinit():\n                    NEW org.aspectj.runtime.internal.CFlowStack\n                    DUP\n                    INVOKESPECIAL org.aspectj.runtime.internal.CFlowStack.\u003cinit\u003e\n ()V\n                    PUTSTATIC BadAdvice.ajc$cflowStack$0 Lorg/aspectj/runtime/in\nternal/CFlowStack;\n                    RETURN\n  end static void ajc$preClinit()\nend public class BadAdvice\njava.lang.NullPointerException\n        at org.aspectj.weaver.bcel.BcelVar.appendConvertableArrayStore(BcelVar.j\nava:96)\n        at org.aspectj.weaver.bcel.BcelShadow.weaveCflowEntry(BcelShadow.java:18\n36)\n        at org.aspectj.weaver.bcel.BcelAdvice.implementOn(BcelAdvice.java:200)\n        at org.aspectj.weaver.Shadow.implementMungers(Shadow.java:511)\n        at org.aspectj.weaver.Shadow.implement(Shadow.java:388)\n        at org.aspectj.weaver.bcel.BcelClassWeaver.implement(BcelClassWeaver.jav\na:1757)\n        at org.aspectj.weaver.bcel.BcelClassWeaver.weave(BcelClassWeaver.java:39\n3)\n        at org.aspectj.weaver.bcel.BcelClassWeaver.weave(BcelClassWeaver.java:96\n)\n        at org.aspectj.weaver.bcel.BcelWeaver.weave(BcelWeaver.java:1415)\n        at org.aspectj.weaver.bcel.BcelWeaver.weaveWithoutDump(BcelWeaver.java:1\n380)\n        at org.aspectj.weaver.bcel.BcelWeaver.weaveAndNotify(BcelWeaver.java:115\n7)\n        at org.aspectj.weaver.bcel.BcelWeaver.weave(BcelWeaver.java:989)\n        at org.aspectj.ajdt.internal.compiler.AjCompilerAdapter.weave(AjCompiler\nAdapter.java:286)\n        at org.aspectj.ajdt.internal.compiler.AjCompilerAdapter.afterCompiling(A\njCompilerAdapter.java:165)\n        at org.aspectj.ajdt.internal.compiler.CompilerAdapter.ajc$afterReturning\n$org_aspectj_ajdt_internal_compiler_CompilerAdapter$2$f9cc9ca0(CompilerAdapter.a\nj:70)\n        at org.aspectj.org.eclipse.jdt.internal.compiler.Compiler.compile(Compil\ner.java:367)\n        at org.aspectj.ajdt.internal.core.builder.AjBuildManager.performCompilat\nion(AjBuildManager.java:728)\n        at org.aspectj.ajdt.internal.core.builder.AjBuildManager.doBuild(AjBuild\nManager.java:206)\n        at org.aspectj.ajdt.internal.core.builder.AjBuildManager.batchBuild(AjBu\nildManager.java:140)\n        at org.aspectj.ajdt.ajc.AjdtCommand.doCommand(AjdtCommand.java:112)\n        at org.aspectj.ajdt.ajc.AjdtCommand.runCommand(AjdtCommand.java:60)\n        at org.aspectj.tools.ajc.Main.run(Main.java:324)\n        at org.aspectj.tools.ajc.Main.runMain(Main.java:238)\n        at org.aspectj.tools.ajc.Main.main(Main.java:82)\nABORT\n\nException thrown from AspectJ DEVELOPMENT\n\nThis might be logged as a bug already -- find current bugs at\n  http://bugs.eclipse.org/bugs/buglist.cgi?product\u003dAspectJ\u0026component\u003dCompiler\n\nBugs for exceptions thrown have titles File:line from the top stack,\ne.g., \"SomeFile.java:243\"\n\nIf you don\u0027t find the exception below in a bug, please add a new bug\nat http://bugs.eclipse.org/bugs/enter_bug.cgi?product\u003dAspectJ\nTo make the bug a priority, please include a test program\nthat can reproduce this exception.\nnull\njava.lang.NullPointerException\n        at org.aspectj.weaver.bcel.BcelVar.appendConvertableArrayStore(BcelVar.j\nava:96)\n        at org.aspectj.weaver.bcel.BcelShadow.weaveCflowEntry(BcelShadow.java:18\n36)\n        at org.aspectj.weaver.bcel.BcelAdvice.implementOn(BcelAdvice.java:200)\n        at org.aspectj.weaver.Shadow.implementMungers(Shadow.java:511)\n        at org.aspectj.weaver.Shadow.implement(Shadow.java:388)\n        at org.aspectj.weaver.bcel.BcelClassWeaver.implement(BcelClassWeaver.jav\na:1757)\n        at org.aspectj.weaver.bcel.BcelClassWeaver.weave(BcelClassWeaver.java:39\n3)\n        at org.aspectj.weaver.bcel.BcelClassWeaver.weave(BcelClassWeaver.java:96\n)\n        at org.aspectj.weaver.bcel.BcelWeaver.weave(BcelWeaver.java:1415)\n        at org.aspectj.weaver.bcel.BcelWeaver.weaveWithoutDump(BcelWeaver.java:1\n380)\n        at org.aspectj.weaver.bcel.BcelWeaver.weaveAndNotify(BcelWeaver.java:115\n7)\n        at org.aspectj.weaver.bcel.BcelWeaver.weave(BcelWeaver.java:989)\n        at org.aspectj.ajdt.internal.compiler.AjCompilerAdapter.weave(AjCompiler\nAdapter.java:286)\n        at org.aspectj.ajdt.internal.compiler.AjCompilerAdapter.afterCompiling(A\njCompilerAdapter.java:165)\n        at org.aspectj.ajdt.internal.compiler.CompilerAdapter.ajc$afterReturning\n$org_aspectj_ajdt_internal_compiler_CompilerAdapter$2$f9cc9ca0(CompilerAdapter.a\nj:70)\n        at org.aspectj.org.eclipse.jdt.internal.compiler.Compiler.compile(Compil\ner.java:367)\n        at org.aspectj.ajdt.internal.core.builder.AjBuildManager.performCompilat\nion(AjBuildManager.java:728)\n        at org.aspectj.ajdt.internal.core.builder.AjBuildManager.doBuild(AjBuild\nManager.java:206)\n        at org.aspectj.ajdt.internal.core.builder.AjBuildManager.batchBuild(AjBu\nildManager.java:140)\n        at org.aspectj.ajdt.ajc.AjdtCommand.doCommand(AjdtCommand.java:112)\n        at org.aspectj.ajdt.ajc.AjdtCommand.runCommand(AjdtCommand.java:60)\n        at org.aspectj.tools.ajc.Main.run(Main.java:324)\n        at org.aspectj.tools.ajc.Main.runMain(Main.java:238)\n        at org.aspectj.tools.ajc.Main.main(Main.java:82)\n\n\n1 fail|abort\n\nNote: there isn\u0027t ever a call to construct a Bar in the first advice, so it \nshouldn\u0027t actually be self-advising at runtime, and even though the advice does \nitself match the cflow expression, it should just push an entry on the cflow \nstack.\n\nBy the way, this would be a great place to have a name for advice, so I could \nexclude this one advice from advising itself.",
    "ugh. I\u0027m not looking forward to diagnosing this one! At least you\u0027ve very\nhelpfully been able to narrow it down to one of the 33 bug \"fixes\" I\u0027ve put in\nover the last week. I\u0027m suspicious of the changes made for bug 59196, will look\ninto this later on today.",
    "ok, I can confirm that this bug is related to the fix for 59196 - it only occurs\nwhen the cflow uses args.",
    "found it! the extra \"..\" in the args pattern was also needed to reproduce the\nbug, which was due to an inconsistency in determining the length of the args\narray to be used for matching when calculating the number of positions that \"..\"\nshould eat. We were ignoring synthetic args everywhere but there. So the actual\nbug was triggered by args binding at least one formal, at a join point with\nsynthetic args, with \"..\" used in the type pattern.\n\nJust running all the suite and then I\u0027ll commit the fix.",
    "Fantastic; thank you! Glad you were able to find and fix it so quickly! The \nrevised AspectJ version builds my code correctly.",
    "fix available and verified..."
  ],
  "commentCreationDates": [
    "2005-09-06T09:18:39+02:00",
    "2005-09-06T10:13:02+02:00",
    "2005-09-06T14:00:28+02:00",
    "2005-09-06T14:24:04+02:00",
    "2005-09-06T19:55:30+02:00",
    "2005-09-08T22:27:28+02:00"
  ],
  "traces": [
    {
      "exceptionType": "java.lang.NullPointerException",
      "elements": [
        {
          "method": "org.aspectj.weaver.bcel.BcelVar.appendConvertableArrayStore",
          "source": "BcelVar.j ava:96"
        },
        {
          "method": "org.aspectj.weaver.bcel.BcelShadow.weaveCflowEntry",
          "source": "BcelShadow.java:18 36"
        },
        {
          "method": "org.aspectj.weaver.bcel.BcelAdvice.implementOn",
          "source": "BcelAdvice.java:200"
        },
        {
          "method": "org.aspectj.weaver.Shadow.implementMungers",
          "source": "Shadow.java:511"
        },
        {
          "method": "org.aspectj.weaver.Shadow.implement",
          "source": "Shadow.java:388"
        },
        {
          "method": "org.aspectj.weaver.bcel.BcelClassWeaver.implement",
          "source": "BcelClassWeaver.jav a:1757"
        },
        {
          "method": "org.aspectj.weaver.bcel.BcelClassWeaver.weave",
          "source": "BcelClassWeaver.java:39 3"
        },
        {
          "method": "org.aspectj.weaver.bcel.BcelClassWeaver.weave",
          "source": "BcelClassWeaver.java:96 "
        },
        {
          "method": "org.aspectj.weaver.bcel.BcelWeaver.weave",
          "source": "BcelWeaver.java:1415"
        },
        {
          "method": "org.aspectj.weaver.bcel.BcelWeaver.weaveWithoutDump",
          "source": "BcelWeaver.java:1 380"
        },
        {
          "method": "org.aspectj.weaver.bcel.BcelWeaver.weaveAndNotify",
          "source": "BcelWeaver.java:115 7"
        },
        {
          "method": "org.aspectj.weaver.bcel.BcelWeaver.weave",
          "source": "BcelWeaver.java:989"
        },
        {
          "method": "org.aspectj.ajdt.internal.compiler.AjCompilerAdapter.weave",
          "source": "AjCompiler Adapter.java:286"
        },
        {
          "method": "org.aspectj.ajdt.internal.compiler.AjCompilerAdapter.afterCompiling",
          "source": "A jCompilerAdapter.java:165"
        },
        {
          "method": "org.aspectj.ajdt.internal.compiler.CompilerAdapter.ajc$afterReturning$org_aspectj_ajdt_internal_compiler_CompilerAdapter$2$f9cc9ca0",
          "source": "CompilerAdapter.a j:70"
        },
        {
          "method": "org.aspectj.org.eclipse.jdt.internal.compiler.Compiler.compile",
          "source": "Compil er.java:367"
        },
        {
          "method": "org.aspectj.ajdt.internal.core.builder.AjBuildManager.performCompilation",
          "source": "AjBuildManager.java:728"
        },
        {
          "method": "org.aspectj.ajdt.internal.core.builder.AjBuildManager.doBuild",
          "source": "AjBuild Manager.java:206"
        },
        {
          "method": "org.aspectj.ajdt.internal.core.builder.AjBuildManager.batchBuild",
          "source": "AjBu ildManager.java:140"
        },
        {
          "method": "org.aspectj.ajdt.ajc.AjdtCommand.doCommand",
          "source": "AjdtCommand.java:112"
        },
        {
          "method": "org.aspectj.ajdt.ajc.AjdtCommand.runCommand",
          "source": "AjdtCommand.java:60"
        },
        {
          "method": "org.aspectj.tools.ajc.Main.run",
          "source": "Main.java:324"
        },
        {
          "method": "org.aspectj.tools.ajc.Main.runMain",
          "source": "Main.java:238"
        },
        {
          "method": "org.aspectj.tools.ajc.Main.main",
          "source": "Main.java:82"
        }
      ],
      "number": 0,
      "commentIndex": 0,
      "bugId": "108816",
      "date": "2005-09-06T09:18:39+02:00",
      "product": "AspectJ",
      "component": "Compiler",
      "severity": "major"
    },
    {
      "exceptionType": "java.lang.NullPointerException",
      "elements": [
        {
          "method": "org.aspectj.weaver.bcel.BcelVar.appendConvertableArrayStore",
          "source": "BcelVar.j ava:96"
        },
        {
          "method": "org.aspectj.weaver.bcel.BcelShadow.weaveCflowEntry",
          "source": "BcelShadow.java:18 36"
        },
        {
          "method": "org.aspectj.weaver.bcel.BcelAdvice.implementOn",
          "source": "BcelAdvice.java:200"
        },
        {
          "method": "org.aspectj.weaver.Shadow.implementMungers",
          "source": "Shadow.java:511"
        },
        {
          "method": "org.aspectj.weaver.Shadow.implement",
          "source": "Shadow.java:388"
        },
        {
          "method": "org.aspectj.weaver.bcel.BcelClassWeaver.implement",
          "source": "BcelClassWeaver.jav a:1757"
        },
        {
          "method": "org.aspectj.weaver.bcel.BcelClassWeaver.weave",
          "source": "BcelClassWeaver.java:39 3"
        },
        {
          "method": "org.aspectj.weaver.bcel.BcelClassWeaver.weave",
          "source": "BcelClassWeaver.java:96 "
        },
        {
          "method": "org.aspectj.weaver.bcel.BcelWeaver.weave",
          "source": "BcelWeaver.java:1415"
        },
        {
          "method": "org.aspectj.weaver.bcel.BcelWeaver.weaveWithoutDump",
          "source": "BcelWeaver.java:1 380"
        },
        {
          "method": "org.aspectj.weaver.bcel.BcelWeaver.weaveAndNotify",
          "source": "BcelWeaver.java:115 7"
        },
        {
          "method": "org.aspectj.weaver.bcel.BcelWeaver.weave",
          "source": "BcelWeaver.java:989"
        },
        {
          "method": "org.aspectj.ajdt.internal.compiler.AjCompilerAdapter.weave",
          "source": "AjCompiler Adapter.java:286"
        },
        {
          "method": "org.aspectj.ajdt.internal.compiler.AjCompilerAdapter.afterCompiling",
          "source": "A jCompilerAdapter.java:165"
        },
        {
          "method": "org.aspectj.ajdt.internal.compiler.CompilerAdapter.ajc$afterReturning$org_aspectj_ajdt_internal_compiler_CompilerAdapter$2$f9cc9ca0",
          "source": "CompilerAdapter.a j:70"
        },
        {
          "method": "org.aspectj.org.eclipse.jdt.internal.compiler.Compiler.compile",
          "source": "Compil er.java:367"
        },
        {
          "method": "org.aspectj.ajdt.internal.core.builder.AjBuildManager.performCompilation",
          "source": "AjBuildManager.java:728"
        },
        {
          "method": "org.aspectj.ajdt.internal.core.builder.AjBuildManager.doBuild",
          "source": "AjBuild Manager.java:206"
        },
        {
          "method": "org.aspectj.ajdt.internal.core.builder.AjBuildManager.batchBuild",
          "source": "AjBu ildManager.java:140"
        },
        {
          "method": "org.aspectj.ajdt.ajc.AjdtCommand.doCommand",
          "source": "AjdtCommand.java:112"
        },
        {
          "method": "org.aspectj.ajdt.ajc.AjdtCommand.runCommand",
          "source": "AjdtCommand.java:60"
        },
        {
          "method": "org.aspectj.tools.ajc.Main.run",
          "source": "Main.java:324"
        },
        {
          "method": "org.aspectj.tools.ajc.Main.runMain",
          "source": "Main.java:238"
        },
        {
          "method": "org.aspectj.tools.ajc.Main.main",
          "source": "Main.java:82"
        }
      ],
      "number": 1,
      "commentIndex": 0,
      "bugId": "108816",
      "date": "2005-09-06T09:18:39+02:00",
      "product": "AspectJ",
      "component": "Compiler",
      "severity": "major"
    }
  ],
  "groupId": "108816",
  "bugId": "108816",
  "date": "2005-09-06T09:18:39+02:00",
  "product": "AspectJ",
  "component": "Compiler",
  "severity": "major"
}