{
  "comments": [
    "version: 2002\n\n2 problems when I use resolveBinding() on the generated AST for the following code :\n\npublic class Foo{\n  int bar() throws Throwable {\n    return Foo.x;\n  }\n  static int x;\n}\n\nthe tree for \"return Foo.x;\" is :\n\nReturnStatement\n +-QualifiedName\n    +-SimpleName: \"Foo\"\n    +-SimpleName: \"x\"\n\n1- resolveBinding() on SimpleName \"Foo\" returns a IVariableBinding object, I\nexpected a ITypeBinding\n\n2- resolveBinding() on SimpleName \"x\" throws a NullPointerException :\n\njava.lang.NullPointerException\n at\norg.eclipse.jdt.core.dom.DefaultBindingResolver.resolveNameForNameReference(DefaultBindingResolver.java:222)\n at\norg.eclipse.jdt.core.dom.DefaultBindingResolver.resolveName(DefaultBindingResolver.java:97)\n at org.eclipse.jdt.core.dom.Name.resolveBinding(Name.java:75)",
    "Already fixed in latest.\nClosed."
  ],
  "commentCreationDates": [
    "2002-03-06T23:18:12+01:00",
    "2002-03-07T16:31:00+01:00"
  ],
  "traces": [
    {
      "exceptionType": "java.lang.NullPointerException",
      "elements": [
        {
          "method": "org.eclipse.jdt.core.dom.DefaultBindingResolver.resolveNameForNameReference",
          "source": "DefaultBindingResolver.java:222"
        },
        {
          "method": "org.eclipse.jdt.core.dom.DefaultBindingResolver.resolveName",
          "source": "DefaultBindingResolver.java:97"
        },
        {
          "method": "org.eclipse.jdt.core.dom.Name.resolveBinding",
          "source": "Name.java:75"
        }
      ],
      "number": 0,
      "commentIndex": 0,
      "bugId": "10913",
      "date": "2002-03-06T23:18:12+01:00",
      "product": "JDT",
      "component": "Core",
      "severity": "normal"
    }
  ],
  "groupId": "10913",
  "bugId": "10913",
  "date": "2002-03-06T23:18:12+01:00",
  "product": "JDT",
  "component": "Core",
  "severity": "normal"
}