{
  "comments": [
    "3.2 M1\n\nIf a failure happens while importing team project sets, the wizard dialog stays up.\n\nTo reproduce (on Windows), import a team project set once, open one file in of\nthe the projects just imported, and try importing again (confirming that you\nwant to overwrite the projects already imported).",
    "3.2 M5, Mac OS X 10.4.3\n\nI\u0027m also seeing this problem when importing a project set into a new workspace.  Loading the same project(s) manually via the CVS Repository works fine.\n\nMy projectSet.psf file:\n\u003d\u003d\u003d\u003d\u003d\u003d\u003d\u003d\u003d\u003d\u003d\u003d\u003d\u003d\u003d\u003d\u003d\u003d\u003d\u003d\u003d\u003d\u003d\u003d\n\n\u003c?xml version\u003d\"1.0\" encoding\u003d\"UTF-8\"?\u003e\n\u003cpsf version\u003d\"2.0\"\u003e\n\t\u003cprovider id\u003d\"org.eclipse.team.cvs.core.cvsnature\"\u003e\n\t\t\u003cproject reference\u003d\"1.0,:extssh:www.arsagilis.com:/cvs,Fitnesse/Fitnesse,Fitnesse\"/\u003e\n\t\u003c/provider\u003e\n\u003c/psf\u003e\n\nTo reproduce:\n\u003d\u003d\u003d\u003d\u003d\u003d\u003d\u003d\u003d\u003d\u003d\u003d\u003d\u003d\u003d\u003d\n1. Right click in Package Explorer -\u003e Import -\u003e Team -\u003e Team Project Set -\u003e Next -\u003e Browse to file above, leave working set checkbox uncheckd -\u003e C  Select the file above, then click next.  \n2. Enter CVS password when prompted.\n3. Wizard shows CVS server connection status, then returns to wizard screen.  \n4. No error messages are displayed, but a closed project folder appears in the Package Explorer.  Opening the project manually reveals an empty project with a  skeleton .project file.\n\nThe stack trace in .log:\n\u003d\u003d\u003d\u003d\u003d\u003d\u003d\u003d\u003d\u003d\u003d\u003d\u003d\u003d\u003d\u003d\u003d\u003d\u003d\u003d\u003d\u003d\u003d\u003d\u003d\n\n!ENTRY org.eclipse.ui 4 0 2006-02-21 15:34:50.858\n!MESSAGE Attempted to beginRule: R/, does not match outer scope rule: MultiRule[P/Fitnesse]\n!STACK 0\njava.lang.IllegalArgumentException: Attempted to beginRule: R/, does not match outer scope rule: MultiRule[P/Fitnesse]\n        at org.eclipse.core.runtime.Assert.isLegal(Assert.java:58)\n        at org.eclipse.core.internal.jobs.ThreadJob.illegalPush(ThreadJob.java:116)\n        at org.eclipse.core.internal.jobs.ThreadJob.push(ThreadJob.java:225)\n        at org.eclipse.core.internal.jobs.ImplicitJobs.begin(ImplicitJobs.java:58)\n        at org.eclipse.core.internal.jobs.JobManager.beginRule(JobManager.java:218)\n        at org.eclipse.core.internal.resources.WorkManager.checkIn(WorkManager.java:96)\n        at org.eclipse.core.internal.resources.Workspace.prepareOperation(Workspace.java:1681)\n        at org.eclipse.core.internal.resources.Project.open(Project.java:832)\n        at org.eclipse.core.internal.resources.Project.open(Project.java:890)\n        at org.eclipse.team.internal.ccvs.core.resources.EclipseFolder.mkdir(EclipseFolder.java:115)\n        at org.eclipse.team.internal.ccvs.core.client.ResponseHandler.createFolder(ResponseHandler.java:80)\n        at org.eclipse.team.internal.ccvs.core.client.StickyHandler.handle(StickyHandler.java:67)\n        at org.eclipse.team.internal.ccvs.core.client.Request.executeRequest(Request.java:218)\n        at org.eclipse.team.internal.ccvs.core.client.Command.doExecute(Command.java:404)\n        at org.eclipse.team.internal.ccvs.core.client.Checkout.doExecute(Checkout.java:159)\n        at org.eclipse.team.internal.ccvs.core.client.CheckoutWithOverwrite.doExecute(CheckoutWithOverwrite.java:52)\n        at org.eclipse.team.internal.ccvs.core.client.Command$1.run(Command.java:323)\n        at org.eclipse.team.internal.ccvs.core.resources.EclipseSynchronizer.run(EclipseSynchronizer.java:1450)\n        at org.eclipse.team.internal.ccvs.core.resources.EclipseResource$2.run(EclipseResource.java:260)\n        at org.eclipse.core.internal.resources.Workspace.run(Workspace.java:1733)\n        at org.eclipse.team.internal.ccvs.core.resources.EclipseResource.run(EclipseResource.java:257)\n        at org.eclipse.team.internal.ccvs.core.client.Command.execute(Command.java:335)\n        at org.eclipse.team.internal.ccvs.core.CVSProjectSetCapability$1.run(CVSProjectSetCapability.java:378)\n        at org.eclipse.core.internal.resources.Workspace.run(Workspace.java:1733)\n        at org.eclipse.team.internal.ccvs.core.CVSProjectSetCapability.checkout(CVSProjectSetCapability.java:406)\n        at org.eclipse.team.internal.ccvs.core.CVSProjectSetCapability.checkout(CVSProjectSetCapability.java:288)\n        at org.eclipse.team.internal.ccvs.core.CVSProjectSetCapability$LoadInfo.checkout(CVSProjectSetCapability.java:226)\n        at org.eclipse.team.internal.ccvs.core.CVSProjectSetCapability.checkout(CVSProjectSetCapability.java:167)\n        at org.eclipse.team.internal.ccvs.core.CVSProjectSetCapability.addToWorkspace(CVSProjectSetCapability.java:119)\n        at org.eclipse.team.internal.ui.ProjectSetImporter.importProjectSet(ProjectSetImporter.java:84)\n        at org.eclipse.team.internal.ui.wizards.ProjectSetImportWizard$1.execute(ProjectSetImportWizard.java:65)\n        at org.eclipse.ui.actions.WorkspaceModifyOperation$1.run(WorkspaceModifyOperation.java:100)\n        at org.eclipse.core.internal.resources.Workspace.run(Workspace.java:1733)\n        at org.eclipse.ui.actions.WorkspaceModifyOperation.run(WorkspaceModifyOperation.java:112)\n        at org.eclipse.jface.operation.ModalContext$ModalContextThread.run(ModalContext.java:113)",
    "I too have seen this problem with the M6 driver(eclipse.buildId\u003dI20060223-1656 with java.fullversion\u003dJ2RE 1.4.2 IBM J9 2.2 Windows XP x86-32 j9n142-20050609 (JIT enabled)).  Additionally, I see the same failure when I Team -\u003e Load Project Map.\n\nThis function worked fine on the M4 driver.  This should be a major regression\n\nMy Team Project Set file:\n------------------------\n\u003c?xml version\u003d\"1.0\" encoding\u003d\"UTF-8\"?\u003e\n\u003cpsf version\u003d\"2.0\"\u003e\n\t\u003cprovider id\u003d\"org.eclipse.team.cvs.core.cvsnature\"\u003e\n\t\t\u003cproject reference\u003d\"1.0,:pserver:eclectic.com:/cvsroot,com.eclectic.test,com.eclectic.test\"/\u003e\n\t\u003c/provider\u003e\n\u003c/psf\u003e\n\n\nStack trace from the Error Log\n------------------------------\njava.lang.IllegalArgumentException: Attempted to beginRule: R/, does not match outer scope rule: MultiRule[P/com.eclectic.test]\n\tat org.eclipse.core.runtime.Assert.isLegal(Assert.java:58)\n\tat org.eclipse.core.internal.jobs.ThreadJob.illegalPush(ThreadJob.java:116)\n\tat org.eclipse.core.internal.jobs.ThreadJob.push(ThreadJob.java:225)\n\tat org.eclipse.core.internal.jobs.ImplicitJobs.begin(ImplicitJobs.java:58)\n\tat org.eclipse.core.internal.jobs.JobManager.beginRule(JobManager.java:218)\n\tat org.eclipse.core.internal.resources.WorkManager.checkIn(WorkManager.java:96)\n\tat org.eclipse.core.internal.resources.Workspace.prepareOperation(Workspace.java:1681)\n\tat org.eclipse.core.internal.resources.Project.open(Project.java:832)\n\tat org.eclipse.core.internal.resources.Project.open(Project.java:890)\n\tat org.eclipse.team.internal.ccvs.core.resources.EclipseFolder.mkdir(EclipseFolder.java:115)\n\tat org.eclipse.team.internal.ccvs.core.client.ResponseHandler.createFolder(ResponseHandler.java:80)\n\tat org.eclipse.team.internal.ccvs.core.client.StickyHandler.handle(StickyHandler.java:67)\n\tat org.eclipse.team.internal.ccvs.core.client.Request.executeRequest(Request.java:218)\n\tat org.eclipse.team.internal.ccvs.core.client.Command.doExecute(Command.java:404)\n\tat org.eclipse.team.internal.ccvs.core.client.Checkout.doExecute(Checkout.java:159)\n\tat org.eclipse.team.internal.ccvs.core.client.CheckoutWithOverwrite.doExecute(CheckoutWithOverwrite.java:52)\n\tat org.eclipse.team.internal.ccvs.core.client.Command$1.run(Command.java:323)\n\tat org.eclipse.team.internal.ccvs.core.resources.EclipseSynchronizer.run(EclipseSynchronizer.java:1450)\n\tat org.eclipse.team.internal.ccvs.core.resources.EclipseResource$2.run(EclipseResource.java:260)\n\tat org.eclipse.core.internal.resources.Workspace.run(Workspace.java:1733)\n\tat org.eclipse.team.internal.ccvs.core.resources.EclipseResource.run(EclipseResource.java:257)\n\tat org.eclipse.team.internal.ccvs.core.client.Command.execute(Command.java:335)\n\tat org.eclipse.team.internal.ccvs.core.CVSProjectSetCapability$1.run(CVSProjectSetCapability.java:378)\n\tat org.eclipse.core.internal.resources.Workspace.run(Workspace.java:1733)\n\tat org.eclipse.team.internal.ccvs.core.CVSProjectSetCapability.checkout(CVSProjectSetCapability.java:406)\n\tat org.eclipse.team.internal.ccvs.core.CVSProjectSetCapability.checkout(CVSProjectSetCapability.java:288)\n\tat org.eclipse.team.internal.ccvs.core.CVSProjectSetCapability$LoadInfo.checkout(CVSProjectSetCapability.java:226)\n\tat org.eclipse.team.internal.ccvs.core.CVSProjectSetCapability.checkout(CVSProjectSetCapability.java:167)\n\tat org.eclipse.team.internal.ccvs.core.CVSProjectSetCapability.addToWorkspace(CVSProjectSetCapability.java:119)\n\tat org.eclipse.team.internal.ui.ProjectSetImporter.importProjectSet(ProjectSetImporter.java:84)\n\tat org.eclipse.team.internal.ui.wizards.ProjectSetImportWizard$1.execute(ProjectSetImportWizard.java:65)\n\tat org.eclipse.ui.actions.WorkspaceModifyOperation$1.run(WorkspaceModifyOperation.java:100)\n\tat org.eclipse.core.internal.resources.Workspace.run(Workspace.java:1733)\n\tat org.eclipse.ui.actions.WorkspaceModifyOperation.run(WorkspaceModifyOperation.java:112)\n\tat org.eclipse.jface.operation.ModalContext$ModalContextThread.run(ModalContext.java:113)\n",
    "The problem mentioned in comment 1 and comment 2 was a problem introduced in M5 that has been fixed (the fix will be available in M6)."
  ],
  "commentCreationDates": [
    "2005-09-09T23:07:50+02:00",
    "2006-02-21T22:50:22+01:00",
    "2006-03-17T09:01:38+01:00",
    "2006-03-17T13:59:03+01:00"
  ],
  "traces": [
    {
      "exceptionType": "java.lang.IllegalArgumentException",
      "message": "Attempted to beginRule: R/, does not match outer scope rule: MultiRule[P/Fitnesse]",
      "elements": [
        {
          "method": "org.eclipse.core.runtime.Assert.isLegal",
          "source": "Assert.java:58"
        },
        {
          "method": "org.eclipse.core.internal.jobs.ThreadJob.illegalPush",
          "source": "ThreadJob.java:116"
        },
        {
          "method": "org.eclipse.core.internal.jobs.ThreadJob.push",
          "source": "ThreadJob.java:225"
        },
        {
          "method": "org.eclipse.core.internal.jobs.ImplicitJobs.begin",
          "source": "ImplicitJobs.java:58"
        },
        {
          "method": "org.eclipse.core.internal.jobs.JobManager.beginRule",
          "source": "JobManager.java:218"
        },
        {
          "method": "org.eclipse.core.internal.resources.WorkManager.checkIn",
          "source": "WorkManager.java:96"
        },
        {
          "method": "org.eclipse.core.internal.resources.Workspace.prepareOperation",
          "source": "Workspace.java:1681"
        },
        {
          "method": "org.eclipse.core.internal.resources.Project.open",
          "source": "Project.java:832"
        },
        {
          "method": "org.eclipse.core.internal.resources.Project.open",
          "source": "Project.java:890"
        },
        {
          "method": "org.eclipse.team.internal.ccvs.core.resources.EclipseFolder.mkdir",
          "source": "EclipseFolder.java:115"
        },
        {
          "method": "org.eclipse.team.internal.ccvs.core.client.ResponseHandler.createFolder",
          "source": "ResponseHandler.java:80"
        },
        {
          "method": "org.eclipse.team.internal.ccvs.core.client.StickyHandler.handle",
          "source": "StickyHandler.java:67"
        },
        {
          "method": "org.eclipse.team.internal.ccvs.core.client.Request.executeRequest",
          "source": "Request.java:218"
        },
        {
          "method": "org.eclipse.team.internal.ccvs.core.client.Command.doExecute",
          "source": "Command.java:404"
        },
        {
          "method": "org.eclipse.team.internal.ccvs.core.client.Checkout.doExecute",
          "source": "Checkout.java:159"
        },
        {
          "method": "org.eclipse.team.internal.ccvs.core.client.CheckoutWithOverwrite.doExecute",
          "source": "CheckoutWithOverwrite.java:52"
        },
        {
          "method": "org.eclipse.team.internal.ccvs.core.client.Command$1.run",
          "source": "Command.java:323"
        },
        {
          "method": "org.eclipse.team.internal.ccvs.core.resources.EclipseSynchronizer.run",
          "source": "EclipseSynchronizer.java:1450"
        },
        {
          "method": "org.eclipse.team.internal.ccvs.core.resources.EclipseResource$2.run",
          "source": "EclipseResource.java:260"
        },
        {
          "method": "org.eclipse.core.internal.resources.Workspace.run",
          "source": "Workspace.java:1733"
        },
        {
          "method": "org.eclipse.team.internal.ccvs.core.resources.EclipseResource.run",
          "source": "EclipseResource.java:257"
        },
        {
          "method": "org.eclipse.team.internal.ccvs.core.client.Command.execute",
          "source": "Command.java:335"
        },
        {
          "method": "org.eclipse.team.internal.ccvs.core.CVSProjectSetCapability$1.run",
          "source": "CVSProjectSetCapability.java:378"
        },
        {
          "method": "org.eclipse.core.internal.resources.Workspace.run",
          "source": "Workspace.java:1733"
        },
        {
          "method": "org.eclipse.team.internal.ccvs.core.CVSProjectSetCapability.checkout",
          "source": "CVSProjectSetCapability.java:406"
        },
        {
          "method": "org.eclipse.team.internal.ccvs.core.CVSProjectSetCapability.checkout",
          "source": "CVSProjectSetCapability.java:288"
        },
        {
          "method": "org.eclipse.team.internal.ccvs.core.CVSProjectSetCapability$LoadInfo.checkout",
          "source": "CVSProjectSetCapability.java:226"
        },
        {
          "method": "org.eclipse.team.internal.ccvs.core.CVSProjectSetCapability.checkout",
          "source": "CVSProjectSetCapability.java:167"
        },
        {
          "method": "org.eclipse.team.internal.ccvs.core.CVSProjectSetCapability.addToWorkspace",
          "source": "CVSProjectSetCapability.java:119"
        },
        {
          "method": "org.eclipse.team.internal.ui.ProjectSetImporter.importProjectSet",
          "source": "ProjectSetImporter.java:84"
        },
        {
          "method": "org.eclipse.team.internal.ui.wizards.ProjectSetImportWizard$1.execute",
          "source": "ProjectSetImportWizard.java:65"
        },
        {
          "method": "org.eclipse.ui.actions.WorkspaceModifyOperation$1.run",
          "source": "WorkspaceModifyOperation.java:100"
        },
        {
          "method": "org.eclipse.core.internal.resources.Workspace.run",
          "source": "Workspace.java:1733"
        },
        {
          "method": "org.eclipse.ui.actions.WorkspaceModifyOperation.run",
          "source": "WorkspaceModifyOperation.java:112"
        },
        {
          "method": "org.eclipse.jface.operation.ModalContext$ModalContextThread.run",
          "source": "ModalContext.java:113"
        }
      ],
      "number": 0,
      "commentIndex": 1,
      "bugId": "109209",
      "date": "2006-02-21T22:50:22+01:00",
      "product": "Platform",
      "component": "Team",
      "severity": "normal"
    },
    {
      "exceptionType": "java.lang.IllegalArgumentException",
      "message": "Attempted to beginRule: R/, does not match outer scope rule: MultiRule[P/com.eclectic.test]",
      "elements": [
        {
          "method": "org.eclipse.core.runtime.Assert.isLegal",
          "source": "Assert.java:58"
        },
        {
          "method": "org.eclipse.core.internal.jobs.ThreadJob.illegalPush",
          "source": "ThreadJob.java:116"
        },
        {
          "method": "org.eclipse.core.internal.jobs.ThreadJob.push",
          "source": "ThreadJob.java:225"
        },
        {
          "method": "org.eclipse.core.internal.jobs.ImplicitJobs.begin",
          "source": "ImplicitJobs.java:58"
        },
        {
          "method": "org.eclipse.core.internal.jobs.JobManager.beginRule",
          "source": "JobManager.java:218"
        },
        {
          "method": "org.eclipse.core.internal.resources.WorkManager.checkIn",
          "source": "WorkManager.java:96"
        },
        {
          "method": "org.eclipse.core.internal.resources.Workspace.prepareOperation",
          "source": "Workspace.java:1681"
        },
        {
          "method": "org.eclipse.core.internal.resources.Project.open",
          "source": "Project.java:832"
        },
        {
          "method": "org.eclipse.core.internal.resources.Project.open",
          "source": "Project.java:890"
        },
        {
          "method": "org.eclipse.team.internal.ccvs.core.resources.EclipseFolder.mkdir",
          "source": "EclipseFolder.java:115"
        },
        {
          "method": "org.eclipse.team.internal.ccvs.core.client.ResponseHandler.createFolder",
          "source": "ResponseHandler.java:80"
        },
        {
          "method": "org.eclipse.team.internal.ccvs.core.client.StickyHandler.handle",
          "source": "StickyHandler.java:67"
        },
        {
          "method": "org.eclipse.team.internal.ccvs.core.client.Request.executeRequest",
          "source": "Request.java:218"
        },
        {
          "method": "org.eclipse.team.internal.ccvs.core.client.Command.doExecute",
          "source": "Command.java:404"
        },
        {
          "method": "org.eclipse.team.internal.ccvs.core.client.Checkout.doExecute",
          "source": "Checkout.java:159"
        },
        {
          "method": "org.eclipse.team.internal.ccvs.core.client.CheckoutWithOverwrite.doExecute",
          "source": "CheckoutWithOverwrite.java:52"
        },
        {
          "method": "org.eclipse.team.internal.ccvs.core.client.Command$1.run",
          "source": "Command.java:323"
        },
        {
          "method": "org.eclipse.team.internal.ccvs.core.resources.EclipseSynchronizer.run",
          "source": "EclipseSynchronizer.java:1450"
        },
        {
          "method": "org.eclipse.team.internal.ccvs.core.resources.EclipseResource$2.run",
          "source": "EclipseResource.java:260"
        },
        {
          "method": "org.eclipse.core.internal.resources.Workspace.run",
          "source": "Workspace.java:1733"
        },
        {
          "method": "org.eclipse.team.internal.ccvs.core.resources.EclipseResource.run",
          "source": "EclipseResource.java:257"
        },
        {
          "method": "org.eclipse.team.internal.ccvs.core.client.Command.execute",
          "source": "Command.java:335"
        },
        {
          "method": "org.eclipse.team.internal.ccvs.core.CVSProjectSetCapability$1.run",
          "source": "CVSProjectSetCapability.java:378"
        },
        {
          "method": "org.eclipse.core.internal.resources.Workspace.run",
          "source": "Workspace.java:1733"
        },
        {
          "method": "org.eclipse.team.internal.ccvs.core.CVSProjectSetCapability.checkout",
          "source": "CVSProjectSetCapability.java:406"
        },
        {
          "method": "org.eclipse.team.internal.ccvs.core.CVSProjectSetCapability.checkout",
          "source": "CVSProjectSetCapability.java:288"
        },
        {
          "method": "org.eclipse.team.internal.ccvs.core.CVSProjectSetCapability$LoadInfo.checkout",
          "source": "CVSProjectSetCapability.java:226"
        },
        {
          "method": "org.eclipse.team.internal.ccvs.core.CVSProjectSetCapability.checkout",
          "source": "CVSProjectSetCapability.java:167"
        },
        {
          "method": "org.eclipse.team.internal.ccvs.core.CVSProjectSetCapability.addToWorkspace",
          "source": "CVSProjectSetCapability.java:119"
        },
        {
          "method": "org.eclipse.team.internal.ui.ProjectSetImporter.importProjectSet",
          "source": "ProjectSetImporter.java:84"
        },
        {
          "method": "org.eclipse.team.internal.ui.wizards.ProjectSetImportWizard$1.execute",
          "source": "ProjectSetImportWizard.java:65"
        },
        {
          "method": "org.eclipse.ui.actions.WorkspaceModifyOperation$1.run",
          "source": "WorkspaceModifyOperation.java:100"
        },
        {
          "method": "org.eclipse.core.internal.resources.Workspace.run",
          "source": "Workspace.java:1733"
        },
        {
          "method": "org.eclipse.ui.actions.WorkspaceModifyOperation.run",
          "source": "WorkspaceModifyOperation.java:112"
        },
        {
          "method": "org.eclipse.jface.operation.ModalContext$ModalContextThread.run",
          "source": "ModalContext.java:113"
        }
      ],
      "number": 1,
      "commentIndex": 2,
      "bugId": "109209",
      "date": "2006-03-17T09:01:38+01:00",
      "product": "Platform",
      "component": "Team",
      "severity": "normal"
    }
  ],
  "groupId": "109209",
  "bugId": "109209",
  "date": "2005-09-09T23:07:50+02:00",
  "product": "Platform",
  "component": "Team",
  "severity": "normal"
}