{
  "comments": [
    "!SUBENTRY 1 org.eclipse.jdt.core 2 75 2005-09-12 09:39:04.575\n!MESSAGE java.lang.NullPointerException encountered while running Java Builder.\n!STACK 0\njava.lang.NullPointerException\n        at\norg.eclipse.jdt.internal.compiler.lookup.SourceTypeBinding.getField(SourceTypeBinding.java:810)\n        at org.eclipse.jdt.internal.compiler.lookup.Scope.findField(Scope.java:749)\n        at\norg.eclipse.jdt.internal.compiler.lookup.Scope.getBinding(Scope.java:1393)\n        at\norg.eclipse.jdt.internal.compiler.lookup.BlockScope.getBinding(BlockScope.java:385)\n        at\norg.eclipse.jdt.internal.compiler.ast.QualifiedNameReference.resolveType(QualifiedNameReference.java:840)\n        at\norg.eclipse.jdt.internal.compiler.ast.Expression.resolveTypeExpecting(Expression.java:848)\n        at\norg.eclipse.jdt.internal.compiler.ast.ArrayInitializer.resolveTypeExpecting(ArrayInitializer.java:177)\n        at\norg.eclipse.jdt.internal.compiler.ast.MemberValuePair.resolveTypeExpecting(MemberValuePair.java:61)\n        at\norg.eclipse.jdt.internal.compiler.ast.Annotation.resolveType(Annotation.java:246)\n        at\norg.eclipse.jdt.internal.compiler.ast.ASTNode.resolveAnnotations(ASTNode.java:436)\n        at\norg.eclipse.jdt.internal.compiler.lookup.FieldBinding.getAnnotationTagBits(FieldBinding.java:211)\n        at\norg.eclipse.jdt.internal.compiler.lookup.SourceTypeBinding.resolveTypeFor(SourceTypeBinding.java:1143)\n        at\norg.eclipse.jdt.internal.compiler.lookup.SourceTypeBinding.fields(SourceTypeBinding.java:630)\n        at\norg.eclipse.jdt.internal.compiler.lookup.ParameterizedTypeBinding.fields(ParameterizedTypeBinding.java:284)\n        at\norg.eclipse.jdt.internal.compiler.lookup.ParameterizedTypeBinding.getField(ParameterizedTypeBinding.java:436)\n        at org.eclipse.jdt.internal.compiler.lookup.Scope.findField(Scope.java:749)\n        at\norg.eclipse.jdt.internal.compiler.ast.FieldDeclaration.resolve(FieldDeclaration.java:172)\n        at\norg.eclipse.jdt.internal.compiler.ast.TypeDeclaration.resolve(TypeDeclaration.java:1029)\n        at\norg.eclipse.jdt.internal.compiler.ast.TypeDeclaration.resolve(TypeDeclaration.java:1112)\n        at\norg.eclipse.jdt.internal.compiler.ast.CompilationUnitDeclaration.resolve(CompilationUnitDeclaration.java:305)\n        at org.eclipse.jdt.internal.compiler.Compiler.process(Compiler.java:504)\n        at org.eclipse.jdt.internal.compiler.Compiler.compile(Compiler.java:329)\n        at\norg.eclipse.jdt.internal.core.builder.AbstractImageBuilder.compile(AbstractImageBuilder.java:240)\n        at\norg.eclipse.jdt.internal.core.builder.AbstractImageBuilder.compile(AbstractImageBuilder.java:190)\n        at\norg.eclipse.jdt.internal.core.builder.BatchImageBuilder.build(BatchImageBuilder.java:50)\n        at\norg.eclipse.jdt.internal.core.builder.JavaBuilder.buildAll(JavaBuilder.java:213)\n        at\norg.eclipse.jdt.internal.core.builder.JavaBuilder.build(JavaBuilder.java:136)\n        at\norg.eclipse.core.internal.events.BuildManager$2.run(BuildManager.java:593)\n        at\norg.eclipse.core.internal.runtime.InternalPlatform.run(InternalPlatform.java:1044)\n        at org.eclipse.core.runtime.Platform.run(Platform.java:783)\n        at\norg.eclipse.core.internal.events.BuildManager.basicBuild(BuildManager.java:168)\n        at\norg.eclipse.core.internal.events.BuildManager.basicBuild(BuildManager.java:202)\n        at\norg.eclipse.core.internal.events.BuildManager$1.run(BuildManager.java:231)\n        at\norg.eclipse.core.internal.runtime.InternalPlatform.run(InternalPlatform.java:1044)\n        at org.eclipse.core.runtime.Platform.run(Platform.java:783)\n        at\norg.eclipse.core.internal.events.BuildManager.basicBuild(BuildManager.java:234)\n        at\norg.eclipse.core.internal.events.BuildManager.basicBuildLoop(BuildManager.java:253)\n        at\norg.eclipse.core.internal.events.BuildManager.build(BuildManager.java:282)\n        at\norg.eclipse.core.internal.events.AutoBuildJob.doBuild(AutoBuildJob.java:139)\n        at org.eclipse.core.internal.events.AutoBuildJob.run(AutoBuildJob.java:200)\n        at org.eclipse.core.internal.jobs.Worker.run(Worker.java:76)",
    "What is your build ID?\nIs this problem reproduceable or did you get it only once?\nDo you have any test case to help us to understand what happen here?\n",
    "Thanks for the info:\n\"Sorry for providing no info about the bug, but i\u0027m\nshort of time now. The build id  I20050627-1435. The\nproblem was reproduced several times (even\nrefresh/clean all, deleting and exporting project\nagain did not helped). It disappeared after commenting\nout all source code and then removing comments from\nall fields one by one.\"\n\nHowever, the test case you send me is not usable as it does not compile at all\ndue to unresolved reference. We really need that you reduce this test case.\n\nAs you won\u0027t be available for next two weeks, I set this bug as REMIND.\nReopen it as soon as you\u0027ll be back and get a smaller test case, thanks\n",
    "Timeout. Closing",
    "I have this same problem. I don\u0027t know if it is one class or what. Seems to happen with the hibernate-annotations and ejb3-persistence annotations being added to my class.\n\nHere is one of my classes that is causing this problem:\n\npackage com.outlooksoft.cpm.contentmgmt;\n\nimport java.util.Date;\nimport java.util.List;\n\nimport javax.persistence.CascadeType;\nimport javax.persistence.Column;\nimport javax.persistence.Entity;\nimport javax.persistence.GeneratedValue;\nimport javax.persistence.GenerationType;\nimport javax.persistence.Id;\nimport javax.persistence.JoinColumn;\nimport javax.persistence.JoinTable;\nimport javax.persistence.ManyToOne;\nimport javax.persistence.OneToMany;\nimport javax.persistence.SequenceGenerator;\nimport javax.persistence.Table;\nimport javax.persistence.Temporal;\nimport javax.persistence.TemporalType;\n\nimport org.hibernate.annotations.AccessType;\nimport org.hibernate.annotations.OnDelete;\nimport org.hibernate.annotations.OnDeleteAction;\n\nimport com.outlooksoft.cpm.ws.CPMUserBean;\n\n@Entity\n@AccessType(\"field\")\n@Table(name\u003d\"C_Folder\")\n@SequenceGenerator(name\u003d\"seq\", sequenceName\u003d\"C_Folder_Seq\")\npublic class Folder\n{\n  @Basic\n  private String path;\n  \n  @OnDelete(action\u003dOnDeleteAction.CASCADE)\n  @JoinTable(name\u003d\"C_Folder_TeamSecurity\")\n  @OneToMany(cascade\u003dCascadeType.ALL, mappedBy\u003d\"folder\")\n  private List\u003cFolderTeamPermission\u003e teamPermissions;\n  \n  @OnDelete(action\u003dOnDeleteAction.CASCADE)\n  @JoinTable(name\u003d\"C_Folder_UserSecurity\")\n  @OneToMany(cascade\u003dCascadeType.ALL, mappedBy\u003d\"folder\")\n  private List\u003cFolderUserPermission\u003e userPermissions;\n  \n  @OnDelete(action\u003dOnDeleteAction.CASCADE)\n  @OneToMany(mappedBy\u003d\"parent\", cascade\u003dCascadeType.ALL)\n  private List\u003cFolder\u003e folders;\n  \n  @OnDelete(action\u003dOnDeleteAction.CASCADE)\n  @OneToMany(mappedBy\u003d\"folder\", cascade\u003dCascadeType.ALL)\n  private List\u003cDocument\u003e documents;\n  \n  @Id\n  @GeneratedValue(generator\u003d\"seq\", strategy\u003dGenerationType.SEQUENCE)\n  private Integer id;\n  \n  private String name;\n  \n  @Column(name\u003d\"parent_id\")\n  @ManyToOne(optional\u003dfalse)\n  private Folder parent;\n  \n  @ManyToOne\n  private CPMUserBean owner;\n  \n  @Temporal(TemporalType.TIMESTAMP)\n  private Date lastModifiedDate;\n  \n  @Temporal(TemporalType.TIMESTAMP)\n  private Date createdDate;\n\n  /**\n   * @return Returns the createdDate.\n   */\n  public Date getCreatedDate()\n  {\n    return createdDate;\n  }\n\n  /**\n   * @param createdDate The createdDate to set.\n   */\n  public void setCreatedDate(Date createdDate)\n  {\n    this.createdDate \u003d createdDate;\n  }\n\n  /**\n   * @return Returns the parent.\n   */\n  public Folder getParent()\n  {\n    return parent;\n  }\n\n  /**\n   * @param parent The parent to set.\n   */\n  public void setParent(Folder folder)\n  {\n    this.parent \u003d folder;\n  }\n\n  /**\n   * @return Returns the lastModifiedDate.\n   */\n  public Date getLastModifiedDate()\n  {\n    return lastModifiedDate;\n  }\n\n  /**\n   * @param lastModifiedDate The lastModifiedDate to set.\n   */\n  public void setLastModifiedDate(Date lastModifiedDate)\n  {\n    this.lastModifiedDate \u003d lastModifiedDate;\n  }\n\n  /**\n   * @return Returns the name.\n   */\n  public String getName()\n  {\n    return name;\n  }\n\n  /**\n   * @param name The name to set.\n   */\n  public void setName(String name)\n  {\n    this.name \u003d name;\n  }\n\n  /**\n   * @return Returns the owner.\n   */\n  public CPMUserBean getOwner()\n  {\n    return owner;\n  }\n\n  /**\n   * @param owner The owner to set.\n   */\n  public void setOwner(CPMUserBean owner)\n  {\n    this.owner \u003d owner;\n  }\n\n  /**\n   * @return Returns the id.\n   */\n  public Integer getId()\n  {\n    return id;\n  }\n\n  public String getPath()\n  {\n    return path;\n  }\n  \n  public void setPath(String path)\n  {\n    this.path \u003d path;\n  }\n  \n  /**\n   * @return Returns the teamPermissions.\n   */\n  public List\u003cFolderTeamPermission\u003e getTeamPermissions()\n  {\n    return teamPermissions;\n  }\n\n  /**\n   * @return Returns the userPermissions.\n   */\n  public List\u003cFolderUserPermission\u003e getUserPermissions()\n  {\n    return userPermissions;\n  }\n}\n",
    "Could you please specify what build you are using?",
    "My comment is in reference to:\n\nEclipse SDK\n\nVersion: 3.1.1\nBuild id: M20050929-0840"
  ],
  "commentCreationDates": [
    "2005-09-12T08:45:32+02:00",
    "2005-09-12T10:38:11+02:00",
    "2005-09-12T12:49:50+02:00",
    "2006-02-03T10:30:56+01:00",
    "2006-02-13T18:46:55+01:00",
    "2006-02-13T20:13:20+01:00",
    "2006-02-13T23:26:55+01:00"
  ],
  "traces": [
    {
      "exceptionType": "java.lang.NullPointerException",
      "elements": [
        {
          "method": "org.eclipse.jdt.internal.compiler.lookup.SourceTypeBinding.getField",
          "source": "SourceTypeBinding.java:810"
        },
        {
          "method": "org.eclipse.jdt.internal.compiler.lookup.Scope.findField",
          "source": "Scope.java:749"
        },
        {
          "method": "org.eclipse.jdt.internal.compiler.lookup.Scope.getBinding",
          "source": "Scope.java:1393"
        },
        {
          "method": "org.eclipse.jdt.internal.compiler.lookup.BlockScope.getBinding",
          "source": "BlockScope.java:385"
        },
        {
          "method": "org.eclipse.jdt.internal.compiler.ast.QualifiedNameReference.resolveType",
          "source": "QualifiedNameReference.java:840"
        },
        {
          "method": "org.eclipse.jdt.internal.compiler.ast.Expression.resolveTypeExpecting",
          "source": "Expression.java:848"
        },
        {
          "method": "org.eclipse.jdt.internal.compiler.ast.ArrayInitializer.resolveTypeExpecting",
          "source": "ArrayInitializer.java:177"
        },
        {
          "method": "org.eclipse.jdt.internal.compiler.ast.MemberValuePair.resolveTypeExpecting",
          "source": "MemberValuePair.java:61"
        },
        {
          "method": "org.eclipse.jdt.internal.compiler.ast.Annotation.resolveType",
          "source": "Annotation.java:246"
        },
        {
          "method": "org.eclipse.jdt.internal.compiler.ast.ASTNode.resolveAnnotations",
          "source": "ASTNode.java:436"
        },
        {
          "method": "org.eclipse.jdt.internal.compiler.lookup.FieldBinding.getAnnotationTagBits",
          "source": "FieldBinding.java:211"
        },
        {
          "method": "org.eclipse.jdt.internal.compiler.lookup.SourceTypeBinding.resolveTypeFor",
          "source": "SourceTypeBinding.java:1143"
        },
        {
          "method": "org.eclipse.jdt.internal.compiler.lookup.SourceTypeBinding.fields",
          "source": "SourceTypeBinding.java:630"
        },
        {
          "method": "org.eclipse.jdt.internal.compiler.lookup.ParameterizedTypeBinding.fields",
          "source": "ParameterizedTypeBinding.java:284"
        },
        {
          "method": "org.eclipse.jdt.internal.compiler.lookup.ParameterizedTypeBinding.getField",
          "source": "ParameterizedTypeBinding.java:436"
        },
        {
          "method": "org.eclipse.jdt.internal.compiler.lookup.Scope.findField",
          "source": "Scope.java:749"
        },
        {
          "method": "org.eclipse.jdt.internal.compiler.ast.FieldDeclaration.resolve",
          "source": "FieldDeclaration.java:172"
        },
        {
          "method": "org.eclipse.jdt.internal.compiler.ast.TypeDeclaration.resolve",
          "source": "TypeDeclaration.java:1029"
        },
        {
          "method": "org.eclipse.jdt.internal.compiler.ast.TypeDeclaration.resolve",
          "source": "TypeDeclaration.java:1112"
        },
        {
          "method": "org.eclipse.jdt.internal.compiler.ast.CompilationUnitDeclaration.resolve",
          "source": "CompilationUnitDeclaration.java:305"
        },
        {
          "method": "org.eclipse.jdt.internal.compiler.Compiler.process",
          "source": "Compiler.java:504"
        },
        {
          "method": "org.eclipse.jdt.internal.compiler.Compiler.compile",
          "source": "Compiler.java:329"
        },
        {
          "method": "org.eclipse.jdt.internal.core.builder.AbstractImageBuilder.compile",
          "source": "AbstractImageBuilder.java:240"
        },
        {
          "method": "org.eclipse.jdt.internal.core.builder.AbstractImageBuilder.compile",
          "source": "AbstractImageBuilder.java:190"
        },
        {
          "method": "org.eclipse.jdt.internal.core.builder.BatchImageBuilder.build",
          "source": "BatchImageBuilder.java:50"
        },
        {
          "method": "org.eclipse.jdt.internal.core.builder.JavaBuilder.buildAll",
          "source": "JavaBuilder.java:213"
        },
        {
          "method": "org.eclipse.jdt.internal.core.builder.JavaBuilder.build",
          "source": "JavaBuilder.java:136"
        },
        {
          "method": "org.eclipse.core.internal.events.BuildManager$2.run",
          "source": "BuildManager.java:593"
        },
        {
          "method": "org.eclipse.core.internal.runtime.InternalPlatform.run",
          "source": "InternalPlatform.java:1044"
        },
        {
          "method": "org.eclipse.core.runtime.Platform.run",
          "source": "Platform.java:783"
        },
        {
          "method": "org.eclipse.core.internal.events.BuildManager.basicBuild",
          "source": "BuildManager.java:168"
        },
        {
          "method": "org.eclipse.core.internal.events.BuildManager.basicBuild",
          "source": "BuildManager.java:202"
        },
        {
          "method": "org.eclipse.core.internal.events.BuildManager$1.run",
          "source": "BuildManager.java:231"
        },
        {
          "method": "org.eclipse.core.internal.runtime.InternalPlatform.run",
          "source": "InternalPlatform.java:1044"
        },
        {
          "method": "org.eclipse.core.runtime.Platform.run",
          "source": "Platform.java:783"
        },
        {
          "method": "org.eclipse.core.internal.events.BuildManager.basicBuild",
          "source": "BuildManager.java:234"
        },
        {
          "method": "org.eclipse.core.internal.events.BuildManager.basicBuildLoop",
          "source": "BuildManager.java:253"
        },
        {
          "method": "org.eclipse.core.internal.events.BuildManager.build",
          "source": "BuildManager.java:282"
        },
        {
          "method": "org.eclipse.core.internal.events.AutoBuildJob.doBuild",
          "source": "AutoBuildJob.java:139"
        },
        {
          "method": "org.eclipse.core.internal.events.AutoBuildJob.run",
          "source": "AutoBuildJob.java:200"
        },
        {
          "method": "org.eclipse.core.internal.jobs.Worker.run",
          "source": "Worker.java:76"
        }
      ],
      "number": 0,
      "commentIndex": 0,
      "bugId": "109270",
      "date": "2005-09-12T08:45:32+02:00",
      "product": "JDT",
      "component": "Core",
      "severity": "normal"
    }
  ],
  "groupId": "109270",
  "bugId": "109270",
  "date": "2005-09-12T08:45:32+02:00",
  "product": "JDT",
  "component": "Core",
  "severity": "normal"
}