{
  "comments": [
    "I\u0027m having trouble running Eclipse 3.1 on a PowerPC pSeries with SLES9. I\ndownloaded the Linux (PPC/GTK 2) eclipse-SDK-3.1-linux-gtk-ppc.tar.gz version. I\nstart Eclipse with -vmargs -Dosgi.locking\u003dnone and I see the splash screen but\nthen I get a dialog box saying something like this:\n\nAn error has occurred. See the log file\n/bglhome/usr3/clappi/eclipse/configuration/1126619768980.log.\n\nThe log files look like this:\n\n!SESSION 2005-09-06 \n16:18:27.491 -----------------------------------------------\neclipse.buildId\u003dI20050627-1435\njava.fullversion\u003dJ2RE 1.4.2 IBM build cxp641420ifx-20040722 (142GA+75755) \n(JIT enabled: jitc)\nBootLoader constants: OS\u003dlinux, ARCH\u003dppc, WS\u003dgtk, NL\u003den_US\nFramework arguments:  -vmargs -Dosgi.locking\u003dnone\nCommand-line arguments:  -os linux -ws gtk -arch \nppc -vmargs -Dosgi.locking\u003dnone\n\n!ENTRY org.eclipse.osgi 2005-09-06 16:18:33.201\n!MESSAGE Application error\n!STACK 1\njava.lang.UnsatisfiedLinkError: \n/bglhome/usr3/clappi/eclipse/configuration/org.eclipse.osgi/bundles/71/1/.cp/libswt-pi-gtk-3138.so:\n\n/bglhome/usr3/clappi/eclipse/configuration/org.eclipse.osgi/bundles/71/1/.cp/libswt-pi-gtk-3138.so:\n\ncannot open shared object file: No such file or directory\n at java.lang.ClassLoader$NativeLibrary.load(Native Method)\n at java.lang.ClassLoader.loadLibrary0(ClassLoader.java:2120)\n at java.lang.ClassLoader.loadLibrary(ClassLoader.java:1968)\n at java.lang.Runtime.loadLibrary0(Runtime.java:824)\n at java.lang.System.loadLibrary(System.java:908)\n at org.eclipse.swt.internal.Library.loadLibrary(Library.java:123)\n at org.eclipse.swt.internal.gtk.OS.\u003cclinit\u003e(OS.java:19)\n at org.eclipse.swt.internal.Converter.wcsToMbcs(Converter.java:63)\n at org.eclipse.swt.internal.Converter.wcsToMbcs(Converter.java:54)\n at org.eclipse.swt.widgets.Display.\u003cclinit\u003e(Display.java:122)\n at org.eclipse.ui.internal.Workbench.createDisplay(Workbench.java:381)\n at org.eclipse.ui.PlatformUI.createDisplay(PlatformUI.java:155)\n at \norg.eclipse.ui.internal.ide.IDEApplication.createDisplay(IDEApplication.java:128)\n at org.eclipse.ui.internal.ide.IDEApplication.run(IDEApplication.java:79)\n at \norg.eclipse.core.internal.runtime.PlatformActivator$1.run(PlatformActivator.java:226)\n at \norg.eclipse.core.runtime.adaptor.EclipseStarter.run(EclipseStarter.java:376)\n at \norg.eclipse.core.runtime.adaptor.EclipseStarter.run(EclipseStarter.java:163)\n at sun.reflect.NativeMethodAccessorImpl.invoke0(Native Method)\n at \nsun.reflect.NativeMethodAccessorImpl.invoke(NativeMethodAccessorImpl.java:85)\n at \nsun.reflect.NativeMethodAccessorImpl.invoke(NativeMethodAccessorImpl.java:58)\n at \nsun.reflect.DelegatingMethodAccessorImpl.invoke(DelegatingMethodAccessorImpl.java:60)\n at java.lang.reflect.Method.invoke(Method.java:391)\n at org.eclipse.core.launcher.Main.invokeFramework(Main.java:334)\n at org.eclipse.core.launcher.Main.basicRun(Main.java:278)\n at org.eclipse.core.launcher.Main.run(Main.java:973)\n at org.eclipse.core.launcher.Main.main(Main.java:948)\n\nwhich is weird because \n/bglhome/usr3/clappi/eclipse/configuration/org.eclipse.osgi/bundles/71/1/.cp/libswt-pi-gtk-3138.so\n\nis definitely there and accessible.\n\nRunning ldd libswt-pi-gtk-3138.so shows this:\n\nldd: warning: you do not have execution permission for `./libswt-pi-gtk-3138.so\u0027\n        libgtk-x11-2.0.so.0 \u003d\u003e /opt/gnome/lib/libgtk-x11-2.0.so.0 (0x6fcd4000)\n        libgthread-2.0.so.0 \u003d\u003e /opt/gnome/lib/libgthread-2.0.so.0 (0x6fcaf000)\n        libXtst.so.6 \u003d\u003e /usr/X11R6/lib/libXtst.so.6 (0x6fc88000)\n        libc.so.6 \u003d\u003e /lib/tls/libc.so.6 (0x6fb41000)\n        libgdk_pixbuf-2.0.so.0 \u003d\u003e /opt/gnome/lib/libgdk_pixbuf-2.0.so.0 (0x6fb0c000)\n        libgdk-x11-2.0.so.0 \u003d\u003e /opt/gnome/lib/libgdk-x11-2.0.so.0 (0x6fa70000)\n        libX11.so.6 \u003d\u003e /usr/X11R6/lib/libX11.so.6 (0x6f941000)\n        libpangoxft-1.0.so.0 \u003d\u003e /opt/gnome/lib/libpangoxft-1.0.so.0 (0x6f900000)\n        libpangox-1.0.so.0 \u003d\u003e /opt/gnome/lib/libpangox-1.0.so.0 (0x6f8d2000)\n        libpango-1.0.so.0 \u003d\u003e /opt/gnome/lib/libpango-1.0.so.0 (0x6f878000)\n        libatk-1.0.so.0 \u003d\u003e /opt/gnome/lib/libatk-1.0.so.0 (0x6f837000)\n        libgobject-2.0.so.0 \u003d\u003e /opt/gnome/lib/libgobject-2.0.so.0 (0x6f7d9000)\n        libgmodule-2.0.so.0 \u003d\u003e /opt/gnome/lib/libgmodule-2.0.so.0 (0x6f7b5000)\n        libdl.so.2 \u003d\u003e /lib/libdl.so.2 (0x6f792000)\n        libglib-2.0.so.0 \u003d\u003e /opt/gnome/lib/libglib-2.0.so.0 (0x6f6f8000)\n        libm.so.6 \u003d\u003e /lib/tls/libm.so.6 (0x6f663000)\n        libpthread.so.0 \u003d\u003e /lib/tls/libpthread.so.0 (0x6f640000)\n        libXext.so.6 \u003d\u003e /usr/X11R6/lib/libXext.so.6 (0x6f60d000)\n        /lib/ld.so.1 \u003d\u003e /lib/ld.so.1 (0x08000000)\n        libXrandr.so.2 \u003d\u003e /usr/X11R6/lib/libXrandr.so.2 (0x6f5e9000)\n        libXi.so.6 \u003d\u003e /usr/X11R6/lib/libXi.so.6 (0x6f5bf000)\n        libXft.so.2 \u003d\u003e /usr/X11R6/lib/libXft.so.2 (0x6f58b000)\n        libXrender.so.1 \u003d\u003e /usr/X11R6/lib/libXrender.so.1 (0x6f561000)\n        libfontconfig.so.1 \u003d\u003e /usr/lib/libfontconfig.so.1 (0x6f510000)\n        libfreetype.so.6 \u003d\u003e /usr/lib/libfreetype.so.6 (0x6f47b000)\n        libexpat.so.0 \u003d\u003e /usr/local/lib/libexpat.so.0 (0x6f435000)\n\nRunning java -version shows this:\n\njava version \"1.4.2\"\nJava(TM) 2 Runtime Environment, Standard Edition (build 1.4.2)\nClassic VM (build 1.4.2, J2RE 1.4.2 IBM build cxp641420ifx-20040722\n(142GA+75755) (JIT enabled: jitc))\n\nI\u0027m running gtk2-2.2.4-125.4 version of GTK2.\n\nAny ideas?",
    "Moving to SWT",
    "Cory and I determined that the problem was that the default \"java\" mapped to a\n64-bit VM rather than a 32-bit VM needed for Eclipse/PPC.\n\nI am marking this as a duplicate of bug 85699, since the error message clearly\ndidn\u0027t help here.  Another related issue is bug 73839, which requests a 64-bit\nbuild for ppc64 architectures.\n\n*** This bug has been marked as a duplicate of 85699 ***"
  ],
  "commentCreationDates": [
    "2005-09-13T16:03:23+02:00",
    "2005-09-13T17:02:18+02:00",
    "2005-10-04T16:59:24+02:00"
  ],
  "traces": [
    {
      "exceptionType": "java.lang.UnsatisfiedLinkError",
      "message": "/bglhome/usr3/clappi/eclipse/configuration/org.eclipse.osgi/bundles/71/1/.cp/libswt-pi-gtk-3138.so:  /bglhome/usr3/clappi/eclipse/configuration/org.eclipse.osgi/bundles/71/1/.cp/libswt-pi-gtk-3138.so:  cannot open shared object file: No such file or directory",
      "elements": [
        {
          "method": "java.lang.ClassLoader$NativeLibrary.load",
          "source": "Native Method"
        },
        {
          "method": "java.lang.ClassLoader.loadLibrary0",
          "source": "ClassLoader.java:2120"
        },
        {
          "method": "java.lang.ClassLoader.loadLibrary",
          "source": "ClassLoader.java:1968"
        },
        {
          "method": "java.lang.Runtime.loadLibrary0",
          "source": "Runtime.java:824"
        },
        {
          "method": "java.lang.System.loadLibrary",
          "source": "System.java:908"
        },
        {
          "method": "org.eclipse.swt.internal.Library.loadLibrary",
          "source": "Library.java:123"
        },
        {
          "method": "org.eclipse.swt.internal.gtk.OS.\u003cclinit\u003e",
          "source": "OS.java:19"
        },
        {
          "method": "org.eclipse.swt.internal.Converter.wcsToMbcs",
          "source": "Converter.java:63"
        },
        {
          "method": "org.eclipse.swt.internal.Converter.wcsToMbcs",
          "source": "Converter.java:54"
        },
        {
          "method": "org.eclipse.swt.widgets.Display.\u003cclinit\u003e",
          "source": "Display.java:122"
        },
        {
          "method": "org.eclipse.ui.internal.Workbench.createDisplay",
          "source": "Workbench.java:381"
        },
        {
          "method": "org.eclipse.ui.PlatformUI.createDisplay",
          "source": "PlatformUI.java:155"
        },
        {
          "method": "org.eclipse.ui.internal.ide.IDEApplication.createDisplay",
          "source": "IDEApplication.java:128"
        },
        {
          "method": "org.eclipse.ui.internal.ide.IDEApplication.run",
          "source": "IDEApplication.java:79"
        },
        {
          "method": "org.eclipse.core.internal.runtime.PlatformActivator$1.run",
          "source": "PlatformActivator.java:226"
        },
        {
          "method": "org.eclipse.core.runtime.adaptor.EclipseStarter.run",
          "source": "EclipseStarter.java:376"
        },
        {
          "method": "org.eclipse.core.runtime.adaptor.EclipseStarter.run",
          "source": "EclipseStarter.java:163"
        },
        {
          "method": "sun.reflect.NativeMethodAccessorImpl.invoke0",
          "source": "Native Method"
        },
        {
          "method": "sun.reflect.NativeMethodAccessorImpl.invoke",
          "source": "NativeMethodAccessorImpl.java:85"
        },
        {
          "method": "sun.reflect.NativeMethodAccessorImpl.invoke",
          "source": "NativeMethodAccessorImpl.java:58"
        },
        {
          "method": "sun.reflect.DelegatingMethodAccessorImpl.invoke",
          "source": "DelegatingMethodAccessorImpl.java:60"
        },
        {
          "method": "java.lang.reflect.Method.invoke",
          "source": "Method.java:391"
        },
        {
          "method": "org.eclipse.core.launcher.Main.invokeFramework",
          "source": "Main.java:334"
        },
        {
          "method": "org.eclipse.core.launcher.Main.basicRun",
          "source": "Main.java:278"
        },
        {
          "method": "org.eclipse.core.launcher.Main.run",
          "source": "Main.java:973"
        },
        {
          "method": "org.eclipse.core.launcher.Main.main",
          "source": "Main.java:948"
        }
      ],
      "number": 0,
      "commentIndex": 0,
      "bugId": "109395",
      "duplicateId": "85699",
      "date": "2005-09-13T16:03:23+02:00",
      "product": "Platform",
      "component": "SWT",
      "severity": "normal"
    }
  ],
  "groupId": "85699",
  "bugId": "109395",
  "duplicateId": "85699",
  "date": "2005-09-13T16:03:23+02:00",
  "product": "Platform",
  "component": "SWT",
  "severity": "normal"
}