{
  "comments": [
    "Testcase: A.aj containing:\n\nfinal abstract aspect A {}\n\nThis causes the compiler to abort with an internal compiler error:\n\nC:\\Documents and Settings\\mchapman\\A.aj [error] Internal compiler error\norg.aspectj.apache.bcel.classfile.ClassFormatException: Class can\u0027t be both\nfinal and abstract\n        at org.aspectj.apache.bcel.classfile.ClassParser.readClassInfo(ClassPars\ner.java:242)\n        at org.aspectj.apache.bcel.classfile.ClassParser.parse(ClassParser.java:\n165)\n        at org.aspectj.weaver.bcel.Utility.makeJavaClass(Utility.java:489)\n        at org.aspectj.weaver.bcel.UnwovenClassFile.getJavaClass(UnwovenClassFil\ne.java:63)\n        at org.aspectj.weaver.bcel.UnwovenClassFile.getClassName(UnwovenClassFil\ne.java:147)\n        at org.aspectj.ajdt.internal.core.builder.AjState.noteResult(AjState.jav\na:497)\n        at org.aspectj.ajdt.internal.core.builder.AjBuildManager$3.acceptResult(\nAjBuildManager.java:748)\n        at org.aspectj.ajdt.internal.compiler.AjCompilerAdapter.afterProcessing(\nAjCompilerAdapter.java:186)\n        at org.aspectj.ajdt.internal.compiler.CompilerAdapter.ajc$afterReturning\n$org_aspectj_ajdt_internal_compiler_CompilerAdapter$4$6b855184(CompilerAdapter.a\nj:89)\n        at org.aspectj.org.eclipse.jdt.internal.compiler.Compiler.process(Compil\ner.java:528)\n        at org.aspectj.org.eclipse.jdt.internal.compiler.Compiler.compile(Compil\ner.java:329)\n        at org.aspectj.ajdt.internal.core.builder.AjBuildManager.performCompilat\nion(AjBuildManager.java:728)\n        at org.aspectj.ajdt.internal.core.builder.AjBuildManager.doBuild(AjBuild\nManager.java:206)\n        at org.aspectj.ajdt.internal.core.builder.AjBuildManager.batchBuild(AjBu\nildManager.java:140)\n        at org.aspectj.ajdt.ajc.AjdtCommand.doCommand(AjdtCommand.java:112)\n        at org.aspectj.ajdt.ajc.AjdtCommand.runCommand(AjdtCommand.java:60)\n        at org.aspectj.tools.ajc.Main.run(Main.java:324)\n        at org.aspectj.tools.ajc.Main.runMain(Main.java:238)\n        at org.aspectj.tools.ajc.Main.main(Main.java:82)\n\n(no source information available)\nC:\\Documents and Settings\\mchapman\\A.aj:1 [error] The class A can be either abst\nract or final, not both\nfinal abstract aspect A {}\n\nABORT\n\nException thrown from AspectJ DEVELOPMENT\n\n\nC:\\Documents and Settings\\mchapman\u003eajc -version\nAspectJ Compiler DEVELOPMENT built on Tuesday Sep 13, 2005 at 22:31:40 GMT\n\nThe expected behaviour is naturally just to get a regular compiler errror saying\n\"The aspect A can be either abstract or final, not both\".",
    "Fix checked in - will be in next build.  will close this bug when its available.",
    "fix available."
  ],
  "commentCreationDates": [
    "2005-09-14T12:06:29+02:00",
    "2005-09-14T13:13:40+02:00",
    "2005-09-15T16:42:39+02:00"
  ],
  "traces": [
    {
      "exceptionType": "org.aspectj.apache.bcel.classfile.ClassFormatException",
      "message": "Class can\u0027t be both final and abstract",
      "elements": [
        {
          "method": "org.aspectj.apache.bcel.classfile.ClassParser.readClassInfo",
          "source": "ClassPars er.java:242"
        },
        {
          "method": "org.aspectj.apache.bcel.classfile.ClassParser.parse",
          "source": "ClassParser.java: 165"
        },
        {
          "method": "org.aspectj.weaver.bcel.Utility.makeJavaClass",
          "source": "Utility.java:489"
        },
        {
          "method": "org.aspectj.weaver.bcel.UnwovenClassFile.getJavaClass",
          "source": "UnwovenClassFil e.java:63"
        },
        {
          "method": "org.aspectj.weaver.bcel.UnwovenClassFile.getClassName",
          "source": "UnwovenClassFil e.java:147"
        },
        {
          "method": "org.aspectj.ajdt.internal.core.builder.AjState.noteResult",
          "source": "AjState.jav a:497"
        },
        {
          "method": "org.aspectj.ajdt.internal.core.builder.AjBuildManager$3.acceptResult",
          "source": " AjBuildManager.java:748"
        },
        {
          "method": "org.aspectj.ajdt.internal.compiler.AjCompilerAdapter.afterProcessing",
          "source": " AjCompilerAdapter.java:186"
        },
        {
          "method": "org.aspectj.ajdt.internal.compiler.CompilerAdapter.ajc$afterReturning$org_aspectj_ajdt_internal_compiler_CompilerAdapter$4$6b855184",
          "source": "CompilerAdapter.a j:89"
        },
        {
          "method": "org.aspectj.org.eclipse.jdt.internal.compiler.Compiler.process",
          "source": "Compil er.java:528"
        },
        {
          "method": "org.aspectj.org.eclipse.jdt.internal.compiler.Compiler.compile",
          "source": "Compil er.java:329"
        },
        {
          "method": "org.aspectj.ajdt.internal.core.builder.AjBuildManager.performCompilation",
          "source": "AjBuildManager.java:728"
        },
        {
          "method": "org.aspectj.ajdt.internal.core.builder.AjBuildManager.doBuild",
          "source": "AjBuild Manager.java:206"
        },
        {
          "method": "org.aspectj.ajdt.internal.core.builder.AjBuildManager.batchBuild",
          "source": "AjBu ildManager.java:140"
        },
        {
          "method": "org.aspectj.ajdt.ajc.AjdtCommand.doCommand",
          "source": "AjdtCommand.java:112"
        },
        {
          "method": "org.aspectj.ajdt.ajc.AjdtCommand.runCommand",
          "source": "AjdtCommand.java:60"
        },
        {
          "method": "org.aspectj.tools.ajc.Main.run",
          "source": "Main.java:324"
        },
        {
          "method": "org.aspectj.tools.ajc.Main.runMain",
          "source": "Main.java:238"
        },
        {
          "method": "org.aspectj.tools.ajc.Main.main",
          "source": "Main.java:82"
        }
      ],
      "number": 0,
      "commentIndex": 0,
      "bugId": "109486",
      "date": "2005-09-14T12:06:29+02:00",
      "product": "AspectJ",
      "component": "Compiler",
      "severity": "normal"
    }
  ],
  "groupId": "109486",
  "bugId": "109486",
  "date": "2005-09-14T12:06:29+02:00",
  "product": "AspectJ",
  "component": "Compiler",
  "severity": "normal"
}