{
  "comments": [
    "Eclipse with CDT installed on server, When i first start eclipse everything is\nall right.But next time I get a popup saying an error occured and to see log file.\nHere is de log file : \n\n!SESSION 2005-09-23 10:35:44.906 -----------------------------------------------\neclipse.buildId\u003dI20050627-1435\njava.version\u003d1.5.0_01\njava.vendor\u003dSun Microsystems Inc.\nBootLoader constants: OS\u003dsolaris, ARCH\u003dsparc, WS\u003dmotif, NL\u003den\nCommand-line arguments:  -os solaris -ws motif -arch sparc\n\n!ENTRY org.eclipse.osgi 2005-09-23 10:35:46.588\n!MESSAGE Application error\n!STACK 1\norg.eclipse.core.runtime.CoreException[1]: java.lang.ClassNotFoundException:\norg.eclipse.ui.internal.ide.IDEApplication\n        at\norg.eclipse.osgi.framework.internal.core.BundleLoader.findClass(BundleLoader.java:403)\n        at\norg.eclipse.osgi.framework.internal.core.BundleLoader.findClass(BundleLoader.java:350)\n        at\norg.eclipse.osgi.framework.adaptor.core.AbstractClassLoader.loadClass(AbstractClassLoader.java:78)\n        at java.lang.ClassLoader.loadClass(ClassLoader.java:251)\n        at\norg.eclipse.osgi.framework.internal.core.BundleLoader.loadClass(BundleLoader.java:275)\n        at\norg.eclipse.osgi.framework.internal.core.BundleHost.loadClass(BundleHost.java:227)\n        at\norg.eclipse.osgi.framework.internal.core.AbstractBundle.loadClass(AbstractBundle.java:1259)\n        at\norg.eclipse.core.internal.registry.ConfigurationElement.createExecutableExtension(ConfigurationElement.java:152)\n        at\norg.eclipse.core.internal.registry.ConfigurationElement.createExecutableExtension(ConfigurationElement.java:142)\n        at\norg.eclipse.core.internal.registry.ConfigurationElement.createExecutableExtension(ConfigurationElement.java:129)\n        at\norg.eclipse.core.internal.registry.ConfigurationElementHandle.createExecutableExtension(ConfigurationElementHandle.java:48)\n        at\norg.eclipse.core.internal.runtime.PlatformActivator$1.run(PlatformActivator.java:222)\n        at\norg.eclipse.core.runtime.adaptor.EclipseStarter.run(EclipseStarter.java:376)\n        at\norg.eclipse.core.runtime.adaptor.EclipseStarter.run(EclipseStarter.java:163)\n        at sun.reflect.NativeMethodAccessorImpl.invoke0(Native Method)\n        at\nsun.reflect.NativeMethodAccessorImpl.invoke(NativeMethodAccessorImpl.java:39)\n        at\nsun.reflect.DelegatingMethodAccessorImpl.invoke(DelegatingMethodAccessorImpl.java:25)\n        at java.lang.reflect.Method.invoke(Method.java:585)\n        at org.eclipse.core.launcher.Main.invokeFramework(Main.java:334)\n        at org.eclipse.core.launcher.Main.basicRun(Main.java:278)\n        at org.eclipse.core.launcher.Main.run(Main.java:973)\n        at org.eclipse.core.launcher.Main.main(Main.java:948)\n~",
    "I doubt this is a CDT problem. IDEApplication is the main driver out of the\nEclipse platform. Do you get the same thing when the CDT is not installed?",
    "(In reply to comment #1)\n\u003e I doubt this is a CDT problem. IDEApplication is the main driver out of the\n\u003e Eclipse platform. Do you get the same thing when the CDT is not installed?\n\nThis appear only in one of our platform with CDT, we suspect that something went\nwrong when we install CDT, on another system running eclipse 3.1 with CDT , the\nproblem doesn\u0027t appear.\nThe only difference between the 2 systems is java version .",
    "(In reply to comment #2)\n\u003e (In reply to comment #1)\n\u003e \u003e I doubt this is a CDT problem. IDEApplication is the main driver out of the\n\u003e \u003e Eclipse platform. Do you get the same thing when the CDT is not installed?\n\u003e \n\u003e This appear only in one of our platform with CDT, we suspect that something went\n\u003e wrong when we install CDT, on another system running eclipse 3.1 with CDT , the\n\u003e problem doesn\u0027t appear.\n\u003e The only difference between the 2 systems is java version .\n\na file in eclipse hierarchie might have been modified after installing CDT.\nI reinstall eclipse and CDT and everything seems to be ok\n",
    "I have exactly this problem right now. It is only affecting new users (i.e. users that have not yet used Eclipse) existing users are fine. Erasing ~/.eclipse allows the user to use eclipse again, once. I hope a Eclipse/CDT reinstall fixes it but I don\u0027t see how Eclipse or the CDT can have been corrupted. The real bug is that there is inadequate info in the log."
  ],
  "commentCreationDates": [
    "2005-09-23T11:37:33+02:00",
    "2005-09-23T13:39:31+02:00",
    "2005-09-23T14:07:12+02:00",
    "2005-09-23T15:01:58+02:00",
    "2005-11-22T17:41:18+01:00"
  ],
  "traces": [
    {
      "exceptionType": "java.lang.ClassNotFoundException",
      "message": "org.eclipse.ui.internal.ide.IDEApplication",
      "elements": [
        {
          "method": "org.eclipse.osgi.framework.internal.core.BundleLoader.findClass",
          "source": "BundleLoader.java:403"
        },
        {
          "method": "org.eclipse.osgi.framework.internal.core.BundleLoader.findClass",
          "source": "BundleLoader.java:350"
        },
        {
          "method": "org.eclipse.osgi.framework.adaptor.core.AbstractClassLoader.loadClass",
          "source": "AbstractClassLoader.java:78"
        },
        {
          "method": "java.lang.ClassLoader.loadClass",
          "source": "ClassLoader.java:251"
        },
        {
          "method": "org.eclipse.osgi.framework.internal.core.BundleLoader.loadClass",
          "source": "BundleLoader.java:275"
        },
        {
          "method": "org.eclipse.osgi.framework.internal.core.BundleHost.loadClass",
          "source": "BundleHost.java:227"
        },
        {
          "method": "org.eclipse.osgi.framework.internal.core.AbstractBundle.loadClass",
          "source": "AbstractBundle.java:1259"
        },
        {
          "method": "org.eclipse.core.internal.registry.ConfigurationElement.createExecutableExtension",
          "source": "ConfigurationElement.java:152"
        },
        {
          "method": "org.eclipse.core.internal.registry.ConfigurationElement.createExecutableExtension",
          "source": "ConfigurationElement.java:142"
        },
        {
          "method": "org.eclipse.core.internal.registry.ConfigurationElement.createExecutableExtension",
          "source": "ConfigurationElement.java:129"
        },
        {
          "method": "org.eclipse.core.internal.registry.ConfigurationElementHandle.createExecutableExtension",
          "source": "ConfigurationElementHandle.java:48"
        },
        {
          "method": "org.eclipse.core.internal.runtime.PlatformActivator$1.run",
          "source": "PlatformActivator.java:222"
        },
        {
          "method": "org.eclipse.core.runtime.adaptor.EclipseStarter.run",
          "source": "EclipseStarter.java:376"
        },
        {
          "method": "org.eclipse.core.runtime.adaptor.EclipseStarter.run",
          "source": "EclipseStarter.java:163"
        },
        {
          "method": "sun.reflect.NativeMethodAccessorImpl.invoke0",
          "source": "Native Method"
        },
        {
          "method": "sun.reflect.NativeMethodAccessorImpl.invoke",
          "source": "NativeMethodAccessorImpl.java:39"
        },
        {
          "method": "sun.reflect.DelegatingMethodAccessorImpl.invoke",
          "source": "DelegatingMethodAccessorImpl.java:25"
        },
        {
          "method": "java.lang.reflect.Method.invoke",
          "source": "Method.java:585"
        },
        {
          "method": "org.eclipse.core.launcher.Main.invokeFramework",
          "source": "Main.java:334"
        },
        {
          "method": "org.eclipse.core.launcher.Main.basicRun",
          "source": "Main.java:278"
        },
        {
          "method": "org.eclipse.core.launcher.Main.run",
          "source": "Main.java:973"
        },
        {
          "method": "org.eclipse.core.launcher.Main.main",
          "source": "Main.java:948"
        }
      ],
      "number": 0,
      "commentIndex": 0,
      "bugId": "110406",
      "date": "2005-09-23T11:37:33+02:00",
      "product": "CDT",
      "component": "UI",
      "severity": "blocker"
    }
  ],
  "groupId": "110406",
  "bugId": "110406",
  "date": "2005-09-23T11:37:33+02:00",
  "product": "CDT",
  "component": "UI",
  "severity": "blocker"
}