{
  "comments": [
    "Eclipse 20020305-I\n\n\nI don\u0027t know how to cause this error to happen.  All I can say is you need to \n\u003cg\u003e work on a feature for a couple of weeks, lovingly hand crafting the code, \nadding new classes, modifying many many other classes \u003c/g\u003e and then when you \ncommit your changes you get the following error included below.\nIn addition to the error log, some changes were released and others weren\u0027t.  I \nhad deleted a file (a dll) and then imported a new version that I was \nreleasing.  The dll was removed from the repository and the new one was not \nadded.\n\nI issued the commit from the top of the project.\nAfter the failure, when I synchronized, the things which had been released \nappeared as conflicts and the things which hadn\u0027t were still waiting to be \nreleased.  The only exception was the dll file which appeared as a conflict but \nthe HEAD stream actually had no such file.\n\n\nLog: Fri Mar 08 12:13:38 EST 2002\n4 org.eclipse.team.cvs.ui 1 Internal error\norg.eclipse.team.internal.ccvs.core.util.AssertionFailedException: assertion \nfailed: \n\tat org.eclipse.team.internal.ccvs.core.util.Assert.isTrue(Assert.java\n(Compiled Code))\n\tat org.eclipse.team.internal.ccvs.core.util.Assert.isTrue(Assert.java\n(Compiled Code))\n\tat org.eclipse.team.internal.ccvs.core.client.RemoveEntryHandler.handle\n(RemoveEntryHandler.java:49)\n\tat org.eclipse.team.internal.ccvs.core.client.Command.processResponses\n(Command.java(Compiled Code))\n\tat org.eclipse.team.internal.ccvs.core.client.Command.execute\n(Command.java:399)\n\tat org.eclipse.team.ccvs.core.CVSTeamProvider.checkin\n(CVSTeamProvider.java:322)\n\tat org.eclipse.team.internal.ccvs.ui.RepositoryManager.commit\n(RepositoryManager.java:488)\n\tat org.eclipse.team.internal.ccvs.ui.sync.CommitSyncAction.run\n(CommitSyncAction.java:162)\n\tat org.eclipse.team.internal.ccvs.ui.sync.MergeAction$1.execute\n(MergeAction.java:105)\n\tat org.eclipse.ui.actions.WorkspaceModifyOperation$1.run\n(WorkspaceModifyOperation.java:64)\n\tat org.eclipse.core.internal.resources.Workspace.run\n(Workspace.java:1232)\n\tat org.eclipse.ui.actions.WorkspaceModifyOperation.run\n(WorkspaceModifyOperation.java:78)\n\tat org.eclipse.jface.operation.ModalContext$ModalContextThread.run\n(ModalContext.java:98)",
    "\n\n*** This bug has been marked as a duplicate of 10871 ***"
  ],
  "commentCreationDates": [
    "2002-03-08T19:31:37+01:00",
    "2002-03-09T01:01:42+01:00"
  ],
  "traces": [
    {
      "exceptionType": "org.eclipse.team.internal.ccvs.core.util.AssertionFailedException",
      "message": "assertion  failed:",
      "elements": [
        {
          "method": "org.eclipse.team.internal.ccvs.core.util.Assert.isTrue",
          "source": "Assert.java (Compiled Code)"
        },
        {
          "method": "org.eclipse.team.internal.ccvs.core.util.Assert.isTrue",
          "source": "Assert.java (Compiled Code)"
        },
        {
          "method": "org.eclipse.team.internal.ccvs.core.client.RemoveEntryHandler.handle",
          "source": "RemoveEntryHandler.java:49"
        },
        {
          "method": "org.eclipse.team.internal.ccvs.core.client.Command.processResponses",
          "source": "Command.java(Compiled Code)"
        },
        {
          "method": "org.eclipse.team.internal.ccvs.core.client.Command.execute",
          "source": "Command.java:399"
        },
        {
          "method": "org.eclipse.team.ccvs.core.CVSTeamProvider.checkin",
          "source": "CVSTeamProvider.java:322"
        },
        {
          "method": "org.eclipse.team.internal.ccvs.ui.RepositoryManager.commit",
          "source": "RepositoryManager.java:488"
        },
        {
          "method": "org.eclipse.team.internal.ccvs.ui.sync.CommitSyncAction.run",
          "source": "CommitSyncAction.java:162"
        },
        {
          "method": "org.eclipse.team.internal.ccvs.ui.sync.MergeAction$1.execute",
          "source": "MergeAction.java:105"
        },
        {
          "method": "org.eclipse.ui.actions.WorkspaceModifyOperation$1.run",
          "source": "WorkspaceModifyOperation.java:64"
        },
        {
          "method": "org.eclipse.core.internal.resources.Workspace.run",
          "source": "Workspace.java:1232"
        },
        {
          "method": "org.eclipse.ui.actions.WorkspaceModifyOperation.run",
          "source": "WorkspaceModifyOperation.java:78"
        },
        {
          "method": "org.eclipse.jface.operation.ModalContext$ModalContextThread.run",
          "source": "ModalContext.java:98"
        }
      ],
      "number": 0,
      "commentIndex": 0,
      "bugId": "11049",
      "duplicateId": "10871",
      "date": "2002-03-08T19:31:37+01:00",
      "product": "Platform",
      "component": "Team",
      "severity": "normal"
    }
  ],
  "groupId": "10871",
  "bugId": "11049",
  "duplicateId": "10871",
  "date": "2002-03-08T19:31:37+01:00",
  "product": "Platform",
  "component": "Team",
  "severity": "normal"
}