{
  "comments": [
    "In my SWT application, hitting Cmd+Q twice very quickly to exit it, results in\nthis execption:\n\norg.eclipse.swt.SWTException: Device is disposed\n    at org.eclipse.swt.SWT.error(SWT.java:3251)\n    at org.eclipse.swt.SWT.error(SWT.java:3174)\n    at org.eclipse.swt.SWT.error(SWT.java:3145)\n    at org.eclipse.swt.widgets.Display.error(Display.java:1017)\n    at org.eclipse.swt.widgets.Display.checkDevice(Display.java:571)\n    at org.eclipse.swt.widgets.Display.readAndDispatch(Display.java:2725)\n    at org.eclipse.swt.widgets.Display.release(Display.java:2818)\n    at org.eclipse.swt.graphics.Device.dispose(Device.java:202)\n    at org.eclipse.swt.widgets.Display.close(Display.java:844)\n    at org.eclipse.swt.widgets.Display.commandProc(Display.java:727)\n    at org.eclipse.swt.internal.carbon.OS.SendEventToEventTarget(Native Method)\n    at org.eclipse.swt.widgets.Display.readAndDispatch(Display.java:2736)\n    at net.sourceforge.rssowl.controller.GUI.runEventLoop(Unknown Source)\n    at net.sourceforge.rssowl.controller.GUI.showGui(Unknown Source)\n    at net.sourceforge.rssowl.controller.RSSOwlLoader.\u003cinit\u003e(Unknown Source)\n    at net.sourceforge.rssowl.controller.RSSOwlLoader.main(Unknown Source)\n\nIt looks as if the Display is still processing the second Cmd+Q although it has\nbeen disposed by the first Cmd+Q.\n\nBen",
    "Fixed \u003e 20051004\n\nBen, can you confirm this is FIXEDFORYOU in the latest?  Thanks.",
    "Thanks. Will let you know once my Mac tester has tested.\n\nBen",
    "Ok looks good! \n\nBen"
  ],
  "commentCreationDates": [
    "2005-09-26T09:10:12+02:00",
    "2005-10-05T02:32:41+02:00",
    "2005-10-05T09:06:55+02:00",
    "2005-10-06T09:08:02+02:00"
  ],
  "traces": [
    {
      "exceptionType": "org.eclipse.swt.SWTException",
      "message": "Device is disposed",
      "elements": [
        {
          "method": "org.eclipse.swt.SWT.error",
          "source": "SWT.java:3251"
        },
        {
          "method": "org.eclipse.swt.SWT.error",
          "source": "SWT.java:3174"
        },
        {
          "method": "org.eclipse.swt.SWT.error",
          "source": "SWT.java:3145"
        },
        {
          "method": "org.eclipse.swt.widgets.Display.error",
          "source": "Display.java:1017"
        },
        {
          "method": "org.eclipse.swt.widgets.Display.checkDevice",
          "source": "Display.java:571"
        },
        {
          "method": "org.eclipse.swt.widgets.Display.readAndDispatch",
          "source": "Display.java:2725"
        },
        {
          "method": "org.eclipse.swt.widgets.Display.release",
          "source": "Display.java:2818"
        },
        {
          "method": "org.eclipse.swt.graphics.Device.dispose",
          "source": "Device.java:202"
        },
        {
          "method": "org.eclipse.swt.widgets.Display.close",
          "source": "Display.java:844"
        },
        {
          "method": "org.eclipse.swt.widgets.Display.commandProc",
          "source": "Display.java:727"
        },
        {
          "method": "org.eclipse.swt.internal.carbon.OS.SendEventToEventTarget",
          "source": "Native Method"
        },
        {
          "method": "org.eclipse.swt.widgets.Display.readAndDispatch",
          "source": "Display.java:2736"
        },
        {
          "method": "net.sourceforge.rssowl.controller.GUI.runEventLoop",
          "source": "Unknown Source"
        },
        {
          "method": "net.sourceforge.rssowl.controller.GUI.showGui",
          "source": "Unknown Source"
        },
        {
          "method": "net.sourceforge.rssowl.controller.RSSOwlLoader.\u003cinit\u003e",
          "source": "Unknown Source"
        },
        {
          "method": "net.sourceforge.rssowl.controller.RSSOwlLoader.main",
          "source": "Unknown Source"
        }
      ],
      "number": 0,
      "commentIndex": 0,
      "bugId": "110559",
      "date": "2005-09-26T09:10:12+02:00",
      "product": "Platform",
      "component": "SWT",
      "severity": "normal"
    }
  ],
  "groupId": "110559",
  "bugId": "110559",
  "date": "2005-09-26T09:10:12+02:00",
  "product": "Platform",
  "component": "SWT",
  "severity": "normal"
}