{
  "comments": [
    "I got the following problems in the error log:\n\neclipse.buildId\u003dI20050219-1500\njava.version\u003d1.4.2_07\njava.vendor\u003dSun Microsystems Inc.\nBootLoader constants: OS\u003dsolaris, ARCH\u003dsparc, WS\u003dmotif, NL\u003den\nCommand-line arguments:  -os solaris -ws motif -arch sparc\n\n\n\n!ENTRY org.eclipse.core.resources 1 1 2005-09-30 09:40:52.806\n!MESSAGE Could not load library: libcore_3_1_0.so.  This library provides \nplatform-specific optimizations for certain file system operations.  This \nlibrary is not present on all platforms, so this may not be an error.  The \nresources plug-in will safely fall back to using java.io.File functionality.\n\n!ENTRY org.eclipse.cdt.core 4 4 2005-09-30 09:40:55.386\n!MESSAGE Background Indexer Crash Recovery\n!STACK 0\njava.lang.NoSuchMethodError: \norg.eclipse.core.resources.IProject.getContentTypeMatcher()\nLorg/eclipse/core/runtime/content/IContentTypeMatcher;\n        at org.eclipse.cdt.core.CCorePlugin.getContentType(CCorePlugin.java:883)\n        at org.eclipse.cdt.core.model.CoreModel.isValidTranslationUnitName\n(CoreModel.java:201)\n        at \norg.eclipse.cdt.internal.core.index.domsourceindexer.DOMAddFolderToIndex$1.visit\n(DOMAddFolderToIndex.java:72)\n        at org.eclipse.core.internal.resources.Resource$1.visitElement\n(Resource.java:52)\n        at org.eclipse.core.internal.watson.ElementTreeIterator.doIteration\n(ElementTreeIterator.java:81)\n        at org.eclipse.core.internal.watson.ElementTreeIterator.doIteration\n(ElementTreeIterator.java:85)\n        at org.eclipse.core.internal.watson.ElementTreeIterator.iterate\n(ElementTreeIterator.java:126)\n        at org.eclipse.core.internal.resources.Resource.accept(Resource.java:62)\n        at \norg.eclipse.cdt.internal.core.index.domsourceindexer.DOMAddFolderToIndex.execute\n(DOMAddFolderToIndex.java:66)\n        at org.eclipse.cdt.internal.core.search.processing.JobManager.run\n(JobManager.java:466)\n        at java.lang.Thread.run(Thread.java:534)",
    "Looks like a version mismatch. Are you using CDT 3.0 with Eclipse 3.0 instead \nof Eclipse 3.1?",
    "(In reply to comment #1)\n\u003e Looks like a version mismatch. Are you using CDT 3.0 with Eclipse 3.0 instead \n\u003e of Eclipse 3.1?\n\nThis is the description that appears in the \"about Eclipse Platform\" box\n\nEclipse Platform\n\nVersion: 3.1.0\nBuild id: I20050219-1500\n\n",
    "I have marked this defect as WORKSFORME.   This error only happens when you mix versions of Eclipse and CDT.  I would suggest that you re-install both from scratch in an empty directory and start with a new workspace.  If you can reproduce the problem, please re-open the defect and add the exact version of CDT (as well as Eclipse -- If you are using a different version than you already reported here)"
  ],
  "commentCreationDates": [
    "2005-09-30T11:27:10+02:00",
    "2005-09-30T13:49:57+02:00",
    "2005-09-30T14:20:44+02:00",
    "2006-08-15T18:05:36+02:00"
  ],
  "traces": [
    {
      "exceptionType": "java.lang.NoSuchMethodError",
      "message": "org.eclipse.core.resources.IProject.getContentTypeMatcher() Lorg/eclipse/core/runtime/content/IContentTypeMatcher;",
      "elements": [
        {
          "method": "org.eclipse.cdt.core.CCorePlugin.getContentType",
          "source": "CCorePlugin.java:883"
        },
        {
          "method": "org.eclipse.cdt.core.model.CoreModel.isValidTranslationUnitName",
          "source": "CoreModel.java:201"
        },
        {
          "method": "org.eclipse.cdt.internal.core.index.domsourceindexer.DOMAddFolderToIndex$1.visit",
          "source": "DOMAddFolderToIndex.java:72"
        },
        {
          "method": "org.eclipse.core.internal.resources.Resource$1.visitElement",
          "source": "Resource.java:52"
        },
        {
          "method": "org.eclipse.core.internal.watson.ElementTreeIterator.doIteration",
          "source": "ElementTreeIterator.java:81"
        },
        {
          "method": "org.eclipse.core.internal.watson.ElementTreeIterator.doIteration",
          "source": "ElementTreeIterator.java:85"
        },
        {
          "method": "org.eclipse.core.internal.watson.ElementTreeIterator.iterate",
          "source": "ElementTreeIterator.java:126"
        },
        {
          "method": "org.eclipse.core.internal.resources.Resource.accept",
          "source": "Resource.java:62"
        },
        {
          "method": "org.eclipse.cdt.internal.core.index.domsourceindexer.DOMAddFolderToIndex.execute",
          "source": "DOMAddFolderToIndex.java:66"
        },
        {
          "method": "org.eclipse.cdt.internal.core.search.processing.JobManager.run",
          "source": "JobManager.java:466"
        },
        {
          "method": "java.lang.Thread.run",
          "source": "Thread.java:534"
        }
      ],
      "number": 0,
      "commentIndex": 0,
      "bugId": "111192",
      "date": "2005-09-30T11:27:10+02:00",
      "product": "CDT",
      "component": "cdt-core",
      "severity": "blocker"
    }
  ],
  "groupId": "111192",
  "bugId": "111192",
  "date": "2005-09-30T11:27:10+02:00",
  "product": "CDT",
  "component": "cdt-core",
  "severity": "blocker"
}