{
  "comments": [
    "Build: 20020305\n\nDescription:\nI\u0027m running a benchmark that opens all the perspectives and then closes them \nall.  I loop through this 100 times and at the end of each loop I wait for all \nthe windows to finish closing before I continue.  I never make it to the second \niteration though, because I get a null pointer exception in the runnable that \nAbstractListenerActionDelegate.pageActivated puts in the event queue.\n\nThe source for AbstractListenerActionDelegate.pageActivated is as follows:\n\npublic void pageActivated(final IWorkbenchPage page) {\t\n    if (getPage() !\u003d null \u0026\u0026 getPage().equals(page)) {\n        Runnable r\u003d new Runnable() {\n            public void run() {\n                if (!getPage().getWorkbenchWindow().getShell().isDisposed()) {\n                    ISelection selection\u003d DebugSelectionManager.getDefault\n().getSelection(page,IDebugUIConstants.ID_DEBUG_VIEW);\n                    update(getAction(), selection);\n                }\n            }\n        };\n\n        getPage().getWorkbenchWindow().getShell().getDisplay().asyncExec(r);\n    }\n}\n\nIt looks to me like the runnable doesn\u0027t get to execute until after my code has \nalready closed the window and set the shell to null.\n\nStack:\norg.eclipse.swt.SWTException: Failed to execute runnable \n(java.lang.NullPointerException)\n\tat org.eclipse.swt.SWT.error(SWT.java:1887)\n\tat org.eclipse.swt.widgets.Synchronizer.runAsyncMessages\n(Synchronizer.java:96)\n\tat org.eclipse.swt.widgets.Display.runAsyncMessages(Display.java:1397)\n\tat org.eclipse.swt.widgets.Display.readAndDispatch(Display.java:1211)\n\tat org.eclipse.swt.widgets.Display.release(Display.java:1261)\n\tat org.eclipse.swt.graphics.Device.dispose(Device.java:198)\n\tat org.eclipse.ui.internal.Workbench.run(Workbench.java:688)\n\tat org.eclipse.core.internal.boot.InternalBootLoader.run\n(InternalBootLoader.java:777)\n\tat org.eclipse.core.boot.BootLoader.run(BootLoader.java:319)\n\tat java.lang.reflect.Method.invoke(Native Method)\n\tat org.eclipse.core.launcher.Main.basicRun(Main.java:151)\n\tat org.eclipse.core.launcher.Main.run(Main.java:502)\n\tat org.eclipse.core.launcher.UIMain.main(UIMain.java:52)\n*** Stack trace of contained exception ***\njava.lang.NullPointerException\n\tat \norg.eclipse.debug.internal.ui.actions.AbstractListenerActionDelegate$2.run\n(AbstractListenerActionDelegate.java:167)\n\tat org.eclipse.swt.widgets.RunnableLock.run(RunnableLock.java:29)\n\tat org.eclipse.swt.widgets.Synchronizer.runAsyncMessages\n(Synchronizer.java:93)\n\tat org.eclipse.swt.widgets.Display.runAsyncMessages(Display.java:1397)\n\tat org.eclipse.swt.widgets.Display.readAndDispatch(Display.java:1211)\n\tat org.eclipse.swt.widgets.Display.release(Display.java:1261)\n\tat org.eclipse.swt.graphics.Device.dispose(Device.java:198)\n\tat org.eclipse.ui.internal.Workbench.run(Workbench.java:688)\n\tat org.eclipse.core.internal.boot.InternalBootLoader.run\n(InternalBootLoader.java:777)\n\tat org.eclipse.core.boot.BootLoader.run(BootLoader.java:319)\n\tat java.lang.reflect.Method.invoke(Native Method)\n\tat org.eclipse.core.launcher.Main.basicRun(Main.java:151)\n\tat org.eclipse.core.launcher.Main.run(Main.java:502)\n\tat org.eclipse.core.launcher.UIMain.main(UIMain.java:52)",
    "Fixed in AbstractListenerActionDelegate.pageActivated()",
    "Please verify (Jared).",
    "Verified code."
  ],
  "commentCreationDates": [
    "2002-03-11T18:12:29+01:00",
    "2002-03-11T19:37:07+01:00",
    "2002-03-11T19:37:23+01:00",
    "2002-03-12T13:47:06+01:00"
  ],
  "traces": [
    {
      "exceptionType": "org.eclipse.swt.SWTException",
      "message": "Failed to execute runnable  (java.lang.NullPointerException)",
      "elements": [
        {
          "method": "org.eclipse.swt.SWT.error",
          "source": "SWT.java:1887"
        },
        {
          "method": "org.eclipse.swt.widgets.Synchronizer.runAsyncMessages",
          "source": "Synchronizer.java:96"
        },
        {
          "method": "org.eclipse.swt.widgets.Display.runAsyncMessages",
          "source": "Display.java:1397"
        },
        {
          "method": "org.eclipse.swt.widgets.Display.readAndDispatch",
          "source": "Display.java:1211"
        },
        {
          "method": "org.eclipse.swt.widgets.Display.release",
          "source": "Display.java:1261"
        },
        {
          "method": "org.eclipse.swt.graphics.Device.dispose",
          "source": "Device.java:198"
        },
        {
          "method": "org.eclipse.ui.internal.Workbench.run",
          "source": "Workbench.java:688"
        },
        {
          "method": "org.eclipse.core.internal.boot.InternalBootLoader.run",
          "source": "InternalBootLoader.java:777"
        },
        {
          "method": "org.eclipse.core.boot.BootLoader.run",
          "source": "BootLoader.java:319"
        },
        {
          "method": "java.lang.reflect.Method.invoke",
          "source": "Native Method"
        },
        {
          "method": "org.eclipse.core.launcher.Main.basicRun",
          "source": "Main.java:151"
        },
        {
          "method": "org.eclipse.core.launcher.Main.run",
          "source": "Main.java:502"
        },
        {
          "method": "org.eclipse.core.launcher.UIMain.main",
          "source": "UIMain.java:52"
        }
      ],
      "number": 0,
      "commentIndex": 0,
      "bugId": "11110",
      "date": "2002-03-11T18:12:29+01:00",
      "product": "Platform",
      "component": "Debug",
      "severity": "normal"
    },
    {
      "exceptionType": "java.lang.NullPointerException",
      "elements": [
        {
          "method": "org.eclipse.debug.internal.ui.actions.AbstractListenerActionDelegate$2.run",
          "source": "AbstractListenerActionDelegate.java:167"
        },
        {
          "method": "org.eclipse.swt.widgets.RunnableLock.run",
          "source": "RunnableLock.java:29"
        },
        {
          "method": "org.eclipse.swt.widgets.Synchronizer.runAsyncMessages",
          "source": "Synchronizer.java:93"
        },
        {
          "method": "org.eclipse.swt.widgets.Display.runAsyncMessages",
          "source": "Display.java:1397"
        },
        {
          "method": "org.eclipse.swt.widgets.Display.readAndDispatch",
          "source": "Display.java:1211"
        },
        {
          "method": "org.eclipse.swt.widgets.Display.release",
          "source": "Display.java:1261"
        },
        {
          "method": "org.eclipse.swt.graphics.Device.dispose",
          "source": "Device.java:198"
        },
        {
          "method": "org.eclipse.ui.internal.Workbench.run",
          "source": "Workbench.java:688"
        },
        {
          "method": "org.eclipse.core.internal.boot.InternalBootLoader.run",
          "source": "InternalBootLoader.java:777"
        },
        {
          "method": "org.eclipse.core.boot.BootLoader.run",
          "source": "BootLoader.java:319"
        },
        {
          "method": "java.lang.reflect.Method.invoke",
          "source": "Native Method"
        },
        {
          "method": "org.eclipse.core.launcher.Main.basicRun",
          "source": "Main.java:151"
        },
        {
          "method": "org.eclipse.core.launcher.Main.run",
          "source": "Main.java:502"
        },
        {
          "method": "org.eclipse.core.launcher.UIMain.main",
          "source": "UIMain.java:52"
        }
      ],
      "number": 1,
      "commentIndex": 0,
      "bugId": "11110",
      "date": "2002-03-11T18:12:29+01:00",
      "product": "Platform",
      "component": "Debug",
      "severity": "normal"
    }
  ],
  "groupId": "11110",
  "bugId": "11110",
  "date": "2002-03-11T18:12:29+01:00",
  "product": "Platform",
  "component": "Debug",
  "severity": "normal"
}