{
  "comments": [
    "I\u0027m trying to get an ITypeBinding for a parameterized type. When I pass in \njava.util.List\u003cInteger\u003e to the following method, I get an npe in the jdt code. \nSee below for stack trace:\n\n  public static ITypeBinding getTypeBinding(final String typeName, \nIJavaProject javaProject)\n    {\n        class BindingRequestor extends ASTRequestor\n        {\n            private ITypeBinding _result \u003d null;\n \n            public void acceptBinding(String bindingKey, IBinding binding)\n            {\n                if (_result \u003d\u003d null \u0026\u0026 binding !\u003d null \u0026\u0026 binding.getKind() \u003d\u003d \nIBinding.TYPE)\n                _result \u003d (ITypeBinding) binding;\n            }\n        }\n\n        String[] keys \u003d new String[] { BindingKey.createTypeBindingKey( \ntypeName ) };\n        final BindingRequestor requestor \u003d new BindingRequestor();\n        final ASTParser parser \u003d ASTParser.newParser(AST.JLS3);\n        parser.setResolveBindings(true);\n        parser.setProject(javaProject);\n        // this doesn?t really do a parse; it?s a type lookup\n        parser.createASTs(new ICompilationUnit[] {}, keys, requestor, null);\n        return requestor._result;\n    }\n\n\n\nStack Trace::\n\n\njava.lang.NullPointerException\n\n            at \norg.eclipse.jdt.internal.compiler.lookup.ParameterizedTypeBinding.initialize\n(ParameterizedTypeBinding.java:544)\n\n            at \norg.eclipse.jdt.internal.compiler.lookup.ParameterizedTypeBinding.\u003cinit\u003e\n(ParameterizedTypeBinding.java:38)\n\n            at \norg.eclipse.jdt.internal.compiler.lookup.LookupEnvironment.createParameterizedT\nype(LookupEnvironment.java:559)\n\n            at \norg.eclipse.jdt.internal.core.util.BindingKeyResolver.consumeParameterizedType\n(BindingKeyResolver.java:279)\n\n            at \norg.eclipse.jdt.internal.core.util.BindingKeyParser.parseParameterizedType\n(BindingKeyParser.java:759)\n\n            at org.eclipse.jdt.internal.core.util.BindingKeyParser.parse\n(BindingKeyParser.java:571)\n\n            at org.eclipse.jdt.internal.core.util.BindingKeyParser.parse\n(BindingKeyParser.java:540)\n\n            at \norg.eclipse.jdt.internal.core.util.BindingKeyResolver.getCompilerBinding\n(BindingKeyResolver.java:439)\n\n            at org.eclipse.jdt.core.dom.CompilationUnitResolver.resolve\n(CompilationUnitResolver.java:734)\n\n            at org.eclipse.jdt.core.dom.CompilationUnitResolver.resolve\n(CompilationUnitResolver.java:460)\n\n            at org.eclipse.jdt.core.dom.ASTParser.createASTs\n(ASTParser.java:664)\n\n            at \ncom.bea.wlw.common.core.util.ParameterizedTypeUtil.getTypeBinding\n(ParameterizedTypeUtil.java:155)\n\n            at \ncom.bea.wlw.netui.ui.dialogs.ActionOutputEditor$ListItemInfo.validateType\n(ActionOutputEditor.java:1068)\n\n            at \ncom.bea.wlw.netui.ui.dialogs.ActionOutputEditor$ListItemInfo.validate\n(ActionOutputEditor.java:1014)\n\n            at \ncom.bea.wlw.netui.ui.dialogs.ActionOutputEditor$ListItemInfo.access$9\n(ActionOutputEditor.java:1000)\n\n            at com.bea.wlw.netui.ui.dialogs.ActionOutputEditor.doValidate\n(ActionOutputEditor.java:527)\n\n            at com.bea.wlw.netui.ui.dialogs.ActionOutputEditor.loadData\n(ActionOutputEditor.java:501)\n\n            at com.bea.wlw.netui.ui.dialogs.ActionOutputEditor.\u003cinit\u003e\n(ActionOutputEditor.java:199)\n\n            at \ncom.bea.wlw.netui.ui.actions.EditActionOutputAction.newSwingDialog\n(EditActionOutputAction.java:56)\n\n            at com.bea.wlw.netui.ui.actions.SwingDialogLauncher.run\n(SwingDialogLauncher.java:78)\n\n            at com.bea.wlw.netui.ui.actions.MenuItemAction.widgetSelected\n(MenuItemAction.java:49)\n\n            at org.eclipse.swt.widgets.TypedListener.handleEvent\n(TypedListener.java:90)\n\n            at org.eclipse.swt.widgets.EventTable.sendEvent(EventTable.java:66)\n\n            at org.eclipse.swt.widgets.Widget.sendEvent(Widget.java:843)\n\n            at org.eclipse.swt.widgets.Display.runDeferredEvents\n(Display.java:3080)\n\n            at org.eclipse.swt.widgets.Display.readAndDispatch\n(Display.java:2713)\n\n            at org.eclipse.ui.internal.Workbench.runEventLoop\n(Workbench.java:1699)\n\n            at org.eclipse.ui.internal.Workbench.runUI(Workbench.java:1663)\n\n            at org.eclipse.ui.internal.Workbench.createAndRunWorkbench\n(Workbench.java:367)\n\n            at org.eclipse.ui.PlatformUI.createAndRunWorkbench\n(PlatformUI.java:143)\n\n            at org.eclipse.ui.internal.ide.IDEApplication.run\n(IDEApplication.java:103)\n\n            at org.eclipse.core.internal.runtime.PlatformActivator$1.run\n(PlatformActivator.java:226)\n\n            at org.eclipse.core.runtime.adaptor.EclipseStarter.run\n(EclipseStarter.java:376)\n\n            at org.eclipse.core.runtime.adaptor.EclipseStarter.run\n(EclipseStarter.java:163)\n\n            at sun.reflect.NativeMethodAccessorImpl.invoke0(Native Method)\n\n            at sun.reflect.NativeMethodAccessorImpl.invoke\n(NativeMethodAccessorImpl.java:39)\n\n            at sun.reflect.DelegatingMethodAccessorImpl.invoke\n(DelegatingMethodAccessorImpl.java:25)\n\n            at java.lang.reflect.Method.invoke(Method.java:585)\n\n            at org.eclipse.core.launcher.Main.invokeFramework(Main.java:334)\n\n            at org.eclipse.core.launcher.Main.basicRun(Main.java:278)\n\n            at org.eclipse.core.launcher.Main.run(Main.java:973)\n\n            at org.eclipse.core.launcher.Main.main(Main.java:948)",
    "In this case the _result should be null since the given type is incorrect.\njava.util.List\u003cjava.lang.Integer\u003e would work however.",
    "Released for 3.3M6.\nRegression tests added in org.eclipse.jdt.core.tests.dom.BatchASTCreationTests#test081/test082",
    "Verified for 3.3 M6 using build I20070320-0010"
  ],
  "commentCreationDates": [
    "2005-10-04T23:09:37+02:00",
    "2007-02-09T15:29:59+01:00",
    "2007-02-09T16:00:32+01:00",
    "2007-03-20T15:53:17+01:00"
  ],
  "traces": [
    {
      "exceptionType": "java.lang.NullPointerException",
      "elements": [
        {
          "method": "org.eclipse.jdt.internal.compiler.lookup.ParameterizedTypeBinding.initialize",
          "source": "ParameterizedTypeBinding.java:544"
        },
        {
          "method": "org.eclipse.jdt.internal.compiler.lookup.ParameterizedTypeBinding.\u003cinit\u003e",
          "source": "ParameterizedTypeBinding.java:38"
        },
        {
          "method": "org.eclipse.jdt.internal.compiler.lookup.LookupEnvironment.createParameterizedType",
          "source": "LookupEnvironment.java:559"
        },
        {
          "method": "org.eclipse.jdt.internal.core.util.BindingKeyResolver.consumeParameterizedType",
          "source": "BindingKeyResolver.java:279"
        },
        {
          "method": "org.eclipse.jdt.internal.core.util.BindingKeyParser.parseParameterizedType",
          "source": "BindingKeyParser.java:759"
        },
        {
          "method": "org.eclipse.jdt.internal.core.util.BindingKeyParser.parse",
          "source": "BindingKeyParser.java:571"
        },
        {
          "method": "org.eclipse.jdt.internal.core.util.BindingKeyParser.parse",
          "source": "BindingKeyParser.java:540"
        },
        {
          "method": "org.eclipse.jdt.internal.core.util.BindingKeyResolver.getCompilerBinding",
          "source": "BindingKeyResolver.java:439"
        },
        {
          "method": "org.eclipse.jdt.core.dom.CompilationUnitResolver.resolve",
          "source": "CompilationUnitResolver.java:734"
        },
        {
          "method": "org.eclipse.jdt.core.dom.CompilationUnitResolver.resolve",
          "source": "CompilationUnitResolver.java:460"
        },
        {
          "method": "org.eclipse.jdt.core.dom.ASTParser.createASTs",
          "source": "ASTParser.java:664"
        },
        {
          "method": "com.bea.wlw.common.core.util.ParameterizedTypeUtil.getTypeBinding",
          "source": "ParameterizedTypeUtil.java:155"
        },
        {
          "method": "com.bea.wlw.netui.ui.dialogs.ActionOutputEditor$ListItemInfo.validateType",
          "source": "ActionOutputEditor.java:1068"
        },
        {
          "method": "com.bea.wlw.netui.ui.dialogs.ActionOutputEditor$ListItemInfo.validate",
          "source": "ActionOutputEditor.java:1014"
        },
        {
          "method": "com.bea.wlw.netui.ui.dialogs.ActionOutputEditor$ListItemInfo.access$9",
          "source": "ActionOutputEditor.java:1000"
        },
        {
          "method": "com.bea.wlw.netui.ui.dialogs.ActionOutputEditor.doValidate",
          "source": "ActionOutputEditor.java:527"
        },
        {
          "method": "com.bea.wlw.netui.ui.dialogs.ActionOutputEditor.loadData",
          "source": "ActionOutputEditor.java:501"
        },
        {
          "method": "com.bea.wlw.netui.ui.dialogs.ActionOutputEditor.\u003cinit\u003e",
          "source": "ActionOutputEditor.java:199"
        },
        {
          "method": "com.bea.wlw.netui.ui.actions.EditActionOutputAction.newSwingDialog",
          "source": "EditActionOutputAction.java:56"
        },
        {
          "method": "com.bea.wlw.netui.ui.actions.SwingDialogLauncher.run",
          "source": "SwingDialogLauncher.java:78"
        },
        {
          "method": "com.bea.wlw.netui.ui.actions.MenuItemAction.widgetSelected",
          "source": "MenuItemAction.java:49"
        },
        {
          "method": "org.eclipse.swt.widgets.TypedListener.handleEvent",
          "source": "TypedListener.java:90"
        },
        {
          "method": "org.eclipse.swt.widgets.EventTable.sendEvent",
          "source": "EventTable.java:66"
        },
        {
          "method": "org.eclipse.swt.widgets.Widget.sendEvent",
          "source": "Widget.java:843"
        },
        {
          "method": "org.eclipse.swt.widgets.Display.runDeferredEvents",
          "source": "Display.java:3080"
        },
        {
          "method": "org.eclipse.swt.widgets.Display.readAndDispatch",
          "source": "Display.java:2713"
        },
        {
          "method": "org.eclipse.ui.internal.Workbench.runEventLoop",
          "source": "Workbench.java:1699"
        },
        {
          "method": "org.eclipse.ui.internal.Workbench.runUI",
          "source": "Workbench.java:1663"
        },
        {
          "method": "org.eclipse.ui.internal.Workbench.createAndRunWorkbench",
          "source": "Workbench.java:367"
        },
        {
          "method": "org.eclipse.ui.PlatformUI.createAndRunWorkbench",
          "source": "PlatformUI.java:143"
        },
        {
          "method": "org.eclipse.ui.internal.ide.IDEApplication.run",
          "source": "IDEApplication.java:103"
        },
        {
          "method": "org.eclipse.core.internal.runtime.PlatformActivator$1.run",
          "source": "PlatformActivator.java:226"
        },
        {
          "method": "org.eclipse.core.runtime.adaptor.EclipseStarter.run",
          "source": "EclipseStarter.java:376"
        },
        {
          "method": "org.eclipse.core.runtime.adaptor.EclipseStarter.run",
          "source": "EclipseStarter.java:163"
        },
        {
          "method": "sun.reflect.NativeMethodAccessorImpl.invoke0",
          "source": "Native Method"
        },
        {
          "method": "sun.reflect.NativeMethodAccessorImpl.invoke",
          "source": "NativeMethodAccessorImpl.java:39"
        },
        {
          "method": "sun.reflect.DelegatingMethodAccessorImpl.invoke",
          "source": "DelegatingMethodAccessorImpl.java:25"
        },
        {
          "method": "java.lang.reflect.Method.invoke",
          "source": "Method.java:585"
        },
        {
          "method": "org.eclipse.core.launcher.Main.invokeFramework",
          "source": "Main.java:334"
        },
        {
          "method": "org.eclipse.core.launcher.Main.basicRun",
          "source": "Main.java:278"
        },
        {
          "method": "org.eclipse.core.launcher.Main.run",
          "source": "Main.java:973"
        },
        {
          "method": "org.eclipse.core.launcher.Main.main",
          "source": "Main.java:948"
        }
      ],
      "number": 0,
      "commentIndex": 0,
      "bugId": "111529",
      "date": "2005-10-04T23:09:37+02:00",
      "product": "JDT",
      "component": "Core",
      "severity": "normal"
    }
  ],
  "groupId": "111529",
  "bugId": "111529",
  "date": "2005-10-04T23:09:37+02:00",
  "product": "JDT",
  "component": "Core",
  "severity": "normal"
}