{
  "comments": [
    "I hope you can help me because I don\u0027t know why this problem occour. \n\nWhat I just do is, I start the \"Build All\" wizzard in an updatesite-project and\nthen get this PDE Export error together with a log.zip file on the root point of\nthe update site. \nIn the logfile there is a regarding Ant log of the pde-project, that was to be\nbuilt, complaining about a failing import statement. \nBut this is strange, because if I start the build of this project manually in\nAnt it works fine. \n\nSo how can I export/build my whole updatesite at once? \n\nThanks for your help! \n\nBest Regards, Michael \n\nOutput of my PDE-Error: \njava.lang.IllegalArgumentException: Attempted to beginRule: R/, does not match\nouter scope rule:\nMultiRule[P/com.amadeus.eclipse_update-site,org.eclipse.pde.internal.ui.wizards.exports.FeatureExportJob$SchedulingRule@1621103]\n\nat org.eclipse.core.internal.runtime.Assert.isLegal(Assert.java:58) \nat org.eclipse.core.internal.jobs.ThreadJob.illegalPush(ThreadJob.java:106) \nat org.eclipse.core.internal.jobs.ThreadJob.push(ThreadJob.java:200) \nat org.eclipse.core.internal.jobs.ImplicitJobs.begin(ImplicitJobs.java:80) \nat org.eclipse.core.internal.jobs.JobManager.beginRule(JobManager.java:170) \nat org.eclipse.core.internal.resources.WorkManager.checkIn(WorkManager.java:95) \nat\norg.eclipse.core.internal.resources.Workspace.prepareOperation(Workspace.java:1628) \nat org.eclipse.core.internal.resources.Resource.refreshLocal(Resource.java:1224) \nat org.eclipse.pde.internal.ui.build.BuildSiteJob.refresh(BuildSiteJob.java:53) \nat org.eclipse.pde.internal.ui.build.BuildSiteJob.run(BuildSiteJob.java:42) \nat org.eclipse.core.internal.jobs.Worker.run(Worker.java:66)",
    "Would you be able to provide a reproduceable test case?\n",
    "(In reply to comment #1)\n\u003e Would you be able to provide a reproduceable test case?\nYes, sure!\nWhat can I deliver to you in order to help you debugging?",
    "The smaller the better.\nA workspace or a couple of projects would be good and steps to reproduce the pb\nfrom there. Also please tell me which version of eclipse you are using (help \u003e\nabout sdk \u003e build id)\nMake sure that you don\u0027t put your company\u0027s code out there :)",
    "The user had a structural pb in the features."
  ],
  "commentCreationDates": [
    "2005-10-05T16:31:40+02:00",
    "2005-11-10T22:16:16+01:00",
    "2005-11-10T22:26:56+01:00",
    "2005-11-10T22:34:28+01:00",
    "2005-11-15T14:10:23+01:00"
  ],
  "traces": [
    {
      "exceptionType": "java.lang.IllegalArgumentException",
      "message": "Attempted to beginRule: R/, does not match outer scope rule: MultiRule[P/com.amadeus.eclipse_update-site,org.eclipse.pde.internal.ui.wizards.exports.FeatureExportJob$SchedulingRule@1621103]",
      "elements": [
        {
          "method": "org.eclipse.core.internal.runtime.Assert.isLegal",
          "source": "Assert.java:58"
        },
        {
          "method": "org.eclipse.core.internal.jobs.ThreadJob.illegalPush",
          "source": "ThreadJob.java:106"
        },
        {
          "method": "org.eclipse.core.internal.jobs.ThreadJob.push",
          "source": "ThreadJob.java:200"
        },
        {
          "method": "org.eclipse.core.internal.jobs.ImplicitJobs.begin",
          "source": "ImplicitJobs.java:80"
        },
        {
          "method": "org.eclipse.core.internal.jobs.JobManager.beginRule",
          "source": "JobManager.java:170"
        },
        {
          "method": "org.eclipse.core.internal.resources.WorkManager.checkIn",
          "source": "WorkManager.java:95"
        },
        {
          "method": "org.eclipse.core.internal.resources.Workspace.prepareOperation",
          "source": "Workspace.java:1628"
        },
        {
          "method": "org.eclipse.core.internal.resources.Resource.refreshLocal",
          "source": "Resource.java:1224"
        },
        {
          "method": "org.eclipse.pde.internal.ui.build.BuildSiteJob.refresh",
          "source": "BuildSiteJob.java:53"
        },
        {
          "method": "org.eclipse.pde.internal.ui.build.BuildSiteJob.run",
          "source": "BuildSiteJob.java:42"
        },
        {
          "method": "org.eclipse.core.internal.jobs.Worker.run",
          "source": "Worker.java:66"
        }
      ],
      "number": 0,
      "commentIndex": 0,
      "bugId": "111614",
      "date": "2005-10-05T16:31:40+02:00",
      "product": "PDE",
      "component": "Build",
      "severity": "major"
    }
  ],
  "groupId": "111614",
  "bugId": "111614",
  "date": "2005-10-05T16:31:40+02:00",
  "product": "PDE",
  "component": "Build",
  "severity": "major"
}