{
  "comments": [
    "I20051004-0800\n\n- create CVS connection :pserver:anonymous@dev.eclipse.org:/cvsroot/eclipse\n- check out org.eclipse.core.expressions\n\u003d\u003e synchronizes without any problems\n\n- delete file org.eclipse.core.expressions/ElementHandler.java\n\u003d\u003e synchronizing the project results in the timeout below. This prevents out\nco-op from submitting patches :-(. Replacing the whole package from HEAD\nrestores normal operation.\n\nPlease move to Community/CVS if you think that\u0027s an issue with the\ndev.eclipse.org CVS server.\n\nLog:\n\n!ENTRY org.eclipse.team.core 4 0 2005-10-07 19:57:20.571\n!MESSAGE Problems reported while synchronizing CVS Workspace. 0 of 1 resources\nwere synchronized.\n!SUBENTRY 1 org.eclipse.team.core 4 0 2005-10-07 19:57:20.571\n!MESSAGE An error occurred synchronizing /org.eclipse.core.expressions: I/O has\nbeen interrupted.\n!STACK 1\norg.eclipse.team.internal.ccvs.core.connection.CVSCommunicationException[0]:\njava.io.InterruptedIOException: Timeout while reading from input stream\n        at\norg.eclipse.team.internal.core.streams.PollingInputStream.read(PollingInputStream.java:125)\n        at java.io.BufferedInputStream.fill(BufferedInputStream.java:218)\n        at java.io.BufferedInputStream.read(BufferedInputStream.java:235)\n        at\norg.eclipse.team.internal.ccvs.core.connection.Connection.readLine(Connection.java:144)\n        at\norg.eclipse.team.internal.ccvs.core.client.Session.readLine(Session.java:293)\n        at\norg.eclipse.team.internal.ccvs.core.client.Request.executeRequest(Request.java:142)\n        at\norg.eclipse.team.internal.ccvs.core.client.Command.doExecute(Command.java:404)\n        at\norg.eclipse.team.internal.ccvs.core.client.Update.doExecute(Update.java:187)\n        at\norg.eclipse.team.internal.ccvs.core.client.Command$1.run(Command.java:323)\n        at\norg.eclipse.team.internal.ccvs.core.client.Command.execute(Command.java:337)\n        at\norg.eclipse.team.internal.ccvs.core.resources.RemoteFolderTreeBuilder.fetchDelta(RemoteFolderTreeBuilder.java:618)\n        at\norg.eclipse.team.internal.ccvs.core.resources.RemoteFolderTreeBuilder.fetchDelta(RemoteFolderTreeBuilder.java:191)\n        at\norg.eclipse.team.internal.ccvs.core.resources.RemoteFolderTreeBuilder.buildTree(RemoteFolderTreeBuilder.java:156)\n        at\norg.eclipse.team.internal.ccvs.core.resources.RemoteFolderTreeBuilder.buildRemoteTree(RemoteFolderTreeBuilder.java:139)\n        at\norg.eclipse.team.internal.ccvs.core.resources.CVSWorkspaceRoot.getRemoteTree(CVSWorkspaceRoot.java:180)\n        at\norg.eclipse.team.internal.ccvs.core.syncinfo.CVSResourceVariantTree.fetchVariant(CVSResourceVariantTree.java:80)\n        at\norg.eclipse.team.core.variants.AbstractResourceVariantTree.refresh(AbstractResourceVariantTree.java:86)\n        at\norg.eclipse.team.internal.ccvs.core.syncinfo.CVSResourceVariantTree.refresh(CVSResourceVariantTree.java:327)\n        at\norg.eclipse.team.core.variants.AbstractResourceVariantTree.refresh(AbstractResourceVariantTree.java:55)\n        at\norg.eclipse.team.core.variants.ResourceVariantTreeSubscriber.refresh(ResourceVariantTreeSubscriber.java:160)\n        at\norg.eclipse.team.core.variants.ResourceVariantTreeSubscriber.refresh(ResourceVariantTreeSubscriber.java:125)\n        at\norg.eclipse.team.internal.ui.synchronize.RefreshSubscriberJob.run(RefreshSubscriberJob.java:341)\n        at org.eclipse.core.internal.jobs.Worker.run(Worker.java:76)\n!SUBENTRY 2 org.eclipse.team.cvs.core 4 0 2005-10-07 19:57:20.587\n!MESSAGE I/O has been interrupted.\n!STACK 0\njava.io.InterruptedIOException: Timeout while reading from input stream\n        at\norg.eclipse.team.internal.core.streams.PollingInputStream.read(PollingInputStream.java:125)\n        at java.io.BufferedInputStream.fill(BufferedInputStream.java:218)\n        at java.io.BufferedInputStream.read(BufferedInputStream.java:235)\n        at\norg.eclipse.team.internal.ccvs.core.connection.Connection.readLine(Connection.java:144)\n        at\norg.eclipse.team.internal.ccvs.core.client.Session.readLine(Session.java:293)\n        at\norg.eclipse.team.internal.ccvs.core.client.Request.executeRequest(Request.java:142)\n        at\norg.eclipse.team.internal.ccvs.core.client.Command.doExecute(Command.java:404)\n        at\norg.eclipse.team.internal.ccvs.core.client.Update.doExecute(Update.java:187)\n        at\norg.eclipse.team.internal.ccvs.core.client.Command$1.run(Command.java:323)\n        at\norg.eclipse.team.internal.ccvs.core.client.Command.execute(Command.java:337)\n        at\norg.eclipse.team.internal.ccvs.core.resources.RemoteFolderTreeBuilder.fetchDelta(RemoteFolderTreeBuilder.java:618)\n        at\norg.eclipse.team.internal.ccvs.core.resources.RemoteFolderTreeBuilder.fetchDelta(RemoteFolderTreeBuilder.java:191)\n        at\norg.eclipse.team.internal.ccvs.core.resources.RemoteFolderTreeBuilder.buildTree(RemoteFolderTreeBuilder.java:156)\n        at\norg.eclipse.team.internal.ccvs.core.resources.RemoteFolderTreeBuilder.buildRemoteTree(RemoteFolderTreeBuilder.java:139)\n        at\norg.eclipse.team.internal.ccvs.core.resources.CVSWorkspaceRoot.getRemoteTree(CVSWorkspaceRoot.java:180)\n        at\norg.eclipse.team.internal.ccvs.core.syncinfo.CVSResourceVariantTree.fetchVariant(CVSResourceVariantTree.java:80)\n        at\norg.eclipse.team.core.variants.AbstractResourceVariantTree.refresh(AbstractResourceVariantTree.java:86)\n        at\norg.eclipse.team.internal.ccvs.core.syncinfo.CVSResourceVariantTree.refresh(CVSResourceVariantTree.java:327)\n        at\norg.eclipse.team.core.variants.AbstractResourceVariantTree.refresh(AbstractResourceVariantTree.java:55)\n        at\norg.eclipse.team.core.variants.ResourceVariantTreeSubscriber.refresh(ResourceVariantTreeSubscriber.java:160)\n        at\norg.eclipse.team.core.variants.ResourceVariantTreeSubscriber.refresh(ResourceVariantTreeSubscriber.java:125)\n        at\norg.eclipse.team.internal.ui.synchronize.RefreshSubscriberJob.run(RefreshSubscriberJob.java:341)\n        at org.eclipse.core.internal.jobs.Worker.run(Worker.java:76)\n!SUBENTRY 3 org.eclipse.team.cvs.core 4 4 2005-10-07 19:57:20.618\n!MESSAGE The most likely cause of the interrupt is either an intermittent\nnetwork failure or a communications timeout.\n!SUBENTRY 3 org.eclipse.team.cvs.core 4 4 2005-10-07 19:57:20.618\n!MESSAGE The CVS communications timeout can be adjusted in the Team/CVS preferences.\n!SUBENTRY 3 org.eclipse.team.cvs.core 4 4 2005-10-07 19:57:20.618\n!MESSAGE Another possible cause is the improper configuration of the \"ext\"\nconnection method.\n!SUBENTRY 3 org.eclipse.team.cvs.core 4 4 2005-10-07 19:57:20.634\n!MESSAGE The \"ext\" connection method can be configured on the Team/CVS/EXT\nConnection Method preference page",
    "Did you increase the CVS timeout to see if that helped?",
    "Yes, we increased it to 600s, but the problem remained the same (timeout\nexception after waiting for 10 minutes). With the same connection, I don\u0027t have\nproblems with changed or added files - only deletions seem to cause harm.\n\nI also tried it with eclipse 3.0.2 and got the same problem. I guess this\nproblem now occurs because of a new CVS server version.",
    "It worked for me the first time I tried it but the second time I got a \ndifferent timeout (below). The third time, it worked again. Moving to \nCommunity/CVS as this does not appear to be an Eclipse problem:\n\norg.eclipse.team.internal.ccvs.core.connection.CVSCommunicationException[-6]: \njava.net.SocketException: Operation timed out: connect:could be due to invalid \naddress\nat java.net.PlainSocketImpl.socketConnect(Native Method)\nat java.net.PlainSocketImpl.doConnect(PlainSocketImpl.java:336)\nat java.net.PlainSocketImpl.connectToAddress(PlainSocketImpl.java:201)\nat java.net.PlainSocketImpl.connect(PlainSocketImpl.java:188)\nat java.net.Socket.connect(Socket.java:478)\nat java.net.Socket.connect(Socket.java:428)\nat java.net.Socket.\u003cinit\u003e(Socket.java:335)\nat java.net.Socket.\u003cinit\u003e(Socket.java:150)\nat org.eclipse.team.internal.ccvs.core.util.Util$1.run(Util.java:181)\nat java.lang.Thread.run(Thread.java:816)\n",
    "I tested this from my home cable connection, and can\u0027t reproduce.\n\nI set up pserver connection as explained, checked out\norg.eclipse.core.expressions, deleted\norg.eclipse.core.expressions/ElementHandler.java and Synchronize with repository\nworked fine about 10 times in a row.\n\nI then introduced a 2-minute delay, re-Sync and all was well.  I then Override\nand Update to refetch the deleted file, deleted it again, waited 10 minutes,\nSync with repo.  Worked fine.\n\nClosing as worksforme.  As per bug 113351, we were having intermittent CVS\nissues with some of the nodes, and those were solved recently.  Feel free to\nreopen if this problem persists.\n\nD.",
    "Reopening. We still or again have the same problem. I\u0027m not sure whether it worked at any point in time, since most of the patches we make don\u0027t delete files.\n\nI verified with the link on the committers page that our DNS should be OK:\n\"Your DNS seems okay! Thanks!\"\nThe IP address given there is not the address in our local LAN, but I don\u0027t think that should be a problem here.",
    "Despite my best efforts, I can\u0027t reproduce this.  I even tried on a 28.8 modem (!!!)\n\nSorry guys, if I can\u0027t reproduce it, I\u0027m powerless.\n\nD."
  ],
  "commentCreationDates": [
    "2005-10-07T20:15:38+02:00",
    "2005-10-08T19:29:07+02:00",
    "2005-10-08T21:16:05+02:00",
    "2005-10-11T15:25:04+02:00",
    "2005-11-01T19:35:58+01:00",
    "2005-11-22T14:16:00+01:00",
    "2005-12-16T21:22:20+01:00"
  ],
  "traces": [
    {
      "exceptionType": "java.io.InterruptedIOException",
      "message": "Timeout while reading from input stream",
      "elements": [
        {
          "method": "org.eclipse.team.internal.core.streams.PollingInputStream.read",
          "source": "PollingInputStream.java:125"
        },
        {
          "method": "java.io.BufferedInputStream.fill",
          "source": "BufferedInputStream.java:218"
        },
        {
          "method": "java.io.BufferedInputStream.read",
          "source": "BufferedInputStream.java:235"
        },
        {
          "method": "org.eclipse.team.internal.ccvs.core.connection.Connection.readLine",
          "source": "Connection.java:144"
        },
        {
          "method": "org.eclipse.team.internal.ccvs.core.client.Session.readLine",
          "source": "Session.java:293"
        },
        {
          "method": "org.eclipse.team.internal.ccvs.core.client.Request.executeRequest",
          "source": "Request.java:142"
        },
        {
          "method": "org.eclipse.team.internal.ccvs.core.client.Command.doExecute",
          "source": "Command.java:404"
        },
        {
          "method": "org.eclipse.team.internal.ccvs.core.client.Update.doExecute",
          "source": "Update.java:187"
        },
        {
          "method": "org.eclipse.team.internal.ccvs.core.client.Command$1.run",
          "source": "Command.java:323"
        },
        {
          "method": "org.eclipse.team.internal.ccvs.core.client.Command.execute",
          "source": "Command.java:337"
        },
        {
          "method": "org.eclipse.team.internal.ccvs.core.resources.RemoteFolderTreeBuilder.fetchDelta",
          "source": "RemoteFolderTreeBuilder.java:618"
        },
        {
          "method": "org.eclipse.team.internal.ccvs.core.resources.RemoteFolderTreeBuilder.fetchDelta",
          "source": "RemoteFolderTreeBuilder.java:191"
        },
        {
          "method": "org.eclipse.team.internal.ccvs.core.resources.RemoteFolderTreeBuilder.buildTree",
          "source": "RemoteFolderTreeBuilder.java:156"
        },
        {
          "method": "org.eclipse.team.internal.ccvs.core.resources.RemoteFolderTreeBuilder.buildRemoteTree",
          "source": "RemoteFolderTreeBuilder.java:139"
        },
        {
          "method": "org.eclipse.team.internal.ccvs.core.resources.CVSWorkspaceRoot.getRemoteTree",
          "source": "CVSWorkspaceRoot.java:180"
        },
        {
          "method": "org.eclipse.team.internal.ccvs.core.syncinfo.CVSResourceVariantTree.fetchVariant",
          "source": "CVSResourceVariantTree.java:80"
        },
        {
          "method": "org.eclipse.team.core.variants.AbstractResourceVariantTree.refresh",
          "source": "AbstractResourceVariantTree.java:86"
        },
        {
          "method": "org.eclipse.team.internal.ccvs.core.syncinfo.CVSResourceVariantTree.refresh",
          "source": "CVSResourceVariantTree.java:327"
        },
        {
          "method": "org.eclipse.team.core.variants.AbstractResourceVariantTree.refresh",
          "source": "AbstractResourceVariantTree.java:55"
        },
        {
          "method": "org.eclipse.team.core.variants.ResourceVariantTreeSubscriber.refresh",
          "source": "ResourceVariantTreeSubscriber.java:160"
        },
        {
          "method": "org.eclipse.team.core.variants.ResourceVariantTreeSubscriber.refresh",
          "source": "ResourceVariantTreeSubscriber.java:125"
        },
        {
          "method": "org.eclipse.team.internal.ui.synchronize.RefreshSubscriberJob.run",
          "source": "RefreshSubscriberJob.java:341"
        },
        {
          "method": "org.eclipse.core.internal.jobs.Worker.run",
          "source": "Worker.java:76"
        }
      ],
      "number": 0,
      "commentIndex": 0,
      "bugId": "111966",
      "date": "2005-10-07T20:15:38+02:00",
      "product": "Community",
      "component": "CVS",
      "severity": "major"
    },
    {
      "exceptionType": "java.io.InterruptedIOException",
      "message": "Timeout while reading from input stream",
      "elements": [
        {
          "method": "org.eclipse.team.internal.core.streams.PollingInputStream.read",
          "source": "PollingInputStream.java:125"
        },
        {
          "method": "java.io.BufferedInputStream.fill",
          "source": "BufferedInputStream.java:218"
        },
        {
          "method": "java.io.BufferedInputStream.read",
          "source": "BufferedInputStream.java:235"
        },
        {
          "method": "org.eclipse.team.internal.ccvs.core.connection.Connection.readLine",
          "source": "Connection.java:144"
        },
        {
          "method": "org.eclipse.team.internal.ccvs.core.client.Session.readLine",
          "source": "Session.java:293"
        },
        {
          "method": "org.eclipse.team.internal.ccvs.core.client.Request.executeRequest",
          "source": "Request.java:142"
        },
        {
          "method": "org.eclipse.team.internal.ccvs.core.client.Command.doExecute",
          "source": "Command.java:404"
        },
        {
          "method": "org.eclipse.team.internal.ccvs.core.client.Update.doExecute",
          "source": "Update.java:187"
        },
        {
          "method": "org.eclipse.team.internal.ccvs.core.client.Command$1.run",
          "source": "Command.java:323"
        },
        {
          "method": "org.eclipse.team.internal.ccvs.core.client.Command.execute",
          "source": "Command.java:337"
        },
        {
          "method": "org.eclipse.team.internal.ccvs.core.resources.RemoteFolderTreeBuilder.fetchDelta",
          "source": "RemoteFolderTreeBuilder.java:618"
        },
        {
          "method": "org.eclipse.team.internal.ccvs.core.resources.RemoteFolderTreeBuilder.fetchDelta",
          "source": "RemoteFolderTreeBuilder.java:191"
        },
        {
          "method": "org.eclipse.team.internal.ccvs.core.resources.RemoteFolderTreeBuilder.buildTree",
          "source": "RemoteFolderTreeBuilder.java:156"
        },
        {
          "method": "org.eclipse.team.internal.ccvs.core.resources.RemoteFolderTreeBuilder.buildRemoteTree",
          "source": "RemoteFolderTreeBuilder.java:139"
        },
        {
          "method": "org.eclipse.team.internal.ccvs.core.resources.CVSWorkspaceRoot.getRemoteTree",
          "source": "CVSWorkspaceRoot.java:180"
        },
        {
          "method": "org.eclipse.team.internal.ccvs.core.syncinfo.CVSResourceVariantTree.fetchVariant",
          "source": "CVSResourceVariantTree.java:80"
        },
        {
          "method": "org.eclipse.team.core.variants.AbstractResourceVariantTree.refresh",
          "source": "AbstractResourceVariantTree.java:86"
        },
        {
          "method": "org.eclipse.team.internal.ccvs.core.syncinfo.CVSResourceVariantTree.refresh",
          "source": "CVSResourceVariantTree.java:327"
        },
        {
          "method": "org.eclipse.team.core.variants.AbstractResourceVariantTree.refresh",
          "source": "AbstractResourceVariantTree.java:55"
        },
        {
          "method": "org.eclipse.team.core.variants.ResourceVariantTreeSubscriber.refresh",
          "source": "ResourceVariantTreeSubscriber.java:160"
        },
        {
          "method": "org.eclipse.team.core.variants.ResourceVariantTreeSubscriber.refresh",
          "source": "ResourceVariantTreeSubscriber.java:125"
        },
        {
          "method": "org.eclipse.team.internal.ui.synchronize.RefreshSubscriberJob.run",
          "source": "RefreshSubscriberJob.java:341"
        },
        {
          "method": "org.eclipse.core.internal.jobs.Worker.run",
          "source": "Worker.java:76"
        }
      ],
      "number": 1,
      "commentIndex": 0,
      "bugId": "111966",
      "date": "2005-10-07T20:15:38+02:00",
      "product": "Community",
      "component": "CVS",
      "severity": "major"
    },
    {
      "exceptionType": "java.net.SocketException",
      "message": "Operation timed out: connect:could be due to invalid  address",
      "elements": [
        {
          "method": "java.net.PlainSocketImpl.socketConnect",
          "source": "Native Method"
        },
        {
          "method": "java.net.PlainSocketImpl.doConnect",
          "source": "PlainSocketImpl.java:336"
        },
        {
          "method": "java.net.PlainSocketImpl.connectToAddress",
          "source": "PlainSocketImpl.java:201"
        },
        {
          "method": "java.net.PlainSocketImpl.connect",
          "source": "PlainSocketImpl.java:188"
        },
        {
          "method": "java.net.Socket.connect",
          "source": "Socket.java:478"
        },
        {
          "method": "java.net.Socket.connect",
          "source": "Socket.java:428"
        },
        {
          "method": "java.net.Socket.\u003cinit\u003e",
          "source": "Socket.java:335"
        },
        {
          "method": "java.net.Socket.\u003cinit\u003e",
          "source": "Socket.java:150"
        },
        {
          "method": "org.eclipse.team.internal.ccvs.core.util.Util$1.run",
          "source": "Util.java:181"
        },
        {
          "method": "java.lang.Thread.run",
          "source": "Thread.java:816"
        }
      ],
      "number": 2,
      "commentIndex": 3,
      "bugId": "111966",
      "date": "2005-10-11T15:25:04+02:00",
      "product": "Community",
      "component": "CVS",
      "severity": "major"
    }
  ],
  "groupId": "111966",
  "bugId": "111966",
  "date": "2005-10-07T20:15:38+02:00",
  "product": "Community",
  "component": "CVS",
  "severity": "major"
}