{
  "comments": [
    "on WTP M8 plus patches when importing an ear in headless mode\nusing the ear import op we get this\n-----------------------------------------------------\nStarting workbench.\nframework search path: d:\\EJBDeployX53978\\itp\\plugins\nCreating the project.\njava.lang.IllegalArgumentException: Path for project must have only one segment.\n        at org.eclipse.core.internal.utils.Assert.isLegal(Assert.java:60)\n        at org.eclipse.core.internal.resources.WorkspaceRoot.getProject\n(WorkspaceRoot.java:134)\n        at org.eclipse.jem.util.emf.workbench.ProjectUtilities.getProject\n(ProjectUtilities.java:728)\n        at \norg.eclipse.jst.j2ee.internal.archive.operations.J2EEArtifactImportOperation.fix\nModuleReference(J2EEArtifactI\nmportOperation.java:150)\n        at \norg.eclipse.jst.j2ee.internal.archive.operations.EARComponentImportOperation.fix\nupClasspaths(EARComponentImpo\nrtOperation.java:114)\n        at \norg.eclipse.jst.j2ee.internal.archive.operations.EARComponentImportOperation.doE\nxecute(EARComponentImportOper\nation.java:79)\n        at \norg.eclipse.jst.j2ee.internal.archive.operations.J2EEArtifactImportOperation.exe\ncute(J2EEArtifactImportOperat\nion.java:53)\n        at \norg.eclipse.wst.common.frameworks.internal.datamodel.ExtendableOperationImpl.doE\nxecute(ExtendableOperationImp\nl.java:159)\n        at \norg.eclipse.wst.common.frameworks.internal.datamodel.ExtendableOperationImpl$1.r\nun(ExtendableOperationImpl.ja\nva:127)\n        at org.eclipse.core.internal.resources.Workspace.run\n(Workspace.java:1719)\n        at org.eclipse.core.internal.resources.Workspace.run\n(Workspace.java:1739)\n        at \norg.eclipse.wst.common.frameworks.internal.datamodel.ExtendableOperationImpl.exe\ncute(ExtendableOperationImpl.\njava:133)\n        at com.ibm.etools.ejbdeploy.batch.plugin.BatchExtension.importEar\n(BatchExtension.java:905)\n        at com.ibm.etools.ejbdeploy.batch.plugin.BatchExtension.runEarDeploy\n(BatchExtension.java:302)\n        at com.ibm.etools.ejbdeploy.batch.plugin.BatchExtension.access$0\n(BatchExtension.java:297)\n        at com.ibm.etools.ejbdeploy.batch.plugin.BatchExtension$RunDeploy.run\n(BatchExtension.java:280)\n        at org.eclipse.core.internal.resources.Workspace.run\n(Workspace.java:1719)\n        at org.eclipse.core.internal.resources.Workspace.run\n(Workspace.java:1739)\n        at \ncom.ibm.etools.ejbdeploy.batch.plugin.BatchExtension$RunDeploy.execute\n(BatchExtension.java:264)\n        at com.ibm.etools.ejbdeploy.batch.plugin.BatchExtension.run\n(BatchExtension.java:227)\n        at org.eclipse.core.internal.runtime.PlatformActivator$1.run\n(PlatformActivator.java:226)\n        at org.eclipse.core.runtime.adaptor.EclipseStarter.run\n(EclipseStarter.java:376)\n        at sun.reflect.NativeMethodAccessorImpl.invoke0(Native Method)\n        at sun.reflect.NativeMethodAccessorImpl.invoke\n(NativeMethodAccessorImpl.java:64)\n        at sun.reflect.DelegatingMethodAccessorImpl.invoke\n(DelegatingMethodAccessorImpl.java:43)\n        at java.lang.reflect.Method.invoke(Method.java:615)\n        at com.ibm.etools.ejbdeploy.batch.impl.BootLoaderLoader.run\n(BootLoaderLoader.java:272)\n        at com.ibm.etools.ejbdeploy.batch.impl.BatchDeploy.execute\n(BatchDeploy.java:99)\n        at com.ibm.etools.ejbdeploy.EJBDeploy.execute(EJBDeploy.java:83)",
    "We need an urgent patch for this on top of M8.",
    "code dropped.",
    "Created an attachment (id\u003d28239)\npatch for M8\n",
    "closing."
  ],
  "commentCreationDates": [
    "2005-10-12T19:24:56+02:00",
    "2005-10-12T23:06:57+02:00",
    "2005-10-13T17:21:07+02:00",
    "2005-10-13T17:21:33+02:00",
    "2005-12-09T19:39:14+01:00"
  ],
  "traces": [
    {
      "exceptionType": "java.lang.IllegalArgumentException",
      "message": "Path for project must have only one segment.",
      "elements": [
        {
          "method": "org.eclipse.core.internal.utils.Assert.isLegal",
          "source": "Assert.java:60"
        },
        {
          "method": "org.eclipse.core.internal.resources.WorkspaceRoot.getProject",
          "source": "WorkspaceRoot.java:134"
        },
        {
          "method": "org.eclipse.jem.util.emf.workbench.ProjectUtilities.getProject",
          "source": "ProjectUtilities.java:728"
        },
        {
          "method": "org.eclipse.jst.j2ee.internal.archive.operations.J2EEArtifactImportOperation.fixModuleReference",
          "source": "J2EEArtifactI mportOperation.java:150"
        },
        {
          "method": "org.eclipse.jst.j2ee.internal.archive.operations.EARComponentImportOperation.fixupClasspaths",
          "source": "EARComponentImpo rtOperation.java:114"
        },
        {
          "method": "org.eclipse.jst.j2ee.internal.archive.operations.EARComponentImportOperation.doExecute",
          "source": "EARComponentImportOper ation.java:79"
        },
        {
          "method": "org.eclipse.jst.j2ee.internal.archive.operations.J2EEArtifactImportOperation.execute",
          "source": "J2EEArtifactImportOperat ion.java:53"
        },
        {
          "method": "org.eclipse.wst.common.frameworks.internal.datamodel.ExtendableOperationImpl.doExecute",
          "source": "ExtendableOperationImp l.java:159"
        },
        {
          "method": "org.eclipse.wst.common.frameworks.internal.datamodel.ExtendableOperationImpl$1.run",
          "source": "ExtendableOperationImpl.ja va:127"
        },
        {
          "method": "org.eclipse.core.internal.resources.Workspace.run",
          "source": "Workspace.java:1719"
        },
        {
          "method": "org.eclipse.core.internal.resources.Workspace.run",
          "source": "Workspace.java:1739"
        },
        {
          "method": "org.eclipse.wst.common.frameworks.internal.datamodel.ExtendableOperationImpl.execute",
          "source": "ExtendableOperationImpl. java:133"
        },
        {
          "method": "com.ibm.etools.ejbdeploy.batch.plugin.BatchExtension.importEar",
          "source": "BatchExtension.java:905"
        },
        {
          "method": "com.ibm.etools.ejbdeploy.batch.plugin.BatchExtension.runEarDeploy",
          "source": "BatchExtension.java:302"
        },
        {
          "method": "com.ibm.etools.ejbdeploy.batch.plugin.BatchExtension.access$0",
          "source": "BatchExtension.java:297"
        },
        {
          "method": "com.ibm.etools.ejbdeploy.batch.plugin.BatchExtension$RunDeploy.run",
          "source": "BatchExtension.java:280"
        },
        {
          "method": "org.eclipse.core.internal.resources.Workspace.run",
          "source": "Workspace.java:1719"
        },
        {
          "method": "org.eclipse.core.internal.resources.Workspace.run",
          "source": "Workspace.java:1739"
        },
        {
          "method": "com.ibm.etools.ejbdeploy.batch.plugin.BatchExtension$RunDeploy.execute",
          "source": "BatchExtension.java:264"
        },
        {
          "method": "com.ibm.etools.ejbdeploy.batch.plugin.BatchExtension.run",
          "source": "BatchExtension.java:227"
        },
        {
          "method": "org.eclipse.core.internal.runtime.PlatformActivator$1.run",
          "source": "PlatformActivator.java:226"
        },
        {
          "method": "org.eclipse.core.runtime.adaptor.EclipseStarter.run",
          "source": "EclipseStarter.java:376"
        },
        {
          "method": "sun.reflect.NativeMethodAccessorImpl.invoke0",
          "source": "Native Method"
        },
        {
          "method": "sun.reflect.NativeMethodAccessorImpl.invoke",
          "source": "NativeMethodAccessorImpl.java:64"
        },
        {
          "method": "sun.reflect.DelegatingMethodAccessorImpl.invoke",
          "source": "DelegatingMethodAccessorImpl.java:43"
        },
        {
          "method": "java.lang.reflect.Method.invoke",
          "source": "Method.java:615"
        },
        {
          "method": "com.ibm.etools.ejbdeploy.batch.impl.BootLoaderLoader.run",
          "source": "BootLoaderLoader.java:272"
        },
        {
          "method": "com.ibm.etools.ejbdeploy.batch.impl.BatchDeploy.execute",
          "source": "BatchDeploy.java:99"
        },
        {
          "method": "com.ibm.etools.ejbdeploy.EJBDeploy.execute",
          "source": "EJBDeploy.java:83"
        }
      ],
      "number": 0,
      "commentIndex": 0,
      "bugId": "112369",
      "date": "2005-10-12T19:24:56+02:00",
      "product": "Web Tools",
      "component": "jst.j2ee",
      "severity": "blocker"
    }
  ],
  "groupId": "112369",
  "bugId": "112369",
  "date": "2005-10-12T19:24:56+02:00",
  "product": "Web Tools",
  "component": "jst.j2ee",
  "severity": "blocker"
}