{
  "comments": [
    "On compiling a rather large set of plugins, so apologies for no test program. \nFull stack trace below, though:\n\njava.lang.IllegalStateException\nat\norg.aspectj.weaver.ResolvedMemberImpl.parameterizedWith(ResolvedMemberImpl.java:551)\nat org.aspectj.weaver.ReferenceType.getDeclaredMethods(ReferenceType.java:376)\nat org.aspectj.weaver.ResolvedType.addAndRecurse(ResolvedType.java:249)\nat org.aspectj.weaver.ResolvedType.addAndRecurse(ResolvedType.java:276)\nat org.aspectj.weaver.ResolvedType.getMethodsWithoutIterator(ResolvedType.java:244)\nat org.aspectj.weaver.ResolvedType.lookupResolvedMember(ResolvedType.java:346)\nat\norg.aspectj.weaver.JoinPointSignatureIterator.findSignaturesFromSupertypes(JoinPointSignatureIterator.java:167)\nat\norg.aspectj.weaver.JoinPointSignatureIterator.hasNext(JoinPointSignatureIterator.java:68)\nat org.aspectj.weaver.patterns.SignaturePattern.matches(SignaturePattern.java:129)\nat\norg.aspectj.weaver.patterns.WithincodePointcut.matchInternal(WithincodePointcut.java:73)\nat org.aspectj.weaver.patterns.Pointcut.match(Pointcut.java:143)\nat org.aspectj.weaver.patterns.AndPointcut.matchInternal(AndPointcut.java:55)\nat org.aspectj.weaver.patterns.Pointcut.match(Pointcut.java:143)\nat org.aspectj.weaver.patterns.AndPointcut.matchInternal(AndPointcut.java:55)\nat org.aspectj.weaver.patterns.Pointcut.match(Pointcut.java:143)\nat org.aspectj.weaver.ShadowMunger.match(ShadowMunger.java:64)\nat org.aspectj.weaver.Checker.match(Checker.java:63)\nat org.aspectj.weaver.bcel.BcelClassWeaver.match(BcelClassWeaver.java:1748)\nat\norg.aspectj.weaver.bcel.BcelClassWeaver.matchInvokeInstruction(BcelClassWeaver.java:1735)\nat org.aspectj.weaver.bcel.BcelClassWeaver.match(BcelClassWeaver.java:1532)\nat org.aspectj.weaver.bcel.BcelClassWeaver.match(BcelClassWeaver.java:1358)\nat org.aspectj.weaver.bcel.BcelClassWeaver.weave(BcelClassWeaver.java:382)\nat org.aspectj.weaver.bcel.BcelClassWeaver.weave(BcelClassWeaver.java:98)\nat org.aspectj.weaver.bcel.BcelWeaver.weave(BcelWeaver.java:1464)\nat org.aspectj.weaver.bcel.BcelWeaver.weaveWithoutDump(BcelWeaver.java:1429)\nat org.aspectj.weaver.bcel.BcelWeaver.weaveAndNotify(BcelWeaver.java:1203)\nat org.aspectj.weaver.bcel.BcelWeaver.weave(BcelWeaver.java:1039)\nat\norg.aspectj.ajdt.internal.compiler.AjCompilerAdapter.weave(AjCompilerAdapter.java:300)\nat\norg.aspectj.ajdt.internal.compiler.AjCompilerAdapter.afterCompiling(AjCompilerAdapter.java:178)\nat\norg.aspectj.ajdt.internal.compiler.CompilerAdapter.ajc$afterReturning$org_aspectj_ajdt_internal_compiler_CompilerAdapter$2$f9cc9ca0(CompilerAdapter.aj:70)\nat org.aspectj.org.eclipse.jdt.internal.compiler.Compiler.compile(Compiler.java:367)\nat\norg.aspectj.ajdt.internal.core.builder.AjBuildManager.performCompilation(AjBuildManager.java:759)\nat\norg.aspectj.ajdt.internal.core.builder.AjBuildManager.doBuild(AjBuildManager.java:225)\nat\norg.aspectj.ajdt.internal.core.builder.AjBuildManager.batchBuild(AjBuildManager.java:151)\nat org.aspectj.ajde.internal.CompilerAdapter.compile(CompilerAdapter.java:122)\nat\norg.aspectj.ajde.internal.AspectJBuildManager$CompilerThread.run(AspectJBuildManager.java:191)\n\ntrouble in: \npublic class\nde.berlios.rcpviewer.gui.acme.factory.exts.ColourAttributeGuiFactory extends\norg.essentialplatform.louis.factory.attribute.AbstractAttributeGuiFactory:\n  static final boolean $assertionsDisabled\n  static Class class$0\n  static void \u003cclinit\u003e():\n    staticinitialization(void\nde.berlios.rcpviewer.gui.acme.factory.exts.ColourAttributeGuiFactory.\u003cclinit\u003e())\n    |               LDC\nde.berlios.rcpviewer.gui.acme.factory.exts.ColourAttributeGuiFactory   (line 29)\n    | method-call(boolean java.lang.Class.desiredAssertionStatus())\n    | |             INVOKEVIRTUAL java.lang.Class.desiredAssertionStatus ()Z\n    | method-call(boolean java.lang.Class.desiredAssertionStatus())\n    |               IFNE L0\n    |               ICONST_1\n    |               GOTO L1\n    |           L0: ICONST_0\n    |           L1: PUTSTATIC\nde.berlios.rcpviewer.gui.acme.factory.exts.ColourAttributeGuiFactory.$assertionsDisabled\nZ\n    |               RETURN\n    staticinitialization(void\nde.berlios.rcpviewer.gui.acme.factory.exts.ColourAttributeGuiFactory.\u003cclinit\u003e())\n  end static void \u003cclinit\u003e()\n\n  public void \u003cinit\u003e():\n                    ALOAD_0     //\nde.berlios.rcpviewer.gui.acme.factory.exts.ColourAttributeGuiFactory this  \n(line 29)\n                    INVOKESPECIAL\norg.essentialplatform.louis.factory.attribute.AbstractAttributeGuiFactory.\u003cinit\u003e ()V\n    constructor-execution(void\nde.berlios.rcpviewer.gui.acme.factory.exts.ColourAttributeGuiFactory.\u003cinit\u003e())\n    |               RETURN\n    constructor-execution(void\nde.berlios.rcpviewer.gui.acme.factory.exts.ColourAttributeGuiFactory.\u003cinit\u003e())\n  end public void \u003cinit\u003e()\n\n  public boolean isApplicable(Object,\norg.essentialplatform.louis.factory.IGuiFactory)   \norg.aspectj.weaver.MethodDeclarationLineNumber: 35:1257\n:\n    method-execution(boolean\nde.berlios.rcpviewer.gui.acme.factory.exts.ColourAttributeGuiFactory.isApplicable(java.lang.Object,\norg.essentialplatform.louis.factory.IGuiFactory))\n    |               ALOAD_1     // java.lang.Object model   (line 36)\n    |               IFNONNULL L0\n    |               NEW java.lang.IllegalArgumentException\n    |               DUP\n    |               INVOKESPECIAL java.lang.IllegalArgumentException.\u003cinit\u003e ()V\n    |               ATHROW\n    |           L0: ALOAD_1     // java.lang.Object model   (line 37)\n    |               INSTANCEOF org.eclipse.emf.ecore.EAttribute\n    |               IFEQ L1\n    |               LDC org.eclipse.swt.graphics.Color   (line 38)\n    |               ALOAD_1     // java.lang.Object model   (line 39)\n    |               CHECKCAST org.eclipse.emf.ecore.EAttribute\n    | method-call(org.eclipse.emf.ecore.EClassifier\norg.eclipse.emf.ecore.EAttribute.getEType())\n    | |             INVOKEINTERFACE org.eclipse.emf.ecore.EAttribute.getEType\n()Lorg/eclipse/emf/ecore/EClassifier;\n    | method-call(org.eclipse.emf.ecore.EClassifier\norg.eclipse.emf.ecore.EAttribute.getEType())\n    |               INVOKEINTERFACE\norg.eclipse.emf.ecore.EClassifier.getInstanceClass ()Ljava/lang/Class;\n    |               INVOKEVIRTUAL java.lang.Object.equals (Ljava/lang/Object;)Z\n  (line 38)\n    |               IRETURN\n    |           L1: ICONST_0   (line 41)\n    |               IRETURN\n    method-execution(boolean\nde.berlios.rcpviewer.gui.acme.factory.exts.ColourAttributeGuiFactory.isApplicable(java.lang.Object,\norg.essentialplatform.louis.factory.IGuiFactory))\n  end public boolean isApplicable(Object,\norg.essentialplatform.louis.factory.IGuiFactory)\n\n  protected\norg.essentialplatform.louis.factory.attribute.AbstractAttributeFormPart\ncreateFormPart(org.eclipse.emf.ecore.EAttribute)   \norg.aspectj.weaver.MethodDeclarationLineNumber: 48:1748\n:\n                    NEW\nde.berlios.rcpviewer.gui.acme.factory.exts.ColourAttributeFormPart   (line 49)\n                    DUP\n                    ALOAD_1     // org.eclipse.emf.ecore.EAttribute model\n                    INVOKESPECIAL\nde.berlios.rcpviewer.gui.acme.factory.exts.ColourAttributeFormPart.\u003cinit\u003e\n(Lorg/eclipse/emf/ecore/EAttribute;)V\n                    ARETURN\n  end protected\norg.essentialplatform.louis.factory.attribute.AbstractAttributeFormPart\ncreateFormPart(org.eclipse.emf.ecore.EAttribute)\n\n  protected org.eclipse.swt.widgets.Text\ncreateMainControl(org.eclipse.swt.widgets.Composite,\norg.essentialplatform.louis.factory.attribute.AbstractAttributeFormPart,\norg.eclipse.emf.ecore.EAttribute, org.essentialplatform.louis.factory.GuiHints)\n   org.aspectj.weaver.MethodDeclarationLineNumber: 56:2136\n:\n                    NEW org.eclipse.swt.widgets.Text   (line 61)\n                    DUP\n                    ALOAD_1     // org.eclipse.swt.widgets.Composite parent\n                    ICONST_0\n                    INVOKESPECIAL org.eclipse.swt.widgets.Text.\u003cinit\u003e\n(Lorg/eclipse/swt/widgets/Composite;I)V\n                    ASTORE 5\n                    ALOAD 5     // org.eclipse.swt.widgets.Text text   (line 62)\n                    ALOAD_1     // org.eclipse.swt.widgets.Composite parent\n                    INVOKEVIRTUAL\norg.eclipse.swt.widgets.Composite.getBackground ()Lorg/eclipse/swt/graphics/Color;\n                    INVOKEVIRTUAL org.eclipse.swt.widgets.Text.setBackground\n(Lorg/eclipse/swt/graphics/Color;)V\n                    ALOAD 5     // org.eclipse.swt.widgets.Text text   (line 63)\n                    ICONST_0\n                    INVOKEVIRTUAL org.eclipse.swt.widgets.Text.setEditable (Z)V\n                    ALOAD 5     // org.eclipse.swt.widgets.Text text   (line 64)\n                    ALOAD_0     //\nde.berlios.rcpviewer.gui.acme.factory.exts.ColourAttributeGuiFactory this\n                    ALOAD_3     // org.eclipse.emf.ecore.EAttribute model\n                    ALOAD 4     // org.essentialplatform.louis.factory.GuiHints\nhints\n                    INVOKEVIRTUAL\nde.berlios.rcpviewer.gui.acme.factory.exts.ColourAttributeGuiFactory.isEditable\n(Lorg/eclipse/emf/ecore/EAttribute;Lorg/essentialplatform/louis/factory/GuiHints;)Z\n                    INVOKEVIRTUAL org.eclipse.swt.widgets.Text.setEnabled (Z)V\n                    ALOAD 5     // org.eclipse.swt.widgets.Text text   (line 65)\n                    ARETURN\n  end protected org.eclipse.swt.widgets.Text\ncreateMainControl(org.eclipse.swt.widgets.Composite,\norg.essentialplatform.louis.factory.attribute.AbstractAttributeFormPart,\norg.eclipse.emf.ecore.EAttribute, org.essentialplatform.louis.factory.GuiHints)\n\n  protected org.eclipse.swt.widgets.Control[]\ncreateAdditionalEditControls(org.eclipse.swt.widgets.Composite,\norg.essentialplatform.louis.factory.attribute.AbstractAttributeFormPart,\norg.eclipse.emf.ecore.EAttribute, org.essentialplatform.louis.factory.GuiHints)\n   org.aspectj.weaver.MethodDeclarationLineNumber: 72:2783\n:\n                    GETSTATIC\nde.berlios.rcpviewer.gui.acme.factory.exts.ColourAttributeGuiFactory.$assertionsDisabled\nZ   (line 78)\n                    IFNE L0\n                    ALOAD_1     // org.eclipse.swt.widgets.Composite parent\n                    IFNONNULL L0\n                    NEW java.lang.AssertionError\n                    DUP\n                    INVOKESPECIAL java.lang.AssertionError.\u003cinit\u003e ()V\n                    ATHROW\n                L0: GETSTATIC\nde.berlios.rcpviewer.gui.acme.factory.exts.ColourAttributeGuiFactory.$assertionsDisabled\nZ   (line 79)\n                    IFNE L1\n                    ALOAD_2     //\norg.essentialplatform.louis.factory.attribute.AbstractAttributeFormPart part\n                    IFNONNULL L1\n                    NEW java.lang.AssertionError\n                    DUP\n                    INVOKESPECIAL java.lang.AssertionError.\u003cinit\u003e ()V\n                    ATHROW\n                L1: NEW org.eclipse.swt.widgets.Button   (line 80)\n                    DUP\n                    ALOAD_1     // org.eclipse.swt.widgets.Composite parent\n                    LDC 8388616\n                    INVOKESPECIAL org.eclipse.swt.widgets.Button.\u003cinit\u003e\n(Lorg/eclipse/swt/widgets/Composite;I)V\n                    ASTORE 5\n                    ALOAD 5     // org.eclipse.swt.widgets.Button change   (line 81)\n                    LDC \"...\"\n                    INVOKEVIRTUAL org.eclipse.swt.widgets.Button.setText\n(Ljava/lang/String;)V\n                    NEW org.eclipse.swt.layout.GridData   (line 82)\n                    DUP\n                    INVOKESPECIAL org.eclipse.swt.layout.GridData.\u003cinit\u003e ()V\n                    ASTORE 6\n                    ALOAD 6     // org.eclipse.swt.layout.GridData buttonData  \n(line 83)\n                    ALOAD_2     //\norg.essentialplatform.louis.factory.attribute.AbstractAttributeFormPart part\n                    INVOKEVIRTUAL\norg.essentialplatform.louis.factory.attribute.AbstractAttributeFormPart.getControl\n()Lorg/eclipse/swt/widgets/Control;\n                    CHECKCAST org.eclipse.swt.widgets.Text\n                    INVOKEVIRTUAL org.eclipse.swt.widgets.Text.getLineHeight ()I\n                    PUTFIELD org.eclipse.swt.layout.GridData.heightHint I\n                    ALOAD 5     // org.eclipse.swt.widgets.Button change   (line 84)\n                    ALOAD 6     // org.eclipse.swt.layout.GridData buttonData\n                    INVOKEVIRTUAL org.eclipse.swt.widgets.Button.setLayoutData\n(Ljava/lang/Object;)V\n                    ALOAD 5     // org.eclipse.swt.widgets.Button change   (line 85)\n                    NEW\nde.berlios.rcpviewer.gui.acme.factory.exts.ColourAttributeGuiFactory$1\n                    DUP\n                    ALOAD_0     //\nde.berlios.rcpviewer.gui.acme.factory.exts.ColourAttributeGuiFactory this\n                    ALOAD_1     // org.eclipse.swt.widgets.Composite parent\n                    ALOAD_2     //\norg.essentialplatform.louis.factory.attribute.AbstractAttributeFormPart part\n                    INVOKESPECIAL\nde.berlios.rcpviewer.gui.acme.factory.exts.ColourAttributeGuiFactory$1.\u003cinit\u003e\n(Lde/berlios/rcpviewer/gui/acme/factory/exts/ColourAttributeGuiFactory;Lorg/eclipse/swt/widgets/Composite;Lorg/essentialplatform/louis/factory/attribute/AbstractAttributeFormPart;)V\n                    INVOKEVIRTUAL\norg.eclipse.swt.widgets.Button.addSelectionListener\n(Lorg/eclipse/swt/events/SelectionListener;)V\n                    ICONST_1   (line 104)\n                    ANEWARRAY org.eclipse.swt.widgets.Control\n                    DUP\n                    ICONST_0\n                    ALOAD 5     // org.eclipse.swt.widgets.Button change\n                    AASTORE\n                    ARETURN\n  end protected org.eclipse.swt.widgets.Control[]\ncreateAdditionalEditControls(org.eclipse.swt.widgets.Composite,\norg.essentialplatform.louis.factory.attribute.AbstractAttributeFormPart,\norg.eclipse.emf.ecore.EAttribute, org.essentialplatform.louis.factory.GuiHints)\n\n  protected volatile org.eclipse.swt.widgets.Control\ncreateMainControl(org.eclipse.swt.widgets.Composite,\norg.essentialplatform.louis.factory.attribute.AbstractAttributeFormPart,\norg.eclipse.emf.ecore.EAttribute, org.essentialplatform.louis.factory.GuiHints):\n                    ALOAD_0   (line 1)\n                    ALOAD_1\n                    ALOAD_2\n                    CHECKCAST\norg.essentialplatform.louis.factory.attribute.AbstractAttributeFormPart\n                    ALOAD_3\n                    ALOAD 4\n                    INVOKEVIRTUAL\nde.berlios.rcpviewer.gui.acme.factory.exts.ColourAttributeGuiFactory.createMainControl\n(Lorg/eclipse/swt/widgets/Composite;Lorg/essentialplatform/louis/factory/attribute/AbstractAttributeFormPart;Lorg/eclipse/emf/ecore/EAttribute;Lorg/essentialplatform/louis/factory/GuiHints;)Lorg/eclipse/swt/widgets/Text;\n                    ARETURN\n  end protected volatile org.eclipse.swt.widgets.Control\ncreateMainControl(org.eclipse.swt.widgets.Composite,\norg.essentialplatform.louis.factory.attribute.AbstractAttributeFormPart,\norg.eclipse.emf.ecore.EAttribute, org.essentialplatform.louis.factory.GuiHints)\nend public class\nde.berlios.rcpviewer.gui.acme.factory.exts.ColourAttributeGuiFactory\n\nwhen matching pointcut ((withincode(* de.berlios.rcpviewer.session.IPojo+.*(..))\n\u0026\u0026 !withincode(void de.berlios.rcpviewer.session.IPojo+.addTo*(..))) \u0026\u0026\ncall(public boolean java.util.Collection+.add(java.lang.Object+)))\nwhen matching shadow method-call(org.eclipse.emf.ecore.EClassifier\norg.eclipse.emf.ecore.EAttribute.getEType())\nwhen weaving type\nde.berlios.rcpviewer.gui.acme.factory.exts.ColourAttributeGuiFactory\nwhen weaving classes \nwhen weaving \nwhen batch building\nBuildConfig[D:\\dkhaywood\\rcpviewer-workspace\\.metadata\\.plugins\\org.eclipse.ajdt.core\\de.berlios.rcpviewer.gui.acme.generated.lst]\n#Files\u003d11",
    "I have a suspicion it might be that the compiler can\u0027t cope with:\npublic class ColourAttributeGuiFactory extends\nAbstractAttributeGuiFactory\u003cColor,Text\u003e {\n\nI seem to remember something similar trying to parameterize a Comparator.",
    "Its a shame the text for the illegalstateexception has been lost - it can be\nthrown for a couple of reasons.\n\nI\u0027ve recently changed parameterization in a quest to get some generic ITDs\nworking properly.  I know its not a great answer, but can you try with a more\nrecent AspectJ?  Todays dev build includes a lot of good stuff - but it won\u0027t be\navailable in an AJDT for a few days if thats what you need to retry this.\n\n",
    "I\u0027ve tried again to reproduce this with the lastest versions of the compiler, but have been unable to do so. Somewhat unsatisfactorily (since we never managed to capture a reliably failing test case) I\u0027m going to have to close this out as \"FIXED\" (which in this case really means \"WE-HIGHLY-SUSPECT-THIS-IS-FIXED-BY-CHANGES-MADE-SINCE-THE-REPORT-WAS-FILED\"). If the problem resurfaces using the latest builds then please reopen and we will continue to investigate.\n\nThanks, Adria.n"
  ],
  "commentCreationDates": [
    "2005-10-17T23:58:48+02:00",
    "2005-10-18T00:00:33+02:00",
    "2005-10-20T18:44:52+02:00",
    "2005-11-28T11:52:28+01:00"
  ],
  "traces": [
    {
      "exceptionType": "java.lang.IllegalStateException",
      "elements": [
        {
          "method": "org.aspectj.weaver.ResolvedMemberImpl.parameterizedWith",
          "source": "ResolvedMemberImpl.java:551"
        },
        {
          "method": "org.aspectj.weaver.ReferenceType.getDeclaredMethods",
          "source": "ReferenceType.java:376"
        },
        {
          "method": "org.aspectj.weaver.ResolvedType.addAndRecurse",
          "source": "ResolvedType.java:249"
        },
        {
          "method": "org.aspectj.weaver.ResolvedType.addAndRecurse",
          "source": "ResolvedType.java:276"
        },
        {
          "method": "org.aspectj.weaver.ResolvedType.getMethodsWithoutIterator",
          "source": "ResolvedType.java:244"
        },
        {
          "method": "org.aspectj.weaver.ResolvedType.lookupResolvedMember",
          "source": "ResolvedType.java:346"
        },
        {
          "method": "org.aspectj.weaver.JoinPointSignatureIterator.findSignaturesFromSupertypes",
          "source": "JoinPointSignatureIterator.java:167"
        },
        {
          "method": "org.aspectj.weaver.JoinPointSignatureIterator.hasNext",
          "source": "JoinPointSignatureIterator.java:68"
        },
        {
          "method": "org.aspectj.weaver.patterns.SignaturePattern.matches",
          "source": "SignaturePattern.java:129"
        },
        {
          "method": "org.aspectj.weaver.patterns.WithincodePointcut.matchInternal",
          "source": "WithincodePointcut.java:73"
        },
        {
          "method": "org.aspectj.weaver.patterns.Pointcut.match",
          "source": "Pointcut.java:143"
        },
        {
          "method": "org.aspectj.weaver.patterns.AndPointcut.matchInternal",
          "source": "AndPointcut.java:55"
        },
        {
          "method": "org.aspectj.weaver.patterns.Pointcut.match",
          "source": "Pointcut.java:143"
        },
        {
          "method": "org.aspectj.weaver.patterns.AndPointcut.matchInternal",
          "source": "AndPointcut.java:55"
        },
        {
          "method": "org.aspectj.weaver.patterns.Pointcut.match",
          "source": "Pointcut.java:143"
        },
        {
          "method": "org.aspectj.weaver.ShadowMunger.match",
          "source": "ShadowMunger.java:64"
        },
        {
          "method": "org.aspectj.weaver.Checker.match",
          "source": "Checker.java:63"
        },
        {
          "method": "org.aspectj.weaver.bcel.BcelClassWeaver.match",
          "source": "BcelClassWeaver.java:1748"
        },
        {
          "method": "org.aspectj.weaver.bcel.BcelClassWeaver.matchInvokeInstruction",
          "source": "BcelClassWeaver.java:1735"
        },
        {
          "method": "org.aspectj.weaver.bcel.BcelClassWeaver.match",
          "source": "BcelClassWeaver.java:1532"
        },
        {
          "method": "org.aspectj.weaver.bcel.BcelClassWeaver.match",
          "source": "BcelClassWeaver.java:1358"
        },
        {
          "method": "org.aspectj.weaver.bcel.BcelClassWeaver.weave",
          "source": "BcelClassWeaver.java:382"
        },
        {
          "method": "org.aspectj.weaver.bcel.BcelClassWeaver.weave",
          "source": "BcelClassWeaver.java:98"
        },
        {
          "method": "org.aspectj.weaver.bcel.BcelWeaver.weave",
          "source": "BcelWeaver.java:1464"
        },
        {
          "method": "org.aspectj.weaver.bcel.BcelWeaver.weaveWithoutDump",
          "source": "BcelWeaver.java:1429"
        },
        {
          "method": "org.aspectj.weaver.bcel.BcelWeaver.weaveAndNotify",
          "source": "BcelWeaver.java:1203"
        },
        {
          "method": "org.aspectj.weaver.bcel.BcelWeaver.weave",
          "source": "BcelWeaver.java:1039"
        },
        {
          "method": "org.aspectj.ajdt.internal.compiler.AjCompilerAdapter.weave",
          "source": "AjCompilerAdapter.java:300"
        },
        {
          "method": "org.aspectj.ajdt.internal.compiler.AjCompilerAdapter.afterCompiling",
          "source": "AjCompilerAdapter.java:178"
        },
        {
          "method": "org.aspectj.ajdt.internal.compiler.CompilerAdapter.ajc$afterReturning$org_aspectj_ajdt_internal_compiler_CompilerAdapter$2$f9cc9ca0",
          "source": "CompilerAdapter.aj:70"
        },
        {
          "method": "org.aspectj.org.eclipse.jdt.internal.compiler.Compiler.compile",
          "source": "Compiler.java:367"
        },
        {
          "method": "org.aspectj.ajdt.internal.core.builder.AjBuildManager.performCompilation",
          "source": "AjBuildManager.java:759"
        },
        {
          "method": "org.aspectj.ajdt.internal.core.builder.AjBuildManager.doBuild",
          "source": "AjBuildManager.java:225"
        },
        {
          "method": "org.aspectj.ajdt.internal.core.builder.AjBuildManager.batchBuild",
          "source": "AjBuildManager.java:151"
        },
        {
          "method": "org.aspectj.ajde.internal.CompilerAdapter.compile",
          "source": "CompilerAdapter.java:122"
        },
        {
          "method": "org.aspectj.ajde.internal.AspectJBuildManager$CompilerThread.run",
          "source": "AspectJBuildManager.java:191"
        }
      ],
      "number": 0,
      "commentIndex": 0,
      "bugId": "112880",
      "date": "2005-10-17T23:58:48+02:00",
      "product": "AspectJ",
      "component": "Compiler",
      "severity": "normal"
    }
  ],
  "groupId": "112880",
  "bugId": "112880",
  "date": "2005-10-17T23:58:48+02:00",
  "product": "AspectJ",
  "component": "Compiler",
  "severity": "normal"
}