{
  "comments": [
    "I20020312\n\nAdd project to workspace. One of its natures was missing. I get the following\nerror in 0312:\n\norg.eclipse.swt.SWTException: Invalid thread access\n        at org.eclipse.swt.SWT.error(SWT.java:1887)\n        at org.eclipse.swt.SWT.error(SWT.java:1819)\n        at org.eclipse.swt.widgets.Widget.error(Widget.java:283)\n        at org.eclipse.swt.widgets.Shell.\u003cinit\u003e(Shell.java:197)\n        at org.eclipse.swt.widgets.Shell.\u003cinit\u003e(Shell.java:259)\n        at org.eclipse.jface.window.Window.createShell(Window.java:296)\n        at org.eclipse.jface.window.Window.create(Window.java:262)\n        at org.eclipse.jface.window.Window.open(Window.java:512)\n        at\norg.eclipse.pde.internal.WorkspaceModelManager.handleMissingNature(WorkspaceModelManager.java:622)\n        at\norg.eclipse.pde.internal.WorkspaceModelManager.handleResourceDelta(WorkspaceModelManager.java:353)\n        at\norg.eclipse.pde.internal.WorkspaceModelManager.resourceChanged(WorkspaceModelManager.java:517)\n        at\norg.eclipse.core.internal.events.NotificationManager$1.run(NotificationManager.java:123)\n        at\norg.eclipse.core.internal.runtime.InternalPlatform.run(InternalPlatform.java(Compiled\nCode))\n        at org.eclipse.core.runtime.Platform.run(Platform.java(Compiled Code))\n        at\norg.eclipse.core.internal.events.NotificationManager.notify(NotificationManager.java:138)\n        at\norg.eclipse.core.internal.events.NotificationManager.broadcastChanges(NotificationManager.java:62)\n        at\norg.eclipse.core.internal.resources.Workspace.broadcastChanges(Workspace.java:127)\n        at\norg.eclipse.core.internal.resources.Workspace.endOperation(Workspace.java(Compiled\nCode))\n        at org.eclipse.core.internal.resources.Workspace.run(Workspace.java:1297)\n        at\norg.eclipse.ui.actions.WorkspaceModifyOperation.run(WorkspaceModifyOperation.java:78)\n        at\norg.eclipse.jface.operation.ModalContext$ModalContextThread.run(ModalContext.java:98)",
    "This dialog has now been disabled. We will find a different way to warn users \nabout this."
  ],
  "commentCreationDates": [
    "2002-03-13T18:23:44+01:00",
    "2002-03-28T00:43:47+01:00"
  ],
  "traces": [
    {
      "exceptionType": "org.eclipse.swt.SWTException",
      "message": "Invalid thread access",
      "elements": [
        {
          "method": "org.eclipse.swt.SWT.error",
          "source": "SWT.java:1887"
        },
        {
          "method": "org.eclipse.swt.SWT.error",
          "source": "SWT.java:1819"
        },
        {
          "method": "org.eclipse.swt.widgets.Widget.error",
          "source": "Widget.java:283"
        },
        {
          "method": "org.eclipse.swt.widgets.Shell.\u003cinit\u003e",
          "source": "Shell.java:197"
        },
        {
          "method": "org.eclipse.swt.widgets.Shell.\u003cinit\u003e",
          "source": "Shell.java:259"
        },
        {
          "method": "org.eclipse.jface.window.Window.createShell",
          "source": "Window.java:296"
        },
        {
          "method": "org.eclipse.jface.window.Window.create",
          "source": "Window.java:262"
        },
        {
          "method": "org.eclipse.jface.window.Window.open",
          "source": "Window.java:512"
        },
        {
          "method": "org.eclipse.pde.internal.WorkspaceModelManager.handleMissingNature",
          "source": "WorkspaceModelManager.java:622"
        },
        {
          "method": "org.eclipse.pde.internal.WorkspaceModelManager.handleResourceDelta",
          "source": "WorkspaceModelManager.java:353"
        },
        {
          "method": "org.eclipse.pde.internal.WorkspaceModelManager.resourceChanged",
          "source": "WorkspaceModelManager.java:517"
        },
        {
          "method": "org.eclipse.core.internal.events.NotificationManager$1.run",
          "source": "NotificationManager.java:123"
        },
        {
          "method": "org.eclipse.core.internal.runtime.InternalPlatform.run",
          "source": "InternalPlatform.java(Compiled Code)"
        },
        {
          "method": "org.eclipse.core.runtime.Platform.run",
          "source": "Platform.java(Compiled Code)"
        },
        {
          "method": "org.eclipse.core.internal.events.NotificationManager.notify",
          "source": "NotificationManager.java:138"
        },
        {
          "method": "org.eclipse.core.internal.events.NotificationManager.broadcastChanges",
          "source": "NotificationManager.java:62"
        },
        {
          "method": "org.eclipse.core.internal.resources.Workspace.broadcastChanges",
          "source": "Workspace.java:127"
        },
        {
          "method": "org.eclipse.core.internal.resources.Workspace.endOperation",
          "source": "Workspace.java(Compiled Code)"
        },
        {
          "method": "org.eclipse.core.internal.resources.Workspace.run",
          "source": "Workspace.java:1297"
        },
        {
          "method": "org.eclipse.ui.actions.WorkspaceModifyOperation.run",
          "source": "WorkspaceModifyOperation.java:78"
        },
        {
          "method": "org.eclipse.jface.operation.ModalContext$ModalContextThread.run",
          "source": "ModalContext.java:98"
        }
      ],
      "number": 0,
      "commentIndex": 0,
      "bugId": "11286",
      "date": "2002-03-13T18:23:44+01:00",
      "product": "PDE",
      "component": "UI",
      "severity": "normal"
    }
  ],
  "groupId": "11286",
  "bugId": "11286",
  "date": "2002-03-13T18:23:44+01:00",
  "product": "PDE",
  "component": "UI",
  "severity": "normal"
}