{
  "comments": [
    "I\u0027m running Fedora Core4 on x86_64.  (\"Linux blue.coffinated.com\n2.6.13-1.1532_FC4 #1 Thu Oct 20 01:28:35 EDT 2005 x86_64 x86_64 x86_64\nGNU/Linux\").  I downloaded the 3.1.1 tarfile and unpacked it.  When I try to\nstart eclipse I get the splash screen and then an error dialog pointing to the\nstack trace below.  I have tried various suggestions like removing ~/.eclipse,\nusing a different workspace, using -clean.  Nothing seems to make the slightest\ndifference.  Also tried removing all the x386 gtk libs in case they were\nconfusing things.  Again, no difference. The .so file DOES, in fact exist. Any\nidea what might be going wrong?\n\n-mike\n\n\neclipse.buildId\u003dM20050929-0840\njava.version\u003d1.5.0\njava.vendor\u003dSun Microsystems Inc.\nBootLoader constants: OS\u003dlinux, ARCH\u003dx86_64, WS\u003dgtk, NL\u003den_US\nCommand-line arguments:  -os linux -ws gtk -arch x86_64 -clean -data\n/home/mhc/workspace\n\n!ENTRY org.eclipse.osgi 2005-10-24 21:29:43.414\n!MESSAGE Application error\n!STACK 1\njava.lang.UnsatisfiedLinkError:\n/usr/local/eclipse-3.1.1-64bit/configuration/org.eclipse.osgi/bundles/80/1/.cp/libswt-pi-gtk-3139.\nso:\n/usr/local/eclipse-3.1.1-64bit/configuration/org.eclipse.osgi/bundles/80/1/.cp/libswt-pi-gtk-3139.so:\ncannot open shared objec\nt file: No such file or directory\n        at java.lang.ClassLoader$NativeLibrary.load(Native Method)\n        at java.lang.ClassLoader.loadLibrary0(ClassLoader.java:1751)\n        at java.lang.ClassLoader.loadLibrary(ClassLoader.java:1660)\n        at java.lang.Runtime.loadLibrary0(Runtime.java:822)\n        at java.lang.System.loadLibrary(System.java:992)\n        at org.eclipse.swt.internal.Library.loadLibrary(Library.java:123)\n        at org.eclipse.swt.internal.gtk.OS.\u003cclinit\u003e(OS.java:19)\n        at org.eclipse.swt.internal.Converter.wcsToMbcs(Converter.java:63)\n        at org.eclipse.swt.internal.Converter.wcsToMbcs(Converter.java:54)\n        at org.eclipse.swt.widgets.Display.\u003cclinit\u003e(Display.java:122)\n        at org.eclipse.ui.internal.Workbench.createDisplay(Workbench.java:381)\n        at org.eclipse.ui.PlatformUI.createDisplay(PlatformUI.java:155)\n        at\norg.eclipse.ui.internal.ide.IDEApplication.createDisplay(IDEApplication.java:128)\n        at org.eclipse.ui.internal.ide.IDEApplication.run(IDEApplication.java:79)\n        at\norg.eclipse.core.internal.runtime.PlatformActivator$1.run(PlatformActivator.java:226)\n        at\norg.eclipse.core.runtime.adaptor.EclipseStarter.run(EclipseStarter.java:376)\n        at\norg.eclipse.core.runtime.adaptor.EclipseStarter.run(EclipseStarter.java:163)\n        at sun.reflect.NativeMethodAccessorImpl.invoke0(Native Method)\n        at\nsun.reflect.NativeMethodAccessorImpl.invoke(NativeMethodAccessorImpl.java:39)\n        at\nsun.reflect.DelegatingMethodAccessorImpl.invoke(DelegatingMethodAccessorImpl.java:25)\n        at java.lang.reflect.Method.invoke(Method.java:585)\n        at org.eclipse.core.launcher.Main.invokeFramework(Main.java:334)\n        at org.eclipse.core.launcher.Main.basicRun(Main.java:278)\n        at org.eclipse.core.launcher.Main.run(Main.java:973)\n        at org.eclipse.core.launcher.Main.main(Main.java:948)",
    "Sorry; my stupid.  I forgot the -vm option and it was trying to run it with a\n32bit JVM.",
    "I would like to print some better warning message as this is a common\nproblem, but I\u0027m not exactly sure how to safely do that (bug 85699)."
  ],
  "commentCreationDates": [
    "2005-10-25T07:25:33+02:00",
    "2005-10-25T07:31:32+02:00",
    "2005-10-25T14:52:26+02:00"
  ],
  "traces": [
    {
      "exceptionType": "java.lang.UnsatisfiedLinkError",
      "message": "/usr/local/eclipse-3.1.1-64bit/configuration/org.eclipse.osgi/bundles/80/1/.cp/libswt-pi-gtk-3139. so: /usr/local/eclipse-3.1.1-64bit/configuration/org.eclipse.osgi/bundles/80/1/.cp/libswt-pi-gtk-3139.so: cannot open shared objec t file: No such file or directory",
      "elements": [
        {
          "method": "java.lang.ClassLoader$NativeLibrary.load",
          "source": "Native Method"
        },
        {
          "method": "java.lang.ClassLoader.loadLibrary0",
          "source": "ClassLoader.java:1751"
        },
        {
          "method": "java.lang.ClassLoader.loadLibrary",
          "source": "ClassLoader.java:1660"
        },
        {
          "method": "java.lang.Runtime.loadLibrary0",
          "source": "Runtime.java:822"
        },
        {
          "method": "java.lang.System.loadLibrary",
          "source": "System.java:992"
        },
        {
          "method": "org.eclipse.swt.internal.Library.loadLibrary",
          "source": "Library.java:123"
        },
        {
          "method": "org.eclipse.swt.internal.gtk.OS.\u003cclinit\u003e",
          "source": "OS.java:19"
        },
        {
          "method": "org.eclipse.swt.internal.Converter.wcsToMbcs",
          "source": "Converter.java:63"
        },
        {
          "method": "org.eclipse.swt.internal.Converter.wcsToMbcs",
          "source": "Converter.java:54"
        },
        {
          "method": "org.eclipse.swt.widgets.Display.\u003cclinit\u003e",
          "source": "Display.java:122"
        },
        {
          "method": "org.eclipse.ui.internal.Workbench.createDisplay",
          "source": "Workbench.java:381"
        },
        {
          "method": "org.eclipse.ui.PlatformUI.createDisplay",
          "source": "PlatformUI.java:155"
        },
        {
          "method": "org.eclipse.ui.internal.ide.IDEApplication.createDisplay",
          "source": "IDEApplication.java:128"
        },
        {
          "method": "org.eclipse.ui.internal.ide.IDEApplication.run",
          "source": "IDEApplication.java:79"
        },
        {
          "method": "org.eclipse.core.internal.runtime.PlatformActivator$1.run",
          "source": "PlatformActivator.java:226"
        },
        {
          "method": "org.eclipse.core.runtime.adaptor.EclipseStarter.run",
          "source": "EclipseStarter.java:376"
        },
        {
          "method": "org.eclipse.core.runtime.adaptor.EclipseStarter.run",
          "source": "EclipseStarter.java:163"
        },
        {
          "method": "sun.reflect.NativeMethodAccessorImpl.invoke0",
          "source": "Native Method"
        },
        {
          "method": "sun.reflect.NativeMethodAccessorImpl.invoke",
          "source": "NativeMethodAccessorImpl.java:39"
        },
        {
          "method": "sun.reflect.DelegatingMethodAccessorImpl.invoke",
          "source": "DelegatingMethodAccessorImpl.java:25"
        },
        {
          "method": "java.lang.reflect.Method.invoke",
          "source": "Method.java:585"
        },
        {
          "method": "org.eclipse.core.launcher.Main.invokeFramework",
          "source": "Main.java:334"
        },
        {
          "method": "org.eclipse.core.launcher.Main.basicRun",
          "source": "Main.java:278"
        },
        {
          "method": "org.eclipse.core.launcher.Main.run",
          "source": "Main.java:973"
        },
        {
          "method": "org.eclipse.core.launcher.Main.main",
          "source": "Main.java:948"
        }
      ],
      "number": 0,
      "commentIndex": 0,
      "bugId": "113628",
      "date": "2005-10-25T07:25:33+02:00",
      "product": "Platform",
      "component": "SWT",
      "severity": "normal"
    }
  ],
  "groupId": "113628",
  "bugId": "113628",
  "date": "2005-10-25T07:25:33+02:00",
  "product": "Platform",
  "component": "SWT",
  "severity": "normal"
}