{
  "comments": [
    "I believe this was due to bad code in the \norg.eclipse.jdt.internal.debug.ui.launcher.JavaElementPropertyTester.isApplet \nmethod:\n\tprivate boolean isApplet(IJavaElement element) {\n        try {\n            IType type \u003d getType(element);\n            IType[] allSuperTypes \u003d JavaModelUtil.getAllSuperTypes(type, new \nNullProgressMonitor());\n            for (int i \u003d 0; i \u003c allSuperTypes.length; i++) {\n                IType superType \u003d allSuperTypes[i];\n                if (superType.getFullyQualifiedName().equals\n(\"java.applet.Applet\")) { //$NON-NLS-1$\n                    return true;\n                }\n            }\n        } catch (JavaModelException e) {\n        }\n        return false;\n\t}\n\nThe call to getType will (reasonably) return null if the element passed in is \nan IPackageDeclaration or an IImportDeclaration.  The isApplet method passes \nthis null to getAllSuperTypes and the NPE quickly ensues.  The isApplet method \nshould check for this null and return false.\n\nTo reproduce this turn the package or import declaration filters off in the \nnavigator and bring up the popup menu on a package or import declaration.  \nThen try to follow the Run As or Debug As cascade menus.  At this point no \ncascade appears and if you then dismiss the popup, you will find the exception \nin the Error Log view.\n\nHere is the full exception...\njava.lang.NullPointerException\n\tat org.eclipse.jdt.internal.corext.util.JavaModelUtil.getAllSuperTypes\n(Unknown Source)\n\tat \norg.eclipse.jdt.internal.debug.ui.launcher.JavaElementPropertyTester.isApplet\n(Unknown Source)\n\tat \norg.eclipse.jdt.internal.debug.ui.launcher.JavaElementPropertyTester.test\n(Unknown Source)\n\tat org.eclipse.core.internal.expressions.Property.test(Unknown Source)\n\tat org.eclipse.core.internal.expressions.TestExpression.evaluate\n(Unknown Source)\n\tat \norg.eclipse.core.internal.expressions.CompositeExpression.evaluateAnd(Unknown \nSource)\n\tat org.eclipse.core.internal.expressions.IterateExpression.evaluate\n(Unknown Source)\n\tat \norg.eclipse.core.internal.expressions.CompositeExpression.evaluateAnd(Unknown \nSource)\n\tat org.eclipse.core.internal.expressions.WithExpression.evaluate\n(Unknown Source)\n\tat \norg.eclipse.core.internal.expressions.CompositeExpression.evaluateAnd(Unknown \nSource)\n\tat org.eclipse.core.internal.expressions.EnablementExpression.evaluate\n(Unknown Source)\n\tat \norg.eclipse.debug.internal.ui.launchConfigurations.LaunchShortcutExtension.eval\nEnablementExpression(Unknown Source)\n\tat org.eclipse.debug.ui.actions.ContextualLaunchAction.isApplicable\n(Unknown Source)\n\tat org.eclipse.debug.ui.actions.ContextualLaunchAction.fillMenu\n(Unknown Source)\n\tat org.eclipse.debug.ui.actions.ContextualLaunchAction$1.menuShown\n(Unknown Source)\n\tat org.eclipse.swt.widgets.TypedListener.handleEvent(Unknown Source)\n\tat org.eclipse.swt.widgets.EventTable.sendEvent(Unknown Source)\n\tat org.eclipse.swt.widgets.Widget.sendEvent(Unknown Source)\n\tat org.eclipse.swt.widgets.Widget.sendEvent(Unknown Source)\n\tat org.eclipse.swt.widgets.Widget.sendEvent(Unknown Source)\n\tat org.eclipse.swt.widgets.Control.WM_INITMENUPOPUP(Unknown Source)\n\tat org.eclipse.swt.widgets.Control.windowProc(Unknown Source)\n\tat org.eclipse.swt.widgets.Decorations.windowProc(Unknown Source)\n\tat org.eclipse.swt.widgets.Display.windowProc(Unknown Source)\n\tat org.eclipse.swt.internal.win32.OS.TrackPopupMenu(Native Method)\n\tat org.eclipse.swt.widgets.Menu._setVisible(Unknown Source)\n\tat org.eclipse.swt.widgets.Display.runPopups(Unknown Source)\n\tat org.eclipse.swt.widgets.Display.readAndDispatch(Unknown Source)\n\tat org.eclipse.ui.internal.Workbench.runEventLoop(Unknown Source)\n\tat org.eclipse.ui.internal.Workbench.runUI(Unknown Source)\n\tat org.eclipse.ui.internal.Workbench.createAndRunWorkbench(Unknown \nSource)\n\tat org.eclipse.ui.PlatformUI.createAndRunWorkbench(Unknown Source)\n\tat org.eclipse.ui.internal.ide.IDEApplication.run(Unknown Source)\n\tat org.eclipse.core.internal.runtime.PlatformActivator$1.run(Unknown \nSource)\n\tat org.eclipse.core.runtime.adaptor.EclipseStarter.run\n(EclipseStarter.java:376)\n\tat org.eclipse.core.runtime.adaptor.EclipseStarter.run\n(EclipseStarter.java:163)\n\tat sun.reflect.NativeMethodAccessorImpl.invoke0(Native Method)\n\tat sun.reflect.NativeMethodAccessorImpl.invoke\n(NativeMethodAccessorImpl.java:85)\n\tat sun.reflect.NativeMethodAccessorImpl.invoke\n(NativeMethodAccessorImpl.java:58)\n\tat sun.reflect.DelegatingMethodAccessorImpl.invoke\n(DelegatingMethodAccessorImpl.java:60)\n\tat java.lang.reflect.Method.invoke(Method.java:391)\n\tat org.eclipse.core.launcher.Main.invokeFramework(Main.java:334)\n\tat org.eclipse.core.launcher.Main.basicRun(Main.java:278)\n\tat org.eclipse.core.launcher.Main.run(Main.java:973)\n\tat org.eclipse.core.launcher.Main.main(Main.java:948)",
    "Moving to Debug.",
    "This has been fixed while fixing bug 112455.",
    "Verified."
  ],
  "commentCreationDates": [
    "2005-10-26T19:14:56+02:00",
    "2005-10-26T20:11:34+02:00",
    "2005-10-26T20:16:09+02:00",
    "2005-10-26T20:16:42+02:00"
  ],
  "traces": [
    {
      "exceptionType": "java.lang.NullPointerException",
      "elements": [
        {
          "method": "org.eclipse.jdt.internal.corext.util.JavaModelUtil.getAllSuperTypes",
          "source": "Unknown Source"
        },
        {
          "method": "org.eclipse.jdt.internal.debug.ui.launcher.JavaElementPropertyTester.isApplet",
          "source": "Unknown Source"
        },
        {
          "method": "org.eclipse.jdt.internal.debug.ui.launcher.JavaElementPropertyTester.test",
          "source": "Unknown Source"
        },
        {
          "method": "org.eclipse.core.internal.expressions.Property.test",
          "source": "Unknown Source"
        },
        {
          "method": "org.eclipse.core.internal.expressions.TestExpression.evaluate",
          "source": "Unknown Source"
        },
        {
          "method": "org.eclipse.core.internal.expressions.CompositeExpression.evaluateAnd",
          "source": "Unknown  Source"
        },
        {
          "method": "org.eclipse.core.internal.expressions.IterateExpression.evaluate",
          "source": "Unknown Source"
        },
        {
          "method": "org.eclipse.core.internal.expressions.CompositeExpression.evaluateAnd",
          "source": "Unknown  Source"
        },
        {
          "method": "org.eclipse.core.internal.expressions.WithExpression.evaluate",
          "source": "Unknown Source"
        },
        {
          "method": "org.eclipse.core.internal.expressions.CompositeExpression.evaluateAnd",
          "source": "Unknown  Source"
        },
        {
          "method": "org.eclipse.core.internal.expressions.EnablementExpression.evaluate",
          "source": "Unknown Source"
        },
        {
          "method": "org.eclipse.debug.internal.ui.launchConfigurations.LaunchShortcutExtension.evalEnablementExpression",
          "source": "Unknown Source"
        },
        {
          "method": "org.eclipse.debug.ui.actions.ContextualLaunchAction.isApplicable",
          "source": "Unknown Source"
        },
        {
          "method": "org.eclipse.debug.ui.actions.ContextualLaunchAction.fillMenu",
          "source": "Unknown Source"
        },
        {
          "method": "org.eclipse.debug.ui.actions.ContextualLaunchAction$1.menuShown",
          "source": "Unknown Source"
        },
        {
          "method": "org.eclipse.swt.widgets.TypedListener.handleEvent",
          "source": "Unknown Source"
        },
        {
          "method": "org.eclipse.swt.widgets.EventTable.sendEvent",
          "source": "Unknown Source"
        },
        {
          "method": "org.eclipse.swt.widgets.Widget.sendEvent",
          "source": "Unknown Source"
        },
        {
          "method": "org.eclipse.swt.widgets.Widget.sendEvent",
          "source": "Unknown Source"
        },
        {
          "method": "org.eclipse.swt.widgets.Widget.sendEvent",
          "source": "Unknown Source"
        },
        {
          "method": "org.eclipse.swt.widgets.Control.WM_INITMENUPOPUP",
          "source": "Unknown Source"
        },
        {
          "method": "org.eclipse.swt.widgets.Control.windowProc",
          "source": "Unknown Source"
        },
        {
          "method": "org.eclipse.swt.widgets.Decorations.windowProc",
          "source": "Unknown Source"
        },
        {
          "method": "org.eclipse.swt.widgets.Display.windowProc",
          "source": "Unknown Source"
        },
        {
          "method": "org.eclipse.swt.internal.win32.OS.TrackPopupMenu",
          "source": "Native Method"
        },
        {
          "method": "org.eclipse.swt.widgets.Menu._setVisible",
          "source": "Unknown Source"
        },
        {
          "method": "org.eclipse.swt.widgets.Display.runPopups",
          "source": "Unknown Source"
        },
        {
          "method": "org.eclipse.swt.widgets.Display.readAndDispatch",
          "source": "Unknown Source"
        },
        {
          "method": "org.eclipse.ui.internal.Workbench.runEventLoop",
          "source": "Unknown Source"
        },
        {
          "method": "org.eclipse.ui.internal.Workbench.runUI",
          "source": "Unknown Source"
        },
        {
          "method": "org.eclipse.ui.internal.Workbench.createAndRunWorkbench",
          "source": "Unknown  Source"
        },
        {
          "method": "org.eclipse.ui.PlatformUI.createAndRunWorkbench",
          "source": "Unknown Source"
        },
        {
          "method": "org.eclipse.ui.internal.ide.IDEApplication.run",
          "source": "Unknown Source"
        },
        {
          "method": "org.eclipse.core.internal.runtime.PlatformActivator$1.run",
          "source": "Unknown  Source"
        },
        {
          "method": "org.eclipse.core.runtime.adaptor.EclipseStarter.run",
          "source": "EclipseStarter.java:376"
        },
        {
          "method": "org.eclipse.core.runtime.adaptor.EclipseStarter.run",
          "source": "EclipseStarter.java:163"
        },
        {
          "method": "sun.reflect.NativeMethodAccessorImpl.invoke0",
          "source": "Native Method"
        },
        {
          "method": "sun.reflect.NativeMethodAccessorImpl.invoke",
          "source": "NativeMethodAccessorImpl.java:85"
        },
        {
          "method": "sun.reflect.NativeMethodAccessorImpl.invoke",
          "source": "NativeMethodAccessorImpl.java:58"
        },
        {
          "method": "sun.reflect.DelegatingMethodAccessorImpl.invoke",
          "source": "DelegatingMethodAccessorImpl.java:60"
        },
        {
          "method": "java.lang.reflect.Method.invoke",
          "source": "Method.java:391"
        },
        {
          "method": "org.eclipse.core.launcher.Main.invokeFramework",
          "source": "Main.java:334"
        },
        {
          "method": "org.eclipse.core.launcher.Main.basicRun",
          "source": "Main.java:278"
        },
        {
          "method": "org.eclipse.core.launcher.Main.run",
          "source": "Main.java:973"
        },
        {
          "method": "org.eclipse.core.launcher.Main.main",
          "source": "Main.java:948"
        }
      ],
      "number": 0,
      "commentIndex": 0,
      "bugId": "113857",
      "date": "2005-10-26T19:14:56+02:00",
      "product": "JDT",
      "component": "Debug",
      "severity": "normal"
    }
  ],
  "groupId": "113857",
  "bugId": "113857",
  "date": "2005-10-26T19:14:56+02:00",
  "product": "JDT",
  "component": "Debug",
  "severity": "normal"
}