{
  "comments": [
    "In N20051029-0010, there were test failures on MacOS X.  These test failure  \nseem to have occurred somewhere within the virtual support for tables.  A \nchange for TableViewer went in at 5 p.m. the previous day. \n  \ntestSetIndexedSelection   \nFailure   \nFirst elements do not match    \n   \njunit.framework.AssertionFailedError: First elements do not match    \n at   \norg.eclipse.jface.tests.viewers.VirtualLazyTableViewerTest.testSetIndexedSelection(VirtualLazyTableViewerTest.java:93)   \n at org.eclipse.test.EclipseTestRunner.run(EclipseTestRunner.java:330)   \n at org.eclipse.test.EclipseTestRunner.run(EclipseTestRunner.java:204)   \n at org.eclipse.test.CoreTestApplication.runTests(CoreTestApplication.java:35)   \n at org.eclipse.test.CoreTestApplication.run(CoreTestApplication.java:31)   \n at   \norg.eclipse.core.internal.runtime.PlatformActivator$1.run(PlatformActivator.java:226)   \n at   \norg.eclipse.core.runtime.adaptor.EclipseStarter.run(EclipseStarter.java:376)   \n at   \norg.eclipse.core.runtime.adaptor.EclipseStarter.run(EclipseStarter.java:165)   \n at org.eclipse.core.launcher.Main.invokeFramework(Main.java:338)   \n at org.eclipse.core.launcher.Main.basicRun(Main.java:282)   \n at org.eclipse.core.launcher.Main.run(Main.java:977)   \n at org.eclipse.core.launcher.Main.main(Main.java:952)",
    "This might have been caused by changes in the tests. I will look into this tonight.",
    "Fixed on the Mac, testing on Linux/GTK and Windows XP...",
    "I want a Linux machine of my own - the one in the lab never works when I need it :-(",
    "Everything works on Windows XP - I\u0027m crossing my fingers for Linux...\n\nMarking as fixed.",
    "[I20051031-2000]\nVerified that the test ran successfully on Mac, Linux, and Windows."
  ],
  "commentCreationDates": [
    "2005-10-29T14:49:27+02:00",
    "2005-10-30T01:28:50+02:00",
    "2005-10-30T03:30:16+01:00",
    "2005-10-30T03:32:35+01:00",
    "2005-10-30T03:55:29+01:00",
    "2005-11-01T17:29:09+01:00"
  ],
  "traces": [
    {
      "exceptionType": "junit.framework.AssertionFailedError",
      "message": "First elements do not match",
      "elements": [
        {
          "method": "org.eclipse.jface.tests.viewers.VirtualLazyTableViewerTest.testSetIndexedSelection",
          "source": "VirtualLazyTableViewerTest.java:93"
        },
        {
          "method": "org.eclipse.test.EclipseTestRunner.run",
          "source": "EclipseTestRunner.java:330"
        },
        {
          "method": "org.eclipse.test.EclipseTestRunner.run",
          "source": "EclipseTestRunner.java:204"
        },
        {
          "method": "org.eclipse.test.CoreTestApplication.runTests",
          "source": "CoreTestApplication.java:35"
        },
        {
          "method": "org.eclipse.test.CoreTestApplication.run",
          "source": "CoreTestApplication.java:31"
        },
        {
          "method": "org.eclipse.core.internal.runtime.PlatformActivator$1.run",
          "source": "PlatformActivator.java:226"
        },
        {
          "method": "org.eclipse.core.runtime.adaptor.EclipseStarter.run",
          "source": "EclipseStarter.java:376"
        },
        {
          "method": "org.eclipse.core.runtime.adaptor.EclipseStarter.run",
          "source": "EclipseStarter.java:165"
        },
        {
          "method": "org.eclipse.core.launcher.Main.invokeFramework",
          "source": "Main.java:338"
        },
        {
          "method": "org.eclipse.core.launcher.Main.basicRun",
          "source": "Main.java:282"
        },
        {
          "method": "org.eclipse.core.launcher.Main.run",
          "source": "Main.java:977"
        },
        {
          "method": "org.eclipse.core.launcher.Main.main",
          "source": "Main.java:952"
        }
      ],
      "number": 0,
      "commentIndex": 0,
      "bugId": "114289",
      "date": "2005-10-29T14:49:27+02:00",
      "product": "Platform",
      "component": "UI",
      "severity": "major"
    }
  ],
  "groupId": "114289",
  "bugId": "114289",
  "date": "2005-10-29T14:49:27+02:00",
  "product": "Platform",
  "component": "UI",
  "severity": "major"
}