{
  "comments": [
    "I\u0027m using I20051101-0010, and it fails to find the shared libraries:\n\n/opt/local/eclipse/I1101-0010/eclipse/eclipse -vm \\\n  /opt/local/j2sdk1.4.2_08/bin/java\n\nGive me an error:\n/opt/local/eclipse/I1101-0010/eclipse/configuration/org.eclipse.osgi/bundles/50/1/.cp/libswt-motif-3212.so:\nld.so.1: java: fatal: libm.so.2: open failed: No such file or directory\n\n\nI have libm.so -\u003e libm.so.1\nbash$ uname -a\nSunOS unknown 5.8 Generic_117350-26 sun4u sparc SUNW,Sun-Blade-100\n\n\nthe full log:\n!SESSION 2005-11-01 09:33:38.646 -----------------------------------------------\neclipse.buildId\u003dI20051101-0010\njava.version\u003d1.4.2_09\njava.vendor\u003dSun Microsystems Inc.\nBootLoader constants: OS\u003dsolaris, ARCH\u003dsparc, WS\u003dmotif, NL\u003den_CA\nCommand-line arguments:  -os solaris -ws motif -arch sparc\n\n!ENTRY org.eclipse.osgi 2005-11-01 09:33:42.587\n!MESSAGE Application error\n!STACK 1\njava.lang.UnsatisfiedLinkError:\n/opt/local/eclipse/I1101-0010/eclipse/configuration/org.eclipse.osgi/bundles/50/1/.cp/libswt-motif-3212.so:\nld.so.1: java: fatal: libm.so.2: open failed: No such file or directory\n        at java.lang.ClassLoader$NativeLibrary.load(Native Method)\n        at java.lang.ClassLoader.loadLibrary0(ClassLoader.java:1586)\n        at java.lang.ClassLoader.loadLibrary(ClassLoader.java:1495)\n        at java.lang.Runtime.loadLibrary0(Runtime.java:788)\n        at java.lang.System.loadLibrary(System.java:834)\n        at org.eclipse.swt.internal.Library.loadLibrary(Library.java:123)\n        at org.eclipse.swt.internal.motif.OS.\u003cclinit\u003e(OS.java:18)\n        at org.eclipse.swt.graphics.Device.\u003cclinit\u003e(Device.java:113)\n        at org.eclipse.ui.internal.Workbench.createDisplay(Workbench.java:390)\n        at org.eclipse.ui.PlatformUI.createDisplay(PlatformUI.java:155)\n        at\norg.eclipse.ui.internal.ide.IDEApplication.createDisplay(IDEApplication.java:131)\n        at org.eclipse.ui.internal.ide.IDEApplication.run(IDEApplication.java:82)\n        at\norg.eclipse.core.internal.runtime.PlatformActivator$1.run(PlatformActivator.java:226)\n        at\norg.eclipse.core.runtime.adaptor.EclipseStarter.run(EclipseStarter.java:376)\n        at\norg.eclipse.core.runtime.adaptor.EclipseStarter.run(EclipseStarter.java:165)\n        at sun.reflect.NativeMethodAccessorImpl.invoke0(Native Method)\n        at\nsun.reflect.NativeMethodAccessorImpl.invoke(NativeMethodAccessorImpl.java:39)\n        at\nsun.reflect.DelegatingMethodAccessorImpl.invoke(DelegatingMethodAccessorImpl.java:25)\n        at java.lang.reflect.Method.invoke(Method.java:324)\n        at org.eclipse.core.launcher.Main.invokeFramework(Main.java:338)\n        at org.eclipse.core.launcher.Main.basicRun(Main.java:282)\n        at org.eclipse.core.launcher.Main.run(Main.java:977)\n        at org.eclipse.core.launcher.Main.main(Main.java:952)",
    "This was caused by an upgrade to the build machine to Solaris 10. As there were\nno changes to the library for this build, only a rebuild, I have replaced the\nbinaries with those from the last integration build.\n\nI am keeping this bug open to track the problem of building the libraries in the\nfuture.",
    "Fixed \u003e 20051212"
  ],
  "commentCreationDates": [
    "2005-11-01T14:42:39+01:00",
    "2005-11-01T15:31:23+01:00",
    "2005-12-12T22:44:51+01:00"
  ],
  "traces": [
    {
      "exceptionType": "java.lang.UnsatisfiedLinkError",
      "message": "/opt/local/eclipse/I1101-0010/eclipse/configuration/org.eclipse.osgi/bundles/50/1/.cp/libswt-motif-3212.so: ld.so.1: java: fatal: libm.so.2: open failed: No such file or directory",
      "elements": [
        {
          "method": "java.lang.ClassLoader$NativeLibrary.load",
          "source": "Native Method"
        },
        {
          "method": "java.lang.ClassLoader.loadLibrary0",
          "source": "ClassLoader.java:1586"
        },
        {
          "method": "java.lang.ClassLoader.loadLibrary",
          "source": "ClassLoader.java:1495"
        },
        {
          "method": "java.lang.Runtime.loadLibrary0",
          "source": "Runtime.java:788"
        },
        {
          "method": "java.lang.System.loadLibrary",
          "source": "System.java:834"
        },
        {
          "method": "org.eclipse.swt.internal.Library.loadLibrary",
          "source": "Library.java:123"
        },
        {
          "method": "org.eclipse.swt.internal.motif.OS.\u003cclinit\u003e",
          "source": "OS.java:18"
        },
        {
          "method": "org.eclipse.swt.graphics.Device.\u003cclinit\u003e",
          "source": "Device.java:113"
        },
        {
          "method": "org.eclipse.ui.internal.Workbench.createDisplay",
          "source": "Workbench.java:390"
        },
        {
          "method": "org.eclipse.ui.PlatformUI.createDisplay",
          "source": "PlatformUI.java:155"
        },
        {
          "method": "org.eclipse.ui.internal.ide.IDEApplication.createDisplay",
          "source": "IDEApplication.java:131"
        },
        {
          "method": "org.eclipse.ui.internal.ide.IDEApplication.run",
          "source": "IDEApplication.java:82"
        },
        {
          "method": "org.eclipse.core.internal.runtime.PlatformActivator$1.run",
          "source": "PlatformActivator.java:226"
        },
        {
          "method": "org.eclipse.core.runtime.adaptor.EclipseStarter.run",
          "source": "EclipseStarter.java:376"
        },
        {
          "method": "org.eclipse.core.runtime.adaptor.EclipseStarter.run",
          "source": "EclipseStarter.java:165"
        },
        {
          "method": "sun.reflect.NativeMethodAccessorImpl.invoke0",
          "source": "Native Method"
        },
        {
          "method": "sun.reflect.NativeMethodAccessorImpl.invoke",
          "source": "NativeMethodAccessorImpl.java:39"
        },
        {
          "method": "sun.reflect.DelegatingMethodAccessorImpl.invoke",
          "source": "DelegatingMethodAccessorImpl.java:25"
        },
        {
          "method": "java.lang.reflect.Method.invoke",
          "source": "Method.java:324"
        },
        {
          "method": "org.eclipse.core.launcher.Main.invokeFramework",
          "source": "Main.java:338"
        },
        {
          "method": "org.eclipse.core.launcher.Main.basicRun",
          "source": "Main.java:282"
        },
        {
          "method": "org.eclipse.core.launcher.Main.run",
          "source": "Main.java:977"
        },
        {
          "method": "org.eclipse.core.launcher.Main.main",
          "source": "Main.java:952"
        }
      ],
      "number": 0,
      "commentIndex": 0,
      "bugId": "114518",
      "date": "2005-11-01T14:42:39+01:00",
      "product": "Platform",
      "component": "SWT",
      "severity": "normal"
    }
  ],
  "groupId": "114518",
  "bugId": "114518",
  "date": "2005-11-01T14:42:39+01:00",
  "product": "Platform",
  "component": "SWT",
  "severity": "normal"
}