{
  "comments": [
    "I\u0027ve installed Mylar 0.4 from the update site and Eclipse freeze after restart.\nLog file is below.\nThat was Eclipse 3.2M1 with Mylar for 3.1 stream.\n\n!SESSION 2005-11-01 11:20:46.445 -----------------------------------------------\neclipse.buildId\u003dI20050811-1530\njava.version\u003d1.5.0_05\njava.vendor\u003dSun Microsystems Inc.\nBootLoader constants: OS\u003dwin32, ARCH\u003dx86, WS\u003dwin32, NL\u003den_US\nCommand-line arguments:  -os win32 -ws win32 -arch x86 -data C:\\eclipse3\\workspace\n\n!ENTRY org.eclipse.osgi 2005-11-01 11:21:25.579\n!MESSAGE While loading class\n\"org.eclipse.mylar.java.ui.actions.ApplyMylarToPackageExplorerAction\", thread\n\"main\" timed out waiting (5000ms) for thread \"Worker-6\" to finish starting\nbundle \"org.eclipse.mylar.java\". To avoid deadlock, thread \"main\" is proceeding\nbut \"org.eclipse.mylar.java.ui.actions.ApplyMylarToPackageExplorerAction\" may\nnot be fully initialized.\n!STACK 0\njava.lang.Exception: Generated exception.\n        at\norg.eclipse.core.runtime.adaptor.EclipseClassLoader.findLocalClass(EclipseClassLoader.java:108)\n        at\norg.eclipse.osgi.framework.internal.core.BundleLoader.findLocalClass(BundleLoader.java:337)\n        at\norg.eclipse.osgi.framework.internal.core.BundleLoader.findClass(BundleLoader.java:389)\n        at\norg.eclipse.osgi.framework.internal.core.BundleLoader.findClass(BundleLoader.java:350)\n        at\norg.eclipse.osgi.framework.adaptor.core.AbstractClassLoader.loadClass(AbstractClassLoader.java:78)\n        at java.lang.ClassLoader.loadClass(ClassLoader.java:251)\n        at java.lang.ClassLoader.loadClassInternal(ClassLoader.java:319)\n        at org.eclipse.mylar.java.MylarJavaPlugin$1.run(MylarJavaPlugin.java:112)\n        at org.eclipse.swt.widgets.RunnableLock.run(RunnableLock.java:35)\n        at\norg.eclipse.swt.widgets.Synchronizer.runAsyncMessages(Synchronizer.java:123)\n        at org.eclipse.swt.widgets.Display.runAsyncMessages(Display.java:3114)\n        at org.eclipse.swt.widgets.Display.readAndDispatch(Display.java:2768)\n        at org.eclipse.ui.internal.Workbench.runEventLoop(Workbench.java:1734)\n        at org.eclipse.ui.internal.Workbench.runUI(Workbench.java:1698)\n        at\norg.eclipse.ui.internal.Workbench.createAndRunWorkbench(Workbench.java:367)\n        at org.eclipse.ui.PlatformUI.createAndRunWorkbench(PlatformUI.java:143)\n        at org.eclipse.ui.internal.ide.IDEApplication.run(IDEApplication.java:103)\n        at\norg.eclipse.core.internal.runtime.PlatformActivator$1.run(PlatformActivator.java:226)\n        at\norg.eclipse.core.runtime.adaptor.EclipseStarter.run(EclipseStarter.java:376)\n        at\norg.eclipse.core.runtime.adaptor.EclipseStarter.run(EclipseStarter.java:163)\n        at sun.reflect.NativeMethodAccessorImpl.invoke0(Native Method)\n        at\nsun.reflect.NativeMethodAccessorImpl.invoke(NativeMethodAccessorImpl.java:39)\n        at\nsun.reflect.DelegatingMethodAccessorImpl.invoke(DelegatingMethodAccessorImpl.java:25)\n        at java.lang.reflect.Method.invoke(Method.java:585)\n        at org.eclipse.core.launcher.Main.invokeFramework(Main.java:338)\n        at org.eclipse.core.launcher.Main.basicRun(Main.java:282)\n        at org.eclipse.core.launcher.Main.run(Main.java:977)\n        at org.eclipse.core.launcher.Main.main(Main.java:952)",
    "And here I thought that we were guarding against all the lazy startup dangers...\n\nWhat was the effect of this, did you have to hit Stop on the progress dialog, or\nkill Eclipse?  Did Mylar come up properly after restart?  Also, I\u0027m curious\nabout what\u0027s forcing you to use 3.2M1 (Subclipse)?  We\u0027ll only be able to\nsupport the latest milestone of 3.2 because of the cost of merging, but\nhopefully initialization order could fix this issue for the 3.1 stream.",
    "(In reply to comment #1)\n\u003e And here I thought that we were guarding against all the lazy startup dangers...\n\nApparently not all...\n\n\u003e What was the effect of this, did you have to hit Stop on the progress dialog, or\n\u003e kill Eclipse?  \n\nThe workbench window was gray. So I had to kill it.\n\n\u003e Did Mylar come up properly after restart?  \n\nLooks like it did.\n\n\u003e Also, I\u0027m curious\n\u003e about what\u0027s forcing you to use 3.2M1 (Subclipse)?  \n\nIt doesn\u0027t seem that Subclipse is actually that sensitive (turns out that my\nworkspace have some garage that make it worse on 3.2M2). \nHowever AJDT does not have update site for 3.2 stream.\n\n\u003e We\u0027ll only be able to\n\u003e support the latest milestone of 3.2 because of the cost of merging, but\n\u003e hopefully initialization order could fix this issue for the 3.1 stream.\n\nRight. When 3.2M3 get out, I\u0027ll have to decide what I like more - new M3\nfeatures or convenience of getting new AJDT builds...",
    "Eugene, I saw this happen once and will keep an eye on it.  There was no bad\nbehavior, since this class actually does get loaded.  Let me know if you see it\nagain.",
    "Another user ran into this, scheduling for this week.\n\n\n*** This bug has been marked as a duplicate of 115496 ***"
  ],
  "commentCreationDates": [
    "2005-11-01T19:54:21+01:00",
    "2005-11-01T22:49:06+01:00",
    "2005-11-01T22:56:02+01:00",
    "2005-11-07T23:21:25+01:00",
    "2005-11-08T17:00:00+01:00"
  ],
  "traces": [
    {
      "exceptionType": "java.lang.Exception",
      "message": "Generated exception.",
      "elements": [
        {
          "method": "org.eclipse.core.runtime.adaptor.EclipseClassLoader.findLocalClass",
          "source": "EclipseClassLoader.java:108"
        },
        {
          "method": "org.eclipse.osgi.framework.internal.core.BundleLoader.findLocalClass",
          "source": "BundleLoader.java:337"
        },
        {
          "method": "org.eclipse.osgi.framework.internal.core.BundleLoader.findClass",
          "source": "BundleLoader.java:389"
        },
        {
          "method": "org.eclipse.osgi.framework.internal.core.BundleLoader.findClass",
          "source": "BundleLoader.java:350"
        },
        {
          "method": "org.eclipse.osgi.framework.adaptor.core.AbstractClassLoader.loadClass",
          "source": "AbstractClassLoader.java:78"
        },
        {
          "method": "java.lang.ClassLoader.loadClass",
          "source": "ClassLoader.java:251"
        },
        {
          "method": "java.lang.ClassLoader.loadClassInternal",
          "source": "ClassLoader.java:319"
        },
        {
          "method": "org.eclipse.mylar.java.MylarJavaPlugin$1.run",
          "source": "MylarJavaPlugin.java:112"
        },
        {
          "method": "org.eclipse.swt.widgets.RunnableLock.run",
          "source": "RunnableLock.java:35"
        },
        {
          "method": "org.eclipse.swt.widgets.Synchronizer.runAsyncMessages",
          "source": "Synchronizer.java:123"
        },
        {
          "method": "org.eclipse.swt.widgets.Display.runAsyncMessages",
          "source": "Display.java:3114"
        },
        {
          "method": "org.eclipse.swt.widgets.Display.readAndDispatch",
          "source": "Display.java:2768"
        },
        {
          "method": "org.eclipse.ui.internal.Workbench.runEventLoop",
          "source": "Workbench.java:1734"
        },
        {
          "method": "org.eclipse.ui.internal.Workbench.runUI",
          "source": "Workbench.java:1698"
        },
        {
          "method": "org.eclipse.ui.internal.Workbench.createAndRunWorkbench",
          "source": "Workbench.java:367"
        },
        {
          "method": "org.eclipse.ui.PlatformUI.createAndRunWorkbench",
          "source": "PlatformUI.java:143"
        },
        {
          "method": "org.eclipse.ui.internal.ide.IDEApplication.run",
          "source": "IDEApplication.java:103"
        },
        {
          "method": "org.eclipse.core.internal.runtime.PlatformActivator$1.run",
          "source": "PlatformActivator.java:226"
        },
        {
          "method": "org.eclipse.core.runtime.adaptor.EclipseStarter.run",
          "source": "EclipseStarter.java:376"
        },
        {
          "method": "org.eclipse.core.runtime.adaptor.EclipseStarter.run",
          "source": "EclipseStarter.java:163"
        },
        {
          "method": "sun.reflect.NativeMethodAccessorImpl.invoke0",
          "source": "Native Method"
        },
        {
          "method": "sun.reflect.NativeMethodAccessorImpl.invoke",
          "source": "NativeMethodAccessorImpl.java:39"
        },
        {
          "method": "sun.reflect.DelegatingMethodAccessorImpl.invoke",
          "source": "DelegatingMethodAccessorImpl.java:25"
        },
        {
          "method": "java.lang.reflect.Method.invoke",
          "source": "Method.java:585"
        },
        {
          "method": "org.eclipse.core.launcher.Main.invokeFramework",
          "source": "Main.java:338"
        },
        {
          "method": "org.eclipse.core.launcher.Main.basicRun",
          "source": "Main.java:282"
        },
        {
          "method": "org.eclipse.core.launcher.Main.run",
          "source": "Main.java:977"
        },
        {
          "method": "org.eclipse.core.launcher.Main.main",
          "source": "Main.java:952"
        }
      ],
      "number": 0,
      "commentIndex": 0,
      "bugId": "114614",
      "duplicateId": "115496",
      "date": "2005-11-01T19:54:21+01:00",
      "product": "Mylyn",
      "component": "Core",
      "severity": "normal"
    }
  ],
  "groupId": "115496",
  "bugId": "114614",
  "duplicateId": "115496",
  "date": "2005-11-01T19:54:21+01:00",
  "product": "Mylyn",
  "component": "Core",
  "severity": "normal"
}