{
  "comments": [
    "When compiling this program with ajc -1.5\n\npublic aspect Wildcard {\n    Class\u003c? extends Wildcard\u003e Wildcard.cl;\n\n    void foo() throws Exception {\n\tWildcard ci \u003d cl.newInstance();\n    }\n}\n\najc throws this exception\n\njava.lang.NullPointerException\n        at\norg.aspectj.org.eclipse.jdt.internal.compiler.lookup.CaptureBinding.initializeBounds(CaptureBinding.java:75)\n        at\norg.aspectj.org.eclipse.jdt.internal.compiler.lookup.ParameterizedTypeBinding.capture(ParameterizedTypeBinding.java:105)\n        at\norg.aspectj.org.eclipse.jdt.internal.compiler.ast.SingleNameReference.resolveType(SingleNameReference.java:772)\n        at\norg.aspectj.org.eclipse.jdt.internal.compiler.ast.MessageSend.resolveType(MessageSend.java:293)\n        at\norg.aspectj.org.eclipse.jdt.internal.compiler.ast.LocalDeclaration.resolve(LocalDeclaration.java:199)\n        at\norg.aspectj.org.eclipse.jdt.internal.compiler.ast.AbstractMethodDeclaration.resolveStatements(AbstractMethodDeclaration.java:422)\n        at\norg.aspectj.org.eclipse.jdt.internal.compiler.ast.MethodDeclaration.resolveStatements(MethodDeclaration.java:178)\n        at\norg.aspectj.org.eclipse.jdt.internal.compiler.ast.AbstractMethodDeclaration.resolve(AbstractMethodDeclaration.java:400)\n        at\norg.aspectj.org.eclipse.jdt.internal.compiler.ast.TypeDeclaration.resolve(TypeDeclaration.java:1076)\n        at\norg.aspectj.ajdt.internal.compiler.ast.AspectDeclaration.resolve(AspectDeclaration.java:114)\n        at\norg.aspectj.org.eclipse.jdt.internal.compiler.ast.TypeDeclaration.resolve(TypeDeclaration.java:1125)\n        at\norg.aspectj.org.eclipse.jdt.internal.compiler.ast.CompilationUnitDeclaration.resolve(CompilationUnitDeclaration.java:305)\n        at\norg.aspectj.org.eclipse.jdt.internal.compiler.Compiler.process(Compiler.java:514)\n        at\norg.aspectj.org.eclipse.jdt.internal.compiler.Compiler.compile(Compiler.java:329)\n        at\norg.aspectj.ajdt.internal.core.builder.AjBuildManager.performCompilation(AjBuildManager.java:759)\n        at\norg.aspectj.ajdt.internal.core.builder.AjBuildManager.doBuild(AjBuildManager.java:225)\n        at\norg.aspectj.ajdt.internal.core.builder.AjBuildManager.batchBuild(AjBuildManager.java:151)\n        at org.aspectj.ajdt.ajc.AjdtCommand.doCommand(AjdtCommand.java:112)\n        at org.aspectj.ajdt.ajc.AjdtCommand.runCommand(AjdtCommand.java:60)\n        at org.aspectj.tools.ajc.Main.run(Main.java:326)\n        at org.aspectj.tools.ajc.Main.runMain(Main.java:240)\n        at org.aspectj.tools.ajc.Main.main(Main.java:83)",
    "thanks for the clear bug report - don\u0027t think you could write a much smaller\ntestcase ;)",
    "Fix checked in.  The problem was in the conversion process between eclipse types\nand aj types.  If it is not an ITD then no conversion takes place but if it is\nan ITD then the conversion process was losing some information about the type\nvariable behind \u0027? extends Wildcard\u0027  (which is \u0027T extends Object\u0027 from the\ngeneric type Class).\n\nI worry there are a few other bugs lurking in that conversion process :(\n\nfix checked in, waiting on build.",
    "fix available."
  ],
  "commentCreationDates": [
    "2005-11-02T12:56:02+01:00",
    "2005-11-02T12:59:29+01:00",
    "2005-11-02T16:16:35+01:00",
    "2005-11-03T08:25:16+01:00"
  ],
  "traces": [
    {
      "exceptionType": "java.lang.NullPointerException",
      "elements": [
        {
          "method": "org.aspectj.org.eclipse.jdt.internal.compiler.lookup.CaptureBinding.initializeBounds",
          "source": "CaptureBinding.java:75"
        },
        {
          "method": "org.aspectj.org.eclipse.jdt.internal.compiler.lookup.ParameterizedTypeBinding.capture",
          "source": "ParameterizedTypeBinding.java:105"
        },
        {
          "method": "org.aspectj.org.eclipse.jdt.internal.compiler.ast.SingleNameReference.resolveType",
          "source": "SingleNameReference.java:772"
        },
        {
          "method": "org.aspectj.org.eclipse.jdt.internal.compiler.ast.MessageSend.resolveType",
          "source": "MessageSend.java:293"
        },
        {
          "method": "org.aspectj.org.eclipse.jdt.internal.compiler.ast.LocalDeclaration.resolve",
          "source": "LocalDeclaration.java:199"
        },
        {
          "method": "org.aspectj.org.eclipse.jdt.internal.compiler.ast.AbstractMethodDeclaration.resolveStatements",
          "source": "AbstractMethodDeclaration.java:422"
        },
        {
          "method": "org.aspectj.org.eclipse.jdt.internal.compiler.ast.MethodDeclaration.resolveStatements",
          "source": "MethodDeclaration.java:178"
        },
        {
          "method": "org.aspectj.org.eclipse.jdt.internal.compiler.ast.AbstractMethodDeclaration.resolve",
          "source": "AbstractMethodDeclaration.java:400"
        },
        {
          "method": "org.aspectj.org.eclipse.jdt.internal.compiler.ast.TypeDeclaration.resolve",
          "source": "TypeDeclaration.java:1076"
        },
        {
          "method": "org.aspectj.ajdt.internal.compiler.ast.AspectDeclaration.resolve",
          "source": "AspectDeclaration.java:114"
        },
        {
          "method": "org.aspectj.org.eclipse.jdt.internal.compiler.ast.TypeDeclaration.resolve",
          "source": "TypeDeclaration.java:1125"
        },
        {
          "method": "org.aspectj.org.eclipse.jdt.internal.compiler.ast.CompilationUnitDeclaration.resolve",
          "source": "CompilationUnitDeclaration.java:305"
        },
        {
          "method": "org.aspectj.org.eclipse.jdt.internal.compiler.Compiler.process",
          "source": "Compiler.java:514"
        },
        {
          "method": "org.aspectj.org.eclipse.jdt.internal.compiler.Compiler.compile",
          "source": "Compiler.java:329"
        },
        {
          "method": "org.aspectj.ajdt.internal.core.builder.AjBuildManager.performCompilation",
          "source": "AjBuildManager.java:759"
        },
        {
          "method": "org.aspectj.ajdt.internal.core.builder.AjBuildManager.doBuild",
          "source": "AjBuildManager.java:225"
        },
        {
          "method": "org.aspectj.ajdt.internal.core.builder.AjBuildManager.batchBuild",
          "source": "AjBuildManager.java:151"
        },
        {
          "method": "org.aspectj.ajdt.ajc.AjdtCommand.doCommand",
          "source": "AjdtCommand.java:112"
        },
        {
          "method": "org.aspectj.ajdt.ajc.AjdtCommand.runCommand",
          "source": "AjdtCommand.java:60"
        },
        {
          "method": "org.aspectj.tools.ajc.Main.run",
          "source": "Main.java:326"
        },
        {
          "method": "org.aspectj.tools.ajc.Main.runMain",
          "source": "Main.java:240"
        },
        {
          "method": "org.aspectj.tools.ajc.Main.main",
          "source": "Main.java:83"
        }
      ],
      "number": 0,
      "commentIndex": 0,
      "bugId": "114744",
      "date": "2005-11-02T12:56:02+01:00",
      "product": "AspectJ",
      "component": "Compiler",
      "severity": "normal"
    }
  ],
  "groupId": "114744",
  "bugId": "114744",
  "date": "2005-11-02T12:56:02+01:00",
  "product": "AspectJ",
  "component": "Compiler",
  "severity": "normal"
}