{
  "comments": [
    "After upgrading to GTK+ 2.6.10, I get the following test failure in the  \norg.eclipse.ui.tests.compare.UIComparePreferencesAuto.  The problem seems to  \nbe a change in event ordering.  If I block the UI thread just before the  \nfailure occurs, then the Restore Defaults and Apply buttons are missing.  If I  \nspin the event loop just before the test occurs, then the Restore Defaults and  \nApply buttons appear.  I believe in this way it is possible to workaround the \nproblem.  \n \nI\u0027m not sure if this points to a larger problem in SWT.  It is a vanilla GTK+ \n2.6.10 with two patches applied by Gentoo: \n\"2.2.1-disable_icons_smooth_alpha.patch\" and \"2.6-smoothscroll-r5.patch.bz2\". \n \n  \njunit.framework.AssertionFailedError: Warning: Button {Restore \u0026Defaults}   \n\tActual Width -\u003e 0   \n\tRecommended Width -\u003e 93   \n\tat junit.framework.Assert.fail(Assert.java:47)   \n\tat junit.framework.Assert.assertTrue(Assert.java:20)   \n\tat   \norg.eclipse.ui.tests.util.DialogCheck.verifyButtonText(DialogCheck.java:163)   \n\tat   \norg.eclipse.ui.tests.util.DialogCheck.verifyCompositeText(DialogCheck.java:124)   \n\tat   \norg.eclipse.ui.tests.util.DialogCheck.verifyCompositeText(DialogCheck.java:132)   \n\tat   \norg.eclipse.ui.tests.util.DialogCheck.verifyCompositeText(DialogCheck.java:132)   \n\tat   \norg.eclipse.ui.tests.util.DialogCheck.verifyCompositeText(DialogCheck.java:132)   \n\tat   \norg.eclipse.ui.tests.util.DialogCheck.verifyCompositeText(DialogCheck.java:132)   \n\tat   \norg.eclipse.ui.tests.util.DialogCheck.verifyCompositeText(DialogCheck.java:132)   \n\tat   \norg.eclipse.ui.tests.util.DialogCheck.verifyCompositeText(DialogCheck.java:132)   \n\tat   \norg.eclipse.ui.tests.util.DialogCheck.verifyCompositeText(DialogCheck.java:132)   \n\tat   \norg.eclipse.ui.tests.util.DialogCheck.assertDialogTexts(DialogCheck.java:84)   \n\tat   \norg.eclipse.ui.tests.compare.UIComparePreferencesAuto.testCompareViewersPref(UIComparePreferencesAuto.java:62)   \n\tat sun.reflect.NativeMethodAccessorImpl.invoke0(Native Method)   \n\tat   \nsun.reflect.NativeMethodAccessorImpl.invoke(NativeMethodAccessorImpl.java:39)   \n\tat   \nsun.reflect.DelegatingMethodAccessorImpl.invoke(DelegatingMethodAccessorImpl.java:25)   \n\tat java.lang.reflect.Method.invoke(Method.java:585)   \n\tat junit.framework.TestCase.runTest(TestCase.java:154)   \n\tat junit.framework.TestCase.runBare(TestCase.java:127)   \n\tat junit.framework.TestResult$1.protect(TestResult.java:106)   \n\tat junit.framework.TestResult.runProtected(TestResult.java:124)   \n\tat junit.framework.TestResult.run(TestResult.java:109)   \n\tat junit.framework.TestCase.run(TestCase.java:118)   \n\tat junit.framework.TestSuite.runTest(TestSuite.java:208)   \n\tat junit.framework.TestSuite.run(TestSuite.java:203)   \n\tat   \norg.eclipse.jdt.internal.junit.runner.RemoteTestRunner.runTests(RemoteTestRunner.java:478)   \n\tat   \norg.eclipse.jdt.internal.junit.runner.RemoteTestRunner.run(RemoteTestRunner.java:344)   \n\tat   \norg.eclipse.pde.internal.junit.runtime.RemotePluginTestRunner.main(RemotePluginTestRunner.java:57)   \n\tat   \norg.eclipse.pde.internal.junit.runtime.UITestApplication$1.run(UITestApplication.java:99)   \n\tat org.eclipse.swt.widgets.RunnableLock.run(RunnableLock.java:35)   \n\tat   \norg.eclipse.swt.widgets.Synchronizer.runAsyncMessages(Synchronizer.java:123)   \n\tat org.eclipse.swt.widgets.Display.runAsyncMessages(Display.java:3038)   \n\tat org.eclipse.swt.widgets.Display.readAndDispatch(Display.java:2746)   \n\tat org.eclipse.ui.internal.Workbench.runEventLoop(Workbench.java:1774)   \n\tat org.eclipse.ui.internal.Workbench.runUI(Workbench.java:1738)   \n\tat   \norg.eclipse.ui.internal.Workbench.createAndRunWorkbench(Workbench.java:376)   \n\tat   \norg.eclipse.ui.PlatformUI.createAndRunWorkbench(PlatformUI.java:143)   \n\tat   \norg.eclipse.ui.internal.ide.IDEApplication.run(IDEApplication.java:106)   \n\tat   \norg.eclipse.pde.internal.junit.runtime.UITestApplication.run(UITestApplication.java:39)   \n\tat   \norg.eclipse.core.internal.runtime.PlatformActivator$1.run(PlatformActivator.java:226)   \n\tat   \norg.eclipse.core.runtime.adaptor.EclipseStarter.run(EclipseStarter.java:376)   \n\tat   \norg.eclipse.core.runtime.adaptor.EclipseStarter.run(EclipseStarter.java:165)   \n\tat sun.reflect.NativeMethodAccessorImpl.invoke0(Native Method)   \n\tat   \nsun.reflect.NativeMethodAccessorImpl.invoke(NativeMethodAccessorImpl.java:39)   \n\tat   \nsun.reflect.DelegatingMethodAccessorImpl.invoke(DelegatingMethodAccessorImpl.java:25)   \n\tat java.lang.reflect.Method.invoke(Method.java:585)   \n\tat org.eclipse.core.launcher.Main.invokeFramework(Main.java:338)   \n\tat org.eclipse.core.launcher.Main.basicRun(Main.java:282)   \n\tat org.eclipse.core.launcher.Main.run(Main.java:977)   \n\tat org.eclipse.core.launcher.Main.main(Main.java:952)",
    "Created an attachment (id\u003d29266)\nScreenshot showing the problem\n",
    "This has started working for me.  No other changes on my system. "
  ],
  "commentCreationDates": [
    "2005-11-03T14:56:40+01:00",
    "2005-11-03T15:00:47+01:00",
    "2005-11-09T23:13:51+01:00"
  ],
  "traces": [
    {
      "exceptionType": "junit.framework.AssertionFailedError",
      "message": "Warning: Button {Restore \u0026Defaults}     Actual Width -\u003e 0     Recommended Width -\u003e 93",
      "elements": [
        {
          "method": "junit.framework.Assert.fail",
          "source": "Assert.java:47"
        },
        {
          "method": "junit.framework.Assert.assertTrue",
          "source": "Assert.java:20"
        },
        {
          "method": "org.eclipse.ui.tests.util.DialogCheck.verifyButtonText",
          "source": "DialogCheck.java:163"
        },
        {
          "method": "org.eclipse.ui.tests.util.DialogCheck.verifyCompositeText",
          "source": "DialogCheck.java:124"
        },
        {
          "method": "org.eclipse.ui.tests.util.DialogCheck.verifyCompositeText",
          "source": "DialogCheck.java:132"
        },
        {
          "method": "org.eclipse.ui.tests.util.DialogCheck.verifyCompositeText",
          "source": "DialogCheck.java:132"
        },
        {
          "method": "org.eclipse.ui.tests.util.DialogCheck.verifyCompositeText",
          "source": "DialogCheck.java:132"
        },
        {
          "method": "org.eclipse.ui.tests.util.DialogCheck.verifyCompositeText",
          "source": "DialogCheck.java:132"
        },
        {
          "method": "org.eclipse.ui.tests.util.DialogCheck.verifyCompositeText",
          "source": "DialogCheck.java:132"
        },
        {
          "method": "org.eclipse.ui.tests.util.DialogCheck.verifyCompositeText",
          "source": "DialogCheck.java:132"
        },
        {
          "method": "org.eclipse.ui.tests.util.DialogCheck.verifyCompositeText",
          "source": "DialogCheck.java:132"
        },
        {
          "method": "org.eclipse.ui.tests.util.DialogCheck.assertDialogTexts",
          "source": "DialogCheck.java:84"
        },
        {
          "method": "org.eclipse.ui.tests.compare.UIComparePreferencesAuto.testCompareViewersPref",
          "source": "UIComparePreferencesAuto.java:62"
        },
        {
          "method": "sun.reflect.NativeMethodAccessorImpl.invoke0",
          "source": "Native Method"
        },
        {
          "method": "sun.reflect.NativeMethodAccessorImpl.invoke",
          "source": "NativeMethodAccessorImpl.java:39"
        },
        {
          "method": "sun.reflect.DelegatingMethodAccessorImpl.invoke",
          "source": "DelegatingMethodAccessorImpl.java:25"
        },
        {
          "method": "java.lang.reflect.Method.invoke",
          "source": "Method.java:585"
        },
        {
          "method": "junit.framework.TestCase.runTest",
          "source": "TestCase.java:154"
        },
        {
          "method": "junit.framework.TestCase.runBare",
          "source": "TestCase.java:127"
        },
        {
          "method": "junit.framework.TestResult$1.protect",
          "source": "TestResult.java:106"
        },
        {
          "method": "junit.framework.TestResult.runProtected",
          "source": "TestResult.java:124"
        },
        {
          "method": "junit.framework.TestResult.run",
          "source": "TestResult.java:109"
        },
        {
          "method": "junit.framework.TestCase.run",
          "source": "TestCase.java:118"
        },
        {
          "method": "junit.framework.TestSuite.runTest",
          "source": "TestSuite.java:208"
        },
        {
          "method": "junit.framework.TestSuite.run",
          "source": "TestSuite.java:203"
        },
        {
          "method": "org.eclipse.jdt.internal.junit.runner.RemoteTestRunner.runTests",
          "source": "RemoteTestRunner.java:478"
        },
        {
          "method": "org.eclipse.jdt.internal.junit.runner.RemoteTestRunner.run",
          "source": "RemoteTestRunner.java:344"
        },
        {
          "method": "org.eclipse.pde.internal.junit.runtime.RemotePluginTestRunner.main",
          "source": "RemotePluginTestRunner.java:57"
        },
        {
          "method": "org.eclipse.pde.internal.junit.runtime.UITestApplication$1.run",
          "source": "UITestApplication.java:99"
        },
        {
          "method": "org.eclipse.swt.widgets.RunnableLock.run",
          "source": "RunnableLock.java:35"
        },
        {
          "method": "org.eclipse.swt.widgets.Synchronizer.runAsyncMessages",
          "source": "Synchronizer.java:123"
        },
        {
          "method": "org.eclipse.swt.widgets.Display.runAsyncMessages",
          "source": "Display.java:3038"
        },
        {
          "method": "org.eclipse.swt.widgets.Display.readAndDispatch",
          "source": "Display.java:2746"
        },
        {
          "method": "org.eclipse.ui.internal.Workbench.runEventLoop",
          "source": "Workbench.java:1774"
        },
        {
          "method": "org.eclipse.ui.internal.Workbench.runUI",
          "source": "Workbench.java:1738"
        },
        {
          "method": "org.eclipse.ui.internal.Workbench.createAndRunWorkbench",
          "source": "Workbench.java:376"
        },
        {
          "method": "org.eclipse.ui.PlatformUI.createAndRunWorkbench",
          "source": "PlatformUI.java:143"
        },
        {
          "method": "org.eclipse.ui.internal.ide.IDEApplication.run",
          "source": "IDEApplication.java:106"
        },
        {
          "method": "org.eclipse.pde.internal.junit.runtime.UITestApplication.run",
          "source": "UITestApplication.java:39"
        },
        {
          "method": "org.eclipse.core.internal.runtime.PlatformActivator$1.run",
          "source": "PlatformActivator.java:226"
        },
        {
          "method": "org.eclipse.core.runtime.adaptor.EclipseStarter.run",
          "source": "EclipseStarter.java:376"
        },
        {
          "method": "org.eclipse.core.runtime.adaptor.EclipseStarter.run",
          "source": "EclipseStarter.java:165"
        },
        {
          "method": "sun.reflect.NativeMethodAccessorImpl.invoke0",
          "source": "Native Method"
        },
        {
          "method": "sun.reflect.NativeMethodAccessorImpl.invoke",
          "source": "NativeMethodAccessorImpl.java:39"
        },
        {
          "method": "sun.reflect.DelegatingMethodAccessorImpl.invoke",
          "source": "DelegatingMethodAccessorImpl.java:25"
        },
        {
          "method": "java.lang.reflect.Method.invoke",
          "source": "Method.java:585"
        },
        {
          "method": "org.eclipse.core.launcher.Main.invokeFramework",
          "source": "Main.java:338"
        },
        {
          "method": "org.eclipse.core.launcher.Main.basicRun",
          "source": "Main.java:282"
        },
        {
          "method": "org.eclipse.core.launcher.Main.run",
          "source": "Main.java:977"
        },
        {
          "method": "org.eclipse.core.launcher.Main.main",
          "source": "Main.java:952"
        }
      ],
      "number": 0,
      "commentIndex": 0,
      "bugId": "114916",
      "date": "2005-11-03T14:56:40+01:00",
      "product": "Platform",
      "component": "UI",
      "severity": "normal"
    }
  ],
  "groupId": "114916",
  "bugId": "114916",
  "date": "2005-11-03T14:56:40+01:00",
  "product": "Platform",
  "component": "UI",
  "severity": "normal"
}