{
  "comments": [
    "build 2002-03-14 on Win98.\n\n- was programming for about 5 hours (without restarting Eclipse)\n- got a No More Handles exception and was prompted to close the workspace\n- closed and saved OK\n\n- Note: no other applications running at the time (not Notes, not IE although \nthey had been previously started and stopped a couple of times)\n- Note: I used to get this error a lot (especially when running Eclipse in \nEclipse) but I haven\u0027t seen it in months\n- Note: I hadn\u0027t been running Eclipse in Eclipse, just running our test suites\n- Note: development is done entirely in (my own) Java perspective and Debug \nperspectives\n\nHere is the log file with the error.\n\nLog: Sat Mar 16 13:39:46 EST 2002\n1 org.eclipse.core.resources 4 Unhandled exception caught in event loop.\nLog: Sat Mar 16 13:39:46 EST 2002\n4 org.eclipse.ui 0 No more handles\norg.eclipse.swt.SWTError: No more handles\n\tat org.eclipse.swt.SWT.error(SWT.java:1912)\n\tat org.eclipse.swt.graphics.Image.init(Image.java(Compiled Code))\n\tat org.eclipse.swt.graphics.Image.init(Image.java(Compiled Code))\n\tat org.eclipse.swt.custom.StyledText.handlePaint(StyledText.java\n(Compiled Code))\n\tat org.eclipse.swt.custom.StyledText.handlePaint(StyledText.java\n(Compiled Code))\n\tat org.eclipse.swt.custom.StyledText$13.handleEvent(StyledText.java\n(Compiled Code))\n\tat org.eclipse.swt.widgets.Widget.sendEvent(Widget.java(Compiled Code))\n\tat org.eclipse.swt.widgets.Widget.sendEvent(Widget.java(Compiled Code))\n\tat org.eclipse.swt.widgets.Composite.WM_PAINT(Composite.java(Compiled \nCode))\n\tat org.eclipse.swt.widgets.Control.windowProc(Control.java(Compiled \nCode))\n\tat org.eclipse.swt.widgets.Display.windowProc(Display.java(Compiled \nCode))\n\tat org.eclipse.swt.internal.win32.OS.DispatchMessageA(Native Method)\n\tat org.eclipse.swt.internal.win32.OS.DispatchMessage(OS.java(Compiled \nCode))\n\tat org.eclipse.swt.widgets.Display.readAndDispatch(Display.java\n(Compiled Code))\n\tat org.eclipse.ui.internal.Workbench.runEventLoop(Workbench.java\n(Compiled Code))\n\tat org.eclipse.ui.internal.Workbench.run(Workbench.java:675)\n\tat org.eclipse.core.internal.boot.InternalBootLoader.run\n(InternalBootLoader.java:777)\n\tat org.eclipse.core.boot.BootLoader.run(BootLoader.java:319)\n\tat java.lang.reflect.Method.invoke(Native Method)\n\tat org.eclipse.core.launcher.Main.basicRun(Main.java:151)\n\tat org.eclipse.core.launcher.Main.run(Main.java:502)\n\tat org.eclipse.core.launcher.Main.main(Main.java:362)",
    "Also note that my machine hadn\u0027t been rebooted for probably 2 or 3 days. (not \nsure if that makes a difference or not)",
    "Note this is Win98. CM to investigate if this is related to accessibility \nchanges.",
    "Note that this happened again this morning.\nSame scenerio. (no other apps open, hadn\u0027t rebooted for a day or so)",
    "I will look, but at first glance I think it is much more likely to be changes \nin StyledText - I do not currntly have any accessibility added to StyledText, \nand from the stack trace, that\u0027s where the error occurred.",
    "It\u0027s doubtful that this is StyledText, but we will double check to make sure we \naren\u0027t leaking resources.  Most likely scenario is someone else in Eclipse \nleaking resources and StyledText just happens to be the one that needs a \nresource when no more are left.",
    "Verified that StyledText is disposing of the resources it creates.",
    "Was not related to accessibility changes. I ran for quite a while, and did not \nhave any casses where the number of AddRef\u0027s exceeded the number of Releases.\nOLE objects do take up some space, but Veronika says it\u0027s not too bad.\nThey don\u0027t take up any handles.\nHave you seen this problem since then?",
    "I have since changed my OS to WinXP. (and therefore haven\u0027t seen this problem)",
    "\n\n*** This bug has been marked as a duplicate of 16101 ***"
  ],
  "commentCreationDates": [
    "2002-03-16T18:44:04+01:00",
    "2002-03-16T18:56:12+01:00",
    "2002-03-18T14:13:28+01:00",
    "2002-03-18T14:52:09+01:00",
    "2002-03-18T15:09:25+01:00",
    "2002-03-18T15:55:56+01:00",
    "2002-03-18T20:15:35+01:00",
    "2002-05-16T06:45:02+02:00",
    "2002-05-16T16:05:20+02:00",
    "2002-05-16T17:54:31+02:00"
  ],
  "traces": [
    {
      "exceptionType": "org.eclipse.swt.SWTError",
      "message": "No more handles",
      "elements": [
        {
          "method": "org.eclipse.swt.SWT.error",
          "source": "SWT.java:1912"
        },
        {
          "method": "org.eclipse.swt.graphics.Image.init",
          "source": "Image.java(Compiled Code)"
        },
        {
          "method": "org.eclipse.swt.graphics.Image.init",
          "source": "Image.java(Compiled Code)"
        },
        {
          "method": "org.eclipse.swt.custom.StyledText.handlePaint",
          "source": "StyledText.java (Compiled Code)"
        },
        {
          "method": "org.eclipse.swt.custom.StyledText.handlePaint",
          "source": "StyledText.java (Compiled Code)"
        },
        {
          "method": "org.eclipse.swt.custom.StyledText$13.handleEvent",
          "source": "StyledText.java (Compiled Code)"
        },
        {
          "method": "org.eclipse.swt.widgets.Widget.sendEvent",
          "source": "Widget.java(Compiled Code)"
        },
        {
          "method": "org.eclipse.swt.widgets.Widget.sendEvent",
          "source": "Widget.java(Compiled Code)"
        },
        {
          "method": "org.eclipse.swt.widgets.Composite.WM_PAINT",
          "source": "Composite.java(Compiled  Code)"
        },
        {
          "method": "org.eclipse.swt.widgets.Control.windowProc",
          "source": "Control.java(Compiled  Code)"
        },
        {
          "method": "org.eclipse.swt.widgets.Display.windowProc",
          "source": "Display.java(Compiled  Code)"
        },
        {
          "method": "org.eclipse.swt.internal.win32.OS.DispatchMessageA",
          "source": "Native Method"
        },
        {
          "method": "org.eclipse.swt.internal.win32.OS.DispatchMessage",
          "source": "OS.java(Compiled  Code)"
        },
        {
          "method": "org.eclipse.swt.widgets.Display.readAndDispatch",
          "source": "Display.java (Compiled Code)"
        },
        {
          "method": "org.eclipse.ui.internal.Workbench.runEventLoop",
          "source": "Workbench.java (Compiled Code)"
        },
        {
          "method": "org.eclipse.ui.internal.Workbench.run",
          "source": "Workbench.java:675"
        },
        {
          "method": "org.eclipse.core.internal.boot.InternalBootLoader.run",
          "source": "InternalBootLoader.java:777"
        },
        {
          "method": "org.eclipse.core.boot.BootLoader.run",
          "source": "BootLoader.java:319"
        },
        {
          "method": "java.lang.reflect.Method.invoke",
          "source": "Native Method"
        },
        {
          "method": "org.eclipse.core.launcher.Main.basicRun",
          "source": "Main.java:151"
        },
        {
          "method": "org.eclipse.core.launcher.Main.run",
          "source": "Main.java:502"
        },
        {
          "method": "org.eclipse.core.launcher.Main.main",
          "source": "Main.java:362"
        }
      ],
      "number": 0,
      "commentIndex": 0,
      "bugId": "11507",
      "duplicateId": "16101",
      "date": "2002-03-16T18:44:04+01:00",
      "product": "Platform",
      "component": "SWT",
      "severity": "normal"
    }
  ],
  "groupId": "16101",
  "bugId": "11507",
  "duplicateId": "16101",
  "date": "2002-03-16T18:44:04+01:00",
  "product": "Platform",
  "component": "SWT",
  "severity": "normal"
}