{
  "comments": [
    "When running TDJAVA in a blank workspace and hitting Finish on page 2, the \nfollowing Exception occurs:\n\nIWAB0014E Unexpected exception occured.\n  Could not find template null.\n      java.lang.IllegalArgumentException: Could not find template null.\n      at \norg.eclipse.wst.common.project.facet.core.internal.ProjectFacetsManagerImpl.getT\nemplate(ProjectFacetsManagerImpl.java:230)\n      at \norg.eclipse.wst.common.project.facet.core.ProjectFacetsManager.getTemplate\n(ProjectFacetsManager.java:217)\n      at \norg.eclipse.jst.ws.internal.consumption.common.FacetUtils.getInitialFacetVersion\nsFromTemplate(FacetUtils.java:107)\n      at \norg.eclipse.jst.ws.internal.creation.ui.extension.PreServiceDevelopCommand.execu\nte(PreServiceDevelopCommand.java:130)\n      at \norg.eclipse.wst.command.internal.env.core.fragment.CommandFragmentEngine.runComm\nand(CommandFragmentEngine.java:347)\n      at \norg.eclipse.wst.command.internal.env.core.fragment.CommandFragmentEngine.visitTo\np(CommandFragmentEngine.java:311)\n      at \norg.eclipse.wst.command.internal.env.core.fragment.CommandFragmentEngine.moveFor\nwardToNextStop(CommandFragmentEngine.java:219)\n      at \norg.eclipse.wst.command.internal.env.ui.widgets.SimpleCommandEngineManager$4.run\n(SimpleCommandEngineManager.java:204)\n      at org.eclipse.jface.operation.ModalContext.runInCurrentThread\n(ModalContext.java:346)\n      at org.eclipse.jface.operation.ModalContext.run(ModalContext.java:291)\n      at org.eclipse.jface.wizard.WizardDialog.run(WizardDialog.java:830)\n      at \norg.eclipse.wst.command.internal.env.ui.widgets.SimpleCommandEngineManager.runFo\nrwardToNextStop(SimpleCommandEngineManager.java:175)\n      at \norg.eclipse.wst.command.internal.env.ui.widgets.WizardPageManager.runForwardToNe\nxtStop(WizardPageManager.java:78)\n      at \norg.eclipse.wst.command.internal.env.ui.widgets.WizardPageManager.performFinish\n(WizardPageManager.java:227)\n      at \norg.eclipse.wst.command.internal.env.ui.widgets.DynamicWizard.performFinish\n(DynamicWizard.java:333)\n      at org.eclipse.jface.wizard.WizardDialog.finishPressed\n(WizardDialog.java:676)\n      at org.eclipse.jface.wizard.WizardDialog.buttonPressed\n(WizardDialog.java:349)\n      at org.eclipse.jface.dialogs.Dialog$2.widgetSelected(Dialog.java:556)\n      at org.eclipse.swt.widgets.TypedListener.handleEvent\n(TypedListener.java:90)\n      at org.eclipse.swt.widgets.EventTable.sendEvent(EventTable.java:66)\n      at org.eclipse.swt.widgets.Widget.sendEvent(Widget.java:843)\n      at org.eclipse.swt.widgets.Display.runDeferredEvents(Display.java:3080)\n      at org.eclipse.swt.widgets.Display.readAndDispatch(Display.java:2713)\n      at org.eclipse.jface.window.Window.runEventLoop(Window.java:809)\n      at org.eclipse.jface.window.Window.open(Window.java:787)\n      at org.eclipse.ui.actions.NewWizardAction.run(NewWizardAction.java:181)\n      at org.eclipse.ui.actions.NewWizardDropDownAction.run\n(NewWizardDropDownAction.java:174)\n      at org.eclipse.jface.action.Action.runWithEvent(Action.java:996)\n      at org.eclipse.jface.action.ActionContributionItem.handleWidgetSelection\n(ActionContributionItem.java:538)\n      at org.eclipse.jface.action.ActionContributionItem.access$2\n(ActionContributionItem.java:488)\n      at org.eclipse.jface.action.ActionContributionItem$6.handleEvent\n(ActionContributionItem.java:441)\n      at org.eclipse.swt.widgets.EventTable.sendEvent(EventTable.java:66)\n      at org.eclipse.swt.widgets.Widget.sendEvent(Widget.java:843)\n      at org.eclipse.swt.widgets.Display.runDeferredEvents(Display.java:3080)\n      at org.eclipse.swt.widgets.Display.readAndDispatch(Display.java:2713)\n      at org.eclipse.ui.internal.Workbench.runEventLoop(Workbench.java:1699)\n      at org.eclipse.ui.internal.Workbench.runUI(Workbench.java:1663)\n      at org.eclipse.ui.internal.Workbench.createAndRunWorkbench\n(Workbench.java:367)\n      at org.eclipse.ui.PlatformUI.createAndRunWorkbench(PlatformUI.java:143)\n      at org.eclipse.ui.internal.ide.IDEApplication.run(IDEApplication.java:103)\n      at org.eclipse.core.internal.runtime.PlatformActivator$1.run\n(PlatformActivator.java:226)\n      at org.eclipse.core.runtime.adaptor.EclipseStarter.run\n(EclipseStarter.java:376)\n      at org.eclipse.core.runtime.adaptor.EclipseStarter.run\n(EclipseStarter.java:163)\n      at sun.reflect.NativeMethodAccessorImpl.invoke0(Native Method)\n      at sun.reflect.NativeMethodAccessorImpl.invoke\n(NativeMethodAccessorImpl.java:39)\n      at sun.reflect.DelegatingMethodAccessorImpl.invoke\n(DelegatingMethodAccessorImpl.java:25)\n      at java.lang.reflect.Method.invoke(Method.java:324)\n      at org.eclipse.core.launcher.Main.invokeFramework(Main.java:334)\n      at org.eclipse.core.launcher.Main.basicRun(Main.java:278)\n      at org.eclipse.core.launcher.Main.run(Main.java:973)\n      at org.eclipse.core.launcher.Main.main(Main.java:948)",
    "Created an attachment (id\u003d29345)\napply directly to\norg.eclipse.jst.ws.creation.ui/src/org/eclipse/jst/ws/internal/creation/ui/widgets/binding/ServerWidgetBinding.java\n\npatch 1 of 1",
    "The attached patch is ready to be committed.",
    "Patch committed but not released yet.",
    "Released to v20051107_1452.  Please resolve the defect.",
    "Resolving",
    "Closing"
  ],
  "commentCreationDates": [
    "2005-11-04T16:30:24+01:00",
    "2005-11-04T16:41:53+01:00",
    "2005-11-04T16:43:34+01:00",
    "2005-11-04T22:21:17+01:00",
    "2005-11-07T19:23:57+01:00",
    "2005-11-07T22:16:48+01:00",
    "2005-12-09T20:57:38+01:00"
  ],
  "traces": [
    {
      "exceptionType": "java.lang.IllegalArgumentException",
      "message": "Could not find template null.",
      "elements": [
        {
          "method": "org.eclipse.wst.common.project.facet.core.internal.ProjectFacetsManagerImpl.getTemplate",
          "source": "ProjectFacetsManagerImpl.java:230"
        },
        {
          "method": "org.eclipse.wst.common.project.facet.core.ProjectFacetsManager.getTemplate",
          "source": "ProjectFacetsManager.java:217"
        },
        {
          "method": "org.eclipse.jst.ws.internal.consumption.common.FacetUtils.getInitialFacetVersionsFromTemplate",
          "source": "FacetUtils.java:107"
        },
        {
          "method": "org.eclipse.jst.ws.internal.creation.ui.extension.PreServiceDevelopCommand.execute",
          "source": "PreServiceDevelopCommand.java:130"
        },
        {
          "method": "org.eclipse.wst.command.internal.env.core.fragment.CommandFragmentEngine.runCommand",
          "source": "CommandFragmentEngine.java:347"
        },
        {
          "method": "org.eclipse.wst.command.internal.env.core.fragment.CommandFragmentEngine.visitTop",
          "source": "CommandFragmentEngine.java:311"
        },
        {
          "method": "org.eclipse.wst.command.internal.env.core.fragment.CommandFragmentEngine.moveForwardToNextStop",
          "source": "CommandFragmentEngine.java:219"
        },
        {
          "method": "org.eclipse.wst.command.internal.env.ui.widgets.SimpleCommandEngineManager$4.run",
          "source": "SimpleCommandEngineManager.java:204"
        },
        {
          "method": "org.eclipse.jface.operation.ModalContext.runInCurrentThread",
          "source": "ModalContext.java:346"
        },
        {
          "method": "org.eclipse.jface.operation.ModalContext.run",
          "source": "ModalContext.java:291"
        },
        {
          "method": "org.eclipse.jface.wizard.WizardDialog.run",
          "source": "WizardDialog.java:830"
        },
        {
          "method": "org.eclipse.wst.command.internal.env.ui.widgets.SimpleCommandEngineManager.runForwardToNextStop",
          "source": "SimpleCommandEngineManager.java:175"
        },
        {
          "method": "org.eclipse.wst.command.internal.env.ui.widgets.WizardPageManager.runForwardToNextStop",
          "source": "WizardPageManager.java:78"
        },
        {
          "method": "org.eclipse.wst.command.internal.env.ui.widgets.WizardPageManager.performFinish",
          "source": "WizardPageManager.java:227"
        },
        {
          "method": "org.eclipse.wst.command.internal.env.ui.widgets.DynamicWizard.performFinish",
          "source": "DynamicWizard.java:333"
        },
        {
          "method": "org.eclipse.jface.wizard.WizardDialog.finishPressed",
          "source": "WizardDialog.java:676"
        },
        {
          "method": "org.eclipse.jface.wizard.WizardDialog.buttonPressed",
          "source": "WizardDialog.java:349"
        },
        {
          "method": "org.eclipse.jface.dialogs.Dialog$2.widgetSelected",
          "source": "Dialog.java:556"
        },
        {
          "method": "org.eclipse.swt.widgets.TypedListener.handleEvent",
          "source": "TypedListener.java:90"
        },
        {
          "method": "org.eclipse.swt.widgets.EventTable.sendEvent",
          "source": "EventTable.java:66"
        },
        {
          "method": "org.eclipse.swt.widgets.Widget.sendEvent",
          "source": "Widget.java:843"
        },
        {
          "method": "org.eclipse.swt.widgets.Display.runDeferredEvents",
          "source": "Display.java:3080"
        },
        {
          "method": "org.eclipse.swt.widgets.Display.readAndDispatch",
          "source": "Display.java:2713"
        },
        {
          "method": "org.eclipse.jface.window.Window.runEventLoop",
          "source": "Window.java:809"
        },
        {
          "method": "org.eclipse.jface.window.Window.open",
          "source": "Window.java:787"
        },
        {
          "method": "org.eclipse.ui.actions.NewWizardAction.run",
          "source": "NewWizardAction.java:181"
        },
        {
          "method": "org.eclipse.ui.actions.NewWizardDropDownAction.run",
          "source": "NewWizardDropDownAction.java:174"
        },
        {
          "method": "org.eclipse.jface.action.Action.runWithEvent",
          "source": "Action.java:996"
        },
        {
          "method": "org.eclipse.jface.action.ActionContributionItem.handleWidgetSelection",
          "source": "ActionContributionItem.java:538"
        },
        {
          "method": "org.eclipse.jface.action.ActionContributionItem.access$2",
          "source": "ActionContributionItem.java:488"
        },
        {
          "method": "org.eclipse.jface.action.ActionContributionItem$6.handleEvent",
          "source": "ActionContributionItem.java:441"
        },
        {
          "method": "org.eclipse.swt.widgets.EventTable.sendEvent",
          "source": "EventTable.java:66"
        },
        {
          "method": "org.eclipse.swt.widgets.Widget.sendEvent",
          "source": "Widget.java:843"
        },
        {
          "method": "org.eclipse.swt.widgets.Display.runDeferredEvents",
          "source": "Display.java:3080"
        },
        {
          "method": "org.eclipse.swt.widgets.Display.readAndDispatch",
          "source": "Display.java:2713"
        },
        {
          "method": "org.eclipse.ui.internal.Workbench.runEventLoop",
          "source": "Workbench.java:1699"
        },
        {
          "method": "org.eclipse.ui.internal.Workbench.runUI",
          "source": "Workbench.java:1663"
        },
        {
          "method": "org.eclipse.ui.internal.Workbench.createAndRunWorkbench",
          "source": "Workbench.java:367"
        },
        {
          "method": "org.eclipse.ui.PlatformUI.createAndRunWorkbench",
          "source": "PlatformUI.java:143"
        },
        {
          "method": "org.eclipse.ui.internal.ide.IDEApplication.run",
          "source": "IDEApplication.java:103"
        },
        {
          "method": "org.eclipse.core.internal.runtime.PlatformActivator$1.run",
          "source": "PlatformActivator.java:226"
        },
        {
          "method": "org.eclipse.core.runtime.adaptor.EclipseStarter.run",
          "source": "EclipseStarter.java:376"
        },
        {
          "method": "org.eclipse.core.runtime.adaptor.EclipseStarter.run",
          "source": "EclipseStarter.java:163"
        },
        {
          "method": "sun.reflect.NativeMethodAccessorImpl.invoke0",
          "source": "Native Method"
        },
        {
          "method": "sun.reflect.NativeMethodAccessorImpl.invoke",
          "source": "NativeMethodAccessorImpl.java:39"
        },
        {
          "method": "sun.reflect.DelegatingMethodAccessorImpl.invoke",
          "source": "DelegatingMethodAccessorImpl.java:25"
        },
        {
          "method": "java.lang.reflect.Method.invoke",
          "source": "Method.java:324"
        },
        {
          "method": "org.eclipse.core.launcher.Main.invokeFramework",
          "source": "Main.java:334"
        },
        {
          "method": "org.eclipse.core.launcher.Main.basicRun",
          "source": "Main.java:278"
        },
        {
          "method": "org.eclipse.core.launcher.Main.run",
          "source": "Main.java:973"
        },
        {
          "method": "org.eclipse.core.launcher.Main.main",
          "source": "Main.java:948"
        }
      ],
      "number": 0,
      "commentIndex": 0,
      "bugId": "115090",
      "date": "2005-11-04T16:30:24+01:00",
      "product": "Web Tools",
      "component": "jst.ws",
      "severity": "normal"
    }
  ],
  "groupId": "115090",
  "bugId": "115090",
  "date": "2005-11-04T16:30:24+01:00",
  "product": "Web Tools",
  "component": "jst.ws",
  "severity": "normal"
}