{
  "comments": [
    "it says there are 16 more exceptions, but they are not in the log.\n\n# more 1130778979446.log\n!SESSION Oct 31, 2005 11:16:22.267 ---------------------------------------------\neclipse.buildId\u003dM200503110845\njava.fullversion\u003dJ2RE 1.4.2 IBM AIX build ca142-20050609 (JIT enabled: jitc)\nBootLoader constants: OS\u003daix, ARCH\u003dppc, WS\u003dmotif, NL\u003den\n\n!ENTRY org.eclipse.osgi Oct 31, 2005 11:16:22.270\n!MESSAGE Application error\n!STACK 1\njava.lang.ExceptionInInitializerError\n        at org.eclipse.swt.graphics.Device.\u003cclinit\u003e(Device.java:89)\n        at org.eclipse.ui.internal.Workbench.createDisplay(Workbench.java:268)\n        at org.eclipse.ui.PlatformUI.createDisplay(PlatformUI.java:153)\n        at\norg.eclipse.ui.internal.ide.IDEApplication.createDisplay(IDEApplication.java:122)\n        at org.eclipse.ui.internal.ide.IDEApplication.run(IDEApplication.java:72)\n        at\norg.eclipse.core.internal.runtime.PlatformActivator$1.run(PlatformActivator.java:335)\n        at\norg.eclipse.core.runtime.adaptor.EclipseStarter.run(EclipseStarter.java:273)\n        at\norg.eclipse.core.runtime.adaptor.EclipseStarter.run(EclipseStarter.java:129)\n        at sun.reflect.NativeMethodAccessorImpl.invoke0(Native Method)\n        at\nsun.reflect.NativeMethodAccessorImpl.invoke(NativeMethodAccessorImpl.java:85)\n        at\nsun.reflect.NativeMethodAccessorImpl.invoke(NativeMethodAccessorImpl.java:58)\n        at\nsun.reflect.DelegatingMethodAccessorImpl.invoke(DelegatingMethodAccessorImpl.java:60)\n        at java.lang.reflect.Method.invoke(Method.java:391)\n        at org.eclipse.core.launcher.Main.basicRun(Main.java:185)\n        at org.eclipse.core.launcher.Main.run(Main.java:704)\n        at org.eclipse.core.launcher.Main.main(Main.java:688)\nCaused by: java.lang.NullPointerException\n        at java.lang.ClassLoader.loadLibrary0(ClassLoader.java:2171)\n        at java.lang.ClassLoader.loadLibrary(ClassLoader.java:1988)\n        at java.lang.Runtime.loadLibrary0(Runtime.java:824)\n        at java.lang.System.loadLibrary(System.java:908)\n        at org.eclipse.swt.internal.Library.loadLibrary(Library.java:100)\n        at org.eclipse.swt.internal.motif.OS.\u003cclinit\u003e(OS.java:20)",
    "Moving to SWT for comment. Looks like a dup of bug 88077.",
    "This does seem strange and looks like it might be a VM problem (as\nwas the case in bug 88077).  Do you have any other VM versions\nyou can try?",
    "Bug 88077 was refering to a 64-bit VM.  This one looks like it\u0027s 32-bit.",
    "*** Bug 145498 has been marked as a duplicate of this bug. ***",
    "Based on the \"Caused By\" section of the trace, this does seem like a VM problem of a similar nature to bug 139519.  Can you try with a newer VM, either a 1.5 or a 1.4.2 whose date is in 2006, and follow up here with whether or not this helped?\n",
    "I believe that this is a duplicate of bug 145498, which became fixed when the user added the missing package described in bug 139786.  Marking report as a duplicate; if installing this package does not help you get running then please reopen this report, thanks.\n\n\n*** This bug has been marked as a duplicate of 145498 ***"
  ],
  "commentCreationDates": [
    "2005-11-11T09:06:36+01:00",
    "2005-11-11T12:31:46+01:00",
    "2005-11-11T14:30:51+01:00",
    "2006-04-28T20:08:06+02:00",
    "2006-06-06T16:24:15+02:00",
    "2006-06-06T17:04:56+02:00",
    "2006-10-18T20:41:59+02:00"
  ],
  "traces": [
    {
      "exceptionType": "java.lang.ExceptionInInitializerError",
      "elements": [
        {
          "method": "org.eclipse.swt.graphics.Device.\u003cclinit\u003e",
          "source": "Device.java:89"
        },
        {
          "method": "org.eclipse.ui.internal.Workbench.createDisplay",
          "source": "Workbench.java:268"
        },
        {
          "method": "org.eclipse.ui.PlatformUI.createDisplay",
          "source": "PlatformUI.java:153"
        },
        {
          "method": "org.eclipse.ui.internal.ide.IDEApplication.createDisplay",
          "source": "IDEApplication.java:122"
        },
        {
          "method": "org.eclipse.ui.internal.ide.IDEApplication.run",
          "source": "IDEApplication.java:72"
        },
        {
          "method": "org.eclipse.core.internal.runtime.PlatformActivator$1.run",
          "source": "PlatformActivator.java:335"
        },
        {
          "method": "org.eclipse.core.runtime.adaptor.EclipseStarter.run",
          "source": "EclipseStarter.java:273"
        },
        {
          "method": "org.eclipse.core.runtime.adaptor.EclipseStarter.run",
          "source": "EclipseStarter.java:129"
        },
        {
          "method": "sun.reflect.NativeMethodAccessorImpl.invoke0",
          "source": "Native Method"
        },
        {
          "method": "sun.reflect.NativeMethodAccessorImpl.invoke",
          "source": "NativeMethodAccessorImpl.java:85"
        },
        {
          "method": "sun.reflect.NativeMethodAccessorImpl.invoke",
          "source": "NativeMethodAccessorImpl.java:58"
        },
        {
          "method": "sun.reflect.DelegatingMethodAccessorImpl.invoke",
          "source": "DelegatingMethodAccessorImpl.java:60"
        },
        {
          "method": "java.lang.reflect.Method.invoke",
          "source": "Method.java:391"
        },
        {
          "method": "org.eclipse.core.launcher.Main.basicRun",
          "source": "Main.java:185"
        },
        {
          "method": "org.eclipse.core.launcher.Main.run",
          "source": "Main.java:704"
        },
        {
          "method": "org.eclipse.core.launcher.Main.main",
          "source": "Main.java:688"
        }
      ],
      "causedBy": {
        "exceptionType": "java.lang.NullPointerException",
        "elements": [
          {
            "method": "java.lang.ClassLoader.loadLibrary0",
            "source": "ClassLoader.java:2171"
          },
          {
            "method": "java.lang.ClassLoader.loadLibrary",
            "source": "ClassLoader.java:1988"
          },
          {
            "method": "java.lang.Runtime.loadLibrary0",
            "source": "Runtime.java:824"
          },
          {
            "method": "java.lang.System.loadLibrary",
            "source": "System.java:908"
          },
          {
            "method": "org.eclipse.swt.internal.Library.loadLibrary",
            "source": "Library.java:100"
          },
          {
            "method": "org.eclipse.swt.internal.motif.OS.\u003cclinit\u003e",
            "source": "OS.java:20"
          }
        ],
        "number": 0,
        "commentIndex": 0
      },
      "number": 0,
      "commentIndex": 0,
      "bugId": "115979",
      "duplicateId": "145498",
      "date": "2005-11-11T09:06:36+01:00",
      "product": "Platform",
      "component": "SWT",
      "severity": "normal"
    }
  ],
  "groupId": "145498",
  "bugId": "115979",
  "duplicateId": "145498",
  "date": "2005-11-11T09:06:36+01:00",
  "product": "Platform",
  "component": "SWT",
  "severity": "normal"
}