{
  "comments": [
    "Installing eclipse on FC4 with a properly installed and built Sun Java \ninstallation. \n \nSDK runs fine.  Stable, no errors, etc.  \n \nInstalling cdt-3.0.0 throws these errors.  The first is a missing TableLock \nfile.  I\u0027ve confirmed it is indeed not there. \n \n \n \n$usr/share/eclipse/eclipse  \n!SESSION 2005-11-14 01:36:31.343  \n-----------------------------------------------  \neclipse.buildId\u003dM20050929-0840  \njava.version\u003d1.5.0_05  \njava.vendor\u003dSun Microsystems Inc.  \nBootLoader constants: OS\u003dlinux, ARCH\u003dx86, WS\u003dgtk, NL\u003den_US  \nCommand-line arguments:  -os linux -ws gtk -arch x86  \n  \n!ENTRY org.eclipse.osgi 2005-11-14 01:36:31.555  \n!MESSAGE Error reading  \nconfiguration: /usr/share/eclipse/configuration/org.eclipse.osgi/.manager/.fileTableLock  \n(No such file or directory)  \n!STACK 0  \njava.io.FileNotFoundException: /usr/share/eclipse/configuration/org.eclipse.osgi/.manager/.fileTableLock  \n(No such file or directory)  \n        at java.io.FileOutputStream.openAppend(Native Method)  \n        at java.io.FileOutputStream.\u003cinit\u003e(FileOutputStream.java:177)  \n        at  \norg.eclipse.core.runtime.internal.adaptor.Locker_JavaNio.lock(Locker_JavaNio.java:34)  \n        at  \norg.eclipse.core.runtime.adaptor.FileManager.lock(FileManager.java:361)  \n        at  \norg.eclipse.core.runtime.adaptor.FileManager.open(FileManager.java:658)  \n        at  \norg.eclipse.core.runtime.adaptor.EclipseAdaptor.initFileManager(EclipseAdaptor.java:818)  \n        at  \norg.eclipse.core.runtime.adaptor.EclipseAdaptor.initialize(EclipseAdaptor.java:139)  \n        at  \norg.eclipse.osgi.framework.internal.core.Framework.initialize(Framework.java:128)  \n        at  \norg.eclipse.osgi.framework.internal.core.Framework.\u003cinit\u003e(Framework.java:106)  \n        at  \norg.eclipse.osgi.framework.internal.core.OSGi.createFramework(OSGi.java:90)  \n        at org.eclipse.osgi.framework.internal.core.OSGi.\u003cinit\u003e(OSGi.java:31)  \n        at  \norg.eclipse.core.runtime.adaptor.EclipseStarter.startup(EclipseStarter.java:272)  \n        at  \norg.eclipse.core.runtime.adaptor.EclipseStarter.run(EclipseStarter.java:159)  \n        at sun.reflect.NativeMethodAccessorImpl.invoke0(Native Method)  \n        at  \nsun.reflect.NativeMethodAccessorImpl.invoke(NativeMethodAccessorImpl.java:39)  \n        at  \nsun.reflect.DelegatingMethodAccessorImpl.invoke(DelegatingMethodAccessorImpl.java:25)  \n        at java.lang.reflect.Method.invoke(Method.java:585)  \n        at org.eclipse.core.launcher.Main.invokeFramework(Main.java:334)  \n        at org.eclipse.core.launcher.Main.basicRun(Main.java:278)  \n        at org.eclipse.core.launcher.Main.run(Main.java:973)  \n        at org.eclipse.core.launcher.Main.main(Main.java:948)",
    "Found more information.  The install works properly as root, but not as a \nregular user.  ",
    "\n\nThis was a permissions problem.  I ran:\n\ncd eclipse\nchown -R root *\nchown root .eclipseproduct\nchown -R krlux *\nchown krlux .eclipseproduct\n\nAnd it works fine. ",
    "Since it appears that there was no problem with CDT, I\u0027m going to mark this INVALID."
  ],
  "commentCreationDates": [
    "2005-11-14T08:41:32+01:00",
    "2005-11-14T08:45:04+01:00",
    "2005-11-25T05:24:18+01:00",
    "2007-05-11T18:05:42+02:00"
  ],
  "traces": [
    {
      "exceptionType": "java.io.FileNotFoundException",
      "message": "/usr/share/eclipse/configuration/org.eclipse.osgi/.manager/.fileTableLock   (No such file or directory)",
      "elements": [
        {
          "method": "java.io.FileOutputStream.openAppend",
          "source": "Native Method"
        },
        {
          "method": "java.io.FileOutputStream.\u003cinit\u003e",
          "source": "FileOutputStream.java:177"
        },
        {
          "method": "org.eclipse.core.runtime.internal.adaptor.Locker_JavaNio.lock",
          "source": "Locker_JavaNio.java:34"
        },
        {
          "method": "org.eclipse.core.runtime.adaptor.FileManager.lock",
          "source": "FileManager.java:361"
        },
        {
          "method": "org.eclipse.core.runtime.adaptor.FileManager.open",
          "source": "FileManager.java:658"
        },
        {
          "method": "org.eclipse.core.runtime.adaptor.EclipseAdaptor.initFileManager",
          "source": "EclipseAdaptor.java:818"
        },
        {
          "method": "org.eclipse.core.runtime.adaptor.EclipseAdaptor.initialize",
          "source": "EclipseAdaptor.java:139"
        },
        {
          "method": "org.eclipse.osgi.framework.internal.core.Framework.initialize",
          "source": "Framework.java:128"
        },
        {
          "method": "org.eclipse.osgi.framework.internal.core.Framework.\u003cinit\u003e",
          "source": "Framework.java:106"
        },
        {
          "method": "org.eclipse.osgi.framework.internal.core.OSGi.createFramework",
          "source": "OSGi.java:90"
        },
        {
          "method": "org.eclipse.osgi.framework.internal.core.OSGi.\u003cinit\u003e",
          "source": "OSGi.java:31"
        },
        {
          "method": "org.eclipse.core.runtime.adaptor.EclipseStarter.startup",
          "source": "EclipseStarter.java:272"
        },
        {
          "method": "org.eclipse.core.runtime.adaptor.EclipseStarter.run",
          "source": "EclipseStarter.java:159"
        },
        {
          "method": "sun.reflect.NativeMethodAccessorImpl.invoke0",
          "source": "Native Method"
        },
        {
          "method": "sun.reflect.NativeMethodAccessorImpl.invoke",
          "source": "NativeMethodAccessorImpl.java:39"
        },
        {
          "method": "sun.reflect.DelegatingMethodAccessorImpl.invoke",
          "source": "DelegatingMethodAccessorImpl.java:25"
        },
        {
          "method": "java.lang.reflect.Method.invoke",
          "source": "Method.java:585"
        },
        {
          "method": "org.eclipse.core.launcher.Main.invokeFramework",
          "source": "Main.java:334"
        },
        {
          "method": "org.eclipse.core.launcher.Main.basicRun",
          "source": "Main.java:278"
        },
        {
          "method": "org.eclipse.core.launcher.Main.run",
          "source": "Main.java:973"
        },
        {
          "method": "org.eclipse.core.launcher.Main.main",
          "source": "Main.java:948"
        }
      ],
      "number": 0,
      "commentIndex": 0,
      "bugId": "116187",
      "date": "2005-11-14T08:41:32+01:00",
      "product": "CDT",
      "component": "cdt-core",
      "severity": "normal"
    }
  ],
  "groupId": "116187",
  "bugId": "116187",
  "date": "2005-11-14T08:41:32+01:00",
  "product": "CDT",
  "component": "cdt-core",
  "severity": "normal"
}