{
  "comments": [
    "I am using the latest version of AJDT (1.3.0.20051125115230).\n\n\nThe reason is not entirely clear, but I have a pointcut of form \n    public pointcut realPC(Common entity)\n    \t: pc1(entity) || pc2(entity);\n\nJust a few hours back, I used to get an error regarding incompatible binding\nof entity in the || poincut. When I got that error, Eclipse was frozen to the \npoint that clicking \"Details\" on exception report made Eclipse hang and \nhad to kill it using the task manager. So I modified the program to avoid\n|| expression in pointcut, after unsuccessfully trying various ways to \nexpress the pointcut. It was an ugly thing to do, since I essentially had to \nduplicate the advice for both pointcuts. Anyway...\n\nThen I tried to reproduce on a smaller project to provide a minimal\nprogram to reproduced the bug. However, it worked just fine on that project\n(and I couldn\u0027t see any material difference in the pointcuts or the classes\ninvolved). Encouraged by this, I retried the or-ed version of the pointcut\non the real project. This time, I get the crash and can acccess the stack\ntrace.\n\njava.lang.NullPointerException\nat org.aspectj.weaver.ast.Test.makeInstanceof(Test.java:78)\nat org.aspectj.weaver.patterns.IfPointcut.findResidueInternal(IfPointcut.java:181)\nat org.aspectj.weaver.patterns.Pointcut.findResidue(Pointcut.java:267)\nat org.aspectj.weaver.patterns.AndPointcut.findResidueInternal(AndPointcut.java:97)\nat org.aspectj.weaver.patterns.Pointcut.findResidue(Pointcut.java:267)\nat org.aspectj.weaver.patterns.AndPointcut.findResidueInternal(AndPointcut.java:97)\nat org.aspectj.weaver.patterns.Pointcut.findResidue(Pointcut.java:267)\nat org.aspectj.weaver.patterns.OrPointcut.findResidueInternal(OrPointcut.java:99)\nat org.aspectj.weaver.patterns.Pointcut.findResidue(Pointcut.java:267)\nat org.aspectj.weaver.patterns.OrPointcut.findResidueInternal(OrPointcut.java:99)\nat org.aspectj.weaver.patterns.Pointcut.findResidue(Pointcut.java:267)\nat org.aspectj.weaver.bcel.BcelAdvice.specializeOn(BcelAdvice.java:133)\nat org.aspectj.weaver.bcel.BcelShadow.prepareForMungers(BcelShadow.java:308)\nat org.aspectj.weaver.Shadow.implement(Shadow.java:404)\nat org.aspectj.weaver.bcel.BcelClassWeaver.implement(BcelClassWeaver.java:2146)\nat org.aspectj.weaver.bcel.BcelClassWeaver.weave(BcelClassWeaver.java:467)\nat org.aspectj.weaver.bcel.BcelClassWeaver.weave(BcelClassWeaver.java:102)\nat org.aspectj.weaver.bcel.BcelWeaver.weave(BcelWeaver.java:1534)\nat org.aspectj.weaver.bcel.BcelWeaver.weaveWithoutDump(BcelWeaver.java:1485)\nat org.aspectj.weaver.bcel.BcelWeaver.weaveAndNotify(BcelWeaver.java:1266)\nat org.aspectj.weaver.bcel.BcelWeaver.weave(BcelWeaver.java:1088)\nat org.aspectj.ajdt.internal.compiler.AjCompilerAdapter.weave(AjCompilerAdapter.java:300)\nat org.aspectj.ajdt.internal.compiler.AjCompilerAdapter.afterCompiling(AjCompilerAdapter.java:178)\nat org.aspectj.ajdt.internal.compiler.CompilerAdapter.ajc$afterReturning$org_aspectj_ajdt_internal_compiler_CompilerAdapter$2$f9cc9ca0(CompilerAdapter.aj:70)\nat org.aspectj.org.eclipse.jdt.internal.compiler.Compiler.compile(Compiler.java:367)\nat org.aspectj.ajdt.internal.core.builder.AjBuildManager.performCompilation(AjBuildManager.java:809)\nat org.aspectj.ajdt.internal.core.builder.AjBuildManager.doBuild(AjBuildManager.java:230)\nat org.aspectj.ajdt.internal.core.builder.AjBuildManager.batchBuild(AjBuildManager.java:156)\nat org.aspectj.ajde.internal.CompilerAdapter.compile(CompilerAdapter.java:122)\nat org.aspectj.ajde.internal.AspectJBuildManager$CompilerThread.run(AspectJBuildManager.java:191)\n\ntrouble in: \npublic abstract class com.aspectivity.mgmt.web.entity.ManageEntity extends com.aspectivity.mgmt.web.TemplatePage:\n  public void \u003cinit\u003e(com.aspectivity.mgmt.model.Entity, boolean, String, String, String, String, String)    org.aspectj.weaver.MethodDeclarationLineNumber: 19:557\n:\n                    ALOAD_0     // com.aspectivity.mgmt.web.entity.ManageEntity this   (line 19)\n                    INVOKESPECIAL com.aspectivity.mgmt.web.TemplatePage.\u003cinit\u003e ()V\n                    ALOAD_1\n                    ASTORE 9\n                    ILOAD_2\n                    ISTORE 10\n                    ALOAD_3\n                    ASTORE 11\n                    ALOAD 4\n                    ASTORE 12\n                    ALOAD 5\n                    ASTORE 13\n                    ALOAD 6\n                    ASTORE 14\n                    ALOAD 7\n                    ASTORE 15\n    constructor-execution(void com.aspectivity.mgmt.web.entity.ManageEntity.\u003cinit\u003e(com.aspectivity.mgmt.model.Entity, boolean, java.lang.String, java.lang.String, java.lang.String, java.lang.String, java.lang.String))\n    |               ALOAD_0     // com.aspectivity.mgmt.web.entity.ManageEntity this   (line 23)\n    |               ALOAD_3     // java.lang.String pageTitle\n    |               INVOKEVIRTUAL com.aspectivity.mgmt.web.entity.ManageEntity.setPageTitle (Ljava/lang/String;)V\n    |               ALOAD_0     // com.aspectivity.mgmt.web.entity.ManageEntity this   (line 25)\n    |               ALOAD_0     // com.aspectivity.mgmt.web.entity.ManageEntity this\n    |               ALOAD_1     // com.aspectivity.mgmt.model.Entity entity\n    |               ALOAD 5     // java.lang.String addEntityLinkText\n    |               INVOKEVIRTUAL com.aspectivity.mgmt.web.entity.ManageEntity.getEntitiesListView (Lcom/aspectivity/mgmt/model/Entity;Ljava/lang/String;)Lwicket/markup/html/list/ListView;\n    |               INVOKEVIRTUAL com.aspectivity.mgmt.web.entity.ManageEntity.add (Lwicket/Component;)Lwicket/MarkupContainer;\n    |               POP\n    |               ALOAD_0     // com.aspectivity.mgmt.web.entity.ManageEntity this   (line 27)\n    |               LDC \"addEntityLink\"\n    |               ACONST_NULL\n    |               INVOKEVIRTUAL com.aspectivity.mgmt.web.entity.ManageEntity.getEditLink (Ljava/lang/String;Lcom/aspectivity/mgmt/model/Entity;)Lwicket/markup/html/link/Link;\n    |               ASTORE 8\n    |               ALOAD_0     // com.aspectivity.mgmt.web.entity.ManageEntity this   (line 28)\n    |               ALOAD 8     // wicket.markup.html.link.Link addEntityLink\n    |               INVOKEVIRTUAL com.aspectivity.mgmt.web.entity.ManageEntity.add (Lwicket/Component;)Lwicket/MarkupContainer;\n    |               POP\n    |               ALOAD 8     // wicket.markup.html.link.Link addEntityLink   (line 29)\n    |               NEW wicket.markup.html.basic.Label\n    |               DUP\n    |               LDC \"addEntityLinkText\"\n    |               ALOAD 5     // java.lang.String addEntityLinkText\n    |               INVOKESPECIAL wicket.markup.html.basic.Label.\u003cinit\u003e (Ljava/lang/String;Ljava/lang/String;)V\n    |               INVOKEVIRTUAL wicket.markup.html.link.Link.add (Lwicket/Component;)Lwicket/MarkupContainer;\n    |               POP\n    |               ILOAD_2     // boolean isInitialView   (line 31)\n    |               IFEQ L0\n    |               ALOAD_0     // com.aspectivity.mgmt.web.entity.ManageEntity this   (line 32)\n    |               NEW wicket.markup.html.basic.Label\n    |               DUP\n    |               LDC \"editEntity\"\n    |               LDC \"\"\n    |               INVOKESPECIAL wicket.markup.html.basic.Label.\u003cinit\u003e (Ljava/lang/String;Ljava/lang/String;)V\n    |               INVOKEVIRTUAL com.aspectivity.mgmt.web.entity.ManageEntity.add (Lwicket/Component;)Lwicket/MarkupContainer;\n    |               POP\n    |               GOTO L1\n    |           L0: ALOAD_0     // com.aspectivity.mgmt.web.entity.ManageEntity this   (line 34)\n    |               ALOAD_0     // com.aspectivity.mgmt.web.entity.ManageEntity this\n    |               ALOAD_1     // com.aspectivity.mgmt.model.Entity entity\n    |               ILOAD_2     // boolean isInitialView\n    |               ALOAD 6     // java.lang.String addPanelTtile\n    |               ALOAD 7     // java.lang.String editPanelTitle\n    |               INVOKESPECIAL com.aspectivity.mgmt.web.entity.ManageEntity.getEditPanel (Lcom/aspectivity/mgmt/model/Entity;ZLjava/lang/String;Ljava/lang/String;)Lwicket/Component;\n    |               INVOKEVIRTUAL com.aspectivity.mgmt.web.entity.ManageEntity.add (Lwicket/Component;)Lwicket/MarkupContainer;\n    |               POP\n    |           L1: ALOAD_0     // com.aspectivity.mgmt.web.entity.ManageEntity this   (line 37)\n    |               NEW wicket.markup.html.basic.Label\n    |               DUP\n    |               LDC \"listViewTitle\"\n    |               ALOAD 4     // java.lang.String listViewTitle\n    |               INVOKESPECIAL wicket.markup.html.basic.Label.\u003cinit\u003e (Ljava/lang/String;Ljava/lang/String;)V\n    |               INVOKEVIRTUAL com.aspectivity.mgmt.web.entity.ManageEntity.add (Lwicket/Component;)Lwicket/MarkupContainer;\n    |               POP\n    |               RETURN   (line 38)\n    constructor-execution(void com.aspectivity.mgmt.web.entity.ManageEntity.\u003cinit\u003e(com.aspectivity.mgmt.model.Entity, boolean, java.lang.String, java.lang.String, java.lang.String, java.lang.String, java.lang.String))\n  end public void \u003cinit\u003e(com.aspectivity.mgmt.model.Entity, boolean, String, String, String, String, String)\n\n  protected abstract com.aspectivity.mgmt.model.Entity createNewEntity()    org.aspectj.weaver.MethodDeclarationLineNumber: 40:1233\n;\n\n  protected abstract void removeEntity(com.aspectivity.mgmt.model.Entity)    org.aspectj.weaver.MethodDeclarationLineNumber: 41:1278\n;\n\n  protected abstract java.util.List getAllEntities()    org.aspectj.weaver.MethodDeclarationLineNumber: 42:1351\n;\n\n  protected abstract com.aspectivity.mgmt.web.entity.ManageEntity createNewPage(com.aspectivity.mgmt.model.Entity, boolean)    org.aspectj.weaver.MethodDeclarationLineNumber: 44:1406\n;\n\n  protected abstract wicket.Component createEditPanel(String, String, com.aspectivity.mgmt.model.Entity)    org.aspectj.weaver.MethodDeclarationLineNumber: 45:1490\n;\n\n  protected wicket.markup.html.list.ListView getEntitiesListView(com.aspectivity.mgmt.model.Entity, String)    org.aspectj.weaver.MethodDeclarationLineNumber: 47:1581\n:\n                    NEW com.aspectivity.mgmt.web.entity.EntityListView   (line 48)\n                    DUP\n                    ALOAD_0     // com.aspectivity.mgmt.web.entity.ManageEntity this\n                    LDC \"entityList\"\n                    ALOAD_0     // com.aspectivity.mgmt.web.entity.ManageEntity this\n                    INVOKEVIRTUAL com.aspectivity.mgmt.web.entity.ManageEntity.getAllEntities ()Ljava/util/List;\n                    ALOAD_1     // com.aspectivity.mgmt.model.Entity entity\n                    INVOKESPECIAL com.aspectivity.mgmt.web.entity.EntityListView.\u003cinit\u003e (Lcom/aspectivity/mgmt/web/entity/ManageEntity;Ljava/lang/String;Ljava/util/List;Lcom/aspectivity/mgmt/model/Entity;)V\n                    ARETURN\n  end protected wicket.markup.html.list.ListView getEntitiesListView(com.aspectivity.mgmt.model.Entity, String)\n\n  protected wicket.markup.html.link.Link getEditLink(String, com.aspectivity.mgmt.model.Entity)    org.aspectj.weaver.MethodDeclarationLineNumber: 51:1743\n:\n                    NEW wicket.markup.html.link.PageLink   (line 52)\n                    DUP\n                    ALOAD_1     // java.lang.String name\n                    NEW com.aspectivity.mgmt.web.entity.ManageEntity$1\n                    DUP\n                    ALOAD_0     // com.aspectivity.mgmt.web.entity.ManageEntity this\n                    ALOAD_2     // com.aspectivity.mgmt.model.Entity entity\n                    INVOKESPECIAL com.aspectivity.mgmt.web.entity.ManageEntity$1.\u003cinit\u003e (Lcom/aspectivity/mgmt/web/entity/ManageEntity;Lcom/aspectivity/mgmt/model/Entity;)V\n                    INVOKESPECIAL wicket.markup.html.link.PageLink.\u003cinit\u003e (Ljava/lang/String;Lwicket/markup/html/link/IPageLink;)V\n                    ARETURN\n  end protected wicket.markup.html.link.Link getEditLink(String, com.aspectivity.mgmt.model.Entity)\n\n  protected wicket.markup.html.link.Link getRemoveLink(String, wicket.markup.html.list.ListItem)    org.aspectj.weaver.MethodDeclarationLineNumber: 63:2013\n:\n                    NEW com.aspectivity.mgmt.web.entity.ManageEntity$2   (line 64)\n                    DUP\n                    ALOAD_0     // com.aspectivity.mgmt.web.entity.ManageEntity this\n                    ALOAD_1     // java.lang.String id\n                    ALOAD_2     // wicket.markup.html.list.ListItem item\n                    INVOKESPECIAL com.aspectivity.mgmt.web.entity.ManageEntity$2.\u003cinit\u003e (Lcom/aspectivity/mgmt/web/entity/ManageEntity;Ljava/lang/String;Lwicket/markup/html/list/ListItem;)V\n                    ARETURN\n  end protected wicket.markup.html.link.Link getRemoveLink(String, wicket.markup.html.list.ListItem)\n\n  private wicket.Component getEditPanel(com.aspectivity.mgmt.model.Entity, boolean, String, String)    org.aspectj.weaver.MethodDeclarationLineNumber: 75:2376\n:\n                    ALOAD_1     // com.aspectivity.mgmt.model.Entity entity   (line 77)\n                    IFNONNULL L0\n                    ALOAD_3     // java.lang.String addPanelTtile\n                    GOTO L1\n                L0: ALOAD 4     // java.lang.String editPanelTitle\n                L1: ASTORE 5\n                    ALOAD_1     // com.aspectivity.mgmt.model.Entity entity   (line 78)\n                    IFNONNULL L2\n                    ALOAD_0     // com.aspectivity.mgmt.web.entity.ManageEntity this   (line 79)\n                    INVOKEVIRTUAL com.aspectivity.mgmt.web.entity.ManageEntity.createNewEntity ()Lcom/aspectivity/mgmt/model/Entity;\n                    ASTORE_1     // com.aspectivity.mgmt.model.Entity entity\n                L2: ALOAD_0     // com.aspectivity.mgmt.web.entity.ManageEntity this   (line 81)\n                    LDC \"editEntity\"\n                    ALOAD 5     // java.lang.String panelTitle\n                    ALOAD_1     // com.aspectivity.mgmt.model.Entity entity\n                    INVOKEVIRTUAL com.aspectivity.mgmt.web.entity.ManageEntity.createEditPanel (Ljava/lang/String;Ljava/lang/String;Lcom/aspectivity/mgmt/model/Entity;)Lwicket/Component;\n                    ARETURN\n  end private wicket.Component getEditPanel(com.aspectivity.mgmt.model.Entity, boolean, String, String)\n\nend public abstract class com.aspectivity.mgmt.web.entity.ManageEntity\n\nwhen implementing on shadow constructor-execution(void com.aspectivity.mgmt.web.entity.ManageEntity.\u003cinit\u003e(com.aspectivity.mgmt.model.Entity, boolean, java.lang.String, java.lang.String, java.lang.String, java.lang.String, java.lang.String))\nwhen weaving type com.aspectivity.mgmt.web.entity.ManageEntity\nwhen weaving classes \nwhen weaving \nwhen batch building BuildConfig[C:\\work\\projects\\workspace\\.metadata\\.plugins\\org.eclipse.ajdt.core\\Aspectivity.generated.lst] #Files\u003d87",
    "Ramnivas, to investigate this further we need to know the complete pointcuts you are using,  what are the definitions of pc1() and pc2() (and any other required pointcuts)?\n\nWe know the shadow that is causing the problem:\n\nconstructor-execution(void\ncom.aspectivity.mgmt.web.entity.ManageEntity.\u003cinit\u003e(com.aspectivity.mgmt.model.Entity,\nboolean, java.lang.String, java.lang.String, java.lang.String,\njava.lang.String, java.lang.String))\n\nso that + the pointcuts should be enough to progress.",
    "Andy,\n\nHere is the pointcut along with relevant parts of base and derived aspect.\npublic abstract aspect AbstractEntityManagementAspect {\n    public abstract pointcut entityAccessor(CommonEntity entity);\n\n    ... advice to the pointcut...\n}\n\npublic aspect UIDEntityManagementAspect extends AbstractEntityManagementAspect {\n    public pointcut entityAccessor1(CommonEntity entity)\n        : (execution(* CommonEntity+.add*(CommonEntity+))\n           || (execution(* CommonEntity+.remove*(CommonEntity+))))\n          \u0026\u0026 within(CommonEntity+)\n          \u0026\u0026 args(entity) \u0026\u0026 if(entity !\u003d null);\n   \n    public pointcut entityAccessor2(CommonEntity entity)\n        : execution(ManageEntity.new(CommonEntity+, ..)) \n          \u0026\u0026 within(ManageEntity)\n          \u0026\u0026 args(entity, ..) \n          \u0026\u0026 if(entity !\u003d null);\n    \n    public pointcut entityAccessor(CommonEntity entity)\n        : entityAccessor1(entity) || entityAccessor2(entity);\n\n    declare parents: Entity implements CommonEntity;\n}",
    "Created an attachment (id\u003d31107)\ntestcase patch\n\nApply the patch to the tests project.\n\nWith the given information in the previous comment I\u0027ve recreated the problem and created an AJ testcase.\n\nNote everything compiles fine (no NPE) if\n\npublic pointcut entityAccessor2(CommonEntity entity)\n    : execution(ManageEntity.new(CommonEntity+, ..)) \n      \u0026\u0026 within(ManageEntity)\n      \u0026\u0026 args(entity, ..)                          \u003c-------------\n      \u0026\u0026 if(entity !\u003d null);\n\nis changed to:\n\npublic pointcut entityAccessor2(CommonEntity entity)\n    : execution(ManageEntity.new(CommonEntity+, ..)) \n      \u0026\u0026 within(ManageEntity)\n      \u0026\u0026 args(entity)                               \u003c--------------\n      \u0026\u0026 if(entity !\u003d null);",
    "Another note...it also doesn\u0027t fail (no NPE) if the two if pointcuts are removed ie. if we have:\n\n    public pointcut entityAccessor1(CommonEntity entity)\n        : (execution(* CommonEntity+.add*(CommonEntity+))\n           || (execution(* CommonEntity+.remove*(CommonEntity+))))\n          \u0026\u0026 within(CommonEntity+)\n          \u0026\u0026 args(entity);\n\n    public pointcut entityAccessor2(CommonEntity entity)\n        : execution(ManageEntity.new(CommonEntity+, ..)) \n          \u0026\u0026 within(ManageEntity)\n          \u0026\u0026 args(entity, ..) ;\n\n    public pointcut entityAccessor(CommonEntity entity)\n        : entityAccessor1(entity) || entityAccessor2(entity);\n\n    declare parents: Entity implements CommonEntity;\n\nThen the tests pass.",
    "Created an attachment (id\u003d31118)\nsimplified testcase\n\nApply patch to the tests project.\n\nThis patch contains a simplified testcase to the one previously attached. It contains the three things needed to recreate this bug:\n\n* An OR pointcut\n* if pointcut\n* args(something,..)",
    "Thanks for the test case - that helped a lot. I\u0027ve followed the code paths through, and found the cause of the bug. At the join point for the constructor taking (String, boolean), the side of the pointcut that matches using args(String) can never match, and so does not bind any variable. The other side of the pointcut does of course match in this case. Because there is no binding in that branch (legitimately) the Var can be null when we come to look at it. After much careful investigation, the fix is a simple one-line change to IfPointcut.findResidue to cope with this case.\n\nFix committed in tree, waiting on build.",
    "fix available."
  ],
  "commentCreationDates": [
    "2005-11-27T06:01:55+01:00",
    "2005-12-02T11:25:27+01:00",
    "2005-12-02T16:25:59+01:00",
    "2005-12-05T09:45:39+01:00",
    "2005-12-05T14:52:04+01:00",
    "2005-12-05T15:08:01+01:00",
    "2005-12-06T03:20:53+01:00",
    "2005-12-07T11:40:13+01:00"
  ],
  "traces": [
    {
      "exceptionType": "java.lang.NullPointerException",
      "elements": [
        {
          "method": "org.aspectj.weaver.ast.Test.makeInstanceof",
          "source": "Test.java:78"
        },
        {
          "method": "org.aspectj.weaver.patterns.IfPointcut.findResidueInternal",
          "source": "IfPointcut.java:181"
        },
        {
          "method": "org.aspectj.weaver.patterns.Pointcut.findResidue",
          "source": "Pointcut.java:267"
        },
        {
          "method": "org.aspectj.weaver.patterns.AndPointcut.findResidueInternal",
          "source": "AndPointcut.java:97"
        },
        {
          "method": "org.aspectj.weaver.patterns.Pointcut.findResidue",
          "source": "Pointcut.java:267"
        },
        {
          "method": "org.aspectj.weaver.patterns.AndPointcut.findResidueInternal",
          "source": "AndPointcut.java:97"
        },
        {
          "method": "org.aspectj.weaver.patterns.Pointcut.findResidue",
          "source": "Pointcut.java:267"
        },
        {
          "method": "org.aspectj.weaver.patterns.OrPointcut.findResidueInternal",
          "source": "OrPointcut.java:99"
        },
        {
          "method": "org.aspectj.weaver.patterns.Pointcut.findResidue",
          "source": "Pointcut.java:267"
        },
        {
          "method": "org.aspectj.weaver.patterns.OrPointcut.findResidueInternal",
          "source": "OrPointcut.java:99"
        },
        {
          "method": "org.aspectj.weaver.patterns.Pointcut.findResidue",
          "source": "Pointcut.java:267"
        },
        {
          "method": "org.aspectj.weaver.bcel.BcelAdvice.specializeOn",
          "source": "BcelAdvice.java:133"
        },
        {
          "method": "org.aspectj.weaver.bcel.BcelShadow.prepareForMungers",
          "source": "BcelShadow.java:308"
        },
        {
          "method": "org.aspectj.weaver.Shadow.implement",
          "source": "Shadow.java:404"
        },
        {
          "method": "org.aspectj.weaver.bcel.BcelClassWeaver.implement",
          "source": "BcelClassWeaver.java:2146"
        },
        {
          "method": "org.aspectj.weaver.bcel.BcelClassWeaver.weave",
          "source": "BcelClassWeaver.java:467"
        },
        {
          "method": "org.aspectj.weaver.bcel.BcelClassWeaver.weave",
          "source": "BcelClassWeaver.java:102"
        },
        {
          "method": "org.aspectj.weaver.bcel.BcelWeaver.weave",
          "source": "BcelWeaver.java:1534"
        },
        {
          "method": "org.aspectj.weaver.bcel.BcelWeaver.weaveWithoutDump",
          "source": "BcelWeaver.java:1485"
        },
        {
          "method": "org.aspectj.weaver.bcel.BcelWeaver.weaveAndNotify",
          "source": "BcelWeaver.java:1266"
        },
        {
          "method": "org.aspectj.weaver.bcel.BcelWeaver.weave",
          "source": "BcelWeaver.java:1088"
        },
        {
          "method": "org.aspectj.ajdt.internal.compiler.AjCompilerAdapter.weave",
          "source": "AjCompilerAdapter.java:300"
        },
        {
          "method": "org.aspectj.ajdt.internal.compiler.AjCompilerAdapter.afterCompiling",
          "source": "AjCompilerAdapter.java:178"
        },
        {
          "method": "org.aspectj.ajdt.internal.compiler.CompilerAdapter.ajc$afterReturning$org_aspectj_ajdt_internal_compiler_CompilerAdapter$2$f9cc9ca0",
          "source": "CompilerAdapter.aj:70"
        },
        {
          "method": "org.aspectj.org.eclipse.jdt.internal.compiler.Compiler.compile",
          "source": "Compiler.java:367"
        },
        {
          "method": "org.aspectj.ajdt.internal.core.builder.AjBuildManager.performCompilation",
          "source": "AjBuildManager.java:809"
        },
        {
          "method": "org.aspectj.ajdt.internal.core.builder.AjBuildManager.doBuild",
          "source": "AjBuildManager.java:230"
        },
        {
          "method": "org.aspectj.ajdt.internal.core.builder.AjBuildManager.batchBuild",
          "source": "AjBuildManager.java:156"
        },
        {
          "method": "org.aspectj.ajde.internal.CompilerAdapter.compile",
          "source": "CompilerAdapter.java:122"
        },
        {
          "method": "org.aspectj.ajde.internal.AspectJBuildManager$CompilerThread.run",
          "source": "AspectJBuildManager.java:191"
        }
      ],
      "number": 0,
      "commentIndex": 0,
      "bugId": "118149",
      "date": "2005-11-27T06:01:55+01:00",
      "product": "AspectJ",
      "component": "Compiler",
      "severity": "critical"
    }
  ],
  "groupId": "118149",
  "bugId": "118149",
  "date": "2005-11-27T06:01:55+01:00",
  "product": "AspectJ",
  "component": "Compiler",
  "severity": "critical"
}