{
  "comments": [
    "Driver:  RC1 12/02 00:59\n\nAfter creating a Web project targeting Geronimo without selecting the check box to \"add the project to an EAR\", I tried to run through a bottom-up scenario.  I noticed that on the 3rd page, the EAR fields are enabled.\n\nHowever, this did not seem to hinder the running of the scenario.",
    "I spoke too soon.  I was able to go through the Web service creation wizard a few times even with the EAR field filled in.  However, I just tried again and got the following error on start server:\n\nPublishing failed\n  Distribution of configuration failed.  See .log for details.\n      java.lang.Exception: Distributing project g3EAR failed.\n      at org.apache.geronimo.core.internal.GeronimoServerBehaviour.doFail(GeronimoServerBehaviour.java:277)\n      at org.apache.geronimo.core.internal.GeronimoServerBehaviour.doDeploy(GeronimoServerBehaviour.java:234)\n      at org.apache.geronimo.core.internal.GeronimoServerBehaviour.invokeCommand(GeronimoServerBehaviour.java:205)\n      at org.apache.geronimo.core.internal.GeronimoServerBehaviour.publishModule(GeronimoServerBehaviour.java:192)\n      at org.eclipse.wst.server.core.model.ServerBehaviourDelegate.publishModule(ServerBehaviourDelegate.java:658)\n      at org.eclipse.wst.server.core.model.ServerBehaviourDelegate.publishModules(ServerBehaviourDelegate.java:740)\n      at org.eclipse.wst.server.core.model.ServerBehaviourDelegate.publish(ServerBehaviourDelegate.java:596)\n      at org.eclipse.wst.server.core.internal.Server.doPublish(Server.java:740)\n      at org.eclipse.wst.server.core.internal.Server.publish(Server.java:729)\n      at org.eclipse.jst.ws.internal.consumption.ui.command.StartServerCommand$1.run(StartServerCommand.java:185)\n      at org.eclipse.jface.operation.ModalContext$ModalContextThread.run(ModalContext.java:113)\n",
    "I have the same exact issue. Very frustating when you don\u0027t know why it is happening.",
    "With WTP 1.0, Geronimo 1.0 server and the 01/09 Geronimo plugin, having Geronimo targetted server in an EAR no longer cause the problem in comment #1.  The new problem is documented in when deploying more than 1 Web project in EAR to Geronimo:\n\nhttp://issues.apache.org/jira/browse/GERONIMODEVTOOLS-39\n\nSince Geronimo targetted Web project can be in an EAR or not, as long as Geronimo can handle Web project with EAR properly, the fact that the Web services wizard always adds the project to an EAR is not that big of an issue.\n\nCurrently, we enable the EAR field if server tooling API returns to tell us that EAR is supported on the server.  There\u0027s no API to let us check to see if the Web project can be install directly on the server.\n\nBug 111341 had been opened for this enhancement request.\n\nPlease see bug 103999 for status on other issues found in deploying Web service to Geronimo.\n",
    "With WTP M101 200602070438 + Geronimo 0206 plugins, if I do not put Geronimo targetted Web project into an EAR, I ran into \"Error deploying to Axis\"."
  ],
  "commentCreationDates": [
    "2005-12-03T13:22:08+01:00",
    "2005-12-03T13:26:30+01:00",
    "2005-12-22T15:07:21+01:00",
    "2006-01-11T22:07:07+01:00",
    "2006-02-07T20:01:45+01:00"
  ],
  "traces": [
    {
      "exceptionType": "java.lang.Exception",
      "message": "Distributing project g3EAR failed.",
      "elements": [
        {
          "method": "org.apache.geronimo.core.internal.GeronimoServerBehaviour.doFail",
          "source": "GeronimoServerBehaviour.java:277"
        },
        {
          "method": "org.apache.geronimo.core.internal.GeronimoServerBehaviour.doDeploy",
          "source": "GeronimoServerBehaviour.java:234"
        },
        {
          "method": "org.apache.geronimo.core.internal.GeronimoServerBehaviour.invokeCommand",
          "source": "GeronimoServerBehaviour.java:205"
        },
        {
          "method": "org.apache.geronimo.core.internal.GeronimoServerBehaviour.publishModule",
          "source": "GeronimoServerBehaviour.java:192"
        },
        {
          "method": "org.eclipse.wst.server.core.model.ServerBehaviourDelegate.publishModule",
          "source": "ServerBehaviourDelegate.java:658"
        },
        {
          "method": "org.eclipse.wst.server.core.model.ServerBehaviourDelegate.publishModules",
          "source": "ServerBehaviourDelegate.java:740"
        },
        {
          "method": "org.eclipse.wst.server.core.model.ServerBehaviourDelegate.publish",
          "source": "ServerBehaviourDelegate.java:596"
        },
        {
          "method": "org.eclipse.wst.server.core.internal.Server.doPublish",
          "source": "Server.java:740"
        },
        {
          "method": "org.eclipse.wst.server.core.internal.Server.publish",
          "source": "Server.java:729"
        },
        {
          "method": "org.eclipse.jst.ws.internal.consumption.ui.command.StartServerCommand$1.run",
          "source": "StartServerCommand.java:185"
        },
        {
          "method": "org.eclipse.jface.operation.ModalContext$ModalContextThread.run",
          "source": "ModalContext.java:113"
        }
      ],
      "number": 0,
      "commentIndex": 1,
      "bugId": "119165",
      "date": "2005-12-03T13:26:30+01:00",
      "product": "Web Tools",
      "component": "jst.ws",
      "severity": "normal"
    }
  ],
  "groupId": "119165",
  "bugId": "119165",
  "date": "2005-12-03T13:22:08+01:00",
  "product": "Web Tools",
  "component": "jst.ws",
  "severity": "normal"
}