{
  "comments": [
    "It is same problem as bug: 24867 (concerning similar problem in M1) which state is \u0027worksforme\u0027 but it seems that it does not. I have no idea how to start the workbench\n\nI am using Ubuntu and JDK 5.0. \nEclipse generates in .log the following message: \n\n!ENTRY org.eclipse.osgi 2005-12-06 18:30:28.814\n!MESSAGE Application error\n!STACK 1\njava.lang.UnsatisfiedLinkError: /home/kk/.eclipse/org.eclipse.platform_3.1.1/configuration/org.eclipse.osgi/bundles/33/1/.cp/libswt-pi-gtk-3139.so: /home/kk/.eclipse/org.eclipse.platform_3.1.1/configuration/org.eclipse.osgi/bundles/33/1/.cp/libswt-pi-gtk-3139.so: cannot open shared object file: No such file or directory\n        at java.lang.ClassLoader$NativeLibrary.load(Native Method)\n        at java.lang.ClassLoader.loadLibrary0(ClassLoader.java:1751)\n        at java.lang.ClassLoader.loadLibrary(ClassLoader.java:1660)\n        at java.lang.Runtime.loadLibrary0(Runtime.java:822)\n        at java.lang.System.loadLibrary(System.java:992)\n        at org.eclipse.swt.internal.Library.loadLibrary(Library.java:123)\n        at org.eclipse.swt.internal.gtk.OS.\u003cclinit\u003e(OS.java:19)\n        at org.eclipse.swt.internal.Converter.wcsToMbcs(Converter.java:63)\n        at org.eclipse.swt.internal.Converter.wcsToMbcs(Converter.java:54)\n        at org.eclipse.swt.widgets.Display.\u003cclinit\u003e(Display.java:122)\n        at org.eclipse.ui.internal.Workbench.createDisplay(Workbench.java:381)\n        at org.eclipse.ui.PlatformUI.createDisplay(PlatformUI.java:155)\n        at org.eclipse.ui.internal.ide.IDEApplication.createDisplay(IDEApplication.java:128)\n        at org.eclipse.ui.internal.ide.IDEApplication.run(IDEApplication.java:79)\n        at org.eclipse.core.internal.runtime.PlatformActivator$1.run(PlatformActivator.java:226)\n        at org.eclipse.core.runtime.adaptor.EclipseStarter.run(EclipseStarter.java:376)\n        at org.eclipse.core.runtime.adaptor.EclipseStarter.run(EclipseStarter.java:163)\n        at sun.reflect.NativeMethodAccessorImpl.invoke0(Native Method)\n        at sun.reflect.NativeMethodAccessorImpl.invoke(NativeMethodAccessorImpl.java:39)\n        at sun.reflect.DelegatingMethodAccessorImpl.invoke(DelegatingMethodAccessorImpl.java:25)\n        at java.lang.reflect.Method.invoke(Method.java:585)\n        at org.eclipse.core.launcher.Main.invokeFramework(Main.java:334)\n        at org.eclipse.core.launcher.Main.basicRun(Main.java:278)\n        at org.eclipse.core.launcher.Main.run(Main.java:973)\n        at org.eclipse.core.launcher.Main.main(Main.java:948)\n\nIt was installed from a fresh dowload.",
    "The SWT library is not finding all of its dependencies.  Are you on\nx86-64?  If so, it may be that you\u0027re using a 32-bit VM but have\n64-bit GTK+ installed, or the other way around.\n\nIf it\u0027s not an architecture mismatch, you can run:\n\n  ldd /home/kk/.eclipse/org.eclipse.platform_3.1.1/configuration/org.eclipse.osgi/bundles/33/1/.cp/libswt-pi-gtk-3139.so\n\nto see which dependency you are missing.",
    "Any luck?",
    "I have downloaded the latest 3.2 version and it works fine.\nNothing changed in the environment. I have no idea why the 3.1.1 does not.\nYes I am runnig a 64bit platform but VM is also 64bit and so the eclipse workbench.\nThanks."
  ],
  "commentCreationDates": [
    "2005-12-06T17:59:36+01:00",
    "2005-12-06T18:22:16+01:00",
    "2005-12-10T05:24:44+01:00",
    "2005-12-10T17:29:40+01:00"
  ],
  "traces": [
    {
      "exceptionType": "java.lang.UnsatisfiedLinkError",
      "message": "/home/kk/.eclipse/org.eclipse.platform_3.1.1/configuration/org.eclipse.osgi/bundles/33/1/.cp/libswt-pi-gtk-3139.so: /home/kk/.eclipse/org.eclipse.platform_3.1.1/configuration/org.eclipse.osgi/bundles/33/1/.cp/libswt-pi-gtk-3139.so: cannot open shared object file: No such file or directory",
      "elements": [
        {
          "method": "java.lang.ClassLoader$NativeLibrary.load",
          "source": "Native Method"
        },
        {
          "method": "java.lang.ClassLoader.loadLibrary0",
          "source": "ClassLoader.java:1751"
        },
        {
          "method": "java.lang.ClassLoader.loadLibrary",
          "source": "ClassLoader.java:1660"
        },
        {
          "method": "java.lang.Runtime.loadLibrary0",
          "source": "Runtime.java:822"
        },
        {
          "method": "java.lang.System.loadLibrary",
          "source": "System.java:992"
        },
        {
          "method": "org.eclipse.swt.internal.Library.loadLibrary",
          "source": "Library.java:123"
        },
        {
          "method": "org.eclipse.swt.internal.gtk.OS.\u003cclinit\u003e",
          "source": "OS.java:19"
        },
        {
          "method": "org.eclipse.swt.internal.Converter.wcsToMbcs",
          "source": "Converter.java:63"
        },
        {
          "method": "org.eclipse.swt.internal.Converter.wcsToMbcs",
          "source": "Converter.java:54"
        },
        {
          "method": "org.eclipse.swt.widgets.Display.\u003cclinit\u003e",
          "source": "Display.java:122"
        },
        {
          "method": "org.eclipse.ui.internal.Workbench.createDisplay",
          "source": "Workbench.java:381"
        },
        {
          "method": "org.eclipse.ui.PlatformUI.createDisplay",
          "source": "PlatformUI.java:155"
        },
        {
          "method": "org.eclipse.ui.internal.ide.IDEApplication.createDisplay",
          "source": "IDEApplication.java:128"
        },
        {
          "method": "org.eclipse.ui.internal.ide.IDEApplication.run",
          "source": "IDEApplication.java:79"
        },
        {
          "method": "org.eclipse.core.internal.runtime.PlatformActivator$1.run",
          "source": "PlatformActivator.java:226"
        },
        {
          "method": "org.eclipse.core.runtime.adaptor.EclipseStarter.run",
          "source": "EclipseStarter.java:376"
        },
        {
          "method": "org.eclipse.core.runtime.adaptor.EclipseStarter.run",
          "source": "EclipseStarter.java:163"
        },
        {
          "method": "sun.reflect.NativeMethodAccessorImpl.invoke0",
          "source": "Native Method"
        },
        {
          "method": "sun.reflect.NativeMethodAccessorImpl.invoke",
          "source": "NativeMethodAccessorImpl.java:39"
        },
        {
          "method": "sun.reflect.DelegatingMethodAccessorImpl.invoke",
          "source": "DelegatingMethodAccessorImpl.java:25"
        },
        {
          "method": "java.lang.reflect.Method.invoke",
          "source": "Method.java:585"
        },
        {
          "method": "org.eclipse.core.launcher.Main.invokeFramework",
          "source": "Main.java:334"
        },
        {
          "method": "org.eclipse.core.launcher.Main.basicRun",
          "source": "Main.java:278"
        },
        {
          "method": "org.eclipse.core.launcher.Main.run",
          "source": "Main.java:973"
        },
        {
          "method": "org.eclipse.core.launcher.Main.main",
          "source": "Main.java:948"
        }
      ],
      "number": 0,
      "commentIndex": 0,
      "bugId": "119454",
      "date": "2005-12-06T17:59:36+01:00",
      "product": "Platform",
      "component": "SWT",
      "severity": "normal"
    }
  ],
  "groupId": "119454",
  "bugId": "119454",
  "date": "2005-12-06T17:59:36+01:00",
  "product": "Platform",
  "component": "SWT",
  "severity": "normal"
}