{
  "comments": [
    "Saw the following exception on the log file.\nNot sure how to reproduce it.\nDid not get any report (any dialog) of that exception.\n\norg.eclipse.swt.SWTException: Widget is disposed\n        at org.eclipse.swt.SWT.error(SWT.java:1887)\n        at org.eclipse.swt.SWT.error(SWT.java:1819)\n        at org.eclipse.swt.widgets.Widget.error(Widget.java:368)\n        at org.eclipse.swt.widgets.Control.getDisplay(Control.java(Compiled Code\n))\n        at org.eclipse.pde.internal.wizards.imports.PluginImportWizardFirstPage.\ncurrentLaunchChanged(PluginImportWizardFirstPage.java:256)\n        at org.eclipse.pde.internal.PDEPlugin$DebugListener.fireCurrentLaunchCha\nnged(PDEPlugin.java:120)\n        at org.eclipse.pde.internal.PDEPlugin$DebugListener.handleDebugEvent(PDE\nPlugin.java:110)\n        at org.eclipse.debug.core.DebugPlugin.fireDebugEvent(DebugPlugin.java:20\n5)\n        at org.eclipse.debug.internal.core.RuntimeProcess.fireEvent(RuntimeProce\nss.java:205)\n        at org.eclipse.debug.internal.core.RuntimeProcess.fireTerminateEvent(Run\ntimeProcess.java:213)\n        at org.eclipse.debug.internal.core.RuntimeProcess.terminated(RuntimeProc\ness.java:182)\n        at org.eclipse.debug.internal.core.ProcessMonitor.monitorProcess(Process\nMonitor.java:49)\n        at org.eclipse.debug.internal.core.ProcessMonitor.access$0(ProcessMonito\nr.java:42)\n        at org.eclipse.debug.internal.core.ProcessMonitor$1.run(ProcessMonitor.j\nava:62)\n        at java.lang.Thread.run(Thread.java:498)",
    "This code is no longer in the import wizard page so you won\u0027t be seeing this \nexception again."
  ],
  "commentCreationDates": [
    "2002-03-20T17:38:29+01:00",
    "2002-04-03T22:19:13+02:00"
  ],
  "traces": [
    {
      "exceptionType": "org.eclipse.swt.SWTException",
      "message": "Widget is disposed",
      "elements": [
        {
          "method": "org.eclipse.swt.SWT.error",
          "source": "SWT.java:1887"
        },
        {
          "method": "org.eclipse.swt.SWT.error",
          "source": "SWT.java:1819"
        },
        {
          "method": "org.eclipse.swt.widgets.Widget.error",
          "source": "Widget.java:368"
        },
        {
          "method": "org.eclipse.swt.widgets.Control.getDisplay",
          "source": "Control.java(Compiled Code )"
        },
        {
          "method": "org.eclipse.pde.internal.wizards.imports.PluginImportWizardFirstPage.currentLaunchChanged",
          "source": "PluginImportWizardFirstPage.java:256"
        },
        {
          "method": "org.eclipse.pde.internal.PDEPlugin$DebugListener.fireCurrentLaunchChanged",
          "source": "PDEPlugin.java:120"
        },
        {
          "method": "org.eclipse.pde.internal.PDEPlugin$DebugListener.handleDebugEvent",
          "source": "PDE Plugin.java:110"
        },
        {
          "method": "org.eclipse.debug.core.DebugPlugin.fireDebugEvent",
          "source": "DebugPlugin.java:20 5"
        },
        {
          "method": "org.eclipse.debug.internal.core.RuntimeProcess.fireEvent",
          "source": "RuntimeProce ss.java:205"
        },
        {
          "method": "org.eclipse.debug.internal.core.RuntimeProcess.fireTerminateEvent",
          "source": "Run timeProcess.java:213"
        },
        {
          "method": "org.eclipse.debug.internal.core.RuntimeProcess.terminated",
          "source": "RuntimeProc ess.java:182"
        },
        {
          "method": "org.eclipse.debug.internal.core.ProcessMonitor.monitorProcess",
          "source": "Process Monitor.java:49"
        },
        {
          "method": "org.eclipse.debug.internal.core.ProcessMonitor.access$0",
          "source": "ProcessMonito r.java:42"
        },
        {
          "method": "org.eclipse.debug.internal.core.ProcessMonitor$1.run",
          "source": "ProcessMonitor.j ava:62"
        },
        {
          "method": "java.lang.Thread.run",
          "source": "Thread.java:498"
        }
      ],
      "number": 0,
      "commentIndex": 0,
      "bugId": "11950",
      "date": "2002-03-20T17:38:29+01:00",
      "product": "PDE",
      "component": "UI",
      "severity": "normal"
    }
  ],
  "groupId": "11950",
  "bugId": "11950",
  "date": "2002-03-20T17:38:29+01:00",
  "product": "PDE",
  "component": "UI",
  "severity": "normal"
}