{
  "comments": [
    "Using build I20051206-1200.\n\nI wanted to apply a patch and then got a NPE. Here\u0027s the corresponding stack trace:\n!ENTRY org.eclipse.ui 4 0 2005-12-08 09:50:50.011\n!MESSAGE java.lang.NullPointerException\n!STACK 0\njava.lang.NullPointerException\n        at org.eclipse.compare.internal.patch.WorkspacePatcher.parse(WorkspacePatcher.java:111)\n        at org.eclipse.compare.internal.patch.InputPatchPage.isPatchFile(InputPatchPage.java:735)\n        at org.eclipse.compare.internal.patch.InputPatchPage.adjustToCurrentTarget(InputPatchPage.java:711)\n        at org.eclipse.compare.internal.patch.InputPatchPage.createControl(InputPatchPage.java:149)\n        at org.eclipse.jface.wizard.Wizard.createPageControls(Wizard.java:179)\n        at org.eclipse.jface.wizard.WizardDialog.createPageControls(WizardDialog.java:611)\n        at org.eclipse.jface.wizard.WizardDialog.createContents(WizardDialog.java:502)\n        at org.eclipse.jface.window.Window.create(Window.java:417)\n        at org.eclipse.jface.dialogs.Dialog.create(Dialog.java:1051)\n        at org.eclipse.jface.window.Window.open(Window.java:775)\n        at org.eclipse.compare.internal.patch.CompareWithPatchAction.run(CompareWithPatchAction.java:85)\n        at org.eclipse.compare.internal.BaseCompareAction.run(BaseCompareAction.java:26)\n        at org.eclipse.ui.internal.PluginAction.runWithEvent(PluginAction.java:251)\n        at org.eclipse.jface.action.ActionContributionItem.handleWidgetSelection(ActionContributionItem.java:530)\n        at org.eclipse.jface.action.ActionContributionItem.access$2(ActionContributionItem.java:480)\n        at org.eclipse.jface.action.ActionContributionItem$5.handleEvent(ActionContributionItem.java:392)\n        at org.eclipse.swt.widgets.EventTable.sendEvent(EventTable.java:66)\n        at org.eclipse.swt.widgets.Widget.sendEvent(Widget.java:906)\n        at org.eclipse.swt.widgets.Display.runDeferredEvents(Display.java:3241)\n        at org.eclipse.swt.widgets.Display.readAndDispatch(Display.java:2861)\n        at org.eclipse.ui.internal.Workbench.runEventLoop(Workbench.java:1763)\n        at org.eclipse.ui.internal.Workbench.runUI(Workbench.java:1727)\n        at org.eclipse.ui.internal.Workbench.createAndRunWorkbench(Workbench.java:396)\n        at org.eclipse.ui.PlatformUI.createAndRunWorkbench(PlatformUI.java:143)\n        at org.eclipse.ui.internal.ide.IDEApplication.run(IDEApplication.java:106)\n        at org.eclipse.core.internal.runtime.PlatformActivator$1.run(PlatformActivator.java:109)\n        at org.eclipse.core.runtime.internal.adaptor.EclipseAppLauncher.runApplication(EclipseAppLauncher.java:92)\n        at org.eclipse.core.runtime.internal.adaptor.EclipseAppLauncher.start(EclipseAppLauncher.java:68)\n        at org.eclipse.core.runtime.adaptor.EclipseStarter.run(EclipseStarter.java:369)\n        at org.eclipse.core.runtime.adaptor.EclipseStarter.run(EclipseStarter.java:167)\n        at sun.reflect.NativeMethodAccessorImpl.invoke0(Native Method)\n        at sun.reflect.NativeMethodAccessorImpl.invoke(NativeMethodAccessorImpl.java:39)\n        at sun.reflect.DelegatingMethodAccessorImpl.invoke(DelegatingMethodAccessorImpl.java:25)\n        at java.lang.reflect.Method.invoke(Method.java:324)\n        at org.eclipse.core.launcher.Main.invokeFramework(Main.java:338)\n        at org.eclipse.core.launcher.Main.basicRun(Main.java:282)\n        at org.eclipse.core.launcher.Main.run(Main.java:977)\n        at org.eclipse.core.launcher.Main.main(Main.java:952)",
    "The code has changed considerably since this bug was logged. Without steps, there is no way for us to test whether this is still an issue."
  ],
  "commentCreationDates": [
    "2005-12-08T08:52:55+01:00",
    "2007-01-22T21:28:28+01:00"
  ],
  "traces": [
    {
      "exceptionType": "java.lang.NullPointerException",
      "elements": [
        {
          "method": "org.eclipse.compare.internal.patch.WorkspacePatcher.parse",
          "source": "WorkspacePatcher.java:111"
        },
        {
          "method": "org.eclipse.compare.internal.patch.InputPatchPage.isPatchFile",
          "source": "InputPatchPage.java:735"
        },
        {
          "method": "org.eclipse.compare.internal.patch.InputPatchPage.adjustToCurrentTarget",
          "source": "InputPatchPage.java:711"
        },
        {
          "method": "org.eclipse.compare.internal.patch.InputPatchPage.createControl",
          "source": "InputPatchPage.java:149"
        },
        {
          "method": "org.eclipse.jface.wizard.Wizard.createPageControls",
          "source": "Wizard.java:179"
        },
        {
          "method": "org.eclipse.jface.wizard.WizardDialog.createPageControls",
          "source": "WizardDialog.java:611"
        },
        {
          "method": "org.eclipse.jface.wizard.WizardDialog.createContents",
          "source": "WizardDialog.java:502"
        },
        {
          "method": "org.eclipse.jface.window.Window.create",
          "source": "Window.java:417"
        },
        {
          "method": "org.eclipse.jface.dialogs.Dialog.create",
          "source": "Dialog.java:1051"
        },
        {
          "method": "org.eclipse.jface.window.Window.open",
          "source": "Window.java:775"
        },
        {
          "method": "org.eclipse.compare.internal.patch.CompareWithPatchAction.run",
          "source": "CompareWithPatchAction.java:85"
        },
        {
          "method": "org.eclipse.compare.internal.BaseCompareAction.run",
          "source": "BaseCompareAction.java:26"
        },
        {
          "method": "org.eclipse.ui.internal.PluginAction.runWithEvent",
          "source": "PluginAction.java:251"
        },
        {
          "method": "org.eclipse.jface.action.ActionContributionItem.handleWidgetSelection",
          "source": "ActionContributionItem.java:530"
        },
        {
          "method": "org.eclipse.jface.action.ActionContributionItem.access$2",
          "source": "ActionContributionItem.java:480"
        },
        {
          "method": "org.eclipse.jface.action.ActionContributionItem$5.handleEvent",
          "source": "ActionContributionItem.java:392"
        },
        {
          "method": "org.eclipse.swt.widgets.EventTable.sendEvent",
          "source": "EventTable.java:66"
        },
        {
          "method": "org.eclipse.swt.widgets.Widget.sendEvent",
          "source": "Widget.java:906"
        },
        {
          "method": "org.eclipse.swt.widgets.Display.runDeferredEvents",
          "source": "Display.java:3241"
        },
        {
          "method": "org.eclipse.swt.widgets.Display.readAndDispatch",
          "source": "Display.java:2861"
        },
        {
          "method": "org.eclipse.ui.internal.Workbench.runEventLoop",
          "source": "Workbench.java:1763"
        },
        {
          "method": "org.eclipse.ui.internal.Workbench.runUI",
          "source": "Workbench.java:1727"
        },
        {
          "method": "org.eclipse.ui.internal.Workbench.createAndRunWorkbench",
          "source": "Workbench.java:396"
        },
        {
          "method": "org.eclipse.ui.PlatformUI.createAndRunWorkbench",
          "source": "PlatformUI.java:143"
        },
        {
          "method": "org.eclipse.ui.internal.ide.IDEApplication.run",
          "source": "IDEApplication.java:106"
        },
        {
          "method": "org.eclipse.core.internal.runtime.PlatformActivator$1.run",
          "source": "PlatformActivator.java:109"
        },
        {
          "method": "org.eclipse.core.runtime.internal.adaptor.EclipseAppLauncher.runApplication",
          "source": "EclipseAppLauncher.java:92"
        },
        {
          "method": "org.eclipse.core.runtime.internal.adaptor.EclipseAppLauncher.start",
          "source": "EclipseAppLauncher.java:68"
        },
        {
          "method": "org.eclipse.core.runtime.adaptor.EclipseStarter.run",
          "source": "EclipseStarter.java:369"
        },
        {
          "method": "org.eclipse.core.runtime.adaptor.EclipseStarter.run",
          "source": "EclipseStarter.java:167"
        },
        {
          "method": "sun.reflect.NativeMethodAccessorImpl.invoke0",
          "source": "Native Method"
        },
        {
          "method": "sun.reflect.NativeMethodAccessorImpl.invoke",
          "source": "NativeMethodAccessorImpl.java:39"
        },
        {
          "method": "sun.reflect.DelegatingMethodAccessorImpl.invoke",
          "source": "DelegatingMethodAccessorImpl.java:25"
        },
        {
          "method": "java.lang.reflect.Method.invoke",
          "source": "Method.java:324"
        },
        {
          "method": "org.eclipse.core.launcher.Main.invokeFramework",
          "source": "Main.java:338"
        },
        {
          "method": "org.eclipse.core.launcher.Main.basicRun",
          "source": "Main.java:282"
        },
        {
          "method": "org.eclipse.core.launcher.Main.run",
          "source": "Main.java:977"
        },
        {
          "method": "org.eclipse.core.launcher.Main.main",
          "source": "Main.java:952"
        }
      ],
      "number": 0,
      "commentIndex": 0,
      "bugId": "119826",
      "date": "2005-12-08T08:52:55+01:00",
      "product": "Platform",
      "component": "Compare",
      "severity": "normal"
    }
  ],
  "groupId": "119826",
  "bugId": "119826",
  "date": "2005-12-08T08:52:55+01:00",
  "product": "Platform",
  "component": "Compare",
  "severity": "normal"
}