{
  "comments": [
    "The following excpetion is being thrown on RC1 build when i clear out the EAR project name to enter the different ear name in the ejb project creation wizard.\n\n!ENTRY org.eclipse.ui 4 0 2005-12-09 10:07:50.366\n!MESSAGE Path for project must have only one segment.\n!STACK 0\njava.lang.IllegalArgumentException: Path for project must have only one segment.\n\n        at java.lang.Throwable.\u003cinit\u003e(Throwable.java:72)\n        at org.eclipse.core.internal.utils.Assert.isLegal(Assert.java:60)\n        at org.eclipse.core.internal.resources.WorkspaceRoot.getProject(Workspac\neRoot.java:134)\n        at org.eclipse.jem.util.emf.workbench.ProjectUtilities.getProject(Projec\ntUtilities.java:728)\n        at org.eclipse.jst.j2ee.project.facet.J2EEModuleFacetInstallDataModelPro\nvider.propertySet(J2EEModuleFacetInstallDataModelProvider.java:90)\n        at org.eclipse.jst.j2ee.internal.ejb.project.operations.EjbFacetInstallD\nataModelProvider.propertySet(EjbFacetInstallDataModelProvider.java:74)\n        at org.eclipse.wst.common.frameworks.internal.datamodel.DataModelImpl.in\nternalSetProperty(DataModelImpl.java:180)\n        at org.eclipse.wst.common.frameworks.internal.datamodel.DataModelImpl.se\ntProperty(DataModelImpl.java:170)\n        at org.eclipse.wst.common.frameworks.internal.datamodel.ui.DataModelSync\nhHelper.setProperty(DataModelSynchHelper.java:189)\n        at org.eclipse.wst.common.frameworks.internal.datamodel.ui.DataModelSync\nhHelper$ComboListener.modifyText(DataModelSynchHelper.java:107)\n        at org.eclipse.swt.widgets.TypedListener.handleEvent(TypedListener.java:\n188)\n        at org.eclipse.swt.widgets.EventTable.sendEvent(EventTable.java:66)\n        at org.eclipse.swt.widgets.Widget.sendEvent(Widget.java:843)\n        at org.eclipse.swt.widgets.Widget.sendEvent(Widget.java:867)\n        at org.eclipse.swt.widgets.Widget.sendEvent(Widget.java:848)\n        at org.eclipse.swt.widgets.Combo.wmCommandChild(Combo.java:2000)\n        at org.eclipse.swt.widgets.Control.WM_COMMAND(Control.java:3164)\n        at org.eclipse.swt.widgets.Control.windowProc(Control.java:3041)\n        at org.eclipse.swt.widgets.Display.windowProc(Display.java:3706)\n        at org.eclipse.swt.internal.win32.OS.CallWindowProcW(Native Method)\n        at org.eclipse.swt.internal.win32.OS.CallWindowProc(OS.java:1580)\n        at org.eclipse.swt.widgets.Combo.callWindowProc(Combo.java:276)\n        at org.eclipse.swt.widgets.Control.windowProc(Control.java:3123)\n        at org.eclipse.swt.widgets.Combo.windowProc(Combo.java:1755)\n        at org.eclipse.swt.widgets.Display.windowProc(Display.java:3706)\n        at org.eclipse.swt.internal.win32.OS.CallWindowProcW(Native Method)\n        at org.eclipse.swt.internal.win32.OS.CallWindowProc(OS.java:1580)\n        at org.eclipse.swt.widgets.Combo.callWindowProc(Combo.java:280)\n        at org.eclipse.swt.widgets.Combo.windowProc(Combo.java:1726)\n        at org.eclipse.swt.widgets.Display.windowProc(Display.java:3706)\n        at org.eclipse.swt.internal.win32.OS.DispatchMessageW(Native Method)\n        at org.eclipse.swt.internal.win32.OS.DispatchMessage(OS.java:1656)\n        at org.eclipse.swt.widgets.Display.readAndDispatch(Display.java:2711)\n        at org.eclipse.jface.window.Window.runEventLoop(Window.java:809)\n        at org.eclipse.jface.window.Window.open(Window.java:787)\n        at org.eclipse.ui.actions.NewProjectAction.run(NewProjectAction.java:114\n)\n        at org.eclipse.jface.action.Action.runWithEvent(Action.java:996)\n        at org.eclipse.jface.action.ActionContributionItem.handleWidgetSelection\n(ActionContributionItem.java:538)\n        at org.eclipse.jface.action.ActionContributionItem.access$2(ActionContri\nbutionItem.java:488)\n        at org.eclipse.jface.action.ActionContributionItem$5.handleEvent(ActionC\nontributionItem.java:400)\n        at org.eclipse.swt.widgets.EventTable.sendEvent(EventTable.java:66)\n        at org.eclipse.swt.widgets.Widget.sendEvent(Widget.java:843)\n        at org.eclipse.swt.widgets.Display.runDeferredEvents(Display.java:3080)\n        at org.eclipse.swt.widgets.Display.readAndDispatch(Display.java:2713)\n        at org.eclipse.ui.internal.Workbench.runEventLoop(Workbench.java:1699)\n        at org.eclipse.ui.internal.Workbench.runUI(Workbench.java:1663)\n        at org.eclipse.ui.internal.Workbench.createAndRunWorkbench(Workbench.jav\na:367)\n        at org.eclipse.ui.PlatformUI.createAndRunWorkbench(PlatformUI.java:143)\n        at org.eclipse.ui.internal.ide.IDEApplication.run(IDEApplication.java:10\n3)\n        at org.eclipse.core.internal.runtime.PlatformActivator$1.run(PlatformAct\nivator.java:226)\n        at org.eclipse.core.runtime.adaptor.EclipseStarter.run(EclipseStarter.ja\nva:376)\n        at org.eclipse.core.runtime.adaptor.EclipseStarter.run(EclipseStarter.ja\nva:163)\n        at sun.reflect.NativeMethodAccessorImpl.invoke0(Native Method)\n        at sun.reflect.NativeMethodAccessorImpl.invoke(NativeMethodAccessorImpl.\njava:85)\n        at sun.reflect.NativeMethodAccessorImpl.invoke(NativeMethodAccessorImpl.\njava:58)\n        at sun.reflect.DelegatingMethodAccessorImpl.invoke(DelegatingMethodAcces\nsorImpl.java:60)\n        at java.lang.reflect.Method.invoke(Method.java:391)\n        at org.eclipse.core.launcher.Main.invokeFramework(Main.java:334)\n        at org.eclipse.core.launcher.Main.basicRun(Main.java:278)\n        at org.eclipse.core.launcher.Main.run(Main.java:973)\n        at org.eclipse.core.launcher.Main.main(Main.java:948)\nPath for project must have only one segment.",
    "Fixed for the next build.",
    "*** Bug 124406 has been marked as a duplicate of this bug. ***",
    "Closing"
  ],
  "commentCreationDates": [
    "2005-12-09T15:09:06+01:00",
    "2006-01-11T14:25:27+01:00",
    "2006-01-19T16:29:43+01:00",
    "2006-06-15T17:47:42+02:00"
  ],
  "traces": [
    {
      "exceptionType": "java.lang.IllegalArgumentException",
      "message": "Path for project must have only one segment.",
      "elements": [
        {
          "method": "java.lang.Throwable.\u003cinit\u003e",
          "source": "Throwable.java:72"
        },
        {
          "method": "org.eclipse.core.internal.utils.Assert.isLegal",
          "source": "Assert.java:60"
        },
        {
          "method": "org.eclipse.core.internal.resources.WorkspaceRoot.getProject",
          "source": "Workspac eRoot.java:134"
        },
        {
          "method": "org.eclipse.jem.util.emf.workbench.ProjectUtilities.getProject",
          "source": "Projec tUtilities.java:728"
        },
        {
          "method": "org.eclipse.jst.j2ee.project.facet.J2EEModuleFacetInstallDataModelProvider.propertySet",
          "source": "J2EEModuleFacetInstallDataModelProvider.java:90"
        },
        {
          "method": "org.eclipse.jst.j2ee.internal.ejb.project.operations.EjbFacetInstallDataModelProvider.propertySet",
          "source": "EjbFacetInstallDataModelProvider.java:74"
        },
        {
          "method": "org.eclipse.wst.common.frameworks.internal.datamodel.DataModelImpl.internalSetProperty",
          "source": "DataModelImpl.java:180"
        },
        {
          "method": "org.eclipse.wst.common.frameworks.internal.datamodel.DataModelImpl.setProperty",
          "source": "DataModelImpl.java:170"
        },
        {
          "method": "org.eclipse.wst.common.frameworks.internal.datamodel.ui.DataModelSynchHelper.setProperty",
          "source": "DataModelSynchHelper.java:189"
        },
        {
          "method": "org.eclipse.wst.common.frameworks.internal.datamodel.ui.DataModelSynchHelper$ComboListener.modifyText",
          "source": "DataModelSynchHelper.java:107"
        },
        {
          "method": "org.eclipse.swt.widgets.TypedListener.handleEvent",
          "source": "TypedListener.java: 188"
        },
        {
          "method": "org.eclipse.swt.widgets.EventTable.sendEvent",
          "source": "EventTable.java:66"
        },
        {
          "method": "org.eclipse.swt.widgets.Widget.sendEvent",
          "source": "Widget.java:843"
        },
        {
          "method": "org.eclipse.swt.widgets.Widget.sendEvent",
          "source": "Widget.java:867"
        },
        {
          "method": "org.eclipse.swt.widgets.Widget.sendEvent",
          "source": "Widget.java:848"
        },
        {
          "method": "org.eclipse.swt.widgets.Combo.wmCommandChild",
          "source": "Combo.java:2000"
        },
        {
          "method": "org.eclipse.swt.widgets.Control.WM_COMMAND",
          "source": "Control.java:3164"
        },
        {
          "method": "org.eclipse.swt.widgets.Control.windowProc",
          "source": "Control.java:3041"
        },
        {
          "method": "org.eclipse.swt.widgets.Display.windowProc",
          "source": "Display.java:3706"
        },
        {
          "method": "org.eclipse.swt.internal.win32.OS.CallWindowProcW",
          "source": "Native Method"
        },
        {
          "method": "org.eclipse.swt.internal.win32.OS.CallWindowProc",
          "source": "OS.java:1580"
        },
        {
          "method": "org.eclipse.swt.widgets.Combo.callWindowProc",
          "source": "Combo.java:276"
        },
        {
          "method": "org.eclipse.swt.widgets.Control.windowProc",
          "source": "Control.java:3123"
        },
        {
          "method": "org.eclipse.swt.widgets.Combo.windowProc",
          "source": "Combo.java:1755"
        },
        {
          "method": "org.eclipse.swt.widgets.Display.windowProc",
          "source": "Display.java:3706"
        },
        {
          "method": "org.eclipse.swt.internal.win32.OS.CallWindowProcW",
          "source": "Native Method"
        },
        {
          "method": "org.eclipse.swt.internal.win32.OS.CallWindowProc",
          "source": "OS.java:1580"
        },
        {
          "method": "org.eclipse.swt.widgets.Combo.callWindowProc",
          "source": "Combo.java:280"
        },
        {
          "method": "org.eclipse.swt.widgets.Combo.windowProc",
          "source": "Combo.java:1726"
        },
        {
          "method": "org.eclipse.swt.widgets.Display.windowProc",
          "source": "Display.java:3706"
        },
        {
          "method": "org.eclipse.swt.internal.win32.OS.DispatchMessageW",
          "source": "Native Method"
        },
        {
          "method": "org.eclipse.swt.internal.win32.OS.DispatchMessage",
          "source": "OS.java:1656"
        },
        {
          "method": "org.eclipse.swt.widgets.Display.readAndDispatch",
          "source": "Display.java:2711"
        },
        {
          "method": "org.eclipse.jface.window.Window.runEventLoop",
          "source": "Window.java:809"
        },
        {
          "method": "org.eclipse.jface.window.Window.open",
          "source": "Window.java:787"
        },
        {
          "method": "org.eclipse.ui.actions.NewProjectAction.run",
          "source": "NewProjectAction.java:114 "
        },
        {
          "method": "org.eclipse.jface.action.Action.runWithEvent",
          "source": "Action.java:996"
        },
        {
          "method": "org.eclipse.jface.action.ActionContributionItem.handleWidgetSelection",
          "source": "ActionContributionItem.java:538"
        },
        {
          "method": "org.eclipse.jface.action.ActionContributionItem.access$2",
          "source": "ActionContri butionItem.java:488"
        },
        {
          "method": "org.eclipse.jface.action.ActionContributionItem$5.handleEvent",
          "source": "ActionC ontributionItem.java:400"
        },
        {
          "method": "org.eclipse.swt.widgets.EventTable.sendEvent",
          "source": "EventTable.java:66"
        },
        {
          "method": "org.eclipse.swt.widgets.Widget.sendEvent",
          "source": "Widget.java:843"
        },
        {
          "method": "org.eclipse.swt.widgets.Display.runDeferredEvents",
          "source": "Display.java:3080"
        },
        {
          "method": "org.eclipse.swt.widgets.Display.readAndDispatch",
          "source": "Display.java:2713"
        },
        {
          "method": "org.eclipse.ui.internal.Workbench.runEventLoop",
          "source": "Workbench.java:1699"
        },
        {
          "method": "org.eclipse.ui.internal.Workbench.runUI",
          "source": "Workbench.java:1663"
        },
        {
          "method": "org.eclipse.ui.internal.Workbench.createAndRunWorkbench",
          "source": "Workbench.jav a:367"
        },
        {
          "method": "org.eclipse.ui.PlatformUI.createAndRunWorkbench",
          "source": "PlatformUI.java:143"
        },
        {
          "method": "org.eclipse.ui.internal.ide.IDEApplication.run",
          "source": "IDEApplication.java:10 3"
        },
        {
          "method": "org.eclipse.core.internal.runtime.PlatformActivator$1.run",
          "source": "PlatformAct ivator.java:226"
        },
        {
          "method": "org.eclipse.core.runtime.adaptor.EclipseStarter.run",
          "source": "EclipseStarter.ja va:376"
        },
        {
          "method": "org.eclipse.core.runtime.adaptor.EclipseStarter.run",
          "source": "EclipseStarter.ja va:163"
        },
        {
          "method": "sun.reflect.NativeMethodAccessorImpl.invoke0",
          "source": "Native Method"
        },
        {
          "method": "sun.reflect.NativeMethodAccessorImpl.invoke",
          "source": "NativeMethodAccessorImpl. java:85"
        },
        {
          "method": "sun.reflect.NativeMethodAccessorImpl.invoke",
          "source": "NativeMethodAccessorImpl. java:58"
        },
        {
          "method": "sun.reflect.DelegatingMethodAccessorImpl.invoke",
          "source": "DelegatingMethodAcces sorImpl.java:60"
        },
        {
          "method": "java.lang.reflect.Method.invoke",
          "source": "Method.java:391"
        },
        {
          "method": "org.eclipse.core.launcher.Main.invokeFramework",
          "source": "Main.java:334"
        },
        {
          "method": "org.eclipse.core.launcher.Main.basicRun",
          "source": "Main.java:278"
        },
        {
          "method": "org.eclipse.core.launcher.Main.run",
          "source": "Main.java:973"
        },
        {
          "method": "org.eclipse.core.launcher.Main.main",
          "source": "Main.java:948"
        }
      ],
      "number": 0,
      "commentIndex": 0,
      "bugId": "120105",
      "date": "2005-12-09T15:09:06+01:00",
      "product": "Web Tools",
      "component": "jst.j2ee",
      "severity": "major"
    }
  ],
  "groupId": "120105",
  "bugId": "120105",
  "date": "2005-12-09T15:09:06+01:00",
  "product": "Web Tools",
  "component": "jst.j2ee",
  "severity": "major"
}