{
  "comments": [
    "Create a dynamic web project.  Click run on server.  Select an IBM WebSphere 6.0 manual creation, and hit finish from first page of the wizard.  An error dialog pops up, now when you hit finish or cancel, you always get this class cast so there is no way to kill the wizard from taking over your workbench unless you shutdown and restart.\n\n!ENTRY org.eclipse.ui 4 0 2005-12-13 16:52:16.09\n!MESSAGE org/eclipse/wst/server/core/internal/Server incompatible with org/eclipse/wst/server/core/IServerWorkingCopy\n!STACK 0\njava.lang.ClassCastException: org/eclipse/wst/server/core/internal/Server incompatible with org/eclipse/wst/server/core/IServerWorkingCopy\n\tat org.eclipse.wst.server.ui.internal.wizard.fragment.NewServerWizardFragment.createChildFragments(NewServerWizardFragment.java:103)\n\tat org.eclipse.wst.server.ui.internal.wizard.fragment.NewServerWizardFragment.getChildFragments(NewServerWizardFragment.java:86)\n\tat org.eclipse.wst.server.ui.internal.wizard.TaskWizard.addSubWizardFragments(TaskWizard.java:310)\n\tat org.eclipse.wst.server.ui.internal.wizard.TaskWizard.addSubWizardFragments(TaskWizard.java:314)\n\tat org.eclipse.wst.server.ui.internal.wizard.TaskWizard.getAllWizardFragments(TaskWizard.java:298)\n\tat org.eclipse.wst.server.ui.internal.wizard.TaskWizard.performFinish(TaskWizard.java:165)\n\tat org.eclipse.jface.wizard.WizardDialog.finishPressed(WizardDialog.java:676)\n\tat org.eclipse.wst.server.ui.internal.wizard.ClosableWizardDialog.finishPressed(ClosableWizardDialog.java:33)\n\tat org.eclipse.jface.wizard.WizardDialog.buttonPressed(WizardDialog.java:349)\n\tat org.eclipse.jface.dialogs.Dialog$2.widgetSelected(Dialog.java:556)\n\tat org.eclipse.swt.widgets.TypedListener.handleEvent(TypedListener.java:90)\n\tat org.eclipse.swt.widgets.EventTable.sendEvent(EventTable.java:66)\n\tat org.eclipse.swt.widgets.Widget.sendEvent(Widget.java:843)\n\tat org.eclipse.swt.widgets.Display.runDeferredEvents(Display.java:3080)\n\tat org.eclipse.swt.widgets.Display.readAndDispatch(Display.java:2713)\n\tat org.eclipse.jface.window.Window.runEventLoop(Window.java:809)\n\tat org.eclipse.jface.window.Window.open(Window.java:787)\n\tat org.eclipse.wst.server.ui.internal.actions.RunOnServerActionDelegate.getServer(RunOnServerActionDelegate.java:110)\n\tat org.eclipse.wst.server.ui.internal.actions.RunOnServerActionDelegate.run(RunOnServerActionDelegate.java:210)\n\tat org.eclipse.wst.server.ui.internal.actions.RunOnServerActionDelegate.run(RunOnServerActionDelegate.java:386)\n\tat org.eclipse.wst.server.ui.internal.ServerLaunchShortcut.launch(ServerLaunchShortcut.java:42)\n\tat org.eclipse.debug.internal.ui.launchConfigurations.LaunchShortcutExtension.launch(LaunchShortcutExtension.java:372)\n\tat org.eclipse.debug.internal.ui.actions.LaunchShortcutAction.run(LaunchShortcutAction.java:62)\n\tat org.eclipse.jface.action.Action.runWithEvent(Action.java:996)\n\tat org.eclipse.jface.action.ActionContributionItem.handleWidgetSelection(ActionContributionItem.java:538)\n\tat org.eclipse.jface.action.ActionContributionItem.access$2(ActionContributionItem.java:488)\n\tat org.eclipse.jface.action.ActionContributionItem$5.handleEvent(ActionContributionItem.java:400)\n\tat org.eclipse.swt.widgets.EventTable.sendEvent(EventTable.java:66)\n\tat org.eclipse.swt.widgets.Widget.sendEvent(Widget.java:843)\n\tat org.eclipse.swt.widgets.Display.runDeferredEvents(Display.java:3080)\n\tat org.eclipse.swt.widgets.Display.readAndDispatch(Display.java:2713)\n\tat org.eclipse.ui.internal.Workbench.runEventLoop(Workbench.java:1699)\n\tat org.eclipse.ui.internal.Workbench.runUI(Workbench.java:1663)\n\tat org.eclipse.ui.internal.Workbench.createAndRunWorkbench(Workbench.java:367)\n\tat org.eclipse.ui.PlatformUI.createAndRunWorkbench(PlatformUI.java:143)\n\tat org.eclipse.ui.internal.ide.IDEApplication.run(IDEApplication.java:103)\n\tat org.eclipse.core.internal.runtime.PlatformActivator$1.run(PlatformActivator.java:226)\n\tat org.eclipse.core.runtime.adaptor.EclipseStarter.run(EclipseStarter.java:376)\n\tat org.eclipse.core.runtime.adaptor.EclipseStarter.run(EclipseStarter.java:163)\n\tat sun.reflect.NativeMethodAccessorImpl.invoke0(Native Method)\n\tat sun.reflect.NativeMethodAccessorImpl.invoke(NativeMethodAccessorImpl.java:85)\n\tat sun.reflect.NativeMethodAccessorImpl.invoke(NativeMethodAccessorImpl.java:58)\n\tat sun.reflect.DelegatingMethodAccessorImpl.invoke(DelegatingMethodAccessorImpl.java:60)\n\tat java.lang.reflect.Method.invoke(Method.java:391)\n\tat org.eclipse.core.launcher.Main.invokeFramework(Main.java:334)\n\tat org.eclipse.core.launcher.Main.basicRun(Main.java:278)\n\tat org.eclipse.core.launcher.Main.run(Main.java:973)\n\tat org.eclipse.core.launcher.Main.main(Main.java:948)",
    "Fix checked into HEAD, will be released once 1.0.1 builds start.",
    "Released for next 1.0.1 build.",
    "I still problems here.  If I try and hit finish from the first page like in the original defect for IBM server, I get a null pointer dialogue.  I close that and now every button, next, finish cancel gives this error and I have to close the workbench because the wizard won\u0027t go away.\n\n!ENTRY org.eclipse.ui 4 0 2006-01-25 11:09:00.00\n!MESSAGE org.eclipse.wst.server.core.internal.Server\n!STACK 0\njava.lang.ClassCastException: org.eclipse.wst.server.core.internal.Server\n        at org.eclipse.wst.server.ui.internal.wizard.fragment.ModifyModulesWizar\ndFragment.updateModules(ModifyModulesWizardFragment.java:72)\n        at org.eclipse.wst.server.ui.internal.wizard.fragment.ModifyModulesWizar\ndFragment.getChildFragments(ModifyModulesWizardFragment.java:62)\n        at org.eclipse.wst.server.ui.internal.wizard.TaskWizard.addSubWizardFrag\nments(TaskWizard.java:310)\n        at org.eclipse.wst.server.ui.internal.wizard.TaskWizard.addSubWizardFrag\nments(TaskWizard.java:314)\n        at org.eclipse.wst.server.ui.internal.wizard.TaskWizard.getAllWizardFrag\nments(TaskWizard.java:298)\n        at org.eclipse.wst.server.ui.internal.wizard.TaskWizard.switchWizardFrag\nment(TaskWizard.java:263)\n        at org.eclipse.wst.server.ui.internal.wizard.TaskWizardPage.setVisible(T\naskWizardPage.java:92)\n        at org.eclipse.jface.wizard.WizardDialog.updateForPage(WizardDialog.java\n:1030)\n        at org.eclipse.jface.wizard.WizardDialog.access$2(WizardDialog.java:1013\n)\n        at org.eclipse.jface.wizard.WizardDialog$4.run(WizardDialog.java:1003)\n        at org.eclipse.swt.custom.BusyIndicator.showWhile(BusyIndicator.java:69)\n\n        at org.eclipse.jface.wizard.WizardDialog.showPage(WizardDialog.java:1001\n)\n        at org.eclipse.jface.wizard.WizardDialog.nextPressed(WizardDialog.java:7\n53)\n        at org.eclipse.jface.wizard.WizardDialog.buttonPressed(WizardDialog.java\n:345)\n        at org.eclipse.jface.dialogs.Dialog$2.widgetSelected(Dialog.java:556)\n        at org.eclipse.swt.widgets.TypedListener.handleEvent(TypedListener.java:\n90)\n        at org.eclipse.swt.widgets.EventTable.sendEvent(EventTable.java:66)\n        at org.eclipse.swt.widgets.Widget.sendEvent(Widget.java:843)\n        at org.eclipse.swt.widgets.Display.runDeferredEvents(Display.java:3080)\n        at org.eclipse.swt.widgets.Display.readAndDispatch(Display.java:2713)\n        at org.eclipse.jface.window.Window.runEventLoop(Window.java:809)\n        at org.eclipse.jface.window.Window.open(Window.java:787)\n        at org.eclipse.wst.server.ui.internal.actions.RunOnServerActionDelegate.\ngetServer(RunOnServerActionDelegate.java:110)\n        at org.eclipse.wst.server.ui.internal.actions.RunOnServerActionDelegate.\nrun(RunOnServerActionDelegate.java:210)\n        at org.eclipse.wst.server.ui.internal.actions.RunOnServerActionDelegate.\nrun(RunOnServerActionDelegate.java:386)\n        at org.eclipse.wst.server.ui.internal.ServerLaunchShortcut.launch(Server\nLaunchShortcut.java:42)\n        at org.eclipse.debug.internal.ui.launchConfigurations.LaunchShortcutExte\nnsion.launch(LaunchShortcutExtension.java:372)\n        at org.eclipse.debug.internal.ui.actions.LaunchShortcutAction.run(Launch\nShortcutAction.java:62)\n        at org.eclipse.jface.action.Action.runWithEvent(Action.java:996)\n        at org.eclipse.jface.action.ActionContributionItem.handleWidgetSelection\n(ActionContributionItem.java:538)\n        at org.eclipse.jface.action.ActionContributionItem.access$2(ActionContri\nbutionItem.java:488)\n        at org.eclipse.jface.action.ActionContributionItem$5.handleEvent(ActionC\nontributionItem.java:400)\n        at org.eclipse.swt.widgets.EventTable.sendEvent(EventTable.java:66)\n        at org.eclipse.swt.widgets.Widget.sendEvent(Widget.java:843)\n        at org.eclipse.swt.widgets.Display.runDeferredEvents(Display.java:3080)\n        at org.eclipse.swt.widgets.Display.readAndDispatch(Display.java:2713)\n        at org.eclipse.ui.internal.Workbench.runEventLoop(Workbench.java:1699)\n        at org.eclipse.ui.internal.Workbench.runUI(Workbench.java:1663)\n        at org.eclipse.ui.internal.Workbench.createAndRunWorkbench(Workbench.jav\na:367)\n        at org.eclipse.ui.PlatformUI.createAndRunWorkbench(PlatformUI.java:143)\n        at org.eclipse.ui.internal.ide.IDEApplication.run(IDEApplication.java:10\n3)\n        at org.eclipse.core.internal.runtime.PlatformActivator$1.run(PlatformAct\nivator.java:226)\n        at org.eclipse.core.runtime.adaptor.EclipseStarter.run(EclipseStarter.ja\nva:376)\n        at org.eclipse.core.runtime.adaptor.EclipseStarter.run(EclipseStarter.ja\nva:163)\n        at sun.reflect.NativeMethodAccessorImpl.invoke0(Native Method)\n        at sun.reflect.NativeMethodAccessorImpl.invoke(Unknown Source)\n        at sun.reflect.DelegatingMethodAccessorImpl.invoke(Unknown Source)\n        at java.lang.reflect.Method.invoke(Unknown Source)\n        at org.eclipse.core.launcher.Main.invokeFramework(Main.java:334)\n        at org.eclipse.core.launcher.Main.basicRun(Main.java:278)\n        at org.eclipse.core.launcher.Main.run(Main.java:973)\n        at org.eclipse.core.launcher.Main.main(Main.java:948)\norg.eclipse.wst.server.core.internal.Server\n",
    "Same bug; different place. I\u0027ve gone through all of the wizards to make sure this bad cast isn\u0027t being made in other places as well.",
    "Fix released for next M-build.",
    "Verified on 061606"
  ],
  "commentCreationDates": [
    "2005-12-13T22:00:11+01:00",
    "2005-12-29T03:13:23+01:00",
    "2006-01-04T23:09:13+01:00",
    "2006-01-25T16:08:47+01:00",
    "2006-01-25T18:56:36+01:00",
    "2006-01-28T18:02:57+01:00",
    "2006-06-16T19:58:40+02:00"
  ],
  "traces": [
    {
      "exceptionType": "java.lang.ClassCastException",
      "message": "org/eclipse/wst/server/core/internal/Server incompatible with org/eclipse/wst/server/core/IServerWorkingCopy",
      "elements": [
        {
          "method": "org.eclipse.wst.server.ui.internal.wizard.fragment.NewServerWizardFragment.createChildFragments",
          "source": "NewServerWizardFragment.java:103"
        },
        {
          "method": "org.eclipse.wst.server.ui.internal.wizard.fragment.NewServerWizardFragment.getChildFragments",
          "source": "NewServerWizardFragment.java:86"
        },
        {
          "method": "org.eclipse.wst.server.ui.internal.wizard.TaskWizard.addSubWizardFragments",
          "source": "TaskWizard.java:310"
        },
        {
          "method": "org.eclipse.wst.server.ui.internal.wizard.TaskWizard.addSubWizardFragments",
          "source": "TaskWizard.java:314"
        },
        {
          "method": "org.eclipse.wst.server.ui.internal.wizard.TaskWizard.getAllWizardFragments",
          "source": "TaskWizard.java:298"
        },
        {
          "method": "org.eclipse.wst.server.ui.internal.wizard.TaskWizard.performFinish",
          "source": "TaskWizard.java:165"
        },
        {
          "method": "org.eclipse.jface.wizard.WizardDialog.finishPressed",
          "source": "WizardDialog.java:676"
        },
        {
          "method": "org.eclipse.wst.server.ui.internal.wizard.ClosableWizardDialog.finishPressed",
          "source": "ClosableWizardDialog.java:33"
        },
        {
          "method": "org.eclipse.jface.wizard.WizardDialog.buttonPressed",
          "source": "WizardDialog.java:349"
        },
        {
          "method": "org.eclipse.jface.dialogs.Dialog$2.widgetSelected",
          "source": "Dialog.java:556"
        },
        {
          "method": "org.eclipse.swt.widgets.TypedListener.handleEvent",
          "source": "TypedListener.java:90"
        },
        {
          "method": "org.eclipse.swt.widgets.EventTable.sendEvent",
          "source": "EventTable.java:66"
        },
        {
          "method": "org.eclipse.swt.widgets.Widget.sendEvent",
          "source": "Widget.java:843"
        },
        {
          "method": "org.eclipse.swt.widgets.Display.runDeferredEvents",
          "source": "Display.java:3080"
        },
        {
          "method": "org.eclipse.swt.widgets.Display.readAndDispatch",
          "source": "Display.java:2713"
        },
        {
          "method": "org.eclipse.jface.window.Window.runEventLoop",
          "source": "Window.java:809"
        },
        {
          "method": "org.eclipse.jface.window.Window.open",
          "source": "Window.java:787"
        },
        {
          "method": "org.eclipse.wst.server.ui.internal.actions.RunOnServerActionDelegate.getServer",
          "source": "RunOnServerActionDelegate.java:110"
        },
        {
          "method": "org.eclipse.wst.server.ui.internal.actions.RunOnServerActionDelegate.run",
          "source": "RunOnServerActionDelegate.java:210"
        },
        {
          "method": "org.eclipse.wst.server.ui.internal.actions.RunOnServerActionDelegate.run",
          "source": "RunOnServerActionDelegate.java:386"
        },
        {
          "method": "org.eclipse.wst.server.ui.internal.ServerLaunchShortcut.launch",
          "source": "ServerLaunchShortcut.java:42"
        },
        {
          "method": "org.eclipse.debug.internal.ui.launchConfigurations.LaunchShortcutExtension.launch",
          "source": "LaunchShortcutExtension.java:372"
        },
        {
          "method": "org.eclipse.debug.internal.ui.actions.LaunchShortcutAction.run",
          "source": "LaunchShortcutAction.java:62"
        },
        {
          "method": "org.eclipse.jface.action.Action.runWithEvent",
          "source": "Action.java:996"
        },
        {
          "method": "org.eclipse.jface.action.ActionContributionItem.handleWidgetSelection",
          "source": "ActionContributionItem.java:538"
        },
        {
          "method": "org.eclipse.jface.action.ActionContributionItem.access$2",
          "source": "ActionContributionItem.java:488"
        },
        {
          "method": "org.eclipse.jface.action.ActionContributionItem$5.handleEvent",
          "source": "ActionContributionItem.java:400"
        },
        {
          "method": "org.eclipse.swt.widgets.EventTable.sendEvent",
          "source": "EventTable.java:66"
        },
        {
          "method": "org.eclipse.swt.widgets.Widget.sendEvent",
          "source": "Widget.java:843"
        },
        {
          "method": "org.eclipse.swt.widgets.Display.runDeferredEvents",
          "source": "Display.java:3080"
        },
        {
          "method": "org.eclipse.swt.widgets.Display.readAndDispatch",
          "source": "Display.java:2713"
        },
        {
          "method": "org.eclipse.ui.internal.Workbench.runEventLoop",
          "source": "Workbench.java:1699"
        },
        {
          "method": "org.eclipse.ui.internal.Workbench.runUI",
          "source": "Workbench.java:1663"
        },
        {
          "method": "org.eclipse.ui.internal.Workbench.createAndRunWorkbench",
          "source": "Workbench.java:367"
        },
        {
          "method": "org.eclipse.ui.PlatformUI.createAndRunWorkbench",
          "source": "PlatformUI.java:143"
        },
        {
          "method": "org.eclipse.ui.internal.ide.IDEApplication.run",
          "source": "IDEApplication.java:103"
        },
        {
          "method": "org.eclipse.core.internal.runtime.PlatformActivator$1.run",
          "source": "PlatformActivator.java:226"
        },
        {
          "method": "org.eclipse.core.runtime.adaptor.EclipseStarter.run",
          "source": "EclipseStarter.java:376"
        },
        {
          "method": "org.eclipse.core.runtime.adaptor.EclipseStarter.run",
          "source": "EclipseStarter.java:163"
        },
        {
          "method": "sun.reflect.NativeMethodAccessorImpl.invoke0",
          "source": "Native Method"
        },
        {
          "method": "sun.reflect.NativeMethodAccessorImpl.invoke",
          "source": "NativeMethodAccessorImpl.java:85"
        },
        {
          "method": "sun.reflect.NativeMethodAccessorImpl.invoke",
          "source": "NativeMethodAccessorImpl.java:58"
        },
        {
          "method": "sun.reflect.DelegatingMethodAccessorImpl.invoke",
          "source": "DelegatingMethodAccessorImpl.java:60"
        },
        {
          "method": "java.lang.reflect.Method.invoke",
          "source": "Method.java:391"
        },
        {
          "method": "org.eclipse.core.launcher.Main.invokeFramework",
          "source": "Main.java:334"
        },
        {
          "method": "org.eclipse.core.launcher.Main.basicRun",
          "source": "Main.java:278"
        },
        {
          "method": "org.eclipse.core.launcher.Main.run",
          "source": "Main.java:973"
        },
        {
          "method": "org.eclipse.core.launcher.Main.main",
          "source": "Main.java:948"
        }
      ],
      "number": 0,
      "commentIndex": 0,
      "bugId": "120753",
      "date": "2005-12-13T22:00:11+01:00",
      "product": "Web Tools",
      "component": "wst.server",
      "severity": "major"
    },
    {
      "exceptionType": "java.lang.ClassCastException",
      "message": "org.eclipse.wst.server.core.internal.Server",
      "elements": [
        {
          "method": "org.eclipse.wst.server.ui.internal.wizard.fragment.ModifyModulesWizardFragment.updateModules",
          "source": "ModifyModulesWizardFragment.java:72"
        },
        {
          "method": "org.eclipse.wst.server.ui.internal.wizard.fragment.ModifyModulesWizardFragment.getChildFragments",
          "source": "ModifyModulesWizardFragment.java:62"
        },
        {
          "method": "org.eclipse.wst.server.ui.internal.wizard.TaskWizard.addSubWizardFragments",
          "source": "TaskWizard.java:310"
        },
        {
          "method": "org.eclipse.wst.server.ui.internal.wizard.TaskWizard.addSubWizardFragments",
          "source": "TaskWizard.java:314"
        },
        {
          "method": "org.eclipse.wst.server.ui.internal.wizard.TaskWizard.getAllWizardFragments",
          "source": "TaskWizard.java:298"
        },
        {
          "method": "org.eclipse.wst.server.ui.internal.wizard.TaskWizard.switchWizardFragment",
          "source": "TaskWizard.java:263"
        },
        {
          "method": "org.eclipse.wst.server.ui.internal.wizard.TaskWizardPage.setVisible",
          "source": "T askWizardPage.java:92"
        },
        {
          "method": "org.eclipse.jface.wizard.WizardDialog.updateForPage",
          "source": "WizardDialog.java :1030"
        },
        {
          "method": "org.eclipse.jface.wizard.WizardDialog.access$2",
          "source": "WizardDialog.java:1013 "
        },
        {
          "method": "org.eclipse.jface.wizard.WizardDialog$4.run",
          "source": "WizardDialog.java:1003"
        },
        {
          "method": "org.eclipse.swt.custom.BusyIndicator.showWhile",
          "source": "BusyIndicator.java:69"
        },
        {
          "method": "org.eclipse.jface.wizard.WizardDialog.showPage",
          "source": "WizardDialog.java:1001 "
        },
        {
          "method": "org.eclipse.jface.wizard.WizardDialog.nextPressed",
          "source": "WizardDialog.java:7 53"
        },
        {
          "method": "org.eclipse.jface.wizard.WizardDialog.buttonPressed",
          "source": "WizardDialog.java :345"
        },
        {
          "method": "org.eclipse.jface.dialogs.Dialog$2.widgetSelected",
          "source": "Dialog.java:556"
        },
        {
          "method": "org.eclipse.swt.widgets.TypedListener.handleEvent",
          "source": "TypedListener.java: 90"
        },
        {
          "method": "org.eclipse.swt.widgets.EventTable.sendEvent",
          "source": "EventTable.java:66"
        },
        {
          "method": "org.eclipse.swt.widgets.Widget.sendEvent",
          "source": "Widget.java:843"
        },
        {
          "method": "org.eclipse.swt.widgets.Display.runDeferredEvents",
          "source": "Display.java:3080"
        },
        {
          "method": "org.eclipse.swt.widgets.Display.readAndDispatch",
          "source": "Display.java:2713"
        },
        {
          "method": "org.eclipse.jface.window.Window.runEventLoop",
          "source": "Window.java:809"
        },
        {
          "method": "org.eclipse.jface.window.Window.open",
          "source": "Window.java:787"
        },
        {
          "method": "org.eclipse.wst.server.ui.internal.actions.RunOnServerActionDelegate.getServer",
          "source": "RunOnServerActionDelegate.java:110"
        },
        {
          "method": "org.eclipse.wst.server.ui.internal.actions.RunOnServerActionDelegate.run",
          "source": "RunOnServerActionDelegate.java:210"
        },
        {
          "method": "org.eclipse.wst.server.ui.internal.actions.RunOnServerActionDelegate.run",
          "source": "RunOnServerActionDelegate.java:386"
        },
        {
          "method": "org.eclipse.wst.server.ui.internal.ServerLaunchShortcut.launch",
          "source": "Server LaunchShortcut.java:42"
        },
        {
          "method": "org.eclipse.debug.internal.ui.launchConfigurations.LaunchShortcutExtension.launch",
          "source": "LaunchShortcutExtension.java:372"
        },
        {
          "method": "org.eclipse.debug.internal.ui.actions.LaunchShortcutAction.run",
          "source": "Launch ShortcutAction.java:62"
        },
        {
          "method": "org.eclipse.jface.action.Action.runWithEvent",
          "source": "Action.java:996"
        },
        {
          "method": "org.eclipse.jface.action.ActionContributionItem.handleWidgetSelection",
          "source": "ActionContributionItem.java:538"
        },
        {
          "method": "org.eclipse.jface.action.ActionContributionItem.access$2",
          "source": "ActionContri butionItem.java:488"
        },
        {
          "method": "org.eclipse.jface.action.ActionContributionItem$5.handleEvent",
          "source": "ActionC ontributionItem.java:400"
        },
        {
          "method": "org.eclipse.swt.widgets.EventTable.sendEvent",
          "source": "EventTable.java:66"
        },
        {
          "method": "org.eclipse.swt.widgets.Widget.sendEvent",
          "source": "Widget.java:843"
        },
        {
          "method": "org.eclipse.swt.widgets.Display.runDeferredEvents",
          "source": "Display.java:3080"
        },
        {
          "method": "org.eclipse.swt.widgets.Display.readAndDispatch",
          "source": "Display.java:2713"
        },
        {
          "method": "org.eclipse.ui.internal.Workbench.runEventLoop",
          "source": "Workbench.java:1699"
        },
        {
          "method": "org.eclipse.ui.internal.Workbench.runUI",
          "source": "Workbench.java:1663"
        },
        {
          "method": "org.eclipse.ui.internal.Workbench.createAndRunWorkbench",
          "source": "Workbench.jav a:367"
        },
        {
          "method": "org.eclipse.ui.PlatformUI.createAndRunWorkbench",
          "source": "PlatformUI.java:143"
        },
        {
          "method": "org.eclipse.ui.internal.ide.IDEApplication.run",
          "source": "IDEApplication.java:10 3"
        },
        {
          "method": "org.eclipse.core.internal.runtime.PlatformActivator$1.run",
          "source": "PlatformAct ivator.java:226"
        },
        {
          "method": "org.eclipse.core.runtime.adaptor.EclipseStarter.run",
          "source": "EclipseStarter.ja va:376"
        },
        {
          "method": "org.eclipse.core.runtime.adaptor.EclipseStarter.run",
          "source": "EclipseStarter.ja va:163"
        },
        {
          "method": "sun.reflect.NativeMethodAccessorImpl.invoke0",
          "source": "Native Method"
        },
        {
          "method": "sun.reflect.NativeMethodAccessorImpl.invoke",
          "source": "Unknown Source"
        },
        {
          "method": "sun.reflect.DelegatingMethodAccessorImpl.invoke",
          "source": "Unknown Source"
        },
        {
          "method": "java.lang.reflect.Method.invoke",
          "source": "Unknown Source"
        },
        {
          "method": "org.eclipse.core.launcher.Main.invokeFramework",
          "source": "Main.java:334"
        },
        {
          "method": "org.eclipse.core.launcher.Main.basicRun",
          "source": "Main.java:278"
        },
        {
          "method": "org.eclipse.core.launcher.Main.run",
          "source": "Main.java:973"
        },
        {
          "method": "org.eclipse.core.launcher.Main.main",
          "source": "Main.java:948"
        }
      ],
      "number": 1,
      "commentIndex": 3,
      "bugId": "120753",
      "date": "2006-01-25T16:08:47+01:00",
      "product": "Web Tools",
      "component": "wst.server",
      "severity": "major"
    }
  ],
  "groupId": "120753",
  "bugId": "120753",
  "date": "2005-12-13T22:00:11+01:00",
  "product": "Web Tools",
  "component": "wst.server",
  "severity": "major"
}