{
  "comments": [
    "I did a fresh install and installed wtp and p4wsad on in a separate plugin folder.\n\nMost of the time I get this error:\n\nmmoeller@mmoeller:~/eclipse-311\u003e ./eclipse -vmargs -Xmx782m\nThe application \u0027Eclipse\u0027 lost its connection to the display :0.0;\nmost likely the X server was shut down or you killed/destroyed\nthe application.\n\n\nBut once I got this:\n\nThe program \u0027Eclipse\u0027 received an X Window System error.\nThis probably reflects a bug in the program.\nThe error was \u0027BadLength (poly request too large or internal Xlib length erro\u0027.\n  (Details: serial 360323 error_code 16 request_code 1 minor_code 0)\n  (Note to programmers: normally, X errors are reported asynchronously;\n   that is, you will receive the error a while after causing it.\n   To debug your program, run it with the --sync command line\n   option to change this behavior. You can then get a meaningful\n   backtrace from your debugger if you break on the gdk_x_error() function.)\n\nAt this point the process froze bad enough to only die after a SIGKILL.\n\nOnly thing that seems logged is in my .xsession-errors which constantly says:\n\nX Error: BadWindow (invalid Window parameter) 3\n  Major opcode:  20\n  Minor opcode:  0\n  Resource id:  0x5e00030\nX Error: BadWindow (invalid Window parameter) 3\n  Major opcode:  20\n  Minor opcode:  0\n  Resource id:  0x5e00030\nX Error: BadWindow (invalid Window parameter) 3\n  Major opcode:  20\n  Minor opcode:  0\n  Resource id:  0x5e00030\n\nwhile running eclipse, especially on startup...",
    "Are you displaying remotely somewhere, or is this local to the machine?\n\nAlso, what version of X?",
    "This consistently seems to happen when I checkout projects using P4WSAD (perforce team plugin). It does use external programs to do its actions it seems like (a \"p4\" binary), but I dont understand why this should cause X related issues (besides the system being busy for a while).\n\nSuSe 10.0/KDE/Eclipse 3.1.1\n\nmmoeller@mmoeller:~\u003e echo $DISPLAY\n:0.0\nmmoeller@mmoeller:~\u003e X -version\n\nX Window System Version 6.8.2\nRelease Date: 9 February 2005\nX Protocol Version 11, Revision 0, Release 6.8.2\nBuild Operating System: SuSE Linux [ELF] SuSE\nCurrent Operating System: Linux mmoeller 2.6.13-15-smp #1 SMP Tue Sep 13 14:56:15 UTC 2005 x86_64\nBuild Date: 07 October 2005\n        Before reporting problems, check http://wiki.X.Org\n        to make sure that you have the latest version.\nModule Loader present\n",
    "I have the same problem with Eclipse-Linux-GTK 3.1.1 or 3.2M4.\nThe exception appears when i try to compare a file with Revision or Local History. Due to no java trace in console i think the exception come from GTK+ or GDK lib.\nA workaround is to use the Motif version.",
    "With this cmd : eclipse -ws gtk -debug, i obtained the following trace on action Compare to Revision :\n\norg.eclipse.swt.SWTError: Unspecified error\n        at org.eclipse.swt.graphics.Device.XIOErrorProc(Device.java:819)\n        at org.eclipse.swt.internal.gtk.OS._gtk_main_do_event(Native Method)\n        at org.eclipse.swt.internal.gtk.OS.gtk_main_do_event(OS.java:5018)\n        at org.eclipse.swt.widgets.Display.eventProc(Display.java:1062)\n        at org.eclipse.swt.internal.gtk.OS._g_main_context_iteration(Native  Method)\n        at  org.eclipse.swt.internal.gtk.OS.g_main_context_iteration(OS.java:1344)\n        at org.eclipse.swt.widgets.Display.readAndDispatch(Display.java:2741)\n        at org.eclipse.ui.internal.Workbench.runEventLoop(Workbench.java:1762)\n        at org.eclipse.ui.internal.Workbench.runUI(Workbench.java:1726)\n        at \norg.eclipse.ui.internal.Workbench.createAndRunWorkbench(Workbench.java:397)\n        at \norg.eclipse.ui.PlatformUI.createAndRunWorkbench(PlatformUI.java:143)\n        at \norg.eclipse.ui.internal.ide.IDEApplication.run(IDEApplication.java:106)\n        at \norg.eclipse.core.internal.runtime.PlatformActivator$1.run(PlatformActivator.java:109)\n        at \norg.eclipse.core.runtime.internal.adaptor.EclipseAppLauncher.runApplication(EclipseAppLauncher.java:92)\n        at \norg.eclipse.core.runtime.internal.adaptor.EclipseAppLauncher.start(EclipseAppLauncher.java:68)\n        at \norg.eclipse.core.runtime.adaptor.EclipseStarter.run(EclipseStarter.java:379)\n        at \norg.eclipse.core.runtime.adaptor.EclipseStarter.run(EclipseStarter.java:177)\n        at sun.reflect.NativeMethodAccessorImpl.invoke0(Native Method)\n        at \nsun.reflect.NativeMethodAccessorImpl.invoke(NativeMethodAccessorImpl.java:39)\n        at \nsun.reflect.DelegatingMethodAccessorImpl.invoke(DelegatingMethodAccessorImpl.java:25)\n        at java.lang.reflect.Method.invoke(Method.java:324)\n        at org.eclipse.core.launcher.Main.invokeFramework(Main.java:338)\n        at org.eclipse.core.launcher.Main.basicRun(Main.java:282)\n        at org.eclipse.core.launcher.Main.run(Main.java:977)\n        at org.eclipse.core.launcher.Main.main(Main.java:952)\nThe application \u0027Eclipse\u0027 lost its connection to the display :0.0;\nmost likely the X server was shut down or you killed/destroyed\nthe application.\n"
  ],
  "commentCreationDates": [
    "2005-12-16T23:38:18+01:00",
    "2005-12-17T00:15:33+01:00",
    "2005-12-18T21:03:57+01:00",
    "2006-01-06T16:20:08+01:00",
    "2006-01-17T20:56:07+01:00"
  ],
  "traces": [
    {
      "exceptionType": "org.eclipse.swt.SWTError",
      "message": "Unspecified error",
      "elements": [
        {
          "method": "org.eclipse.swt.graphics.Device.XIOErrorProc",
          "source": "Device.java:819"
        },
        {
          "method": "org.eclipse.swt.internal.gtk.OS._gtk_main_do_event",
          "source": "Native Method"
        },
        {
          "method": "org.eclipse.swt.internal.gtk.OS.gtk_main_do_event",
          "source": "OS.java:5018"
        },
        {
          "method": "org.eclipse.swt.widgets.Display.eventProc",
          "source": "Display.java:1062"
        },
        {
          "method": "org.eclipse.swt.internal.gtk.OS._g_main_context_iteration",
          "source": "Native  Method"
        },
        {
          "method": "org.eclipse.swt.internal.gtk.OS.g_main_context_iteration",
          "source": "OS.java:1344"
        },
        {
          "method": "org.eclipse.swt.widgets.Display.readAndDispatch",
          "source": "Display.java:2741"
        },
        {
          "method": "org.eclipse.ui.internal.Workbench.runEventLoop",
          "source": "Workbench.java:1762"
        },
        {
          "method": "org.eclipse.ui.internal.Workbench.runUI",
          "source": "Workbench.java:1726"
        },
        {
          "method": "org.eclipse.ui.internal.Workbench.createAndRunWorkbench",
          "source": "Workbench.java:397"
        },
        {
          "method": "org.eclipse.ui.PlatformUI.createAndRunWorkbench",
          "source": "PlatformUI.java:143"
        },
        {
          "method": "org.eclipse.ui.internal.ide.IDEApplication.run",
          "source": "IDEApplication.java:106"
        },
        {
          "method": "org.eclipse.core.internal.runtime.PlatformActivator$1.run",
          "source": "PlatformActivator.java:109"
        },
        {
          "method": "org.eclipse.core.runtime.internal.adaptor.EclipseAppLauncher.runApplication",
          "source": "EclipseAppLauncher.java:92"
        },
        {
          "method": "org.eclipse.core.runtime.internal.adaptor.EclipseAppLauncher.start",
          "source": "EclipseAppLauncher.java:68"
        },
        {
          "method": "org.eclipse.core.runtime.adaptor.EclipseStarter.run",
          "source": "EclipseStarter.java:379"
        },
        {
          "method": "org.eclipse.core.runtime.adaptor.EclipseStarter.run",
          "source": "EclipseStarter.java:177"
        },
        {
          "method": "sun.reflect.NativeMethodAccessorImpl.invoke0",
          "source": "Native Method"
        },
        {
          "method": "sun.reflect.NativeMethodAccessorImpl.invoke",
          "source": "NativeMethodAccessorImpl.java:39"
        },
        {
          "method": "sun.reflect.DelegatingMethodAccessorImpl.invoke",
          "source": "DelegatingMethodAccessorImpl.java:25"
        },
        {
          "method": "java.lang.reflect.Method.invoke",
          "source": "Method.java:324"
        },
        {
          "method": "org.eclipse.core.launcher.Main.invokeFramework",
          "source": "Main.java:338"
        },
        {
          "method": "org.eclipse.core.launcher.Main.basicRun",
          "source": "Main.java:282"
        },
        {
          "method": "org.eclipse.core.launcher.Main.run",
          "source": "Main.java:977"
        },
        {
          "method": "org.eclipse.core.launcher.Main.main",
          "source": "Main.java:952"
        }
      ],
      "number": 0,
      "commentIndex": 4,
      "bugId": "121296",
      "date": "2006-01-17T20:56:07+01:00",
      "product": "Platform",
      "component": "SWT",
      "severity": "normal"
    }
  ],
  "groupId": "121296",
  "bugId": "121296",
  "date": "2005-12-16T23:38:18+01:00",
  "product": "Platform",
  "component": "SWT",
  "severity": "normal"
}