{
  "comments": [
    "I\u0027m getting an \"abort trouble in\" error message when using load-time weaving.  My class is a generic class - the error message says \"Wrong number of type parameters supplied\", so I think it\u0027s something to do with my class being generic.\n\nBTW, this is against the released version of AJ - Version field in bug report form just has M5, RC1, RC2 etc.\n\nI have the following class and interface (pruned down):\n\n--- START com/mycompany/MyClass.java ---\n\npackage com.mycompany;\n\nimport java.io.*;\n\nclass MyClass\u003cT,E\u003e implements MyInterface\u003cT\u003e\n{\n    public static void main(String[] arg)\n    {\n    }\n\n    public T read()\n        throws IOException\n    {\n        return null;\n    }\n\n    public void exceptionDetected(E e)\n    {\n    }\n}\n\ninterface MyInterface\u003cT\u003e\n{\n    public T read()\n        throws IOException;\n}\n\n--- END com/mycompany/MyClass.java ---\n\nHere\u0027s my aop.xml:\n\n--- START META-INF/aop.xml ---\n\n\u003caspectj\u003e\n\n    \u003caspects\u003e\n        \u003caspect name\u003d\"com.mycompany.MyAspect\"/\u003e\n    \u003c/aspects\u003e\n\n    \u003cweaver/\u003e\n\n\u003c/aspectj\u003e\n\n--- END META-INF/aop.xml ---\n\nHere\u0027s my Aspect (using @AJ):\n\n--- START com/mycompany/MyAspect.java ---\n\npackage com.mycompany;\n\nimport org.aspectj.lang.annotation.Aspect;\nimport org.aspectj.lang.annotation.Before;\nimport org.aspectj.lang.annotation.Pointcut;\n\n@Aspect\npublic class MyAspect\n{\n    @Pointcut(\"execution(* com.mycompany.MyOtherClass.read())\")\n    void myPointcut()\n    {\n    }\n\n    @Before(\"myPointcut()\")\n    public void myAdvice()\n    {\n        System.out.println(\"read()\");\n    }\n}\n\n--- END com/mycompany/MyAspect.java ---\n\nAnd here\u0027s another class which is referenced in the aspect:\n\n--- START com/mycompany/MyOtherClass.java ---\n\npackage com.mycompany;\n\nclass MyOtherClass\n{\n    public void read()\n    {\n    }\n}\n\n--- END com/mycompany/MyOtherClass.java ---\n\nWhen I run MyClass (it\u0027s got a main method), I get an error reported as attached below.\n\nWhen I change the aspect to reference MyClass instead of MyOtherClass, no error message is reported.\n\nBTW, I can\u0027t any way to have attachments to a bug report - is what I\u0027ve done the correct way to do it?\n\nThanks,\nCalum\n\n--- START OUTPUT ---\n\nabort trouble in: \n class com.mycompany.MyClass extends java.lang.Object implements com.mycompany.MyInterface:\n  void \u003cinit\u003e():\n                    ALOAD_0     // com.mycompany.MyClass this   (line 5)\n                    INVOKESPECIAL java.lang.Object.\u003cinit\u003e ()V\n    constructor-execution(void com.mycompany.MyClass.\u003cinit\u003e())\n    |               RETURN\n    constructor-execution(void com.mycompany.MyClass.\u003cinit\u003e())\n  end void \u003cinit\u003e()\n\n  public static void main(String[]):\n                    RETURN   (line 9)\n  end public static void main(String[])\n\n  public Object read() throws java.io.IOException:\n                    ACONST_NULL   (line 14)\n                    ARETURN\n  end public Object read() throws java.io.IOException\n\n  public void exceptionDetected(Object):\n                    RETURN   (line 19)\n  end public void exceptionDetected(Object)\n\nend  class com.mycompany.MyClass\n -- (IllegalStateException) Wrong number of type parameters supplied\nWrong number of type parameters supplied\njava.lang.IllegalStateException: Wrong number of type parameters supplied\n\tat org.aspectj.weaver.ResolvedMemberImpl.parameterizedWith(ResolvedMemberImpl.java:609)\n\tat org.aspectj.weaver.ResolvedMemberImpl.parameterizedWith(ResolvedMemberImpl.java:590)\n\tat org.aspectj.weaver.ReferenceType.getDeclaredMethods(ReferenceType.java:421)\n\tat org.aspectj.weaver.ResolvedType.addAndRecurse(ResolvedType.java:262)\n\tat org.aspectj.weaver.ResolvedType.getMethodsWithoutIterator(ResolvedType.java:257)\n\tat org.aspectj.weaver.ResolvedType.lookupResolvedMember(ResolvedType.java:375)\n\tat org.aspectj.weaver.JoinPointSignatureIterator.findSignaturesFromSupertypes(JoinPointSignatureIterator.java:167)\n\tat org.aspectj.weaver.JoinPointSignatureIterator.hasNext(JoinPointSignatureIterator.java:68)\n\tat org.aspectj.weaver.patterns.SignaturePattern.matches(SignaturePattern.java:286)\n\tat org.aspectj.weaver.patterns.KindedPointcut.matchInternal(KindedPointcut.java:106)\n\tat org.aspectj.weaver.patterns.Pointcut.match(Pointcut.java:145)\n\tat org.aspectj.weaver.patterns.AndPointcut.matchInternal(AndPointcut.java:55)\n\tat org.aspectj.weaver.patterns.Pointcut.match(Pointcut.java:145)\n\tat org.aspectj.weaver.ShadowMunger.match(ShadowMunger.java:64)\n\tat org.aspectj.weaver.Advice.match(Advice.java:109)\n\tat org.aspectj.weaver.bcel.BcelAdvice.match(BcelAdvice.java:104)\n\tat org.aspectj.weaver.bcel.BcelClassWeaver.match(BcelClassWeaver.java:2113)\n\tat org.aspectj.weaver.bcel.BcelClassWeaver.match(BcelClassWeaver.java:1713)\n\tat org.aspectj.weaver.bcel.BcelClassWeaver.weave(BcelClassWeaver.java:455)\n\tat org.aspectj.weaver.bcel.BcelClassWeaver.weave(BcelClassWeaver.java:102)\n\tat org.aspectj.weaver.bcel.BcelWeaver.weave(BcelWeaver.java:1543)\n\tat org.aspectj.weaver.bcel.BcelWeaver.weaveWithoutDump(BcelWeaver.java:1494)\n\tat org.aspectj.weaver.bcel.BcelWeaver.weaveAndNotify(BcelWeaver.java:1275)\n\tat org.aspectj.weaver.bcel.BcelWeaver.weave(BcelWeaver.java:1097)\n\tat org.aspectj.weaver.tools.WeavingAdaptor.getWovenBytes(WeavingAdaptor.java:277)\n\tat org.aspectj.weaver.tools.WeavingAdaptor.weaveClass(WeavingAdaptor.java:210)\n\tat org.aspectj.weaver.loadtime.Aj.preProcess(Aj.java:65)\n\tat org.aspectj.weaver.loadtime.ClassPreProcessorAgentAdapter.transform(ClassPreProcessorAgentAdapter.java:52)\n\tat sun.instrument.TransformerManager.transform(TransformerManager.java:122)\n\tat sun.instrument.InstrumentationImpl.transform(InstrumentationImpl.java:155)\n\tat java.lang.ClassLoader.defineClass1(Native Method)\n\tat java.lang.ClassLoader.defineClass(ClassLoader.java:620)\n\tat java.security.SecureClassLoader.defineClass(SecureClassLoader.java:124)\n\tat java.net.URLClassLoader.defineClass(URLClassLoader.java:260)\n\tat java.net.URLClassLoader.access$100(URLClassLoader.java:56)\n\tat java.net.URLClassLoader$1.run(URLClassLoader.java:195)\n\tat java.security.AccessController.doPrivileged(Native Method)\n\tat java.net.URLClassLoader.findClass(URLClassLoader.java:188)\n\tat java.lang.ClassLoader.loadClass(ClassLoader.java:306)\n\tat sun.misc.Launcher$AppClassLoader.loadClass(Launcher.java:268)\n\tat java.lang.ClassLoader.loadClass(ClassLoader.java:251)\n\tat java.lang.ClassLoader.loadClassInternal(ClassLoader.java:319)\n\tat java.lang.Class.forName0(Native Method)\n\tat java.lang.Class.forName(Class.java:164)\n\tat com.intellij.rt.execution.application.AppMain.main(AppMain.java:83)\n\nMessage: abort trouble in: \n class com.mycompany.MyClass extends java.lang.Object implements com.mycompany.MyInterface:\n  void \u003cinit\u003e():\n                    ALOAD_0     // com.mycompany.MyClass this   (line 5)\n                    INVOKESPECIAL java.lang.Object.\u003cinit\u003e ()V\n    constructor-execution(void com.mycompany.MyClass.\u003cinit\u003e())\n    |               RETURN\n    constructor-execution(void com.mycompany.MyClass.\u003cinit\u003e())\n  end void \u003cinit\u003e()\n\n  public static void main(String[]):\n                    RETURN   (line 9)\n  end public static void main(String[])\n\n  public Object read() throws java.io.IOException:\n                    ACONST_NULL   (line 14)\n                    ARETURN\n  end public Object read() throws java.io.IOException\n\n  public void exceptionDetected(Object):\n                    RETURN   (line 19)\n  end public void exceptionDetected(Object)\n\nend  class com.mycompany.MyClass\n -- (IllegalStateException) Wrong number of type parameters supplied\nWrong number of type parameters supplied\njava.lang.IllegalStateException: Wrong number of type parameters supplied\n\tat org.aspectj.weaver.ResolvedMemberImpl.parameterizedWith(ResolvedMemberImpl.java:609)\n\tat org.aspectj.weaver.ResolvedMemberImpl.parameterizedWith(ResolvedMemberImpl.java:590)\n\tat org.aspectj.weaver.ReferenceType.getDeclaredMethods(ReferenceType.java:421)\n\tat org.aspectj.weaver.ResolvedType.addAndRecurse(ResolvedType.java:262)\n\tat org.aspectj.weaver.ResolvedType.getMethodsWithoutIterator(ResolvedType.java:257)\n\tat org.aspectj.weaver.ResolvedType.lookupResolvedMember(ResolvedType.java:375)\n\tat org.aspectj.weaver.JoinPointSignatureIterator.findSignaturesFromSupertypes(JoinPointSignatureIterator.java:167)\n\tat org.aspectj.weaver.JoinPointSignatureIterator.hasNext(JoinPointSignatureIterator.java:68)\n\tat org.aspectj.weaver.patterns.SignaturePattern.matches(SignaturePattern.java:286)\n\tat org.aspectj.weaver.patterns.KindedPointcut.matchInternal(KindedPointcut.java:106)\n\tat org.aspectj.weaver.patterns.Pointcut.match(Pointcut.java:145)\n\tat org.aspectj.weaver.patterns.AndPointcut.matchInternal(AndPointcut.java:55)\n\tat org.aspectj.weaver.patterns.Pointcut.match(Pointcut.java:145)\n\tat org.aspectj.weaver.ShadowMunger.match(ShadowMunger.java:64)\n\tat org.aspectj.weaver.Advice.match(Advice.java:109)\n\tat org.aspectj.weaver.bcel.BcelAdvice.match(BcelAdvice.java:104)\n\tat org.aspectj.weaver.bcel.BcelClassWeaver.match(BcelClassWeaver.java:2113)\n\tat org.aspectj.weaver.bcel.BcelClassWeaver.match(BcelClassWeaver.java:1713)\n\tat org.aspectj.weaver.bcel.BcelClassWeaver.weave(BcelClassWeaver.java:455)\n\tat org.aspectj.weaver.bcel.BcelClassWeaver.weave(BcelClassWeaver.java:102)\n\tat org.aspectj.weaver.bcel.BcelWeaver.weave(BcelWeaver.java:1543)\n\tat org.aspectj.weaver.bcel.BcelWeaver.weaveWithoutDump(BcelWeaver.java:1494)\n\tat org.aspectj.weaver.bcel.BcelWeaver.weaveAndNotify(BcelWeaver.java:1275)\n\tat org.aspectj.weaver.bcel.BcelWeaver.weave(BcelWeaver.java:1097)\n\tat org.aspectj.weaver.tools.WeavingAdaptor.getWovenBytes(WeavingAdaptor.java:277)\n\tat org.aspectj.weaver.tools.WeavingAdaptor.weaveClass(WeavingAdaptor.java:210)\n\tat org.aspectj.weaver.loadtime.Aj.preProcess(Aj.java:65)\n\tat org.aspectj.weaver.loadtime.ClassPreProcessorAgentAdapter.transform(ClassPreProcessorAgentAdapter.java:52)\n\tat sun.instrument.TransformerManager.transform(TransformerManager.java:122)\n\tat sun.instrument.InstrumentationImpl.transform(InstrumentationImpl.java:155)\n\tat java.lang.ClassLoader.defineClass1(Native Method)\n\tat java.lang.ClassLoader.defineClass(ClassLoader.java:620)\n\tat java.security.SecureClassLoader.defineClass(SecureClassLoader.java:124)\n\tat java.net.URLClassLoader.defineClass(URLClassLoader.java:260)\n\tat java.net.URLClassLoader.access$100(URLClassLoader.java:56)\n\tat java.net.URLClassLoader$1.run(URLClassLoader.java:195)\n\tat java.security.AccessController.doPrivileged(Native Method)\n\tat java.net.URLClassLoader.findClass(URLClassLoader.java:188)\n\tat java.lang.ClassLoader.loadClass(ClassLoader.java:306)\n\tat sun.misc.Launcher$AppClassLoader.loadClass(Launcher.java:268)\n\tat java.lang.ClassLoader.loadClass(ClassLoader.java:251)\n\tat java.lang.ClassLoader.loadClassInternal(ClassLoader.java:319)\n\tat java.lang.Class.forName0(Native Method)\n\tat java.lang.Class.forName(Class.java:164)\n\tat com.intellij.rt.execution.application.AppMain.main(AppMain.java:83)\n\norg.aspectj.bridge.AbortException: trouble in: \n class com.mycompany.MyClass extends java.lang.Object implements com.mycompany.MyInterface:\n  void \u003cinit\u003e():\n                    ALOAD_0     // com.mycompany.MyClass this   (line 5)\n                    INVOKESPECIAL java.lang.Object.\u003cinit\u003e ()V\n    constructor-execution(void com.mycompany.MyClass.\u003cinit\u003e())\n    |               RETURN\n    constructor-execution(void com.mycompany.MyClass.\u003cinit\u003e())\n  end void \u003cinit\u003e()\n\n  public static void main(String[]):\n                    RETURN   (line 9)\n  end public static void main(String[])\n\n  public Object read() throws java.io.IOException:\n                    ACONST_NULL   (line 14)\n                    ARETURN\n  end public Object read() throws java.io.IOException\n\n  public void exceptionDetected(Object):\n                    RETURN   (line 19)\n  end public void exceptionDetected(Object)\n\nend  class com.mycompany.MyClass\n\n\tat org.aspectj.bridge.MessageWriter.handleMessage(MessageWriter.java:47)\n\tat org.aspectj.weaver.tools.WeavingAdaptor$WeavingAdaptorMessageHandler.handleMessage(WeavingAdaptor.java:411)\n\tat org.aspectj.weaver.bcel.BcelWeaver.weave(BcelWeaver.java:1554)\n\tat org.aspectj.weaver.bcel.BcelWeaver.weaveWithoutDump(BcelWeaver.java:1494)\n\tat org.aspectj.weaver.bcel.BcelWeaver.weaveAndNotify(BcelWeaver.java:1275)\n\tat org.aspectj.weaver.bcel.BcelWeaver.weave(BcelWeaver.java:1097)\n\tat org.aspectj.weaver.tools.WeavingAdaptor.getWovenBytes(WeavingAdaptor.java:277)\n\tat org.aspectj.weaver.tools.WeavingAdaptor.weaveClass(WeavingAdaptor.java:210)\n\tat org.aspectj.weaver.loadtime.Aj.preProcess(Aj.java:65)\n\tat org.aspectj.weaver.loadtime.ClassPreProcessorAgentAdapter.transform(ClassPreProcessorAgentAdapter.java:52)\n\tat sun.instrument.TransformerManager.transform(TransformerManager.java:122)\n\tat sun.instrument.InstrumentationImpl.transform(InstrumentationImpl.java:155)\n\tat java.lang.ClassLoader.defineClass1(Native Method)\n\tat java.lang.ClassLoader.defineClass(ClassLoader.java:620)\n\tat java.security.SecureClassLoader.defineClass(SecureClassLoader.java:124)\n\tat java.net.URLClassLoader.defineClass(URLClassLoader.java:260)\n\tat java.net.URLClassLoader.access$100(URLClassLoader.java:56)\n\tat java.net.URLClassLoader$1.run(URLClassLoader.java:195)\n\tat java.security.AccessController.doPrivileged(Native Method)\n\tat java.net.URLClassLoader.findClass(URLClassLoader.java:188)\n\tat java.lang.ClassLoader.loadClass(ClassLoader.java:306)\n\tat sun.misc.Launcher$AppClassLoader.loadClass(Launcher.java:268)\n\tat java.lang.ClassLoader.loadClass(ClassLoader.java:251)\n\tat java.lang.ClassLoader.loadClassInternal(ClassLoader.java:319)\n\tat java.lang.Class.forName0(Native Method)\n\tat java.lang.Class.forName(Class.java:164)\n\tat com.intellij.rt.execution.application.AppMain.main(AppMain.java:83)\n\n--- END OUTPUT ---",
    "Thanks for the clear report - I prefer when you include the code inline rather than as attachments - but other committers may feel differently :)\n\nAnd thanks for the pointer on not having 1.5.0 as a version against which bugs can be reported - I\u0027ve submitted a request to eclipse.org to get that fixed.\n\nHere is a smaller, standalone program that also fails in the same way, without LTW:\n\n\u003d\u003d\u003d8\u003c\u003d\u003d\u003d\u003d\u003d\u003d\u003d\u003d\u003d\u003d\u003d\u003d\u003d\u003d\u003d\u003d\nimport java.io.*;\n\naspect MyAspect {\n    before(): execution(* MyOtherClass.read()) { }\n}\n\n\nclass MyClass\u003cT,E\u003e implements MyInterface\u003cT\u003e {\n\n    public static void main(String[] arg) { }\n\n    public T read() throws IOException {\n        return null;\n    }\n\n    public void exceptionDetected(E e) { }\n}\n\n\ninterface MyInterface\u003cT\u003e {\n    public T read() throws IOException;\n}\n\nclass MyOtherClass {\n    public void read() { }\n}\n\u003d\u003d\u003d8\u003c\u003d\u003d\u003d\u003d\u003d\u003d\u003d\u003d\u003d\u003d\u003d\u003d\u003d\u003d\u003d\u003d\n\n",
    "as i suspected, the bug is related to using different numbers of type variables in the class and the interface.  What is being expressed is valid, but we don\u0027t cope well with it.  Changing MyInterface to add a redundant type variable is a workaround:\n\ninterface MyInterface\u003cT,X\u003e { \n  public T read() throws IOException;\n}\n\nclass MyClass\u003cT,E\u003e implements MyInterface\u003cT,E\u003e {\n...\n}\n\n",
    "Fix checked in.  The problem is just parameterizing a types super interfaces using the collapsed bounds of the types own type variables - here the erasures for the type variables are Object and Object when the superinterface only takes one type parameter.  We now use the correct bounds for parameterizing the superinterface.  Possibly could do with more testcases that experiment in the area of parameterizing types with type variables.\n\nfixes checked into HEAD.",
    "fix available."
  ],
  "commentCreationDates": [
    "2005-12-20T16:11:29+01:00",
    "2005-12-20T16:33:09+01:00",
    "2005-12-20T16:39:31+01:00",
    "2005-12-21T11:47:03+01:00",
    "2006-02-15T11:18:52+01:00"
  ],
  "traces": [
    {
      "exceptionType": "java.lang.IllegalStateException",
      "message": "Wrong number of type parameters supplied",
      "elements": [
        {
          "method": "org.aspectj.weaver.ResolvedMemberImpl.parameterizedWith",
          "source": "ResolvedMemberImpl.java:609"
        },
        {
          "method": "org.aspectj.weaver.ResolvedMemberImpl.parameterizedWith",
          "source": "ResolvedMemberImpl.java:590"
        },
        {
          "method": "org.aspectj.weaver.ReferenceType.getDeclaredMethods",
          "source": "ReferenceType.java:421"
        },
        {
          "method": "org.aspectj.weaver.ResolvedType.addAndRecurse",
          "source": "ResolvedType.java:262"
        },
        {
          "method": "org.aspectj.weaver.ResolvedType.getMethodsWithoutIterator",
          "source": "ResolvedType.java:257"
        },
        {
          "method": "org.aspectj.weaver.ResolvedType.lookupResolvedMember",
          "source": "ResolvedType.java:375"
        },
        {
          "method": "org.aspectj.weaver.JoinPointSignatureIterator.findSignaturesFromSupertypes",
          "source": "JoinPointSignatureIterator.java:167"
        },
        {
          "method": "org.aspectj.weaver.JoinPointSignatureIterator.hasNext",
          "source": "JoinPointSignatureIterator.java:68"
        },
        {
          "method": "org.aspectj.weaver.patterns.SignaturePattern.matches",
          "source": "SignaturePattern.java:286"
        },
        {
          "method": "org.aspectj.weaver.patterns.KindedPointcut.matchInternal",
          "source": "KindedPointcut.java:106"
        },
        {
          "method": "org.aspectj.weaver.patterns.Pointcut.match",
          "source": "Pointcut.java:145"
        },
        {
          "method": "org.aspectj.weaver.patterns.AndPointcut.matchInternal",
          "source": "AndPointcut.java:55"
        },
        {
          "method": "org.aspectj.weaver.patterns.Pointcut.match",
          "source": "Pointcut.java:145"
        },
        {
          "method": "org.aspectj.weaver.ShadowMunger.match",
          "source": "ShadowMunger.java:64"
        },
        {
          "method": "org.aspectj.weaver.Advice.match",
          "source": "Advice.java:109"
        },
        {
          "method": "org.aspectj.weaver.bcel.BcelAdvice.match",
          "source": "BcelAdvice.java:104"
        },
        {
          "method": "org.aspectj.weaver.bcel.BcelClassWeaver.match",
          "source": "BcelClassWeaver.java:2113"
        },
        {
          "method": "org.aspectj.weaver.bcel.BcelClassWeaver.match",
          "source": "BcelClassWeaver.java:1713"
        },
        {
          "method": "org.aspectj.weaver.bcel.BcelClassWeaver.weave",
          "source": "BcelClassWeaver.java:455"
        },
        {
          "method": "org.aspectj.weaver.bcel.BcelClassWeaver.weave",
          "source": "BcelClassWeaver.java:102"
        },
        {
          "method": "org.aspectj.weaver.bcel.BcelWeaver.weave",
          "source": "BcelWeaver.java:1543"
        },
        {
          "method": "org.aspectj.weaver.bcel.BcelWeaver.weaveWithoutDump",
          "source": "BcelWeaver.java:1494"
        },
        {
          "method": "org.aspectj.weaver.bcel.BcelWeaver.weaveAndNotify",
          "source": "BcelWeaver.java:1275"
        },
        {
          "method": "org.aspectj.weaver.bcel.BcelWeaver.weave",
          "source": "BcelWeaver.java:1097"
        },
        {
          "method": "org.aspectj.weaver.tools.WeavingAdaptor.getWovenBytes",
          "source": "WeavingAdaptor.java:277"
        },
        {
          "method": "org.aspectj.weaver.tools.WeavingAdaptor.weaveClass",
          "source": "WeavingAdaptor.java:210"
        },
        {
          "method": "org.aspectj.weaver.loadtime.Aj.preProcess",
          "source": "Aj.java:65"
        },
        {
          "method": "org.aspectj.weaver.loadtime.ClassPreProcessorAgentAdapter.transform",
          "source": "ClassPreProcessorAgentAdapter.java:52"
        },
        {
          "method": "sun.instrument.TransformerManager.transform",
          "source": "TransformerManager.java:122"
        },
        {
          "method": "sun.instrument.InstrumentationImpl.transform",
          "source": "InstrumentationImpl.java:155"
        },
        {
          "method": "java.lang.ClassLoader.defineClass1",
          "source": "Native Method"
        },
        {
          "method": "java.lang.ClassLoader.defineClass",
          "source": "ClassLoader.java:620"
        },
        {
          "method": "java.security.SecureClassLoader.defineClass",
          "source": "SecureClassLoader.java:124"
        },
        {
          "method": "java.net.URLClassLoader.defineClass",
          "source": "URLClassLoader.java:260"
        },
        {
          "method": "java.net.URLClassLoader.access$100",
          "source": "URLClassLoader.java:56"
        },
        {
          "method": "java.net.URLClassLoader$1.run",
          "source": "URLClassLoader.java:195"
        },
        {
          "method": "java.security.AccessController.doPrivileged",
          "source": "Native Method"
        },
        {
          "method": "java.net.URLClassLoader.findClass",
          "source": "URLClassLoader.java:188"
        },
        {
          "method": "java.lang.ClassLoader.loadClass",
          "source": "ClassLoader.java:306"
        },
        {
          "method": "sun.misc.Launcher$AppClassLoader.loadClass",
          "source": "Launcher.java:268"
        },
        {
          "method": "java.lang.ClassLoader.loadClass",
          "source": "ClassLoader.java:251"
        },
        {
          "method": "java.lang.ClassLoader.loadClassInternal",
          "source": "ClassLoader.java:319"
        },
        {
          "method": "java.lang.Class.forName0",
          "source": "Native Method"
        },
        {
          "method": "java.lang.Class.forName",
          "source": "Class.java:164"
        },
        {
          "method": "com.intellij.rt.execution.application.AppMain.main",
          "source": "AppMain.java:83"
        }
      ],
      "number": 0,
      "commentIndex": 0,
      "bugId": "121575",
      "date": "2005-12-20T16:11:29+01:00",
      "product": "AspectJ",
      "component": "Compiler",
      "severity": "normal"
    },
    {
      "exceptionType": "java.lang.IllegalStateException",
      "message": "Wrong number of type parameters supplied",
      "elements": [
        {
          "method": "org.aspectj.weaver.ResolvedMemberImpl.parameterizedWith",
          "source": "ResolvedMemberImpl.java:609"
        },
        {
          "method": "org.aspectj.weaver.ResolvedMemberImpl.parameterizedWith",
          "source": "ResolvedMemberImpl.java:590"
        },
        {
          "method": "org.aspectj.weaver.ReferenceType.getDeclaredMethods",
          "source": "ReferenceType.java:421"
        },
        {
          "method": "org.aspectj.weaver.ResolvedType.addAndRecurse",
          "source": "ResolvedType.java:262"
        },
        {
          "method": "org.aspectj.weaver.ResolvedType.getMethodsWithoutIterator",
          "source": "ResolvedType.java:257"
        },
        {
          "method": "org.aspectj.weaver.ResolvedType.lookupResolvedMember",
          "source": "ResolvedType.java:375"
        },
        {
          "method": "org.aspectj.weaver.JoinPointSignatureIterator.findSignaturesFromSupertypes",
          "source": "JoinPointSignatureIterator.java:167"
        },
        {
          "method": "org.aspectj.weaver.JoinPointSignatureIterator.hasNext",
          "source": "JoinPointSignatureIterator.java:68"
        },
        {
          "method": "org.aspectj.weaver.patterns.SignaturePattern.matches",
          "source": "SignaturePattern.java:286"
        },
        {
          "method": "org.aspectj.weaver.patterns.KindedPointcut.matchInternal",
          "source": "KindedPointcut.java:106"
        },
        {
          "method": "org.aspectj.weaver.patterns.Pointcut.match",
          "source": "Pointcut.java:145"
        },
        {
          "method": "org.aspectj.weaver.patterns.AndPointcut.matchInternal",
          "source": "AndPointcut.java:55"
        },
        {
          "method": "org.aspectj.weaver.patterns.Pointcut.match",
          "source": "Pointcut.java:145"
        },
        {
          "method": "org.aspectj.weaver.ShadowMunger.match",
          "source": "ShadowMunger.java:64"
        },
        {
          "method": "org.aspectj.weaver.Advice.match",
          "source": "Advice.java:109"
        },
        {
          "method": "org.aspectj.weaver.bcel.BcelAdvice.match",
          "source": "BcelAdvice.java:104"
        },
        {
          "method": "org.aspectj.weaver.bcel.BcelClassWeaver.match",
          "source": "BcelClassWeaver.java:2113"
        },
        {
          "method": "org.aspectj.weaver.bcel.BcelClassWeaver.match",
          "source": "BcelClassWeaver.java:1713"
        },
        {
          "method": "org.aspectj.weaver.bcel.BcelClassWeaver.weave",
          "source": "BcelClassWeaver.java:455"
        },
        {
          "method": "org.aspectj.weaver.bcel.BcelClassWeaver.weave",
          "source": "BcelClassWeaver.java:102"
        },
        {
          "method": "org.aspectj.weaver.bcel.BcelWeaver.weave",
          "source": "BcelWeaver.java:1543"
        },
        {
          "method": "org.aspectj.weaver.bcel.BcelWeaver.weaveWithoutDump",
          "source": "BcelWeaver.java:1494"
        },
        {
          "method": "org.aspectj.weaver.bcel.BcelWeaver.weaveAndNotify",
          "source": "BcelWeaver.java:1275"
        },
        {
          "method": "org.aspectj.weaver.bcel.BcelWeaver.weave",
          "source": "BcelWeaver.java:1097"
        },
        {
          "method": "org.aspectj.weaver.tools.WeavingAdaptor.getWovenBytes",
          "source": "WeavingAdaptor.java:277"
        },
        {
          "method": "org.aspectj.weaver.tools.WeavingAdaptor.weaveClass",
          "source": "WeavingAdaptor.java:210"
        },
        {
          "method": "org.aspectj.weaver.loadtime.Aj.preProcess",
          "source": "Aj.java:65"
        },
        {
          "method": "org.aspectj.weaver.loadtime.ClassPreProcessorAgentAdapter.transform",
          "source": "ClassPreProcessorAgentAdapter.java:52"
        },
        {
          "method": "sun.instrument.TransformerManager.transform",
          "source": "TransformerManager.java:122"
        },
        {
          "method": "sun.instrument.InstrumentationImpl.transform",
          "source": "InstrumentationImpl.java:155"
        },
        {
          "method": "java.lang.ClassLoader.defineClass1",
          "source": "Native Method"
        },
        {
          "method": "java.lang.ClassLoader.defineClass",
          "source": "ClassLoader.java:620"
        },
        {
          "method": "java.security.SecureClassLoader.defineClass",
          "source": "SecureClassLoader.java:124"
        },
        {
          "method": "java.net.URLClassLoader.defineClass",
          "source": "URLClassLoader.java:260"
        },
        {
          "method": "java.net.URLClassLoader.access$100",
          "source": "URLClassLoader.java:56"
        },
        {
          "method": "java.net.URLClassLoader$1.run",
          "source": "URLClassLoader.java:195"
        },
        {
          "method": "java.security.AccessController.doPrivileged",
          "source": "Native Method"
        },
        {
          "method": "java.net.URLClassLoader.findClass",
          "source": "URLClassLoader.java:188"
        },
        {
          "method": "java.lang.ClassLoader.loadClass",
          "source": "ClassLoader.java:306"
        },
        {
          "method": "sun.misc.Launcher$AppClassLoader.loadClass",
          "source": "Launcher.java:268"
        },
        {
          "method": "java.lang.ClassLoader.loadClass",
          "source": "ClassLoader.java:251"
        },
        {
          "method": "java.lang.ClassLoader.loadClassInternal",
          "source": "ClassLoader.java:319"
        },
        {
          "method": "java.lang.Class.forName0",
          "source": "Native Method"
        },
        {
          "method": "java.lang.Class.forName",
          "source": "Class.java:164"
        },
        {
          "method": "com.intellij.rt.execution.application.AppMain.main",
          "source": "AppMain.java:83"
        }
      ],
      "number": 1,
      "commentIndex": 0,
      "bugId": "121575",
      "date": "2005-12-20T16:11:29+01:00",
      "product": "AspectJ",
      "component": "Compiler",
      "severity": "normal"
    },
    {
      "exceptionType": "java.io.IOException",
      "message": "ACONST_NULL   (line 14)                     ARETURN   end public Object read() throws java.io.IOException    public void exceptionDetected(Object):                     RETURN   (line 19)   end public void exceptionDetected(Object)  end  class com.mycompany.MyClass",
      "elements": [
        {
          "method": "org.aspectj.bridge.MessageWriter.handleMessage",
          "source": "MessageWriter.java:47"
        },
        {
          "method": "org.aspectj.weaver.tools.WeavingAdaptor$WeavingAdaptorMessageHandler.handleMessage",
          "source": "WeavingAdaptor.java:411"
        },
        {
          "method": "org.aspectj.weaver.bcel.BcelWeaver.weave",
          "source": "BcelWeaver.java:1554"
        },
        {
          "method": "org.aspectj.weaver.bcel.BcelWeaver.weaveWithoutDump",
          "source": "BcelWeaver.java:1494"
        },
        {
          "method": "org.aspectj.weaver.bcel.BcelWeaver.weaveAndNotify",
          "source": "BcelWeaver.java:1275"
        },
        {
          "method": "org.aspectj.weaver.bcel.BcelWeaver.weave",
          "source": "BcelWeaver.java:1097"
        },
        {
          "method": "org.aspectj.weaver.tools.WeavingAdaptor.getWovenBytes",
          "source": "WeavingAdaptor.java:277"
        },
        {
          "method": "org.aspectj.weaver.tools.WeavingAdaptor.weaveClass",
          "source": "WeavingAdaptor.java:210"
        },
        {
          "method": "org.aspectj.weaver.loadtime.Aj.preProcess",
          "source": "Aj.java:65"
        },
        {
          "method": "org.aspectj.weaver.loadtime.ClassPreProcessorAgentAdapter.transform",
          "source": "ClassPreProcessorAgentAdapter.java:52"
        },
        {
          "method": "sun.instrument.TransformerManager.transform",
          "source": "TransformerManager.java:122"
        },
        {
          "method": "sun.instrument.InstrumentationImpl.transform",
          "source": "InstrumentationImpl.java:155"
        },
        {
          "method": "java.lang.ClassLoader.defineClass1",
          "source": "Native Method"
        },
        {
          "method": "java.lang.ClassLoader.defineClass",
          "source": "ClassLoader.java:620"
        },
        {
          "method": "java.security.SecureClassLoader.defineClass",
          "source": "SecureClassLoader.java:124"
        },
        {
          "method": "java.net.URLClassLoader.defineClass",
          "source": "URLClassLoader.java:260"
        },
        {
          "method": "java.net.URLClassLoader.access$100",
          "source": "URLClassLoader.java:56"
        },
        {
          "method": "java.net.URLClassLoader$1.run",
          "source": "URLClassLoader.java:195"
        },
        {
          "method": "java.security.AccessController.doPrivileged",
          "source": "Native Method"
        },
        {
          "method": "java.net.URLClassLoader.findClass",
          "source": "URLClassLoader.java:188"
        },
        {
          "method": "java.lang.ClassLoader.loadClass",
          "source": "ClassLoader.java:306"
        },
        {
          "method": "sun.misc.Launcher$AppClassLoader.loadClass",
          "source": "Launcher.java:268"
        },
        {
          "method": "java.lang.ClassLoader.loadClass",
          "source": "ClassLoader.java:251"
        },
        {
          "method": "java.lang.ClassLoader.loadClassInternal",
          "source": "ClassLoader.java:319"
        },
        {
          "method": "java.lang.Class.forName0",
          "source": "Native Method"
        },
        {
          "method": "java.lang.Class.forName",
          "source": "Class.java:164"
        },
        {
          "method": "com.intellij.rt.execution.application.AppMain.main",
          "source": "AppMain.java:83"
        }
      ],
      "number": 2,
      "commentIndex": 0,
      "bugId": "121575",
      "date": "2005-12-20T16:11:29+01:00",
      "product": "AspectJ",
      "component": "Compiler",
      "severity": "normal"
    }
  ],
  "groupId": "121575",
  "bugId": "121575",
  "date": "2005-12-20T16:11:29+01:00",
  "product": "AspectJ",
  "component": "Compiler",
  "severity": "normal"
}