{
  "comments": [
    "Tied to how editors that do not persist are managed.\nFound this when working with editors in an RCP application.\n\nIf you create multiple editor panes and they are occupied by editors that do not persist, when you restart the workbench both (or more) panes are empty and visible.\n\u003eIf there are no editors to be displayed, should the UI not return to one empty editor pane?\n\nIn 3.1.1, if you open an editor it uses one of the multiple panes; when closed that pane disappears.  Same for 3.2M4.\nIn both 3.1.1 and 3.2M4, if you drag one of the panes you can create additional panes, all empty.  To close these extra panes you have to open an editor in each one and then close the editor.\n\nWhen you close the workbench with multiple empty editor panes in 3.2M4 there is no problem, but in 3.1.1 you get an exception:  Problems occurred when invoking code from plug-in: \"org.eclipse.ui.workbench\".\nPartial stack trace:\norg.eclipse.swt.SWTException: Widget is disposed\nat java.lang.Throwable.\u003cinit\u003e(Throwable.java)\nat java.lang.Throwable.\u003cinit\u003e(Throwable.java)\nat org.eclipse.swt.SWTException.\u003cinit\u003e(SWTException.java:87)\nat org.eclipse.swt.SWT.error(SWT.java:2942)\nat org.eclipse.swt.SWT.error(SWT.java:2865)\nat org.eclipse.swt.SWT.error(SWT.java:2836)\nat org.eclipse.swt.widgets.Widget.error(Widget.java:395)\nat org.eclipse.swt.widgets.Widget.checkWidget(Widget.java)\nat org.eclipse.swt.widgets.Control.getBounds(Control.java:759)\nat org.eclipse.ui.internal.LayoutPartSash.dispose(LayoutPartSash.java:164)\nat org.eclipse.ui.internal.LayoutTreeNode.disposeSashes(LayoutTreeNode.java:127)\nat org.eclipse.ui.internal.PartSashContainer.disposeSashes(PartSashContainer.java:552)\nat org.eclipse.ui.internal.PartSashContainer.dispose(PartSashContainer.java:535)\nat org.eclipse.ui.internal.EditorSashContainer.dispose(EditorSashContainer.java:121)\nat org.eclipse.ui.internal.EditorAreaHelper.dispose(EditorAreaHelper.java:121)\nat org.eclipse.ui.internal.WorkbenchPage.dispose(WorkbenchPage.java:1524)\nat org.eclipse.ui.internal.WorkbenchWindow.closeAllPages(WorkbenchWindow.java:763)\nat org.eclipse.ui.internal.WorkbenchWindow.hardClose(WorkbenchWindow.java:1392)\nat org.eclipse.ui.internal.WorkbenchWindow.busyClose(WorkbenchWindow.java:646)\nat org.eclipse.ui.internal.WorkbenchWindow.access$0(WorkbenchWindow.java:627)\nat org.eclipse.ui.internal.WorkbenchWindow$2.run(WorkbenchWindow.java:728)\nat org.eclipse.swt.custom.BusyIndicator.showWhile(BusyIndicator.java:69)\nat org.eclipse.ui.internal.WorkbenchWindow.close(WorkbenchWindow.java:726)\nat org.eclipse.jface.window.WindowManager.close(WindowManager.java:108)\nat org.eclipse.ui.internal.Workbench$11.run(Workbench.java:588)\nat org.eclipse.core.internal.runtime.InternalPlatform.run(InternalPlatform.java:1044)\nat org.eclipse.core.runtime.Platform.run(Platform.java:783)\nat org.eclipse.ui.internal.Workbench.busyClose(Workbench.java:585)\n\nWhen workbench is restarted you continue to see multiple editor panes.\n\n\u003e 3.2M4 is ok here, but 3.1.1 should attempt to catch or prevent the exception.\n\nTo demo/test this you do not need any code.\n\n1) start a test instance of the workbench SDK\n2) create a plug-in project with the hello world example\n3) on the extensions page of the editor, use the \"show description\" popup menu for an extension element\n4) use the Window \u003e New editor action to create two editors with extension description content\n5) close the plugin.xml editor\n6) arrange the two description editors in two editor panes\n7) close workbench\n\nOn 3.1.1 you will see an error dialog, details in the .log.\nNo error on 3.2M4, but the multiple editor pane on restart is there as it is in 3.1.1.\n\nReal issue is not IDE so much as that class of user can probably ignore and will not often have editors that do not persist. It is RCP applications and those users that may have trouble with both the exception at close and the return to a UI with multiple empty editor panes (nonpersistent RCP Editors may be more common).\n\nThat and the thought that maybe multiple editor panes should not be shown when they are empty (close any extra empty editor panes).",
    "Think I left out workbench start/stop (8/9):\n\n1) start a test instance of the workbench SDK\n2) create a plug-in project with the hello world example\n3) on the extensions page of the editor, use the \"show description\" popup menu\nfor an extension element\n4) use the Window \u003e New editor action to create two editors with extension\ndescription content\n5) close the plugin.xml editor\n6) arrange the two description editors in two editor panes\n7) close workbench\n8) Restart workbench (now you see two empty editor panes)\n9) Close Workbench - this is when the exeception is thrown on 3.1.1",
    "Is this still a problem in 3.3?\n\nPW\n",
    "Changes requested on bug 193523",
    "hi, i\u0027m using eclipse 3.1.2 and i\u0027m facing this problem too\ni\u0027ve not noticed this earlier and posted a \nbug: https://bugs.eclipse.org/bugs/show_bug.cgi?id\u003d204432\n\nis there a solution for this?\n\ni\u0027m doing a plugin development and it will be incorporated\nwith a lot of other plugins so this behavior is not favorable\nas it may cause problems for the other plugins",
    "*** Bug 204432 has been marked as a duplicate of this bug. ***",
    "*** Bug 142538 has been marked as a duplicate of this bug. ***",
    "I was just wondering why there isn\u0027t even a minor response to this.\nI mean if more details need to be provided to reproduce the problem\nor it is being looked.\n\nHopefully the person in charge can place a simple note on this issue.\nThank you for the attention.",
    "(In reply to comment #7)\n\u003e I was just wondering why there isn\u0027t even a minor response to this.\n\u003e I mean if more details need to be provided to reproduce the problem\n\u003e or it is being looked.\n\nP5 with no target milestone ... it\u0027s not being looked at.\n\nIf it is related to bug 154730 then it might be addressed in 3.4.\n\nAs always, I would review patches if someone wants to create them.\n\nPW\n",
    "oh ic\nnvm then\ni\u0027ll try and see wat sort of workaround i can do",
    "We\u0027re seeing this problem with our application which uses Eclipse 3.3.0. I also see the problem in Eclipse 3.3.1."
  ],
  "commentCreationDates": [
    "2005-12-29T15:33:53+01:00",
    "2006-01-03T14:53:00+01:00",
    "2006-09-28T21:17:24+02:00",
    "2007-06-22T15:33:17+02:00",
    "2007-09-26T11:01:19+02:00",
    "2007-09-26T14:53:24+02:00",
    "2007-09-26T20:41:39+02:00",
    "2007-10-03T04:03:02+02:00",
    "2007-10-03T14:18:52+02:00",
    "2007-10-05T15:40:08+02:00",
    "2007-10-25T19:38:09+02:00"
  ],
  "traces": [
    {
      "exceptionType": "org.eclipse.swt.SWTException",
      "message": "Widget is disposed",
      "elements": [
        {
          "method": "java.lang.Throwable.\u003cinit\u003e",
          "source": "Throwable.java"
        },
        {
          "method": "java.lang.Throwable.\u003cinit\u003e",
          "source": "Throwable.java"
        },
        {
          "method": "org.eclipse.swt.SWTException.\u003cinit\u003e",
          "source": "SWTException.java:87"
        },
        {
          "method": "org.eclipse.swt.SWT.error",
          "source": "SWT.java:2942"
        },
        {
          "method": "org.eclipse.swt.SWT.error",
          "source": "SWT.java:2865"
        },
        {
          "method": "org.eclipse.swt.SWT.error",
          "source": "SWT.java:2836"
        },
        {
          "method": "org.eclipse.swt.widgets.Widget.error",
          "source": "Widget.java:395"
        },
        {
          "method": "org.eclipse.swt.widgets.Widget.checkWidget",
          "source": "Widget.java"
        },
        {
          "method": "org.eclipse.swt.widgets.Control.getBounds",
          "source": "Control.java:759"
        },
        {
          "method": "org.eclipse.ui.internal.LayoutPartSash.dispose",
          "source": "LayoutPartSash.java:164"
        },
        {
          "method": "org.eclipse.ui.internal.LayoutTreeNode.disposeSashes",
          "source": "LayoutTreeNode.java:127"
        },
        {
          "method": "org.eclipse.ui.internal.PartSashContainer.disposeSashes",
          "source": "PartSashContainer.java:552"
        },
        {
          "method": "org.eclipse.ui.internal.PartSashContainer.dispose",
          "source": "PartSashContainer.java:535"
        },
        {
          "method": "org.eclipse.ui.internal.EditorSashContainer.dispose",
          "source": "EditorSashContainer.java:121"
        },
        {
          "method": "org.eclipse.ui.internal.EditorAreaHelper.dispose",
          "source": "EditorAreaHelper.java:121"
        },
        {
          "method": "org.eclipse.ui.internal.WorkbenchPage.dispose",
          "source": "WorkbenchPage.java:1524"
        },
        {
          "method": "org.eclipse.ui.internal.WorkbenchWindow.closeAllPages",
          "source": "WorkbenchWindow.java:763"
        },
        {
          "method": "org.eclipse.ui.internal.WorkbenchWindow.hardClose",
          "source": "WorkbenchWindow.java:1392"
        },
        {
          "method": "org.eclipse.ui.internal.WorkbenchWindow.busyClose",
          "source": "WorkbenchWindow.java:646"
        },
        {
          "method": "org.eclipse.ui.internal.WorkbenchWindow.access$0",
          "source": "WorkbenchWindow.java:627"
        },
        {
          "method": "org.eclipse.ui.internal.WorkbenchWindow$2.run",
          "source": "WorkbenchWindow.java:728"
        },
        {
          "method": "org.eclipse.swt.custom.BusyIndicator.showWhile",
          "source": "BusyIndicator.java:69"
        },
        {
          "method": "org.eclipse.ui.internal.WorkbenchWindow.close",
          "source": "WorkbenchWindow.java:726"
        },
        {
          "method": "org.eclipse.jface.window.WindowManager.close",
          "source": "WindowManager.java:108"
        },
        {
          "method": "org.eclipse.ui.internal.Workbench$11.run",
          "source": "Workbench.java:588"
        },
        {
          "method": "org.eclipse.core.internal.runtime.InternalPlatform.run",
          "source": "InternalPlatform.java:1044"
        },
        {
          "method": "org.eclipse.core.runtime.Platform.run",
          "source": "Platform.java:783"
        },
        {
          "method": "org.eclipse.ui.internal.Workbench.busyClose",
          "source": "Workbench.java:585"
        }
      ],
      "number": 0,
      "commentIndex": 0,
      "bugId": "122322",
      "date": "2005-12-29T15:33:53+01:00",
      "product": "Platform",
      "component": "UI",
      "severity": "normal"
    }
  ],
  "groupId": "122322",
  "bugId": "122322",
  "date": "2005-12-29T15:33:53+01:00",
  "product": "Platform",
  "component": "UI",
  "severity": "normal"
}