{
  "comments": [
    "If you attempt to delete selected text in a StyledText widget, where the selection extends beyond the visible windowarea, you get an SWTException:\n\nCaused by: java.lang.IllegalArgumentException: Argument not valid\n        at org.eclipse.swt.SWT.error(SWT.java:3267)\n        at org.eclipse.swt.SWT.error(SWT.java:3206)\n        at org.eclipse.swt.SWT.error(SWT.java:3177)\n        at org.eclipse.swt.custom.DefaultContent.error(DefaultContent.java:670)\n        at org.eclipse.swt.custom.DefaultContent.getLine(DefaultContent.java:478)\n        at org.eclipse.swt.custom.StyledTextRenderer.getTextLayout(StyledTextRenderer.java:643)\n        at org.eclipse.swt.custom.StyledTextRenderer.getTextLayout(StyledTextRenderer.java:607)\n        at org.eclipse.swt.custom.StyledTextRenderer.calculate(StyledTextRenderer.java:197)\n        at org.eclipse.swt.custom.StyledText.getVerticalScrollOffset(StyledText.java:4547)\n        at org.eclipse.swt.custom.StyledTextRenderer$1.run(StyledTextRenderer.java:240)\n        at org.eclipse.swt.widgets.RunnableLock.run(RunnableLock.java:35)\n        at org.eclipse.swt.widgets.Synchronizer.runAsyncMessages(Synchronizer.java:123)",
    "Created an attachment (id\u003d32352)\nJavaclass which exhibits problem\n\nIf the StyledText does not have the Style SWT.WRAP the exception does not happen",
    "fixed in HEAD \u003e 20060317\n\nplease verify",
    "(In reply to comment #2)\n\u003e fixed in HEAD \u003e 20060317\n\u003e \n\u003e please verify\n\u003e \nVerified. Thank you\n"
  ],
  "commentCreationDates": [
    "2005-12-30T10:38:23+01:00",
    "2005-12-30T13:03:31+01:00",
    "2006-03-17T20:27:59+01:00",
    "2006-04-26T12:05:07+02:00"
  ],
  "traces": [
    {
      "exceptionType": "java.lang.IllegalArgumentException",
      "message": "Argument not valid",
      "elements": [
        {
          "method": "org.eclipse.swt.SWT.error",
          "source": "SWT.java:3267"
        },
        {
          "method": "org.eclipse.swt.SWT.error",
          "source": "SWT.java:3206"
        },
        {
          "method": "org.eclipse.swt.SWT.error",
          "source": "SWT.java:3177"
        },
        {
          "method": "org.eclipse.swt.custom.DefaultContent.error",
          "source": "DefaultContent.java:670"
        },
        {
          "method": "org.eclipse.swt.custom.DefaultContent.getLine",
          "source": "DefaultContent.java:478"
        },
        {
          "method": "org.eclipse.swt.custom.StyledTextRenderer.getTextLayout",
          "source": "StyledTextRenderer.java:643"
        },
        {
          "method": "org.eclipse.swt.custom.StyledTextRenderer.getTextLayout",
          "source": "StyledTextRenderer.java:607"
        },
        {
          "method": "org.eclipse.swt.custom.StyledTextRenderer.calculate",
          "source": "StyledTextRenderer.java:197"
        },
        {
          "method": "org.eclipse.swt.custom.StyledText.getVerticalScrollOffset",
          "source": "StyledText.java:4547"
        },
        {
          "method": "org.eclipse.swt.custom.StyledTextRenderer$1.run",
          "source": "StyledTextRenderer.java:240"
        },
        {
          "method": "org.eclipse.swt.widgets.RunnableLock.run",
          "source": "RunnableLock.java:35"
        },
        {
          "method": "org.eclipse.swt.widgets.Synchronizer.runAsyncMessages",
          "source": "Synchronizer.java:123"
        }
      ],
      "number": 0,
      "commentIndex": 0,
      "bugId": "122379",
      "date": "2005-12-30T10:38:23+01:00",
      "product": "Platform",
      "component": "SWT",
      "severity": "major"
    }
  ],
  "groupId": "122379",
  "bugId": "122379",
  "date": "2005-12-30T10:38:23+01:00",
  "product": "Platform",
  "component": "SWT",
  "severity": "major"
}