{
  "comments": [
    "Our headless application that uses WTP is failing on WTP 1.0.1\non ear import. Seems like 1.0.1 needs a facet runtime configured.\nwhich is not the behaviour on 1.0.0.\n\njava.lang.IllegalArgumentException: Could not find runtime .\n        at org.eclipse.wst.common.project.facet.core.runtime.internal.RuntimeMan\nagerImpl.getRuntime(RuntimeManagerImpl.java:186)\n        at org.eclipse.wst.common.project.facet.core.runtime.RuntimeManager.getR\nuntime(RuntimeManager.java:125)\n        at org.eclipse.jst.j2ee.internal.earcreation.EarComponentCreationFacetOp\neration.execute(EarComponentCreationFacetOperation.java:56)\n        at org.eclipse.wst.common.frameworks.internal.datamodel.ExtendableOperat\nionImpl.doExecute(ExtendableOperationImpl.java:163)\n        at org.eclipse.wst.common.frameworks.internal.datamodel.ExtendableOperat\nionImpl$1.run(ExtendableOperationImpl.java:131)\n        at org.eclipse.core.internal.resources.Workspace.run(Workspace.java:1719\n)\n        at org.eclipse.core.internal.resources.Workspace.run(Workspace.java:1739\n)\n        at org.eclipse.wst.common.frameworks.internal.datamodel.ExtendableOperat\nionImpl.execute(ExtendableOperationImpl.java:137)\n        at org.eclipse.jst.j2ee.internal.archive.operations.J2EEArtifactImportOp\neration.createVirtualComponent(J2EEArtifactImportOperation.java:78)\n        at org.eclipse.jst.j2ee.internal.archive.operations.J2EEArtifactImportOp\neration.doExecute(J2EEArtifactImportOperation.java:66)\n        at org.eclipse.jst.j2ee.internal.archive.operations.EARComponentImportOp\neration.doExecute(EARComponentImportOperation.java:59)\n        at org.eclipse.jst.j2ee.internal.archive.operations.J2EEArtifactImportOp\neration.execute(J2EEArtifactImportOperation.java:55)\n        at org.eclipse.wst.common.frameworks.internal.datamodel.ExtendableOperat\nionImpl.doExecute(ExtendableOperationImpl.java:163)\n        at org.eclipse.wst.common.frameworks.internal.datamodel.ExtendableOperat\nionImpl$1.run(ExtendableOperationImpl.java:131)\n        at org.eclipse.core.internal.resources.Workspace.run(Workspace.java:1719\n)\n        at org.eclipse.core.internal.resources.Workspace.run(Workspace.java:1739\n)\n        at org.eclipse.wst.common.frameworks.internal.datamodel.ExtendableOperat\nionImpl.execute(ExtendableOperationImpl.java:137)\n        at com.ibm.etools.ejbdeploy.batch.plugin.BatchExtension.importEar(BatchE\nxtension.java:949)\n        at com.ibm.etools.ejbdeploy.batch.plugin.BatchExtension.runEarDeploy(Bat\nchExtension.java:322)\n        at com.ibm.etools.ejbdeploy.batch.plugin.BatchExtension.access$0(BatchEx\ntension.java:317)\n        at com.ibm.etools.ejbdeploy.batch.plugin.BatchExtension$RunDeploy.run(Ba\ntchExtension.java:300)\n        at org.eclipse.core.internal.resources.Workspace.run(Workspace.java:1719\n)\n        at org.eclipse.core.internal.resources.Workspace.run(Workspace.java:1739\n)\n        at com.ibm.etools.ejbdeploy.batch.plugin.BatchExtension$RunDeploy.execut\ne(BatchExtension.java:284)\n        at com.ibm.etools.ejbdeploy.batch.plugin.BatchExtension.run(BatchExtensi\non.java:247)\n        at org.eclipse.core.internal.runtime.PlatformActivator$1.run(PlatformAct\nivator.java:226)\n        at org.eclipse.core.runtime.adaptor.EclipseStarter.run(EclipseStarter.ja\nva:376)\n        at sun.reflect.NativeMethodAccessorImpl.invoke0(Native Method)\n        at sun.reflect.NativeMethodAccessorImpl.invoke(NativeMethodAccessorImpl.\njava:64)\n        at sun.reflect.DelegatingMethodAccessorImpl.invoke(DelegatingMethodAcces\nsorImpl.java:43)\n        at java.lang.reflect.Method.invoke(Method.java:615)\n        at com.ibm.etools.ejbdeploy.batch.impl.BootLoaderLoader.run(BootLoaderLo\nader.java:272)\n        at com.ibm.etools.ejbdeploy.batch.impl.BatchDeploy.execute(BatchDeploy.j\nava:99)\n        at com.ibm.etools.ejbdeploy.EJBDeploy.execute(EJBDeploy.java:83)\n        at com.ibm.etools.ejbdeploy.EJBDeploy.main(EJBDeploy.java:313)\n[*Error] An unexpected exception was thrown.  Halting execution.\nShutting down workbench.\n\nError executing deployment: java.lang.IllegalArgumentException. Error is Could n\not find runtime ..\njava.lang.IllegalArgumentException: Could not find runtime .\n        at org.eclipse.wst.common.project.facet.core.runtime.internal.RuntimeMan\nagerImpl.getRuntime(RuntimeManagerImpl.java:186)\n        at org.eclipse.wst.common.project.facet.core.runtime.RuntimeManager.getR\nuntime(RuntimeManager.java:125)\n        at org.eclipse.jst.j2ee.internal.earcreation.EarComponentCreationFacetOp\neration.execute(EarComponentCreationFacetOperation.java:56)\n        at org.eclipse.wst.common.frameworks.internal.datamodel.ExtendableOperat\nionImpl.doExecute(ExtendableOperationImpl.java:163)\n        at org.eclipse.wst.common.frameworks.internal.datamodel.ExtendableOperat\nionImpl$1.run(ExtendableOperationImpl.java:131)\n        at org.eclipse.core.internal.resources.Workspace.run(Workspace.java:1719\n)\n        at org.eclipse.core.internal.resources.Workspace.run(Workspace.java:1739\n)\n        at org.eclipse.wst.common.frameworks.internal.datamodel.ExtendableOperat\nionImpl.execute(ExtendableOperationImpl.java:137)\n        at org.eclipse.jst.j2ee.internal.archive.operations.J2EEArtifactImportOp\neration.createVirtualComponent(J2EEArtifactImportOperation.java:78)\n        at org.eclipse.jst.j2ee.internal.archive.operations.J2EEArtifactImportOp\neration.doExecute(J2EEArtifactImportOperation.java:66)\n        at org.eclipse.jst.j2ee.internal.archive.operations.EARComponentImportOp\neration.doExecute(EARComponentImportOperation.java:59)\n        at org.eclipse.jst.j2ee.internal.archive.operations.J2EEArtifactImportOp\neration.execute(J2EEArtifactImportOperation.java:55)\n        at org.eclipse.wst.common.frameworks.internal.datamodel.ExtendableOperat\nionImpl.doExecute(ExtendableOperationImpl.java:163)\n        at org.eclipse.wst.common.frameworks.internal.datamodel.ExtendableOperat\nionImpl$1.run(ExtendableOperationImpl.java:131)\n        at org.eclipse.core.internal.resources.Workspace.run(Workspace.java:1719\n)\n        at org.eclipse.core.internal.resources.Workspace.run(Workspace.java:1739\n)\n        at org.eclipse.wst.common.frameworks.internal.datamodel.ExtendableOperat\nionImpl.execute(ExtendableOperationImpl.java:137)\n        at com.ibm.etools.ejbdeploy.batch.plugin.BatchExtension.importEar(BatchE\nxtension.java:949)\n        at com.ibm.etools.ejbdeploy.batch.plugin.BatchExtension.runEarDeploy(Bat\nchExtension.java:322)\n        at com.ibm.etools.ejbdeploy.batch.plugin.BatchExtension.access$0(BatchEx\ntension.java:317)\n        at com.ibm.etools.ejbdeploy.batch.plugin.BatchExtension$RunDeploy.run(Ba\ntchExtension.java:300)\n        at org.eclipse.core.internal.resources.Workspace.run(Workspace.java:1719\n)\n        at org.eclipse.core.internal.resources.Workspace.run(Workspace.java:1739\n)\n        at com.ibm.etools.ejbdeploy.batch.plugin.BatchExtension$RunDeploy.execut\ne(BatchExtension.java:284)\n        at com.ibm.etools.ejbdeploy.batch.plugin.BatchExtension.run(BatchExtensi\non.java:247)\n        at org.eclipse.core.internal.runtime.PlatformActivator$1.run(PlatformAct\nivator.java:226)\n        at org.eclipse.core.runtime.adaptor.EclipseStarter.run(EclipseStarter.ja\nva:376)\n        at sun.reflect.NativeMethodAccessorImpl.invoke0(Native Method)\n        at sun.reflect.NativeMethodAccessorImpl.invoke(NativeMethodAccessorImpl.\njava:64)\n        at sun.reflect.DelegatingMethodAccessorImpl.invoke(DelegatingMethodAcces\nsorImpl.java:43)\n        at java.lang.reflect.Method.invoke(Method.java:615)\n        at com.ibm.etools.ejbdeploy.batch.impl.BootLoaderLoader.run(BootLoaderLo\nader.java:272)\n        at com.ibm.etools.ejbdeploy.batch.impl.BatchDeploy.execute(BatchDeploy.j\nava:99)\n        at com.ibm.etools.ejbdeploy.EJBDeploy.execute(EJBDeploy.java:83)\n        at com.ibm.etools.ejbdeploy.EJBDeploy.main(EJBDeploy.java:313)\nEJBDeploy level: o0602.91\n\nD:\\EJBDeployX602.91\\itp\u003eejbdeploy d:\\tests\\NameTestEAR.ear working nameout.ear\nStarting workbench.\nframework search path: d:\\EJBDeployX602.91\\itp\\plugins\nCreating the project.\njava.lang.IllegalArgumentException: Could not find runtime .\n        at org.eclipse.wst.common.project.facet.core.runtime.internal.RuntimeMan\nagerImpl.getRuntime(RuntimeManagerImpl.java:186)\n        at org.eclipse.wst.common.project.facet.core.runtime.RuntimeManager.getR\nuntime(RuntimeManager.java:125)\n        at org.eclipse.jst.j2ee.internal.earcreation.EarComponentCreationFacetOp\neration.execute(EarComponentCreationFacetOperation.java:56)\n        at org.eclipse.wst.common.frameworks.internal.datamodel.ExtendableOperat\nionImpl.doExecute(ExtendableOperationImpl.java:163)\n        at org.eclipse.wst.common.frameworks.internal.datamodel.ExtendableOperat\nionImpl$1.run(ExtendableOperationImpl.java:131)\n        at org.eclipse.core.internal.resources.Workspace.run(Workspace.java:1719\n)\n        at org.eclipse.core.internal.resources.Workspace.run(Workspace.java:1739\n)\n        at org.eclipse.wst.common.frameworks.internal.datamodel.ExtendableOperat\nionImpl.execute(ExtendableOperationImpl.java:137)\n        at org.eclipse.jst.j2ee.internal.archive.operations.J2EEArtifactImportOp\neration.createVirtualComponent(J2EEArtifactImportOperation.java:78)\n        at org.eclipse.jst.j2ee.internal.archive.operations.J2EEArtifactImportOp\neration.doExecute(J2EEArtifactImportOperation.java:66)\n        at org.eclipse.jst.j2ee.internal.archive.operations.EARComponentImportOp\neration.doExecute(EARComponentImportOperation.java:59)\n        at org.eclipse.jst.j2ee.internal.archive.operations.J2EEArtifactImportOp\neration.execute(J2EEArtifactImportOperation.java:55)\n        at org.eclipse.wst.common.frameworks.internal.datamodel.ExtendableOperat\nionImpl.doExecute(ExtendableOperationImpl.java:163)\n        at org.eclipse.wst.common.frameworks.internal.datamodel.ExtendableOperat\nionImpl$1.run(ExtendableOperationImpl.java:131)\n        at org.eclipse.core.internal.resources.Workspace.run(Workspace.java:1719\n)\n        at org.eclipse.core.internal.resources.Workspace.run(Workspace.java:1739\n)\n        at org.eclipse.wst.common.frameworks.internal.datamodel.ExtendableOperat\nionImpl.execute(ExtendableOperationImpl.java:137)\n        at com.ibm.etools.ejbdeploy.batch.plugin.BatchExtension.importEar(BatchE\nxtension.java:949)\n        at com.ibm.etools.ejbdeploy.batch.plugin.BatchExtension.runEarDeploy(Bat\nchExtension.java:322)\n        at com.ibm.etools.ejbdeploy.batch.plugin.BatchExtension.access$0(BatchEx\ntension.java:317)\n        at com.ibm.etools.ejbdeploy.batch.plugin.BatchExtension$RunDeploy.run(Ba\ntchExtension.java:300)\n        at org.eclipse.core.internal.resources.Workspace.run(Workspace.java:1719\n)\n        at org.eclipse.core.internal.resources.Workspace.run(Workspace.java:1739\n)\n        at com.ibm.etools.ejbdeploy.batch.plugin.BatchExtension$RunDeploy.execut\ne(BatchExtension.java:284)\n        at com.ibm.etools.ejbdeploy.batch.plugin.BatchExtension.run(BatchExtensi\non.java:247)\n        at org.eclipse.core.internal.runtime.PlatformActivator$1.run(PlatformAct\nivator.java:226)\n        at org.eclipse.core.runtime.adaptor.EclipseStarter.run(EclipseStarter.ja\nva:376)\n        at sun.reflect.NativeMethodAccessorImpl.invoke0(Native Method)\n        at sun.reflect.NativeMethodAccessorImpl.invoke(NativeMethodAccessorImpl.\njava:64)\n        at sun.reflect.DelegatingMethodAccessorImpl.invoke(DelegatingMethodAcces\nsorImpl.java:43)\n        at java.lang.reflect.Method.invoke(Method.java:615)\n        at com.ibm.etools.ejbdeploy.batch.impl.BootLoaderLoader.run(BootLoaderLo\nader.java:272)\n        at com.ibm.etools.ejbdeploy.batch.impl.BatchDeploy.execute(BatchDeploy.j\nava:99)\n        at com.ibm.etools.ejbdeploy.EJBDeploy.execute(EJBDeploy.java:83)\n        at com.ibm.etools.ejbdeploy.EJBDeploy.main(EJBDeploy.java:313)\n[*Error] An unexpected exception was thrown.  Halting execution.\nShutting down workbench.\n\nError executing deployment: java.lang.IllegalArgumentException. Error is Could n\not find runtime ..\njava.lang.IllegalArgumentException: Could not find runtime .\n        at org.eclipse.wst.common.project.facet.core.runtime.internal.RuntimeMan\nagerImpl.getRuntime(RuntimeManagerImpl.java:186)\n        at org.eclipse.wst.common.project.facet.core.runtime.RuntimeManager.getR\nuntime(RuntimeManager.java:125)\n        at org.eclipse.jst.j2ee.internal.earcreation.EarComponentCreationFacetOp\neration.execute(EarComponentCreationFacetOperation.java:56)\n        at org.eclipse.wst.common.frameworks.internal.datamodel.ExtendableOperat\nionImpl.doExecute(ExtendableOperationImpl.java:163)\n        at org.eclipse.wst.common.frameworks.internal.datamodel.ExtendableOperat\nionImpl$1.run(ExtendableOperationImpl.java:131)\n        at org.eclipse.core.internal.resources.Workspace.run(Workspace.java:1719\n)\n        at org.eclipse.core.internal.resources.Workspace.run(Workspace.java:1739\n)\n        at org.eclipse.wst.common.frameworks.internal.datamodel.ExtendableOperat\nionImpl.execute(ExtendableOperationImpl.java:137)\n        at org.eclipse.jst.j2ee.internal.archive.operations.J2EEArtifactImportOp\neration.createVirtualComponent(J2EEArtifactImportOperation.java:78)\n        at org.eclipse.jst.j2ee.internal.archive.operations.J2EEArtifactImportOp\neration.doExecute(J2EEArtifactImportOperation.java:66)\n        at org.eclipse.jst.j2ee.internal.archive.operations.EARComponentImportOp\neration.doExecute(EARComponentImportOperation.java:59)\n        at org.eclipse.jst.j2ee.internal.archive.operations.J2EEArtifactImportOp\neration.execute(J2EEArtifactImportOperation.java:55)\n        at org.eclipse.wst.common.frameworks.internal.datamodel.ExtendableOperat\nionImpl.doExecute(ExtendableOperationImpl.java:163)\n        at org.eclipse.wst.common.frameworks.internal.datamodel.ExtendableOperat\nionImpl$1.run(ExtendableOperationImpl.java:131)\n        at org.eclipse.core.internal.resources.Workspace.run(Workspace.java:1719\n)\n        at org.eclipse.core.internal.resources.Workspace.run(Workspace.java:1739\n)\n        at org.eclipse.wst.common.frameworks.internal.datamodel.ExtendableOperat\nionImpl.execute(ExtendableOperationImpl.java:137)\n        at com.ibm.etools.ejbdeploy.batch.plugin.BatchExtension.importEar(BatchE\nxtension.java:949)\n        at com.ibm.etools.ejbdeploy.batch.plugin.BatchExtension.runEarDeploy(Bat\nchExtension.java:322)\n        at com.ibm.etools.ejbdeploy.batch.plugin.BatchExtension.access$0(BatchEx\ntension.java:317)\n        at com.ibm.etools.ejbdeploy.batch.plugin.BatchExtension$RunDeploy.run(Ba\ntchExtension.java:300)\n        at org.eclipse.core.internal.resources.Workspace.run(Workspace.java:1719\n)\n        at org.eclipse.core.internal.resources.Workspace.run(Workspace.java:1739\n)\n        at com.ibm.etools.ejbdeploy.batch.plugin.BatchExtension$RunDeploy.execut\ne(BatchExtension.java:284)\n        at com.ibm.etools.ejbdeploy.batch.plugin.BatchExtension.run(BatchExtensi\non.java:247)\n        at org.eclipse.core.internal.runtime.PlatformActivator$1.run(PlatformAct\nivator.java:226)\n        at org.eclipse.core.runtime.adaptor.EclipseStarter.run(EclipseStarter.ja\nva:376)\n        at sun.reflect.NativeMethodAccessorImpl.invoke0(Native Method)\n        at sun.reflect.NativeMethodAccessorImpl.invoke(NativeMethodAccessorImpl.\njava:64)\n        at sun.reflect.DelegatingMethodAccessorImpl.invoke(DelegatingMethodAcces\nsorImpl.java:43)\n        at java.lang.reflect.Method.invoke(Method.java:615)\n        at com.ibm.etools.ejbdeploy.batch.impl.BootLoaderLoader.run(BootLoaderLo\nader.java:272)\n        at com.ibm.etools.ejbdeploy.batch.impl.BatchDeploy.execute(BatchDeploy.j\nava:99)\n        at com.ibm.etools.ejbdeploy.EJBDeploy.execute(EJBDeploy.java:83)\n        at com.ibm.etools.ejbdeploy.EJBDeploy.main(EJBDeploy.java:313)",
    "This is fixed for the 1/13/06 WTP 1.0.1 committers build.  \n\nThe operation will now allow a null runtime as in 1.0.0.",
    "OK"
  ],
  "commentCreationDates": [
    "2006-01-12T17:26:00+01:00",
    "2006-01-12T17:58:58+01:00",
    "2006-06-13T17:29:04+02:00"
  ],
  "traces": [
    {
      "exceptionType": "java.lang.IllegalArgumentException",
      "message": "Could not find runtime .",
      "elements": [
        {
          "method": "org.eclipse.wst.common.project.facet.core.runtime.internal.RuntimeManagerImpl.getRuntime",
          "source": "RuntimeManagerImpl.java:186"
        },
        {
          "method": "org.eclipse.wst.common.project.facet.core.runtime.RuntimeManager.getRuntime",
          "source": "RuntimeManager.java:125"
        },
        {
          "method": "org.eclipse.jst.j2ee.internal.earcreation.EarComponentCreationFacetOperation.execute",
          "source": "EarComponentCreationFacetOperation.java:56"
        },
        {
          "method": "org.eclipse.wst.common.frameworks.internal.datamodel.ExtendableOperationImpl.doExecute",
          "source": "ExtendableOperationImpl.java:163"
        },
        {
          "method": "org.eclipse.wst.common.frameworks.internal.datamodel.ExtendableOperationImpl$1.run",
          "source": "ExtendableOperationImpl.java:131"
        },
        {
          "method": "org.eclipse.core.internal.resources.Workspace.run",
          "source": "Workspace.java:1719 "
        },
        {
          "method": "org.eclipse.core.internal.resources.Workspace.run",
          "source": "Workspace.java:1739 "
        },
        {
          "method": "org.eclipse.wst.common.frameworks.internal.datamodel.ExtendableOperationImpl.execute",
          "source": "ExtendableOperationImpl.java:137"
        },
        {
          "method": "org.eclipse.jst.j2ee.internal.archive.operations.J2EEArtifactImportOperation.createVirtualComponent",
          "source": "J2EEArtifactImportOperation.java:78"
        },
        {
          "method": "org.eclipse.jst.j2ee.internal.archive.operations.J2EEArtifactImportOperation.doExecute",
          "source": "J2EEArtifactImportOperation.java:66"
        },
        {
          "method": "org.eclipse.jst.j2ee.internal.archive.operations.EARComponentImportOperation.doExecute",
          "source": "EARComponentImportOperation.java:59"
        },
        {
          "method": "org.eclipse.jst.j2ee.internal.archive.operations.J2EEArtifactImportOperation.execute",
          "source": "J2EEArtifactImportOperation.java:55"
        },
        {
          "method": "org.eclipse.wst.common.frameworks.internal.datamodel.ExtendableOperationImpl.doExecute",
          "source": "ExtendableOperationImpl.java:163"
        },
        {
          "method": "org.eclipse.wst.common.frameworks.internal.datamodel.ExtendableOperationImpl$1.run",
          "source": "ExtendableOperationImpl.java:131"
        },
        {
          "method": "org.eclipse.core.internal.resources.Workspace.run",
          "source": "Workspace.java:1719 "
        },
        {
          "method": "org.eclipse.core.internal.resources.Workspace.run",
          "source": "Workspace.java:1739 "
        },
        {
          "method": "org.eclipse.wst.common.frameworks.internal.datamodel.ExtendableOperationImpl.execute",
          "source": "ExtendableOperationImpl.java:137"
        },
        {
          "method": "com.ibm.etools.ejbdeploy.batch.plugin.BatchExtension.importEar",
          "source": "BatchE xtension.java:949"
        },
        {
          "method": "com.ibm.etools.ejbdeploy.batch.plugin.BatchExtension.runEarDeploy",
          "source": "Bat chExtension.java:322"
        },
        {
          "method": "com.ibm.etools.ejbdeploy.batch.plugin.BatchExtension.access$0",
          "source": "BatchEx tension.java:317"
        },
        {
          "method": "com.ibm.etools.ejbdeploy.batch.plugin.BatchExtension$RunDeploy.run",
          "source": "Ba tchExtension.java:300"
        },
        {
          "method": "org.eclipse.core.internal.resources.Workspace.run",
          "source": "Workspace.java:1719 "
        },
        {
          "method": "org.eclipse.core.internal.resources.Workspace.run",
          "source": "Workspace.java:1739 "
        },
        {
          "method": "com.ibm.etools.ejbdeploy.batch.plugin.BatchExtension$RunDeploy.execute",
          "source": "BatchExtension.java:284"
        },
        {
          "method": "com.ibm.etools.ejbdeploy.batch.plugin.BatchExtension.run",
          "source": "BatchExtensi on.java:247"
        },
        {
          "method": "org.eclipse.core.internal.runtime.PlatformActivator$1.run",
          "source": "PlatformAct ivator.java:226"
        },
        {
          "method": "org.eclipse.core.runtime.adaptor.EclipseStarter.run",
          "source": "EclipseStarter.ja va:376"
        },
        {
          "method": "sun.reflect.NativeMethodAccessorImpl.invoke0",
          "source": "Native Method"
        },
        {
          "method": "sun.reflect.NativeMethodAccessorImpl.invoke",
          "source": "NativeMethodAccessorImpl. java:64"
        },
        {
          "method": "sun.reflect.DelegatingMethodAccessorImpl.invoke",
          "source": "DelegatingMethodAcces sorImpl.java:43"
        },
        {
          "method": "java.lang.reflect.Method.invoke",
          "source": "Method.java:615"
        },
        {
          "method": "com.ibm.etools.ejbdeploy.batch.impl.BootLoaderLoader.run",
          "source": "BootLoaderLo ader.java:272"
        },
        {
          "method": "com.ibm.etools.ejbdeploy.batch.impl.BatchDeploy.execute",
          "source": "BatchDeploy.j ava:99"
        },
        {
          "method": "com.ibm.etools.ejbdeploy.EJBDeploy.execute",
          "source": "EJBDeploy.java:83"
        },
        {
          "method": "com.ibm.etools.ejbdeploy.EJBDeploy.main",
          "source": "EJBDeploy.java:313"
        }
      ],
      "number": 0,
      "commentIndex": 0,
      "bugId": "123634",
      "date": "2006-01-12T17:26:00+01:00",
      "product": "Web Tools",
      "component": "jst.j2ee",
      "severity": "blocker"
    },
    {
      "exceptionType": "java.lang.IllegalArgumentException",
      "message": "Could not find runtime .",
      "elements": [
        {
          "method": "org.eclipse.wst.common.project.facet.core.runtime.internal.RuntimeManagerImpl.getRuntime",
          "source": "RuntimeManagerImpl.java:186"
        },
        {
          "method": "org.eclipse.wst.common.project.facet.core.runtime.RuntimeManager.getRuntime",
          "source": "RuntimeManager.java:125"
        },
        {
          "method": "org.eclipse.jst.j2ee.internal.earcreation.EarComponentCreationFacetOperation.execute",
          "source": "EarComponentCreationFacetOperation.java:56"
        },
        {
          "method": "org.eclipse.wst.common.frameworks.internal.datamodel.ExtendableOperationImpl.doExecute",
          "source": "ExtendableOperationImpl.java:163"
        },
        {
          "method": "org.eclipse.wst.common.frameworks.internal.datamodel.ExtendableOperationImpl$1.run",
          "source": "ExtendableOperationImpl.java:131"
        },
        {
          "method": "org.eclipse.core.internal.resources.Workspace.run",
          "source": "Workspace.java:1719 "
        },
        {
          "method": "org.eclipse.core.internal.resources.Workspace.run",
          "source": "Workspace.java:1739 "
        },
        {
          "method": "org.eclipse.wst.common.frameworks.internal.datamodel.ExtendableOperationImpl.execute",
          "source": "ExtendableOperationImpl.java:137"
        },
        {
          "method": "org.eclipse.jst.j2ee.internal.archive.operations.J2EEArtifactImportOperation.createVirtualComponent",
          "source": "J2EEArtifactImportOperation.java:78"
        },
        {
          "method": "org.eclipse.jst.j2ee.internal.archive.operations.J2EEArtifactImportOperation.doExecute",
          "source": "J2EEArtifactImportOperation.java:66"
        },
        {
          "method": "org.eclipse.jst.j2ee.internal.archive.operations.EARComponentImportOperation.doExecute",
          "source": "EARComponentImportOperation.java:59"
        },
        {
          "method": "org.eclipse.jst.j2ee.internal.archive.operations.J2EEArtifactImportOperation.execute",
          "source": "J2EEArtifactImportOperation.java:55"
        },
        {
          "method": "org.eclipse.wst.common.frameworks.internal.datamodel.ExtendableOperationImpl.doExecute",
          "source": "ExtendableOperationImpl.java:163"
        },
        {
          "method": "org.eclipse.wst.common.frameworks.internal.datamodel.ExtendableOperationImpl$1.run",
          "source": "ExtendableOperationImpl.java:131"
        },
        {
          "method": "org.eclipse.core.internal.resources.Workspace.run",
          "source": "Workspace.java:1719 "
        },
        {
          "method": "org.eclipse.core.internal.resources.Workspace.run",
          "source": "Workspace.java:1739 "
        },
        {
          "method": "org.eclipse.wst.common.frameworks.internal.datamodel.ExtendableOperationImpl.execute",
          "source": "ExtendableOperationImpl.java:137"
        },
        {
          "method": "com.ibm.etools.ejbdeploy.batch.plugin.BatchExtension.importEar",
          "source": "BatchE xtension.java:949"
        },
        {
          "method": "com.ibm.etools.ejbdeploy.batch.plugin.BatchExtension.runEarDeploy",
          "source": "Bat chExtension.java:322"
        },
        {
          "method": "com.ibm.etools.ejbdeploy.batch.plugin.BatchExtension.access$0",
          "source": "BatchEx tension.java:317"
        },
        {
          "method": "com.ibm.etools.ejbdeploy.batch.plugin.BatchExtension$RunDeploy.run",
          "source": "Ba tchExtension.java:300"
        },
        {
          "method": "org.eclipse.core.internal.resources.Workspace.run",
          "source": "Workspace.java:1719 "
        },
        {
          "method": "org.eclipse.core.internal.resources.Workspace.run",
          "source": "Workspace.java:1739 "
        },
        {
          "method": "com.ibm.etools.ejbdeploy.batch.plugin.BatchExtension$RunDeploy.execute",
          "source": "BatchExtension.java:284"
        },
        {
          "method": "com.ibm.etools.ejbdeploy.batch.plugin.BatchExtension.run",
          "source": "BatchExtensi on.java:247"
        },
        {
          "method": "org.eclipse.core.internal.runtime.PlatformActivator$1.run",
          "source": "PlatformAct ivator.java:226"
        },
        {
          "method": "org.eclipse.core.runtime.adaptor.EclipseStarter.run",
          "source": "EclipseStarter.ja va:376"
        },
        {
          "method": "sun.reflect.NativeMethodAccessorImpl.invoke0",
          "source": "Native Method"
        },
        {
          "method": "sun.reflect.NativeMethodAccessorImpl.invoke",
          "source": "NativeMethodAccessorImpl. java:64"
        },
        {
          "method": "sun.reflect.DelegatingMethodAccessorImpl.invoke",
          "source": "DelegatingMethodAcces sorImpl.java:43"
        },
        {
          "method": "java.lang.reflect.Method.invoke",
          "source": "Method.java:615"
        },
        {
          "method": "com.ibm.etools.ejbdeploy.batch.impl.BootLoaderLoader.run",
          "source": "BootLoaderLo ader.java:272"
        },
        {
          "method": "com.ibm.etools.ejbdeploy.batch.impl.BatchDeploy.execute",
          "source": "BatchDeploy.j ava:99"
        },
        {
          "method": "com.ibm.etools.ejbdeploy.EJBDeploy.execute",
          "source": "EJBDeploy.java:83"
        },
        {
          "method": "com.ibm.etools.ejbdeploy.EJBDeploy.main",
          "source": "EJBDeploy.java:313"
        }
      ],
      "number": 1,
      "commentIndex": 0,
      "bugId": "123634",
      "date": "2006-01-12T17:26:00+01:00",
      "product": "Web Tools",
      "component": "jst.j2ee",
      "severity": "blocker"
    },
    {
      "exceptionType": "java.lang.IllegalArgumentException",
      "message": "Could not find runtime .",
      "elements": [
        {
          "method": "org.eclipse.wst.common.project.facet.core.runtime.internal.RuntimeManagerImpl.getRuntime",
          "source": "RuntimeManagerImpl.java:186"
        },
        {
          "method": "org.eclipse.wst.common.project.facet.core.runtime.RuntimeManager.getRuntime",
          "source": "RuntimeManager.java:125"
        },
        {
          "method": "org.eclipse.jst.j2ee.internal.earcreation.EarComponentCreationFacetOperation.execute",
          "source": "EarComponentCreationFacetOperation.java:56"
        },
        {
          "method": "org.eclipse.wst.common.frameworks.internal.datamodel.ExtendableOperationImpl.doExecute",
          "source": "ExtendableOperationImpl.java:163"
        },
        {
          "method": "org.eclipse.wst.common.frameworks.internal.datamodel.ExtendableOperationImpl$1.run",
          "source": "ExtendableOperationImpl.java:131"
        },
        {
          "method": "org.eclipse.core.internal.resources.Workspace.run",
          "source": "Workspace.java:1719 "
        },
        {
          "method": "org.eclipse.core.internal.resources.Workspace.run",
          "source": "Workspace.java:1739 "
        },
        {
          "method": "org.eclipse.wst.common.frameworks.internal.datamodel.ExtendableOperationImpl.execute",
          "source": "ExtendableOperationImpl.java:137"
        },
        {
          "method": "org.eclipse.jst.j2ee.internal.archive.operations.J2EEArtifactImportOperation.createVirtualComponent",
          "source": "J2EEArtifactImportOperation.java:78"
        },
        {
          "method": "org.eclipse.jst.j2ee.internal.archive.operations.J2EEArtifactImportOperation.doExecute",
          "source": "J2EEArtifactImportOperation.java:66"
        },
        {
          "method": "org.eclipse.jst.j2ee.internal.archive.operations.EARComponentImportOperation.doExecute",
          "source": "EARComponentImportOperation.java:59"
        },
        {
          "method": "org.eclipse.jst.j2ee.internal.archive.operations.J2EEArtifactImportOperation.execute",
          "source": "J2EEArtifactImportOperation.java:55"
        },
        {
          "method": "org.eclipse.wst.common.frameworks.internal.datamodel.ExtendableOperationImpl.doExecute",
          "source": "ExtendableOperationImpl.java:163"
        },
        {
          "method": "org.eclipse.wst.common.frameworks.internal.datamodel.ExtendableOperationImpl$1.run",
          "source": "ExtendableOperationImpl.java:131"
        },
        {
          "method": "org.eclipse.core.internal.resources.Workspace.run",
          "source": "Workspace.java:1719 "
        },
        {
          "method": "org.eclipse.core.internal.resources.Workspace.run",
          "source": "Workspace.java:1739 "
        },
        {
          "method": "org.eclipse.wst.common.frameworks.internal.datamodel.ExtendableOperationImpl.execute",
          "source": "ExtendableOperationImpl.java:137"
        },
        {
          "method": "com.ibm.etools.ejbdeploy.batch.plugin.BatchExtension.importEar",
          "source": "BatchE xtension.java:949"
        },
        {
          "method": "com.ibm.etools.ejbdeploy.batch.plugin.BatchExtension.runEarDeploy",
          "source": "Bat chExtension.java:322"
        },
        {
          "method": "com.ibm.etools.ejbdeploy.batch.plugin.BatchExtension.access$0",
          "source": "BatchEx tension.java:317"
        },
        {
          "method": "com.ibm.etools.ejbdeploy.batch.plugin.BatchExtension$RunDeploy.run",
          "source": "Ba tchExtension.java:300"
        },
        {
          "method": "org.eclipse.core.internal.resources.Workspace.run",
          "source": "Workspace.java:1719 "
        },
        {
          "method": "org.eclipse.core.internal.resources.Workspace.run",
          "source": "Workspace.java:1739 "
        },
        {
          "method": "com.ibm.etools.ejbdeploy.batch.plugin.BatchExtension$RunDeploy.execute",
          "source": "BatchExtension.java:284"
        },
        {
          "method": "com.ibm.etools.ejbdeploy.batch.plugin.BatchExtension.run",
          "source": "BatchExtensi on.java:247"
        },
        {
          "method": "org.eclipse.core.internal.runtime.PlatformActivator$1.run",
          "source": "PlatformAct ivator.java:226"
        },
        {
          "method": "org.eclipse.core.runtime.adaptor.EclipseStarter.run",
          "source": "EclipseStarter.ja va:376"
        },
        {
          "method": "sun.reflect.NativeMethodAccessorImpl.invoke0",
          "source": "Native Method"
        },
        {
          "method": "sun.reflect.NativeMethodAccessorImpl.invoke",
          "source": "NativeMethodAccessorImpl. java:64"
        },
        {
          "method": "sun.reflect.DelegatingMethodAccessorImpl.invoke",
          "source": "DelegatingMethodAcces sorImpl.java:43"
        },
        {
          "method": "java.lang.reflect.Method.invoke",
          "source": "Method.java:615"
        },
        {
          "method": "com.ibm.etools.ejbdeploy.batch.impl.BootLoaderLoader.run",
          "source": "BootLoaderLo ader.java:272"
        },
        {
          "method": "com.ibm.etools.ejbdeploy.batch.impl.BatchDeploy.execute",
          "source": "BatchDeploy.j ava:99"
        },
        {
          "method": "com.ibm.etools.ejbdeploy.EJBDeploy.execute",
          "source": "EJBDeploy.java:83"
        },
        {
          "method": "com.ibm.etools.ejbdeploy.EJBDeploy.main",
          "source": "EJBDeploy.java:313"
        }
      ],
      "number": 2,
      "commentIndex": 0,
      "bugId": "123634",
      "date": "2006-01-12T17:26:00+01:00",
      "product": "Web Tools",
      "component": "jst.j2ee",
      "severity": "blocker"
    },
    {
      "exceptionType": "java.lang.IllegalArgumentException",
      "message": "Could not find runtime .",
      "elements": [
        {
          "method": "org.eclipse.wst.common.project.facet.core.runtime.internal.RuntimeManagerImpl.getRuntime",
          "source": "RuntimeManagerImpl.java:186"
        },
        {
          "method": "org.eclipse.wst.common.project.facet.core.runtime.RuntimeManager.getRuntime",
          "source": "RuntimeManager.java:125"
        },
        {
          "method": "org.eclipse.jst.j2ee.internal.earcreation.EarComponentCreationFacetOperation.execute",
          "source": "EarComponentCreationFacetOperation.java:56"
        },
        {
          "method": "org.eclipse.wst.common.frameworks.internal.datamodel.ExtendableOperationImpl.doExecute",
          "source": "ExtendableOperationImpl.java:163"
        },
        {
          "method": "org.eclipse.wst.common.frameworks.internal.datamodel.ExtendableOperationImpl$1.run",
          "source": "ExtendableOperationImpl.java:131"
        },
        {
          "method": "org.eclipse.core.internal.resources.Workspace.run",
          "source": "Workspace.java:1719 "
        },
        {
          "method": "org.eclipse.core.internal.resources.Workspace.run",
          "source": "Workspace.java:1739 "
        },
        {
          "method": "org.eclipse.wst.common.frameworks.internal.datamodel.ExtendableOperationImpl.execute",
          "source": "ExtendableOperationImpl.java:137"
        },
        {
          "method": "org.eclipse.jst.j2ee.internal.archive.operations.J2EEArtifactImportOperation.createVirtualComponent",
          "source": "J2EEArtifactImportOperation.java:78"
        },
        {
          "method": "org.eclipse.jst.j2ee.internal.archive.operations.J2EEArtifactImportOperation.doExecute",
          "source": "J2EEArtifactImportOperation.java:66"
        },
        {
          "method": "org.eclipse.jst.j2ee.internal.archive.operations.EARComponentImportOperation.doExecute",
          "source": "EARComponentImportOperation.java:59"
        },
        {
          "method": "org.eclipse.jst.j2ee.internal.archive.operations.J2EEArtifactImportOperation.execute",
          "source": "J2EEArtifactImportOperation.java:55"
        },
        {
          "method": "org.eclipse.wst.common.frameworks.internal.datamodel.ExtendableOperationImpl.doExecute",
          "source": "ExtendableOperationImpl.java:163"
        },
        {
          "method": "org.eclipse.wst.common.frameworks.internal.datamodel.ExtendableOperationImpl$1.run",
          "source": "ExtendableOperationImpl.java:131"
        },
        {
          "method": "org.eclipse.core.internal.resources.Workspace.run",
          "source": "Workspace.java:1719 "
        },
        {
          "method": "org.eclipse.core.internal.resources.Workspace.run",
          "source": "Workspace.java:1739 "
        },
        {
          "method": "org.eclipse.wst.common.frameworks.internal.datamodel.ExtendableOperationImpl.execute",
          "source": "ExtendableOperationImpl.java:137"
        },
        {
          "method": "com.ibm.etools.ejbdeploy.batch.plugin.BatchExtension.importEar",
          "source": "BatchE xtension.java:949"
        },
        {
          "method": "com.ibm.etools.ejbdeploy.batch.plugin.BatchExtension.runEarDeploy",
          "source": "Bat chExtension.java:322"
        },
        {
          "method": "com.ibm.etools.ejbdeploy.batch.plugin.BatchExtension.access$0",
          "source": "BatchEx tension.java:317"
        },
        {
          "method": "com.ibm.etools.ejbdeploy.batch.plugin.BatchExtension$RunDeploy.run",
          "source": "Ba tchExtension.java:300"
        },
        {
          "method": "org.eclipse.core.internal.resources.Workspace.run",
          "source": "Workspace.java:1719 "
        },
        {
          "method": "org.eclipse.core.internal.resources.Workspace.run",
          "source": "Workspace.java:1739 "
        },
        {
          "method": "com.ibm.etools.ejbdeploy.batch.plugin.BatchExtension$RunDeploy.execute",
          "source": "BatchExtension.java:284"
        },
        {
          "method": "com.ibm.etools.ejbdeploy.batch.plugin.BatchExtension.run",
          "source": "BatchExtensi on.java:247"
        },
        {
          "method": "org.eclipse.core.internal.runtime.PlatformActivator$1.run",
          "source": "PlatformAct ivator.java:226"
        },
        {
          "method": "org.eclipse.core.runtime.adaptor.EclipseStarter.run",
          "source": "EclipseStarter.ja va:376"
        },
        {
          "method": "sun.reflect.NativeMethodAccessorImpl.invoke0",
          "source": "Native Method"
        },
        {
          "method": "sun.reflect.NativeMethodAccessorImpl.invoke",
          "source": "NativeMethodAccessorImpl. java:64"
        },
        {
          "method": "sun.reflect.DelegatingMethodAccessorImpl.invoke",
          "source": "DelegatingMethodAcces sorImpl.java:43"
        },
        {
          "method": "java.lang.reflect.Method.invoke",
          "source": "Method.java:615"
        },
        {
          "method": "com.ibm.etools.ejbdeploy.batch.impl.BootLoaderLoader.run",
          "source": "BootLoaderLo ader.java:272"
        },
        {
          "method": "com.ibm.etools.ejbdeploy.batch.impl.BatchDeploy.execute",
          "source": "BatchDeploy.j ava:99"
        },
        {
          "method": "com.ibm.etools.ejbdeploy.EJBDeploy.execute",
          "source": "EJBDeploy.java:83"
        },
        {
          "method": "com.ibm.etools.ejbdeploy.EJBDeploy.main",
          "source": "EJBDeploy.java:313"
        }
      ],
      "number": 3,
      "commentIndex": 0,
      "bugId": "123634",
      "date": "2006-01-12T17:26:00+01:00",
      "product": "Web Tools",
      "component": "jst.j2ee",
      "severity": "blocker"
    }
  ],
  "groupId": "123634",
  "bugId": "123634",
  "date": "2006-01-12T17:26:00+01:00",
  "product": "Web Tools",
  "component": "jst.j2ee",
  "severity": "blocker"
}