{
  "comments": [
    "Hi,\n\nToday I tried to follow your web service tutorial at \n\n\"http://www.eclipse.org/webtools/community/tutorials/BottomUpWebService/BottomUpWebService.html\". It works fine unless I uncheck \"Run modules directly from workspace\" of the Tomcat configuration file.\n\nHere is what I did in details:\n\n1. Installed wtp-all-in-one-sdk-1.0-win32.zip\n2. Installed jakarta-tomcat-5.0.28.zip (core edition)\n3. Changed Eclipse Preferences:\n     Java - Build Path: selected \"Folder\" radio button\n     Java - JRE\u0027s     : added j2sdk1.4.2_08\n4. Opened the server view and added Tomcat 5.0.28\n5. Changed Tomcat server configuration file\n     unchecked: Run modules directly from workspace\n6. Created dynamic web project \"ConverterProj\"\n6.1 Agreed to cache \"web-app_2_4.xsd\"\n6.2 Agreed to open J2EE perspective\n7. Changed project properties:\n     Selected Tomcat 5.0.28 server as the default server\n8. Created package \"wtp\"\n9. Added class \"Converter\" to \"wtp\" package\n10. Attempted to create the web service\n10.1 Selected \"Converter.java\"\n10.2 Opened File -\u003e New -\u003e Other... -\u003e Web Services -\u003e Web Service\n10.3 Checked:\n     Generate a proxy\n     Test the web service\n     Monitor the web service\n     Overwrite files without warning\n10.4 Clicked \"Next\" to go to Object Selection Page\n10.5 Clicked \"Next\" to go to Service Deployment Configuration\n10.6 Clicked \"Finish\" on the Service Deployment Configuration screen\n11. Received error message:\n\nPublishing failed\n  Error copying file to C:\\Programme\\Tomcat 5.0.28\\webapps\\ConverterProj\\WEB-INF\\lib\\saaj.jar: Error deleting C:\\Programme\\Tomcat \n\n5.0.28\\webapps\\ConverterProj\\WEB-INF\\lib\\saaj.jar\n      java.lang.Exception: Error deleting C:\\Programme\\Tomcat 5.0.28\\webapps\\ConverterProj\\WEB-INF\\lib\\saaj.jar\n      at org.eclipse.jst.server.core.PublishUtil.copyFile(PublishUtil.java:123)\n      at org.eclipse.jst.server.core.PublishUtil.copyFile(PublishUtil.java:154)\n      at org.eclipse.jst.server.core.PublishUtil.smartCopy(PublishUtil.java:260)\n      at org.eclipse.jst.server.core.PublishUtil.smartCopy(PublishUtil.java:266)\n      at org.eclipse.jst.server.core.PublishUtil.smartCopy(PublishUtil.java:266)\n      at org.eclipse.jst.server.tomcat.core.internal.TomcatServerBehaviour.publishDir(TomcatServerBehaviour.java:282)\n      at org.eclipse.jst.server.tomcat.core.internal.TomcatServerBehaviour.publishModule(TomcatServerBehaviour.java:247)\n      at org.eclipse.wst.server.core.model.ServerBehaviourDelegate.publishModule(ServerBehaviourDelegate.java:658)\n      at org.eclipse.wst.server.core.model.ServerBehaviourDelegate.publishModules(ServerBehaviourDelegate.java:738)\n      at org.eclipse.wst.server.core.model.ServerBehaviourDelegate.publish(ServerBehaviourDelegate.java:596)\n      at org.eclipse.wst.server.core.internal.Server.doPublish(Server.java:799)\n      at org.eclipse.wst.server.core.internal.Server.publish(Server.java:788)\n      at org.eclipse.jst.ws.internal.consumption.ui.command.StartServerCommand$1.run(StartServerCommand.java:185)\n      at org.eclipse.jface.operation.ModalContext$ModalContextThread.run(ModalContext.java:113)\n\n12. Output to console was:\n\n15.01.2006 20:41:16 org.apache.coyote.http11.Http11Protocol init\nINFO: Initializing Coyote HTTP/1.1 on http-8080\n15.01.2006 20:41:16 org.apache.catalina.startup.Catalina load\nINFO: Initialization processed in 1187 ms\n15.01.2006 20:41:16 org.apache.catalina.core.StandardService start\nINFO: Starting service Catalina\n15.01.2006 20:41:16 org.apache.catalina.core.StandardEngine start\nINFO: Starting Servlet Engine: Apache Tomcat/5.0.28\n15.01.2006 20:41:16 org.apache.catalina.core.StandardHost start\nINFO: XML validation disabled\n15.01.2006 20:41:17 org.apache.axis.configuration.EngineConfigurationFactoryServlet getServerEngineConfig\nSCHWERWIEGEND: Unable to find config file.  Creating new servlet engine config file: /WEB-INF/server-config.wsdd\n15.01.2006 20:41:17 org.apache.axis.utils.JavaUtils isAttachmentSupported\nWARNUNG: Unable to find required classes (javax.activation.DataHandler and javax.mail.internet.MimeMultipart). Attachment support is \n\ndisabled.\n15.01.2006 20:41:18 org.apache.catalina.core.StandardHost getDeployer\nINFO: Create Host deployer for direct deployment ( non-jmx ) \n15.01.2006 20:41:18 org.apache.catalina.core.StandardHostDeployer install\nINFO: Processing Context configuration file URL file:C:\\Programme\\Tomcat 5.0.28\\conf\\Catalina\\localhost\\admin.xml\n15.01.2006 20:41:18 org.apache.struts.util.PropertyMessageResources \u003cinit\u003e\nINFO: Initializing, config\u003d\u0027org.apache.struts.util.LocalStrings\u0027, returnNull\u003dtrue\n15.01.2006 20:41:18 org.apache.struts.util.PropertyMessageResources \u003cinit\u003e\nINFO: Initializing, config\u003d\u0027org.apache.struts.action.ActionResources\u0027, returnNull\u003dtrue\n15.01.2006 20:41:19 org.apache.struts.util.PropertyMessageResources \u003cinit\u003e\nINFO: Initializing, config\u003d\u0027org.apache.webapp.admin.ApplicationResources\u0027, returnNull\u003dtrue\n15.01.2006 20:41:20 org.apache.catalina.core.StandardHostDeployer install\nINFO: Processing Context configuration file URL file:C:\\Programme\\Tomcat 5.0.28\\conf\\Catalina\\localhost\\balancer.xml\n15.01.2006 20:41:20 org.apache.catalina.core.StandardHostDeployer install\nINFO: Processing Context configuration file URL file:C:\\Programme\\Tomcat 5.0.28\\conf\\Catalina\\localhost\\manager.xml\n15.01.2006 20:41:21 org.apache.catalina.core.StandardHostDeployer install\nINFO: Installing web application at context path /jsp-examples from URL file:C:\\Programme\\Tomcat 5.0.28\\webapps\\jsp-examples\n15.01.2006 20:41:21 org.apache.catalina.core.StandardHostDeployer install\nINFO: Installing web application at context path  from URL file:C:\\Programme\\Tomcat 5.0.28\\webapps\\ROOT\n15.01.2006 20:41:21 org.apache.catalina.core.StandardHostDeployer install\nINFO: Installing web application at context path /servlets-examples from URL file:C:\\Programme\\Tomcat 5.0.28\\webapps\\servlets-examples\n15.01.2006 20:41:21 org.apache.catalina.core.StandardHostDeployer install\nINFO: Installing web application at context path /tomcat-docs from URL file:C:\\Programme\\Tomcat 5.0.28\\webapps\\tomcat-docs\n15.01.2006 20:41:21 org.apache.catalina.core.StandardHostDeployer install\nINFO: Installing web application at context path /webdav from URL file:C:\\Programme\\Tomcat 5.0.28\\webapps\\webdav\n15.01.2006 20:41:22 org.apache.coyote.http11.Http11Protocol start\nINFO: Starting Coyote HTTP/1.1 on http-8080\n15.01.2006 20:41:22 org.apache.jk.common.ChannelSocket init\nINFO: JK2: ajp13 listening on /0.0.0.0:8009\n15.01.2006 20:41:22 org.apache.jk.server.JkMain start\nINFO: Jk running ID\u003d0 time\u003d15/78  config\u003dC:\\Programme\\Tomcat 5.0.28\\conf\\jk2.properties\n15.01.2006 20:41:22 org.apache.catalina.startup.Catalina start\nINFO: Server startup in 5891 ms\n15.01.2006 20:41:22 org.apache.axis.configuration.EngineConfigurationFactoryServlet getServerEngineConfig\nSCHWERWIEGEND: Unable to find config file.  Creating new servlet engine config file: /WEB-INF/server-config.wsdd\n15.01.2006 20:41:41 org.apache.catalina.core.StandardHostDeployer install\nINFO: Installing web application at context path /ConverterProjClient from URL file:C:\\Programme\\Tomcat 5.0.28\\webapps\\ConverterProjClient\n\n\nAbout Eclipse SDK Features:\nVersion of Eclipse  - 3.1.1\nBuild ID of Eclipse - M20050929-0840\nVersion of WTP      - 1.0.0\nBuild ID of WTP     - 200512210855\n\n\nRegards,\n\nThomas Raddatz",
    "Hi Tim,\n\nI can reproduce the problem easily if I create the Tomcat server first and change the server config to unchecked \"Run modules directly from workspace\" before running a bottom-up Web service scenario.  The problem occurs during publish.\n\nI wonder if this is similar to bug 120709 which is a similar publish fail error with copying.  However, that problem was intermitten but this one I could reproduce everytime by first making sure that the server is stopped and the Web project had not been added to the server before running the Web service scenario with \"generate proxy\" and \"test\".",
    "\n\n*** This bug has been marked as a duplicate of 120709 ***",
    "Closing old bugs."
  ],
  "commentCreationDates": [
    "2006-01-15T19:59:20+01:00",
    "2006-02-10T03:59:57+01:00",
    "2006-07-11T20:34:16+02:00",
    "2006-11-21T19:45:51+01:00"
  ],
  "traces": [
    {
      "exceptionType": "java.lang.Exception",
      "message": "Error deleting C:\\Programme\\Tomcat 5.0.28\\webapps\\ConverterProj\\WEB-INF\\lib\\saaj.jar",
      "elements": [
        {
          "method": "org.eclipse.jst.server.core.PublishUtil.copyFile",
          "source": "PublishUtil.java:123"
        },
        {
          "method": "org.eclipse.jst.server.core.PublishUtil.copyFile",
          "source": "PublishUtil.java:154"
        },
        {
          "method": "org.eclipse.jst.server.core.PublishUtil.smartCopy",
          "source": "PublishUtil.java:260"
        },
        {
          "method": "org.eclipse.jst.server.core.PublishUtil.smartCopy",
          "source": "PublishUtil.java:266"
        },
        {
          "method": "org.eclipse.jst.server.core.PublishUtil.smartCopy",
          "source": "PublishUtil.java:266"
        },
        {
          "method": "org.eclipse.jst.server.tomcat.core.internal.TomcatServerBehaviour.publishDir",
          "source": "TomcatServerBehaviour.java:282"
        },
        {
          "method": "org.eclipse.jst.server.tomcat.core.internal.TomcatServerBehaviour.publishModule",
          "source": "TomcatServerBehaviour.java:247"
        },
        {
          "method": "org.eclipse.wst.server.core.model.ServerBehaviourDelegate.publishModule",
          "source": "ServerBehaviourDelegate.java:658"
        },
        {
          "method": "org.eclipse.wst.server.core.model.ServerBehaviourDelegate.publishModules",
          "source": "ServerBehaviourDelegate.java:738"
        },
        {
          "method": "org.eclipse.wst.server.core.model.ServerBehaviourDelegate.publish",
          "source": "ServerBehaviourDelegate.java:596"
        },
        {
          "method": "org.eclipse.wst.server.core.internal.Server.doPublish",
          "source": "Server.java:799"
        },
        {
          "method": "org.eclipse.wst.server.core.internal.Server.publish",
          "source": "Server.java:788"
        },
        {
          "method": "org.eclipse.jst.ws.internal.consumption.ui.command.StartServerCommand$1.run",
          "source": "StartServerCommand.java:185"
        },
        {
          "method": "org.eclipse.jface.operation.ModalContext$ModalContextThread.run",
          "source": "ModalContext.java:113"
        }
      ],
      "number": 0,
      "commentIndex": 0,
      "bugId": "123908",
      "duplicateId": "120709",
      "date": "2006-01-15T19:59:20+01:00",
      "product": "Web Tools",
      "component": "jst.server",
      "severity": "normal"
    }
  ],
  "groupId": "120709",
  "bugId": "123908",
  "duplicateId": "120709",
  "date": "2006-01-15T19:59:20+01:00",
  "product": "Web Tools",
  "component": "jst.server",
  "severity": "normal"
}