{
  "comments": [
    "Using build I20060117-0800 but also happens with build I20060103-0800.\n\nI\u0027ve created a project called \"JDK15\" with \"src\" source folder in which I\u0027ve imported sources of Sun JDK 1.5.0. I try to build my workspace and get following exceptions:\n!ENTRY org.eclipse.core.resources 4 2 2006-01-18 16:00:18.421\n!MESSAGE Problems occurred when invoking code from plug-in: \"org.eclipse.core.resources\".\n!STACK 0\njava.lang.NullPointerException\n        at org.eclipse.jdt.internal.compiler.lookup.ReferenceBinding.detectAnnotationCycle(ReferenceBinding.java:431)\n        at org.eclipse.jdt.internal.compiler.lookup.MethodVerifier15.verify(MethodVerifier15.java:552)\n        at org.eclipse.jdt.internal.compiler.lookup.SourceTypeBinding.verifyMethods(SourceTypeBinding.java:1451)\n        at org.eclipse.jdt.internal.compiler.lookup.CompilationUnitScope.verifyMethods(CompilationUnitScope.java:743)\n        at org.eclipse.jdt.internal.compiler.Compiler.process(Compiler.java:512)\n        at org.eclipse.jdt.internal.compiler.Compiler.compile(Compiler.java:332)\n        at org.eclipse.jdt.internal.core.builder.AbstractImageBuilder.compile(AbstractImageBuilder.java:286)\n        at org.eclipse.jdt.internal.core.builder.AbstractImageBuilder.compile(AbstractImageBuilder.java:251)\n        at org.eclipse.jdt.internal.core.builder.BatchImageBuilder.build(BatchImageBuilder.java:50)\n        at org.eclipse.jdt.internal.core.builder.JavaBuilder.buildAll(JavaBuilder.java:214)\n        at org.eclipse.jdt.internal.core.builder.JavaBuilder.build(JavaBuilder.java:142)\n        at org.eclipse.core.internal.events.BuildManager$2.run(BuildManager.java:593)\n        at org.eclipse.core.runtime.SafeRunner.run(SafeRunner.java:37)\n        at org.eclipse.core.runtime.Platform.run(Platform.java:785)\n        at org.eclipse.core.internal.events.BuildManager.basicBuild(BuildManager.java:168)\n        at org.eclipse.core.internal.events.BuildManager.basicBuild(BuildManager.java:202)\n        at org.eclipse.core.internal.events.BuildManager$1.run(BuildManager.java:231)\n        at org.eclipse.core.runtime.SafeRunner.run(SafeRunner.java:37)\n        at org.eclipse.core.runtime.Platform.run(Platform.java:785)\n        at org.eclipse.core.internal.events.BuildManager.basicBuild(BuildManager.java:234)\n        at org.eclipse.core.internal.events.BuildManager.basicBuildLoop(BuildManager.java:253)\n        at org.eclipse.core.internal.events.BuildManager.build(BuildManager.java:282)\n        at org.eclipse.core.internal.events.AutoBuildJob.doBuild(AutoBuildJob.java:143)\n        at org.eclipse.core.internal.events.AutoBuildJob.run(AutoBuildJob.java:204)\n        at org.eclipse.core.internal.jobs.Worker.run(Worker.java:58)\n\n!ENTRY org.eclipse.core.resources 2 75 2006-01-18 16:00:18.437\n!MESSAGE Errors during build.\n!SUBENTRY 1 org.eclipse.jdt.core 2 75 2006-01-18 16:00:18.437\n!MESSAGE Errors running builder \"Java Builder\" on project Generics.\n!SUBENTRY 1 org.eclipse.jdt.core 2 75 2006-01-18 16:00:18.437\n!MESSAGE java.lang.NullPointerException encountered while running Java Builder.\n!STACK 0\njava.lang.NullPointerException\n        at org.eclipse.jdt.internal.compiler.lookup.ReferenceBinding.detectAnnotationCycle(ReferenceBinding.java:431)\n        at org.eclipse.jdt.internal.compiler.lookup.MethodVerifier15.verify(MethodVerifier15.java:552)\n        at org.eclipse.jdt.internal.compiler.lookup.SourceTypeBinding.verifyMethods(SourceTypeBinding.java:1451)\n        at org.eclipse.jdt.internal.compiler.lookup.CompilationUnitScope.verifyMethods(CompilationUnitScope.java:743)\n        at org.eclipse.jdt.internal.compiler.Compiler.process(Compiler.java:512)\n        at org.eclipse.jdt.internal.compiler.Compiler.compile(Compiler.java:332)\n        at org.eclipse.jdt.internal.core.builder.AbstractImageBuilder.compile(AbstractImageBuilder.java:286)\n        at org.eclipse.jdt.internal.core.builder.AbstractImageBuilder.compile(AbstractImageBuilder.java:251)\n        at org.eclipse.jdt.internal.core.builder.BatchImageBuilder.build(BatchImageBuilder.java:50)\n        at org.eclipse.jdt.internal.core.builder.JavaBuilder.buildAll(JavaBuilder.java:214)\n        at org.eclipse.jdt.internal.core.builder.JavaBuilder.build(JavaBuilder.java:142)\n        at org.eclipse.core.internal.events.BuildManager$2.run(BuildManager.java:593)\n        at org.eclipse.core.runtime.SafeRunner.run(SafeRunner.java:37)\n        at org.eclipse.core.runtime.Platform.run(Platform.java:785)\n        at org.eclipse.core.internal.events.BuildManager.basicBuild(BuildManager.java:168)\n        at org.eclipse.core.internal.events.BuildManager.basicBuild(BuildManager.java:202)\n        at org.eclipse.core.internal.events.BuildManager$1.run(BuildManager.java:231)\n        at org.eclipse.core.runtime.SafeRunner.run(SafeRunner.java:37)\n        at org.eclipse.core.runtime.Platform.run(Platform.java:785)\n        at org.eclipse.core.internal.events.BuildManager.basicBuild(BuildManager.java:234)\n        at org.eclipse.core.internal.events.BuildManager.basicBuildLoop(BuildManager.java:253)\n        at org.eclipse.core.internal.events.BuildManager.build(BuildManager.java:282)\n        at org.eclipse.core.internal.events.AutoBuildJob.doBuild(AutoBuildJob.java:143)\n        at org.eclipse.core.internal.events.AutoBuildJob.run(AutoBuildJob.java:204)\n        at org.eclipse.core.internal.jobs.Worker.run(Worker.java:58)\n\nSeems to be a regression as this does not happen with 3.2 M4.\n\nNote that symptom is the same using VM 1.4 or 1.5 to run eclipse session...",
    "\n\n*** This bug has been marked as a duplicate of 124119 ***",
    "Reopen to set original duplicate bug",
    "\n\n*** This bug has been marked as a duplicate of 95056 ***",
    "Verified that I do not get error any longer with fix released in HEAD...\n(see bug 95056 comment 12) \n"
  ],
  "commentCreationDates": [
    "2006-01-18T15:21:04+01:00",
    "2006-01-18T15:38:20+01:00",
    "2006-01-18T18:13:08+01:00",
    "2006-01-18T18:13:23+01:00",
    "2006-01-18T18:14:44+01:00"
  ],
  "traces": [
    {
      "exceptionType": "java.lang.NullPointerException",
      "elements": [
        {
          "method": "org.eclipse.jdt.internal.compiler.lookup.ReferenceBinding.detectAnnotationCycle",
          "source": "ReferenceBinding.java:431"
        },
        {
          "method": "org.eclipse.jdt.internal.compiler.lookup.MethodVerifier15.verify",
          "source": "MethodVerifier15.java:552"
        },
        {
          "method": "org.eclipse.jdt.internal.compiler.lookup.SourceTypeBinding.verifyMethods",
          "source": "SourceTypeBinding.java:1451"
        },
        {
          "method": "org.eclipse.jdt.internal.compiler.lookup.CompilationUnitScope.verifyMethods",
          "source": "CompilationUnitScope.java:743"
        },
        {
          "method": "org.eclipse.jdt.internal.compiler.Compiler.process",
          "source": "Compiler.java:512"
        },
        {
          "method": "org.eclipse.jdt.internal.compiler.Compiler.compile",
          "source": "Compiler.java:332"
        },
        {
          "method": "org.eclipse.jdt.internal.core.builder.AbstractImageBuilder.compile",
          "source": "AbstractImageBuilder.java:286"
        },
        {
          "method": "org.eclipse.jdt.internal.core.builder.AbstractImageBuilder.compile",
          "source": "AbstractImageBuilder.java:251"
        },
        {
          "method": "org.eclipse.jdt.internal.core.builder.BatchImageBuilder.build",
          "source": "BatchImageBuilder.java:50"
        },
        {
          "method": "org.eclipse.jdt.internal.core.builder.JavaBuilder.buildAll",
          "source": "JavaBuilder.java:214"
        },
        {
          "method": "org.eclipse.jdt.internal.core.builder.JavaBuilder.build",
          "source": "JavaBuilder.java:142"
        },
        {
          "method": "org.eclipse.core.internal.events.BuildManager$2.run",
          "source": "BuildManager.java:593"
        },
        {
          "method": "org.eclipse.core.runtime.SafeRunner.run",
          "source": "SafeRunner.java:37"
        },
        {
          "method": "org.eclipse.core.runtime.Platform.run",
          "source": "Platform.java:785"
        },
        {
          "method": "org.eclipse.core.internal.events.BuildManager.basicBuild",
          "source": "BuildManager.java:168"
        },
        {
          "method": "org.eclipse.core.internal.events.BuildManager.basicBuild",
          "source": "BuildManager.java:202"
        },
        {
          "method": "org.eclipse.core.internal.events.BuildManager$1.run",
          "source": "BuildManager.java:231"
        },
        {
          "method": "org.eclipse.core.runtime.SafeRunner.run",
          "source": "SafeRunner.java:37"
        },
        {
          "method": "org.eclipse.core.runtime.Platform.run",
          "source": "Platform.java:785"
        },
        {
          "method": "org.eclipse.core.internal.events.BuildManager.basicBuild",
          "source": "BuildManager.java:234"
        },
        {
          "method": "org.eclipse.core.internal.events.BuildManager.basicBuildLoop",
          "source": "BuildManager.java:253"
        },
        {
          "method": "org.eclipse.core.internal.events.BuildManager.build",
          "source": "BuildManager.java:282"
        },
        {
          "method": "org.eclipse.core.internal.events.AutoBuildJob.doBuild",
          "source": "AutoBuildJob.java:143"
        },
        {
          "method": "org.eclipse.core.internal.events.AutoBuildJob.run",
          "source": "AutoBuildJob.java:204"
        },
        {
          "method": "org.eclipse.core.internal.jobs.Worker.run",
          "source": "Worker.java:58"
        }
      ],
      "number": 0,
      "commentIndex": 0,
      "bugId": "124301",
      "duplicateId": "95056",
      "date": "2006-01-18T15:21:04+01:00",
      "product": "JDT",
      "component": "Core",
      "severity": "normal"
    },
    {
      "exceptionType": "java.lang.NullPointerException",
      "elements": [
        {
          "method": "org.eclipse.jdt.internal.compiler.lookup.ReferenceBinding.detectAnnotationCycle",
          "source": "ReferenceBinding.java:431"
        },
        {
          "method": "org.eclipse.jdt.internal.compiler.lookup.MethodVerifier15.verify",
          "source": "MethodVerifier15.java:552"
        },
        {
          "method": "org.eclipse.jdt.internal.compiler.lookup.SourceTypeBinding.verifyMethods",
          "source": "SourceTypeBinding.java:1451"
        },
        {
          "method": "org.eclipse.jdt.internal.compiler.lookup.CompilationUnitScope.verifyMethods",
          "source": "CompilationUnitScope.java:743"
        },
        {
          "method": "org.eclipse.jdt.internal.compiler.Compiler.process",
          "source": "Compiler.java:512"
        },
        {
          "method": "org.eclipse.jdt.internal.compiler.Compiler.compile",
          "source": "Compiler.java:332"
        },
        {
          "method": "org.eclipse.jdt.internal.core.builder.AbstractImageBuilder.compile",
          "source": "AbstractImageBuilder.java:286"
        },
        {
          "method": "org.eclipse.jdt.internal.core.builder.AbstractImageBuilder.compile",
          "source": "AbstractImageBuilder.java:251"
        },
        {
          "method": "org.eclipse.jdt.internal.core.builder.BatchImageBuilder.build",
          "source": "BatchImageBuilder.java:50"
        },
        {
          "method": "org.eclipse.jdt.internal.core.builder.JavaBuilder.buildAll",
          "source": "JavaBuilder.java:214"
        },
        {
          "method": "org.eclipse.jdt.internal.core.builder.JavaBuilder.build",
          "source": "JavaBuilder.java:142"
        },
        {
          "method": "org.eclipse.core.internal.events.BuildManager$2.run",
          "source": "BuildManager.java:593"
        },
        {
          "method": "org.eclipse.core.runtime.SafeRunner.run",
          "source": "SafeRunner.java:37"
        },
        {
          "method": "org.eclipse.core.runtime.Platform.run",
          "source": "Platform.java:785"
        },
        {
          "method": "org.eclipse.core.internal.events.BuildManager.basicBuild",
          "source": "BuildManager.java:168"
        },
        {
          "method": "org.eclipse.core.internal.events.BuildManager.basicBuild",
          "source": "BuildManager.java:202"
        },
        {
          "method": "org.eclipse.core.internal.events.BuildManager$1.run",
          "source": "BuildManager.java:231"
        },
        {
          "method": "org.eclipse.core.runtime.SafeRunner.run",
          "source": "SafeRunner.java:37"
        },
        {
          "method": "org.eclipse.core.runtime.Platform.run",
          "source": "Platform.java:785"
        },
        {
          "method": "org.eclipse.core.internal.events.BuildManager.basicBuild",
          "source": "BuildManager.java:234"
        },
        {
          "method": "org.eclipse.core.internal.events.BuildManager.basicBuildLoop",
          "source": "BuildManager.java:253"
        },
        {
          "method": "org.eclipse.core.internal.events.BuildManager.build",
          "source": "BuildManager.java:282"
        },
        {
          "method": "org.eclipse.core.internal.events.AutoBuildJob.doBuild",
          "source": "AutoBuildJob.java:143"
        },
        {
          "method": "org.eclipse.core.internal.events.AutoBuildJob.run",
          "source": "AutoBuildJob.java:204"
        },
        {
          "method": "org.eclipse.core.internal.jobs.Worker.run",
          "source": "Worker.java:58"
        }
      ],
      "number": 1,
      "commentIndex": 0,
      "bugId": "124301",
      "duplicateId": "95056",
      "date": "2006-01-18T15:21:04+01:00",
      "product": "JDT",
      "component": "Core",
      "severity": "normal"
    }
  ],
  "groupId": "95056",
  "bugId": "124301",
  "duplicateId": "95056",
  "date": "2006-01-18T15:21:04+01:00",
  "product": "JDT",
  "component": "Core",
  "severity": "normal"
}