{
  "comments": [
    "Version: 3.2.0\nBuild id: I20060118-0800\n\nAfter installing this build, I restarted my self-hosting dev workspace, and got many of these complaints in the console during startup.\n\n!ENTRY org.eclipse.jdt.launching 4 4 2006-01-19 11:19:35.306\n!MESSAGE Unable to retreive system properties\n!STACK 1\norg.eclipse.core.runtime.CoreException: Unable to retreive system properties\n        at org.eclipse.jdt.launching.AbstractVMInstall.abort(AbstractVMInstall.java:453)\n        at org.eclipse.jdt.launching.AbstractVMInstall.evaluateSystemProperties(AbstractVMInstall.java:397)\n        at org.eclipse.pde.internal.core.ExecutionEnvironmentAnalyzer.analyze(ExecutionEnvironmentAnalyzer.java:98)\n        at org.eclipse.jdt.internal.launching.environments.Analyzer.analyze(Analyzer.java:41)\n        at org.eclipse.jdt.internal.launching.environments.EnvironmentsManager.analyze(EnvironmentsManager.java:293)\n        at org.eclipse.jdt.internal.launching.environments.EnvironmentsManager.initializeCompatibilities(EnvironmentsManager.java:199)\n        at org.eclipse.jdt.internal.launching.environments.ExecutionEnvironment.init(ExecutionEnvironment.java:64)\n        at org.eclipse.jdt.internal.launching.environments.ExecutionEnvironment.getDefaultVM(ExecutionEnvironment.java:101)\n        at org.eclipse.jdt.internal.launching.JREContainerInitializer.resolveVM(JREContainerInitializer.java:74)\n        at org.eclipse.jdt.internal.launching.JREContainerInitializer.initialize(JREContainerInitializer.java:51)\n        at org.eclipse.jdt.internal.core.JavaModelManager.initializeContainer(JavaModelManager.java:1741)\n        at org.eclipse.jdt.internal.core.JavaModelManager.getClasspathContainer(JavaModelManager.java:1171)\n        at org.eclipse.jdt.core.JavaCore.getClasspathContainer(JavaCore.java:1458)\n        at org.eclipse.jdt.internal.core.JavaProject.getResolvedClasspath(JavaProject.java:2153)\n        at org.eclipse.jdt.internal.core.JavaProject.getResolvedClasspath(JavaProject.java:2057)\n        at org.eclipse.jdt.internal.core.JavaModelManager.determineIfOnClasspath(JavaModelManager.java:734)\n        at org.eclipse.jdt.internal.core.JavaModelManager.create(JavaModelManager.java:623)\n        at org.eclipse.jdt.internal.core.JavaModelManager.create(JavaModelManager.java:552)\n        at org.eclipse.jdt.core.JavaCore.create(JavaCore.java:1372)\n        at org.eclipse.jdt.internal.ui.ResourceAdapterFactory.getAdapter(ResourceAdapterFactory.java:32)\n        at org.eclipse.core.internal.runtime.AdapterFactoryProxy.getAdapter(AdapterFactoryProxy.java:63)\n        at org.eclipse.core.internal.runtime.AdapterManager.getAdapter(AdapterManager.java:253)\n        at org.eclipse.core.runtime.PlatformObject.getAdapter(PlatformObject.java:65)\n        at org.eclipse.jdt.internal.ui.filters.NamePatternFilter.select(NamePatternFilter.java:62)\n        at org.eclipse.jdt.internal.ui.packageview.PackageExplorerPart$PackageExplorerProblemTreeViewer.filter(PackageExplorerPart.java:324)\n        at org.eclipse.jdt.internal.ui.packageview.PackageExplorerPart$PackageExplorerProblemTreeViewer.getFilteredChildren(PackageExplorerPart.ja\n        at org.eclipse.jface.viewers.StructuredViewer.getSortedChildren(StructuredViewer.java:944)\n        at org.eclipse.jdt.internal.ui.packageview.PackageExplorerPart$PackageExplorerProblemTreeViewer.getSortedChildren(PackageExplorerPart.java\n        at org.eclipse.jface.viewers.AbstractTreeViewer$1.run(AbstractTreeViewer.java:517)\n        at org.eclipse.swt.custom.BusyIndicator.showWhile(BusyIndicator.java:69)\n        at org.eclipse.jface.viewers.AbstractTreeViewer.createChildren(AbstractTreeViewer.java:499)\n        at org.eclipse.jface.viewers.TreeViewer.createChildren(TreeViewer.java:794)\n        at org.eclipse.jface.viewers.AbstractTreeViewer.internalExpand(AbstractTreeViewer.java:1090)\n        at org.eclipse.jface.viewers.AbstractTreeViewer.internalExpand(AbstractTreeViewer.java:1087)\n        at org.eclipse.jface.viewers.AbstractTreeViewer.internalExpand(AbstractTreeViewer.java:1087)\n        at org.eclipse.jface.viewers.AbstractTreeViewer.setSelectionToWidget(AbstractTreeViewer.java:1785)\n        at org.eclipse.jface.viewers.StructuredViewer.setSelectionToWidget(StructuredViewer.java:1552)\n        at org.eclipse.jface.viewers.AbstractTreeViewer.setSelectionToWidget(AbstractTreeViewer.java:2121)\n        at org.eclipse.jdt.internal.ui.packageview.PackageExplorerPart$PackageExplorerProblemTreeViewer.setSelectionToWidget(PackageExplorerPart.j\n        at org.eclipse.jface.viewers.StructuredViewer.setSelection(StructuredViewer.java:1508)\n        at org.eclipse.jdt.internal.ui.packageview.PackageExplorerPart.showInput(PackageExplorerPart.java:1522)\n        at org.eclipse.jdt.internal.ui.packageview.PackageExplorerPart.editorActivated(PackageExplorerPart.java:1487)\n        at org.eclipse.jdt.internal.ui.packageview.PackageExplorerPart$1.partActivated(PackageExplorerPart.java:218)\n        at org.eclipse.ui.internal.PartListenerList$1.run(PartListenerList.java:71)\n        at org.eclipse.core.runtime.SafeRunner.run(SafeRunner.java:37)\n        at org.eclipse.core.runtime.Platform.run(Platform.java:785)\n        at org.eclipse.ui.internal.PartListenerList.fireEvent(PartListenerList.java:57)\n        at org.eclipse.ui.internal.PartListenerList.firePartActivated(PartListenerList.java:69)\n        at org.eclipse.ui.internal.PartService.firePartActivated(PartService.java:73)\n        at org.eclipse.ui.internal.PartService.setActivePart(PartService.java:171)\n        at org.eclipse.ui.internal.WorkbenchPagePartList.fireActivePartChanged(WorkbenchPagePartList.java:56)\n        at org.eclipse.ui.internal.PartList.setActivePart(PartList.java:117)\n        at org.eclipse.ui.internal.WorkbenchPage.setActivePart(WorkbenchPage.java:2961)\n        at org.eclipse.ui.internal.WorkbenchPage.activate(WorkbenchPage.java:555)\n        at org.eclipse.ui.internal.WorkbenchPage.makeActive(WorkbenchPage.java:1100)\n        at org.eclipse.ui.internal.WorkbenchPage.updateActivePart(WorkbenchPage.java:1080)\n        at org.eclipse.ui.internal.WorkbenchPage.handleDeferredEvents(WorkbenchPage.java:1264)\n        at org.eclipse.ui.internal.WorkbenchPage.deferUpdates(WorkbenchPage.java:1253)\n        at org.eclipse.ui.internal.WorkbenchPage.restoreState(WorkbenchPage.java:2739)\n        at org.eclipse.ui.internal.WorkbenchWindow.restoreState(WorkbenchWindow.java:1837)\n        at org.eclipse.ui.internal.Workbench.doRestoreState(Workbench.java:2704)\n        at org.eclipse.ui.internal.Workbench.access$14(Workbench.java:2653)\n        at org.eclipse.ui.internal.Workbench$17.run(Workbench.java:1569)\n        at org.eclipse.ui.internal.Workbench.runStartupWithProgress(Workbench.java:1321)\n        at org.eclipse.ui.internal.Workbench.restoreState(Workbench.java:1567)\n        at org.eclipse.ui.internal.Workbench.access$12(Workbench.java:1546)\n        at org.eclipse.ui.internal.Workbench$15.run(Workbench.java:1429)\n        at org.eclipse.core.runtime.SafeRunner.run(SafeRunner.java:37)\n        at org.eclipse.core.runtime.Platform.run(Platform.java:785)\n        at org.eclipse.ui.internal.Workbench.restoreState(Workbench.java:1373)\n        at org.eclipse.ui.internal.WorkbenchConfigurer.restoreState(WorkbenchConfigurer.java:183)\n        at org.eclipse.ui.application.WorkbenchAdvisor.openWindows(WorkbenchAdvisor.java:700)\n        at org.eclipse.ui.internal.Workbench.init(Workbench.java:989)\n        at org.eclipse.ui.internal.Workbench.runUI(Workbench.java:1723)\n        at org.eclipse.ui.internal.Workbench.createAndRunWorkbench(Workbench.java:400)\n        at org.eclipse.ui.PlatformUI.createAndRunWorkbench(PlatformUI.java:143)\n        at org.eclipse.ui.internal.ide.IDEApplication.run(IDEApplication.java:106)\n        at org.eclipse.core.internal.runtime.PlatformActivator$1.run(PlatformActivator.java:109)\n        at org.eclipse.core.runtime.internal.adaptor.EclipseAppLauncher.runApplication(EclipseAppLauncher.java:92)\n        at org.eclipse.core.runtime.internal.adaptor.EclipseAppLauncher.start(EclipseAppLauncher.java:68)\n        at org.eclipse.core.runtime.adaptor.EclipseStarter.run(EclipseStarter.java:373)\n        at org.eclipse.core.runtime.adaptor.EclipseStarter.run(EclipseStarter.java:168)\n        at sun.reflect.NativeMethodAccessorImpl.invoke0(Native Method)\n        at sun.reflect.NativeMethodAccessorImpl.invoke(NativeMethodAccessorImpl.java:39)\n        at sun.reflect.DelegatingMethodAccessorImpl.invoke(DelegatingMethodAccessorImpl.java:25)\n        at java.lang.reflect.Method.invoke(Method.java:324)\n        at org.eclipse.core.launcher.Main.invokeFramework(Main.java:338)\n        at org.eclipse.core.launcher.Main.basicRun(Main.java:282)\n        at org.eclipse.core.launcher.Main.run(Main.java:977)\n        at org.eclipse.core.launcher.Main.main(Main.java:952)\n!SUBENTRY 1 org.eclipse.jdt.launching 4 150 2006-01-19 11:19:35.316\n!MESSAGE Unable to retreive system properties\n\n!ENTRY org.eclipse.jdt.launching 4 4 2006-01-19 11:19:55.465\n!MESSAGE Unable to retreive system properties\n!STACK 1\norg.eclipse.core.runtime.CoreException: Unable to retreive system properties\n        at org.eclipse.jdt.launching.AbstractVMInstall.abort(AbstractVMInstall.java:453)\n        at org.eclipse.jdt.launching.AbstractVMInstall.evaluateSystemProperties(AbstractVMInstall.java:397)\n        at org.eclipse.pde.internal.core.ExecutionEnvironmentAnalyzer.analyze(ExecutionEnvironmentAnalyzer.java:98)\n        at org.eclipse.jdt.internal.launching.environments.Analyzer.analyze(Analyzer.java:41)\n        at org.eclipse.jdt.internal.launching.environments.EnvironmentsManager.analyze(EnvironmentsManager.java:293)\n        at org.eclipse.jdt.internal.launching.environments.EnvironmentsManager.initializeCompatibilities(EnvironmentsManager.java:199)\n        at org.eclipse.jdt.internal.launching.environments.ExecutionEnvironment.init(ExecutionEnvironment.java:64)\n        at org.eclipse.jdt.internal.launching.environments.ExecutionEnvironment.getDefaultVM(ExecutionEnvironment.java:101)\n        at org.eclipse.jdt.internal.launching.JREContainerInitializer.resolveVM(JREContainerInitializer.java:74)\n        at org.eclipse.jdt.internal.launching.JREContainerInitializer.initialize(JREContainerInitializer.java:51)\n        at org.eclipse.jdt.internal.core.JavaModelManager.initializeContainer(JavaModelManager.java:1741)\n        at org.eclipse.jdt.internal.core.JavaModelManager.getClasspathContainer(JavaModelManager.java:1171)\n        at org.eclipse.jdt.core.JavaCore.getClasspathContainer(JavaCore.java:1458)\n        at org.eclipse.jdt.internal.core.JavaProject.getResolvedClasspath(JavaProject.java:2153)\n        at org.eclipse.jdt.internal.core.JavaProject.getResolvedClasspath(JavaProject.java:2057)\n        at org.eclipse.jdt.internal.core.JavaModelManager.determineIfOnClasspath(JavaModelManager.java:734)\n        at org.eclipse.jdt.internal.core.JavaModelManager.create(JavaModelManager.java:623)\n        at org.eclipse.jdt.internal.core.JavaModelManager.create(JavaModelManager.java:552)\n        at org.eclipse.jdt.core.JavaCore.create(JavaCore.java:1372)\n        at org.eclipse.jdt.internal.ui.ResourceAdapterFactory.getAdapter(ResourceAdapterFactory.java:32)\n        at org.eclipse.core.internal.runtime.AdapterFactoryProxy.getAdapter(AdapterFactoryProxy.java:63)\n        at org.eclipse.core.internal.runtime.AdapterManager.getAdapter(AdapterManager.java:253)\n        at org.eclipse.core.runtime.PlatformObject.getAdapter(PlatformObject.java:65)\n        at org.eclipse.jdt.internal.ui.filters.NamePatternFilter.select(NamePatternFilter.java:62)\n        at org.eclipse.jdt.internal.ui.packageview.PackageExplorerPart$PackageExplorerProblemTreeViewer.filter(PackageExplorerPart.java:324)\n        at org.eclipse.jdt.internal.ui.packageview.PackageExplorerPart$PackageExplorerProblemTreeViewer.getFilteredChildren(PackageExplorerPart.ja\n        at org.eclipse.jface.viewers.StructuredViewer.getSortedChildren(StructuredViewer.java:944)\n        at org.eclipse.jdt.internal.ui.packageview.PackageExplorerPart$PackageExplorerProblemTreeViewer.getSortedChildren(PackageExplorerPart.java\n        at org.eclipse.jface.viewers.AbstractTreeViewer$1.run(AbstractTreeViewer.java:517)\n        at org.eclipse.swt.custom.BusyIndicator.showWhile(BusyIndicator.java:69)\n        at org.eclipse.jface.viewers.AbstractTreeViewer.createChildren(AbstractTreeViewer.java:499)\n        at org.eclipse.jface.viewers.TreeViewer.createChildren(TreeViewer.java:794)\n        at org.eclipse.jface.viewers.AbstractTreeViewer.internalExpand(AbstractTreeViewer.java:1090)\n        at org.eclipse.jface.viewers.AbstractTreeViewer.internalExpand(AbstractTreeViewer.java:1087)\n        at org.eclipse.jface.viewers.AbstractTreeViewer.internalExpand(AbstractTreeViewer.java:1087)\n        at org.eclipse.jface.viewers.AbstractTreeViewer.setSelectionToWidget(AbstractTreeViewer.java:1785)\n        at org.eclipse.jface.viewers.StructuredViewer.setSelectionToWidget(StructuredViewer.java:1552)\n        at org.eclipse.jface.viewers.AbstractTreeViewer.setSelectionToWidget(AbstractTreeViewer.java:2121)\n        at org.eclipse.jdt.internal.ui.packageview.PackageExplorerPart$PackageExplorerProblemTreeViewer.setSelectionToWidget(PackageExplorerPart.j\n        at org.eclipse.jface.viewers.StructuredViewer.setSelection(StructuredViewer.java:1508)\n        at org.eclipse.jdt.internal.ui.packageview.PackageExplorerPart.showInput(PackageExplorerPart.java:1522)\n        at org.eclipse.jdt.internal.ui.packageview.PackageExplorerPart.editorActivated(PackageExplorerPart.java:1487)\n        at org.eclipse.jdt.internal.ui.packageview.PackageExplorerPart$1.partActivated(PackageExplorerPart.java:218)\n        at org.eclipse.ui.internal.PartListenerList$1.run(PartListenerList.java:71)\n        at org.eclipse.core.runtime.SafeRunner.run(SafeRunner.java:37)\n        at org.eclipse.core.runtime.Platform.run(Platform.java:785)\n        at org.eclipse.ui.internal.PartListenerList.fireEvent(PartListenerList.java:57)\n        at org.eclipse.ui.internal.PartListenerList.firePartActivated(PartListenerList.java:69)\n        at org.eclipse.ui.internal.PartService.firePartActivated(PartService.java:73)\n        at org.eclipse.ui.internal.PartService.setActivePart(PartService.java:171)\n        at org.eclipse.ui.internal.WorkbenchPagePartList.fireActivePartChanged(WorkbenchPagePartList.java:56)\n        at org.eclipse.ui.internal.PartList.setActivePart(PartList.java:117)\n        at org.eclipse.ui.internal.WorkbenchPage.setActivePart(WorkbenchPage.java:2961)\n        at org.eclipse.ui.internal.WorkbenchPage.activate(WorkbenchPage.java:555)\n        at org.eclipse.ui.internal.WorkbenchPage.makeActive(WorkbenchPage.java:1100)\n        at org.eclipse.ui.internal.WorkbenchPage.updateActivePart(WorkbenchPage.java:1080)\n        at org.eclipse.ui.internal.WorkbenchPage.handleDeferredEvents(WorkbenchPage.java:1264)\n        at org.eclipse.ui.internal.WorkbenchPage.deferUpdates(WorkbenchPage.java:1253)\n        at org.eclipse.ui.internal.WorkbenchPage.restoreState(WorkbenchPage.java:2739)\n        at org.eclipse.ui.internal.WorkbenchWindow.restoreState(WorkbenchWindow.java:1837)\n        at org.eclipse.ui.internal.Workbench.doRestoreState(Workbench.java:2704)\n        at org.eclipse.ui.internal.Workbench.access$14(Workbench.java:2653)\n        at org.eclipse.ui.internal.Workbench$17.run(Workbench.java:1569)\n        at org.eclipse.ui.internal.Workbench.runStartupWithProgress(Workbench.java:1321)\n        at org.eclipse.ui.internal.Workbench.restoreState(Workbench.java:1567)\n        at org.eclipse.ui.internal.Workbench.access$12(Workbench.java:1546)\n        at org.eclipse.ui.internal.Workbench$15.run(Workbench.java:1429)\n        at org.eclipse.core.runtime.SafeRunner.run(SafeRunner.java:37)\n        at org.eclipse.core.runtime.Platform.run(Platform.java:785)\n        at org.eclipse.ui.internal.Workbench.restoreState(Workbench.java:1373)\n        at org.eclipse.ui.internal.WorkbenchConfigurer.restoreState(WorkbenchConfigurer.java:183)\n        at org.eclipse.ui.application.WorkbenchAdvisor.openWindows(WorkbenchAdvisor.java:700)\n        at org.eclipse.ui.internal.Workbench.init(Workbench.java:989)\n        at org.eclipse.ui.internal.Workbench.runUI(Workbench.java:1723)\n        at org.eclipse.ui.internal.Workbench.createAndRunWorkbench(Workbench.java:400)\n        at org.eclipse.ui.PlatformUI.createAndRunWorkbench(PlatformUI.java:143)\n        at org.eclipse.ui.internal.ide.IDEApplication.run(IDEApplication.java:106)\n        at org.eclipse.core.internal.runtime.PlatformActivator$1.run(PlatformActivator.java:109)\n        at org.eclipse.core.runtime.internal.adaptor.EclipseAppLauncher.runApplication(EclipseAppLauncher.java:92)\n        at org.eclipse.core.runtime.internal.adaptor.EclipseAppLauncher.start(EclipseAppLauncher.java:68)\n        at org.eclipse.core.runtime.adaptor.EclipseStarter.run(EclipseStarter.java:373)\n        at org.eclipse.core.runtime.adaptor.EclipseStarter.run(EclipseStarter.java:168)\n        at sun.reflect.NativeMethodAccessorImpl.invoke0(Native Method)\n        at sun.reflect.NativeMethodAccessorImpl.invoke(NativeMethodAccessorImpl.java:39)\n        at sun.reflect.DelegatingMethodAccessorImpl.invoke(DelegatingMethodAccessorImpl.java:25)\n        at java.lang.reflect.Method.invoke(Method.java:324)\n        at org.eclipse.core.launcher.Main.invokeFramework(Main.java:338)\n        at org.eclipse.core.launcher.Main.basicRun(Main.java:282)\n        at org.eclipse.core.launcher.Main.run(Main.java:977)\n        at org.eclipse.core.launcher.Main.main(Main.java:952)\n!SUBENTRY 1 org.eclipse.jdt.launching 4 150 2006-01-19 11:19:55.475\n!MESSAGE Unable to retreive system properties\n\n!ENTRY org.eclipse.jdt.launching 4 4 2006-01-19 11:20:15.564\n!MESSAGE Unable to retreive system properties\n!STACK 1\norg.eclipse.core.runtime.CoreException: Unable to retreive system properties\n        at org.eclipse.jdt.launching.AbstractVMInstall.abort(AbstractVMInstall.java:453)\n        at org.eclipse.jdt.launching.AbstractVMInstall.evaluateSystemProperties(AbstractVMInstall.java:397)\n        at org.eclipse.pde.internal.core.ExecutionEnvironmentAnalyzer.analyze(ExecutionEnvironmentAnalyzer.java:110)\n        at org.eclipse.jdt.internal.launching.environments.Analyzer.analyze(Analyzer.java:41)\n        at org.eclipse.jdt.internal.launching.environments.EnvironmentsManager.analyze(EnvironmentsManager.java:293)\n        at org.eclipse.jdt.internal.launching.environments.EnvironmentsManager.initializeCompatibilities(EnvironmentsManager.java:199)\n        at org.eclipse.jdt.internal.launching.environments.ExecutionEnvironment.init(ExecutionEnvironment.java:64)\n        at org.eclipse.jdt.internal.launching.environments.ExecutionEnvironment.getDefaultVM(ExecutionEnvironment.java:101)\n        at org.eclipse.jdt.internal.launching.JREContainerInitializer.resolveVM(JREContainerInitializer.java:74)\n        at org.eclipse.jdt.internal.launching.JREContainerInitializer.initialize(JREContainerInitializer.java:51)\n        at org.eclipse.jdt.internal.core.JavaModelManager.initializeContainer(JavaModelManager.java:1741)\n        at org.eclipse.jdt.internal.core.JavaModelManager.getClasspathContainer(JavaModelManager.java:1171)\n        at org.eclipse.jdt.core.JavaCore.getClasspathContainer(JavaCore.java:1458)\n        at org.eclipse.jdt.internal.core.JavaProject.getResolvedClasspath(JavaProject.java:2153)\n        at org.eclipse.jdt.internal.core.JavaProject.getResolvedClasspath(JavaProject.java:2057)\n        at org.eclipse.jdt.internal.core.JavaModelManager.determineIfOnClasspath(JavaModelManager.java:734)\n        at org.eclipse.jdt.internal.core.JavaModelManager.create(JavaModelManager.java:623)\n        at org.eclipse.jdt.internal.core.JavaModelManager.create(JavaModelManager.java:552)\n        at org.eclipse.jdt.core.JavaCore.create(JavaCore.java:1372)\n        at org.eclipse.jdt.internal.ui.ResourceAdapterFactory.getAdapter(ResourceAdapterFactory.java:32)\n        at org.eclipse.core.internal.runtime.AdapterFactoryProxy.getAdapter(AdapterFactoryProxy.java:63)\n        at org.eclipse.core.internal.runtime.AdapterManager.getAdapter(AdapterManager.java:253)\n        at org.eclipse.core.runtime.PlatformObject.getAdapter(PlatformObject.java:65)\n        at org.eclipse.jdt.internal.ui.filters.NamePatternFilter.select(NamePatternFilter.java:62)\n        at org.eclipse.jdt.internal.ui.packageview.PackageExplorerPart$PackageExplorerProblemTreeViewer.filter(PackageExplorerPart.java:324)\n        at org.eclipse.jdt.internal.ui.packageview.PackageExplorerPart$PackageExplorerProblemTreeViewer.getFilteredChildren(PackageExplorerPart.ja\n        at org.eclipse.jface.viewers.StructuredViewer.getSortedChildren(StructuredViewer.java:944)\n        at org.eclipse.jdt.internal.ui.packageview.PackageExplorerPart$PackageExplorerProblemTreeViewer.getSortedChildren(PackageExplorerPart.java\n        at org.eclipse.jface.viewers.AbstractTreeViewer$1.run(AbstractTreeViewer.java:517)\n        at org.eclipse.swt.custom.BusyIndicator.showWhile(BusyIndicator.java:69)\n        at org.eclipse.jface.viewers.AbstractTreeViewer.createChildren(AbstractTreeViewer.java:499)\n        at org.eclipse.jface.viewers.TreeViewer.createChildren(TreeViewer.java:794)\n        at org.eclipse.jface.viewers.AbstractTreeViewer.internalExpand(AbstractTreeViewer.java:1090)\n        at org.eclipse.jface.viewers.AbstractTreeViewer.internalExpand(AbstractTreeViewer.java:1087)\n        at org.eclipse.jface.viewers.AbstractTreeViewer.internalExpand(AbstractTreeViewer.java:1087)\n        at org.eclipse.jface.viewers.AbstractTreeViewer.setSelectionToWidget(AbstractTreeViewer.java:1785)\n        at org.eclipse.jface.viewers.StructuredViewer.setSelectionToWidget(StructuredViewer.java:1552)\n        at org.eclipse.jface.viewers.AbstractTreeViewer.setSelectionToWidget(AbstractTreeViewer.java:2121)\n        at org.eclipse.jdt.internal.ui.packageview.PackageExplorerPart$PackageExplorerProblemTreeViewer.setSelectionToWidget(PackageExplorerPart.j\n        at org.eclipse.jface.viewers.StructuredViewer.setSelection(StructuredViewer.java:1508)\n        at org.eclipse.jdt.internal.ui.packageview.PackageExplorerPart.showInput(PackageExplorerPart.java:1522)\n        at org.eclipse.jdt.internal.ui.packageview.PackageExplorerPart.editorActivated(PackageExplorerPart.java:1487)\n        at org.eclipse.jdt.internal.ui.packageview.PackageExplorerPart$1.partActivated(PackageExplorerPart.java:218)\n        at org.eclipse.ui.internal.PartListenerList$1.run(PartListenerList.java:71)\n        at org.eclipse.core.runtime.SafeRunner.run(SafeRunner.java:37)\n        at org.eclipse.core.runtime.Platform.run(Platform.java:785)\n        at org.eclipse.ui.internal.PartListenerList.fireEvent(PartListenerList.java:57)\n        at org.eclipse.ui.internal.PartListenerList.firePartActivated(PartListenerList.java:69)\n        at org.eclipse.ui.internal.PartService.firePartActivated(PartService.java:73)\n        at org.eclipse.ui.internal.PartService.setActivePart(PartService.java:171)\n        at org.eclipse.ui.internal.WorkbenchPagePartList.fireActivePartChanged(WorkbenchPagePartList.java:56)\n        at org.eclipse.ui.internal.PartList.setActivePart(PartList.java:117)\n        at org.eclipse.ui.internal.WorkbenchPage.setActivePart(WorkbenchPage.java:2961)\n        at org.eclipse.ui.internal.WorkbenchPage.activate(WorkbenchPage.java:555)\n        at org.eclipse.ui.internal.WorkbenchPage.makeActive(WorkbenchPage.java:1100)\n        at org.eclipse.ui.internal.WorkbenchPage.updateActivePart(WorkbenchPage.java:1080)\n        at org.eclipse.ui.internal.WorkbenchPage.handleDeferredEvents(WorkbenchPage.java:1264)\n        at org.eclipse.ui.internal.WorkbenchPage.deferUpdates(WorkbenchPage.java:1253)\n        at org.eclipse.ui.internal.WorkbenchPage.restoreState(WorkbenchPage.java:2739)\n        at org.eclipse.ui.internal.WorkbenchWindow.restoreState(WorkbenchWindow.java:1837)\n        at org.eclipse.ui.internal.Workbench.doRestoreState(Workbench.java:2704)\n        at org.eclipse.ui.internal.Workbench.access$14(Workbench.java:2653)\n        at org.eclipse.ui.internal.Workbench$17.run(Workbench.java:1569)\n        at org.eclipse.ui.internal.Workbench.runStartupWithProgress(Workbench.java:1321)\n        at org.eclipse.ui.internal.Workbench.restoreState(Workbench.java:1567)\n        at org.eclipse.ui.internal.Workbench.access$12(Workbench.java:1546)\n        at org.eclipse.ui.internal.Workbench$15.run(Workbench.java:1429)\n        at org.eclipse.core.runtime.SafeRunner.run(SafeRunner.java:37)\n        at org.eclipse.core.runtime.Platform.run(Platform.java:785)\n        at org.eclipse.ui.internal.Workbench.restoreState(Workbench.java:1373)\n        at org.eclipse.ui.internal.WorkbenchConfigurer.restoreState(WorkbenchConfigurer.java:183)\n        at org.eclipse.ui.application.WorkbenchAdvisor.openWindows(WorkbenchAdvisor.java:700)\n        at org.eclipse.ui.internal.Workbench.init(Workbench.java:989)\n        at org.eclipse.ui.internal.Workbench.runUI(Workbench.java:1723)\n        at org.eclipse.ui.internal.Workbench.createAndRunWorkbench(Workbench.java:400)\n        at org.eclipse.ui.PlatformUI.createAndRunWorkbench(PlatformUI.java:143)\n        at org.eclipse.ui.internal.ide.IDEApplication.run(IDEApplication.java:106)\n        at org.eclipse.core.internal.runtime.PlatformActivator$1.run(PlatformActivator.java:109)\n        at org.eclipse.core.runtime.internal.adaptor.EclipseAppLauncher.runApplication(EclipseAppLauncher.java:92)\n        at org.eclipse.core.runtime.internal.adaptor.EclipseAppLauncher.start(EclipseAppLauncher.java:68)\n        at org.eclipse.core.runtime.adaptor.EclipseStarter.run(EclipseStarter.java:373)\n        at org.eclipse.core.runtime.adaptor.EclipseStarter.run(EclipseStarter.java:168)\n        at sun.reflect.NativeMethodAccessorImpl.invoke0(Native Method)\n        at sun.reflect.NativeMethodAccessorImpl.invoke(NativeMethodAccessorImpl.java:39)\n        at sun.reflect.DelegatingMethodAccessorImpl.invoke(DelegatingMethodAccessorImpl.java:25)\n        at java.lang.reflect.Method.invoke(Method.java:324)\n        at org.eclipse.core.launcher.Main.invokeFramework(Main.java:338)\n        at org.eclipse.core.launcher.Main.basicRun(Main.java:282)\n        at org.eclipse.core.launcher.Main.run(Main.java:977)\n        at org.eclipse.core.launcher.Main.main(Main.java:952)\n!SUBENTRY 1 org.eclipse.jdt.launching 4 150 2006-01-19 11:20:15.574\n!MESSAGE Unable to retreive system properties",
    "\n\n*** This bug has been marked as a duplicate of 124137 ***"
  ],
  "commentCreationDates": [
    "2006-01-19T10:21:37+01:00",
    "2006-01-19T16:20:33+01:00"
  ],
  "traces": [
    {
      "exceptionType": "org.eclipse.core.runtime.CoreException",
      "message": "Unable to retreive system properties",
      "elements": [
        {
          "method": "org.eclipse.jdt.launching.AbstractVMInstall.abort",
          "source": "AbstractVMInstall.java:453"
        },
        {
          "method": "org.eclipse.jdt.launching.AbstractVMInstall.evaluateSystemProperties",
          "source": "AbstractVMInstall.java:397"
        },
        {
          "method": "org.eclipse.pde.internal.core.ExecutionEnvironmentAnalyzer.analyze",
          "source": "ExecutionEnvironmentAnalyzer.java:98"
        },
        {
          "method": "org.eclipse.jdt.internal.launching.environments.Analyzer.analyze",
          "source": "Analyzer.java:41"
        },
        {
          "method": "org.eclipse.jdt.internal.launching.environments.EnvironmentsManager.analyze",
          "source": "EnvironmentsManager.java:293"
        },
        {
          "method": "org.eclipse.jdt.internal.launching.environments.EnvironmentsManager.initializeCompatibilities",
          "source": "EnvironmentsManager.java:199"
        },
        {
          "method": "org.eclipse.jdt.internal.launching.environments.ExecutionEnvironment.init",
          "source": "ExecutionEnvironment.java:64"
        },
        {
          "method": "org.eclipse.jdt.internal.launching.environments.ExecutionEnvironment.getDefaultVM",
          "source": "ExecutionEnvironment.java:101"
        },
        {
          "method": "org.eclipse.jdt.internal.launching.JREContainerInitializer.resolveVM",
          "source": "JREContainerInitializer.java:74"
        },
        {
          "method": "org.eclipse.jdt.internal.launching.JREContainerInitializer.initialize",
          "source": "JREContainerInitializer.java:51"
        },
        {
          "method": "org.eclipse.jdt.internal.core.JavaModelManager.initializeContainer",
          "source": "JavaModelManager.java:1741"
        },
        {
          "method": "org.eclipse.jdt.internal.core.JavaModelManager.getClasspathContainer",
          "source": "JavaModelManager.java:1171"
        },
        {
          "method": "org.eclipse.jdt.core.JavaCore.getClasspathContainer",
          "source": "JavaCore.java:1458"
        },
        {
          "method": "org.eclipse.jdt.internal.core.JavaProject.getResolvedClasspath",
          "source": "JavaProject.java:2153"
        },
        {
          "method": "org.eclipse.jdt.internal.core.JavaProject.getResolvedClasspath",
          "source": "JavaProject.java:2057"
        },
        {
          "method": "org.eclipse.jdt.internal.core.JavaModelManager.determineIfOnClasspath",
          "source": "JavaModelManager.java:734"
        },
        {
          "method": "org.eclipse.jdt.internal.core.JavaModelManager.create",
          "source": "JavaModelManager.java:623"
        },
        {
          "method": "org.eclipse.jdt.internal.core.JavaModelManager.create",
          "source": "JavaModelManager.java:552"
        },
        {
          "method": "org.eclipse.jdt.core.JavaCore.create",
          "source": "JavaCore.java:1372"
        },
        {
          "method": "org.eclipse.jdt.internal.ui.ResourceAdapterFactory.getAdapter",
          "source": "ResourceAdapterFactory.java:32"
        },
        {
          "method": "org.eclipse.core.internal.runtime.AdapterFactoryProxy.getAdapter",
          "source": "AdapterFactoryProxy.java:63"
        },
        {
          "method": "org.eclipse.core.internal.runtime.AdapterManager.getAdapter",
          "source": "AdapterManager.java:253"
        },
        {
          "method": "org.eclipse.core.runtime.PlatformObject.getAdapter",
          "source": "PlatformObject.java:65"
        },
        {
          "method": "org.eclipse.jdt.internal.ui.filters.NamePatternFilter.select",
          "source": "NamePatternFilter.java:62"
        },
        {
          "method": "org.eclipse.jdt.internal.ui.packageview.PackageExplorerPart$PackageExplorerProblemTreeViewer.filter",
          "source": "PackageExplorerPart.java:324"
        }
      ],
      "number": 0,
      "commentIndex": 0,
      "bugId": "124461",
      "duplicateId": "124137",
      "date": "2006-01-19T10:21:37+01:00",
      "product": "JDT",
      "component": "Debug",
      "severity": "normal"
    },
    {
      "exceptionType": "org.eclipse.core.runtime.CoreException",
      "message": "Unable to retreive system properties",
      "elements": [
        {
          "method": "org.eclipse.jdt.launching.AbstractVMInstall.abort",
          "source": "AbstractVMInstall.java:453"
        },
        {
          "method": "org.eclipse.jdt.launching.AbstractVMInstall.evaluateSystemProperties",
          "source": "AbstractVMInstall.java:397"
        },
        {
          "method": "org.eclipse.pde.internal.core.ExecutionEnvironmentAnalyzer.analyze",
          "source": "ExecutionEnvironmentAnalyzer.java:98"
        },
        {
          "method": "org.eclipse.jdt.internal.launching.environments.Analyzer.analyze",
          "source": "Analyzer.java:41"
        },
        {
          "method": "org.eclipse.jdt.internal.launching.environments.EnvironmentsManager.analyze",
          "source": "EnvironmentsManager.java:293"
        },
        {
          "method": "org.eclipse.jdt.internal.launching.environments.EnvironmentsManager.initializeCompatibilities",
          "source": "EnvironmentsManager.java:199"
        },
        {
          "method": "org.eclipse.jdt.internal.launching.environments.ExecutionEnvironment.init",
          "source": "ExecutionEnvironment.java:64"
        },
        {
          "method": "org.eclipse.jdt.internal.launching.environments.ExecutionEnvironment.getDefaultVM",
          "source": "ExecutionEnvironment.java:101"
        },
        {
          "method": "org.eclipse.jdt.internal.launching.JREContainerInitializer.resolveVM",
          "source": "JREContainerInitializer.java:74"
        },
        {
          "method": "org.eclipse.jdt.internal.launching.JREContainerInitializer.initialize",
          "source": "JREContainerInitializer.java:51"
        },
        {
          "method": "org.eclipse.jdt.internal.core.JavaModelManager.initializeContainer",
          "source": "JavaModelManager.java:1741"
        },
        {
          "method": "org.eclipse.jdt.internal.core.JavaModelManager.getClasspathContainer",
          "source": "JavaModelManager.java:1171"
        },
        {
          "method": "org.eclipse.jdt.core.JavaCore.getClasspathContainer",
          "source": "JavaCore.java:1458"
        },
        {
          "method": "org.eclipse.jdt.internal.core.JavaProject.getResolvedClasspath",
          "source": "JavaProject.java:2153"
        },
        {
          "method": "org.eclipse.jdt.internal.core.JavaProject.getResolvedClasspath",
          "source": "JavaProject.java:2057"
        },
        {
          "method": "org.eclipse.jdt.internal.core.JavaModelManager.determineIfOnClasspath",
          "source": "JavaModelManager.java:734"
        },
        {
          "method": "org.eclipse.jdt.internal.core.JavaModelManager.create",
          "source": "JavaModelManager.java:623"
        },
        {
          "method": "org.eclipse.jdt.internal.core.JavaModelManager.create",
          "source": "JavaModelManager.java:552"
        },
        {
          "method": "org.eclipse.jdt.core.JavaCore.create",
          "source": "JavaCore.java:1372"
        },
        {
          "method": "org.eclipse.jdt.internal.ui.ResourceAdapterFactory.getAdapter",
          "source": "ResourceAdapterFactory.java:32"
        },
        {
          "method": "org.eclipse.core.internal.runtime.AdapterFactoryProxy.getAdapter",
          "source": "AdapterFactoryProxy.java:63"
        },
        {
          "method": "org.eclipse.core.internal.runtime.AdapterManager.getAdapter",
          "source": "AdapterManager.java:253"
        },
        {
          "method": "org.eclipse.core.runtime.PlatformObject.getAdapter",
          "source": "PlatformObject.java:65"
        },
        {
          "method": "org.eclipse.jdt.internal.ui.filters.NamePatternFilter.select",
          "source": "NamePatternFilter.java:62"
        },
        {
          "method": "org.eclipse.jdt.internal.ui.packageview.PackageExplorerPart$PackageExplorerProblemTreeViewer.filter",
          "source": "PackageExplorerPart.java:324"
        }
      ],
      "number": 1,
      "commentIndex": 0,
      "bugId": "124461",
      "duplicateId": "124137",
      "date": "2006-01-19T10:21:37+01:00",
      "product": "JDT",
      "component": "Debug",
      "severity": "normal"
    },
    {
      "exceptionType": "org.eclipse.core.runtime.CoreException",
      "message": "Unable to retreive system properties",
      "elements": [
        {
          "method": "org.eclipse.jdt.launching.AbstractVMInstall.abort",
          "source": "AbstractVMInstall.java:453"
        },
        {
          "method": "org.eclipse.jdt.launching.AbstractVMInstall.evaluateSystemProperties",
          "source": "AbstractVMInstall.java:397"
        },
        {
          "method": "org.eclipse.pde.internal.core.ExecutionEnvironmentAnalyzer.analyze",
          "source": "ExecutionEnvironmentAnalyzer.java:110"
        },
        {
          "method": "org.eclipse.jdt.internal.launching.environments.Analyzer.analyze",
          "source": "Analyzer.java:41"
        },
        {
          "method": "org.eclipse.jdt.internal.launching.environments.EnvironmentsManager.analyze",
          "source": "EnvironmentsManager.java:293"
        },
        {
          "method": "org.eclipse.jdt.internal.launching.environments.EnvironmentsManager.initializeCompatibilities",
          "source": "EnvironmentsManager.java:199"
        },
        {
          "method": "org.eclipse.jdt.internal.launching.environments.ExecutionEnvironment.init",
          "source": "ExecutionEnvironment.java:64"
        },
        {
          "method": "org.eclipse.jdt.internal.launching.environments.ExecutionEnvironment.getDefaultVM",
          "source": "ExecutionEnvironment.java:101"
        },
        {
          "method": "org.eclipse.jdt.internal.launching.JREContainerInitializer.resolveVM",
          "source": "JREContainerInitializer.java:74"
        },
        {
          "method": "org.eclipse.jdt.internal.launching.JREContainerInitializer.initialize",
          "source": "JREContainerInitializer.java:51"
        },
        {
          "method": "org.eclipse.jdt.internal.core.JavaModelManager.initializeContainer",
          "source": "JavaModelManager.java:1741"
        },
        {
          "method": "org.eclipse.jdt.internal.core.JavaModelManager.getClasspathContainer",
          "source": "JavaModelManager.java:1171"
        },
        {
          "method": "org.eclipse.jdt.core.JavaCore.getClasspathContainer",
          "source": "JavaCore.java:1458"
        },
        {
          "method": "org.eclipse.jdt.internal.core.JavaProject.getResolvedClasspath",
          "source": "JavaProject.java:2153"
        },
        {
          "method": "org.eclipse.jdt.internal.core.JavaProject.getResolvedClasspath",
          "source": "JavaProject.java:2057"
        },
        {
          "method": "org.eclipse.jdt.internal.core.JavaModelManager.determineIfOnClasspath",
          "source": "JavaModelManager.java:734"
        },
        {
          "method": "org.eclipse.jdt.internal.core.JavaModelManager.create",
          "source": "JavaModelManager.java:623"
        },
        {
          "method": "org.eclipse.jdt.internal.core.JavaModelManager.create",
          "source": "JavaModelManager.java:552"
        },
        {
          "method": "org.eclipse.jdt.core.JavaCore.create",
          "source": "JavaCore.java:1372"
        },
        {
          "method": "org.eclipse.jdt.internal.ui.ResourceAdapterFactory.getAdapter",
          "source": "ResourceAdapterFactory.java:32"
        },
        {
          "method": "org.eclipse.core.internal.runtime.AdapterFactoryProxy.getAdapter",
          "source": "AdapterFactoryProxy.java:63"
        },
        {
          "method": "org.eclipse.core.internal.runtime.AdapterManager.getAdapter",
          "source": "AdapterManager.java:253"
        },
        {
          "method": "org.eclipse.core.runtime.PlatformObject.getAdapter",
          "source": "PlatformObject.java:65"
        },
        {
          "method": "org.eclipse.jdt.internal.ui.filters.NamePatternFilter.select",
          "source": "NamePatternFilter.java:62"
        },
        {
          "method": "org.eclipse.jdt.internal.ui.packageview.PackageExplorerPart$PackageExplorerProblemTreeViewer.filter",
          "source": "PackageExplorerPart.java:324"
        }
      ],
      "number": 2,
      "commentIndex": 0,
      "bugId": "124461",
      "duplicateId": "124137",
      "date": "2006-01-19T10:21:37+01:00",
      "product": "JDT",
      "component": "Debug",
      "severity": "normal"
    }
  ],
  "groupId": "124137",
  "bugId": "124461",
  "duplicateId": "124137",
  "date": "2006-01-19T10:21:37+01:00",
  "product": "JDT",
  "component": "Debug",
  "severity": "normal"
}