{
  "comments": [
    "I simply cannot get Eclipse to run on my AMD64 box, no matter what I try.  I am running under JDK1.6.0, 64-bit version of course, and I have also tried the blackdown 1.4.2 64-bit edition.  Furthermore, I tried version 3.1.1 of Eclipse.  The error I get under most configurations is the following.  After a while, they seem to accumulate until a dialog box pops up informing me that Eclipse has completely run out of memory and must shut down.  In eclipse.ini, I added the flags -Xms512m and -Xmx1024m, and I have 2GB of physical RAM.  Any hints would be greatly appreciated, this has been blocking me for months.  Thanks!\n\njava.lang.OutOfMemoryError: unable to create new native thread\n        at java.lang.Thread.start(Native Method)\n        at org.eclipse.core.internal.jobs.WorkerPool.jobQueued(WorkerPool.java:140)\n        at org.eclipse.core.internal.jobs.WorkerPool.startJob(WorkerPool.java:226)\n        at org.eclipse.core.internal.jobs.Worker.run(Worker.java:69)\nUnhandled event loop exception\nReason:\nFailed to execute runnable (java.lang.OutOfMemoryError: unable to create new native thread)\nUnhandled event loop exception\nReason:\nunable to create new native thread\nFatal error happened during workbench emergency close.\njava.lang.OutOfMemoryError: unable to create new native thread\n        at java.lang.Thread.start(Native Method)\n        at org.eclipse.jface.operation.ModalContext.run(ModalContext.java:302)\n        at org.eclipse.jface.dialogs.ProgressMonitorDialog.run(ProgressMonitorDialog.java:447)\n        at org.eclipse.ui.internal.progress.ProgressMonitorJobsDialog.run(ProgressMonitorJobsDialog.java:261)\n        at org.eclipse.ui.internal.ide.IDEWorkbenchAdvisor.disconnectFromWorkspace(IDEWorkbenchAdvisor.java:298)\n        at org.eclipse.ui.internal.ide.IDEWorkbenchAdvisor.postShutdown(IDEWorkbenchAdvisor.java:200)\n        at org.eclipse.ui.internal.Workbench.shutdown(Workbench.java:1997)\n        at org.eclipse.ui.internal.Workbench.busyClose(Workbench.java:596)\n        at org.eclipse.ui.internal.Workbench.access$8(Workbench.java:522)\n        at org.eclipse.ui.internal.Workbench$13.run(Workbench.java:713)\n        at org.eclipse.swt.custom.BusyIndicator.showWhile(BusyIndicator.java:69)\n        at org.eclipse.ui.internal.Workbench.close(Workbench.java:711)\n        at org.eclipse.ui.internal.WorkbenchConfigurer.emergencyClose(WorkbenchConfigurer.java:165)\n        at org.eclipse.ui.internal.ide.IDEExceptionHandler.closeWorkbench(IDEExceptionHandler.java:121)\n        at org.eclipse.ui.internal.ide.IDEExceptionHandler.handleException(IDEExceptionHandler.java:100)\n        at org.eclipse.ui.internal.ide.IDEWorkbenchAdvisor.eventLoopException(IDEWorkbenchAdvisor.java:210)\n        at org.eclipse.ui.internal.ExceptionHandler.handleException(ExceptionHandler.java:62)\n        at org.eclipse.jface.window.Window.runEventLoop(Window.java:812)\n        at org.eclipse.jface.window.Window.open(Window.java:787)\n        at org.eclipse.ui.internal.OpenPreferencesAction.run(OpenPreferencesAction.java:66)\n        at org.eclipse.jface.action.Action.runWithEvent(Action.java:996)\n        at org.eclipse.jface.action.ActionContributionItem.handleWidgetSelection(ActionContributionItem.java:538)\n        at org.eclipse.jface.action.ActionContributionItem.access$2(ActionContributionItem.java:488)\n        at org.eclipse.jface.action.ActionContributionItem$5.handleEvent(ActionContributionItem.java:400)\n        at org.eclipse.swt.widgets.EventTable.sendEvent(EventTable.java:66)\n        at org.eclipse.swt.widgets.Widget.sendEvent(Widget.java:1021)\n        at org.eclipse.swt.widgets.Display.runDeferredEvents(Display.java:2867)\n        at org.eclipse.swt.widgets.Display.readAndDispatch(Display.java:2572)\n        at org.eclipse.ui.internal.Workbench.runEventLoop(Workbench.java:1699)\n        at org.eclipse.ui.internal.Workbench.runUI(Workbench.java:1663)\n        at org.eclipse.ui.internal.Workbench.createAndRunWorkbench(Workbench.java:367)\n        at org.eclipse.ui.PlatformUI.createAndRunWorkbench(PlatformUI.java:143)\n        at org.eclipse.ui.internal.ide.IDEApplication.run(IDEApplication.java:103)\n        at org.eclipse.core.internal.runtime.PlatformActivator$1.run(PlatformActivator.java:226)\n        at org.eclipse.core.runtime.adaptor.EclipseStarter.run(EclipseStarter.java:376)\n        at org.eclipse.core.runtime.adaptor.EclipseStarter.run(EclipseStarter.java:163)\n        at sun.reflect.NativeMethodAccessorImpl.invoke0(Native Method)\n        at sun.reflect.NativeMethodAccessorImpl.invoke(NativeMethodAccessorImpl.java:39)\n        at sun.reflect.DelegatingMethodAccessorImpl.invoke(DelegatingMethodAccessorImpl.java:25)\n        at java.lang.reflect.Method.invoke(Method.java:324)\n        at org.eclipse.core.launcher.Main.invokeFramework(Main.java:334)\n        at org.eclipse.core.launcher.Main.basicRun(Main.java:278)\n        at org.eclipse.core.launcher.Main.run(Main.java:973)\n        at org.eclipse.core.launcher.Main.main(Main.java:948)\nUnhandled event loop exception\nReason:\nunable to create new native thread",
    "\n\n*** This bug has been marked as a duplicate of 124762 ***"
  ],
  "commentCreationDates": [
    "2006-01-21T15:33:59+01:00",
    "2006-01-21T20:15:25+01:00"
  ],
  "traces": [
    {
      "exceptionType": "java.lang.OutOfMemoryError",
      "message": "unable to create new native thread",
      "elements": [
        {
          "method": "java.lang.Thread.start",
          "source": "Native Method"
        },
        {
          "method": "org.eclipse.core.internal.jobs.WorkerPool.jobQueued",
          "source": "WorkerPool.java:140"
        },
        {
          "method": "org.eclipse.core.internal.jobs.WorkerPool.startJob",
          "source": "WorkerPool.java:226"
        },
        {
          "method": "org.eclipse.core.internal.jobs.Worker.run",
          "source": "Worker.java:69"
        }
      ],
      "number": 0,
      "commentIndex": 0,
      "bugId": "124783",
      "duplicateId": "124762",
      "date": "2006-01-21T15:33:59+01:00",
      "product": "Platform",
      "component": "Runtime",
      "severity": "critical"
    },
    {
      "exceptionType": "java.lang.OutOfMemoryError",
      "message": "unable to create new native thread",
      "elements": [
        {
          "method": "java.lang.Thread.start",
          "source": "Native Method"
        },
        {
          "method": "org.eclipse.jface.operation.ModalContext.run",
          "source": "ModalContext.java:302"
        },
        {
          "method": "org.eclipse.jface.dialogs.ProgressMonitorDialog.run",
          "source": "ProgressMonitorDialog.java:447"
        },
        {
          "method": "org.eclipse.ui.internal.progress.ProgressMonitorJobsDialog.run",
          "source": "ProgressMonitorJobsDialog.java:261"
        },
        {
          "method": "org.eclipse.ui.internal.ide.IDEWorkbenchAdvisor.disconnectFromWorkspace",
          "source": "IDEWorkbenchAdvisor.java:298"
        },
        {
          "method": "org.eclipse.ui.internal.ide.IDEWorkbenchAdvisor.postShutdown",
          "source": "IDEWorkbenchAdvisor.java:200"
        },
        {
          "method": "org.eclipse.ui.internal.Workbench.shutdown",
          "source": "Workbench.java:1997"
        },
        {
          "method": "org.eclipse.ui.internal.Workbench.busyClose",
          "source": "Workbench.java:596"
        },
        {
          "method": "org.eclipse.ui.internal.Workbench.access$8",
          "source": "Workbench.java:522"
        },
        {
          "method": "org.eclipse.ui.internal.Workbench$13.run",
          "source": "Workbench.java:713"
        },
        {
          "method": "org.eclipse.swt.custom.BusyIndicator.showWhile",
          "source": "BusyIndicator.java:69"
        },
        {
          "method": "org.eclipse.ui.internal.Workbench.close",
          "source": "Workbench.java:711"
        },
        {
          "method": "org.eclipse.ui.internal.WorkbenchConfigurer.emergencyClose",
          "source": "WorkbenchConfigurer.java:165"
        },
        {
          "method": "org.eclipse.ui.internal.ide.IDEExceptionHandler.closeWorkbench",
          "source": "IDEExceptionHandler.java:121"
        },
        {
          "method": "org.eclipse.ui.internal.ide.IDEExceptionHandler.handleException",
          "source": "IDEExceptionHandler.java:100"
        },
        {
          "method": "org.eclipse.ui.internal.ide.IDEWorkbenchAdvisor.eventLoopException",
          "source": "IDEWorkbenchAdvisor.java:210"
        },
        {
          "method": "org.eclipse.ui.internal.ExceptionHandler.handleException",
          "source": "ExceptionHandler.java:62"
        },
        {
          "method": "org.eclipse.jface.window.Window.runEventLoop",
          "source": "Window.java:812"
        },
        {
          "method": "org.eclipse.jface.window.Window.open",
          "source": "Window.java:787"
        },
        {
          "method": "org.eclipse.ui.internal.OpenPreferencesAction.run",
          "source": "OpenPreferencesAction.java:66"
        },
        {
          "method": "org.eclipse.jface.action.Action.runWithEvent",
          "source": "Action.java:996"
        },
        {
          "method": "org.eclipse.jface.action.ActionContributionItem.handleWidgetSelection",
          "source": "ActionContributionItem.java:538"
        },
        {
          "method": "org.eclipse.jface.action.ActionContributionItem.access$2",
          "source": "ActionContributionItem.java:488"
        },
        {
          "method": "org.eclipse.jface.action.ActionContributionItem$5.handleEvent",
          "source": "ActionContributionItem.java:400"
        },
        {
          "method": "org.eclipse.swt.widgets.EventTable.sendEvent",
          "source": "EventTable.java:66"
        },
        {
          "method": "org.eclipse.swt.widgets.Widget.sendEvent",
          "source": "Widget.java:1021"
        },
        {
          "method": "org.eclipse.swt.widgets.Display.runDeferredEvents",
          "source": "Display.java:2867"
        },
        {
          "method": "org.eclipse.swt.widgets.Display.readAndDispatch",
          "source": "Display.java:2572"
        },
        {
          "method": "org.eclipse.ui.internal.Workbench.runEventLoop",
          "source": "Workbench.java:1699"
        },
        {
          "method": "org.eclipse.ui.internal.Workbench.runUI",
          "source": "Workbench.java:1663"
        },
        {
          "method": "org.eclipse.ui.internal.Workbench.createAndRunWorkbench",
          "source": "Workbench.java:367"
        },
        {
          "method": "org.eclipse.ui.PlatformUI.createAndRunWorkbench",
          "source": "PlatformUI.java:143"
        },
        {
          "method": "org.eclipse.ui.internal.ide.IDEApplication.run",
          "source": "IDEApplication.java:103"
        },
        {
          "method": "org.eclipse.core.internal.runtime.PlatformActivator$1.run",
          "source": "PlatformActivator.java:226"
        },
        {
          "method": "org.eclipse.core.runtime.adaptor.EclipseStarter.run",
          "source": "EclipseStarter.java:376"
        },
        {
          "method": "org.eclipse.core.runtime.adaptor.EclipseStarter.run",
          "source": "EclipseStarter.java:163"
        },
        {
          "method": "sun.reflect.NativeMethodAccessorImpl.invoke0",
          "source": "Native Method"
        },
        {
          "method": "sun.reflect.NativeMethodAccessorImpl.invoke",
          "source": "NativeMethodAccessorImpl.java:39"
        },
        {
          "method": "sun.reflect.DelegatingMethodAccessorImpl.invoke",
          "source": "DelegatingMethodAccessorImpl.java:25"
        },
        {
          "method": "java.lang.reflect.Method.invoke",
          "source": "Method.java:324"
        },
        {
          "method": "org.eclipse.core.launcher.Main.invokeFramework",
          "source": "Main.java:334"
        },
        {
          "method": "org.eclipse.core.launcher.Main.basicRun",
          "source": "Main.java:278"
        },
        {
          "method": "org.eclipse.core.launcher.Main.run",
          "source": "Main.java:973"
        },
        {
          "method": "org.eclipse.core.launcher.Main.main",
          "source": "Main.java:948"
        }
      ],
      "number": 1,
      "commentIndex": 0,
      "bugId": "124783",
      "duplicateId": "124762",
      "date": "2006-01-21T15:33:59+01:00",
      "product": "Platform",
      "component": "Runtime",
      "severity": "critical"
    }
  ],
  "groupId": "124762",
  "bugId": "124783",
  "duplicateId": "124762",
  "date": "2006-01-21T15:33:59+01:00",
  "product": "Platform",
  "component": "Runtime",
  "severity": "critical"
}