{
  "comments": [
    "I have a csv file.The first line has column name and the next line has data type.After this i have comma separated values.\n\nAfter the values I have a new line then again i have column name(for second table) and then data type and again comma separated values.\n\nFor example\n\nCustomerName,CustomerAge\nSTRING,INT\na,1,\nb,2,\nc,3\n\nCustomerGroup,CustomerIncome\nSTRING,INT\nA1,12,\nA2,23,\nA3,34\n\n\nNow a am doing a query \nselect CustomerName, CustomerAge from {filenmae} for first the data set.\n\nand \nselect CustomerGroup, CustomerIncome from {filenmae} for second  the data set.\n\nBut i am getting the exception when i run my {designfile}.rptdesign through BIRT engine.It is coming even if i use only one data set .\n\nException is\nJan 24, 2006 2:49:23 PM org.eclipse.birt.data.engine.odaconsumer.PreparedStatement execute\nSEVERE: Cannot execute statement.\norg.eclipse.datatools.connectivity.oda.OdaException: 3 \u003e\u003d 3\n        at org.eclipse.datatools.connectivity.oda.flatfile.Query.fetchQueriedDataFromFileToVector(Qu\nery.java:826)\n        at org.eclipse.datatools.connectivity.oda.flatfile.Query.executeQuery(Query.java:159)\n        at org.eclipse.datatools.connectivity.oda.consumer.helper.OdaQuery.doExecuteQuery(OdaQuery.j\nava:439)\n        at org.eclipse.datatools.connectivity.oda.consumer.helper.OdaQuery.executeQuery(OdaQuery.jav\na:404)\n        at org.eclipse.birt.data.engine.odaconsumer.PreparedStatement.execute(PreparedStatement.java\n:551)\n        at org.eclipse.birt.data.engine.executor.DataSourceQuery.execute(DataSourceQuery.java:490)\n        at org.eclipse.birt.data.engine.impl.PreparedExtendedDSQuery$ExtendedDSQueryExecutor.execute\nOdiQuery(PreparedExtendedDSQuery.java:313)\n        at org.eclipse.birt.data.engine.impl.PreparedQuery$Executor.execute(PreparedQuery.java:634)\n        at org.eclipse.birt.data.engine.impl.QueryResults.getResultIterator(QueryResults.java:105)\n        at org.eclipse.birt.report.engine.data.dte.DteDataEngine.execute(DteDataEngine.java:214)\n        at org.eclipse.birt.report.engine.executor.ExtendedItemExecutor.executeQueries(ExtendedItemE\nxecutor.java:215)\n        at org.eclipse.birt.report.engine.executor.ExtendedItemExecutor.generateInFactory(ExtendedIt\nemExecutor.java:166)\n        at org.eclipse.birt.report.engine.executor.ExtendedItemExecutor.generateContent(ExtendedItem\nExecutor.java:111)\n        at org.eclipse.birt.report.engine.executor.ExtendedItemExecutor.execute(ExtendedItemExecutor\n.java:91)\n        at org.eclipse.birt.report.engine.executor.ReportExecutorVisitor.visitExtendedItem(ReportExe\ncutorVisitor.java:81)\n        at org.eclipse.birt.report.engine.ir.ExtendedItemDesign.accept(ExtendedItemDesign.java:30)\n        at org.eclipse.birt.report.engine.executor.ReportExecutor.execute(ReportExecutor.java:159)\n        at org.eclipse.birt.report.engine.api.impl.RunAndRenderTask.run(RunAndRenderTask.java:198)\n        at org.eclipse.birt.demo.RunReport.run(RunReport.java:184)\n        at org.eclipse.birt.demo.RunReport.main(RunReport.java:101)\nJan 24, 2006 2:49:23 PM org.eclipse.birt.report.engine.data.dte.DteDataEngine execute\nSEVERE: Cannot execute the statement.\n3 \u003e\u003d 3\norg.eclipse.birt.data.engine.core.DataException: Cannot execute the statement.\n3 \u003e\u003d 3\n        at org.eclipse.birt.data.engine.odaconsumer.PreparedStatement.execute(PreparedStatement.java\n:565)\n        at org.eclipse.birt.data.engine.executor.DataSourceQuery.execute(DataSourceQuery.java:490)\n        at org.eclipse.birt.data.engine.impl.PreparedExtendedDSQuery$ExtendedDSQueryExecutor.execute\nOdiQuery(PreparedExtendedDSQuery.java:313)\n        at org.eclipse.birt.data.engine.impl.PreparedQuery$Executor.execute(PreparedQuery.java:634)\n        at org.eclipse.birt.data.engine.impl.QueryResults.getResultIterator(QueryResults.java:105)\n        at org.eclipse.birt.report.engine.data.dte.DteDataEngine.execute(DteDataEngine.java:214)\n        at org.eclipse.birt.report.engine.executor.ExtendedItemExecutor.executeQueries(ExtendedItemE\nxecutor.java:215)\n        at org.eclipse.birt.report.engine.executor.ExtendedItemExecutor.generateInFactory(ExtendedIt\nemExecutor.java:166)\n        at org.eclipse.birt.report.engine.executor.ExtendedItemExecutor.generateContent(ExtendedItem\nExecutor.java:111)\n        at org.eclipse.birt.report.engine.executor.ExtendedItemExecutor.execute(ExtendedItemExecutor\n.java:91)\n        at org.eclipse.birt.report.engine.executor.ReportExecutorVisitor.visitExtendedItem(ReportExe\ncutorVisitor.java:81)\n        at org.eclipse.birt.report.engine.ir.ExtendedItemDesign.accept(ExtendedItemDesign.java:30)\n        at org.eclipse.birt.report.engine.executor.ReportExecutor.execute(ReportExecutor.java:159)\n        at org.eclipse.birt.report.engine.api.impl.RunAndRenderTask.run(RunAndRenderTask.java:198)\n        at org.eclipse.birt.demo.RunReport.run(RunReport.java:184)\n        at org.eclipse.birt.demo.RunReport.main(RunReport.java:101)\nCaused by: org.eclipse.datatools.connectivity.oda.OdaException: 3 \u003e\u003d 3\n        at org.eclipse.datatools.connectivity.oda.flatfile.Query.fetchQueriedDataFromFileToVector(Qu\nery.java:826)\n        at org.eclipse.datatools.connectivity.oda.flatfile.Query.executeQuery(Query.java:159)\n        at org.eclipse.datatools.connectivity.oda.consumer.helper.OdaQuery.doExecuteQuery(OdaQuery.j\nava:439)\n        at org.eclipse.datatools.connectivity.oda.consumer.helper.OdaQuery.executeQuery(OdaQuery.jav\na:404)\n        at org.eclipse.birt.data.engine.odaconsumer.PreparedStatement.execute(PreparedStatement.java\n:551)\n        ... 15 more\nJan 24, 2006 2:49:23 PM org.eclipse.birt.chart.log.impl.JavaUtilLoggerImpl log\nSEVERE: Exception\norg.eclipse.birt.chart.exception.ChartException: The DataSet bound to the chart returned no rows.\n        at org.eclipse.birt.chart.reportitem.ChartReportItemPresentationImpl.onRowSets(ChartReportIt\nemPresentationImpl.java:333)\n        at org.eclipse.birt.report.engine.presentation.LocalizedEmitter.startExtendedContent(Localiz\nedEmitter.java:494)\n        at org.eclipse.birt.report.engine.presentation.LocalizedEmitter.startForeign(LocalizedEmitte\nr.java:292)\n        at org.eclipse.birt.report.engine.presentation.WrappedEmitter.startForeign(WrappedEmitter.ja\nva:209)\n        at org.eclipse.birt.report.engine.presentation.DefaultPaginationEmitter.startForeign(Default\nPaginationEmitter.java:251)\n        at org.eclipse.birt.report.engine.executor.ExtendedItemExecutor.execute(ExtendedItemExecutor\n.java:100)\n        at org.eclipse.birt.report.engine.executor.ReportExecutorVisitor.visitExtendedItem(ReportExe\ncutorVisitor.java:81)\n        at org.eclipse.birt.report.engine.ir.ExtendedItemDesign.accept(ExtendedItemDesign.java:30)\n        at org.eclipse.birt.report.engine.executor.ReportExecutor.execute(ReportExecutor.java:159)\n        at org.eclipse.birt.report.engine.api.impl.RunAndRenderTask.run(RunAndRenderTask.java:198)\n        at org.eclipse.birt.demo.RunReport.run(RunReport.java:184)\n        at org.eclipse.birt.demo.RunReport.main(RunReport.java:101)\nJan 24, 2006 2:49:23 PM org.eclipse.birt.chart.log.impl.JavaUtilLoggerImpl log\nSEVERE: Exception\norg.eclipse.birt.chart.exception.ChartException: The DataSet bound to the chart returned no rows.\n        at org.eclipse.birt.chart.reportitem.ChartReportItemPresentationImpl.onRowSets(ChartReportIt\nemPresentationImpl.java:333)\n        at org.eclipse.birt.report.engine.presentation.LocalizedEmitter.startExtendedContent(Localiz\nedEmitter.java:494)\n        at org.eclipse.birt.report.engine.presentation.LocalizedEmitter.startForeign(LocalizedEmitte\nr.java:292)\n        at org.eclipse.birt.report.engine.presentation.WrappedEmitter.startForeign(WrappedEmitter.ja\nva:209)\n        at org.eclipse.birt.report.engine.presentation.DefaultPaginationEmitter.startForeign(Default\nPaginationEmitter.java:251)\n        at org.eclipse.birt.report.engine.executor.ExtendedItemExecutor.execute(ExtendedItemExecutor\n.java:100)\n        at org.eclipse.birt.report.engine.executor.ReportExecutorVisitor.visitExtendedItem(ReportExe\ncutorVisitor.java:81)\n        at org.eclipse.birt.report.engine.ir.ExtendedItemDesign.accept(ExtendedItemDesign.java:30)\n        at org.eclipse.birt.report.engine.executor.ReportExecutor.execute(ReportExecutor.java:159)\n        at org.eclipse.birt.report.engine.api.impl.RunAndRenderTask.run(RunAndRenderTask.java:198)\n        at org.eclipse.birt.demo.RunReport.run(RunReport.java:184)\n        at org.eclipse.birt.demo.RunReport.main(RunReport.java:101)\n\nNote:\nThis format works properly for excel sheets.",
    "This is an enhancement for flatfile ODA to two data tables in on one CSV file.\n\nThe work around would be to split these two tables into two different CSV files and define one dataset for each.\n\nlastly, please look into the source code of the flatfile ODA driver and see if you can modify it to meet your need. \n\n",
    "Actually the tailing comma leads to the exception.Furthermore, the current implementation of flat file driver only accept .csv files which host one and only one table.\n\nThe following is the correct format of the .csv file:\n\n----file1.csv-----\nCustomerName,CustomerAge\nSTRING,INT\na,1\nb,2\nc,3\n\n----file2.csv-----\nCustomerGroup,CustomerIncome\nSTRING,INT\nA1,12\nA2,23\nA3,34\n",
    "This bug is actually caused by using invalid csv file. Invalidate it as appropriate."
  ],
  "commentCreationDates": [
    "2006-01-24T09:21:44+01:00",
    "2006-02-05T07:39:30+01:00",
    "2006-02-10T16:22:05+01:00",
    "2007-02-05T09:46:47+01:00"
  ],
  "traces": [
    {
      "exceptionType": "org.eclipse.datatools.connectivity.oda.OdaException",
      "message": "3 \u003e\u003d 3",
      "elements": [
        {
          "method": "org.eclipse.datatools.connectivity.oda.flatfile.Query.fetchQueriedDataFromFileToVector",
          "source": "Qu ery.java:826"
        },
        {
          "method": "org.eclipse.datatools.connectivity.oda.flatfile.Query.executeQuery",
          "source": "Query.java:159"
        },
        {
          "method": "org.eclipse.datatools.connectivity.oda.consumer.helper.OdaQuery.doExecuteQuery",
          "source": "OdaQuery.j ava:439"
        },
        {
          "method": "org.eclipse.datatools.connectivity.oda.consumer.helper.OdaQuery.executeQuery",
          "source": "OdaQuery.jav a:404"
        },
        {
          "method": "org.eclipse.birt.data.engine.odaconsumer.PreparedStatement.execute",
          "source": "PreparedStatement.java :551"
        },
        {
          "method": "org.eclipse.birt.data.engine.executor.DataSourceQuery.execute",
          "source": "DataSourceQuery.java:490"
        },
        {
          "method": "org.eclipse.birt.data.engine.impl.PreparedExtendedDSQuery$ExtendedDSQueryExecutor.executeOdiQuery",
          "source": "PreparedExtendedDSQuery.java:313"
        },
        {
          "method": "org.eclipse.birt.data.engine.impl.PreparedQuery$Executor.execute",
          "source": "PreparedQuery.java:634"
        },
        {
          "method": "org.eclipse.birt.data.engine.impl.QueryResults.getResultIterator",
          "source": "QueryResults.java:105"
        },
        {
          "method": "org.eclipse.birt.report.engine.data.dte.DteDataEngine.execute",
          "source": "DteDataEngine.java:214"
        },
        {
          "method": "org.eclipse.birt.report.engine.executor.ExtendedItemExecutor.executeQueries",
          "source": "ExtendedItemE xecutor.java:215"
        },
        {
          "method": "org.eclipse.birt.report.engine.executor.ExtendedItemExecutor.generateInFactory",
          "source": "ExtendedIt emExecutor.java:166"
        },
        {
          "method": "org.eclipse.birt.report.engine.executor.ExtendedItemExecutor.generateContent",
          "source": "ExtendedItem Executor.java:111"
        },
        {
          "method": "org.eclipse.birt.report.engine.executor.ExtendedItemExecutor.execute",
          "source": "ExtendedItemExecutor .java:91"
        },
        {
          "method": "org.eclipse.birt.report.engine.executor.ReportExecutorVisitor.visitExtendedItem",
          "source": "ReportExe cutorVisitor.java:81"
        },
        {
          "method": "org.eclipse.birt.report.engine.ir.ExtendedItemDesign.accept",
          "source": "ExtendedItemDesign.java:30"
        },
        {
          "method": "org.eclipse.birt.report.engine.executor.ReportExecutor.execute",
          "source": "ReportExecutor.java:159"
        },
        {
          "method": "org.eclipse.birt.report.engine.api.impl.RunAndRenderTask.run",
          "source": "RunAndRenderTask.java:198"
        },
        {
          "method": "org.eclipse.birt.demo.RunReport.run",
          "source": "RunReport.java:184"
        },
        {
          "method": "org.eclipse.birt.demo.RunReport.main",
          "source": "RunReport.java:101"
        }
      ],
      "number": 0,
      "commentIndex": 0,
      "bugId": "124975",
      "date": "2006-01-24T09:21:44+01:00",
      "product": "BIRT",
      "component": "Data Access",
      "severity": "enhancement"
    },
    {
      "exceptionType": "org.eclipse.birt.data.engine.core.DataException",
      "message": "Cannot execute the statement. 3 \u003e\u003d 3",
      "elements": [
        {
          "method": "org.eclipse.birt.data.engine.odaconsumer.PreparedStatement.execute",
          "source": "PreparedStatement.java :565"
        },
        {
          "method": "org.eclipse.birt.data.engine.executor.DataSourceQuery.execute",
          "source": "DataSourceQuery.java:490"
        },
        {
          "method": "org.eclipse.birt.data.engine.impl.PreparedExtendedDSQuery$ExtendedDSQueryExecutor.executeOdiQuery",
          "source": "PreparedExtendedDSQuery.java:313"
        },
        {
          "method": "org.eclipse.birt.data.engine.impl.PreparedQuery$Executor.execute",
          "source": "PreparedQuery.java:634"
        },
        {
          "method": "org.eclipse.birt.data.engine.impl.QueryResults.getResultIterator",
          "source": "QueryResults.java:105"
        },
        {
          "method": "org.eclipse.birt.report.engine.data.dte.DteDataEngine.execute",
          "source": "DteDataEngine.java:214"
        },
        {
          "method": "org.eclipse.birt.report.engine.executor.ExtendedItemExecutor.executeQueries",
          "source": "ExtendedItemE xecutor.java:215"
        },
        {
          "method": "org.eclipse.birt.report.engine.executor.ExtendedItemExecutor.generateInFactory",
          "source": "ExtendedIt emExecutor.java:166"
        },
        {
          "method": "org.eclipse.birt.report.engine.executor.ExtendedItemExecutor.generateContent",
          "source": "ExtendedItem Executor.java:111"
        },
        {
          "method": "org.eclipse.birt.report.engine.executor.ExtendedItemExecutor.execute",
          "source": "ExtendedItemExecutor .java:91"
        },
        {
          "method": "org.eclipse.birt.report.engine.executor.ReportExecutorVisitor.visitExtendedItem",
          "source": "ReportExe cutorVisitor.java:81"
        },
        {
          "method": "org.eclipse.birt.report.engine.ir.ExtendedItemDesign.accept",
          "source": "ExtendedItemDesign.java:30"
        },
        {
          "method": "org.eclipse.birt.report.engine.executor.ReportExecutor.execute",
          "source": "ReportExecutor.java:159"
        },
        {
          "method": "org.eclipse.birt.report.engine.api.impl.RunAndRenderTask.run",
          "source": "RunAndRenderTask.java:198"
        },
        {
          "method": "org.eclipse.birt.demo.RunReport.run",
          "source": "RunReport.java:184"
        },
        {
          "method": "org.eclipse.birt.demo.RunReport.main",
          "source": "RunReport.java:101"
        }
      ],
      "causedBy": {
        "exceptionType": "org.eclipse.datatools.connectivity.oda.OdaException",
        "message": "3 \u003e\u003d 3",
        "elements": [
          {
            "method": "org.eclipse.datatools.connectivity.oda.flatfile.Query.fetchQueriedDataFromFileToVector",
            "source": "Qu ery.java:826"
          },
          {
            "method": "org.eclipse.datatools.connectivity.oda.flatfile.Query.executeQuery",
            "source": "Query.java:159"
          },
          {
            "method": "org.eclipse.datatools.connectivity.oda.consumer.helper.OdaQuery.doExecuteQuery",
            "source": "OdaQuery.j ava:439"
          },
          {
            "method": "org.eclipse.datatools.connectivity.oda.consumer.helper.OdaQuery.executeQuery",
            "source": "OdaQuery.jav a:404"
          },
          {
            "method": "org.eclipse.birt.data.engine.odaconsumer.PreparedStatement.execute",
            "source": "PreparedStatement.java :551"
          }
        ],
        "number": 0,
        "commentIndex": 0
      },
      "number": 1,
      "commentIndex": 0,
      "bugId": "124975",
      "date": "2006-01-24T09:21:44+01:00",
      "product": "BIRT",
      "component": "Data Access",
      "severity": "enhancement"
    },
    {
      "exceptionType": "org.eclipse.birt.chart.exception.ChartException",
      "message": "The DataSet bound to the chart returned no rows.",
      "elements": [
        {
          "method": "org.eclipse.birt.chart.reportitem.ChartReportItemPresentationImpl.onRowSets",
          "source": "ChartReportIt emPresentationImpl.java:333"
        },
        {
          "method": "org.eclipse.birt.report.engine.presentation.LocalizedEmitter.startExtendedContent",
          "source": "Localiz edEmitter.java:494"
        },
        {
          "method": "org.eclipse.birt.report.engine.presentation.LocalizedEmitter.startForeign",
          "source": "LocalizedEmitte r.java:292"
        },
        {
          "method": "org.eclipse.birt.report.engine.presentation.WrappedEmitter.startForeign",
          "source": "WrappedEmitter.ja va:209"
        },
        {
          "method": "org.eclipse.birt.report.engine.presentation.DefaultPaginationEmitter.startForeign",
          "source": "Default PaginationEmitter.java:251"
        },
        {
          "method": "org.eclipse.birt.report.engine.executor.ExtendedItemExecutor.execute",
          "source": "ExtendedItemExecutor .java:100"
        },
        {
          "method": "org.eclipse.birt.report.engine.executor.ReportExecutorVisitor.visitExtendedItem",
          "source": "ReportExe cutorVisitor.java:81"
        },
        {
          "method": "org.eclipse.birt.report.engine.ir.ExtendedItemDesign.accept",
          "source": "ExtendedItemDesign.java:30"
        },
        {
          "method": "org.eclipse.birt.report.engine.executor.ReportExecutor.execute",
          "source": "ReportExecutor.java:159"
        },
        {
          "method": "org.eclipse.birt.report.engine.api.impl.RunAndRenderTask.run",
          "source": "RunAndRenderTask.java:198"
        },
        {
          "method": "org.eclipse.birt.demo.RunReport.run",
          "source": "RunReport.java:184"
        },
        {
          "method": "org.eclipse.birt.demo.RunReport.main",
          "source": "RunReport.java:101"
        }
      ],
      "number": 2,
      "commentIndex": 0,
      "bugId": "124975",
      "date": "2006-01-24T09:21:44+01:00",
      "product": "BIRT",
      "component": "Data Access",
      "severity": "enhancement"
    },
    {
      "exceptionType": "org.eclipse.birt.chart.exception.ChartException",
      "message": "The DataSet bound to the chart returned no rows.",
      "elements": [
        {
          "method": "org.eclipse.birt.chart.reportitem.ChartReportItemPresentationImpl.onRowSets",
          "source": "ChartReportIt emPresentationImpl.java:333"
        },
        {
          "method": "org.eclipse.birt.report.engine.presentation.LocalizedEmitter.startExtendedContent",
          "source": "Localiz edEmitter.java:494"
        },
        {
          "method": "org.eclipse.birt.report.engine.presentation.LocalizedEmitter.startForeign",
          "source": "LocalizedEmitte r.java:292"
        },
        {
          "method": "org.eclipse.birt.report.engine.presentation.WrappedEmitter.startForeign",
          "source": "WrappedEmitter.ja va:209"
        },
        {
          "method": "org.eclipse.birt.report.engine.presentation.DefaultPaginationEmitter.startForeign",
          "source": "Default PaginationEmitter.java:251"
        },
        {
          "method": "org.eclipse.birt.report.engine.executor.ExtendedItemExecutor.execute",
          "source": "ExtendedItemExecutor .java:100"
        },
        {
          "method": "org.eclipse.birt.report.engine.executor.ReportExecutorVisitor.visitExtendedItem",
          "source": "ReportExe cutorVisitor.java:81"
        },
        {
          "method": "org.eclipse.birt.report.engine.ir.ExtendedItemDesign.accept",
          "source": "ExtendedItemDesign.java:30"
        },
        {
          "method": "org.eclipse.birt.report.engine.executor.ReportExecutor.execute",
          "source": "ReportExecutor.java:159"
        },
        {
          "method": "org.eclipse.birt.report.engine.api.impl.RunAndRenderTask.run",
          "source": "RunAndRenderTask.java:198"
        },
        {
          "method": "org.eclipse.birt.demo.RunReport.run",
          "source": "RunReport.java:184"
        },
        {
          "method": "org.eclipse.birt.demo.RunReport.main",
          "source": "RunReport.java:101"
        }
      ],
      "number": 3,
      "commentIndex": 0,
      "bugId": "124975",
      "date": "2006-01-24T09:21:44+01:00",
      "product": "BIRT",
      "component": "Data Access",
      "severity": "enhancement"
    }
  ],
  "groupId": "124975",
  "bugId": "124975",
  "date": "2006-01-24T09:21:44+01:00",
  "product": "BIRT",
  "component": "Data Access",
  "severity": "enhancement"
}