{
  "comments": [
    "My command line looks like this:\n\n\n%JAVACMD% -cp \"%BIRTCLASSPATH%\" -DBIRT_HOME\u003d\"%BIRT_HOME%\\Report Engine\" org.eclipse.birt.report.engine.api.ReportRunner  -f  PDF -o output  pdfTest.rptdesign \n\nIt would seem there is no way to specify the name of the output pdf file, I need different outputs for different parameters.\n\nI get the stacktrace below:\nWARNING: output\\pdfTest.PDF (The system cannot find the path specified)\njava.io.FileNotFoundException: output\\pdfTest.PDF (The system cannot find the pa\nth specified)\n        at java.io.FileOutputStream.open(Native Method)\n        at java.io.FileOutputStream.\u003cinit\u003e(FileOutputStream.java:179)\n        at java.io.FileOutputStream.\u003cinit\u003e(FileOutputStream.java:131)\n        at org.eclipse.birt.report.engine.emitter.pdf.PDFEmitter.initialize(PDFE\nmitter.java:172)\n        at org.eclipse.birt.report.engine.layout.impl.ReportLayoutEngine.initial\nize(ReportLayoutEngine.java:415)\n        at org.eclipse.birt.report.engine.presentation.WrappedEmitter.initialize\n(WrappedEmitter.java:44)\n        at org.eclipse.birt.report.engine.presentation.LocalizedEmitter.initiali\nze(LocalizedEmitter.java:129)\n        at org.eclipse.birt.report.engine.api.impl.RunAndRenderTask.createConten\ntEmitter(RunAndRenderTask.java:145)\n        at org.eclipse.birt.report.engine.api.impl.RunAndRenderTask.run(RunAndRe\nnderTask.java:174)\n        at org.eclipse.birt.report.engine.api.ReportRunner.runAndRenderReport(Re\nportRunner.java:232)\n        at org.eclipse.birt.report.engine.api.ReportRunner.execute(ReportRunner.\njava:158)\n        at org.eclipse.birt.report.engine.api.ReportRunner.main(ReportRunner.jav\na:129)",
    "Created an attachment (id\u003d33567)\npatch for this bug\n\nNow it works.\n",
    "Created an attachment (id\u003d33568)\npatch for this bug\n\n",
    "(In reply to comment #0)\n\u003e My command line looks like this:\n\u003e %JAVACMD% -cp \"%BIRTCLASSPATH%\" -DBIRT_HOME\u003d\"%BIRT_HOME%\\Report Engine\"\n\u003e org.eclipse.birt.report.engine.api.ReportRunner  -f  PDF -o output \n\u003e pdfTest.rptdesign \n\nThe command line was actually like this:\norg.eclipse.birt.report.engine.api.ReportRunner  -f PDF -o output.pdf  pdfTest.rptdesign\n\nThe problem was that the format was PDF and was getting compared with .pdf\n",
    "accepting this patch",
    "fixed"
  ],
  "commentCreationDates": [
    "2006-01-24T22:35:49+01:00",
    "2006-01-25T02:12:25+01:00",
    "2006-01-25T02:15:21+01:00",
    "2006-01-25T02:21:45+01:00",
    "2006-02-01T04:14:20+01:00",
    "2006-02-15T09:52:11+01:00"
  ],
  "traces": [
    {
      "exceptionType": "java.io.FileNotFoundException",
      "message": "output\\pdfTest.PDF (The system cannot find the pa th specified)",
      "elements": [
        {
          "method": "java.io.FileOutputStream.open",
          "source": "Native Method"
        },
        {
          "method": "java.io.FileOutputStream.\u003cinit\u003e",
          "source": "FileOutputStream.java:179"
        },
        {
          "method": "java.io.FileOutputStream.\u003cinit\u003e",
          "source": "FileOutputStream.java:131"
        },
        {
          "method": "org.eclipse.birt.report.engine.emitter.pdf.PDFEmitter.initialize",
          "source": "PDFE mitter.java:172"
        },
        {
          "method": "org.eclipse.birt.report.engine.layout.impl.ReportLayoutEngine.initialize",
          "source": "ReportLayoutEngine.java:415"
        },
        {
          "method": "org.eclipse.birt.report.engine.presentation.WrappedEmitter.initialize",
          "source": "WrappedEmitter.java:44"
        },
        {
          "method": "org.eclipse.birt.report.engine.presentation.LocalizedEmitter.initialize",
          "source": "LocalizedEmitter.java:129"
        },
        {
          "method": "org.eclipse.birt.report.engine.api.impl.RunAndRenderTask.createContentEmitter",
          "source": "RunAndRenderTask.java:145"
        },
        {
          "method": "org.eclipse.birt.report.engine.api.impl.RunAndRenderTask.run",
          "source": "RunAndRe nderTask.java:174"
        },
        {
          "method": "org.eclipse.birt.report.engine.api.ReportRunner.runAndRenderReport",
          "source": "Re portRunner.java:232"
        },
        {
          "method": "org.eclipse.birt.report.engine.api.ReportRunner.execute",
          "source": "ReportRunner. java:158"
        },
        {
          "method": "org.eclipse.birt.report.engine.api.ReportRunner.main",
          "source": "ReportRunner.jav a:129"
        }
      ],
      "number": 0,
      "commentIndex": 0,
      "bugId": "125084",
      "date": "2006-01-24T22:35:49+01:00",
      "product": "BIRT",
      "component": "Report Engine",
      "severity": "normal"
    }
  ],
  "groupId": "125084",
  "bugId": "125084",
  "date": "2006-01-24T22:35:49+01:00",
  "product": "BIRT",
  "component": "Report Engine",
  "severity": "normal"
}