{
  "comments": [
    "There is supposed to be an extension point from the model.jar named reportItemModel. I find one called reportItem but not reportItemModel, however, I looked back in the 1.0.1 files and see the exact same thing. My report worked until I upgraded to 2.0. So I would assume, either it didn\u0027t need to access the reportItemModel extension in 1.0.1 and now it does or I have something set up wrong in my new 2.0 installation. I now get this error when I run my code. \n\n\nJan 29, 2006 7:47:58 PM org.eclipse.birt.core.util.BirtTimer logTimeTaken\nINFO: Engine startup takes 313 Milliseconds.\nJan 29, 2006 7:47:59 PM org.eclipse.birt.report.model.metadata.ExtensionLoader load\nSEVERE: Message:The extension point [org.eclipse.birt.report.model.reportItemModel] is not found. Error code:EXTENSION_POINT_NOT_FOUND \njava.lang.NoClassDefFoundError: org/eclipse/datatools/connectivity/oda/util/manifest/ExtensionManifest\n\tat org.eclipse.birt.report.model.parser.ModuleState$DataSourcesState.startElement(ModuleState.java:140)\n\tat org.eclipse.birt.report.model.parser.ModuleParserHandler.startElement(ModuleParserHandler.java:158)\n\tat org.apache.crimson.parser.Parser2.maybeElement(Unknown Source)\n\tat org.apache.crimson.parser.Parser2.content(Unknown Source)\n\tat org.apache.crimson.parser.Parser2.maybeElement(Unknown Source)\n\tat org.apache.crimson.parser.Parser2.content(Unknown Source)\n\tat org.apache.crimson.parser.Parser2.maybeElement(Unknown Source)\n\tat org.apache.crimson.parser.Parser2.parseInternal(Unknown Source)\n\tat org.apache.crimson.parser.Parser2.parse(Unknown Source)\n\tat org.apache.crimson.parser.XMLReaderImpl.parse(Unknown Source)\n\tat javax.xml.parsers.SAXParser.parse(Unknown Source)\n\tat org.eclipse.birt.report.model.parser.ModuleReader.readModule(ModuleReader.java:89)\n\tat org.eclipse.birt.report.model.parser.ModuleReader.readModule(ModuleReader.java:171)\n\tat org.eclipse.birt.report.model.parser.DesignReader.read(DesignReader.java:135)\n\tat org.eclipse.birt.report.model.core.DesignSession.openDesign(DesignSession.java:177)\n\tat org.eclipse.birt.report.model.api.SessionHandle.openDesign(SessionHandle.java:133)\n\tat org.eclipse.birt.report.engine.parser.ReportParser.getDesignHandle(ReportParser.java:93)\n\tat org.eclipse.birt.report.engine.api.impl.ReportEngineHelper.openReportDesign(ReportEngineHelper.java:103)\n\tat org.eclipse.birt.report.engine.api.ReportEngine.openReportDesign(ReportEngine.java:219)\n\tat eventTrackMainScreen.EventTrackingMainScreen$5.mouseClicked(EventTrackingMainScreen.java:213)\n\tat java.awt.AWTEventMulticaster.mouseClicked(Unknown Source)\n\tat java.awt.Component.processMouseEvent(Unknown Source)\n\tat java.awt.Component.processEvent(Unknown Source)\n\tat java.awt.Container.processEvent(Unknown Source)\n\tat java.awt.Component.dispatchEventImpl(Unknown Source)\n\tat java.awt.Container.dispatchEventImpl(Unknown Source)\n\tat java.awt.Component.dispatchEvent(Unknown Source)\n\tat java.awt.LightweightDispatcher.retargetMouseEvent(Unknown Source)\n\tat java.awt.LightweightDispatcher.processMouseEvent(Unknown Source)\n\tat java.awt.LightweightDispatcher.dispatchEvent(Unknown Source)\n\tat java.awt.Container.dispatchEventImpl(Unknown Source)\n\tat java.awt.Window.dispatchEventImpl(Unknown Source)\n\tat java.awt.Component.dispatchEvent(Unknown Source)\n\tat java.awt.EventQueue.dispatchEvent(Unknown Source)\n\tat java.awt.EventDispatchThread.pumpOneEventForHierarchy(Unknown Source)\n\tat java.awt.EventDispatchThread.pumpEventsForHierarchy(Unknown Source)\n\tat java.awt.EventDispatchThread.pumpEvents(Unknown Source)\n\tat java.awt.EventDispatchThread.pumpEvents(Unknown Source)\n\tat java.awt.EventDispatchThread.run(Unknown Source)\n\nHere is the code I am running. I did change my Engine Home as requested by someone in a forum I read. This change is shown below. It didn\u0027t make a difference to my error. The line of code it errs out on is \"report \u003d engine.openReportDesign(entity_simple);\"\n\npublic void mouseClicked(MouseEvent e) {\n  \t  \t\tString format \u003d HTMLRenderOption.OUTPUT_FORMAT_PDF;\n  \t  \t\tEngineConfig config \u003d new EngineConfig();\n  \t  \t\tconfig.setEngineHome(\n  \t  \t\t\t\t\"C:/Program Files/Eclipse/eclipse/plugins/org.eclipse.birt.report.engine_2.0.0\");\n  \t  \t\tHTMLEmitterConfig hc \u003d new HTMLEmitterConfig();\n  \t  \t\tHTMLCompleteImageHandler imageHandler \u003d new HTMLCompleteImageHandler();\n  \t  \t\thc.setImageHandler(imageHandler);\n  \t  \t\tconfig.setEmitterConfiguration(HTMLRenderOption.OUTPUT_FORMAT_HTML, hc);\n  \t  \t\tReportEngine engine \u003d new ReportEngine(config);\n  \t  \t\tString entity_simple \u003d \"../Event_Tracking_Reports/entity_detailed.rptdesign\";\n  \t  \t\tIReportRunnable report \u003d null;\n  \t  \t\ttry\n  \t  \t\t{\n  \t  \t\t\treport \u003d engine.openReportDesign(entity_simple);\n  \t  \t\t}\n  \t  \t\tcatch(EngineException ee)\n  \t  \t\t{\n  \t  \t\t\tSystem.err.println(\"Report \" + entity_simple + \" not found!\\n\");\n  \t  \t\t\tengine.destroy();\n  \t  \t\t\treturn;\n  \t  \t\t}\n  \t  \t\tHashMap values \u003d new HashMap();\n  \t  \t\tObject type \u003d new String(\"%\");\n  \t  \t\tObject gender \u003d new String(\"%\");\n  \t  \t\tObject status \u003d new String(\"%\");\n  \t  \t\tObject age1 \u003d new String(\"26 years\");\n  \t  \t\tObject age2 \u003d new String(\"33 years\");\n  \t  \t\tvalues.put(\"entity_type\", type);\n  \t  \t\tvalues.put(\"gender\",gender);\n  \t  \t\tvalues.put(\"status\",status);\n  \t  \t\tvalues.put(\"age1\",age1);\n  \t  \t\tvalues.put(\"age2\",age2);\n  \t  \t\tparseParams(engine, report, values);\n  \t  \t\tIRunAndRenderTask task \u003d engine.createRunAndRenderTask(report);\n  \t  \t\tHTMLRenderOption options \u003d new HTMLRenderOption();\n  \t  \t\toptions.setOutputFormat(format);\n  \t  \t\tString output \u003d entity_simple.replaceFirst(\".rptdesign\", \".\" + format);\n  \t  \t\toptions.setOutputFileName(output);\n  \t  \t\ttask.setRenderOption(options);\n  \t  \t\ttask.setParameterValues(values);\n  \t  \t\ttry\n  \t  \t\t{\n  \t  \t\t\ttask.run();\n  \t  \t\t\tSystem.out.println(\"Created Report \" + output + \".\\n\");\n  \t  \t\t}\n  \t  \t\tcatch(EngineException ee1)\n  \t  \t\t{\n  \t  \t\t\tSystem.err.println(\"Report \" + entity_simple + \" run failed.\\n\");\n  \t  \t\t\tSystem.err.println(ee1.toString());\n  \t  \t\t}\n  \t  \t\tengine.destroy();\n\nPlease email me at abaile33@mymail.slcc.edu if any more information is needed or if my problem is just a programming problem. Thanks",
    "There is something wrong with the set-up config. The following code you wrote is wrong.\nEngineConfig config \u003d new EngineConfig();\n                        config.setEngineHome(\n                                        \"C:/Program\nFiles/Eclipse/eclipse/plugins/org.eclipse.birt.report.engine_2.0.0\");\nThe engine home must be \"C:/Program\nFiles/Eclipse/eclipse\". Then BIRT will search the extensions in the Engine_Home + \"/plugins\" package. Here Engine_Home is the value you set.",
    "Verified in build 20060215"
  ],
  "commentCreationDates": [
    "2006-01-30T04:36:22+01:00",
    "2006-02-06T03:15:29+01:00",
    "2006-02-15T07:58:01+01:00"
  ],
  "traces": [
    {
      "exceptionType": "java.lang.NoClassDefFoundError",
      "message": "org/eclipse/datatools/connectivity/oda/util/manifest/ExtensionManifest",
      "elements": [
        {
          "method": "org.eclipse.birt.report.model.parser.ModuleState$DataSourcesState.startElement",
          "source": "ModuleState.java:140"
        },
        {
          "method": "org.eclipse.birt.report.model.parser.ModuleParserHandler.startElement",
          "source": "ModuleParserHandler.java:158"
        },
        {
          "method": "org.apache.crimson.parser.Parser2.maybeElement",
          "source": "Unknown Source"
        },
        {
          "method": "org.apache.crimson.parser.Parser2.content",
          "source": "Unknown Source"
        },
        {
          "method": "org.apache.crimson.parser.Parser2.maybeElement",
          "source": "Unknown Source"
        },
        {
          "method": "org.apache.crimson.parser.Parser2.content",
          "source": "Unknown Source"
        },
        {
          "method": "org.apache.crimson.parser.Parser2.maybeElement",
          "source": "Unknown Source"
        },
        {
          "method": "org.apache.crimson.parser.Parser2.parseInternal",
          "source": "Unknown Source"
        },
        {
          "method": "org.apache.crimson.parser.Parser2.parse",
          "source": "Unknown Source"
        },
        {
          "method": "org.apache.crimson.parser.XMLReaderImpl.parse",
          "source": "Unknown Source"
        },
        {
          "method": "javax.xml.parsers.SAXParser.parse",
          "source": "Unknown Source"
        },
        {
          "method": "org.eclipse.birt.report.model.parser.ModuleReader.readModule",
          "source": "ModuleReader.java:89"
        },
        {
          "method": "org.eclipse.birt.report.model.parser.ModuleReader.readModule",
          "source": "ModuleReader.java:171"
        },
        {
          "method": "org.eclipse.birt.report.model.parser.DesignReader.read",
          "source": "DesignReader.java:135"
        },
        {
          "method": "org.eclipse.birt.report.model.core.DesignSession.openDesign",
          "source": "DesignSession.java:177"
        },
        {
          "method": "org.eclipse.birt.report.model.api.SessionHandle.openDesign",
          "source": "SessionHandle.java:133"
        },
        {
          "method": "org.eclipse.birt.report.engine.parser.ReportParser.getDesignHandle",
          "source": "ReportParser.java:93"
        },
        {
          "method": "org.eclipse.birt.report.engine.api.impl.ReportEngineHelper.openReportDesign",
          "source": "ReportEngineHelper.java:103"
        },
        {
          "method": "org.eclipse.birt.report.engine.api.ReportEngine.openReportDesign",
          "source": "ReportEngine.java:219"
        },
        {
          "method": "eventTrackMainScreen.EventTrackingMainScreen$5.mouseClicked",
          "source": "EventTrackingMainScreen.java:213"
        },
        {
          "method": "java.awt.AWTEventMulticaster.mouseClicked",
          "source": "Unknown Source"
        },
        {
          "method": "java.awt.Component.processMouseEvent",
          "source": "Unknown Source"
        },
        {
          "method": "java.awt.Component.processEvent",
          "source": "Unknown Source"
        },
        {
          "method": "java.awt.Container.processEvent",
          "source": "Unknown Source"
        },
        {
          "method": "java.awt.Component.dispatchEventImpl",
          "source": "Unknown Source"
        },
        {
          "method": "java.awt.Container.dispatchEventImpl",
          "source": "Unknown Source"
        },
        {
          "method": "java.awt.Component.dispatchEvent",
          "source": "Unknown Source"
        },
        {
          "method": "java.awt.LightweightDispatcher.retargetMouseEvent",
          "source": "Unknown Source"
        },
        {
          "method": "java.awt.LightweightDispatcher.processMouseEvent",
          "source": "Unknown Source"
        },
        {
          "method": "java.awt.LightweightDispatcher.dispatchEvent",
          "source": "Unknown Source"
        },
        {
          "method": "java.awt.Container.dispatchEventImpl",
          "source": "Unknown Source"
        },
        {
          "method": "java.awt.Window.dispatchEventImpl",
          "source": "Unknown Source"
        },
        {
          "method": "java.awt.Component.dispatchEvent",
          "source": "Unknown Source"
        },
        {
          "method": "java.awt.EventQueue.dispatchEvent",
          "source": "Unknown Source"
        },
        {
          "method": "java.awt.EventDispatchThread.pumpOneEventForHierarchy",
          "source": "Unknown Source"
        },
        {
          "method": "java.awt.EventDispatchThread.pumpEventsForHierarchy",
          "source": "Unknown Source"
        },
        {
          "method": "java.awt.EventDispatchThread.pumpEvents",
          "source": "Unknown Source"
        },
        {
          "method": "java.awt.EventDispatchThread.pumpEvents",
          "source": "Unknown Source"
        },
        {
          "method": "java.awt.EventDispatchThread.run",
          "source": "Unknown Source"
        }
      ],
      "number": 0,
      "commentIndex": 0,
      "bugId": "125665",
      "date": "2006-01-30T04:36:22+01:00",
      "product": "BIRT",
      "component": "Report",
      "severity": "blocker"
    }
  ],
  "groupId": "125665",
  "bugId": "125665",
  "date": "2006-01-30T04:36:22+01:00",
  "product": "BIRT",
  "component": "Report",
  "severity": "blocker"
}