{
  "comments": [
    "Build 20020328\n\n1. Have a thread suspended at a breakpoint and this thread has a native method \non its stack.\n2. In the java editor put the cursor over the definition of the selected method.\nObserve: You get the following stack trace in the console:\n\nLog: Tue Apr 02 12:24:57 CEST 2002\n4 org.eclipse.jdt.debug.ui 150 Internal Error\norg.eclipse.debug.core.DebugException: Variable information unavailable for \nnative methods\n        at \norg.eclipse.jdt.internal.debug.core.model.JDIDebugElement.requestFailed\n(JDIDebugElement.java:196)\n        at org.eclipse.jdt.internal.debug.core.model.JDIStackFrame.getVariables0\n(JDIStackFrame.java:211)\n        at org.eclipse.jdt.internal.debug.core.model.JDIStackFrame.getVariables\n(JDIStackFrame.java:201)\n        at org.eclipse.jdt.internal.debug.core.model.JDIStackFrame.findVariable\n(JDIStackFrame.java:544)\n        at org.eclipse.jdt.internal.debug.core.model.JDIThread.findVariable\n(JDIThread.java:1337)\n        at org.eclipse.jdt.internal.debug.core.model.JDIDebugTarget.findVariable\n(JDIDebugTarget.java:1314)\n        at org.eclipse.jdt.internal.debug.ui.JavaDebugHover.getHoverInfo\n(JavaDebugHover.java:73)\n        at \norg.eclipse.jdt.internal.ui.text.java.hover.JavaTextHover.getHoverInfo\n(JavaTextHover.java:300)\n        at org.eclipse.jface.text.TextViewerHoverManager.computeInformation\n(TextViewerHoverManager.java:56)\n        at \norg.eclipse.jface.text.AbstractInformationControlManager.showInformation\n(AbstractInformationControlManager.java:536)\n        at \norg.eclipse.jface.text.AbstractHoverInformationControlManager$MouseTracker.mouse\nHover(AbstractHoverInformationControlManager.java:233)\n        at org.eclipse.swt.widgets.TypedListener.handleEvent\n(TypedListener.java:207)\n        at org.eclipse.swt.widgets.EventTable.sendEvent(EventTable.java:75)\n        at org.eclipse.swt.widgets.Widget.notifyListeners(Widget.java:637)\n        at org.eclipse.swt.widgets.Display.runDeferredEvents(Display.java:1420)\n        at org.eclipse.swt.widgets.Display.readAndDispatch(Display.java:1208)\n        at org.eclipse.ui.internal.Workbench.runEventLoop(Workbench.java:755)\n        at org.eclipse.ui.internal.Workbench.run(Workbench.java:738)\n        at org.eclipse.core.internal.boot.InternalBootLoader.run\n(InternalBootLoader.java:777)\n        at org.eclipse.core.boot.BootLoader.run(BootLoader.java:319)\n        at java.lang.reflect.Method.invoke(Native Method)\n        at org.eclipse.core.launcher.Main.basicRun(Main.java:196)\n        at org.eclipse.core.launcher.Main.run(Main.java:555)\n        at org.eclipse.core.launcher.UIMain.main(UIMain.java:52)\n        4 org.eclipse.jdt.debug 5012 Variable information unavailable for \nnative methods",
    "Fixed in JDIStackFrame.\nAs well, changed findVariable to use getVariables0 instead of getVariables.\nPlease verify.",
    "Verified"
  ],
  "commentCreationDates": [
    "2002-04-02T11:41:24+02:00",
    "2002-04-03T04:33:30+02:00",
    "2002-04-09T16:10:20+02:00"
  ],
  "traces": [
    {
      "exceptionType": "org.eclipse.debug.core.DebugException",
      "message": "Variable information unavailable for  native methods",
      "elements": [
        {
          "method": "org.eclipse.jdt.internal.debug.core.model.JDIDebugElement.requestFailed",
          "source": "JDIDebugElement.java:196"
        },
        {
          "method": "org.eclipse.jdt.internal.debug.core.model.JDIStackFrame.getVariables0",
          "source": "JDIStackFrame.java:211"
        },
        {
          "method": "org.eclipse.jdt.internal.debug.core.model.JDIStackFrame.getVariables",
          "source": "JDIStackFrame.java:201"
        },
        {
          "method": "org.eclipse.jdt.internal.debug.core.model.JDIStackFrame.findVariable",
          "source": "JDIStackFrame.java:544"
        },
        {
          "method": "org.eclipse.jdt.internal.debug.core.model.JDIThread.findVariable",
          "source": "JDIThread.java:1337"
        },
        {
          "method": "org.eclipse.jdt.internal.debug.core.model.JDIDebugTarget.findVariable",
          "source": "JDIDebugTarget.java:1314"
        },
        {
          "method": "org.eclipse.jdt.internal.debug.ui.JavaDebugHover.getHoverInfo",
          "source": "JavaDebugHover.java:73"
        },
        {
          "method": "org.eclipse.jdt.internal.ui.text.java.hover.JavaTextHover.getHoverInfo",
          "source": "JavaTextHover.java:300"
        },
        {
          "method": "org.eclipse.jface.text.TextViewerHoverManager.computeInformation",
          "source": "TextViewerHoverManager.java:56"
        },
        {
          "method": "org.eclipse.jface.text.AbstractInformationControlManager.showInformation",
          "source": "AbstractInformationControlManager.java:536"
        },
        {
          "method": "org.eclipse.jface.text.AbstractHoverInformationControlManager$MouseTracker.mouseHover",
          "source": "AbstractHoverInformationControlManager.java:233"
        },
        {
          "method": "org.eclipse.swt.widgets.TypedListener.handleEvent",
          "source": "TypedListener.java:207"
        },
        {
          "method": "org.eclipse.swt.widgets.EventTable.sendEvent",
          "source": "EventTable.java:75"
        },
        {
          "method": "org.eclipse.swt.widgets.Widget.notifyListeners",
          "source": "Widget.java:637"
        },
        {
          "method": "org.eclipse.swt.widgets.Display.runDeferredEvents",
          "source": "Display.java:1420"
        },
        {
          "method": "org.eclipse.swt.widgets.Display.readAndDispatch",
          "source": "Display.java:1208"
        },
        {
          "method": "org.eclipse.ui.internal.Workbench.runEventLoop",
          "source": "Workbench.java:755"
        },
        {
          "method": "org.eclipse.ui.internal.Workbench.run",
          "source": "Workbench.java:738"
        },
        {
          "method": "org.eclipse.core.internal.boot.InternalBootLoader.run",
          "source": "InternalBootLoader.java:777"
        },
        {
          "method": "org.eclipse.core.boot.BootLoader.run",
          "source": "BootLoader.java:319"
        },
        {
          "method": "java.lang.reflect.Method.invoke",
          "source": "Native Method"
        },
        {
          "method": "org.eclipse.core.launcher.Main.basicRun",
          "source": "Main.java:196"
        },
        {
          "method": "org.eclipse.core.launcher.Main.run",
          "source": "Main.java:555"
        },
        {
          "method": "org.eclipse.core.launcher.UIMain.main",
          "source": "UIMain.java:52"
        }
      ],
      "number": 0,
      "commentIndex": 0,
      "bugId": "12591",
      "date": "2002-04-02T11:41:24+02:00",
      "product": "JDT",
      "component": "Debug",
      "severity": "normal"
    }
  ],
  "groupId": "12591",
  "bugId": "12591",
  "date": "2002-04-02T11:41:24+02:00",
  "product": "JDT",
  "component": "Debug",
  "severity": "normal"
}