{
  "comments": [
    "I20060131-1200\n\nFound in console but not in .log. Sorry no steps.\n\nUnhandled event loop exception during blocked modal context.\norg.eclipse.swt.SWTException: Failed to execute runnable (java.lang.NullPointerException)\n        at org.eclipse.swt.SWT.error(SWT.java:3283)\n        at org.eclipse.swt.SWT.error(SWT.java:3206)\n        at org.eclipse.swt.widgets.Synchronizer.runAsyncMessages(Synchronizer.java:126)\n        at org.eclipse.swt.widgets.Display.runAsyncMessages(Display.java:3264)\n        at org.eclipse.swt.widgets.Display.readAndDispatch(Display.java:2910)\n        at org.eclipse.jface.operation.ModalContext$ModalContextThread.block(ModalContext.java:156)\n        at org.eclipse.jface.operation.ModalContext.run(ModalContext.java:317)\n        at org.eclipse.jface.dialogs.ProgressMonitorDialog.run(ProgressMonitorDialog.java:453)\n        at org.eclipse.ui.internal.progress.ProgressMonitorJobsDialog.run(ProgressMonitorJobsDialog.java:261)\n        at org.eclipse.ui.internal.progress.ProgressManager$3.run(ProgressManager.java:866)\n        at org.eclipse.swt.custom.BusyIndicator.showWhile(BusyIndicator.java:69)\n        at org.eclipse.ui.internal.progress.ProgressManager.busyCursorWhile(ProgressManager.java:900)\n        at org.eclipse.ui.internal.progress.ProgressManager.busyCursorWhile(ProgressManager.java:876)\n        at org.eclipse.team.internal.ui.synchronize.actions.RemoveSynchronizeParticipantAction.run(RemoveSynchronizeParticipantAction.java:49)\n        at org.eclipse.jface.action.Action.runWithEvent(Action.java:492)\n        at org.eclipse.jface.action.ActionContributionItem.handleWidgetSelection(ActionContributionItem.java:530)\n        at org.eclipse.jface.action.ActionContributionItem.access$2(ActionContributionItem.java:480)\n        at org.eclipse.jface.action.ActionContributionItem$5.handleEvent(ActionContributionItem.java:392)\n        at org.eclipse.swt.widgets.EventTable.sendEvent(EventTable.java:66)\n        at org.eclipse.swt.widgets.Widget.sendEvent(Widget.java:920)\n        at org.eclipse.swt.widgets.Display.runDeferredEvents(Display.java:3287)\n        at org.eclipse.swt.widgets.Display.readAndDispatch(Display.java:2907)\n        at org.eclipse.ui.internal.Workbench.runEventLoop(Workbench.java:1792)\n        at org.eclipse.ui.internal.Workbench.runUI(Workbench.java:1756)\n        at org.eclipse.ui.internal.Workbench.createAndRunWorkbench(Workbench.java:401)\n        at org.eclipse.ui.PlatformUI.createAndRunWorkbench(PlatformUI.java:143)\n        at org.eclipse.ui.internal.ide.IDEApplication.run(IDEApplication.java:106)\n        at org.eclipse.core.internal.runtime.PlatformActivator$1.run(PlatformActivator.java:109)\n        at org.eclipse.core.runtime.internal.adaptor.EclipseAppLauncher.runApplication(EclipseAppLauncher.java:93)\n        at org.eclipse.core.runtime.internal.adaptor.EclipseAppLauncher.start(EclipseAppLauncher.java:69)\n        at org.eclipse.core.runtime.adaptor.EclipseStarter.run(EclipseStarter.java:374)\n        at org.eclipse.core.runtime.adaptor.EclipseStarter.run(EclipseStarter.java:169)\n        at sun.reflect.NativeMethodAccessorImpl.invoke0(Native Method)\n        at sun.reflect.NativeMethodAccessorImpl.invoke(NativeMethodAccessorImpl.java:39)\n        at sun.reflect.DelegatingMethodAccessorImpl.invoke(DelegatingMethodAccessorImpl.java:25)\n        at java.lang.reflect.Method.invoke(Method.java:585)\n        at org.eclipse.core.launcher.Main.invokeFramework(Main.java:338)\n        at org.eclipse.core.launcher.Main.basicRun(Main.java:282)\n        at org.eclipse.core.launcher.Main.run(Main.java:977)\n        at org.eclipse.core.launcher.Main.main(Main.java:952)\nCaused by: java.lang.NullPointerException\n        at org.eclipse.team.internal.ui.synchronize.SynchronizeView.clearCrossReferenceCache(SynchronizeView.java:162)\n        at org.eclipse.team.internal.ui.synchronize.SynchronizeView.access$2(SynchronizeView.java:160)\n        at org.eclipse.team.internal.ui.synchronize.SynchronizeView$1.run(SynchronizeView.java:275)\n        at org.eclipse.swt.widgets.RunnableLock.run(RunnableLock.java:35)\n        at org.eclipse.swt.widgets.Synchronizer.runAsyncMessages(Synchronizer.java:123)\n        ... 37 more",
    "Fixed"
  ],
  "commentCreationDates": [
    "2006-02-07T09:38:30+01:00",
    "2006-02-07T11:00:25+01:00"
  ],
  "traces": [
    {
      "exceptionType": "org.eclipse.swt.SWTException",
      "message": "Failed to execute runnable (java.lang.NullPointerException)",
      "elements": [
        {
          "method": "org.eclipse.swt.SWT.error",
          "source": "SWT.java:3283"
        },
        {
          "method": "org.eclipse.swt.SWT.error",
          "source": "SWT.java:3206"
        },
        {
          "method": "org.eclipse.swt.widgets.Synchronizer.runAsyncMessages",
          "source": "Synchronizer.java:126"
        },
        {
          "method": "org.eclipse.swt.widgets.Display.runAsyncMessages",
          "source": "Display.java:3264"
        },
        {
          "method": "org.eclipse.swt.widgets.Display.readAndDispatch",
          "source": "Display.java:2910"
        },
        {
          "method": "org.eclipse.jface.operation.ModalContext$ModalContextThread.block",
          "source": "ModalContext.java:156"
        },
        {
          "method": "org.eclipse.jface.operation.ModalContext.run",
          "source": "ModalContext.java:317"
        },
        {
          "method": "org.eclipse.jface.dialogs.ProgressMonitorDialog.run",
          "source": "ProgressMonitorDialog.java:453"
        },
        {
          "method": "org.eclipse.ui.internal.progress.ProgressMonitorJobsDialog.run",
          "source": "ProgressMonitorJobsDialog.java:261"
        },
        {
          "method": "org.eclipse.ui.internal.progress.ProgressManager$3.run",
          "source": "ProgressManager.java:866"
        },
        {
          "method": "org.eclipse.swt.custom.BusyIndicator.showWhile",
          "source": "BusyIndicator.java:69"
        },
        {
          "method": "org.eclipse.ui.internal.progress.ProgressManager.busyCursorWhile",
          "source": "ProgressManager.java:900"
        },
        {
          "method": "org.eclipse.ui.internal.progress.ProgressManager.busyCursorWhile",
          "source": "ProgressManager.java:876"
        },
        {
          "method": "org.eclipse.team.internal.ui.synchronize.actions.RemoveSynchronizeParticipantAction.run",
          "source": "RemoveSynchronizeParticipantAction.java:49"
        },
        {
          "method": "org.eclipse.jface.action.Action.runWithEvent",
          "source": "Action.java:492"
        },
        {
          "method": "org.eclipse.jface.action.ActionContributionItem.handleWidgetSelection",
          "source": "ActionContributionItem.java:530"
        },
        {
          "method": "org.eclipse.jface.action.ActionContributionItem.access$2",
          "source": "ActionContributionItem.java:480"
        },
        {
          "method": "org.eclipse.jface.action.ActionContributionItem$5.handleEvent",
          "source": "ActionContributionItem.java:392"
        },
        {
          "method": "org.eclipse.swt.widgets.EventTable.sendEvent",
          "source": "EventTable.java:66"
        },
        {
          "method": "org.eclipse.swt.widgets.Widget.sendEvent",
          "source": "Widget.java:920"
        },
        {
          "method": "org.eclipse.swt.widgets.Display.runDeferredEvents",
          "source": "Display.java:3287"
        },
        {
          "method": "org.eclipse.swt.widgets.Display.readAndDispatch",
          "source": "Display.java:2907"
        },
        {
          "method": "org.eclipse.ui.internal.Workbench.runEventLoop",
          "source": "Workbench.java:1792"
        },
        {
          "method": "org.eclipse.ui.internal.Workbench.runUI",
          "source": "Workbench.java:1756"
        },
        {
          "method": "org.eclipse.ui.internal.Workbench.createAndRunWorkbench",
          "source": "Workbench.java:401"
        },
        {
          "method": "org.eclipse.ui.PlatformUI.createAndRunWorkbench",
          "source": "PlatformUI.java:143"
        },
        {
          "method": "org.eclipse.ui.internal.ide.IDEApplication.run",
          "source": "IDEApplication.java:106"
        },
        {
          "method": "org.eclipse.core.internal.runtime.PlatformActivator$1.run",
          "source": "PlatformActivator.java:109"
        },
        {
          "method": "org.eclipse.core.runtime.internal.adaptor.EclipseAppLauncher.runApplication",
          "source": "EclipseAppLauncher.java:93"
        },
        {
          "method": "org.eclipse.core.runtime.internal.adaptor.EclipseAppLauncher.start",
          "source": "EclipseAppLauncher.java:69"
        },
        {
          "method": "org.eclipse.core.runtime.adaptor.EclipseStarter.run",
          "source": "EclipseStarter.java:374"
        },
        {
          "method": "org.eclipse.core.runtime.adaptor.EclipseStarter.run",
          "source": "EclipseStarter.java:169"
        },
        {
          "method": "sun.reflect.NativeMethodAccessorImpl.invoke0",
          "source": "Native Method"
        },
        {
          "method": "sun.reflect.NativeMethodAccessorImpl.invoke",
          "source": "NativeMethodAccessorImpl.java:39"
        },
        {
          "method": "sun.reflect.DelegatingMethodAccessorImpl.invoke",
          "source": "DelegatingMethodAccessorImpl.java:25"
        },
        {
          "method": "java.lang.reflect.Method.invoke",
          "source": "Method.java:585"
        },
        {
          "method": "org.eclipse.core.launcher.Main.invokeFramework",
          "source": "Main.java:338"
        },
        {
          "method": "org.eclipse.core.launcher.Main.basicRun",
          "source": "Main.java:282"
        },
        {
          "method": "org.eclipse.core.launcher.Main.run",
          "source": "Main.java:977"
        },
        {
          "method": "org.eclipse.core.launcher.Main.main",
          "source": "Main.java:952"
        }
      ],
      "causedBy": {
        "exceptionType": "java.lang.NullPointerException",
        "elements": [
          {
            "method": "org.eclipse.team.internal.ui.synchronize.SynchronizeView.clearCrossReferenceCache",
            "source": "SynchronizeView.java:162"
          },
          {
            "method": "org.eclipse.team.internal.ui.synchronize.SynchronizeView.access$2",
            "source": "SynchronizeView.java:160"
          },
          {
            "method": "org.eclipse.team.internal.ui.synchronize.SynchronizeView$1.run",
            "source": "SynchronizeView.java:275"
          },
          {
            "method": "org.eclipse.swt.widgets.RunnableLock.run",
            "source": "RunnableLock.java:35"
          },
          {
            "method": "org.eclipse.swt.widgets.Synchronizer.runAsyncMessages",
            "source": "Synchronizer.java:123"
          }
        ],
        "number": 0,
        "commentIndex": 0
      },
      "number": 0,
      "commentIndex": 0,
      "bugId": "126704",
      "date": "2006-02-07T09:38:30+01:00",
      "product": "Platform",
      "component": "Team",
      "severity": "normal"
    }
  ],
  "groupId": "126704",
  "bugId": "126704",
  "date": "2006-02-07T09:38:30+01:00",
  "product": "Platform",
  "component": "Team",
  "severity": "normal"
}