{
  "comments": [
    "I tried to use xerces 2.0.1 in the scrapebook. My Buildpath contains the correkt\nxerces.jar and I typed in the scrapbook:\n\njavax.xml.parsers.DocumentBuilderFactory.newInstance();\n\nI got this Error (I activated debugPrintln in javax.xml.parsers.FactoryFinder in\nthe xerces sources):\n\nJAXP: debug is on\nJAXP: loaded from fallback value: org.apache.xerces.jaxp.DocumentBuilderFactoryImpl\njavax.xml.parsers.FactoryConfigurationError: Provider\norg.apache.xerces.jaxp.DocumentBuilderFactoryImpl not found\n\tat\njavax.xml.parsers.DocumentBuilderFactory.newInstance(DocumentBuilderFactory.java:145)\n\tat CodeSnippet_30.run(CodeSnippet_30.java:3)\n\tat\norg.eclipse.jdt.internal.debug.ui.snippeteditor.ScrapbookMain1.eval(ScrapbookMain1.java:14)\n\tat java.lang.reflect.Method.invoke(Native Method)\n\tat\norg.eclipse.jdt.internal.debug.ui.snippeteditor.ScrapbookMain.evalLoop(ScrapbookMain.java:46)\n\tat\norg.eclipse.jdt.internal.debug.ui.snippeteditor.ScrapbookMain.main(ScrapbookMain.java:27)\n\t\nThe problematic xerces-code is in javax/xml/parsers/FactoryFinder.newInstance:\n\ntry {\n    Class spiClass;\n    if (classLoader \u003d\u003d null) {\n        spiClass \u003d Class.forName(className);\n    } else {\n        spiClass \u003d classLoader.loadClass(className);\n    }\n    return spiClass.newInstance();\n} catch (ClassNotFoundException x) {\n    throw new ConfigurationError(\n        \"Provider \" + className + \" not found\", x);\n} catch (Exception x) {\n    throw new ConfigurationError(\n        \"Provider \" + className + \" could not be instantiated: \" + x,\n        x);\n}\n\nif I use always the first if-body, everything works fine. However normaly,\nclassLoader isnt null and I get the FactoryConfigurationError above. Outside\neclipse there are of course no problems with that.\nUnfortunetly I cannot further qualify this behaviour, but maybe my bugreport helps.",
    "I was able to execute the code successfully. Is \"org.appache.xerces\" on the \nclasspath of the project containing the scrapbook file? It will need to be able \nto see the code."
  ],
  "commentCreationDates": [
    "2002-04-03T14:56:41+02:00",
    "2002-04-09T22:23:58+02:00"
  ],
  "traces": [
    {
      "exceptionType": "javax.xml.parsers.FactoryConfigurationError",
      "message": "Provider org.apache.xerces.jaxp.DocumentBuilderFactoryImpl not found",
      "elements": [
        {
          "method": "javax.xml.parsers.DocumentBuilderFactory.newInstance",
          "source": "DocumentBuilderFactory.java:145"
        },
        {
          "method": "CodeSnippet_30.run",
          "source": "CodeSnippet_30.java:3"
        },
        {
          "method": "org.eclipse.jdt.internal.debug.ui.snippeteditor.ScrapbookMain1.eval",
          "source": "ScrapbookMain1.java:14"
        },
        {
          "method": "java.lang.reflect.Method.invoke",
          "source": "Native Method"
        },
        {
          "method": "org.eclipse.jdt.internal.debug.ui.snippeteditor.ScrapbookMain.evalLoop",
          "source": "ScrapbookMain.java:46"
        },
        {
          "method": "org.eclipse.jdt.internal.debug.ui.snippeteditor.ScrapbookMain.main",
          "source": "ScrapbookMain.java:27"
        }
      ],
      "number": 0,
      "commentIndex": 0,
      "bugId": "12681",
      "date": "2002-04-03T14:56:41+02:00",
      "product": "JDT",
      "component": "Debug",
      "severity": "normal"
    }
  ],
  "groupId": "12681",
  "bugId": "12681",
  "date": "2002-04-03T14:56:41+02:00",
  "product": "JDT",
  "component": "Debug",
  "severity": "normal"
}