{
  "comments": [
    "I20060208-0848 + plugins for smoke test\n\nType an \"@\" in a javadoc. Content assist opens, Exception in log:\n\n!ENTRY org.eclipse.ui 4 0 2006-02-10 13:01:55.872\n!MESSAGE Failed to execute runnable (org.eclipse.jface.util.Assert$AssertionFailedException: null argument;)\n!STACK 0\norg.eclipse.swt.SWTException: Failed to execute runnable (org.eclipse.jface.util.Assert$AssertionFailedException: null argument;)\n        at org.eclipse.swt.SWT.error(SWT.java:3349)\n        at org.eclipse.swt.SWT.error(SWT.java:3272)\n        at org.eclipse.swt.widgets.Synchronizer.runAsyncMessages(Synchronizer.java:126)\n        at org.eclipse.swt.widgets.Display.runAsyncMessages(Display.java:3264)\n        at org.eclipse.swt.widgets.Display.readAndDispatch(Display.java:2910)\n        at org.eclipse.ui.internal.Workbench.runEventLoop(Workbench.java:1793)\n        at org.eclipse.ui.internal.Workbench.runUI(Workbench.java:1757)\n        at org.eclipse.ui.internal.Workbench.createAndRunWorkbench(Workbench.java:402)\n        at org.eclipse.ui.PlatformUI.createAndRunWorkbench(PlatformUI.java:143)\n        at org.eclipse.ui.internal.ide.IDEApplication.run(IDEApplication.java:106)\n        at org.eclipse.core.internal.runtime.PlatformActivator$1.run(PlatformActivator.java:109)\n        at org.eclipse.core.runtime.internal.adaptor.EclipseAppLauncher.runApplication(EclipseAppLauncher.java:92)\n        at org.eclipse.core.runtime.internal.adaptor.EclipseAppLauncher.start(EclipseAppLauncher.java:68)\n        at org.eclipse.core.runtime.adaptor.EclipseStarter.run(EclipseStarter.java:374)\n        at org.eclipse.core.runtime.adaptor.EclipseStarter.run(EclipseStarter.java:169)\n        at sun.reflect.NativeMethodAccessorImpl.invoke0(Native Method)\n        at sun.reflect.NativeMethodAccessorImpl.invoke(NativeMethodAccessorImpl.java:39)\n        at sun.reflect.DelegatingMethodAccessorImpl.invoke(DelegatingMethodAccessorImpl.java:25)\n        at java.lang.reflect.Method.invoke(Method.java:585)\n        at org.eclipse.core.launcher.Main.invokeFramework(Main.java:338)\n        at org.eclipse.core.launcher.Main.basicRun(Main.java:282)\n        at org.eclipse.core.launcher.Main.run(Main.java:977)\n        at org.eclipse.core.launcher.Main.main(Main.java:952)\nCaused by: org.eclipse.jface.util.Assert$AssertionFailedException: null argument;\n        at org.eclipse.jface.util.Assert.isNotNull(Assert.java:149)\n        at org.eclipse.jface.util.Assert.isNotNull(Assert.java:125)\n        at org.eclipse.jdt.internal.ui.text.correction.JavaCorrectionAssistant.\u003cinit\u003e(JavaCorrectionAssistant.java:70)\n        at org.eclipse.jdt.ui.text.JavaSourceViewerConfiguration.getQuickAssistAssistant(JavaSourceViewerConfiguration.java:428)\n        at org.eclipse.jface.text.source.SourceViewer.configure(SourceViewer.java:360)\n        at org.eclipse.jdt.internal.ui.javaeditor.JavaSourceViewer.configure(JavaSourceViewer.java:214)\n        at org.eclipse.jdt.internal.ui.text.java.hover.SourceViewerInformationControl.\u003cinit\u003e(SourceViewerInformationControl.java:137)\n        at org.eclipse.jdt.internal.ui.text.java.hover.SourceViewerInformationControl.\u003cinit\u003e(SourceViewerInformationControl.java:90)\n        at org.eclipse.jdt.internal.ui.text.java.hover.SourceViewerInformationControl.\u003cinit\u003e(SourceViewerInformationControl.java:193)\n        at org.eclipse.jdt.internal.ui.text.java.hover.SourceViewerInformationControl.\u003cinit\u003e(SourceViewerInformationControl.java:219)\n        at org.eclipse.jdt.internal.ui.text.template.contentassist.TemplateInformationControlCreator.createInformationControl(TemplateInformationContr\nolCreator.java:35)\n        at org.eclipse.jface.text.AbstractInformationControlManager.getInformationControl(AbstractInformationControlManager.java:619)\n        at org.eclipse.jface.text.AbstractInformationControlManager.internalShowInformationControl(AbstractInformationControlManager.java:850)\n        at org.eclipse.jface.text.AbstractInformationControlManager.presentInformation(AbstractInformationControlManager.java:836)\n        at org.eclipse.jface.text.AbstractInformationControlManager.setInformation(AbstractInformationControlManager.java:291)\n        at org.eclipse.jface.text.contentassist.AdditionalInfoController.computeInformation(AdditionalInfoController.java:236)\n        at org.eclipse.jface.text.AbstractInformationControlManager.doShowInformation(AbstractInformationControlManager.java:820)\n        at org.eclipse.jface.text.AbstractInformationControlManager.showInformation(AbstractInformationControlManager.java:810)\n        at org.eclipse.jface.text.contentassist.AdditionalInfoController$1.run(AdditionalInfoController.java:173)\n        at org.eclipse.swt.widgets.RunnableLock.run(RunnableLock.java:35)\n        at org.eclipse.swt.widgets.Synchronizer.runAsyncMessages(Synchronizer.java:123)",
    "The same AFE also makes \u0027Compare with Local History\u0027 fail (Exceptions, dialog partly empty, etc.)",
    "Fixed in HEAD.\nAvailable in builds \u003e\u003d I20060210-0800.",
    "Verified in I20060214-0010."
  ],
  "commentCreationDates": [
    "2006-02-10T12:03:43+01:00",
    "2006-02-10T12:06:47+01:00",
    "2006-02-10T12:12:41+01:00",
    "2006-02-14T15:28:25+01:00"
  ],
  "traces": [
    {
      "exceptionType": "org.eclipse.jface.util.Assert$AssertionFailedException",
      "message": "null argument;)",
      "elements": [
        {
          "method": "org.eclipse.swt.SWT.error",
          "source": "SWT.java:3349"
        },
        {
          "method": "org.eclipse.swt.SWT.error",
          "source": "SWT.java:3272"
        },
        {
          "method": "org.eclipse.swt.widgets.Synchronizer.runAsyncMessages",
          "source": "Synchronizer.java:126"
        },
        {
          "method": "org.eclipse.swt.widgets.Display.runAsyncMessages",
          "source": "Display.java:3264"
        },
        {
          "method": "org.eclipse.swt.widgets.Display.readAndDispatch",
          "source": "Display.java:2910"
        },
        {
          "method": "org.eclipse.ui.internal.Workbench.runEventLoop",
          "source": "Workbench.java:1793"
        },
        {
          "method": "org.eclipse.ui.internal.Workbench.runUI",
          "source": "Workbench.java:1757"
        },
        {
          "method": "org.eclipse.ui.internal.Workbench.createAndRunWorkbench",
          "source": "Workbench.java:402"
        },
        {
          "method": "org.eclipse.ui.PlatformUI.createAndRunWorkbench",
          "source": "PlatformUI.java:143"
        },
        {
          "method": "org.eclipse.ui.internal.ide.IDEApplication.run",
          "source": "IDEApplication.java:106"
        },
        {
          "method": "org.eclipse.core.internal.runtime.PlatformActivator$1.run",
          "source": "PlatformActivator.java:109"
        },
        {
          "method": "org.eclipse.core.runtime.internal.adaptor.EclipseAppLauncher.runApplication",
          "source": "EclipseAppLauncher.java:92"
        },
        {
          "method": "org.eclipse.core.runtime.internal.adaptor.EclipseAppLauncher.start",
          "source": "EclipseAppLauncher.java:68"
        },
        {
          "method": "org.eclipse.core.runtime.adaptor.EclipseStarter.run",
          "source": "EclipseStarter.java:374"
        },
        {
          "method": "org.eclipse.core.runtime.adaptor.EclipseStarter.run",
          "source": "EclipseStarter.java:169"
        },
        {
          "method": "sun.reflect.NativeMethodAccessorImpl.invoke0",
          "source": "Native Method"
        },
        {
          "method": "sun.reflect.NativeMethodAccessorImpl.invoke",
          "source": "NativeMethodAccessorImpl.java:39"
        },
        {
          "method": "sun.reflect.DelegatingMethodAccessorImpl.invoke",
          "source": "DelegatingMethodAccessorImpl.java:25"
        },
        {
          "method": "java.lang.reflect.Method.invoke",
          "source": "Method.java:585"
        },
        {
          "method": "org.eclipse.core.launcher.Main.invokeFramework",
          "source": "Main.java:338"
        },
        {
          "method": "org.eclipse.core.launcher.Main.basicRun",
          "source": "Main.java:282"
        },
        {
          "method": "org.eclipse.core.launcher.Main.run",
          "source": "Main.java:977"
        },
        {
          "method": "org.eclipse.core.launcher.Main.main",
          "source": "Main.java:952"
        }
      ],
      "causedBy": {
        "exceptionType": "org.eclipse.jface.util.Assert$AssertionFailedException",
        "message": "null argument;",
        "elements": [
          {
            "method": "org.eclipse.jface.util.Assert.isNotNull",
            "source": "Assert.java:149"
          },
          {
            "method": "org.eclipse.jface.util.Assert.isNotNull",
            "source": "Assert.java:125"
          },
          {
            "method": "org.eclipse.jdt.internal.ui.text.correction.JavaCorrectionAssistant.\u003cinit\u003e",
            "source": "JavaCorrectionAssistant.java:70"
          },
          {
            "method": "org.eclipse.jdt.ui.text.JavaSourceViewerConfiguration.getQuickAssistAssistant",
            "source": "JavaSourceViewerConfiguration.java:428"
          },
          {
            "method": "org.eclipse.jface.text.source.SourceViewer.configure",
            "source": "SourceViewer.java:360"
          },
          {
            "method": "org.eclipse.jdt.internal.ui.javaeditor.JavaSourceViewer.configure",
            "source": "JavaSourceViewer.java:214"
          },
          {
            "method": "org.eclipse.jdt.internal.ui.text.java.hover.SourceViewerInformationControl.\u003cinit\u003e",
            "source": "SourceViewerInformationControl.java:137"
          },
          {
            "method": "org.eclipse.jdt.internal.ui.text.java.hover.SourceViewerInformationControl.\u003cinit\u003e",
            "source": "SourceViewerInformationControl.java:90"
          },
          {
            "method": "org.eclipse.jdt.internal.ui.text.java.hover.SourceViewerInformationControl.\u003cinit\u003e",
            "source": "SourceViewerInformationControl.java:193"
          },
          {
            "method": "org.eclipse.jdt.internal.ui.text.java.hover.SourceViewerInformationControl.\u003cinit\u003e",
            "source": "SourceViewerInformationControl.java:219"
          },
          {
            "method": "org.eclipse.jdt.internal.ui.text.template.contentassist.TemplateInformationControlCreator.createInformationControl",
            "source": "TemplateInformationContr olCreator.java:35"
          },
          {
            "method": "org.eclipse.jface.text.AbstractInformationControlManager.getInformationControl",
            "source": "AbstractInformationControlManager.java:619"
          },
          {
            "method": "org.eclipse.jface.text.AbstractInformationControlManager.internalShowInformationControl",
            "source": "AbstractInformationControlManager.java:850"
          },
          {
            "method": "org.eclipse.jface.text.AbstractInformationControlManager.presentInformation",
            "source": "AbstractInformationControlManager.java:836"
          },
          {
            "method": "org.eclipse.jface.text.AbstractInformationControlManager.setInformation",
            "source": "AbstractInformationControlManager.java:291"
          },
          {
            "method": "org.eclipse.jface.text.contentassist.AdditionalInfoController.computeInformation",
            "source": "AdditionalInfoController.java:236"
          },
          {
            "method": "org.eclipse.jface.text.AbstractInformationControlManager.doShowInformation",
            "source": "AbstractInformationControlManager.java:820"
          },
          {
            "method": "org.eclipse.jface.text.AbstractInformationControlManager.showInformation",
            "source": "AbstractInformationControlManager.java:810"
          },
          {
            "method": "org.eclipse.jface.text.contentassist.AdditionalInfoController$1.run",
            "source": "AdditionalInfoController.java:173"
          },
          {
            "method": "org.eclipse.swt.widgets.RunnableLock.run",
            "source": "RunnableLock.java:35"
          },
          {
            "method": "org.eclipse.swt.widgets.Synchronizer.runAsyncMessages",
            "source": "Synchronizer.java:123"
          }
        ],
        "number": 0,
        "commentIndex": 0
      },
      "number": 0,
      "commentIndex": 0,
      "bugId": "127250",
      "date": "2006-02-10T12:03:43+01:00",
      "product": "JDT",
      "component": "Text",
      "severity": "major"
    }
  ],
  "groupId": "127250",
  "bugId": "127250",
  "date": "2006-02-10T12:03:43+01:00",
  "product": "JDT",
  "component": "Text",
  "severity": "major"
}