{
  "comments": [
    "testOpenCloseWindows:org.eclipse.debug.ui.DebugPerspective(org.eclipse.ui.tests.performance.OpenCloseWindowTest)\norg.eclipse.core.runtime.CoreException[0]: org.eclipse.swt.SWTException: Failed\nto execute runnable (java.lang.NullPointerException)\n        at org.eclipse.swt.SWT.error(SWT.java:3349)\n        at org.eclipse.swt.SWT.error(SWT.java:3272)\n        at\norg.eclipse.swt.widgets.Synchronizer.runAsyncMessages(Synchronizer.java:126)\n        at org.eclipse.swt.widgets.Display.runAsyncMessages(Display.java:3264)\n        at org.eclipse.swt.widgets.Display.readAndDispatch(Display.java:2910)\n        at\norg.eclipse.ui.tests.harness.util.UITestCase.processEvents(UITestCase.java:222)\n        at\norg.eclipse.ui.tests.performance.OpenCloseWindowTest.access$0(OpenCloseWindowTest.java:1)\n        at\norg.eclipse.ui.tests.performance.OpenCloseWindowTest$1.run(OpenCloseWindowTest.java:46)\n        at\norg.eclipse.ui.tests.performance.BasicPerformanceTest.exercise(BasicPerformanceTest.java:255)\n        at\norg.eclipse.ui.tests.performance.BasicPerformanceTest.exercise(BasicPerformanceTest.java:237)\n        at\norg.eclipse.ui.tests.performance.OpenCloseWindowTest.runTest(OpenCloseWindowTest.java:37)\n        at junit.framework.TestCase.runBare(TestCase.java:127)\n        at junit.framework.TestResult$1.protect(TestResult.java:106)\n        at junit.framework.TestResult.runProtected(TestResult.java:124)\n        at junit.framework.TestResult.run(TestResult.java:109)\n        at junit.framework.TestCase.run(TestCase.java:118)\n        at junit.framework.TestSuite.runTest(TestSuite.java:208)\n        at junit.framework.TestSuite.run(TestSuite.java:203)\n        at junit.framework.TestSuite.runTest(TestSuite.java:208)\n        at junit.framework.TestSuite.run(TestSuite.java:203)\n        at junit.extensions.TestDecorator.basicRun(TestDecorator.java:22)\n        at junit.extensions.TestSetup$1.protect(TestSetup.java:19)\n        at junit.framework.TestResult.runProtected(TestResult.java:124)\n        at junit.extensions.TestSetup.run(TestSetup.java:23)\n        at\norg.eclipse.jdt.internal.junit.runner.RemoteTestRunner.runTests(RemoteTestRunner.java:478)\n        at\norg.eclipse.jdt.internal.junit.runner.RemoteTestRunner.run(RemoteTestRunner.java:344)\n        at\norg.eclipse.pde.internal.junit.runtime.RemotePluginTestRunner.main(RemotePluginTestRunner.java:57)\n        at\norg.eclipse.pde.internal.junit.runtime.UITestApplication$1.run(UITestApplication.java:105)\n        at org.eclipse.swt.widgets.RunnableLock.run(RunnableLock.java:35)\n        at\norg.eclipse.swt.widgets.Synchronizer.runAsyncMessages(Synchronizer.java:123)\n        at org.eclipse.swt.widgets.Display.runAsyncMessages(Display.java:3264)\n        at org.eclipse.swt.widgets.Display.readAndDispatch(Display.java:2910)\n        at org.eclipse.ui.internal.Workbench.runEventLoop(Workbench.java:1830)\n        at org.eclipse.ui.internal.Workbench.runUI(Workbench.java:1794)\n        at\norg.eclipse.ui.internal.Workbench.createAndRunWorkbench(Workbench.java:410)\n        at org.eclipse.ui.PlatformUI.createAndRunWorkbench(PlatformUI.java:143)\n        at\norg.eclipse.ui.internal.ide.IDEApplication.run(IDEApplication.java:106)\n        at\norg.eclipse.pde.internal.junit.runtime.UITestApplication.run(UITestApplication.java:45)\n        at\norg.eclipse.core.internal.runtime.PlatformActivator$1.run(PlatformActivator.java:109)\n        at\norg.eclipse.core.runtime.internal.adaptor.EclipseAppLauncher.runApplication(EclipseAppLauncher.java:92)\n        at\norg.eclipse.core.runtime.internal.adaptor.EclipseAppLauncher.start(EclipseAppLauncher.java:68)\n        at\norg.eclipse.core.runtime.adaptor.EclipseStarter.run(EclipseStarter.java:374)\n        at\norg.eclipse.core.runtime.adaptor.EclipseStarter.run(EclipseStarter.java:169)\n        at sun.reflect.NativeMethodAccessorImpl.invoke0(Native Method)\n        at\nsun.reflect.NativeMethodAccessorImpl.invoke(NativeMethodAccessorImpl.java:64)\n        at\nsun.reflect.DelegatingMethodAccessorImpl.invoke(DelegatingMethodAccessorImpl.java:43)\n        at java.lang.reflect.Method.invoke(Method.java:615)\n        at org.eclipse.core.launcher.Main.invokeFramework(Main.java:338)\n        at org.eclipse.core.launcher.Main.basicRun(Main.java:282)\n        at org.eclipse.core.launcher.Main.run(Main.java:977)\n        at org.eclipse.core.launcher.Main.main(Main.java:952)\nCaused by: java.lang.NullPointerException\n        at\norg.eclipse.debug.internal.ui.views.launch.LaunchView$6.run(LaunchView.java:353)\n        at org.eclipse.swt.widgets.RunnableLock.run(RunnableLock.java:35)\n        at\norg.eclipse.swt.widgets.Synchronizer.runAsyncMessages(Synchronizer.java:123)\n        ... 48 more",
    "Sorry, committed that too early.\n\nbuild I20060208-0848\n\nSaw this while running the UI team\u0027s performance tests.\nThe test in question rapidly opens and closes a workbench window.\n\nThe asyncExec in LaunchView.initializeSelections() job should check isAvailable() not only when queuing the async exec, but also when it\u0027s about to be run, since the view may have been closed between queuing and running. \nAll asyncExecs should double check.\n\nThis check could be done for all callers in AbstractDebugView.asyncExec using a wrapper runnable. \n",
    "Fixed in LaunchView. The initializeSelection did not need a job, it\u0027s already called in an async, so the check isAvailable() is now done at the right time.",
    "Please verify, Kevin.",
    "verfied"
  ],
  "commentCreationDates": [
    "2006-02-10T01:04:09+01:00",
    "2006-02-10T01:07:45+01:00",
    "2006-02-10T18:30:42+01:00",
    "2006-02-10T18:31:04+01:00",
    "2006-02-13T16:38:14+01:00"
  ],
  "traces": [
    {
      "exceptionType": "org.eclipse.swt.SWTException",
      "message": "Failed to execute runnable (java.lang.NullPointerException)",
      "elements": [
        {
          "method": "org.eclipse.swt.SWT.error",
          "source": "SWT.java:3349"
        },
        {
          "method": "org.eclipse.swt.SWT.error",
          "source": "SWT.java:3272"
        },
        {
          "method": "org.eclipse.swt.widgets.Synchronizer.runAsyncMessages",
          "source": "Synchronizer.java:126"
        },
        {
          "method": "org.eclipse.swt.widgets.Display.runAsyncMessages",
          "source": "Display.java:3264"
        },
        {
          "method": "org.eclipse.swt.widgets.Display.readAndDispatch",
          "source": "Display.java:2910"
        },
        {
          "method": "org.eclipse.ui.tests.harness.util.UITestCase.processEvents",
          "source": "UITestCase.java:222"
        },
        {
          "method": "org.eclipse.ui.tests.performance.OpenCloseWindowTest.access$0",
          "source": "OpenCloseWindowTest.java:1"
        },
        {
          "method": "org.eclipse.ui.tests.performance.OpenCloseWindowTest$1.run",
          "source": "OpenCloseWindowTest.java:46"
        },
        {
          "method": "org.eclipse.ui.tests.performance.BasicPerformanceTest.exercise",
          "source": "BasicPerformanceTest.java:255"
        },
        {
          "method": "org.eclipse.ui.tests.performance.BasicPerformanceTest.exercise",
          "source": "BasicPerformanceTest.java:237"
        },
        {
          "method": "org.eclipse.ui.tests.performance.OpenCloseWindowTest.runTest",
          "source": "OpenCloseWindowTest.java:37"
        },
        {
          "method": "junit.framework.TestCase.runBare",
          "source": "TestCase.java:127"
        },
        {
          "method": "junit.framework.TestResult$1.protect",
          "source": "TestResult.java:106"
        },
        {
          "method": "junit.framework.TestResult.runProtected",
          "source": "TestResult.java:124"
        },
        {
          "method": "junit.framework.TestResult.run",
          "source": "TestResult.java:109"
        },
        {
          "method": "junit.framework.TestCase.run",
          "source": "TestCase.java:118"
        },
        {
          "method": "junit.framework.TestSuite.runTest",
          "source": "TestSuite.java:208"
        },
        {
          "method": "junit.framework.TestSuite.run",
          "source": "TestSuite.java:203"
        },
        {
          "method": "junit.framework.TestSuite.runTest",
          "source": "TestSuite.java:208"
        },
        {
          "method": "junit.framework.TestSuite.run",
          "source": "TestSuite.java:203"
        },
        {
          "method": "junit.extensions.TestDecorator.basicRun",
          "source": "TestDecorator.java:22"
        },
        {
          "method": "junit.extensions.TestSetup$1.protect",
          "source": "TestSetup.java:19"
        },
        {
          "method": "junit.framework.TestResult.runProtected",
          "source": "TestResult.java:124"
        },
        {
          "method": "junit.extensions.TestSetup.run",
          "source": "TestSetup.java:23"
        },
        {
          "method": "org.eclipse.jdt.internal.junit.runner.RemoteTestRunner.runTests",
          "source": "RemoteTestRunner.java:478"
        },
        {
          "method": "org.eclipse.jdt.internal.junit.runner.RemoteTestRunner.run",
          "source": "RemoteTestRunner.java:344"
        },
        {
          "method": "org.eclipse.pde.internal.junit.runtime.RemotePluginTestRunner.main",
          "source": "RemotePluginTestRunner.java:57"
        },
        {
          "method": "org.eclipse.pde.internal.junit.runtime.UITestApplication$1.run",
          "source": "UITestApplication.java:105"
        },
        {
          "method": "org.eclipse.swt.widgets.RunnableLock.run",
          "source": "RunnableLock.java:35"
        },
        {
          "method": "org.eclipse.swt.widgets.Synchronizer.runAsyncMessages",
          "source": "Synchronizer.java:123"
        },
        {
          "method": "org.eclipse.swt.widgets.Display.runAsyncMessages",
          "source": "Display.java:3264"
        },
        {
          "method": "org.eclipse.swt.widgets.Display.readAndDispatch",
          "source": "Display.java:2910"
        },
        {
          "method": "org.eclipse.ui.internal.Workbench.runEventLoop",
          "source": "Workbench.java:1830"
        },
        {
          "method": "org.eclipse.ui.internal.Workbench.runUI",
          "source": "Workbench.java:1794"
        },
        {
          "method": "org.eclipse.ui.internal.Workbench.createAndRunWorkbench",
          "source": "Workbench.java:410"
        },
        {
          "method": "org.eclipse.ui.PlatformUI.createAndRunWorkbench",
          "source": "PlatformUI.java:143"
        },
        {
          "method": "org.eclipse.ui.internal.ide.IDEApplication.run",
          "source": "IDEApplication.java:106"
        },
        {
          "method": "org.eclipse.pde.internal.junit.runtime.UITestApplication.run",
          "source": "UITestApplication.java:45"
        },
        {
          "method": "org.eclipse.core.internal.runtime.PlatformActivator$1.run",
          "source": "PlatformActivator.java:109"
        },
        {
          "method": "org.eclipse.core.runtime.internal.adaptor.EclipseAppLauncher.runApplication",
          "source": "EclipseAppLauncher.java:92"
        },
        {
          "method": "org.eclipse.core.runtime.internal.adaptor.EclipseAppLauncher.start",
          "source": "EclipseAppLauncher.java:68"
        },
        {
          "method": "org.eclipse.core.runtime.adaptor.EclipseStarter.run",
          "source": "EclipseStarter.java:374"
        },
        {
          "method": "org.eclipse.core.runtime.adaptor.EclipseStarter.run",
          "source": "EclipseStarter.java:169"
        },
        {
          "method": "sun.reflect.NativeMethodAccessorImpl.invoke0",
          "source": "Native Method"
        },
        {
          "method": "sun.reflect.NativeMethodAccessorImpl.invoke",
          "source": "NativeMethodAccessorImpl.java:64"
        },
        {
          "method": "sun.reflect.DelegatingMethodAccessorImpl.invoke",
          "source": "DelegatingMethodAccessorImpl.java:43"
        },
        {
          "method": "java.lang.reflect.Method.invoke",
          "source": "Method.java:615"
        },
        {
          "method": "org.eclipse.core.launcher.Main.invokeFramework",
          "source": "Main.java:338"
        },
        {
          "method": "org.eclipse.core.launcher.Main.basicRun",
          "source": "Main.java:282"
        },
        {
          "method": "org.eclipse.core.launcher.Main.run",
          "source": "Main.java:977"
        },
        {
          "method": "org.eclipse.core.launcher.Main.main",
          "source": "Main.java:952"
        }
      ],
      "causedBy": {
        "exceptionType": "java.lang.NullPointerException",
        "elements": [
          {
            "method": "org.eclipse.debug.internal.ui.views.launch.LaunchView$6.run",
            "source": "LaunchView.java:353"
          },
          {
            "method": "org.eclipse.swt.widgets.RunnableLock.run",
            "source": "RunnableLock.java:35"
          },
          {
            "method": "org.eclipse.swt.widgets.Synchronizer.runAsyncMessages",
            "source": "Synchronizer.java:123"
          }
        ],
        "number": 0,
        "commentIndex": 0
      },
      "number": 0,
      "commentIndex": 0,
      "bugId": "127204",
      "date": "2006-02-10T01:04:09+01:00",
      "product": "JDT",
      "component": "Debug",
      "severity": "normal"
    }
  ],
  "groupId": "127204",
  "bugId": "127204",
  "date": "2006-02-10T01:04:09+01:00",
  "product": "JDT",
  "component": "Debug",
  "severity": "normal"
}