{
  "comments": [
    "Creating a Java Web Service Client \nhttp://www.eclipse.org/webtools/community/tutorials/WebServiceClient/WebServiceClient.html\nTomcat 4.1, BEA 8.1\nAxis runtime\n\nError:\nIWAB0399E Error in generating Java from WSDL\njava.lang.NullPointerException",
    "Created an attachment (id\u003d34484)\nWSDL file\n\n",
    "Matti,\nthis error occurs whenever the underlying Apache Axis emitters fail. Running the WSDL thru Axis WSDL2Java yields the following null pointer exception:\n\n( 9:11:53.32) C:\\Downloads\\127227 \u003e java org.apache.axis.wsdl.WSDL2Java SOAPFrontGetShowBalanceJMS.wsdl\n- Unable to find required classes (javax.activation.DataHandler and javax.mail.internet.MimeMultipart). Attachment support is disabl\ned.\njava.lang.NullPointerException\n        at org.apache.axis.wsdl.toJava.JavaBeanWriter.preprocess(JavaBeanWriter.java:308)\n        at org.apache.axis.wsdl.toJava.JavaBeanWriter.getImplementsText(JavaBeanWriter.java:500)\n        at org.apache.axis.wsdl.toJava.JavaBeanWriter.writeFileHeader(JavaBeanWriter.java:179)\n        at org.apache.axis.wsdl.toJava.JavaWriter.generate(JavaWriter.java:129)\n        at org.apache.axis.wsdl.toJava.JavaBeanWriter.generate(JavaBeanWriter.java:1270)\n        at org.apache.axis.wsdl.toJava.JavaTypeWriter.generate(JavaTypeWriter.java:113)\n        at org.apache.axis.wsdl.toJava.JavaGeneratorFactory$Writers.generate(JavaGeneratorFactory.java:421)\n        at org.apache.axis.wsdl.gen.Parser.generateTypes(Parser.java:547)\n        at org.apache.axis.wsdl.gen.Parser.generate(Parser.java:432)\n        at org.apache.axis.wsdl.gen.Parser.access$000(Parser.java:45)\n        at org.apache.axis.wsdl.gen.Parser$WSDLRunnable.run(Parser.java:362)\n        at java.lang.Thread.run(Thread.java:568)\n\nPlease open this bug in the Apache JIRA bug database, http://ws.apache.org/axis/bugs.html.\n\nThanks - CB.",
    "See previous comment 2.",
    "*** Bug 127228 has been marked as a duplicate of this bug. ***",
    "(In reply to comment #2)\n\u003e Matti,\n\u003e this error occurs whenever the underlying Apache Axis emitters fail. Running\n\u003e the WSDL thru Axis WSDL2Java yields the following null pointer exception:\n\u003e ( 9:11:53.32) C:\\Downloads\\127227 \u003e java org.apache.axis.wsdl.WSDL2Java\n\u003e SOAPFrontGetShowBalanceJMS.wsdl\n\u003e - Unable to find required classes (javax.activation.DataHandler and\n\u003e javax.mail.internet.MimeMultipart). Attachment support is disabl\n\u003e ed.\n\u003e java.lang.NullPointerException\n\u003e         at\n\u003e org.apache.axis.wsdl.toJava.JavaBeanWriter.preprocess(JavaBeanWriter.java:308)\n\u003e         at\n\u003e org.apache.axis.wsdl.toJava.JavaBeanWriter.getImplementsText(JavaBeanWriter.java:500)\n\u003e         at\n\u003e org.apache.axis.wsdl.toJava.JavaBeanWriter.writeFileHeader(JavaBeanWriter.java:179)\n\u003e         at org.apache.axis.wsdl.toJava.JavaWriter.generate(JavaWriter.java:129)\n\u003e         at\n\u003e org.apache.axis.wsdl.toJava.JavaBeanWriter.generate(JavaBeanWriter.java:1270)\n\u003e         at\n\u003e org.apache.axis.wsdl.toJava.JavaTypeWriter.generate(JavaTypeWriter.java:113)\n\u003e         at\n\u003e org.apache.axis.wsdl.toJava.JavaGeneratorFactory$Writers.generate(JavaGeneratorFactory.java:421)\n\u003e         at org.apache.axis.wsdl.gen.Parser.generateTypes(Parser.java:547)\n\u003e         at org.apache.axis.wsdl.gen.Parser.generate(Parser.java:432)\n\u003e         at org.apache.axis.wsdl.gen.Parser.access$000(Parser.java:45)\n\u003e         at org.apache.axis.wsdl.gen.Parser$WSDLRunnable.run(Parser.java:362)\n\u003e         at java.lang.Thread.run(Thread.java:568)\n\u003e Please open this bug in the Apache JIRA bug database,\n\u003e http://ws.apache.org/axis/bugs.html.\n\u003e Thanks - CB.\n\nThis bug is in Apache JIRA\nhttps://issues.apache.org/jira/browse/AXIS-2402\n\nI believe this bug is unresolved and affects all AXIS 1.3, 1.4, but not AXIS 2.0 versions.\n",
    "This is part of a mass update to close out all stale WTP bugs which are in the resolved state without an appropriate targeted version.  If you feel this bug was closed inappropriately, please reopen."
  ],
  "commentCreationDates": [
    "2006-02-10T08:04:51+01:00",
    "2006-02-10T08:05:22+01:00",
    "2006-02-23T14:12:52+01:00",
    "2006-02-23T14:15:52+01:00",
    "2006-02-23T14:17:04+01:00",
    "2006-09-26T08:41:38+02:00",
    "2006-11-28T20:48:46+01:00"
  ],
  "traces": [
    {
      "exceptionType": "java.lang.NullPointerException",
      "elements": [
        {
          "method": "org.apache.axis.wsdl.toJava.JavaBeanWriter.preprocess",
          "source": "JavaBeanWriter.java:308"
        },
        {
          "method": "org.apache.axis.wsdl.toJava.JavaBeanWriter.getImplementsText",
          "source": "JavaBeanWriter.java:500"
        },
        {
          "method": "org.apache.axis.wsdl.toJava.JavaBeanWriter.writeFileHeader",
          "source": "JavaBeanWriter.java:179"
        },
        {
          "method": "org.apache.axis.wsdl.toJava.JavaWriter.generate",
          "source": "JavaWriter.java:129"
        },
        {
          "method": "org.apache.axis.wsdl.toJava.JavaBeanWriter.generate",
          "source": "JavaBeanWriter.java:1270"
        },
        {
          "method": "org.apache.axis.wsdl.toJava.JavaTypeWriter.generate",
          "source": "JavaTypeWriter.java:113"
        },
        {
          "method": "org.apache.axis.wsdl.toJava.JavaGeneratorFactory$Writers.generate",
          "source": "JavaGeneratorFactory.java:421"
        },
        {
          "method": "org.apache.axis.wsdl.gen.Parser.generateTypes",
          "source": "Parser.java:547"
        },
        {
          "method": "org.apache.axis.wsdl.gen.Parser.generate",
          "source": "Parser.java:432"
        },
        {
          "method": "org.apache.axis.wsdl.gen.Parser.access$000",
          "source": "Parser.java:45"
        },
        {
          "method": "org.apache.axis.wsdl.gen.Parser$WSDLRunnable.run",
          "source": "Parser.java:362"
        },
        {
          "method": "java.lang.Thread.run",
          "source": "Thread.java:568"
        }
      ],
      "number": 0,
      "commentIndex": 2,
      "bugId": "127227",
      "date": "2006-02-23T14:12:52+01:00",
      "product": "Web Tools",
      "component": "wst.wsdl",
      "severity": "normal"
    }
  ],
  "groupId": "127227",
  "bugId": "127227",
  "date": "2006-02-10T08:04:51+01:00",
  "product": "Web Tools",
  "component": "wst.wsdl",
  "severity": "normal"
}