{
  "comments": [
    "Smoke:Data set can not wok.\n\nSteps:\n1.Create a data source\n2.create a data set, click \"OK\" button\n\nActual Results:\n1.System throws exception\njava.lang.NoClassDefFoundError\n\tat org.eclipse.datatools.connectivity.oda.consumer.helper.OdaObject.logMethodCalled(OdaObject.java:352)\n\tat org.eclipse.datatools.connectivity.oda.consumer.helper.OdaDriver.\u003cinit\u003e(OdaDriver.java:46)\n\tat org.eclipse.birt.data.engine.odaconsumer.Driver.getDriverHelper(Driver.java:113)\n\tat org.eclipse.birt.data.engine.odaconsumer.DriverManager.getDriverHelper(DriverManager.java:70)\n\tat org.eclipse.birt.data.engine.odaconsumer.ConnectionManager.openConnection(ConnectionManager.java:113)\n\tat org.eclipse.birt.data.engine.executor.DataSource.newConnection(DataSource.java:154)\n\tat org.eclipse.birt.data.engine.executor.DataSource.open(DataSource.java:147)\n\tat org.eclipse.birt.data.engine.impl.DataSourceRuntime.openOdiDataSource(DataSourceRuntime.java:150)\n\tat org.eclipse.birt.data.engine.impl.PreparedQuery$Executor.openDataSource(PreparedQuery.java:838)\n\tat org.eclipse.birt.data.engine.impl.PreparedExtendedDSQuery$ExtendedDSQueryExecutor.getParameterMetaData(PreparedExtendedDSQuery.java:591)\n\tat org.eclipse.birt.data.engine.impl.PreparedExtendedDSQuery$ExtendedDSQueryExecutor.access$000(PreparedExtendedDSQuery.java:138)\n\tat org.eclipse.birt.data.engine.impl.PreparedExtendedDSQuery.getParameterMetaData(PreparedExtendedDSQuery.java:130)\n\tat org.eclipse.birt.report.designer.internal.ui.util.DataSetManager.getParametersFromDataSet(DataSetManager.java:843)\n\tat org.eclipse.birt.report.designer.internal.ui.dialogs.DataSetParametersPage.refreshParameters(DataSetParametersPage.java:738)\n\tat org.eclipse.birt.report.designer.internal.ui.dialogs.DataSetParametersPage.isValid(DataSetParametersPage.java:1033)\n\tat org.eclipse.birt.report.designer.internal.ui.dialogs.DataSetParametersPage.performOk(DataSetParametersPage.java:1015)\n\tat org.eclipse.birt.report.designer.ui.dialogs.properties.AbstractPropertyDialog.okPressed(AbstractPropertyDialog.java:570)\n\tat org.eclipse.birt.report.designer.ui.dialogs.properties.AbstractPropertyDialog.okPressed(AbstractPropertyDialog.java:555)\n\tat org.eclipse.birt.report.designer.ui.dialogs.DataSetEditor.okPressed(DataSetEditor.java:261)\n\tat org.eclipse.birt.report.designer.ui.dialogs.properties.AbstractPropertyDialog.buttonPressed(AbstractPropertyDialog.java:437)\n\tat org.eclipse.jface.dialogs.Dialog$2.widgetSelected(Dialog.java:607)\n\tat org.eclipse.swt.widgets.TypedListener.handleEvent(TypedListener.java:90)\n\tat org.eclipse.swt.widgets.EventTable.sendEvent(EventTable.java:66)\n\tat org.eclipse.swt.widgets.Widget.sendEvent(Widget.java:914)\n\tat org.eclipse.swt.widgets.Display.runDeferredEvents(Display.java:3285)\n\tat org.eclipse.swt.widgets.Display.readAndDispatch(Display.java:2905)\n\tat org.eclipse.jface.window.Window.runEventLoop(Window.java:808)\n\tat org.eclipse.jface.window.Window.open(Window.java:786)\n\tat org.eclipse.birt.report.designer.internal.ui.dialogs.BaseDialog.open(BaseDialog.java:145)\n\tat org.eclipse.birt.report.designer.ui.actions.NewDataSetAction.editDataSet(NewDataSetAction.java:190)\n\tat org.eclipse.birt.report.designer.ui.actions.NewDataSetAction.run(NewDataSetAction.java:128)\n\tat org.eclipse.jface.action.Action.runWithEvent(Action.java:492)\n\tat org.eclipse.jface.action.ActionContributionItem.handleWidgetSelection(ActionContributionItem.java:530)\n\tat org.eclipse.jface.action.ActionContributionItem.access$2(ActionContributionItem.java:480)\n\tat org.eclipse.jface.action.ActionContributionItem$5.handleEvent(ActionContributionItem.java:392)\n\tat org.eclipse.swt.widgets.EventTable.sendEvent(EventTable.java:66)\n\tat org.eclipse.swt.widgets.Widget.sendEvent(Widget.java:914)\n\tat org.eclipse.swt.widgets.Display.runDeferredEvents(Display.java:3285)\n\tat org.eclipse.swt.widgets.Display.readAndDispatch(Display.java:2905)\n\tat org.eclipse.ui.internal.Workbench.runEventLoop(Workbench.java:1762)\n\tat org.eclipse.ui.internal.Workbench.runUI(Workbench.java:1726)\n\tat org.eclipse.ui.internal.Workbench.createAndRunWorkbench(Workbench.java:397)\n\tat org.eclipse.ui.PlatformUI.createAndRunWorkbench(PlatformUI.java:143)\n\tat org.eclipse.ui.internal.ide.IDEApplication.run(IDEApplication.java:106)\n\tat org.eclipse.core.internal.runtime.PlatformActivator$1.run(PlatformActivator.java:109)\n\tat org.eclipse.core.runtime.internal.adaptor.EclipseAppLauncher.runApplication(EclipseAppLauncher.java:92)\n\tat org.eclipse.core.runtime.internal.adaptor.EclipseAppLauncher.start(EclipseAppLauncher.java:68)\n\tat org.eclipse.core.runtime.adaptor.EclipseStarter.run(EclipseStarter.java:379)\n\tat org.eclipse.core.runtime.adaptor.EclipseStarter.run(EclipseStarter.java:177)\n\tat sun.reflect.NativeMethodAccessorImpl.invoke0(Native Method)\n\tat sun.reflect.NativeMethodAccessorImpl.invoke(NativeMethodAccessorImpl.java:39)\n\tat sun.reflect.DelegatingMethodAccessorImpl.invoke(DelegatingMethodAccessorImpl.java:25)\n\tat java.lang.reflect.Method.invoke(Method.java:324)\n\tat org.eclipse.core.launcher.Main.invokeFramework(Main.java:338)\n\tat org.eclipse.core.launcher.Main.basicRun(Main.java:282)\n\tat org.eclipse.core.launcher.Main.run(Main.java:977)\n\tat org.eclipse.core.launcher.Main.main(Main.java:952)\n\n\nExpected Results:\n1.Work well",
    "This bug is caused by ODA. In org.eclipse.datatools.connectivity.oda.util.logging#LogManager, there is a static instance, which is sm_dateFormat. In some platform, this instance can not be successfully created. Trace is below:\n\norg.eclipse.swt.SWTException: Failed to execute runnable (java.lang.ExceptionInInitializerError)\n\n         at org.eclipse.swt.SWT.error(SWT.java:3283)\n\n         at org.eclipse.swt.SWT.error(SWT.java:3206)\n\n         at org.eclipse.swt.widgets.Synchronizer.runAsyncMessages(Synchronizer.java:126)\n\n         at org.eclipse.swt.widgets.Display.runAsyncMessages(Display.java:3262)\n\n         at org.eclipse.swt.widgets.Display.readAndDispatch(Display.java:2908)\n\n         at org.eclipse.jface.window.Window.runEventLoop(Window.java:808)\n\n         at org.eclipse.jface.window.Window.open(Window.java:786)\n\n         at org.eclipse.birt.report.designer.internal.ui.dialogs.BaseDialog.open(BaseDialog.java:145)\n\n         at org.eclipse.birt.report.designer.ui.actions.NewDataSetAction.editDataSet(NewDataSetAction.java:190)\n\n         at org.eclipse.birt.report.designer.ui.actions.NewDataSetAction.run(NewDataSetAction.java:128)\n\n         at org.eclipse.jface.action.Action.runWithEvent(Action.java:492)\n\n         at org.eclipse.jface.action.ActionContributionItem.handleWidgetSelection(ActionContributionItem.java:530)\n\n         at org.eclipse.jface.action.ActionContributionItem.access$2(ActionContributionItem.java:480)\n\n         at org.eclipse.jface.action.ActionContributionItem$5.handleEvent(ActionContributionItem.java:392)\n\n         at org.eclipse.swt.widgets.EventTable.sendEvent(EventTable.java:66)\n\n         at org.eclipse.swt.widgets.Widget.sendEvent(Widget.java:914)\n\n         at org.eclipse.swt.widgets.Display.runDeferredEvents(Display.java:3285)\n\n         at org.eclipse.swt.widgets.Display.readAndDispatch(Display.java:2905)\n\n         at org.eclipse.ui.internal.Workbench.runEventLoop(Workbench.java:1762)\n\n         at org.eclipse.ui.internal.Workbench.runUI(Workbench.java:1726)\n\n         at org.eclipse.ui.internal.Workbench.createAndRunWorkbench(Workbench.java:397)\n\n         at org.eclipse.ui.PlatformUI.createAndRunWorkbench(PlatformUI.java:143)\n\n         at org.eclipse.ui.internal.ide.IDEApplication.run(IDEApplication.java:106)\n\n         at org.eclipse.core.internal.runtime.PlatformActivator$1.run(PlatformActivator.java:109)\n\n         at org.eclipse.core.runtime.internal.adaptor.EclipseAppLauncher.runApplication(EclipseAppLauncher.java:92)\n\n         at org.eclipse.core.runtime.internal.adaptor.EclipseAppLauncher.start(EclipseAppLauncher.java:68)\n\n         at org.eclipse.core.runtime.adaptor.EclipseStarter.run(EclipseStarter.java:379)\n\n         at org.eclipse.core.runtime.adaptor.EclipseStarter.run(EclipseStarter.java:177)\n\n         at sun.reflect.NativeMethodAccessorImpl.invoke0(Native Method)\n\n         at sun.reflect.NativeMethodAccessorImpl.invoke(NativeMethodAccessorImpl.java:39)\n\n         at sun.reflect.DelegatingMethodAccessorImpl.invoke(DelegatingMethodAccessorImpl.java:25)\n\n         at java.lang.reflect.Method.invoke(Method.java:324)\n\n         at org.eclipse.core.launcher.Main.invokeFramework(Main.java:338)\n\n         at org.eclipse.core.launcher.Main.basicRun(Main.java:282)\n\n         at org.eclipse.core.launcher.Main.run(Main.java:977)\n\n         at org.eclipse.core.launcher.Main.main(Main.java:952)\n\nCaused by: java.lang.ExceptionInInitializerError\n\n         at org.eclipse.datatools.connectivity.oda.consumer.helper.OdaObject.logMethodCalled(OdaObject.java:352)\n\n         at org.eclipse.datatools.connectivity.oda.consumer.helper.OdaDriver.\u003cinit\u003e(OdaDriver.java:46)\n\n         at org.eclipse.birt.data.engine.odaconsumer.Driver.getDriverHelper(Driver.java:113)\n\n         at org.eclipse.birt.data.engine.odaconsumer.DriverManager.getDriverHelper(DriverManager.java:70)\n\n         at org.eclipse.birt.data.engine.odaconsumer.ConnectionManager.openConnection(ConnectionManager.java:113)\n\n         at org.eclipse.birt.data.engine.executor.DataSource.newConnection(DataSource.java:154)\n\n         at org.eclipse.birt.data.engine.executor.DataSource.open(DataSource.java:147)\n\n         at org.eclipse.birt.data.engine.impl.DataSourceRuntime.openOdiDataSource(DataSourceRuntime.java:150)\n\n         at org.eclipse.birt.data.engine.impl.PreparedQuery$Executor.openDataSource(PreparedQuery.java:838)\n\n         at org.eclipse.birt.data.engine.impl.PreparedQuery$Executor.prepareExecution(PreparedQuery.java:661)\n\n         at org.eclipse.birt.data.engine.impl.PreparedQuery$Executor.access$000(PreparedQuery.java:498)\n\n         at org.eclipse.birt.data.engine.impl.PreparedQuery.doPrepare(PreparedQuery.java:225)\n\n         at org.eclipse.birt.data.engine.impl.PreparedDataSourceQuery.execute(PreparedDataSourceQuery.java:145)\n\n         at org.eclipse.birt.report.designer.internal.ui.util.DataSetManager.execute(DataSetManager.java:296)\n\n         at org.eclipse.birt.report.designer.internal.ui.util.DataSetManager.execute(DataSetManager.java:273)\n\n         at org.eclipse.birt.report.designer.internal.ui.dialogs.ResultSetPreviewPage.updateResults(ResultSetPreviewPage.java:143)\n\n         at org.eclipse.birt.report.designer.internal.ui.dialogs.ResultSetPreviewPage$4.run(ResultSetPreviewPage.java:401)\n\n         at org.eclipse.swt.widgets.RunnableLock.run(RunnableLock.java:35)\n\n         at org.eclipse.swt.widgets.Synchronizer.runAsyncMessages(Synchronizer.java:123)\n\n         ... 33 more\n\nCaused by: java.lang.NullPointerException\n\n         at com.ibm.icu.util.TimeZone.getDefault(TimeZone.java:697)\n\n         at com.ibm.icu.text.SimpleDateFormat.initialize(SimpleDateFormat.java:466)\n\n         at com.ibm.icu.text.SimpleDateFormat.\u003cinit\u003e(SimpleDateFormat.java:335)\n\n         at com.ibm.icu.text.SimpleDateFormat.\u003cinit\u003e(SimpleDateFormat.java:310)\n\n         at org.eclipse.datatools.connectivity.oda.util.logging.LogManager.\u003cclinit\u003e(LogManager.java:323)\n\n         ... 52 more",
    "I\u0027m able to create a data set from a 3.2M4 deployment environment.\nOne of the previous comments made was that: \"In some platform, this instance can\nnot be successfully created.\".\n\nWhat are those \"some platform\" that this problem is seen in?\n\nThe error is related to the use of ICU4J, as shown in the stack.  Please make sure that whatever environment this is testing on has the correct version of the com.ibm.icu_3.4.2.jar installed.\n\nCaused by: java.lang.NullPointerException\n\n         at com.ibm.icu.util.TimeZone.getDefault(TimeZone.java:697)\n         at\ncom.ibm.icu.text.SimpleDateFormat.initialize(SimpleDateFormat.java:466)\n         at com.ibm.icu.text.SimpleDateFormat.\u003cinit\u003e(SimpleDateFormat.java:335)\n         at com.ibm.icu.text.SimpleDateFormat.\u003cinit\u003e(SimpleDateFormat.java:310)\n         at\norg.eclipse.datatools.connectivity.oda.util.logging.LogManager.\u003cclinit\u003e(LogManager.java:323)",
    "I have tested this bug in two WinXP system, and their locale both are Chinese, but there is no problem in Win2000 system with Chinese locale of one machine. First ICU are installed correctly since we are using the plugin attached by Eclipse3.2M4. Secondly this bug might belong to ICU. Below test can be simply to test whether this bug exists in a specified platform.\n\npublic class TestICU\n{\n\tpublic static void main( String[] argv )\n\t{\n\t\tSimpleDateFormat sm_dateFormat \u003d new SimpleDateFormat( \"yyyyMMdd-HHmmss\" );\n\t\tSystem.out.println( sm_dateFormat.toString( ) );\n\t}\n\t\n}",
    "Add below code at the begining of previous comments.\n\nimport com.ibm.icu.text.SimpleDateFormat;",
    "I\u0027d tried to run similar test Java application in my WinXP platform, but did not get any error in either Chinese (PRC) or English(US) as the default system locale.\n\nAlso tried to search for related info from ICU web sites, and did not find any related references.  I figure that since such configuration should be fairly common, ICU web sites would have mentioned related issues if this were an ICU4J bug.\nhttp://icu.sourceforge.net/\nhttp://lists.sourceforge.net/lists/listinfo/icu-support\n\nIn any case, do you see such problem when testing on English(US) default locale?\n\nBTW, my testing sets system default locale by going to the \"Advanced\" tab in the Windows XP\u0027s Regional and Language Options, and set the \"Language for non Unicode programs\" to \"Chinese(PRC)\".  \n",
    "Linda, we repoduced this issue in both Chinese (PRC) and English(US) as the default system locale.\n",
    "Temporarily rollback ICU4J implementation in ODA source...\nso that the BIRT smoke tests are not blocked, and there can be more time to investigate the difference in systems configuration from mine, where the problem cannot be reproduced.",
    "It seems that com.ibm.icu.util.TimeZone.getDefault( ) method has a bug in xp environment. When I use timezone GMT +8(China) or GMT -5(US) they null pointer exception would always be thrown. But if I set the timezone to GMT(Greenwich Mean Time, London) everything works fine. (We can change the timezone currently in use through control panel).\n\nIn windows 2000 environment, the method works smoothly, however.\n\n",
    "It seems that com.ibm.icu.util.ZoneMeta.getSystemTimeZone(String) method has a bug. It cannot handle GMT-offset-based time zone ID with format like \"GMT+8:00\"(meanwhile it does manage to handle some other kinds of timezone id, say, \"GMT\", or \"Asia/Shanghai\".This will in turn possibly lead to a NPE.\n\nThe following is the code of problem in com.ibm.icu.util.TimeZone class.\n  \n    public static synchronized TimeZone getDefault() {\n        if (defaultZone \u003d\u003d null) {\n            //The following line get a TimeZone instance which may possiblility have \n            //a GMT-offset-based time zone ID \n            java.util.TimeZone temp\u003djava.util.TimeZone.getDefault();\n\n            //The calling of ZoneMeta.getSystemTimeZone(temp.getID())\n            //will then return a null value.\n            defaultZone \u003d ZoneMeta.getSystemTimeZone(temp.getID());\n        }\n        //The null pointer exception is thrown out here.\n        return (TimeZone) defaultZone.clone();\n    }\n\nAs far as I know, in some windows XP environment java.util.TimeZone.getDefault() method will return TimeZone instances with GMT-offset-based time zone ID (On the other hand, I do find that in some XP and windows 2000 environment the method will return time zone ID with format like \"Asia/Shanghai\".In that case the com.ibm.icu.util.TimeZone.getDefault() method works fine). \n\nThis problem has been logged to ICU support mailist.\n",
    "Re-committed ICU4J implementation in ODA plugins.\n\nPer comments from the ICU team in #127582:\n\"the ICU4J fix has been made and is scheduled for ICU4J 3.4.3, which\nshould be released in a week or so.  That should be in time to go into Eclipse\n3.2M6.\"\n\nA temporary work-around for those WindowsXP platforms that return an offset-based time zone style id, is to configure the Windows time zone to ?GMT?, and set the time according to local time.",
    "fixed"
  ],
  "commentCreationDates": [
    "2006-02-10T05:10:29+01:00",
    "2006-02-10T08:08:18+01:00",
    "2006-02-10T20:18:57+01:00",
    "2006-02-11T04:14:05+01:00",
    "2006-02-11T04:15:25+01:00",
    "2006-02-11T22:34:48+01:00",
    "2006-02-13T02:45:30+01:00",
    "2006-02-13T04:48:04+01:00",
    "2006-02-13T09:10:12+01:00",
    "2006-02-13T12:42:52+01:00",
    "2006-02-15T00:00:04+01:00",
    "2006-02-16T02:51:15+01:00"
  ],
  "traces": [
    {
      "exceptionType": "java.lang.NoClassDefFoundError",
      "elements": [
        {
          "method": "org.eclipse.datatools.connectivity.oda.consumer.helper.OdaObject.logMethodCalled",
          "source": "OdaObject.java:352"
        },
        {
          "method": "org.eclipse.datatools.connectivity.oda.consumer.helper.OdaDriver.\u003cinit\u003e",
          "source": "OdaDriver.java:46"
        },
        {
          "method": "org.eclipse.birt.data.engine.odaconsumer.Driver.getDriverHelper",
          "source": "Driver.java:113"
        },
        {
          "method": "org.eclipse.birt.data.engine.odaconsumer.DriverManager.getDriverHelper",
          "source": "DriverManager.java:70"
        },
        {
          "method": "org.eclipse.birt.data.engine.odaconsumer.ConnectionManager.openConnection",
          "source": "ConnectionManager.java:113"
        },
        {
          "method": "org.eclipse.birt.data.engine.executor.DataSource.newConnection",
          "source": "DataSource.java:154"
        },
        {
          "method": "org.eclipse.birt.data.engine.executor.DataSource.open",
          "source": "DataSource.java:147"
        },
        {
          "method": "org.eclipse.birt.data.engine.impl.DataSourceRuntime.openOdiDataSource",
          "source": "DataSourceRuntime.java:150"
        },
        {
          "method": "org.eclipse.birt.data.engine.impl.PreparedQuery$Executor.openDataSource",
          "source": "PreparedQuery.java:838"
        },
        {
          "method": "org.eclipse.birt.data.engine.impl.PreparedExtendedDSQuery$ExtendedDSQueryExecutor.getParameterMetaData",
          "source": "PreparedExtendedDSQuery.java:591"
        },
        {
          "method": "org.eclipse.birt.data.engine.impl.PreparedExtendedDSQuery$ExtendedDSQueryExecutor.access$000",
          "source": "PreparedExtendedDSQuery.java:138"
        },
        {
          "method": "org.eclipse.birt.data.engine.impl.PreparedExtendedDSQuery.getParameterMetaData",
          "source": "PreparedExtendedDSQuery.java:130"
        },
        {
          "method": "org.eclipse.birt.report.designer.internal.ui.util.DataSetManager.getParametersFromDataSet",
          "source": "DataSetManager.java:843"
        },
        {
          "method": "org.eclipse.birt.report.designer.internal.ui.dialogs.DataSetParametersPage.refreshParameters",
          "source": "DataSetParametersPage.java:738"
        },
        {
          "method": "org.eclipse.birt.report.designer.internal.ui.dialogs.DataSetParametersPage.isValid",
          "source": "DataSetParametersPage.java:1033"
        },
        {
          "method": "org.eclipse.birt.report.designer.internal.ui.dialogs.DataSetParametersPage.performOk",
          "source": "DataSetParametersPage.java:1015"
        },
        {
          "method": "org.eclipse.birt.report.designer.ui.dialogs.properties.AbstractPropertyDialog.okPressed",
          "source": "AbstractPropertyDialog.java:570"
        },
        {
          "method": "org.eclipse.birt.report.designer.ui.dialogs.properties.AbstractPropertyDialog.okPressed",
          "source": "AbstractPropertyDialog.java:555"
        },
        {
          "method": "org.eclipse.birt.report.designer.ui.dialogs.DataSetEditor.okPressed",
          "source": "DataSetEditor.java:261"
        },
        {
          "method": "org.eclipse.birt.report.designer.ui.dialogs.properties.AbstractPropertyDialog.buttonPressed",
          "source": "AbstractPropertyDialog.java:437"
        },
        {
          "method": "org.eclipse.jface.dialogs.Dialog$2.widgetSelected",
          "source": "Dialog.java:607"
        },
        {
          "method": "org.eclipse.swt.widgets.TypedListener.handleEvent",
          "source": "TypedListener.java:90"
        },
        {
          "method": "org.eclipse.swt.widgets.EventTable.sendEvent",
          "source": "EventTable.java:66"
        },
        {
          "method": "org.eclipse.swt.widgets.Widget.sendEvent",
          "source": "Widget.java:914"
        },
        {
          "method": "org.eclipse.swt.widgets.Display.runDeferredEvents",
          "source": "Display.java:3285"
        },
        {
          "method": "org.eclipse.swt.widgets.Display.readAndDispatch",
          "source": "Display.java:2905"
        },
        {
          "method": "org.eclipse.jface.window.Window.runEventLoop",
          "source": "Window.java:808"
        },
        {
          "method": "org.eclipse.jface.window.Window.open",
          "source": "Window.java:786"
        },
        {
          "method": "org.eclipse.birt.report.designer.internal.ui.dialogs.BaseDialog.open",
          "source": "BaseDialog.java:145"
        },
        {
          "method": "org.eclipse.birt.report.designer.ui.actions.NewDataSetAction.editDataSet",
          "source": "NewDataSetAction.java:190"
        },
        {
          "method": "org.eclipse.birt.report.designer.ui.actions.NewDataSetAction.run",
          "source": "NewDataSetAction.java:128"
        },
        {
          "method": "org.eclipse.jface.action.Action.runWithEvent",
          "source": "Action.java:492"
        },
        {
          "method": "org.eclipse.jface.action.ActionContributionItem.handleWidgetSelection",
          "source": "ActionContributionItem.java:530"
        },
        {
          "method": "org.eclipse.jface.action.ActionContributionItem.access$2",
          "source": "ActionContributionItem.java:480"
        },
        {
          "method": "org.eclipse.jface.action.ActionContributionItem$5.handleEvent",
          "source": "ActionContributionItem.java:392"
        },
        {
          "method": "org.eclipse.swt.widgets.EventTable.sendEvent",
          "source": "EventTable.java:66"
        },
        {
          "method": "org.eclipse.swt.widgets.Widget.sendEvent",
          "source": "Widget.java:914"
        },
        {
          "method": "org.eclipse.swt.widgets.Display.runDeferredEvents",
          "source": "Display.java:3285"
        },
        {
          "method": "org.eclipse.swt.widgets.Display.readAndDispatch",
          "source": "Display.java:2905"
        },
        {
          "method": "org.eclipse.ui.internal.Workbench.runEventLoop",
          "source": "Workbench.java:1762"
        },
        {
          "method": "org.eclipse.ui.internal.Workbench.runUI",
          "source": "Workbench.java:1726"
        },
        {
          "method": "org.eclipse.ui.internal.Workbench.createAndRunWorkbench",
          "source": "Workbench.java:397"
        },
        {
          "method": "org.eclipse.ui.PlatformUI.createAndRunWorkbench",
          "source": "PlatformUI.java:143"
        },
        {
          "method": "org.eclipse.ui.internal.ide.IDEApplication.run",
          "source": "IDEApplication.java:106"
        },
        {
          "method": "org.eclipse.core.internal.runtime.PlatformActivator$1.run",
          "source": "PlatformActivator.java:109"
        },
        {
          "method": "org.eclipse.core.runtime.internal.adaptor.EclipseAppLauncher.runApplication",
          "source": "EclipseAppLauncher.java:92"
        },
        {
          "method": "org.eclipse.core.runtime.internal.adaptor.EclipseAppLauncher.start",
          "source": "EclipseAppLauncher.java:68"
        },
        {
          "method": "org.eclipse.core.runtime.adaptor.EclipseStarter.run",
          "source": "EclipseStarter.java:379"
        },
        {
          "method": "org.eclipse.core.runtime.adaptor.EclipseStarter.run",
          "source": "EclipseStarter.java:177"
        },
        {
          "method": "sun.reflect.NativeMethodAccessorImpl.invoke0",
          "source": "Native Method"
        },
        {
          "method": "sun.reflect.NativeMethodAccessorImpl.invoke",
          "source": "NativeMethodAccessorImpl.java:39"
        },
        {
          "method": "sun.reflect.DelegatingMethodAccessorImpl.invoke",
          "source": "DelegatingMethodAccessorImpl.java:25"
        },
        {
          "method": "java.lang.reflect.Method.invoke",
          "source": "Method.java:324"
        },
        {
          "method": "org.eclipse.core.launcher.Main.invokeFramework",
          "source": "Main.java:338"
        },
        {
          "method": "org.eclipse.core.launcher.Main.basicRun",
          "source": "Main.java:282"
        },
        {
          "method": "org.eclipse.core.launcher.Main.run",
          "source": "Main.java:977"
        },
        {
          "method": "org.eclipse.core.launcher.Main.main",
          "source": "Main.java:952"
        }
      ],
      "number": 0,
      "commentIndex": 0,
      "bugId": "127221",
      "date": "2006-02-10T05:10:29+01:00",
      "product": "BIRT",
      "component": "Data",
      "severity": "blocker"
    },
    {
      "exceptionType": "org.eclipse.swt.SWTException",
      "message": "Failed to execute runnable (java.lang.ExceptionInInitializerError)",
      "elements": [
        {
          "method": "org.eclipse.swt.SWT.error",
          "source": "SWT.java:3283"
        },
        {
          "method": "org.eclipse.swt.SWT.error",
          "source": "SWT.java:3206"
        },
        {
          "method": "org.eclipse.swt.widgets.Synchronizer.runAsyncMessages",
          "source": "Synchronizer.java:126"
        },
        {
          "method": "org.eclipse.swt.widgets.Display.runAsyncMessages",
          "source": "Display.java:3262"
        },
        {
          "method": "org.eclipse.swt.widgets.Display.readAndDispatch",
          "source": "Display.java:2908"
        },
        {
          "method": "org.eclipse.jface.window.Window.runEventLoop",
          "source": "Window.java:808"
        },
        {
          "method": "org.eclipse.jface.window.Window.open",
          "source": "Window.java:786"
        },
        {
          "method": "org.eclipse.birt.report.designer.internal.ui.dialogs.BaseDialog.open",
          "source": "BaseDialog.java:145"
        },
        {
          "method": "org.eclipse.birt.report.designer.ui.actions.NewDataSetAction.editDataSet",
          "source": "NewDataSetAction.java:190"
        },
        {
          "method": "org.eclipse.birt.report.designer.ui.actions.NewDataSetAction.run",
          "source": "NewDataSetAction.java:128"
        },
        {
          "method": "org.eclipse.jface.action.Action.runWithEvent",
          "source": "Action.java:492"
        },
        {
          "method": "org.eclipse.jface.action.ActionContributionItem.handleWidgetSelection",
          "source": "ActionContributionItem.java:530"
        },
        {
          "method": "org.eclipse.jface.action.ActionContributionItem.access$2",
          "source": "ActionContributionItem.java:480"
        },
        {
          "method": "org.eclipse.jface.action.ActionContributionItem$5.handleEvent",
          "source": "ActionContributionItem.java:392"
        },
        {
          "method": "org.eclipse.swt.widgets.EventTable.sendEvent",
          "source": "EventTable.java:66"
        },
        {
          "method": "org.eclipse.swt.widgets.Widget.sendEvent",
          "source": "Widget.java:914"
        },
        {
          "method": "org.eclipse.swt.widgets.Display.runDeferredEvents",
          "source": "Display.java:3285"
        },
        {
          "method": "org.eclipse.swt.widgets.Display.readAndDispatch",
          "source": "Display.java:2905"
        },
        {
          "method": "org.eclipse.ui.internal.Workbench.runEventLoop",
          "source": "Workbench.java:1762"
        },
        {
          "method": "org.eclipse.ui.internal.Workbench.runUI",
          "source": "Workbench.java:1726"
        },
        {
          "method": "org.eclipse.ui.internal.Workbench.createAndRunWorkbench",
          "source": "Workbench.java:397"
        },
        {
          "method": "org.eclipse.ui.PlatformUI.createAndRunWorkbench",
          "source": "PlatformUI.java:143"
        },
        {
          "method": "org.eclipse.ui.internal.ide.IDEApplication.run",
          "source": "IDEApplication.java:106"
        },
        {
          "method": "org.eclipse.core.internal.runtime.PlatformActivator$1.run",
          "source": "PlatformActivator.java:109"
        },
        {
          "method": "org.eclipse.core.runtime.internal.adaptor.EclipseAppLauncher.runApplication",
          "source": "EclipseAppLauncher.java:92"
        },
        {
          "method": "org.eclipse.core.runtime.internal.adaptor.EclipseAppLauncher.start",
          "source": "EclipseAppLauncher.java:68"
        },
        {
          "method": "org.eclipse.core.runtime.adaptor.EclipseStarter.run",
          "source": "EclipseStarter.java:379"
        },
        {
          "method": "org.eclipse.core.runtime.adaptor.EclipseStarter.run",
          "source": "EclipseStarter.java:177"
        },
        {
          "method": "sun.reflect.NativeMethodAccessorImpl.invoke0",
          "source": "Native Method"
        },
        {
          "method": "sun.reflect.NativeMethodAccessorImpl.invoke",
          "source": "NativeMethodAccessorImpl.java:39"
        },
        {
          "method": "sun.reflect.DelegatingMethodAccessorImpl.invoke",
          "source": "DelegatingMethodAccessorImpl.java:25"
        },
        {
          "method": "java.lang.reflect.Method.invoke",
          "source": "Method.java:324"
        },
        {
          "method": "org.eclipse.core.launcher.Main.invokeFramework",
          "source": "Main.java:338"
        },
        {
          "method": "org.eclipse.core.launcher.Main.basicRun",
          "source": "Main.java:282"
        },
        {
          "method": "org.eclipse.core.launcher.Main.run",
          "source": "Main.java:977"
        },
        {
          "method": "org.eclipse.core.launcher.Main.main",
          "source": "Main.java:952"
        }
      ],
      "causedBy": {
        "exceptionType": "java.lang.ExceptionInInitializerError",
        "elements": [
          {
            "method": "org.eclipse.datatools.connectivity.oda.consumer.helper.OdaObject.logMethodCalled",
            "source": "OdaObject.java:352"
          },
          {
            "method": "org.eclipse.datatools.connectivity.oda.consumer.helper.OdaDriver.\u003cinit\u003e",
            "source": "OdaDriver.java:46"
          },
          {
            "method": "org.eclipse.birt.data.engine.odaconsumer.Driver.getDriverHelper",
            "source": "Driver.java:113"
          },
          {
            "method": "org.eclipse.birt.data.engine.odaconsumer.DriverManager.getDriverHelper",
            "source": "DriverManager.java:70"
          },
          {
            "method": "org.eclipse.birt.data.engine.odaconsumer.ConnectionManager.openConnection",
            "source": "ConnectionManager.java:113"
          },
          {
            "method": "org.eclipse.birt.data.engine.executor.DataSource.newConnection",
            "source": "DataSource.java:154"
          },
          {
            "method": "org.eclipse.birt.data.engine.executor.DataSource.open",
            "source": "DataSource.java:147"
          },
          {
            "method": "org.eclipse.birt.data.engine.impl.DataSourceRuntime.openOdiDataSource",
            "source": "DataSourceRuntime.java:150"
          },
          {
            "method": "org.eclipse.birt.data.engine.impl.PreparedQuery$Executor.openDataSource",
            "source": "PreparedQuery.java:838"
          },
          {
            "method": "org.eclipse.birt.data.engine.impl.PreparedQuery$Executor.prepareExecution",
            "source": "PreparedQuery.java:661"
          },
          {
            "method": "org.eclipse.birt.data.engine.impl.PreparedQuery$Executor.access$000",
            "source": "PreparedQuery.java:498"
          },
          {
            "method": "org.eclipse.birt.data.engine.impl.PreparedQuery.doPrepare",
            "source": "PreparedQuery.java:225"
          },
          {
            "method": "org.eclipse.birt.data.engine.impl.PreparedDataSourceQuery.execute",
            "source": "PreparedDataSourceQuery.java:145"
          },
          {
            "method": "org.eclipse.birt.report.designer.internal.ui.util.DataSetManager.execute",
            "source": "DataSetManager.java:296"
          },
          {
            "method": "org.eclipse.birt.report.designer.internal.ui.util.DataSetManager.execute",
            "source": "DataSetManager.java:273"
          },
          {
            "method": "org.eclipse.birt.report.designer.internal.ui.dialogs.ResultSetPreviewPage.updateResults",
            "source": "ResultSetPreviewPage.java:143"
          },
          {
            "method": "org.eclipse.birt.report.designer.internal.ui.dialogs.ResultSetPreviewPage$4.run",
            "source": "ResultSetPreviewPage.java:401"
          },
          {
            "method": "org.eclipse.swt.widgets.RunnableLock.run",
            "source": "RunnableLock.java:35"
          },
          {
            "method": "org.eclipse.swt.widgets.Synchronizer.runAsyncMessages",
            "source": "Synchronizer.java:123"
          }
        ],
        "causedBy": {
          "exceptionType": "java.lang.NullPointerException",
          "elements": [
            {
              "method": "com.ibm.icu.util.TimeZone.getDefault",
              "source": "TimeZone.java:697"
            },
            {
              "method": "com.ibm.icu.text.SimpleDateFormat.initialize",
              "source": "SimpleDateFormat.java:466"
            },
            {
              "method": "com.ibm.icu.text.SimpleDateFormat.\u003cinit\u003e",
              "source": "SimpleDateFormat.java:335"
            },
            {
              "method": "com.ibm.icu.text.SimpleDateFormat.\u003cinit\u003e",
              "source": "SimpleDateFormat.java:310"
            },
            {
              "method": "org.eclipse.datatools.connectivity.oda.util.logging.LogManager.\u003cclinit\u003e",
              "source": "LogManager.java:323"
            }
          ],
          "number": 0,
          "commentIndex": 0
        },
        "number": 0,
        "commentIndex": 0
      },
      "number": 1,
      "commentIndex": 1,
      "bugId": "127221",
      "date": "2006-02-10T08:08:18+01:00",
      "product": "BIRT",
      "component": "Data",
      "severity": "blocker"
    },
    {
      "exceptionType": "java.lang.NullPointerException",
      "elements": [
        {
          "method": "com.ibm.icu.util.TimeZone.getDefault",
          "source": "TimeZone.java:697"
        },
        {
          "method": "com.ibm.icu.text.SimpleDateFormat.initialize",
          "source": "SimpleDateFormat.java:466"
        },
        {
          "method": "com.ibm.icu.text.SimpleDateFormat.\u003cinit\u003e",
          "source": "SimpleDateFormat.java:335"
        },
        {
          "method": "com.ibm.icu.text.SimpleDateFormat.\u003cinit\u003e",
          "source": "SimpleDateFormat.java:310"
        },
        {
          "method": "org.eclipse.datatools.connectivity.oda.util.logging.LogManager.\u003cclinit\u003e",
          "source": "LogManager.java:323"
        }
      ],
      "number": 2,
      "commentIndex": 2,
      "bugId": "127221",
      "date": "2006-02-10T20:18:57+01:00",
      "product": "BIRT",
      "component": "Data",
      "severity": "blocker"
    }
  ],
  "groupId": "127221",
  "bugId": "127221",
  "date": "2006-02-10T05:10:29+01:00",
  "product": "BIRT",
  "component": "Data",
  "severity": "blocker"
}