{
  "comments": [
    "Follow-up of bug 125301 comment 5 point 1. See bug 125301 comment 3 for test case details...\n\nStack trace is:\njava.lang.IllegalArgumentException\n        at org.eclipse.jdt.core.Signature.getReturnType(Signature.java:1633)\n        at org.eclipse.jdt.core.Signature.getReturnType(Signature.java:1649)\n        at org.eclipse.jdt.ui.JavaElementLabels.getMethodLabel(JavaElementLabels.java:502)\n        at org.eclipse.jdt.ui.JavaElementLabels.getElementLabel(JavaElementLabels.java:410)\n        at org.eclipse.jdt.ui.JavaElementLabels.getElementLabel(JavaElementLabels.java:387)\n        at org.eclipse.jdt.internal.ui.text.java.hover.JavadocHover.getInfoText(JavadocHover.java:144)\n        at org.eclipse.jdt.internal.ui.text.java.hover.JavadocHover.getHoverInfo(JavadocHover.java:119)\n        at org.eclipse.jdt.internal.ui.text.java.hover.AbstractJavaEditorTextHover.getHoverInfo(AbstractJavaEditorTextHover.java:112)\n        at org.eclipse.jdt.internal.ui.text.java.hover.BestMatchHover.getHoverInfo(BestMatchHover.java:102)\n        at org.eclipse.jdt.internal.ui.text.java.hover.JavaEditorTextHoverProxy.getHoverInfo(JavaEditorTextHoverProxy.java:69)\n        at org.eclipse.jface.text.TextViewerHoverManager$4.run(TextViewerHoverManager.java:160)",
    "BindingKey.toSignature() returns the type signature for a method belonging to such a type. Would need to escape $ in binding key.",
    "Reproduce using 3.3RC4:\n\n1. Create the following classes (in separate files):\n\npublic class A$B {\n        public void m() {\n        }\n}\n\npublic class X {\n        void foo() {\n                new A$B().m();\n        }\n}\n\n2. Hover over m in \u0027new A$B().m()\u0027\nObserve: you get the following exception in the .log:\n!ENTRY org.eclipse.jface.text 4 0 2007-06-21 18:23:45.406\n!MESSAGE Unexpected runtime error while computing a text hover\n!STACK 0\njava.lang.IllegalArgumentException\n\tat org.eclipse.jdt.core.Signature.getReturnType(Signature.java:1641)\n\tat org.eclipse.jdt.core.Signature.getReturnType(Signature.java:1657)\n\tat org.eclipse.jdt.ui.JavaElementLabels.getMethodLabel(JavaElementLabels.java:510)\n\tat org.eclipse.jdt.ui.JavaElementLabels.getElementLabel(JavaElementLabels.java:427)\n\tat org.eclipse.jdt.ui.JavaElementLabels.getElementLabel(JavaElementLabels.java:404)\n\tat org.eclipse.jdt.internal.ui.text.java.hover.JavadocHover.getInfoText(JavadocHover.java:225)\n\tat org.eclipse.jdt.internal.ui.text.java.hover.JavadocHover.getHoverInfo(JavadocHover.java:173)\n\tat org.eclipse.jdt.internal.ui.text.java.hover.AbstractJavaEditorTextHover.getHoverInfo(AbstractJavaEditorTextHover.java:125)\n\tat org.eclipse.jdt.internal.ui.text.java.hover.BestMatchHover.getHoverInfo(BestMatchHover.java:102)\n\tat org.eclipse.jdt.internal.ui.text.java.hover.JavaEditorTextHoverProxy.getHoverInfo(JavaEditorTextHoverProxy.java:69)\n\tat org.eclipse.jface.text.TextViewerHoverManager$4.run(TextViewerHoverManager.java:165)"
  ],
  "commentCreationDates": [
    "2006-02-14T15:53:49+01:00",
    "2006-02-14T16:36:51+01:00",
    "2007-06-21T18:26:10+02:00"
  ],
  "traces": [
    {
      "exceptionType": "java.lang.IllegalArgumentException",
      "elements": [
        {
          "method": "org.eclipse.jdt.core.Signature.getReturnType",
          "source": "Signature.java:1633"
        },
        {
          "method": "org.eclipse.jdt.core.Signature.getReturnType",
          "source": "Signature.java:1649"
        },
        {
          "method": "org.eclipse.jdt.ui.JavaElementLabels.getMethodLabel",
          "source": "JavaElementLabels.java:502"
        },
        {
          "method": "org.eclipse.jdt.ui.JavaElementLabels.getElementLabel",
          "source": "JavaElementLabels.java:410"
        },
        {
          "method": "org.eclipse.jdt.ui.JavaElementLabels.getElementLabel",
          "source": "JavaElementLabels.java:387"
        },
        {
          "method": "org.eclipse.jdt.internal.ui.text.java.hover.JavadocHover.getInfoText",
          "source": "JavadocHover.java:144"
        },
        {
          "method": "org.eclipse.jdt.internal.ui.text.java.hover.JavadocHover.getHoverInfo",
          "source": "JavadocHover.java:119"
        },
        {
          "method": "org.eclipse.jdt.internal.ui.text.java.hover.AbstractJavaEditorTextHover.getHoverInfo",
          "source": "AbstractJavaEditorTextHover.java:112"
        },
        {
          "method": "org.eclipse.jdt.internal.ui.text.java.hover.BestMatchHover.getHoverInfo",
          "source": "BestMatchHover.java:102"
        },
        {
          "method": "org.eclipse.jdt.internal.ui.text.java.hover.JavaEditorTextHoverProxy.getHoverInfo",
          "source": "JavaEditorTextHoverProxy.java:69"
        },
        {
          "method": "org.eclipse.jface.text.TextViewerHoverManager$4.run",
          "source": "TextViewerHoverManager.java:160"
        }
      ],
      "number": 0,
      "commentIndex": 0,
      "bugId": "127739",
      "date": "2006-02-14T15:53:49+01:00",
      "product": "JDT",
      "component": "Core",
      "severity": "normal"
    },
    {
      "exceptionType": "java.lang.IllegalArgumentException",
      "elements": [
        {
          "method": "org.eclipse.jdt.core.Signature.getReturnType",
          "source": "Signature.java:1641"
        },
        {
          "method": "org.eclipse.jdt.core.Signature.getReturnType",
          "source": "Signature.java:1657"
        },
        {
          "method": "org.eclipse.jdt.ui.JavaElementLabels.getMethodLabel",
          "source": "JavaElementLabels.java:510"
        },
        {
          "method": "org.eclipse.jdt.ui.JavaElementLabels.getElementLabel",
          "source": "JavaElementLabels.java:427"
        },
        {
          "method": "org.eclipse.jdt.ui.JavaElementLabels.getElementLabel",
          "source": "JavaElementLabels.java:404"
        },
        {
          "method": "org.eclipse.jdt.internal.ui.text.java.hover.JavadocHover.getInfoText",
          "source": "JavadocHover.java:225"
        },
        {
          "method": "org.eclipse.jdt.internal.ui.text.java.hover.JavadocHover.getHoverInfo",
          "source": "JavadocHover.java:173"
        },
        {
          "method": "org.eclipse.jdt.internal.ui.text.java.hover.AbstractJavaEditorTextHover.getHoverInfo",
          "source": "AbstractJavaEditorTextHover.java:125"
        },
        {
          "method": "org.eclipse.jdt.internal.ui.text.java.hover.BestMatchHover.getHoverInfo",
          "source": "BestMatchHover.java:102"
        },
        {
          "method": "org.eclipse.jdt.internal.ui.text.java.hover.JavaEditorTextHoverProxy.getHoverInfo",
          "source": "JavaEditorTextHoverProxy.java:69"
        },
        {
          "method": "org.eclipse.jface.text.TextViewerHoverManager$4.run",
          "source": "TextViewerHoverManager.java:165"
        }
      ],
      "number": 1,
      "commentIndex": 2,
      "bugId": "127739",
      "date": "2007-06-21T18:26:10+02:00",
      "product": "JDT",
      "component": "Core",
      "severity": "normal"
    }
  ],
  "groupId": "127739",
  "bugId": "127739",
  "date": "2006-02-14T15:53:49+01:00",
  "product": "JDT",
  "component": "Core",
  "severity": "normal"
}