{
  "comments": [
    "SWT-win32, v3224\n\nWhen running the code below, the following exception is thrown:\n\nException in thread \"main\" org.eclipse.swt.SWTException: Widget is disposed\n\tat org.eclipse.swt.SWT.error(SWT.java:3349)\n\tat org.eclipse.swt.SWT.error(SWT.java:3272)\n\tat org.eclipse.swt.SWT.error(SWT.java:3243)\n\tat org.eclipse.swt.widgets.Widget.error(Widget.java:432)\n\tat org.eclipse.swt.widgets.Widget.checkWidget(Widget.java:327)\n\tat org.eclipse.swt.widgets.Canvas.getCaret(Canvas.java:108)\n\tat org.eclipse.swt.widgets.Caret.releaseParent(Caret.java:283)\n\tat org.eclipse.swt.widgets.Widget.release(Widget.java:748)\n\tat org.eclipse.swt.widgets.Widget.dispose(Widget.java:412)\n\tat CaretDisposeTest.main(CaretDisposeTest.java:...)\n\n---\n\nimport org.eclipse.swt.*;\nimport org.eclipse.swt.widgets.*;\n\npublic class CaretDisposeTest {\n  public static void main(String[] args) {\n    Display display \u003d new Display();\n    Shell shell \u003d new Shell(display);\n    Caret caret \u003d new Caret(shell, SWT.NONE);\n    shell.setCaret(null);\n    shell.dispose();\n    caret.dispose();\n    display.dispose();\n  }\n}"
  ],
  "commentCreationDates": [
    "2006-02-15T07:04:03+01:00"
  ],
  "traces": [
    {
      "exceptionType": "org.eclipse.swt.SWTException",
      "message": "Widget is disposed",
      "elements": [
        {
          "method": "org.eclipse.swt.SWT.error",
          "source": "SWT.java:3349"
        },
        {
          "method": "org.eclipse.swt.SWT.error",
          "source": "SWT.java:3272"
        },
        {
          "method": "org.eclipse.swt.SWT.error",
          "source": "SWT.java:3243"
        },
        {
          "method": "org.eclipse.swt.widgets.Widget.error",
          "source": "Widget.java:432"
        },
        {
          "method": "org.eclipse.swt.widgets.Widget.checkWidget",
          "source": "Widget.java:327"
        },
        {
          "method": "org.eclipse.swt.widgets.Canvas.getCaret",
          "source": "Canvas.java:108"
        },
        {
          "method": "org.eclipse.swt.widgets.Caret.releaseParent",
          "source": "Caret.java:283"
        },
        {
          "method": "org.eclipse.swt.widgets.Widget.release",
          "source": "Widget.java:748"
        },
        {
          "method": "org.eclipse.swt.widgets.Widget.dispose",
          "source": "Widget.java:412"
        },
        {
          "method": "CaretDisposeTest.main",
          "source": "CaretDisposeTest.java:..."
        }
      ],
      "number": 0,
      "commentIndex": 0,
      "bugId": "127975",
      "date": "2006-02-15T07:04:03+01:00",
      "product": "Platform",
      "component": "SWT",
      "severity": "normal"
    }
  ],
  "groupId": "127975",
  "bugId": "127975",
  "date": "2006-02-15T07:04:03+01:00",
  "product": "Platform",
  "component": "SWT",
  "severity": "normal"
}