{
  "comments": [
    "I import an SVN hosted project, it\u0027s about 16000 files.\nI go to look up a symbol and the indexer starts.  At the same point on multiple attempts the indexer stops progressing.  On stdout(err?) there are messages like:\norg.eclipse.core.internal.utils.AssertionFailedException: Assertion failed: Malformed tree.\n        at org.eclipse.core.internal.utils.Assert.isTrue(Assert.java:109)\n        at org.eclipse.core.internal.dtree.DeltaDataTree.getChildNodes(DeltaDataTree.java:522)\n        at org.eclipse.core.internal.dtree.DeltaDataTree.getChildren(DeltaDataTree.java:534)\n        at org.eclipse.core.internal.watson.ElementTree.getChildIDs(ElementTree.java:331)\n        at org.eclipse.core.internal.watson.ElementTree.getChildren(ElementTree.java:347)\n        at org.eclipse.core.internal.resources.Container.getChildren(Container.java:93)\n        at org.eclipse.core.internal.resources.WorkspaceRoot.getProjects(WorkspaceRoot.java:152)\n        at org.eclipse.core.internal.localstore.FileSystemResourceManager.pathForLocation(FileSystemResourceManager.java:475)\n        at org.eclipse.core.internal.localstore.FileSystemResourceManager.fileForLocation(FileSystemResourceManager.java:194)\n        at org.eclipse.core.internal.resources.WorkspaceRoot.getFileForLocation(WorkspaceRoot.java:87)\n        at org.eclipse.cdt.internal.core.index.domsourceindexer.IndexEncoderUtil.calculateIndexFlags(IndexEncoderUtil.java:38)\n        at org.eclipse.cdt.internal.core.index.domsourceindexer.CGenerateIndexVisitor.processName(CGenerateIndexVisitor.java:135)\n        at org.eclipse.cdt.internal.core.index.domsourceindexer.CGenerateIndexVisitor.visit(CGenerateIndexVisitor.java:80)\n        at org.eclipse.cdt.internal.core.dom.parser.c.CASTName.accept(CASTName.java:86)\n        at org.eclipse.cdt.internal.core.dom.parser.c.CASTIdExpression.accept(CASTIdExpression.java:47)\n        at org.eclipse.cdt.internal.core.dom.parser.c.CASTFunctionCallExpression.accept(CASTFunctionCallExpression.java:66)\n        at org.eclipse.cdt.internal.core.dom.parser.c.CASTBinaryExpression.accept(CASTBinaryExpression.java:81)\n        at org.eclipse.cdt.internal.core.dom.parser.c.CASTForStatement.accept(CASTForStatement.java:93)\n        at org.eclipse.cdt.internal.core.dom.parser.c.CASTCompoundStatement.accept(CASTCompoundStatement.java:67)\n        at org.eclipse.cdt.internal.core.dom.parser.c.CASTSwitchStatement.accept(CASTSwitchStatement.java:66)\n        at org.eclipse.cdt.internal.core.dom.parser.c.CASTCompoundStatement.accept(CASTCompoundStatement.java:67)\n        at org.eclipse.cdt.internal.core.dom.parser.c.CASTFunctionDefinition.accept(CASTFunctionDefinition.java:96)\n        at org.eclipse.cdt.internal.core.dom.parser.c.CASTTranslationUnit.accept(CASTTranslationUnit.java:481)\n        at org.eclipse.cdt.internal.core.index.domsourceindexer.DOMSourceIndexerRunner.indexFile(DOMSourceIndexerRunner.java:133)\n        at org.eclipse.cdt.internal.core.index.domsourceindexer.AbstractIndexerRunner.index(AbstractIndexerRunner.java:76)\n        at org.eclipse.cdt.internal.core.index.cindexstorage.Index.add(Index.java:110)\n        at org.eclipse.cdt.internal.core.index.domsourceindexer.DOMAddCompilationUnitToIndex.indexDocument(DOMAddCompilationUnitToIndex.java:29)\n        at org.eclipse.cdt.internal.core.index.domsourceindexer.DOMAddFileToIndex.execute(DOMAddFileToIndex.java:60)\n        at org.eclipse.cdt.internal.core.search.processing.JobManager.run(JobManager.java:466)\n        at java.lang.Thread.run(Unknown Source)\njava.lang.NullPointerException\n        at org.eclipse.cdt.internal.core.dom.parser.cpp.CPPVisitor.createBinding(CPPVisitor.java:349)\n        at org.eclipse.cdt.internal.core.dom.parser.cpp.CPPVisitor.createBinding(CPPVisitor.java:190)\n        at org.eclipse.cdt.internal.core.dom.parser.cpp.CPPASTName.resolveBinding(CPPASTName.java:52)\n        at org.eclipse.cdt.internal.core.index.domsourceindexer.CPPGenerateIndexVisitor.processName(CPPGenerateIndexVisitor.java:148)\n        at org.eclipse.cdt.internal.core.index.domsourceindexer.CPPGenerateIndexVisitor.visit(CPPGenerateIndexVisitor.java:112)\n        at org.eclipse.cdt.internal.core.dom.parser.cpp.CPPASTName.accept(CPPASTName.java:90)\n        at org.eclipse.cdt.internal.core.dom.parser.cpp.CPPASTElaboratedTypeSpecifier.accept(CPPASTElaboratedTypeSpecifier.java:68)\n        at org.eclipse.cdt.internal.core.dom.parser.cpp.CPPASTParameterDeclaration.accept(CPPASTParameterDeclaration.java:64)\n        at org.eclipse.cdt.internal.core.dom.parser.cpp.CPPASTFunctionDeclarator.postAccept(CPPASTFunctionDeclarator.java:181)\n        at org.eclipse.cdt.internal.core.dom.parser.cpp.CPPASTDeclarator.accept(CPPASTDeclarator.java:131)\n        at org.eclipse.cdt.internal.core.dom.parser.cpp.CPPASTSimpleDeclaration.accept(CPPASTSimpleDeclaration.java:74)\n        at org.eclipse.cdt.internal.core.dom.parser.cpp.CPPASTTemplateDeclaration.accept(CPPASTTemplateDeclaration.java:95)\n        at org.eclipse.cdt.internal.core.dom.parser.cpp.CPPASTTranslationUnit.accept(CPPASTTranslationUnit.java:520)\n        at org.eclipse.cdt.internal.core.index.domsourceindexer.DOMSourceIndexerRunner.indexFile(DOMSourceIndexerRunner.java:133)\n        at org.eclipse.cdt.internal.core.index.domsourceindexer.AbstractIndexerRunner.index(AbstractIndexerRunner.java:76)\n        at org.eclipse.cdt.internal.core.index.cindexstorage.Index.add(Index.java:110)\n        at org.eclipse.cdt.internal.core.index.domsourceindexer.DOMAddCompilationUnitToIndex.indexDocument(DOMAddCompilationUnitToIndex.java:29)\n        at org.eclipse.cdt.internal.core.index.domsourceindexer.DOMAddFileToIndex.execute(DOMAddFileToIndex.java:60)\n        at org.eclipse.cdt.internal.core.search.processing.JobManager.run(JobManager.java:466)\n        at java.lang.Thread.run(Unknown Source)\norg.eclipse.core.internal.utils.AssertionFailedException: Assertion failed: Malformed tree.\n        at org.eclipse.core.internal.utils.Assert.isTrue(Assert.java:109)\n        at org.eclipse.core.internal.dtree.DeltaDataTree.getChildNodes(DeltaDataTree.java:522)\n        at org.eclipse.core.internal.dtree.DeltaDataTree.getChildren(DeltaDataTree.java:534)\n        at org.eclipse.core.internal.watson.ElementTree.getChildIDs(ElementTree.java:331)\n        at org.eclipse.core.internal.watson.ElementTree.getChildren(ElementTree.java:347)\n        at org.eclipse.core.internal.resources.Container.getChildren(Container.java:93)\n        at org.eclipse.core.internal.resources.WorkspaceRoot.getProjects(WorkspaceRoot.java:152)\n        at org.eclipse.core.internal.localstore.FileSystemResourceManager.pathForLocation(FileSystemResourceManager.java:475)\n        at org.eclipse.core.internal.localstore.FileSystemResourceManager.fileForLocation(FileSystemResourceManager.java:194)\n        at org.eclipse.core.internal.resources.WorkspaceRoot.getFileForLocation(WorkspaceRoot.java:87)\n        at org.eclipse.cdt.internal.core.index.domsourceindexer.IndexEncoderUtil.calculateIndexFlags(IndexEncoderUtil.java:38)\n        at org.eclipse.cdt.internal.core.index.domsourceindexer.CGenerateIndexVisitor.processName(CGenerateIndexVisitor.java:135)\n        at org.eclipse.cdt.internal.core.index.domsourceindexer.CGenerateIndexVisitor.visit(CGenerateIndexVisitor.java:80)\n        at org.eclipse.cdt.internal.core.dom.parser.c.CASTName.accept(CASTName.java:86)\n        at org.eclipse.cdt.internal.core.dom.parser.c.CASTIdExpression.accept(CASTIdExpression.java:47)\n        at org.eclipse.cdt.internal.core.dom.parser.c.CASTFieldReference.accept(CASTFieldReference.java:80)\n        at org.eclipse.cdt.internal.core.dom.parser.c.CASTUnaryExpression.accept(CASTUnaryExpression.java:65)\n        at org.eclipse.cdt.internal.core.dom.parser.c.CASTFunctionCallExpression.accept(CASTFunctionCallExpression.java:66)\n        at org.eclipse.cdt.internal.core.dom.parser.c.CASTExpressionStatement.accept(CASTExpressionStatement.java:57)\n        at org.eclipse.cdt.internal.core.dom.parser.c.CASTCompoundStatement.accept(CASTCompoundStatement.java:67)\n        at org.eclipse.cdt.internal.core.dom.parser.c.CASTFunctionDefinition.accept(CASTFunctionDefinition.java:96)\n        at org.eclipse.cdt.internal.core.dom.parser.c.CASTTranslationUnit.accept(CASTTranslationUnit.java:481)\n        at org.eclipse.cdt.internal.core.index.domsourceindexer.DOMSourceIndexerRunner.indexFile(DOMSourceIndexerRunner.java:133)\n        at org.eclipse.cdt.internal.core.index.domsourceindexer.AbstractIndexerRunner.index(AbstractIndexerRunner.java:76)\n        at org.eclipse.cdt.internal.core.index.cindexstorage.Index.add(Index.java:110)\n        at org.eclipse.cdt.internal.core.index.domsourceindexer.DOMAddCompilationUnitToIndex.indexDocument(DOMAddCompilationUnitToIndex.java:29)\n        at org.eclipse.cdt.internal.core.index.domsourceindexer.DOMAddFileToIndex.execute(DOMAddFileToIndex.java:60)\n        at org.eclipse.cdt.internal.core.search.processing.JobManager.run(JobManager.java:466)\n        at java.lang.Thread.run(Unknown Source)\n                                                                           \nSorry I know very little about Java, or eclipse, or the CDT.  I\u0027m just starting to look.\n\nThe eclipse is from eclipse-SDK-3.1.2-linux-gtk-x86_64.tar.gz tarball, CDT and subclipse were installed from the net within the last two weeks.\n\nI can give more version info on CDT when the import currrently tieing up the UI finishes.  Oo, no I used the run in background button and the manage config dialog seems to be saying 3.0.1.\n\nThe running import and the hanging indexer have both been going for about 5 hours so I\u0027m pretty sure they\u0027re OK/hung respectively.\n\nWhen the second import finishes/or crashes out I\u0027ll try a project with just the hanging file to see what happens.\n\nThanks for your time",
    "I tried setting up a project with just the fille that the indexer stalled on.  After deleting the original project there were no problems executing searches. Although there wasn\u0027t much point in the searches I tried I assume that merely executing them get the indexer to do its thing.\n\nBTW when the indexer stalls, it doesn\u0027t finish when i click the little red stop button and even if I exit eclipse I have to go kill of java processes afterward.\n\nIs there a list, or some general guidlines as to what would be helpful to collect on the state of the processes left behind?\n\nThanks for your time.\n",
    "The indexer works differently today, CGenerateIndexVisitor no longer exists."
  ],
  "commentCreationDates": [
    "2006-02-15T05:57:05+01:00",
    "2006-02-16T18:52:57+01:00",
    "2007-11-23T11:02:46+01:00"
  ],
  "traces": [
    {
      "exceptionType": "org.eclipse.core.internal.utils.AssertionFailedException",
      "message": "Assertion failed: Malformed tree.",
      "elements": [
        {
          "method": "org.eclipse.core.internal.utils.Assert.isTrue",
          "source": "Assert.java:109"
        },
        {
          "method": "org.eclipse.core.internal.dtree.DeltaDataTree.getChildNodes",
          "source": "DeltaDataTree.java:522"
        },
        {
          "method": "org.eclipse.core.internal.dtree.DeltaDataTree.getChildren",
          "source": "DeltaDataTree.java:534"
        },
        {
          "method": "org.eclipse.core.internal.watson.ElementTree.getChildIDs",
          "source": "ElementTree.java:331"
        },
        {
          "method": "org.eclipse.core.internal.watson.ElementTree.getChildren",
          "source": "ElementTree.java:347"
        },
        {
          "method": "org.eclipse.core.internal.resources.Container.getChildren",
          "source": "Container.java:93"
        },
        {
          "method": "org.eclipse.core.internal.resources.WorkspaceRoot.getProjects",
          "source": "WorkspaceRoot.java:152"
        },
        {
          "method": "org.eclipse.core.internal.localstore.FileSystemResourceManager.pathForLocation",
          "source": "FileSystemResourceManager.java:475"
        },
        {
          "method": "org.eclipse.core.internal.localstore.FileSystemResourceManager.fileForLocation",
          "source": "FileSystemResourceManager.java:194"
        },
        {
          "method": "org.eclipse.core.internal.resources.WorkspaceRoot.getFileForLocation",
          "source": "WorkspaceRoot.java:87"
        },
        {
          "method": "org.eclipse.cdt.internal.core.index.domsourceindexer.IndexEncoderUtil.calculateIndexFlags",
          "source": "IndexEncoderUtil.java:38"
        },
        {
          "method": "org.eclipse.cdt.internal.core.index.domsourceindexer.CGenerateIndexVisitor.processName",
          "source": "CGenerateIndexVisitor.java:135"
        },
        {
          "method": "org.eclipse.cdt.internal.core.index.domsourceindexer.CGenerateIndexVisitor.visit",
          "source": "CGenerateIndexVisitor.java:80"
        },
        {
          "method": "org.eclipse.cdt.internal.core.dom.parser.c.CASTName.accept",
          "source": "CASTName.java:86"
        },
        {
          "method": "org.eclipse.cdt.internal.core.dom.parser.c.CASTIdExpression.accept",
          "source": "CASTIdExpression.java:47"
        },
        {
          "method": "org.eclipse.cdt.internal.core.dom.parser.c.CASTFunctionCallExpression.accept",
          "source": "CASTFunctionCallExpression.java:66"
        },
        {
          "method": "org.eclipse.cdt.internal.core.dom.parser.c.CASTBinaryExpression.accept",
          "source": "CASTBinaryExpression.java:81"
        },
        {
          "method": "org.eclipse.cdt.internal.core.dom.parser.c.CASTForStatement.accept",
          "source": "CASTForStatement.java:93"
        },
        {
          "method": "org.eclipse.cdt.internal.core.dom.parser.c.CASTCompoundStatement.accept",
          "source": "CASTCompoundStatement.java:67"
        },
        {
          "method": "org.eclipse.cdt.internal.core.dom.parser.c.CASTSwitchStatement.accept",
          "source": "CASTSwitchStatement.java:66"
        },
        {
          "method": "org.eclipse.cdt.internal.core.dom.parser.c.CASTCompoundStatement.accept",
          "source": "CASTCompoundStatement.java:67"
        },
        {
          "method": "org.eclipse.cdt.internal.core.dom.parser.c.CASTFunctionDefinition.accept",
          "source": "CASTFunctionDefinition.java:96"
        },
        {
          "method": "org.eclipse.cdt.internal.core.dom.parser.c.CASTTranslationUnit.accept",
          "source": "CASTTranslationUnit.java:481"
        },
        {
          "method": "org.eclipse.cdt.internal.core.index.domsourceindexer.DOMSourceIndexerRunner.indexFile",
          "source": "DOMSourceIndexerRunner.java:133"
        },
        {
          "method": "org.eclipse.cdt.internal.core.index.domsourceindexer.AbstractIndexerRunner.index",
          "source": "AbstractIndexerRunner.java:76"
        },
        {
          "method": "org.eclipse.cdt.internal.core.index.cindexstorage.Index.add",
          "source": "Index.java:110"
        },
        {
          "method": "org.eclipse.cdt.internal.core.index.domsourceindexer.DOMAddCompilationUnitToIndex.indexDocument",
          "source": "DOMAddCompilationUnitToIndex.java:29"
        },
        {
          "method": "org.eclipse.cdt.internal.core.index.domsourceindexer.DOMAddFileToIndex.execute",
          "source": "DOMAddFileToIndex.java:60"
        },
        {
          "method": "org.eclipse.cdt.internal.core.search.processing.JobManager.run",
          "source": "JobManager.java:466"
        },
        {
          "method": "java.lang.Thread.run",
          "source": "Unknown Source"
        }
      ],
      "number": 0,
      "commentIndex": 0,
      "bugId": "127969",
      "date": "2006-02-15T05:57:05+01:00",
      "product": "CDT",
      "component": "CDT-parser",
      "severity": "major"
    },
    {
      "exceptionType": "java.lang.NullPointerException",
      "elements": [
        {
          "method": "org.eclipse.cdt.internal.core.dom.parser.cpp.CPPVisitor.createBinding",
          "source": "CPPVisitor.java:349"
        },
        {
          "method": "org.eclipse.cdt.internal.core.dom.parser.cpp.CPPVisitor.createBinding",
          "source": "CPPVisitor.java:190"
        },
        {
          "method": "org.eclipse.cdt.internal.core.dom.parser.cpp.CPPASTName.resolveBinding",
          "source": "CPPASTName.java:52"
        },
        {
          "method": "org.eclipse.cdt.internal.core.index.domsourceindexer.CPPGenerateIndexVisitor.processName",
          "source": "CPPGenerateIndexVisitor.java:148"
        },
        {
          "method": "org.eclipse.cdt.internal.core.index.domsourceindexer.CPPGenerateIndexVisitor.visit",
          "source": "CPPGenerateIndexVisitor.java:112"
        },
        {
          "method": "org.eclipse.cdt.internal.core.dom.parser.cpp.CPPASTName.accept",
          "source": "CPPASTName.java:90"
        },
        {
          "method": "org.eclipse.cdt.internal.core.dom.parser.cpp.CPPASTElaboratedTypeSpecifier.accept",
          "source": "CPPASTElaboratedTypeSpecifier.java:68"
        },
        {
          "method": "org.eclipse.cdt.internal.core.dom.parser.cpp.CPPASTParameterDeclaration.accept",
          "source": "CPPASTParameterDeclaration.java:64"
        },
        {
          "method": "org.eclipse.cdt.internal.core.dom.parser.cpp.CPPASTFunctionDeclarator.postAccept",
          "source": "CPPASTFunctionDeclarator.java:181"
        },
        {
          "method": "org.eclipse.cdt.internal.core.dom.parser.cpp.CPPASTDeclarator.accept",
          "source": "CPPASTDeclarator.java:131"
        },
        {
          "method": "org.eclipse.cdt.internal.core.dom.parser.cpp.CPPASTSimpleDeclaration.accept",
          "source": "CPPASTSimpleDeclaration.java:74"
        },
        {
          "method": "org.eclipse.cdt.internal.core.dom.parser.cpp.CPPASTTemplateDeclaration.accept",
          "source": "CPPASTTemplateDeclaration.java:95"
        },
        {
          "method": "org.eclipse.cdt.internal.core.dom.parser.cpp.CPPASTTranslationUnit.accept",
          "source": "CPPASTTranslationUnit.java:520"
        },
        {
          "method": "org.eclipse.cdt.internal.core.index.domsourceindexer.DOMSourceIndexerRunner.indexFile",
          "source": "DOMSourceIndexerRunner.java:133"
        },
        {
          "method": "org.eclipse.cdt.internal.core.index.domsourceindexer.AbstractIndexerRunner.index",
          "source": "AbstractIndexerRunner.java:76"
        },
        {
          "method": "org.eclipse.cdt.internal.core.index.cindexstorage.Index.add",
          "source": "Index.java:110"
        },
        {
          "method": "org.eclipse.cdt.internal.core.index.domsourceindexer.DOMAddCompilationUnitToIndex.indexDocument",
          "source": "DOMAddCompilationUnitToIndex.java:29"
        },
        {
          "method": "org.eclipse.cdt.internal.core.index.domsourceindexer.DOMAddFileToIndex.execute",
          "source": "DOMAddFileToIndex.java:60"
        },
        {
          "method": "org.eclipse.cdt.internal.core.search.processing.JobManager.run",
          "source": "JobManager.java:466"
        },
        {
          "method": "java.lang.Thread.run",
          "source": "Unknown Source"
        }
      ],
      "number": 1,
      "commentIndex": 0,
      "bugId": "127969",
      "date": "2006-02-15T05:57:05+01:00",
      "product": "CDT",
      "component": "CDT-parser",
      "severity": "major"
    },
    {
      "exceptionType": "org.eclipse.core.internal.utils.AssertionFailedException",
      "message": "Assertion failed: Malformed tree.",
      "elements": [
        {
          "method": "org.eclipse.core.internal.utils.Assert.isTrue",
          "source": "Assert.java:109"
        },
        {
          "method": "org.eclipse.core.internal.dtree.DeltaDataTree.getChildNodes",
          "source": "DeltaDataTree.java:522"
        },
        {
          "method": "org.eclipse.core.internal.dtree.DeltaDataTree.getChildren",
          "source": "DeltaDataTree.java:534"
        },
        {
          "method": "org.eclipse.core.internal.watson.ElementTree.getChildIDs",
          "source": "ElementTree.java:331"
        },
        {
          "method": "org.eclipse.core.internal.watson.ElementTree.getChildren",
          "source": "ElementTree.java:347"
        },
        {
          "method": "org.eclipse.core.internal.resources.Container.getChildren",
          "source": "Container.java:93"
        },
        {
          "method": "org.eclipse.core.internal.resources.WorkspaceRoot.getProjects",
          "source": "WorkspaceRoot.java:152"
        },
        {
          "method": "org.eclipse.core.internal.localstore.FileSystemResourceManager.pathForLocation",
          "source": "FileSystemResourceManager.java:475"
        },
        {
          "method": "org.eclipse.core.internal.localstore.FileSystemResourceManager.fileForLocation",
          "source": "FileSystemResourceManager.java:194"
        },
        {
          "method": "org.eclipse.core.internal.resources.WorkspaceRoot.getFileForLocation",
          "source": "WorkspaceRoot.java:87"
        },
        {
          "method": "org.eclipse.cdt.internal.core.index.domsourceindexer.IndexEncoderUtil.calculateIndexFlags",
          "source": "IndexEncoderUtil.java:38"
        },
        {
          "method": "org.eclipse.cdt.internal.core.index.domsourceindexer.CGenerateIndexVisitor.processName",
          "source": "CGenerateIndexVisitor.java:135"
        },
        {
          "method": "org.eclipse.cdt.internal.core.index.domsourceindexer.CGenerateIndexVisitor.visit",
          "source": "CGenerateIndexVisitor.java:80"
        },
        {
          "method": "org.eclipse.cdt.internal.core.dom.parser.c.CASTName.accept",
          "source": "CASTName.java:86"
        },
        {
          "method": "org.eclipse.cdt.internal.core.dom.parser.c.CASTIdExpression.accept",
          "source": "CASTIdExpression.java:47"
        },
        {
          "method": "org.eclipse.cdt.internal.core.dom.parser.c.CASTFieldReference.accept",
          "source": "CASTFieldReference.java:80"
        },
        {
          "method": "org.eclipse.cdt.internal.core.dom.parser.c.CASTUnaryExpression.accept",
          "source": "CASTUnaryExpression.java:65"
        },
        {
          "method": "org.eclipse.cdt.internal.core.dom.parser.c.CASTFunctionCallExpression.accept",
          "source": "CASTFunctionCallExpression.java:66"
        },
        {
          "method": "org.eclipse.cdt.internal.core.dom.parser.c.CASTExpressionStatement.accept",
          "source": "CASTExpressionStatement.java:57"
        },
        {
          "method": "org.eclipse.cdt.internal.core.dom.parser.c.CASTCompoundStatement.accept",
          "source": "CASTCompoundStatement.java:67"
        },
        {
          "method": "org.eclipse.cdt.internal.core.dom.parser.c.CASTFunctionDefinition.accept",
          "source": "CASTFunctionDefinition.java:96"
        },
        {
          "method": "org.eclipse.cdt.internal.core.dom.parser.c.CASTTranslationUnit.accept",
          "source": "CASTTranslationUnit.java:481"
        },
        {
          "method": "org.eclipse.cdt.internal.core.index.domsourceindexer.DOMSourceIndexerRunner.indexFile",
          "source": "DOMSourceIndexerRunner.java:133"
        },
        {
          "method": "org.eclipse.cdt.internal.core.index.domsourceindexer.AbstractIndexerRunner.index",
          "source": "AbstractIndexerRunner.java:76"
        },
        {
          "method": "org.eclipse.cdt.internal.core.index.cindexstorage.Index.add",
          "source": "Index.java:110"
        },
        {
          "method": "org.eclipse.cdt.internal.core.index.domsourceindexer.DOMAddCompilationUnitToIndex.indexDocument",
          "source": "DOMAddCompilationUnitToIndex.java:29"
        },
        {
          "method": "org.eclipse.cdt.internal.core.index.domsourceindexer.DOMAddFileToIndex.execute",
          "source": "DOMAddFileToIndex.java:60"
        },
        {
          "method": "org.eclipse.cdt.internal.core.search.processing.JobManager.run",
          "source": "JobManager.java:466"
        },
        {
          "method": "java.lang.Thread.run",
          "source": "Unknown Source"
        }
      ],
      "number": 2,
      "commentIndex": 0,
      "bugId": "127969",
      "date": "2006-02-15T05:57:05+01:00",
      "product": "CDT",
      "component": "CDT-parser",
      "severity": "major"
    }
  ],
  "groupId": "127969",
  "bugId": "127969",
  "date": "2006-02-15T05:57:05+01:00",
  "product": "CDT",
  "component": "CDT-parser",
  "severity": "major"
}