{
  "comments": [
    "Build 3.2m5, multiple windows, using categorization in problem view.\n\nOccasionally when incrementally building, I am seeing a dialog popup and telling about an error while queuing viewer updates, with following entry in the .log.\n\n!ENTRY org.eclipse.ui 4 4 2006-02-20 15:22:18.027\n!MESSAGE Unhandled event loop exception\n\n!ENTRY org.eclipse.ui 4 0 2006-02-20 15:22:18.027\n!MESSAGE Failed to execute runnable (java.lang.ArrayIndexOutOfBoundsException)\n!STACK 0\norg.eclipse.swt.SWTException: Failed to execute runnable (java.lang.ArrayIndexOutOfBoundsException)\n        at org.eclipse.swt.SWT.error(SWT.java:3349)\n        at org.eclipse.swt.SWT.error(SWT.java:3272)\n        at org.eclipse.swt.widgets.Synchronizer.runAsyncMessages(Synchronizer.java:126)\n        at org.eclipse.swt.widgets.Display.runAsyncMessages(Display.java:3264)\n        at org.eclipse.swt.widgets.Display.readAndDispatch(Display.java:2910)\n        at org.eclipse.ui.internal.Workbench.runEventLoop(Workbench.java:1899)\n        at org.eclipse.ui.internal.Workbench.runUI(Workbench.java:1863)\n        at org.eclipse.ui.internal.Workbench.createAndRunWorkbench(Workbench.java:417)\n        at org.eclipse.ui.PlatformUI.createAndRunWorkbench(PlatformUI.java:143)\n        at org.eclipse.ui.internal.ide.IDEApplication.run(IDEApplication.java:106)\n        at org.eclipse.core.internal.runtime.PlatformActivator$1.run(PlatformActivator.java:99)\n        at org.eclipse.core.runtime.internal.adaptor.EclipseAppLauncher.runApplication(EclipseAppLauncher.java:92)\n        at org.eclipse.core.runtime.internal.adaptor.EclipseAppLauncher.start(EclipseAppLauncher.java:68)\n        at org.eclipse.core.runtime.adaptor.EclipseStarter.run(EclipseStarter.java:374)\n        at org.eclipse.core.runtime.adaptor.EclipseStarter.run(EclipseStarter.java:169)\n        at sun.reflect.NativeMethodAccessorImpl.invoke0(Native Method)\n        at sun.reflect.NativeMethodAccessorImpl.invoke(NativeMethodAccessorImpl.java:39)\n        at sun.reflect.DelegatingMethodAccessorImpl.invoke(DelegatingMethodAccessorImpl.java:25)\n        at java.lang.reflect.Method.invoke(Method.java:324)\n        at org.eclipse.core.launcher.Main.invokeFramework(Main.java:338)\n        at org.eclipse.core.launcher.Main.basicRun(Main.java:282)\n        at org.eclipse.core.launcher.Main.run(Main.java:977)\n        at org.eclipse.core.launcher.Main.main(Main.java:952)\nCaused by: java.lang.ArrayIndexOutOfBoundsException\n        at java.lang.System.arraycopy(Native Method)\n        at org.eclipse.ui.views.markers.internal.MarkerAdapter$MarkerCategory.getChildren(MarkerAdapter.java:76)\n        at org.eclipse.ui.views.markers.internal.MarkerTreeContentProvider.hasChildren(MarkerTreeContentProvider.java:67)\n        at org.eclipse.jface.viewers.AbstractTreeViewer.isExpandable(AbstractTreeViewer.java:1787)\n        at org.eclipse.jface.viewers.TreeViewer.isExpandable(TreeViewer.java:807)\n        at org.eclipse.jface.viewers.AbstractTreeViewer.isExpandable(AbstractTreeViewer.java:1810)\n        at org.eclipse.jface.viewers.AbstractTreeViewer.updatePlus(AbstractTreeViewer.java:2379)\n        at org.eclipse.jface.viewers.AbstractTreeViewer.updateChildren(AbstractTreeViewer.java:2315)\n        at org.eclipse.jface.viewers.AbstractTreeViewer.internalRefreshStruct(AbstractTreeViewer.java:1563)\n        at org.eclipse.jface.viewers.TreeViewer.internalRefreshStruct(TreeViewer.java:912)\n        at org.eclipse.jface.viewers.AbstractTreeViewer.internalRefresh(AbstractTreeViewer.java:1540)\n        at org.eclipse.jface.viewers.AbstractTreeViewer.internalRefresh(AbstractTreeViewer.java:1495)\n        at org.eclipse.jface.viewers.StructuredViewer$8.run(StructuredViewer.java:1351)\n        at org.eclipse.jface.viewers.StructuredViewer.preservingSelection(StructuredViewer.java:1261)\n        at org.eclipse.jface.viewers.StructuredViewer.refresh(StructuredViewer.java:1349)\n        at org.eclipse.jface.viewers.StructuredViewer.refresh(StructuredViewer.java:1306)\n        at org.eclipse.ui.views.markers.internal.MarkerView$UpdateJob.runInUIThread(MarkerView.java:264)\n        at org.eclipse.ui.progress.UIJob$1.run(UIJob.java:93)\n        at org.eclipse.swt.widgets.RunnableLock.run(RunnableLock.java:35)\n        at org.eclipse.swt.widgets.Synchronizer.runAsyncMessages(Synchronizer.java:123)\n        ... 20 more\nMon Feb 20 15:22:18 CET 2006 - [Worker-28] Build requested, needsBuild: false state: 4 delay: 100",
    "Created an attachment (id\u003d35005)\nError dialog with detailed error description \u003cg\u003e\n\n",
    "The code for handling the indeterminate build state for the markers needed to be extended to the categories.\n\nFixed in build \u003e20060223",
    "Verified in 20060328-0100"
  ],
  "commentCreationDates": [
    "2006-02-20T14:23:57+01:00",
    "2006-02-20T14:24:36+01:00",
    "2006-02-24T15:02:55+01:00",
    "2006-03-28T16:52:30+02:00"
  ],
  "traces": [
    {
      "exceptionType": "org.eclipse.swt.SWTException",
      "message": "Failed to execute runnable (java.lang.ArrayIndexOutOfBoundsException)",
      "elements": [
        {
          "method": "org.eclipse.swt.SWT.error",
          "source": "SWT.java:3349"
        },
        {
          "method": "org.eclipse.swt.SWT.error",
          "source": "SWT.java:3272"
        },
        {
          "method": "org.eclipse.swt.widgets.Synchronizer.runAsyncMessages",
          "source": "Synchronizer.java:126"
        },
        {
          "method": "org.eclipse.swt.widgets.Display.runAsyncMessages",
          "source": "Display.java:3264"
        },
        {
          "method": "org.eclipse.swt.widgets.Display.readAndDispatch",
          "source": "Display.java:2910"
        },
        {
          "method": "org.eclipse.ui.internal.Workbench.runEventLoop",
          "source": "Workbench.java:1899"
        },
        {
          "method": "org.eclipse.ui.internal.Workbench.runUI",
          "source": "Workbench.java:1863"
        },
        {
          "method": "org.eclipse.ui.internal.Workbench.createAndRunWorkbench",
          "source": "Workbench.java:417"
        },
        {
          "method": "org.eclipse.ui.PlatformUI.createAndRunWorkbench",
          "source": "PlatformUI.java:143"
        },
        {
          "method": "org.eclipse.ui.internal.ide.IDEApplication.run",
          "source": "IDEApplication.java:106"
        },
        {
          "method": "org.eclipse.core.internal.runtime.PlatformActivator$1.run",
          "source": "PlatformActivator.java:99"
        },
        {
          "method": "org.eclipse.core.runtime.internal.adaptor.EclipseAppLauncher.runApplication",
          "source": "EclipseAppLauncher.java:92"
        },
        {
          "method": "org.eclipse.core.runtime.internal.adaptor.EclipseAppLauncher.start",
          "source": "EclipseAppLauncher.java:68"
        },
        {
          "method": "org.eclipse.core.runtime.adaptor.EclipseStarter.run",
          "source": "EclipseStarter.java:374"
        },
        {
          "method": "org.eclipse.core.runtime.adaptor.EclipseStarter.run",
          "source": "EclipseStarter.java:169"
        },
        {
          "method": "sun.reflect.NativeMethodAccessorImpl.invoke0",
          "source": "Native Method"
        },
        {
          "method": "sun.reflect.NativeMethodAccessorImpl.invoke",
          "source": "NativeMethodAccessorImpl.java:39"
        },
        {
          "method": "sun.reflect.DelegatingMethodAccessorImpl.invoke",
          "source": "DelegatingMethodAccessorImpl.java:25"
        },
        {
          "method": "java.lang.reflect.Method.invoke",
          "source": "Method.java:324"
        },
        {
          "method": "org.eclipse.core.launcher.Main.invokeFramework",
          "source": "Main.java:338"
        },
        {
          "method": "org.eclipse.core.launcher.Main.basicRun",
          "source": "Main.java:282"
        },
        {
          "method": "org.eclipse.core.launcher.Main.run",
          "source": "Main.java:977"
        },
        {
          "method": "org.eclipse.core.launcher.Main.main",
          "source": "Main.java:952"
        }
      ],
      "causedBy": {
        "exceptionType": "java.lang.ArrayIndexOutOfBoundsException",
        "elements": [
          {
            "method": "java.lang.System.arraycopy",
            "source": "Native Method"
          },
          {
            "method": "org.eclipse.ui.views.markers.internal.MarkerAdapter$MarkerCategory.getChildren",
            "source": "MarkerAdapter.java:76"
          },
          {
            "method": "org.eclipse.ui.views.markers.internal.MarkerTreeContentProvider.hasChildren",
            "source": "MarkerTreeContentProvider.java:67"
          },
          {
            "method": "org.eclipse.jface.viewers.AbstractTreeViewer.isExpandable",
            "source": "AbstractTreeViewer.java:1787"
          },
          {
            "method": "org.eclipse.jface.viewers.TreeViewer.isExpandable",
            "source": "TreeViewer.java:807"
          },
          {
            "method": "org.eclipse.jface.viewers.AbstractTreeViewer.isExpandable",
            "source": "AbstractTreeViewer.java:1810"
          },
          {
            "method": "org.eclipse.jface.viewers.AbstractTreeViewer.updatePlus",
            "source": "AbstractTreeViewer.java:2379"
          },
          {
            "method": "org.eclipse.jface.viewers.AbstractTreeViewer.updateChildren",
            "source": "AbstractTreeViewer.java:2315"
          },
          {
            "method": "org.eclipse.jface.viewers.AbstractTreeViewer.internalRefreshStruct",
            "source": "AbstractTreeViewer.java:1563"
          },
          {
            "method": "org.eclipse.jface.viewers.TreeViewer.internalRefreshStruct",
            "source": "TreeViewer.java:912"
          },
          {
            "method": "org.eclipse.jface.viewers.AbstractTreeViewer.internalRefresh",
            "source": "AbstractTreeViewer.java:1540"
          },
          {
            "method": "org.eclipse.jface.viewers.AbstractTreeViewer.internalRefresh",
            "source": "AbstractTreeViewer.java:1495"
          },
          {
            "method": "org.eclipse.jface.viewers.StructuredViewer$8.run",
            "source": "StructuredViewer.java:1351"
          },
          {
            "method": "org.eclipse.jface.viewers.StructuredViewer.preservingSelection",
            "source": "StructuredViewer.java:1261"
          },
          {
            "method": "org.eclipse.jface.viewers.StructuredViewer.refresh",
            "source": "StructuredViewer.java:1349"
          },
          {
            "method": "org.eclipse.jface.viewers.StructuredViewer.refresh",
            "source": "StructuredViewer.java:1306"
          },
          {
            "method": "org.eclipse.ui.views.markers.internal.MarkerView$UpdateJob.runInUIThread",
            "source": "MarkerView.java:264"
          },
          {
            "method": "org.eclipse.ui.progress.UIJob$1.run",
            "source": "UIJob.java:93"
          },
          {
            "method": "org.eclipse.swt.widgets.RunnableLock.run",
            "source": "RunnableLock.java:35"
          },
          {
            "method": "org.eclipse.swt.widgets.Synchronizer.runAsyncMessages",
            "source": "Synchronizer.java:123"
          }
        ],
        "number": 0,
        "commentIndex": 0
      },
      "number": 0,
      "commentIndex": 0,
      "bugId": "128644",
      "date": "2006-02-20T14:23:57+01:00",
      "product": "Platform",
      "component": "UI",
      "severity": "major"
    }
  ],
  "groupId": "128644",
  "bugId": "128644",
  "date": "2006-02-20T14:23:57+01:00",
  "product": "Platform",
  "component": "UI",
  "severity": "major"
}