{
  "comments": [
    "I20060217-1115 + ZRH-plugins from HEAD\n\nOpen Search view and choose \"Empty Text Search\" from history dropdown. Then right-click in the (empty) results pane or press Shift+F10 to open the context menu.\n\njava.lang.NullPointerException\n        at org.eclipse.search2.internal.ui.text2.ReplaceAction.setupReplaceAll(ReplaceAction.java:122)\n        at org.eclipse.search2.internal.ui.text2.ReplaceAction.\u003cinit\u003e(ReplaceAction.java:91)\n        at org.eclipse.search2.internal.ui.text2.RetrieverReplaceTab.fillContextMenu(RetrieverReplaceTab.java:460)\n        at org.eclipse.search2.internal.ui.text2.RetrieverPage.fillContextMenu(RetrieverPage.java:266)\n        at org.eclipse.search.ui.text.AbstractTextSearchViewPage$2.menuAboutToShow(AbstractTextSearchViewPage.java:467)\n        at org.eclipse.jface.action.MenuManager.fireAboutToShow(MenuManager.java:285)\n        at org.eclipse.jface.action.MenuManager.handleAboutToShow(MenuManager.java:390)\n        at org.eclipse.jface.action.MenuManager.access$1(MenuManager.java:387)\n        at org.eclipse.jface.action.MenuManager$2.menuShown(MenuManager.java:412)\n        at org.eclipse.swt.widgets.TypedListener.handleEvent(TypedListener.java:117)\n        at org.eclipse.swt.widgets.EventTable.sendEvent(EventTable.java:66)\n        at org.eclipse.swt.widgets.Widget.sendEvent(Widget.java:925)\n        at org.eclipse.swt.widgets.Widget.sendEvent(Widget.java:949)\n        at org.eclipse.swt.widgets.Widget.sendEvent(Widget.java:930)\n        at org.eclipse.swt.widgets.Control.WM_INITMENUPOPUP(Control.java:3546)\n        at org.eclipse.swt.widgets.Control.windowProc(Control.java:3262)\n        at org.eclipse.swt.widgets.Decorations.windowProc(Decorations.java:1538)\n        at org.eclipse.swt.widgets.Display.windowProc(Display.java:3965)\n        at org.eclipse.swt.internal.win32.OS.TrackPopupMenu(Native Method)\n        at org.eclipse.swt.widgets.Menu._setVisible(Menu.java:225)\n        at org.eclipse.swt.widgets.Display.runPopups(Display.java:3313)\n        at org.eclipse.swt.widgets.Display.readAndDispatch(Display.java:2901)\n        at org.eclipse.ui.internal.Workbench.runEventLoop(Workbench.java:1899)\n        at org.eclipse.ui.internal.Workbench.runUI(Workbench.java:1863)\n        at org.eclipse.ui.internal.Workbench.createAndRunWorkbench(Workbench.java:417)\n        at org.eclipse.ui.PlatformUI.createAndRunWorkbench(PlatformUI.java:143)\n        at org.eclipse.ui.internal.ide.IDEApplication.run(IDEApplication.java:106)\n        at org.eclipse.core.internal.runtime.PlatformActivator$1.run(PlatformActivator.java:99)\n        at org.eclipse.core.runtime.internal.adaptor.EclipseAppLauncher.runApplication(EclipseAppLauncher.java:92)\n        at org.eclipse.core.runtime.internal.adaptor.EclipseAppLauncher.start(EclipseAppLauncher.java:68)\n        at org.eclipse.core.runtime.adaptor.EclipseStarter.run(EclipseStarter.java:374)\n        at org.eclipse.core.runtime.adaptor.EclipseStarter.run(EclipseStarter.java:169)\n        at sun.reflect.NativeMethodAccessorImpl.invoke0(Native Method)\n        at sun.reflect.NativeMethodAccessorImpl.invoke(NativeMethodAccessorImpl.java:39)\n        at sun.reflect.DelegatingMethodAccessorImpl.invoke(DelegatingMethodAccessorImpl.java:25)\n        at java.lang.reflect.Method.invoke(Method.java:585)\n        at org.eclipse.core.launcher.Main.invokeFramework(Main.java:338)\n        at org.eclipse.core.launcher.Main.basicRun(Main.java:282)\n        at org.eclipse.core.launcher.Main.run(Main.java:977)\n        at org.eclipse.core.launcher.Main.main(Main.java:952)",
    "There are is no empty search-view no more.",
    "reopen",
    "New text search UI has been removed again from 3.2."
  ],
  "commentCreationDates": [
    "2006-02-21T10:58:48+01:00",
    "2006-03-15T10:17:01+01:00",
    "2006-04-11T16:21:13+02:00",
    "2006-04-11T16:21:26+02:00"
  ],
  "traces": [
    {
      "exceptionType": "java.lang.NullPointerException",
      "elements": [
        {
          "method": "org.eclipse.search2.internal.ui.text2.ReplaceAction.setupReplaceAll",
          "source": "ReplaceAction.java:122"
        },
        {
          "method": "org.eclipse.search2.internal.ui.text2.ReplaceAction.\u003cinit\u003e",
          "source": "ReplaceAction.java:91"
        },
        {
          "method": "org.eclipse.search2.internal.ui.text2.RetrieverReplaceTab.fillContextMenu",
          "source": "RetrieverReplaceTab.java:460"
        },
        {
          "method": "org.eclipse.search2.internal.ui.text2.RetrieverPage.fillContextMenu",
          "source": "RetrieverPage.java:266"
        },
        {
          "method": "org.eclipse.search.ui.text.AbstractTextSearchViewPage$2.menuAboutToShow",
          "source": "AbstractTextSearchViewPage.java:467"
        },
        {
          "method": "org.eclipse.jface.action.MenuManager.fireAboutToShow",
          "source": "MenuManager.java:285"
        },
        {
          "method": "org.eclipse.jface.action.MenuManager.handleAboutToShow",
          "source": "MenuManager.java:390"
        },
        {
          "method": "org.eclipse.jface.action.MenuManager.access$1",
          "source": "MenuManager.java:387"
        },
        {
          "method": "org.eclipse.jface.action.MenuManager$2.menuShown",
          "source": "MenuManager.java:412"
        },
        {
          "method": "org.eclipse.swt.widgets.TypedListener.handleEvent",
          "source": "TypedListener.java:117"
        },
        {
          "method": "org.eclipse.swt.widgets.EventTable.sendEvent",
          "source": "EventTable.java:66"
        },
        {
          "method": "org.eclipse.swt.widgets.Widget.sendEvent",
          "source": "Widget.java:925"
        },
        {
          "method": "org.eclipse.swt.widgets.Widget.sendEvent",
          "source": "Widget.java:949"
        },
        {
          "method": "org.eclipse.swt.widgets.Widget.sendEvent",
          "source": "Widget.java:930"
        },
        {
          "method": "org.eclipse.swt.widgets.Control.WM_INITMENUPOPUP",
          "source": "Control.java:3546"
        },
        {
          "method": "org.eclipse.swt.widgets.Control.windowProc",
          "source": "Control.java:3262"
        },
        {
          "method": "org.eclipse.swt.widgets.Decorations.windowProc",
          "source": "Decorations.java:1538"
        },
        {
          "method": "org.eclipse.swt.widgets.Display.windowProc",
          "source": "Display.java:3965"
        },
        {
          "method": "org.eclipse.swt.internal.win32.OS.TrackPopupMenu",
          "source": "Native Method"
        },
        {
          "method": "org.eclipse.swt.widgets.Menu._setVisible",
          "source": "Menu.java:225"
        },
        {
          "method": "org.eclipse.swt.widgets.Display.runPopups",
          "source": "Display.java:3313"
        },
        {
          "method": "org.eclipse.swt.widgets.Display.readAndDispatch",
          "source": "Display.java:2901"
        },
        {
          "method": "org.eclipse.ui.internal.Workbench.runEventLoop",
          "source": "Workbench.java:1899"
        },
        {
          "method": "org.eclipse.ui.internal.Workbench.runUI",
          "source": "Workbench.java:1863"
        },
        {
          "method": "org.eclipse.ui.internal.Workbench.createAndRunWorkbench",
          "source": "Workbench.java:417"
        },
        {
          "method": "org.eclipse.ui.PlatformUI.createAndRunWorkbench",
          "source": "PlatformUI.java:143"
        },
        {
          "method": "org.eclipse.ui.internal.ide.IDEApplication.run",
          "source": "IDEApplication.java:106"
        },
        {
          "method": "org.eclipse.core.internal.runtime.PlatformActivator$1.run",
          "source": "PlatformActivator.java:99"
        },
        {
          "method": "org.eclipse.core.runtime.internal.adaptor.EclipseAppLauncher.runApplication",
          "source": "EclipseAppLauncher.java:92"
        },
        {
          "method": "org.eclipse.core.runtime.internal.adaptor.EclipseAppLauncher.start",
          "source": "EclipseAppLauncher.java:68"
        },
        {
          "method": "org.eclipse.core.runtime.adaptor.EclipseStarter.run",
          "source": "EclipseStarter.java:374"
        },
        {
          "method": "org.eclipse.core.runtime.adaptor.EclipseStarter.run",
          "source": "EclipseStarter.java:169"
        },
        {
          "method": "sun.reflect.NativeMethodAccessorImpl.invoke0",
          "source": "Native Method"
        },
        {
          "method": "sun.reflect.NativeMethodAccessorImpl.invoke",
          "source": "NativeMethodAccessorImpl.java:39"
        },
        {
          "method": "sun.reflect.DelegatingMethodAccessorImpl.invoke",
          "source": "DelegatingMethodAccessorImpl.java:25"
        },
        {
          "method": "java.lang.reflect.Method.invoke",
          "source": "Method.java:585"
        },
        {
          "method": "org.eclipse.core.launcher.Main.invokeFramework",
          "source": "Main.java:338"
        },
        {
          "method": "org.eclipse.core.launcher.Main.basicRun",
          "source": "Main.java:282"
        },
        {
          "method": "org.eclipse.core.launcher.Main.run",
          "source": "Main.java:977"
        },
        {
          "method": "org.eclipse.core.launcher.Main.main",
          "source": "Main.java:952"
        }
      ],
      "number": 0,
      "commentIndex": 0,
      "bugId": "128777",
      "date": "2006-02-21T10:58:48+01:00",
      "product": "Platform",
      "component": "Search",
      "severity": "normal"
    }
  ],
  "groupId": "128777",
  "bugId": "128777",
  "date": "2006-02-21T10:58:48+01:00",
  "product": "Platform",
  "component": "Search",
  "severity": "normal"
}