{
  "comments": [
    "Hi,\n\nAlthought this is not common scenario I marked this defect as Major because it \nends up crashing the Eclipse.\n\nIt is really easy to reproduce it.  In any constructor with at least one \nargument, add the word \"private\" before the first argument declaration.  \nSomething similar to...\n\npublic class MyClass\n{\n     public MyClass(private int i){}\n}\n\nBtw, I tested this with the 020321 and 020402 drivers.",
    "Reproduced. When saving such code in editor, we get the following stack trace:\n\n2 org.eclipse.ui 0 Save Failed\njava.lang.NullPointerException\n        at \norg.eclipse.jdt.internal.compiler.problem.ProblemReporter.illegalModifierForVari\nable(ProblemReporter.java:967)\n        at \norg.eclipse.jdt.internal.compiler.lookup.BlockScope.checkAndSetModifiersForVaria\nble(BlockScope.java:165)\n        at org.eclipse.jdt.internal.compiler.lookup.BlockScope.addLocalVariable\n(BlockScope.java:96)\n        at org.eclipse.jdt.internal.compiler.ast.Argument.bind(Argument.java:31)\n        at \norg.eclipse.jdt.internal.compiler.ast.AbstractMethodDeclaration.bindArguments\n(AbstractMethodDeclaration.java:134)\n        at \norg.eclipse.jdt.internal.compiler.ast.AbstractMethodDeclaration.resolve\n(AbstractMethodDeclaration.java:313)\n        at org.eclipse.jdt.internal.compiler.ast.ConstructorDeclaration.resolve\n(ConstructorDeclaration.java:339)\n        at org.eclipse.jdt.internal.compiler.ast.TypeDeclaration.resolve\n(TypeDeclaration.java:898)\n        at org.eclipse.jdt.internal.compiler.ast.TypeDeclaration.resolve\n(TypeDeclaration.java:930)\n        at \norg.eclipse.jdt.internal.compiler.ast.CompilationUnitDeclaration.resolve\n(CompilationUnitDeclaration.java:213)\n        at org.eclipse.jdt.internal.compiler.Compiler.resolve(Compiler.java:561)\n        at org.eclipse.jdt.internal.core.CompilationUnitProblemFinder.resolve\n(CompilationUnitProblemFinder.java:149)\n        at org.eclipse.jdt.internal.core.CompilationUnit.buildStructure\n(CompilationUnit.java:79)\n        at org.eclipse.jdt.internal.core.CompilationUnit.makeConsistent\n(CompilationUnit.java:552)\n        at org.eclipse.jdt.internal.core.WorkingCopy.reconcile\n(WorkingCopy.java:333)\n        at \norg.eclipse.jdt.internal.ui.javaeditor.CompilationUnitDocumentProvider.doSaveDoc\nument(CompilationUnitDocumentProvider.java:384)\n        at org.eclipse.ui.texteditor.AbstractDocumentProvider.saveDocument\n(AbstractDocumentProvider.java:361)\n        at org.eclipse.ui.texteditor.AbstractTextEditor$9.execute\n(AbstractTextEditor.java:1685)\n        at org.eclipse.ui.actions.WorkspaceModifyOperation$1.run\n(WorkspaceModifyOperation.java:64)\n        at org.eclipse.core.internal.resources.Workspace.run\n(Workspace.java:1343)\n        at org.eclipse.ui.actions.WorkspaceModifyOperation.run\n(WorkspaceModifyOperation.java:78)\n        at org.eclipse.ui.texteditor.AbstractTextEditor.performSaveOperation\n(AbstractTextEditor.java:1703)\n        at \norg.eclipse.jdt.internal.ui.javaeditor.CompilationUnitEditor.performSaveOperatio\nn(CompilationUnitEditor.java:569)\n        at org.eclipse.jdt.internal.ui.javaeditor.CompilationUnitEditor.doSave\n(CompilationUnitEditor.java:617)\n        at org.eclipse.ui.internal.EditorManager$9.run(EditorManager.java:811)\n        at org.eclipse.jface.operation.ModalContext.runInCurrentThread\n(ModalContext.java:296)\n        at org.eclipse.jface.operation.ModalContext.run(ModalContext.java:249)\n        at org.eclipse.jface.dialogs.ProgressMonitorDialog.run\n(ProgressMonitorDialog.java:335)\n        at org.eclipse.ui.internal.EditorManager.runProgressMonitorOperation\n(EditorManager.java:689)\n        at org.eclipse.ui.internal.EditorManager.saveEditor\n(EditorManager.java:816)\n        at org.eclipse.ui.internal.WorkbenchPage.saveEditor\n(WorkbenchPage.java:1481)\n        at org.eclipse.ui.internal.SaveAction.run(SaveAction.java:32)\n        at org.eclipse.jface.action.Action.runWithEvent(Action.java:590)\n        at org.eclipse.jface.action.ActionContributionItem.handleWidgetSelection\n(ActionContributionItem.java:407)\n        at org.eclipse.jface.action.ActionContributionItem.handleWidgetEvent\n(ActionContributionItem.java:361)\n        at org.eclipse.jface.action.ActionContributionItem.access$0\n(ActionContributionItem.java:352)\n        at \norg.eclipse.jface.action.ActionContributionItem$ActionListener.handleEvent\n(ActionContributionItem.java:47)\n        at org.eclipse.swt.widgets.EventTable.sendEvent(EventTable.java:75)\n        at org.eclipse.swt.widgets.Widget.notifyListeners(Widget.java:637)\n        at org.eclipse.swt.widgets.Display.runDeferredEvents(Display.java:1420)\n        at org.eclipse.swt.widgets.Display.readAndDispatch(Display.java:1208)\n        at org.eclipse.ui.internal.Workbench.runEventLoop(Workbench.java:755)\n        at org.eclipse.ui.internal.Workbench.run(Workbench.java:738)\n        at org.eclipse.core.internal.boot.InternalBootLoader.run\n(InternalBootLoader.java:777)\n        at org.eclipse.core.boot.BootLoader.run(BootLoader.java:319)\n        at java.lang.reflect.Method.invoke(Native Method)\n        at org.eclipse.core.launcher.Main.basicRun(Main.java:190)\n        at org.eclipse.core.launcher.Main.run(Main.java:549)\n        at org.eclipse.core.launcher.UIMain.main(UIMain.java:52)\nSave Failed",
    "Error reporting did cause NPE. Fixed the bug, and also tuned the error messages \n(in particular added one for duplicate modifiers on arguments).\n\nFixed, regression test added (NegativeTest#test262 + test263)."
  ],
  "commentCreationDates": [
    "2002-04-05T23:06:36+02:00",
    "2002-04-08T13:06:35+02:00",
    "2002-04-08T16:22:32+02:00"
  ],
  "traces": [
    {
      "exceptionType": "java.lang.NullPointerException",
      "elements": [
        {
          "method": "org.eclipse.jdt.internal.compiler.problem.ProblemReporter.illegalModifierForVariable",
          "source": "ProblemReporter.java:967"
        },
        {
          "method": "org.eclipse.jdt.internal.compiler.lookup.BlockScope.checkAndSetModifiersForVariable",
          "source": "BlockScope.java:165"
        },
        {
          "method": "org.eclipse.jdt.internal.compiler.lookup.BlockScope.addLocalVariable",
          "source": "BlockScope.java:96"
        },
        {
          "method": "org.eclipse.jdt.internal.compiler.ast.Argument.bind",
          "source": "Argument.java:31"
        },
        {
          "method": "org.eclipse.jdt.internal.compiler.ast.AbstractMethodDeclaration.bindArguments",
          "source": "AbstractMethodDeclaration.java:134"
        },
        {
          "method": "org.eclipse.jdt.internal.compiler.ast.AbstractMethodDeclaration.resolve",
          "source": "AbstractMethodDeclaration.java:313"
        },
        {
          "method": "org.eclipse.jdt.internal.compiler.ast.ConstructorDeclaration.resolve",
          "source": "ConstructorDeclaration.java:339"
        },
        {
          "method": "org.eclipse.jdt.internal.compiler.ast.TypeDeclaration.resolve",
          "source": "TypeDeclaration.java:898"
        },
        {
          "method": "org.eclipse.jdt.internal.compiler.ast.TypeDeclaration.resolve",
          "source": "TypeDeclaration.java:930"
        },
        {
          "method": "org.eclipse.jdt.internal.compiler.ast.CompilationUnitDeclaration.resolve",
          "source": "CompilationUnitDeclaration.java:213"
        },
        {
          "method": "org.eclipse.jdt.internal.compiler.Compiler.resolve",
          "source": "Compiler.java:561"
        },
        {
          "method": "org.eclipse.jdt.internal.core.CompilationUnitProblemFinder.resolve",
          "source": "CompilationUnitProblemFinder.java:149"
        },
        {
          "method": "org.eclipse.jdt.internal.core.CompilationUnit.buildStructure",
          "source": "CompilationUnit.java:79"
        },
        {
          "method": "org.eclipse.jdt.internal.core.CompilationUnit.makeConsistent",
          "source": "CompilationUnit.java:552"
        },
        {
          "method": "org.eclipse.jdt.internal.core.WorkingCopy.reconcile",
          "source": "WorkingCopy.java:333"
        },
        {
          "method": "org.eclipse.jdt.internal.ui.javaeditor.CompilationUnitDocumentProvider.doSaveDocument",
          "source": "CompilationUnitDocumentProvider.java:384"
        },
        {
          "method": "org.eclipse.ui.texteditor.AbstractDocumentProvider.saveDocument",
          "source": "AbstractDocumentProvider.java:361"
        },
        {
          "method": "org.eclipse.ui.texteditor.AbstractTextEditor$9.execute",
          "source": "AbstractTextEditor.java:1685"
        },
        {
          "method": "org.eclipse.ui.actions.WorkspaceModifyOperation$1.run",
          "source": "WorkspaceModifyOperation.java:64"
        },
        {
          "method": "org.eclipse.core.internal.resources.Workspace.run",
          "source": "Workspace.java:1343"
        },
        {
          "method": "org.eclipse.ui.actions.WorkspaceModifyOperation.run",
          "source": "WorkspaceModifyOperation.java:78"
        },
        {
          "method": "org.eclipse.ui.texteditor.AbstractTextEditor.performSaveOperation",
          "source": "AbstractTextEditor.java:1703"
        },
        {
          "method": "org.eclipse.jdt.internal.ui.javaeditor.CompilationUnitEditor.performSaveOperation",
          "source": "CompilationUnitEditor.java:569"
        },
        {
          "method": "org.eclipse.jdt.internal.ui.javaeditor.CompilationUnitEditor.doSave",
          "source": "CompilationUnitEditor.java:617"
        },
        {
          "method": "org.eclipse.ui.internal.EditorManager$9.run",
          "source": "EditorManager.java:811"
        },
        {
          "method": "org.eclipse.jface.operation.ModalContext.runInCurrentThread",
          "source": "ModalContext.java:296"
        },
        {
          "method": "org.eclipse.jface.operation.ModalContext.run",
          "source": "ModalContext.java:249"
        },
        {
          "method": "org.eclipse.jface.dialogs.ProgressMonitorDialog.run",
          "source": "ProgressMonitorDialog.java:335"
        },
        {
          "method": "org.eclipse.ui.internal.EditorManager.runProgressMonitorOperation",
          "source": "EditorManager.java:689"
        },
        {
          "method": "org.eclipse.ui.internal.EditorManager.saveEditor",
          "source": "EditorManager.java:816"
        },
        {
          "method": "org.eclipse.ui.internal.WorkbenchPage.saveEditor",
          "source": "WorkbenchPage.java:1481"
        },
        {
          "method": "org.eclipse.ui.internal.SaveAction.run",
          "source": "SaveAction.java:32"
        },
        {
          "method": "org.eclipse.jface.action.Action.runWithEvent",
          "source": "Action.java:590"
        },
        {
          "method": "org.eclipse.jface.action.ActionContributionItem.handleWidgetSelection",
          "source": "ActionContributionItem.java:407"
        },
        {
          "method": "org.eclipse.jface.action.ActionContributionItem.handleWidgetEvent",
          "source": "ActionContributionItem.java:361"
        },
        {
          "method": "org.eclipse.jface.action.ActionContributionItem.access$0",
          "source": "ActionContributionItem.java:352"
        },
        {
          "method": "org.eclipse.jface.action.ActionContributionItem$ActionListener.handleEvent",
          "source": "ActionContributionItem.java:47"
        },
        {
          "method": "org.eclipse.swt.widgets.EventTable.sendEvent",
          "source": "EventTable.java:75"
        },
        {
          "method": "org.eclipse.swt.widgets.Widget.notifyListeners",
          "source": "Widget.java:637"
        },
        {
          "method": "org.eclipse.swt.widgets.Display.runDeferredEvents",
          "source": "Display.java:1420"
        },
        {
          "method": "org.eclipse.swt.widgets.Display.readAndDispatch",
          "source": "Display.java:1208"
        },
        {
          "method": "org.eclipse.ui.internal.Workbench.runEventLoop",
          "source": "Workbench.java:755"
        },
        {
          "method": "org.eclipse.ui.internal.Workbench.run",
          "source": "Workbench.java:738"
        },
        {
          "method": "org.eclipse.core.internal.boot.InternalBootLoader.run",
          "source": "InternalBootLoader.java:777"
        },
        {
          "method": "org.eclipse.core.boot.BootLoader.run",
          "source": "BootLoader.java:319"
        },
        {
          "method": "java.lang.reflect.Method.invoke",
          "source": "Native Method"
        },
        {
          "method": "org.eclipse.core.launcher.Main.basicRun",
          "source": "Main.java:190"
        },
        {
          "method": "org.eclipse.core.launcher.Main.run",
          "source": "Main.java:549"
        },
        {
          "method": "org.eclipse.core.launcher.UIMain.main",
          "source": "UIMain.java:52"
        }
      ],
      "number": 0,
      "commentIndex": 1,
      "bugId": "12908",
      "date": "2002-04-08T13:06:35+02:00",
      "product": "JDT",
      "component": "Core",
      "severity": "major"
    }
  ],
  "groupId": "12908",
  "bugId": "12908",
  "date": "2002-04-05T23:06:36+02:00",
  "product": "JDT",
  "component": "Core",
  "severity": "major"
}