{
  "comments": [
    "org.aspectj.weaver.BCException\nat org.aspectj.weaver.bcel.BcelShadow.initializeKindedAnnotationVars(BcelShadow.java:1553)\nat org.aspectj.weaver.bcel.BcelShadow.getKindedAnnotationVar(BcelShadow.java:995)\nat org.aspectj.weaver.patterns.AnnotationPointcut.findResidueInternal(AnnotationPointcut.java:196)\nat org.aspectj.weaver.patterns.Pointcut.findResidue(Pointcut.java:268)\nat org.aspectj.weaver.patterns.AndPointcut.findResidueInternal(AndPointcut.java:97)\nat org.aspectj.weaver.patterns.Pointcut.findResidue(Pointcut.java:268)\nat org.aspectj.weaver.patterns.AndPointcut.findResidueInternal(AndPointcut.java:97)\nat org.aspectj.weaver.patterns.Pointcut.findResidue(Pointcut.java:268)\nat org.aspectj.weaver.patterns.AndPointcut.findResidueInternal(AndPointcut.java:97)\nat org.aspectj.weaver.patterns.Pointcut.findResidue(Pointcut.java:268)\nat org.aspectj.weaver.bcel.BcelAdvice.specializeOn(BcelAdvice.java:132)\nat org.aspectj.weaver.bcel.BcelShadow.prepareForMungers(BcelShadow.java:313)\nat org.aspectj.weaver.Shadow.implement(Shadow.java:404)\nat org.aspectj.weaver.bcel.BcelClassWeaver.implement(BcelClassWeaver.java:2146)\nat org.aspectj.weaver.bcel.BcelClassWeaver.weave(BcelClassWeaver.java:467)\nat org.aspectj.weaver.bcel.BcelClassWeaver.weave(BcelClassWeaver.java:102)\nat org.aspectj.weaver.bcel.BcelWeaver.weave(BcelWeaver.java:1543)\nat org.aspectj.weaver.bcel.BcelWeaver.weaveWithoutDump(BcelWeaver.java:1494)\nat org.aspectj.weaver.bcel.BcelWeaver.weaveAndNotify(BcelWeaver.java:1275)\nat org.aspectj.weaver.bcel.BcelWeaver.weave(BcelWeaver.java:1097)\nat org.aspectj.ajdt.internal.compiler.AjCompilerAdapter.weave(AjCompilerAdapter.java:300)\nat org.aspectj.ajdt.internal.compiler.AjCompilerAdapter.afterCompiling(AjCompilerAdapter.java:178)\nat org.aspectj.ajdt.internal.compiler.CompilerAdapter.ajc$afterReturning$org_aspectj_ajdt_internal_compiler_CompilerAdapter$2$f9cc9ca0(CompilerAdapter.aj:70)\nat org.aspectj.org.eclipse.jdt.internal.compiler.Compiler.compile(Compiler.java:367)\nat org.aspectj.ajdt.internal.core.builder.AjBuildManager.performCompilation(AjBuildManager.java:811)\nat org.aspectj.ajdt.internal.core.builder.AjBuildManager.doBuild(AjBuildManager.java:230)\nat org.aspectj.ajdt.internal.core.builder.AjBuildManager.batchBuild(AjBuildManager.java:156)\nat org.aspectj.ajde.internal.CompilerAdapter.compile(CompilerAdapter.java:122)\nat org.aspectj.ajde.internal.AspectJBuildManager$CompilerThread.run(AspectJBuildManager.java:191)\n\ntrouble in: \npublic class com.ytg.bilette.client.core.providers.DomainContentProvider extends java.lang.Object implements com.ytg.bilette.client.core.providers.IRefreshableStructuredContentProvider:\n  private java.util.HashSet listeners [Signature(Ljava/util/HashSet\u003cLcom/ytg/bilette/client/core/providers/IDomainObjectChangeListener\u003cTT;\u003e;\u003e;)]\n  private com.ytg.bilette.client.core.providers.DomainContentProvider$State state [Signature(Lcom/ytg/bilette/client/core/providers/DomainContentProvider$State;)]\n  private Class clazz [Signature(Ljava/lang/Class\u003c+Lcom/ytg/bilette/model/GenericDomainObject;\u003e;)]\n  private boolean deletable\n  private java.util.List summaries [Signature(Ljava/util/List\u003cTT;\u003e;)]\n  static Class class$0\n  public void \u003cinit\u003e(Class)    org.aspectj.weaver.MethodDeclarationLineNumber: 47:1136\n:\n                    ALOAD_0     // com.ytg.bilette.client.core.providers.DomainContentProvider this   (line 47)\n                    \u0026#304;NVOKESPEC\u0026#304;AL java.lang.Object.\u003cinit\u003e ()V\n    constructor-execution(void com.ytg.bilette.client.core.providers.DomainContentProvider.\u003cinit\u003e(java.lang.Class))\n    |               ALOAD_0     // com.ytg.bilette.client.core.providers.DomainContentProvider this   (line 34)\n    |               NEW java.util.HashSet\n    |               DUP\n    |               \u0026#304;NVOKESPEC\u0026#304;AL java.util.HashSet.\u003cinit\u003e ()V\n    |               PUTF\u0026#304;ELD com.ytg.bilette.client.core.providers.DomainContentProvider.listeners Ljava/util/HashSet;\n    |               ALOAD_0     // com.ytg.bilette.client.core.providers.DomainContentProvider this   (line 36)\n    |               GETSTAT\u0026#304;C com.ytg.bilette.client.core.providers.DomainContentProvider$State.NOT_INITIALIZED Lcom/ytg/bilette/client/core/providers/DomainContentProvider$State;\n    |               PUTF\u0026#304;ELD com.ytg.bilette.client.core.providers.DomainContentProvider.state Lcom/ytg/bilette/client/core/providers/DomainContentProvider$State;\n    |               ALOAD_0     // com.ytg.bilette.client.core.providers.DomainContentProvider this   (line 40)\n    |               \u0026#304;CONST_0\n    |               PUTF\u0026#304;ELD com.ytg.bilette.client.core.providers.DomainContentProvider.deletable Z\n    |               ALOAD_0     // com.ytg.bilette.client.core.providers.DomainContentProvider this   (line 48)\n    |               ALOAD_1     // java.lang.Class clazz\n    |               PUTF\u0026#304;ELD com.ytg.bilette.client.core.providers.DomainContentProvider.clazz Ljava/lang/Class;\n    |               ALOAD_1     // java.lang.Class clazz   (line 50)\n    |               \u0026#304;NVOKEV\u0026#304;RTUAL java.lang.Class.getInterfaces ()[Ljava/lang/Class;\n    |               ASTORE_2\n    |               \u0026#304;CONST_0   (line 51)\n    |               \u0026#304;STORE_3\n    |               GOTO L2\n    |           L0: ALOAD_2     // java.lang.Class[] interfaces   (line 52)\n    |               \u0026#304;LOAD_3     // int i\n    |               AALOAD\n    |               LDC com.ytg.bilette.model.Deletable\n    |               \u0026#304;NVOKEV\u0026#304;RTUAL java.lang.Object.equals (Ljava/lang/Object;)Z\n    |               \u0026#304;FEQ L1\n    |               ALOAD_0     // com.ytg.bilette.client.core.providers.DomainContentProvider this   (line 53)\n    |               \u0026#304;CONST_1\n    |               PUTF\u0026#304;ELD com.ytg.bilette.client.core.providers.DomainContentProvider.deletable Z\n    |               GOTO L3   (line 54)\n    |           L1: \u0026#304;\u0026#304;NC 3 1     // int i   (line 51)\n    |           L2: \u0026#304;LOAD_3     // int i\n    |               ALOAD_2     // java.lang.Class[] interfaces\n    |               ARRAYLENGTH\n    |               \u0026#304;F_\u0026#304;CMPLT L0\n    |           L3: RETURN   (line 57)\n    constructor-execution(void com.ytg.bilette.client.core.providers.DomainContentProvider.\u003cinit\u003e(java.lang.Class))\n  end public void \u003cinit\u003e(Class)\n\n  public Object[] getElements(Object)    org.aspectj.weaver.MethodDeclarationLineNumber: 65:1611\n:\n                    ALOAD_0     // com.ytg.bilette.client.core.providers.DomainContentProvider this   (line 66)\n                    ALOAD_1     // java.lang.Object input\n                    \u0026#304;NVOKESPEC\u0026#304;AL com.ytg.bilette.client.core.providers.DomainContentProvider.checkInput (Ljava/lang/Object;)Z\n                    \u0026#304;STORE_2\n                    ALOAD_0     // com.ytg.bilette.client.core.providers.DomainContentProvider this   (line 68)\n                    \u0026#304;LOAD_2     // boolean includeDeleted\n                    \u0026#304;NVOKEV\u0026#304;RTUAL com.ytg.bilette.client.core.providers.DomainContentProvider.getSummaries (Z)Ljava/util/List;\n                    \u0026#304;NVOKE\u0026#304;NTERFACE java.util.List.toArray ()[Ljava/lang/Object;\n                    ARETURN\n  end public Object[] getElements(Object)\n\n  private void checkInitialized(boolean)    org.aspectj.weaver.MethodDeclarationLineNumber: 71:1759\n:\n                    GETSTAT\u0026#304;C com.ytg.bilette.client.core.providers.DomainContentProvider$State.NOT_INITIALIZED Lcom/ytg/bilette/client/core/providers/DomainContentProvider$State;   (line 72)\n                    ALOAD_0     // com.ytg.bilette.client.core.providers.DomainContentProvider this\n                    GETF\u0026#304;ELD com.ytg.bilette.client.core.providers.DomainContentProvider.state Lcom/ytg/bilette/client/core/providers/DomainContentProvider$State;\n                    \u0026#304;NVOKEV\u0026#304;RTUAL com.ytg.bilette.client.core.providers.DomainContentProvider$State.equals (Ljava/lang/Object;)Z\n                    \u0026#304;FNE L0\n                    GETSTAT\u0026#304;C com.ytg.bilette.client.core.providers.DomainContentProvider$State.LIGHT_INITIALIZED Lcom/ytg/bilette/client/core/providers/DomainContentProvider$State;   (line 73)\n                    ALOAD_0     // com.ytg.bilette.client.core.providers.DomainContentProvider this\n                    GETF\u0026#304;ELD com.ytg.bilette.client.core.providers.DomainContentProvider.state Lcom/ytg/bilette/client/core/providers/DomainContentProvider$State;\n                    \u0026#304;NVOKEV\u0026#304;RTUAL com.ytg.bilette.client.core.providers.DomainContentProvider$State.equals (Ljava/lang/Object;)Z\n                    \u0026#304;FEQ L1\n                    \u0026#304;LOAD_1     // boolean includeDeleted\n                    \u0026#304;FEQ L1\n                L0: ALOAD_0     // com.ytg.bilette.client.core.providers.DomainContentProvider this   (line 74)\n                    ACONST_NULL\n                    ACONST_NULL\n                    \u0026#304;LOAD_1     // boolean includeDeleted\n                    \u0026#304;NVOKESPEC\u0026#304;AL com.ytg.bilette.client.core.providers.DomainContentProvider.getData (Lcom/ytg/bilette/dao/SummaryDAO;Lorg/eclipse/core/runtime/IProgressMonitor;Z)V\n                L1: RETURN   (line 75)\n  end private void checkInitialized(boolean)\n\n  private boolean checkInput(Object)    org.aspectj.weaver.MethodDeclarationLineNumber: 83:2060\n:\n                    ALOAD_1     // java.lang.Object input   (line 84)\n                    \u0026#304;NSTANCEOF java.lang.Boolean\n                    LDC \"Input for generic content provider must be Boolean value\"   (line 85)\n                    \u0026#304;NVOKESTAT\u0026#304;C org.eclipse.jface.util.Assert.isTrue (ZLjava/lang/String;)Z   (line 84)\n                    POP\n                    ALOAD_1     // java.lang.Object input   (line 86)\n                    CHECKCAST java.lang.Boolean\n                    \u0026#304;NVOKEV\u0026#304;RTUAL java.lang.Boolean.booleanValue ()Z\n                    \u0026#304;STORE_2\n                    ALOAD_0     // com.ytg.bilette.client.core.providers.DomainContentProvider this   (line 87)\n                    GETF\u0026#304;ELD com.ytg.bilette.client.core.providers.DomainContentProvider.deletable Z\n                    \u0026#304;FNE L1\n                    ALOAD_0     // com.ytg.bilette.client.core.providers.DomainContentProvider this   (line 88)\n                    GETF\u0026#304;ELD com.ytg.bilette.client.core.providers.DomainContentProvider.deletable Z\n                    \u0026#304;FNE L0\n                    \u0026#304;LOAD_2     // boolean includeDeleted\n                    \u0026#304;FEQ L1\n                L0: \u0026#304;CONST_0\n                    GOTO L2\n                L1: \u0026#304;CONST_1\n                L2: LDC \"Nondeletable object yet deleted flag!\"   (line 89)\n                    \u0026#304;NVOKESTAT\u0026#304;C org.eclipse.jface.util.Assert.isLegal (ZLjava/lang/String;)Z   (line 87)\n                    POP\n                    \u0026#304;LOAD_2     // boolean includeDeleted   (line 91)\n                    \u0026#304;RETURN\n  end private boolean checkInput(Object)\n\n  public void dispose()    org.aspectj.weaver.MethodDeclarationLineNumber: 99:2522\n:\n                    RETURN   (line 101)\n  end public void dispose()\n\n  public void inputChanged(org.eclipse.jface.viewers.Viewer, Object, Object)    org.aspectj.weaver.MethodDeclarationLineNumber: 109:2747\n:\n                    RETURN   (line 111)\n  end public void inputChanged(org.eclipse.jface.viewers.Viewer, Object, Object)\n\n  private void getData(com.ytg.bilette.dao.SummaryDAO, org.eclipse.core.runtime.IProgressMonitor, boolean)    org.aspectj.weaver.MethodDeclarationLineNumber: 115:2954\n:\n                    ALOAD_1\n                    ASTORE 4\n                    ALOAD_2\n                    ASTORE 5\n                    \u0026#304;LOAD_3\n                    \u0026#304;STORE 6\n    method-execution(void com.ytg.bilette.client.core.providers.DomainContentProvider.getData(com.ytg.bilette.dao.SummaryDAO, org.eclipse.core.runtime.IProgressMonitor, boolean))\n    |               ALOAD_0     // com.ytg.bilette.client.core.providers.DomainContentProvider this   (line 117)\n    |               ALOAD_1     // com.ytg.bilette.dao.SummaryDAO dao\n    |               ALOAD_0     // com.ytg.bilette.client.core.providers.DomainContentProvider this\n    |               GETF\u0026#304;ELD com.ytg.bilette.client.core.providers.DomainContentProvider.clazz Ljava/lang/Class;\n    |               \u0026#304;LOAD_3     // boolean includeDeleted\n    |               \u0026#304;NVOKE\u0026#304;NTERFACE com.ytg.bilette.dao.SummaryDAO.getSummaries (Ljava/lang/Class;Z)Ljava/util/List;\n    |               PUTF\u0026#304;ELD com.ytg.bilette.client.core.providers.DomainContentProvider.summaries Ljava/util/List;\n    |               \u0026#304;LOAD_3     // boolean includeDeleted   (line 118)\n    |               \u0026#304;FEQ L0\n    |               ALOAD_0     // com.ytg.bilette.client.core.providers.DomainContentProvider this   (line 119)\n    |               GETSTAT\u0026#304;C com.ytg.bilette.client.core.providers.DomainContentProvider$State.FULL_INITIALIZED Lcom/ytg/bilette/client/core/providers/DomainContentProvider$State;\n    |               PUTF\u0026#304;ELD com.ytg.bilette.client.core.providers.DomainContentProvider.state Lcom/ytg/bilette/client/core/providers/DomainContentProvider$State;\n    |               GOTO L1\n    |           L0: ALOAD_0     // com.ytg.bilette.client.core.providers.DomainContentProvider this   (line 121)\n    |               GETSTAT\u0026#304;C com.ytg.bilette.client.core.providers.DomainContentProvider$State.LIGHT_INITIALIZED Lcom/ytg/bilette/client/core/providers/DomainContentProvider$State;\n    |               PUTF\u0026#304;ELD com.ytg.bilette.client.core.providers.DomainContentProvider.state Lcom/ytg/bilette/client/core/providers/DomainContentProvider$State;\n    |           L1: RETURN   (line 122)\n    method-execution(void com.ytg.bilette.client.core.providers.DomainContentProvider.getData(com.ytg.bilette.dao.SummaryDAO, org.eclipse.core.runtime.IProgressMonitor, boolean))\n  end private void getData(com.ytg.bilette.dao.SummaryDAO, org.eclipse.core.runtime.IProgressMonitor, boolean)\n\n  public java.util.List getSummaries(boolean)    org.aspectj.weaver.MethodDeclarationLineNumber: 128:3308\n:\n                    ALOAD_0     // com.ytg.bilette.client.core.providers.DomainContentProvider this   (line 129)\n                    \u0026#304;LOAD_1     // boolean includeDeleted\n                    \u0026#304;NVOKESPEC\u0026#304;AL com.ytg.bilette.client.core.providers.DomainContentProvider.checkInitialized (Z)V\n                    \u0026#304;LOAD_1     // boolean includeDeleted   (line 131)\n                    \u0026#304;FNE L0\n                    GETSTAT\u0026#304;C com.ytg.bilette.client.core.providers.DomainContentProvider$State.LIGHT_INITIALIZED Lcom/ytg/bilette/client/core/providers/DomainContentProvider$State;\n                    ALOAD_0     // com.ytg.bilette.client.core.providers.DomainContentProvider this\n                    GETF\u0026#304;ELD com.ytg.bilette.client.core.providers.DomainContentProvider.state Lcom/ytg/bilette/client/core/providers/DomainContentProvider$State;\n                    \u0026#304;NVOKEV\u0026#304;RTUAL com.ytg.bilette.client.core.providers.DomainContentProvider$State.equals (Ljava/lang/Object;)Z\n                    \u0026#304;FEQ L1\n                L0: ALOAD_0     // com.ytg.bilette.client.core.providers.DomainContentProvider this   (line 132)\n                    GETF\u0026#304;ELD com.ytg.bilette.client.core.providers.DomainContentProvider.summaries Ljava/util/List;\n                    ARETURN\n                L1: ALOAD_0     // com.ytg.bilette.client.core.providers.DomainContentProvider this   (line 134)\n                    GETF\u0026#304;ELD com.ytg.bilette.client.core.providers.DomainContentProvider.summaries Ljava/util/List;\n                    \u0026#304;NVOKE\u0026#304;NTERFACE java.util.List.iterator ()Ljava/util/Iterator;\n                    ASTORE_2\n                    NEW java.util.ArrayList   (line 135)\n                    DUP\n                    \u0026#304;NVOKESPEC\u0026#304;AL java.util.ArrayList.\u003cinit\u003e ()V\n                    ASTORE_3\n                    GOTO L3   (line 136)\n                L2: ALOAD_2     // java.util.Iterator i   (line 137)\n                    \u0026#304;NVOKE\u0026#304;NTERFACE java.util.Iterator.next ()Ljava/lang/Object;\n                    CHECKCAST com.ytg.bilette.model.Deletable\n                    CHECKCAST com.ytg.bilette.model.Deletable\n                    ASTORE 4\n                    ALOAD 4     // com.ytg.bilette.model.Deletable object   (line 138)\n                    \u0026#304;NVOKE\u0026#304;NTERFACE com.ytg.bilette.model.Deletable.isDeleted ()Z\n                    \u0026#304;FNE L3\n                    ALOAD_3     // java.util.ArrayList list   (line 139)\n                    ALOAD 4     // com.ytg.bilette.model.Deletable object\n                    CHECKCAST com.ytg.bilette.model.GenericDomainObject\n                    \u0026#304;NVOKEV\u0026#304;RTUAL java.util.ArrayList.add (Ljava/lang/Object;)Z\n                    POP\n                L3: ALOAD_2     // java.util.Iterator i   (line 136)\n                    \u0026#304;NVOKE\u0026#304;NTERFACE java.util.Iterator.hasNext ()Z\n                    \u0026#304;FNE L2\n                    ALOAD_3     // java.util.ArrayList list   (line 142)\n                    ARETURN\n  end public java.util.List getSummaries(boolean)\n\n  public synchronized void refresh()    org.aspectj.weaver.MethodDeclarationLineNumber: 148:3783\n:\n                    ALOAD_0     // com.ytg.bilette.client.core.providers.DomainContentProvider this   (line 149)\n                    GETSTAT\u0026#304;C com.ytg.bilette.client.core.providers.DomainContentProvider$State.NOT_INITIALIZED Lcom/ytg/bilette/client/core/providers/DomainContentProvider$State;\n                    PUTF\u0026#304;ELD com.ytg.bilette.client.core.providers.DomainContentProvider.state Lcom/ytg/bilette/client/core/providers/DomainContentProvider$State;\n                    \u0026#304;CONST_0   (line 150)\n                    \u0026#304;STORE_1\n                    ALOAD_0     // com.ytg.bilette.client.core.providers.DomainContentProvider this   (line 152)\n                    GETF\u0026#304;ELD com.ytg.bilette.client.core.providers.DomainContentProvider.deletable Z\n                    \u0026#304;FEQ L2\n                    ALOAD_0     // com.ytg.bilette.client.core.providers.DomainContentProvider this   (line 153)\n                    GETF\u0026#304;ELD com.ytg.bilette.client.core.providers.DomainContentProvider.listeners Ljava/util/HashSet;\n                    \u0026#304;NVOKEV\u0026#304;RTUAL java.util.HashSet.iterator ()Ljava/util/Iterator;\n                    ASTORE_2\n                    GOTO L1   (line 154)\n                L0: ALOAD_2     // java.util.Iterator i   (line 155)\n                    \u0026#304;NVOKE\u0026#304;NTERFACE java.util.Iterator.next ()Ljava/lang/Object;\n                    CHECKCAST com.ytg.bilette.client.core.providers.IDomainObjectChangeListener\n                    ASTORE_3\n                    ALOAD_3     // com.ytg.bilette.client.core.providers.IDomainObjectChangeListener listener   (line 156)\n                    \u0026#304;NVOKE\u0026#304;NTERFACE com.ytg.bilette.client.core.providers.IDomainObjectChangeListener.isIncludeDeleted ()Z\n                    \u0026#304;FEQ L1\n                    \u0026#304;CONST_1   (line 157)\n                    \u0026#304;STORE_1     // boolean includeDeleted\n                    GOTO L2   (line 158)\n                L1: ALOAD_2     // java.util.Iterator i   (line 154)\n                    \u0026#304;NVOKE\u0026#304;NTERFACE java.util.Iterator.hasNext ()Z\n                    \u0026#304;FNE L0\n                L2: ALOAD_0     // com.ytg.bilette.client.core.providers.DomainContentProvider this   (line 163)\n                    ACONST_NULL\n                    ACONST_NULL\n                    \u0026#304;LOAD_1     // boolean includeDeleted\n                    \u0026#304;NVOKESPEC\u0026#304;AL com.ytg.bilette.client.core.providers.DomainContentProvider.getData (Lcom/ytg/bilette/dao/SummaryDAO;Lorg/eclipse/core/runtime/IProgressMonitor;Z)V\n                    ALOAD_0     // com.ytg.bilette.client.core.providers.DomainContentProvider this   (line 165)\n                    ACONST_NULL\n                    ACONST_NULL\n                    \u0026#304;NVOKESPEC\u0026#304;AL com.ytg.bilette.client.core.providers.DomainContentProvider.notifyAllListeners (Lcom/ytg/bilette/model/GenericDomainObject;Lcom/ytg/bilette/model/GenericDomainObject;)V\n                    RETURN   (line 166)\n  end public synchronized void refresh()\n\n  private synchronized void notifyAllListeners(com.ytg.bilette.model.GenericDomainObject, com.ytg.bilette.model.GenericDomainObject)    org.aspectj.weaver.MethodDeclarationLineNumber: 174:4356\n:\n                    ALOAD_0     // com.ytg.bilette.client.core.providers.DomainContentProvider this   (line 175)\n                    GETF\u0026#304;ELD com.ytg.bilette.client.core.providers.DomainContentProvider.listeners Ljava/util/HashSet;\n                    \u0026#304;NVOKEV\u0026#304;RTUAL java.util.HashSet.iterator ()Ljava/util/Iterator;\n                    ASTORE_3\n                    GOTO L2   (line 176)\n                L0: ALOAD_3     // java.util.Iterator i   (line 177)\n                    \u0026#304;NVOKE\u0026#304;NTERFACE java.util.Iterator.next ()Ljava/lang/Object;\n                    CHECKCAST com.ytg.bilette.client.core.providers.IDomainObjectChangeListener\n                    ASTORE 4\n                    ALOAD_1     // com.ytg.bilette.model.GenericDomainObject oldObj   (line 178)\n                    \u0026#304;FNONNULL L1\n                    ALOAD_2     // com.ytg.bilette.model.GenericDomainObject newObj\n                    \u0026#304;FNONNULL L1\n                    ALOAD 4     // com.ytg.bilette.client.core.providers.IDomainObjectChangeListener listener   (line 179)\n                    \u0026#304;NVOKE\u0026#304;NTERFACE com.ytg.bilette.client.core.providers.IDomainObjectChangeListener.fullRefresh ()V\n                    GOTO L2\n                L1: ALOAD 4     // com.ytg.bilette.client.core.providers.IDomainObjectChangeListener listener   (line 181)\n                    ALOAD_1     // com.ytg.bilette.model.GenericDomainObject oldObj\n                    ALOAD_2     // com.ytg.bilette.model.GenericDomainObject newObj\n                    \u0026#304;NVOKE\u0026#304;NTERFACE com.ytg.bilette.client.core.providers.IDomainObjectChangeListener.concessionChanged (Lcom/ytg/bilette/model/GenericDomainObject;Lcom/ytg/bilette/model/GenericDomainObject;)V\n                L2: ALOAD_3     // java.util.Iterator i   (line 176)\n                    \u0026#304;NVOKE\u0026#304;NTERFACE java.util.Iterator.hasNext ()Z\n                    \u0026#304;FNE L0\n                    RETURN   (line 183)\n  end private synchronized void notifyAllListeners(com.ytg.bilette.model.GenericDomainObject, com.ytg.bilette.model.GenericDomainObject)\n\n  public synchronized void addListener(com.ytg.bilette.client.core.providers.IDomainObjectChangeListener)    org.aspectj.weaver.MethodDeclarationLineNumber: 185:4715\n:\n                    ALOAD_0     // com.ytg.bilette.client.core.providers.DomainContentProvider this   (line 186)\n                    GETF\u0026#304;ELD com.ytg.bilette.client.core.providers.DomainContentProvider.listeners Ljava/util/HashSet;\n                    ALOAD_1     // com.ytg.bilette.client.core.providers.IDomainObjectChangeListener listener\n                    \u0026#304;NVOKEV\u0026#304;RTUAL java.util.HashSet.add (Ljava/lang/Object;)Z\n                    POP\n                    RETURN   (line 187)\n  end public synchronized void addListener(com.ytg.bilette.client.core.providers.IDomainObjectChangeListener)\n\n  public synchronized void removeListener(com.ytg.bilette.client.core.providers.IDomainObjectChangeListener)    org.aspectj.weaver.MethodDeclarationLineNumber: 189:4831\n:\n                    ALOAD_0     // com.ytg.bilette.client.core.providers.DomainContentProvider this   (line 190)\n                    GETF\u0026#304;ELD com.ytg.bilette.client.core.providers.DomainContentProvider.listeners Ljava/util/HashSet;\n                    ALOAD_1     // com.ytg.bilette.client.core.providers.IDomainObjectChangeListener listener\n                    \u0026#304;NVOKEV\u0026#304;RTUAL java.util.HashSet.remove (Ljava/lang/Object;)Z\n                    POP\n                    RETURN   (line 191)\n  end public synchronized void removeListener(com.ytg.bilette.client.core.providers.IDomainObjectChangeListener)\n\nend public class com.ytg.bilette.client.core.providers.DomainContentProvider\n\nwhen implementing on shadow method-execution(void com.ytg.bilette.client.core.providers.DomainContentProvider.getData(com.ytg.bilette.dao.SummaryDAO, org.eclipse.core.runtime.IProgressMonitor, boolean))\nwhen weaving type com.ytg.bilette.client.core.providers.DomainContentProvider\nwhen weaving classes \nwhen weaving \nwhen batch building BuildConfig[F:\\java\\Bilette\\.metadata\\.plugins\\org.eclipse.ajdt.core\\com.ytg.bilette.client.core.generated.lst] #Files\u003d22",
    "Are you able to supply any more information? what were you doing at the time? are you using Java5? are you using annotations? are you using annotation binding pointcuts? Did it occur on a full build or an incremental compile? (I suspect the 1.2.1 level of AJ that you raised the bug against isnt quite right... I assume you are on AspectJ 5)\n\nThe line number has \u0027moved\u0027 since the version in which this stack trace is reported (but I know we haven\u0027t made recent AJs available in AJDT yet) - but although it has moved it could still be a bug as I haven\u0027t knowingly fixed anything in this area.",
    "Yeah sure. Sorry The bug export was so good I couldn\u0027t touch it. :)\n\nAnyways, \nI think it is due the fact that that class being tried to be vowen has java 1.5 templates and template was refered in a matched method... The bug occured o n every build triger.\n\nA snipped version of the code is here:\npublic class DomainContentProvider\u003cT extends GenericDomainObject\u003e implements\n\t\tIRefreshableStructuredContentProvider\u003cT\u003e {\n\u003c...\u003e\n\t@DAOOperation(clazz \u003d SummaryDAO.class, remove \u003d DAORemoveCondition.ALWAYS)\n\tprivate void getData(SummaryDAO dao, IProgressMonitor monitor,\n\t\t\tboolean includeDeleted) {\n\t\tsummaries \u003d (List\u003cT\u003e) dao.getSummaries(clazz, includeDeleted);\n\t\tif (includeDeleted)\n\t\t\tstate \u003d State.FULL_INITIALIZED;\n\t\telse\n\t\t\tstate \u003d State.LIGHT_INITIALIZED;\n\t}\n\u003c...\u003e\n}",
    "Problem recreated with this small test program:\n\n\u003d\u003d\u003d\u003d\u003d\u003d\u003d8\u003c\u003d\u003d\u003d\u003d\u003d\u003d\u003d\u003d\u003d\u003d\u003d\u003d\u003d\u003d\u003d\u003d\u003d\u003d\u003d\u003d\u003d\u003d\u003d\u003d\nimport java.lang.annotation.*;\n\ninterface GDO {}\n\n@Retention(RetentionPolicy.RUNTIME) @interface Marker { }\n\nclass DCP\u003cT extends GDO\u003e {\n @Marker void getData(){}\n}\n\naspect X {\n  before(Marker a): execution(* getData(..)) \u0026\u0026 @annotation(a) { System.err.println(a);  }\n}\n\npublic class A {\n\tpublic static void main(String[] args) {\n\t\tnew DCP().getData();\n\t}\n}\n\n\u003d\u003d\u003d\u003d\u003d\u003d\u003d8\u003c\u003d\u003d\u003d\u003d\u003d\u003d\u003d\u003d\u003d\u003d\u003d\u003d\u003d\u003d\u003d\u003d\u003d\u003d\u003d\u003d\u003d\u003d\u003d\u003d\n(thanks for giving me your code snippet to work from)\n\nAs suspected by the raiser, the combination of generics and annotations is the problem.  We start working with the raw type when we should be working with the generic type when discovering the annotations.  The fix is when working with a raw or parameterized type, use the generic type to locate annotations.\n\nfix committed."
  ],
  "commentCreationDates": [
    "2006-02-28T01:32:19+01:00",
    "2006-02-28T08:25:12+01:00",
    "2006-02-28T09:38:13+01:00",
    "2006-05-12T12:39:28+02:00"
  ],
  "traces": [
    {
      "exceptionType": "org.aspectj.weaver.BCException",
      "elements": [
        {
          "method": "org.aspectj.weaver.bcel.BcelShadow.initializeKindedAnnotationVars",
          "source": "BcelShadow.java:1553"
        },
        {
          "method": "org.aspectj.weaver.bcel.BcelShadow.getKindedAnnotationVar",
          "source": "BcelShadow.java:995"
        },
        {
          "method": "org.aspectj.weaver.patterns.AnnotationPointcut.findResidueInternal",
          "source": "AnnotationPointcut.java:196"
        },
        {
          "method": "org.aspectj.weaver.patterns.Pointcut.findResidue",
          "source": "Pointcut.java:268"
        },
        {
          "method": "org.aspectj.weaver.patterns.AndPointcut.findResidueInternal",
          "source": "AndPointcut.java:97"
        },
        {
          "method": "org.aspectj.weaver.patterns.Pointcut.findResidue",
          "source": "Pointcut.java:268"
        },
        {
          "method": "org.aspectj.weaver.patterns.AndPointcut.findResidueInternal",
          "source": "AndPointcut.java:97"
        },
        {
          "method": "org.aspectj.weaver.patterns.Pointcut.findResidue",
          "source": "Pointcut.java:268"
        },
        {
          "method": "org.aspectj.weaver.patterns.AndPointcut.findResidueInternal",
          "source": "AndPointcut.java:97"
        },
        {
          "method": "org.aspectj.weaver.patterns.Pointcut.findResidue",
          "source": "Pointcut.java:268"
        },
        {
          "method": "org.aspectj.weaver.bcel.BcelAdvice.specializeOn",
          "source": "BcelAdvice.java:132"
        },
        {
          "method": "org.aspectj.weaver.bcel.BcelShadow.prepareForMungers",
          "source": "BcelShadow.java:313"
        },
        {
          "method": "org.aspectj.weaver.Shadow.implement",
          "source": "Shadow.java:404"
        },
        {
          "method": "org.aspectj.weaver.bcel.BcelClassWeaver.implement",
          "source": "BcelClassWeaver.java:2146"
        },
        {
          "method": "org.aspectj.weaver.bcel.BcelClassWeaver.weave",
          "source": "BcelClassWeaver.java:467"
        },
        {
          "method": "org.aspectj.weaver.bcel.BcelClassWeaver.weave",
          "source": "BcelClassWeaver.java:102"
        },
        {
          "method": "org.aspectj.weaver.bcel.BcelWeaver.weave",
          "source": "BcelWeaver.java:1543"
        },
        {
          "method": "org.aspectj.weaver.bcel.BcelWeaver.weaveWithoutDump",
          "source": "BcelWeaver.java:1494"
        },
        {
          "method": "org.aspectj.weaver.bcel.BcelWeaver.weaveAndNotify",
          "source": "BcelWeaver.java:1275"
        },
        {
          "method": "org.aspectj.weaver.bcel.BcelWeaver.weave",
          "source": "BcelWeaver.java:1097"
        },
        {
          "method": "org.aspectj.ajdt.internal.compiler.AjCompilerAdapter.weave",
          "source": "AjCompilerAdapter.java:300"
        },
        {
          "method": "org.aspectj.ajdt.internal.compiler.AjCompilerAdapter.afterCompiling",
          "source": "AjCompilerAdapter.java:178"
        },
        {
          "method": "org.aspectj.ajdt.internal.compiler.CompilerAdapter.ajc$afterReturning$org_aspectj_ajdt_internal_compiler_CompilerAdapter$2$f9cc9ca0",
          "source": "CompilerAdapter.aj:70"
        },
        {
          "method": "org.aspectj.org.eclipse.jdt.internal.compiler.Compiler.compile",
          "source": "Compiler.java:367"
        },
        {
          "method": "org.aspectj.ajdt.internal.core.builder.AjBuildManager.performCompilation",
          "source": "AjBuildManager.java:811"
        },
        {
          "method": "org.aspectj.ajdt.internal.core.builder.AjBuildManager.doBuild",
          "source": "AjBuildManager.java:230"
        },
        {
          "method": "org.aspectj.ajdt.internal.core.builder.AjBuildManager.batchBuild",
          "source": "AjBuildManager.java:156"
        },
        {
          "method": "org.aspectj.ajde.internal.CompilerAdapter.compile",
          "source": "CompilerAdapter.java:122"
        },
        {
          "method": "org.aspectj.ajde.internal.AspectJBuildManager$CompilerThread.run",
          "source": "AspectJBuildManager.java:191"
        }
      ],
      "number": 0,
      "commentIndex": 0,
      "bugId": "129704",
      "date": "2006-02-28T01:32:19+01:00",
      "product": "AspectJ",
      "component": "Compiler",
      "severity": "normal"
    }
  ],
  "groupId": "129704",
  "bugId": "129704",
  "date": "2006-02-28T01:32:19+01:00",
  "product": "AspectJ",
  "component": "Compiler",
  "severity": "normal"
}