{
  "comments": [
    "I20060228-1207\n\nFound this in the log:\n\n!ENTRY org.eclipse.ui 4 0 2006-03-01 12:13:33.142\n!MESSAGE org.eclipse.jdt.internal.ui.wizards.buildpaths.CPListElementAttribute\n!STACK 0\njava.lang.ClassCastException: org.eclipse.jdt.internal.ui.wizards.buildpaths.CPListElementAttribute\n        at org.eclipse.jdt.internal.ui.wizards.buildpaths.newsourcepage.NewSourceContainerWorkbookPage.setSelection(NewSourceContainerWorkbookPage.jav\na:318)\n        at org.eclipse.jdt.internal.ui.wizards.buildpaths.BuildPathsBlock.tabChanged(BuildPathsBlock.java:907)\n        at org.eclipse.jdt.internal.ui.wizards.buildpaths.BuildPathsBlock.access$2(BuildPathsBlock.java:900)\n        at org.eclipse.jdt.internal.ui.wizards.buildpaths.BuildPathsBlock$1.widgetSelected(BuildPathsBlock.java:277)\n        at org.eclipse.swt.widgets.TypedListener.handleEvent(TypedListener.java:90)\n        at org.eclipse.swt.widgets.EventTable.sendEvent(EventTable.java:66)\n        at org.eclipse.swt.widgets.Widget.sendEvent(Widget.java:925)\n        at org.eclipse.swt.widgets.Display.runDeferredEvents(Display.java:3328)\n        at org.eclipse.swt.widgets.Display.readAndDispatch(Display.java:2948)\n        at org.eclipse.jface.window.Window.runEventLoop(Window.java:820)\n        at org.eclipse.jface.window.Window.open(Window.java:796)\n        at org.eclipse.ui.actions.NewProjectAction.run(NewProjectAction.java:116)\n        at org.eclipse.jface.action.Action.runWithEvent(Action.java:499)\n        at org.eclipse.jface.action.ActionContributionItem.handleWidgetSelection(ActionContributionItem.java:539)\n        at org.eclipse.jface.action.ActionContributionItem.access$2(ActionContributionItem.java:488)\n        at org.eclipse.jface.action.ActionContributionItem$5.handleEvent(ActionContributionItem.java:400)\n        at org.eclipse.swt.widgets.EventTable.sendEvent(EventTable.java:66)\n        at org.eclipse.swt.widgets.Widget.sendEvent(Widget.java:925)\n        at org.eclipse.swt.widgets.Display.runDeferredEvents(Display.java:3328)\n        at org.eclipse.swt.widgets.Display.readAndDispatch(Display.java:2948)\n        at org.eclipse.ui.internal.Workbench.runEventLoop(Workbench.java:1927)\n        at org.eclipse.ui.internal.Workbench.runUI(Workbench.java:1891)\n        at org.eclipse.ui.internal.Workbench.createAndRunWorkbench(Workbench.java:423)\n        at org.eclipse.ui.PlatformUI.createAndRunWorkbench(PlatformUI.java:143)\n        at org.eclipse.ui.internal.ide.IDEApplication.run(IDEApplication.java:107)\n        at org.eclipse.core.internal.runtime.PlatformActivator$1.run(PlatformActivator.java:99)\n        at org.eclipse.core.runtime.internal.adaptor.EclipseAppLauncher.runApplication(EclipseAppLauncher.java:92)\n        at org.eclipse.core.runtime.internal.adaptor.EclipseAppLauncher.start(EclipseAppLauncher.java:68)\n        at org.eclipse.core.runtime.adaptor.EclipseStarter.run(EclipseStarter.java:374)\n        at org.eclipse.core.runtime.adaptor.EclipseStarter.run(EclipseStarter.java:169)\n        at sun.reflect.NativeMethodAccessorImpl.invoke0(Native Method)\n        at sun.reflect.NativeMethodAccessorImpl.invoke(NativeMethodAccessorImpl.java:39)\n        at sun.reflect.DelegatingMethodAccessorImpl.invoke(DelegatingMethodAccessorImpl.java:25)\n        at java.lang.reflect.Method.invoke(Method.java:585)\n        at org.eclipse.core.launcher.Main.invokeFramework(Main.java:338)\n        at org.eclipse.core.launcher.Main.basicRun(Main.java:282)\n        at org.eclipse.core.launcher.Main.run(Main.java:977)\n        at org.eclipse.core.launcher.Main.main(Main.java:952)",
    "To reproduce:\n\n1. Open New Java Project Wizard\n2. Type in project name\n3. Next\n4. Go to Libraries tab\n5. Expand JRE node\n6. Select Access rules\n7. Go to Source tab\n-\u003eException is thrown\n",
    "fixed \u003e I20060228-1207"
  ],
  "commentCreationDates": [
    "2006-03-01T16:23:08+01:00",
    "2006-03-01T16:59:49+01:00",
    "2006-03-01T17:10:25+01:00"
  ],
  "traces": [
    {
      "exceptionType": "java.lang.ClassCastException",
      "message": "org.eclipse.jdt.internal.ui.wizards.buildpaths.CPListElementAttribute",
      "elements": [
        {
          "method": "org.eclipse.jdt.internal.ui.wizards.buildpaths.newsourcepage.NewSourceContainerWorkbookPage.setSelection",
          "source": "NewSourceContainerWorkbookPage.jav a:318"
        },
        {
          "method": "org.eclipse.jdt.internal.ui.wizards.buildpaths.BuildPathsBlock.tabChanged",
          "source": "BuildPathsBlock.java:907"
        },
        {
          "method": "org.eclipse.jdt.internal.ui.wizards.buildpaths.BuildPathsBlock.access$2",
          "source": "BuildPathsBlock.java:900"
        },
        {
          "method": "org.eclipse.jdt.internal.ui.wizards.buildpaths.BuildPathsBlock$1.widgetSelected",
          "source": "BuildPathsBlock.java:277"
        },
        {
          "method": "org.eclipse.swt.widgets.TypedListener.handleEvent",
          "source": "TypedListener.java:90"
        },
        {
          "method": "org.eclipse.swt.widgets.EventTable.sendEvent",
          "source": "EventTable.java:66"
        },
        {
          "method": "org.eclipse.swt.widgets.Widget.sendEvent",
          "source": "Widget.java:925"
        },
        {
          "method": "org.eclipse.swt.widgets.Display.runDeferredEvents",
          "source": "Display.java:3328"
        },
        {
          "method": "org.eclipse.swt.widgets.Display.readAndDispatch",
          "source": "Display.java:2948"
        },
        {
          "method": "org.eclipse.jface.window.Window.runEventLoop",
          "source": "Window.java:820"
        },
        {
          "method": "org.eclipse.jface.window.Window.open",
          "source": "Window.java:796"
        },
        {
          "method": "org.eclipse.ui.actions.NewProjectAction.run",
          "source": "NewProjectAction.java:116"
        },
        {
          "method": "org.eclipse.jface.action.Action.runWithEvent",
          "source": "Action.java:499"
        },
        {
          "method": "org.eclipse.jface.action.ActionContributionItem.handleWidgetSelection",
          "source": "ActionContributionItem.java:539"
        },
        {
          "method": "org.eclipse.jface.action.ActionContributionItem.access$2",
          "source": "ActionContributionItem.java:488"
        },
        {
          "method": "org.eclipse.jface.action.ActionContributionItem$5.handleEvent",
          "source": "ActionContributionItem.java:400"
        },
        {
          "method": "org.eclipse.swt.widgets.EventTable.sendEvent",
          "source": "EventTable.java:66"
        },
        {
          "method": "org.eclipse.swt.widgets.Widget.sendEvent",
          "source": "Widget.java:925"
        },
        {
          "method": "org.eclipse.swt.widgets.Display.runDeferredEvents",
          "source": "Display.java:3328"
        },
        {
          "method": "org.eclipse.swt.widgets.Display.readAndDispatch",
          "source": "Display.java:2948"
        },
        {
          "method": "org.eclipse.ui.internal.Workbench.runEventLoop",
          "source": "Workbench.java:1927"
        },
        {
          "method": "org.eclipse.ui.internal.Workbench.runUI",
          "source": "Workbench.java:1891"
        },
        {
          "method": "org.eclipse.ui.internal.Workbench.createAndRunWorkbench",
          "source": "Workbench.java:423"
        },
        {
          "method": "org.eclipse.ui.PlatformUI.createAndRunWorkbench",
          "source": "PlatformUI.java:143"
        },
        {
          "method": "org.eclipse.ui.internal.ide.IDEApplication.run",
          "source": "IDEApplication.java:107"
        },
        {
          "method": "org.eclipse.core.internal.runtime.PlatformActivator$1.run",
          "source": "PlatformActivator.java:99"
        },
        {
          "method": "org.eclipse.core.runtime.internal.adaptor.EclipseAppLauncher.runApplication",
          "source": "EclipseAppLauncher.java:92"
        },
        {
          "method": "org.eclipse.core.runtime.internal.adaptor.EclipseAppLauncher.start",
          "source": "EclipseAppLauncher.java:68"
        },
        {
          "method": "org.eclipse.core.runtime.adaptor.EclipseStarter.run",
          "source": "EclipseStarter.java:374"
        },
        {
          "method": "org.eclipse.core.runtime.adaptor.EclipseStarter.run",
          "source": "EclipseStarter.java:169"
        },
        {
          "method": "sun.reflect.NativeMethodAccessorImpl.invoke0",
          "source": "Native Method"
        },
        {
          "method": "sun.reflect.NativeMethodAccessorImpl.invoke",
          "source": "NativeMethodAccessorImpl.java:39"
        },
        {
          "method": "sun.reflect.DelegatingMethodAccessorImpl.invoke",
          "source": "DelegatingMethodAccessorImpl.java:25"
        },
        {
          "method": "java.lang.reflect.Method.invoke",
          "source": "Method.java:585"
        },
        {
          "method": "org.eclipse.core.launcher.Main.invokeFramework",
          "source": "Main.java:338"
        },
        {
          "method": "org.eclipse.core.launcher.Main.basicRun",
          "source": "Main.java:282"
        },
        {
          "method": "org.eclipse.core.launcher.Main.run",
          "source": "Main.java:977"
        },
        {
          "method": "org.eclipse.core.launcher.Main.main",
          "source": "Main.java:952"
        }
      ],
      "number": 0,
      "commentIndex": 0,
      "bugId": "129971",
      "date": "2006-03-01T16:23:08+01:00",
      "product": "JDT",
      "component": "UI",
      "severity": "normal"
    }
  ],
  "groupId": "129971",
  "bugId": "129971",
  "date": "2006-03-01T16:23:08+01:00",
  "product": "JDT",
  "component": "UI",
  "severity": "normal"
}