{
  "comments": [
    "Hi,\n\nI\u0027ve upgraded to 3.2M5a event though it is said it is not necessary so am not sure if this is a bug or not, yet report it, so it might not hit later people upgrading to M6.\n\nWhen I start M5a shortly after displaying the splash screen a dialog appears telling me an error occured and reffering me to a log file. The content of said file is posted below.\n\nIf I start M5 (installed in a different directory, but using the same Workspace and same $HOME/.eclipse directory) everyting works as expected.\n\n$ cat /home/claudio/.eclipse/org.eclipse.platform_3.1.0/configuration/1142111265969.log\n!SESSION 2006-03-11 22:07:45.860 -----------------------------------------------\neclipse.buildId\u003dI20060223-1656\njava.version\u003d1.5.0_06\njava.vendor\u003dSun Microsystems Inc.\nBootLoader constants: OS\u003dlinux, ARCH\u003dx86, WS\u003dgtk, NL\u003den_GB\nCommand-line arguments:  -os linux -ws gtk -arch x86\n\n!ENTRY org.eclipse.core.runtime 4 0 2006-03-11 22:07:46.881\n!MESSAGE FrameworkEvent.ERROR\n!STACK 0\norg.osgi.framework.BundleException: Exception in org.eclipse.core.internal.runtime.PlatformActivator.start() of bundle org.eclipse.core.runtime.\n        at org.eclipse.osgi.framework.internal.core.BundleContextImpl.startActivator(BundleContextImpl.java:1013)\n        at org.eclipse.osgi.framework.internal.core.BundleContextImpl.start(BundleContextImpl.java:969)\n        at org.eclipse.osgi.framework.internal.core.BundleHost.startWorker(BundleHost.java:314)\n        at org.eclipse.osgi.framework.internal.core.AbstractBundle.resume(AbstractBundle.java:329)\n        at org.eclipse.osgi.framework.internal.core.Framework.resumeBundle(Framework.java:1037)\n        at org.eclipse.osgi.framework.internal.core.StartLevelManager.resumeBundles(StartLevelManager.java:573)\n        at org.eclipse.osgi.framework.internal.core.StartLevelManager.incFWSL(StartLevelManager.java:495)\n        at org.eclipse.osgi.framework.internal.core.StartLevelManager.doSetStartLevel(StartLevelManager.java:275)\n        at org.eclipse.osgi.framework.internal.core.StartLevelManager.dispatchEvent(StartLevelManager.java:455)\n        at org.eclipse.osgi.framework.eventmgr.EventManager.dispatchEvent(EventManager.java:189)\n        at org.eclipse.osgi.framework.eventmgr.EventManager$EventThread.run(EventManager.java:291)\nCaused by: java.lang.NullPointerException\n        at org.eclipse.core.internal.runtime.AdapterManagerListener.registerFactoryProxies(AdapterManagerListener.java:42)\n        at org.eclipse.core.internal.runtime.AdapterManagerListener.\u003cinit\u003e(AdapterManagerListener.java:31)\n        at org.eclipse.core.internal.runtime.InternalPlatform.start(InternalPlatform.java:981)\n        at org.eclipse.core.internal.runtime.PlatformActivator.start(PlatformActivator.java:40)\n        at org.eclipse.osgi.framework.internal.core.BundleContextImpl$2.run(BundleContextImpl.java:994)\n        at java.security.AccessController.doPrivileged(Native Method)\n        at org.eclipse.osgi.framework.internal.core.BundleContextImpl.startActivator(BundleContextImpl.java:988)\n        ... 10 more\nRoot exception:\njava.lang.NullPointerException\n        at org.eclipse.core.internal.runtime.AdapterManagerListener.registerFactoryProxies(AdapterManagerListener.java:42)\n        at org.eclipse.core.internal.runtime.AdapterManagerListener.\u003cinit\u003e(AdapterManagerListener.java:31)\n        at org.eclipse.core.internal.runtime.InternalPlatform.start(InternalPlatform.java:981)\n        at org.eclipse.core.internal.runtime.PlatformActivator.start(PlatformActivator.java:40)\n        at org.eclipse.osgi.framework.internal.core.BundleContextImpl$2.run(BundleContextImpl.java:994)\n        at java.security.AccessController.doPrivileged(Native Method)\n        at org.eclipse.osgi.framework.internal.core.BundleContextImpl.startActivator(BundleContextImpl.java:988)\n        at org.eclipse.osgi.framework.internal.core.BundleContextImpl.start(BundleContextImpl.java:969)\n        at org.eclipse.osgi.framework.internal.core.BundleHost.startWorker(BundleHost.java:314)\n        at org.eclipse.osgi.framework.internal.core.AbstractBundle.resume(AbstractBundle.java:329)\n        at org.eclipse.osgi.framework.internal.core.Framework.resumeBundle(Framework.java:1037)\n        at org.eclipse.osgi.framework.internal.core.StartLevelManager.resumeBundles(StartLevelManager.java:573)\n        at org.eclipse.osgi.framework.internal.core.StartLevelManager.incFWSL(StartLevelManager.java:495)\n        at org.eclipse.osgi.framework.internal.core.StartLevelManager.doSetStartLevel(StartLevelManager.java:275)\n        at org.eclipse.osgi.framework.internal.core.StartLevelManager.dispatchEvent(StartLevelManager.java:455)\n        at org.eclipse.osgi.framework.eventmgr.EventManager.dispatchEvent(EventManager.java:189)\n        at org.eclipse.osgi.framework.eventmgr.EventManager$EventThread.run(EventManager.java:291)\n\n!ENTRY org.eclipse.update.configurator 4 0 2006-03-11 22:07:47.643\n!MESSAGE FrameworkEvent.ERROR\n!STACK 0\norg.osgi.framework.BundleException: Exception in org.eclipse.update.internal.configurator.ConfigurationActivator.start() of bundle org.eclipse.update.configurator.\n        at org.eclipse.osgi.framework.internal.core.BundleContextImpl.startActivator(BundleContextImpl.java:1013)\n        at org.eclipse.osgi.framework.internal.core.BundleContextImpl.start(BundleContextImpl.java:969)\n        at org.eclipse.osgi.framework.internal.core.BundleHost.startWorker(BundleHost.java:314)\n        at org.eclipse.osgi.framework.internal.core.AbstractBundle.resume(AbstractBundle.java:329)\n        at org.eclipse.osgi.framework.internal.core.Framework.resumeBundle(Framework.java:1037)\n        at org.eclipse.osgi.framework.internal.core.StartLevelManager.resumeBundles(StartLevelManager.java:573)\n        at org.eclipse.osgi.framework.internal.core.StartLevelManager.incFWSL(StartLevelManager.java:495)\n        at org.eclipse.osgi.framework.internal.core.StartLevelManager.doSetStartLevel(StartLevelManager.java:275)\n        at org.eclipse.osgi.framework.internal.core.StartLevelManager.dispatchEvent(StartLevelManager.java:455)\n        at org.eclipse.osgi.framework.eventmgr.EventManager.dispatchEvent(EventManager.java:189)\n        at org.eclipse.osgi.framework.eventmgr.EventManager$EventThread.run(EventManager.java:291)\nCaused by: java.lang.Exception: Cannot initialize the Update Configurator\n        at org.eclipse.update.internal.configurator.ConfigurationActivator.initialize(ConfigurationActivator.java:89)\n        at org.eclipse.update.internal.configurator.ConfigurationActivator.start(ConfigurationActivator.java:67)\n        at org.eclipse.osgi.framework.internal.core.BundleContextImpl$2.run(BundleContextImpl.java:994)\n        at java.security.AccessController.doPrivileged(Native Method)\n        at org.eclipse.osgi.framework.internal.core.BundleContextImpl.startActivator(BundleContextImpl.java:988)\n        ... 10 more\nRoot exception:\njava.lang.Exception: Cannot initialize the Update Configurator\n        at org.eclipse.update.internal.configurator.ConfigurationActivator.initialize(ConfigurationActivator.java:89)\n        at org.eclipse.update.internal.configurator.ConfigurationActivator.start(ConfigurationActivator.java:67)\n        at org.eclipse.osgi.framework.internal.core.BundleContextImpl$2.run(BundleContextImpl.java:994)\n        at java.security.AccessController.doPrivileged(Native Method)\n        at org.eclipse.osgi.framework.internal.core.BundleContextImpl.startActivator(BundleContextImpl.java:988)\n        at org.eclipse.osgi.framework.internal.core.BundleContextImpl.start(BundleContextImpl.java:969)\n        at org.eclipse.osgi.framework.internal.core.BundleHost.startWorker(BundleHost.java:314)\n        at org.eclipse.osgi.framework.internal.core.AbstractBundle.resume(AbstractBundle.java:329)\n        at org.eclipse.osgi.framework.internal.core.Framework.resumeBundle(Framework.java:1037)\n        at org.eclipse.osgi.framework.internal.core.StartLevelManager.resumeBundles(StartLevelManager.java:573)\n        at org.eclipse.osgi.framework.internal.core.StartLevelManager.incFWSL(StartLevelManager.java:495)\n        at org.eclipse.osgi.framework.internal.core.StartLevelManager.doSetStartLevel(StartLevelManager.java:275)\n        at org.eclipse.osgi.framework.internal.core.StartLevelManager.dispatchEvent(StartLevelManager.java:455)\n        at org.eclipse.osgi.framework.eventmgr.EventManager.dispatchEvent(EventManager.java:189)\n        at org.eclipse.osgi.framework.eventmgr.EventManager$EventThread.run(EventManager.java:291)\n\n!ENTRY org.eclipse.osgi 4 0 2006-03-11 22:07:47.682\n!MESSAGE Startup error\n!STACK 1\njava.lang.IllegalStateException: Bundle initial@reference:file:plugins/org.eclipse.core.runtime_3.2.0.v20060216.jar/ [7] is not active.\n        at org.eclipse.core.runtime.adaptor.EclipseStarter.ensureBundlesActive(EclipseStarter.java:416)\n        at org.eclipse.core.runtime.adaptor.EclipseStarter.startup(EclipseStarter.java:303)\n        at org.eclipse.core.runtime.adaptor.EclipseStarter.run(EclipseStarter.java:165)\n        at sun.reflect.NativeMethodAccessorImpl.invoke0(Native Method)\n        at sun.reflect.NativeMethodAccessorImpl.invoke(Unknown Source)\n        at sun.reflect.DelegatingMethodAccessorImpl.invoke(Unknown Source)\n        at java.lang.reflect.Method.invoke(Unknown Source)\n        at org.eclipse.core.launcher.Main.invokeFramework(Main.java:338)\n        at org.eclipse.core.launcher.Main.basicRun(Main.java:282)\n        at org.eclipse.core.launcher.Main.run(Main.java:977)\n        at org.eclipse.core.launcher.Main.main(Main.java:952)",
    "I just recognize that the statement \"using the same Workspace\" is just guessing, as eclipse does not reach the point I could see which workspace it opens. But in any case I did not specify on the commandline a different workspace. This is how I called eclipse:\n\n$ /usr/local/java/eclipse/eclipse\n\n$ /usr/local/java/eclipse-3.2M5/eclipse\n\n($ ist the shell prompt)\n\n/usr/local/eclipse contains 3.2M5a while /usr/local/java/eclipse-3.2M5 contains 3.2M5 as indicated by the name.\n\n",
    "I could solve the problem by starting eclipse 3.2M5a with the -clean option once. ",
    "Are you installing eclipse as read-only?",
    "Sort of yes. I created a user i-eclipse and unpacked the eclipse tar into /usr/local/java beeing this user. This user is used only for this purpose.\n\nWhen I work, and also when I created the crash I reported here, I always so it as user claudio. This user has no write permissions to any file below /usr/local/java/eclipse. So it is read-only.\n\nThen I have $HOME/Eclipse owned by claudio with two subdirectories Workspace and AddOns.\n\nWorkspace is as the name implies my workspace directory.\n\nAddOns is where I install the addons as user claudio. I do not install any plugins as user i-eclipse.\n\nCurrently I have just subclipse plugin. \n\n ls -l $HOME/Eclipse/AddOns/eclipse/*/\n/home/claudio/Eclipse/AddOns/eclipse/features/:\ntotal 4\ndrwxr-xr-x  4 claudio claudio 4096 2006-02-22 14:22 org.tigris.subversion.subclipse_0.9.106\n\n/home/claudio/Eclipse/AddOns/eclipse/plugins/:\ntotal 12\ndrwxr-xr-x  2 claudio claudio 4096 2006-02-22 14:22 org.tigris.subversion.subclipse_0.9.106\ndrwxr-xr-x  5 claudio claudio 4096 2006-02-22 14:22 org.tigris.subversion.subclipse.core_0.9.106\ndrwxr-xr-x  5 claudio claudio 4096 2006-02-22 14:22 org.tigris.subversion.subclipse.ui_0.9.106\n\n\nThe reason for this set up is, that I want to install never eclipse releases \"cleanly\" without the need to reinstall addons or having my user settings mixed in with the installed eclipse.\n \nSo when I installed 3.2M5a I did as user i-eclipse just this\n\ncd /usr/local/java/\nmv eclipse eclipse-3.2M5\ntar xzvf /var/tmp/eclipse-SDK-3.2M5a-linux-gtk.tar.gz\n\nThis way I still have the previous version 3.2M5 available if the new one has problems, and the new one is installed in a fresh eclipse directory. "
  ],
  "commentCreationDates": [
    "2006-03-11T21:10:45+01:00",
    "2006-03-11T21:18:30+01:00",
    "2006-03-17T21:45:08+01:00",
    "2006-03-21T15:49:17+01:00",
    "2006-03-21T16:52:27+01:00"
  ],
  "traces": [
    {
      "exceptionType": "org.osgi.framework.BundleException",
      "message": "Exception in org.eclipse.core.internal.runtime.PlatformActivator.start() of bundle org.eclipse.core.runtime.",
      "elements": [
        {
          "method": "org.eclipse.osgi.framework.internal.core.BundleContextImpl.startActivator",
          "source": "BundleContextImpl.java:1013"
        },
        {
          "method": "org.eclipse.osgi.framework.internal.core.BundleContextImpl.start",
          "source": "BundleContextImpl.java:969"
        },
        {
          "method": "org.eclipse.osgi.framework.internal.core.BundleHost.startWorker",
          "source": "BundleHost.java:314"
        },
        {
          "method": "org.eclipse.osgi.framework.internal.core.AbstractBundle.resume",
          "source": "AbstractBundle.java:329"
        },
        {
          "method": "org.eclipse.osgi.framework.internal.core.Framework.resumeBundle",
          "source": "Framework.java:1037"
        },
        {
          "method": "org.eclipse.osgi.framework.internal.core.StartLevelManager.resumeBundles",
          "source": "StartLevelManager.java:573"
        },
        {
          "method": "org.eclipse.osgi.framework.internal.core.StartLevelManager.incFWSL",
          "source": "StartLevelManager.java:495"
        },
        {
          "method": "org.eclipse.osgi.framework.internal.core.StartLevelManager.doSetStartLevel",
          "source": "StartLevelManager.java:275"
        },
        {
          "method": "org.eclipse.osgi.framework.internal.core.StartLevelManager.dispatchEvent",
          "source": "StartLevelManager.java:455"
        },
        {
          "method": "org.eclipse.osgi.framework.eventmgr.EventManager.dispatchEvent",
          "source": "EventManager.java:189"
        },
        {
          "method": "org.eclipse.osgi.framework.eventmgr.EventManager$EventThread.run",
          "source": "EventManager.java:291"
        }
      ],
      "causedBy": {
        "exceptionType": "java.lang.NullPointerException",
        "elements": [
          {
            "method": "org.eclipse.core.internal.runtime.AdapterManagerListener.registerFactoryProxies",
            "source": "AdapterManagerListener.java:42"
          },
          {
            "method": "org.eclipse.core.internal.runtime.AdapterManagerListener.\u003cinit\u003e",
            "source": "AdapterManagerListener.java:31"
          },
          {
            "method": "org.eclipse.core.internal.runtime.InternalPlatform.start",
            "source": "InternalPlatform.java:981"
          },
          {
            "method": "org.eclipse.core.internal.runtime.PlatformActivator.start",
            "source": "PlatformActivator.java:40"
          },
          {
            "method": "org.eclipse.osgi.framework.internal.core.BundleContextImpl$2.run",
            "source": "BundleContextImpl.java:994"
          },
          {
            "method": "java.security.AccessController.doPrivileged",
            "source": "Native Method"
          },
          {
            "method": "org.eclipse.osgi.framework.internal.core.BundleContextImpl.startActivator",
            "source": "BundleContextImpl.java:988"
          }
        ],
        "number": 0,
        "commentIndex": 0
      },
      "number": 0,
      "commentIndex": 0,
      "bugId": "131438",
      "date": "2006-03-11T21:10:45+01:00",
      "product": "Platform",
      "component": "Runtime",
      "severity": "minor"
    },
    {
      "exceptionType": "java.lang.NullPointerException",
      "elements": [
        {
          "method": "org.eclipse.core.internal.runtime.AdapterManagerListener.registerFactoryProxies",
          "source": "AdapterManagerListener.java:42"
        },
        {
          "method": "org.eclipse.core.internal.runtime.AdapterManagerListener.\u003cinit\u003e",
          "source": "AdapterManagerListener.java:31"
        },
        {
          "method": "org.eclipse.core.internal.runtime.InternalPlatform.start",
          "source": "InternalPlatform.java:981"
        },
        {
          "method": "org.eclipse.core.internal.runtime.PlatformActivator.start",
          "source": "PlatformActivator.java:40"
        },
        {
          "method": "org.eclipse.osgi.framework.internal.core.BundleContextImpl$2.run",
          "source": "BundleContextImpl.java:994"
        },
        {
          "method": "java.security.AccessController.doPrivileged",
          "source": "Native Method"
        },
        {
          "method": "org.eclipse.osgi.framework.internal.core.BundleContextImpl.startActivator",
          "source": "BundleContextImpl.java:988"
        },
        {
          "method": "org.eclipse.osgi.framework.internal.core.BundleContextImpl.start",
          "source": "BundleContextImpl.java:969"
        },
        {
          "method": "org.eclipse.osgi.framework.internal.core.BundleHost.startWorker",
          "source": "BundleHost.java:314"
        },
        {
          "method": "org.eclipse.osgi.framework.internal.core.AbstractBundle.resume",
          "source": "AbstractBundle.java:329"
        },
        {
          "method": "org.eclipse.osgi.framework.internal.core.Framework.resumeBundle",
          "source": "Framework.java:1037"
        },
        {
          "method": "org.eclipse.osgi.framework.internal.core.StartLevelManager.resumeBundles",
          "source": "StartLevelManager.java:573"
        },
        {
          "method": "org.eclipse.osgi.framework.internal.core.StartLevelManager.incFWSL",
          "source": "StartLevelManager.java:495"
        },
        {
          "method": "org.eclipse.osgi.framework.internal.core.StartLevelManager.doSetStartLevel",
          "source": "StartLevelManager.java:275"
        },
        {
          "method": "org.eclipse.osgi.framework.internal.core.StartLevelManager.dispatchEvent",
          "source": "StartLevelManager.java:455"
        },
        {
          "method": "org.eclipse.osgi.framework.eventmgr.EventManager.dispatchEvent",
          "source": "EventManager.java:189"
        },
        {
          "method": "org.eclipse.osgi.framework.eventmgr.EventManager$EventThread.run",
          "source": "EventManager.java:291"
        }
      ],
      "number": 1,
      "commentIndex": 0,
      "bugId": "131438",
      "date": "2006-03-11T21:10:45+01:00",
      "product": "Platform",
      "component": "Runtime",
      "severity": "minor"
    },
    {
      "exceptionType": "org.osgi.framework.BundleException",
      "message": "Exception in org.eclipse.update.internal.configurator.ConfigurationActivator.start() of bundle org.eclipse.update.configurator.",
      "elements": [
        {
          "method": "org.eclipse.osgi.framework.internal.core.BundleContextImpl.startActivator",
          "source": "BundleContextImpl.java:1013"
        },
        {
          "method": "org.eclipse.osgi.framework.internal.core.BundleContextImpl.start",
          "source": "BundleContextImpl.java:969"
        },
        {
          "method": "org.eclipse.osgi.framework.internal.core.BundleHost.startWorker",
          "source": "BundleHost.java:314"
        },
        {
          "method": "org.eclipse.osgi.framework.internal.core.AbstractBundle.resume",
          "source": "AbstractBundle.java:329"
        },
        {
          "method": "org.eclipse.osgi.framework.internal.core.Framework.resumeBundle",
          "source": "Framework.java:1037"
        },
        {
          "method": "org.eclipse.osgi.framework.internal.core.StartLevelManager.resumeBundles",
          "source": "StartLevelManager.java:573"
        },
        {
          "method": "org.eclipse.osgi.framework.internal.core.StartLevelManager.incFWSL",
          "source": "StartLevelManager.java:495"
        },
        {
          "method": "org.eclipse.osgi.framework.internal.core.StartLevelManager.doSetStartLevel",
          "source": "StartLevelManager.java:275"
        },
        {
          "method": "org.eclipse.osgi.framework.internal.core.StartLevelManager.dispatchEvent",
          "source": "StartLevelManager.java:455"
        },
        {
          "method": "org.eclipse.osgi.framework.eventmgr.EventManager.dispatchEvent",
          "source": "EventManager.java:189"
        },
        {
          "method": "org.eclipse.osgi.framework.eventmgr.EventManager$EventThread.run",
          "source": "EventManager.java:291"
        }
      ],
      "causedBy": {
        "exceptionType": "java.lang.Exception",
        "message": "Cannot initialize the Update Configurator",
        "elements": [
          {
            "method": "org.eclipse.update.internal.configurator.ConfigurationActivator.initialize",
            "source": "ConfigurationActivator.java:89"
          },
          {
            "method": "org.eclipse.update.internal.configurator.ConfigurationActivator.start",
            "source": "ConfigurationActivator.java:67"
          },
          {
            "method": "org.eclipse.osgi.framework.internal.core.BundleContextImpl$2.run",
            "source": "BundleContextImpl.java:994"
          },
          {
            "method": "java.security.AccessController.doPrivileged",
            "source": "Native Method"
          },
          {
            "method": "org.eclipse.osgi.framework.internal.core.BundleContextImpl.startActivator",
            "source": "BundleContextImpl.java:988"
          }
        ],
        "number": 0,
        "commentIndex": 0
      },
      "number": 2,
      "commentIndex": 0,
      "bugId": "131438",
      "date": "2006-03-11T21:10:45+01:00",
      "product": "Platform",
      "component": "Runtime",
      "severity": "minor"
    },
    {
      "exceptionType": "java.lang.Exception",
      "message": "Cannot initialize the Update Configurator",
      "elements": [
        {
          "method": "org.eclipse.update.internal.configurator.ConfigurationActivator.initialize",
          "source": "ConfigurationActivator.java:89"
        },
        {
          "method": "org.eclipse.update.internal.configurator.ConfigurationActivator.start",
          "source": "ConfigurationActivator.java:67"
        },
        {
          "method": "org.eclipse.osgi.framework.internal.core.BundleContextImpl$2.run",
          "source": "BundleContextImpl.java:994"
        },
        {
          "method": "java.security.AccessController.doPrivileged",
          "source": "Native Method"
        },
        {
          "method": "org.eclipse.osgi.framework.internal.core.BundleContextImpl.startActivator",
          "source": "BundleContextImpl.java:988"
        },
        {
          "method": "org.eclipse.osgi.framework.internal.core.BundleContextImpl.start",
          "source": "BundleContextImpl.java:969"
        },
        {
          "method": "org.eclipse.osgi.framework.internal.core.BundleHost.startWorker",
          "source": "BundleHost.java:314"
        },
        {
          "method": "org.eclipse.osgi.framework.internal.core.AbstractBundle.resume",
          "source": "AbstractBundle.java:329"
        },
        {
          "method": "org.eclipse.osgi.framework.internal.core.Framework.resumeBundle",
          "source": "Framework.java:1037"
        },
        {
          "method": "org.eclipse.osgi.framework.internal.core.StartLevelManager.resumeBundles",
          "source": "StartLevelManager.java:573"
        },
        {
          "method": "org.eclipse.osgi.framework.internal.core.StartLevelManager.incFWSL",
          "source": "StartLevelManager.java:495"
        },
        {
          "method": "org.eclipse.osgi.framework.internal.core.StartLevelManager.doSetStartLevel",
          "source": "StartLevelManager.java:275"
        },
        {
          "method": "org.eclipse.osgi.framework.internal.core.StartLevelManager.dispatchEvent",
          "source": "StartLevelManager.java:455"
        },
        {
          "method": "org.eclipse.osgi.framework.eventmgr.EventManager.dispatchEvent",
          "source": "EventManager.java:189"
        },
        {
          "method": "org.eclipse.osgi.framework.eventmgr.EventManager$EventThread.run",
          "source": "EventManager.java:291"
        }
      ],
      "number": 3,
      "commentIndex": 0,
      "bugId": "131438",
      "date": "2006-03-11T21:10:45+01:00",
      "product": "Platform",
      "component": "Runtime",
      "severity": "minor"
    },
    {
      "exceptionType": "java.lang.IllegalStateException",
      "message": "Bundle initial@reference:file:plugins/org.eclipse.core.runtime_3.2.0.v20060216.jar/ [7] is not active.",
      "elements": [
        {
          "method": "org.eclipse.core.runtime.adaptor.EclipseStarter.ensureBundlesActive",
          "source": "EclipseStarter.java:416"
        },
        {
          "method": "org.eclipse.core.runtime.adaptor.EclipseStarter.startup",
          "source": "EclipseStarter.java:303"
        },
        {
          "method": "org.eclipse.core.runtime.adaptor.EclipseStarter.run",
          "source": "EclipseStarter.java:165"
        },
        {
          "method": "sun.reflect.NativeMethodAccessorImpl.invoke0",
          "source": "Native Method"
        },
        {
          "method": "sun.reflect.NativeMethodAccessorImpl.invoke",
          "source": "Unknown Source"
        },
        {
          "method": "sun.reflect.DelegatingMethodAccessorImpl.invoke",
          "source": "Unknown Source"
        },
        {
          "method": "java.lang.reflect.Method.invoke",
          "source": "Unknown Source"
        },
        {
          "method": "org.eclipse.core.launcher.Main.invokeFramework",
          "source": "Main.java:338"
        },
        {
          "method": "org.eclipse.core.launcher.Main.basicRun",
          "source": "Main.java:282"
        },
        {
          "method": "org.eclipse.core.launcher.Main.run",
          "source": "Main.java:977"
        },
        {
          "method": "org.eclipse.core.launcher.Main.main",
          "source": "Main.java:952"
        }
      ],
      "number": 4,
      "commentIndex": 0,
      "bugId": "131438",
      "date": "2006-03-11T21:10:45+01:00",
      "product": "Platform",
      "component": "Runtime",
      "severity": "minor"
    }
  ],
  "groupId": "131438",
  "bugId": "131438",
  "date": "2006-03-11T21:10:45+01:00",
  "product": "Platform",
  "component": "Runtime",
  "severity": "minor"
}