{
  "comments": [
    "steps to reproduce:\n\n   - using command line example from BIRT runtime package\n   - type in \"genReport --mode runrender Sample(usingXMLDS).rptdesign\"\n\nexpected behavior:\n\n   - the html report is created without any error printed in console\n\nactual behavior: \n\n   - the html report was created with exceptions thrown out in console\n\norg.eclipse.birt.data.engine.odaconsumer.PreparedStateme\nnt doSetProperty\nWARNING: Cannot set statement property.\njava.lang.UnsupportedOperationException: IQuery.setProperty( String propertyName\n, String propertyValue )\n        at org.eclipse.datatools.connectivity.oda.consumer.helper.OdaObject.hand\nleUnsupportedOp(OdaObject.java:278)\n        at org.eclipse.datatools.connectivity.oda.consumer.helper.OdaQuery.setPr\noperty(OdaQuery.java:229)\n        at org.eclipse.birt.data.engine.odaconsumer.PreparedStatement.doSetPrope\nrty(PreparedStatement.java:154)\n        at org.eclipse.birt.data.engine.odaconsumer.PreparedStatement.setPropert\ny(PreparedStatement.java:136)\n        at org.eclipse.birt.data.engine.executor.DataSourceQuery.addProperties(D\nataSourceQuery.java:349)\n        at org.eclipse.birt.data.engine.executor.DataSourceQuery.prepare(DataSou\nrceQuery.java:304)\n        at org.eclipse.birt.data.engine.impl.PreparedExtendedDSQuery$ExtendedDSQ\nueryExecutor.prepareOdiQuery(PreparedExtendedDSQuery.java:277)\n        at org.eclipse.birt.data.engine.impl.PreparedQuery$Executor.prepareExecu\ntion(PreparedQuery.java:715)\n        at org.eclipse.birt.data.engine.impl.PreparedQuery$Executor.access$000(P\nreparedQuery.java:537)\n        at org.eclipse.birt.data.engine.impl.PreparedQuery.doPrepare(PreparedQue\nry.java:226)\n        at org.eclipse.birt.data.engine.impl.PreparedDataSourceQuery.execute(Pre\nparedDataSourceQuery.java:145)\n        at org.eclipse.birt.report.engine.data.dte.DteDataEngine.execute(DteData\nEngine.java:205)\n        at org.eclipse.birt.report.engine.executor.QueryItemExecutor.openResultS\net(QueryItemExecutor.java:62)\n        at org.eclipse.birt.report.engine.executor.TableItemExecutor.execute(Tab\nleItemExecutor.java:122)\n        at org.eclipse.birt.report.engine.executor.ReportExecutorVisitor.visitTa\nbleItem(ReportExecutorVisitor.java:188)\n        at org.eclipse.birt.report.engine.ir.TableItemDesign.accept(TableItemDes\nign.java:69)\n        at org.eclipse.birt.report.engine.executor.ReportExecutor.execute(Report\nExecutor.java:125)\n        at org.eclipse.birt.report.engine.executor.ReportExecutor.execute(Report\nExecutor.java:89)\n        at org.eclipse.birt.report.engine.api.impl.RunAndRenderTask.run(RunAndRe\nnderTask.java:175)\n        at org.eclipse.birt.report.engine.api.ReportRunner.runAndRenderReport(Re\nportRunner.java:232)\n        at org.eclipse.birt.report.engine.api.ReportRunner.execute(ReportRunner.\njava:158)\n        at org.eclipse.birt.report.engine.api.ReportRunner.main(ReportRunner.jav\na:129)\nMar 13, 2006 4:19:21 AM org.eclipse.birt.data.engine.odaconsumer.PreparedStateme\nnt doSetProperty\nWARNING: Cannot set statement property.\njava.lang.UnsupportedOperationException: IQuery.setProperty( String propertyName\n, String propertyValue )\n        at org.eclipse.datatools.connectivity.oda.consumer.helper.OdaObject.hand\nleUnsupportedOp(OdaObject.java:278)\n        at org.eclipse.datatools.connectivity.oda.consumer.helper.OdaQuery.setPr\noperty(OdaQuery.java:229)\n        at org.eclipse.birt.data.engine.odaconsumer.PreparedStatement.doSetPrope\nrty(PreparedStatement.java:154)\n        at org.eclipse.birt.data.engine.odaconsumer.PreparedStatement.setPropert\ny(PreparedStatement.java:136)\n        at org.eclipse.birt.data.engine.executor.DataSourceQuery.addProperties(D\nataSourceQuery.java:349)\n        at org.eclipse.birt.data.engine.executor.DataSourceQuery.prepare(DataSou\nrceQuery.java:304)\n        at org.eclipse.birt.data.engine.impl.PreparedExtendedDSQuery$ExtendedDSQ\nueryExecutor.prepareOdiQuery(PreparedExtendedDSQuery.java:277)\n        at org.eclipse.birt.data.engine.impl.PreparedQuery$Executor.prepareExecu\ntion(PreparedQuery.java:715)\n        at org.eclipse.birt.data.engine.impl.PreparedQuery$Executor.access$000(P\nreparedQuery.java:537)\n        at org.eclipse.birt.data.engine.impl.PreparedQuery.doPrepare(PreparedQue\nry.java:226)\n        at org.eclipse.birt.data.engine.impl.PreparedDataSourceQuery.execute(Pre\nparedDataSourceQuery.java:145)\n        at org.eclipse.birt.report.engine.data.dte.DteDataEngine.execute(DteData\nEngine.java:205)\n        at org.eclipse.birt.report.engine.executor.QueryItemExecutor.openResultS\net(QueryItemExecutor.java:62)\n        at org.eclipse.birt.report.engine.executor.TableItemExecutor.execute(Tab\nleItemExecutor.java:122)\n        at org.eclipse.birt.report.engine.executor.ReportExecutorVisitor.visitTa\nbleItem(ReportExecutorVisitor.java:188)\n        at org.eclipse.birt.report.engine.ir.TableItemDesign.accept(TableItemDes\nign.java:69)\n        at org.eclipse.birt.report.engine.executor.ReportExecutor.execute(Report\nExecutor.java:125)\n        at org.eclipse.birt.report.engine.executor.ReportExecutor.execute(Report\nExecutor.java:89)\n        at org.eclipse.birt.report.engine.api.impl.RunAndRenderTask.run(RunAndRe\nnderTask.java:175)\n        at org.eclipse.birt.report.engine.api.ReportRunner.runAndRenderReport(Re\nportRunner.java:232)\n        at org.eclipse.birt.report.engine.api.ReportRunner.execute(ReportRunner.\njava:158)\n        at org.eclipse.birt.report.engine.api.ReportRunner.main(ReportRunner.jav\na:129)\nMar 13, 2006 4:19:21 AM org.eclipse.birt.data.engine.odaconsumer.PreparedStateme\nnt doSetProperty\nWARNING: Cannot set statement property.\njava.lang.UnsupportedOperationException: IQuery.setProperty( String propertyName\n, String propertyValue )\n        at org.eclipse.datatools.connectivity.oda.consumer.helper.OdaObject.hand\nleUnsupportedOp(OdaObject.java:278)\n        at org.eclipse.datatools.connectivity.oda.consumer.helper.OdaQuery.setPr\noperty(OdaQuery.java:229)\n        at org.eclipse.birt.data.engine.odaconsumer.PreparedStatement.doSetPrope\nrty(PreparedStatement.java:154)\n        at org.eclipse.birt.data.engine.odaconsumer.PreparedStatement.setPropert\ny(PreparedStatement.java:136)\n        at org.eclipse.birt.data.engine.executor.DataSourceQuery.addProperties(D\nataSourceQuery.java:349)\n        at org.eclipse.birt.data.engine.executor.DataSourceQuery.prepare(DataSou\nrceQuery.java:304)\n        at org.eclipse.birt.data.engine.impl.PreparedExtendedDSQuery$ExtendedDSQ\nueryExecutor.prepareOdiQuery(PreparedExtendedDSQuery.java:277)\n        at org.eclipse.birt.data.engine.impl.PreparedQuery$Executor.prepareExecu\ntion(PreparedQuery.java:715)\n        at org.eclipse.birt.data.engine.impl.PreparedQuery$Executor.access$000(P\nreparedQuery.java:537)\n        at org.eclipse.birt.data.engine.impl.PreparedQuery.doPrepare(PreparedQue\nry.java:226)\n        at org.eclipse.birt.data.engine.impl.PreparedDataSourceQuery.execute(Pre\nparedDataSourceQuery.java:145)\n        at org.eclipse.birt.report.engine.data.dte.DteDataEngine.execute(DteData\nEngine.java:205)\n        at org.eclipse.birt.report.engine.executor.QueryItemExecutor.openResultS\net(QueryItemExecutor.java:62)\n        at org.eclipse.birt.report.engine.executor.TableItemExecutor.execute(Tab\nleItemExecutor.java:122)\n        at org.eclipse.birt.report.engine.executor.ReportExecutorVisitor.visitTa\nbleItem(ReportExecutorVisitor.java:188)\n        at org.eclipse.birt.report.engine.ir.TableItemDesign.accept(TableItemDes\nign.java:69)\n\nC:\\xiangli\\birt-runtime-2.1M5\\CommandLineExample\u003egenReport --mode runrender Samp\nle(usingXMLDS).rptdesign\n\nC:\\xiangli\\birt-runtime-2.1M5\\CommandLineExample\u003eECHO off\nMar 13, 2006 4:23:57 AM org.eclipse.birt.data.engine.odaconsumer.PreparedStateme\nnt doSetProperty\nWARNING: Cannot set statement property.\njava.lang.UnsupportedOperationException: IQuery.setProperty( String propertyName\n, String propertyValue )\n        at org.eclipse.datatools.connectivity.oda.consumer.helper.OdaObject.hand\nleUnsupportedOp(OdaObject.java:278)\n        at org.eclipse.datatools.connectivity.oda.consumer.helper.OdaQuery.setPr\noperty(OdaQuery.java:229)\n        at org.eclipse.birt.data.engine.odaconsumer.PreparedStatement.doSetPrope\nrty(PreparedStatement.java:154)\n        at org.eclipse.birt.data.engine.odaconsumer.PreparedStatement.setPropert\ny(PreparedStatement.java:136)\n        at org.eclipse.birt.data.engine.executor.DataSourceQuery.addProperties(D\nataSourceQuery.java:349)\n        at org.eclipse.birt.data.engine.executor.DataSourceQuery.prepare(DataSou\nrceQuery.java:304)\n        at org.eclipse.birt.data.engine.impl.PreparedExtendedDSQuery$ExtendedDSQ\nueryExecutor.prepareOdiQuery(PreparedExtendedDSQuery.java:277)\n        at org.eclipse.birt.data.engine.impl.PreparedQuery$Executor.prepareExecu\ntion(PreparedQuery.java:715)\n        at org.eclipse.birt.data.engine.impl.PreparedQuery$Executor.access$000(P\nreparedQuery.java:537)\n        at org.eclipse.birt.data.engine.impl.PreparedQuery.doPrepare(PreparedQue\nry.java:226)\n        at org.eclipse.birt.data.engine.impl.PreparedDataSourceQuery.execute(Pre\nparedDataSourceQuery.java:145)\n        at org.eclipse.birt.report.engine.data.dte.DteDataEngine.execute(DteData\nEngine.java:205)\n        at org.eclipse.birt.report.engine.executor.QueryItemExecutor.openResultS\net(QueryItemExecutor.java:62)\n        at org.eclipse.birt.report.engine.executor.TableItemExecutor.execute(Tab\nleItemExecutor.java:122)\n        at org.eclipse.birt.report.engine.executor.ReportExecutorVisitor.visitTa\nbleItem(ReportExecutorVisitor.java:188)\n        at org.eclipse.birt.report.engine.ir.TableItemDesign.accept(TableItemDes\nign.java:69)\n        at org.eclipse.birt.report.engine.executor.ReportExecutor.execute(Report\nExecutor.java:125)\n        at org.eclipse.birt.report.engine.executor.ReportExecutor.execute(Report\nExecutor.java:89)\n        at org.eclipse.birt.report.engine.api.impl.RunAndRenderTask.run(RunAndRe\nnderTask.java:175)\n        at org.eclipse.birt.report.engine.api.ReportRunner.runAndRenderReport(Re\nportRunner.java:232)\n        at org.eclipse.birt.report.engine.api.ReportRunner.execute(ReportRunner.\njava:158)\n        at org.eclipse.birt.report.engine.api.ReportRunner.main(ReportRunner.jav\na:129)\nMar 13, 2006 4:23:57 AM org.eclipse.birt.data.engine.odaconsumer.PreparedStateme\nnt doSetProperty\nWARNING: Cannot set statement property.\njava.lang.UnsupportedOperationException: IQuery.setProperty( String propertyName\n, String propertyValue )\n        at org.eclipse.datatools.connectivity.oda.consumer.helper.OdaObject.hand\nleUnsupportedOp(OdaObject.java:278)\n        at org.eclipse.datatools.connectivity.oda.consumer.helper.OdaQuery.setPr\noperty(OdaQuery.java:229)\n        at org.eclipse.birt.data.engine.odaconsumer.PreparedStatement.doSetPrope\nrty(PreparedStatement.java:154)\n        at org.eclipse.birt.data.engine.odaconsumer.PreparedStatement.setPropert\ny(PreparedStatement.java:136)\n        at org.eclipse.birt.data.engine.executor.DataSourceQuery.addProperties(D\nataSourceQuery.java:349)\n        at org.eclipse.birt.data.engine.executor.DataSourceQuery.prepare(DataSou\nrceQuery.java:304)\n        at org.eclipse.birt.data.engine.impl.PreparedExtendedDSQuery$ExtendedDSQ\nueryExecutor.prepareOdiQuery(PreparedExtendedDSQuery.java:277)\n        at org.eclipse.birt.data.engine.impl.PreparedQuery$Executor.prepareExecu\ntion(PreparedQuery.java:715)\n        at org.eclipse.birt.data.engine.impl.PreparedQuery$Executor.access$000(P\nreparedQuery.java:537)\n        at org.eclipse.birt.data.engine.impl.PreparedQuery.doPrepare(PreparedQue\nry.java:226)\n        at org.eclipse.birt.data.engine.impl.PreparedDataSourceQuery.execute(Pre\nparedDataSourceQuery.java:145)\n        at org.eclipse.birt.report.engine.data.dte.DteDataEngine.execute(DteData\nEngine.java:205)\n        at org.eclipse.birt.report.engine.executor.QueryItemExecutor.openResultS\net(QueryItemExecutor.java:62)\n        at org.eclipse.birt.report.engine.executor.TableItemExecutor.execute(Tab\nleItemExecutor.java:122)\n        at org.eclipse.birt.report.engine.executor.ReportExecutorVisitor.visitTa\nbleItem(ReportExecutorVisitor.java:188)\n        at org.eclipse.birt.report.engine.ir.TableItemDesign.accept(TableItemDes\nign.java:69)\n        at org.eclipse.birt.report.engine.executor.ReportExecutor.execute(Report\nExecutor.java:125)\n        at org.eclipse.birt.report.engine.executor.ReportExecutor.execute(Report\nExecutor.java:89)\n        at org.eclipse.birt.report.engine.api.impl.RunAndRenderTask.run(RunAndRe\nnderTask.java:175)\n        at org.eclipse.birt.report.engine.api.ReportRunner.runAndRenderReport(Re\nportRunner.java:232)\n        at org.eclipse.birt.report.engine.api.ReportRunner.execute(ReportRunner.\njava:158)\n        at org.eclipse.birt.report.engine.api.ReportRunner.main(ReportRunner.jav\na:129)\nMar 13, 2006 4:23:57 AM org.eclipse.birt.data.engine.odaconsumer.PreparedStateme\nnt doSetProperty\nWARNING: Cannot set statement property.\njava.lang.UnsupportedOperationException: IQuery.setProperty( String propertyName\n, String propertyValue )\n        at org.eclipse.datatools.connectivity.oda.consumer.helper.OdaObject.hand\nleUnsupportedOp(OdaObject.java:278)\n        at org.eclipse.datatools.connectivity.oda.consumer.helper.OdaQuery.setPr\noperty(OdaQuery.java:229)\n        at org.eclipse.birt.data.engine.odaconsumer.PreparedStatement.doSetPrope\nrty(PreparedStatement.java:154)\n        at org.eclipse.birt.data.engine.odaconsumer.PreparedStatement.setPropert\ny(PreparedStatement.java:136)\n        at org.eclipse.birt.data.engine.executor.DataSourceQuery.addProperties(D\nataSourceQuery.java:349)\n        at org.eclipse.birt.data.engine.executor.DataSourceQuery.prepare(DataSou\nrceQuery.java:304)\n        at org.eclipse.birt.data.engine.impl.PreparedExtendedDSQuery$ExtendedDSQ\nueryExecutor.prepareOdiQuery(PreparedExtendedDSQuery.java:277)\n        at org.eclipse.birt.data.engine.impl.PreparedQuery$Executor.prepareExecu\ntion(PreparedQuery.java:715)\n        at org.eclipse.birt.data.engine.impl.PreparedQuery$Executor.access$000(P\nreparedQuery.java:537)\n        at org.eclipse.birt.data.engine.impl.PreparedQuery.doPrepare(PreparedQue\nry.java:226)\n        at org.eclipse.birt.data.engine.impl.PreparedDataSourceQuery.execute(Pre\nparedDataSourceQuery.java:145)\n        at org.eclipse.birt.report.engine.data.dte.DteDataEngine.execute(DteData\nEngine.java:205)\n        at org.eclipse.birt.report.engine.executor.QueryItemExecutor.openResultS\net(QueryItemExecutor.java:62)\n        at org.eclipse.birt.report.engine.executor.TableItemExecutor.execute(Tab\nleItemExecutor.java:122)\n        at org.eclipse.birt.report.engine.executor.ReportExecutorVisitor.visitTa\nbleItem(ReportExecutorVisitor.java:188)\n        at org.eclipse.birt.report.engine.ir.TableItemDesign.accept(TableItemDes\nign.java:69)\n        at org.eclipse.birt.report.engine.executor.ReportExecutor.execute(Report\nExecutor.java:125)\n        at org.eclipse.birt.report.engine.executor.ReportExecutor.execute(Report\nExecutor.java:89)\n        at org.eclipse.birt.report.engine.api.impl.RunAndRenderTask.run(RunAndRe\nnderTask.java:175)\n        at org.eclipse.birt.report.engine.api.ReportRunner.runAndRenderReport(Re\nportRunner.java:232)\n        at org.eclipse.birt.report.engine.api.ReportRunner.execute(ReportRunner.\njava:158)\n        at org.eclipse.birt.report.engine.api.ReportRunner.main(ReportRunner.jav\na:129)\nMar 13, 2006 4:23:57 AM org.eclipse.birt.data.engine.odaconsumer.PreparedStateme\nnt doSetProperty\nWARNING: Cannot set statement property.\njava.lang.UnsupportedOperationException: IQuery.setProperty( String propertyName\n, String propertyValue )\n        at org.eclipse.datatools.connectivity.oda.consumer.helper.OdaObject.hand\nleUnsupportedOp(OdaObject.java:278)\n        at org.eclipse.datatools.connectivity.oda.consumer.helper.OdaQuery.setPr\noperty(OdaQuery.java:229)\n        at org.eclipse.birt.data.engine.odaconsumer.PreparedStatement.doSetPrope\nrty(PreparedStatement.java:154)\n        at org.eclipse.birt.data.engine.odaconsumer.PreparedStatement.setPropert\ny(PreparedStatement.java:136)\n        at org.eclipse.birt.data.engine.executor.DataSourceQuery.addProperties(D\nataSourceQuery.java:349)\n        at org.eclipse.birt.data.engine.executor.DataSourceQuery.prepare(DataSou\nrceQuery.java:304)\n        at org.eclipse.birt.data.engine.impl.PreparedExtendedDSQuery$ExtendedDSQ\nueryExecutor.prepareOdiQuery(PreparedExtendedDSQuery.java:277)\n        at org.eclipse.birt.data.engine.impl.PreparedQuery$Executor.prepareExecu\ntion(PreparedQuery.java:715)\n        at org.eclipse.birt.data.engine.impl.PreparedQuery$Executor.access$000(P\nreparedQuery.java:537)\n        at org.eclipse.birt.data.engine.impl.PreparedQuery.doPrepare(PreparedQue\nry.java:226)\n        at org.eclipse.birt.data.engine.impl.PreparedDataSourceQuery.execute(Pre\nparedDataSourceQuery.java:145)\n        at org.eclipse.birt.report.engine.data.dte.DteDataEngine.execute(DteData\nEngine.java:205)\n        at org.eclipse.birt.report.engine.executor.QueryItemExecutor.openResultS\net(QueryItemExecutor.java:62)\n        at org.eclipse.birt.report.engine.executor.TableItemExecutor.execute(Tab\nleItemExecutor.java:122)\n        at org.eclipse.birt.report.engine.executor.ReportExecutorVisitor.visitTa\nbleItem(ReportExecutorVisitor.java:188)\n        at org.eclipse.birt.report.engine.ir.TableItemDesign.accept(TableItemDes\nign.java:69)\n        at org.eclipse.birt.report.engine.executor.ReportExecutor.execute(Report\nExecutor.java:125)\n        at org.eclipse.birt.report.engine.executor.ReportExecutor.execute(Report\nExecutor.java:89)\n        at org.eclipse.birt.report.engine.api.impl.RunAndRenderTask.run(RunAndRe\nnderTask.java:175)\n        at org.eclipse.birt.report.engine.api.ReportRunner.runAndRenderReport(Re\nportRunner.java:232)\n        at org.eclipse.birt.report.engine.api.ReportRunner.execute(ReportRunner.\njava:158)\n        at org.eclipse.birt.report.engine.api.ReportRunner.main(ReportRunner.jav\na:129)",
    "Created an attachment (id\u003d36125)\nthe report design\n\n",
    "Created an attachment (id\u003d36126)\nthe data source\n\n",
    "Fixed.",
    "Verified, 20060411"
  ],
  "commentCreationDates": [
    "2006-03-13T12:25:51+01:00",
    "2006-03-13T12:28:21+01:00",
    "2006-03-13T12:29:06+01:00",
    "2006-03-14T11:24:36+01:00",
    "2006-04-11T07:39:48+02:00"
  ],
  "traces": [
    {
      "exceptionType": "java.lang.UnsupportedOperationException",
      "message": "IQuery.setProperty( String propertyName , String propertyValue )",
      "elements": [
        {
          "method": "org.eclipse.datatools.connectivity.oda.consumer.helper.OdaObject.handleUnsupportedOp",
          "source": "OdaObject.java:278"
        },
        {
          "method": "org.eclipse.datatools.connectivity.oda.consumer.helper.OdaQuery.setProperty",
          "source": "OdaQuery.java:229"
        },
        {
          "method": "org.eclipse.birt.data.engine.odaconsumer.PreparedStatement.doSetProperty",
          "source": "PreparedStatement.java:154"
        },
        {
          "method": "org.eclipse.birt.data.engine.odaconsumer.PreparedStatement.setProperty",
          "source": "PreparedStatement.java:136"
        },
        {
          "method": "org.eclipse.birt.data.engine.executor.DataSourceQuery.addProperties",
          "source": "D ataSourceQuery.java:349"
        },
        {
          "method": "org.eclipse.birt.data.engine.executor.DataSourceQuery.prepare",
          "source": "DataSou rceQuery.java:304"
        },
        {
          "method": "org.eclipse.birt.data.engine.impl.PreparedExtendedDSQuery$ExtendedDSQueryExecutor.prepareOdiQuery",
          "source": "PreparedExtendedDSQuery.java:277"
        },
        {
          "method": "org.eclipse.birt.data.engine.impl.PreparedQuery$Executor.prepareExecution",
          "source": "PreparedQuery.java:715"
        },
        {
          "method": "org.eclipse.birt.data.engine.impl.PreparedQuery$Executor.access$000",
          "source": "P reparedQuery.java:537"
        },
        {
          "method": "org.eclipse.birt.data.engine.impl.PreparedQuery.doPrepare",
          "source": "PreparedQue ry.java:226"
        },
        {
          "method": "org.eclipse.birt.data.engine.impl.PreparedDataSourceQuery.execute",
          "source": "Pre paredDataSourceQuery.java:145"
        },
        {
          "method": "org.eclipse.birt.report.engine.data.dte.DteDataEngine.execute",
          "source": "DteData Engine.java:205"
        },
        {
          "method": "org.eclipse.birt.report.engine.executor.QueryItemExecutor.openResultSet",
          "source": "QueryItemExecutor.java:62"
        },
        {
          "method": "org.eclipse.birt.report.engine.executor.TableItemExecutor.execute",
          "source": "Tab leItemExecutor.java:122"
        },
        {
          "method": "org.eclipse.birt.report.engine.executor.ReportExecutorVisitor.visitTableItem",
          "source": "ReportExecutorVisitor.java:188"
        },
        {
          "method": "org.eclipse.birt.report.engine.ir.TableItemDesign.accept",
          "source": "TableItemDes ign.java:69"
        },
        {
          "method": "org.eclipse.birt.report.engine.executor.ReportExecutor.execute",
          "source": "Report Executor.java:125"
        },
        {
          "method": "org.eclipse.birt.report.engine.executor.ReportExecutor.execute",
          "source": "Report Executor.java:89"
        },
        {
          "method": "org.eclipse.birt.report.engine.api.impl.RunAndRenderTask.run",
          "source": "RunAndRe nderTask.java:175"
        },
        {
          "method": "org.eclipse.birt.report.engine.api.ReportRunner.runAndRenderReport",
          "source": "Re portRunner.java:232"
        },
        {
          "method": "org.eclipse.birt.report.engine.api.ReportRunner.execute",
          "source": "ReportRunner. java:158"
        },
        {
          "method": "org.eclipse.birt.report.engine.api.ReportRunner.main",
          "source": "ReportRunner.jav a:129"
        }
      ],
      "number": 0,
      "commentIndex": 0,
      "bugId": "131511",
      "date": "2006-03-13T12:25:51+01:00",
      "product": "BIRT",
      "component": "Data",
      "severity": "normal"
    },
    {
      "exceptionType": "java.lang.UnsupportedOperationException",
      "message": "IQuery.setProperty( String propertyName , String propertyValue )",
      "elements": [
        {
          "method": "org.eclipse.datatools.connectivity.oda.consumer.helper.OdaObject.handleUnsupportedOp",
          "source": "OdaObject.java:278"
        },
        {
          "method": "org.eclipse.datatools.connectivity.oda.consumer.helper.OdaQuery.setProperty",
          "source": "OdaQuery.java:229"
        },
        {
          "method": "org.eclipse.birt.data.engine.odaconsumer.PreparedStatement.doSetProperty",
          "source": "PreparedStatement.java:154"
        },
        {
          "method": "org.eclipse.birt.data.engine.odaconsumer.PreparedStatement.setProperty",
          "source": "PreparedStatement.java:136"
        },
        {
          "method": "org.eclipse.birt.data.engine.executor.DataSourceQuery.addProperties",
          "source": "D ataSourceQuery.java:349"
        },
        {
          "method": "org.eclipse.birt.data.engine.executor.DataSourceQuery.prepare",
          "source": "DataSou rceQuery.java:304"
        },
        {
          "method": "org.eclipse.birt.data.engine.impl.PreparedExtendedDSQuery$ExtendedDSQueryExecutor.prepareOdiQuery",
          "source": "PreparedExtendedDSQuery.java:277"
        },
        {
          "method": "org.eclipse.birt.data.engine.impl.PreparedQuery$Executor.prepareExecution",
          "source": "PreparedQuery.java:715"
        },
        {
          "method": "org.eclipse.birt.data.engine.impl.PreparedQuery$Executor.access$000",
          "source": "P reparedQuery.java:537"
        },
        {
          "method": "org.eclipse.birt.data.engine.impl.PreparedQuery.doPrepare",
          "source": "PreparedQue ry.java:226"
        },
        {
          "method": "org.eclipse.birt.data.engine.impl.PreparedDataSourceQuery.execute",
          "source": "Pre paredDataSourceQuery.java:145"
        },
        {
          "method": "org.eclipse.birt.report.engine.data.dte.DteDataEngine.execute",
          "source": "DteData Engine.java:205"
        },
        {
          "method": "org.eclipse.birt.report.engine.executor.QueryItemExecutor.openResultSet",
          "source": "QueryItemExecutor.java:62"
        },
        {
          "method": "org.eclipse.birt.report.engine.executor.TableItemExecutor.execute",
          "source": "Tab leItemExecutor.java:122"
        },
        {
          "method": "org.eclipse.birt.report.engine.executor.ReportExecutorVisitor.visitTableItem",
          "source": "ReportExecutorVisitor.java:188"
        },
        {
          "method": "org.eclipse.birt.report.engine.ir.TableItemDesign.accept",
          "source": "TableItemDes ign.java:69"
        },
        {
          "method": "org.eclipse.birt.report.engine.executor.ReportExecutor.execute",
          "source": "Report Executor.java:125"
        },
        {
          "method": "org.eclipse.birt.report.engine.executor.ReportExecutor.execute",
          "source": "Report Executor.java:89"
        },
        {
          "method": "org.eclipse.birt.report.engine.api.impl.RunAndRenderTask.run",
          "source": "RunAndRe nderTask.java:175"
        },
        {
          "method": "org.eclipse.birt.report.engine.api.ReportRunner.runAndRenderReport",
          "source": "Re portRunner.java:232"
        },
        {
          "method": "org.eclipse.birt.report.engine.api.ReportRunner.execute",
          "source": "ReportRunner. java:158"
        },
        {
          "method": "org.eclipse.birt.report.engine.api.ReportRunner.main",
          "source": "ReportRunner.jav a:129"
        }
      ],
      "number": 1,
      "commentIndex": 0,
      "bugId": "131511",
      "date": "2006-03-13T12:25:51+01:00",
      "product": "BIRT",
      "component": "Data",
      "severity": "normal"
    },
    {
      "exceptionType": "java.lang.UnsupportedOperationException",
      "message": "IQuery.setProperty( String propertyName , String propertyValue )",
      "elements": [
        {
          "method": "org.eclipse.datatools.connectivity.oda.consumer.helper.OdaObject.handleUnsupportedOp",
          "source": "OdaObject.java:278"
        },
        {
          "method": "org.eclipse.datatools.connectivity.oda.consumer.helper.OdaQuery.setProperty",
          "source": "OdaQuery.java:229"
        },
        {
          "method": "org.eclipse.birt.data.engine.odaconsumer.PreparedStatement.doSetProperty",
          "source": "PreparedStatement.java:154"
        },
        {
          "method": "org.eclipse.birt.data.engine.odaconsumer.PreparedStatement.setProperty",
          "source": "PreparedStatement.java:136"
        },
        {
          "method": "org.eclipse.birt.data.engine.executor.DataSourceQuery.addProperties",
          "source": "D ataSourceQuery.java:349"
        },
        {
          "method": "org.eclipse.birt.data.engine.executor.DataSourceQuery.prepare",
          "source": "DataSou rceQuery.java:304"
        },
        {
          "method": "org.eclipse.birt.data.engine.impl.PreparedExtendedDSQuery$ExtendedDSQueryExecutor.prepareOdiQuery",
          "source": "PreparedExtendedDSQuery.java:277"
        },
        {
          "method": "org.eclipse.birt.data.engine.impl.PreparedQuery$Executor.prepareExecution",
          "source": "PreparedQuery.java:715"
        },
        {
          "method": "org.eclipse.birt.data.engine.impl.PreparedQuery$Executor.access$000",
          "source": "P reparedQuery.java:537"
        },
        {
          "method": "org.eclipse.birt.data.engine.impl.PreparedQuery.doPrepare",
          "source": "PreparedQue ry.java:226"
        },
        {
          "method": "org.eclipse.birt.data.engine.impl.PreparedDataSourceQuery.execute",
          "source": "Pre paredDataSourceQuery.java:145"
        },
        {
          "method": "org.eclipse.birt.report.engine.data.dte.DteDataEngine.execute",
          "source": "DteData Engine.java:205"
        },
        {
          "method": "org.eclipse.birt.report.engine.executor.QueryItemExecutor.openResultSet",
          "source": "QueryItemExecutor.java:62"
        },
        {
          "method": "org.eclipse.birt.report.engine.executor.TableItemExecutor.execute",
          "source": "Tab leItemExecutor.java:122"
        },
        {
          "method": "org.eclipse.birt.report.engine.executor.ReportExecutorVisitor.visitTableItem",
          "source": "ReportExecutorVisitor.java:188"
        },
        {
          "method": "org.eclipse.birt.report.engine.ir.TableItemDesign.accept",
          "source": "TableItemDes ign.java:69"
        }
      ],
      "number": 2,
      "commentIndex": 0,
      "bugId": "131511",
      "date": "2006-03-13T12:25:51+01:00",
      "product": "BIRT",
      "component": "Data",
      "severity": "normal"
    },
    {
      "exceptionType": "java.lang.UnsupportedOperationException",
      "message": "IQuery.setProperty( String propertyName , String propertyValue )",
      "elements": [
        {
          "method": "org.eclipse.datatools.connectivity.oda.consumer.helper.OdaObject.handleUnsupportedOp",
          "source": "OdaObject.java:278"
        },
        {
          "method": "org.eclipse.datatools.connectivity.oda.consumer.helper.OdaQuery.setProperty",
          "source": "OdaQuery.java:229"
        },
        {
          "method": "org.eclipse.birt.data.engine.odaconsumer.PreparedStatement.doSetProperty",
          "source": "PreparedStatement.java:154"
        },
        {
          "method": "org.eclipse.birt.data.engine.odaconsumer.PreparedStatement.setProperty",
          "source": "PreparedStatement.java:136"
        },
        {
          "method": "org.eclipse.birt.data.engine.executor.DataSourceQuery.addProperties",
          "source": "D ataSourceQuery.java:349"
        },
        {
          "method": "org.eclipse.birt.data.engine.executor.DataSourceQuery.prepare",
          "source": "DataSou rceQuery.java:304"
        },
        {
          "method": "org.eclipse.birt.data.engine.impl.PreparedExtendedDSQuery$ExtendedDSQueryExecutor.prepareOdiQuery",
          "source": "PreparedExtendedDSQuery.java:277"
        },
        {
          "method": "org.eclipse.birt.data.engine.impl.PreparedQuery$Executor.prepareExecution",
          "source": "PreparedQuery.java:715"
        },
        {
          "method": "org.eclipse.birt.data.engine.impl.PreparedQuery$Executor.access$000",
          "source": "P reparedQuery.java:537"
        },
        {
          "method": "org.eclipse.birt.data.engine.impl.PreparedQuery.doPrepare",
          "source": "PreparedQue ry.java:226"
        },
        {
          "method": "org.eclipse.birt.data.engine.impl.PreparedDataSourceQuery.execute",
          "source": "Pre paredDataSourceQuery.java:145"
        },
        {
          "method": "org.eclipse.birt.report.engine.data.dte.DteDataEngine.execute",
          "source": "DteData Engine.java:205"
        },
        {
          "method": "org.eclipse.birt.report.engine.executor.QueryItemExecutor.openResultSet",
          "source": "QueryItemExecutor.java:62"
        },
        {
          "method": "org.eclipse.birt.report.engine.executor.TableItemExecutor.execute",
          "source": "Tab leItemExecutor.java:122"
        },
        {
          "method": "org.eclipse.birt.report.engine.executor.ReportExecutorVisitor.visitTableItem",
          "source": "ReportExecutorVisitor.java:188"
        },
        {
          "method": "org.eclipse.birt.report.engine.ir.TableItemDesign.accept",
          "source": "TableItemDes ign.java:69"
        },
        {
          "method": "org.eclipse.birt.report.engine.executor.ReportExecutor.execute",
          "source": "Report Executor.java:125"
        },
        {
          "method": "org.eclipse.birt.report.engine.executor.ReportExecutor.execute",
          "source": "Report Executor.java:89"
        },
        {
          "method": "org.eclipse.birt.report.engine.api.impl.RunAndRenderTask.run",
          "source": "RunAndRe nderTask.java:175"
        },
        {
          "method": "org.eclipse.birt.report.engine.api.ReportRunner.runAndRenderReport",
          "source": "Re portRunner.java:232"
        },
        {
          "method": "org.eclipse.birt.report.engine.api.ReportRunner.execute",
          "source": "ReportRunner. java:158"
        },
        {
          "method": "org.eclipse.birt.report.engine.api.ReportRunner.main",
          "source": "ReportRunner.jav a:129"
        }
      ],
      "number": 3,
      "commentIndex": 0,
      "bugId": "131511",
      "date": "2006-03-13T12:25:51+01:00",
      "product": "BIRT",
      "component": "Data",
      "severity": "normal"
    },
    {
      "exceptionType": "java.lang.UnsupportedOperationException",
      "message": "IQuery.setProperty( String propertyName , String propertyValue )",
      "elements": [
        {
          "method": "org.eclipse.datatools.connectivity.oda.consumer.helper.OdaObject.handleUnsupportedOp",
          "source": "OdaObject.java:278"
        },
        {
          "method": "org.eclipse.datatools.connectivity.oda.consumer.helper.OdaQuery.setProperty",
          "source": "OdaQuery.java:229"
        },
        {
          "method": "org.eclipse.birt.data.engine.odaconsumer.PreparedStatement.doSetProperty",
          "source": "PreparedStatement.java:154"
        },
        {
          "method": "org.eclipse.birt.data.engine.odaconsumer.PreparedStatement.setProperty",
          "source": "PreparedStatement.java:136"
        },
        {
          "method": "org.eclipse.birt.data.engine.executor.DataSourceQuery.addProperties",
          "source": "D ataSourceQuery.java:349"
        },
        {
          "method": "org.eclipse.birt.data.engine.executor.DataSourceQuery.prepare",
          "source": "DataSou rceQuery.java:304"
        },
        {
          "method": "org.eclipse.birt.data.engine.impl.PreparedExtendedDSQuery$ExtendedDSQueryExecutor.prepareOdiQuery",
          "source": "PreparedExtendedDSQuery.java:277"
        },
        {
          "method": "org.eclipse.birt.data.engine.impl.PreparedQuery$Executor.prepareExecution",
          "source": "PreparedQuery.java:715"
        },
        {
          "method": "org.eclipse.birt.data.engine.impl.PreparedQuery$Executor.access$000",
          "source": "P reparedQuery.java:537"
        },
        {
          "method": "org.eclipse.birt.data.engine.impl.PreparedQuery.doPrepare",
          "source": "PreparedQue ry.java:226"
        },
        {
          "method": "org.eclipse.birt.data.engine.impl.PreparedDataSourceQuery.execute",
          "source": "Pre paredDataSourceQuery.java:145"
        },
        {
          "method": "org.eclipse.birt.report.engine.data.dte.DteDataEngine.execute",
          "source": "DteData Engine.java:205"
        },
        {
          "method": "org.eclipse.birt.report.engine.executor.QueryItemExecutor.openResultSet",
          "source": "QueryItemExecutor.java:62"
        },
        {
          "method": "org.eclipse.birt.report.engine.executor.TableItemExecutor.execute",
          "source": "Tab leItemExecutor.java:122"
        },
        {
          "method": "org.eclipse.birt.report.engine.executor.ReportExecutorVisitor.visitTableItem",
          "source": "ReportExecutorVisitor.java:188"
        },
        {
          "method": "org.eclipse.birt.report.engine.ir.TableItemDesign.accept",
          "source": "TableItemDes ign.java:69"
        },
        {
          "method": "org.eclipse.birt.report.engine.executor.ReportExecutor.execute",
          "source": "Report Executor.java:125"
        },
        {
          "method": "org.eclipse.birt.report.engine.executor.ReportExecutor.execute",
          "source": "Report Executor.java:89"
        },
        {
          "method": "org.eclipse.birt.report.engine.api.impl.RunAndRenderTask.run",
          "source": "RunAndRe nderTask.java:175"
        },
        {
          "method": "org.eclipse.birt.report.engine.api.ReportRunner.runAndRenderReport",
          "source": "Re portRunner.java:232"
        },
        {
          "method": "org.eclipse.birt.report.engine.api.ReportRunner.execute",
          "source": "ReportRunner. java:158"
        },
        {
          "method": "org.eclipse.birt.report.engine.api.ReportRunner.main",
          "source": "ReportRunner.jav a:129"
        }
      ],
      "number": 4,
      "commentIndex": 0,
      "bugId": "131511",
      "date": "2006-03-13T12:25:51+01:00",
      "product": "BIRT",
      "component": "Data",
      "severity": "normal"
    },
    {
      "exceptionType": "java.lang.UnsupportedOperationException",
      "message": "IQuery.setProperty( String propertyName , String propertyValue )",
      "elements": [
        {
          "method": "org.eclipse.datatools.connectivity.oda.consumer.helper.OdaObject.handleUnsupportedOp",
          "source": "OdaObject.java:278"
        },
        {
          "method": "org.eclipse.datatools.connectivity.oda.consumer.helper.OdaQuery.setProperty",
          "source": "OdaQuery.java:229"
        },
        {
          "method": "org.eclipse.birt.data.engine.odaconsumer.PreparedStatement.doSetProperty",
          "source": "PreparedStatement.java:154"
        },
        {
          "method": "org.eclipse.birt.data.engine.odaconsumer.PreparedStatement.setProperty",
          "source": "PreparedStatement.java:136"
        },
        {
          "method": "org.eclipse.birt.data.engine.executor.DataSourceQuery.addProperties",
          "source": "D ataSourceQuery.java:349"
        },
        {
          "method": "org.eclipse.birt.data.engine.executor.DataSourceQuery.prepare",
          "source": "DataSou rceQuery.java:304"
        },
        {
          "method": "org.eclipse.birt.data.engine.impl.PreparedExtendedDSQuery$ExtendedDSQueryExecutor.prepareOdiQuery",
          "source": "PreparedExtendedDSQuery.java:277"
        },
        {
          "method": "org.eclipse.birt.data.engine.impl.PreparedQuery$Executor.prepareExecution",
          "source": "PreparedQuery.java:715"
        },
        {
          "method": "org.eclipse.birt.data.engine.impl.PreparedQuery$Executor.access$000",
          "source": "P reparedQuery.java:537"
        },
        {
          "method": "org.eclipse.birt.data.engine.impl.PreparedQuery.doPrepare",
          "source": "PreparedQue ry.java:226"
        },
        {
          "method": "org.eclipse.birt.data.engine.impl.PreparedDataSourceQuery.execute",
          "source": "Pre paredDataSourceQuery.java:145"
        },
        {
          "method": "org.eclipse.birt.report.engine.data.dte.DteDataEngine.execute",
          "source": "DteData Engine.java:205"
        },
        {
          "method": "org.eclipse.birt.report.engine.executor.QueryItemExecutor.openResultSet",
          "source": "QueryItemExecutor.java:62"
        },
        {
          "method": "org.eclipse.birt.report.engine.executor.TableItemExecutor.execute",
          "source": "Tab leItemExecutor.java:122"
        },
        {
          "method": "org.eclipse.birt.report.engine.executor.ReportExecutorVisitor.visitTableItem",
          "source": "ReportExecutorVisitor.java:188"
        },
        {
          "method": "org.eclipse.birt.report.engine.ir.TableItemDesign.accept",
          "source": "TableItemDes ign.java:69"
        },
        {
          "method": "org.eclipse.birt.report.engine.executor.ReportExecutor.execute",
          "source": "Report Executor.java:125"
        },
        {
          "method": "org.eclipse.birt.report.engine.executor.ReportExecutor.execute",
          "source": "Report Executor.java:89"
        },
        {
          "method": "org.eclipse.birt.report.engine.api.impl.RunAndRenderTask.run",
          "source": "RunAndRe nderTask.java:175"
        },
        {
          "method": "org.eclipse.birt.report.engine.api.ReportRunner.runAndRenderReport",
          "source": "Re portRunner.java:232"
        },
        {
          "method": "org.eclipse.birt.report.engine.api.ReportRunner.execute",
          "source": "ReportRunner. java:158"
        },
        {
          "method": "org.eclipse.birt.report.engine.api.ReportRunner.main",
          "source": "ReportRunner.jav a:129"
        }
      ],
      "number": 5,
      "commentIndex": 0,
      "bugId": "131511",
      "date": "2006-03-13T12:25:51+01:00",
      "product": "BIRT",
      "component": "Data",
      "severity": "normal"
    },
    {
      "exceptionType": "java.lang.UnsupportedOperationException",
      "message": "IQuery.setProperty( String propertyName , String propertyValue )",
      "elements": [
        {
          "method": "org.eclipse.datatools.connectivity.oda.consumer.helper.OdaObject.handleUnsupportedOp",
          "source": "OdaObject.java:278"
        },
        {
          "method": "org.eclipse.datatools.connectivity.oda.consumer.helper.OdaQuery.setProperty",
          "source": "OdaQuery.java:229"
        },
        {
          "method": "org.eclipse.birt.data.engine.odaconsumer.PreparedStatement.doSetProperty",
          "source": "PreparedStatement.java:154"
        },
        {
          "method": "org.eclipse.birt.data.engine.odaconsumer.PreparedStatement.setProperty",
          "source": "PreparedStatement.java:136"
        },
        {
          "method": "org.eclipse.birt.data.engine.executor.DataSourceQuery.addProperties",
          "source": "D ataSourceQuery.java:349"
        },
        {
          "method": "org.eclipse.birt.data.engine.executor.DataSourceQuery.prepare",
          "source": "DataSou rceQuery.java:304"
        },
        {
          "method": "org.eclipse.birt.data.engine.impl.PreparedExtendedDSQuery$ExtendedDSQueryExecutor.prepareOdiQuery",
          "source": "PreparedExtendedDSQuery.java:277"
        },
        {
          "method": "org.eclipse.birt.data.engine.impl.PreparedQuery$Executor.prepareExecution",
          "source": "PreparedQuery.java:715"
        },
        {
          "method": "org.eclipse.birt.data.engine.impl.PreparedQuery$Executor.access$000",
          "source": "P reparedQuery.java:537"
        },
        {
          "method": "org.eclipse.birt.data.engine.impl.PreparedQuery.doPrepare",
          "source": "PreparedQue ry.java:226"
        },
        {
          "method": "org.eclipse.birt.data.engine.impl.PreparedDataSourceQuery.execute",
          "source": "Pre paredDataSourceQuery.java:145"
        },
        {
          "method": "org.eclipse.birt.report.engine.data.dte.DteDataEngine.execute",
          "source": "DteData Engine.java:205"
        },
        {
          "method": "org.eclipse.birt.report.engine.executor.QueryItemExecutor.openResultSet",
          "source": "QueryItemExecutor.java:62"
        },
        {
          "method": "org.eclipse.birt.report.engine.executor.TableItemExecutor.execute",
          "source": "Tab leItemExecutor.java:122"
        },
        {
          "method": "org.eclipse.birt.report.engine.executor.ReportExecutorVisitor.visitTableItem",
          "source": "ReportExecutorVisitor.java:188"
        },
        {
          "method": "org.eclipse.birt.report.engine.ir.TableItemDesign.accept",
          "source": "TableItemDes ign.java:69"
        },
        {
          "method": "org.eclipse.birt.report.engine.executor.ReportExecutor.execute",
          "source": "Report Executor.java:125"
        },
        {
          "method": "org.eclipse.birt.report.engine.executor.ReportExecutor.execute",
          "source": "Report Executor.java:89"
        },
        {
          "method": "org.eclipse.birt.report.engine.api.impl.RunAndRenderTask.run",
          "source": "RunAndRe nderTask.java:175"
        },
        {
          "method": "org.eclipse.birt.report.engine.api.ReportRunner.runAndRenderReport",
          "source": "Re portRunner.java:232"
        },
        {
          "method": "org.eclipse.birt.report.engine.api.ReportRunner.execute",
          "source": "ReportRunner. java:158"
        },
        {
          "method": "org.eclipse.birt.report.engine.api.ReportRunner.main",
          "source": "ReportRunner.jav a:129"
        }
      ],
      "number": 6,
      "commentIndex": 0,
      "bugId": "131511",
      "date": "2006-03-13T12:25:51+01:00",
      "product": "BIRT",
      "component": "Data",
      "severity": "normal"
    }
  ],
  "groupId": "131511",
  "bugId": "131511",
  "date": "2006-03-13T12:25:51+01:00",
  "product": "BIRT",
  "component": "Data",
  "severity": "normal"
}