{
  "comments": [
    "steps to reproduce:\n\n   - using command line example from BIRT runtime package\n   - type in \"genReport --mode runrender Products.rptdesign\"\n\nexpected behavior:\n\n   - the html report is created without any error printed in console\n\nactual behavior: \n\n   - the creation of the html report was failed.\n   - several exceptions were thrown out in console.\n   - note that this report can be previewed in browser using the old url\n     (http://localhost:8080/viewer/run?__report\u003dreport/Products.rptdesign)\n\norg.eclipse.birt.data.engine.odaconsumer.PreparedStateme\nnt doSetProperty\nWARNING: Cannot set statement property.\njava.lang.UnsupportedOperationException: IQuery.setProperty( String propertyName\n, String propertyValue )\n        at org.eclipse.datatools.connectivity.oda.consumer.helper.OdaObject.hand\nleUnsupportedOp(OdaObject.java:278)\n        at org.eclipse.datatools.connectivity.oda.consumer.helper.OdaQuery.setPr\noperty(OdaQuery.java:229)\n        at org.eclipse.birt.data.engine.odaconsumer.PreparedStatement.doSetPrope\nrty(PreparedStatement.java:154)\n        at org.eclipse.birt.data.engine.odaconsumer.PreparedStatement.setPropert\ny(PreparedStatement.java:136)\n        at org.eclipse.birt.data.engine.executor.DataSourceQuery.addProperties(D\nataSourceQuery.java:349)\n        at org.eclipse.birt.data.engine.executor.DataSourceQuery.prepare(DataSou\nrceQuery.java:304)\n        at org.eclipse.birt.data.engine.impl.PreparedExtendedDSQuery$ExtendedDSQ\nueryExecutor.prepareOdiQuery(PreparedExtendedDSQuery.java:277)\n        at org.eclipse.birt.data.engine.impl.PreparedQuery$Executor.prepareExecu\ntion(PreparedQuery.java:715)\n        at org.eclipse.birt.data.engine.impl.PreparedQuery$Executor.access$000(P\nreparedQuery.java:537)\n        at org.eclipse.birt.data.engine.impl.PreparedQuery.doPrepare(PreparedQue\nry.java:226)\n        at org.eclipse.birt.data.engine.impl.PreparedDataSourceQuery.execute(Pre\nparedDataSourceQuery.java:145)\n        at org.eclipse.birt.report.engine.data.dte.DteDataEngine.execute(DteData\nEngine.java:205)\n        at org.eclipse.birt.report.engine.executor.QueryItemExecutor.openResultS\net(QueryItemExecutor.java:62)\n        at org.eclipse.birt.report.engine.executor.TableItemExecutor.execute(Tab\nleItemExecutor.java:122)\n        at org.eclipse.birt.report.engine.executor.ReportExecutorVisitor.visitTa\nbleItem(ReportExecutorVisitor.java:188)\n        at org.eclipse.birt.report.engine.ir.TableItemDesign.accept(TableItemDes\nign.java:69)\n        at org.eclipse.birt.report.engine.executor.ReportExecutor.execute(Report\nExecutor.java:125)\n        at org.eclipse.birt.report.engine.executor.ReportExecutor.execute(Report\nExecutor.java:89)\n        at org.eclipse.birt.report.engine.api.impl.RunAndRenderTask.run(RunAndRe\nnderTask.java:175)\n        at org.eclipse.birt.report.engine.api.ReportRunner.runAndRenderReport(Re\nportRunner.java:232)\n        at org.eclipse.birt.report.engine.api.ReportRunner.execute(ReportRunner.\njava:158)\n        at org.eclipse.birt.report.engine.api.ReportRunner.main(ReportRunner.jav\na:129)\nMar 13, 2006 4:47:14 AM org.eclipse.birt.data.engine.odaconsumer.PreparedStateme\nnt doSetProperty\nWARNING: Cannot set statement property.\njava.lang.UnsupportedOperationException: IQuery.setProperty( String propertyName\n, String propertyValue )\n        at org.eclipse.datatools.connectivity.oda.consumer.helper.OdaObject.hand\nleUnsupportedOp(OdaObject.java:278)\n        at org.eclipse.datatools.connectivity.oda.consumer.helper.OdaQuery.setPr\noperty(OdaQuery.java:229)\n        at org.eclipse.birt.data.engine.odaconsumer.PreparedStatement.doSetPrope\nrty(PreparedStatement.java:154)\n        at org.eclipse.birt.data.engine.odaconsumer.PreparedStatement.setPropert\ny(PreparedStatement.java:136)\n        at org.eclipse.birt.data.engine.executor.DataSourceQuery.addProperties(D\nataSourceQuery.java:349)\n        at org.eclipse.birt.data.engine.executor.DataSourceQuery.prepare(DataSou\nrceQuery.java:304)\n        at org.eclipse.birt.data.engine.impl.PreparedExtendedDSQuery$ExtendedDSQ\nueryExecutor.prepareOdiQuery(PreparedExtendedDSQuery.java:277)\n        at org.eclipse.birt.data.engine.impl.PreparedQuery$Executor.prepareExecu\ntion(PreparedQuery.java:715)\n        at org.eclipse.birt.data.engine.impl.PreparedQuery$Executor.access$000(P\nreparedQuery.java:537)\n        at org.eclipse.birt.data.engine.impl.PreparedQuery.doPrepare(PreparedQue\nry.java:226)\n        at org.eclipse.birt.data.engine.impl.PreparedDataSourceQuery.execute(Pre\nparedDataSourceQuery.java:145)\n        at org.eclipse.birt.report.engine.data.dte.DteDataEngine.execute(DteData\nEngine.java:205)\n        at org.eclipse.birt.report.engine.executor.QueryItemExecutor.openResultS\net(QueryItemExecutor.java:62)\n        at org.eclipse.birt.report.engine.executor.TableItemExecutor.execute(Tab\nleItemExecutor.java:122)\n        at org.eclipse.birt.report.engine.executor.ReportExecutorVisitor.visitTa\nbleItem(ReportExecutorVisitor.java:188)\n        at org.eclipse.birt.report.engine.ir.TableItemDesign.accept(TableItemDes\nign.java:69)\n        at org.eclipse.birt.report.engine.executor.ReportExecutor.execute(Report\nExecutor.java:125)\n        at org.eclipse.birt.report.engine.executor.ReportExecutor.execute(Report\nExecutor.java:89)\n        at org.eclipse.birt.report.engine.api.impl.RunAndRenderTask.run(RunAndRe\nnderTask.java:175)\n        at org.eclipse.birt.report.engine.api.ReportRunner.runAndRenderReport(Re\nportRunner.java:232)\n        at org.eclipse.birt.report.engine.api.ReportRunner.execute(ReportRunner.\njava:158)\n        at org.eclipse.birt.report.engine.api.ReportRunner.main(ReportRunner.jav\na:129)\nMar 13, 2006 4:47:14 AM org.eclipse.birt.data.engine.odaconsumer.PreparedStateme\nnt doSetProperty\nWARNING: Cannot set statement property.\njava.lang.UnsupportedOperationException: IQuery.setProperty( String propertyName\n, String propertyValue )\n        at org.eclipse.datatools.connectivity.oda.consumer.helper.OdaObject.hand\nleUnsupportedOp(OdaObject.java:278)\n        at org.eclipse.datatools.connectivity.oda.consumer.helper.OdaQuery.setPr\noperty(OdaQuery.java:229)\n        at org.eclipse.birt.data.engine.odaconsumer.PreparedStatement.doSetPrope\nrty(PreparedStatement.java:154)\n        at org.eclipse.birt.data.engine.odaconsumer.PreparedStatement.setPropert\ny(PreparedStatement.java:136)\n        at org.eclipse.birt.data.engine.executor.DataSourceQuery.addProperties(D\nataSourceQuery.java:349)\n        at org.eclipse.birt.data.engine.executor.DataSourceQuery.prepare(DataSou\nrceQuery.java:304)\n        at org.eclipse.birt.data.engine.impl.PreparedExtendedDSQuery$ExtendedDSQ\nueryExecutor.prepareOdiQuery(PreparedExtendedDSQuery.java:277)\n        at org.eclipse.birt.data.engine.impl.PreparedQuery$Executor.prepareExecu\ntion(PreparedQuery.java:715)\n        at org.eclipse.birt.data.engine.impl.PreparedQuery$Executor.access$000(P\nreparedQuery.java:537)\n        at org.eclipse.birt.data.engine.impl.PreparedQuery.doPrepare(PreparedQue\nry.java:226)\n        at org.eclipse.birt.data.engine.impl.PreparedDataSourceQuery.execute(Pre\nparedDataSourceQuery.java:145)\n        at org.eclipse.birt.report.engine.data.dte.DteDataEngine.execute(DteData\nEngine.java:205)\n        at org.eclipse.birt.report.engine.executor.QueryItemExecutor.openResultS\net(QueryItemExecutor.java:62)\n        at org.eclipse.birt.report.engine.executor.TableItemExecutor.execute(Tab\nleItemExecutor.java:122)\n        at org.eclipse.birt.report.engine.executor.ReportExecutorVisitor.visitTa\nbleItem(ReportExecutorVisitor.java:188)\n        at org.eclipse.birt.report.engine.ir.TableItemDesign.accept(TableItemDes\nign.java:69)\n        at org.eclipse.birt.report.engine.executor.ReportExecutor.execute(Report\nExecutor.java:125)\n        at org.eclipse.birt.report.engine.executor.ReportExecutor.execute(Report\nExecutor.java:89)\n        at org.eclipse.birt.report.engine.api.impl.RunAndRenderTask.run(RunAndRe\nnderTask.java:175)\n        at org.eclipse.birt.report.engine.api.ReportRunner.runAndRenderReport(Re\nportRunner.java:232)\n        at org.eclipse.birt.report.engine.api.ReportRunner.execute(ReportRunner.\njava:158)\n        at org.eclipse.birt.report.engine.api.ReportRunner.main(ReportRunner.jav\na:129)\nMar 13, 2006 4:47:14 AM org.eclipse.birt.data.engine.odaconsumer.PreparedStateme\nnt doSetProperty\nWARNING: Cannot set statement property.\njava.lang.UnsupportedOperationException: IQuery.setProperty( String propertyName\n, String propertyValue )\n        at org.eclipse.datatools.connectivity.oda.consumer.helper.OdaObject.hand\nleUnsupportedOp(OdaObject.java:278)\n        at org.eclipse.datatools.connectivity.oda.consumer.helper.OdaQuery.setPr\noperty(OdaQuery.java:229)\n        at org.eclipse.birt.data.engine.odaconsumer.PreparedStatement.doSetPrope\nrty(PreparedStatement.java:154)\n        at org.eclipse.birt.data.engine.odaconsumer.PreparedStatement.setPropert\ny(PreparedStatement.java:136)\n        at org.eclipse.birt.data.engine.executor.DataSourceQuery.addProperties(D\nataSourceQuery.java:349)\n        at org.eclipse.birt.data.engine.executor.DataSourceQuery.prepare(DataSou\nrceQuery.java:304)\n        at org.eclipse.birt.data.engine.impl.PreparedExtendedDSQuery$ExtendedDSQ\nueryExecutor.prepareOdiQuery(PreparedExtendedDSQuery.java:277)\n        at org.eclipse.birt.data.engine.impl.PreparedQuery$Executor.prepareExecu\ntion(PreparedQuery.java:715)\n        at org.eclipse.birt.data.engine.impl.PreparedQuery$Executor.access$000(P\nreparedQuery.java:537)\n        at org.eclipse.birt.data.engine.impl.PreparedQuery.doPrepare(PreparedQue\nry.java:226)\n        at org.eclipse.birt.data.engine.impl.PreparedDataSourceQuery.execute(Pre\nparedDataSourceQuery.java:145)\n        at org.eclipse.birt.report.engine.data.dte.DteDataEngine.execute(DteData\nEngine.java:205)\n        at org.eclipse.birt.report.engine.executor.QueryItemExecutor.openResultS\net(QueryItemExecutor.java:62)\n        at org.eclipse.birt.report.engine.executor.TableItemExecutor.execute(Tab\nleItemExecutor.java:122)\n        at org.eclipse.birt.report.engine.executor.ReportExecutorVisitor.visitTa\nbleItem(ReportExecutorVisitor.java:188)\n        at org.eclipse.birt.report.engine.ir.TableItemDesign.accept(TableItemDes\nign.java:69)\n        at org.eclipse.birt.report.engine.executor.ReportExecutor.execute(Report\nExecutor.java:125)\n        at org.eclipse.birt.report.engine.executor.ReportExecutor.execute(Report\nExecutor.java:89)\n        at org.eclipse.birt.report.engine.api.impl.RunAndRenderTask.run(RunAndRe\nnderTask.java:175)\n        at org.eclipse.birt.report.engine.api.ReportRunner.runAndRenderReport(Re\nportRunner.java:232)\n        at org.eclipse.birt.report.engine.api.ReportRunner.execute(ReportRunner.\njava:158)\n        at org.eclipse.birt.report.engine.api.ReportRunner.main(ReportRunner.jav\na:129)\njava.lang.NullPointerException\n        at org.eclipse.birt.report.engine.api.HTMLActionHandler.buildDrillAction\n(HTMLActionHandler.java:88)\n        at org.eclipse.birt.report.engine.api.HTMLActionHandler.getURL(HTMLActio\nnHandler.java:55)\n        at org.eclipse.birt.report.engine.emitter.html.HTMLReportEmitter.handleA\nction(HTMLReportEmitter.java:1995)\n        at org.eclipse.birt.report.engine.emitter.html.HTMLReportEmitter.startTe\nxt(HTMLReportEmitter.java:1184)\n        at org.eclipse.birt.report.engine.emitter.html.HTMLReportEmitter.startDa\nta(HTMLReportEmitter.java:1446)\n        at org.eclipse.birt.report.engine.presentation.WrappedEmitter.startData(\nWrappedEmitter.java:339)\n        at org.eclipse.birt.report.engine.presentation.LocalizedEmitter.startDat\na(LocalizedEmitter.java:290)\n        at org.eclipse.birt.report.engine.presentation.WrappedEmitter.startData(\nWrappedEmitter.java:339)\n        at org.eclipse.birt.report.engine.presentation.DefaultPaginationEmitter.\nstartData(DefaultPaginationEmitter.java:299)\n        at org.eclipse.birt.report.engine.executor.DataItemExecutor.execute(Data\nItemExecutor.java:132)\n        at org.eclipse.birt.report.engine.executor.ReportExecutorVisitor.visitDa\ntaItem(ReportExecutorVisitor.java:158)\n        at org.eclipse.birt.report.engine.ir.DataItemDesign.accept(DataItemDesig\nn.java:69)\n        at org.eclipse.birt.report.engine.executor.TableItemExecutor.accessRow(T\nableItemExecutor.java:590)\n        at org.eclipse.birt.report.engine.executor.TableItemExecutor.accessTable\nBand(TableItemExecutor.java:480)\n        at org.eclipse.birt.report.engine.executor.TableItemExecutor.accessGroup\nHeader(TableItemExecutor.java:441)\n        at org.eclipse.birt.report.engine.executor.ListingElementExecutor.access\nQuery(ListingElementExecutor.java:162)\n        at org.eclipse.birt.report.engine.executor.TableItemExecutor.execute(Tab\nleItemExecutor.java:151)\n        at org.eclipse.birt.report.engine.executor.ReportExecutorVisitor.visitTa\nbleItem(ReportExecutorVisitor.java:188)\n        at org.eclipse.birt.report.engine.ir.TableItemDesign.accept(TableItemDes\nign.java:69)\n        at org.eclipse.birt.report.engine.executor.ReportExecutor.execute(Report\nExecutor.java:125)\n        at org.eclipse.birt.report.engine.executor.ReportExecutor.execute(Report\nExecutor.java:89)\n        at org.eclipse.birt.report.engine.api.impl.RunAndRenderTask.run(RunAndRe\nnderTask.java:175)\n        at org.eclipse.birt.report.engine.api.ReportRunner.runAndRenderReport(Re\nportRunner.java:232)\n        at org.eclipse.birt.report.engine.api.ReportRunner.execute(ReportRunner.\njava:158)\n        at org.eclipse.birt.report.engine.api.ReportRunner.main(ReportRunner.jav\na:129)\nMar 13, 2006 4:47:15 AM org.eclipse.birt.report.engine.api.impl.RunAndRenderTask\n run\nSEVERE: An error happened while running the report. Cause:\njava.lang.NullPointerException\n        at org.eclipse.birt.report.engine.api.HTMLActionHandler.buildDrillAction\n(HTMLActionHandler.java:88)\n        at org.eclipse.birt.report.engine.api.HTMLActionHandler.getURL(HTMLActio\nnHandler.java:55)\n        at org.eclipse.birt.report.engine.emitter.html.HTMLReportEmitter.handleA\nction(HTMLReportEmitter.java:1995)\n        at org.eclipse.birt.report.engine.emitter.html.HTMLReportEmitter.startTe\nxt(HTMLReportEmitter.java:1184)\n        at org.eclipse.birt.report.engine.emitter.html.HTMLReportEmitter.startDa\nta(HTMLReportEmitter.java:1446)\n        at org.eclipse.birt.report.engine.presentation.WrappedEmitter.startData(\nWrappedEmitter.java:339)\n        at org.eclipse.birt.report.engine.presentation.LocalizedEmitter.startDat\na(LocalizedEmitter.java:290)\n        at org.eclipse.birt.report.engine.presentation.WrappedEmitter.startData(\nWrappedEmitter.java:339)\n        at org.eclipse.birt.report.engine.presentation.DefaultPaginationEmitter.\nstartData(DefaultPaginationEmitter.java:299)\n        at org.eclipse.birt.report.engine.executor.DataItemExecutor.execute(Data\nItemExecutor.java:132)\n        at org.eclipse.birt.report.engine.executor.ReportExecutorVisitor.visitDa\ntaItem(ReportExecutorVisitor.java:158)\n        at org.eclipse.birt.report.engine.ir.DataItemDesign.accept(DataItemDesig\nn.java:69)\n        at org.eclipse.birt.report.engine.executor.TableItemExecutor.accessRow(T\nableItemExecutor.java:590)\n        at org.eclipse.birt.report.engine.executor.TableItemExecutor.accessTable\nBand(TableItemExecutor.java:480)\n        at org.eclipse.birt.report.engine.executor.TableItemExecutor.accessGroup\nHeader(TableItemExecutor.java:441)\n        at org.eclipse.birt.report.engine.executor.ListingElementExecutor.access\nQuery(ListingElementExecutor.java:162)\n        at org.eclipse.birt.report.engine.executor.TableItemExecutor.execute(Tab\nleItemExecutor.java:151)\n        at org.eclipse.birt.report.engine.executor.ReportExecutorVisitor.visitTa\nbleItem(ReportExecutorVisitor.java:188)\n        at org.eclipse.birt.report.engine.ir.TableItemDesign.accept(TableItemDes\nign.java:69)\n        at org.eclipse.birt.report.engine.executor.ReportExecutor.execute(Report\nExecutor.java:125)\n        at org.eclipse.birt.report.engine.executor.ReportExecutor.execute(Report\nExecutor.java:89)\n        at org.eclipse.birt.report.engine.api.impl.RunAndRenderTask.run(RunAndRe\nnderTask.java:175)\n        at org.eclipse.birt.report.engine.api.ReportRunner.runAndRenderReport(Re\nportRunner.java:232)\n        at org.eclipse.birt.report.engine.api.ReportRunner.execute(ReportRunner.\njava:158)\n        at org.eclipse.birt.report.engine.api.ReportRunner.main(ReportRunner.jav\na:129)\nMar 13, 2006 4:47:15 AM org.eclipse.birt.report.engine.api.ReportRunner runAndRe\nnderReport\nSEVERE: Error happened while running the report\norg.eclipse.birt.report.engine.api.EngineException: Error happened while running\n the report\n        at org.eclipse.birt.report.engine.api.impl.RunAndRenderTask.run(RunAndRe\nnderTask.java:186)\n        at org.eclipse.birt.report.engine.api.ReportRunner.runAndRenderReport(Re\nportRunner.java:232)\n        at org.eclipse.birt.report.engine.api.ReportRunner.execute(ReportRunner.\njava:158)\n        at org.eclipse.birt.report.engine.api.ReportRunner.main(ReportRunner.jav\na:129)\nCaused by: java.lang.NullPointerException\n        at org.eclipse.birt.report.engine.api.HTMLActionHandler.buildDrillAction\n(HTMLActionHandler.java:88)\n        at org.eclipse.birt.report.engine.api.HTMLActionHandler.getURL(HTMLActio\nnHandler.java:55)\n        at org.eclipse.birt.report.engine.emitter.html.HTMLReportEmitter.handleA\nction(HTMLReportEmitter.java:1995)\n        at org.eclipse.birt.report.engine.emitter.html.HTMLReportEmitter.startTe\nxt(HTMLReportEmitter.java:1184)\n        at org.eclipse.birt.report.engine.emitter.html.HTMLReportEmitter.startDa\nta(HTMLReportEmitter.java:1446)\n        at org.eclipse.birt.report.engine.presentation.WrappedEmitter.startData(\nWrappedEmitter.java:339)\n        at org.eclipse.birt.report.engine.presentation.LocalizedEmitter.startDat\na(LocalizedEmitter.java:290)\n        at org.eclipse.birt.report.engine.presentation.WrappedEmitter.startData(\nWrappedEmitter.java:339)\n        at org.eclipse.birt.report.engine.presentation.DefaultPaginationEmitter.\nstartData(DefaultPaginationEmitter.java:299)\n        at org.eclipse.birt.report.engine.executor.DataItemExecutor.execute(Data\nItemExecutor.java:132)\n        at org.eclipse.birt.report.engine.executor.ReportExecutorVisitor.visitDa\ntaItem(ReportExecutorVisitor.java:158)\n        at org.eclipse.birt.report.engine.ir.DataItemDesign.accept(DataItemDesig\nn.java:69)\n        at org.eclipse.birt.report.engine.executor.TableItemExecutor.accessRow(T\nableItemExecutor.java:590)\n        at org.eclipse.birt.report.engine.executor.TableItemExecutor.accessTable\nBand(TableItemExecutor.java:480)\n        at org.eclipse.birt.report.engine.executor.TableItemExecutor.accessGroup\nHeader(TableItemExecutor.java:441)\n        at org.eclipse.birt.report.engine.executor.ListingElementExecutor.access\nQuery(ListingElementExecutor.java:162)\n        at org.eclipse.birt.report.engine.executor.TableItemExecutor.execute(Tab\nleItemExecutor.java:151)\n        at org.eclipse.birt.report.engine.executor.ReportExecutorVisitor.visitTa\nbleItem(ReportExecutorVisitor.java:188)\n        at org.eclipse.birt.report.engine.ir.TableItemDesign.accept(TableItemDes\nign.java:69)\n        at org.eclipse.birt.report.engine.executor.ReportExecutor.execute(Report\nExecutor.java:125)\n        at org.eclipse.birt.report.engine.executor.ReportExecutor.execute(Report\nExecutor.java:89)\n        at org.eclipse.birt.report.engine.api.impl.RunAndRenderTask.run(RunAndRe\nnderTask.java:175)\n        ... 3 more",
    "Created an attachment (id\u003d36128)\nthe report design\n\n",
    "Created an attachment (id\u003d36129)\nthe data source\n\n",
    "Fixed.",
    "Verified, 20060411"
  ],
  "commentCreationDates": [
    "2006-03-13T12:45:59+01:00",
    "2006-03-13T12:47:11+01:00",
    "2006-03-13T12:47:22+01:00",
    "2006-03-14T11:24:45+01:00",
    "2006-04-11T07:53:48+02:00"
  ],
  "traces": [
    {
      "exceptionType": "java.lang.UnsupportedOperationException",
      "message": "IQuery.setProperty( String propertyName , String propertyValue )",
      "elements": [
        {
          "method": "org.eclipse.datatools.connectivity.oda.consumer.helper.OdaObject.handleUnsupportedOp",
          "source": "OdaObject.java:278"
        },
        {
          "method": "org.eclipse.datatools.connectivity.oda.consumer.helper.OdaQuery.setProperty",
          "source": "OdaQuery.java:229"
        },
        {
          "method": "org.eclipse.birt.data.engine.odaconsumer.PreparedStatement.doSetProperty",
          "source": "PreparedStatement.java:154"
        },
        {
          "method": "org.eclipse.birt.data.engine.odaconsumer.PreparedStatement.setProperty",
          "source": "PreparedStatement.java:136"
        },
        {
          "method": "org.eclipse.birt.data.engine.executor.DataSourceQuery.addProperties",
          "source": "D ataSourceQuery.java:349"
        },
        {
          "method": "org.eclipse.birt.data.engine.executor.DataSourceQuery.prepare",
          "source": "DataSou rceQuery.java:304"
        },
        {
          "method": "org.eclipse.birt.data.engine.impl.PreparedExtendedDSQuery$ExtendedDSQueryExecutor.prepareOdiQuery",
          "source": "PreparedExtendedDSQuery.java:277"
        },
        {
          "method": "org.eclipse.birt.data.engine.impl.PreparedQuery$Executor.prepareExecution",
          "source": "PreparedQuery.java:715"
        },
        {
          "method": "org.eclipse.birt.data.engine.impl.PreparedQuery$Executor.access$000",
          "source": "P reparedQuery.java:537"
        },
        {
          "method": "org.eclipse.birt.data.engine.impl.PreparedQuery.doPrepare",
          "source": "PreparedQue ry.java:226"
        },
        {
          "method": "org.eclipse.birt.data.engine.impl.PreparedDataSourceQuery.execute",
          "source": "Pre paredDataSourceQuery.java:145"
        },
        {
          "method": "org.eclipse.birt.report.engine.data.dte.DteDataEngine.execute",
          "source": "DteData Engine.java:205"
        },
        {
          "method": "org.eclipse.birt.report.engine.executor.QueryItemExecutor.openResultSet",
          "source": "QueryItemExecutor.java:62"
        },
        {
          "method": "org.eclipse.birt.report.engine.executor.TableItemExecutor.execute",
          "source": "Tab leItemExecutor.java:122"
        },
        {
          "method": "org.eclipse.birt.report.engine.executor.ReportExecutorVisitor.visitTableItem",
          "source": "ReportExecutorVisitor.java:188"
        },
        {
          "method": "org.eclipse.birt.report.engine.ir.TableItemDesign.accept",
          "source": "TableItemDes ign.java:69"
        },
        {
          "method": "org.eclipse.birt.report.engine.executor.ReportExecutor.execute",
          "source": "Report Executor.java:125"
        },
        {
          "method": "org.eclipse.birt.report.engine.executor.ReportExecutor.execute",
          "source": "Report Executor.java:89"
        },
        {
          "method": "org.eclipse.birt.report.engine.api.impl.RunAndRenderTask.run",
          "source": "RunAndRe nderTask.java:175"
        },
        {
          "method": "org.eclipse.birt.report.engine.api.ReportRunner.runAndRenderReport",
          "source": "Re portRunner.java:232"
        },
        {
          "method": "org.eclipse.birt.report.engine.api.ReportRunner.execute",
          "source": "ReportRunner. java:158"
        },
        {
          "method": "org.eclipse.birt.report.engine.api.ReportRunner.main",
          "source": "ReportRunner.jav a:129"
        }
      ],
      "number": 0,
      "commentIndex": 0,
      "bugId": "131514",
      "date": "2006-03-13T12:45:59+01:00",
      "product": "BIRT",
      "component": "Data",
      "severity": "normal"
    },
    {
      "exceptionType": "java.lang.UnsupportedOperationException",
      "message": "IQuery.setProperty( String propertyName , String propertyValue )",
      "elements": [
        {
          "method": "org.eclipse.datatools.connectivity.oda.consumer.helper.OdaObject.handleUnsupportedOp",
          "source": "OdaObject.java:278"
        },
        {
          "method": "org.eclipse.datatools.connectivity.oda.consumer.helper.OdaQuery.setProperty",
          "source": "OdaQuery.java:229"
        },
        {
          "method": "org.eclipse.birt.data.engine.odaconsumer.PreparedStatement.doSetProperty",
          "source": "PreparedStatement.java:154"
        },
        {
          "method": "org.eclipse.birt.data.engine.odaconsumer.PreparedStatement.setProperty",
          "source": "PreparedStatement.java:136"
        },
        {
          "method": "org.eclipse.birt.data.engine.executor.DataSourceQuery.addProperties",
          "source": "D ataSourceQuery.java:349"
        },
        {
          "method": "org.eclipse.birt.data.engine.executor.DataSourceQuery.prepare",
          "source": "DataSou rceQuery.java:304"
        },
        {
          "method": "org.eclipse.birt.data.engine.impl.PreparedExtendedDSQuery$ExtendedDSQueryExecutor.prepareOdiQuery",
          "source": "PreparedExtendedDSQuery.java:277"
        },
        {
          "method": "org.eclipse.birt.data.engine.impl.PreparedQuery$Executor.prepareExecution",
          "source": "PreparedQuery.java:715"
        },
        {
          "method": "org.eclipse.birt.data.engine.impl.PreparedQuery$Executor.access$000",
          "source": "P reparedQuery.java:537"
        },
        {
          "method": "org.eclipse.birt.data.engine.impl.PreparedQuery.doPrepare",
          "source": "PreparedQue ry.java:226"
        },
        {
          "method": "org.eclipse.birt.data.engine.impl.PreparedDataSourceQuery.execute",
          "source": "Pre paredDataSourceQuery.java:145"
        },
        {
          "method": "org.eclipse.birt.report.engine.data.dte.DteDataEngine.execute",
          "source": "DteData Engine.java:205"
        },
        {
          "method": "org.eclipse.birt.report.engine.executor.QueryItemExecutor.openResultSet",
          "source": "QueryItemExecutor.java:62"
        },
        {
          "method": "org.eclipse.birt.report.engine.executor.TableItemExecutor.execute",
          "source": "Tab leItemExecutor.java:122"
        },
        {
          "method": "org.eclipse.birt.report.engine.executor.ReportExecutorVisitor.visitTableItem",
          "source": "ReportExecutorVisitor.java:188"
        },
        {
          "method": "org.eclipse.birt.report.engine.ir.TableItemDesign.accept",
          "source": "TableItemDes ign.java:69"
        },
        {
          "method": "org.eclipse.birt.report.engine.executor.ReportExecutor.execute",
          "source": "Report Executor.java:125"
        },
        {
          "method": "org.eclipse.birt.report.engine.executor.ReportExecutor.execute",
          "source": "Report Executor.java:89"
        },
        {
          "method": "org.eclipse.birt.report.engine.api.impl.RunAndRenderTask.run",
          "source": "RunAndRe nderTask.java:175"
        },
        {
          "method": "org.eclipse.birt.report.engine.api.ReportRunner.runAndRenderReport",
          "source": "Re portRunner.java:232"
        },
        {
          "method": "org.eclipse.birt.report.engine.api.ReportRunner.execute",
          "source": "ReportRunner. java:158"
        },
        {
          "method": "org.eclipse.birt.report.engine.api.ReportRunner.main",
          "source": "ReportRunner.jav a:129"
        }
      ],
      "number": 1,
      "commentIndex": 0,
      "bugId": "131514",
      "date": "2006-03-13T12:45:59+01:00",
      "product": "BIRT",
      "component": "Data",
      "severity": "normal"
    },
    {
      "exceptionType": "java.lang.UnsupportedOperationException",
      "message": "IQuery.setProperty( String propertyName , String propertyValue )",
      "elements": [
        {
          "method": "org.eclipse.datatools.connectivity.oda.consumer.helper.OdaObject.handleUnsupportedOp",
          "source": "OdaObject.java:278"
        },
        {
          "method": "org.eclipse.datatools.connectivity.oda.consumer.helper.OdaQuery.setProperty",
          "source": "OdaQuery.java:229"
        },
        {
          "method": "org.eclipse.birt.data.engine.odaconsumer.PreparedStatement.doSetProperty",
          "source": "PreparedStatement.java:154"
        },
        {
          "method": "org.eclipse.birt.data.engine.odaconsumer.PreparedStatement.setProperty",
          "source": "PreparedStatement.java:136"
        },
        {
          "method": "org.eclipse.birt.data.engine.executor.DataSourceQuery.addProperties",
          "source": "D ataSourceQuery.java:349"
        },
        {
          "method": "org.eclipse.birt.data.engine.executor.DataSourceQuery.prepare",
          "source": "DataSou rceQuery.java:304"
        },
        {
          "method": "org.eclipse.birt.data.engine.impl.PreparedExtendedDSQuery$ExtendedDSQueryExecutor.prepareOdiQuery",
          "source": "PreparedExtendedDSQuery.java:277"
        },
        {
          "method": "org.eclipse.birt.data.engine.impl.PreparedQuery$Executor.prepareExecution",
          "source": "PreparedQuery.java:715"
        },
        {
          "method": "org.eclipse.birt.data.engine.impl.PreparedQuery$Executor.access$000",
          "source": "P reparedQuery.java:537"
        },
        {
          "method": "org.eclipse.birt.data.engine.impl.PreparedQuery.doPrepare",
          "source": "PreparedQue ry.java:226"
        },
        {
          "method": "org.eclipse.birt.data.engine.impl.PreparedDataSourceQuery.execute",
          "source": "Pre paredDataSourceQuery.java:145"
        },
        {
          "method": "org.eclipse.birt.report.engine.data.dte.DteDataEngine.execute",
          "source": "DteData Engine.java:205"
        },
        {
          "method": "org.eclipse.birt.report.engine.executor.QueryItemExecutor.openResultSet",
          "source": "QueryItemExecutor.java:62"
        },
        {
          "method": "org.eclipse.birt.report.engine.executor.TableItemExecutor.execute",
          "source": "Tab leItemExecutor.java:122"
        },
        {
          "method": "org.eclipse.birt.report.engine.executor.ReportExecutorVisitor.visitTableItem",
          "source": "ReportExecutorVisitor.java:188"
        },
        {
          "method": "org.eclipse.birt.report.engine.ir.TableItemDesign.accept",
          "source": "TableItemDes ign.java:69"
        },
        {
          "method": "org.eclipse.birt.report.engine.executor.ReportExecutor.execute",
          "source": "Report Executor.java:125"
        },
        {
          "method": "org.eclipse.birt.report.engine.executor.ReportExecutor.execute",
          "source": "Report Executor.java:89"
        },
        {
          "method": "org.eclipse.birt.report.engine.api.impl.RunAndRenderTask.run",
          "source": "RunAndRe nderTask.java:175"
        },
        {
          "method": "org.eclipse.birt.report.engine.api.ReportRunner.runAndRenderReport",
          "source": "Re portRunner.java:232"
        },
        {
          "method": "org.eclipse.birt.report.engine.api.ReportRunner.execute",
          "source": "ReportRunner. java:158"
        },
        {
          "method": "org.eclipse.birt.report.engine.api.ReportRunner.main",
          "source": "ReportRunner.jav a:129"
        }
      ],
      "number": 2,
      "commentIndex": 0,
      "bugId": "131514",
      "date": "2006-03-13T12:45:59+01:00",
      "product": "BIRT",
      "component": "Data",
      "severity": "normal"
    },
    {
      "exceptionType": "java.lang.UnsupportedOperationException",
      "message": "IQuery.setProperty( String propertyName , String propertyValue )",
      "elements": [
        {
          "method": "org.eclipse.datatools.connectivity.oda.consumer.helper.OdaObject.handleUnsupportedOp",
          "source": "OdaObject.java:278"
        },
        {
          "method": "org.eclipse.datatools.connectivity.oda.consumer.helper.OdaQuery.setProperty",
          "source": "OdaQuery.java:229"
        },
        {
          "method": "org.eclipse.birt.data.engine.odaconsumer.PreparedStatement.doSetProperty",
          "source": "PreparedStatement.java:154"
        },
        {
          "method": "org.eclipse.birt.data.engine.odaconsumer.PreparedStatement.setProperty",
          "source": "PreparedStatement.java:136"
        },
        {
          "method": "org.eclipse.birt.data.engine.executor.DataSourceQuery.addProperties",
          "source": "D ataSourceQuery.java:349"
        },
        {
          "method": "org.eclipse.birt.data.engine.executor.DataSourceQuery.prepare",
          "source": "DataSou rceQuery.java:304"
        },
        {
          "method": "org.eclipse.birt.data.engine.impl.PreparedExtendedDSQuery$ExtendedDSQueryExecutor.prepareOdiQuery",
          "source": "PreparedExtendedDSQuery.java:277"
        },
        {
          "method": "org.eclipse.birt.data.engine.impl.PreparedQuery$Executor.prepareExecution",
          "source": "PreparedQuery.java:715"
        },
        {
          "method": "org.eclipse.birt.data.engine.impl.PreparedQuery$Executor.access$000",
          "source": "P reparedQuery.java:537"
        },
        {
          "method": "org.eclipse.birt.data.engine.impl.PreparedQuery.doPrepare",
          "source": "PreparedQue ry.java:226"
        },
        {
          "method": "org.eclipse.birt.data.engine.impl.PreparedDataSourceQuery.execute",
          "source": "Pre paredDataSourceQuery.java:145"
        },
        {
          "method": "org.eclipse.birt.report.engine.data.dte.DteDataEngine.execute",
          "source": "DteData Engine.java:205"
        },
        {
          "method": "org.eclipse.birt.report.engine.executor.QueryItemExecutor.openResultSet",
          "source": "QueryItemExecutor.java:62"
        },
        {
          "method": "org.eclipse.birt.report.engine.executor.TableItemExecutor.execute",
          "source": "Tab leItemExecutor.java:122"
        },
        {
          "method": "org.eclipse.birt.report.engine.executor.ReportExecutorVisitor.visitTableItem",
          "source": "ReportExecutorVisitor.java:188"
        },
        {
          "method": "org.eclipse.birt.report.engine.ir.TableItemDesign.accept",
          "source": "TableItemDes ign.java:69"
        },
        {
          "method": "org.eclipse.birt.report.engine.executor.ReportExecutor.execute",
          "source": "Report Executor.java:125"
        },
        {
          "method": "org.eclipse.birt.report.engine.executor.ReportExecutor.execute",
          "source": "Report Executor.java:89"
        },
        {
          "method": "org.eclipse.birt.report.engine.api.impl.RunAndRenderTask.run",
          "source": "RunAndRe nderTask.java:175"
        },
        {
          "method": "org.eclipse.birt.report.engine.api.ReportRunner.runAndRenderReport",
          "source": "Re portRunner.java:232"
        },
        {
          "method": "org.eclipse.birt.report.engine.api.ReportRunner.execute",
          "source": "ReportRunner. java:158"
        },
        {
          "method": "org.eclipse.birt.report.engine.api.ReportRunner.main",
          "source": "ReportRunner.jav a:129"
        }
      ],
      "number": 3,
      "commentIndex": 0,
      "bugId": "131514",
      "date": "2006-03-13T12:45:59+01:00",
      "product": "BIRT",
      "component": "Data",
      "severity": "normal"
    },
    {
      "exceptionType": "java.lang.NullPointerException",
      "elements": [
        {
          "method": "org.eclipse.birt.report.engine.api.HTMLActionHandler.buildDrillAction",
          "source": "HTMLActionHandler.java:88"
        },
        {
          "method": "org.eclipse.birt.report.engine.api.HTMLActionHandler.getURL",
          "source": "HTMLActio nHandler.java:55"
        },
        {
          "method": "org.eclipse.birt.report.engine.emitter.html.HTMLReportEmitter.handleAction",
          "source": "HTMLReportEmitter.java:1995"
        },
        {
          "method": "org.eclipse.birt.report.engine.emitter.html.HTMLReportEmitter.startText",
          "source": "HTMLReportEmitter.java:1184"
        },
        {
          "method": "org.eclipse.birt.report.engine.emitter.html.HTMLReportEmitter.startData",
          "source": "HTMLReportEmitter.java:1446"
        },
        {
          "method": "org.eclipse.birt.report.engine.presentation.WrappedEmitter.startData",
          "source": " WrappedEmitter.java:339"
        },
        {
          "method": "org.eclipse.birt.report.engine.presentation.LocalizedEmitter.startData",
          "source": "LocalizedEmitter.java:290"
        },
        {
          "method": "org.eclipse.birt.report.engine.presentation.WrappedEmitter.startData",
          "source": " WrappedEmitter.java:339"
        },
        {
          "method": "org.eclipse.birt.report.engine.presentation.DefaultPaginationEmitter.startData",
          "source": "DefaultPaginationEmitter.java:299"
        },
        {
          "method": "org.eclipse.birt.report.engine.executor.DataItemExecutor.execute",
          "source": "Data ItemExecutor.java:132"
        },
        {
          "method": "org.eclipse.birt.report.engine.executor.ReportExecutorVisitor.visitDataItem",
          "source": "ReportExecutorVisitor.java:158"
        },
        {
          "method": "org.eclipse.birt.report.engine.ir.DataItemDesign.accept",
          "source": "DataItemDesig n.java:69"
        },
        {
          "method": "org.eclipse.birt.report.engine.executor.TableItemExecutor.accessRow",
          "source": "T ableItemExecutor.java:590"
        },
        {
          "method": "org.eclipse.birt.report.engine.executor.TableItemExecutor.accessTableBand",
          "source": "TableItemExecutor.java:480"
        },
        {
          "method": "org.eclipse.birt.report.engine.executor.TableItemExecutor.accessGroupHeader",
          "source": "TableItemExecutor.java:441"
        },
        {
          "method": "org.eclipse.birt.report.engine.executor.ListingElementExecutor.accessQuery",
          "source": "ListingElementExecutor.java:162"
        },
        {
          "method": "org.eclipse.birt.report.engine.executor.TableItemExecutor.execute",
          "source": "Tab leItemExecutor.java:151"
        },
        {
          "method": "org.eclipse.birt.report.engine.executor.ReportExecutorVisitor.visitTableItem",
          "source": "ReportExecutorVisitor.java:188"
        },
        {
          "method": "org.eclipse.birt.report.engine.ir.TableItemDesign.accept",
          "source": "TableItemDes ign.java:69"
        },
        {
          "method": "org.eclipse.birt.report.engine.executor.ReportExecutor.execute",
          "source": "Report Executor.java:125"
        },
        {
          "method": "org.eclipse.birt.report.engine.executor.ReportExecutor.execute",
          "source": "Report Executor.java:89"
        },
        {
          "method": "org.eclipse.birt.report.engine.api.impl.RunAndRenderTask.run",
          "source": "RunAndRe nderTask.java:175"
        },
        {
          "method": "org.eclipse.birt.report.engine.api.ReportRunner.runAndRenderReport",
          "source": "Re portRunner.java:232"
        },
        {
          "method": "org.eclipse.birt.report.engine.api.ReportRunner.execute",
          "source": "ReportRunner. java:158"
        },
        {
          "method": "org.eclipse.birt.report.engine.api.ReportRunner.main",
          "source": "ReportRunner.jav a:129"
        }
      ],
      "number": 4,
      "commentIndex": 0,
      "bugId": "131514",
      "date": "2006-03-13T12:45:59+01:00",
      "product": "BIRT",
      "component": "Data",
      "severity": "normal"
    },
    {
      "exceptionType": "java.lang.NullPointerException",
      "elements": [
        {
          "method": "org.eclipse.birt.report.engine.api.HTMLActionHandler.buildDrillAction",
          "source": "HTMLActionHandler.java:88"
        },
        {
          "method": "org.eclipse.birt.report.engine.api.HTMLActionHandler.getURL",
          "source": "HTMLActio nHandler.java:55"
        },
        {
          "method": "org.eclipse.birt.report.engine.emitter.html.HTMLReportEmitter.handleAction",
          "source": "HTMLReportEmitter.java:1995"
        },
        {
          "method": "org.eclipse.birt.report.engine.emitter.html.HTMLReportEmitter.startText",
          "source": "HTMLReportEmitter.java:1184"
        },
        {
          "method": "org.eclipse.birt.report.engine.emitter.html.HTMLReportEmitter.startData",
          "source": "HTMLReportEmitter.java:1446"
        },
        {
          "method": "org.eclipse.birt.report.engine.presentation.WrappedEmitter.startData",
          "source": " WrappedEmitter.java:339"
        },
        {
          "method": "org.eclipse.birt.report.engine.presentation.LocalizedEmitter.startData",
          "source": "LocalizedEmitter.java:290"
        },
        {
          "method": "org.eclipse.birt.report.engine.presentation.WrappedEmitter.startData",
          "source": " WrappedEmitter.java:339"
        },
        {
          "method": "org.eclipse.birt.report.engine.presentation.DefaultPaginationEmitter.startData",
          "source": "DefaultPaginationEmitter.java:299"
        },
        {
          "method": "org.eclipse.birt.report.engine.executor.DataItemExecutor.execute",
          "source": "Data ItemExecutor.java:132"
        },
        {
          "method": "org.eclipse.birt.report.engine.executor.ReportExecutorVisitor.visitDataItem",
          "source": "ReportExecutorVisitor.java:158"
        },
        {
          "method": "org.eclipse.birt.report.engine.ir.DataItemDesign.accept",
          "source": "DataItemDesig n.java:69"
        },
        {
          "method": "org.eclipse.birt.report.engine.executor.TableItemExecutor.accessRow",
          "source": "T ableItemExecutor.java:590"
        },
        {
          "method": "org.eclipse.birt.report.engine.executor.TableItemExecutor.accessTableBand",
          "source": "TableItemExecutor.java:480"
        },
        {
          "method": "org.eclipse.birt.report.engine.executor.TableItemExecutor.accessGroupHeader",
          "source": "TableItemExecutor.java:441"
        },
        {
          "method": "org.eclipse.birt.report.engine.executor.ListingElementExecutor.accessQuery",
          "source": "ListingElementExecutor.java:162"
        },
        {
          "method": "org.eclipse.birt.report.engine.executor.TableItemExecutor.execute",
          "source": "Tab leItemExecutor.java:151"
        },
        {
          "method": "org.eclipse.birt.report.engine.executor.ReportExecutorVisitor.visitTableItem",
          "source": "ReportExecutorVisitor.java:188"
        },
        {
          "method": "org.eclipse.birt.report.engine.ir.TableItemDesign.accept",
          "source": "TableItemDes ign.java:69"
        },
        {
          "method": "org.eclipse.birt.report.engine.executor.ReportExecutor.execute",
          "source": "Report Executor.java:125"
        },
        {
          "method": "org.eclipse.birt.report.engine.executor.ReportExecutor.execute",
          "source": "Report Executor.java:89"
        },
        {
          "method": "org.eclipse.birt.report.engine.api.impl.RunAndRenderTask.run",
          "source": "RunAndRe nderTask.java:175"
        },
        {
          "method": "org.eclipse.birt.report.engine.api.ReportRunner.runAndRenderReport",
          "source": "Re portRunner.java:232"
        },
        {
          "method": "org.eclipse.birt.report.engine.api.ReportRunner.execute",
          "source": "ReportRunner. java:158"
        },
        {
          "method": "org.eclipse.birt.report.engine.api.ReportRunner.main",
          "source": "ReportRunner.jav a:129"
        }
      ],
      "number": 5,
      "commentIndex": 0,
      "bugId": "131514",
      "date": "2006-03-13T12:45:59+01:00",
      "product": "BIRT",
      "component": "Data",
      "severity": "normal"
    },
    {
      "exceptionType": "org.eclipse.birt.report.engine.api.EngineException",
      "message": "Error happened while running  the report",
      "elements": [
        {
          "method": "org.eclipse.birt.report.engine.api.impl.RunAndRenderTask.run",
          "source": "RunAndRe nderTask.java:186"
        },
        {
          "method": "org.eclipse.birt.report.engine.api.ReportRunner.runAndRenderReport",
          "source": "Re portRunner.java:232"
        },
        {
          "method": "org.eclipse.birt.report.engine.api.ReportRunner.execute",
          "source": "ReportRunner. java:158"
        },
        {
          "method": "org.eclipse.birt.report.engine.api.ReportRunner.main",
          "source": "ReportRunner.jav a:129"
        }
      ],
      "causedBy": {
        "exceptionType": "java.lang.NullPointerException",
        "elements": [
          {
            "method": "org.eclipse.birt.report.engine.api.HTMLActionHandler.buildDrillAction",
            "source": "HTMLActionHandler.java:88"
          },
          {
            "method": "org.eclipse.birt.report.engine.api.HTMLActionHandler.getURL",
            "source": "HTMLActio nHandler.java:55"
          },
          {
            "method": "org.eclipse.birt.report.engine.emitter.html.HTMLReportEmitter.handleAction",
            "source": "HTMLReportEmitter.java:1995"
          },
          {
            "method": "org.eclipse.birt.report.engine.emitter.html.HTMLReportEmitter.startText",
            "source": "HTMLReportEmitter.java:1184"
          },
          {
            "method": "org.eclipse.birt.report.engine.emitter.html.HTMLReportEmitter.startData",
            "source": "HTMLReportEmitter.java:1446"
          },
          {
            "method": "org.eclipse.birt.report.engine.presentation.WrappedEmitter.startData",
            "source": " WrappedEmitter.java:339"
          },
          {
            "method": "org.eclipse.birt.report.engine.presentation.LocalizedEmitter.startData",
            "source": "LocalizedEmitter.java:290"
          },
          {
            "method": "org.eclipse.birt.report.engine.presentation.WrappedEmitter.startData",
            "source": " WrappedEmitter.java:339"
          },
          {
            "method": "org.eclipse.birt.report.engine.presentation.DefaultPaginationEmitter.startData",
            "source": "DefaultPaginationEmitter.java:299"
          },
          {
            "method": "org.eclipse.birt.report.engine.executor.DataItemExecutor.execute",
            "source": "Data ItemExecutor.java:132"
          },
          {
            "method": "org.eclipse.birt.report.engine.executor.ReportExecutorVisitor.visitDataItem",
            "source": "ReportExecutorVisitor.java:158"
          },
          {
            "method": "org.eclipse.birt.report.engine.ir.DataItemDesign.accept",
            "source": "DataItemDesig n.java:69"
          },
          {
            "method": "org.eclipse.birt.report.engine.executor.TableItemExecutor.accessRow",
            "source": "T ableItemExecutor.java:590"
          },
          {
            "method": "org.eclipse.birt.report.engine.executor.TableItemExecutor.accessTableBand",
            "source": "TableItemExecutor.java:480"
          },
          {
            "method": "org.eclipse.birt.report.engine.executor.TableItemExecutor.accessGroupHeader",
            "source": "TableItemExecutor.java:441"
          },
          {
            "method": "org.eclipse.birt.report.engine.executor.ListingElementExecutor.accessQuery",
            "source": "ListingElementExecutor.java:162"
          },
          {
            "method": "org.eclipse.birt.report.engine.executor.TableItemExecutor.execute",
            "source": "Tab leItemExecutor.java:151"
          },
          {
            "method": "org.eclipse.birt.report.engine.executor.ReportExecutorVisitor.visitTableItem",
            "source": "ReportExecutorVisitor.java:188"
          },
          {
            "method": "org.eclipse.birt.report.engine.ir.TableItemDesign.accept",
            "source": "TableItemDes ign.java:69"
          },
          {
            "method": "org.eclipse.birt.report.engine.executor.ReportExecutor.execute",
            "source": "Report Executor.java:125"
          },
          {
            "method": "org.eclipse.birt.report.engine.executor.ReportExecutor.execute",
            "source": "Report Executor.java:89"
          },
          {
            "method": "org.eclipse.birt.report.engine.api.impl.RunAndRenderTask.run",
            "source": "RunAndRe nderTask.java:175"
          }
        ],
        "number": 0,
        "commentIndex": 0
      },
      "number": 6,
      "commentIndex": 0,
      "bugId": "131514",
      "date": "2006-03-13T12:45:59+01:00",
      "product": "BIRT",
      "component": "Data",
      "severity": "normal"
    }
  ],
  "groupId": "131514",
  "bugId": "131514",
  "date": "2006-03-13T12:45:59+01:00",
  "product": "BIRT",
  "component": "Data",
  "severity": "normal"
}