{
  "comments": [
    "Build date: 2006-03-09\n    Eclipse: (2006-02-23-1656)\n    EMF: (2006-03-09)\n    UML2: (S2006-03-02-1338)\nOS: Windows XP\nStep to recreate problem:\n\n1. Get UM2_2.0_DBCS_Conformatce_Test_Cases.doc from ftp://rtpgsa.raleigh.ibm.com/projects/w/wswb/anonymous/out/IES_3.2/Enablement%20Testcases/UML2/\n2. Perform Step 1 to Step 12 after following  the document.\n3. Perform Step 13 and fail to apply a stereotype. This happens under both ASCII and DBCS.\n4. The following error logs are displayed in console.\n\n----------------------------------------------------\n\n!SESSION 2006-03-14 11:20:14.796 -----------------------------------------------\neclipse.buildId\u003dI20060223-1656\njava.fullversion\u003dJ2RE 1.5.0 IBM J9 2.3 Windows XP x86-32 j9vmwi3223ifx-20060124 (JIT enabled)\nJ9VM - 20051027_03723_lHdSMR\nJIT  - 20051027_1437_r8\nGC   - 20051020_AA\nBootLoader constants: OS\u003dwin32, ARCH\u003dx86, WS\u003dwin32, NL\u003dja_JP\nCommand-line arguments:  -os win32 -ws win32 -arch x86 -clean -consolelog\n\n!ENTRY org.eclipse.uml2.editor 2 0 2006-03-14 11:31:12.093\n!MESSAGE java.lang.ClassNotFoundException: uml2__UnlimitedNatural\n!STACK 0\norg.eclipse.emf.common.util.WrappedException: java.lang.ClassNotFoundException: uml2__UnlimitedNatural\n        at org.eclipse.emf.ecore.impl.EClassifierImpl.getInstanceClass(EClassifierImpl.java:326)\n        at org.eclipse.emf.ecore.xmi.impl.XMLSaveImpl$Lookup.featureKind(XMLSaveImpl.java:2594)\n        at org.eclipse.emf.ecore.xmi.impl.XMLSaveImpl$Lookup.listKinds(XMLSaveImpl.java:2500)\n        at org.eclipse.emf.ecore.xmi.impl.XMLSaveImpl$Lookup.getFeatures(XMLSaveImpl.java:2437)\n        at org.eclipse.emf.ecore.xmi.impl.XMLSaveImpl.saveFeatures(XMLSaveImpl.java:1046)\n        at org.eclipse.emf.ecore.xmi.impl.XMLSaveImpl.saveElementID(XMLSaveImpl.java:2377)\n        at org.eclipse.emf.ecore.xmi.impl.XMLSaveImpl.saveElement(XMLSaveImpl.java:988)\n        at org.eclipse.emf.ecore.xmi.impl.XMLSaveImpl.saveElement(XMLSaveImpl.java:874)\n        at org.eclipse.emf.ecore.xmi.impl.XMLSaveImpl.saveContainedMany(XMLSaveImpl.java:2106)\n        at org.eclipse.emf.ecore.xmi.impl.XMLSaveImpl.saveFeatures(XMLSaveImpl.java:1334)\n        at org.eclipse.emf.ecore.xmi.impl.XMLSaveImpl.saveElementID(XMLSaveImpl.java:2377)\n        at org.eclipse.emf.ecore.xmi.impl.XMLSaveImpl.saveElement(XMLSaveImpl.java:988)\n        at org.eclipse.emf.ecore.xmi.impl.XMLSaveImpl.saveElement(XMLSaveImpl.java:874)\n        at org.eclipse.emf.ecore.xmi.impl.XMLSaveImpl.saveContainedMany(XMLSaveImpl.java:2106)\n        at org.eclipse.emf.ecore.xmi.impl.XMLSaveImpl.saveFeatures(XMLSaveImpl.java:1334)\n        at org.eclipse.emf.ecore.xmi.impl.XMLSaveImpl.saveElementID(XMLSaveImpl.java:2377)\n        at org.eclipse.emf.ecore.xmi.impl.XMLSaveImpl.saveElement(XMLSaveImpl.java:988)\n        at org.eclipse.emf.ecore.xmi.impl.XMLSaveImpl.saveElement(XMLSaveImpl.java:874)\n        at org.eclipse.emf.ecore.xmi.impl.XMLSaveImpl.saveContainedMany(XMLSaveImpl.java:2106)\n        at org.eclipse.emf.ecore.xmi.impl.XMLSaveImpl.saveFeatures(XMLSaveImpl.java:1334)\n        at org.eclipse.emf.ecore.xmi.impl.XMLSaveImpl.saveElementID(XMLSaveImpl.java:2377)\n        at org.eclipse.emf.ecore.xmi.impl.XMLSaveImpl.saveElement(XMLSaveImpl.java:988)\n        at org.eclipse.emf.ecore.xmi.impl.XMLSaveImpl.saveElement(XMLSaveImpl.java:874)\n        at org.eclipse.emf.ecore.xmi.impl.XMLSaveImpl.saveContainedMany(XMLSaveImpl.java:2106)\n        at org.eclipse.emf.ecore.xmi.impl.XMLSaveImpl.saveFeatures(XMLSaveImpl.java:1334)\n        at org.eclipse.emf.ecore.xmi.impl.XMLSaveImpl.saveElementID(XMLSaveImpl.java:2377)\n        at org.eclipse.emf.ecore.xmi.impl.XMLSaveImpl.writeTopObject(XMLSaveImpl.java:577)\n        at org.eclipse.emf.ecore.xmi.impl.XMLSaveImpl.traverse(XMLSaveImpl.java:511)\n        at org.eclipse.emf.ecore.xmi.impl.XMLSaveImpl.save(XMLSaveImpl.java:229)\n        at org.eclipse.emf.ecore.xmi.impl.XMLResourceImpl.doSave(XMLResourceImpl.java:198)\n        at org.eclipse.emf.ecore.resource.impl.ResourceImpl.save(ResourceImpl.java:944)\n        at org.eclipse.emf.ecore.resource.impl.ResourceImpl.save(ResourceImpl.java:853)\n        at org.eclipse.uml2.presentation.UML2Editor$19.execute(UML2Editor.java:1214)\n        at org.eclipse.ui.actions.WorkspaceModifyOperation$1.run(WorkspaceModifyOperation.java:100)\n        at org.eclipse.core.internal.resources.Workspace.run(Workspace.java:1733)\n        at org.eclipse.ui.actions.WorkspaceModifyOperation.run(WorkspaceModifyOperation.java:112)\n        at org.eclipse.jface.operation.ModalContext$ModalContextThread.run(ModalContext.java:113)\nCaused by: java.lang.ClassNotFoundException: uml2__UnlimitedNatural\n        at java.lang.Class.forName(Class.java:164)\n        at org.eclipse.emf.ecore.impl.EClassifierImpl.getClassForName(EClassifierImpl.java:341)\n        at org.eclipse.emf.ecore.impl.EClassifierImpl.getInstanceClass(EClassifierImpl.java:318)\n        ... 36 more",
    "\n\n*** This bug has been marked as a duplicate of 131180 ***",
    "Note that you have chosen the wrong type for the stereotype property - it should be UML2::UnlimitedNatural instead of uml2::UnlimitedNatural (difference in case). This kind of issue will be less likely in .uml models (second part of test suite) since the primitive type library has been renamed to \"UMLPrimitiveTypes\" (hence there aren\u0027t two types with such similar names).",
    "I made sure the function worked well on Build20060309. Thank you."
  ],
  "commentCreationDates": [
    "2006-03-14T03:27:22+01:00",
    "2006-03-14T18:25:34+01:00",
    "2006-03-14T18:28:03+01:00",
    "2006-03-28T05:20:07+02:00"
  ],
  "traces": [
    {
      "exceptionType": "java.lang.ClassNotFoundException",
      "message": "uml2__UnlimitedNatural",
      "elements": [
        {
          "method": "org.eclipse.emf.ecore.impl.EClassifierImpl.getInstanceClass",
          "source": "EClassifierImpl.java:326"
        },
        {
          "method": "org.eclipse.emf.ecore.xmi.impl.XMLSaveImpl$Lookup.featureKind",
          "source": "XMLSaveImpl.java:2594"
        },
        {
          "method": "org.eclipse.emf.ecore.xmi.impl.XMLSaveImpl$Lookup.listKinds",
          "source": "XMLSaveImpl.java:2500"
        },
        {
          "method": "org.eclipse.emf.ecore.xmi.impl.XMLSaveImpl$Lookup.getFeatures",
          "source": "XMLSaveImpl.java:2437"
        },
        {
          "method": "org.eclipse.emf.ecore.xmi.impl.XMLSaveImpl.saveFeatures",
          "source": "XMLSaveImpl.java:1046"
        },
        {
          "method": "org.eclipse.emf.ecore.xmi.impl.XMLSaveImpl.saveElementID",
          "source": "XMLSaveImpl.java:2377"
        },
        {
          "method": "org.eclipse.emf.ecore.xmi.impl.XMLSaveImpl.saveElement",
          "source": "XMLSaveImpl.java:988"
        },
        {
          "method": "org.eclipse.emf.ecore.xmi.impl.XMLSaveImpl.saveElement",
          "source": "XMLSaveImpl.java:874"
        },
        {
          "method": "org.eclipse.emf.ecore.xmi.impl.XMLSaveImpl.saveContainedMany",
          "source": "XMLSaveImpl.java:2106"
        },
        {
          "method": "org.eclipse.emf.ecore.xmi.impl.XMLSaveImpl.saveFeatures",
          "source": "XMLSaveImpl.java:1334"
        },
        {
          "method": "org.eclipse.emf.ecore.xmi.impl.XMLSaveImpl.saveElementID",
          "source": "XMLSaveImpl.java:2377"
        },
        {
          "method": "org.eclipse.emf.ecore.xmi.impl.XMLSaveImpl.saveElement",
          "source": "XMLSaveImpl.java:988"
        },
        {
          "method": "org.eclipse.emf.ecore.xmi.impl.XMLSaveImpl.saveElement",
          "source": "XMLSaveImpl.java:874"
        },
        {
          "method": "org.eclipse.emf.ecore.xmi.impl.XMLSaveImpl.saveContainedMany",
          "source": "XMLSaveImpl.java:2106"
        },
        {
          "method": "org.eclipse.emf.ecore.xmi.impl.XMLSaveImpl.saveFeatures",
          "source": "XMLSaveImpl.java:1334"
        },
        {
          "method": "org.eclipse.emf.ecore.xmi.impl.XMLSaveImpl.saveElementID",
          "source": "XMLSaveImpl.java:2377"
        },
        {
          "method": "org.eclipse.emf.ecore.xmi.impl.XMLSaveImpl.saveElement",
          "source": "XMLSaveImpl.java:988"
        },
        {
          "method": "org.eclipse.emf.ecore.xmi.impl.XMLSaveImpl.saveElement",
          "source": "XMLSaveImpl.java:874"
        },
        {
          "method": "org.eclipse.emf.ecore.xmi.impl.XMLSaveImpl.saveContainedMany",
          "source": "XMLSaveImpl.java:2106"
        },
        {
          "method": "org.eclipse.emf.ecore.xmi.impl.XMLSaveImpl.saveFeatures",
          "source": "XMLSaveImpl.java:1334"
        },
        {
          "method": "org.eclipse.emf.ecore.xmi.impl.XMLSaveImpl.saveElementID",
          "source": "XMLSaveImpl.java:2377"
        },
        {
          "method": "org.eclipse.emf.ecore.xmi.impl.XMLSaveImpl.saveElement",
          "source": "XMLSaveImpl.java:988"
        },
        {
          "method": "org.eclipse.emf.ecore.xmi.impl.XMLSaveImpl.saveElement",
          "source": "XMLSaveImpl.java:874"
        },
        {
          "method": "org.eclipse.emf.ecore.xmi.impl.XMLSaveImpl.saveContainedMany",
          "source": "XMLSaveImpl.java:2106"
        },
        {
          "method": "org.eclipse.emf.ecore.xmi.impl.XMLSaveImpl.saveFeatures",
          "source": "XMLSaveImpl.java:1334"
        },
        {
          "method": "org.eclipse.emf.ecore.xmi.impl.XMLSaveImpl.saveElementID",
          "source": "XMLSaveImpl.java:2377"
        },
        {
          "method": "org.eclipse.emf.ecore.xmi.impl.XMLSaveImpl.writeTopObject",
          "source": "XMLSaveImpl.java:577"
        },
        {
          "method": "org.eclipse.emf.ecore.xmi.impl.XMLSaveImpl.traverse",
          "source": "XMLSaveImpl.java:511"
        },
        {
          "method": "org.eclipse.emf.ecore.xmi.impl.XMLSaveImpl.save",
          "source": "XMLSaveImpl.java:229"
        },
        {
          "method": "org.eclipse.emf.ecore.xmi.impl.XMLResourceImpl.doSave",
          "source": "XMLResourceImpl.java:198"
        },
        {
          "method": "org.eclipse.emf.ecore.resource.impl.ResourceImpl.save",
          "source": "ResourceImpl.java:944"
        },
        {
          "method": "org.eclipse.emf.ecore.resource.impl.ResourceImpl.save",
          "source": "ResourceImpl.java:853"
        },
        {
          "method": "org.eclipse.uml2.presentation.UML2Editor$19.execute",
          "source": "UML2Editor.java:1214"
        },
        {
          "method": "org.eclipse.ui.actions.WorkspaceModifyOperation$1.run",
          "source": "WorkspaceModifyOperation.java:100"
        },
        {
          "method": "org.eclipse.core.internal.resources.Workspace.run",
          "source": "Workspace.java:1733"
        },
        {
          "method": "org.eclipse.ui.actions.WorkspaceModifyOperation.run",
          "source": "WorkspaceModifyOperation.java:112"
        },
        {
          "method": "org.eclipse.jface.operation.ModalContext$ModalContextThread.run",
          "source": "ModalContext.java:113"
        }
      ],
      "causedBy": {
        "exceptionType": "java.lang.ClassNotFoundException",
        "message": "uml2__UnlimitedNatural",
        "elements": [
          {
            "method": "java.lang.Class.forName",
            "source": "Class.java:164"
          },
          {
            "method": "org.eclipse.emf.ecore.impl.EClassifierImpl.getClassForName",
            "source": "EClassifierImpl.java:341"
          },
          {
            "method": "org.eclipse.emf.ecore.impl.EClassifierImpl.getInstanceClass",
            "source": "EClassifierImpl.java:318"
          }
        ],
        "number": 0,
        "commentIndex": 0
      },
      "number": 0,
      "commentIndex": 0,
      "bugId": "131646",
      "duplicateId": "131180",
      "date": "2006-03-14T03:27:22+01:00",
      "product": "MDT",
      "component": "UML2",
      "severity": "normal"
    }
  ],
  "groupId": "131180",
  "bugId": "131646",
  "duplicateId": "131180",
  "date": "2006-03-14T03:27:22+01:00",
  "product": "MDT",
  "component": "UML2",
  "severity": "normal"
}