{
  "comments": [
    "Note that this can be reproduced in a pure WTP environment (no adopter code present)\n\nTo recreate,\n\n1) Create an ejb project with a single CMP ejb.\n2) Shut down and re-start eclipse.\n3) In the common navigator, expand the node representing the CMP.\n\nSome of the children of the CMP node are missing, and the following exception is written to the console:\n\norg.eclipse.swt.SWTException: Widget is disposed\n        at org.eclipse.swt.SWT.error(SWT.java:2942)\n        at org.eclipse.swt.SWT.error(SWT.java(Inlined Compiled Code))\n        at org.eclipse.swt.SWT.error(SWT.java(Inlined Compiled Code))\n        at org.eclipse.swt.widgets.Widget.error(Widget.java(Inlined Compiled Code))\n        at org.eclipse.swt.widgets.Widget.checkWidget(Widget.java(Compiled Code))\n        at org.eclipse.swt.widgets.TreeItem.getItemCount(TreeItem.java:566)\n        at org.eclipse.jface.viewers.TreeViewer.getItemCount(TreeViewer.java:379)\n        at org.eclipse.jface.viewers.AbstractTreeViewer.updatePlus(AbstractTreeViewer.java:1844)\n        at org.eclipse.jface.viewers.AbstractTreeViewer.createTreeItem(AbstractTreeViewer.java:536)\n        at org.eclipse.wst.common.navigator.internal.provisional.views.CommonViewer.createTreeItem(CommonViewer.java:201)\n        at org.eclipse.jface.viewers.AbstractTreeViewer$1.run(AbstractTreeViewer.java:514)\n        at org.eclipse.swt.custom.BusyIndicator.showWhile(BusyIndicator.java:69)\n        at org.eclipse.jface.viewers.AbstractTreeViewer.createChildren(AbstractTreeViewer.java:494)\n        at org.eclipse.jface.viewers.AbstractTreeViewer.handleTreeExpand(AbstractTreeViewer.java:948)\n        at org.eclipse.jface.viewers.AbstractTreeViewer$4.treeExpanded(AbstractTreeViewer.java:959)\n        at org.eclipse.swt.widgets.TypedListener.handleEvent(TypedListener.java:180)\n        at org.eclipse.swt.widgets.EventTable.sendEvent(EventTable.java(Compiled Code))\n        at org.eclipse.swt.widgets.Widget.sendEvent(Widget.java:843)\n        at org.eclipse.swt.widgets.Widget.sendEvent(Widget.java:867)\n        at org.eclipse.swt.widgets.Widget.sendEvent(Widget.java:852)\n        at org.eclipse.swt.widgets.Tree.wmNotifyChild(Tree.java:3704)\n        at org.eclipse.swt.widgets.Control.WM_NOTIFY(Control.java:3568)\n        at org.eclipse.swt.widgets.Composite.WM_NOTIFY(Composite.java:1035)\n        at org.eclipse.swt.widgets.Control.windowProc(Control.java(Compiled Code))\n        at org.eclipse.swt.widgets.Display.windowProc(Display.java(Compiled Code))\n        at org.eclipse.swt.internal.win32.OS.CallWindowProcW(Native Method)\n        at org.eclipse.swt.internal.win32.OS.CallWindowProc(OS.java(Inlined Compiled Code))\n        at org.eclipse.swt.widgets.Tree.callWindowProc(Tree.java(Compiled Code))\n        at org.eclipse.swt.widgets.Tree.WM_LBUTTONDOWN(Tree.java:2815)\n        at org.eclipse.swt.widgets.Control.windowProc(Control.java(Compiled Code))\n        at org.eclipse.swt.widgets.Tree.windowProc(Tree.java(Compiled Code))\n        at org.eclipse.swt.widgets.Display.windowProc(Display.java(Compiled Code))\n        at org.eclipse.swt.internal.win32.OS.DispatchMessageW(Native Method)\n        at org.eclipse.swt.internal.win32.OS.DispatchMessage(OS.java(Inlined Compiled Code))\n        at org.eclipse.swt.widgets.Display.readAndDispatch(Display.java(Compiled Code))\n        at org.eclipse.ui.internal.Workbench.runEventLoop(Workbench.java(Compiled Code))\n        at org.eclipse.ui.internal.Workbench.runUI(Workbench.java:1663)\n        at org.eclipse.ui.internal.Workbench.createAndRunWorkbench(Workbench.java:367)\n        at org.eclipse.ui.PlatformUI.createAndRunWorkbench(PlatformUI.java:143)\n        at org.eclipse.ui.internal.ide.IDEApplication.run(IDEApplication.java:103)\n        at org.eclipse.core.internal.runtime.PlatformActivator$1.run(PlatformActivator.java:226)\n        at org.eclipse.core.runtime.adaptor.EclipseStarter.run(EclipseStarter.java:376)\n        at org.eclipse.core.runtime.adaptor.EclipseStarter.run(EclipseStarter.java:163)\n        at sun.reflect.NativeMethodAccessorImpl.invoke0(Native Method)\n        at sun.reflect.NativeMethodAccessorImpl.invoke(NativeMethodAccessorImpl.java:85)\n        at sun.reflect.NativeMethodAccessorImpl.invoke(NativeMethodAccessorImpl.java:58)\n        at sun.reflect.DelegatingMethodAccessorImpl.invoke(DelegatingMethodAccessorImpl.java:60)\n        at java.lang.reflect.Method.invoke(Method.java:391)\n        at org.eclipse.core.launcher.Main.invokeFramework(Main.java:334)\n        at org.eclipse.core.launcher.Main.basicRun(Main.java:278)\n        at org.eclipse.core.launcher.Main.run(Main.java:973)\n        at org.eclipse.core.launcher.Main.main(Main.java:948)",
    "Added to the 1.0.2 hot list. Setting priority to P2.",
    "This is fixed for the 03/16/06 WTP 1.0.2 build and the 1.5 head stream.",
    "Verified that this functionality works.",
    "Closing as verified."
  ],
  "commentCreationDates": [
    "2006-03-14T16:48:28+01:00",
    "2006-03-14T20:31:37+01:00",
    "2006-03-15T16:45:35+01:00",
    "2006-09-26T19:12:02+02:00",
    "2006-09-26T20:50:40+02:00"
  ],
  "traces": [
    {
      "exceptionType": "org.eclipse.swt.SWTException",
      "message": "Widget is disposed",
      "elements": [
        {
          "method": "org.eclipse.swt.SWT.error",
          "source": "SWT.java:2942"
        },
        {
          "method": "org.eclipse.swt.SWT.error",
          "source": "SWT.java(Inlined Compiled Code)"
        },
        {
          "method": "org.eclipse.swt.SWT.error",
          "source": "SWT.java(Inlined Compiled Code)"
        },
        {
          "method": "org.eclipse.swt.widgets.Widget.error",
          "source": "Widget.java(Inlined Compiled Code)"
        },
        {
          "method": "org.eclipse.swt.widgets.Widget.checkWidget",
          "source": "Widget.java(Compiled Code)"
        },
        {
          "method": "org.eclipse.swt.widgets.TreeItem.getItemCount",
          "source": "TreeItem.java:566"
        },
        {
          "method": "org.eclipse.jface.viewers.TreeViewer.getItemCount",
          "source": "TreeViewer.java:379"
        },
        {
          "method": "org.eclipse.jface.viewers.AbstractTreeViewer.updatePlus",
          "source": "AbstractTreeViewer.java:1844"
        },
        {
          "method": "org.eclipse.jface.viewers.AbstractTreeViewer.createTreeItem",
          "source": "AbstractTreeViewer.java:536"
        },
        {
          "method": "org.eclipse.wst.common.navigator.internal.provisional.views.CommonViewer.createTreeItem",
          "source": "CommonViewer.java:201"
        },
        {
          "method": "org.eclipse.jface.viewers.AbstractTreeViewer$1.run",
          "source": "AbstractTreeViewer.java:514"
        },
        {
          "method": "org.eclipse.swt.custom.BusyIndicator.showWhile",
          "source": "BusyIndicator.java:69"
        },
        {
          "method": "org.eclipse.jface.viewers.AbstractTreeViewer.createChildren",
          "source": "AbstractTreeViewer.java:494"
        },
        {
          "method": "org.eclipse.jface.viewers.AbstractTreeViewer.handleTreeExpand",
          "source": "AbstractTreeViewer.java:948"
        },
        {
          "method": "org.eclipse.jface.viewers.AbstractTreeViewer$4.treeExpanded",
          "source": "AbstractTreeViewer.java:959"
        },
        {
          "method": "org.eclipse.swt.widgets.TypedListener.handleEvent",
          "source": "TypedListener.java:180"
        },
        {
          "method": "org.eclipse.swt.widgets.EventTable.sendEvent",
          "source": "EventTable.java(Compiled Code)"
        },
        {
          "method": "org.eclipse.swt.widgets.Widget.sendEvent",
          "source": "Widget.java:843"
        },
        {
          "method": "org.eclipse.swt.widgets.Widget.sendEvent",
          "source": "Widget.java:867"
        },
        {
          "method": "org.eclipse.swt.widgets.Widget.sendEvent",
          "source": "Widget.java:852"
        },
        {
          "method": "org.eclipse.swt.widgets.Tree.wmNotifyChild",
          "source": "Tree.java:3704"
        },
        {
          "method": "org.eclipse.swt.widgets.Control.WM_NOTIFY",
          "source": "Control.java:3568"
        },
        {
          "method": "org.eclipse.swt.widgets.Composite.WM_NOTIFY",
          "source": "Composite.java:1035"
        },
        {
          "method": "org.eclipse.swt.widgets.Control.windowProc",
          "source": "Control.java(Compiled Code)"
        },
        {
          "method": "org.eclipse.swt.widgets.Display.windowProc",
          "source": "Display.java(Compiled Code)"
        },
        {
          "method": "org.eclipse.swt.internal.win32.OS.CallWindowProcW",
          "source": "Native Method"
        },
        {
          "method": "org.eclipse.swt.internal.win32.OS.CallWindowProc",
          "source": "OS.java(Inlined Compiled Code)"
        },
        {
          "method": "org.eclipse.swt.widgets.Tree.callWindowProc",
          "source": "Tree.java(Compiled Code)"
        },
        {
          "method": "org.eclipse.swt.widgets.Tree.WM_LBUTTONDOWN",
          "source": "Tree.java:2815"
        },
        {
          "method": "org.eclipse.swt.widgets.Control.windowProc",
          "source": "Control.java(Compiled Code)"
        },
        {
          "method": "org.eclipse.swt.widgets.Tree.windowProc",
          "source": "Tree.java(Compiled Code)"
        },
        {
          "method": "org.eclipse.swt.widgets.Display.windowProc",
          "source": "Display.java(Compiled Code)"
        },
        {
          "method": "org.eclipse.swt.internal.win32.OS.DispatchMessageW",
          "source": "Native Method"
        },
        {
          "method": "org.eclipse.swt.internal.win32.OS.DispatchMessage",
          "source": "OS.java(Inlined Compiled Code)"
        },
        {
          "method": "org.eclipse.swt.widgets.Display.readAndDispatch",
          "source": "Display.java(Compiled Code)"
        },
        {
          "method": "org.eclipse.ui.internal.Workbench.runEventLoop",
          "source": "Workbench.java(Compiled Code)"
        },
        {
          "method": "org.eclipse.ui.internal.Workbench.runUI",
          "source": "Workbench.java:1663"
        },
        {
          "method": "org.eclipse.ui.internal.Workbench.createAndRunWorkbench",
          "source": "Workbench.java:367"
        },
        {
          "method": "org.eclipse.ui.PlatformUI.createAndRunWorkbench",
          "source": "PlatformUI.java:143"
        },
        {
          "method": "org.eclipse.ui.internal.ide.IDEApplication.run",
          "source": "IDEApplication.java:103"
        },
        {
          "method": "org.eclipse.core.internal.runtime.PlatformActivator$1.run",
          "source": "PlatformActivator.java:226"
        },
        {
          "method": "org.eclipse.core.runtime.adaptor.EclipseStarter.run",
          "source": "EclipseStarter.java:376"
        },
        {
          "method": "org.eclipse.core.runtime.adaptor.EclipseStarter.run",
          "source": "EclipseStarter.java:163"
        },
        {
          "method": "sun.reflect.NativeMethodAccessorImpl.invoke0",
          "source": "Native Method"
        },
        {
          "method": "sun.reflect.NativeMethodAccessorImpl.invoke",
          "source": "NativeMethodAccessorImpl.java:85"
        },
        {
          "method": "sun.reflect.NativeMethodAccessorImpl.invoke",
          "source": "NativeMethodAccessorImpl.java:58"
        },
        {
          "method": "sun.reflect.DelegatingMethodAccessorImpl.invoke",
          "source": "DelegatingMethodAccessorImpl.java:60"
        },
        {
          "method": "java.lang.reflect.Method.invoke",
          "source": "Method.java:391"
        },
        {
          "method": "org.eclipse.core.launcher.Main.invokeFramework",
          "source": "Main.java:334"
        },
        {
          "method": "org.eclipse.core.launcher.Main.basicRun",
          "source": "Main.java:278"
        },
        {
          "method": "org.eclipse.core.launcher.Main.run",
          "source": "Main.java:973"
        },
        {
          "method": "org.eclipse.core.launcher.Main.main",
          "source": "Main.java:948"
        }
      ],
      "number": 0,
      "commentIndex": 0,
      "bugId": "131736",
      "date": "2006-03-14T16:48:28+01:00",
      "product": "Web Tools",
      "component": "wst.common",
      "severity": "critical"
    }
  ],
  "groupId": "131736",
  "bugId": "131736",
  "date": "2006-03-14T16:48:28+01:00",
  "product": "Web Tools",
  "component": "wst.common",
  "severity": "critical"
}