{
  "comments": [
    "Using I0309, I got this exception in the log.\nI don\u0027t have steps to reproduce.\n\njava.lang.NullPointerException\n        at\norg.eclipse.core.internal.filesystem.InternalFileSystemCore.getStore(InternalFileSystemCore.java:104)\n        at org.eclipse.core.filesystem.EFS.getStore(EFS.java:296)\n        at org.eclipse.jdt.internal.core.util.Util.toLocalFile(Util.java:2044)\n        at\norg.eclipse.jdt.internal.core.builder.ClasspathJar.\u003cinit\u003e(ClasspathJar.java:91)\n        at\norg.eclipse.jdt.internal.core.builder.ClasspathLocation.forLibrary(ClasspathLocation.java:38)\n        at org.eclipse.jdt.internal.core.builder.State.read(State.java:255)\n        at\norg.eclipse.jdt.internal.core.builder.JavaBuilder.readState(JavaBuilder.java:125)\n        at\norg.eclipse.jdt.internal.core.JavaModelManager.readState(JavaModelManager.java:2586)\n        at\norg.eclipse.jdt.internal.core.JavaModelManager.getLastBuiltState(JavaModelManager.java:1365)\n        at\norg.eclipse.jdt.internal.core.builder.JavaBuilder.getLastState(JavaBuilder.java:367)\n        at\norg.eclipse.jdt.internal.core.builder.JavaBuilder.build(JavaBuilder.java:150)\n        at\norg.eclipse.core.internal.events.BuildManager$2.run(BuildManager.java:593)\n        at org.eclipse.core.runtime.SafeRunner.run(SafeRunner.java:37)\n        at\norg.eclipse.core.internal.events.BuildManager.basicBuild(BuildManager.java:168)\n        at\norg.eclipse.core.internal.events.BuildManager.basicBuild(BuildManager.java:202)\n        at\norg.eclipse.core.internal.events.BuildManager$1.run(BuildManager.java:231)\n        at org.eclipse.core.runtime.SafeRunner.run(SafeRunner.java:37)\n        at\norg.eclipse.core.internal.events.BuildManager.basicBuild(BuildManager.java:234)\n        at\norg.eclipse.core.internal.events.BuildManager.basicBuildLoop(BuildManager.java:253)\n        at\norg.eclipse.core.internal.events.BuildManager.build(BuildManager.java:282)\n        at\norg.eclipse.core.internal.events.AutoBuildJob.doBuild(AutoBuildJob.java:143)\n        at\norg.eclipse.core.internal.events.AutoBuildJob.run(AutoBuildJob.java:204)\n        at org.eclipse.core.internal.jobs.Worker.run(Worker.java:58)\norg.eclipse.core.runtime.CoreException[2]: java.lang.NullPointerException\n        at\norg.eclipse.core.internal.filesystem.InternalFileSystemCore.getStore(InternalFileSystemCore.java:104)\n        at org.eclipse.core.filesystem.EFS.getStore(EFS.java:296)\n        at org.eclipse.jdt.internal.core.util.Util.toLocalFile(Util.java:2044)\n        at\norg.eclipse.jdt.internal.core.builder.ClasspathJar.\u003cinit\u003e(ClasspathJar.java:91)\n        at\norg.eclipse.jdt.internal.core.builder.ClasspathLocation.forLibrary(ClasspathLocation.java:38)\n        at org.eclipse.jdt.internal.core.builder.State.read(State.java:255)\n        at\norg.eclipse.jdt.internal.core.builder.JavaBuilder.readState(JavaBuilder.java:125)\n        at\norg.eclipse.jdt.internal.core.JavaModelManager.readState(JavaModelManager.java:2586)\n        at\norg.eclipse.jdt.internal.core.JavaModelManager.getLastBuiltState(JavaModelManager.java:1365)\n        at\norg.eclipse.jdt.internal.core.builder.JavaBuilder.getLastState(JavaBuilder.java:367)\n        at\norg.eclipse.jdt.internal.core.builder.JavaBuilder.build(JavaBuilder.java:150)\n        at\norg.eclipse.core.internal.events.BuildManager$2.run(BuildManager.java:593)\n        at org.eclipse.core.runtime.SafeRunner.run(SafeRunner.java:37)\n        at\norg.eclipse.core.internal.events.BuildManager.basicBuild(BuildManager.java:168)\n        at\norg.eclipse.core.internal.events.BuildManager.basicBuild(BuildManager.java:202)\n        at\norg.eclipse.core.internal.events.BuildManager$1.run(BuildManager.java:231)\n        at org.eclipse.core.runtime.SafeRunner.run(SafeRunner.java:37)\n        at\norg.eclipse.core.internal.events.BuildManager.basicBuild(BuildManager.java:234)\n        at\norg.eclipse.core.internal.events.BuildManager.basicBuildLoop(BuildManager.java:253)\n        at\norg.eclipse.core.internal.events.BuildManager.build(BuildManager.java:282)\n        at\norg.eclipse.core.internal.events.AutoBuildJob.doBuild(AutoBuildJob.java:143)\n        at\norg.eclipse.core.internal.events.AutoBuildJob.run(AutoBuildJob.java:204)\n        at org.eclipse.core.internal.jobs.Worker.run(Worker.java:58)\njava.lang.NullPointerException\n        at\norg.eclipse.core.internal.filesystem.InternalFileSystemCore.getStore(InternalFileSystemCore.java:104)\n        at org.eclipse.core.filesystem.EFS.getStore(EFS.java:296)\n        at org.eclipse.jdt.internal.core.util.Util.toLocalFile(Util.java:2044)\n        at\norg.eclipse.jdt.internal.core.builder.ClasspathJar.\u003cinit\u003e(ClasspathJar.java:91)\n        at\norg.eclipse.jdt.internal.core.builder.ClasspathLocation.forLibrary(ClasspathLocation.java:38)\n        at org.eclipse.jdt.internal.core.builder.State.read(State.java:255)\n        at\norg.eclipse.jdt.internal.core.builder.JavaBuilder.readState(JavaBuilder.java:125)\n        at\norg.eclipse.jdt.internal.core.JavaModelManager.readState(JavaModelManager.java:2586)\n        at\norg.eclipse.jdt.internal.core.JavaModelManager.getLastBuiltState(JavaModelManager.java:1365)\n        at\norg.eclipse.jdt.internal.core.builder.JavaBuilder.getLastState(JavaBuilder.java:367)\n        at\norg.eclipse.jdt.internal.core.builder.JavaBuilder.build(JavaBuilder.java:150)\n        at\norg.eclipse.core.internal.events.BuildManager$2.run(BuildManager.java:593)\n        at org.eclipse.core.runtime.SafeRunner.run(SafeRunner.java:37)\n        at\norg.eclipse.core.internal.events.BuildManager.basicBuild(BuildManager.java:168)\n        at\norg.eclipse.core.internal.events.BuildManager.basicBuild(BuildManager.java:202)\n        at\norg.eclipse.core.internal.events.BuildManager$1.run(BuildManager.java:231)\n        at org.eclipse.core.runtime.SafeRunner.run(SafeRunner.java:37)\n        at\norg.eclipse.core.internal.events.BuildManager.basicBuild(BuildManager.java:234)\n        at\norg.eclipse.core.internal.events.BuildManager.basicBuildLoop(BuildManager.java:253)\n        at\norg.eclipse.core.internal.events.BuildManager.build(BuildManager.java:282)\n        at\norg.eclipse.core.internal.events.AutoBuildJob.doBuild(AutoBuildJob.java:143)\n        at\norg.eclipse.core.internal.events.AutoBuildJob.run(AutoBuildJob.java:204)\n        at org.eclipse.core.internal.jobs.Worker.run(Worker.java:58)\norg.eclipse.core.runtime.CoreException[2]: java.lang.NullPointerException\n        at\norg.eclipse.core.internal.filesystem.InternalFileSystemCore.getStore(InternalFileSystemCore.java:104)\n        at org.eclipse.core.filesystem.EFS.getStore(EFS.java:296)\n        at org.eclipse.jdt.internal.core.util.Util.toLocalFile(Util.java:2044)\n        at\norg.eclipse.jdt.internal.core.builder.ClasspathJar.\u003cinit\u003e(ClasspathJar.java:91)\n        at\norg.eclipse.jdt.internal.core.builder.ClasspathLocation.forLibrary(ClasspathLocation.java:38)\n        at org.eclipse.jdt.internal.core.builder.State.read(State.java:255)\n        at\norg.eclipse.jdt.internal.core.builder.JavaBuilder.readState(JavaBuilder.java:125)\n        at\norg.eclipse.jdt.internal.core.JavaModelManager.readState(JavaModelManager.java:2586)\n        at\norg.eclipse.jdt.internal.core.JavaModelManager.getLastBuiltState(JavaModelManager.java:1365)\n        at\norg.eclipse.jdt.internal.core.builder.JavaBuilder.getLastState(JavaBuilder.java:367)\n        at\norg.eclipse.jdt.internal.core.builder.JavaBuilder.build(JavaBuilder.java:150)\n        at\norg.eclipse.core.internal.events.BuildManager$2.run(BuildManager.java:593)\n        at org.eclipse.core.runtime.SafeRunner.run(SafeRunner.java:37)\n        at\norg.eclipse.core.internal.events.BuildManager.basicBuild(BuildManager.java:168)\n        at\norg.eclipse.core.internal.events.BuildManager.basicBuild(BuildManager.java:202)\n        at\norg.eclipse.core.internal.events.BuildManager$1.run(BuildManager.java:231)\n        at org.eclipse.core.runtime.SafeRunner.run(SafeRunner.java:37)\n        at\norg.eclipse.core.internal.events.BuildManager.basicBuild(BuildManager.java:234)\n        at\norg.eclipse.core.internal.events.BuildManager.basicBuildLoop(BuildManager.java:253)\n        at\norg.eclipse.core.internal.events.BuildManager.build(BuildManager.java:282)\n        at\norg.eclipse.core.internal.events.AutoBuildJob.doBuild(AutoBuildJob.java:143)\n        at\norg.eclipse.core.internal.events.AutoBuildJob.run(AutoBuildJob.java:204)\n        at org.eclipse.core.internal.jobs.Worker.run(Worker.java:58)",
    "John - any ideas?\n\nIs this something we need to handle or is it your bug?",
    "The problem is in ClasspathJar:\n\nUtil.toLocalFile(resource.getLocationURI(), null)\n\nThe NPE is caused by resource.getLocationURI() returning null. This means the resource\u0027s project does not exist.",
    "Added NPE check that was removed when moving from getLocation() to getLocationURI()",
    "Verified for 3.2 M6 using build I20060329-0010.\n"
  ],
  "commentCreationDates": [
    "2006-03-21T01:29:31+01:00",
    "2006-03-21T08:41:51+01:00",
    "2006-03-27T16:27:49+02:00",
    "2006-03-28T16:54:55+02:00",
    "2006-03-29T11:40:23+02:00"
  ],
  "traces": [
    {
      "exceptionType": "java.lang.NullPointerException",
      "elements": [
        {
          "method": "org.eclipse.core.internal.filesystem.InternalFileSystemCore.getStore",
          "source": "InternalFileSystemCore.java:104"
        },
        {
          "method": "org.eclipse.core.filesystem.EFS.getStore",
          "source": "EFS.java:296"
        },
        {
          "method": "org.eclipse.jdt.internal.core.util.Util.toLocalFile",
          "source": "Util.java:2044"
        },
        {
          "method": "org.eclipse.jdt.internal.core.builder.ClasspathJar.\u003cinit\u003e",
          "source": "ClasspathJar.java:91"
        },
        {
          "method": "org.eclipse.jdt.internal.core.builder.ClasspathLocation.forLibrary",
          "source": "ClasspathLocation.java:38"
        },
        {
          "method": "org.eclipse.jdt.internal.core.builder.State.read",
          "source": "State.java:255"
        },
        {
          "method": "org.eclipse.jdt.internal.core.builder.JavaBuilder.readState",
          "source": "JavaBuilder.java:125"
        },
        {
          "method": "org.eclipse.jdt.internal.core.JavaModelManager.readState",
          "source": "JavaModelManager.java:2586"
        },
        {
          "method": "org.eclipse.jdt.internal.core.JavaModelManager.getLastBuiltState",
          "source": "JavaModelManager.java:1365"
        },
        {
          "method": "org.eclipse.jdt.internal.core.builder.JavaBuilder.getLastState",
          "source": "JavaBuilder.java:367"
        },
        {
          "method": "org.eclipse.jdt.internal.core.builder.JavaBuilder.build",
          "source": "JavaBuilder.java:150"
        },
        {
          "method": "org.eclipse.core.internal.events.BuildManager$2.run",
          "source": "BuildManager.java:593"
        },
        {
          "method": "org.eclipse.core.runtime.SafeRunner.run",
          "source": "SafeRunner.java:37"
        },
        {
          "method": "org.eclipse.core.internal.events.BuildManager.basicBuild",
          "source": "BuildManager.java:168"
        },
        {
          "method": "org.eclipse.core.internal.events.BuildManager.basicBuild",
          "source": "BuildManager.java:202"
        },
        {
          "method": "org.eclipse.core.internal.events.BuildManager$1.run",
          "source": "BuildManager.java:231"
        },
        {
          "method": "org.eclipse.core.runtime.SafeRunner.run",
          "source": "SafeRunner.java:37"
        },
        {
          "method": "org.eclipse.core.internal.events.BuildManager.basicBuild",
          "source": "BuildManager.java:234"
        },
        {
          "method": "org.eclipse.core.internal.events.BuildManager.basicBuildLoop",
          "source": "BuildManager.java:253"
        },
        {
          "method": "org.eclipse.core.internal.events.BuildManager.build",
          "source": "BuildManager.java:282"
        },
        {
          "method": "org.eclipse.core.internal.events.AutoBuildJob.doBuild",
          "source": "AutoBuildJob.java:143"
        },
        {
          "method": "org.eclipse.core.internal.events.AutoBuildJob.run",
          "source": "AutoBuildJob.java:204"
        },
        {
          "method": "org.eclipse.core.internal.jobs.Worker.run",
          "source": "Worker.java:58"
        }
      ],
      "number": 0,
      "commentIndex": 0,
      "bugId": "132613",
      "date": "2006-03-21T01:29:31+01:00",
      "product": "JDT",
      "component": "Core",
      "severity": "normal"
    },
    {
      "exceptionType": "java.lang.NullPointerException",
      "elements": [
        {
          "method": "org.eclipse.core.internal.filesystem.InternalFileSystemCore.getStore",
          "source": "InternalFileSystemCore.java:104"
        },
        {
          "method": "org.eclipse.core.filesystem.EFS.getStore",
          "source": "EFS.java:296"
        },
        {
          "method": "org.eclipse.jdt.internal.core.util.Util.toLocalFile",
          "source": "Util.java:2044"
        },
        {
          "method": "org.eclipse.jdt.internal.core.builder.ClasspathJar.\u003cinit\u003e",
          "source": "ClasspathJar.java:91"
        },
        {
          "method": "org.eclipse.jdt.internal.core.builder.ClasspathLocation.forLibrary",
          "source": "ClasspathLocation.java:38"
        },
        {
          "method": "org.eclipse.jdt.internal.core.builder.State.read",
          "source": "State.java:255"
        },
        {
          "method": "org.eclipse.jdt.internal.core.builder.JavaBuilder.readState",
          "source": "JavaBuilder.java:125"
        },
        {
          "method": "org.eclipse.jdt.internal.core.JavaModelManager.readState",
          "source": "JavaModelManager.java:2586"
        },
        {
          "method": "org.eclipse.jdt.internal.core.JavaModelManager.getLastBuiltState",
          "source": "JavaModelManager.java:1365"
        },
        {
          "method": "org.eclipse.jdt.internal.core.builder.JavaBuilder.getLastState",
          "source": "JavaBuilder.java:367"
        },
        {
          "method": "org.eclipse.jdt.internal.core.builder.JavaBuilder.build",
          "source": "JavaBuilder.java:150"
        },
        {
          "method": "org.eclipse.core.internal.events.BuildManager$2.run",
          "source": "BuildManager.java:593"
        },
        {
          "method": "org.eclipse.core.runtime.SafeRunner.run",
          "source": "SafeRunner.java:37"
        },
        {
          "method": "org.eclipse.core.internal.events.BuildManager.basicBuild",
          "source": "BuildManager.java:168"
        },
        {
          "method": "org.eclipse.core.internal.events.BuildManager.basicBuild",
          "source": "BuildManager.java:202"
        },
        {
          "method": "org.eclipse.core.internal.events.BuildManager$1.run",
          "source": "BuildManager.java:231"
        },
        {
          "method": "org.eclipse.core.runtime.SafeRunner.run",
          "source": "SafeRunner.java:37"
        },
        {
          "method": "org.eclipse.core.internal.events.BuildManager.basicBuild",
          "source": "BuildManager.java:234"
        },
        {
          "method": "org.eclipse.core.internal.events.BuildManager.basicBuildLoop",
          "source": "BuildManager.java:253"
        },
        {
          "method": "org.eclipse.core.internal.events.BuildManager.build",
          "source": "BuildManager.java:282"
        },
        {
          "method": "org.eclipse.core.internal.events.AutoBuildJob.doBuild",
          "source": "AutoBuildJob.java:143"
        },
        {
          "method": "org.eclipse.core.internal.events.AutoBuildJob.run",
          "source": "AutoBuildJob.java:204"
        },
        {
          "method": "org.eclipse.core.internal.jobs.Worker.run",
          "source": "Worker.java:58"
        }
      ],
      "number": 1,
      "commentIndex": 0,
      "bugId": "132613",
      "date": "2006-03-21T01:29:31+01:00",
      "product": "JDT",
      "component": "Core",
      "severity": "normal"
    },
    {
      "exceptionType": "java.lang.NullPointerException",
      "elements": [
        {
          "method": "org.eclipse.core.internal.filesystem.InternalFileSystemCore.getStore",
          "source": "InternalFileSystemCore.java:104"
        },
        {
          "method": "org.eclipse.core.filesystem.EFS.getStore",
          "source": "EFS.java:296"
        },
        {
          "method": "org.eclipse.jdt.internal.core.util.Util.toLocalFile",
          "source": "Util.java:2044"
        },
        {
          "method": "org.eclipse.jdt.internal.core.builder.ClasspathJar.\u003cinit\u003e",
          "source": "ClasspathJar.java:91"
        },
        {
          "method": "org.eclipse.jdt.internal.core.builder.ClasspathLocation.forLibrary",
          "source": "ClasspathLocation.java:38"
        },
        {
          "method": "org.eclipse.jdt.internal.core.builder.State.read",
          "source": "State.java:255"
        },
        {
          "method": "org.eclipse.jdt.internal.core.builder.JavaBuilder.readState",
          "source": "JavaBuilder.java:125"
        },
        {
          "method": "org.eclipse.jdt.internal.core.JavaModelManager.readState",
          "source": "JavaModelManager.java:2586"
        },
        {
          "method": "org.eclipse.jdt.internal.core.JavaModelManager.getLastBuiltState",
          "source": "JavaModelManager.java:1365"
        },
        {
          "method": "org.eclipse.jdt.internal.core.builder.JavaBuilder.getLastState",
          "source": "JavaBuilder.java:367"
        },
        {
          "method": "org.eclipse.jdt.internal.core.builder.JavaBuilder.build",
          "source": "JavaBuilder.java:150"
        },
        {
          "method": "org.eclipse.core.internal.events.BuildManager$2.run",
          "source": "BuildManager.java:593"
        },
        {
          "method": "org.eclipse.core.runtime.SafeRunner.run",
          "source": "SafeRunner.java:37"
        },
        {
          "method": "org.eclipse.core.internal.events.BuildManager.basicBuild",
          "source": "BuildManager.java:168"
        },
        {
          "method": "org.eclipse.core.internal.events.BuildManager.basicBuild",
          "source": "BuildManager.java:202"
        },
        {
          "method": "org.eclipse.core.internal.events.BuildManager$1.run",
          "source": "BuildManager.java:231"
        },
        {
          "method": "org.eclipse.core.runtime.SafeRunner.run",
          "source": "SafeRunner.java:37"
        },
        {
          "method": "org.eclipse.core.internal.events.BuildManager.basicBuild",
          "source": "BuildManager.java:234"
        },
        {
          "method": "org.eclipse.core.internal.events.BuildManager.basicBuildLoop",
          "source": "BuildManager.java:253"
        },
        {
          "method": "org.eclipse.core.internal.events.BuildManager.build",
          "source": "BuildManager.java:282"
        },
        {
          "method": "org.eclipse.core.internal.events.AutoBuildJob.doBuild",
          "source": "AutoBuildJob.java:143"
        },
        {
          "method": "org.eclipse.core.internal.events.AutoBuildJob.run",
          "source": "AutoBuildJob.java:204"
        },
        {
          "method": "org.eclipse.core.internal.jobs.Worker.run",
          "source": "Worker.java:58"
        }
      ],
      "number": 2,
      "commentIndex": 0,
      "bugId": "132613",
      "date": "2006-03-21T01:29:31+01:00",
      "product": "JDT",
      "component": "Core",
      "severity": "normal"
    },
    {
      "exceptionType": "java.lang.NullPointerException",
      "elements": [
        {
          "method": "org.eclipse.core.internal.filesystem.InternalFileSystemCore.getStore",
          "source": "InternalFileSystemCore.java:104"
        },
        {
          "method": "org.eclipse.core.filesystem.EFS.getStore",
          "source": "EFS.java:296"
        },
        {
          "method": "org.eclipse.jdt.internal.core.util.Util.toLocalFile",
          "source": "Util.java:2044"
        },
        {
          "method": "org.eclipse.jdt.internal.core.builder.ClasspathJar.\u003cinit\u003e",
          "source": "ClasspathJar.java:91"
        },
        {
          "method": "org.eclipse.jdt.internal.core.builder.ClasspathLocation.forLibrary",
          "source": "ClasspathLocation.java:38"
        },
        {
          "method": "org.eclipse.jdt.internal.core.builder.State.read",
          "source": "State.java:255"
        },
        {
          "method": "org.eclipse.jdt.internal.core.builder.JavaBuilder.readState",
          "source": "JavaBuilder.java:125"
        },
        {
          "method": "org.eclipse.jdt.internal.core.JavaModelManager.readState",
          "source": "JavaModelManager.java:2586"
        },
        {
          "method": "org.eclipse.jdt.internal.core.JavaModelManager.getLastBuiltState",
          "source": "JavaModelManager.java:1365"
        },
        {
          "method": "org.eclipse.jdt.internal.core.builder.JavaBuilder.getLastState",
          "source": "JavaBuilder.java:367"
        },
        {
          "method": "org.eclipse.jdt.internal.core.builder.JavaBuilder.build",
          "source": "JavaBuilder.java:150"
        },
        {
          "method": "org.eclipse.core.internal.events.BuildManager$2.run",
          "source": "BuildManager.java:593"
        },
        {
          "method": "org.eclipse.core.runtime.SafeRunner.run",
          "source": "SafeRunner.java:37"
        },
        {
          "method": "org.eclipse.core.internal.events.BuildManager.basicBuild",
          "source": "BuildManager.java:168"
        },
        {
          "method": "org.eclipse.core.internal.events.BuildManager.basicBuild",
          "source": "BuildManager.java:202"
        },
        {
          "method": "org.eclipse.core.internal.events.BuildManager$1.run",
          "source": "BuildManager.java:231"
        },
        {
          "method": "org.eclipse.core.runtime.SafeRunner.run",
          "source": "SafeRunner.java:37"
        },
        {
          "method": "org.eclipse.core.internal.events.BuildManager.basicBuild",
          "source": "BuildManager.java:234"
        },
        {
          "method": "org.eclipse.core.internal.events.BuildManager.basicBuildLoop",
          "source": "BuildManager.java:253"
        },
        {
          "method": "org.eclipse.core.internal.events.BuildManager.build",
          "source": "BuildManager.java:282"
        },
        {
          "method": "org.eclipse.core.internal.events.AutoBuildJob.doBuild",
          "source": "AutoBuildJob.java:143"
        },
        {
          "method": "org.eclipse.core.internal.events.AutoBuildJob.run",
          "source": "AutoBuildJob.java:204"
        },
        {
          "method": "org.eclipse.core.internal.jobs.Worker.run",
          "source": "Worker.java:58"
        }
      ],
      "number": 3,
      "commentIndex": 0,
      "bugId": "132613",
      "date": "2006-03-21T01:29:31+01:00",
      "product": "JDT",
      "component": "Core",
      "severity": "normal"
    }
  ],
  "groupId": "132613",
  "bugId": "132613",
  "date": "2006-03-21T01:29:31+01:00",
  "product": "JDT",
  "component": "Core",
  "severity": "normal"
}