{
  "comments": [
    "Problem:\n\u003d\u003d\u003d\u003d\u003d\u003d\u003d\u003d\nWe are trying to launch as many as GDBs to debug our special programs. We got an exception when we are trying to launch about 100 gdbs. Please refer to the following fragment from the .log. The following .log is for WinXP. For Linux, we believe there may also some limit, but it is larger than WinXP.\n\nThe question is : \n - Is there a limitation about how many processes the Spawner class can create?\n - or is there anything I did wrong?\n\nThanks.\n\nFragment from .log:\n\u003d\u003d\u003d\u003d\u003d\u003d\u003d\u003d\u003d\u003d\u003d\u003d\u003d\u003d\u003d\u003d\u003d\u003d\n\n!SUBENTRY 1 org.eclipse.cdt.debug.mi.core 4 150 2006-03-22 17:51:07.817\n!MESSAGE Exec error:Too many processes\n!STACK 0\njava.io.IOException: Exec error:Too many processes\n        at org.eclipse.cdt.utils.spawner.Spawner.exec(Spawner.java:243)\n        at org.eclipse.cdt.utils.spawner.Spawner.\u003cinit\u003e(Spawner.java:57)\n        at org.eclipse.cdt.utils.spawner.Spawner.\u003cinit\u003e(Spawner.java:85)\n        at org.eclipse.cdt.utils.spawner.Spawner.\u003cinit\u003e(Spawner.java:77)\n        at org.eclipse.cdt.utils.spawner.ProcessFactory.exec(ProcessFactory.java:59)\n        at org.eclipse.cdt.debug.mi.core.MIProcessAdapter.getGDBProcess(MIProcessAdapter.java:49)\n        at org.eclipse.cdt.debug.mi.core.MIProcessAdapter.\u003cinit\u003e(MIProcessAdapter.java:37)\n        at org.eclipse.cdt.debug.mi.core.MIPlugin.createCSession(MIPlugin.java:325)\n        at mytools.TestDebugger.createLaunchSession(TestDebugger.java:50)\n        at org.eclipse.cdt.debug.mi.core.GDBCDIDebugger.createDebuggerSession(GDBCDIDebugger.java:73)\n        at mytools.TestLaunchDelegate.launch(TestLaunchDelegate.java:35)\n        at org.eclipse.debug.internal.core.LaunchConfiguration.launch(LaunchConfiguration.java:590)\n        at org.eclipse.debug.internal.core.LaunchConfiguration.launch(LaunchConfiguration.java:515)\n        at org.eclipse.debug.internal.core.LaunchConfiguration.launch(LaunchConfiguration.java:152)\n        at org.eclipse.debug.internal.ui.DebugUIPlugin.buildAndLaunch(DebugUIPlugin.java:737)\n        at org.eclipse.debug.internal.ui.DebugUIPlugin$6.run(DebugUIPlugin.java:931)\n        at org.eclipse.core.internal.jobs.Worker.run(Worker.java:76)",
    "Yes, there is a limitation in the native code (org.eclipse.cdt.core.win32\\library\\Win32ProcessEx.c). If you need a quick fix, just change the value of MAX_PROCS and rebuild the DLL."
  ],
  "commentCreationDates": [
    "2006-03-23T02:20:09+01:00",
    "2006-03-23T17:00:48+01:00"
  ],
  "traces": [
    {
      "exceptionType": "java.io.IOException",
      "message": "Exec error:Too many processes",
      "elements": [
        {
          "method": "org.eclipse.cdt.utils.spawner.Spawner.exec",
          "source": "Spawner.java:243"
        },
        {
          "method": "org.eclipse.cdt.utils.spawner.Spawner.\u003cinit\u003e",
          "source": "Spawner.java:57"
        },
        {
          "method": "org.eclipse.cdt.utils.spawner.Spawner.\u003cinit\u003e",
          "source": "Spawner.java:85"
        },
        {
          "method": "org.eclipse.cdt.utils.spawner.Spawner.\u003cinit\u003e",
          "source": "Spawner.java:77"
        },
        {
          "method": "org.eclipse.cdt.utils.spawner.ProcessFactory.exec",
          "source": "ProcessFactory.java:59"
        },
        {
          "method": "org.eclipse.cdt.debug.mi.core.MIProcessAdapter.getGDBProcess",
          "source": "MIProcessAdapter.java:49"
        },
        {
          "method": "org.eclipse.cdt.debug.mi.core.MIProcessAdapter.\u003cinit\u003e",
          "source": "MIProcessAdapter.java:37"
        },
        {
          "method": "org.eclipse.cdt.debug.mi.core.MIPlugin.createCSession",
          "source": "MIPlugin.java:325"
        },
        {
          "method": "mytools.TestDebugger.createLaunchSession",
          "source": "TestDebugger.java:50"
        },
        {
          "method": "org.eclipse.cdt.debug.mi.core.GDBCDIDebugger.createDebuggerSession",
          "source": "GDBCDIDebugger.java:73"
        },
        {
          "method": "mytools.TestLaunchDelegate.launch",
          "source": "TestLaunchDelegate.java:35"
        },
        {
          "method": "org.eclipse.debug.internal.core.LaunchConfiguration.launch",
          "source": "LaunchConfiguration.java:590"
        },
        {
          "method": "org.eclipse.debug.internal.core.LaunchConfiguration.launch",
          "source": "LaunchConfiguration.java:515"
        },
        {
          "method": "org.eclipse.debug.internal.core.LaunchConfiguration.launch",
          "source": "LaunchConfiguration.java:152"
        },
        {
          "method": "org.eclipse.debug.internal.ui.DebugUIPlugin.buildAndLaunch",
          "source": "DebugUIPlugin.java:737"
        },
        {
          "method": "org.eclipse.debug.internal.ui.DebugUIPlugin$6.run",
          "source": "DebugUIPlugin.java:931"
        },
        {
          "method": "org.eclipse.core.internal.jobs.Worker.run",
          "source": "Worker.java:76"
        }
      ],
      "number": 0,
      "commentIndex": 0,
      "bugId": "132932",
      "date": "2006-03-23T02:20:09+01:00",
      "product": "CDT",
      "component": "cdt-launch",
      "severity": "normal"
    }
  ],
  "groupId": "132932",
  "bugId": "132932",
  "date": "2006-03-23T02:20:09+01:00",
  "product": "CDT",
  "component": "cdt-launch",
  "severity": "normal"
}