{
  "comments": [
    "on debian unstable (i386, piii750, kernel 2.6.16)\n\nwhen using sun jdk 1.5.0_6\nPATH\u003d/opt/java/jdk1.5.0_06/bin:$PATH\nexport PATH\nexport JAVA_HOME\u003d/opt/java/jdk1.5.0_06\n\nIf I launch eclipse without configuration (rm -rf ~/.eclipse)\nit crashed\n\nif I download the stable tgz from eclipse.org, it crashes the same way\n\nI even tried the stable 3.2 build eclipse-SDK-3.2M5a-linux-gtk.tar.gz\nsame bug\n\nthx in advance !\n\nhere is the log\n\n!SESSION 2006-03-26 12:18:36.195 -----------------------------------------------\neclipse.buildId\u003dM20060118-1600\njava.version\u003d1.5.0_06\njava.vendor\u003dSun Microsystems Inc.\nBootLoader constants: OS\u003dlinux, ARCH\u003dx86, WS\u003dgtk, NL\u003den_US\nCommand-line arguments:  -os linux -ws gtk -arch x86\n\n!ENTRY org.eclipse.core.runtime 2 1 2006-03-26 12:18:39.15\n!MESSAGE Problems parsing plug-in manifest for: \"initial@reference:file:plugins/org.eclipse.core.runtime_3.1.2.jar/\".\n!SUBENTRY 1 org.eclipse.core.runtime 2 1 2006-03-26 12:18:39.16\n!MESSAGE Parsing error in \"plugin.xml\" [line 1, column 0]: \"URI was not reported to parser for entity [document]\".\n!STACK 0\norg.xml.sax.SAXParseException: URI was not reported to parser for entity [document]\n        at gnu.xml.aelfred2.SAXDriver.warn(SAXDriver.java:934)\n        at gnu.xml.aelfred2.SAXDriver.startExternalEntity(SAXDriver.java:631)\n        at gnu.xml.aelfred2.XmlParser.pushURL(XmlParser.java:3358)\n        at gnu.xml.aelfred2.XmlParser.doParse(XmlParser.java:159)\n        at gnu.xml.aelfred2.SAXDriver.parse(SAXDriver.java:320)\n        at gnu.xml.aelfred2.XmlReader.parse(XmlReader.java:294)\n        at javax.xml.parsers.SAXParser.parse(SAXParser.java:375)\n        at org.eclipse.core.internal.registry.ExtensionsParser.parseManifest(ExtensionsParser.java:375)\n        at org.eclipse.core.internal.registry.EclipseBundleListener.getBundleModel(EclipseBundleListener.java:197)\n        at org.eclipse.core.internal.registry.EclipseBundleListener.addBundle(EclipseBundleListener.java:101)\n        at org.eclipse.core.internal.registry.EclipseBundleListener.processBundles(EclipseBundleListener.java:82)\n        at org.eclipse.core.internal.registry.ExtensionRegistry.\u003cinit\u003e(ExtensionRegistry.java:687)\n        at org.eclipse.core.internal.runtime.PlatformActivator.startRegistry(PlatformActivator.java:84)\n        at org.eclipse.core.internal.runtime.PlatformActivator.start(PlatformActivator.java:58)\n        at org.eclipse.osgi.framework.internal.core.BundleContextImpl$2.run(BundleContextImpl.java:994)\n        at java.security.AccessController.doPrivileged(Native Method)\n        at org.eclipse.osgi.framework.internal.core.BundleContextImpl.startActivator(BundleContextImpl.java:988)\n        at org.eclipse.osgi.framework.internal.core.BundleContextImpl.start(BundleContextImpl.java:969)\n        at org.eclipse.osgi.framework.internal.core.BundleHost.startWorker(BundleHost.java:316)\n        at org.eclipse.osgi.framework.internal.core.AbstractBundle.resume(AbstractBundle.java:337)\n        at org.eclipse.osgi.framework.internal.core.Framework.resumeBundle(Framework.java:1024)\n        at org.eclipse.osgi.framework.internal.core.StartLevelManager.resumeBundles(StartLevelManager.java:574)\n        at org.eclipse.osgi.framework.internal.core.StartLevelManager.incFWSL(StartLevelManager.java:496)\n        at org.eclipse.osgi.framework.internal.core.StartLevelManager.doSetStartLevel(StartLevelManager.java:275)\n        at org.eclipse.osgi.framework.internal.core.StartLevelManager.dispatchEvent(StartLevelManager.java:456)\n        at org.eclipse.osgi.framework.eventmgr.EventManager.dispatchEvent(EventManager.java:189)\n        at org.eclipse.osgi.framework.eventmgr.EventManager$EventThread.run(EventManager.java:291)\n\n!ENTRY org.eclipse.core.runtime 2 1 2006-03-26 12:18:39.101\n!MESSAGE Problems parsing plug-in manifest for: \"initial@reference:file:plugins/org.eclipse.update.configurator_3.1.0.jar/\".\n!SUBENTRY 1 org.eclipse.core.runtime 2 1 2006-03-26 12:18:39.102\n!MESSAGE Parsing error in \"plugin.xml\" [line 1, column 0]: \"URI was not reported to parser for entity [document]\".\n!STACK 0\norg.xml.sax.SAXParseException: URI was not reported to parser for entity [document]\n        at gnu.xml.aelfred2.SAXDriver.warn(SAXDriver.java:934)\n        at gnu.xml.aelfred2.SAXDriver.startExternalEntity(SAXDriver.java:631)\n        at gnu.xml.aelfred2.XmlParser.pushURL(XmlParser.java:3358)\n        at gnu.xml.aelfred2.XmlParser.doParse(XmlParser.java:159)\n        at gnu.xml.aelfred2.SAXDriver.parse(SAXDriver.java:320)\n        at gnu.xml.aelfred2.XmlReader.parse(XmlReader.java:294)\n        at javax.xml.parsers.SAXParser.parse(SAXParser.java:375)\n        at org.eclipse.core.internal.registry.ExtensionsParser.parseManifest(ExtensionsParser.java:375)\n        at org.eclipse.core.internal.registry.EclipseBundleListener.getBundleModel(EclipseBundleListener.java:197)\n        at org.eclipse.core.internal.registry.EclipseBundleListener.addBundle(EclipseBundleListener.java:101)\n        at org.eclipse.core.internal.registry.EclipseBundleListener.processBundles(EclipseBundleListener.java:82)\n        at org.eclipse.core.internal.registry.ExtensionRegistry.\u003cinit\u003e(ExtensionRegistry.java:687)\n        at org.eclipse.core.internal.runtime.PlatformActivator.startRegistry(PlatformActivator.java:84)\n        at org.eclipse.core.internal.runtime.PlatformActivator.start(PlatformActivator.java:58)\n        at org.eclipse.osgi.framework.internal.core.BundleContextImpl$2.run(BundleContextImpl.java:994)\n        at java.security.AccessController.doPrivileged(Native Method)\n        at org.eclipse.osgi.framework.internal.core.BundleContextImpl.startActivator(BundleContextImpl.java:988)\n        at org.eclipse.osgi.framework.internal.core.BundleContextImpl.start(BundleContextImpl.java:969)\n        at org.eclipse.osgi.framework.internal.core.BundleHost.startWorker(BundleHost.java:316)\n        at org.eclipse.osgi.framework.internal.core.AbstractBundle.resume(AbstractBundle.java:337)\n        at org.eclipse.osgi.framework.internal.core.Framework.resumeBundle(Framework.java:1024)\n        at org.eclipse.osgi.framework.internal.core.StartLevelManager.resumeBundles(StartLevelManager.java:574)\n        at org.eclipse.osgi.framework.internal.core.StartLevelManager.incFWSL(StartLevelManager.java:496)\n        at org.eclipse.osgi.framework.internal.core.StartLevelManager.doSetStartLevel(StartLevelManager.java:275)\n        at org.eclipse.osgi.framework.internal.core.StartLevelManager.dispatchEvent(StartLevelManager.java:456)\n        at org.eclipse.osgi.framework.eventmgr.EventManager.dispatchEvent(EventManager.java:189)\n        at org.eclipse.osgi.framework.eventmgr.EventManager$EventThread.run(EventManager.java:291)\n\n!ENTRY initial@reference:file:plugins/org.eclipse.update.configurator_3.1.0.jar/ 0 0 2006-03-26 12:18:39.760\n!MESSAGE FrameworkEvent.ERROR\n!STACK 0\norg.osgi.framework.BundleException: Exception in org.eclipse.update.internal.configurator.ConfigurationActivator.start() of bundle org.eclipse.update.configurator.\n        at org.eclipse.osgi.framework.internal.core.BundleContextImpl.startActivator(BundleContextImpl.java:1013)\n        at org.eclipse.osgi.framework.internal.core.BundleContextImpl.start(BundleContextImpl.java:969)\n        at org.eclipse.osgi.framework.internal.core.BundleHost.startWorker(BundleHost.java:316)\n        at org.eclipse.osgi.framework.internal.core.AbstractBundle.resume(AbstractBundle.java:337)\n        at org.eclipse.osgi.framework.internal.core.Framework.resumeBundle(Framework.java:1024)\n        at org.eclipse.osgi.framework.internal.core.StartLevelManager.resumeBundles(StartLevelManager.java:574)\n        at org.eclipse.osgi.framework.internal.core.StartLevelManager.incFWSL(StartLevelManager.java:496)\n        at org.eclipse.osgi.framework.internal.core.StartLevelManager.doSetStartLevel(StartLevelManager.java:275)\n        at org.eclipse.osgi.framework.internal.core.StartLevelManager.dispatchEvent(StartLevelManager.java:456)\n        at org.eclipse.osgi.framework.eventmgr.EventManager.dispatchEvent(EventManager.java:189)\n        at org.eclipse.osgi.framework.eventmgr.EventManager$EventThread.run(EventManager.java:291)\nCaused by: org.eclipse.core.runtime.CoreException: Cannot create configuration in file:/home/pitfall/.eclipse/org.eclipse.platform_3.1.2/configuration/\n        at org.eclipse.update.internal.configurator.Utils.newCoreException(Utils.java:71)\n        at org.eclipse.update.internal.configurator.ConfigurationActivator.initialize(ConfigurationActivator.java:106)\n        at org.eclipse.update.internal.configurator.ConfigurationActivator.start(ConfigurationActivator.java:67)\n        at org.eclipse.osgi.framework.internal.core.BundleContextImpl$2.run(BundleContextImpl.java:994)\n        at java.security.AccessController.doPrivileged(Native Method)\n        at org.eclipse.osgi.framework.internal.core.BundleContextImpl.startActivator(BundleContextImpl.java:988)\n        ... 10 more\nRoot exception:\norg.eclipse.core.runtime.CoreException: Cannot create configuration in file:/home/pitfall/.eclipse/org.eclipse.platform_3.1.2/configuration/\n        at org.eclipse.update.internal.configurator.Utils.newCoreException(Utils.java:71)\n        at org.eclipse.update.internal.configurator.ConfigurationActivator.initialize(ConfigurationActivator.java:106)\n        at org.eclipse.update.internal.configurator.ConfigurationActivator.start(ConfigurationActivator.java:67)\n        at org.eclipse.osgi.framework.internal.core.BundleContextImpl$2.run(BundleContextImpl.java:994)\n        at java.security.AccessController.doPrivileged(Native Method)\n        at org.eclipse.osgi.framework.internal.core.BundleContextImpl.startActivator(BundleContextImpl.java:988)\n        at org.eclipse.osgi.framework.internal.core.BundleContextImpl.start(BundleContextImpl.java:969)\n        at org.eclipse.osgi.framework.internal.core.BundleHost.startWorker(BundleHost.java:316)\n        at org.eclipse.osgi.framework.internal.core.AbstractBundle.resume(AbstractBundle.java:337)\n        at org.eclipse.osgi.framework.internal.core.Framework.resumeBundle(Framework.java:1024)\n        at org.eclipse.osgi.framework.internal.core.StartLevelManager.resumeBundles(StartLevelManager.java:574)\n        at org.eclipse.osgi.framework.internal.core.StartLevelManager.incFWSL(StartLevelManager.java:496)\n        at org.eclipse.osgi.framework.internal.core.StartLevelManager.doSetStartLevel(StartLevelManager.java:275)\n        at org.eclipse.osgi.framework.internal.core.StartLevelManager.dispatchEvent(StartLevelManager.java:456)\n        at org.eclipse.osgi.framework.eventmgr.EventManager.dispatchEvent(EventManager.java:189)\n        at org.eclipse.osgi.framework.eventmgr.EventManager$EventThread.run(EventManager.java:291)\n\n!ENTRY org.eclipse.osgi 2006-03-26 12:18:39.781\n!MESSAGE Startup error\n!STACK 1\njava.lang.IllegalStateException: Bundle initial@reference:file:plugins/org.eclipse.update.configurator_3.1.0.jar/ [2] is not active.\n        at org.eclipse.core.runtime.adaptor.EclipseStarter.ensureBundlesActive(EclipseStarter.java:410)\n        at org.eclipse.core.runtime.adaptor.EclipseStarter.startup(EclipseStarter.java:297)\n        at org.eclipse.core.runtime.adaptor.EclipseStarter.run(EclipseStarter.java:159)\n        at sun.reflect.NativeMethodAccessorImpl.invoke0(Native Method)\n        at sun.reflect.NativeMethodAccessorImpl.invoke(NativeMethodAccessorImpl.java:39)\n        at sun.reflect.DelegatingMethodAccessorImpl.invoke(DelegatingMethodAccessorImpl.java:25)\n        at java.lang.reflect.Method.invoke(Method.java:585)\n        at org.eclipse.core.launcher.Main.invokeFramework(Main.java:334)\n        at org.eclipse.core.launcher.Main.basicRun(Main.java:278)\n        at org.eclipse.core.launcher.Main.run(Main.java:973)\n        at org.eclipse.core.launcher.Main.main(Main.java:948)",
    "Is there anything strange about your JVM?  It looks like it is\nusing the gnu.xml.aelfred2 XML parser, and this is failing.\nDo you have a specific CLASSPATH set somehow?",
    "Not that I know\n\nIt\u0027s the 1.5 update 6 from sun.com\n\nIt contains JfreeGraph and MysqlConnectore in its ext directory, not much...",
    "I doubt that Sun ships with the gnu parser :) How did you install it on your machine? ",
    "I really don\u0027t know\n\nwhen I launch eclipse, I do this before : \nPATH\u003d/opt/java/jdk1.5.0_06/bin:$PATH\nexport PATH\nexport JAVA_HOME\u003d/opt/java/jdk1.5.0_06\n\nI\u0027m running debian unstable\nhere\u0027s some info : \nIn my opt/java/sun\u0027sjdk : \npitfall@cavelord:~$ find /opt/java/jdk1.5.0_06/ -type f | grep -i xml\n/opt/java/jdk1.5.0_06/sample/jnlp/jreinstaller/build/win32/jreinstallers/resources/version.xml_windows-i586_1.4.2\n/opt/java/jdk1.5.0_06/sample/jnlp/jreinstaller/build/solaris/jreinstallers/resources/version.xml_solaris-sparc_1.4.2\n/opt/java/jdk1.5.0_06/sample/jnlp/jreinstaller/build/linux/jreinstallers/resources/version.xml_linux-i586_1.4.2\n/opt/java/jdk1.5.0_06/sample/jnlp/servlet/src/classes/jnlp/sample/servlet/XMLParsing.java\n/opt/java/jdk1.5.0_06/sample/jnlp/servlet/src/classes/jnlp/sample/servlet/XMLAttribute.java\n/opt/java/jdk1.5.0_06/sample/jnlp/servlet/src/classes/jnlp/sample/servlet/XMLNode.java\n/opt/java/jdk1.5.0_06/sample/jnlp/raf/war/WEB-INF/web.xml\n/opt/java/jdk1.5.0_06/sample/jnlp/webpad/war/WEB-INF/web.xml\n/opt/java/jdk1.5.0_06/sample/jnlp/webpad/war/app/version.xml\n/opt/java/jdk1.5.0_06/sample/jnlp/corba/war/WEB-INF/web.xml\n\non my system : \npitfall@cavelord:~$ dpkg -l | grep -i xml | grep java\nii  libcommons-digester-java        1.7-2                              Rule based XML Java object mapping tool\nii  libjaxp1.2-java                 1.2.01-1                           Java XML parser and transformer APIs (DOM, S\nii  libxerces2-java                 2.6.2-4                            Validating XML parser for Java with DOM leve\n\n\nknowing that I set my java home to /opt/java/jdk-.. ... why is eclipse crashing on gnu xml parser ?\n\nthx for the feedback",
    "Could you please try a few things:\n- see if the gnu parser is installed into jre/lib/ext?\n- run a small java program that creates an xml parser and see if the parser used is the gnu one?\n",
    "*** Bug 123936 has been marked as a duplicate of this bug. ***",
    "Please reopen if the problem still occurs and can provide the details on gnu parser got into your 1.5vm.\nCC\u0027ing Ben in case he knows anything about gnu parser."
  ],
  "commentCreationDates": [
    "2006-03-26T12:08:45+02:00",
    "2006-03-26T19:15:48+02:00",
    "2006-03-27T15:15:40+02:00",
    "2006-03-27T18:07:40+02:00",
    "2006-03-27T19:21:57+02:00",
    "2006-03-31T15:57:42+02:00",
    "2006-04-05T21:39:01+02:00",
    "2006-09-13T21:47:23+02:00"
  ],
  "traces": [
    {
      "exceptionType": "org.xml.sax.SAXParseException",
      "message": "URI was not reported to parser for entity [document]",
      "elements": [
        {
          "method": "gnu.xml.aelfred2.SAXDriver.warn",
          "source": "SAXDriver.java:934"
        },
        {
          "method": "gnu.xml.aelfred2.SAXDriver.startExternalEntity",
          "source": "SAXDriver.java:631"
        },
        {
          "method": "gnu.xml.aelfred2.XmlParser.pushURL",
          "source": "XmlParser.java:3358"
        },
        {
          "method": "gnu.xml.aelfred2.XmlParser.doParse",
          "source": "XmlParser.java:159"
        },
        {
          "method": "gnu.xml.aelfred2.SAXDriver.parse",
          "source": "SAXDriver.java:320"
        },
        {
          "method": "gnu.xml.aelfred2.XmlReader.parse",
          "source": "XmlReader.java:294"
        },
        {
          "method": "javax.xml.parsers.SAXParser.parse",
          "source": "SAXParser.java:375"
        },
        {
          "method": "org.eclipse.core.internal.registry.ExtensionsParser.parseManifest",
          "source": "ExtensionsParser.java:375"
        },
        {
          "method": "org.eclipse.core.internal.registry.EclipseBundleListener.getBundleModel",
          "source": "EclipseBundleListener.java:197"
        },
        {
          "method": "org.eclipse.core.internal.registry.EclipseBundleListener.addBundle",
          "source": "EclipseBundleListener.java:101"
        },
        {
          "method": "org.eclipse.core.internal.registry.EclipseBundleListener.processBundles",
          "source": "EclipseBundleListener.java:82"
        },
        {
          "method": "org.eclipse.core.internal.registry.ExtensionRegistry.\u003cinit\u003e",
          "source": "ExtensionRegistry.java:687"
        },
        {
          "method": "org.eclipse.core.internal.runtime.PlatformActivator.startRegistry",
          "source": "PlatformActivator.java:84"
        },
        {
          "method": "org.eclipse.core.internal.runtime.PlatformActivator.start",
          "source": "PlatformActivator.java:58"
        },
        {
          "method": "org.eclipse.osgi.framework.internal.core.BundleContextImpl$2.run",
          "source": "BundleContextImpl.java:994"
        },
        {
          "method": "java.security.AccessController.doPrivileged",
          "source": "Native Method"
        },
        {
          "method": "org.eclipse.osgi.framework.internal.core.BundleContextImpl.startActivator",
          "source": "BundleContextImpl.java:988"
        },
        {
          "method": "org.eclipse.osgi.framework.internal.core.BundleContextImpl.start",
          "source": "BundleContextImpl.java:969"
        },
        {
          "method": "org.eclipse.osgi.framework.internal.core.BundleHost.startWorker",
          "source": "BundleHost.java:316"
        },
        {
          "method": "org.eclipse.osgi.framework.internal.core.AbstractBundle.resume",
          "source": "AbstractBundle.java:337"
        },
        {
          "method": "org.eclipse.osgi.framework.internal.core.Framework.resumeBundle",
          "source": "Framework.java:1024"
        },
        {
          "method": "org.eclipse.osgi.framework.internal.core.StartLevelManager.resumeBundles",
          "source": "StartLevelManager.java:574"
        },
        {
          "method": "org.eclipse.osgi.framework.internal.core.StartLevelManager.incFWSL",
          "source": "StartLevelManager.java:496"
        },
        {
          "method": "org.eclipse.osgi.framework.internal.core.StartLevelManager.doSetStartLevel",
          "source": "StartLevelManager.java:275"
        },
        {
          "method": "org.eclipse.osgi.framework.internal.core.StartLevelManager.dispatchEvent",
          "source": "StartLevelManager.java:456"
        },
        {
          "method": "org.eclipse.osgi.framework.eventmgr.EventManager.dispatchEvent",
          "source": "EventManager.java:189"
        },
        {
          "method": "org.eclipse.osgi.framework.eventmgr.EventManager$EventThread.run",
          "source": "EventManager.java:291"
        }
      ],
      "number": 0,
      "commentIndex": 0,
      "bugId": "133291",
      "date": "2006-03-26T12:08:45+02:00",
      "product": "Platform",
      "component": "Runtime",
      "severity": "critical"
    },
    {
      "exceptionType": "org.xml.sax.SAXParseException",
      "message": "URI was not reported to parser for entity [document]",
      "elements": [
        {
          "method": "gnu.xml.aelfred2.SAXDriver.warn",
          "source": "SAXDriver.java:934"
        },
        {
          "method": "gnu.xml.aelfred2.SAXDriver.startExternalEntity",
          "source": "SAXDriver.java:631"
        },
        {
          "method": "gnu.xml.aelfred2.XmlParser.pushURL",
          "source": "XmlParser.java:3358"
        },
        {
          "method": "gnu.xml.aelfred2.XmlParser.doParse",
          "source": "XmlParser.java:159"
        },
        {
          "method": "gnu.xml.aelfred2.SAXDriver.parse",
          "source": "SAXDriver.java:320"
        },
        {
          "method": "gnu.xml.aelfred2.XmlReader.parse",
          "source": "XmlReader.java:294"
        },
        {
          "method": "javax.xml.parsers.SAXParser.parse",
          "source": "SAXParser.java:375"
        },
        {
          "method": "org.eclipse.core.internal.registry.ExtensionsParser.parseManifest",
          "source": "ExtensionsParser.java:375"
        },
        {
          "method": "org.eclipse.core.internal.registry.EclipseBundleListener.getBundleModel",
          "source": "EclipseBundleListener.java:197"
        },
        {
          "method": "org.eclipse.core.internal.registry.EclipseBundleListener.addBundle",
          "source": "EclipseBundleListener.java:101"
        },
        {
          "method": "org.eclipse.core.internal.registry.EclipseBundleListener.processBundles",
          "source": "EclipseBundleListener.java:82"
        },
        {
          "method": "org.eclipse.core.internal.registry.ExtensionRegistry.\u003cinit\u003e",
          "source": "ExtensionRegistry.java:687"
        },
        {
          "method": "org.eclipse.core.internal.runtime.PlatformActivator.startRegistry",
          "source": "PlatformActivator.java:84"
        },
        {
          "method": "org.eclipse.core.internal.runtime.PlatformActivator.start",
          "source": "PlatformActivator.java:58"
        },
        {
          "method": "org.eclipse.osgi.framework.internal.core.BundleContextImpl$2.run",
          "source": "BundleContextImpl.java:994"
        },
        {
          "method": "java.security.AccessController.doPrivileged",
          "source": "Native Method"
        },
        {
          "method": "org.eclipse.osgi.framework.internal.core.BundleContextImpl.startActivator",
          "source": "BundleContextImpl.java:988"
        },
        {
          "method": "org.eclipse.osgi.framework.internal.core.BundleContextImpl.start",
          "source": "BundleContextImpl.java:969"
        },
        {
          "method": "org.eclipse.osgi.framework.internal.core.BundleHost.startWorker",
          "source": "BundleHost.java:316"
        },
        {
          "method": "org.eclipse.osgi.framework.internal.core.AbstractBundle.resume",
          "source": "AbstractBundle.java:337"
        },
        {
          "method": "org.eclipse.osgi.framework.internal.core.Framework.resumeBundle",
          "source": "Framework.java:1024"
        },
        {
          "method": "org.eclipse.osgi.framework.internal.core.StartLevelManager.resumeBundles",
          "source": "StartLevelManager.java:574"
        },
        {
          "method": "org.eclipse.osgi.framework.internal.core.StartLevelManager.incFWSL",
          "source": "StartLevelManager.java:496"
        },
        {
          "method": "org.eclipse.osgi.framework.internal.core.StartLevelManager.doSetStartLevel",
          "source": "StartLevelManager.java:275"
        },
        {
          "method": "org.eclipse.osgi.framework.internal.core.StartLevelManager.dispatchEvent",
          "source": "StartLevelManager.java:456"
        },
        {
          "method": "org.eclipse.osgi.framework.eventmgr.EventManager.dispatchEvent",
          "source": "EventManager.java:189"
        },
        {
          "method": "org.eclipse.osgi.framework.eventmgr.EventManager$EventThread.run",
          "source": "EventManager.java:291"
        }
      ],
      "number": 1,
      "commentIndex": 0,
      "bugId": "133291",
      "date": "2006-03-26T12:08:45+02:00",
      "product": "Platform",
      "component": "Runtime",
      "severity": "critical"
    },
    {
      "exceptionType": "org.osgi.framework.BundleException",
      "message": "Exception in org.eclipse.update.internal.configurator.ConfigurationActivator.start() of bundle org.eclipse.update.configurator.",
      "elements": [
        {
          "method": "org.eclipse.osgi.framework.internal.core.BundleContextImpl.startActivator",
          "source": "BundleContextImpl.java:1013"
        },
        {
          "method": "org.eclipse.osgi.framework.internal.core.BundleContextImpl.start",
          "source": "BundleContextImpl.java:969"
        },
        {
          "method": "org.eclipse.osgi.framework.internal.core.BundleHost.startWorker",
          "source": "BundleHost.java:316"
        },
        {
          "method": "org.eclipse.osgi.framework.internal.core.AbstractBundle.resume",
          "source": "AbstractBundle.java:337"
        },
        {
          "method": "org.eclipse.osgi.framework.internal.core.Framework.resumeBundle",
          "source": "Framework.java:1024"
        },
        {
          "method": "org.eclipse.osgi.framework.internal.core.StartLevelManager.resumeBundles",
          "source": "StartLevelManager.java:574"
        },
        {
          "method": "org.eclipse.osgi.framework.internal.core.StartLevelManager.incFWSL",
          "source": "StartLevelManager.java:496"
        },
        {
          "method": "org.eclipse.osgi.framework.internal.core.StartLevelManager.doSetStartLevel",
          "source": "StartLevelManager.java:275"
        },
        {
          "method": "org.eclipse.osgi.framework.internal.core.StartLevelManager.dispatchEvent",
          "source": "StartLevelManager.java:456"
        },
        {
          "method": "org.eclipse.osgi.framework.eventmgr.EventManager.dispatchEvent",
          "source": "EventManager.java:189"
        },
        {
          "method": "org.eclipse.osgi.framework.eventmgr.EventManager$EventThread.run",
          "source": "EventManager.java:291"
        }
      ],
      "causedBy": {
        "exceptionType": "org.eclipse.core.runtime.CoreException",
        "message": "Cannot create configuration in file:/home/pitfall/.eclipse/org.eclipse.platform_3.1.2/configuration/",
        "elements": [
          {
            "method": "org.eclipse.update.internal.configurator.Utils.newCoreException",
            "source": "Utils.java:71"
          },
          {
            "method": "org.eclipse.update.internal.configurator.ConfigurationActivator.initialize",
            "source": "ConfigurationActivator.java:106"
          },
          {
            "method": "org.eclipse.update.internal.configurator.ConfigurationActivator.start",
            "source": "ConfigurationActivator.java:67"
          },
          {
            "method": "org.eclipse.osgi.framework.internal.core.BundleContextImpl$2.run",
            "source": "BundleContextImpl.java:994"
          },
          {
            "method": "java.security.AccessController.doPrivileged",
            "source": "Native Method"
          },
          {
            "method": "org.eclipse.osgi.framework.internal.core.BundleContextImpl.startActivator",
            "source": "BundleContextImpl.java:988"
          }
        ],
        "number": 0,
        "commentIndex": 0
      },
      "number": 2,
      "commentIndex": 0,
      "bugId": "133291",
      "date": "2006-03-26T12:08:45+02:00",
      "product": "Platform",
      "component": "Runtime",
      "severity": "critical"
    },
    {
      "exceptionType": "org.eclipse.core.runtime.CoreException",
      "message": "Cannot create configuration in file:/home/pitfall/.eclipse/org.eclipse.platform_3.1.2/configuration/",
      "elements": [
        {
          "method": "org.eclipse.update.internal.configurator.Utils.newCoreException",
          "source": "Utils.java:71"
        },
        {
          "method": "org.eclipse.update.internal.configurator.ConfigurationActivator.initialize",
          "source": "ConfigurationActivator.java:106"
        },
        {
          "method": "org.eclipse.update.internal.configurator.ConfigurationActivator.start",
          "source": "ConfigurationActivator.java:67"
        },
        {
          "method": "org.eclipse.osgi.framework.internal.core.BundleContextImpl$2.run",
          "source": "BundleContextImpl.java:994"
        },
        {
          "method": "java.security.AccessController.doPrivileged",
          "source": "Native Method"
        },
        {
          "method": "org.eclipse.osgi.framework.internal.core.BundleContextImpl.startActivator",
          "source": "BundleContextImpl.java:988"
        },
        {
          "method": "org.eclipse.osgi.framework.internal.core.BundleContextImpl.start",
          "source": "BundleContextImpl.java:969"
        },
        {
          "method": "org.eclipse.osgi.framework.internal.core.BundleHost.startWorker",
          "source": "BundleHost.java:316"
        },
        {
          "method": "org.eclipse.osgi.framework.internal.core.AbstractBundle.resume",
          "source": "AbstractBundle.java:337"
        },
        {
          "method": "org.eclipse.osgi.framework.internal.core.Framework.resumeBundle",
          "source": "Framework.java:1024"
        },
        {
          "method": "org.eclipse.osgi.framework.internal.core.StartLevelManager.resumeBundles",
          "source": "StartLevelManager.java:574"
        },
        {
          "method": "org.eclipse.osgi.framework.internal.core.StartLevelManager.incFWSL",
          "source": "StartLevelManager.java:496"
        },
        {
          "method": "org.eclipse.osgi.framework.internal.core.StartLevelManager.doSetStartLevel",
          "source": "StartLevelManager.java:275"
        },
        {
          "method": "org.eclipse.osgi.framework.internal.core.StartLevelManager.dispatchEvent",
          "source": "StartLevelManager.java:456"
        },
        {
          "method": "org.eclipse.osgi.framework.eventmgr.EventManager.dispatchEvent",
          "source": "EventManager.java:189"
        },
        {
          "method": "org.eclipse.osgi.framework.eventmgr.EventManager$EventThread.run",
          "source": "EventManager.java:291"
        }
      ],
      "number": 3,
      "commentIndex": 0,
      "bugId": "133291",
      "date": "2006-03-26T12:08:45+02:00",
      "product": "Platform",
      "component": "Runtime",
      "severity": "critical"
    },
    {
      "exceptionType": "java.lang.IllegalStateException",
      "message": "Bundle initial@reference:file:plugins/org.eclipse.update.configurator_3.1.0.jar/ [2] is not active.",
      "elements": [
        {
          "method": "org.eclipse.core.runtime.adaptor.EclipseStarter.ensureBundlesActive",
          "source": "EclipseStarter.java:410"
        },
        {
          "method": "org.eclipse.core.runtime.adaptor.EclipseStarter.startup",
          "source": "EclipseStarter.java:297"
        },
        {
          "method": "org.eclipse.core.runtime.adaptor.EclipseStarter.run",
          "source": "EclipseStarter.java:159"
        },
        {
          "method": "sun.reflect.NativeMethodAccessorImpl.invoke0",
          "source": "Native Method"
        },
        {
          "method": "sun.reflect.NativeMethodAccessorImpl.invoke",
          "source": "NativeMethodAccessorImpl.java:39"
        },
        {
          "method": "sun.reflect.DelegatingMethodAccessorImpl.invoke",
          "source": "DelegatingMethodAccessorImpl.java:25"
        },
        {
          "method": "java.lang.reflect.Method.invoke",
          "source": "Method.java:585"
        },
        {
          "method": "org.eclipse.core.launcher.Main.invokeFramework",
          "source": "Main.java:334"
        },
        {
          "method": "org.eclipse.core.launcher.Main.basicRun",
          "source": "Main.java:278"
        },
        {
          "method": "org.eclipse.core.launcher.Main.run",
          "source": "Main.java:973"
        },
        {
          "method": "org.eclipse.core.launcher.Main.main",
          "source": "Main.java:948"
        }
      ],
      "number": 4,
      "commentIndex": 0,
      "bugId": "133291",
      "date": "2006-03-26T12:08:45+02:00",
      "product": "Platform",
      "component": "Runtime",
      "severity": "critical"
    }
  ],
  "groupId": "133291",
  "bugId": "133291",
  "date": "2006-03-26T12:08:45+02:00",
  "product": "Platform",
  "component": "Runtime",
  "severity": "critical"
}