{
  "comments": [
    "I have a 64bit Intel CPU 3.6ghz and 64bit Suse Linux 10 edition.. I have downloaded the eclipse-setup-file provided by the site (eclipse-SDK-3.1.2-linux-gtk-x86_64.tar.gz) and extracted it to /usr/eclipse folder with root priviledges.. I have new gtk version and updated the jre but when i try to run eclipse i get the following error message\n\n-------------------------------------------------------------------------------\n!SESSION 2006-03-27 20:21:30.442 -----------------------------------------------\neclipse.buildId\u003dM20060118-1600\njava.version\u003d1.4.2_06\njava.vendor\u003dSun Microsystems Inc.\nBootLoader constants: OS\u003dlinux, ARCH\u003dx86_64, WS\u003dgtk, NL\u003den_US\nCommand-line arguments:  -os linux -ws gtk -arch x86_64\n\n!ENTRY org.eclipse.osgi 2006-03-27 20:21:31.621\n!MESSAGE Application error\n!STACK 1\njava.lang.UnsatisfiedLinkError: /usr/eclipse/configuration/org.eclipse.osgi/bundles/85/1/.cp/libswt-pi-gtk-3139.so: /usr/eclipse/configuration/org.eclipse.osgi/bundles/85/1/.cp/libswt-pi-gtk-3139.so: cannot open shared object file: No such file or directory\n\tat java.lang.ClassLoader$NativeLibrary.load(Native Method)\n\tat java.lang.ClassLoader.loadLibrary0(ClassLoader.java:1586)\n\tat java.lang.ClassLoader.loadLibrary(ClassLoader.java:1495)\n\tat java.lang.Runtime.loadLibrary0(Runtime.java:788)\n\tat java.lang.System.loadLibrary(System.java:834)\n\tat org.eclipse.swt.internal.Library.loadLibrary(Library.java:123)\n\tat org.eclipse.swt.internal.gtk.OS.\u003cclinit\u003e(OS.java:19)\n\tat org.eclipse.swt.internal.Converter.wcsToMbcs(Converter.java:63)\n\tat org.eclipse.swt.internal.Converter.wcsToMbcs(Converter.java:54)\n\tat org.eclipse.swt.widgets.Display.\u003cclinit\u003e(Display.java:122)\n\tat org.eclipse.ui.internal.Workbench.createDisplay(Workbench.java:381)\n\tat org.eclipse.ui.PlatformUI.createDisplay(PlatformUI.java:155)\n\tat org.eclipse.ui.internal.ide.IDEApplication.createDisplay(IDEApplication.java:128)\n\tat org.eclipse.ui.internal.ide.IDEApplication.run(IDEApplication.java:79)\n\tat org.eclipse.core.internal.runtime.PlatformActivator$1.run(PlatformActivator.java:226)\n\tat org.eclipse.core.runtime.adaptor.EclipseStarter.run(EclipseStarter.java:376)\n\tat org.eclipse.core.runtime.adaptor.EclipseStarter.run(EclipseStarter.java:163)\n\tat sun.reflect.NativeMethodAccessorImpl.invoke0(Native Method)\n\tat sun.reflect.NativeMethodAccessorImpl.invoke(NativeMethodAccessorImpl.java:39)\n\tat sun.reflect.DelegatingMethodAccessorImpl.invoke(DelegatingMethodAccessorImpl.java:25)\n\tat java.lang.reflect.Method.invoke(Method.java:324)\n\tat org.eclipse.core.launcher.Main.invokeFramework(Main.java:334)\n\tat org.eclipse.core.launcher.Main.basicRun(Main.java:278)\n\tat org.eclipse.core.launcher.Main.run(Main.java:973)\n\tat org.eclipse.core.launcher.Main.main(Main.java:948)\n-------------------------------------------------------------------------------\n\n\nAs shown above the eclipse cannot find the file /usr/eclipse/configuration/org.eclipse.osgi/bundles/85/1/.cp/libswt-pi-gtk-3139.so\nwhich however exists in the specified directory with the exact name mentioned above!!!!!\nI have searched for solution to this problem in google and i have seen that other people in 64bit systems encounter the same problem with me \nFor example,\nhttp://www.planetamd64.com/lofiversion/index.php/t12898.html",
    "*** Bug 133399 has been marked as a duplicate of this bug. ***",
    "Please launch eclipse with the options \"-console -noExit\".  This should leave you with an osgi\u003e.  Run the \u0027ss\u0027 command to print out the installed bundles.  Attach the output to this bug report.\n\nAlso can you see if setting the execution bit on the library has any effect?",
    "(In reply to comment #2)\n\u003e Please launch eclipse with the options \"-console -noExit\".  This should leave\n\u003e you with an osgi\u003e.  Run the \u0027ss\u0027 command to print out the installed bundles. \n\u003e Attach the output to this bug report.\n\u003e \n\u003e Also can you see if setting the execution bit on the library has any effect?\n\u003e \nHi!\nI\u0027ve got the same problem (AMD64, SUSE 10.0 64bit, eclipse-SDK-3.1.2-linux-gtk-x86_64.tar.gz with checked MD5 sum).\n\nDid as you said and tried to set \u0027x\u0027 bits to user, group AND even others - didn\u0027t help. \n\nThen launched \u0027./eclipse -console -noExit\u0027:\nosgi\u003e ss\n\nFramework is launched.\n\nid      State       Bundle\n0       ACTIVE      system.bundle_3.1.2\n1       ACTIVE      org.eclipse.core.runtime_3.1.2\n2       ACTIVE      org.eclipse.update.configurator_3.1.0\n3       RESOLVED    org.eclipse.tomcat_4.1.30.1\n4       RESOLVED    org.eclipse.jdt.debug.ui_3.1.2\n5       RESOLVED    org.eclipse.sdk_3.1.2\n6       RESOLVED    org.eclipse.jface.text_3.1.2\n7       RESOLVED    org.eclipse.ant.core_3.1.1\n9       RESOLVED    org.eclipse.help.appserver_3.1.0\n10      RESOLVED    org.eclipse.core.filebuffers_3.1.2\n11      RESOLVED    org.eclipse.ui.editors_3.1.1\n12      ACTIVE      org.eclipse.jface_3.1.1\n13      RESOLVED    org.eclipse.jdt_3.1.0\n14      RESOLVED    org.eclipse.ui.workbench.texteditor_3.1.2\n15      ACTIVE      org.eclipse.ui_3.1.2\n16      RESOLVED    org.junit_3.8.1\n17      RESOLVED    org.eclipse.debug.ui_3.1.2\n18      RESOLVED    org.eclipse.ui.forms_3.1.0\n19      RESOLVED    org.eclipse.platform.source.linux.gtk.x86_64_3.1.2\n                    Master\u003d59\n20      RESOLVED    org.eclipse.pde.source_3.1.2\n21      RESOLVED    org.eclipse.ui.cheatsheets_3.1.1\n22      RESOLVED    org.eclipse.jdt.launching_3.1.0\n23      RESOLVED    org.eclipse.jdt.source_3.1.2\n24      RESOLVED    org.eclipse.pde.doc.user_3.1.2\n25      RESOLVED    org.eclipse.pde.runtime_3.1.1\n26      RESOLVED    org.eclipse.update.core_3.1.2\n                    Fragments\u003d71\n27      RESOLVED    org.eclipse.pde.junit.runtime_3.1.0\n28      RESOLVED    org.eclipse.platform_3.1.2\n29      RESOLVED    org.eclipse.osgi.util_3.1.1\n30      RESOLVED    org.eclipse.core.boot_3.1.0\n31      RESOLVED    org.eclipse.jdt.junit.runtime_3.1.0\n32      RESOLVED    org.eclipse.team.core_3.1.1\n33      RESOLVED    org.eclipse.team.ui_3.1.1\n34      ACTIVE      org.eclipse.ui.ide_3.1.1\n35      RESOLVED    org.eclipse.team.cvs.ssh_3.1.0\n36      RESOLVED    org.eclipse.pde.build_3.1.2\n37      RESOLVED    org.eclipse.update.scheduler_3.1.0\n38      RESOLVED    org.eclipse.ltk.ui.refactoring_3.1.1\n40      RESOLVED    org.eclipse.help_3.1.0\n41      RESOLVED    org.eclipse.ui.views_3.1.1\n42      RESOLVED    org.eclipse.rcp.source_3.1.2\n                    Fragments\u003d83\n43      RESOLVED    org.eclipse.team.cvs.core_3.1.1\n44      RESOLVED    org.eclipse.ui.browser_3.1.1\n45      RESOLVED    org.eclipse.help.ui_3.1.1\n46      RESOLVED    org.eclipse.search_3.1.2\n48      RESOLVED    org.eclipse.ui.console_3.1.2\n49      RESOLVED    org.eclipse.core.resources.compatibility_3.1.0\n                    Master\u003d60\n50      ACTIVE      org.eclipse.ui.workbench_3.1.2\n                    Fragments\u003d90\n51      RESOLVED    org.apache.ant_1.6.5\n52      RESOLVED    org.eclipse.pde_3.1.0\n53      RESOLVED    org.eclipse.ui.intro_3.1.1\n54      RESOLVED    org.eclipse.ui.presentations.r21_3.1.0\n55      RESOLVED    org.eclipse.jdt.core_3.1.2\n56      RESOLVED    org.eclipse.platform.doc.user_3.1.1\n57      RESOLVED    org.eclipse.jdt.junit_3.1.1\n58      RESOLVED    org.eclipse.ltk.core.refactoring_3.1.0\n59      RESOLVED    org.eclipse.platform.source_3.1.2\n                    Fragments\u003d19\n60      RESOLVED    org.eclipse.core.resources_3.1.2\n                    Fragments\u003d49, 69\n61      RESOLVED    org.eclipse.compare_3.1.1\n62      RESOLVED    org.eclipse.team.cvs.ui_3.1.1\n63      RESOLVED    org.eclipse.jdt.debug_3.1.1\n64      RESOLVED    org.eclipse.core.variables_3.1.0\n65      RESOLVED    org.eclipse.debug.core_3.1.2\n66      RESOLVED    org.eclipse.update.ui_3.1.1\n67      RESOLVED    org.eclipse.core.expressions_3.1.0\n68      RESOLVED    org.eclipse.ant.ui_3.1.2\n69      RESOLVED    org.eclipse.core.resources.linux_3.1.0\n                    Master\u003d60\n70      RESOLVED    org.eclipse.help.webapp_3.1.0\n71      RESOLVED    org.eclipse.update.core.linux_3.1.0\n                    Master\u003d26\n72      RESOLVED    org.apache.lucene_1.4.3\n73      RESOLVED    org.eclipse.core.commands_3.1.0\n74      RESOLVED    org.eclipse.ui.externaltools_3.1.1\n75      RESOLVED    org.eclipse.swt_3.1.0\n                    Fragments\u003d85\n76      ACTIVE      org.eclipse.core.runtime.compatibility_3.1.0\n77      RESOLVED    org.eclipse.team.cvs.ssh2_3.1.0\n78      RESOLVED    org.eclipse.osgi.services_3.1.2\n79      RESOLVED    org.eclipse.pde.core_3.1.1\n80      RESOLVED    org.eclipse.pde.ui_3.1.2\n81      RESOLVED    org.eclipse.jdt.doc.isv_3.1.2\n82      RESOLVED    org.eclipse.text_3.1.1\n83      RESOLVED    org.eclipse.rcp.source.linux.gtk.x86_64_3.1.2\n                    Master\u003d42\n84      RESOLVED    org.eclipse.jdt.ui_3.1.2\n85      RESOLVED    org.eclipse.swt.gtk.linux.x86_64_3.1.1\n                    Master\u003d75\n86      RESOLVED    org.eclipse.help.base_3.1.0\n87      RESOLVED    org.eclipse.rcp_3.1.0\n88      RESOLVED    org.eclipse.jdt.doc.user_3.1.1\n89      RESOLVED    org.eclipse.platform.doc.isv_3.1.2\n90      RESOLVED    org.eclipse.ui.workbench.compatibility_3.1.0\n                    Master\u003d50\n\nosgi\u003e exit\n\n\n-----------------------------\nmy log entry (to complete things):\n\n!SESSION 2006-04-05 10:17:26.661 -----------------------------------------------\neclipse.buildId\u003dM20060118-1600\njava.version\u003d1.4.2_11\njava.vendor\u003dSun Microsystems Inc.\nBootLoader constants: OS\u003dlinux, ARCH\u003dx86_64, WS\u003dgtk, NL\u003dde_DE\nCommand-line arguments:  -os linux -ws gtk -arch x86_64\n\n!ENTRY org.eclipse.osgi 2006-04-05 10:17:28.504\n!MESSAGE Application error\n!STACK 1\njava.lang.UnsatisfiedLinkError: /opt/eclipse64/eclipse/configuration/org.eclipse.osgi/bundles/85/1/.cp/libswt-pi-gtk-3139.so: /opt/eclipse64/eclipse/configuration/org.eclipse.osgi/bundles/85/1/.cp/libswt-pi-gtk-3139.so: cannot open shared object file: No such file or directory\n\tat java.lang.ClassLoader$NativeLibrary.load(Native Method)\n\tat java.lang.ClassLoader.loadLibrary0(ClassLoader.java:1586)\n\tat java.lang.ClassLoader.loadLibrary(ClassLoader.java:1495)\n\tat java.lang.Runtime.loadLibrary0(Runtime.java:788)\n\tat java.lang.System.loadLibrary(System.java:834)\n\tat org.eclipse.swt.internal.Library.loadLibrary(Library.java:123)\n\tat org.eclipse.swt.internal.gtk.OS.\u003cclinit\u003e(OS.java:19)\n\tat org.eclipse.swt.internal.Converter.wcsToMbcs(Converter.java:63)\n\tat org.eclipse.swt.internal.Converter.wcsToMbcs(Converter.java:54)\n\tat org.eclipse.swt.widgets.Display.\u003cclinit\u003e(Display.java:122)\n\tat org.eclipse.ui.internal.Workbench.createDisplay(Workbench.java:381)\n\tat org.eclipse.ui.PlatformUI.createDisplay(PlatformUI.java:155)\n\tat org.eclipse.ui.internal.ide.IDEApplication.createDisplay(IDEApplication.java:128)\n\tat org.eclipse.ui.internal.ide.IDEApplication.run(IDEApplication.java:79)\n\tat org.eclipse.core.internal.runtime.PlatformActivator$1.run(PlatformActivator.java:226)\n\tat org.eclipse.core.runtime.adaptor.EclipseStarter.run(EclipseStarter.java:376)\n\tat org.eclipse.core.runtime.adaptor.EclipseStarter.run(EclipseStarter.java:163)\n\tat sun.reflect.NativeMethodAccessorImpl.invoke0(Native Method)\n\tat sun.reflect.NativeMethodAccessorImpl.invoke(NativeMethodAccessorImpl.java:39)\n\tat sun.reflect.DelegatingMethodAccessorImpl.invoke(DelegatingMethodAccessorImpl.java:25)\n\tat java.lang.reflect.Method.invoke(Method.java:324)\n\tat org.eclipse.core.launcher.Main.invokeFramework(Main.java:334)\n\tat org.eclipse.core.launcher.Main.basicRun(Main.java:278)\n\tat org.eclipse.core.launcher.Main.run(Main.java:973)\n\tat org.eclipse.core.launcher.Main.main(Main.java:948)\n",
    "(In reply to comment #3)\n\u003e (In reply to comment #2)\n\u003e \u003e Please launch eclipse with the options \"-console -noExit\".  This should leave\n\u003e \u003e you with an osgi\u003e.  Run the \u0027ss\u0027 command to print out the installed bundles. \n\u003e \u003e Attach the output to this bug report.\n\u003e \u003e \n\u003e \u003e Also can you see if setting the execution bit on the library has any effect?\n\u003e \u003e \n\u003e Hi!\n\u003e I\u0027ve got the same problem (AMD64, SUSE 10.0 64bit,\n\u003e eclipse-SDK-3.1.2-linux-gtk-x86_64.tar.gz with checked MD5 sum).\n\nI\u0027ve got it running.\nDid some searching and found this bug 85699, which gave the right hint for my problem and the solution: https://bugs.eclipse.org/bugs/show_bug.cgi?id\u003d85699\n\nAnother example of a very BAD, misleading error message!!!\n\nProblem:\nIn fact, I tried to run the 64bit Eclipse/SWTlib with a 32bit JDK which doesn\u0027t work obviously and which leads to this BAD and MISLEADING error message! Why isn\u0027t there just a JDK version check at startup !!!??? \n\nSolution:\nI\u0027ve just installed the AMD64 version of JDK 5.0 (jdk1.5.0_06) and used the \u0027-vm /path/to/64bit/java\u0027 command line option to start ./eclipse with this JDK -\u003e eclipse runs fine! ",
    "Not sure what error we could give you.  The equinox runtime is pure Java and runs on any cpu.  SWT is trying to load their lib and it does not match what was needed.  They can potentially report a better error.  The same is essentially true of all callers to System.loadLibrary (that is, any normal Java code that has related libs).\n\nMoving to SWT to see if they want to do anything special.",
    "It seems to me that the swt fragment should have had a Bundle-NativeCode header (or similar) which referenced the required details for the so. Then when no clause on the native code header matched (e.g. because 32-bit VM used but have a 64-bit so), an appropriate error message could have been published.\n\nI looked at the manifest for the fragment and it has no Bundle-NativeCode header for the so.\n\nDisclaimer: I no almost nothing about how the SWT plugins are arranged :-)",
    "Currently we do not use the OSGi Bundle-NativeCode header at all as there are various problems with the way it works.  The simple statement is that it does not support variables and so requires the host to enumerate/know about all possible supported platforms.  As I recall (could be old info) putting the header in the fragments was also problematic.\n\nThe other problem was that the bundle native code elements were agressively extracted and installed at bundle install time.  We have several scenarios where the bundles fro several platforms are present (installed) in a system but may or may not resolve depending on the current running environment (e.g., whether or not the WS is GTK or Motif).  Note here that the WS is not know until (and change at) runtime.  That is, well after installing the bundle\n\nHaving said that, we should move to use a standard mechanism as soon as is pratical.  That does not unfortunately help in this case.",
    "Arguably this is the fault of the Linux dynamic linker, it should give\na better errno besides \"no such file or directory\".  The kernel types I\u0027ve\nasked about this usually say \"biarch systems are a bad idea\" and blame\nthe Linux distributions.\n\nI\u0027m marking this as a dup of 85699, we should do some hacky thing where\nwe check the bits and give a better error message, knowing that it\nmay not work perfectly everywhere.\n\n*** This bug has been marked as a duplicate of 85699 ***"
  ],
  "commentCreationDates": [
    "2006-03-27T19:36:22+02:00",
    "2006-03-27T20:28:43+02:00",
    "2006-03-27T20:31:54+02:00",
    "2006-04-05T10:49:02+02:00",
    "2006-04-06T10:34:48+02:00",
    "2006-04-06T20:07:17+02:00",
    "2006-04-06T20:34:26+02:00",
    "2006-04-06T23:23:36+02:00",
    "2006-04-07T00:02:53+02:00"
  ],
  "traces": [
    {
      "exceptionType": "java.lang.UnsatisfiedLinkError",
      "message": "/usr/eclipse/configuration/org.eclipse.osgi/bundles/85/1/.cp/libswt-pi-gtk-3139.so: /usr/eclipse/configuration/org.eclipse.osgi/bundles/85/1/.cp/libswt-pi-gtk-3139.so: cannot open shared object file: No such file or directory",
      "elements": [
        {
          "method": "java.lang.ClassLoader$NativeLibrary.load",
          "source": "Native Method"
        },
        {
          "method": "java.lang.ClassLoader.loadLibrary0",
          "source": "ClassLoader.java:1586"
        },
        {
          "method": "java.lang.ClassLoader.loadLibrary",
          "source": "ClassLoader.java:1495"
        },
        {
          "method": "java.lang.Runtime.loadLibrary0",
          "source": "Runtime.java:788"
        },
        {
          "method": "java.lang.System.loadLibrary",
          "source": "System.java:834"
        },
        {
          "method": "org.eclipse.swt.internal.Library.loadLibrary",
          "source": "Library.java:123"
        },
        {
          "method": "org.eclipse.swt.internal.gtk.OS.\u003cclinit\u003e",
          "source": "OS.java:19"
        },
        {
          "method": "org.eclipse.swt.internal.Converter.wcsToMbcs",
          "source": "Converter.java:63"
        },
        {
          "method": "org.eclipse.swt.internal.Converter.wcsToMbcs",
          "source": "Converter.java:54"
        },
        {
          "method": "org.eclipse.swt.widgets.Display.\u003cclinit\u003e",
          "source": "Display.java:122"
        },
        {
          "method": "org.eclipse.ui.internal.Workbench.createDisplay",
          "source": "Workbench.java:381"
        },
        {
          "method": "org.eclipse.ui.PlatformUI.createDisplay",
          "source": "PlatformUI.java:155"
        },
        {
          "method": "org.eclipse.ui.internal.ide.IDEApplication.createDisplay",
          "source": "IDEApplication.java:128"
        },
        {
          "method": "org.eclipse.ui.internal.ide.IDEApplication.run",
          "source": "IDEApplication.java:79"
        },
        {
          "method": "org.eclipse.core.internal.runtime.PlatformActivator$1.run",
          "source": "PlatformActivator.java:226"
        },
        {
          "method": "org.eclipse.core.runtime.adaptor.EclipseStarter.run",
          "source": "EclipseStarter.java:376"
        },
        {
          "method": "org.eclipse.core.runtime.adaptor.EclipseStarter.run",
          "source": "EclipseStarter.java:163"
        },
        {
          "method": "sun.reflect.NativeMethodAccessorImpl.invoke0",
          "source": "Native Method"
        },
        {
          "method": "sun.reflect.NativeMethodAccessorImpl.invoke",
          "source": "NativeMethodAccessorImpl.java:39"
        },
        {
          "method": "sun.reflect.DelegatingMethodAccessorImpl.invoke",
          "source": "DelegatingMethodAccessorImpl.java:25"
        },
        {
          "method": "java.lang.reflect.Method.invoke",
          "source": "Method.java:324"
        },
        {
          "method": "org.eclipse.core.launcher.Main.invokeFramework",
          "source": "Main.java:334"
        },
        {
          "method": "org.eclipse.core.launcher.Main.basicRun",
          "source": "Main.java:278"
        },
        {
          "method": "org.eclipse.core.launcher.Main.run",
          "source": "Main.java:973"
        },
        {
          "method": "org.eclipse.core.launcher.Main.main",
          "source": "Main.java:948"
        }
      ],
      "number": 0,
      "commentIndex": 0,
      "bugId": "133398",
      "duplicateId": "85699",
      "date": "2006-03-27T19:36:22+02:00",
      "product": "Platform",
      "component": "SWT",
      "severity": "normal"
    },
    {
      "exceptionType": "java.lang.UnsatisfiedLinkError",
      "message": "/opt/eclipse64/eclipse/configuration/org.eclipse.osgi/bundles/85/1/.cp/libswt-pi-gtk-3139.so: /opt/eclipse64/eclipse/configuration/org.eclipse.osgi/bundles/85/1/.cp/libswt-pi-gtk-3139.so: cannot open shared object file: No such file or directory",
      "elements": [
        {
          "method": "java.lang.ClassLoader$NativeLibrary.load",
          "source": "Native Method"
        },
        {
          "method": "java.lang.ClassLoader.loadLibrary0",
          "source": "ClassLoader.java:1586"
        },
        {
          "method": "java.lang.ClassLoader.loadLibrary",
          "source": "ClassLoader.java:1495"
        },
        {
          "method": "java.lang.Runtime.loadLibrary0",
          "source": "Runtime.java:788"
        },
        {
          "method": "java.lang.System.loadLibrary",
          "source": "System.java:834"
        },
        {
          "method": "org.eclipse.swt.internal.Library.loadLibrary",
          "source": "Library.java:123"
        },
        {
          "method": "org.eclipse.swt.internal.gtk.OS.\u003cclinit\u003e",
          "source": "OS.java:19"
        },
        {
          "method": "org.eclipse.swt.internal.Converter.wcsToMbcs",
          "source": "Converter.java:63"
        },
        {
          "method": "org.eclipse.swt.internal.Converter.wcsToMbcs",
          "source": "Converter.java:54"
        },
        {
          "method": "org.eclipse.swt.widgets.Display.\u003cclinit\u003e",
          "source": "Display.java:122"
        },
        {
          "method": "org.eclipse.ui.internal.Workbench.createDisplay",
          "source": "Workbench.java:381"
        },
        {
          "method": "org.eclipse.ui.PlatformUI.createDisplay",
          "source": "PlatformUI.java:155"
        },
        {
          "method": "org.eclipse.ui.internal.ide.IDEApplication.createDisplay",
          "source": "IDEApplication.java:128"
        },
        {
          "method": "org.eclipse.ui.internal.ide.IDEApplication.run",
          "source": "IDEApplication.java:79"
        },
        {
          "method": "org.eclipse.core.internal.runtime.PlatformActivator$1.run",
          "source": "PlatformActivator.java:226"
        },
        {
          "method": "org.eclipse.core.runtime.adaptor.EclipseStarter.run",
          "source": "EclipseStarter.java:376"
        },
        {
          "method": "org.eclipse.core.runtime.adaptor.EclipseStarter.run",
          "source": "EclipseStarter.java:163"
        },
        {
          "method": "sun.reflect.NativeMethodAccessorImpl.invoke0",
          "source": "Native Method"
        },
        {
          "method": "sun.reflect.NativeMethodAccessorImpl.invoke",
          "source": "NativeMethodAccessorImpl.java:39"
        },
        {
          "method": "sun.reflect.DelegatingMethodAccessorImpl.invoke",
          "source": "DelegatingMethodAccessorImpl.java:25"
        },
        {
          "method": "java.lang.reflect.Method.invoke",
          "source": "Method.java:324"
        },
        {
          "method": "org.eclipse.core.launcher.Main.invokeFramework",
          "source": "Main.java:334"
        },
        {
          "method": "org.eclipse.core.launcher.Main.basicRun",
          "source": "Main.java:278"
        },
        {
          "method": "org.eclipse.core.launcher.Main.run",
          "source": "Main.java:973"
        },
        {
          "method": "org.eclipse.core.launcher.Main.main",
          "source": "Main.java:948"
        }
      ],
      "number": 1,
      "commentIndex": 3,
      "bugId": "133398",
      "duplicateId": "85699",
      "date": "2006-04-05T10:49:02+02:00",
      "product": "Platform",
      "component": "SWT",
      "severity": "normal"
    }
  ],
  "groupId": "85699",
  "bugId": "133398",
  "duplicateId": "85699",
  "date": "2006-03-27T19:36:22+02:00",
  "product": "Platform",
  "component": "SWT",
  "severity": "normal"
}