{
  "comments": [
    "If you install WST from the Callisto update site, eclipse will no longer start.  A little experimentation revealed that installing the pre-reqs for WST works just fine.  It is only after installing WST (you don\u0027t have to install the J2EE component to get the fail), will the fail occur.\n\nUntar a fresh 3.2M5a or the latest integration build I20060328-0010\nStart eclipse (this works just fine)\nUse the update manager to Find and Install from the Callisto update site\nSelect the Web Tools Platform\nPress Select Required\nInstall all of the new plug-ins\nSelect Yes to restart the workbench\n\nOptionally, install EMF, GEF, and JEM first, restart, then install WST.\n\nThe following prints to the console:\n\n_X11TransSocketOpen: socket() failed for local\n_X11TransSocketOpenCOTSClient: Unable to open socket for local\n_X11TransOpen: transport open failed for local/tritium.austin.ibm.com:0\n\nEclipse will no longer start up.\n\nHere is the log file:\n\n!SESSION 2006-03-28 08:35:18.761\n-----------------------------------------------\neclipse.buildId\u003dI20060223-1656\njava.fullversion\u003dJ2RE 1.5.0 IBM J9 2.3 Linux x86-32 j9vmxi3223-20060222a (JIT\nenabled)\nJ9VM - 20060220_05389_lHdSMR\nJIT  - 20060220_2133_r8\nGC   - 20060214_AA\nBootLoader constants: OS\u003dlinux, ARCH\u003dx86, WS\u003dgtk, NL\u003den_US\nCommand-line arguments:  -os linux -ws gtk -arch x86\n\n!ENTRY org.eclipse.osgi 4 0 2006-03-28 08:35:23.253\n!MESSAGE Application error\n!STACK 1\norg.eclipse.swt.SWTError: No more handles [gtk_init_check() failed]\n        at org.eclipse.swt.SWT.error(SWT.java:3375)\n        at org.eclipse.swt.widgets.Display.createDisplay(Display.java:788)\n        at org.eclipse.swt.widgets.Display.create(Display.java:776)\n        at org.eclipse.swt.graphics.Device.\u003cinit\u003e(Device.java:145)\n        at org.eclipse.swt.widgets.Display.\u003cinit\u003e(Display.java:452)\n        at org.eclipse.swt.widgets.Display.\u003cinit\u003e(Display.java:443)\n        at org.eclipse.ui.internal.Workbench.createDisplay(Workbench.java:444)\n        at org.eclipse.ui.PlatformUI.createDisplay(PlatformUI.java:155)\n        at\norg.eclipse.ui.internal.ide.IDEApplication.createDisplay(IDEApplication.java:131)\n        at\norg.eclipse.ui.internal.ide.IDEApplication.run(IDEApplication.java:82)\n        at\norg.eclipse.core.internal.runtime.PlatformActivator$1.run(PlatformActivator.java:99)\n        at\norg.eclipse.core.runtime.internal.adaptor.EclipseAppLauncher.runApplication(EclipseAppLauncher.java:92)\n        at\norg.eclipse.core.runtime.internal.adaptor.EclipseAppLauncher.start(EclipseAppLauncher.java:68)\n        at\norg.eclipse.core.runtime.adaptor.EclipseStarter.run(EclipseStarter.java:374)\n        at\norg.eclipse.core.runtime.adaptor.EclipseStarter.run(EclipseStarter.java:169)\n        at sun.reflect.NativeMethodAccessorImpl.invoke0(Native Method)\n        at\nsun.reflect.NativeMethodAccessorImpl.invoke(NativeMethodAccessorImpl.java:64)\n        at\nsun.reflect.DelegatingMethodAccessorImpl.invoke(DelegatingMethodAccessorImpl.java:43)\n        at java.lang.reflect.Method.invoke(Method.java:615)\n        at org.eclipse.core.launcher.Main.invokeFramework(Main.java:338)\n        at org.eclipse.core.launcher.Main.basicRun(Main.java:282)\n        at org.eclipse.core.launcher.Main.run(Main.java:977)\n        at org.eclipse.core.launcher.Main.main(Main.java:952)",
    "Bryan, do you set MOZILLA_FIVE_HOME on your linux system? \nI don\u0027t recall details, but there\u0027s some swt browser things that needs this, perhaps only on some versions of linux, but I think it results in that type of \"no more handles\" error. \n\nOn my linux system, I use the following in my .bashrc\ndeclare -X MOZILLA_FIVE_HOME\u003d\"/usr/lib/mozilla-1.4.3/\"\n\nIf possible, that might be a \"quick test\" for you to try, to see if related. \n\nThanks, \n",
    "See bug 103611 and and bug 103628. \n\nIf this is indeed the problem, seems as though some base code has changed to not even print the warning that MOZILLA_FIVE_HOME not defined. \n\n",
    "Bryan, can you increase the number of handles to try to get by the startup? Perhaps WTP really does need more handles. I assume these are file handles. ",
    "I do not set MOZILLA_FIVE_HOME.  I tried\n\nexport MOZILLA_FIVE_HOME\u003d/usr/lib/mozilla-1.7.12\n\nand that did not work.\n\nHow do I increase the number of available handles?",
    "See the history and discussion in bug 106396.\n\n*** This bug has been marked as a duplicate of 106396 ***",
    "Billy, thanks for catching. \nBryon, thanks for verifying that \nsetting JAVA_HIGH_ZIPFDS\u003d500  \nfixes the problem. \n",
    "Closed."
  ],
  "commentCreationDates": [
    "2006-03-28T17:49:23+02:00",
    "2006-03-28T19:05:31+02:00",
    "2006-03-28T19:11:19+02:00",
    "2006-03-28T19:17:48+02:00",
    "2006-03-28T19:30:30+02:00",
    "2006-03-28T19:34:50+02:00",
    "2006-03-29T04:32:48+02:00",
    "2006-06-22T20:48:47+02:00"
  ],
  "traces": [
    {
      "exceptionType": "org.eclipse.swt.SWTError",
      "message": "No more handles [gtk_init_check() failed]",
      "elements": [
        {
          "method": "org.eclipse.swt.SWT.error",
          "source": "SWT.java:3375"
        },
        {
          "method": "org.eclipse.swt.widgets.Display.createDisplay",
          "source": "Display.java:788"
        },
        {
          "method": "org.eclipse.swt.widgets.Display.create",
          "source": "Display.java:776"
        },
        {
          "method": "org.eclipse.swt.graphics.Device.\u003cinit\u003e",
          "source": "Device.java:145"
        },
        {
          "method": "org.eclipse.swt.widgets.Display.\u003cinit\u003e",
          "source": "Display.java:452"
        },
        {
          "method": "org.eclipse.swt.widgets.Display.\u003cinit\u003e",
          "source": "Display.java:443"
        },
        {
          "method": "org.eclipse.ui.internal.Workbench.createDisplay",
          "source": "Workbench.java:444"
        },
        {
          "method": "org.eclipse.ui.PlatformUI.createDisplay",
          "source": "PlatformUI.java:155"
        },
        {
          "method": "org.eclipse.ui.internal.ide.IDEApplication.createDisplay",
          "source": "IDEApplication.java:131"
        },
        {
          "method": "org.eclipse.ui.internal.ide.IDEApplication.run",
          "source": "IDEApplication.java:82"
        },
        {
          "method": "org.eclipse.core.internal.runtime.PlatformActivator$1.run",
          "source": "PlatformActivator.java:99"
        },
        {
          "method": "org.eclipse.core.runtime.internal.adaptor.EclipseAppLauncher.runApplication",
          "source": "EclipseAppLauncher.java:92"
        },
        {
          "method": "org.eclipse.core.runtime.internal.adaptor.EclipseAppLauncher.start",
          "source": "EclipseAppLauncher.java:68"
        },
        {
          "method": "org.eclipse.core.runtime.adaptor.EclipseStarter.run",
          "source": "EclipseStarter.java:374"
        },
        {
          "method": "org.eclipse.core.runtime.adaptor.EclipseStarter.run",
          "source": "EclipseStarter.java:169"
        },
        {
          "method": "sun.reflect.NativeMethodAccessorImpl.invoke0",
          "source": "Native Method"
        },
        {
          "method": "sun.reflect.NativeMethodAccessorImpl.invoke",
          "source": "NativeMethodAccessorImpl.java:64"
        },
        {
          "method": "sun.reflect.DelegatingMethodAccessorImpl.invoke",
          "source": "DelegatingMethodAccessorImpl.java:43"
        },
        {
          "method": "java.lang.reflect.Method.invoke",
          "source": "Method.java:615"
        },
        {
          "method": "org.eclipse.core.launcher.Main.invokeFramework",
          "source": "Main.java:338"
        },
        {
          "method": "org.eclipse.core.launcher.Main.basicRun",
          "source": "Main.java:282"
        },
        {
          "method": "org.eclipse.core.launcher.Main.run",
          "source": "Main.java:977"
        },
        {
          "method": "org.eclipse.core.launcher.Main.main",
          "source": "Main.java:952"
        }
      ],
      "number": 0,
      "commentIndex": 0,
      "bugId": "133593",
      "duplicateId": "106396",
      "date": "2006-03-28T17:49:23+02:00",
      "product": "Web Tools",
      "component": "Web Standard Tools",
      "severity": "blocker"
    }
  ],
  "groupId": "106396",
  "bugId": "133593",
  "duplicateId": "106396",
  "date": "2006-03-28T17:49:23+02:00",
  "product": "Web Tools",
  "component": "Web Standard Tools",
  "severity": "blocker"
}