{
  "comments": [
    "1.  From a Java project, export the project as jar with source included in the jar.  (Project A)\n2.  I have another java project (Project B) depending on this project.  I modified the classpath from its launch config to include the exported jar instead of the project. (I removed the default classpath.  Then I added Project B back.  Then I added the jar file.)\n\nClasspath looks like this:\n* User Entries:\n  * Project B\n  * projectA.jar\n\n3.  Run the debug session and step into code from Project B.  Got the exception when trying when the debug session is terminated.  \n\nIt only happened once, not sure how to reproduce it.\n\nFrom Error Log:\nAn internal error occurred during \"Initializing Quick Diff\".\n\njava.lang.IllegalStateException: zip file closed\n\tat java.util.zip.ZipFile.ensureOpen(ZipFile.java:550)\n\tat java.util.zip.ZipFile.getInputStream(ZipFile.java:335)\n\tat java.util.zip.ZipFile.getInputStream(ZipFile.java:321)\n\tat org.eclipse.debug.core.sourcelookup.containers.ZipEntryStorage.getContents(ZipEntryStorage.java:66)\n\tat org.eclipse.ui.internal.editors.quickdiff.LastSaveReferenceProvider.setDocumentContent(LastSaveReferenceProvider.java:367)\n\tat org.eclipse.ui.internal.editors.quickdiff.LastSaveReferenceProvider.readDocument(LastSaveReferenceProvider.java:252)\n\tat org.eclipse.ui.internal.editors.quickdiff.LastSaveReferenceProvider.getReference(LastSaveReferenceProvider.java:123)\n\tat org.eclipse.ui.internal.texteditor.quickdiff.DocumentLineDiffer$1.run(DocumentLineDiffer.java:467)\n\tat org.eclipse.core.internal.jobs.Worker.run(Worker.java:58)",
    "looks like the quick diff editor was using our editor input. Not sure how to reproduce.",
    "Marking as works for me, unless we can find steps to reproduce."
  ],
  "commentCreationDates": [
    "2006-03-28T22:43:30+02:00",
    "2006-03-29T19:19:12+02:00",
    "2006-03-31T17:36:49+02:00"
  ],
  "traces": [
    {
      "exceptionType": "java.lang.IllegalStateException",
      "message": "zip file closed",
      "elements": [
        {
          "method": "java.util.zip.ZipFile.ensureOpen",
          "source": "ZipFile.java:550"
        },
        {
          "method": "java.util.zip.ZipFile.getInputStream",
          "source": "ZipFile.java:335"
        },
        {
          "method": "java.util.zip.ZipFile.getInputStream",
          "source": "ZipFile.java:321"
        },
        {
          "method": "org.eclipse.debug.core.sourcelookup.containers.ZipEntryStorage.getContents",
          "source": "ZipEntryStorage.java:66"
        },
        {
          "method": "org.eclipse.ui.internal.editors.quickdiff.LastSaveReferenceProvider.setDocumentContent",
          "source": "LastSaveReferenceProvider.java:367"
        },
        {
          "method": "org.eclipse.ui.internal.editors.quickdiff.LastSaveReferenceProvider.readDocument",
          "source": "LastSaveReferenceProvider.java:252"
        },
        {
          "method": "org.eclipse.ui.internal.editors.quickdiff.LastSaveReferenceProvider.getReference",
          "source": "LastSaveReferenceProvider.java:123"
        },
        {
          "method": "org.eclipse.ui.internal.texteditor.quickdiff.DocumentLineDiffer$1.run",
          "source": "DocumentLineDiffer.java:467"
        },
        {
          "method": "org.eclipse.core.internal.jobs.Worker.run",
          "source": "Worker.java:58"
        }
      ],
      "number": 0,
      "commentIndex": 0,
      "bugId": "133720",
      "date": "2006-03-28T22:43:30+02:00",
      "product": "Platform",
      "component": "Debug",
      "severity": "normal"
    }
  ],
  "groupId": "133720",
  "bugId": "133720",
  "date": "2006-03-28T22:43:30+02:00",
  "product": "Platform",
  "component": "Debug",
  "severity": "normal"
}