{
  "comments": [
    "I used the update procedure to update the 20050527 build to 3.1.2 and now I don\u0027t start.  I get:\n\n!SESSION 2006-03-31 12:13:32.590 -----------------------------------------------\neclipse.buildId\u003dI20050527-1300\njava.version\u003d1.5.0_01\njava.vendor\u003dSun Microsystems Inc.\nBootLoader constants: OS\u003dlinux, ARCH\u003dx86, WS\u003dgtk, NL\u003den_US\nCommand-line arguments:  -os linux -ws gtk -arch x86 -data /home/catfish/test/.eclipse_workspace_data\n\n!ENTRY org.eclipse.osgi 2006-03-31 12:13:34.409\n!MESSAGE Application error\n!STACK 1\njava.lang.VerifyError: (class: org/eclipse/ui/internal/ide/IDEWorkbenchAdvisor, method: refreshFromLocal signature: ()V) Incompatible object argument for function call\n        at org.eclipse.ui.internal.ide.IDEApplication.run(IDEApplication.java:104)\n        at org.eclipse.core.internal.runtime.PlatformActivator$1.run(PlatformActivator.java:226)\n        at org.eclipse.core.runtime.adaptor.EclipseStarter.run(EclipseStarter.java:376)\n        at org.eclipse.core.runtime.adaptor.EclipseStarter.run(EclipseStarter.java:163)\n        at sun.reflect.NativeMethodAccessorImpl.invoke0(Native Method)\n        at sun.reflect.NativeMethodAccessorImpl.invoke(NativeMethodAccessorImpl.java:39)\n        at sun.reflect.DelegatingMethodAccessorImpl.invoke(DelegatingMethodAccessorImpl.java:25)\n        at java.lang.reflect.Method.invoke(Method.java:585)\n        at org.eclipse.core.launcher.Main.invokeFramework(Main.java:334)\n        at org.eclipse.core.launcher.Main.basicRun(Main.java:278)\n        at org.eclipse.core.launcher.Main.run(Main.java:973)\n        at org.eclipse.core.launcher.Main.main(Main.java:948)",
    "This is unfortunatly a wellknow bug, however if you have more details on how to reproduce this that would great.",
    "any advice on how to revert it so I have a working eclipse?",
    "Unfortunately there is nothing easy. You have reinstall eclipse. The best is probably to directly download 3.1.2.",
    "Chris you were not on 3.1.0 level but on 20050527 which was one of the 3.1 RC builds and there were many changes between it and 3.1.0, which came month later. Moving from 3.1 RC builds to 3.1.x is not supported."
  ],
  "commentCreationDates": [
    "2006-03-31T18:22:14+02:00",
    "2006-04-01T00:52:14+02:00",
    "2006-04-01T01:00:26+02:00",
    "2006-04-03T16:04:16+02:00",
    "2006-06-23T06:45:07+02:00"
  ],
  "traces": [
    {
      "exceptionType": "java.lang.VerifyError",
      "message": "(class: org/eclipse/ui/internal/ide/IDEWorkbenchAdvisor, method: refreshFromLocal signature: ()V) Incompatible object argument for function call",
      "elements": [
        {
          "method": "org.eclipse.ui.internal.ide.IDEApplication.run",
          "source": "IDEApplication.java:104"
        },
        {
          "method": "org.eclipse.core.internal.runtime.PlatformActivator$1.run",
          "source": "PlatformActivator.java:226"
        },
        {
          "method": "org.eclipse.core.runtime.adaptor.EclipseStarter.run",
          "source": "EclipseStarter.java:376"
        },
        {
          "method": "org.eclipse.core.runtime.adaptor.EclipseStarter.run",
          "source": "EclipseStarter.java:163"
        },
        {
          "method": "sun.reflect.NativeMethodAccessorImpl.invoke0",
          "source": "Native Method"
        },
        {
          "method": "sun.reflect.NativeMethodAccessorImpl.invoke",
          "source": "NativeMethodAccessorImpl.java:39"
        },
        {
          "method": "sun.reflect.DelegatingMethodAccessorImpl.invoke",
          "source": "DelegatingMethodAccessorImpl.java:25"
        },
        {
          "method": "java.lang.reflect.Method.invoke",
          "source": "Method.java:585"
        },
        {
          "method": "org.eclipse.core.launcher.Main.invokeFramework",
          "source": "Main.java:334"
        },
        {
          "method": "org.eclipse.core.launcher.Main.basicRun",
          "source": "Main.java:278"
        },
        {
          "method": "org.eclipse.core.launcher.Main.run",
          "source": "Main.java:973"
        },
        {
          "method": "org.eclipse.core.launcher.Main.main",
          "source": "Main.java:948"
        }
      ],
      "number": 0,
      "commentIndex": 0,
      "bugId": "134288",
      "date": "2006-03-31T18:22:14+02:00",
      "product": "Platform",
      "component": "Update",
      "severity": "normal"
    }
  ],
  "groupId": "134288",
  "bugId": "134288",
  "date": "2006-03-31T18:22:14+02:00",
  "product": "Platform",
  "component": "Update",
  "severity": "normal"
}