{
  "comments": [
    "SWT Motif CVS\n\nException in thread \"main\" java.lang.StringIndexOutOfBoundsException: String index out of range: 11\n\tat java.lang.String.substring(String.java:1441)\n\tat org.eclipse.swt.widgets.TableColumn.computeDisplayText(TableColumn.java:207)\n\tat org.eclipse.swt.widgets.TableColumn.setSortDirection(TableColumn.java:651)\n\tat org.eclipse.swt.widgets.Table.setSortColumn(Table.java:3491)\n\n--\nOR\n--\n\nException in thread \"main\" java.lang.StringIndexOutOfBoundsException: String ind\nex out of range: 11\n        at java.lang.String.substring(String.java:1441)\n        at org.eclipse.swt.widgets.TableColumn.computeDisplayText(TableColumn.ja\nva:207)\n        at org.eclipse.swt.widgets.TableColumn.updateWidth(TableColumn.java:703)\n        at org.eclipse.swt.widgets.Table.updateColumnWidth(Table.java:3792)\n        at org.eclipse.swt.widgets.TableColumn.setWidth(TableColumn.java:693)\n\n----\n\n\n   public static void main(String[] args) {\n        final Display display \u003d new Display();\n\n        final Shell shell \u003d new Shell(display);\n        shell.setLayout(new FillLayout());\n    \n        final Table table \u003d new Table(shell, SWT.VIRTUAL\n                | SWT.FULL_SELECTION | SWT.MULTI);\n\n        final int columns \u003d 11;\n        for (int i \u003d 0; i \u003c columns; i++) {\n            TableColumn tc \u003d new TableColumn(table, SWT.LEFT);\n            tc.setText(\"Directory\");\n            tc.setWidth(137);\n        }\n        \n        table.setHeaderVisible(true);\n        table.setLinesVisible(true);\n        \n        table.setSortDirection(SWT.DOWN);\n        table.setSortColumn(table.getColumn(0));\n    \n        shell.setSize(350, 200);\n        shell.open();\n\n        while (!shell.isDisposed()) {\n            if (!display.readAndDispatch())\n                display.sleep();\n        }\n        display.dispose();\n    }",
    "fixed \u003e 0403 in TableColumn and TreeColumn\n\nNote that I was not able to reproduce the problem with the provided snippet, but it\u0027s obvious to see from the trace what is happening.  If you\u0027re working from CVS  then you can try the latest just to verify that this is now working for you.\n"
  ],
  "commentCreationDates": [
    "2006-04-01T22:30:54+02:00",
    "2006-04-03T17:27:29+02:00"
  ],
  "traces": [
    {
      "exceptionType": "java.lang.StringIndexOutOfBoundsException",
      "message": "String index out of range: 11",
      "elements": [
        {
          "method": "java.lang.String.substring",
          "source": "String.java:1441"
        },
        {
          "method": "org.eclipse.swt.widgets.TableColumn.computeDisplayText",
          "source": "TableColumn.java:207"
        },
        {
          "method": "org.eclipse.swt.widgets.TableColumn.setSortDirection",
          "source": "TableColumn.java:651"
        },
        {
          "method": "org.eclipse.swt.widgets.Table.setSortColumn",
          "source": "Table.java:3491"
        }
      ],
      "number": 0,
      "commentIndex": 0,
      "bugId": "134382",
      "date": "2006-04-01T22:30:54+02:00",
      "product": "Platform",
      "component": "SWT",
      "severity": "normal"
    },
    {
      "exceptionType": "java.lang.StringIndexOutOfBoundsException",
      "message": "String ind ex out of range: 11",
      "elements": [
        {
          "method": "java.lang.String.substring",
          "source": "String.java:1441"
        },
        {
          "method": "org.eclipse.swt.widgets.TableColumn.computeDisplayText",
          "source": "TableColumn.ja va:207"
        },
        {
          "method": "org.eclipse.swt.widgets.TableColumn.updateWidth",
          "source": "TableColumn.java:703"
        },
        {
          "method": "org.eclipse.swt.widgets.Table.updateColumnWidth",
          "source": "Table.java:3792"
        },
        {
          "method": "org.eclipse.swt.widgets.TableColumn.setWidth",
          "source": "TableColumn.java:693"
        }
      ],
      "number": 1,
      "commentIndex": 0,
      "bugId": "134382",
      "date": "2006-04-01T22:30:54+02:00",
      "product": "Platform",
      "component": "SWT",
      "severity": "normal"
    }
  ],
  "groupId": "134382",
  "bugId": "134382",
  "date": "2006-04-01T22:30:54+02:00",
  "product": "Platform",
  "component": "SWT",
  "severity": "normal"
}