{
  "comments": [
    "Running eclipse -vmargs -Dfoo results in a crash with the following dump:\n\njava(896,0xa000cf80) malloc: java(896,0x1804600) malloc: *** error for object 0x342020: i*** error for object 0x342020: incorrect checksum for freed objencorrect checksum for freed object - object was probably modifiect - object was probably modified after being freed, break at szd after being freed, break at szone_error to debug\none_error to debug\njava(896,0xa000cf80) malloc: java(896,0x1804600) malloc: *** set a breakpoint in szone_er*** set a breakpoint in szone_error to debug\nror to debug\n\nIntel Mac, OS X 10.4.5, JDK 1.5.0_06-111, Eclipse 3.2M6",
    "\nSteve, can you feed me the complete command line that you\u0027re using...my simple test worked for me.\n",
    "(In reply to comment #1)\n\u003e Steve, can you feed me the complete command line that you\u0027re using...my simple\n\u003e test worked for me.\n\u003e \n\n./eclipse -vmargs -Dfoo\n\nI verified that the problem also exists on a coworkers PowerBook G4, also running JDK 1.5.0_06-111. I was able to get a litte more info on the console this time:\n\nException in thread \"Thread-17\" org.eclipse.swt.SWTException: Invalid thread access\n        at org.eclipse.swt.SWT.error(SWT.java:3374)\n        at org.eclipse.swt.SWT.error(SWT.java:3297)\n        at org.eclipse.swt.SWT.error(SWT.java:3268)\n        at org.eclipse.swt.widgets.Widget.error(Widget.java:650)\n        at org.eclipse.swt.widgets.Widget.checkWidget(Widget.java:328)\n        at org.eclipse.swt.widgets.Control.internal_new_GC(Control.java:1303)\n        at org.eclipse.swt.graphics.GC.carbon_new(GC.java:163)\n        at org.eclipse.swt.widgets.Label.drawWidget(Label.java:185)\n        at org.eclipse.swt.widgets.Widget.kEventControlDraw(Widget.java:995)\n        at org.eclipse.swt.widgets.Widget.controlProc(Widget.java:349)\n        at org.eclipse.swt.widgets.Display.controlProc(Display.java:830)\njava(319,0x1804600) malloc: *** error for object 0x341b00: double free\njava(319,0x1804600) malloc: *** set a breakpoint in szone_error to debug\nInvalid memory access of location 00000000 eip\u003d9170a10f",
    "\nMac bug ??\n",
    "You need the -XstartOnFirstThread VM arg. Reopen this bug report if you can\u0027t get it to work.\n\nSee http://www.eclipse.org/swt/macosx/ for more details about how to run SWT on the Mac (if you are interested, there is more detail there than you need).",
    "Changing OS from Mac OS to Mac OS X as per bug 185991"
  ],
  "commentCreationDates": [
    "2006-04-02T09:25:23+02:00",
    "2006-04-03T17:36:43+02:00",
    "2006-04-03T23:00:50+02:00",
    "2006-04-07T17:00:44+02:00",
    "2006-04-11T17:19:58+02:00",
    "2007-07-29T15:19:22+02:00"
  ],
  "traces": [
    {
      "exceptionType": "org.eclipse.swt.SWTException",
      "message": "Invalid thread access",
      "elements": [
        {
          "method": "org.eclipse.swt.SWT.error",
          "source": "SWT.java:3374"
        },
        {
          "method": "org.eclipse.swt.SWT.error",
          "source": "SWT.java:3297"
        },
        {
          "method": "org.eclipse.swt.SWT.error",
          "source": "SWT.java:3268"
        },
        {
          "method": "org.eclipse.swt.widgets.Widget.error",
          "source": "Widget.java:650"
        },
        {
          "method": "org.eclipse.swt.widgets.Widget.checkWidget",
          "source": "Widget.java:328"
        },
        {
          "method": "org.eclipse.swt.widgets.Control.internal_new_GC",
          "source": "Control.java:1303"
        },
        {
          "method": "org.eclipse.swt.graphics.GC.carbon_new",
          "source": "GC.java:163"
        },
        {
          "method": "org.eclipse.swt.widgets.Label.drawWidget",
          "source": "Label.java:185"
        },
        {
          "method": "org.eclipse.swt.widgets.Widget.kEventControlDraw",
          "source": "Widget.java:995"
        },
        {
          "method": "org.eclipse.swt.widgets.Widget.controlProc",
          "source": "Widget.java:349"
        },
        {
          "method": "org.eclipse.swt.widgets.Display.controlProc",
          "source": "Display.java:830"
        }
      ],
      "number": 0,
      "commentIndex": 2,
      "bugId": "134404",
      "date": "2006-04-03T23:00:50+02:00",
      "product": "Platform",
      "component": "SWT",
      "severity": "major"
    }
  ],
  "groupId": "134404",
  "bugId": "134404",
  "date": "2006-04-02T09:25:23+02:00",
  "product": "Platform",
  "component": "SWT",
  "severity": "major"
}