{
  "comments": [
    "\u003e\u003e o  I can\u0027t get the DDL generation to work at all.  I can click on it and \n\u003e\u003e it acts like it\u0027s doing something, but I don\u0027t see anything get generated. \n\u003e\u003e  And, since this is at the project level, will it be traversing all \n\u003e\u003e Entities in the project and attempting to generate the ddl associated with \n\u003e\u003e every Entity.  If the Entity was already properly annotated based on a \n\u003e\u003e database connection, will it generate ddl anyway?  I really wanted this \n\u003e\u003e feature to work since I am not a ddl expert and wanted to work top down.  \n\u003e\u003e It\u0027s just not intuitive yet.\n\n\u003e Did an error go to the error log?  Did the entity generation wizard ever \n\u003e open?  The point of the DDL gen is to take the already annotated classes \n\u003e and create ddl.  At a minimum you will have to add the Entity anotation \n\u003e and the id annotation and annotations for any reference mappings.  After \n\u003e that the generator will use the defaults defined in the persistence spec.  \n\u003e Yes, if the entity is annotated with info based on the database \n\u003e connection, it will generate ddl.\n\nI never did receive the ddl generation wizard to appear.  Thus, this bug report.  I\u0027m not sure if I can add anything else to help reproduce the problem.\n\nI do notice the following errors in the error.log whenever I attempt to use the ddl generation wizard selection (this is the same whether I have a database connection or not):\n\nError 2006-04-04 12:29:54.371 org.eclipse.dali.internal.utility.JDBCTools\njava.lang.NoClassDefFoundError: org.eclipse.dali.internal.utility.JDBCTools\n\tat org.eclipse.dali.db.ddl.OrmDdlGenerator.getJdbcType(OrmDdlGenerator.java:194)\n\tat org.eclipse.dali.db.ddl.OrmDdlGenerator.addBasicColumns(OrmDdlGenerator.java:268)\n\tat org.eclipse.dali.db.ddl.OrmDdlGenerator.createDdl(OrmDdlGenerator.java:219)\n\tat org.eclipse.dali.ui.actions.GenerateDdlAction.execute(GenerateDdlAction.java:28)\n\tat org.eclipse.dali.ui.actions.ProjectAction.execute(ProjectAction.java:90)\n\tat org.eclipse.dali.ui.actions.ProjectAction.execute(ProjectAction.java:71)\n\tat org.eclipse.dali.ui.actions.ProjectAction.run(ProjectAction.java:63)\n\tat org.eclipse.ui.internal.PluginAction.runWithEvent(PluginAction.java:246)\n\tat org.eclipse.jface.action.ActionContributionItem.handleWidgetSelection(ActionContributionItem.java:538)\n\tat org.eclipse.jface.action.ActionContributionItem.access$2(ActionContributionItem.java:488)\n\tat org.eclipse.jface.action.ActionContributionItem$5.handleEvent(ActionContributionItem.java:400)\n\tat org.eclipse.swt.widgets.EventTable.sendEvent(EventTable.java:66)\n\tat org.eclipse.swt.widgets.Widget.sendEvent(Widget.java:843)\n\tat org.eclipse.swt.widgets.Display.runDeferredEvents(Display.java:3125)\n\tat org.eclipse.swt.widgets.Display.readAndDispatch(Display.java:2758)\n\tat org.eclipse.ui.internal.Workbench.runEventLoop(Workbench.java:1699)\n\tat org.eclipse.ui.internal.Workbench.runUI(Workbench.java:1663)\n\tat org.eclipse.ui.internal.Workbench.createAndRunWorkbench(Workbench.java:367)\n\tat org.eclipse.ui.PlatformUI.createAndRunWorkbench(PlatformUI.java:143)\n\tat org.eclipse.ui.internal.ide.IDEApplication.run(IDEApplication.java:103)\n\tat org.eclipse.core.internal.runtime.PlatformActivator$1.run(PlatformActivator.java:226)\n\tat org.eclipse.core.runtime.adaptor.EclipseStarter.run(EclipseStarter.java:376)\n\tat org.eclipse.core.runtime.adaptor.EclipseStarter.run(EclipseStarter.java:163)\n\tat sun.reflect.NativeMethodAccessorImpl.invoke0(Native Method)\n\tat sun.reflect.NativeMethodAccessorImpl.invoke(NativeMethodAccessorImpl.java:64)\n\tat sun.reflect.DelegatingMethodAccessorImpl.invoke(DelegatingMethodAccessorImpl.java:43)\n\tat java.lang.reflect.Method.invoke(Method.java:615)\n\tat org.eclipse.core.launcher.Main.invokeFramework(Main.java:334)\n\tat org.eclipse.core.launcher.Main.basicRun(Main.java:278)\n\tat org.eclipse.core.launcher.Main.run(Main.java:973)\n\tat org.eclipse.core.launcher.Main.main(Main.java:948)\n\nError 2006-04-04 12:29:54.321 Unhandled event loop exception\n \nHope this helps.  Thanks.",
    "Not sure what was wrong with my environment.  It looked okay, but I deleted what I had and re-installed the Latest M1 driver and now the ddl generation wizard appears!  I\u0027m cancelling this bug.  Thank you.",
    "Closing as part of mass query to clean up old resolved bugs in untargetted milestones."
  ],
  "commentCreationDates": [
    "2006-04-04T19:37:53+02:00",
    "2006-04-12T18:25:19+02:00",
    "2007-04-03T17:49:46+02:00"
  ],
  "traces": [
    {
      "exceptionType": "java.lang.NoClassDefFoundError",
      "message": "org.eclipse.dali.internal.utility.JDBCTools",
      "elements": [
        {
          "method": "org.eclipse.dali.db.ddl.OrmDdlGenerator.getJdbcType",
          "source": "OrmDdlGenerator.java:194"
        },
        {
          "method": "org.eclipse.dali.db.ddl.OrmDdlGenerator.addBasicColumns",
          "source": "OrmDdlGenerator.java:268"
        },
        {
          "method": "org.eclipse.dali.db.ddl.OrmDdlGenerator.createDdl",
          "source": "OrmDdlGenerator.java:219"
        },
        {
          "method": "org.eclipse.dali.ui.actions.GenerateDdlAction.execute",
          "source": "GenerateDdlAction.java:28"
        },
        {
          "method": "org.eclipse.dali.ui.actions.ProjectAction.execute",
          "source": "ProjectAction.java:90"
        },
        {
          "method": "org.eclipse.dali.ui.actions.ProjectAction.execute",
          "source": "ProjectAction.java:71"
        },
        {
          "method": "org.eclipse.dali.ui.actions.ProjectAction.run",
          "source": "ProjectAction.java:63"
        },
        {
          "method": "org.eclipse.ui.internal.PluginAction.runWithEvent",
          "source": "PluginAction.java:246"
        },
        {
          "method": "org.eclipse.jface.action.ActionContributionItem.handleWidgetSelection",
          "source": "ActionContributionItem.java:538"
        },
        {
          "method": "org.eclipse.jface.action.ActionContributionItem.access$2",
          "source": "ActionContributionItem.java:488"
        },
        {
          "method": "org.eclipse.jface.action.ActionContributionItem$5.handleEvent",
          "source": "ActionContributionItem.java:400"
        },
        {
          "method": "org.eclipse.swt.widgets.EventTable.sendEvent",
          "source": "EventTable.java:66"
        },
        {
          "method": "org.eclipse.swt.widgets.Widget.sendEvent",
          "source": "Widget.java:843"
        },
        {
          "method": "org.eclipse.swt.widgets.Display.runDeferredEvents",
          "source": "Display.java:3125"
        },
        {
          "method": "org.eclipse.swt.widgets.Display.readAndDispatch",
          "source": "Display.java:2758"
        },
        {
          "method": "org.eclipse.ui.internal.Workbench.runEventLoop",
          "source": "Workbench.java:1699"
        },
        {
          "method": "org.eclipse.ui.internal.Workbench.runUI",
          "source": "Workbench.java:1663"
        },
        {
          "method": "org.eclipse.ui.internal.Workbench.createAndRunWorkbench",
          "source": "Workbench.java:367"
        },
        {
          "method": "org.eclipse.ui.PlatformUI.createAndRunWorkbench",
          "source": "PlatformUI.java:143"
        },
        {
          "method": "org.eclipse.ui.internal.ide.IDEApplication.run",
          "source": "IDEApplication.java:103"
        },
        {
          "method": "org.eclipse.core.internal.runtime.PlatformActivator$1.run",
          "source": "PlatformActivator.java:226"
        },
        {
          "method": "org.eclipse.core.runtime.adaptor.EclipseStarter.run",
          "source": "EclipseStarter.java:376"
        },
        {
          "method": "org.eclipse.core.runtime.adaptor.EclipseStarter.run",
          "source": "EclipseStarter.java:163"
        },
        {
          "method": "sun.reflect.NativeMethodAccessorImpl.invoke0",
          "source": "Native Method"
        },
        {
          "method": "sun.reflect.NativeMethodAccessorImpl.invoke",
          "source": "NativeMethodAccessorImpl.java:64"
        },
        {
          "method": "sun.reflect.DelegatingMethodAccessorImpl.invoke",
          "source": "DelegatingMethodAccessorImpl.java:43"
        },
        {
          "method": "java.lang.reflect.Method.invoke",
          "source": "Method.java:615"
        },
        {
          "method": "org.eclipse.core.launcher.Main.invokeFramework",
          "source": "Main.java:334"
        },
        {
          "method": "org.eclipse.core.launcher.Main.basicRun",
          "source": "Main.java:278"
        },
        {
          "method": "org.eclipse.core.launcher.Main.run",
          "source": "Main.java:973"
        },
        {
          "method": "org.eclipse.core.launcher.Main.main",
          "source": "Main.java:948"
        }
      ],
      "number": 0,
      "commentIndex": 0,
      "bugId": "134825",
      "date": "2006-04-04T19:37:53+02:00",
      "product": "Dali JPA Tools",
      "component": "Framework",
      "severity": "normal"
    }
  ],
  "groupId": "134825",
  "bugId": "134825",
  "date": "2006-04-04T19:37:53+02:00",
  "product": "Dali JPA Tools",
  "component": "Framework",
  "severity": "normal"
}