{
  "comments": [
    "Using last nightly build N20060410-0010.\n\nAfter having replaced text in Java editor, I got following exception when closing Find/Replace dialog (ie. clicking on \u0027Close\u0027 button):\n!ENTRY org.eclipse.ui 4 4 2006-04-10 18:25:10.140\n!MESSAGE Unhandled event loop exception\n\n!ENTRY org.eclipse.ui 4 0 2006-04-10 18:25:10.140\n!MESSAGE Index: 8, Size: 8\n!STACK 0\njava.lang.IndexOutOfBoundsException: Index: 8, Size: 8\n        at java.util.ArrayList.RangeCheck(ArrayList.java:507)\n        at java.util.ArrayList.remove(ArrayList.java:392)\n        at org.eclipse.ui.texteditor.FindReplaceDialog.writeHistory(FindReplaceDialog.java:1739)\n        at org.eclipse.ui.texteditor.FindReplaceDialog.writeConfiguration(FindReplaceDialog.java:1708)\n        at org.eclipse.ui.texteditor.FindReplaceDialog.storeSettings(FindReplaceDialog.java:1006)\n        at org.eclipse.ui.texteditor.FindReplaceDialog.handleDialogClose(FindReplaceDialog.java:967)\n        at org.eclipse.ui.texteditor.FindReplaceDialog.close(FindReplaceDialog.java:945)\n        at org.eclipse.ui.texteditor.FindReplaceDialog.buttonPressed(FindReplaceDialog.java:742)\n        at org.eclipse.jface.dialogs.Dialog$3.widgetSelected(Dialog.java:652)\n        at org.eclipse.swt.widgets.TypedListener.handleEvent(TypedListener.java:90)\n        at org.eclipse.swt.widgets.EventTable.sendEvent(EventTable.java:66)\n        at org.eclipse.swt.widgets.Widget.sendEvent(Widget.java:925)\n        at org.eclipse.swt.widgets.Display.runDeferredEvents(Display.java:3346)\n        at org.eclipse.swt.widgets.Display.readAndDispatch(Display.java:2966)\n        at org.eclipse.ui.internal.Workbench.runEventLoop(Workbench.java:1914)\n        at org.eclipse.ui.internal.Workbench.runUI(Workbench.java:1878)\n        at org.eclipse.ui.internal.Workbench.createAndRunWorkbench(Workbench.java:419)\n        at org.eclipse.ui.PlatformUI.createAndRunWorkbench(PlatformUI.java:143)\n        at org.eclipse.ui.internal.ide.IDEApplication.run(IDEApplication.java:95)\n        at org.eclipse.core.internal.runtime.PlatformActivator$1.run(PlatformActivator.java:78)\n        at org.eclipse.core.runtime.internal.adaptor.EclipseAppLauncher.runApplication(EclipseAppLauncher.java:92)\n        at org.eclipse.core.runtime.internal.adaptor.EclipseAppLauncher.start(EclipseAppLauncher.java:68)\n        at org.eclipse.core.runtime.adaptor.EclipseStarter.run(EclipseStarter.java:376)\n        at org.eclipse.core.runtime.adaptor.EclipseStarter.run(EclipseStarter.java:169)\n        at sun.reflect.NativeMethodAccessorImpl.invoke0(Native Method)\n        at sun.reflect.NativeMethodAccessorImpl.invoke(NativeMethodAccessorImpl.java:39)\n        at sun.reflect.DelegatingMethodAccessorImpl.invoke(DelegatingMethodAccessorImpl.java:25)\n        at java.lang.reflect.Method.invoke(Method.java:324)\n        at org.eclipse.core.launcher.Main.invokeFramework(Main.java:336)\n        at org.eclipse.core.launcher.Main.basicRun(Main.java:280)\n        at org.eclipse.core.launcher.Main.run(Main.java:977)\n        at org.eclipse.core.launcher.Main.main(Main.java:952)\n\nDialog, stays open and when I click on it again, sometimes it closes, sometimes it stay open raising same exception again. Note that always succeeded to close the dialog, either clicking on \u0027Close\u0027 button several times or using \u0027Esc\u0027 key...\n\nNot sure if the component is correct or I should have opened it against UI...",
    "\n\n*** This bug has been marked as a duplicate of 135817 ***"
  ],
  "commentCreationDates": [
    "2006-04-10T18:44:36+02:00",
    "2006-04-10T18:46:14+02:00"
  ],
  "traces": [
    {
      "exceptionType": "java.lang.IndexOutOfBoundsException",
      "message": "Index: 8, Size: 8",
      "elements": [
        {
          "method": "java.util.ArrayList.RangeCheck",
          "source": "ArrayList.java:507"
        },
        {
          "method": "java.util.ArrayList.remove",
          "source": "ArrayList.java:392"
        },
        {
          "method": "org.eclipse.ui.texteditor.FindReplaceDialog.writeHistory",
          "source": "FindReplaceDialog.java:1739"
        },
        {
          "method": "org.eclipse.ui.texteditor.FindReplaceDialog.writeConfiguration",
          "source": "FindReplaceDialog.java:1708"
        },
        {
          "method": "org.eclipse.ui.texteditor.FindReplaceDialog.storeSettings",
          "source": "FindReplaceDialog.java:1006"
        },
        {
          "method": "org.eclipse.ui.texteditor.FindReplaceDialog.handleDialogClose",
          "source": "FindReplaceDialog.java:967"
        },
        {
          "method": "org.eclipse.ui.texteditor.FindReplaceDialog.close",
          "source": "FindReplaceDialog.java:945"
        },
        {
          "method": "org.eclipse.ui.texteditor.FindReplaceDialog.buttonPressed",
          "source": "FindReplaceDialog.java:742"
        },
        {
          "method": "org.eclipse.jface.dialogs.Dialog$3.widgetSelected",
          "source": "Dialog.java:652"
        },
        {
          "method": "org.eclipse.swt.widgets.TypedListener.handleEvent",
          "source": "TypedListener.java:90"
        },
        {
          "method": "org.eclipse.swt.widgets.EventTable.sendEvent",
          "source": "EventTable.java:66"
        },
        {
          "method": "org.eclipse.swt.widgets.Widget.sendEvent",
          "source": "Widget.java:925"
        },
        {
          "method": "org.eclipse.swt.widgets.Display.runDeferredEvents",
          "source": "Display.java:3346"
        },
        {
          "method": "org.eclipse.swt.widgets.Display.readAndDispatch",
          "source": "Display.java:2966"
        },
        {
          "method": "org.eclipse.ui.internal.Workbench.runEventLoop",
          "source": "Workbench.java:1914"
        },
        {
          "method": "org.eclipse.ui.internal.Workbench.runUI",
          "source": "Workbench.java:1878"
        },
        {
          "method": "org.eclipse.ui.internal.Workbench.createAndRunWorkbench",
          "source": "Workbench.java:419"
        },
        {
          "method": "org.eclipse.ui.PlatformUI.createAndRunWorkbench",
          "source": "PlatformUI.java:143"
        },
        {
          "method": "org.eclipse.ui.internal.ide.IDEApplication.run",
          "source": "IDEApplication.java:95"
        },
        {
          "method": "org.eclipse.core.internal.runtime.PlatformActivator$1.run",
          "source": "PlatformActivator.java:78"
        },
        {
          "method": "org.eclipse.core.runtime.internal.adaptor.EclipseAppLauncher.runApplication",
          "source": "EclipseAppLauncher.java:92"
        },
        {
          "method": "org.eclipse.core.runtime.internal.adaptor.EclipseAppLauncher.start",
          "source": "EclipseAppLauncher.java:68"
        },
        {
          "method": "org.eclipse.core.runtime.adaptor.EclipseStarter.run",
          "source": "EclipseStarter.java:376"
        },
        {
          "method": "org.eclipse.core.runtime.adaptor.EclipseStarter.run",
          "source": "EclipseStarter.java:169"
        },
        {
          "method": "sun.reflect.NativeMethodAccessorImpl.invoke0",
          "source": "Native Method"
        },
        {
          "method": "sun.reflect.NativeMethodAccessorImpl.invoke",
          "source": "NativeMethodAccessorImpl.java:39"
        },
        {
          "method": "sun.reflect.DelegatingMethodAccessorImpl.invoke",
          "source": "DelegatingMethodAccessorImpl.java:25"
        },
        {
          "method": "java.lang.reflect.Method.invoke",
          "source": "Method.java:324"
        },
        {
          "method": "org.eclipse.core.launcher.Main.invokeFramework",
          "source": "Main.java:336"
        },
        {
          "method": "org.eclipse.core.launcher.Main.basicRun",
          "source": "Main.java:280"
        },
        {
          "method": "org.eclipse.core.launcher.Main.run",
          "source": "Main.java:977"
        },
        {
          "method": "org.eclipse.core.launcher.Main.main",
          "source": "Main.java:952"
        }
      ],
      "number": 0,
      "commentIndex": 0,
      "bugId": "135921",
      "duplicateId": "135817",
      "date": "2006-04-10T18:44:36+02:00",
      "product": "Platform",
      "component": "Text",
      "severity": "normal"
    }
  ],
  "groupId": "135817",
  "bugId": "135921",
  "duplicateId": "135817",
  "date": "2006-04-10T18:44:36+02:00",
  "product": "Platform",
  "component": "Text",
  "severity": "normal"
}