{
  "comments": [
    "N20060411\n\nIt looks like there is a runtime claspath problem with the compare plugin. I cannot replace a .java file with local history.\n\n!ENTRY org.eclipse.ui 4 0 2006-04-11 12:52:03.908\n!MESSAGE Failed to execute runnable (java.lang.NoClassDefFoundError: com/ibm/icu/util/Calendar)\n!STACK 0\norg.eclipse.swt.SWTException: Failed to execute runnable (java.lang.NoClassDefFoundError: com/ibm/icu/util/Calendar)\n        at org.eclipse.swt.SWT.error(SWT.java:3374)\n        at org.eclipse.swt.SWT.error(SWT.java:3297)\n        at org.eclipse.swt.widgets.Synchronizer.runAsyncMessages(Synchronizer.java:126)\n        at org.eclipse.swt.widgets.Display.runAsyncMessages(Display.java:3323)\n        at org.eclipse.swt.widgets.Display.readAndDispatch(Display.java:2969)\n        at org.eclipse.jface.window.Window.runEventLoop(Window.java:820)\n        at org.eclipse.jface.window.Window.open(Window.java:796)\n        at org.eclipse.compare.EditionSelectionDialog.selectEdition(EditionSelectionDialog.java:464)\n        at org.eclipse.jdt.internal.ui.compare.JavaReplaceWithEditionActionImpl.run(JavaReplaceWithEditionActionImpl.java:132)\n        at org.eclipse.jdt.internal.ui.compare.JavaHistoryActionImpl.run(JavaHistoryActionImpl.java:352)\n        at org.eclipse.jdt.internal.ui.compare.JavaHistoryAction.run(JavaHistoryAction.java:78)\n        at org.eclipse.ui.internal.PluginAction.runWithEvent(PluginAction.java:254)\n        at org.eclipse.jface.action.ActionContributionItem.handleWidgetSelection(ActionContributionItem.java:539)\n        at org.eclipse.jface.action.ActionContributionItem.access$2(ActionContributionItem.java:488)\n        at org.eclipse.jface.action.ActionContributionItem$5.handleEvent(ActionContributionItem.java:400)\n        at org.eclipse.swt.widgets.EventTable.sendEvent(EventTable.java:66)\n        at org.eclipse.swt.widgets.Widget.sendEvent(Widget.java:925)\n        at org.eclipse.swt.widgets.Display.runDeferredEvents(Display.java:3346)\n        at org.eclipse.swt.widgets.Display.readAndDispatch(Display.java:2966)\n        at org.eclipse.ui.internal.Workbench.runEventLoop(Workbench.java:1914)\n        at org.eclipse.ui.internal.Workbench.runUI(Workbench.java:1878)\n        at org.eclipse.ui.internal.Workbench.createAndRunWorkbench(Workbench.java:419)\n        at org.eclipse.ui.PlatformUI.createAndRunWorkbench(PlatformUI.java:143)\n        at org.eclipse.ui.internal.ide.IDEApplication.run(IDEApplication.java:95)\n        at org.eclipse.core.internal.runtime.PlatformActivator$1.run(PlatformActivator.java:78)\n        at org.eclipse.core.runtime.internal.adaptor.EclipseAppLauncher.runApplication(EclipseAppLauncher.java:92)\n        at org.eclipse.core.runtime.internal.adaptor.EclipseAppLauncher.start(EclipseAppLauncher.java:68)\n        at org.eclipse.core.runtime.adaptor.EclipseStarter.run(EclipseStarter.java:376)\n        at org.eclipse.core.runtime.adaptor.EclipseStarter.run(EclipseStarter.java:169)\n        at sun.reflect.NativeMethodAccessorImpl.invoke0(Native Method)\n        at sun.reflect.NativeMethodAccessorImpl.invoke(NativeMethodAccessorImpl.java:39)\n        at sun.reflect.DelegatingMethodAccessorImpl.invoke(DelegatingMethodAccessorImpl.java:25)\n        at java.lang.reflect.Method.invoke(Method.java:585)\n        at org.eclipse.core.launcher.Main.invokeFramework(Main.java:336)\n        at org.eclipse.core.launcher.Main.basicRun(Main.java:280)\n        at org.eclipse.core.launcher.Main.run(Main.java:977)\n        at org.eclipse.core.launcher.Main.main(Main.java:952)\nCaused by: java.lang.NoClassDefFoundError: com/ibm/icu/util/Calendar\n        at org.eclipse.compare.EditionSelectionDialog.dayNumber(EditionSelectionDialog.java:959)\n        at org.eclipse.compare.EditionSelectionDialog.addEdition(EditionSelectionDialog.java:985)\n        at org.eclipse.compare.EditionSelectionDialog.addMemberEdition(EditionSelectionDialog.java:949)\n        at org.eclipse.compare.EditionSelectionDialog.access$16(EditionSelectionDialog.java:885)\n        at org.eclipse.compare.EditionSelectionDialog$9.run(EditionSelectionDialog.java:856)\n        at org.eclipse.swt.widgets.RunnableLock.run(RunnableLock.java:35)\n        at org.eclipse.swt.widgets.Synchronizer.runAsyncMessages(Synchronizer.java:123)\n        ... 34 more",
    "This is a result of applying the patch for bug #135768.\n\nKarice please advise.",
    "Eek - I am not sure why this is marked as a warning, not an error, but in the manifest of the compare plugin the com.ibm.icu.util package is not imported.  It should be.",
    "To be clear, the warning is in EditionSelectionDialog.  ",
    "Thanks Karice. I\u0027ll release the fix.",
    "fixed \u003e 20060411",
    "verified in 20060426"
  ],
  "commentCreationDates": [
    "2006-04-11T13:04:47+02:00",
    "2006-04-11T14:09:24+02:00",
    "2006-04-11T18:47:05+02:00",
    "2006-04-11T18:49:08+02:00",
    "2006-04-11T18:55:11+02:00",
    "2006-04-11T19:03:36+02:00",
    "2006-04-26T16:20:17+02:00"
  ],
  "traces": [
    {
      "exceptionType": "java.lang.NoClassDefFoundError",
      "message": "com/ibm/icu/util/Calendar)",
      "elements": [
        {
          "method": "org.eclipse.swt.SWT.error",
          "source": "SWT.java:3374"
        },
        {
          "method": "org.eclipse.swt.SWT.error",
          "source": "SWT.java:3297"
        },
        {
          "method": "org.eclipse.swt.widgets.Synchronizer.runAsyncMessages",
          "source": "Synchronizer.java:126"
        },
        {
          "method": "org.eclipse.swt.widgets.Display.runAsyncMessages",
          "source": "Display.java:3323"
        },
        {
          "method": "org.eclipse.swt.widgets.Display.readAndDispatch",
          "source": "Display.java:2969"
        },
        {
          "method": "org.eclipse.jface.window.Window.runEventLoop",
          "source": "Window.java:820"
        },
        {
          "method": "org.eclipse.jface.window.Window.open",
          "source": "Window.java:796"
        },
        {
          "method": "org.eclipse.compare.EditionSelectionDialog.selectEdition",
          "source": "EditionSelectionDialog.java:464"
        },
        {
          "method": "org.eclipse.jdt.internal.ui.compare.JavaReplaceWithEditionActionImpl.run",
          "source": "JavaReplaceWithEditionActionImpl.java:132"
        },
        {
          "method": "org.eclipse.jdt.internal.ui.compare.JavaHistoryActionImpl.run",
          "source": "JavaHistoryActionImpl.java:352"
        },
        {
          "method": "org.eclipse.jdt.internal.ui.compare.JavaHistoryAction.run",
          "source": "JavaHistoryAction.java:78"
        },
        {
          "method": "org.eclipse.ui.internal.PluginAction.runWithEvent",
          "source": "PluginAction.java:254"
        },
        {
          "method": "org.eclipse.jface.action.ActionContributionItem.handleWidgetSelection",
          "source": "ActionContributionItem.java:539"
        },
        {
          "method": "org.eclipse.jface.action.ActionContributionItem.access$2",
          "source": "ActionContributionItem.java:488"
        },
        {
          "method": "org.eclipse.jface.action.ActionContributionItem$5.handleEvent",
          "source": "ActionContributionItem.java:400"
        },
        {
          "method": "org.eclipse.swt.widgets.EventTable.sendEvent",
          "source": "EventTable.java:66"
        },
        {
          "method": "org.eclipse.swt.widgets.Widget.sendEvent",
          "source": "Widget.java:925"
        },
        {
          "method": "org.eclipse.swt.widgets.Display.runDeferredEvents",
          "source": "Display.java:3346"
        },
        {
          "method": "org.eclipse.swt.widgets.Display.readAndDispatch",
          "source": "Display.java:2966"
        },
        {
          "method": "org.eclipse.ui.internal.Workbench.runEventLoop",
          "source": "Workbench.java:1914"
        },
        {
          "method": "org.eclipse.ui.internal.Workbench.runUI",
          "source": "Workbench.java:1878"
        },
        {
          "method": "org.eclipse.ui.internal.Workbench.createAndRunWorkbench",
          "source": "Workbench.java:419"
        },
        {
          "method": "org.eclipse.ui.PlatformUI.createAndRunWorkbench",
          "source": "PlatformUI.java:143"
        },
        {
          "method": "org.eclipse.ui.internal.ide.IDEApplication.run",
          "source": "IDEApplication.java:95"
        },
        {
          "method": "org.eclipse.core.internal.runtime.PlatformActivator$1.run",
          "source": "PlatformActivator.java:78"
        },
        {
          "method": "org.eclipse.core.runtime.internal.adaptor.EclipseAppLauncher.runApplication",
          "source": "EclipseAppLauncher.java:92"
        },
        {
          "method": "org.eclipse.core.runtime.internal.adaptor.EclipseAppLauncher.start",
          "source": "EclipseAppLauncher.java:68"
        },
        {
          "method": "org.eclipse.core.runtime.adaptor.EclipseStarter.run",
          "source": "EclipseStarter.java:376"
        },
        {
          "method": "org.eclipse.core.runtime.adaptor.EclipseStarter.run",
          "source": "EclipseStarter.java:169"
        },
        {
          "method": "sun.reflect.NativeMethodAccessorImpl.invoke0",
          "source": "Native Method"
        },
        {
          "method": "sun.reflect.NativeMethodAccessorImpl.invoke",
          "source": "NativeMethodAccessorImpl.java:39"
        },
        {
          "method": "sun.reflect.DelegatingMethodAccessorImpl.invoke",
          "source": "DelegatingMethodAccessorImpl.java:25"
        },
        {
          "method": "java.lang.reflect.Method.invoke",
          "source": "Method.java:585"
        },
        {
          "method": "org.eclipse.core.launcher.Main.invokeFramework",
          "source": "Main.java:336"
        },
        {
          "method": "org.eclipse.core.launcher.Main.basicRun",
          "source": "Main.java:280"
        },
        {
          "method": "org.eclipse.core.launcher.Main.run",
          "source": "Main.java:977"
        },
        {
          "method": "org.eclipse.core.launcher.Main.main",
          "source": "Main.java:952"
        }
      ],
      "causedBy": {
        "exceptionType": "java.lang.NoClassDefFoundError",
        "message": "com/ibm/icu/util/Calendar",
        "elements": [
          {
            "method": "org.eclipse.compare.EditionSelectionDialog.dayNumber",
            "source": "EditionSelectionDialog.java:959"
          },
          {
            "method": "org.eclipse.compare.EditionSelectionDialog.addEdition",
            "source": "EditionSelectionDialog.java:985"
          },
          {
            "method": "org.eclipse.compare.EditionSelectionDialog.addMemberEdition",
            "source": "EditionSelectionDialog.java:949"
          },
          {
            "method": "org.eclipse.compare.EditionSelectionDialog.access$16",
            "source": "EditionSelectionDialog.java:885"
          },
          {
            "method": "org.eclipse.compare.EditionSelectionDialog$9.run",
            "source": "EditionSelectionDialog.java:856"
          },
          {
            "method": "org.eclipse.swt.widgets.RunnableLock.run",
            "source": "RunnableLock.java:35"
          },
          {
            "method": "org.eclipse.swt.widgets.Synchronizer.runAsyncMessages",
            "source": "Synchronizer.java:123"
          }
        ],
        "number": 0,
        "commentIndex": 0
      },
      "number": 0,
      "commentIndex": 0,
      "bugId": "136087",
      "date": "2006-04-11T13:04:47+02:00",
      "product": "Platform",
      "component": "Compare",
      "severity": "critical"
    }
  ],
  "groupId": "136087",
  "bugId": "136087",
  "date": "2006-04-11T13:04:47+02:00",
  "product": "Platform",
  "component": "Compare",
  "severity": "critical"
}