{
  "comments": [
    "When a Java file is pre-selected and click finish on page 1 of the BUEJB Web service wizard, an exception is thrown.  Pre-selecting an EJB works.\n\nIf an EJB is required, please consider either disabling the finish button or popping up a more meaningful error message.\n\nThe following is the current exception:\n\nWAB0014E Unexpected exception occured.\n  org.eclipse.jdt.internal.core.CompilationUnit incompatible with java.lang.String\n      java.lang.ClassCastException: org.eclipse.jdt.internal.core.CompilationUnit \nincompatible with java.lang.String\n      at org.eclipse.jst.ws.internal.creation.ui.extension.PreServiceDevelopCommand.e\nxecute(PreServiceDevelopCommand.java:100)\n      at org.eclipse.wst.command.internal.env.core.fragment.CommandFragmentEngine.run\nCommand(CommandFragmentEngine.java:387)\n      at org.eclipse.wst.command.internal.env.core.fragment.CommandFragmentEngine.vis\nitTop(CommandFragmentEngine.java:327)\n      at org.eclipse.wst.command.internal.env.core.fragment.CommandFragmentEngine.mov\neForwardToNextStop(CommandFragmentEngine.java:226)\n      at org.eclipse.wst.command.internal.env.ui.widgets.SimpleCommandEngineManager$5\n.run(SimpleCommandEngineManager.java:247)\n      at org.eclipse.jface.operation.ModalContext.runInCurrentThread(ModalContext.jav\na:346)\n      at org.eclipse.jface.operation.ModalContext.run(ModalContext.java:291)\n      at org.eclipse.jface.wizard.WizardDialog.run(WizardDialog.java:830)\n      at org.eclipse.wst.command.internal.env.ui.widgets.SimpleCommandEngineManager.r\nunForwardToNextStop(SimpleCommandEngineManager.java:217)\n      at org.eclipse.wst.command.internal.env.ui.widgets.WizardPageManager.runForward\nToNextStop(WizardPageManager.java:79)\n      at org.eclipse.wst.command.internal.env.ui.widgets.WizardPageManager.performFin\nish(WizardPageManager.java:228)\n      at org.eclipse.wst.command.internal.env.ui.widgets.DynamicWizard.performFinish(\nDynamicWizard.java:335)\n      at org.eclipse.jface.wizard.WizardDialog.finishPressed(WizardDialog.java:676)\n\n      at org.eclipse.jface.wizard.WizardDialog.buttonPressed(WizardDialog.java:349)\n\n      at org.eclipse.jface.dialogs.Dialog$2.widgetSelected(Dialog.java:556)\n      at org.eclipse.swt.widgets.TypedListener.handleEvent(TypedListener.java:90)\n      at org.eclipse.swt.widgets.EventTable.sendEvent(EventTable.java:66)\n      at org.eclipse.swt.widgets.Widget.sendEvent(Widget.java:1021)\n      at org.eclipse.swt.widgets.Display.runDeferredEvents(Display.java:2867)\n      at org.eclipse.swt.widgets.Display.readAndDispatch(Display.java:2572)\n      at org.eclipse.jface.window.Window.runEventLoop(Window.java:809)\n      at org.eclipse.jface.window.Window.open(Window.java:787)\n      at org.eclipse.wst.command.internal.env.ui.widgets.popup.DynamicPopupWizard.run\n(DynamicPopupWizard.java:126)\n      at org.eclipse.ui.internal.PluginAction.runWithEvent(PluginAction.java:246)\n      at org.eclipse.jface.action.ActionContributionItem.handleWidgetSelection(Action\nContributionItem.java:538)\n      at org.eclipse.jface.action.ActionContributionItem.access$2(ActionContributionI\ntem.java:488)\n      at org.eclipse.jface.action.ActionContributionItem$5.handleEvent(ActionContribu\ntionItem.java:400)\n      at org.eclipse.swt.widgets.EventTable.sendEvent(EventTable.java:66)\n      at org.eclipse.swt.widgets.Widget.sendEvent(Widget.java:1021)\n      at org.eclipse.swt.widgets.Display.runDeferredEvents(Display.java:2867)\n      at org.eclipse.swt.widgets.Display.readAndDispatch(Display.java:2572)\n      at org.eclipse.ui.internal.Workbench.runEventLoop(Workbench.java:1699)\n      at org.eclipse.ui.internal.Workbench.runUI(Workbench.java:1663)\n      at org.eclipse.ui.internal.Workbench.createAndRunWorkbench(Workbench.java:367)\n\n\n      at org.eclipse.ui.PlatformUI.createAndRunWorkbench(PlatformUI.java:143)\n      at org.eclipse.ui.internal.ide.IDEApplication.run(IDEApplication.java:103)\n      at org.eclipse.core.internal.runtime.PlatformActivator$1.run(PlatformActivator.\njava:226)\n      at org.eclipse.core.runtime.adaptor.EclipseStarter.run(EclipseStarter.java:376)\n\n      at org.eclipse.core.runtime.adaptor.EclipseStarter.run(EclipseStarter.java:163)\n\n      at sun.reflect.NativeMethodAccessorImpl.invoke0(Native Method)\n      at sun.reflect.NativeMethodAccessorImpl.invoke(NativeMethodAccessorImpl.java:64\n)\n      at sun.reflect.DelegatingMethodAccessorImpl.invoke(DelegatingMethodAccessorImpl\n.java:43)\n      at java.lang.reflect.Method.invoke(Method.java:615)\n      at org.eclipse.core.launcher.Main.invokeFramework(Main.java:334)\n      at org.eclipse.core.launcher.Main.basicRun(Main.java:278)\n      at org.eclipse.core.launcher.Main.run(Main.java:973)\n      at org.eclipse.core.launcher.Main.main(Main.java:948)",
    "This problem is fixed indirectly thru bug 136158 since when the user change the Web service type from bottom-up Java to bottom-up EJB, the service definition field is blanked and Next/Finish is disabled.  The user would have to use the Browse button to browse for an EJB before being able to move on.\n\n*** This bug has been marked as a duplicate of 136158 ***",
    "verified in WTP 1.5 RC4",
    "Closed."
  ],
  "commentCreationDates": [
    "2006-04-13T21:55:58+02:00",
    "2006-04-20T22:00:02+02:00",
    "2006-06-02T22:30:20+02:00",
    "2006-06-13T17:44:49+02:00"
  ],
  "traces": [
    {
      "exceptionType": "java.lang.ClassCastException",
      "message": "org.eclipse.jdt.internal.core.CompilationUnit  incompatible with java.lang.String",
      "elements": [
        {
          "method": "org.eclipse.jst.ws.internal.creation.ui.extension.PreServiceDevelopCommand.execute",
          "source": "PreServiceDevelopCommand.java:100"
        },
        {
          "method": "org.eclipse.wst.command.internal.env.core.fragment.CommandFragmentEngine.runCommand",
          "source": "CommandFragmentEngine.java:387"
        },
        {
          "method": "org.eclipse.wst.command.internal.env.core.fragment.CommandFragmentEngine.visitTop",
          "source": "CommandFragmentEngine.java:327"
        },
        {
          "method": "org.eclipse.wst.command.internal.env.core.fragment.CommandFragmentEngine.moveForwardToNextStop",
          "source": "CommandFragmentEngine.java:226"
        },
        {
          "method": "org.eclipse.wst.command.internal.env.ui.widgets.SimpleCommandEngineManager$5.run",
          "source": "SimpleCommandEngineManager.java:247"
        },
        {
          "method": "org.eclipse.jface.operation.ModalContext.runInCurrentThread",
          "source": "ModalContext.jav a:346"
        },
        {
          "method": "org.eclipse.jface.operation.ModalContext.run",
          "source": "ModalContext.java:291"
        },
        {
          "method": "org.eclipse.jface.wizard.WizardDialog.run",
          "source": "WizardDialog.java:830"
        },
        {
          "method": "org.eclipse.wst.command.internal.env.ui.widgets.SimpleCommandEngineManager.runForwardToNextStop",
          "source": "SimpleCommandEngineManager.java:217"
        },
        {
          "method": "org.eclipse.wst.command.internal.env.ui.widgets.WizardPageManager.runForwardToNextStop",
          "source": "WizardPageManager.java:79"
        },
        {
          "method": "org.eclipse.wst.command.internal.env.ui.widgets.WizardPageManager.performFinish",
          "source": "WizardPageManager.java:228"
        },
        {
          "method": "org.eclipse.wst.command.internal.env.ui.widgets.DynamicWizard.performFinish",
          "source": " DynamicWizard.java:335"
        },
        {
          "method": "org.eclipse.jface.wizard.WizardDialog.finishPressed",
          "source": "WizardDialog.java:676"
        },
        {
          "method": "org.eclipse.jface.wizard.WizardDialog.buttonPressed",
          "source": "WizardDialog.java:349"
        },
        {
          "method": "org.eclipse.jface.dialogs.Dialog$2.widgetSelected",
          "source": "Dialog.java:556"
        },
        {
          "method": "org.eclipse.swt.widgets.TypedListener.handleEvent",
          "source": "TypedListener.java:90"
        },
        {
          "method": "org.eclipse.swt.widgets.EventTable.sendEvent",
          "source": "EventTable.java:66"
        },
        {
          "method": "org.eclipse.swt.widgets.Widget.sendEvent",
          "source": "Widget.java:1021"
        },
        {
          "method": "org.eclipse.swt.widgets.Display.runDeferredEvents",
          "source": "Display.java:2867"
        },
        {
          "method": "org.eclipse.swt.widgets.Display.readAndDispatch",
          "source": "Display.java:2572"
        },
        {
          "method": "org.eclipse.jface.window.Window.runEventLoop",
          "source": "Window.java:809"
        },
        {
          "method": "org.eclipse.jface.window.Window.open",
          "source": "Window.java:787"
        },
        {
          "method": "org.eclipse.wst.command.internal.env.ui.widgets.popup.DynamicPopupWizard.run",
          "source": "DynamicPopupWizard.java:126"
        },
        {
          "method": "org.eclipse.ui.internal.PluginAction.runWithEvent",
          "source": "PluginAction.java:246"
        },
        {
          "method": "org.eclipse.jface.action.ActionContributionItem.handleWidgetSelection",
          "source": "Action ContributionItem.java:538"
        },
        {
          "method": "org.eclipse.jface.action.ActionContributionItem.access$2",
          "source": "ActionContributionI tem.java:488"
        },
        {
          "method": "org.eclipse.jface.action.ActionContributionItem$5.handleEvent",
          "source": "ActionContribu tionItem.java:400"
        },
        {
          "method": "org.eclipse.swt.widgets.EventTable.sendEvent",
          "source": "EventTable.java:66"
        },
        {
          "method": "org.eclipse.swt.widgets.Widget.sendEvent",
          "source": "Widget.java:1021"
        },
        {
          "method": "org.eclipse.swt.widgets.Display.runDeferredEvents",
          "source": "Display.java:2867"
        },
        {
          "method": "org.eclipse.swt.widgets.Display.readAndDispatch",
          "source": "Display.java:2572"
        },
        {
          "method": "org.eclipse.ui.internal.Workbench.runEventLoop",
          "source": "Workbench.java:1699"
        },
        {
          "method": "org.eclipse.ui.internal.Workbench.runUI",
          "source": "Workbench.java:1663"
        },
        {
          "method": "org.eclipse.ui.internal.Workbench.createAndRunWorkbench",
          "source": "Workbench.java:367"
        },
        {
          "method": "org.eclipse.ui.PlatformUI.createAndRunWorkbench",
          "source": "PlatformUI.java:143"
        },
        {
          "method": "org.eclipse.ui.internal.ide.IDEApplication.run",
          "source": "IDEApplication.java:103"
        },
        {
          "method": "org.eclipse.core.internal.runtime.PlatformActivator$1.run",
          "source": "PlatformActivator. java:226"
        },
        {
          "method": "org.eclipse.core.runtime.adaptor.EclipseStarter.run",
          "source": "EclipseStarter.java:376"
        },
        {
          "method": "org.eclipse.core.runtime.adaptor.EclipseStarter.run",
          "source": "EclipseStarter.java:163"
        },
        {
          "method": "sun.reflect.NativeMethodAccessorImpl.invoke0",
          "source": "Native Method"
        },
        {
          "method": "sun.reflect.NativeMethodAccessorImpl.invoke",
          "source": "NativeMethodAccessorImpl.java:64 "
        },
        {
          "method": "sun.reflect.DelegatingMethodAccessorImpl.invoke",
          "source": "DelegatingMethodAccessorImpl .java:43"
        },
        {
          "method": "java.lang.reflect.Method.invoke",
          "source": "Method.java:615"
        },
        {
          "method": "org.eclipse.core.launcher.Main.invokeFramework",
          "source": "Main.java:334"
        },
        {
          "method": "org.eclipse.core.launcher.Main.basicRun",
          "source": "Main.java:278"
        },
        {
          "method": "org.eclipse.core.launcher.Main.run",
          "source": "Main.java:973"
        },
        {
          "method": "org.eclipse.core.launcher.Main.main",
          "source": "Main.java:948"
        }
      ],
      "number": 0,
      "commentIndex": 0,
      "bugId": "136742",
      "duplicateId": "136158",
      "date": "2006-04-13T21:55:58+02:00",
      "product": "Web Tools",
      "component": "jst.ws",
      "severity": "normal"
    }
  ],
  "groupId": "136158",
  "bugId": "136742",
  "duplicateId": "136158",
  "date": "2006-04-13T21:55:58+02:00",
  "product": "Web Tools",
  "component": "jst.ws",
  "severity": "normal"
}