{
  "comments": [
    "Getting:\njava.lang.StringIndexOutOfBoundsException\n\tat java.lang.String.substring(String.java:1015)\n\tat org.eclipse.jdt.internal.core.search.matching.PossibleMatch.getQualifiedName(Unknown Source)\n\tat org.eclipse.jdt.internal.core.search.matching.PossibleMatch.\u003cinit\u003e(Unknown Source)\n\tat org.eclipse.jdt.internal.core.search.matching.MatchLocator.locateMatches(Unknown Source)\n\tat org.eclipse.jdt.internal.core.search.JavaSearchParticipant.locateMatches(Unknown Source)\n\tat org.eclipse.jdt.core.search.SearchEngine.findMatches(Unknown Source)\n\tat org.eclipse.jdt.core.search.SearchEngine.search(Unknown Source)\n\tat org.eclipse.jdt.internal.ui.search.JavaSearchQuery.run(Unknown Source)\n\tat org.eclipse.search2.internal.ui.InternalSearchUI$InternalSearchJob.run(Unknown Source)\n\tat org.eclipse.core.internal.jobs.Worker.run(Unknown Source)\n\nInstructions:\n- Search \u003e Java...          \n- search string \"system\"    \n- search for \"Type\"         \n- Limit to \"All Occurrences\"\n- scope \"Workspace\"         \n\nTestcase available upon request.\n\nThis seems to be fixed in Eclipse 3.1 but didn\u0027t find any reference of it being fixed.",
    "Please provide test case to help me to reproduce.\n",
    "In fact I retrieve the bug fixed in 3.1 stream...\nSet as duplicate as I think it won\u0027t have any new update for 3.0 stream.\n\n*** This bug has been marked as a duplicate of 73784 ***"
  ],
  "commentCreationDates": [
    "2006-04-13T20:26:28+02:00",
    "2006-04-13T20:31:37+02:00",
    "2006-04-14T09:20:36+02:00"
  ],
  "traces": [
    {
      "exceptionType": "java.lang.StringIndexOutOfBoundsException",
      "elements": [
        {
          "method": "java.lang.String.substring",
          "source": "String.java:1015"
        },
        {
          "method": "org.eclipse.jdt.internal.core.search.matching.PossibleMatch.getQualifiedName",
          "source": "Unknown Source"
        },
        {
          "method": "org.eclipse.jdt.internal.core.search.matching.PossibleMatch.\u003cinit\u003e",
          "source": "Unknown Source"
        },
        {
          "method": "org.eclipse.jdt.internal.core.search.matching.MatchLocator.locateMatches",
          "source": "Unknown Source"
        },
        {
          "method": "org.eclipse.jdt.internal.core.search.JavaSearchParticipant.locateMatches",
          "source": "Unknown Source"
        },
        {
          "method": "org.eclipse.jdt.core.search.SearchEngine.findMatches",
          "source": "Unknown Source"
        },
        {
          "method": "org.eclipse.jdt.core.search.SearchEngine.search",
          "source": "Unknown Source"
        },
        {
          "method": "org.eclipse.jdt.internal.ui.search.JavaSearchQuery.run",
          "source": "Unknown Source"
        },
        {
          "method": "org.eclipse.search2.internal.ui.InternalSearchUI$InternalSearchJob.run",
          "source": "Unknown Source"
        },
        {
          "method": "org.eclipse.core.internal.jobs.Worker.run",
          "source": "Unknown Source"
        }
      ],
      "number": 0,
      "commentIndex": 0,
      "bugId": "136710",
      "duplicateId": "73784",
      "date": "2006-04-13T20:26:28+02:00",
      "product": "JDT",
      "component": "Core",
      "severity": "normal"
    }
  ],
  "groupId": "73784",
  "bugId": "136710",
  "duplicateId": "73784",
  "date": "2006-04-13T20:26:28+02:00",
  "product": "JDT",
  "component": "Core",
  "severity": "normal"
}