{
  "comments": [
    "I\u0027m using m6 build:  eclipse.buildId\u003dI20060331-2000\n\nI have the following psuedo code structure\n\nclass foo {\n    private AbstractJob[] jobs;\n   \n    class bar  {\n        protected void foobar(MySuperClass y) {\n          myClass xx \u003d (MyClass) y;\n          y.mem \u003d jobs;\n        }\n    }\n}\n\nI set a breakpoint on line y.mem.  Highlight \"jobs\" and try to inspect it.  I get the following exception:\n\nava.lang.ClassCastException: org.eclipse.jdt.internal.debug.core.model.JDINullValue\nat org.eclipse.jdt.internal.debug.core.model.JDIObjectValue.getEnclosingObject(JDIObjectValue.java:274)\nat org.eclipse.jdt.internal.debug.eval.ast.instructions.PushThis.execute(PushThis.java:41)\nat org.eclipse.jdt.internal.debug.eval.ast.engine.Interpreter.execute(Interpreter.java:50)\nat org.eclipse.jdt.internal.debug.eval.ast.engine.ASTEvaluationEngine$1$EvaluationRunnable.run(ASTEvaluationEngine.java:455)\nat org.eclipse.jdt.internal.debug.core.model.JDIThread.runEvaluation(JDIThread.java:584)\nat org.eclipse.jdt.internal.debug.eval.ast.engine.ASTEvaluationEngine$EvalRunnable.run(ASTEvaluationEngine.java:489)\nat org.eclipse.jdt.internal.debug.core.model.JDIThread$ThreadJob.run(JDIThread.java:2467)\nat org.eclipse.core.internal.jobs.Worker.run(Worker.java:58)",
    "I can\u0027t reproduce this. Is this still a problem on 3.2RC2?",
    "Marking as works for me, unable to reproduce. Please re-open with a test case if problem persists."
  ],
  "commentCreationDates": [
    "2006-04-14T21:56:09+02:00",
    "2006-05-02T23:10:06+02:00",
    "2006-06-13T22:03:34+02:00"
  ],
  "traces": [
    {
      "exceptionType": "ava.lang.ClassCastException",
      "message": "org.eclipse.jdt.internal.debug.core.model.JDINullValue",
      "elements": [
        {
          "method": "org.eclipse.jdt.internal.debug.core.model.JDIObjectValue.getEnclosingObject",
          "source": "JDIObjectValue.java:274"
        },
        {
          "method": "org.eclipse.jdt.internal.debug.eval.ast.instructions.PushThis.execute",
          "source": "PushThis.java:41"
        },
        {
          "method": "org.eclipse.jdt.internal.debug.eval.ast.engine.Interpreter.execute",
          "source": "Interpreter.java:50"
        },
        {
          "method": "org.eclipse.jdt.internal.debug.eval.ast.engine.ASTEvaluationEngine$1$EvaluationRunnable.run",
          "source": "ASTEvaluationEngine.java:455"
        },
        {
          "method": "org.eclipse.jdt.internal.debug.core.model.JDIThread.runEvaluation",
          "source": "JDIThread.java:584"
        },
        {
          "method": "org.eclipse.jdt.internal.debug.eval.ast.engine.ASTEvaluationEngine$EvalRunnable.run",
          "source": "ASTEvaluationEngine.java:489"
        },
        {
          "method": "org.eclipse.jdt.internal.debug.core.model.JDIThread$ThreadJob.run",
          "source": "JDIThread.java:2467"
        },
        {
          "method": "org.eclipse.core.internal.jobs.Worker.run",
          "source": "Worker.java:58"
        }
      ],
      "number": 0,
      "commentIndex": 0,
      "bugId": "136882",
      "date": "2006-04-14T21:56:09+02:00",
      "product": "JDT",
      "component": "Debug",
      "severity": "normal"
    }
  ],
  "groupId": "136882",
  "bugId": "136882",
  "date": "2006-04-14T21:56:09+02:00",
  "product": "JDT",
  "component": "Debug",
  "severity": "normal"
}