{
  "comments": [
    "Using the \"Add Jars...\"  button in the J2EE Dependency property sheet producese this exception:\n\n!ENTRY org.eclipse.ui 4 0 2006-04-14 08:56:21.104\n!MESSAGE Assertion failed; Path for IClasspathEntry must be absolute\n!STACK 0\norg.eclipse.jdt.internal.core.Assert$AssertionFailedException: Assertion failed; Path for IClasspathEntry must be absolute\n        at org.eclipse.jdt.internal.core.Assert.isTrue(Assert.java:89)\n        at org.eclipse.jdt.core.JavaCore.newLibraryEntry(JavaCore.java:3135)\n        at org.eclipse.jdt.core.JavaCore.newLibraryEntry(JavaCore.java:3065)\n        at org.eclipse.jst.j2ee.application.internal.operations.ClasspathElement.newClasspathEntriesForArchive(ClasspathElement.java\n:197)\n        at org.eclipse.jst.j2ee.application.internal.operations.ClasspathElement.newClasspathEntries(ClasspathElement.java:218)\n        at org.eclipse.jst.j2ee.application.internal.operations.ClasspathElement.newClasspathEntries(ClasspathElement.java:240)\n        at org.eclipse.jst.j2ee.application.internal.operations.ClassPathSelection.getClasspathEntries(ClassPathSelection.java:245)\n        at org.eclipse.jst.j2ee.application.internal.operations.ClassPathSelection.getClasspathEntriesForSelected(ClassPathSelection\n.java:271)\n        at org.eclipse.jst.j2ee.internal.common.operations.UpdateJavaBuildPathOperation.\u003cinit\u003e(UpdateJavaBuildPathOperation.java:56)\n\n        at org.eclipse.jst.j2ee.internal.WebLibDependencyPropertiesPage.createBuildPathOperationForExternalJar(WebLibDependencyPrope\nrtiesPage.java:341)\n        at org.eclipse.jst.j2ee.internal.WebLibDependencyPropertiesPage.handleSelectProjectJarButton(WebLibDependencyPropertiesPage.\njava:382)\n        at org.eclipse.jst.j2ee.internal.ClasspathTableManager.handleSelectProjectJarButton(ClasspathTableManager.java:283)\n        at org.eclipse.jst.j2ee.internal.ClasspathTableManager.handleEvent(ClasspathTableManager.java:265)\n        at org.eclipse.swt.widgets.EventTable.sendEvent(EventTable.java:66)\n        at org.eclipse.swt.widgets.Widget.sendEvent(Widget.java:843)\n        at org.eclipse.swt.widgets.Display.runDeferredEvents(Display.java:3125)\n        at org.eclipse.swt.widgets.Display.readAndDispatch(Display.java:2758)\n        at org.eclipse.jface.window.Window.runEventLoop(Window.java:809)\n        at org.eclipse.jface.window.Window.open(Window.java:787)\n        at org.eclipse.ui.dialogs.PropertyDialogAction.run(PropertyDialogAction.java:157)\n        at org.eclipse.jface.action.Action.runWithEvent(Action.java:996)\n        at org.eclipse.jface.action.ActionContributionItem.handleWidgetSelection(ActionContributionItem.java:538)\n        at org.eclipse.jface.action.ActionContributionItem.access$2(ActionContributionItem.java:488)\n        at org.eclipse.jface.action.ActionContributionItem$5.handleEvent(ActionContributionItem.java:400)\n        at org.eclipse.swt.widgets.EventTable.sendEvent(EventTable.java:66)\n        at org.eclipse.swt.widgets.Widget.sendEvent(Widget.java:843)\n        at org.eclipse.swt.widgets.Display.runDeferredEvents(Display.java:3125)\n        at org.eclipse.swt.widgets.Display.readAndDispatch(Display.java:2758)\n        at org.eclipse.ui.internal.Workbench.runEventLoop(Workbench.java:1699)\n        at org.eclipse.ui.internal.Workbench.runUI(Workbench.java:1663)\n        at org.eclipse.ui.internal.Workbench.createAndRunWorkbench(Workbench.java:367)\n        at org.eclipse.ui.PlatformUI.createAndRunWorkbench(PlatformUI.java:143)\n        at org.eclipse.ui.internal.ide.IDEApplication.run(IDEApplication.java:103)\n        at org.eclipse.core.internal.runtime.PlatformActivator$1.run(PlatformActivator.java:226)\n        at org.eclipse.core.runtime.adaptor.EclipseStarter.run(EclipseStarter.java:376)\n        at org.eclipse.core.runtime.adaptor.EclipseStarter.run(EclipseStarter.java:163)\n        at sun.reflect.NativeMethodAccessorImpl.invoke0(Native Method)\n        at sun.reflect.NativeMethodAccessorImpl.invoke(Unknown Source)\n        at sun.reflect.DelegatingMethodAccessorImpl.invoke(Unknown Source)\n        at java.lang.reflect.Method.invoke(Unknown Source)\n        at org.eclipse.core.launcher.Main.invokeFramework(Main.java:334)\n        at org.eclipse.core.launcher.Main.basicRun(Main.java:278)\n        at org.eclipse.core.launcher.Main.run(Main.java:973)\n        at org.eclipse.core.launcher.Main.main(Main.java:948)\nAssertion failed; Path for IClasspathEntry must be absolute",
    "Adding to 102 target",
    "Created an attachment (id\u003d38596)\nPatch for ClassPathElement, making path absolute if needed\n\n",
    "+1 for WTP 1.0.2 RC3.",
    "+1",
    "Dropped to M build.\n\nhttp://download.eclipse.org/webtools/committers/drops/R-1.0.2RC3-200604190807/",
    "Ok"
  ],
  "commentCreationDates": [
    "2006-04-14T15:07:31+02:00",
    "2006-04-14T15:31:13+02:00",
    "2006-04-14T16:48:24+02:00",
    "2006-04-17T17:51:28+02:00",
    "2006-04-17T22:12:38+02:00",
    "2006-04-19T16:42:41+02:00",
    "2006-08-28T21:56:35+02:00"
  ],
  "traces": [
    {
      "exceptionType": "org.eclipse.jdt.internal.core.Assert$AssertionFailedException",
      "message": "Assertion failed; Path for IClasspathEntry must be absolute",
      "elements": [
        {
          "method": "org.eclipse.jdt.internal.core.Assert.isTrue",
          "source": "Assert.java:89"
        },
        {
          "method": "org.eclipse.jdt.core.JavaCore.newLibraryEntry",
          "source": "JavaCore.java:3135"
        },
        {
          "method": "org.eclipse.jdt.core.JavaCore.newLibraryEntry",
          "source": "JavaCore.java:3065"
        },
        {
          "method": "org.eclipse.jst.j2ee.application.internal.operations.ClasspathElement.newClasspathEntriesForArchive",
          "source": "ClasspathElement.java :197"
        },
        {
          "method": "org.eclipse.jst.j2ee.application.internal.operations.ClasspathElement.newClasspathEntries",
          "source": "ClasspathElement.java:218"
        },
        {
          "method": "org.eclipse.jst.j2ee.application.internal.operations.ClasspathElement.newClasspathEntries",
          "source": "ClasspathElement.java:240"
        },
        {
          "method": "org.eclipse.jst.j2ee.application.internal.operations.ClassPathSelection.getClasspathEntries",
          "source": "ClassPathSelection.java:245"
        },
        {
          "method": "org.eclipse.jst.j2ee.application.internal.operations.ClassPathSelection.getClasspathEntriesForSelected",
          "source": "ClassPathSelection .java:271"
        },
        {
          "method": "org.eclipse.jst.j2ee.internal.common.operations.UpdateJavaBuildPathOperation.\u003cinit\u003e",
          "source": "UpdateJavaBuildPathOperation.java:56"
        },
        {
          "method": "org.eclipse.jst.j2ee.internal.WebLibDependencyPropertiesPage.createBuildPathOperationForExternalJar",
          "source": "WebLibDependencyPrope rtiesPage.java:341"
        },
        {
          "method": "org.eclipse.jst.j2ee.internal.WebLibDependencyPropertiesPage.handleSelectProjectJarButton",
          "source": "WebLibDependencyPropertiesPage. java:382"
        },
        {
          "method": "org.eclipse.jst.j2ee.internal.ClasspathTableManager.handleSelectProjectJarButton",
          "source": "ClasspathTableManager.java:283"
        },
        {
          "method": "org.eclipse.jst.j2ee.internal.ClasspathTableManager.handleEvent",
          "source": "ClasspathTableManager.java:265"
        },
        {
          "method": "org.eclipse.swt.widgets.EventTable.sendEvent",
          "source": "EventTable.java:66"
        },
        {
          "method": "org.eclipse.swt.widgets.Widget.sendEvent",
          "source": "Widget.java:843"
        },
        {
          "method": "org.eclipse.swt.widgets.Display.runDeferredEvents",
          "source": "Display.java:3125"
        },
        {
          "method": "org.eclipse.swt.widgets.Display.readAndDispatch",
          "source": "Display.java:2758"
        },
        {
          "method": "org.eclipse.jface.window.Window.runEventLoop",
          "source": "Window.java:809"
        },
        {
          "method": "org.eclipse.jface.window.Window.open",
          "source": "Window.java:787"
        },
        {
          "method": "org.eclipse.ui.dialogs.PropertyDialogAction.run",
          "source": "PropertyDialogAction.java:157"
        },
        {
          "method": "org.eclipse.jface.action.Action.runWithEvent",
          "source": "Action.java:996"
        },
        {
          "method": "org.eclipse.jface.action.ActionContributionItem.handleWidgetSelection",
          "source": "ActionContributionItem.java:538"
        },
        {
          "method": "org.eclipse.jface.action.ActionContributionItem.access$2",
          "source": "ActionContributionItem.java:488"
        },
        {
          "method": "org.eclipse.jface.action.ActionContributionItem$5.handleEvent",
          "source": "ActionContributionItem.java:400"
        },
        {
          "method": "org.eclipse.swt.widgets.EventTable.sendEvent",
          "source": "EventTable.java:66"
        },
        {
          "method": "org.eclipse.swt.widgets.Widget.sendEvent",
          "source": "Widget.java:843"
        },
        {
          "method": "org.eclipse.swt.widgets.Display.runDeferredEvents",
          "source": "Display.java:3125"
        },
        {
          "method": "org.eclipse.swt.widgets.Display.readAndDispatch",
          "source": "Display.java:2758"
        },
        {
          "method": "org.eclipse.ui.internal.Workbench.runEventLoop",
          "source": "Workbench.java:1699"
        },
        {
          "method": "org.eclipse.ui.internal.Workbench.runUI",
          "source": "Workbench.java:1663"
        },
        {
          "method": "org.eclipse.ui.internal.Workbench.createAndRunWorkbench",
          "source": "Workbench.java:367"
        },
        {
          "method": "org.eclipse.ui.PlatformUI.createAndRunWorkbench",
          "source": "PlatformUI.java:143"
        },
        {
          "method": "org.eclipse.ui.internal.ide.IDEApplication.run",
          "source": "IDEApplication.java:103"
        },
        {
          "method": "org.eclipse.core.internal.runtime.PlatformActivator$1.run",
          "source": "PlatformActivator.java:226"
        },
        {
          "method": "org.eclipse.core.runtime.adaptor.EclipseStarter.run",
          "source": "EclipseStarter.java:376"
        },
        {
          "method": "org.eclipse.core.runtime.adaptor.EclipseStarter.run",
          "source": "EclipseStarter.java:163"
        },
        {
          "method": "sun.reflect.NativeMethodAccessorImpl.invoke0",
          "source": "Native Method"
        },
        {
          "method": "sun.reflect.NativeMethodAccessorImpl.invoke",
          "source": "Unknown Source"
        },
        {
          "method": "sun.reflect.DelegatingMethodAccessorImpl.invoke",
          "source": "Unknown Source"
        },
        {
          "method": "java.lang.reflect.Method.invoke",
          "source": "Unknown Source"
        },
        {
          "method": "org.eclipse.core.launcher.Main.invokeFramework",
          "source": "Main.java:334"
        },
        {
          "method": "org.eclipse.core.launcher.Main.basicRun",
          "source": "Main.java:278"
        },
        {
          "method": "org.eclipse.core.launcher.Main.run",
          "source": "Main.java:973"
        },
        {
          "method": "org.eclipse.core.launcher.Main.main",
          "source": "Main.java:948"
        }
      ],
      "number": 0,
      "commentIndex": 0,
      "bugId": "136835",
      "date": "2006-04-14T15:07:31+02:00",
      "product": "Web Tools",
      "component": "jst.j2ee",
      "severity": "major"
    }
  ],
  "groupId": "136835",
  "bugId": "136835",
  "date": "2006-04-14T15:07:31+02:00",
  "product": "Web Tools",
  "component": "jst.j2ee",
  "severity": "major"
}