{
  "comments": [
    "The new version 3.2RC1 doesn\u0027t start correctly. After displaying the splashscreen for a few seconds an errorbox occors with the follwing text:\n\nAn error has occurred. See the log file\n/home/hst/.eclipse/org.eclipse.platform_3.1.0/configuration/1145090807718.log.\nAfter confirming the box the start is aborted.\n\nThe content of the file follows.\n\n!SESSION 2006-04-15 10:46:46.664 -----------------------------------------------\neclipse.buildId\u003dI20060413-1718\njava.version\u003d1.4.2_10\njava.vendor\u003dSun Microsystems Inc.\nBootLoader constants: OS\u003dlinux, ARCH\u003dx86, WS\u003dgtk, NL\u003dde_DE\nCommand-line arguments:  -os linux -ws gtk -arch x86\n\n!ENTRY org.eclipse.update.configurator 2006-04-15 10:46:48.471\n!MESSAGE Could not load from shared install\n!STACK 0\njava.lang.Exception\n        at org.eclipse.update.internal.configurator.ConfigurationParser.processConfig(ConfigurationParser.java:306)\n        at org.eclipse.update.internal.configurator.ConfigurationParser.startElement(ConfigurationParser.java:108)\n        at org.apache.crimson.parser.Parser2.maybeElement(Parser2.java:1672)\n        at org.apache.crimson.parser.Parser2.parseInternal(Parser2.java:667)\n        at org.apache.crimson.parser.Parser2.parse(Parser2.java:337)\n        at org.apache.crimson.parser.XMLReaderImpl.parse(XMLReaderImpl.java:448)\n        at javax.xml.parsers.SAXParser.parse(SAXParser.java:345)\n        at org.eclipse.update.internal.configurator.ConfigurationParser.parse(ConfigurationParser.java:72)\n        at org.eclipse.update.internal.configurator.PlatformConfiguration.loadConfig(PlatformConfiguration.java:1028)\n        at org.eclipse.update.internal.configurator.PlatformConfiguration.initializeCurrent(PlatformConfiguration.java:697)\n        at org.eclipse.update.internal.configurator.PlatformConfiguration.\u003cinit\u003e(PlatformConfiguration.java:92)\n        at org.eclipse.update.internal.configurator.PlatformConfiguration.startup(PlatformConfiguration.java:651)\n        at org.eclipse.update.internal.configurator.ConfigurationActivator.getPlatformConfiguration(ConfigurationActivator.java:331)\n        at org.eclipse.update.internal.configurator.ConfigurationActivator.initialize(ConfigurationActivator.java:111)\n        at org.eclipse.update.internal.configurator.ConfigurationActivator.start(ConfigurationActivator.java:71)\n        at org.eclipse.osgi.framework.internal.core.BundleContextImpl$2.run(BundleContextImpl.java:995)\n        at java.security.AccessController.doPrivileged(Native Method)\n        at org.eclipse.osgi.framework.internal.core.BundleContextImpl.startActivator(BundleContextImpl.java:989)\n        at org.eclipse.osgi.framework.internal.core.BundleContextImpl.start(BundleContextImpl.java:970)\n        at org.eclipse.osgi.framework.internal.core.BundleHost.startWorker(BundleHost.java:317)\n        at org.eclipse.osgi.framework.internal.core.AbstractBundle.resume(AbstractBundle.java:329)\n        at org.eclipse.osgi.framework.internal.core.Framework.resumeBundle(Framework.java:1037)\n        at org.eclipse.osgi.framework.internal.core.StartLevelManager.resumeBundles(StartLevelManager.java:573)\n        at org.eclipse.osgi.framework.internal.core.StartLevelManager.incFWSL(StartLevelManager.java:495)\n        at org.eclipse.osgi.framework.internal.core.StartLevelManager.doSetStartLevel(StartLevelManager.java:275)\n        at org.eclipse.osgi.framework.internal.core.StartLevelManager.dispatchEvent(StartLevelManager.java:455)\n        at org.eclipse.osgi.framework.eventmgr.EventManager.dispatchEvent(EventManager.java:189)\n        at org.eclipse.osgi.framework.eventmgr.EventManager$EventThread.run(EventManager.java:291)\n\n!ENTRY org.eclipse.core.runtime 4 0 2006-04-15 10:46:48.479\n!MESSAGE FrameworkEvent.ERROR\n!STACK 0\norg.osgi.framework.BundleException: The bundle could not be resolved. Reason: Missing Constraint: Require-Bundle: org.eclipse.equinox.registry; bundle-version\u003d\"0.0.0\"\n        at org.eclipse.osgi.framework.internal.core.BundleHost.startWorker(BundleHost.java:294)\n        at org.eclipse.osgi.framework.internal.core.AbstractBundle.resume(AbstractBundle.java:329)\n        at org.eclipse.osgi.framework.internal.core.Framework.resumeBundle(Framework.java:1037)\n        at org.eclipse.osgi.framework.internal.core.StartLevelManager.resumeBundles(StartLevelManager.java:573)\n        at org.eclipse.osgi.framework.internal.core.StartLevelManager.incFWSL(StartLevelManager.java:495)\n        at org.eclipse.osgi.framework.internal.core.StartLevelManager.doSetStartLevel(StartLevelManager.java:275)\n        at org.eclipse.osgi.framework.internal.core.StartLevelManager.dispatchEvent(StartLevelManager.java:455)\n        at org.eclipse.osgi.framework.eventmgr.EventManager.dispatchEvent(EventManager.java:189)\n        at org.eclipse.osgi.framework.eventmgr.EventManager$EventThread.run(EventManager.java:291)\n\n!ENTRY org.eclipse.osgi 4 0 2006-04-15 10:46:48.483\n!MESSAGE Bundle initial@reference:file:plugins/org.eclipse.core.runtime_3.2.0.v20060412-2000.jar/ was not resolved.\n\n!ENTRY org.eclipse.osgi 4 0 2006-04-15 10:46:48.487\n!MESSAGE Application error\n!STACK 1\njava.lang.IllegalStateException: Unable to acquire application service. Ensure that the org.eclipse.core.runtime bundle is resolved and started (see config.ini).\n        at org.eclipse.core.runtime.internal.adaptor.EclipseAppLauncher.start(EclipseAppLauncher.java:65)\n        at org.eclipse.core.runtime.adaptor.EclipseStarter.run(EclipseStarter.java:376)\n        at org.eclipse.core.runtime.adaptor.EclipseStarter.run(EclipseStarter.java:169)\n        at sun.reflect.NativeMethodAccessorImpl.invoke0(Native Method)\n        at sun.reflect.NativeMethodAccessorImpl.invoke(NativeMethodAccessorImpl.java:39)\n        at sun.reflect.DelegatingMethodAccessorImpl.invoke(DelegatingMethodAccessorImpl.java:25)\n        at java.lang.reflect.Method.invoke(Method.java:324)\n        at org.eclipse.core.launcher.Main.invokeFramework(Main.java:336)\n        at org.eclipse.core.launcher.Main.basicRun(Main.java:280)\n        at org.eclipse.core.launcher.Main.run(Main.java:977)\n        at org.eclipse.core.launcher.Main.main(Main.java:952)\n\n!ENTRY org.eclipse.osgi 2 0 2006-04-15 10:46:48.500\n!MESSAGE One or more bundles are not resolved because the following root constraints are not resolved:\n!SUBENTRY 1 org.eclipse.osgi 2 0 2006-04-15 10:46:48.500\n!MESSAGE Bundle initial@reference:file:plugins/org.eclipse.core.runtime_3.2.0.v20060412-2000.jar/ was not resolved.\n!SUBENTRY 2 org.eclipse.core.runtime 2 0 2006-04-15 10:46:48.500\n!MESSAGE Missing required bundle org.eclipse.equinox.preferences_0.0.0.\n!SUBENTRY 2 org.eclipse.core.runtime 2 0 2006-04-15 10:46:48.501\n!MESSAGE Missing required bundle org.eclipse.equinox.registry_0.0.0.\n!SUBENTRY 2 org.eclipse.core.runtime 2 0 2006-04-15 10:46:48.501\n!MESSAGE Missing required bundle org.eclipse.core.contenttype_0.0.0.\n!SUBENTRY 2 org.eclipse.core.runtime 2 0 2006-04-15 10:46:48.501\n!MESSAGE Missing required bundle org.eclipse.core.jobs_0.0.0.\n\n!ENTRY org.eclipse.osgi 2 0 2006-04-15 10:46:48.502\n!MESSAGE The following is a complete list of bundles which are not resolved, see the prior log entry for the root cause if it exists:\n!SUBENTRY 1 org.eclipse.osgi 2 0 2006-04-15 10:46:48.502\n!MESSAGE Bundle initial@reference:file:plugins/org.eclipse.core.runtime_3.2.0.v20060412-2000.jar/ [1447] was not resolved.\n!SUBENTRY 2 org.eclipse.core.runtime 2 0 2006-04-15 10:46:48.502\n!MESSAGE Missing required bundle org.eclipse.equinox.registry_0.0.0.\n!SUBENTRY 2 org.eclipse.core.runtime 2 0 2006-04-15 10:46:48.502\n!MESSAGE Missing required bundle org.eclipse.core.jobs_0.0.0.\n!SUBENTRY 2 org.eclipse.core.runtime 2 0 2006-04-15 10:46:48.502\n!MESSAGE Missing required bundle org.eclipse.equinox.preferences_0.0.0.\n!SUBENTRY 2 org.eclipse.core.runtime 2 0 2006-04-15 10:46:48.502\n!MESSAGE Missing required bundle org.eclipse.core.contenttype_0.0.0.\n!SUBENTRY 2 org.eclipse.core.runtime 2 0 2006-04-15 10:46:48.503\n!MESSAGE Missing optionally required bundle org.eclipse.core.runtime.compatibility.auth_0.0.0.\n\n\nWith kind regards\nHeinz",
    "\n\n*** This bug has been marked as a duplicate of 136903 ***"
  ],
  "commentCreationDates": [
    "2006-04-15T15:58:56+02:00",
    "2006-04-15T16:02:15+02:00"
  ],
  "traces": [
    {
      "exceptionType": "java.lang.Exception",
      "elements": [
        {
          "method": "org.eclipse.update.internal.configurator.ConfigurationParser.processConfig",
          "source": "ConfigurationParser.java:306"
        },
        {
          "method": "org.eclipse.update.internal.configurator.ConfigurationParser.startElement",
          "source": "ConfigurationParser.java:108"
        },
        {
          "method": "org.apache.crimson.parser.Parser2.maybeElement",
          "source": "Parser2.java:1672"
        },
        {
          "method": "org.apache.crimson.parser.Parser2.parseInternal",
          "source": "Parser2.java:667"
        },
        {
          "method": "org.apache.crimson.parser.Parser2.parse",
          "source": "Parser2.java:337"
        },
        {
          "method": "org.apache.crimson.parser.XMLReaderImpl.parse",
          "source": "XMLReaderImpl.java:448"
        },
        {
          "method": "javax.xml.parsers.SAXParser.parse",
          "source": "SAXParser.java:345"
        },
        {
          "method": "org.eclipse.update.internal.configurator.ConfigurationParser.parse",
          "source": "ConfigurationParser.java:72"
        },
        {
          "method": "org.eclipse.update.internal.configurator.PlatformConfiguration.loadConfig",
          "source": "PlatformConfiguration.java:1028"
        },
        {
          "method": "org.eclipse.update.internal.configurator.PlatformConfiguration.initializeCurrent",
          "source": "PlatformConfiguration.java:697"
        },
        {
          "method": "org.eclipse.update.internal.configurator.PlatformConfiguration.\u003cinit\u003e",
          "source": "PlatformConfiguration.java:92"
        },
        {
          "method": "org.eclipse.update.internal.configurator.PlatformConfiguration.startup",
          "source": "PlatformConfiguration.java:651"
        },
        {
          "method": "org.eclipse.update.internal.configurator.ConfigurationActivator.getPlatformConfiguration",
          "source": "ConfigurationActivator.java:331"
        },
        {
          "method": "org.eclipse.update.internal.configurator.ConfigurationActivator.initialize",
          "source": "ConfigurationActivator.java:111"
        },
        {
          "method": "org.eclipse.update.internal.configurator.ConfigurationActivator.start",
          "source": "ConfigurationActivator.java:71"
        },
        {
          "method": "org.eclipse.osgi.framework.internal.core.BundleContextImpl$2.run",
          "source": "BundleContextImpl.java:995"
        },
        {
          "method": "java.security.AccessController.doPrivileged",
          "source": "Native Method"
        },
        {
          "method": "org.eclipse.osgi.framework.internal.core.BundleContextImpl.startActivator",
          "source": "BundleContextImpl.java:989"
        },
        {
          "method": "org.eclipse.osgi.framework.internal.core.BundleContextImpl.start",
          "source": "BundleContextImpl.java:970"
        },
        {
          "method": "org.eclipse.osgi.framework.internal.core.BundleHost.startWorker",
          "source": "BundleHost.java:317"
        },
        {
          "method": "org.eclipse.osgi.framework.internal.core.AbstractBundle.resume",
          "source": "AbstractBundle.java:329"
        },
        {
          "method": "org.eclipse.osgi.framework.internal.core.Framework.resumeBundle",
          "source": "Framework.java:1037"
        },
        {
          "method": "org.eclipse.osgi.framework.internal.core.StartLevelManager.resumeBundles",
          "source": "StartLevelManager.java:573"
        },
        {
          "method": "org.eclipse.osgi.framework.internal.core.StartLevelManager.incFWSL",
          "source": "StartLevelManager.java:495"
        },
        {
          "method": "org.eclipse.osgi.framework.internal.core.StartLevelManager.doSetStartLevel",
          "source": "StartLevelManager.java:275"
        },
        {
          "method": "org.eclipse.osgi.framework.internal.core.StartLevelManager.dispatchEvent",
          "source": "StartLevelManager.java:455"
        },
        {
          "method": "org.eclipse.osgi.framework.eventmgr.EventManager.dispatchEvent",
          "source": "EventManager.java:189"
        },
        {
          "method": "org.eclipse.osgi.framework.eventmgr.EventManager$EventThread.run",
          "source": "EventManager.java:291"
        }
      ],
      "number": 0,
      "commentIndex": 0,
      "bugId": "136908",
      "duplicateId": "136903",
      "date": "2006-04-15T15:58:56+02:00",
      "product": "Platform",
      "component": "Runtime",
      "severity": "blocker"
    },
    {
      "exceptionType": "org.osgi.framework.BundleException",
      "message": "The bundle could not be resolved. Reason: Missing Constraint: Require-Bundle: org.eclipse.equinox.registry; bundle-version\u003d\"0.0.0\"",
      "elements": [
        {
          "method": "org.eclipse.osgi.framework.internal.core.BundleHost.startWorker",
          "source": "BundleHost.java:294"
        },
        {
          "method": "org.eclipse.osgi.framework.internal.core.AbstractBundle.resume",
          "source": "AbstractBundle.java:329"
        },
        {
          "method": "org.eclipse.osgi.framework.internal.core.Framework.resumeBundle",
          "source": "Framework.java:1037"
        },
        {
          "method": "org.eclipse.osgi.framework.internal.core.StartLevelManager.resumeBundles",
          "source": "StartLevelManager.java:573"
        },
        {
          "method": "org.eclipse.osgi.framework.internal.core.StartLevelManager.incFWSL",
          "source": "StartLevelManager.java:495"
        },
        {
          "method": "org.eclipse.osgi.framework.internal.core.StartLevelManager.doSetStartLevel",
          "source": "StartLevelManager.java:275"
        },
        {
          "method": "org.eclipse.osgi.framework.internal.core.StartLevelManager.dispatchEvent",
          "source": "StartLevelManager.java:455"
        },
        {
          "method": "org.eclipse.osgi.framework.eventmgr.EventManager.dispatchEvent",
          "source": "EventManager.java:189"
        },
        {
          "method": "org.eclipse.osgi.framework.eventmgr.EventManager$EventThread.run",
          "source": "EventManager.java:291"
        }
      ],
      "number": 1,
      "commentIndex": 0,
      "bugId": "136908",
      "duplicateId": "136903",
      "date": "2006-04-15T15:58:56+02:00",
      "product": "Platform",
      "component": "Runtime",
      "severity": "blocker"
    }
  ],
  "groupId": "136903",
  "bugId": "136908",
  "duplicateId": "136903",
  "date": "2006-04-15T15:58:56+02:00",
  "product": "Platform",
  "component": "Runtime",
  "severity": "blocker"
}