{
  "comments": [
    "It took me a good hour to figure out why the following fragment of code didn\u0027t work:\n\nfinal IProcess proc \u003d ac.createProcess();\t\t\t\t\nproc.setExecutable(\"java.exe\");\nproc.setParameter(\"-classpath %CLASSPATH%;D:\\\\TPTP4.2\\\\TPTP-4.2.0-200604101029\\\\eclipse\\\\workspaces\\\\runtime-EclipseApplication\\\\JavaProject  HelloWorld\");\n\nIConsole console \u003d proc.getConsole();\nIDataProcessor dp \u003d new ClientDataProcessor();\nconsole.setDataProcessor(dp);\n\t\t\t\t\nproc.launch();\nSystem.out.println(\"Process ID ::\u003d\u003e\u003e\"+ proc.getProcessId());\n\nI was consistently getting the following exception:\n\n\norg.eclipse.tptp.platform.execution.exceptions.NoSuchApplicationException: Error: The process launch command execution failed. There is no such application. The error code and error info - 6003 and \"Unable to Start Process : Directory Not Found\"\n\tat org.eclipse.tptp.platform.execution.client.core.internal.ProcessImpl.launchAC(ProcessImpl.java:696)\n\tat org.eclipse.tptp.platform.execution.client.core.internal.ProcessImpl.launch(ProcessImpl.java:119)\n\tat org.eclipse.tptp.platform.execution.samples.TPTPProcess.main(TPTPProcess.java:76)\n\n\n\nIt turns out that I needed to set the location before doing the launch:\nproc.setLocation(\".\");\n\nWe shouldn\u0027t require clients to set a location before a launch.  It should by default be set to \".\"",
    "Defaults now to \"current working dir\"  -- \".\""
  ],
  "commentCreationDates": [
    "2006-04-18T21:37:01+02:00",
    "2006-04-24T19:07:15+02:00"
  ],
  "traces": [
    {
      "exceptionType": "org.eclipse.tptp.platform.execution.exceptions.NoSuchApplicationException",
      "message": "Error: The process launch command execution failed. There is no such application. The error code and error info - 6003 and \"Unable to Start Process : Directory Not Found\"",
      "elements": [
        {
          "method": "org.eclipse.tptp.platform.execution.client.core.internal.ProcessImpl.launchAC",
          "source": "ProcessImpl.java:696"
        },
        {
          "method": "org.eclipse.tptp.platform.execution.client.core.internal.ProcessImpl.launch",
          "source": "ProcessImpl.java:119"
        },
        {
          "method": "org.eclipse.tptp.platform.execution.samples.TPTPProcess.main",
          "source": "TPTPProcess.java:76"
        }
      ],
      "number": 0,
      "commentIndex": 0,
      "bugId": "137348",
      "date": "2006-04-18T21:37:01+02:00",
      "product": "TPTP Profiling",
      "component": "Platform.Execution",
      "severity": "major"
    }
  ],
  "groupId": "137348",
  "bugId": "137348",
  "date": "2006-04-18T21:37:01+02:00",
  "product": "TPTP Profiling",
  "component": "Platform.Execution",
  "severity": "major"
}