{
  "comments": [
    "When running Eclipse with IBM JDK 5.0SR1 I often get the following exception. When target JVM stops at a breakpoint I see CPU utilization 100% for about a minute then my Eclipse either closes silently or shows \"OutOfMemory\" dialog first and closes after that. I have not seen this problem with SUN JDK 1.5.0_06.\n\n!ENTRY org.eclipse.core.jobs 4 2 2006-04-19 17:00:18.746\n!MESSAGE An internal error occurred during: \"Computing hasChildren\".\n!STACK 0\njava.lang.OutOfMemoryError: Failed to fork OS thread\n\tat java.lang.Thread.startImpl(Native Method)\n\tat java.lang.Thread.start(Thread.java:963)\n\tat org.eclipse.core.internal.jobs.WorkerPool.jobQueued(WorkerPool.java:140)\n\tat org.eclipse.core.internal.jobs.JobManager.schedule(JobManager.java:949)\n\tat org.eclipse.core.internal.jobs.InternalJob.schedule(InternalJob.java:349)\n\tat org.eclipse.core.runtime.jobs.Job.schedule(Job.java:421)\n\tat org.eclipse.debug.internal.ui.viewers.AsynchronousRequestMonitor.done(AsynchronousRequestMonitor.java:127)\n\tat org.eclipse.debug.internal.ui.viewers.provisional.AsynchronousContentAdapter.computeIsContainer(AsynchronousContentAdapter.java:105)\n\tat org.eclipse.debug.internal.ui.viewers.provisional.AsynchronousContentAdapter$2.run(AsynchronousContentAdapter.java:58)\n\tat org.eclipse.core.internal.jobs.Worker.run(Worker.java:58)\n\n\n\nI am running WinXP SP2, Eclipse 3.2 I20060413-1718, I start Eclipse with \"-vmargs -Xmx1024M\"\n\n\njava -version says\n\njava version \"1.5.0\"\nJava(TM) 2 Runtime Environment, Standard Edition (build pwi32dev-20060222a (SR1))\nIBM J9 VM (build 2.3, J2RE 1.5.0 IBM J9 2.3 Windows XP x86-32 j9vmwi3223-20060222a (JIT enabled)\nJ9VM - 20060220_05389_lHdSMR\nJIT  - 20060220_2133_r8\nGC   - 20060214_AA)\nJCL  - 20060222a",
    "Created an attachment (id\u003d39004)\nzipped javacore file\n\nThis looks like some sort of concurrency issue. Attached javacore file which I took while Eclipse was using 100% CPU, shows 1300+ worker threads apparently trying to update VariablesView. I was also able to reproduce the problem with SUN JVM, so it is not specific IBM Java5.",
    "I believe LaunchViewer kept redrawing if suspended thread\u0027s stake frames were not visible.\n\n*** This bug has been marked as a duplicate of 120200 ***"
  ],
  "commentCreationDates": [
    "2006-04-19T23:13:53+02:00",
    "2006-04-20T06:14:05+02:00",
    "2006-04-20T17:22:56+02:00"
  ],
  "traces": [
    {
      "exceptionType": "java.lang.OutOfMemoryError",
      "message": "Failed to fork OS thread",
      "elements": [
        {
          "method": "java.lang.Thread.startImpl",
          "source": "Native Method"
        },
        {
          "method": "java.lang.Thread.start",
          "source": "Thread.java:963"
        },
        {
          "method": "org.eclipse.core.internal.jobs.WorkerPool.jobQueued",
          "source": "WorkerPool.java:140"
        },
        {
          "method": "org.eclipse.core.internal.jobs.JobManager.schedule",
          "source": "JobManager.java:949"
        },
        {
          "method": "org.eclipse.core.internal.jobs.InternalJob.schedule",
          "source": "InternalJob.java:349"
        },
        {
          "method": "org.eclipse.core.runtime.jobs.Job.schedule",
          "source": "Job.java:421"
        },
        {
          "method": "org.eclipse.debug.internal.ui.viewers.AsynchronousRequestMonitor.done",
          "source": "AsynchronousRequestMonitor.java:127"
        },
        {
          "method": "org.eclipse.debug.internal.ui.viewers.provisional.AsynchronousContentAdapter.computeIsContainer",
          "source": "AsynchronousContentAdapter.java:105"
        },
        {
          "method": "org.eclipse.debug.internal.ui.viewers.provisional.AsynchronousContentAdapter$2.run",
          "source": "AsynchronousContentAdapter.java:58"
        },
        {
          "method": "org.eclipse.core.internal.jobs.Worker.run",
          "source": "Worker.java:58"
        }
      ],
      "number": 0,
      "commentIndex": 0,
      "bugId": "137605",
      "duplicateId": "120200",
      "date": "2006-04-19T23:13:53+02:00",
      "product": "JDT",
      "component": "Debug",
      "severity": "normal"
    }
  ],
  "groupId": "120200",
  "bugId": "137605",
  "duplicateId": "120200",
  "date": "2006-04-19T23:13:53+02:00",
  "product": "JDT",
  "component": "Debug",
  "severity": "normal"
}