{
  "comments": [
    "I\u0027m trying to install the geronimo plugin for eclipse trought the \"Don\u0027t see your server listed?\" link. I downloads it fine but when I restart eclipse it doesn\u0027t load it. Below my .log eclipse file.\n\n!SESSION 2006-04-19 20:15:20.412 -----------------------------------------------\neclipse.buildId\u003dM20060118-1600\njava.version\u003d1.5.0_06\njava.vendor\u003dSun Microsystems Inc.\nBootLoader constants: OS\u003dlinux, ARCH\u003dx86, WS\u003dgtk, NL\u003den_US\nCommand-line arguments:  -os linux -ws gtk -arch x86\n\n!ENTRY org.eclipse.update.core 4 0 2006-04-19 20:24:59.821\n!MESSAGE Cannot install featureorg.apache.geronimo.feature 1.0.0 [org.eclipse.update.internal.core.SiteFilePackedPluginContentConsumer]\n!STACK 0\njava.lang.ClassCastException: org.eclipse.update.internal.core.SiteFilePackedPluginContentConsumer\n        at org.eclipse.update.internal.core.SiteFileContentConsumer.abort(SiteFileContentConsumer.java:209)\n        at org.eclipse.update.internal.core.FeatureExecutableContentConsumer.abort(FeatureExecutableContentConsumer.java :152)\n        at org.eclipse.update.core.Feature.install(Feature.java:516)\n        at org.eclipse.update.internal.core.SiteFile.install(SiteFile.java:74)\n        at org.eclipse.update.internal.core.ConfiguredSite.install (ConfiguredSite.java:122)\n        at org.eclipse.update.internal.core.ConfiguredSite.install(ConfiguredSite.java:86)\n        at org.eclipse.update.internal.operations.InstallOperation.execute(InstallOperation.java:72)\n        at org.eclipse.update.internal.operations.BatchInstallOperation.execute(BatchInstallOperation.java:84)\n        at org.eclipse.update.standalone.InstallCommand.run(InstallCommand.java:181)\n        at org.eclipse.wst.server.core.internal.InstallableServer.install (InstallableServer.java:128)\n        at org.eclipse.wst.server.ui.internal.wizard.NewInstallableServerWizard$2.performFinish(NewInstallableServerWizard.java:40)\n        at org.eclipse.wst.server.ui.internal.wizard.TaskWizard.executeTask (TaskWizard.java:256)\n        at org.eclipse.wst.server.ui.internal.wizard.TaskWizard$2.run(TaskWizard.java:213)\n        at org.eclipse.core.internal.resources.Workspace.run(Workspace.java:1721)\n        at org.eclipse.core.internal.resources.Workspace.run (Workspace.java:1741)\n        at org.eclipse.wst.server.ui.internal.wizard.page.WorkspaceRunnableAdapter.run(WorkspaceRunnableAdapter.java:35)\n        at org.eclipse.jface.operation.ModalContext$ModalContextThread.run (ModalContext.java:113)",
    "Fixed for rc2"
  ],
  "commentCreationDates": [
    "2006-04-21T03:15:32+02:00",
    "2006-04-24T22:27:54+02:00"
  ],
  "traces": [
    {
      "exceptionType": "java.lang.ClassCastException",
      "message": "org.eclipse.update.internal.core.SiteFilePackedPluginContentConsumer",
      "elements": [
        {
          "method": "org.eclipse.update.internal.core.SiteFileContentConsumer.abort",
          "source": "SiteFileContentConsumer.java:209"
        },
        {
          "method": "org.eclipse.update.internal.core.FeatureExecutableContentConsumer.abort",
          "source": "FeatureExecutableContentConsumer.java :152"
        },
        {
          "method": "org.eclipse.update.core.Feature.install",
          "source": "Feature.java:516"
        },
        {
          "method": "org.eclipse.update.internal.core.SiteFile.install",
          "source": "SiteFile.java:74"
        },
        {
          "method": "org.eclipse.update.internal.core.ConfiguredSite.install",
          "source": "ConfiguredSite.java:122"
        },
        {
          "method": "org.eclipse.update.internal.core.ConfiguredSite.install",
          "source": "ConfiguredSite.java:86"
        },
        {
          "method": "org.eclipse.update.internal.operations.InstallOperation.execute",
          "source": "InstallOperation.java:72"
        },
        {
          "method": "org.eclipse.update.internal.operations.BatchInstallOperation.execute",
          "source": "BatchInstallOperation.java:84"
        },
        {
          "method": "org.eclipse.update.standalone.InstallCommand.run",
          "source": "InstallCommand.java:181"
        },
        {
          "method": "org.eclipse.wst.server.core.internal.InstallableServer.install",
          "source": "InstallableServer.java:128"
        },
        {
          "method": "org.eclipse.wst.server.ui.internal.wizard.NewInstallableServerWizard$2.performFinish",
          "source": "NewInstallableServerWizard.java:40"
        },
        {
          "method": "org.eclipse.wst.server.ui.internal.wizard.TaskWizard.executeTask",
          "source": "TaskWizard.java:256"
        },
        {
          "method": "org.eclipse.wst.server.ui.internal.wizard.TaskWizard$2.run",
          "source": "TaskWizard.java:213"
        },
        {
          "method": "org.eclipse.core.internal.resources.Workspace.run",
          "source": "Workspace.java:1721"
        },
        {
          "method": "org.eclipse.core.internal.resources.Workspace.run",
          "source": "Workspace.java:1741"
        },
        {
          "method": "org.eclipse.wst.server.ui.internal.wizard.page.WorkspaceRunnableAdapter.run",
          "source": "WorkspaceRunnableAdapter.java:35"
        },
        {
          "method": "org.eclipse.jface.operation.ModalContext$ModalContextThread.run",
          "source": "ModalContext.java:113"
        }
      ],
      "number": 0,
      "commentIndex": 0,
      "bugId": "137870",
      "date": "2006-04-21T03:15:32+02:00",
      "product": "Platform",
      "component": "Update",
      "severity": "normal"
    }
  ],
  "groupId": "137870",
  "bugId": "137870",
  "date": "2006-04-21T03:15:32+02:00",
  "product": "Platform",
  "component": "Update",
  "severity": "normal"
}