{
  "comments": [
    "Using RC1 Callisto, I got this exception trying to apply a quickfix for an \"Avoid using if/else statements for short conditions\".\n\njava.lang.ClassCastException: org.eclipse.jdt.core.dom.MethodInvocation\n        at org.eclipse.tptp.platform.analysis.codereview.java.quickfix.conditional.RuleConditionalTernaryQuickFix.fixCodeReviewResult(RuleConditionalTernaryQuickFix.java:91)\n        at org.eclipse.tptp.platform.analysis.codereview.java.quickfix.JavaCodeReviewQuickFix.doQuickfix(JavaCodeReviewQuickFix.java:145)\n        at org.eclipse.tptp.platform.analysis.codereview.java.quickfix.JavaCodeReviewQuickFix.quickfix(JavaCodeReviewQuickFix.java:228)\n        at org.eclipse.tptp.platform.analysis.core.ui.internal.views.ResultsView$3.run(ResultsView.java:193)\n        at org.eclipse.jface.action.Action.runWithEvent(Action.java:499)\n        at org.eclipse.jface.action.ActionContributionItem.handleWidgetSelection(ActionContributionItem.java:539)\n        at org.eclipse.jface.action.ActionContributionItem.access$2(ActionContributionItem.java:488)\n        at org.eclipse.jface.action.ActionContributionItem$5.handleEvent(ActionContributionItem.java:400)\n        at org.eclipse.swt.widgets.EventTable.sendEvent(EventTable.java:66)\n        at org.eclipse.swt.widgets.Widget.sendEvent(Widget.java:925)\n        at org.eclipse.swt.widgets.Display.runDeferredEvents(Display.java:3346)\n        at org.eclipse.swt.widgets.Display.readAndDispatch(Display.java:2966)\n        at org.eclipse.ui.internal.Workbench.runEventLoop(Workbench.java:1914)\n        at org.eclipse.ui.internal.Workbench.runUI(Workbench.java:1878)\n        at org.eclipse.ui.internal.Workbench.createAndRunWorkbench(Workbench.java:419)\n        at org.eclipse.ui.PlatformUI.createAndRunWorkbench(PlatformUI.java:143)\n        at org.eclipse.ui.internal.ide.IDEApplication.run(IDEApplication.java:95)\n        at org.eclipse.core.internal.runtime.PlatformActivator$1.run(PlatformActivator.java:78)\n        at org.eclipse.core.runtime.internal.adaptor.EclipseAppLauncher.runApplication(EclipseAppLauncher.java:92)\n        at org.eclipse.core.runtime.internal.adaptor.EclipseAppLauncher.start(EclipseAppLauncher.java:68)\n        at org.eclipse.core.runtime.adaptor.EclipseStarter.run(EclipseStarter.java:376)\n        at org.eclipse.core.runtime.adaptor.EclipseStarter.run(EclipseStarter.java:169)\n        at sun.reflect.NativeMethodAccessorImpl.invoke0(Native Method)\n        at sun.reflect.NativeMethodAccessorImpl.invoke(NativeMethodAccessorImpl.java:39)\n        at sun.reflect.DelegatingMethodAccessorImpl.invoke(DelegatingMethodAccessorImpl.java:25)\n        at java.lang.reflect.Method.invoke(Method.java:585)\n        at org.eclipse.core.launcher.Main.invokeFramework(Main.java:336)\n        at org.eclipse.core.launcher.Main.basicRun(Main.java:280)\n        at org.eclipse.core.launcher.Main.run(Main.java:977)\n        at org.eclipse.core.launcher.Main.main(Main.java:952)\n\nSteps to reproduce:\n1) Checkout org.eclipse.jdt.core from CVS\n2) Run the Analysis on this project selecting all rules\n3) Stop it after a while because your .log is swamped with:\n\n!ENTRY org.eclipse.tptp.platform.analysis.core 4 4 2006-04-27 13:50:23.235\n!MESSAGE IWAT0482E Invalid node for rule filter satisfiesReturnType:org.eclipse.jdt.core.dom.MethodDeclaration\n\n4) Go to the Analysis result view and select the first result under:\n\"Avoid using if/else statements for short conditions\".\n5) try quick fix.",
    "A couple of problems fixed relating to this.  First the rule was producing results for thing that were not \"simple\".  The allowed results where one term in the \"if\" was an expression and the other was a method invocation.  This is why the ClassCastException occurred.  There was also some clean-up work done in the quickfix.",
    "closed"
  ],
  "commentCreationDates": [
    "2006-04-27T19:54:20+02:00",
    "2006-04-28T15:30:44+02:00",
    "2006-11-21T14:59:55+01:00"
  ],
  "traces": [
    {
      "exceptionType": "java.lang.ClassCastException",
      "message": "org.eclipse.jdt.core.dom.MethodInvocation",
      "elements": [
        {
          "method": "org.eclipse.tptp.platform.analysis.codereview.java.quickfix.conditional.RuleConditionalTernaryQuickFix.fixCodeReviewResult",
          "source": "RuleConditionalTernaryQuickFix.java:91"
        },
        {
          "method": "org.eclipse.tptp.platform.analysis.codereview.java.quickfix.JavaCodeReviewQuickFix.doQuickfix",
          "source": "JavaCodeReviewQuickFix.java:145"
        },
        {
          "method": "org.eclipse.tptp.platform.analysis.codereview.java.quickfix.JavaCodeReviewQuickFix.quickfix",
          "source": "JavaCodeReviewQuickFix.java:228"
        },
        {
          "method": "org.eclipse.tptp.platform.analysis.core.ui.internal.views.ResultsView$3.run",
          "source": "ResultsView.java:193"
        },
        {
          "method": "org.eclipse.jface.action.Action.runWithEvent",
          "source": "Action.java:499"
        },
        {
          "method": "org.eclipse.jface.action.ActionContributionItem.handleWidgetSelection",
          "source": "ActionContributionItem.java:539"
        },
        {
          "method": "org.eclipse.jface.action.ActionContributionItem.access$2",
          "source": "ActionContributionItem.java:488"
        },
        {
          "method": "org.eclipse.jface.action.ActionContributionItem$5.handleEvent",
          "source": "ActionContributionItem.java:400"
        },
        {
          "method": "org.eclipse.swt.widgets.EventTable.sendEvent",
          "source": "EventTable.java:66"
        },
        {
          "method": "org.eclipse.swt.widgets.Widget.sendEvent",
          "source": "Widget.java:925"
        },
        {
          "method": "org.eclipse.swt.widgets.Display.runDeferredEvents",
          "source": "Display.java:3346"
        },
        {
          "method": "org.eclipse.swt.widgets.Display.readAndDispatch",
          "source": "Display.java:2966"
        },
        {
          "method": "org.eclipse.ui.internal.Workbench.runEventLoop",
          "source": "Workbench.java:1914"
        },
        {
          "method": "org.eclipse.ui.internal.Workbench.runUI",
          "source": "Workbench.java:1878"
        },
        {
          "method": "org.eclipse.ui.internal.Workbench.createAndRunWorkbench",
          "source": "Workbench.java:419"
        },
        {
          "method": "org.eclipse.ui.PlatformUI.createAndRunWorkbench",
          "source": "PlatformUI.java:143"
        },
        {
          "method": "org.eclipse.ui.internal.ide.IDEApplication.run",
          "source": "IDEApplication.java:95"
        },
        {
          "method": "org.eclipse.core.internal.runtime.PlatformActivator$1.run",
          "source": "PlatformActivator.java:78"
        },
        {
          "method": "org.eclipse.core.runtime.internal.adaptor.EclipseAppLauncher.runApplication",
          "source": "EclipseAppLauncher.java:92"
        },
        {
          "method": "org.eclipse.core.runtime.internal.adaptor.EclipseAppLauncher.start",
          "source": "EclipseAppLauncher.java:68"
        },
        {
          "method": "org.eclipse.core.runtime.adaptor.EclipseStarter.run",
          "source": "EclipseStarter.java:376"
        },
        {
          "method": "org.eclipse.core.runtime.adaptor.EclipseStarter.run",
          "source": "EclipseStarter.java:169"
        },
        {
          "method": "sun.reflect.NativeMethodAccessorImpl.invoke0",
          "source": "Native Method"
        },
        {
          "method": "sun.reflect.NativeMethodAccessorImpl.invoke",
          "source": "NativeMethodAccessorImpl.java:39"
        },
        {
          "method": "sun.reflect.DelegatingMethodAccessorImpl.invoke",
          "source": "DelegatingMethodAccessorImpl.java:25"
        },
        {
          "method": "java.lang.reflect.Method.invoke",
          "source": "Method.java:585"
        },
        {
          "method": "org.eclipse.core.launcher.Main.invokeFramework",
          "source": "Main.java:336"
        },
        {
          "method": "org.eclipse.core.launcher.Main.basicRun",
          "source": "Main.java:280"
        },
        {
          "method": "org.eclipse.core.launcher.Main.run",
          "source": "Main.java:977"
        },
        {
          "method": "org.eclipse.core.launcher.Main.main",
          "source": "Main.java:952"
        }
      ],
      "number": 0,
      "commentIndex": 0,
      "bugId": "139023",
      "date": "2006-04-27T19:54:20+02:00",
      "product": "TPTP Static Analysis",
      "component": "Platform.Analysis",
      "severity": "normal"
    }
  ],
  "groupId": "139023",
  "bugId": "139023",
  "date": "2006-04-27T19:54:20+02:00",
  "product": "TPTP Static Analysis",
  "component": "Platform.Analysis",
  "severity": "normal"
}