{
  "comments": [
    "3.2 RC2\n\nI was following the \"Creating a Rich Client Application\" PDE cheat sheet, and at some point (I believe in the 2nd or 3rd task), I got the following error in my log. I did not see any problems in the UI.\n\n!ENTRY org.eclipse.pde.ui 4 0 2006-05-01 17:06:25.706\n!MESSAGE Overlapping text edits\n!STACK 0\norg.eclipse.text.edits.MalformedTreeException: Overlapping text edits\n        at org.eclipse.text.edits.TextEdit$InsertionComparator.compare(TextEdit.java:118)\n        at java.util.Collections.indexedBinarySearch(Collections.java:313)\n        at java.util.Collections.binarySearch(Collections.java:301)\n        at org.eclipse.text.edits.TextEdit.computeInsertionIndex(TextEdit.java:757)\n        at org.eclipse.text.edits.TextEdit.internalAdd(TextEdit.java:742)\n        at org.eclipse.text.edits.TextEdit.addChildren(TextEdit.java:346)\n        at org.eclipse.pde.internal.ui.util.PDEModelUtility.modifyModel(PDEModelUtility.java:200)\n        at org.eclipse.pde.internal.ui.wizards.product.ProductDefinitionOperation.modifyExistingFile(ProductDefinitionOperation.java:217)\n        at org.eclipse.pde.internal.ui.wizards.product.ProductDefinitionOperation.run(ProductDefinitionOperation.java:67)\n        at org.eclipse.pde.internal.ui.wizards.product.SynchronizationOperation.run(SynchronizationOperation.java:58)\n        at org.eclipse.jface.operation.ModalContext.runInCurrentThread(ModalContext.java:369)\n        at org.eclipse.jface.operation.ModalContext.run(ModalContext.java:313)\n        at org.eclipse.jface.dialogs.ProgressMonitorDialog.run(ProgressMonitorDialog.java:479)\n        at org.eclipse.ui.internal.progress.ProgressMonitorJobsDialog.run(ProgressMonitorJobsDialog.java:265)\n        at org.eclipse.ui.internal.progress.ProgressManager.run(ProgressManager.java:1107)\n        at org.eclipse.ui.internal.progress.ProgressManager$5.run(ProgressManager.java:1130)\n        at org.eclipse.swt.custom.BusyIndicator.showWhile(BusyIndicator.java:67)\n        at org.eclipse.ui.internal.progress.ProgressManager.runInUI(ProgressManager.java:1126)\n        at org.eclipse.pde.internal.ui.editor.product.OverviewPage.handleSynchronize(OverviewPage.java:185)\n        at org.eclipse.pde.internal.ui.editor.product.OverviewPage.linkActivated(OverviewPage.java:156)\n        at org.eclipse.ui.forms.widgets.FormText.activateLink(FormText.java:1515)\n        at org.eclipse.ui.forms.widgets.FormText.handleMouseClick(FormText.java:1330)\n        at org.eclipse.ui.forms.widgets.FormText.access$16(FormText.java:1304)\n        at org.eclipse.ui.forms.widgets.FormText$6.mouseUp(FormText.java:436)\n        at org.eclipse.swt.widgets.TypedListener.handleEvent(TypedListener.java:137)\n        at org.eclipse.swt.widgets.EventTable.sendEvent(EventTable.java:66)\n        at org.eclipse.swt.widgets.Widget.sendEvent(Widget.java:1481)\n        at org.eclipse.swt.widgets.Widget.sendEvent(Widget.java:1505)\n        at org.eclipse.swt.widgets.Widget.sendEvent(Widget.java:1490)\n        at org.eclipse.swt.widgets.Widget.notifyListeners(Widget.java:1267)\n        at org.eclipse.swt.widgets.Display.runDeferredEvents(Display.java:3295)\n        at org.eclipse.swt.widgets.Display.readAndDispatch(Display.java:2928)\n        at org.eclipse.ui.internal.Workbench.runEventLoop(Workbench.java:1914)\n        at org.eclipse.ui.internal.Workbench.runUI(Workbench.java:1878)\n        at org.eclipse.ui.internal.Workbench.createAndRunWorkbench(Workbench.java:419)\n        at org.eclipse.ui.PlatformUI.createAndRunWorkbench(PlatformUI.java:143)\n        at org.eclipse.ui.internal.ide.IDEApplication.run(IDEApplication.java:95)\n        at org.eclipse.core.internal.runtime.PlatformActivator$1.run(PlatformActivator.java:78)\n        at org.eclipse.core.runtime.internal.adaptor.EclipseAppLauncher.runApplication(EclipseAppLauncher.java:92)\n        at org.eclipse.core.runtime.internal.adaptor.EclipseAppLauncher.start(EclipseAppLauncher.java:68)\n        at org.eclipse.core.runtime.adaptor.EclipseStarter.run(EclipseStarter.java:400)\n        at org.eclipse.core.runtime.adaptor.EclipseStarter.run(EclipseStarter.java:177)\n        at sun.reflect.NativeMethodAccessorImpl.invoke0(Native Method)\n        at sun.reflect.NativeMethodAccessorImpl.invoke(NativeMethodAccessorImpl.java:39)\n        at sun.reflect.DelegatingMethodAccessorImpl.invoke(DelegatingMethodAccessorImpl.java:25)\n        at java.lang.reflect.Method.invoke(Method.java:324)\n        at org.eclipse.core.launcher.Main.invokeFramework(Main.java:336)\n        at org.eclipse.core.launcher.Main.basicRun(Main.java:280)\n        at org.eclipse.core.launcher.Main.run(Main.java:977)\n        at org.eclipse.core.launcher.Main.main(Main.java:952)",
    "The error seems to happen when I click on \"Launch the Product\" or \"Synchronize\" in the Testing section of the product file editor.",
    "this one is a must-fix for RC3",
    "Created an attachment (id\u003d40102)\nsimple and safe patch to address this issue\n\n",
    "Good patch.  Risk is virtually non-existent, very high value.\n\n+1 for RC3.\n\nDejan, we need one more approval.",
    "+1",
    "Patch applied"
  ],
  "commentCreationDates": [
    "2006-05-01T23:20:36+02:00",
    "2006-05-01T23:23:58+02:00",
    "2006-05-02T21:20:24+02:00",
    "2006-05-02T21:39:27+02:00",
    "2006-05-02T21:42:02+02:00",
    "2006-05-02T21:58:39+02:00",
    "2006-05-02T23:20:51+02:00"
  ],
  "traces": [
    {
      "exceptionType": "org.eclipse.text.edits.MalformedTreeException",
      "message": "Overlapping text edits",
      "elements": [
        {
          "method": "org.eclipse.text.edits.TextEdit$InsertionComparator.compare",
          "source": "TextEdit.java:118"
        },
        {
          "method": "java.util.Collections.indexedBinarySearch",
          "source": "Collections.java:313"
        },
        {
          "method": "java.util.Collections.binarySearch",
          "source": "Collections.java:301"
        },
        {
          "method": "org.eclipse.text.edits.TextEdit.computeInsertionIndex",
          "source": "TextEdit.java:757"
        },
        {
          "method": "org.eclipse.text.edits.TextEdit.internalAdd",
          "source": "TextEdit.java:742"
        },
        {
          "method": "org.eclipse.text.edits.TextEdit.addChildren",
          "source": "TextEdit.java:346"
        },
        {
          "method": "org.eclipse.pde.internal.ui.util.PDEModelUtility.modifyModel",
          "source": "PDEModelUtility.java:200"
        },
        {
          "method": "org.eclipse.pde.internal.ui.wizards.product.ProductDefinitionOperation.modifyExistingFile",
          "source": "ProductDefinitionOperation.java:217"
        },
        {
          "method": "org.eclipse.pde.internal.ui.wizards.product.ProductDefinitionOperation.run",
          "source": "ProductDefinitionOperation.java:67"
        },
        {
          "method": "org.eclipse.pde.internal.ui.wizards.product.SynchronizationOperation.run",
          "source": "SynchronizationOperation.java:58"
        },
        {
          "method": "org.eclipse.jface.operation.ModalContext.runInCurrentThread",
          "source": "ModalContext.java:369"
        },
        {
          "method": "org.eclipse.jface.operation.ModalContext.run",
          "source": "ModalContext.java:313"
        },
        {
          "method": "org.eclipse.jface.dialogs.ProgressMonitorDialog.run",
          "source": "ProgressMonitorDialog.java:479"
        },
        {
          "method": "org.eclipse.ui.internal.progress.ProgressMonitorJobsDialog.run",
          "source": "ProgressMonitorJobsDialog.java:265"
        },
        {
          "method": "org.eclipse.ui.internal.progress.ProgressManager.run",
          "source": "ProgressManager.java:1107"
        },
        {
          "method": "org.eclipse.ui.internal.progress.ProgressManager$5.run",
          "source": "ProgressManager.java:1130"
        },
        {
          "method": "org.eclipse.swt.custom.BusyIndicator.showWhile",
          "source": "BusyIndicator.java:67"
        },
        {
          "method": "org.eclipse.ui.internal.progress.ProgressManager.runInUI",
          "source": "ProgressManager.java:1126"
        },
        {
          "method": "org.eclipse.pde.internal.ui.editor.product.OverviewPage.handleSynchronize",
          "source": "OverviewPage.java:185"
        },
        {
          "method": "org.eclipse.pde.internal.ui.editor.product.OverviewPage.linkActivated",
          "source": "OverviewPage.java:156"
        },
        {
          "method": "org.eclipse.ui.forms.widgets.FormText.activateLink",
          "source": "FormText.java:1515"
        },
        {
          "method": "org.eclipse.ui.forms.widgets.FormText.handleMouseClick",
          "source": "FormText.java:1330"
        },
        {
          "method": "org.eclipse.ui.forms.widgets.FormText.access$16",
          "source": "FormText.java:1304"
        },
        {
          "method": "org.eclipse.ui.forms.widgets.FormText$6.mouseUp",
          "source": "FormText.java:436"
        },
        {
          "method": "org.eclipse.swt.widgets.TypedListener.handleEvent",
          "source": "TypedListener.java:137"
        },
        {
          "method": "org.eclipse.swt.widgets.EventTable.sendEvent",
          "source": "EventTable.java:66"
        },
        {
          "method": "org.eclipse.swt.widgets.Widget.sendEvent",
          "source": "Widget.java:1481"
        },
        {
          "method": "org.eclipse.swt.widgets.Widget.sendEvent",
          "source": "Widget.java:1505"
        },
        {
          "method": "org.eclipse.swt.widgets.Widget.sendEvent",
          "source": "Widget.java:1490"
        },
        {
          "method": "org.eclipse.swt.widgets.Widget.notifyListeners",
          "source": "Widget.java:1267"
        },
        {
          "method": "org.eclipse.swt.widgets.Display.runDeferredEvents",
          "source": "Display.java:3295"
        },
        {
          "method": "org.eclipse.swt.widgets.Display.readAndDispatch",
          "source": "Display.java:2928"
        },
        {
          "method": "org.eclipse.ui.internal.Workbench.runEventLoop",
          "source": "Workbench.java:1914"
        },
        {
          "method": "org.eclipse.ui.internal.Workbench.runUI",
          "source": "Workbench.java:1878"
        },
        {
          "method": "org.eclipse.ui.internal.Workbench.createAndRunWorkbench",
          "source": "Workbench.java:419"
        },
        {
          "method": "org.eclipse.ui.PlatformUI.createAndRunWorkbench",
          "source": "PlatformUI.java:143"
        },
        {
          "method": "org.eclipse.ui.internal.ide.IDEApplication.run",
          "source": "IDEApplication.java:95"
        },
        {
          "method": "org.eclipse.core.internal.runtime.PlatformActivator$1.run",
          "source": "PlatformActivator.java:78"
        },
        {
          "method": "org.eclipse.core.runtime.internal.adaptor.EclipseAppLauncher.runApplication",
          "source": "EclipseAppLauncher.java:92"
        },
        {
          "method": "org.eclipse.core.runtime.internal.adaptor.EclipseAppLauncher.start",
          "source": "EclipseAppLauncher.java:68"
        },
        {
          "method": "org.eclipse.core.runtime.adaptor.EclipseStarter.run",
          "source": "EclipseStarter.java:400"
        },
        {
          "method": "org.eclipse.core.runtime.adaptor.EclipseStarter.run",
          "source": "EclipseStarter.java:177"
        },
        {
          "method": "sun.reflect.NativeMethodAccessorImpl.invoke0",
          "source": "Native Method"
        },
        {
          "method": "sun.reflect.NativeMethodAccessorImpl.invoke",
          "source": "NativeMethodAccessorImpl.java:39"
        },
        {
          "method": "sun.reflect.DelegatingMethodAccessorImpl.invoke",
          "source": "DelegatingMethodAccessorImpl.java:25"
        },
        {
          "method": "java.lang.reflect.Method.invoke",
          "source": "Method.java:324"
        },
        {
          "method": "org.eclipse.core.launcher.Main.invokeFramework",
          "source": "Main.java:336"
        },
        {
          "method": "org.eclipse.core.launcher.Main.basicRun",
          "source": "Main.java:280"
        },
        {
          "method": "org.eclipse.core.launcher.Main.run",
          "source": "Main.java:977"
        },
        {
          "method": "org.eclipse.core.launcher.Main.main",
          "source": "Main.java:952"
        }
      ],
      "number": 0,
      "commentIndex": 0,
      "bugId": "139613",
      "date": "2006-05-01T23:20:36+02:00",
      "product": "PDE",
      "component": "UI",
      "severity": "normal"
    }
  ],
  "groupId": "139613",
  "bugId": "139613",
  "date": "2006-05-01T23:20:36+02:00",
  "product": "PDE",
  "component": "UI",
  "severity": "normal"
}