{
  "comments": [
    "Refuses to run on intel based OSX with the following output in the log:\n(note how it assumes the arch is ppc, this isn\u0027t stored in the Info.plist)\n\n!SESSION 2006-05-03 10:57:33.902 -----------------------------------------------\neclipse.buildId\u003dM20060118-1600\njava.version\u003d1.5.0_06\njava.vendor\u003dApple Computer, Inc.\nBootLoader constants: OS\u003dmacosx, ARCH\u003dppc, WS\u003dcarbon, NL\u003den_US\nFramework arguments:  -keyring /Users/anomaly/.eclipse_keyring -showlocation\nCommand-line arguments:  -os macosx -ws carbon -arch ppc -keyring /Users/anomaly/.eclipse_keyring -consoleLog -showlocation\n\n!ENTRY org.eclipse.osgi 2006-05-03 10:57:35.371\n!MESSAGE Application error\n!STACK 1\njava.lang.UnsatisfiedLinkError: /Users/anomaly/src/eclipse/configuration/org.eclipse.osgi/bundles/63/1/.cp/libswt-pi-carbon-3139.jnilib: \n        at java.lang.ClassLoader$NativeLibrary.load(Native Method)\n        at java.lang.ClassLoader.loadLibrary0(ClassLoader.java:1751)\n        at java.lang.ClassLoader.loadLibrary(ClassLoader.java:1660)\n        at java.lang.Runtime.loadLibrary0(Runtime.java:822)\n        at java.lang.System.loadLibrary(System.java:992)\n        at org.eclipse.swt.internal.Library.loadLibrary(Library.java:123)\n        at org.eclipse.swt.internal.carbon.OS.\u003cclinit\u003e(OS.java:20)\n        at org.eclipse.swt.widgets.Display.createDisplay(Display.java:856)\n        at org.eclipse.swt.widgets.Display.create(Display.java:836)\n        at org.eclipse.swt.graphics.Device.\u003cinit\u003e(Device.java:118)\n        at org.eclipse.swt.widgets.Display.\u003cinit\u003e(Display.java:676)\n        at org.eclipse.swt.widgets.Display.\u003cinit\u003e(Display.java:667)\n        at org.eclipse.ui.internal.Workbench.createDisplay(Workbench.java:394)\n        at org.eclipse.ui.PlatformUI.createDisplay(PlatformUI.java:155)\n        at org.eclipse.ui.internal.ide.IDEApplication.createDisplay(IDEApplication.java:128)\n        at org.eclipse.ui.internal.ide.IDEApplication.run(IDEApplication.java:79)\n        at org.eclipse.core.internal.runtime.PlatformActivator$1.run(PlatformActivator.java:226)\n        at org.eclipse.core.runtime.adaptor.EclipseStarter.run(EclipseStarter.java:376)\n        at org.eclipse.core.runtime.adaptor.EclipseStarter.run(EclipseStarter.java:163)\n        at sun.reflect.NativeMethodAccessorImpl.invoke0(Native Method)\n        at sun.reflect.NativeMethodAccessorImpl.invoke(NativeMethodAccessorImpl.java:39)\n        at sun.reflect.DelegatingMethodAccessorImpl.invoke(DelegatingMethodAccessorImpl.java:25)\n        at java.lang.reflect.Method.invoke(Method.java:585)\n        at org.eclipse.core.launcher.Main.invokeFramework(Main.java:334)\n        at org.eclipse.core.launcher.Main.basicRun(Main.java:278)\n        at org.eclipse.core.launcher.Main.run(Main.java:973)\n        at org.eclipse.core.launcher.Main.main(Main.java:948)",
    "\n\n*** This bug has been marked as a duplicate of 131384 ***"
  ],
  "commentCreationDates": [
    "2006-05-02T17:45:20+02:00",
    "2006-05-02T19:58:38+02:00"
  ],
  "traces": [
    {
      "exceptionType": "java.lang.UnsatisfiedLinkError",
      "message": "/Users/anomaly/src/eclipse/configuration/org.eclipse.osgi/bundles/63/1/.cp/libswt-pi-carbon-3139.jnilib:",
      "elements": [
        {
          "method": "java.lang.ClassLoader$NativeLibrary.load",
          "source": "Native Method"
        },
        {
          "method": "java.lang.ClassLoader.loadLibrary0",
          "source": "ClassLoader.java:1751"
        },
        {
          "method": "java.lang.ClassLoader.loadLibrary",
          "source": "ClassLoader.java:1660"
        },
        {
          "method": "java.lang.Runtime.loadLibrary0",
          "source": "Runtime.java:822"
        },
        {
          "method": "java.lang.System.loadLibrary",
          "source": "System.java:992"
        },
        {
          "method": "org.eclipse.swt.internal.Library.loadLibrary",
          "source": "Library.java:123"
        },
        {
          "method": "org.eclipse.swt.internal.carbon.OS.\u003cclinit\u003e",
          "source": "OS.java:20"
        },
        {
          "method": "org.eclipse.swt.widgets.Display.createDisplay",
          "source": "Display.java:856"
        },
        {
          "method": "org.eclipse.swt.widgets.Display.create",
          "source": "Display.java:836"
        },
        {
          "method": "org.eclipse.swt.graphics.Device.\u003cinit\u003e",
          "source": "Device.java:118"
        },
        {
          "method": "org.eclipse.swt.widgets.Display.\u003cinit\u003e",
          "source": "Display.java:676"
        },
        {
          "method": "org.eclipse.swt.widgets.Display.\u003cinit\u003e",
          "source": "Display.java:667"
        },
        {
          "method": "org.eclipse.ui.internal.Workbench.createDisplay",
          "source": "Workbench.java:394"
        },
        {
          "method": "org.eclipse.ui.PlatformUI.createDisplay",
          "source": "PlatformUI.java:155"
        },
        {
          "method": "org.eclipse.ui.internal.ide.IDEApplication.createDisplay",
          "source": "IDEApplication.java:128"
        },
        {
          "method": "org.eclipse.ui.internal.ide.IDEApplication.run",
          "source": "IDEApplication.java:79"
        },
        {
          "method": "org.eclipse.core.internal.runtime.PlatformActivator$1.run",
          "source": "PlatformActivator.java:226"
        },
        {
          "method": "org.eclipse.core.runtime.adaptor.EclipseStarter.run",
          "source": "EclipseStarter.java:376"
        },
        {
          "method": "org.eclipse.core.runtime.adaptor.EclipseStarter.run",
          "source": "EclipseStarter.java:163"
        },
        {
          "method": "sun.reflect.NativeMethodAccessorImpl.invoke0",
          "source": "Native Method"
        },
        {
          "method": "sun.reflect.NativeMethodAccessorImpl.invoke",
          "source": "NativeMethodAccessorImpl.java:39"
        },
        {
          "method": "sun.reflect.DelegatingMethodAccessorImpl.invoke",
          "source": "DelegatingMethodAccessorImpl.java:25"
        },
        {
          "method": "java.lang.reflect.Method.invoke",
          "source": "Method.java:585"
        },
        {
          "method": "org.eclipse.core.launcher.Main.invokeFramework",
          "source": "Main.java:334"
        },
        {
          "method": "org.eclipse.core.launcher.Main.basicRun",
          "source": "Main.java:278"
        },
        {
          "method": "org.eclipse.core.launcher.Main.run",
          "source": "Main.java:973"
        },
        {
          "method": "org.eclipse.core.launcher.Main.main",
          "source": "Main.java:948"
        }
      ],
      "number": 0,
      "commentIndex": 0,
      "bugId": "139726",
      "duplicateId": "131384",
      "date": "2006-05-02T17:45:20+02:00",
      "product": "Platform",
      "component": "Runtime",
      "severity": "major"
    }
  ],
  "groupId": "131384",
  "bugId": "139726",
  "duplicateId": "131384",
  "date": "2006-05-02T17:45:20+02:00",
  "product": "Platform",
  "component": "Runtime",
  "severity": "major"
}