{
  "comments": [
    "hen parsing a document in a project with space (such as \"project with space\"), I\u0027m getting the \"Could not resolve URL\" error:\n\nError messages were issued.\n  Error: Project: project%20with%20space does not exist.  Could not resolve URL: platform:/resource/project%20with%20space/WebContent/WEB-INF/wsdl/Echo.wsdl.\n      java.io.IOException: Project: project%20with%20space does not exist.  Could not resolve URL: platform:/resource/project%20with%20space/WebContent/WEB-INF/wsdl/Echo.wsdl.\n      at org.eclipse.core.internal.resources.PlatformURLResourceConnection.resolve(Unknown Source)\n      at org.eclipse.core.internal.boot.PlatformURLHandler.openConnection(Unknown Source)\n      at org.eclipse.osgi.framework.internal.protocol.URLStreamHandlerProxy.openConnection(URLStreamHandlerProxy.java:113)\n      at java.net.URL.openConnection(URL.java:924)\n      at org.apache.xerces.impl.XMLEntityManager.setupCurrentEntity(Unknown Source)\n      at org.apache.xerces.impl.XMLVersionDetector.determineDocVersion(Unknown Source)\n      at org.apache.xerces.parsers.XML11Configuration.parse(Unknown Source)\n      at org.apache.xerces.parsers.XML11Configuration.parse(Unknown Source)\n      at org.apache.xerces.parsers.XMLParser.parse(Unknown Source)\n      at org.apache.xerces.parsers.DOMParser.parse(Unknown Source)\n      at org.apache.xerces.jaxp.DocumentBuilderImpl.parse(Unknown Source)",
    "Duplicate of bug 123261.  Closing.\n\n*** This bug has been marked as a duplicate of 123261 ***",
    "Closing."
  ],
  "commentCreationDates": [
    "2006-05-02T19:22:20+02:00",
    "2006-05-02T20:19:26+02:00",
    "2006-06-15T16:41:22+02:00"
  ],
  "traces": [
    {
      "exceptionType": "java.io.IOException",
      "message": "Project: project%20with%20space does not exist.  Could not resolve URL: platform:/resource/project%20with%20space/WebContent/WEB-INF/wsdl/Echo.wsdl.",
      "elements": [
        {
          "method": "org.eclipse.core.internal.resources.PlatformURLResourceConnection.resolve",
          "source": "Unknown Source"
        },
        {
          "method": "org.eclipse.core.internal.boot.PlatformURLHandler.openConnection",
          "source": "Unknown Source"
        },
        {
          "method": "org.eclipse.osgi.framework.internal.protocol.URLStreamHandlerProxy.openConnection",
          "source": "URLStreamHandlerProxy.java:113"
        },
        {
          "method": "java.net.URL.openConnection",
          "source": "URL.java:924"
        },
        {
          "method": "org.apache.xerces.impl.XMLEntityManager.setupCurrentEntity",
          "source": "Unknown Source"
        },
        {
          "method": "org.apache.xerces.impl.XMLVersionDetector.determineDocVersion",
          "source": "Unknown Source"
        },
        {
          "method": "org.apache.xerces.parsers.XML11Configuration.parse",
          "source": "Unknown Source"
        },
        {
          "method": "org.apache.xerces.parsers.XML11Configuration.parse",
          "source": "Unknown Source"
        },
        {
          "method": "org.apache.xerces.parsers.XMLParser.parse",
          "source": "Unknown Source"
        },
        {
          "method": "org.apache.xerces.parsers.DOMParser.parse",
          "source": "Unknown Source"
        },
        {
          "method": "org.apache.xerces.jaxp.DocumentBuilderImpl.parse",
          "source": "Unknown Source"
        }
      ],
      "number": 0,
      "commentIndex": 0,
      "bugId": "139761",
      "duplicateId": "123261",
      "date": "2006-05-02T19:22:20+02:00",
      "product": "Platform",
      "component": "Resources",
      "severity": "major"
    }
  ],
  "groupId": "123261",
  "bugId": "139761",
  "duplicateId": "123261",
  "date": "2006-05-02T19:22:20+02:00",
  "product": "Platform",
  "component": "Resources",
  "severity": "major"
}