{
  "comments": [
    "I am adding a series of objects (6) to the tree using Display.syncExec and 3 of the objects are consistently not displayed in the TreeViewer, recieving the exception pasted below.  The TreeViewer has a customized ViewerSorter [org.eclipse.jface.viewers.ViewerSorter] set.  When the sorter is removed from the viewer, or replaced with an un-customized viewer, the exception no longer occurs.  An example of the customized viewer is pasted below as well:\n\n------\n\n!ENTRY org.eclipse.ui 4 0 2006-05-02 16:05:36.352\n!MESSAGE Failed to execute runnable (java.lang.IllegalArgumentException: Index out of bounds)\n!STACK 0\norg.eclipse.swt.SWTException: Failed to execute runnable (java.lang.IllegalArgumentException: Index out of bounds)\n\tat org.eclipse.swt.SWT.error(SWT.java:3374)\n\tat org.eclipse.swt.SWT.error(SWT.java:3297)\n\tat org.eclipse.swt.widgets.Synchronizer.runAsyncMessages(Synchronizer.java:126)\n\tat org.eclipse.swt.widgets.Display.runAsyncMessages(Display.java:3323)\n\tat org.eclipse.swt.widgets.Display.readAndDispatch(Display.java:2969)\n\tat org.eclipse.ui.internal.Workbench.runEventLoop(Workbench.java:1914)\n\tat org.eclipse.ui.internal.Workbench.runUI(Workbench.java:1878)\n\tat org.eclipse.ui.internal.Workbench.createAndRunWorkbench(Workbench.java:419)\n\tat org.eclipse.ui.PlatformUI.createAndRunWorkbench(PlatformUI.java:143)\n\tat org.eclipse.ui.internal.ide.IDEApplication.run(IDEApplication.java:95)\n\tat org.eclipse.core.internal.runtime.PlatformActivator$1.run(PlatformActivator.java:78)\n\tat org.eclipse.core.runtime.internal.adaptor.EclipseAppLauncher.runApplication(EclipseAppLauncher.java:92)\n\tat org.eclipse.core.runtime.internal.adaptor.EclipseAppLauncher.start(EclipseAppLauncher.java:68)\n\tat org.eclipse.core.runtime.adaptor.EclipseStarter.run(EclipseStarter.java:376)\n\tat org.eclipse.core.runtime.adaptor.EclipseStarter.run(EclipseStarter.java:169)\n\tat sun.reflect.NativeMethodAccessorImpl.invoke0(Native Method)\n\tat sun.reflect.NativeMethodAccessorImpl.invoke(NativeMethodAccessorImpl.java:64)\n\tat sun.reflect.DelegatingMethodAccessorImpl.invoke(DelegatingMethodAccessorImpl.java:43)\n\tat java.lang.reflect.Method.invoke(Method.java:615)\n\tat org.eclipse.core.launcher.Main.invokeFramework(Main.java:336)\n\tat org.eclipse.core.launcher.Main.basicRun(Main.java:280)\n\tat org.eclipse.core.launcher.Main.run(Main.java:977)\n\tat org.eclipse.core.launcher.Main.main(Main.java:952)\nCaused by: java.lang.IllegalArgumentException: Index out of bounds\n\tat org.eclipse.swt.SWT.error(SWT.java:3358)\n\tat org.eclipse.swt.SWT.error(SWT.java:3297)\n\tat org.eclipse.swt.SWT.error(SWT.java:3268)\n\tat org.eclipse.swt.widgets.TreeItem.findPrevious(TreeItem.java:222)\n\tat org.eclipse.swt.widgets.TreeItem.\u003cinit\u003e(TreeItem.java:189)\n\tat org.eclipse.jface.viewers.TreeViewer.newItem(TreeViewer.java:579)\n\tat org.eclipse.jface.viewers.AbstractTreeViewer.createTreeItem(AbstractTreeViewer.java:737)\n\tat org.eclipse.jface.viewers.AbstractTreeViewer.createAddedElements(AbstractTreeViewer.java:348)\n\tat org.eclipse.jface.viewers.AbstractTreeViewer.internalAdd(AbstractTreeViewer.java:251)\n\tat org.eclipse.jface.viewers.TreeViewer.internalAdd(TreeViewer.java:887)\n\tat org.eclipse.jface.viewers.AbstractTreeViewer.add(AbstractTreeViewer.java:130)\n\tat org.eclipse.jface.viewers.AbstractTreeViewer.add(AbstractTreeViewer.java:587)\n\tat com.ibm.carma.ui.widget.BasicCARMATreeContentProvider$1.run(BasicCARMATreeContentProvider.java:84)\n\tat org.eclipse.swt.widgets.RunnableLock.run(RunnableLock.java:35)\n\tat org.eclipse.swt.widgets.Synchronizer.runAsyncMessages(Synchronizer.java:123)\n\t... 20 more\n\n----------\n\nTreeViewer.setSorter(new ViewerSorter(){\n            public int category(Object element) {\n                if (element instanceof StatusDisplay) {\n                    return 0;\n                } else if (element instanceof ObjectType1) {\n                    return 1;\n                } else if (element instanceof ObjectType2) {\n                    return 2;\n                } else if (element instanceof ObjectType3) {\n                    return 3;\n                } else\n                    return 10;\n            }\n        });",
    "What is the build id (in the About dialog) you are using?",
    "Using build:\n\nVersion: 3.2.0\nBuild id: I20060419-1640",
    "David, could you please check the next I-build or RC3 if this was actually a duplicate? Thanks.\n\nIf the issue is not resolved, please reopen.\n\n*** This bug has been marked as a duplicate of 138319 ***"
  ],
  "commentCreationDates": [
    "2006-05-02T22:34:48+02:00",
    "2006-05-03T22:59:38+02:00",
    "2006-05-04T15:29:20+02:00",
    "2006-05-05T17:51:19+02:00"
  ],
  "traces": [
    {
      "exceptionType": "java.lang.IllegalArgumentException",
      "message": "Index out of bounds)",
      "elements": [
        {
          "method": "org.eclipse.swt.SWT.error",
          "source": "SWT.java:3374"
        },
        {
          "method": "org.eclipse.swt.SWT.error",
          "source": "SWT.java:3297"
        },
        {
          "method": "org.eclipse.swt.widgets.Synchronizer.runAsyncMessages",
          "source": "Synchronizer.java:126"
        },
        {
          "method": "org.eclipse.swt.widgets.Display.runAsyncMessages",
          "source": "Display.java:3323"
        },
        {
          "method": "org.eclipse.swt.widgets.Display.readAndDispatch",
          "source": "Display.java:2969"
        },
        {
          "method": "org.eclipse.ui.internal.Workbench.runEventLoop",
          "source": "Workbench.java:1914"
        },
        {
          "method": "org.eclipse.ui.internal.Workbench.runUI",
          "source": "Workbench.java:1878"
        },
        {
          "method": "org.eclipse.ui.internal.Workbench.createAndRunWorkbench",
          "source": "Workbench.java:419"
        },
        {
          "method": "org.eclipse.ui.PlatformUI.createAndRunWorkbench",
          "source": "PlatformUI.java:143"
        },
        {
          "method": "org.eclipse.ui.internal.ide.IDEApplication.run",
          "source": "IDEApplication.java:95"
        },
        {
          "method": "org.eclipse.core.internal.runtime.PlatformActivator$1.run",
          "source": "PlatformActivator.java:78"
        },
        {
          "method": "org.eclipse.core.runtime.internal.adaptor.EclipseAppLauncher.runApplication",
          "source": "EclipseAppLauncher.java:92"
        },
        {
          "method": "org.eclipse.core.runtime.internal.adaptor.EclipseAppLauncher.start",
          "source": "EclipseAppLauncher.java:68"
        },
        {
          "method": "org.eclipse.core.runtime.adaptor.EclipseStarter.run",
          "source": "EclipseStarter.java:376"
        },
        {
          "method": "org.eclipse.core.runtime.adaptor.EclipseStarter.run",
          "source": "EclipseStarter.java:169"
        },
        {
          "method": "sun.reflect.NativeMethodAccessorImpl.invoke0",
          "source": "Native Method"
        },
        {
          "method": "sun.reflect.NativeMethodAccessorImpl.invoke",
          "source": "NativeMethodAccessorImpl.java:64"
        },
        {
          "method": "sun.reflect.DelegatingMethodAccessorImpl.invoke",
          "source": "DelegatingMethodAccessorImpl.java:43"
        },
        {
          "method": "java.lang.reflect.Method.invoke",
          "source": "Method.java:615"
        },
        {
          "method": "org.eclipse.core.launcher.Main.invokeFramework",
          "source": "Main.java:336"
        },
        {
          "method": "org.eclipse.core.launcher.Main.basicRun",
          "source": "Main.java:280"
        },
        {
          "method": "org.eclipse.core.launcher.Main.run",
          "source": "Main.java:977"
        },
        {
          "method": "org.eclipse.core.launcher.Main.main",
          "source": "Main.java:952"
        }
      ],
      "causedBy": {
        "exceptionType": "java.lang.IllegalArgumentException",
        "message": "Index out of bounds",
        "elements": [
          {
            "method": "org.eclipse.swt.SWT.error",
            "source": "SWT.java:3358"
          },
          {
            "method": "org.eclipse.swt.SWT.error",
            "source": "SWT.java:3297"
          },
          {
            "method": "org.eclipse.swt.SWT.error",
            "source": "SWT.java:3268"
          },
          {
            "method": "org.eclipse.swt.widgets.TreeItem.findPrevious",
            "source": "TreeItem.java:222"
          },
          {
            "method": "org.eclipse.swt.widgets.TreeItem.\u003cinit\u003e",
            "source": "TreeItem.java:189"
          },
          {
            "method": "org.eclipse.jface.viewers.TreeViewer.newItem",
            "source": "TreeViewer.java:579"
          },
          {
            "method": "org.eclipse.jface.viewers.AbstractTreeViewer.createTreeItem",
            "source": "AbstractTreeViewer.java:737"
          },
          {
            "method": "org.eclipse.jface.viewers.AbstractTreeViewer.createAddedElements",
            "source": "AbstractTreeViewer.java:348"
          },
          {
            "method": "org.eclipse.jface.viewers.AbstractTreeViewer.internalAdd",
            "source": "AbstractTreeViewer.java:251"
          },
          {
            "method": "org.eclipse.jface.viewers.TreeViewer.internalAdd",
            "source": "TreeViewer.java:887"
          },
          {
            "method": "org.eclipse.jface.viewers.AbstractTreeViewer.add",
            "source": "AbstractTreeViewer.java:130"
          },
          {
            "method": "org.eclipse.jface.viewers.AbstractTreeViewer.add",
            "source": "AbstractTreeViewer.java:587"
          },
          {
            "method": "com.ibm.carma.ui.widget.BasicCARMATreeContentProvider$1.run",
            "source": "BasicCARMATreeContentProvider.java:84"
          },
          {
            "method": "org.eclipse.swt.widgets.RunnableLock.run",
            "source": "RunnableLock.java:35"
          },
          {
            "method": "org.eclipse.swt.widgets.Synchronizer.runAsyncMessages",
            "source": "Synchronizer.java:123"
          }
        ],
        "number": 0,
        "commentIndex": 0
      },
      "number": 0,
      "commentIndex": 0,
      "bugId": "139826",
      "duplicateId": "138319",
      "date": "2006-05-02T22:34:48+02:00",
      "product": "Platform",
      "component": "UI",
      "severity": "critical"
    }
  ],
  "groupId": "138319",
  "bugId": "139826",
  "duplicateId": "138319",
  "date": "2006-05-02T22:34:48+02:00",
  "product": "Platform",
  "component": "UI",
  "severity": "critical"
}