{
  "comments": [
    "While testing update, I saw the following exception printed to stdout. It looks like it\u0027s just a problem with the test update site I\u0027m using. However, it output the stack trace to the log file, not stdout. Most people, I would assume, don\u0027t launch eclipse from the command line, so they would never see this, and there is no record of it in the log.\n\norg.eclipse.core.runtime.CoreException: Unable to retrieve remote reference \"htt\np://download.eclipse.org/testUpdates/digest.zip\". [Server returned HTTP response\n code: \"404 Not Found\" for URL: http://download.eclipse.org/testUpdates/digest.z\nip.]\n        at org.eclipse.update.core.Utilities.newCoreException(Utilities.java:223\n)\n        at org.eclipse.update.core.Utilities.newCoreException(Utilities.java:240\n)\n        at org.eclipse.update.core.FeatureContentProvider.asLocalReference(Featu\nreContentProvider.java:241)\n        at org.eclipse.update.internal.core.DigestContentProvider.asLocalReferen\nce(DigestContentProvider.java:24)\n        at org.eclipse.update.internal.core.Digest.parseDigest(Digest.java:29)\n        at org.eclipse.update.core.model.DefaultSiteParser.getLightFeatures(Defa\nultSiteParser.java:919)\n        at org.eclipse.update.core.model.DefaultSiteParser.endElement(DefaultSit\neParser.java:273)\n        at org.apache.xerces.parsers.AbstractSAXParser.endElement(Unknown Source\n)\n        at org.apache.xerces.impl.XMLNSDocumentScannerImpl.scanEndElement(Unknow\nn Source)\n        at org.apache.xerces.impl.XMLDocumentFragmentScannerImpl$FragmentContent\nDispatcher.dispatch(Unknown Source)\n        at org.apache.xerces.impl.XMLDocumentFragmentScannerImpl.scanDocument(Un\nknown Source)\n        at org.apache.xerces.parsers.XML11Configuration.parse(Unknown Source)\n        at org.apache.xerces.parsers.XML11Configuration.parse(Unknown Source)\n        at org.apache.xerces.parsers.XMLParser.parse(Unknown Source)\n        at org.apache.xerces.parsers.AbstractSAXParser.parse(Unknown Source)\n        at javax.xml.parsers.SAXParser.parse(Unknown Source)\n        at org.eclipse.update.core.model.DefaultSiteParser.parse(DefaultSitePars\ner.java:156)\n        at org.eclipse.update.core.model.SiteModelFactory.parseSite(SiteModelFac\ntory.java:78)\n        at org.eclipse.update.internal.core.SiteURLFactory.createSite(SiteURLFac\ntory.java:80)\n        at org.eclipse.update.internal.core.InternalSiteManager.createSite(Inter\nnalSiteManager.java:332)\n        at org.ec1lipse.update.internal.core.InternalSiteManager.createSite(Inter\nnalSiteManager.java:324)\n        at org.eclipse.update.internal.core.InternalSiteManager.createSite(Inter\nnalSiteManager.java:289)\n        at org.eclipse.update.internal.core.InternalSiteManager.attemptCreateSit\ne(InternalSiteManager.java:220)\n        at org.eclipse.update.internal.core.InternalSiteManager.getSite(Internal\nSiteManager.java:161)\n        at org.eclipse.update.core.SiteManager.getSite(SiteManager.java:78)\n        at org.eclipse.update.search.UpdateSearchRequest.searchOneSite(UpdateSea\nrchRequest.java:443)\n        at org.eclipse.update.search.UpdateSearchRequest.performSearch(UpdateSea\nrchRequest.java:292)\n        at org.eclipse.update.ui.UpdateJob.runUpdates(UpdateJob.java:204)\n        at org.eclipse.update.ui.UpdateJob.run(UpdateJob.java:167)\n        at org.eclipse.core.internal.jobs.Worker.run(Worker.java:58)\norg.eclipse.core.runtime.CoreException[0]: java.io.IOException: Server returned\nHTTP response code: \"404 Not Found\" for URL: http://download.eclipse.org/testUpd\nates/digest.zip.\n        at org.eclipse.update.internal.core.UpdateManagerUtils.checkConnectionRe\nsult(UpdateManagerUtils.java:558)\n        at org.eclipse.update.core.ContentReference.getInputStream(ContentRefere\nnce.java:152)\n        at org.eclipse.update.core.FeatureContentProvider.asLocalReference(Featu\nreContentProvider.java:238)\n        at org.eclipse.update.internal.core.DigestContentProvider.asLocalReferen\nce(DigestContentProvider.java:24)\n        at org.eclipse.update.internal.core.Digest.parseDigest(Digest.java:29)\n        at org.eclipse.update.core.model.DefaultSiteParser.getLightFeatures(Defa\nultSiteParser.java:919)\n        at org.eclipse.update.core.model.DefaultSiteParser.endElement(DefaultSit\neParser.java:273)\n        at org.apache.xerces.parsers.AbstractSAXParser.endElement(Unknown Source\n)\n        at org.apache.xerces.impl.XMLNSDocumentScannerImpl.scanEndElement(Unknow\nn Source)\n        at org.apache.xerces.impl.XMLDocumentFragmentScannerImpl$FragmentContent\nDispatcher.dispatch(Unknown Source)\n        at org.apache.xerces.impl.XMLDocumentFragmentScannerImpl.scanDocument(Un\nknown Source)\n        at org.apache.xerces.parsers.XML11Configuration.parse(Unknown Source)\n        at org.apache.xerces.parsers.XML11Configuration.parse(Unknown Source)\n        at org.apache.xerces.parsers.XMLParser.parse(Unknown Source)\n        at org.apache.xerces.parsers.AbstractSAXParser.parse(Unknown Source)\n        at javax.xml.parsers.SAXParser.parse(Unknown Source)\n        at org.eclipse.update.core.model.DefaultSiteParser.parse(DefaultSitePars\ner.java:156)\n        at org.eclipse.update.core.model.SiteModelFactory.parseSite(SiteModelFac                                                              tory.java:78)\n        at org.eclipse.update.internal.core.SiteURLFactory.createSite(SiteURLFac                                                              tory.java:80)\n        at org.eclipse.update.internal.core.InternalSiteManager.createSite(Inter                                                              nalSiteManager.java:332)\n        at org.eclipse.update.internal.core.InternalSiteManager.createSite(Inter                                                              nalSiteManager.java:324)\n        at org.eclipse.update.internal.core.InternalSiteManager.createSite(Inter                                                              nalSiteManager.java:289)\n        at org.eclipse.update.internal.core.InternalSiteManager.attemptCreateSit                                                              e(InternalSiteManager.java:220)\n        at org.eclipse.update.internal.core.InternalSiteManager.getSite(Internal                                                              SiteManager.java:161)\n        at org.eclipse.update.core.SiteManager.getSite(SiteManager.java:78)\n        at org.eclipse.update.search.UpdateSearchRequest.searchOneSite(UpdateSea                                                              rchRequest.java:443)\n        at org.eclipse.update.search.UpdateSearchRequest.performSearch(UpdateSea                                                              rchRequest.java:292)\n        at org.eclipse.update.ui.UpdateJob.runUpdates(UpdateJob.java:204)\n        at org.eclipse.update.ui.UpdateJob.run(UpdateJob.java:167)\n        at org.eclipse.core.internal.jobs.Worker.run(Worker.java:58)",
    "\"However, it output the stack trace to the log file, not stdout.\"\n\nshould be:\n\n\"However, it should output the stack trace to the log file, not stdout.\""
  ],
  "commentCreationDates": [
    "2006-05-02T21:41:18+02:00",
    "2006-05-02T21:43:37+02:00"
  ],
  "traces": [
    {
      "exceptionType": "org.eclipse.core.runtime.CoreException",
      "message": "Unable to retrieve remote reference \"htt p://download.eclipse.org/testUpdates/digest.zip\". [Server returned HTTP response  code: \"404 Not Found\" for URL: http://download.eclipse.org/testUpdates/digest.z ip.]",
      "elements": [
        {
          "method": "org.eclipse.update.core.Utilities.newCoreException",
          "source": "Utilities.java:223 "
        },
        {
          "method": "org.eclipse.update.core.Utilities.newCoreException",
          "source": "Utilities.java:240 "
        },
        {
          "method": "org.eclipse.update.core.FeatureContentProvider.asLocalReference",
          "source": "Featu reContentProvider.java:241"
        },
        {
          "method": "org.eclipse.update.internal.core.DigestContentProvider.asLocalReference",
          "source": "DigestContentProvider.java:24"
        },
        {
          "method": "org.eclipse.update.internal.core.Digest.parseDigest",
          "source": "Digest.java:29"
        },
        {
          "method": "org.eclipse.update.core.model.DefaultSiteParser.getLightFeatures",
          "source": "Defa ultSiteParser.java:919"
        },
        {
          "method": "org.eclipse.update.core.model.DefaultSiteParser.endElement",
          "source": "DefaultSit eParser.java:273"
        },
        {
          "method": "org.apache.xerces.parsers.AbstractSAXParser.endElement",
          "source": "Unknown Source "
        },
        {
          "method": "org.apache.xerces.impl.XMLNSDocumentScannerImpl.scanEndElement",
          "source": "Unknow n Source"
        },
        {
          "method": "org.apache.xerces.impl.XMLDocumentFragmentScannerImpl$FragmentContentDispatcher.dispatch",
          "source": "Unknown Source"
        },
        {
          "method": "org.apache.xerces.impl.XMLDocumentFragmentScannerImpl.scanDocument",
          "source": "Un known Source"
        },
        {
          "method": "org.apache.xerces.parsers.XML11Configuration.parse",
          "source": "Unknown Source"
        },
        {
          "method": "org.apache.xerces.parsers.XML11Configuration.parse",
          "source": "Unknown Source"
        },
        {
          "method": "org.apache.xerces.parsers.XMLParser.parse",
          "source": "Unknown Source"
        },
        {
          "method": "org.apache.xerces.parsers.AbstractSAXParser.parse",
          "source": "Unknown Source"
        },
        {
          "method": "javax.xml.parsers.SAXParser.parse",
          "source": "Unknown Source"
        },
        {
          "method": "org.eclipse.update.core.model.DefaultSiteParser.parse",
          "source": "DefaultSitePars er.java:156"
        },
        {
          "method": "org.eclipse.update.core.model.SiteModelFactory.parseSite",
          "source": "SiteModelFac tory.java:78"
        },
        {
          "method": "org.eclipse.update.internal.core.SiteURLFactory.createSite",
          "source": "SiteURLFac tory.java:80"
        },
        {
          "method": "org.eclipse.update.internal.core.InternalSiteManager.createSite",
          "source": "Inter nalSiteManager.java:332"
        },
        {
          "method": "org.ec1lipse.update.internal.core.InternalSiteManager.createSite",
          "source": "Inter nalSiteManager.java:324"
        },
        {
          "method": "org.eclipse.update.internal.core.InternalSiteManager.createSite",
          "source": "Inter nalSiteManager.java:289"
        },
        {
          "method": "org.eclipse.update.internal.core.InternalSiteManager.attemptCreateSite",
          "source": "InternalSiteManager.java:220"
        },
        {
          "method": "org.eclipse.update.internal.core.InternalSiteManager.getSite",
          "source": "Internal SiteManager.java:161"
        },
        {
          "method": "org.eclipse.update.core.SiteManager.getSite",
          "source": "SiteManager.java:78"
        },
        {
          "method": "org.eclipse.update.search.UpdateSearchRequest.searchOneSite",
          "source": "UpdateSea rchRequest.java:443"
        },
        {
          "method": "org.eclipse.update.search.UpdateSearchRequest.performSearch",
          "source": "UpdateSea rchRequest.java:292"
        },
        {
          "method": "org.eclipse.update.ui.UpdateJob.runUpdates",
          "source": "UpdateJob.java:204"
        },
        {
          "method": "org.eclipse.update.ui.UpdateJob.run",
          "source": "UpdateJob.java:167"
        },
        {
          "method": "org.eclipse.core.internal.jobs.Worker.run",
          "source": "Worker.java:58"
        }
      ],
      "number": 0,
      "commentIndex": 0,
      "bugId": "139813",
      "date": "2006-05-02T21:41:18+02:00",
      "product": "Platform",
      "component": "Update",
      "severity": "normal"
    },
    {
      "exceptionType": "java.io.IOException",
      "message": "Server returned HTTP response code: \"404 Not Found\" for URL: http://download.eclipse.org/testUpd ates/digest.zip.",
      "elements": [
        {
          "method": "org.eclipse.update.internal.core.UpdateManagerUtils.checkConnectionResult",
          "source": "UpdateManagerUtils.java:558"
        },
        {
          "method": "org.eclipse.update.core.ContentReference.getInputStream",
          "source": "ContentRefere nce.java:152"
        },
        {
          "method": "org.eclipse.update.core.FeatureContentProvider.asLocalReference",
          "source": "Featu reContentProvider.java:238"
        },
        {
          "method": "org.eclipse.update.internal.core.DigestContentProvider.asLocalReference",
          "source": "DigestContentProvider.java:24"
        },
        {
          "method": "org.eclipse.update.internal.core.Digest.parseDigest",
          "source": "Digest.java:29"
        },
        {
          "method": "org.eclipse.update.core.model.DefaultSiteParser.getLightFeatures",
          "source": "Defa ultSiteParser.java:919"
        },
        {
          "method": "org.eclipse.update.core.model.DefaultSiteParser.endElement",
          "source": "DefaultSit eParser.java:273"
        },
        {
          "method": "org.apache.xerces.parsers.AbstractSAXParser.endElement",
          "source": "Unknown Source "
        },
        {
          "method": "org.apache.xerces.impl.XMLNSDocumentScannerImpl.scanEndElement",
          "source": "Unknow n Source"
        },
        {
          "method": "org.apache.xerces.impl.XMLDocumentFragmentScannerImpl$FragmentContentDispatcher.dispatch",
          "source": "Unknown Source"
        },
        {
          "method": "org.apache.xerces.impl.XMLDocumentFragmentScannerImpl.scanDocument",
          "source": "Un known Source"
        },
        {
          "method": "org.apache.xerces.parsers.XML11Configuration.parse",
          "source": "Unknown Source"
        },
        {
          "method": "org.apache.xerces.parsers.XML11Configuration.parse",
          "source": "Unknown Source"
        },
        {
          "method": "org.apache.xerces.parsers.XMLParser.parse",
          "source": "Unknown Source"
        },
        {
          "method": "org.apache.xerces.parsers.AbstractSAXParser.parse",
          "source": "Unknown Source"
        },
        {
          "method": "javax.xml.parsers.SAXParser.parse",
          "source": "Unknown Source"
        },
        {
          "method": "org.eclipse.update.core.model.DefaultSiteParser.parse",
          "source": "DefaultSitePars er.java:156"
        },
        {
          "method": "org.eclipse.update.core.model.SiteModelFactory.parseSite",
          "source": "SiteModelFac                                                              tory.java:78"
        },
        {
          "method": "org.eclipse.update.internal.core.SiteURLFactory.createSite",
          "source": "SiteURLFac                                                              tory.java:80"
        },
        {
          "method": "org.eclipse.update.internal.core.InternalSiteManager.createSite",
          "source": "Inter                                                              nalSiteManager.java:332"
        },
        {
          "method": "org.eclipse.update.internal.core.InternalSiteManager.createSite",
          "source": "Inter                                                              nalSiteManager.java:324"
        },
        {
          "method": "org.eclipse.update.internal.core.InternalSiteManager.createSite",
          "source": "Inter                                                              nalSiteManager.java:289"
        },
        {
          "method": "org.eclipse.update.internal.core.InternalSiteManager.attemptCreateSite",
          "source": "InternalSiteManager.java:220"
        },
        {
          "method": "org.eclipse.update.internal.core.InternalSiteManager.getSite",
          "source": "Internal                                                              SiteManager.java:161"
        },
        {
          "method": "org.eclipse.update.core.SiteManager.getSite",
          "source": "SiteManager.java:78"
        },
        {
          "method": "org.eclipse.update.search.UpdateSearchRequest.searchOneSite",
          "source": "UpdateSea                                                              rchRequest.java:443"
        },
        {
          "method": "org.eclipse.update.search.UpdateSearchRequest.performSearch",
          "source": "UpdateSea                                                              rchRequest.java:292"
        },
        {
          "method": "org.eclipse.update.ui.UpdateJob.runUpdates",
          "source": "UpdateJob.java:204"
        },
        {
          "method": "org.eclipse.update.ui.UpdateJob.run",
          "source": "UpdateJob.java:167"
        },
        {
          "method": "org.eclipse.core.internal.jobs.Worker.run",
          "source": "Worker.java:58"
        }
      ],
      "number": 1,
      "commentIndex": 0,
      "bugId": "139813",
      "date": "2006-05-02T21:41:18+02:00",
      "product": "Platform",
      "component": "Update",
      "severity": "normal"
    }
  ],
  "groupId": "139813",
  "bugId": "139813",
  "date": "2006-05-02T21:41:18+02:00",
  "product": "Platform",
  "component": "Update",
  "severity": "normal"
}