{
  "comments": [
    "Hi!\n\nThis problem commed on Gentoo Linux, Gnome, GTK.\n\nI\u0027m getting the following Exception, when I\u0027m trying to run the hello world SWT application.\n\nException in thread \"main\" java.lang.UnsatisfiedLinkError: no swt-pi-gtk-3139 in java.library.path\n\tat java.lang.ClassLoader.loadLibrary(ClassLoader.java:1682)\n\tat java.lang.Runtime.loadLibrary0(Runtime.java:822)\n\tat java.lang.System.loadLibrary(System.java:992)\n\tat org.eclipse.swt.internal.Library.loadLibrary(Library.java:123)\n\tat org.eclipse.swt.internal.gtk.OS.\u003cclinit\u003e(OS.java:19)\n\tat org.eclipse.swt.internal.Converter.wcsToMbcs(Converter.java:63)\n\tat org.eclipse.swt.internal.Converter.wcsToMbcs(Converter.java:54)\n\tat org.eclipse.swt.widgets.Display.\u003cclinit\u003e(Display.java:122)\n\tat org.cookbook.ch08.FirstSWTClass.main(FirstSWTClass.java:15)\n\nI\u0027ve followed the book, and configured the SWT jar file (org.eclipse.swt.gtk.linux.x86_3.1.1.jar) found in eclipse plugin directory to use in the java.library.path varriable, but didn\u0027t help. Also download SUN JRE 1.5, but didn\u0027t fix it (read this solution else where on the internet).\n\nWhat did help, that copied out the \"so\" files from this jar into a directory and configured that for java.library.path.\n\nThan other issues come up, that if I\u0027m using my application with different swt.jars it requires different gtk-s. If I\u0027m using, with the jar comming from eclipse it requires gtk-3139. I\u0027ve downloaded swt 3.1-r1, with gentoo emerge command. If I set this file in the classpath varriable, than it requires gtk-3138. I was only able to solve this problem by creating soft links on the 3139 files, with 3138 links.\n\nSo this means, that different SWT packages requires different libaries, or environment.\n\nI don\u0027t know that this is really a bug , because it isn\u0027t miss behaving and the whole problem is commed from my bad knowlege about GTK. But I want to report it, because others might meet this problemto and I wasn\u0027t able to locate solution on the internet for this issue. Other thing is, that it violates platform independency a little and I don\u0027t want to write down public, but I\u0027ve made a record in required time creating a Hello World application, which I think never going to be beeten :). (Hello CORBA was easier :) )",
    "There is FAQ item about this:\nhttp://www.eclipse.org/swt/faq.php#missingdll\n\nI just updated to it.",
    "closing"
  ],
  "commentCreationDates": [
    "2006-05-03T18:20:53+02:00",
    "2006-05-05T20:11:04+02:00",
    "2006-05-05T20:11:20+02:00"
  ],
  "traces": [
    {
      "exceptionType": "java.lang.UnsatisfiedLinkError",
      "message": "no swt-pi-gtk-3139 in java.library.path",
      "elements": [
        {
          "method": "java.lang.ClassLoader.loadLibrary",
          "source": "ClassLoader.java:1682"
        },
        {
          "method": "java.lang.Runtime.loadLibrary0",
          "source": "Runtime.java:822"
        },
        {
          "method": "java.lang.System.loadLibrary",
          "source": "System.java:992"
        },
        {
          "method": "org.eclipse.swt.internal.Library.loadLibrary",
          "source": "Library.java:123"
        },
        {
          "method": "org.eclipse.swt.internal.gtk.OS.\u003cclinit\u003e",
          "source": "OS.java:19"
        },
        {
          "method": "org.eclipse.swt.internal.Converter.wcsToMbcs",
          "source": "Converter.java:63"
        },
        {
          "method": "org.eclipse.swt.internal.Converter.wcsToMbcs",
          "source": "Converter.java:54"
        },
        {
          "method": "org.eclipse.swt.widgets.Display.\u003cclinit\u003e",
          "source": "Display.java:122"
        },
        {
          "method": "org.cookbook.ch08.FirstSWTClass.main",
          "source": "FirstSWTClass.java:15"
        }
      ],
      "number": 0,
      "commentIndex": 0,
      "bugId": "140013",
      "date": "2006-05-03T18:20:53+02:00",
      "product": "Platform",
      "component": "SWT",
      "severity": "enhancement"
    }
  ],
  "groupId": "140013",
  "bugId": "140013",
  "date": "2006-05-03T18:20:53+02:00",
  "product": "Platform",
  "component": "SWT",
  "severity": "enhancement"
}