{
  "comments": [
    "On a fresh Eclipse 3.1.2 install, if a project is created with a name using .jar at its end, such as Test.jar, then the Open Type action does not work on any class defined in this project.\n\nAs the included stack trace suggest, it seems the .jar name confuses the Java Project in the resolving of its classpath entries, interpreting the project itself as JAR archive.\n\nI\u0027m currently working on a project where .jar project name are imposed by the organisation and I feel there should not be limitations on project names (apart from platform limitations on file system names).\n\nThis bug occurs also on the 3.2RC1 release. I don\u0027t know if it needs to be reported there also, so I will not do it unless told to do so.\n\n------------------------------------------------------------------\nLog extract:\n!SUBENTRY 1 org.eclipse.jdt.core 4 -1 2006-05-02 13:30:06.519\n!MESSAGE I/O exception\n!STACK 0\njava.util.zip.ZipException: The system cannot find the path specified\n        at java.util.zip.ZipFile.open(Native Method)\n        at java.util.zip.ZipFile.\u003cinit\u003e(Unknown Source)\n        at java.util.zip.ZipFile.\u003cinit\u003e(Unknown Source)\n        at org.eclipse.jdt.internal.core.JavaModelManager.getZipFile(JavaModelManager.java:1461)\n        at org.eclipse.jdt.internal.core.JarPackageFragmentRoot.getJar(JarPackageFragmentRoot.java:181)\n        at org.eclipse.jdt.internal.core.JarPackageFragmentRoot.computeChildren(JarPackageFragmentRoot.java:78)\n        at org.eclipse.jdt.internal.core.PackageFragmentRoot.buildStructure(PackageFragmentRoot.java:174)\n        at org.eclipse.jdt.internal.core.Openable.generateInfos(Openable.java:233)\n        at org.eclipse.jdt.internal.core.JavaElement.openWhenClosed(JavaElement.java:488)\n        at org.eclipse.jdt.internal.core.JavaElement.getElementInfo(JavaElement.java:232)\n        at org.eclipse.jdt.internal.core.JavaElement.getElementInfo(JavaElement.java:218)\n        at org.eclipse.jdt.internal.core.JavaElement.getChildren(JavaElement.java:173)\n        at org.eclipse.jdt.internal.ui.packageview.PackageFragmentProvider.getChildren(PackageFragmentProvider.java:87)\n        at org.eclipse.jdt.internal.ui.packageview.PackageExplorerContentProvider.getChildren(PackageExplorerContentProvider.java:155)\n\n        at org.eclipse.jdt.internal.ui.packageview.PackageExplorerPart$PackageExplorerProblemTreeViewer.isExpandable(PackageExplorerPart.java:306)\n\n        at org.eclipse.jface.viewers.AbstractTreeViewer.updateChildren(AbstractTreeViewer.java:1680)\n        at org.eclipse.jface.viewers.AbstractTreeViewer.internalRefreshStruct(AbstractTreeViewer.java:1268)\n        at org.eclipse.jface.viewers.AbstractTreeViewer.internalRefreshStruct(AbstractTreeViewer.java:1275)\n        at org.eclipse.jface.viewers.AbstractTreeViewer.internalRefreshStruct(AbstractTreeViewer.java:1275)\n        at org.eclipse.jface.viewers.AbstractTreeViewer.internalRefresh(AbstractTreeViewer.java:1245)\n        at org.eclipse.jface.viewers.AbstractTreeViewer.internalRefresh(AbstractTreeViewer.java:1201)\n        at org.eclipse.jdt.internal.ui.packageview.PackageExplorerPart$PackageExplorerProblemTreeViewer.internalRefresh(PackageExplorerPart.java:518)\n\n        at org.eclipse.jface.viewers.StructuredViewer$8.run(StructuredViewer.java:1291)\n        at org.eclipse.jface.viewers.StructuredViewer.preservingSelection(StructuredViewer.java:1201)\n        at org.eclipse.jdt.internal.ui.packageview.PackageExplorerPart$PackageExplorerProblemTreeViewer.preservingSelection(PackageExplorerPart.java:624)\n\n        at org.eclipse.jface.viewers.StructuredViewer.refresh(StructuredViewer.java:1289)\n        at org.eclipse.jface.viewers.StructuredViewer.refresh(StructuredViewer.java:1246)\n        at org.eclipse.jdt.internal.ui.viewsupport.FilterUpdater$1.run(FilterUpdater.java:50)\n        at org.eclipse.swt.widgets.RunnableLock.run(RunnableLock.java:35)\n        at org.eclipse.swt.widgets.Synchronizer.runAsyncMessages(Synchronizer.java:123)\n        at org.eclipse.swt.widgets.Display.runAsyncMessages(Display.java:3057)\n        at org.eclipse.swt.widgets.Display.readAndDispatch(Display.java:2716)\n        at org.eclipse.ui.internal.Workbench.runEventLoop(Workbench.java:1699)\n        at org.eclipse.ui.internal.Workbench.runUI(Workbench.java:1663)\n        at org.eclipse.ui.internal.Workbench.createAndRunWorkbench(Workbench.java:367)\n        at org.eclipse.ui.PlatformUI.createAndRunWorkbench(PlatformUI.java:143)\n        at org.eclipse.ui.internal.ide.IDEApplication.run(IDEApplication.java:103)\n        at org.eclipse.core.internal.runtime.PlatformActivator$1.run(PlatformActivator.java:226)\n        at org.eclipse.core.runtime.adaptor.EclipseStarter.run(EclipseStarter.java:376)\n        at org.eclipse.core.runtime.adaptor.EclipseStarter.run(EclipseStarter.java:163)\n        at sun.reflect.NativeMethodAccessorImpl.invoke0(Native Method)\n        at sun.reflect.NativeMethodAccessorImpl.invoke(Unknown Source)\n        at sun.reflect.DelegatingMethodAccessorImpl.invoke(Unknown Source)\n        at java.lang.reflect.Method.invoke(Unknown Source)\n        at org.eclipse.core.launcher.Main.invokeFramework(Main.java:334)\n        at org.eclipse.core.launcher.Main.basicRun(Main.java:278)\n        at org.eclipse.core.launcher.Main.run(Main.java:973)\n        at org.eclipse.core.launcher.Main.main(Main.java:948)",
    "\n\n*** This bug has been marked as a duplicate of 138184 ***",
    "Verified for 3.4 M2 using build I20070917-0010."
  ],
  "commentCreationDates": [
    "2006-05-04T09:43:00+02:00",
    "2006-05-04T12:12:58+02:00",
    "2007-09-18T09:37:52+02:00"
  ],
  "traces": [
    {
      "exceptionType": "java.util.zip.ZipException",
      "message": "The system cannot find the path specified",
      "elements": [
        {
          "method": "java.util.zip.ZipFile.open",
          "source": "Native Method"
        },
        {
          "method": "java.util.zip.ZipFile.\u003cinit\u003e",
          "source": "Unknown Source"
        },
        {
          "method": "java.util.zip.ZipFile.\u003cinit\u003e",
          "source": "Unknown Source"
        },
        {
          "method": "org.eclipse.jdt.internal.core.JavaModelManager.getZipFile",
          "source": "JavaModelManager.java:1461"
        },
        {
          "method": "org.eclipse.jdt.internal.core.JarPackageFragmentRoot.getJar",
          "source": "JarPackageFragmentRoot.java:181"
        },
        {
          "method": "org.eclipse.jdt.internal.core.JarPackageFragmentRoot.computeChildren",
          "source": "JarPackageFragmentRoot.java:78"
        },
        {
          "method": "org.eclipse.jdt.internal.core.PackageFragmentRoot.buildStructure",
          "source": "PackageFragmentRoot.java:174"
        },
        {
          "method": "org.eclipse.jdt.internal.core.Openable.generateInfos",
          "source": "Openable.java:233"
        },
        {
          "method": "org.eclipse.jdt.internal.core.JavaElement.openWhenClosed",
          "source": "JavaElement.java:488"
        },
        {
          "method": "org.eclipse.jdt.internal.core.JavaElement.getElementInfo",
          "source": "JavaElement.java:232"
        },
        {
          "method": "org.eclipse.jdt.internal.core.JavaElement.getElementInfo",
          "source": "JavaElement.java:218"
        },
        {
          "method": "org.eclipse.jdt.internal.core.JavaElement.getChildren",
          "source": "JavaElement.java:173"
        },
        {
          "method": "org.eclipse.jdt.internal.ui.packageview.PackageFragmentProvider.getChildren",
          "source": "PackageFragmentProvider.java:87"
        },
        {
          "method": "org.eclipse.jdt.internal.ui.packageview.PackageExplorerContentProvider.getChildren",
          "source": "PackageExplorerContentProvider.java:155"
        },
        {
          "method": "org.eclipse.jdt.internal.ui.packageview.PackageExplorerPart$PackageExplorerProblemTreeViewer.isExpandable",
          "source": "PackageExplorerPart.java:306"
        },
        {
          "method": "org.eclipse.jface.viewers.AbstractTreeViewer.updateChildren",
          "source": "AbstractTreeViewer.java:1680"
        },
        {
          "method": "org.eclipse.jface.viewers.AbstractTreeViewer.internalRefreshStruct",
          "source": "AbstractTreeViewer.java:1268"
        },
        {
          "method": "org.eclipse.jface.viewers.AbstractTreeViewer.internalRefreshStruct",
          "source": "AbstractTreeViewer.java:1275"
        },
        {
          "method": "org.eclipse.jface.viewers.AbstractTreeViewer.internalRefreshStruct",
          "source": "AbstractTreeViewer.java:1275"
        },
        {
          "method": "org.eclipse.jface.viewers.AbstractTreeViewer.internalRefresh",
          "source": "AbstractTreeViewer.java:1245"
        },
        {
          "method": "org.eclipse.jface.viewers.AbstractTreeViewer.internalRefresh",
          "source": "AbstractTreeViewer.java:1201"
        },
        {
          "method": "org.eclipse.jdt.internal.ui.packageview.PackageExplorerPart$PackageExplorerProblemTreeViewer.internalRefresh",
          "source": "PackageExplorerPart.java:518"
        },
        {
          "method": "org.eclipse.jface.viewers.StructuredViewer$8.run",
          "source": "StructuredViewer.java:1291"
        },
        {
          "method": "org.eclipse.jface.viewers.StructuredViewer.preservingSelection",
          "source": "StructuredViewer.java:1201"
        },
        {
          "method": "org.eclipse.jdt.internal.ui.packageview.PackageExplorerPart$PackageExplorerProblemTreeViewer.preservingSelection",
          "source": "PackageExplorerPart.java:624"
        },
        {
          "method": "org.eclipse.jface.viewers.StructuredViewer.refresh",
          "source": "StructuredViewer.java:1289"
        },
        {
          "method": "org.eclipse.jface.viewers.StructuredViewer.refresh",
          "source": "StructuredViewer.java:1246"
        },
        {
          "method": "org.eclipse.jdt.internal.ui.viewsupport.FilterUpdater$1.run",
          "source": "FilterUpdater.java:50"
        },
        {
          "method": "org.eclipse.swt.widgets.RunnableLock.run",
          "source": "RunnableLock.java:35"
        },
        {
          "method": "org.eclipse.swt.widgets.Synchronizer.runAsyncMessages",
          "source": "Synchronizer.java:123"
        },
        {
          "method": "org.eclipse.swt.widgets.Display.runAsyncMessages",
          "source": "Display.java:3057"
        },
        {
          "method": "org.eclipse.swt.widgets.Display.readAndDispatch",
          "source": "Display.java:2716"
        },
        {
          "method": "org.eclipse.ui.internal.Workbench.runEventLoop",
          "source": "Workbench.java:1699"
        },
        {
          "method": "org.eclipse.ui.internal.Workbench.runUI",
          "source": "Workbench.java:1663"
        },
        {
          "method": "org.eclipse.ui.internal.Workbench.createAndRunWorkbench",
          "source": "Workbench.java:367"
        },
        {
          "method": "org.eclipse.ui.PlatformUI.createAndRunWorkbench",
          "source": "PlatformUI.java:143"
        },
        {
          "method": "org.eclipse.ui.internal.ide.IDEApplication.run",
          "source": "IDEApplication.java:103"
        },
        {
          "method": "org.eclipse.core.internal.runtime.PlatformActivator$1.run",
          "source": "PlatformActivator.java:226"
        },
        {
          "method": "org.eclipse.core.runtime.adaptor.EclipseStarter.run",
          "source": "EclipseStarter.java:376"
        },
        {
          "method": "org.eclipse.core.runtime.adaptor.EclipseStarter.run",
          "source": "EclipseStarter.java:163"
        },
        {
          "method": "sun.reflect.NativeMethodAccessorImpl.invoke0",
          "source": "Native Method"
        },
        {
          "method": "sun.reflect.NativeMethodAccessorImpl.invoke",
          "source": "Unknown Source"
        },
        {
          "method": "sun.reflect.DelegatingMethodAccessorImpl.invoke",
          "source": "Unknown Source"
        },
        {
          "method": "java.lang.reflect.Method.invoke",
          "source": "Unknown Source"
        },
        {
          "method": "org.eclipse.core.launcher.Main.invokeFramework",
          "source": "Main.java:334"
        },
        {
          "method": "org.eclipse.core.launcher.Main.basicRun",
          "source": "Main.java:278"
        },
        {
          "method": "org.eclipse.core.launcher.Main.run",
          "source": "Main.java:973"
        },
        {
          "method": "org.eclipse.core.launcher.Main.main",
          "source": "Main.java:948"
        }
      ],
      "number": 0,
      "commentIndex": 0,
      "bugId": "140117",
      "duplicateId": "138184",
      "date": "2006-05-04T09:43:00+02:00",
      "product": "JDT",
      "component": "Core",
      "severity": "normal"
    }
  ],
  "groupId": "138184",
  "bugId": "140117",
  "duplicateId": "138184",
  "date": "2006-05-04T09:43:00+02:00",
  "product": "JDT",
  "component": "Core",
  "severity": "normal"
}