{
  "comments": [
    "Version: 3.2.0\nBuild id: I20060504-0920\n\nI was testing  eclipse-gtk on solaris for RC3 and I notice this walkback after I closed eclipse. I don\u0027t know what I did that actually caused the problem.\nNothing in the .log file.\n\nbash-3.00$ ./start.sh\nException in thread \"Text Viewer Hover Presenter\" java.lang.NullPointerException\n        at org.eclipse.jdt.internal.ui.text.java.hover.AbstractJavaEditorTextHover.getStyleSheet(AbstractJavaEditorTextHover.java:182)\n        at org.eclipse.jdt.internal.ui.text.java.hover.JavadocHover.getHoverInfo(JavadocHover.java:180)\n        at org.eclipse.jdt.internal.ui.text.java.hover.AbstractJavaEditorTextHover.getHoverInfo(AbstractJavaEditorTextHover.java:121)\n        at org.eclipse.jdt.internal.ui.text.java.hover.BestMatchHover.getHoverInfo(BestMatchHover.java:102)\n        at org.eclipse.jdt.internal.ui.text.java.hover.JavaEditorTextHoverProxy.getHoverInfo(JavaEditorTextHoverProxy.java:69)\n        at org.eclipse.jface.text.TextViewerHoverManager$4.run(TextViewerHoverManager.java:160)",
    "Looks like a VM / JIT bug. The corresponding line in the code is:\n\nstyleSheetURL\u003d FileLocator.toFileURL(styleSheetURL);\n\nNo way an NPE can happen here."
  ],
  "commentCreationDates": [
    "2006-05-04T22:17:38+02:00",
    "2006-05-04T22:22:49+02:00"
  ],
  "traces": [
    {
      "exceptionType": "java.lang.NullPointerException",
      "elements": [
        {
          "method": "org.eclipse.jdt.internal.ui.text.java.hover.AbstractJavaEditorTextHover.getStyleSheet",
          "source": "AbstractJavaEditorTextHover.java:182"
        },
        {
          "method": "org.eclipse.jdt.internal.ui.text.java.hover.JavadocHover.getHoverInfo",
          "source": "JavadocHover.java:180"
        },
        {
          "method": "org.eclipse.jdt.internal.ui.text.java.hover.AbstractJavaEditorTextHover.getHoverInfo",
          "source": "AbstractJavaEditorTextHover.java:121"
        },
        {
          "method": "org.eclipse.jdt.internal.ui.text.java.hover.BestMatchHover.getHoverInfo",
          "source": "BestMatchHover.java:102"
        },
        {
          "method": "org.eclipse.jdt.internal.ui.text.java.hover.JavaEditorTextHoverProxy.getHoverInfo",
          "source": "JavaEditorTextHoverProxy.java:69"
        },
        {
          "method": "org.eclipse.jface.text.TextViewerHoverManager$4.run",
          "source": "TextViewerHoverManager.java:160"
        }
      ],
      "number": 0,
      "commentIndex": 0,
      "bugId": "140243",
      "date": "2006-05-04T22:17:38+02:00",
      "product": "JDT",
      "component": "Text",
      "severity": "normal"
    }
  ],
  "groupId": "140243",
  "bugId": "140243",
  "date": "2006-05-04T22:17:38+02:00",
  "product": "JDT",
  "component": "Text",
  "severity": "normal"
}