{
  "comments": [
    "In the Specify a Driver and Connection Details page of the connection profile wizard, the driver definitions is not being saved.\n\n1) open Data Source Explorer\n2) Right click on Database then select New...\n3) Select SQL Model-JDBC connection and click Next\n4) Enter any name and click next to the Specify a Driver and Connection Details\n5) Click on the ... button to open Driver Defintion wizard\n6) create any defintion and click OK\n7) Back to the Specify a Driver and Connection Details page and the driver defintion is not save.",
    "I can\u0027t reproduce this in the DTP 0.9 5/4 build with Eclipse 3.2RC2. One thing I did notice is that the newly created driver definition is not selected by default after you exit the wizard and return to the generic JDBC connection profile page -- you have to drop the combo box and then select it.",
    "I had the same problem in the DTP 0.9 5/8 build with Eclipse 3.2RC2. \nIn addition, I got an error at console as follows. \n\nOS: Windows XP sp2 Japanese version\nBuild: dtp-sdk_0.9RC3_N050806 + eclipse-SDK-3.2RC2-win32\n\n------Error Log -----------\n!ENTRY org.eclipse.datatools.connectivity.ui 4 10001 2006-05-09 11:00:39.234\n!MESSAGE Internal Error - org.eclipse.datatools.connectivity\n!STACK 1\norg.eclipse.core.runtime.CoreException: Error loading driver instance data.\n        at org.eclipse.datatools.connectivity.drivers.XMLFileManager.loadPropert\nySets(XMLFileManager.java:228)\n        at org.eclipse.datatools.connectivity.internal.ui.DriverListCombo.refres\nhCombo(DriverListCombo.java:426)\n        at org.eclipse.datatools.connectivity.internal.ui.DriverListCombo$EditBu\nttonSelectionChangedListener.widgetSelected(DriverListCombo.java:602)\n        at org.eclipse.swt.widgets.TypedListener.handleEvent(TypedListener.java:\n90)\n        at org.eclipse.swt.widgets.EventTable.sendEvent(EventTable.java:66)\n        at org.eclipse.swt.widgets.Widget.sendEvent(Widget.java:925)\n        at org.eclipse.swt.widgets.Display.runDeferredEvents(Display.java:3348)\n        at org.eclipse.swt.widgets.Display.readAndDispatch(Display.java:2968)\n        at org.eclipse.jface.window.Window.runEventLoop(Window.java:820)\n        at org.eclipse.jface.window.Window.open(Window.java:796)\n        at org.eclipse.datatools.connectivity.ui.dse.actions.AddProfileViewActio\nn.run(AddProfileViewAction.java:106)\n        at org.eclipse.jface.action.Action.runWithEvent(Action.java:499)\n        at org.eclipse.jface.action.ActionContributionItem.handleWidgetSelection\n(ActionContributionItem.java:539)\n        at org.eclipse.jface.action.ActionContributionItem.access$2(ActionContri\nbutionItem.java:488)\n        at org.eclipse.jface.action.ActionContributionItem$5.handleEvent(ActionC\nontributionItem.java:400)\n        at org.eclipse.swt.widgets.EventTable.sendEvent(EventTable.java:66)\n        at org.eclipse.swt.widgets.Widget.sendEvent(Widget.java:925)\n        at org.eclipse.swt.widgets.Display.runDeferredEvents(Display.java:3348)\n        at org.eclipse.swt.widgets.Display.readAndDispatch(Display.java:2968)\n        at org.eclipse.ui.internal.Workbench.runEventLoop(Workbench.java:1914)\n        at org.eclipse.ui.internal.Workbench.runUI(Workbench.java:1878)\n        at org.eclipse.ui.internal.Workbench.createAndRunWorkbench(Workbench.jav\na:419)\n        at org.eclipse.ui.PlatformUI.createAndRunWorkbench(PlatformUI.java:143)\n        at org.eclipse.ui.internal.ide.IDEApplication.run(IDEApplication.java:95\n)\n        at org.eclipse.core.internal.runtime.PlatformActivator$1.run(PlatformAct\nivator.java:78)\n        at org.eclipse.core.runtime.internal.adaptor.EclipseAppLauncher.runAppli\ncation(EclipseAppLauncher.java:92)\n        at org.eclipse.core.runtime.internal.adaptor.EclipseAppLauncher.start(Ec\nlipseAppLauncher.java:68)\n        at org.eclipse.core.runtime.adaptor.EclipseStarter.run(EclipseStarter.ja\nva:400)\n        at org.eclipse.core.runtime.adaptor.EclipseStarter.run(EclipseStarter.ja\nva:177)\n        at sun.reflect.NativeMethodAccessorImpl.invoke0(Native Method)\n        at sun.reflect.NativeMethodAccessorImpl.invoke(NativeMethodAccessorImpl.\njava:64)\n        at sun.reflect.DelegatingMethodAccessorImpl.invoke(DelegatingMethodAcces\nsorImpl.java:43)\n        at java.lang.reflect.Method.invoke(Method.java:615)\n        at org.eclipse.core.launcher.Main.invokeFramework(Main.java:336)\n        at org.eclipse.core.launcher.Main.basicRun(Main.java:280)\n        at org.eclipse.core.launcher.Main.run(Main.java:977)\n        at org.eclipse.core.launcher.Main.main(Main.java:952)\norg.eclipse.core.runtime.CoreException[-1]: org.xml.sax.SAXParseException: ????\n???G???R?[?h??: \"UTF8\"\n        at org.apache.xerces.parsers.DOMParser.parse(Unknown Source)\n        at org.apache.xerces.jaxp.DocumentBuilderImpl.parse(Unknown Source)\n        at org.eclipse.datatools.connectivity.drivers.XMLFileManager.loadPropert\nySets(XMLFileManager.java:207)\n        at org.eclipse.datatools.connectivity.internal.ui.DriverListCombo.refres\nhCombo(DriverListCombo.java:426)\n        at org.eclipse.datatools.connectivity.internal.ui.DriverListCombo$EditBu\nttonSelectionChangedListener.widgetSelected(DriverListCombo.java:602)\n        at org.eclipse.swt.widgets.TypedListener.handleEvent(TypedListener.java:\n90)\n        at org.eclipse.swt.widgets.EventTable.sendEvent(EventTable.java:66)\n        at org.eclipse.swt.widgets.Widget.sendEvent(Widget.java:925)\n        at org.eclipse.swt.widgets.Display.runDeferredEvents(Display.java:3348)\n        at org.eclipse.swt.widgets.Display.readAndDispatch(Display.java:2968)\n        at org.eclipse.jface.window.Window.runEventLoop(Window.java:820)\n        at org.eclipse.jface.window.Window.open(Window.java:796)\n        at org.eclipse.datatools.connectivity.ui.dse.actions.AddProfileViewActio\nn.run(AddProfileViewAction.java:106)\n        at org.eclipse.jface.action.Action.runWithEvent(Action.java:499)\n        at org.eclipse.jface.action.ActionContributionItem.handleWidgetSelection\n(ActionContributionItem.java:539)\n        at org.eclipse.jface.action.ActionContributionItem.access$2(ActionContri\nbutionItem.java:488)\n        at org.eclipse.jface.action.ActionContributionItem$5.handleEvent(ActionC\nontributionItem.java:400)\n        at org.eclipse.swt.widgets.EventTable.sendEvent(EventTable.java:66)\n        at org.eclipse.swt.widgets.Widget.sendEvent(Widget.java:925)\n        at org.eclipse.swt.widgets.Display.runDeferredEvents(Display.java:3348)\n        at org.eclipse.swt.widgets.Display.readAndDispatch(Display.java:2968)\n        at org.eclipse.ui.internal.Workbench.runEventLoop(Workbench.java:1914)\n        at org.eclipse.ui.internal.Workbench.runUI(Workbench.java:1878)\n        at org.eclipse.ui.internal.Workbench.createAndRunWorkbench(Workbench.jav\na:419)\n        at org.eclipse.ui.PlatformUI.createAndRunWorkbench(PlatformUI.java:143)\n        at org.eclipse.ui.internal.ide.IDEApplication.run(IDEApplication.java:95\n)\n        at org.eclipse.core.internal.runtime.PlatformActivator$1.run(PlatformAct\nivator.java:78)\n        at org.eclipse.core.runtime.internal.adaptor.EclipseAppLauncher.runAppli\ncation(EclipseAppLauncher.java:92)\n        at org.eclipse.core.runtime.internal.adaptor.EclipseAppLauncher.start(Ec\nlipseAppLauncher.java:68)\n        at org.eclipse.core.runtime.adaptor.EclipseStarter.run(EclipseStarter.ja\nva:400)\n        at org.eclipse.core.runtime.adaptor.EclipseStarter.run(EclipseStarter.ja\nva:177)\n        at sun.reflect.NativeMethodAccessorImpl.invoke0(Native Method)\n        at sun.reflect.NativeMethodAccessorImpl.invoke(NativeMethodAccessorImpl.\njava:64)\n        at sun.reflect.DelegatingMethodAccessorImpl.invoke(DelegatingMethodAcces\nsorImpl.java:43)\n        at java.lang.reflect.Method.invoke(Method.java:615)\n        at org.eclipse.core.launcher.Main.invokeFramework(Main.java:336)\n        at org.eclipse.core.launcher.Main.basicRun(Main.java:280)\n        at org.eclipse.core.launcher.Main.run(Main.java:977)\n        at org.eclipse.core.launcher.Main.main(Main.java:952)\n!SUBENTRY 1 org.eclipse.datatools.connectivity 4 -1 2006-05-09 11:00:39.281\n!MESSAGE Error loading driver instance data.\n!STACK 0\norg.xml.sax.SAXParseException: ???????G???R?[?h??: \"UTF8\"\n        at org.apache.xerces.parsers.DOMParser.parse(Unknown Source)\n        at org.apache.xerces.jaxp.DocumentBuilderImpl.parse(Unknown Source)\n        at org.eclipse.datatools.connectivity.drivers.XMLFileManager.loadPropert\nySets(XMLFileManager.java:207)\n        at org.eclipse.datatools.connectivity.internal.ui.DriverListCombo.refres\nhCombo(DriverListCombo.java:426)\n        at org.eclipse.datatools.connectivity.internal.ui.DriverListCombo$EditBu\nttonSelectionChangedListener.widgetSelected(DriverListCombo.java:602)\n        at org.eclipse.swt.widgets.TypedListener.handleEvent(TypedListener.java:\n90)\n        at org.eclipse.swt.widgets.EventTable.sendEvent(EventTable.java:66)\n        at org.eclipse.swt.widgets.Widget.sendEvent(Widget.java:925)\n        at org.eclipse.swt.widgets.Display.runDeferredEvents(Display.java:3348)\n        at org.eclipse.swt.widgets.Display.readAndDispatch(Display.java:2968)\n        at org.eclipse.jface.window.Window.runEventLoop(Window.java:820)\n        at org.eclipse.jface.window.Window.open(Window.java:796)\n        at org.eclipse.datatools.connectivity.ui.dse.actions.AddProfileViewActio\nn.run(AddProfileViewAction.java:106)\n        at org.eclipse.jface.action.Action.runWithEvent(Action.java:499)\n        at org.eclipse.jface.action.ActionContributionItem.handleWidgetSelection\n(ActionContributionItem.java:539)\n        at org.eclipse.jface.action.ActionContributionItem.access$2(ActionContri\nbutionItem.java:488)\n        at org.eclipse.jface.action.ActionContributionItem$5.handleEvent(ActionC\nontributionItem.java:400)\n        at org.eclipse.swt.widgets.EventTable.sendEvent(EventTable.java:66)\n        at org.eclipse.swt.widgets.Widget.sendEvent(Widget.java:925)\n        at org.eclipse.swt.widgets.Display.runDeferredEvents(Display.java:3348)\n        at org.eclipse.swt.widgets.Display.readAndDispatch(Display.java:2968)\n        at org.eclipse.ui.internal.Workbench.runEventLoop(Workbench.java:1914)\n        at org.eclipse.ui.internal.Workbench.runUI(Workbench.java:1878)\n        at org.eclipse.ui.internal.Workbench.createAndRunWorkbench(Workbench.jav\na:419)\n        at org.eclipse.ui.PlatformUI.createAndRunWorkbench(PlatformUI.java:143)\n        at org.eclipse.ui.internal.ide.IDEApplication.run(IDEApplication.java:95\n)\n        at org.eclipse.core.internal.runtime.PlatformActivator$1.run(PlatformAct\nivator.java:78)\n        at org.eclipse.core.runtime.internal.adaptor.EclipseAppLauncher.runAppli\ncation(EclipseAppLauncher.java:92)\n        at org.eclipse.core.runtime.internal.adaptor.EclipseAppLauncher.start(Ec\nlipseAppLauncher.java:68)\n        at org.eclipse.core.runtime.adaptor.EclipseStarter.run(EclipseStarter.ja\nva:400)\n        at org.eclipse.core.runtime.adaptor.EclipseStarter.run(EclipseStarter.ja\nva:177)\n        at sun.reflect.NativeMethodAccessorImpl.invoke0(Native Method)\n        at sun.reflect.NativeMethodAccessorImpl.invoke(NativeMethodAccessorImpl.\njava:64)\n        at sun.reflect.DelegatingMethodAccessorImpl.invoke(DelegatingMethodAcces\nsorImpl.java:43)\n        at java.lang.reflect.Method.invoke(Method.java:615)\n        at org.eclipse.core.launcher.Main.invokeFramework(Main.java:336)\n        at org.eclipse.core.launcher.Main.basicRun(Main.java:280)\n        at org.eclipse.core.launcher.Main.run(Main.java:977)\n        at org.eclipse.core.launcher.Main.main(Main.java:952)",
    "Sorry. Some character was garbled in my comments. \nIt said \u0027org.eclipse.core.runtime.CoreException[-1]: org.xml.sax.SAXParseException: Invalid encoding name \"UTF8\"\u0027. \n\nThis value should be change to the correct name \"UTF-8\". ",
    "Brian,\n\nNotice the Japanese locale for the machine below. Is this related to the recent changes in driver defs?",
    "I am experiencing the same problem using DTP0.9RC2, Sun JDK 1.4.2_08, win32, en_US. \n\nFYI, I have tried downloading DTP at least 4 different times over the past few months and everytime I have encountered basic bugs like this one. I can\u0027t help but believe this is related to the lack unit tests in your CVS source tree. DTP seems to have a lot of potential. What it seems to really need is a good suite of unit tests to hopefully prevent these types of embarrasing bugs. I can only hope that your fix for this particular problem will include a unit test.\n\n- Ron",
    "Hi John and Brian,\nI am able to reproduce this using dtp-sdk_0.9RC3_N050406 as well as 05/05 and 05/09 drivers. I set up a clean envirnment using Eclipse 3.2RC2 SDK, EMF 2.2.0RC2 and GEF 3.2RC2. After I create a  driver definition it does not appear in the combo box  in the Driver details page.I have attached the log, there are some other erros as well.\nCan you pls take a look, this will block the TVT ",
    "Created an attachment (id\u003d40759)\nError log\n\n",
    "Quy,\n Since this is blocking many TVT test cases, can you change the status to blocking (i am assuming this is reproducible).Only the owner or the assignee can do this. ",
    "Delivered a fix to change the encoding string from \"UTF8\" to \"UTF-8\", though I (like John) am not able to duplicate the issue on the English version of Windows.",
    "FWIW, I am having the problem using the English version of windows along with the Xerces 2.8.0 parser.",
    "We tested the fix in a build (thanks Rupesh!) and it seems to fix the problem. Can you verify Quy?",
    "Could you please tell me the date of the build which contains the fix.  Thanks.",
    "Probably tomorrow morning\u0027s build. There were some speed issues with uploading the new build this afternoon. I\u0027d wait for the next build to be posted on the DTP site tomorrow morning sometime.",
    "Can\u0027t get a good connection to the download server. Will post this build first thing in the morning.",
    "Verified successfully with dtp-sdk_0.9RC3_N051006.\nThank. "
  ],
  "commentCreationDates": [
    "2006-05-05T02:49:51+02:00",
    "2006-05-05T18:36:41+02:00",
    "2006-05-09T04:08:06+02:00",
    "2006-05-09T04:12:27+02:00",
    "2006-05-09T15:56:59+02:00",
    "2006-05-09T18:00:40+02:00",
    "2006-05-09T18:43:17+02:00",
    "2006-05-09T18:53:10+02:00",
    "2006-05-09T19:39:51+02:00",
    "2006-05-09T20:57:31+02:00",
    "2006-05-09T21:25:16+02:00",
    "2006-05-10T00:44:33+02:00",
    "2006-05-10T00:56:11+02:00",
    "2006-05-10T00:59:15+02:00",
    "2006-05-10T03:10:36+02:00",
    "2006-05-11T10:00:51+02:00"
  ],
  "traces": [
    {
      "exceptionType": "org.eclipse.core.runtime.CoreException",
      "message": "Error loading driver instance data.",
      "elements": [
        {
          "method": "org.eclipse.datatools.connectivity.drivers.XMLFileManager.loadPropertySets",
          "source": "XMLFileManager.java:228"
        },
        {
          "method": "org.eclipse.datatools.connectivity.internal.ui.DriverListCombo.refreshCombo",
          "source": "DriverListCombo.java:426"
        },
        {
          "method": "org.eclipse.datatools.connectivity.internal.ui.DriverListCombo$EditButtonSelectionChangedListener.widgetSelected",
          "source": "DriverListCombo.java:602"
        },
        {
          "method": "org.eclipse.swt.widgets.TypedListener.handleEvent",
          "source": "TypedListener.java: 90"
        },
        {
          "method": "org.eclipse.swt.widgets.EventTable.sendEvent",
          "source": "EventTable.java:66"
        },
        {
          "method": "org.eclipse.swt.widgets.Widget.sendEvent",
          "source": "Widget.java:925"
        },
        {
          "method": "org.eclipse.swt.widgets.Display.runDeferredEvents",
          "source": "Display.java:3348"
        },
        {
          "method": "org.eclipse.swt.widgets.Display.readAndDispatch",
          "source": "Display.java:2968"
        },
        {
          "method": "org.eclipse.jface.window.Window.runEventLoop",
          "source": "Window.java:820"
        },
        {
          "method": "org.eclipse.jface.window.Window.open",
          "source": "Window.java:796"
        },
        {
          "method": "org.eclipse.datatools.connectivity.ui.dse.actions.AddProfileViewAction.run",
          "source": "AddProfileViewAction.java:106"
        },
        {
          "method": "org.eclipse.jface.action.Action.runWithEvent",
          "source": "Action.java:499"
        },
        {
          "method": "org.eclipse.jface.action.ActionContributionItem.handleWidgetSelection",
          "source": "ActionContributionItem.java:539"
        },
        {
          "method": "org.eclipse.jface.action.ActionContributionItem.access$2",
          "source": "ActionContri butionItem.java:488"
        },
        {
          "method": "org.eclipse.jface.action.ActionContributionItem$5.handleEvent",
          "source": "ActionC ontributionItem.java:400"
        },
        {
          "method": "org.eclipse.swt.widgets.EventTable.sendEvent",
          "source": "EventTable.java:66"
        },
        {
          "method": "org.eclipse.swt.widgets.Widget.sendEvent",
          "source": "Widget.java:925"
        },
        {
          "method": "org.eclipse.swt.widgets.Display.runDeferredEvents",
          "source": "Display.java:3348"
        },
        {
          "method": "org.eclipse.swt.widgets.Display.readAndDispatch",
          "source": "Display.java:2968"
        },
        {
          "method": "org.eclipse.ui.internal.Workbench.runEventLoop",
          "source": "Workbench.java:1914"
        },
        {
          "method": "org.eclipse.ui.internal.Workbench.runUI",
          "source": "Workbench.java:1878"
        },
        {
          "method": "org.eclipse.ui.internal.Workbench.createAndRunWorkbench",
          "source": "Workbench.jav a:419"
        },
        {
          "method": "org.eclipse.ui.PlatformUI.createAndRunWorkbench",
          "source": "PlatformUI.java:143"
        },
        {
          "method": "org.eclipse.ui.internal.ide.IDEApplication.run",
          "source": "IDEApplication.java:95 "
        },
        {
          "method": "org.eclipse.core.internal.runtime.PlatformActivator$1.run",
          "source": "PlatformAct ivator.java:78"
        },
        {
          "method": "org.eclipse.core.runtime.internal.adaptor.EclipseAppLauncher.runApplication",
          "source": "EclipseAppLauncher.java:92"
        },
        {
          "method": "org.eclipse.core.runtime.internal.adaptor.EclipseAppLauncher.start",
          "source": "Ec lipseAppLauncher.java:68"
        },
        {
          "method": "org.eclipse.core.runtime.adaptor.EclipseStarter.run",
          "source": "EclipseStarter.ja va:400"
        },
        {
          "method": "org.eclipse.core.runtime.adaptor.EclipseStarter.run",
          "source": "EclipseStarter.ja va:177"
        },
        {
          "method": "sun.reflect.NativeMethodAccessorImpl.invoke0",
          "source": "Native Method"
        },
        {
          "method": "sun.reflect.NativeMethodAccessorImpl.invoke",
          "source": "NativeMethodAccessorImpl. java:64"
        },
        {
          "method": "sun.reflect.DelegatingMethodAccessorImpl.invoke",
          "source": "DelegatingMethodAcces sorImpl.java:43"
        },
        {
          "method": "java.lang.reflect.Method.invoke",
          "source": "Method.java:615"
        },
        {
          "method": "org.eclipse.core.launcher.Main.invokeFramework",
          "source": "Main.java:336"
        },
        {
          "method": "org.eclipse.core.launcher.Main.basicRun",
          "source": "Main.java:280"
        },
        {
          "method": "org.eclipse.core.launcher.Main.run",
          "source": "Main.java:977"
        },
        {
          "method": "org.eclipse.core.launcher.Main.main",
          "source": "Main.java:952"
        }
      ],
      "number": 0,
      "commentIndex": 2,
      "bugId": "140280",
      "date": "2006-05-09T04:08:06+02:00",
      "product": "Data Tools",
      "component": "Connectivity",
      "severity": "blocker"
    },
    {
      "exceptionType": "org.xml.sax.SAXParseException",
      "message": "???? ???G???R?[?h??: \"UTF8\"",
      "elements": [
        {
          "method": "org.apache.xerces.parsers.DOMParser.parse",
          "source": "Unknown Source"
        },
        {
          "method": "org.apache.xerces.jaxp.DocumentBuilderImpl.parse",
          "source": "Unknown Source"
        },
        {
          "method": "org.eclipse.datatools.connectivity.drivers.XMLFileManager.loadPropertySets",
          "source": "XMLFileManager.java:207"
        },
        {
          "method": "org.eclipse.datatools.connectivity.internal.ui.DriverListCombo.refreshCombo",
          "source": "DriverListCombo.java:426"
        },
        {
          "method": "org.eclipse.datatools.connectivity.internal.ui.DriverListCombo$EditButtonSelectionChangedListener.widgetSelected",
          "source": "DriverListCombo.java:602"
        },
        {
          "method": "org.eclipse.swt.widgets.TypedListener.handleEvent",
          "source": "TypedListener.java: 90"
        },
        {
          "method": "org.eclipse.swt.widgets.EventTable.sendEvent",
          "source": "EventTable.java:66"
        },
        {
          "method": "org.eclipse.swt.widgets.Widget.sendEvent",
          "source": "Widget.java:925"
        },
        {
          "method": "org.eclipse.swt.widgets.Display.runDeferredEvents",
          "source": "Display.java:3348"
        },
        {
          "method": "org.eclipse.swt.widgets.Display.readAndDispatch",
          "source": "Display.java:2968"
        },
        {
          "method": "org.eclipse.jface.window.Window.runEventLoop",
          "source": "Window.java:820"
        },
        {
          "method": "org.eclipse.jface.window.Window.open",
          "source": "Window.java:796"
        },
        {
          "method": "org.eclipse.datatools.connectivity.ui.dse.actions.AddProfileViewAction.run",
          "source": "AddProfileViewAction.java:106"
        },
        {
          "method": "org.eclipse.jface.action.Action.runWithEvent",
          "source": "Action.java:499"
        },
        {
          "method": "org.eclipse.jface.action.ActionContributionItem.handleWidgetSelection",
          "source": "ActionContributionItem.java:539"
        },
        {
          "method": "org.eclipse.jface.action.ActionContributionItem.access$2",
          "source": "ActionContri butionItem.java:488"
        },
        {
          "method": "org.eclipse.jface.action.ActionContributionItem$5.handleEvent",
          "source": "ActionC ontributionItem.java:400"
        },
        {
          "method": "org.eclipse.swt.widgets.EventTable.sendEvent",
          "source": "EventTable.java:66"
        },
        {
          "method": "org.eclipse.swt.widgets.Widget.sendEvent",
          "source": "Widget.java:925"
        },
        {
          "method": "org.eclipse.swt.widgets.Display.runDeferredEvents",
          "source": "Display.java:3348"
        },
        {
          "method": "org.eclipse.swt.widgets.Display.readAndDispatch",
          "source": "Display.java:2968"
        },
        {
          "method": "org.eclipse.ui.internal.Workbench.runEventLoop",
          "source": "Workbench.java:1914"
        },
        {
          "method": "org.eclipse.ui.internal.Workbench.runUI",
          "source": "Workbench.java:1878"
        },
        {
          "method": "org.eclipse.ui.internal.Workbench.createAndRunWorkbench",
          "source": "Workbench.jav a:419"
        },
        {
          "method": "org.eclipse.ui.PlatformUI.createAndRunWorkbench",
          "source": "PlatformUI.java:143"
        },
        {
          "method": "org.eclipse.ui.internal.ide.IDEApplication.run",
          "source": "IDEApplication.java:95 "
        },
        {
          "method": "org.eclipse.core.internal.runtime.PlatformActivator$1.run",
          "source": "PlatformAct ivator.java:78"
        },
        {
          "method": "org.eclipse.core.runtime.internal.adaptor.EclipseAppLauncher.runApplication",
          "source": "EclipseAppLauncher.java:92"
        },
        {
          "method": "org.eclipse.core.runtime.internal.adaptor.EclipseAppLauncher.start",
          "source": "Ec lipseAppLauncher.java:68"
        },
        {
          "method": "org.eclipse.core.runtime.adaptor.EclipseStarter.run",
          "source": "EclipseStarter.ja va:400"
        },
        {
          "method": "org.eclipse.core.runtime.adaptor.EclipseStarter.run",
          "source": "EclipseStarter.ja va:177"
        },
        {
          "method": "sun.reflect.NativeMethodAccessorImpl.invoke0",
          "source": "Native Method"
        },
        {
          "method": "sun.reflect.NativeMethodAccessorImpl.invoke",
          "source": "NativeMethodAccessorImpl. java:64"
        },
        {
          "method": "sun.reflect.DelegatingMethodAccessorImpl.invoke",
          "source": "DelegatingMethodAcces sorImpl.java:43"
        },
        {
          "method": "java.lang.reflect.Method.invoke",
          "source": "Method.java:615"
        },
        {
          "method": "org.eclipse.core.launcher.Main.invokeFramework",
          "source": "Main.java:336"
        },
        {
          "method": "org.eclipse.core.launcher.Main.basicRun",
          "source": "Main.java:280"
        },
        {
          "method": "org.eclipse.core.launcher.Main.run",
          "source": "Main.java:977"
        },
        {
          "method": "org.eclipse.core.launcher.Main.main",
          "source": "Main.java:952"
        }
      ],
      "number": 1,
      "commentIndex": 2,
      "bugId": "140280",
      "date": "2006-05-09T04:08:06+02:00",
      "product": "Data Tools",
      "component": "Connectivity",
      "severity": "blocker"
    },
    {
      "exceptionType": "org.xml.sax.SAXParseException",
      "message": "???????G???R?[?h??: \"UTF8\"",
      "elements": [
        {
          "method": "org.apache.xerces.parsers.DOMParser.parse",
          "source": "Unknown Source"
        },
        {
          "method": "org.apache.xerces.jaxp.DocumentBuilderImpl.parse",
          "source": "Unknown Source"
        },
        {
          "method": "org.eclipse.datatools.connectivity.drivers.XMLFileManager.loadPropertySets",
          "source": "XMLFileManager.java:207"
        },
        {
          "method": "org.eclipse.datatools.connectivity.internal.ui.DriverListCombo.refreshCombo",
          "source": "DriverListCombo.java:426"
        },
        {
          "method": "org.eclipse.datatools.connectivity.internal.ui.DriverListCombo$EditButtonSelectionChangedListener.widgetSelected",
          "source": "DriverListCombo.java:602"
        },
        {
          "method": "org.eclipse.swt.widgets.TypedListener.handleEvent",
          "source": "TypedListener.java: 90"
        },
        {
          "method": "org.eclipse.swt.widgets.EventTable.sendEvent",
          "source": "EventTable.java:66"
        },
        {
          "method": "org.eclipse.swt.widgets.Widget.sendEvent",
          "source": "Widget.java:925"
        },
        {
          "method": "org.eclipse.swt.widgets.Display.runDeferredEvents",
          "source": "Display.java:3348"
        },
        {
          "method": "org.eclipse.swt.widgets.Display.readAndDispatch",
          "source": "Display.java:2968"
        },
        {
          "method": "org.eclipse.jface.window.Window.runEventLoop",
          "source": "Window.java:820"
        },
        {
          "method": "org.eclipse.jface.window.Window.open",
          "source": "Window.java:796"
        },
        {
          "method": "org.eclipse.datatools.connectivity.ui.dse.actions.AddProfileViewAction.run",
          "source": "AddProfileViewAction.java:106"
        },
        {
          "method": "org.eclipse.jface.action.Action.runWithEvent",
          "source": "Action.java:499"
        },
        {
          "method": "org.eclipse.jface.action.ActionContributionItem.handleWidgetSelection",
          "source": "ActionContributionItem.java:539"
        },
        {
          "method": "org.eclipse.jface.action.ActionContributionItem.access$2",
          "source": "ActionContri butionItem.java:488"
        },
        {
          "method": "org.eclipse.jface.action.ActionContributionItem$5.handleEvent",
          "source": "ActionC ontributionItem.java:400"
        },
        {
          "method": "org.eclipse.swt.widgets.EventTable.sendEvent",
          "source": "EventTable.java:66"
        },
        {
          "method": "org.eclipse.swt.widgets.Widget.sendEvent",
          "source": "Widget.java:925"
        },
        {
          "method": "org.eclipse.swt.widgets.Display.runDeferredEvents",
          "source": "Display.java:3348"
        },
        {
          "method": "org.eclipse.swt.widgets.Display.readAndDispatch",
          "source": "Display.java:2968"
        },
        {
          "method": "org.eclipse.ui.internal.Workbench.runEventLoop",
          "source": "Workbench.java:1914"
        },
        {
          "method": "org.eclipse.ui.internal.Workbench.runUI",
          "source": "Workbench.java:1878"
        },
        {
          "method": "org.eclipse.ui.internal.Workbench.createAndRunWorkbench",
          "source": "Workbench.jav a:419"
        },
        {
          "method": "org.eclipse.ui.PlatformUI.createAndRunWorkbench",
          "source": "PlatformUI.java:143"
        },
        {
          "method": "org.eclipse.ui.internal.ide.IDEApplication.run",
          "source": "IDEApplication.java:95 "
        },
        {
          "method": "org.eclipse.core.internal.runtime.PlatformActivator$1.run",
          "source": "PlatformAct ivator.java:78"
        },
        {
          "method": "org.eclipse.core.runtime.internal.adaptor.EclipseAppLauncher.runApplication",
          "source": "EclipseAppLauncher.java:92"
        },
        {
          "method": "org.eclipse.core.runtime.internal.adaptor.EclipseAppLauncher.start",
          "source": "Ec lipseAppLauncher.java:68"
        },
        {
          "method": "org.eclipse.core.runtime.adaptor.EclipseStarter.run",
          "source": "EclipseStarter.ja va:400"
        },
        {
          "method": "org.eclipse.core.runtime.adaptor.EclipseStarter.run",
          "source": "EclipseStarter.ja va:177"
        },
        {
          "method": "sun.reflect.NativeMethodAccessorImpl.invoke0",
          "source": "Native Method"
        },
        {
          "method": "sun.reflect.NativeMethodAccessorImpl.invoke",
          "source": "NativeMethodAccessorImpl. java:64"
        },
        {
          "method": "sun.reflect.DelegatingMethodAccessorImpl.invoke",
          "source": "DelegatingMethodAcces sorImpl.java:43"
        },
        {
          "method": "java.lang.reflect.Method.invoke",
          "source": "Method.java:615"
        },
        {
          "method": "org.eclipse.core.launcher.Main.invokeFramework",
          "source": "Main.java:336"
        },
        {
          "method": "org.eclipse.core.launcher.Main.basicRun",
          "source": "Main.java:280"
        },
        {
          "method": "org.eclipse.core.launcher.Main.run",
          "source": "Main.java:977"
        },
        {
          "method": "org.eclipse.core.launcher.Main.main",
          "source": "Main.java:952"
        }
      ],
      "number": 2,
      "commentIndex": 2,
      "bugId": "140280",
      "date": "2006-05-09T04:08:06+02:00",
      "product": "Data Tools",
      "component": "Connectivity",
      "severity": "blocker"
    }
  ],
  "groupId": "140280",
  "bugId": "140280",
  "date": "2006-05-05T02:49:51+02:00",
  "product": "Data Tools",
  "component": "Connectivity",
  "severity": "blocker"
}