{
  "comments": [
    "I have installed eclipse on Sun Solaris. After Installation of Java 4, I unzipped eclipse (ver 3.1.2)\n--- Solaris Details ---\nSunOS blrsnse3 5.8 Generic_108528-27 sun4u sparc SUNW,Sun-Fire-880System \u003d SunOS\n--- Java Details ---\njava version \"1.4.2_08\"\nJava(TM) 2 Runtime Environment, Standard Edition (build 1.4.2_08-b03)\nJava HotSpot(TM) Client VM (build 1.4.2_08-b03, mixed mode)\n\nWhen I am trying to run eclipse first time, I am getting following error:\n\n!SESSION 2006-05-10 10:35:49.845 -----------------------------------------------\neclipse.buildId\u003dM20060118-1600\njava.version\u003d1.4.2_08\njava.vendor\u003dSun Microsystems Inc.\nBootLoader constants: OS\u003dsolaris, ARCH\u003dsparc, WS\u003dmotif, NL\u003den_US\nCommand-line arguments:  -os solaris -ws motif -arch sparc\n\n!ENTRY org.eclipse.osgi 2006-05-10 10:35:50.704\n!MESSAGE Application error\n!STACK 1\njava.lang.IllegalStateException: Unable to acquire application service.\n        at org.eclipse.core.runtime.adaptor.EclipseStarter.run(EclipseStarter.java:367)\n        at org.eclipse.core.runtime.adaptor.EclipseStarter.run(EclipseStarter.java:163)\n        at sun.reflect.NativeMethodAccessorImpl.invoke0(Native Method)\n        at sun.reflect.NativeMethodAccessorImpl.invoke(NativeMethodAccessorImpl.java:39)\n        at sun.reflect.DelegatingMethodAccessorImpl.invoke(DelegatingMethodAccessorImpl.java:25)\n        at java.lang.reflect.Method.invoke(Method.java:324)\n        at org.eclipse.core.launcher.Main.invokeFramework(Main.java:334)\n        at org.eclipse.core.launcher.Main.basicRun(Main.java:278)\n        at org.eclipse.core.launcher.Main.run(Main.java:973)\n        at org.eclipse.core.launcher.Main.main(Main.java:948)\n\nPls help me for the resolution of the bug.\n\nThanks\n-Amal",
    "Did you succesfully start eclipse before installing your jre?\nCould you run with eclipse and specify -clean on the command line?",
    "(In reply to comment #1)\n\u003e Did you succesfully start eclipse before installing your jre?\nNo. I thought I have to install jre 1.4 before I unzip \u0026 start eclipse. I did not tried unzippping/starting eclipse before installation of Java 1.4.2_08\n\u003e Could you run with eclipse and specify -clean on the command line?\n\u003e \nI tried that It gave me the same error.\n\nThe way I am running eclipse is like this:\n1. go to eclipse home directory\n2. run eclipse file\n\nI am listing directory contents:\ncbasavar - blrsnse3 48\u003e ll\ntotal 384\ndrwxr-xr-x   6 cbasavar eng         4096 May 10 14:29 .\ndrwxrwxrwx  37 cbasavar eng        28672 May 10 14:14 ..\n-rw-rw-r--   1 cbasavar eng           59 Jan 19 03:58 .eclipseproduct\ndrwxrwxr-x   5 cbasavar eng         4096 May 10 14:30 configuration\n-rwxr-xr-x   1 cbasavar eng        48992 Jan 19 03:58 eclipse ---\u003e am running this file.\n-rw-rw-r--   1 cbasavar eng        10540 Jan 19 03:58 Eclipse.l.pm\n-rw-rw-r--   1 cbasavar eng         7916 Jan 19 03:58 Eclipse.m.pm\n-rw-rw-r--   1 cbasavar eng         6796 Jan 19 03:58 Eclipse.s.pm\n-rw-rw-r--   1 cbasavar eng         5620 Jan 19 03:58 Eclipse.t.pm\n-rw-rw-r--   1 cbasavar eng        16536 Jan 19 03:58 epl-v10.html\ndrwxr-xr-x   3 cbasavar eng         4096 May 10 10:14 features\n-rw-rw-r--   1 cbasavar eng         6506 Jan 19 03:58 notice.html\ndrwxr-xr-x   2 cbasavar eng         4096 May 10 10:14 plugins\ndrwxrwxr-x   2 cbasavar eng         4096 Jan 19 03:58 readme\n-rw-rw-r--   1 cbasavar eng        32567 Jan 19 03:58 startup.jar\n\nI presume this is the correct way to start eclipse.\n\nThanks\n-Amal",
    "Have you unzipped eclipse 3.1.2 over an install of eclipse 3.1?\nIt seems to me that you are missing some files. Could you try to re-extract the archive in another location and run again?",
    "(In reply to comment #3)\n\u003e Have you unzipped eclipse 3.1.2 over an install of eclipse 3.1?\n\u003e It seems to me that you are missing some files. Could you try to re-extract the\n\u003e archive in another location and run again?\n\u003e \n\nThis is the first time I am installing eclipse :-( Installing in another location I have already tried that. Same error.\n\nWhat I am trying to do now is to download eclipse-sdk-3.2M6-solaris-motif.zip, then unzip \u0026 see if it works.\n\nLet me know if you hv anyother suggestion for me.\n\nThanks\n-Amal",
    "Hi All,\n\nAfter installation of eclipse-sdk-3.2M6-solaris-motif.zip, its working fine.\n\nThanks Pascal for the support.\n\nCheers\n-Amal"
  ],
  "commentCreationDates": [
    "2006-05-10T07:43:50+02:00",
    "2006-05-10T13:03:07+02:00",
    "2006-05-10T14:07:19+02:00",
    "2006-05-10T14:32:52+02:00",
    "2006-05-10T15:04:47+02:00",
    "2006-05-11T12:31:03+02:00"
  ],
  "traces": [
    {
      "exceptionType": "java.lang.IllegalStateException",
      "message": "Unable to acquire application service.",
      "elements": [
        {
          "method": "org.eclipse.core.runtime.adaptor.EclipseStarter.run",
          "source": "EclipseStarter.java:367"
        },
        {
          "method": "org.eclipse.core.runtime.adaptor.EclipseStarter.run",
          "source": "EclipseStarter.java:163"
        },
        {
          "method": "sun.reflect.NativeMethodAccessorImpl.invoke0",
          "source": "Native Method"
        },
        {
          "method": "sun.reflect.NativeMethodAccessorImpl.invoke",
          "source": "NativeMethodAccessorImpl.java:39"
        },
        {
          "method": "sun.reflect.DelegatingMethodAccessorImpl.invoke",
          "source": "DelegatingMethodAccessorImpl.java:25"
        },
        {
          "method": "java.lang.reflect.Method.invoke",
          "source": "Method.java:324"
        },
        {
          "method": "org.eclipse.core.launcher.Main.invokeFramework",
          "source": "Main.java:334"
        },
        {
          "method": "org.eclipse.core.launcher.Main.basicRun",
          "source": "Main.java:278"
        },
        {
          "method": "org.eclipse.core.launcher.Main.run",
          "source": "Main.java:973"
        },
        {
          "method": "org.eclipse.core.launcher.Main.main",
          "source": "Main.java:948"
        }
      ],
      "number": 0,
      "commentIndex": 0,
      "bugId": "140981",
      "date": "2006-05-10T07:43:50+02:00",
      "product": "Platform",
      "component": "Runtime",
      "severity": "blocker"
    }
  ],
  "groupId": "140981",
  "bugId": "140981",
  "date": "2006-05-10T07:43:50+02:00",
  "product": "Platform",
  "component": "Runtime",
  "severity": "blocker"
}