{
  "comments": [
    "When running EMF generation using the new adapter framework gives the following error when running standalone in maven environment:\n\njava.lang.NoClassDefFoundError: org.eclipse.jdt.core.formatter.CodeFormatter\n        at java.lang.J9VMInternals.verifyImpl(Native Method)\n        at java.lang.J9VMInternals.verify(J9VMInternals.java:42)\n        at java.lang.J9VMInternals.verify(J9VMInternals.java:40)\n        at java.lang.J9VMInternals.verify(J9VMInternals.java:40)\n        at java.lang.J9VMInternals.initialize(J9VMInternals.java:111)\n        at org.eclipse.emf.codegen.ecore.genmodel.generator.GenModelGeneratorAda\npterFactory.createGenModelAdapter(GenModelGeneratorAdapterFactory.java:73)\n        at org.eclipse.emf.codegen.ecore.genmodel.util.GenModelAdapterFactory$1.\ncaseGenModel(GenModelAdapterFactory.java:92)\n        at org.eclipse.emf.codegen.ecore.genmodel.util.GenModelSwitch.doSwitch(G\nenModelSwitch.java:112)\n        at org.eclipse.emf.codegen.ecore.genmodel.util.GenModelSwitch.doSwitch(G\nenModelSwitch.java:86)\n        at org.eclipse.emf.codegen.ecore.genmodel.util.GenModelSwitch.doSwitch(G\nenModelSwitch.java:72)\n        at org.eclipse.emf.codegen.ecore.genmodel.util.GenModelAdapterFactory.cr\neateAdapter(GenModelAdapterFactory.java:158)\n        at org.eclipse.emf.common.notify.impl.AdapterFactoryImpl.createAdapter(A\ndapterFactoryImpl.java:138)\n        at org.eclipse.emf.common.notify.impl.AdapterFactoryImpl.adaptNew(Adapte\nrFactoryImpl.java:112)\n        at org.eclipse.emf.common.notify.impl.AdapterFactoryImpl.adapt(AdapterFa\nctoryImpl.java:98)\n        at org.eclipse.emf.codegen.ecore.genmodel.generator.GenModelGeneratorAda\npterFactory.adapt(GenModelGeneratorAdapterFactory.java:66)\n        at org.eclipse.emf.common.notify.impl.AdapterFactoryImpl.adapt(AdapterFa\nctoryImpl.java:64)\n        at org.eclipse.emf.codegen.ecore.generator.Generator.getAdapters(Generat\nor.java:188)\n        at org.eclipse.emf.codegen.ecore.generator.Generator.getGeneratorData(Ge\nnerator.java:224)\n        at org.eclipse.emf.codegen.ecore.generator.Generator.generate(Generator.\njava:278)\n        at org.eclipse.emf.codegen.ecore.generator.Generator.generate(Generator.\njava:265)",
    "The fix is in CVS.\n\nI was unable to reproduce this problem running standalone; however, Kapil has tested the fix under maven.",
    "Fixed in EMF 2.2.0.I200605110000"
  ],
  "commentCreationDates": [
    "2006-05-10T20:04:23+02:00",
    "2006-05-10T20:43:48+02:00",
    "2006-05-11T18:40:18+02:00"
  ],
  "traces": [
    {
      "exceptionType": "java.lang.NoClassDefFoundError",
      "message": "org.eclipse.jdt.core.formatter.CodeFormatter",
      "elements": [
        {
          "method": "java.lang.J9VMInternals.verifyImpl",
          "source": "Native Method"
        },
        {
          "method": "java.lang.J9VMInternals.verify",
          "source": "J9VMInternals.java:42"
        },
        {
          "method": "java.lang.J9VMInternals.verify",
          "source": "J9VMInternals.java:40"
        },
        {
          "method": "java.lang.J9VMInternals.verify",
          "source": "J9VMInternals.java:40"
        },
        {
          "method": "java.lang.J9VMInternals.initialize",
          "source": "J9VMInternals.java:111"
        },
        {
          "method": "org.eclipse.emf.codegen.ecore.genmodel.generator.GenModelGeneratorAdapterFactory.createGenModelAdapter",
          "source": "GenModelGeneratorAdapterFactory.java:73"
        },
        {
          "method": "org.eclipse.emf.codegen.ecore.genmodel.util.GenModelAdapterFactory$1.caseGenModel",
          "source": "GenModelAdapterFactory.java:92"
        },
        {
          "method": "org.eclipse.emf.codegen.ecore.genmodel.util.GenModelSwitch.doSwitch",
          "source": "G enModelSwitch.java:112"
        },
        {
          "method": "org.eclipse.emf.codegen.ecore.genmodel.util.GenModelSwitch.doSwitch",
          "source": "G enModelSwitch.java:86"
        },
        {
          "method": "org.eclipse.emf.codegen.ecore.genmodel.util.GenModelSwitch.doSwitch",
          "source": "G enModelSwitch.java:72"
        },
        {
          "method": "org.eclipse.emf.codegen.ecore.genmodel.util.GenModelAdapterFactory.createAdapter",
          "source": "GenModelAdapterFactory.java:158"
        },
        {
          "method": "org.eclipse.emf.common.notify.impl.AdapterFactoryImpl.createAdapter",
          "source": "A dapterFactoryImpl.java:138"
        },
        {
          "method": "org.eclipse.emf.common.notify.impl.AdapterFactoryImpl.adaptNew",
          "source": "Adapte rFactoryImpl.java:112"
        },
        {
          "method": "org.eclipse.emf.common.notify.impl.AdapterFactoryImpl.adapt",
          "source": "AdapterFa ctoryImpl.java:98"
        },
        {
          "method": "org.eclipse.emf.codegen.ecore.genmodel.generator.GenModelGeneratorAdapterFactory.adapt",
          "source": "GenModelGeneratorAdapterFactory.java:66"
        },
        {
          "method": "org.eclipse.emf.common.notify.impl.AdapterFactoryImpl.adapt",
          "source": "AdapterFa ctoryImpl.java:64"
        },
        {
          "method": "org.eclipse.emf.codegen.ecore.generator.Generator.getAdapters",
          "source": "Generat or.java:188"
        },
        {
          "method": "org.eclipse.emf.codegen.ecore.generator.Generator.getGeneratorData",
          "source": "Ge nerator.java:224"
        },
        {
          "method": "org.eclipse.emf.codegen.ecore.generator.Generator.generate",
          "source": "Generator. java:278"
        },
        {
          "method": "org.eclipse.emf.codegen.ecore.generator.Generator.generate",
          "source": "Generator. java:265"
        }
      ],
      "number": 0,
      "commentIndex": 0,
      "bugId": "141108",
      "date": "2006-05-10T20:04:23+02:00",
      "product": "EMF",
      "component": "Tools",
      "severity": "major"
    }
  ],
  "groupId": "141108",
  "bugId": "141108",
  "date": "2006-05-10T20:04:23+02:00",
  "product": "EMF",
  "component": "Tools",
  "severity": "major"
}