{
  "comments": [
    "From bug 128972:\n\nI am having trouble again in this setting using RC4. See output below. Hope you\ncan help!!! Thanks!!!\n\n(runtime workbench is started with JDK 1.4.2)\n\n!ENTRY org.eclipse.osgi 2006-05-15 13:40:12.929\n!MESSAGE Error installing bundle:\nreference:file:../../eclipse32/plugins/org.eclipse.jdt.junit.runtime_3.2.0.v20060512-1326/\n!STACK 0\norg.osgi.framework.BundleException: No match is available for the required\nexecution environment: J2SE-1.3\n        at\norg.eclipse.osgi.framework.internal.core.Framework.verifyExecutionEnvironment(Framework.java:605)\n        at\norg.eclipse.osgi.framework.internal.core.Framework.createAndVerifyBundle(Framework.java:560)\n        at\norg.eclipse.osgi.framework.internal.core.Framework.installWorkerPrivileged(Framework.java:822)\n        at\norg.eclipse.osgi.framework.internal.core.Framework$2.run(Framework.java:737)\n        at java.security.AccessController.doPrivileged(Native Method)\n        at\norg.eclipse.osgi.framework.internal.core.Framework.installWorker(Framework.java:788)\n        at\norg.eclipse.osgi.framework.internal.core.Framework.installBundle(Framework.java:732)\n        at\norg.eclipse.osgi.framework.internal.core.BundleContextImpl.installBundle(BundleContextImpl.java:221)\n        at\norg.eclipse.core.runtime.adaptor.EclipseStarter.installBundles(EclipseStarter.java:956)\n        at\norg.eclipse.core.runtime.adaptor.EclipseStarter.loadBasicBundles(EclipseStarter.java:543)\n        at\norg.eclipse.core.runtime.adaptor.EclipseStarter.startup(EclipseStarter.java:288)\n        at\norg.eclipse.core.runtime.adaptor.EclipseStarter.run(EclipseStarter.java:159)\n        at sun.reflect.NativeMethodAccessorImpl.invoke0(Native Method)\n        at\nsun.reflect.NativeMethodAccessorImpl.invoke(NativeMethodAccessorImpl.java:39)\n        at\nsun.reflect.DelegatingMethodAccessorImpl.invoke(DelegatingMethodAccessorImpl.java:25)\n        at java.lang.reflect.Method.invoke(Method.java:324)\n        at org.eclipse.core.launcher.Main.invokeFramework(Main.java:336)\n        at org.eclipse.core.launcher.Main.basicRun(Main.java:280)\n        at org.eclipse.core.launcher.Main.run(Main.java:977)\n        at org.eclipse.core.launcher.Main.main(Main.java:952)",
    "Martin, \nwhat exactly is your target composed of?",
    "Eclipse 3.1 did not set the org.osgi.framework.executionenvironment correctly.  To work around the issue you should set the property yourself.  For example, on J2SE-1.5 you would use the following property.\n\norg.osgi.framework.executionenvironment\u003dOSGi/Minimum-1.0,OSGi/Minimum-1.1,JRE-1.1,J2SE-1.2,J2SE-1.3,J2SE-1.4,J2SE-1.5\n\nEclipse 3.2 sets the property correctly for the various JRE levels.",
    "Tom, so the stack in comment 0 indicates that org.eclipse.osgi 3.1.x is being used here?",
    "My development environment is 3.2RC4, my target environment contains osgi and core.runtime of 3.1 as well as several self-implemented plugins.\n\nWorked some milestones back in time (maybe RC1 \u0026 RC2, definitely M6).\n",
    "Then Tom\u0027s theory in comment 2 is correct.\n\nThe problem surfaced because JDT (and all other plug-ins in the sdk) have specified their EE in the late RC* cycles.\n\nMoving to Equinox as the problem is in osgi 3.1\n\nWhat\u0027s the solution here?  Should we remove the EE from jdt.junit.runtime, pde.junit.runtime and org.junit?  or is the workaround sufficient?\n\nNote that the problem only occurs when you are running Plugin JUnit tests in pre-3.2 targets not containing the three plugins listed above.",
    "A solution cannot involve removing the EE headers.  I think the work around should be sufficient.  If so I would like to close as WONTFIX.",
    "The work around is completely sufficient for me. So would be okay for me to close as WONTFIX.",
    "Closing."
  ],
  "commentCreationDates": [
    "2006-05-15T14:23:03+02:00",
    "2006-05-15T14:26:06+02:00",
    "2006-05-15T14:59:21+02:00",
    "2006-05-15T15:03:16+02:00",
    "2006-05-15T15:14:31+02:00",
    "2006-05-15T15:20:39+02:00",
    "2006-05-24T23:23:48+02:00",
    "2006-05-25T11:11:37+02:00",
    "2006-05-25T14:43:50+02:00"
  ],
  "traces": [
    {
      "exceptionType": "org.osgi.framework.BundleException",
      "message": "No match is available for the required execution environment: J2SE-1.3",
      "elements": [
        {
          "method": "org.eclipse.osgi.framework.internal.core.Framework.verifyExecutionEnvironment",
          "source": "Framework.java:605"
        },
        {
          "method": "org.eclipse.osgi.framework.internal.core.Framework.createAndVerifyBundle",
          "source": "Framework.java:560"
        },
        {
          "method": "org.eclipse.osgi.framework.internal.core.Framework.installWorkerPrivileged",
          "source": "Framework.java:822"
        },
        {
          "method": "org.eclipse.osgi.framework.internal.core.Framework$2.run",
          "source": "Framework.java:737"
        },
        {
          "method": "java.security.AccessController.doPrivileged",
          "source": "Native Method"
        },
        {
          "method": "org.eclipse.osgi.framework.internal.core.Framework.installWorker",
          "source": "Framework.java:788"
        },
        {
          "method": "org.eclipse.osgi.framework.internal.core.Framework.installBundle",
          "source": "Framework.java:732"
        },
        {
          "method": "org.eclipse.osgi.framework.internal.core.BundleContextImpl.installBundle",
          "source": "BundleContextImpl.java:221"
        },
        {
          "method": "org.eclipse.core.runtime.adaptor.EclipseStarter.installBundles",
          "source": "EclipseStarter.java:956"
        },
        {
          "method": "org.eclipse.core.runtime.adaptor.EclipseStarter.loadBasicBundles",
          "source": "EclipseStarter.java:543"
        },
        {
          "method": "org.eclipse.core.runtime.adaptor.EclipseStarter.startup",
          "source": "EclipseStarter.java:288"
        },
        {
          "method": "org.eclipse.core.runtime.adaptor.EclipseStarter.run",
          "source": "EclipseStarter.java:159"
        },
        {
          "method": "sun.reflect.NativeMethodAccessorImpl.invoke0",
          "source": "Native Method"
        },
        {
          "method": "sun.reflect.NativeMethodAccessorImpl.invoke",
          "source": "NativeMethodAccessorImpl.java:39"
        },
        {
          "method": "sun.reflect.DelegatingMethodAccessorImpl.invoke",
          "source": "DelegatingMethodAccessorImpl.java:25"
        },
        {
          "method": "java.lang.reflect.Method.invoke",
          "source": "Method.java:324"
        },
        {
          "method": "org.eclipse.core.launcher.Main.invokeFramework",
          "source": "Main.java:336"
        },
        {
          "method": "org.eclipse.core.launcher.Main.basicRun",
          "source": "Main.java:280"
        },
        {
          "method": "org.eclipse.core.launcher.Main.run",
          "source": "Main.java:977"
        },
        {
          "method": "org.eclipse.core.launcher.Main.main",
          "source": "Main.java:952"
        }
      ],
      "number": 0,
      "commentIndex": 0,
      "bugId": "141744",
      "date": "2006-05-15T14:23:03+02:00",
      "product": "Equinox",
      "component": "Framework",
      "severity": "normal"
    }
  ],
  "groupId": "141744",
  "bugId": "141744",
  "date": "2006-05-15T14:23:03+02:00",
  "product": "Equinox",
  "component": "Framework",
  "severity": "normal"
}