{
  "comments": [
    "After adding a chart \n\n\njava.lang.ClassCastException\n        at org.eclipse.birt.chart.reportitem.ChartReportItemQueryImpl.setModelObject(ChartReportItemQueryImpl.java:81)\n        at org.eclipse.birt.report.engine.data.dte.ReportQueryBuilder$QueryBuilderVisitor.visitExtendedItem(ReportQueryBuilder.java:337)\n        at org.eclipse.birt.report.engine.ir.ExtendedItemDesign.accept(ExtendedItemDesign.java:30)\n        at org.eclipse.birt.report.engine.data.dte.ReportQueryBuilder$QueryBuilderVisitor.buildQuery(ReportQueryBuilder.java:193)\n        at org.eclipse.birt.report.engine.data.dte.ReportQueryBuilder.build(ReportQueryBuilder.java:114)\n        at org.eclipse.birt.report.engine.data.dte.DteDataEngine.prepare(DteDataEngine.java:162)\n        at org.eclipse.birt.report.engine.executor.ReportExecutor.execute(ReportExecutor.java:107)\n        at org.eclipse.birt.report.engine.executor.ReportExecutor.execute(ReportExecutor.java:89)\n        at org.eclipse.birt.report.engine.api.impl.RunAndRenderTask.run(RunAndRenderTask.java:175)\n        at org.eclipse.birt.report.services.ReportEngineService.runAndRenderReport(Unknown Source)\n        at org.eclipse.birt.report.viewer.aggregation.layout.EngineFragment.doService(Unknown Source)\n        at org.eclipse.birt.report.viewer.aggregation.BaseFragment.service(Unknown Source)\n        at org.eclipse.birt.report.viewer.servlet.ViewerServlet.doGet(Unknown Source)\n        at javax.servlet.http.HttpServlet.service(HttpServlet.java:689)\n        at org.apache.axis.transport.http.AxisServletBase.service(AxisServletBase.java:327)\n        at javax.servlet.http.HttpServlet.service(HttpServlet.java:802)\n        at org.apache.catalina.core.ApplicationFilterChain.internalDoFilter(ApplicationFilterChain.java:252)\n        at org.apache.catalina.core.ApplicationFilterChain.doFilter(ApplicationFilterChain.java:173)\n        at org.apache.catalina.core.StandardWrapperValve.invoke(StandardWrapperValve.java:213)\n        at org.apache.catalina.core.StandardContextValve.invoke(StandardContextValve.java:178)\n        at org.apache.catalina.core.StandardHostValve.invoke(StandardHostValve.java:126)\n        at org.apache.catalina.valves.ErrorReportValve.invoke(ErrorReportValve.java:105)\n        at org.apache.catalina.core.StandardEngineValve.invoke(StandardEngineValve.java:107)\n        at org.apache.catalina.connector.CoyoteAdapter.service(CoyoteAdapter.java:148)\n        at org.apache.coyote.http11.Http11Processor.process(Http11Processor.java:868)\n        at org.apache.coyote.http11.Http11BaseProtocol$Http11ConnectionHandler.processConnection(Http11BaseProtocol.java:663)\n        at org.apache.tomcat.util.net.PoolTcpEndpoint.processSocket(PoolTcpEndpoint.java:527)\n        at org.apache.tomcat.util.net.LeaderFollowerWorkerThread.runIt(LeaderFollowerWorkerThread.java:80)\n        at org.apache.tomcat.util.threads.ThreadPool$ControlRunnable.run(ThreadPool.java:684)\n        at java.lang.Thread.run(Thread.java:534)",
    "Please provide more details about your environment, and the report you use and \nwhen this exception happens.",
    "This is running on freebsd. The error occurs when I try to view the report via the run command using the browser. If the report doenst contain the chart, it shows up fine. \n\nSomeone on IRC mentioned that it is a conversion problem. All numbers are rounded using round() in the mysql query.",
    "I have to add that the report shows perfectly in preview as html or pdf in the designer.",
    "What version are you using, did you try with RC2?\n\nWhen you say the run command in the browser, is it the browser you launch from \neclipse (or the url from the browser launched inside eclipse). Is it your own \nweb server?",
    "We are running the latest stable version. Its a url within a regular browser. We have tried it with the latest release, and even the nightly build.",
    "Could you confirm your birt version? Actually the ChartReportItemQueryImpl is no longer used since build N20060429.",
    "We didnt copy the charting and reporting engine along with the newest birt.\nSorry. Good catch with that last comment."
  ],
  "commentCreationDates": [
    "2006-05-16T08:13:56+02:00",
    "2006-05-16T11:09:56+02:00",
    "2006-05-16T17:07:35+02:00",
    "2006-05-16T17:15:39+02:00",
    "2006-05-17T10:00:50+02:00",
    "2006-05-17T17:18:19+02:00",
    "2006-05-18T04:41:17+02:00",
    "2006-05-18T08:34:06+02:00"
  ],
  "traces": [
    {
      "exceptionType": "java.lang.ClassCastException",
      "elements": [
        {
          "method": "org.eclipse.birt.chart.reportitem.ChartReportItemQueryImpl.setModelObject",
          "source": "ChartReportItemQueryImpl.java:81"
        },
        {
          "method": "org.eclipse.birt.report.engine.data.dte.ReportQueryBuilder$QueryBuilderVisitor.visitExtendedItem",
          "source": "ReportQueryBuilder.java:337"
        },
        {
          "method": "org.eclipse.birt.report.engine.ir.ExtendedItemDesign.accept",
          "source": "ExtendedItemDesign.java:30"
        },
        {
          "method": "org.eclipse.birt.report.engine.data.dte.ReportQueryBuilder$QueryBuilderVisitor.buildQuery",
          "source": "ReportQueryBuilder.java:193"
        },
        {
          "method": "org.eclipse.birt.report.engine.data.dte.ReportQueryBuilder.build",
          "source": "ReportQueryBuilder.java:114"
        },
        {
          "method": "org.eclipse.birt.report.engine.data.dte.DteDataEngine.prepare",
          "source": "DteDataEngine.java:162"
        },
        {
          "method": "org.eclipse.birt.report.engine.executor.ReportExecutor.execute",
          "source": "ReportExecutor.java:107"
        },
        {
          "method": "org.eclipse.birt.report.engine.executor.ReportExecutor.execute",
          "source": "ReportExecutor.java:89"
        },
        {
          "method": "org.eclipse.birt.report.engine.api.impl.RunAndRenderTask.run",
          "source": "RunAndRenderTask.java:175"
        },
        {
          "method": "org.eclipse.birt.report.services.ReportEngineService.runAndRenderReport",
          "source": "Unknown Source"
        },
        {
          "method": "org.eclipse.birt.report.viewer.aggregation.layout.EngineFragment.doService",
          "source": "Unknown Source"
        },
        {
          "method": "org.eclipse.birt.report.viewer.aggregation.BaseFragment.service",
          "source": "Unknown Source"
        },
        {
          "method": "org.eclipse.birt.report.viewer.servlet.ViewerServlet.doGet",
          "source": "Unknown Source"
        },
        {
          "method": "javax.servlet.http.HttpServlet.service",
          "source": "HttpServlet.java:689"
        },
        {
          "method": "org.apache.axis.transport.http.AxisServletBase.service",
          "source": "AxisServletBase.java:327"
        },
        {
          "method": "javax.servlet.http.HttpServlet.service",
          "source": "HttpServlet.java:802"
        },
        {
          "method": "org.apache.catalina.core.ApplicationFilterChain.internalDoFilter",
          "source": "ApplicationFilterChain.java:252"
        },
        {
          "method": "org.apache.catalina.core.ApplicationFilterChain.doFilter",
          "source": "ApplicationFilterChain.java:173"
        },
        {
          "method": "org.apache.catalina.core.StandardWrapperValve.invoke",
          "source": "StandardWrapperValve.java:213"
        },
        {
          "method": "org.apache.catalina.core.StandardContextValve.invoke",
          "source": "StandardContextValve.java:178"
        },
        {
          "method": "org.apache.catalina.core.StandardHostValve.invoke",
          "source": "StandardHostValve.java:126"
        },
        {
          "method": "org.apache.catalina.valves.ErrorReportValve.invoke",
          "source": "ErrorReportValve.java:105"
        },
        {
          "method": "org.apache.catalina.core.StandardEngineValve.invoke",
          "source": "StandardEngineValve.java:107"
        },
        {
          "method": "org.apache.catalina.connector.CoyoteAdapter.service",
          "source": "CoyoteAdapter.java:148"
        },
        {
          "method": "org.apache.coyote.http11.Http11Processor.process",
          "source": "Http11Processor.java:868"
        },
        {
          "method": "org.apache.coyote.http11.Http11BaseProtocol$Http11ConnectionHandler.processConnection",
          "source": "Http11BaseProtocol.java:663"
        },
        {
          "method": "org.apache.tomcat.util.net.PoolTcpEndpoint.processSocket",
          "source": "PoolTcpEndpoint.java:527"
        },
        {
          "method": "org.apache.tomcat.util.net.LeaderFollowerWorkerThread.runIt",
          "source": "LeaderFollowerWorkerThread.java:80"
        },
        {
          "method": "org.apache.tomcat.util.threads.ThreadPool$ControlRunnable.run",
          "source": "ThreadPool.java:684"
        },
        {
          "method": "java.lang.Thread.run",
          "source": "Thread.java:534"
        }
      ],
      "number": 0,
      "commentIndex": 0,
      "bugId": "141932",
      "date": "2006-05-16T08:13:56+02:00",
      "product": "BIRT",
      "component": "Chart",
      "severity": "normal"
    }
  ],
  "groupId": "141932",
  "bugId": "141932",
  "date": "2006-05-16T08:13:56+02:00",
  "product": "BIRT",
  "component": "Chart",
  "severity": "normal"
}