{
  "comments": [
    "After I\u0027m done with an OleControlSite, I setParent() to a \"non visisble holding composite\", and then I dispose() its parent, which is an OleFrame.  The next time I need an OleControlSite, I take a previous one, create a new OleFrame, and then set the parent to the new OleFrame.  That works on the UI.. until a focusIn event is received by OleControlSite.  COMObject seems to look up the old (original) OleFrame and sends it setMenu().  That results in the \"widget is disposed\" error.   In case you\u0027re wondering why I\u0027m attemting to re-use OleControlSites, it\u0027s because we instantiate and dispose tons of them in our app, and there is a very significant handle / memory leak because of that.\n\nStack Trace:\norg.eclipse.swt.SWTException: Widget is disposed\n\tat org.eclipse.swt.SWT.error(SWT.java:3374)\n\tat org.eclipse.swt.SWT.error(SWT.java:3297)\n\tat org.eclipse.swt.SWT.error(SWT.java:3268)\n\tat org.eclipse.swt.widgets.Widget.error(Widget.java:432)\n\tat org.eclipse.swt.widgets.Widget.checkWidget(Widget.java:327)\n\tat org.eclipse.swt.widgets.Control.getShell(Control.java:1101)\n\tat org.eclipse.swt.ole.win32.OleFrame.SetMenu(OleFrame.java:695)\n\tat org.eclipse.swt.ole.win32.OleFrame.access$9(OleFrame.java:690)\n\tat org.eclipse.swt.ole.win32.OleFrame$5.method10(OleFrame.java:300)\n\tat org.eclipse.swt.internal.ole.win32.COMObject.callback10(COMObject.java:153)\n\tat org.eclipse.swt.internal.win32.OS.DispatchMessageW(Native Method)\n\tat org.eclipse.swt.internal.win32.OS.DispatchMessage(OS.java:1922)\n\tat org.eclipse.swt.widgets.Display.readAndDispatch(Display.java:2966)\n\tat ReParentOleBrowser.run(ReParentOleBrowser.java:175)\n\tat ReParentOleBrowser.main(ReParentOleBrowser.java:50)\n\nI have a sample program if you need it.\n\nI\u0027m using the latest SWT I could find..  swt-win32-3230.dll with a corresponding swt.jar file.",
    "same as Bug 142582 ?\nI closing this as invalid okay ?"
  ],
  "commentCreationDates": [
    "2006-05-18T20:57:53+02:00",
    "2006-05-19T21:43:47+02:00"
  ],
  "traces": [
    {
      "exceptionType": "org.eclipse.swt.SWTException",
      "message": "Widget is disposed",
      "elements": [
        {
          "method": "org.eclipse.swt.SWT.error",
          "source": "SWT.java:3374"
        },
        {
          "method": "org.eclipse.swt.SWT.error",
          "source": "SWT.java:3297"
        },
        {
          "method": "org.eclipse.swt.SWT.error",
          "source": "SWT.java:3268"
        },
        {
          "method": "org.eclipse.swt.widgets.Widget.error",
          "source": "Widget.java:432"
        },
        {
          "method": "org.eclipse.swt.widgets.Widget.checkWidget",
          "source": "Widget.java:327"
        },
        {
          "method": "org.eclipse.swt.widgets.Control.getShell",
          "source": "Control.java:1101"
        },
        {
          "method": "org.eclipse.swt.ole.win32.OleFrame.SetMenu",
          "source": "OleFrame.java:695"
        },
        {
          "method": "org.eclipse.swt.ole.win32.OleFrame.access$9",
          "source": "OleFrame.java:690"
        },
        {
          "method": "org.eclipse.swt.ole.win32.OleFrame$5.method10",
          "source": "OleFrame.java:300"
        },
        {
          "method": "org.eclipse.swt.internal.ole.win32.COMObject.callback10",
          "source": "COMObject.java:153"
        },
        {
          "method": "org.eclipse.swt.internal.win32.OS.DispatchMessageW",
          "source": "Native Method"
        },
        {
          "method": "org.eclipse.swt.internal.win32.OS.DispatchMessage",
          "source": "OS.java:1922"
        },
        {
          "method": "org.eclipse.swt.widgets.Display.readAndDispatch",
          "source": "Display.java:2966"
        },
        {
          "method": "ReParentOleBrowser.run",
          "source": "ReParentOleBrowser.java:175"
        },
        {
          "method": "ReParentOleBrowser.main",
          "source": "ReParentOleBrowser.java:50"
        }
      ],
      "number": 0,
      "commentIndex": 0,
      "bugId": "142578",
      "date": "2006-05-18T20:57:53+02:00",
      "product": "Platform",
      "component": "SWT",
      "severity": "normal"
    }
  ],
  "groupId": "142578",
  "bugId": "142578",
  "date": "2006-05-18T20:57:53+02:00",
  "product": "Platform",
  "component": "SWT",
  "severity": "normal"
}