{
  "comments": [
    "build 2002-04-18 on WinXP.\n\nI got a bunch of these in my log when stepping over a method call. I had been \ndebugging, had hit my breakpoint and went \"into\" a couple of times, browsed \nsome variable values, and then hit \"over\" and got these in the log.\n\n\u003clog-entry date\u003d\"Fri Apr 19 15:36:25 EDT 2002\"\u003e\n  \u003cstatus\n     plugin-id\u003d\"org.eclipse.debug.ui\"\n     severity\u003d\"ERROR\"\n     message\u003d\"Error logged from Debug UI: \"\n     code\u003d\"120\"\u003e\n    \u003cexception\n       message\u003d\"com.sun.jdi.InternalException: Got error code in reply: 34 \noccurred while retrieving value.\"\n       trace\u003d\"\norg.eclipse.debug.core.DebugException[5010]: com.sun.jdi.InternalException: Got\nerror code in reply: 34\n        at org.eclipse.jdi.internal.MirrorImpl.defaultReplyErrorHandler\n(MirrorImpl.java(Compiled Code))\n        at org.eclipse.jdi.internal.StackFrameImpl.getValues\n(StackFrameImpl.java(Compiled Code))\n        at org.eclipse.jdi.internal.StackFrameImpl.getValue\n(StackFrameImpl.java:66)\n        at \norg.eclipse.jdt.internal.debug.core.model.JDILocalVariable.retrieveValue\n(JDILocalVariable.java:50)\n        at \norg.eclipse.jdt.internal.debug.core.model.JDIVariable.getCurrentValue\n(JDIVariable.java:61)\n        at org.eclipse.jdt.internal.debug.core.model.JDIVariable.getValue\n(JDIVariable.java:83)\n        at \norg.eclipse.debug.internal.ui.views.VariablesViewContentProvider.hasChildren\n(VariablesViewContentProvider.java:136)\n        at org.eclipse.jface.viewers.AbstractTreeViewer.isExpandable\n(AbstractTreeViewer.java(Compiled Code))\n        at org.eclipse.jface.viewers.AbstractTreeViewer.updateChildren\n(AbstractTreeViewer.java(Compiled Code))\n        at org.eclipse.jface.viewers.AbstractTreeViewer.internalRefresh\n(AbstractTreeViewer.java(Compiled Code))\n        at org.eclipse.jface.viewers.AbstractTreeViewer.internalRefresh\n(AbstractTreeViewer.java(Compiled Code))\n        at org.eclipse.jface.viewers.AbstractTreeViewer.internalRefresh\n(AbstractTreeViewer.java:829)\n        at org.eclipse.jface.viewers.StructuredViewer$1.run\n(StructuredViewer.java:676)\n        at org.eclipse.jface.viewers.StructuredViewer.preservingSelection\n(StructuredViewer.java:616)\n        at org.eclipse.jface.viewers.StructuredViewer.refresh\n(StructuredViewer.java:674)\n        at org.eclipse.jface.viewers.StructuredViewer.refresh\n(StructuredViewer.java:636)\n        at org.eclipse.debug.internal.ui.views.VariablesViewer.refresh\n(VariablesViewer.java:62)\n        at \norg.eclipse.debug.internal.ui.views.AbstractDebugEventHandler.refresh\n(AbstractDebugEventHandler.java:115)\n        at \norg.eclipse.debug.internal.ui.views.VariablesViewEventHandler.doHandleDebugEven\nts(VariablesViewEventHandler.java:36)\n        at org.eclipse.debug.internal.ui.views.AbstractDebugEventHandler$1.run\n(AbstractDebugEventHandler.java:49)\n        at org.eclipse.swt.widgets.RunnableLock.run(RunnableLock.java(Compiled \nCode))\n        at org.eclipse.swt.widgets.Synchronizer.runAsyncMessages\n(Synchronizer.java(Compiled Code))\n        at org.eclipse.swt.widgets.Display.runAsyncMessages(Display.java\n(Compiled Code))\n        at org.eclipse.swt.widgets.Display.readAndDispatch(Display.java\n(Compiled Code))\n        at org.eclipse.ui.internal.Workbench.runEventLoop(Workbench.java\n(Compiled Code))\n        at org.eclipse.ui.internal.Workbench.run(Workbench.java:816)\n        at org.eclipse.core.internal.boot.InternalBootLoader.run\n(InternalBootLoader.java:643)\n        at org.eclipse.core.boot.BootLoader.run(BootLoader.java:349)\n        at java.lang.reflect.Method.invoke(Native Method)\n        at org.eclipse.core.launcher.Main.basicRun(Main.java:195)\n        at org.eclipse.core.launcher.Main.run(Main.java:541)\n        at org.eclipse.core.launcher.UIMain.main(UIMain.java:52)\n\"\u003e\n    \u003c/exception\u003e\n  \u003c/status\u003e\n\u003c/log-entry\u003e",
    "Yikes. JDWP error code 34 states \"The variable is not an appropriate type for \nthe function used.\" But looking at the java doc, it is not clear how this can \nhappen. Leaving open for now - \"hoping\" for a reproduceable test case.",
    "This seems to happen every time in my current workspace (I have shutdown and \ncome back in again). Will zip up workspace and send instruction and more \ndetail.",
    "I was able to reproduce the problem. It appears to be a VM bug, as the problem \noccurrs with IBM1.3.0 but not Sun\u0027s 1.3.1_01 VM. We are attepmting to retrieve \nthe value of the local \"e\" which is the IOException caught when \nclosing \"input\". It works in the first try/catch/finally block, and then causes \na problem in the second try/catch/finally block. However, there are no bad side \neffects other than the variable displays as \"\u003cnot responding\u003e\" in the UI. We \nsimply catch the exception (log it) and keep going. The debugger recovers OK.\n\nDo not intend to fix, but we should report the bug to IBM."
  ],
  "commentCreationDates": [
    "2002-04-19T21:29:04+02:00",
    "2002-04-19T22:09:09+02:00",
    "2002-04-19T22:45:32+02:00",
    "2002-04-20T16:30:02+02:00"
  ],
  "traces": [
    {
      "exceptionType": "com.sun.jdi.InternalException",
      "message": "Got error code in reply: 34",
      "elements": [
        {
          "method": "org.eclipse.jdi.internal.MirrorImpl.defaultReplyErrorHandler",
          "source": "MirrorImpl.java(Compiled Code)"
        },
        {
          "method": "org.eclipse.jdi.internal.StackFrameImpl.getValues",
          "source": "StackFrameImpl.java(Compiled Code)"
        },
        {
          "method": "org.eclipse.jdi.internal.StackFrameImpl.getValue",
          "source": "StackFrameImpl.java:66"
        },
        {
          "method": "org.eclipse.jdt.internal.debug.core.model.JDILocalVariable.retrieveValue",
          "source": "JDILocalVariable.java:50"
        },
        {
          "method": "org.eclipse.jdt.internal.debug.core.model.JDIVariable.getCurrentValue",
          "source": "JDIVariable.java:61"
        },
        {
          "method": "org.eclipse.jdt.internal.debug.core.model.JDIVariable.getValue",
          "source": "JDIVariable.java:83"
        },
        {
          "method": "org.eclipse.debug.internal.ui.views.VariablesViewContentProvider.hasChildren",
          "source": "VariablesViewContentProvider.java:136"
        },
        {
          "method": "org.eclipse.jface.viewers.AbstractTreeViewer.isExpandable",
          "source": "AbstractTreeViewer.java(Compiled Code)"
        },
        {
          "method": "org.eclipse.jface.viewers.AbstractTreeViewer.updateChildren",
          "source": "AbstractTreeViewer.java(Compiled Code)"
        },
        {
          "method": "org.eclipse.jface.viewers.AbstractTreeViewer.internalRefresh",
          "source": "AbstractTreeViewer.java(Compiled Code)"
        },
        {
          "method": "org.eclipse.jface.viewers.AbstractTreeViewer.internalRefresh",
          "source": "AbstractTreeViewer.java(Compiled Code)"
        },
        {
          "method": "org.eclipse.jface.viewers.AbstractTreeViewer.internalRefresh",
          "source": "AbstractTreeViewer.java:829"
        },
        {
          "method": "org.eclipse.jface.viewers.StructuredViewer$1.run",
          "source": "StructuredViewer.java:676"
        },
        {
          "method": "org.eclipse.jface.viewers.StructuredViewer.preservingSelection",
          "source": "StructuredViewer.java:616"
        },
        {
          "method": "org.eclipse.jface.viewers.StructuredViewer.refresh",
          "source": "StructuredViewer.java:674"
        },
        {
          "method": "org.eclipse.jface.viewers.StructuredViewer.refresh",
          "source": "StructuredViewer.java:636"
        },
        {
          "method": "org.eclipse.debug.internal.ui.views.VariablesViewer.refresh",
          "source": "VariablesViewer.java:62"
        },
        {
          "method": "org.eclipse.debug.internal.ui.views.AbstractDebugEventHandler.refresh",
          "source": "AbstractDebugEventHandler.java:115"
        },
        {
          "method": "org.eclipse.debug.internal.ui.views.VariablesViewEventHandler.doHandleDebugEvents",
          "source": "VariablesViewEventHandler.java:36"
        },
        {
          "method": "org.eclipse.debug.internal.ui.views.AbstractDebugEventHandler$1.run",
          "source": "AbstractDebugEventHandler.java:49"
        },
        {
          "method": "org.eclipse.swt.widgets.RunnableLock.run",
          "source": "RunnableLock.java(Compiled  Code)"
        },
        {
          "method": "org.eclipse.swt.widgets.Synchronizer.runAsyncMessages",
          "source": "Synchronizer.java(Compiled Code)"
        },
        {
          "method": "org.eclipse.swt.widgets.Display.runAsyncMessages",
          "source": "Display.java (Compiled Code)"
        },
        {
          "method": "org.eclipse.swt.widgets.Display.readAndDispatch",
          "source": "Display.java (Compiled Code)"
        },
        {
          "method": "org.eclipse.ui.internal.Workbench.runEventLoop",
          "source": "Workbench.java (Compiled Code)"
        },
        {
          "method": "org.eclipse.ui.internal.Workbench.run",
          "source": "Workbench.java:816"
        },
        {
          "method": "org.eclipse.core.internal.boot.InternalBootLoader.run",
          "source": "InternalBootLoader.java:643"
        },
        {
          "method": "org.eclipse.core.boot.BootLoader.run",
          "source": "BootLoader.java:349"
        },
        {
          "method": "java.lang.reflect.Method.invoke",
          "source": "Native Method"
        },
        {
          "method": "org.eclipse.core.launcher.Main.basicRun",
          "source": "Main.java:195"
        },
        {
          "method": "org.eclipse.core.launcher.Main.run",
          "source": "Main.java:541"
        },
        {
          "method": "org.eclipse.core.launcher.UIMain.main",
          "source": "UIMain.java:52"
        }
      ],
      "number": 0,
      "commentIndex": 0,
      "bugId": "14259",
      "date": "2002-04-19T21:29:04+02:00",
      "product": "JDT",
      "component": "Debug",
      "severity": "normal"
    }
  ],
  "groupId": "14259",
  "bugId": "14259",
  "date": "2002-04-19T21:29:04+02:00",
  "product": "JDT",
  "component": "Debug",
  "severity": "normal"
}