{
  "comments": [
    "java.lang.ArrayIndexOutOfBoundsException: 1                                                                                      \n        at org.eclipse.update.internal.provisional.SiteOptimizerApplication.getFeatureListFromSiteXML(SiteOptimizerApplication.ja\n        at org.eclipse.update.internal.provisional.SiteOptimizerApplication.getFeatureList(SiteOptimizerApplication.java:380)    \n        at org.eclipse.update.internal.provisional.SiteOptimizerApplication.runDigestBuilder(SiteOptimizerApplication.java:188)  \n        at org.eclipse.update.internal.provisional.SiteOptimizerApplication.run(SiteOptimizerApplication.java:472)               \n        at org.eclipse.core.internal.runtime.PlatformActivator$1.run(PlatformActivator.java:78)                                  \n        at org.eclipse.core.runtime.internal.adaptor.EclipseAppLauncher.runApplication(EclipseAppLauncher.java:92)               \n        at org.eclipse.core.runtime.internal.adaptor.EclipseAppLauncher.start(EclipseAppLauncher.java:68)                        \n        at org.eclipse.core.runtime.adaptor.EclipseStarter.run(EclipseStarter.java:400)                                          \n        at org.eclipse.core.runtime.adaptor.EclipseStarter.run(EclipseStarter.java:177)                                          \n        at sun.reflect.NativeMethodAccessorImpl.invoke0(Native Method)                                                           \n        at sun.reflect.NativeMethodAccessorImpl.invoke(NativeMethodAccessorImpl.java:39)                                         \n        at sun.reflect.DelegatingMethodAccessorImpl.invoke(DelegatingMethodAccessorImpl.java:25)                                 \n        at java.lang.reflect.Method.invoke(Method.java:585)                                                                      \n        at org.eclipse.core.launcher.Main.invokeFramework(Main.java:336)                                                         \n        at org.eclipse.core.launcher.Main.basicRun(Main.java:280)                                                                \n        at org.eclipse.core.launcher.Main.run(Main.java:977)                                                                     \n        at org.eclipse.core.launcher.Main.main(Main.java:952)",
    "site.xml:\n\n\u003c?xml version\u003d\"1.0\" encoding\u003d\"UTF-8\"?\u003e\n\u003c?xml-stylesheet type\u003d\"text/xsl\" href\u003d\"web/site.xsl\"?\u003e\n\u003csite mirrorsURL\u003d\"http://www.eclipse.org/downloads/download.php?file\u003d/technology/gmf/update-site/milestone/site.xml\u0026amp;format\u003dxml\"\u003e\n\n\t\u003cfeature url\u003d\"features/org.apache.batik_1.6.0.v20060518-1000.jar\" patch\u003d\"false\" id\u003d\"org.apache.batik\" version\u003d\"1.6.0.v20060518-1000\"\u003e\n\t\t\u003ccategory name\u003d\"S-S20060518-200605181000\"/\u003e\n\t\u003c/feature\u003e\n\n\t\u003ccategory-def label\u003d\"Graphical Modeling Framework S-S20060518-200605181000\" name\u003d\"S-S20060518-200605181000\"\u003e\n\t\t\u003cdescription\u003e\nThis category contains the various features of the S-S20060518-200605181000 build of the Graphical Modeling Framework.\t\t\n\t\t\u003c/description\u003e\n\t\u003c/category-def\u003e\n\u003c/site\u003e\n",
    "Sorry the exception was truncated. The first lines look like folows:\njava.lang.ArrayIndexOutOfBoundsException: 1                                                                                                       \n        at org.eclipse.update.internal.provisional.SiteOptimizerApplication.getFeatureListFromSiteXML(SiteOptimizerApplication.java:430)          \n        at org.eclipse.update.internal.provisional.SiteOptimizerApplication.getFeatureList(SiteOptimizerApplication.java:380)                     \n        at org.eclipse.update.internal.provisional.SiteOptimizerApplication.runDigestBuilder(SiteOptimizerApplication.java:188)    \n\nThe SiteOptimizerApplication line 430 seems to be bogus.",
    "This looked like a coding error in a previous release. However, I will attach a patch to be a bit more vigilant so it will be impossible to get a ArrayIndexOutOfBoundsException.",
    "Created an attachment (id\u003d63568)\norg.eclipse.update.core.patch\n\nadds a safeguard for the AOOBE",
    "let\u0027s try to get this in M7 Dejan",
    "Done - thanks, Chris."
  ],
  "commentCreationDates": [
    "2006-05-19T13:43:13+02:00",
    "2006-05-19T13:47:27+02:00",
    "2006-05-19T13:52:47+02:00",
    "2007-04-12T03:38:08+02:00",
    "2007-04-12T03:38:53+02:00",
    "2007-04-12T03:39:10+02:00",
    "2007-04-13T00:03:27+02:00"
  ],
  "traces": [
    {
      "exceptionType": "java.lang.ArrayIndexOutOfBoundsException",
      "message": "1                                                                                               at org.eclipse.update.internal.provisional.SiteOptimizerApplication.getFeatureListFromSiteXML(SiteOptimizerApplication.ja",
      "elements": [
        {
          "method": "org.eclipse.update.internal.provisional.SiteOptimizerApplication.getFeatureList",
          "source": "SiteOptimizerApplication.java:380"
        },
        {
          "method": "org.eclipse.update.internal.provisional.SiteOptimizerApplication.runDigestBuilder",
          "source": "SiteOptimizerApplication.java:188"
        },
        {
          "method": "org.eclipse.update.internal.provisional.SiteOptimizerApplication.run",
          "source": "SiteOptimizerApplication.java:472"
        },
        {
          "method": "org.eclipse.core.internal.runtime.PlatformActivator$1.run",
          "source": "PlatformActivator.java:78"
        },
        {
          "method": "org.eclipse.core.runtime.internal.adaptor.EclipseAppLauncher.runApplication",
          "source": "EclipseAppLauncher.java:92"
        },
        {
          "method": "org.eclipse.core.runtime.internal.adaptor.EclipseAppLauncher.start",
          "source": "EclipseAppLauncher.java:68"
        },
        {
          "method": "org.eclipse.core.runtime.adaptor.EclipseStarter.run",
          "source": "EclipseStarter.java:400"
        },
        {
          "method": "org.eclipse.core.runtime.adaptor.EclipseStarter.run",
          "source": "EclipseStarter.java:177"
        },
        {
          "method": "sun.reflect.NativeMethodAccessorImpl.invoke0",
          "source": "Native Method"
        },
        {
          "method": "sun.reflect.NativeMethodAccessorImpl.invoke",
          "source": "NativeMethodAccessorImpl.java:39"
        },
        {
          "method": "sun.reflect.DelegatingMethodAccessorImpl.invoke",
          "source": "DelegatingMethodAccessorImpl.java:25"
        },
        {
          "method": "java.lang.reflect.Method.invoke",
          "source": "Method.java:585"
        },
        {
          "method": "org.eclipse.core.launcher.Main.invokeFramework",
          "source": "Main.java:336"
        },
        {
          "method": "org.eclipse.core.launcher.Main.basicRun",
          "source": "Main.java:280"
        },
        {
          "method": "org.eclipse.core.launcher.Main.run",
          "source": "Main.java:977"
        },
        {
          "method": "org.eclipse.core.launcher.Main.main",
          "source": "Main.java:952"
        }
      ],
      "number": 0,
      "commentIndex": 0,
      "bugId": "142724",
      "date": "2006-05-19T13:43:13+02:00",
      "product": "Platform",
      "component": "Update",
      "severity": "major"
    },
    {
      "exceptionType": "java.lang.ArrayIndexOutOfBoundsException",
      "message": "1",
      "elements": [
        {
          "method": "org.eclipse.update.internal.provisional.SiteOptimizerApplication.getFeatureListFromSiteXML",
          "source": "SiteOptimizerApplication.java:430"
        },
        {
          "method": "org.eclipse.update.internal.provisional.SiteOptimizerApplication.getFeatureList",
          "source": "SiteOptimizerApplication.java:380"
        },
        {
          "method": "org.eclipse.update.internal.provisional.SiteOptimizerApplication.runDigestBuilder",
          "source": "SiteOptimizerApplication.java:188"
        }
      ],
      "number": 1,
      "commentIndex": 2,
      "bugId": "142724",
      "date": "2006-05-19T13:52:47+02:00",
      "product": "Platform",
      "component": "Update",
      "severity": "major"
    }
  ],
  "groupId": "142724",
  "bugId": "142724",
  "date": "2006-05-19T13:43:13+02:00",
  "product": "Platform",
  "component": "Update",
  "severity": "major"
}