{
  "comments": [
    "Hi,\n\nI cannot start Eclipse 3.1.2 on OS X 10.4.6. When I open the .app file i get a dialog that I should check the logfile in /Users/user/Documents/workspace/.metadata/.log. I have updated to J2SE 5.0 Release 4 (Intel, but the problem did not disappear. \n\nThe logfile contains the follwing:\n\n!SESSION 2006-05-19 16:01:25.488 -----------------------------------------------\neclipse.buildId\u003dM20060118-1600\njava.version\u003d1.5.0_06\njava.vendor\u003dApple Computer, Inc.\nBootLoader constants: OS\u003dmacosx, ARCH\u003dppc, WS\u003dcarbon, NL\u003dde_DE\nFramework arguments:  -keyring /Users/flo/.eclipse_keyring -showlocation\nCommand-line arguments:  -os macosx -ws carbon -arch ppc -keyring /Users/flo/.eclipse_keyring -consoleLog -showlocation\n\n!ENTRY org.eclipse.osgi 2006-05-19 16:01:27.871\n!MESSAGE Application error\n!STACK 1\njava.lang.UnsatisfiedLinkError: /Users/flo/Desktop/eclipse/configuration/org.eclipse.osgi/bundles/63/1/.cp/libswt-pi-carbon-3139.jnilib: \n        at java.lang.ClassLoader$NativeLibrary.load(Native Method)\n        at java.lang.ClassLoader.loadLibrary0(ClassLoader.java:1751)\n        at java.lang.ClassLoader.loadLibrary(ClassLoader.java:1660)\n        at java.lang.Runtime.loadLibrary0(Runtime.java:822)\n        at java.lang.System.loadLibrary(System.java:992)\n        at org.eclipse.swt.internal.Library.loadLibrary(Library.java:123)\n        at org.eclipse.swt.internal.carbon.OS.\u003cclinit\u003e(OS.java:20)\n        at org.eclipse.swt.widgets.Display.createDisplay(Display.java:856)\n        at org.eclipse.swt.widgets.Display.create(Display.java:836)\n        at org.eclipse.swt.graphics.Device.\u003cinit\u003e(Device.java:118)\n        at org.eclipse.swt.widgets.Display.\u003cinit\u003e(Display.java:676)\n        at org.eclipse.swt.widgets.Display.\u003cinit\u003e(Display.java:667)\n        at org.eclipse.ui.internal.Workbench.createDisplay(Workbench.java:394)\n        at org.eclipse.ui.PlatformUI.createDisplay(PlatformUI.java:155)\n        at org.eclipse.ui.internal.ide.IDEApplication.createDisplay(IDEApplication.java:128)\n        at org.eclipse.ui.internal.ide.IDEApplication.run(IDEApplication.java:79)\n        at org.eclipse.core.internal.runtime.PlatformActivator$1.run(PlatformActivator.java:226)\n        at org.eclipse.core.runtime.adaptor.EclipseStarter.run(EclipseStarter.java:376)\n        at org.eclipse.core.runtime.adaptor.EclipseStarter.run(EclipseStarter.java:163)\n        at sun.reflect.NativeMethodAccessorImpl.invoke0(Native Method)\n        at sun.reflect.NativeMethodAccessorImpl.invoke(NativeMethodAccessorImpl.java:39)\n        at sun.reflect.DelegatingMethodAccessorImpl.invoke(DelegatingMethodAccessorImpl.java:25)\n        at java.lang.reflect.Method.invoke(Method.java:585)\n        at org.eclipse.core.launcher.Main.invokeFramework(Main.java:334)\n        at org.eclipse.core.launcher.Main.basicRun(Main.java:278)\n        at org.eclipse.core.launcher.Main.run(Main.java:973)\n        at org.eclipse.core.launcher.Main.main(Main.java:948)\n\nI also tried to use Eclipse 3.2RC4. Eclipse starts up, but when I open Window/Preferences the whole System hangs up.\n\nIs there any solution to keep me on working with Eclipse?",
    "similar to Bug142529, maybe PDE is failing to copy the dll to the right place, or not setting the correct permision of the file.\n\nWassim: have you seen this before ? (note, eclipse version 3.1.2)\n\n\nFlorian: The problem you described on Eclipse 3.2RC4 is unrelated with this one, please open a separated problem report for it.",
    "cc DJ since this is a runtime issue.\n\nPDE only extracts DLL\u0027s etc. when using the SWT launcher.\n\nWhen you are running an Eclipse application (either host or runtime), the extraction is handled by the runtime.",
    "Created an attachment (id\u003d42119)\neclipse log\n\nI am new to the mac world, but this is the same problem I have with Eclipse 3.1.2\n\nSince I am new to the mac-world, I do not know how to find the correct Mac OS X version. I know it is a 10.4 (intel), but that is as much as I know.\n\nThe problem is the same and I just want to add my .log-file from eclipse.",
    "Do I read correctly that the users in comment 0 and comment 3 are on intel macs?  The standard eclipse 3.1.2 download is not expected to run on these because it is not compiled with universal binaries.  You can get these from bug 98889, or upgrade to a recent 3.2 stream build, such as 3.2RC5.\n",
    "Closing, please reopen it if you are *not* trying to run Eclipse 3.1.2 on an Intel Mac. Thanks."
  ],
  "commentCreationDates": [
    "2006-05-19T16:19:30+02:00",
    "2006-05-19T21:57:40+02:00",
    "2006-05-19T22:04:29+02:00",
    "2006-05-21T12:52:38+02:00",
    "2006-05-24T16:57:23+02:00",
    "2006-05-24T17:40:11+02:00"
  ],
  "traces": [
    {
      "exceptionType": "java.lang.UnsatisfiedLinkError",
      "message": "/Users/flo/Desktop/eclipse/configuration/org.eclipse.osgi/bundles/63/1/.cp/libswt-pi-carbon-3139.jnilib:",
      "elements": [
        {
          "method": "java.lang.ClassLoader$NativeLibrary.load",
          "source": "Native Method"
        },
        {
          "method": "java.lang.ClassLoader.loadLibrary0",
          "source": "ClassLoader.java:1751"
        },
        {
          "method": "java.lang.ClassLoader.loadLibrary",
          "source": "ClassLoader.java:1660"
        },
        {
          "method": "java.lang.Runtime.loadLibrary0",
          "source": "Runtime.java:822"
        },
        {
          "method": "java.lang.System.loadLibrary",
          "source": "System.java:992"
        },
        {
          "method": "org.eclipse.swt.internal.Library.loadLibrary",
          "source": "Library.java:123"
        },
        {
          "method": "org.eclipse.swt.internal.carbon.OS.\u003cclinit\u003e",
          "source": "OS.java:20"
        },
        {
          "method": "org.eclipse.swt.widgets.Display.createDisplay",
          "source": "Display.java:856"
        },
        {
          "method": "org.eclipse.swt.widgets.Display.create",
          "source": "Display.java:836"
        },
        {
          "method": "org.eclipse.swt.graphics.Device.\u003cinit\u003e",
          "source": "Device.java:118"
        },
        {
          "method": "org.eclipse.swt.widgets.Display.\u003cinit\u003e",
          "source": "Display.java:676"
        },
        {
          "method": "org.eclipse.swt.widgets.Display.\u003cinit\u003e",
          "source": "Display.java:667"
        },
        {
          "method": "org.eclipse.ui.internal.Workbench.createDisplay",
          "source": "Workbench.java:394"
        },
        {
          "method": "org.eclipse.ui.PlatformUI.createDisplay",
          "source": "PlatformUI.java:155"
        },
        {
          "method": "org.eclipse.ui.internal.ide.IDEApplication.createDisplay",
          "source": "IDEApplication.java:128"
        },
        {
          "method": "org.eclipse.ui.internal.ide.IDEApplication.run",
          "source": "IDEApplication.java:79"
        },
        {
          "method": "org.eclipse.core.internal.runtime.PlatformActivator$1.run",
          "source": "PlatformActivator.java:226"
        },
        {
          "method": "org.eclipse.core.runtime.adaptor.EclipseStarter.run",
          "source": "EclipseStarter.java:376"
        },
        {
          "method": "org.eclipse.core.runtime.adaptor.EclipseStarter.run",
          "source": "EclipseStarter.java:163"
        },
        {
          "method": "sun.reflect.NativeMethodAccessorImpl.invoke0",
          "source": "Native Method"
        },
        {
          "method": "sun.reflect.NativeMethodAccessorImpl.invoke",
          "source": "NativeMethodAccessorImpl.java:39"
        },
        {
          "method": "sun.reflect.DelegatingMethodAccessorImpl.invoke",
          "source": "DelegatingMethodAccessorImpl.java:25"
        },
        {
          "method": "java.lang.reflect.Method.invoke",
          "source": "Method.java:585"
        },
        {
          "method": "org.eclipse.core.launcher.Main.invokeFramework",
          "source": "Main.java:334"
        },
        {
          "method": "org.eclipse.core.launcher.Main.basicRun",
          "source": "Main.java:278"
        },
        {
          "method": "org.eclipse.core.launcher.Main.run",
          "source": "Main.java:973"
        },
        {
          "method": "org.eclipse.core.launcher.Main.main",
          "source": "Main.java:948"
        }
      ],
      "number": 0,
      "commentIndex": 0,
      "bugId": "142748",
      "date": "2006-05-19T16:19:30+02:00",
      "product": "Platform",
      "component": "SWT",
      "severity": "blocker"
    }
  ],
  "groupId": "142748",
  "bugId": "142748",
  "date": "2006-05-19T16:19:30+02:00",
  "product": "Platform",
  "component": "SWT",
  "severity": "blocker"
}