{
  "comments": [
    "Opened for IBM (Jason Sholl) on WTP 512:  (may be related to EMF2DOMRenderer being used instead of EMF2DOMSSERender...\n\n\nI\u0027m not sure why this started happening; everything was working before, but now, every time I create a new EJB project in IBM product, the EJB validator dies when trying to validate because the ejb-jar.xml file is not DTD valid.  There are lots of exceptions like the one below.\n\n!ENTRY org.eclipse.wst.validation 4 0 2006-05-22 14:11:08.602\n!MESSAGE\n*** ERROR ***: Mon May 22 14:11:08 EDT 2006    org.eclipse.wst.validation.internal.core.ValidationException: IWAE0053E A\nn internal error has occurred running validation on project:TestItEAR]:TestItEAR, check the log file for details\n        at org.eclipse.jst.j2ee.model.internal.validation.EarValidator.validateInJob(EarValidator.java:165)\n        at org.eclipse.jst.j2ee.internal.validation.UIEarValidator.validateInJob(UIEarValidator.java:217)\n        at org.eclipse.wst.validation.internal.operations.ValidatorJob.run(ValidatorJob.java:70)\n        at org.eclipse.core.internal.jobs.Worker.run(Worker.java:58)\n\n!ENTRY org.eclipse.wst.validation 4 0 2006-05-22 14:11:08.612\n!MESSAGE\n*** ERROR ***: Mon May 22 14:11:08 EDT 2006    org.eclipse.jst.j2ee.commonarchivecore.internal.exception.DeploymentDescr\niptorLoadException: META-INF/application.xml\n    Stack trace of nested exception:\n    org.eclipse.jst.j2ee.commonarchivecore.internal.exception.ResourceLoadException: IWAE0007E Could not load resource \"\nMETA-INF/application.xml\" in archive \"[/TestItEAR]:TestItEAR\"\n    Stack trace of nested exception:\n    org.eclipse.emf.common.util.WrappedException: org.xml.sax.SAXParseException: cvc-complex-type.2.4.b: The content of\nelement \u0027application\u0027 is not complete. One of \u0027{\"http://java.sun.com/xml/ns/j2ee\":display-name, \"http://java.sun.com/xml\n/ns/j2ee\":icon, \"http://java.sun.com/xml/ns/j2ee\":module}\u0027 is expected.\n        at org.eclipse.wst.common.internal.emf.resource.EMF2DOMRenderer.loadDocument(EMF2DOMRenderer.java:79)\n        at org.eclipse.wst.common.internal.emf.resource.EMF2DOMRenderer.doLoad(EMF2DOMRenderer.java:60)\n        at org.eclipse.wst.common.internal.emf.resource.TranslatorResourceImpl.basicDoLoad(TranslatorResourceImpl.java:1\n41)\n        at org.eclipse.wst.common.internal.emf.resource.CompatibilityXMIResourceImpl.doLoad(CompatibilityXMIResourceImpl\n.java:173)\n        at org.eclipse.emf.ecore.resource.impl.ResourceImpl.load(ResourceImpl.java:1089)\n        at org.eclipse.emf.ecore.resource.impl.ResourceImpl.load(ResourceImpl.java:895)\n        at org.eclipse.wst.common.internal.emf.resource.TranslatorResourceImpl.load(TranslatorResourceImpl.java:384)\n        at org.eclipse.emf.ecore.resource.impl.ResourceSetImpl.demandLoad(ResourceSetImpl.java:249)\n        at org.eclipse.jem.internal.util.emf.workbench.ProjectResourceSetImpl.demandLoad(ProjectResourceSetImpl.java:83)\n\n        at org.eclipse.emf.ecore.resource.impl.ResourceSetImpl.demandLoadHelper(ResourceSetImpl.java:264)\n        at org.eclipse.emf.ecore.resource.impl.ResourceSetImpl.getResource(ResourceSetImpl.java:346)\n        at org.eclipse.jem.internal.util.emf.workbench.ProjectResourceSetImpl.getResource(ProjectResourceSetImpl.java:26\n2)\n        at org.eclipse.jst.j2ee.internal.archive.operations.ComponentLoadStrategyImpl.getMofResource(ComponentLoadStrate\ngyImpl.java:460)\n        at org.eclipse.jst.j2ee.commonarchivecore.internal.impl.ArchiveImpl.getMofResource(ArchiveImpl.java:869)\n        at org.eclipse.jst.j2ee.commonarchivecore.internal.impl.ModuleFileImpl.getDeploymentDescriptorResource(ModuleFil\neImpl.java:255)\n        at org.eclipse.jst.j2ee.commonarchivecore.internal.strategy.XmlBasedImportStrategyImpl.primLoadDeploymentDescrip\ntor(XmlBasedImportStrategyImpl.java:39)\n        at org.eclipse.jst.j2ee.commonarchivecore.internal.strategy.Ear12ImportStrategyImpl.loadDeploymentDescriptor(Ear\n12ImportStrategyImpl.java:87)\n        at org.eclipse.jst.j2ee.commonarchivecore.internal.strategy.Ear12ImportStrategyImpl.importMetaData(Ear12ImportSt\nrategyImpl.java:81)\n        at org.eclipse.jst.j2ee.commonarchivecore.internal.impl.EARFileImpl.getDeploymentDescriptor(EARFileImpl.java:296\n)\n        at org.eclipse.jst.j2ee.model.internal.validation.EarValidator.validateInJob(EarValidator.java:142)\n        at org.eclipse.jst.j2ee.internal.validation.UIEarValidator.validateInJob(UIEarValidator.java:217)\n        at org.eclipse.wst.validation.internal.operations.ValidatorJob.run(ValidatorJob.java:70)\n        at org.eclipse.core.internal.jobs.Worker.run(Worker.java:58)\n    Caused by: org.xml.sax.SAXParseException: cvc-complex-type.2.4.b: The content of element \u0027application\u0027 is not comple\nte. One of \u0027{\"http://java.sun.com/xml/ns/j2ee\":display-name, \"http://java.sun.com/xml/ns/j2ee\":icon, \"http://java.sun.co\nm/xml/ns/j2ee\":module}\u0027 is expected.\n        at org.apache.xerces.util.ErrorHandlerWrapper.createSAXParseException(Unknown Source)\n        at org.apache.xerces.util.ErrorHandlerWrapper.error(Unknown Source)\n        at org.apache.xerces.impl.XMLErrorReporter.reportError(Unknown Source)\n        at org.apache.xerces.impl.XMLErrorReporter.reportError(Unknown Source)\n        at org.apache.xerces.impl.xs.XMLSchemaValidator$XSIErrorReporter.reportError(Unknown Source)\n        at org.apache.xerces.impl.xs.XMLSchemaValidator.reportSchemaError(Unknown Source)\n        at org.apache.xerces.impl.xs.XMLSchemaValidator.elementLocallyValidComplexType(Unknown Source)\n        at org.apache.xerces.impl.xs.XMLSchemaValidator.elementLocallyValidType(Unknown Source)\n        at org.apache.xerces.impl.xs.XMLSchemaValidator.processElementContent(Unknown Source)\n        at org.apache.xerces.impl.xs.XMLSchemaValidator.handleEndElement(Unknown Source)\n        at org.apache.xerces.impl.xs.XMLSchemaValidator.endElement(Unknown Source)\n        at org.apache.xerces.impl.XMLNSDocumentScannerImpl.scanEndElement(Unknown Source)\n        at org.apache.xerces.impl.XMLDocumentFragmentScannerImpl$FragmentContentDispatcher.dispatch(Unknown Source)\n        at org.apache.xerces.impl.XMLDocumentFragmentScannerImpl.scanDocument(Unknown Source)\n        at org.apache.xerces.parsers.XML11Configuration.parse(Unknown Source)\n        at org.apache.xerces.parsers.XML11Configuration.parse(Unknown Source)\n        at org.apache.xerces.parsers.XMLParser.parse(Unknown Source)\n        at org.apache.xerces.parsers.DOMParser.parse(Unknown Source)\n        at org.apache.xerces.jaxp.DocumentBuilderImpl.parse(Unknown Source)\n        at javax.xml.parsers.DocumentBuilder.parse(Unknown Source)\n        at org.eclipse.wst.common.internal.emf.utilities.DOMUtilities.loadDocument(DOMUtilities.java:546)\n        at org.eclipse.wst.common.internal.emf.resource.EMF2DOMRenderer.loadDocument(EMF2DOMRenderer.java:72)\n        ... 22 more",
    "The problem is in the IBM driver, it is not a WTP issue.",
    "OK"
  ],
  "commentCreationDates": [
    "2006-05-23T22:35:00+02:00",
    "2006-05-24T16:37:52+02:00",
    "2006-05-24T16:39:32+02:00"
  ],
  "traces": [
    {
      "exceptionType": "org.eclipse.wst.validation.internal.core.ValidationException",
      "message": "IWAE0053E A n internal error has occurred running validation on project:TestItEAR]:TestItEAR, check the log file for details",
      "elements": [
        {
          "method": "org.eclipse.jst.j2ee.model.internal.validation.EarValidator.validateInJob",
          "source": "EarValidator.java:165"
        },
        {
          "method": "org.eclipse.jst.j2ee.internal.validation.UIEarValidator.validateInJob",
          "source": "UIEarValidator.java:217"
        },
        {
          "method": "org.eclipse.wst.validation.internal.operations.ValidatorJob.run",
          "source": "ValidatorJob.java:70"
        },
        {
          "method": "org.eclipse.core.internal.jobs.Worker.run",
          "source": "Worker.java:58"
        }
      ],
      "number": 0,
      "commentIndex": 0,
      "bugId": "143318",
      "date": "2006-05-23T22:35:00+02:00",
      "product": "Web Tools",
      "component": "jst.j2ee",
      "severity": "major"
    },
    {
      "exceptionType": "org.xml.sax.SAXParseException",
      "message": "cvc-complex-type.2.4.b: The content of element \u0027application\u0027 is not complete. One of \u0027{\"http://java.sun.com/xml/ns/j2ee\":display-name, \"http://java.sun.com/xml /ns/j2ee\":icon, \"http://java.sun.com/xml/ns/j2ee\":module}\u0027 is expected.",
      "elements": [
        {
          "method": "org.eclipse.wst.common.internal.emf.resource.EMF2DOMRenderer.loadDocument",
          "source": "EMF2DOMRenderer.java:79"
        },
        {
          "method": "org.eclipse.wst.common.internal.emf.resource.EMF2DOMRenderer.doLoad",
          "source": "EMF2DOMRenderer.java:60"
        },
        {
          "method": "org.eclipse.wst.common.internal.emf.resource.TranslatorResourceImpl.basicDoLoad",
          "source": "TranslatorResourceImpl.java:1 41"
        },
        {
          "method": "org.eclipse.wst.common.internal.emf.resource.CompatibilityXMIResourceImpl.doLoad",
          "source": "CompatibilityXMIResourceImpl .java:173"
        },
        {
          "method": "org.eclipse.emf.ecore.resource.impl.ResourceImpl.load",
          "source": "ResourceImpl.java:1089"
        },
        {
          "method": "org.eclipse.emf.ecore.resource.impl.ResourceImpl.load",
          "source": "ResourceImpl.java:895"
        },
        {
          "method": "org.eclipse.wst.common.internal.emf.resource.TranslatorResourceImpl.load",
          "source": "TranslatorResourceImpl.java:384"
        },
        {
          "method": "org.eclipse.emf.ecore.resource.impl.ResourceSetImpl.demandLoad",
          "source": "ResourceSetImpl.java:249"
        },
        {
          "method": "org.eclipse.jem.internal.util.emf.workbench.ProjectResourceSetImpl.demandLoad",
          "source": "ProjectResourceSetImpl.java:83"
        },
        {
          "method": "org.eclipse.emf.ecore.resource.impl.ResourceSetImpl.demandLoadHelper",
          "source": "ResourceSetImpl.java:264"
        },
        {
          "method": "org.eclipse.emf.ecore.resource.impl.ResourceSetImpl.getResource",
          "source": "ResourceSetImpl.java:346"
        },
        {
          "method": "org.eclipse.jem.internal.util.emf.workbench.ProjectResourceSetImpl.getResource",
          "source": "ProjectResourceSetImpl.java:26 2"
        },
        {
          "method": "org.eclipse.jst.j2ee.internal.archive.operations.ComponentLoadStrategyImpl.getMofResource",
          "source": "ComponentLoadStrate gyImpl.java:460"
        },
        {
          "method": "org.eclipse.jst.j2ee.commonarchivecore.internal.impl.ArchiveImpl.getMofResource",
          "source": "ArchiveImpl.java:869"
        },
        {
          "method": "org.eclipse.jst.j2ee.commonarchivecore.internal.impl.ModuleFileImpl.getDeploymentDescriptorResource",
          "source": "ModuleFil eImpl.java:255"
        },
        {
          "method": "org.eclipse.jst.j2ee.commonarchivecore.internal.strategy.XmlBasedImportStrategyImpl.primLoadDeploymentDescriptor",
          "source": "XmlBasedImportStrategyImpl.java:39"
        },
        {
          "method": "org.eclipse.jst.j2ee.commonarchivecore.internal.strategy.Ear12ImportStrategyImpl.loadDeploymentDescriptor",
          "source": "Ear 12ImportStrategyImpl.java:87"
        },
        {
          "method": "org.eclipse.jst.j2ee.commonarchivecore.internal.strategy.Ear12ImportStrategyImpl.importMetaData",
          "source": "Ear12ImportSt rategyImpl.java:81"
        },
        {
          "method": "org.eclipse.jst.j2ee.commonarchivecore.internal.impl.EARFileImpl.getDeploymentDescriptor",
          "source": "EARFileImpl.java:296 "
        },
        {
          "method": "org.eclipse.jst.j2ee.model.internal.validation.EarValidator.validateInJob",
          "source": "EarValidator.java:142"
        },
        {
          "method": "org.eclipse.jst.j2ee.internal.validation.UIEarValidator.validateInJob",
          "source": "UIEarValidator.java:217"
        },
        {
          "method": "org.eclipse.wst.validation.internal.operations.ValidatorJob.run",
          "source": "ValidatorJob.java:70"
        },
        {
          "method": "org.eclipse.core.internal.jobs.Worker.run",
          "source": "Worker.java:58"
        }
      ],
      "causedBy": {
        "exceptionType": "org.xml.sax.SAXParseException",
        "message": "cvc-complex-type.2.4.b: The content of element \u0027application\u0027 is not comple te. One of \u0027{\"http://java.sun.com/xml/ns/j2ee\":display-name, \"http://java.sun.com/xml/ns/j2ee\":icon, \"http://java.sun.co m/xml/ns/j2ee\":module}\u0027 is expected.",
        "elements": [
          {
            "method": "org.apache.xerces.util.ErrorHandlerWrapper.createSAXParseException",
            "source": "Unknown Source"
          },
          {
            "method": "org.apache.xerces.util.ErrorHandlerWrapper.error",
            "source": "Unknown Source"
          },
          {
            "method": "org.apache.xerces.impl.XMLErrorReporter.reportError",
            "source": "Unknown Source"
          },
          {
            "method": "org.apache.xerces.impl.XMLErrorReporter.reportError",
            "source": "Unknown Source"
          },
          {
            "method": "org.apache.xerces.impl.xs.XMLSchemaValidator$XSIErrorReporter.reportError",
            "source": "Unknown Source"
          },
          {
            "method": "org.apache.xerces.impl.xs.XMLSchemaValidator.reportSchemaError",
            "source": "Unknown Source"
          },
          {
            "method": "org.apache.xerces.impl.xs.XMLSchemaValidator.elementLocallyValidComplexType",
            "source": "Unknown Source"
          },
          {
            "method": "org.apache.xerces.impl.xs.XMLSchemaValidator.elementLocallyValidType",
            "source": "Unknown Source"
          },
          {
            "method": "org.apache.xerces.impl.xs.XMLSchemaValidator.processElementContent",
            "source": "Unknown Source"
          },
          {
            "method": "org.apache.xerces.impl.xs.XMLSchemaValidator.handleEndElement",
            "source": "Unknown Source"
          },
          {
            "method": "org.apache.xerces.impl.xs.XMLSchemaValidator.endElement",
            "source": "Unknown Source"
          },
          {
            "method": "org.apache.xerces.impl.XMLNSDocumentScannerImpl.scanEndElement",
            "source": "Unknown Source"
          },
          {
            "method": "org.apache.xerces.impl.XMLDocumentFragmentScannerImpl$FragmentContentDispatcher.dispatch",
            "source": "Unknown Source"
          },
          {
            "method": "org.apache.xerces.impl.XMLDocumentFragmentScannerImpl.scanDocument",
            "source": "Unknown Source"
          },
          {
            "method": "org.apache.xerces.parsers.XML11Configuration.parse",
            "source": "Unknown Source"
          },
          {
            "method": "org.apache.xerces.parsers.XML11Configuration.parse",
            "source": "Unknown Source"
          },
          {
            "method": "org.apache.xerces.parsers.XMLParser.parse",
            "source": "Unknown Source"
          },
          {
            "method": "org.apache.xerces.parsers.DOMParser.parse",
            "source": "Unknown Source"
          },
          {
            "method": "org.apache.xerces.jaxp.DocumentBuilderImpl.parse",
            "source": "Unknown Source"
          },
          {
            "method": "javax.xml.parsers.DocumentBuilder.parse",
            "source": "Unknown Source"
          },
          {
            "method": "org.eclipse.wst.common.internal.emf.utilities.DOMUtilities.loadDocument",
            "source": "DOMUtilities.java:546"
          },
          {
            "method": "org.eclipse.wst.common.internal.emf.resource.EMF2DOMRenderer.loadDocument",
            "source": "EMF2DOMRenderer.java:72"
          }
        ],
        "number": 0,
        "commentIndex": 0
      },
      "number": 1,
      "commentIndex": 0,
      "bugId": "143318",
      "date": "2006-05-23T22:35:00+02:00",
      "product": "Web Tools",
      "component": "jst.j2ee",
      "severity": "major"
    }
  ],
  "groupId": "143318",
  "bugId": "143318",
  "date": "2006-05-23T22:35:00+02:00",
  "product": "Web Tools",
  "component": "jst.j2ee",
  "severity": "major"
}