{
  "comments": [
    "I start debugging a local application and some times when I press F6 to step over, the application begin running as if I ordered it to resume and, at the same time, the debug view inside the debug perspective looses the threads and stacks, showing that the application is disconected.\n\nThere is no message in the console view, but, in the momment of the disconection, the log file shows the following error.\n\n!ENTRY org.eclipse.jdt.debug 4 120 2006-05-30 09:50:45.955\n!MESSAGE Internal error logged from JDI Debug:\n!STACK 0\ncom.sun.jdi.VMDisconnectedException: Got IOException from Virtual Machine\n        at org.eclipse.jdi.internal.connect.PacketReceiveManager.getReply(PacketReceiveManager.java:162)\n        at org.eclipse.jdi.internal.connect.PacketReceiveManager.getReply(PacketReceiveManager.java:177)\n        at org.eclipse.jdi.internal.MirrorImpl.requestVM(MirrorImpl.java:174)\n        at org.eclipse.jdi.internal.MirrorImpl.requestVM(MirrorImpl.java:192)\n        at org.eclipse.jdi.internal.MirrorImpl.requestVM(MirrorImpl.java:222)\n        at org.eclipse.jdi.internal.ReferenceTypeImpl.interfaces(ReferenceTypeImpl.java:593)\n        at org.eclipse.jdi.internal.ReferenceTypeImpl.allFields(ReferenceTypeImpl.java:695)\n        at org.eclipse.jdi.internal.ReferenceTypeImpl.allFields(ReferenceTypeImpl.java:699)\n        at org.eclipse.jdi.internal.ReferenceTypeImpl.allFields(ReferenceTypeImpl.java:706)\n        at org.eclipse.jdi.internal.ReferenceTypeImpl.allFields(ReferenceTypeImpl.java:706)\n        at org.eclipse.jdi.internal.ReferenceTypeImpl.allFields(ReferenceTypeImpl.java:706)\n        at org.eclipse.jdt.internal.debug.core.model.JDIObjectValue.getField(JDIObjectValue.java:184)\n        at org.eclipse.jdt.internal.debug.ui.JavaDebugHover.getHoverInfo(JavaDebugHover.java:193)\n        at org.eclipse.jdt.internal.ui.text.java.hover.BestMatchHover.getHoverInfo(BestMatchHover.java:102)\n        at org.eclipse.jdt.internal.ui.text.java.hover.JavaEditorTextHoverProxy.getHoverInfo(JavaEditorTextHoverProxy.java:69)\n        at org.eclipse.jface.text.TextViewerHoverManager$4.run(TextViewerHoverManager.java:160)\n_____________________________________\n\nSometimes the error happens the first time I try to step the debug, just after it stopped on a breakpoint. in others ocasions, I can step the debug for about five minutes before the error happening.",
    "Created an attachment (id\u003d42945)\nlog \n\n",
    "\n\n*** This bug has been marked as a duplicate of 136731 ***",
    "Should be dup of bug 134684 ",
    "\n\n*** This bug has been marked as a duplicate of 134684 ***"
  ],
  "commentCreationDates": [
    "2006-05-30T15:11:49+02:00",
    "2006-05-30T15:14:12+02:00",
    "2006-06-02T17:02:03+02:00",
    "2006-06-02T17:37:48+02:00",
    "2006-06-02T17:37:56+02:00"
  ],
  "traces": [
    {
      "exceptionType": "com.sun.jdi.VMDisconnectedException",
      "message": "Got IOException from Virtual Machine",
      "elements": [
        {
          "method": "org.eclipse.jdi.internal.connect.PacketReceiveManager.getReply",
          "source": "PacketReceiveManager.java:162"
        },
        {
          "method": "org.eclipse.jdi.internal.connect.PacketReceiveManager.getReply",
          "source": "PacketReceiveManager.java:177"
        },
        {
          "method": "org.eclipse.jdi.internal.MirrorImpl.requestVM",
          "source": "MirrorImpl.java:174"
        },
        {
          "method": "org.eclipse.jdi.internal.MirrorImpl.requestVM",
          "source": "MirrorImpl.java:192"
        },
        {
          "method": "org.eclipse.jdi.internal.MirrorImpl.requestVM",
          "source": "MirrorImpl.java:222"
        },
        {
          "method": "org.eclipse.jdi.internal.ReferenceTypeImpl.interfaces",
          "source": "ReferenceTypeImpl.java:593"
        },
        {
          "method": "org.eclipse.jdi.internal.ReferenceTypeImpl.allFields",
          "source": "ReferenceTypeImpl.java:695"
        },
        {
          "method": "org.eclipse.jdi.internal.ReferenceTypeImpl.allFields",
          "source": "ReferenceTypeImpl.java:699"
        },
        {
          "method": "org.eclipse.jdi.internal.ReferenceTypeImpl.allFields",
          "source": "ReferenceTypeImpl.java:706"
        },
        {
          "method": "org.eclipse.jdi.internal.ReferenceTypeImpl.allFields",
          "source": "ReferenceTypeImpl.java:706"
        },
        {
          "method": "org.eclipse.jdi.internal.ReferenceTypeImpl.allFields",
          "source": "ReferenceTypeImpl.java:706"
        },
        {
          "method": "org.eclipse.jdt.internal.debug.core.model.JDIObjectValue.getField",
          "source": "JDIObjectValue.java:184"
        },
        {
          "method": "org.eclipse.jdt.internal.debug.ui.JavaDebugHover.getHoverInfo",
          "source": "JavaDebugHover.java:193"
        },
        {
          "method": "org.eclipse.jdt.internal.ui.text.java.hover.BestMatchHover.getHoverInfo",
          "source": "BestMatchHover.java:102"
        },
        {
          "method": "org.eclipse.jdt.internal.ui.text.java.hover.JavaEditorTextHoverProxy.getHoverInfo",
          "source": "JavaEditorTextHoverProxy.java:69"
        },
        {
          "method": "org.eclipse.jface.text.TextViewerHoverManager$4.run",
          "source": "TextViewerHoverManager.java:160"
        }
      ],
      "number": 0,
      "commentIndex": 0,
      "bugId": "144430",
      "duplicateId": "134684",
      "date": "2006-05-30T15:11:49+02:00",
      "product": "Platform",
      "component": "Debug",
      "severity": "major"
    }
  ],
  "groupId": "171075",
  "bugId": "144430",
  "duplicateId": "134684",
  "date": "2006-05-30T15:11:49+02:00",
  "product": "Platform",
  "component": "Debug",
  "severity": "major"
}