{
  "comments": [
    "!ENTRY org.eclipse.jdt.ui 4 2 2006-05-30 12:03:50.786\n!MESSAGE Problems occurred when invoking code from plug-in:\n\"org.eclipse.jdt.ui\".\n!STACK 0\njava.lang.IllegalArgumentException\n        at org.eclipse.jdt.core.dom.ASTNode.setSourceRange(ASTNode.java:2599)\n        at org.eclipse.jdt.core.dom.ASTConverter.convert(ASTConverter.java:483)\n        at\norg.eclipse.jdt.core.dom.ASTConverter.buildBodyDeclarations(ASTConverter.java:179)\n        at\norg.eclipse.jdt.core.dom.ASTConverter.convert(ASTConverter.java:2659)\n        at\norg.eclipse.jdt.core.dom.ASTConverter.convert(ASTConverter.java:2420)\n        at org.eclipse.jdt.core.dom.ASTConverter.convert(ASTConverter.java:511)\n        at\norg.eclipse.jdt.core.dom.ASTConverter.buildBodyDeclarations(ASTConverter.java:179)\n        at\norg.eclipse.jdt.core.dom.ASTConverter.convert(ASTConverter.java:2659)\n        at\norg.eclipse.jdt.core.dom.ASTConverter.convert(ASTConverter.java:1242)\n        at org.eclipse.jdt.core.dom.AST.convertCompilationUnit(AST.java:270)\n        at\norg.eclipse.jdt.internal.core.CompilationUnit.buildStructure(CompilationUnit.java:187)\n        at\norg.eclipse.jdt.internal.core.Openable.generateInfos(Openable.java:229)\n        at\norg.eclipse.jdt.internal.core.JavaElement.openWhenClosed(JavaElement.java:505)\n        at\norg.eclipse.jdt.internal.core.CompilationUnit.makeConsistent(CompilationUnit.java:993)\n        at\norg.eclipse.jdt.internal.core.ReconcileWorkingCopyOperation.makeConsistent(ReconcileWorkingCopyOperation.java:131)\n        at\norg.eclipse.jdt.internal.core.ReconcileWorkingCopyOperation.executeOperation(ReconcileWorkingCopyOperation.java:71)\n        at\norg.eclipse.jdt.internal.core.JavaModelOperation.run(JavaModelOperation.java:720)\n        at\norg.eclipse.jdt.internal.core.JavaModelOperation.runOperation(JavaModelOperation.java:779)\n        at\norg.eclipse.jdt.internal.core.CompilationUnit.reconcile(CompilationUnit.java:1123)\n        at\norg.eclipse.jdt.internal.ui.text.java.JavaReconcilingStrategy$1.run(JavaReconcilingStrategy.java:97)\n        at org.eclipse.core.runtime.SafeRunner.run(SafeRunner.java:37)\n        at\norg.eclipse.jdt.internal.ui.text.java.JavaReconcilingStrategy.reconcile(JavaReconcilingStrategy.java:82)\n        at\norg.eclipse.jdt.internal.ui.text.java.JavaReconcilingStrategy.reconcile(JavaReconcilingStrategy.java:145)\n        at\norg.eclipse.jdt.internal.ui.text.CompositeReconcilingStrategy.reconcile(CompositeReconcilingStrategy.java:86)\n        at\norg.eclipse.jdt.internal.ui.text.JavaCompositeReconcilingStrategy.reconcile(JavaCompositeReconcilingStrategy.java:94)\n        at\norg.eclipse.jface.text.reconciler.MonoReconciler.process(MonoReconciler.java:75)\n        at\norg.eclipse.jdt.internal.ui.text.JavaReconciler.process(JavaReconciler.java:342)\n        at\norg.eclipse.jface.text.reconciler.AbstractReconciler$BackgroundThread.run(AbstractReconciler.java:204)",
    "This exception was thrown while working with eclipse.\nI have just downloaded eclipse-3.2RC6 and have not changed any preferences or configuration.\nAfter some time I noticed this exception was thrown this is the .log file.\n\nps: Sorry for the previous comment. I accidently press enter.\n",
    "Could you please provide the contents of the compilation unit when you got this error?\nI\u0027ll investigate it. Might be another case of incomplete recovery.",
    "This looks like a case where a method declaration doesn\u0027t have its declaration source end set.\nDavid, this might come from a recovery issue.",
    "methodDeclaration.bodyEnd is not set in this case. A test case would be very welcome.",
    "I tried most of the compilation units i have been working in the time the exception occred. I edit them, scroll through them and so on but I could not reproduce the error. \nSorry but it is imposible for me to provide an compilation unit",
    "Created an attachment (id\u003d43159)\nPatch to log errors during the conversion\n\nThis patch will log the cu contents when something wrong (RuntimeException) happens during the conversion and then rethrow it.\nWe would still get the same behavior, but at least it would be trivial to provide a test case to reproduce the issue."
  ],
  "commentCreationDates": [
    "2006-05-30T16:25:11+02:00",
    "2006-05-30T16:28:28+02:00",
    "2006-05-30T16:29:17+02:00",
    "2006-05-30T17:04:00+02:00",
    "2006-05-30T17:04:59+02:00",
    "2006-05-31T11:49:02+02:00",
    "2006-05-31T21:37:45+02:00"
  ],
  "traces": [
    {
      "exceptionType": "java.lang.IllegalArgumentException",
      "elements": [
        {
          "method": "org.eclipse.jdt.core.dom.ASTNode.setSourceRange",
          "source": "ASTNode.java:2599"
        },
        {
          "method": "org.eclipse.jdt.core.dom.ASTConverter.convert",
          "source": "ASTConverter.java:483"
        },
        {
          "method": "org.eclipse.jdt.core.dom.ASTConverter.buildBodyDeclarations",
          "source": "ASTConverter.java:179"
        },
        {
          "method": "org.eclipse.jdt.core.dom.ASTConverter.convert",
          "source": "ASTConverter.java:2659"
        },
        {
          "method": "org.eclipse.jdt.core.dom.ASTConverter.convert",
          "source": "ASTConverter.java:2420"
        },
        {
          "method": "org.eclipse.jdt.core.dom.ASTConverter.convert",
          "source": "ASTConverter.java:511"
        },
        {
          "method": "org.eclipse.jdt.core.dom.ASTConverter.buildBodyDeclarations",
          "source": "ASTConverter.java:179"
        },
        {
          "method": "org.eclipse.jdt.core.dom.ASTConverter.convert",
          "source": "ASTConverter.java:2659"
        },
        {
          "method": "org.eclipse.jdt.core.dom.ASTConverter.convert",
          "source": "ASTConverter.java:1242"
        },
        {
          "method": "org.eclipse.jdt.core.dom.AST.convertCompilationUnit",
          "source": "AST.java:270"
        },
        {
          "method": "org.eclipse.jdt.internal.core.CompilationUnit.buildStructure",
          "source": "CompilationUnit.java:187"
        },
        {
          "method": "org.eclipse.jdt.internal.core.Openable.generateInfos",
          "source": "Openable.java:229"
        },
        {
          "method": "org.eclipse.jdt.internal.core.JavaElement.openWhenClosed",
          "source": "JavaElement.java:505"
        },
        {
          "method": "org.eclipse.jdt.internal.core.CompilationUnit.makeConsistent",
          "source": "CompilationUnit.java:993"
        },
        {
          "method": "org.eclipse.jdt.internal.core.ReconcileWorkingCopyOperation.makeConsistent",
          "source": "ReconcileWorkingCopyOperation.java:131"
        },
        {
          "method": "org.eclipse.jdt.internal.core.ReconcileWorkingCopyOperation.executeOperation",
          "source": "ReconcileWorkingCopyOperation.java:71"
        },
        {
          "method": "org.eclipse.jdt.internal.core.JavaModelOperation.run",
          "source": "JavaModelOperation.java:720"
        },
        {
          "method": "org.eclipse.jdt.internal.core.JavaModelOperation.runOperation",
          "source": "JavaModelOperation.java:779"
        },
        {
          "method": "org.eclipse.jdt.internal.core.CompilationUnit.reconcile",
          "source": "CompilationUnit.java:1123"
        },
        {
          "method": "org.eclipse.jdt.internal.ui.text.java.JavaReconcilingStrategy$1.run",
          "source": "JavaReconcilingStrategy.java:97"
        },
        {
          "method": "org.eclipse.core.runtime.SafeRunner.run",
          "source": "SafeRunner.java:37"
        },
        {
          "method": "org.eclipse.jdt.internal.ui.text.java.JavaReconcilingStrategy.reconcile",
          "source": "JavaReconcilingStrategy.java:82"
        },
        {
          "method": "org.eclipse.jdt.internal.ui.text.java.JavaReconcilingStrategy.reconcile",
          "source": "JavaReconcilingStrategy.java:145"
        },
        {
          "method": "org.eclipse.jdt.internal.ui.text.CompositeReconcilingStrategy.reconcile",
          "source": "CompositeReconcilingStrategy.java:86"
        },
        {
          "method": "org.eclipse.jdt.internal.ui.text.JavaCompositeReconcilingStrategy.reconcile",
          "source": "JavaCompositeReconcilingStrategy.java:94"
        },
        {
          "method": "org.eclipse.jface.text.reconciler.MonoReconciler.process",
          "source": "MonoReconciler.java:75"
        },
        {
          "method": "org.eclipse.jdt.internal.ui.text.JavaReconciler.process",
          "source": "JavaReconciler.java:342"
        },
        {
          "method": "org.eclipse.jface.text.reconciler.AbstractReconciler$BackgroundThread.run",
          "source": "AbstractReconciler.java:204"
        }
      ],
      "number": 0,
      "commentIndex": 0,
      "bugId": "144450",
      "date": "2006-05-30T16:25:11+02:00",
      "product": "JDT",
      "component": "Core",
      "severity": "normal"
    }
  ],
  "groupId": "144450",
  "bugId": "144450",
  "date": "2006-05-30T16:25:11+02:00",
  "product": "JDT",
  "component": "Core",
  "severity": "normal"
}