{
  "comments": [
    "Matching on a pointcut such as the following:\n\n        before() : accessingRedField(Coloured) { // ... }\n\n\tprivate pointcut accessingRedField(Coloured coloured) :\n\t\tget(* *) \u0026\u0026 \n\t\t@annotation(coloured) \u0026\u0026\n\t\tif(coloured.value() \u003d\u003d Colour.RED);\n\ncauses:\n\norg.aspectj.weaver.BCException\nat org.aspectj.weaver.patterns.AnnotationPointcut.findResidueInternal(AnnotationPointcut.java:199)\nat org.aspectj.weaver.patterns.Pointcut.findResidue(Pointcut.java:267)\nat org.aspectj.weaver.patterns.AndPointcut.findResidueInternal(AndPointcut.java:93)\nat org.aspectj.weaver.patterns.Pointcut.findResidue(Pointcut.java:267)\nat org.aspectj.weaver.patterns.AndPointcut.findResidueInternal(AndPointcut.java:93)\nat org.aspectj.weaver.patterns.Pointcut.findResidue(Pointcut.java:267)\nat org.aspectj.weaver.patterns.IfPointcut.findResidueInternal(IfPointcut.java:173)\nat org.aspectj.weaver.patterns.Pointcut.findResidue(Pointcut.java:267)\nat org.aspectj.weaver.patterns.AndPointcut.findResidueInternal(AndPointcut.java:93)\nat org.aspectj.weaver.patterns.Pointcut.findResidue(Pointcut.java:267)\nat org.aspectj.weaver.patterns.AndPointcut.findResidueInternal(AndPointcut.java:93)\nat org.aspectj.weaver.patterns.Pointcut.findResidue(Pointcut.java:267)\nat org.aspectj.weaver.patterns.NotPointcut.findResidueInternal(NotPointcut.java:96)\nat org.aspectj.weaver.patterns.Pointcut.findResidue(Pointcut.java:267)\nat org.aspectj.weaver.patterns.AndPointcut.findResidueInternal(AndPointcut.java:93)\nat org.aspectj.weaver.patterns.Pointcut.findResidue(Pointcut.java:267)\nat org.aspectj.weaver.patterns.AndPointcut.findResidueInternal(AndPointcut.java:93)\nat org.aspectj.weaver.patterns.Pointcut.findResidue(Pointcut.java:267)\nat org.aspectj.weaver.patterns.AndPointcut.findResidueInternal(AndPointcut.java:93)\nat org.aspectj.weaver.patterns.Pointcut.findResidue(Pointcut.java:267)\nat org.aspectj.weaver.bcel.BcelAdvice.specializeOn(BcelAdvice.java:132)\nat org.aspectj.weaver.bcel.BcelShadow.prepareForMungers(BcelShadow.java:325)\nat org.aspectj.weaver.Shadow.implement(Shadow.java:455)\nat org.aspectj.weaver.bcel.BcelClassWeaver.implement(BcelClassWeaver.java:2236)\nat org.aspectj.weaver.bcel.BcelClassWeaver.weave(BcelClassWeaver.java:491)\nat org.aspectj.weaver.bcel.BcelClassWeaver.weave(BcelClassWeaver.java:109)\nat org.aspectj.weaver.bcel.BcelWeaver.weave(BcelWeaver.java:1560)\nat org.aspectj.weaver.bcel.BcelWeaver.weaveWithoutDump(BcelWeaver.java:1511)\nat org.aspectj.weaver.bcel.BcelWeaver.weaveAndNotify(BcelWeaver.java:1291)\nat org.aspectj.weaver.bcel.BcelWeaver.weave(BcelWeaver.java:1113)\nat org.aspectj.ajdt.internal.compiler.AjCompilerAdapter.weave(AjCompilerAdapter.java:311)\nat org.aspectj.ajdt.internal.compiler.AjCompilerAdapter.afterCompiling(AjCompilerAdapter.java:183)\nat org.aspectj.ajdt.internal.compiler.CompilerAdapter.ajc$afterReturning$org_aspectj_ajdt_internal_compiler_CompilerAdapter$2$f9cc9ca0(CompilerAdapter.aj:70)\nat org.aspectj.org.eclipse.jdt.internal.compiler.Compiler.compile(Compiler.java:367)\nat org.aspectj.ajdt.internal.core.builder.AjBuildManager.performCompilation(AjBuildManager.java:862)\nat org.aspectj.ajdt.internal.core.builder.AjBuildManager.doBuild(AjBuildManager.java:242)\nat org.aspectj.ajdt.internal.core.builder.AjBuildManager.batchBuild(AjBuildManager.java:161)\nat org.aspectj.ajde.internal.CompilerAdapter.compile(CompilerAdapter.java:122)\nat org.aspectj.ajde.internal.AspectJBuildManager$CompilerThread.run(AspectJBuildManager.java:191)\n\ntrouble in: \npublic class rainbow.RainbowFields extends java.lang.Object:\n  private int a\n  private int x [RuntimeVisibleAnnotations]\n  private int y [RuntimeVisibleAnnotations]\n  private int z [RuntimeVisibleAnnotations]\n  public void \u003cinit\u003e():\n                    ALOAD_0     // Lrainbow/RainbowFields; this   (line 3)\n                    INVOKESPECIAL java.lang.Object.\u003cinit\u003e ()V\n    constructor-execution(void rainbow.RainbowFields.\u003cinit\u003e())\n    |               RETURN\n    constructor-execution(void rainbow.RainbowFields.\u003cinit\u003e())\n  end public void \u003cinit\u003e()\n\n  public int getA()    org.aspectj.weaver.MethodDeclarationLineNumber: 10:204\n:\n    method-execution(int rainbow.RainbowFields.getA())\n    |               ALOAD_0     // Lrainbow/RainbowFields; this   (line 11)\n    | field-get(int rainbow.RainbowFields.a)\n    | |             GETFIELD rainbow.RainbowFields.a I\n    | field-get(int rainbow.RainbowFields.a)\n    |               IRETURN\n    method-execution(int rainbow.RainbowFields.getA())\n  end public int getA()\n\n  public void setA(int)    org.aspectj.weaver.MethodDeclarationLineNumber: 13:244\n:\n    method-execution(void rainbow.RainbowFields.setA(int))\n    |               ALOAD_0     // Lrainbow/RainbowFields; this   (line 14)\n    |               ILOAD_1     // I a\n    | field-set(int rainbow.RainbowFields.a)\n    | |             PUTFIELD rainbow.RainbowFields.a I\n    | field-set(int rainbow.RainbowFields.a)\n    |               RETURN   (line 15)\n    method-execution(void rainbow.RainbowFields.setA(int))\n  end public void setA(int)\n\n  public int getX()    org.aspectj.weaver.MethodDeclarationLineNumber: 16:290\n:\n    method-execution(int rainbow.RainbowFields.getX())\n    |               ALOAD_0     // Lrainbow/RainbowFields; this   (line 17)\n    | field-get(int rainbow.RainbowFields.x)\n    | |             GETFIELD rainbow.RainbowFields.x I\n    | field-get(int rainbow.RainbowFields.x)\n    |               IRETURN\n    method-execution(int rainbow.RainbowFields.getX())\n  end public int getX()\n\n  public void setX(int)    org.aspectj.weaver.MethodDeclarationLineNumber: 19:330\n:\n    method-execution(void rainbow.RainbowFields.setX(int))\n    |               ALOAD_0     // Lrainbow/RainbowFields; this   (line 20)\n    |               ILOAD_1     // I x\n    | field-set(int rainbow.RainbowFields.x)\n    | |             PUTFIELD rainbow.RainbowFields.x I\n    | field-set(int rainbow.RainbowFields.x)\n    |               RETURN   (line 21)\n    method-execution(void rainbow.RainbowFields.setX(int))\n  end public void setX(int)\n\n  public int getY()    org.aspectj.weaver.MethodDeclarationLineNumber: 22:376\n:\n    method-execution(int rainbow.RainbowFields.getY())\n    |               ALOAD_0     // Lrainbow/RainbowFields; this   (line 23)\n    | field-get(int rainbow.RainbowFields.y)\n    | |             GETFIELD rainbow.RainbowFields.y I\n    | field-get(int rainbow.RainbowFields.y)\n    |               IRETURN\n    method-execution(int rainbow.RainbowFields.getY())\n  end public int getY()\n\n  public void setY(int)    org.aspectj.weaver.MethodDeclarationLineNumber: 25:416\n:\n    method-execution(void rainbow.RainbowFields.setY(int))\n    |               ALOAD_0     // Lrainbow/RainbowFields; this   (line 26)\n    |               ILOAD_1     // I y\n    | field-set(int rainbow.RainbowFields.y)\n    | |             PUTFIELD rainbow.RainbowFields.y I\n    | field-set(int rainbow.RainbowFields.y)\n    |               RETURN   (line 27)\n    method-execution(void rainbow.RainbowFields.setY(int))\n  end public void setY(int)\n\n  public int getZ()    org.aspectj.weaver.MethodDeclarationLineNumber: 28:462\n:\n    method-execution(int rainbow.RainbowFields.getZ())\n    |               ALOAD_0     // Lrainbow/RainbowFields; this   (line 29)\n    | field-get(int rainbow.RainbowFields.z)\n    | |             GETFIELD rainbow.RainbowFields.z I\n    | field-get(int rainbow.RainbowFields.z)\n    |               IRETURN\n    method-execution(int rainbow.RainbowFields.getZ())\n  end public int getZ()\n\n  public void setZ(int)    org.aspectj.weaver.MethodDeclarationLineNumber: 31:502\n:\n    method-execution(void rainbow.RainbowFields.setZ(int))\n    |               ALOAD_0     // Lrainbow/RainbowFields; this   (line 32)\n    |               ILOAD_1     // I z\n    | field-set(int rainbow.RainbowFields.z)\n    | |             PUTFIELD rainbow.RainbowFields.z I\n    | field-set(int rainbow.RainbowFields.z)\n    |               RETURN   (line 33)\n    method-execution(void rainbow.RainbowFields.setZ(int))\n  end public void setZ(int)\n\nend public class rainbow.RainbowFields\n\nwhen implementing on shadow field-set(int rainbow.RainbowFields.a)\nwhen weaving type rainbow.RainbowFields\nwhen weaving classes \nwhen weaving \nwhen batch building BuildConfig[C:\\cygwin\\home\\Adrian\\projects\\aop-course-labs-and-samples-new\\.metadata\\.plugins\\org.eclipse.ajdt.core\\Pointcuts lab 3 - solution.generated.lst] #Files\u003d12",
    "works in cvs version, just not in latest AJDT for Eclipse 3.1...\n\n*** This bug has been marked as a duplicate of 138223 ***"
  ],
  "commentCreationDates": [
    "2006-06-02T14:17:33+02:00",
    "2006-06-02T14:38:39+02:00"
  ],
  "traces": [
    {
      "exceptionType": "org.aspectj.weaver.BCException",
      "elements": [
        {
          "method": "org.aspectj.weaver.patterns.AnnotationPointcut.findResidueInternal",
          "source": "AnnotationPointcut.java:199"
        },
        {
          "method": "org.aspectj.weaver.patterns.Pointcut.findResidue",
          "source": "Pointcut.java:267"
        },
        {
          "method": "org.aspectj.weaver.patterns.AndPointcut.findResidueInternal",
          "source": "AndPointcut.java:93"
        },
        {
          "method": "org.aspectj.weaver.patterns.Pointcut.findResidue",
          "source": "Pointcut.java:267"
        },
        {
          "method": "org.aspectj.weaver.patterns.AndPointcut.findResidueInternal",
          "source": "AndPointcut.java:93"
        },
        {
          "method": "org.aspectj.weaver.patterns.Pointcut.findResidue",
          "source": "Pointcut.java:267"
        },
        {
          "method": "org.aspectj.weaver.patterns.IfPointcut.findResidueInternal",
          "source": "IfPointcut.java:173"
        },
        {
          "method": "org.aspectj.weaver.patterns.Pointcut.findResidue",
          "source": "Pointcut.java:267"
        },
        {
          "method": "org.aspectj.weaver.patterns.AndPointcut.findResidueInternal",
          "source": "AndPointcut.java:93"
        },
        {
          "method": "org.aspectj.weaver.patterns.Pointcut.findResidue",
          "source": "Pointcut.java:267"
        },
        {
          "method": "org.aspectj.weaver.patterns.AndPointcut.findResidueInternal",
          "source": "AndPointcut.java:93"
        },
        {
          "method": "org.aspectj.weaver.patterns.Pointcut.findResidue",
          "source": "Pointcut.java:267"
        },
        {
          "method": "org.aspectj.weaver.patterns.NotPointcut.findResidueInternal",
          "source": "NotPointcut.java:96"
        },
        {
          "method": "org.aspectj.weaver.patterns.Pointcut.findResidue",
          "source": "Pointcut.java:267"
        },
        {
          "method": "org.aspectj.weaver.patterns.AndPointcut.findResidueInternal",
          "source": "AndPointcut.java:93"
        },
        {
          "method": "org.aspectj.weaver.patterns.Pointcut.findResidue",
          "source": "Pointcut.java:267"
        },
        {
          "method": "org.aspectj.weaver.patterns.AndPointcut.findResidueInternal",
          "source": "AndPointcut.java:93"
        },
        {
          "method": "org.aspectj.weaver.patterns.Pointcut.findResidue",
          "source": "Pointcut.java:267"
        },
        {
          "method": "org.aspectj.weaver.patterns.AndPointcut.findResidueInternal",
          "source": "AndPointcut.java:93"
        },
        {
          "method": "org.aspectj.weaver.patterns.Pointcut.findResidue",
          "source": "Pointcut.java:267"
        },
        {
          "method": "org.aspectj.weaver.bcel.BcelAdvice.specializeOn",
          "source": "BcelAdvice.java:132"
        },
        {
          "method": "org.aspectj.weaver.bcel.BcelShadow.prepareForMungers",
          "source": "BcelShadow.java:325"
        },
        {
          "method": "org.aspectj.weaver.Shadow.implement",
          "source": "Shadow.java:455"
        },
        {
          "method": "org.aspectj.weaver.bcel.BcelClassWeaver.implement",
          "source": "BcelClassWeaver.java:2236"
        },
        {
          "method": "org.aspectj.weaver.bcel.BcelClassWeaver.weave",
          "source": "BcelClassWeaver.java:491"
        },
        {
          "method": "org.aspectj.weaver.bcel.BcelClassWeaver.weave",
          "source": "BcelClassWeaver.java:109"
        },
        {
          "method": "org.aspectj.weaver.bcel.BcelWeaver.weave",
          "source": "BcelWeaver.java:1560"
        },
        {
          "method": "org.aspectj.weaver.bcel.BcelWeaver.weaveWithoutDump",
          "source": "BcelWeaver.java:1511"
        },
        {
          "method": "org.aspectj.weaver.bcel.BcelWeaver.weaveAndNotify",
          "source": "BcelWeaver.java:1291"
        },
        {
          "method": "org.aspectj.weaver.bcel.BcelWeaver.weave",
          "source": "BcelWeaver.java:1113"
        },
        {
          "method": "org.aspectj.ajdt.internal.compiler.AjCompilerAdapter.weave",
          "source": "AjCompilerAdapter.java:311"
        },
        {
          "method": "org.aspectj.ajdt.internal.compiler.AjCompilerAdapter.afterCompiling",
          "source": "AjCompilerAdapter.java:183"
        },
        {
          "method": "org.aspectj.ajdt.internal.compiler.CompilerAdapter.ajc$afterReturning$org_aspectj_ajdt_internal_compiler_CompilerAdapter$2$f9cc9ca0",
          "source": "CompilerAdapter.aj:70"
        },
        {
          "method": "org.aspectj.org.eclipse.jdt.internal.compiler.Compiler.compile",
          "source": "Compiler.java:367"
        },
        {
          "method": "org.aspectj.ajdt.internal.core.builder.AjBuildManager.performCompilation",
          "source": "AjBuildManager.java:862"
        },
        {
          "method": "org.aspectj.ajdt.internal.core.builder.AjBuildManager.doBuild",
          "source": "AjBuildManager.java:242"
        },
        {
          "method": "org.aspectj.ajdt.internal.core.builder.AjBuildManager.batchBuild",
          "source": "AjBuildManager.java:161"
        },
        {
          "method": "org.aspectj.ajde.internal.CompilerAdapter.compile",
          "source": "CompilerAdapter.java:122"
        },
        {
          "method": "org.aspectj.ajde.internal.AspectJBuildManager$CompilerThread.run",
          "source": "AspectJBuildManager.java:191"
        }
      ],
      "number": 0,
      "commentIndex": 0,
      "bugId": "145048",
      "duplicateId": "138223",
      "date": "2006-06-02T14:17:33+02:00",
      "product": "AspectJ",
      "component": "Compiler",
      "severity": "normal"
    }
  ],
  "groupId": "138223",
  "bugId": "145048",
  "duplicateId": "138223",
  "date": "2006-06-02T14:17:33+02:00",
  "product": "AspectJ",
  "component": "Compiler",
  "severity": "normal"
}