{
  "comments": [
    "The Pax Wicket bundle imports \"javax.crypto\" package, and that is resolved fine during the initial install. However, if I do a \"update\" on that bundle, I get the following stack trace.\n\n * The console reports that the package is exported by the System bundle.\n * org.ops4j.pax.wicket.service is exported by the bundle that we update.\n * Using the Equinox version from Bugzilla 144730 dated 6/6/06\n\n\norg.osgi.framework.BundleException: The bundle could not be resolved. Reason: \nMissing Constraint: Import-Package: javax.crypto; version\u003d\"0.0.0\", Package \nuses conflict: Import-Package: org.ops4j.pax.wicket.service; version\u003d\"0.0.0\", \nMissing Constraint: Import-Package: org.ops4j.pax.wicket.service; \nversion\u003d\"0.0.0\"\n        at \norg.eclipse.osgi.framework.internal.core.BundleHost.startWorker(BundleHost.java:294)\n        at \norg.eclipse.osgi.framework.internal.core.AbstractBundle.start(AbstractBundle.java:256)\n        at \norg.eclipse.osgi.framework.internal.core.FrameworkCommandProvider._start(FrameworkCommandProvider.java:239)\n        at sun.reflect.NativeMethodAccessorImpl.invoke0(Native Method)\n        at \nsun.reflect.NativeMethodAccessorImpl.invoke(NativeMethodAccessorImpl.java:39)\n        at \nsun.reflect.DelegatingMethodAccessorImpl.invoke(DelegatingMethodAccessorImpl.java:25)\n        at java.lang.reflect.Method.invoke(Method.java:585)\n        at \norg.eclipse.osgi.framework.internal.core.FrameworkCommandInterpreter.execute(FrameworkCommandInterpreter.java:145)\n        at \norg.eclipse.osgi.framework.internal.core.FrameworkConsole.docommand(FrameworkConsole.java:293)\n        at \norg.eclipse.osgi.framework.internal.core.FrameworkConsole.console(FrameworkConsole.java:278)\n        at \norg.eclipse.osgi.framework.internal.core.FrameworkConsole.run(FrameworkConsole.java:213)\n        at java.lang.Thread.run(Thread.java:595)",
    "Niclas, please attach the manifest to the Pax Wicket bundle.  Thanks.",
    "Created an attachment (id\u003d43822)\nBundle Manifest\n\n",
    "The performance fix in bug 144730 is not complete.  It needs an extra check when a bundle has been updated and its old bundle is pending removal.  Duping this bug to bug 144730 because the patch provided in that bug needs to be updated to fix this.\n\nTo work around the issue you can call PackageAdmin.refreshPackages on the bundle you updated.  From the console this can be done with the \"refresh\" command.\n\n*** This bug has been marked as a duplicate of 144730 ***"
  ],
  "commentCreationDates": [
    "2006-06-07T06:31:07+02:00",
    "2006-06-07T14:59:10+02:00",
    "2006-06-08T05:49:11+02:00",
    "2006-06-08T22:49:01+02:00"
  ],
  "traces": [
    {
      "exceptionType": "org.osgi.framework.BundleException",
      "message": "The bundle could not be resolved. Reason:  Missing Constraint: Import-Package: javax.crypto; version\u003d\"0.0.0\", Package  uses conflict: Import-Package: org.ops4j.pax.wicket.service; version\u003d\"0.0.0\",  Missing Constraint: Import-Package: org.ops4j.pax.wicket.service;  version\u003d\"0.0.0\"",
      "elements": [
        {
          "method": "org.eclipse.osgi.framework.internal.core.BundleHost.startWorker",
          "source": "BundleHost.java:294"
        },
        {
          "method": "org.eclipse.osgi.framework.internal.core.AbstractBundle.start",
          "source": "AbstractBundle.java:256"
        },
        {
          "method": "org.eclipse.osgi.framework.internal.core.FrameworkCommandProvider._start",
          "source": "FrameworkCommandProvider.java:239"
        },
        {
          "method": "sun.reflect.NativeMethodAccessorImpl.invoke0",
          "source": "Native Method"
        },
        {
          "method": "sun.reflect.NativeMethodAccessorImpl.invoke",
          "source": "NativeMethodAccessorImpl.java:39"
        },
        {
          "method": "sun.reflect.DelegatingMethodAccessorImpl.invoke",
          "source": "DelegatingMethodAccessorImpl.java:25"
        },
        {
          "method": "java.lang.reflect.Method.invoke",
          "source": "Method.java:585"
        },
        {
          "method": "org.eclipse.osgi.framework.internal.core.FrameworkCommandInterpreter.execute",
          "source": "FrameworkCommandInterpreter.java:145"
        },
        {
          "method": "org.eclipse.osgi.framework.internal.core.FrameworkConsole.docommand",
          "source": "FrameworkConsole.java:293"
        },
        {
          "method": "org.eclipse.osgi.framework.internal.core.FrameworkConsole.console",
          "source": "FrameworkConsole.java:278"
        },
        {
          "method": "org.eclipse.osgi.framework.internal.core.FrameworkConsole.run",
          "source": "FrameworkConsole.java:213"
        },
        {
          "method": "java.lang.Thread.run",
          "source": "Thread.java:595"
        }
      ],
      "number": 0,
      "commentIndex": 0,
      "bugId": "145692",
      "duplicateId": "144730",
      "date": "2006-06-07T06:31:07+02:00",
      "product": "Equinox",
      "component": "Framework",
      "severity": "normal"
    }
  ],
  "groupId": "144730",
  "bugId": "145692",
  "duplicateId": "144730",
  "date": "2006-06-07T06:31:07+02:00",
  "product": "Equinox",
  "component": "Framework",
  "severity": "normal"
}