{
  "comments": [
    "The followign stacktrace appeared in an e-mail someone sent me. The problme is that the shutdown of TeamUIPlugin does a Team.getSynchronizeManager. This may be the first call to get the manager and hence may cause classes to be loaded. The code should be refactored to avoid loading the class on shutdown.\n\n!ENTRY org.eclipse.osgi 4 0 2006-06-05 14:15:28.454 \n!MESSAGE Error while stopping \"org.eclipse.team.ui_3.2.0.I200605181830\". \n!STACK 0 \norg.osgi.framework.BundleException: Exception in org.eclipse.team.internal.ui.TeamUIPlugin.stop() of bundle org.eclipse.team.ui. \n        at org.eclipse.osgi.framework.internal.core.BundleContextImpl.stop(BundleContextImpl.java:1052) \n        at org.eclipse.osgi.framework.internal.core.BundleHost.stopWorker(BundleHost.java:396) \n        at org.eclipse.osgi.framework.internal.core.AbstractBundle.stop(AbstractBundle.java:400) \n        at org.eclipse.core.runtime.internal.adaptor.BundleStopper.basicStopBundles(BundleStopper.java:86) \n        at org.eclipse.core.runtime.internal.adaptor.BundleStopper.stopBundles(BundleStopper.java:73) \n        at org.eclipse.core.runtime.internal.adaptor.EclipseAdaptorHook.frameworkStopping(EclipseAdaptorHook.java:156) \n        at org.eclipse.osgi.baseadaptor.BaseAdaptor.frameworkStopping(BaseAdaptor.java:288) \n        at org.eclipse.osgi.framework.internal.core.Framework.shutdown(Framework.java:529) \n        at org.eclipse.osgi.framework.internal.core.Framework.close(Framework.java:440) \n        at org.eclipse.osgi.framework.internal.core.OSGi.close(OSGi.java:41) \n        at org.eclipse.core.runtime.adaptor.EclipseStarter.shutdown(EclipseStarter.java:423) \n        at org.eclipse.core.runtime.adaptor.EclipseStarter.run(EclipseStarter.java:193) \n        at sun.reflect.NativeMethodAccessorImpl.invoke0(Native Method) \n        at sun.reflect.NativeMethodAccessorImpl.invoke(NativeMethodAccessorImpl.java:64) \n        at sun.reflect.DelegatingMethodAccessorImpl.invoke(DelegatingMethodAccessorImpl.java:43) \n        at java.lang.reflect.Method.invoke(Method.java:615) \n        at org.eclipse.core.launcher.Main.invokeFramework(Main.java:336) \n        at org.eclipse.core.launcher.Main.basicRun(Main.java:280) \n        at org.eclipse.core.launcher.Main.run(Main.java:977) \n        at org.eclipse.core.launcher.Main.main(Main.java:952) \nCaused by: java.lang.NoClassDefFoundError: org.eclipse.ui.Saveable \n        at java.lang.J9VMInternals.verifyImpl(Native Method) \n        at java.lang.J9VMInternals.verify(J9VMInternals.java:59) \n        at java.lang.J9VMInternals.initialize(J9VMInternals.java:120) \n        at org.eclipse.team.ui.TeamUI.getSynchronizeManager(TeamUI.java:52) \n        at org.eclipse.team.internal.ui.TeamUIPlugin.stop(TeamUIPlugin.java:231) \n        at org.eclipse.osgi.framework.internal.core.BundleContextImpl$3.run(BundleContextImpl.java:1036) \n        at java.security.AccessController.doPrivileged(AccessController.java:241) \n        at org.eclipse.osgi.framework.internal.core.BundleContextImpl.stop(BundleContextImpl.java:1032)",
    "Fixed",
    "*** Bug 158239 has been marked as a duplicate of this bug. ***"
  ],
  "commentCreationDates": [
    "2006-06-13T17:15:07+02:00",
    "2006-06-21T21:49:51+02:00",
    "2006-09-22T16:23:57+02:00"
  ],
  "traces": [
    {
      "exceptionType": "org.osgi.framework.BundleException",
      "message": "Exception in org.eclipse.team.internal.ui.TeamUIPlugin.stop() of bundle org.eclipse.team.ui.",
      "elements": [
        {
          "method": "org.eclipse.osgi.framework.internal.core.BundleContextImpl.stop",
          "source": "BundleContextImpl.java:1052"
        },
        {
          "method": "org.eclipse.osgi.framework.internal.core.BundleHost.stopWorker",
          "source": "BundleHost.java:396"
        },
        {
          "method": "org.eclipse.osgi.framework.internal.core.AbstractBundle.stop",
          "source": "AbstractBundle.java:400"
        },
        {
          "method": "org.eclipse.core.runtime.internal.adaptor.BundleStopper.basicStopBundles",
          "source": "BundleStopper.java:86"
        },
        {
          "method": "org.eclipse.core.runtime.internal.adaptor.BundleStopper.stopBundles",
          "source": "BundleStopper.java:73"
        },
        {
          "method": "org.eclipse.core.runtime.internal.adaptor.EclipseAdaptorHook.frameworkStopping",
          "source": "EclipseAdaptorHook.java:156"
        },
        {
          "method": "org.eclipse.osgi.baseadaptor.BaseAdaptor.frameworkStopping",
          "source": "BaseAdaptor.java:288"
        },
        {
          "method": "org.eclipse.osgi.framework.internal.core.Framework.shutdown",
          "source": "Framework.java:529"
        },
        {
          "method": "org.eclipse.osgi.framework.internal.core.Framework.close",
          "source": "Framework.java:440"
        },
        {
          "method": "org.eclipse.osgi.framework.internal.core.OSGi.close",
          "source": "OSGi.java:41"
        },
        {
          "method": "org.eclipse.core.runtime.adaptor.EclipseStarter.shutdown",
          "source": "EclipseStarter.java:423"
        },
        {
          "method": "org.eclipse.core.runtime.adaptor.EclipseStarter.run",
          "source": "EclipseStarter.java:193"
        },
        {
          "method": "sun.reflect.NativeMethodAccessorImpl.invoke0",
          "source": "Native Method"
        },
        {
          "method": "sun.reflect.NativeMethodAccessorImpl.invoke",
          "source": "NativeMethodAccessorImpl.java:64"
        },
        {
          "method": "sun.reflect.DelegatingMethodAccessorImpl.invoke",
          "source": "DelegatingMethodAccessorImpl.java:43"
        },
        {
          "method": "java.lang.reflect.Method.invoke",
          "source": "Method.java:615"
        },
        {
          "method": "org.eclipse.core.launcher.Main.invokeFramework",
          "source": "Main.java:336"
        },
        {
          "method": "org.eclipse.core.launcher.Main.basicRun",
          "source": "Main.java:280"
        },
        {
          "method": "org.eclipse.core.launcher.Main.run",
          "source": "Main.java:977"
        },
        {
          "method": "org.eclipse.core.launcher.Main.main",
          "source": "Main.java:952"
        }
      ],
      "causedBy": {
        "exceptionType": "java.lang.NoClassDefFoundError",
        "message": "org.eclipse.ui.Saveable",
        "elements": [
          {
            "method": "java.lang.J9VMInternals.verifyImpl",
            "source": "Native Method"
          },
          {
            "method": "java.lang.J9VMInternals.verify",
            "source": "J9VMInternals.java:59"
          },
          {
            "method": "java.lang.J9VMInternals.initialize",
            "source": "J9VMInternals.java:120"
          },
          {
            "method": "org.eclipse.team.ui.TeamUI.getSynchronizeManager",
            "source": "TeamUI.java:52"
          },
          {
            "method": "org.eclipse.team.internal.ui.TeamUIPlugin.stop",
            "source": "TeamUIPlugin.java:231"
          },
          {
            "method": "org.eclipse.osgi.framework.internal.core.BundleContextImpl$3.run",
            "source": "BundleContextImpl.java:1036"
          },
          {
            "method": "java.security.AccessController.doPrivileged",
            "source": "AccessController.java:241"
          },
          {
            "method": "org.eclipse.osgi.framework.internal.core.BundleContextImpl.stop",
            "source": "BundleContextImpl.java:1032"
          }
        ],
        "number": 0,
        "commentIndex": 0
      },
      "number": 0,
      "commentIndex": 0,
      "bugId": "146847",
      "date": "2006-06-13T17:15:07+02:00",
      "product": "Platform",
      "component": "Team",
      "severity": "normal"
    }
  ],
  "groupId": "146847",
  "bugId": "146847",
  "date": "2006-06-13T17:15:07+02:00",
  "product": "Platform",
  "component": "Team",
  "severity": "normal"
}