{
  "comments": [
    "Using build M20060609-1217.\n\nI have some changes in my workspace and I want to reset them. So, in Synchronize view, I select all my changes and click on \"Override and Update...\" popup-menu item. Strangly, nothing happen...\n\nLooking at console, I see following stack trace:\n!ENTRY org.eclipse.ui 4 4 2006-06-13 16:03:52.468\n!MESSAGE Unhandled event loop exception\n\n!ENTRY org.eclipse.ui 4 0 2006-06-13 16:03:52.468\n!MESSAGE java.lang.NullPointerException\n!STACK 0\njava.lang.NullPointerException\n        at org.eclipse.team.internal.ui.mapping.ResourceModelProviderOperation.isResourcePath(ResourceModelProviderOperation.java:137)\n        at org.eclipse.team.internal.ui.mapping.ResourceModelProviderOperation.getTraversals(ResourceModelProviderOperation.java:110)\n        at org.eclipse.team.internal.ui.mapping.ResourceModelProviderOperation.getFileDeltas(ResourceModelProviderOperation.java:68)\n        at org.eclipse.team.internal.ui.mapping.ResourceModelProviderOperation.getFileDeltas(ResourceModelProviderOperation.java:57)\n        at org.eclipse.team.internal.ui.mapping.ResourceModelProviderOperation.getTargetDiffs(ResourceModelProviderOperation.java:163)\n        at org.eclipse.team.internal.ui.mapping.ResourceMergeHandler$1.getJobName(ResourceMergeHandler.java:84)\n        at org.eclipse.team.ui.TeamOperation$TeamOperationJobContext.\u003cinit\u003e(TeamOperation.java:65)\n        at org.eclipse.team.ui.TeamOperation.getRunnableContext(TeamOperation.java:351)\n        at org.eclipse.team.ui.TeamOperation.run(TeamOperation.java:159)\n        at org.eclipse.team.ui.mapping.MergeActionHandler.execute(MergeActionHandler.java:152)\n        at org.eclipse.team.internal.ui.mapping.ResourceMergeHandler.execute(ResourceMergeHandler.java:117)\n        at org.eclipse.ltk.ui.refactoring.model.RefactoringSynchronizationActionProvider$RefactoringHandlerDelegate.execute(RefactoringSynchronizationActionProvider.java:100)\n        at org.eclipse.team.internal.ui.mapping.MergeAction.runWithEvent(MergeAction.java:80)\n        at org.eclipse.jface.action.ActionContributionItem.handleWidgetSelection(ActionContributionItem.java:539)\n        at org.eclipse.jface.action.ActionContributionItem.access$2(ActionContributionItem.java:488)\n        at org.eclipse.jface.action.ActionContributionItem$5.handleEvent(ActionContributionItem.java:400)\n        at org.eclipse.swt.widgets.EventTable.sendEvent(EventTable.java:66)\n        at org.eclipse.swt.widgets.Widget.sendEvent(Widget.java:928)\n        at org.eclipse.swt.widgets.Display.runDeferredEvents(Display.java:3348)\n        at org.eclipse.swt.widgets.Display.readAndDispatch(Display.java:2968)\n        at org.eclipse.ui.internal.Workbench.runEventLoop(Workbench.java:1914)\n        at org.eclipse.ui.internal.Workbench.runUI(Workbench.java:1878)\n        at org.eclipse.ui.internal.Workbench.createAndRunWorkbench(Workbench.java:419)\n        at org.eclipse.ui.PlatformUI.createAndRunWorkbench(PlatformUI.java:149)\n        at org.eclipse.ui.internal.ide.IDEApplication.run(IDEApplication.java:95)\n        at org.eclipse.core.internal.runtime.PlatformActivator$1.run(PlatformActivator.java:78)\n        at org.eclipse.core.runtime.internal.adaptor.EclipseAppLauncher.runApplication(EclipseAppLauncher.java:92)\n        at org.eclipse.core.runtime.internal.adaptor.EclipseAppLauncher.start(EclipseAppLauncher.java:68)\n        at org.eclipse.core.runtime.adaptor.EclipseStarter.run(EclipseStarter.java:400)\n        at org.eclipse.core.runtime.adaptor.EclipseStarter.run(EclipseStarter.java:177)\n        at sun.reflect.NativeMethodAccessorImpl.invoke0(Native Method)\n        at sun.reflect.NativeMethodAccessorImpl.invoke(NativeMethodAccessorImpl.java:39)\n        at sun.reflect.DelegatingMethodAccessorImpl.invoke(DelegatingMethodAccessorImpl.java:25)\n        at java.lang.reflect.Method.invoke(Method.java:324)\n        at org.eclipse.core.launcher.Main.invokeFramework(Main.java:336)\n        at org.eclipse.core.launcher.Main.basicRun(Main.java:280)\n        at org.eclipse.core.launcher.Main.run(Main.java:977)\n        at org.eclipse.core.launcher.Main.main(Main.java:952)\n\nUpdate projects (without overriding), reset perspective, exit/restart session do not fix the problem. The only workaround if found to cancel my wksp changes was to use \"Replace with...\" action...\n\nNote that this problem was reproduceable after having made new changes on replaced contents...\n\nLet me know if you need more info (the complete workpsace for example) to help you to reproduce.",
    "Could you provide a set of steps starting from an empty workspace to produce the problem? Or, if that is not practical, can you describe the state of your workspace (i.e. how many projects in your workspace, how many projects did you sync, did you configure the sync view at all or are you using the default settings, etc)?",
    "Unfortunately (or fortunately), this issue only occurs in one of my workspaces. I cannot reproduce neither in other existing ones nor in a brand new one.\n\nAbout my workspace stats:\n - 15 projects in it (some locals, some on dev.eclipse.org, one on local\n      repository)\n - 6 items in my synchronize view (dev.eclipse.org and local repositories)\n - I\u0027m using a specific Team perspective I\u0027ve renamed \u0027Ffr Synchronizing\u0027\n   (note that NPE also occurs if I try to \u0027Override and Update\u0027 in Team \n    Synchronizing perspective)\n\nI can send my zipped workspace if this can help.\n",
    "Sure, send me your workspace and I\u0027ll have a look. ",
    "First downsize severity as this issue cannot be reproduceable in any other wksp...\n",
    "Created an attachment (id\u003d45039)\nPatch to protect against the NPE\n\nI wasn\u0027t able to reproduce the problem but the it turns out top be fairly straightforward to fix. I\u0027m attaching a patch since it should be safe to apply the fix to 3.2.1 as well.",
    "I\u0027ve released the patch to HEAD. We\u0027ll elease it to 3.2.1 once 3.2 ships.",
    "*** Bug 149377 has been marked as a duplicate of this bug. ***",
    "Fix released to 3.2.1.",
    "Verified in M20060830-0800",
    "*** Bug 156035 has been marked as a duplicate of this bug. ***"
  ],
  "commentCreationDates": [
    "2006-06-13T16:27:49+02:00",
    "2006-06-13T16:49:22+02:00",
    "2006-06-13T17:54:13+02:00",
    "2006-06-13T20:57:42+02:00",
    "2006-06-14T09:41:33+02:00",
    "2006-06-21T22:16:18+02:00",
    "2006-06-21T22:18:26+02:00",
    "2006-07-05T16:59:32+02:00",
    "2006-07-06T21:51:31+02:00",
    "2006-08-31T15:17:49+02:00",
    "2006-09-05T16:44:45+02:00"
  ],
  "traces": [
    {
      "exceptionType": "java.lang.NullPointerException",
      "elements": [
        {
          "method": "org.eclipse.team.internal.ui.mapping.ResourceModelProviderOperation.isResourcePath",
          "source": "ResourceModelProviderOperation.java:137"
        },
        {
          "method": "org.eclipse.team.internal.ui.mapping.ResourceModelProviderOperation.getTraversals",
          "source": "ResourceModelProviderOperation.java:110"
        },
        {
          "method": "org.eclipse.team.internal.ui.mapping.ResourceModelProviderOperation.getFileDeltas",
          "source": "ResourceModelProviderOperation.java:68"
        },
        {
          "method": "org.eclipse.team.internal.ui.mapping.ResourceModelProviderOperation.getFileDeltas",
          "source": "ResourceModelProviderOperation.java:57"
        },
        {
          "method": "org.eclipse.team.internal.ui.mapping.ResourceModelProviderOperation.getTargetDiffs",
          "source": "ResourceModelProviderOperation.java:163"
        },
        {
          "method": "org.eclipse.team.internal.ui.mapping.ResourceMergeHandler$1.getJobName",
          "source": "ResourceMergeHandler.java:84"
        },
        {
          "method": "org.eclipse.team.ui.TeamOperation$TeamOperationJobContext.\u003cinit\u003e",
          "source": "TeamOperation.java:65"
        },
        {
          "method": "org.eclipse.team.ui.TeamOperation.getRunnableContext",
          "source": "TeamOperation.java:351"
        },
        {
          "method": "org.eclipse.team.ui.TeamOperation.run",
          "source": "TeamOperation.java:159"
        },
        {
          "method": "org.eclipse.team.ui.mapping.MergeActionHandler.execute",
          "source": "MergeActionHandler.java:152"
        },
        {
          "method": "org.eclipse.team.internal.ui.mapping.ResourceMergeHandler.execute",
          "source": "ResourceMergeHandler.java:117"
        },
        {
          "method": "org.eclipse.ltk.ui.refactoring.model.RefactoringSynchronizationActionProvider$RefactoringHandlerDelegate.execute",
          "source": "RefactoringSynchronizationActionProvider.java:100"
        },
        {
          "method": "org.eclipse.team.internal.ui.mapping.MergeAction.runWithEvent",
          "source": "MergeAction.java:80"
        },
        {
          "method": "org.eclipse.jface.action.ActionContributionItem.handleWidgetSelection",
          "source": "ActionContributionItem.java:539"
        },
        {
          "method": "org.eclipse.jface.action.ActionContributionItem.access$2",
          "source": "ActionContributionItem.java:488"
        },
        {
          "method": "org.eclipse.jface.action.ActionContributionItem$5.handleEvent",
          "source": "ActionContributionItem.java:400"
        },
        {
          "method": "org.eclipse.swt.widgets.EventTable.sendEvent",
          "source": "EventTable.java:66"
        },
        {
          "method": "org.eclipse.swt.widgets.Widget.sendEvent",
          "source": "Widget.java:928"
        },
        {
          "method": "org.eclipse.swt.widgets.Display.runDeferredEvents",
          "source": "Display.java:3348"
        },
        {
          "method": "org.eclipse.swt.widgets.Display.readAndDispatch",
          "source": "Display.java:2968"
        },
        {
          "method": "org.eclipse.ui.internal.Workbench.runEventLoop",
          "source": "Workbench.java:1914"
        },
        {
          "method": "org.eclipse.ui.internal.Workbench.runUI",
          "source": "Workbench.java:1878"
        },
        {
          "method": "org.eclipse.ui.internal.Workbench.createAndRunWorkbench",
          "source": "Workbench.java:419"
        },
        {
          "method": "org.eclipse.ui.PlatformUI.createAndRunWorkbench",
          "source": "PlatformUI.java:149"
        },
        {
          "method": "org.eclipse.ui.internal.ide.IDEApplication.run",
          "source": "IDEApplication.java:95"
        },
        {
          "method": "org.eclipse.core.internal.runtime.PlatformActivator$1.run",
          "source": "PlatformActivator.java:78"
        },
        {
          "method": "org.eclipse.core.runtime.internal.adaptor.EclipseAppLauncher.runApplication",
          "source": "EclipseAppLauncher.java:92"
        },
        {
          "method": "org.eclipse.core.runtime.internal.adaptor.EclipseAppLauncher.start",
          "source": "EclipseAppLauncher.java:68"
        },
        {
          "method": "org.eclipse.core.runtime.adaptor.EclipseStarter.run",
          "source": "EclipseStarter.java:400"
        },
        {
          "method": "org.eclipse.core.runtime.adaptor.EclipseStarter.run",
          "source": "EclipseStarter.java:177"
        },
        {
          "method": "sun.reflect.NativeMethodAccessorImpl.invoke0",
          "source": "Native Method"
        },
        {
          "method": "sun.reflect.NativeMethodAccessorImpl.invoke",
          "source": "NativeMethodAccessorImpl.java:39"
        },
        {
          "method": "sun.reflect.DelegatingMethodAccessorImpl.invoke",
          "source": "DelegatingMethodAccessorImpl.java:25"
        },
        {
          "method": "java.lang.reflect.Method.invoke",
          "source": "Method.java:324"
        },
        {
          "method": "org.eclipse.core.launcher.Main.invokeFramework",
          "source": "Main.java:336"
        },
        {
          "method": "org.eclipse.core.launcher.Main.basicRun",
          "source": "Main.java:280"
        },
        {
          "method": "org.eclipse.core.launcher.Main.run",
          "source": "Main.java:977"
        },
        {
          "method": "org.eclipse.core.launcher.Main.main",
          "source": "Main.java:952"
        }
      ],
      "number": 0,
      "commentIndex": 0,
      "bugId": "146833",
      "date": "2006-06-13T16:27:49+02:00",
      "product": "Platform",
      "component": "Team",
      "severity": "normal"
    }
  ],
  "groupId": "146833",
  "bugId": "146833",
  "date": "2006-06-13T16:27:49+02:00",
  "product": "Platform",
  "component": "Team",
  "severity": "normal"
}