{
  "comments": [
    "\u003e\u003e\u003e Environment: WinXP + Java 1.5.0_06 + Eclipse 3.2 RC/ + EMF 2.2.0 RC7 + ECF 0.8.5 \nFurthermore,  we have downloaded from CVS the projects\n- org.eclipse.ecf\n- org.eclipse.ecf.discovery\n- org.eclipse.ecf.example.collab\n- org.eclipse.ecf.presence\n- org.eclipse.ecf.provider\n- org.eclipse.ecf.ui\n\n\u003e\u003e\u003e Steps to reproduce: \n\n- Start the ServerApplication: we have started the ServerApplication \n  - BOTH from the projects in the workspace by the menu ?Run? AND from the installed package by command shell  \n    (once at a time, of course) and we have the above mentioned exception. \n- Start the clients: we have started \n  - BOTH the client installed IN Eclipse AND the ?ECF Example Collab Client? \n    once at a time and at the same time, on the same pc and on several pc, and we have the same exception.\n \n-  Start the collaboration: we select ?Connect Workspace (new Dialog)? from ECF menu and specify the protocol ?ECF Generic? and Group ID   \t      ?ecftcp://***.***.***.***:3282/server?.\n\nThe connection and presence awareness work well.\n\n- Select ?send file?: Both ?Send file to X? and ?Send File? (to group) allow to choose the file and then they fail launching an exception (that follows) on the client who has requested to send the file. After the communication error, the client goes on (doesn?t crash) while others clients don?t notice anything.\n\n\u003e\u003e\u003e The exception is the following:\norg.eclipse.ecf.core.SharedObjectCreateException: Container GUID[ea_dOe1hV.l_79dNeFQuDN0R9L0-] had exception creating shared object GUID[P9MuuQAIDVCBlkXh3fyhNCgVXP4-]: java.lang.ClassNotFoundException: org.eclipse.ecf.example.collab.share.io.EclipseFileTransfer\n\tat org.eclipse.osgi.framework.internal.core.BundleLoader.findClass(BundleLoader.java:407)\n\tat org.eclipse.osgi.framework.internal.core.BundleLoader.findClass(BundleLoader.java:352)\n\tat org.eclipse.osgi.internal.baseadaptor.DefaultClassLoader.loadClass(DefaultClassLoader.java:83)\n\tat java.lang.ClassLoader.loadClass(Unknown Source)\n\tat java.lang.ClassLoader.loadClassInternal(Unknown Source)\n\tat java.lang.Class.forName0(Native Method)\n\tat java.lang.Class.forName(Unknown Source)\n\tat org.eclipse.ecf.provider.generic.SOManager.loadSharedObject(SOManager.java:135)\n\tat org.eclipse.ecf.provider.generic.SOManager.createSharedObject(SOManager.java:171)\n\tat org.eclipse.ecf.example.collab.share.GenericSharedObject.createObject(GenericSharedObject.java:478)\n\tat org.eclipse.ecf.example.collab.share.EclipseCollabSharedObject.createObject(EclipseCollabSharedObject.java:1217)\n\tat org.eclipse.ecf.example.collab.ui.LineChatClientView.createObject(LineChatClientView.java:322)\n\tat org.eclipse.ecf.example.collab.ui.ChatComposite$37.run(ChatComposite.java:1126)\n- \tat java.lang.Thread.run(Unknown Source)",
    "Fixed in 0.8.6 stable.  Problem was that I changed the buddy classloading structure for 0.8.5 and forgot to change one spot where classes were being loaded in generic provider."
  ],
  "commentCreationDates": [
    "2006-06-15T13:06:26+02:00",
    "2006-06-19T00:44:18+02:00"
  ],
  "traces": [
    {
      "exceptionType": "java.lang.ClassNotFoundException",
      "message": "org.eclipse.ecf.example.collab.share.io.EclipseFileTransfer",
      "elements": [
        {
          "method": "org.eclipse.osgi.framework.internal.core.BundleLoader.findClass",
          "source": "BundleLoader.java:407"
        },
        {
          "method": "org.eclipse.osgi.framework.internal.core.BundleLoader.findClass",
          "source": "BundleLoader.java:352"
        },
        {
          "method": "org.eclipse.osgi.internal.baseadaptor.DefaultClassLoader.loadClass",
          "source": "DefaultClassLoader.java:83"
        },
        {
          "method": "java.lang.ClassLoader.loadClass",
          "source": "Unknown Source"
        },
        {
          "method": "java.lang.ClassLoader.loadClassInternal",
          "source": "Unknown Source"
        },
        {
          "method": "java.lang.Class.forName0",
          "source": "Native Method"
        },
        {
          "method": "java.lang.Class.forName",
          "source": "Unknown Source"
        },
        {
          "method": "org.eclipse.ecf.provider.generic.SOManager.loadSharedObject",
          "source": "SOManager.java:135"
        },
        {
          "method": "org.eclipse.ecf.provider.generic.SOManager.createSharedObject",
          "source": "SOManager.java:171"
        },
        {
          "method": "org.eclipse.ecf.example.collab.share.GenericSharedObject.createObject",
          "source": "GenericSharedObject.java:478"
        },
        {
          "method": "org.eclipse.ecf.example.collab.share.EclipseCollabSharedObject.createObject",
          "source": "EclipseCollabSharedObject.java:1217"
        },
        {
          "method": "org.eclipse.ecf.example.collab.ui.LineChatClientView.createObject",
          "source": "LineChatClientView.java:322"
        },
        {
          "method": "org.eclipse.ecf.example.collab.ui.ChatComposite$37.run",
          "source": "ChatComposite.java:1126"
        }
      ],
      "number": 0,
      "commentIndex": 0,
      "bugId": "147269",
      "date": "2006-06-15T13:06:26+02:00",
      "product": "ECF",
      "component": "ecf.examples",
      "severity": "major"
    }
  ],
  "groupId": "147269",
  "bugId": "147269",
  "date": "2006-06-15T13:06:26+02:00",
  "product": "ECF",
  "component": "ecf.examples",
  "severity": "major"
}