{
  "comments": [
    "I hit the below exception when closing an EAR project referencing an open EJB project.\n\njava.lang.NullPointerException\n        at org.eclipse.jst.j2ee.internal.common.classpath.J2EEComponentClasspathUpdater.resourceChanged(J2EEComponentClasspat\nhUpdater.java:459)\n        at org.eclipse.core.internal.events.NotificationManager$2.run(NotificationManager.java:280)\n        at org.eclipse.core.runtime.SafeRunner.run(SafeRunner.java:37)\n        at org.eclipse.core.internal.events.NotificationManager.notify(NotificationManager.java:274)\n        at org.eclipse.core.internal.events.NotificationManager.broadcastChanges(NotificationManager.java:148)\n        at org.eclipse.core.internal.resources.Workspace.broadcastPostChange(Workspace.java:256)\n        at org.eclipse.core.internal.resources.Workspace.endOperation(Workspace.java:958)\n        at org.eclipse.core.internal.resources.InternalWorkspaceJob.run(InternalWorkspaceJob.java:45)\n        at org.eclipse.core.internal.jobs.Worker.run(Worker.java:58)",
    "code checked in.",
    "closing"
  ],
  "commentCreationDates": [
    "2006-06-25T17:34:24+02:00",
    "2006-07-12T20:34:54+02:00",
    "2006-07-12T20:35:11+02:00"
  ],
  "traces": [
    {
      "exceptionType": "java.lang.NullPointerException",
      "elements": [
        {
          "method": "org.eclipse.jst.j2ee.internal.common.classpath.J2EEComponentClasspathUpdater.resourceChanged",
          "source": "J2EEComponentClasspat hUpdater.java:459"
        },
        {
          "method": "org.eclipse.core.internal.events.NotificationManager$2.run",
          "source": "NotificationManager.java:280"
        },
        {
          "method": "org.eclipse.core.runtime.SafeRunner.run",
          "source": "SafeRunner.java:37"
        },
        {
          "method": "org.eclipse.core.internal.events.NotificationManager.notify",
          "source": "NotificationManager.java:274"
        },
        {
          "method": "org.eclipse.core.internal.events.NotificationManager.broadcastChanges",
          "source": "NotificationManager.java:148"
        },
        {
          "method": "org.eclipse.core.internal.resources.Workspace.broadcastPostChange",
          "source": "Workspace.java:256"
        },
        {
          "method": "org.eclipse.core.internal.resources.Workspace.endOperation",
          "source": "Workspace.java:958"
        },
        {
          "method": "org.eclipse.core.internal.resources.InternalWorkspaceJob.run",
          "source": "InternalWorkspaceJob.java:45"
        },
        {
          "method": "org.eclipse.core.internal.jobs.Worker.run",
          "source": "Worker.java:58"
        }
      ],
      "number": 0,
      "commentIndex": 0,
      "bugId": "148569",
      "date": "2006-06-25T17:34:24+02:00",
      "product": "Web Tools",
      "component": "jst.j2ee",
      "severity": "normal"
    }
  ],
  "groupId": "148569",
  "bugId": "148569",
  "date": "2006-06-25T17:34:24+02:00",
  "product": "Web Tools",
  "component": "jst.j2ee",
  "severity": "normal"
}