{
  "comments": [
    "select  Run-\u003eDebug\nselect Remote Java Application\nclick the \"new\" icon\nNow I get a form for creating a new configuration\ntype in a name\nselect a Project\nselect a project by clicking the browse button\nuse the defaultvalues for host and port\nclick apply\nclick debug\n\nNow I get the following errormessage:\n\nLaunch configuration New_configuration at /Users/kajh/Documents/workspace/.metadata/.plugins/org.eclipse.debug.core/.launches/New_configuration.launch does not exist.\n\nI have tried to delete?$PATH_TO_WORKSPACE/workspace/.metadata/.plugins/org.eclipse.debug.core but that didn\u0027t help.\n\nI\u0027m using eclipse 3.2RC7 on MacOS X 10.4.6 with java 1.5.0_06-112",
    "I get the following stacktrace in my eclipse log:\n\n!ENTRY org.eclipse.debug.ui 4 120 2006-06-26 13:14:34.264\n!MESSAGE Error logged from Debug UI: \n!STACK 1\norg.eclipse.debug.core.DebugException: Launch configuration New_configuration at /Users/kajh/Documents/workspace/.metadata/.plugins/org.eclipse.debug.core/.launches/New_configuration.launch does not exist.\n        at org.eclipse.debug.internal.core.LaunchManager.createDebugException(LaunchManager.java:784)\n        at org.eclipse.debug.internal.core.LaunchManager.getInfo(LaunchManager.java:1181)\n        at org.eclipse.debug.internal.core.LaunchConfiguration.getInfo(LaunchConfiguration.java:356)\n        at org.eclipse.debug.internal.core.LaunchConfiguration.getAttribute(LaunchConfiguration.java:257)\n        at org.eclipse.debug.ui.DebugUITools.launch(DebugUITools.java:511)\n        at org.eclipse.debug.internal.ui.launchConfigurations.LaunchConfigurationsDialog.handleLaunchPressed(LaunchConfigurationsDialog.java:955)\n        at org.eclipse.debug.internal.ui.launchConfigurations.LaunchConfigurationsDialog.buttonPressed(LaunchConfigurationsDialog.java:304)\n        at org.eclipse.jface.dialogs.Dialog$3.widgetSelected(Dialog.java:660)\n        at org.eclipse.swt.widgets.TypedListener.handleEvent(TypedListener.java:90)\n        at org.eclipse.swt.widgets.EventTable.sendEvent(EventTable.java:66)\n        at org.eclipse.swt.widgets.Widget.sendEvent(Widget.java:1496)\n        at org.eclipse.swt.widgets.Widget.sendEvent(Widget.java:1520)\n        at org.eclipse.swt.widgets.Widget.sendEvent(Widget.java:1505)\n        at org.eclipse.swt.widgets.Widget.notifyListeners(Widget.java:1279)\n        at org.eclipse.swt.widgets.Display.runDeferredEvents(Display.java:3312)\n        at org.eclipse.swt.widgets.Display.readAndDispatch(Display.java:2941)\n        at org.eclipse.jface.window.Window.runEventLoop(Window.java:820)\n        at org.eclipse.jface.window.Window.open(Window.java:796)\n        at org.eclipse.debug.internal.ui.launchConfigurations.LaunchConfigurationsDialog.open(LaunchConfigurationsDialog.java:1086)\n        at org.eclipse.debug.ui.DebugUITools$1.run(DebugUITools.java:375)\n        at org.eclipse.swt.custom.BusyIndicator.showWhile(BusyIndicator.java:67)\n        at org.eclipse.debug.ui.DebugUITools.openLaunchConfigurationDialogOnGroup(DebugUITools.java:379)\n        at org.eclipse.debug.ui.DebugUITools.openLaunchConfigurationDialogOnGroup(DebugUITools.java:321)\n        at org.eclipse.debug.ui.actions.OpenLaunchDialogAction.run(OpenLaunchDialogAction.java:80)\n        at org.eclipse.debug.ui.actions.OpenLaunchDialogAction.run(OpenLaunchDialogAction.java:99)\n        at org.eclipse.ui.internal.PluginAction.runWithEvent(PluginAction.java:254)\n        at org.eclipse.ui.internal.WWinPluginAction.runWithEvent(WWinPluginAction.java:229)\n        at org.eclipse.jface.action.ActionContributionItem.handleWidgetSelection(ActionContributionItem.java:539)\n        at org.eclipse.jface.action.ActionContributionItem.access$2(ActionContributionItem.java:488)\n        at org.eclipse.jface.action.ActionContributionItem$5.handleEvent(ActionContributionItem.java:400)\n        at org.eclipse.swt.widgets.EventTable.sendEvent(EventTable.java:66)\n        at org.eclipse.swt.widgets.Widget.sendEvent(Widget.java:1496)\n        at org.eclipse.swt.widgets.Widget.sendEvent(Widget.java:1520)\n        at org.eclipse.swt.widgets.Widget.sendEvent(Widget.java:1505)\n        at org.eclipse.swt.widgets.Widget.notifyListeners(Widget.java:1279)\n        at org.eclipse.swt.widgets.Display.runDeferredEvents(Display.java:3312)\n        at org.eclipse.swt.widgets.Display.readAndDispatch(Display.java:2941)\n        at org.eclipse.ui.internal.Workbench.runEventLoop(Workbench.java:1914)\n        at org.eclipse.ui.internal.Workbench.runUI(Workbench.java:1878)\n        at org.eclipse.ui.internal.Workbench.createAndRunWorkbench(Workbench.java:419)\n        at org.eclipse.ui.PlatformUI.createAndRunWorkbench(PlatformUI.java:149)\n        at org.eclipse.ui.internal.ide.IDEApplication.run(IDEApplication.java:95)\n        at org.eclipse.core.internal.runtime.PlatformActivator$1.run(PlatformActivator.java:78)\n        at org.eclipse.core.runtime.internal.adaptor.EclipseAppLauncher.runApplication(EclipseAppLauncher.java:92)\n        at org.eclipse.core.runtime.internal.adaptor.EclipseAppLauncher.start(EclipseAppLauncher.java:68)\n        at org.eclipse.core.runtime.adaptor.EclipseStarter.run(EclipseStarter.java:400)\n        at org.eclipse.core.runtime.adaptor.EclipseStarter.run(EclipseStarter.java:177)\n        at sun.reflect.NativeMethodAccessorImpl.invoke0(Native Method)\n        at sun.reflect.NativeMethodAccessorImpl.invoke(NativeMethodAccessorImpl.java:39)\n        at sun.reflect.DelegatingMethodAccessorImpl.invoke(DelegatingMethodAccessorImpl.java:25)\n        at java.lang.reflect.Method.invoke(Method.java:585)\n        at org.eclipse.core.launcher.Main.invokeFramework(Main.java:336)\n        at org.eclipse.core.launcher.Main.basicRun(Main.java:280)\n        at org.eclipse.core.launcher.Main.run(Main.java:977)\n        at org.eclipse.core.launcher.Main.main(Main.java:952)\n",
    "This works fine for me with the same OS/JDK.\nDoes the file exist? Can eclipse read/write to the .launches directory?",
    "\u003eDoes the file exist? \n\nyes\n\n\u003eCan eclipse read/write to the .launches directory?\n\nyes\n\nAfter deleting workspace/.metadata/.plugins this now seems to work.\n\nAnyway... this is a bit strange. My workspace is quite new. It is only about 2 weeks old (got new MacBook Pro 2 week ago :) \n\nWell... atleast now it is working :)",
    "Marking as works for me. Unable to reproduce."
  ],
  "commentCreationDates": [
    "2006-06-26T12:09:59+02:00",
    "2006-06-26T13:12:41+02:00",
    "2006-06-26T20:27:58+02:00",
    "2006-06-29T22:23:03+02:00",
    "2006-09-18T22:54:41+02:00"
  ],
  "traces": [
    {
      "exceptionType": "org.eclipse.debug.core.DebugException",
      "message": "Launch configuration New_configuration at /Users/kajh/Documents/workspace/.metadata/.plugins/org.eclipse.debug.core/.launches/New_configuration.launch does not exist.",
      "elements": [
        {
          "method": "org.eclipse.debug.internal.core.LaunchManager.createDebugException",
          "source": "LaunchManager.java:784"
        },
        {
          "method": "org.eclipse.debug.internal.core.LaunchManager.getInfo",
          "source": "LaunchManager.java:1181"
        },
        {
          "method": "org.eclipse.debug.internal.core.LaunchConfiguration.getInfo",
          "source": "LaunchConfiguration.java:356"
        },
        {
          "method": "org.eclipse.debug.internal.core.LaunchConfiguration.getAttribute",
          "source": "LaunchConfiguration.java:257"
        },
        {
          "method": "org.eclipse.debug.ui.DebugUITools.launch",
          "source": "DebugUITools.java:511"
        },
        {
          "method": "org.eclipse.debug.internal.ui.launchConfigurations.LaunchConfigurationsDialog.handleLaunchPressed",
          "source": "LaunchConfigurationsDialog.java:955"
        },
        {
          "method": "org.eclipse.debug.internal.ui.launchConfigurations.LaunchConfigurationsDialog.buttonPressed",
          "source": "LaunchConfigurationsDialog.java:304"
        },
        {
          "method": "org.eclipse.jface.dialogs.Dialog$3.widgetSelected",
          "source": "Dialog.java:660"
        },
        {
          "method": "org.eclipse.swt.widgets.TypedListener.handleEvent",
          "source": "TypedListener.java:90"
        },
        {
          "method": "org.eclipse.swt.widgets.EventTable.sendEvent",
          "source": "EventTable.java:66"
        },
        {
          "method": "org.eclipse.swt.widgets.Widget.sendEvent",
          "source": "Widget.java:1496"
        },
        {
          "method": "org.eclipse.swt.widgets.Widget.sendEvent",
          "source": "Widget.java:1520"
        },
        {
          "method": "org.eclipse.swt.widgets.Widget.sendEvent",
          "source": "Widget.java:1505"
        },
        {
          "method": "org.eclipse.swt.widgets.Widget.notifyListeners",
          "source": "Widget.java:1279"
        },
        {
          "method": "org.eclipse.swt.widgets.Display.runDeferredEvents",
          "source": "Display.java:3312"
        },
        {
          "method": "org.eclipse.swt.widgets.Display.readAndDispatch",
          "source": "Display.java:2941"
        },
        {
          "method": "org.eclipse.jface.window.Window.runEventLoop",
          "source": "Window.java:820"
        },
        {
          "method": "org.eclipse.jface.window.Window.open",
          "source": "Window.java:796"
        },
        {
          "method": "org.eclipse.debug.internal.ui.launchConfigurations.LaunchConfigurationsDialog.open",
          "source": "LaunchConfigurationsDialog.java:1086"
        },
        {
          "method": "org.eclipse.debug.ui.DebugUITools$1.run",
          "source": "DebugUITools.java:375"
        },
        {
          "method": "org.eclipse.swt.custom.BusyIndicator.showWhile",
          "source": "BusyIndicator.java:67"
        },
        {
          "method": "org.eclipse.debug.ui.DebugUITools.openLaunchConfigurationDialogOnGroup",
          "source": "DebugUITools.java:379"
        },
        {
          "method": "org.eclipse.debug.ui.DebugUITools.openLaunchConfigurationDialogOnGroup",
          "source": "DebugUITools.java:321"
        },
        {
          "method": "org.eclipse.debug.ui.actions.OpenLaunchDialogAction.run",
          "source": "OpenLaunchDialogAction.java:80"
        },
        {
          "method": "org.eclipse.debug.ui.actions.OpenLaunchDialogAction.run",
          "source": "OpenLaunchDialogAction.java:99"
        },
        {
          "method": "org.eclipse.ui.internal.PluginAction.runWithEvent",
          "source": "PluginAction.java:254"
        },
        {
          "method": "org.eclipse.ui.internal.WWinPluginAction.runWithEvent",
          "source": "WWinPluginAction.java:229"
        },
        {
          "method": "org.eclipse.jface.action.ActionContributionItem.handleWidgetSelection",
          "source": "ActionContributionItem.java:539"
        },
        {
          "method": "org.eclipse.jface.action.ActionContributionItem.access$2",
          "source": "ActionContributionItem.java:488"
        },
        {
          "method": "org.eclipse.jface.action.ActionContributionItem$5.handleEvent",
          "source": "ActionContributionItem.java:400"
        },
        {
          "method": "org.eclipse.swt.widgets.EventTable.sendEvent",
          "source": "EventTable.java:66"
        },
        {
          "method": "org.eclipse.swt.widgets.Widget.sendEvent",
          "source": "Widget.java:1496"
        },
        {
          "method": "org.eclipse.swt.widgets.Widget.sendEvent",
          "source": "Widget.java:1520"
        },
        {
          "method": "org.eclipse.swt.widgets.Widget.sendEvent",
          "source": "Widget.java:1505"
        },
        {
          "method": "org.eclipse.swt.widgets.Widget.notifyListeners",
          "source": "Widget.java:1279"
        },
        {
          "method": "org.eclipse.swt.widgets.Display.runDeferredEvents",
          "source": "Display.java:3312"
        },
        {
          "method": "org.eclipse.swt.widgets.Display.readAndDispatch",
          "source": "Display.java:2941"
        },
        {
          "method": "org.eclipse.ui.internal.Workbench.runEventLoop",
          "source": "Workbench.java:1914"
        },
        {
          "method": "org.eclipse.ui.internal.Workbench.runUI",
          "source": "Workbench.java:1878"
        },
        {
          "method": "org.eclipse.ui.internal.Workbench.createAndRunWorkbench",
          "source": "Workbench.java:419"
        },
        {
          "method": "org.eclipse.ui.PlatformUI.createAndRunWorkbench",
          "source": "PlatformUI.java:149"
        },
        {
          "method": "org.eclipse.ui.internal.ide.IDEApplication.run",
          "source": "IDEApplication.java:95"
        },
        {
          "method": "org.eclipse.core.internal.runtime.PlatformActivator$1.run",
          "source": "PlatformActivator.java:78"
        },
        {
          "method": "org.eclipse.core.runtime.internal.adaptor.EclipseAppLauncher.runApplication",
          "source": "EclipseAppLauncher.java:92"
        },
        {
          "method": "org.eclipse.core.runtime.internal.adaptor.EclipseAppLauncher.start",
          "source": "EclipseAppLauncher.java:68"
        },
        {
          "method": "org.eclipse.core.runtime.adaptor.EclipseStarter.run",
          "source": "EclipseStarter.java:400"
        },
        {
          "method": "org.eclipse.core.runtime.adaptor.EclipseStarter.run",
          "source": "EclipseStarter.java:177"
        },
        {
          "method": "sun.reflect.NativeMethodAccessorImpl.invoke0",
          "source": "Native Method"
        },
        {
          "method": "sun.reflect.NativeMethodAccessorImpl.invoke",
          "source": "NativeMethodAccessorImpl.java:39"
        },
        {
          "method": "sun.reflect.DelegatingMethodAccessorImpl.invoke",
          "source": "DelegatingMethodAccessorImpl.java:25"
        },
        {
          "method": "java.lang.reflect.Method.invoke",
          "source": "Method.java:585"
        },
        {
          "method": "org.eclipse.core.launcher.Main.invokeFramework",
          "source": "Main.java:336"
        },
        {
          "method": "org.eclipse.core.launcher.Main.basicRun",
          "source": "Main.java:280"
        },
        {
          "method": "org.eclipse.core.launcher.Main.run",
          "source": "Main.java:977"
        },
        {
          "method": "org.eclipse.core.launcher.Main.main",
          "source": "Main.java:952"
        }
      ],
      "number": 0,
      "commentIndex": 1,
      "bugId": "148620",
      "date": "2006-06-26T13:12:41+02:00",
      "product": "JDT",
      "component": "Debug",
      "severity": "normal"
    }
  ],
  "groupId": "148620",
  "bugId": "148620",
  "date": "2006-06-26T12:09:59+02:00",
  "product": "JDT",
  "component": "Debug",
  "severity": "normal"
}