{
  "comments": [
    "Steps to reproduce:\n\n(Note: the description below is with an integration build, but I also checked with 3.2RC7 SDK.)\n\nThe attached site contains two features, of which one has an externalized \ndescription and a feature.properties file for the default and the \u0027de\u0027 locale. \nThis time I have made sure that the provider-name attribute is set (see https://bugs.eclipse.org/bugs/show_bug.cgi?id\u003d148927). Now I put it into a folder that contains also the Eclipse SDK and:\n\n[snip]\nleif@seneca ~/temp/testdigest $ tar xfz eclipse-SDK-I20060620-1010-linux-gtk.tar.gz\nleif@seneca ~/temp/testdigest $ tar xfz s.tar.gz\nleif@seneca ~/temp/testdigest $ java -jar eclipse/startup.jar -data ./workspace -application org.eclipse.update.core.siteOptimizer -digestBuilder -digestOutputDir\u003d. -siteXML\u003ds/site.xml s\nExtracting locales from s/features/f1_1.0.0.jar\nExtracting locales from s/features/f2_1.0.0.jar\nProcessing... s/features/f1_1.0.0.jar\nleif@seneca ~/temp/testdigest $ cat ./workspace/.metadata/.log\n!SESSION 2006-06-27 22:34:43.002 -----------------------------------------------\neclipse.buildId\u003dI20060620-1010\njava.version\u003d1.5.0_06\njava.vendor\u003dSun Microsystems Inc.\nBootLoader constants: OS\u003dlinux, ARCH\u003dx86, WS\u003dgtk, NL\u003den_US\nFramework arguments:  -application org.eclipse.update.core.siteOptimizer -digestBuilder -digestOutputDir\u003d. -siteXML\u003ds/site.xml s\nCommand-line arguments:  -data ./workspace -application org.eclipse.update.core.siteOptimizer -digestBuilder -digestOutputDir\u003d. -siteXML\u003ds/site.xml s\n\n!ENTRY org.eclipse.osgi 4 0 2006-06-27 22:34:50.099\n!MESSAGE Application error\n!STACK 1\njava.lang.NullPointerException\n        at org.eclipse.update.internal.core.UpdateManagerUtils.getWritableXMLString(UpdateManagerUtils.java:1021)\n        at org.eclipse.update.internal.provisional.SiteOptimizerApplication.writeFeatureDigest(SiteOptimizerApplication.java:775)\n        at org.eclipse.update.internal.provisional.SiteOptimizerApplication$AvailableLocale.writeFeatureDigests(SiteOptimizerApplication.java:637)\n        at org.eclipse.update.internal.provisional.SiteOptimizerApplication.runDigestBuilder(SiteOptimizerApplication.java:243)\n        at org.eclipse.update.internal.provisional.SiteOptimizerApplication.run(SiteOptimizerApplication.java:511)\n        at org.eclipse.core.internal.runtime.PlatformActivator$1.run(PlatformActivator.java:78)\n        at org.eclipse.core.runtime.internal.adaptor.EclipseAppLauncher.runApplication(EclipseAppLauncher.java:92)\n        at org.eclipse.core.runtime.internal.adaptor.EclipseAppLauncher.start(EclipseAppLauncher.java:68)\n        at org.eclipse.core.runtime.adaptor.EclipseStarter.run(EclipseStarter.java:400)\n        at org.eclipse.core.runtime.adaptor.EclipseStarter.run(EclipseStarter.java:177)\n        at sun.reflect.NativeMethodAccessorImpl.invoke0(Native Method)\n        at sun.reflect.NativeMethodAccessorImpl.invoke(NativeMethodAccessorImpl.java:39)\n        at sun.reflect.DelegatingMethodAccessorImpl.invoke(DelegatingMethodAccessorImpl.java:25)\n        at java.lang.reflect.Method.invoke(Method.java:585)\n        at org.eclipse.core.launcher.Main.invokeFramework(Main.java:336)\n        at org.eclipse.core.launcher.Main.basicRun(Main.java:280)\n        at org.eclipse.core.launcher.Main.run(Main.java:977)\n        at org.eclipse.core.launcher.Main.main(Main.java:952)\n[snap]",
    "Created an attachment (id\u003d45437)\nsite to reproduce\n\n"
  ],
  "commentCreationDates": [
    "2006-06-28T06:07:54+02:00",
    "2006-06-28T06:08:36+02:00"
  ],
  "traces": [
    {
      "exceptionType": "java.lang.NullPointerException",
      "elements": [
        {
          "method": "org.eclipse.update.internal.core.UpdateManagerUtils.getWritableXMLString",
          "source": "UpdateManagerUtils.java:1021"
        },
        {
          "method": "org.eclipse.update.internal.provisional.SiteOptimizerApplication.writeFeatureDigest",
          "source": "SiteOptimizerApplication.java:775"
        },
        {
          "method": "org.eclipse.update.internal.provisional.SiteOptimizerApplication$AvailableLocale.writeFeatureDigests",
          "source": "SiteOptimizerApplication.java:637"
        },
        {
          "method": "org.eclipse.update.internal.provisional.SiteOptimizerApplication.runDigestBuilder",
          "source": "SiteOptimizerApplication.java:243"
        },
        {
          "method": "org.eclipse.update.internal.provisional.SiteOptimizerApplication.run",
          "source": "SiteOptimizerApplication.java:511"
        },
        {
          "method": "org.eclipse.core.internal.runtime.PlatformActivator$1.run",
          "source": "PlatformActivator.java:78"
        },
        {
          "method": "org.eclipse.core.runtime.internal.adaptor.EclipseAppLauncher.runApplication",
          "source": "EclipseAppLauncher.java:92"
        },
        {
          "method": "org.eclipse.core.runtime.internal.adaptor.EclipseAppLauncher.start",
          "source": "EclipseAppLauncher.java:68"
        },
        {
          "method": "org.eclipse.core.runtime.adaptor.EclipseStarter.run",
          "source": "EclipseStarter.java:400"
        },
        {
          "method": "org.eclipse.core.runtime.adaptor.EclipseStarter.run",
          "source": "EclipseStarter.java:177"
        },
        {
          "method": "sun.reflect.NativeMethodAccessorImpl.invoke0",
          "source": "Native Method"
        },
        {
          "method": "sun.reflect.NativeMethodAccessorImpl.invoke",
          "source": "NativeMethodAccessorImpl.java:39"
        },
        {
          "method": "sun.reflect.DelegatingMethodAccessorImpl.invoke",
          "source": "DelegatingMethodAccessorImpl.java:25"
        },
        {
          "method": "java.lang.reflect.Method.invoke",
          "source": "Method.java:585"
        },
        {
          "method": "org.eclipse.core.launcher.Main.invokeFramework",
          "source": "Main.java:336"
        },
        {
          "method": "org.eclipse.core.launcher.Main.basicRun",
          "source": "Main.java:280"
        },
        {
          "method": "org.eclipse.core.launcher.Main.run",
          "source": "Main.java:977"
        },
        {
          "method": "org.eclipse.core.launcher.Main.main",
          "source": "Main.java:952"
        }
      ],
      "number": 0,
      "commentIndex": 0,
      "bugId": "148928",
      "date": "2006-06-28T06:07:54+02:00",
      "product": "Platform",
      "component": "Update",
      "severity": "normal"
    }
  ],
  "groupId": "148928",
  "bugId": "148928",
  "date": "2006-06-28T06:07:54+02:00",
  "product": "Platform",
  "component": "Update",
  "severity": "normal"
}