{
  "comments": [
    "I20060627 + latest JDT Core\n\nCreate the following CU in jdt.core.tests.model:\n/*******************************************************************************\n * Copyright (c) 2000, 2006 IBM Corporation and others.\n * All rights reserved. This program and the accompanying materials\n * are made available under the terms of the Eclipse Public License v1.0\n * which accompanies this distribution, and is available at\n * http://www.eclipse.org/legal/epl-v10.html\n * \n * Contributors:\n *     IBM Corporation - initial API and implementation\n *******************************************************************************/\npackage org.eclipse.jdt.core.tests.model;\n\nimport java.nio.ByteBuffer;\nimport java.nio.CharBuffer;\nimport java.nio.charset.Charset;\nimport java.nio.charset.CharsetDecoder;\nimport java.nio.charset.CharsetEncoder;\nimport java.nio.charset.CoderResult;\n\npublic class TestCharset extends Charset {\n\n\tpublic TestCharset(String canonicalName, String[] aliases) {\n\t\tsuper(canonicalName, aliases);\n\t}\n\t\n\tpublic boolean contains(Charset cs) {\n\t\treturn cs \u003d\u003d this;\n\t}\n\n\tpublic CharsetDecoder newDecoder() {\n\t\treturn new CharsetDecoder(this, 2.0, 2.0) {\n\t\t\tCharsetDecoder(CharSet\n\t\t\tprotected CoderResult decodeLoop(ByteBuffer in, CharBuffer out) {\n\t\t\t\treturn null;\n\t\t\t}\n\t\t};;\n\t}\n\n\tpublic CharsetEncoder newEncoder() {\n\t\treturn null;\n\t}\n\n}\n\nObserve: You get the following exception when the AST is being created:\n!ENTRY org.eclipse.jdt.ui 4 0 2006-06-29 12:23:21.439\n!MESSAGE Error in JDT Core during AST creation\n!STACK 0\njava.lang.IllegalArgumentException\n        at org.eclipse.jdt.core.dom.ASTNode.setSourceRange(ASTNode.java:2599)\n        at org.eclipse.jdt.core.dom.ASTConverter.convert(ASTConverter.java:430)\n        at org.eclipse.jdt.core.dom.ASTConverter.buildBodyDeclarations(ASTConverter.java:318)\n        at org.eclipse.jdt.core.dom.ASTConverter.convert(ASTConverter.java:2284)\n        at org.eclipse.jdt.core.dom.ASTConverter.convert(ASTConverter.java:1541)\n        at org.eclipse.jdt.core.dom.ASTConverter.convert(ASTConverter.java:2341)\n        at org.eclipse.jdt.core.dom.ASTConverter.convert(ASTConverter.java:2412)\n        at org.eclipse.jdt.core.dom.ASTConverter.convert(ASTConverter.java:511)\n        at org.eclipse.jdt.core.dom.ASTConverter.buildBodyDeclarations(ASTConverter.java:179)\n        at org.eclipse.jdt.core.dom.ASTConverter.convert(ASTConverter.java:2666)\n        at org.eclipse.jdt.core.dom.ASTConverter.convert(ASTConverter.java:1249)\n        at org.eclipse.jdt.core.dom.CompilationUnitResolver.convert(CompilationUnitResolver.java:253)\n        at org.eclipse.jdt.core.dom.ASTParser.internalCreateAST(ASTParser.java:856)\n        at org.eclipse.jdt.core.dom.ASTParser.createAST(ASTParser.java:630)\n        at org.eclipse.jdt.internal.ui.javaeditor.ASTProvider$1.run(ASTProvider.java:605)\n        at org.eclipse.core.runtime.SafeRunner.run(SafeRunner.java:37)\n        at org.eclipse.jdt.internal.ui.javaeditor.ASTProvider.createAST(ASTProvider.java:600)\n        at org.eclipse.jdt.internal.ui.javaeditor.ASTProvider.getAST(ASTProvider.java:514)\n        at org.eclipse.jdt.internal.ui.javaeditor.ClipboardOperationAction.getClipboardData(ClipboardOperationAction.java:397)\n        at org.eclipse.jdt.internal.ui.javaeditor.ClipboardOperationAction.doCutCopyWithImportsOperation(ClipboardOperationAction.java:323)\n        at org.eclipse.jdt.internal.ui.javaeditor.ClipboardOperationAction.internalDoOperation(ClipboardOperationAction.java:279)\n        at org.eclipse.jdt.internal.ui.javaeditor.ClipboardOperationAction$1.run(ClipboardOperationAction.java:248)\n        at org.eclipse.swt.custom.BusyIndicator.showWhile(BusyIndicator.java:67)\n        at org.eclipse.jdt.internal.ui.javaeditor.ClipboardOperationAction.run(ClipboardOperationAction.java:246)\n        at org.eclipse.jface.action.Action.runWithEvent(Action.java:499)\n        at org.eclipse.ui.actions.RetargetAction.runWithEvent(RetargetAction.java:229)\n        at org.eclipse.jface.action.ActionContributionItem.handleWidgetSelection(ActionContributionItem.java:539)\n        at org.eclipse.jface.action.ActionContributionItem.access$2(ActionContributionItem.java:488)\n        at org.eclipse.jface.action.ActionContributionItem$5.handleEvent(ActionContributionItem.java:400)\n        at org.eclipse.swt.widgets.EventTable.sendEvent(EventTable.java:66)\n        at org.eclipse.swt.widgets.Widget.sendEvent(Widget.java:928)\n        at org.eclipse.swt.widgets.Display.runDeferredEvents(Display.java:3375)\n        at org.eclipse.swt.widgets.Display.readAndDispatch(Display.java:2995)\n        at org.eclipse.ui.internal.Workbench.runEventLoop(Workbench.java:1914)\n        at org.eclipse.ui.internal.Workbench.runUI(Workbench.java:1878)\n        at org.eclipse.ui.internal.Workbench.createAndRunWorkbench(Workbench.java:419)\n        at org.eclipse.ui.PlatformUI.createAndRunWorkbench(PlatformUI.java:149)\n        at org.eclipse.ui.internal.ide.IDEApplication.run(IDEApplication.java:95)\n        at org.eclipse.core.internal.runtime.PlatformActivator$1.run(PlatformActivator.java:78)\n        at org.eclipse.core.runtime.internal.adaptor.EclipseAppLauncher.runApplication(EclipseAppLauncher.java:92)\n        at org.eclipse.core.runtime.internal.adaptor.EclipseAppLauncher.start(EclipseAppLauncher.java:68)\n        at org.eclipse.core.runtime.adaptor.EclipseStarter.run(EclipseStarter.java:400)\n        at org.eclipse.core.runtime.adaptor.EclipseStarter.run(EclipseStarter.java:177)\n        at sun.reflect.NativeMethodAccessorImpl.invoke0(Native Method)\n        at sun.reflect.NativeMethodAccessorImpl.invoke(NativeMethodAccessorImpl.java:39)\n        at sun.reflect.DelegatingMethodAccessorImpl.invoke(DelegatingMethodAccessorImpl.java:25)\n        at java.lang.reflect.Method.invoke(Method.java:585)\n        at org.eclipse.core.launcher.Main.invokeFramework(Main.java:336)\n        at org.eclipse.core.launcher.Main.basicRun(Main.java:280)\n        at org.eclipse.core.launcher.Main.run(Main.java:977)\n        at org.eclipse.core.launcher.Main.main(Main.java:952)",
    "David,\n\nThis is another case of recovery that has not completed properly.\n                        CharsetDecoder(CharSet\n                        protected CoderResult decodeLoop(ByteBuffer in,\n\nWhen trying to retrieve the end position of the method declaration name (CharsetDecoder in this case), the recovery scanner doesn\u0027t return any token.\nIt is at the beginning of the identifier and it seems to return EOF. I would expect to get an identifier token.",
    "Added disabled regression test\norg.eclipse.jdt.core.tests.dom.ASTConverterTestAST3_2._test0652 in HEAD."
  ],
  "commentCreationDates": [
    "2006-06-29T12:23:51+02:00",
    "2006-06-29T16:44:51+02:00",
    "2006-06-29T16:46:00+02:00"
  ],
  "traces": [
    {
      "exceptionType": "java.lang.IllegalArgumentException",
      "elements": [
        {
          "method": "org.eclipse.jdt.core.dom.ASTNode.setSourceRange",
          "source": "ASTNode.java:2599"
        },
        {
          "method": "org.eclipse.jdt.core.dom.ASTConverter.convert",
          "source": "ASTConverter.java:430"
        },
        {
          "method": "org.eclipse.jdt.core.dom.ASTConverter.buildBodyDeclarations",
          "source": "ASTConverter.java:318"
        },
        {
          "method": "org.eclipse.jdt.core.dom.ASTConverter.convert",
          "source": "ASTConverter.java:2284"
        },
        {
          "method": "org.eclipse.jdt.core.dom.ASTConverter.convert",
          "source": "ASTConverter.java:1541"
        },
        {
          "method": "org.eclipse.jdt.core.dom.ASTConverter.convert",
          "source": "ASTConverter.java:2341"
        },
        {
          "method": "org.eclipse.jdt.core.dom.ASTConverter.convert",
          "source": "ASTConverter.java:2412"
        },
        {
          "method": "org.eclipse.jdt.core.dom.ASTConverter.convert",
          "source": "ASTConverter.java:511"
        },
        {
          "method": "org.eclipse.jdt.core.dom.ASTConverter.buildBodyDeclarations",
          "source": "ASTConverter.java:179"
        },
        {
          "method": "org.eclipse.jdt.core.dom.ASTConverter.convert",
          "source": "ASTConverter.java:2666"
        },
        {
          "method": "org.eclipse.jdt.core.dom.ASTConverter.convert",
          "source": "ASTConverter.java:1249"
        },
        {
          "method": "org.eclipse.jdt.core.dom.CompilationUnitResolver.convert",
          "source": "CompilationUnitResolver.java:253"
        },
        {
          "method": "org.eclipse.jdt.core.dom.ASTParser.internalCreateAST",
          "source": "ASTParser.java:856"
        },
        {
          "method": "org.eclipse.jdt.core.dom.ASTParser.createAST",
          "source": "ASTParser.java:630"
        },
        {
          "method": "org.eclipse.jdt.internal.ui.javaeditor.ASTProvider$1.run",
          "source": "ASTProvider.java:605"
        },
        {
          "method": "org.eclipse.core.runtime.SafeRunner.run",
          "source": "SafeRunner.java:37"
        },
        {
          "method": "org.eclipse.jdt.internal.ui.javaeditor.ASTProvider.createAST",
          "source": "ASTProvider.java:600"
        },
        {
          "method": "org.eclipse.jdt.internal.ui.javaeditor.ASTProvider.getAST",
          "source": "ASTProvider.java:514"
        },
        {
          "method": "org.eclipse.jdt.internal.ui.javaeditor.ClipboardOperationAction.getClipboardData",
          "source": "ClipboardOperationAction.java:397"
        },
        {
          "method": "org.eclipse.jdt.internal.ui.javaeditor.ClipboardOperationAction.doCutCopyWithImportsOperation",
          "source": "ClipboardOperationAction.java:323"
        },
        {
          "method": "org.eclipse.jdt.internal.ui.javaeditor.ClipboardOperationAction.internalDoOperation",
          "source": "ClipboardOperationAction.java:279"
        },
        {
          "method": "org.eclipse.jdt.internal.ui.javaeditor.ClipboardOperationAction$1.run",
          "source": "ClipboardOperationAction.java:248"
        },
        {
          "method": "org.eclipse.swt.custom.BusyIndicator.showWhile",
          "source": "BusyIndicator.java:67"
        },
        {
          "method": "org.eclipse.jdt.internal.ui.javaeditor.ClipboardOperationAction.run",
          "source": "ClipboardOperationAction.java:246"
        },
        {
          "method": "org.eclipse.jface.action.Action.runWithEvent",
          "source": "Action.java:499"
        },
        {
          "method": "org.eclipse.ui.actions.RetargetAction.runWithEvent",
          "source": "RetargetAction.java:229"
        },
        {
          "method": "org.eclipse.jface.action.ActionContributionItem.handleWidgetSelection",
          "source": "ActionContributionItem.java:539"
        },
        {
          "method": "org.eclipse.jface.action.ActionContributionItem.access$2",
          "source": "ActionContributionItem.java:488"
        },
        {
          "method": "org.eclipse.jface.action.ActionContributionItem$5.handleEvent",
          "source": "ActionContributionItem.java:400"
        },
        {
          "method": "org.eclipse.swt.widgets.EventTable.sendEvent",
          "source": "EventTable.java:66"
        },
        {
          "method": "org.eclipse.swt.widgets.Widget.sendEvent",
          "source": "Widget.java:928"
        },
        {
          "method": "org.eclipse.swt.widgets.Display.runDeferredEvents",
          "source": "Display.java:3375"
        },
        {
          "method": "org.eclipse.swt.widgets.Display.readAndDispatch",
          "source": "Display.java:2995"
        },
        {
          "method": "org.eclipse.ui.internal.Workbench.runEventLoop",
          "source": "Workbench.java:1914"
        },
        {
          "method": "org.eclipse.ui.internal.Workbench.runUI",
          "source": "Workbench.java:1878"
        },
        {
          "method": "org.eclipse.ui.internal.Workbench.createAndRunWorkbench",
          "source": "Workbench.java:419"
        },
        {
          "method": "org.eclipse.ui.PlatformUI.createAndRunWorkbench",
          "source": "PlatformUI.java:149"
        },
        {
          "method": "org.eclipse.ui.internal.ide.IDEApplication.run",
          "source": "IDEApplication.java:95"
        },
        {
          "method": "org.eclipse.core.internal.runtime.PlatformActivator$1.run",
          "source": "PlatformActivator.java:78"
        },
        {
          "method": "org.eclipse.core.runtime.internal.adaptor.EclipseAppLauncher.runApplication",
          "source": "EclipseAppLauncher.java:92"
        },
        {
          "method": "org.eclipse.core.runtime.internal.adaptor.EclipseAppLauncher.start",
          "source": "EclipseAppLauncher.java:68"
        },
        {
          "method": "org.eclipse.core.runtime.adaptor.EclipseStarter.run",
          "source": "EclipseStarter.java:400"
        },
        {
          "method": "org.eclipse.core.runtime.adaptor.EclipseStarter.run",
          "source": "EclipseStarter.java:177"
        },
        {
          "method": "sun.reflect.NativeMethodAccessorImpl.invoke0",
          "source": "Native Method"
        },
        {
          "method": "sun.reflect.NativeMethodAccessorImpl.invoke",
          "source": "NativeMethodAccessorImpl.java:39"
        },
        {
          "method": "sun.reflect.DelegatingMethodAccessorImpl.invoke",
          "source": "DelegatingMethodAccessorImpl.java:25"
        },
        {
          "method": "java.lang.reflect.Method.invoke",
          "source": "Method.java:585"
        },
        {
          "method": "org.eclipse.core.launcher.Main.invokeFramework",
          "source": "Main.java:336"
        },
        {
          "method": "org.eclipse.core.launcher.Main.basicRun",
          "source": "Main.java:280"
        },
        {
          "method": "org.eclipse.core.launcher.Main.run",
          "source": "Main.java:977"
        },
        {
          "method": "org.eclipse.core.launcher.Main.main",
          "source": "Main.java:952"
        }
      ],
      "number": 0,
      "commentIndex": 0,
      "bugId": "149126",
      "date": "2006-06-29T12:23:51+02:00",
      "product": "JDT",
      "component": "Core",
      "severity": "normal"
    }
  ],
  "groupId": "149126",
  "bugId": "149126",
  "date": "2006-06-29T12:23:51+02:00",
  "product": "JDT",
  "component": "Core",
  "severity": "normal"
}