{
  "comments": [
    "I20060628-1135 + ZRH-plugins from 20060704_1144\n\nCreate new java project:\n- enter name, use default project layout (separate source and output folders)\n- press Next\n-\u003e on Source tab, project has 2 packages as children: (default package) and src\n\u003d\u003e expected: src is a source folder, no default package\n\nWhen I open the context menu on src and choose \u0027Use as Source Folder\u0027, I get a dialog and this exception:\n\norg.eclipse.core.runtime.CoreException: The folder is already a source folder.\n        at org.eclipse.jdt.internal.corext.buildpath.ClasspathModifier.validateAndAddEntry(ClasspathModifier.java:1952)\n        at org.eclipse.jdt.internal.corext.buildpath.ClasspathModifier.setNewEntry(ClasspathModifier.java:1880)\n        at org.eclipse.jdt.internal.corext.buildpath.ClasspathModifier.addToClasspath(ClasspathModifier.java:236)\n        at org.eclipse.jdt.internal.corext.buildpath.AddSelectedSourceFolderOperation.run(AddSelectedSourceFolderOperation.java:72)\n        at org.eclipse.jdt.internal.ui.wizards.buildpaths.newsourcepage.ClasspathModifierAction.run(ClasspathModifierAction.java:58)\n        at org.eclipse.jface.action.Action.runWithEvent(Action.java:499)\n        at org.eclipse.jface.action.ActionContributionItem.handleWidgetSelection(ActionContributionItem.java:539)\n        at org.eclipse.jface.action.ActionContributionItem.access$2(ActionContributionItem.java:488)\n        at org.eclipse.jface.action.ActionContributionItem$5.handleEvent(ActionContributionItem.java:400)\n        at org.eclipse.swt.widgets.EventTable.sendEvent(EventTable.java:66)\n        at org.eclipse.swt.widgets.Widget.sendEvent(Widget.java:928)\n        at org.eclipse.swt.widgets.Display.runDeferredEvents(Display.java:3375)\n        at org.eclipse.swt.widgets.Display.readAndDispatch(Display.java:2995)\n        at org.eclipse.jface.window.Window.runEventLoop(Window.java:820)\n        at org.eclipse.jface.window.Window.open(Window.java:796)\n        at org.eclipse.jdt.ui.actions.AbstractOpenWizardAction.run(AbstractOpenWizardAction.java:83)\n        at org.eclipse.jdt.internal.ui.wizards.OpenJavaProjectWizardToolbarAction.run(OpenJavaProjectWizardToolbarAction.java:45)\n        at org.eclipse.ui.internal.PluginAction.runWithEvent(PluginAction.java:254)\n        at org.eclipse.ui.internal.WWinPluginAction.runWithEvent(WWinPluginAction.java:229)\n        at org.eclipse.jface.action.ActionContributionItem.handleWidgetSelection(ActionContributionItem.java:539)\n        at org.eclipse.jface.action.ActionContributionItem.access$2(ActionContributionItem.java:488)\n        at org.eclipse.jface.action.ActionContributionItem$6.handleEvent(ActionContributionItem.java:441)\n        at org.eclipse.swt.widgets.EventTable.sendEvent(EventTable.java:66)\n        at org.eclipse.swt.widgets.Widget.sendEvent(Widget.java:928)\n        at org.eclipse.swt.widgets.Display.runDeferredEvents(Display.java:3375)\n        at org.eclipse.swt.widgets.Display.readAndDispatch(Display.java:2995)\n        at org.eclipse.ui.internal.Workbench.runEventLoop(Workbench.java:1914)\n        at org.eclipse.ui.internal.Workbench.runUI(Workbench.java:1878)\n        at org.eclipse.ui.internal.Workbench.createAndRunWorkbench(Workbench.java:419)\n        at org.eclipse.ui.PlatformUI.createAndRunWorkbench(PlatformUI.java:149)\n        at org.eclipse.ui.internal.ide.IDEApplication.run(IDEApplication.java:95)\n        at org.eclipse.core.internal.runtime.PlatformActivator$1.run(PlatformActivator.java:78)\n        at org.eclipse.core.runtime.internal.adaptor.EclipseAppLauncher.runApplication(EclipseAppLauncher.java:92)\n        at org.eclipse.core.runtime.internal.adaptor.EclipseAppLauncher.start(EclipseAppLauncher.java:68)\n        at org.eclipse.core.runtime.adaptor.EclipseStarter.run(EclipseStarter.java:400)\n        at org.eclipse.core.runtime.adaptor.EclipseStarter.run(EclipseStarter.java:177)\n        at sun.reflect.NativeMethodAccessorImpl.invoke0(Native Method)\n        at sun.reflect.NativeMethodAccessorImpl.invoke(NativeMethodAccessorImpl.java:39)\n        at sun.reflect.DelegatingMethodAccessorImpl.invoke(DelegatingMethodAccessorImpl.java:25)\n        at java.lang.reflect.Method.invoke(Method.java:585)\n        at org.eclipse.core.launcher.Main.invokeFramework(Main.java:336)\n        at org.eclipse.core.launcher.Main.basicRun(Main.java:280)\n        at org.eclipse.core.launcher.Main.run(Main.java:977)\n        at org.eclipse.core.launcher.Main.main(Main.java:952)",
    "BTW: when I press \"Finish\" on any page, the project is created as expected.",
    "\n\n*** This bug has been marked as a duplicate of 149440 ***"
  ],
  "commentCreationDates": [
    "2006-07-04T12:01:22+02:00",
    "2006-07-04T12:03:01+02:00",
    "2006-07-04T12:04:13+02:00"
  ],
  "traces": [
    {
      "exceptionType": "org.eclipse.core.runtime.CoreException",
      "message": "The folder is already a source folder.",
      "elements": [
        {
          "method": "org.eclipse.jdt.internal.corext.buildpath.ClasspathModifier.validateAndAddEntry",
          "source": "ClasspathModifier.java:1952"
        },
        {
          "method": "org.eclipse.jdt.internal.corext.buildpath.ClasspathModifier.setNewEntry",
          "source": "ClasspathModifier.java:1880"
        },
        {
          "method": "org.eclipse.jdt.internal.corext.buildpath.ClasspathModifier.addToClasspath",
          "source": "ClasspathModifier.java:236"
        },
        {
          "method": "org.eclipse.jdt.internal.corext.buildpath.AddSelectedSourceFolderOperation.run",
          "source": "AddSelectedSourceFolderOperation.java:72"
        },
        {
          "method": "org.eclipse.jdt.internal.ui.wizards.buildpaths.newsourcepage.ClasspathModifierAction.run",
          "source": "ClasspathModifierAction.java:58"
        },
        {
          "method": "org.eclipse.jface.action.Action.runWithEvent",
          "source": "Action.java:499"
        },
        {
          "method": "org.eclipse.jface.action.ActionContributionItem.handleWidgetSelection",
          "source": "ActionContributionItem.java:539"
        },
        {
          "method": "org.eclipse.jface.action.ActionContributionItem.access$2",
          "source": "ActionContributionItem.java:488"
        },
        {
          "method": "org.eclipse.jface.action.ActionContributionItem$5.handleEvent",
          "source": "ActionContributionItem.java:400"
        },
        {
          "method": "org.eclipse.swt.widgets.EventTable.sendEvent",
          "source": "EventTable.java:66"
        },
        {
          "method": "org.eclipse.swt.widgets.Widget.sendEvent",
          "source": "Widget.java:928"
        },
        {
          "method": "org.eclipse.swt.widgets.Display.runDeferredEvents",
          "source": "Display.java:3375"
        },
        {
          "method": "org.eclipse.swt.widgets.Display.readAndDispatch",
          "source": "Display.java:2995"
        },
        {
          "method": "org.eclipse.jface.window.Window.runEventLoop",
          "source": "Window.java:820"
        },
        {
          "method": "org.eclipse.jface.window.Window.open",
          "source": "Window.java:796"
        },
        {
          "method": "org.eclipse.jdt.ui.actions.AbstractOpenWizardAction.run",
          "source": "AbstractOpenWizardAction.java:83"
        },
        {
          "method": "org.eclipse.jdt.internal.ui.wizards.OpenJavaProjectWizardToolbarAction.run",
          "source": "OpenJavaProjectWizardToolbarAction.java:45"
        },
        {
          "method": "org.eclipse.ui.internal.PluginAction.runWithEvent",
          "source": "PluginAction.java:254"
        },
        {
          "method": "org.eclipse.ui.internal.WWinPluginAction.runWithEvent",
          "source": "WWinPluginAction.java:229"
        },
        {
          "method": "org.eclipse.jface.action.ActionContributionItem.handleWidgetSelection",
          "source": "ActionContributionItem.java:539"
        },
        {
          "method": "org.eclipse.jface.action.ActionContributionItem.access$2",
          "source": "ActionContributionItem.java:488"
        },
        {
          "method": "org.eclipse.jface.action.ActionContributionItem$6.handleEvent",
          "source": "ActionContributionItem.java:441"
        },
        {
          "method": "org.eclipse.swt.widgets.EventTable.sendEvent",
          "source": "EventTable.java:66"
        },
        {
          "method": "org.eclipse.swt.widgets.Widget.sendEvent",
          "source": "Widget.java:928"
        },
        {
          "method": "org.eclipse.swt.widgets.Display.runDeferredEvents",
          "source": "Display.java:3375"
        },
        {
          "method": "org.eclipse.swt.widgets.Display.readAndDispatch",
          "source": "Display.java:2995"
        },
        {
          "method": "org.eclipse.ui.internal.Workbench.runEventLoop",
          "source": "Workbench.java:1914"
        },
        {
          "method": "org.eclipse.ui.internal.Workbench.runUI",
          "source": "Workbench.java:1878"
        },
        {
          "method": "org.eclipse.ui.internal.Workbench.createAndRunWorkbench",
          "source": "Workbench.java:419"
        },
        {
          "method": "org.eclipse.ui.PlatformUI.createAndRunWorkbench",
          "source": "PlatformUI.java:149"
        },
        {
          "method": "org.eclipse.ui.internal.ide.IDEApplication.run",
          "source": "IDEApplication.java:95"
        },
        {
          "method": "org.eclipse.core.internal.runtime.PlatformActivator$1.run",
          "source": "PlatformActivator.java:78"
        },
        {
          "method": "org.eclipse.core.runtime.internal.adaptor.EclipseAppLauncher.runApplication",
          "source": "EclipseAppLauncher.java:92"
        },
        {
          "method": "org.eclipse.core.runtime.internal.adaptor.EclipseAppLauncher.start",
          "source": "EclipseAppLauncher.java:68"
        },
        {
          "method": "org.eclipse.core.runtime.adaptor.EclipseStarter.run",
          "source": "EclipseStarter.java:400"
        },
        {
          "method": "org.eclipse.core.runtime.adaptor.EclipseStarter.run",
          "source": "EclipseStarter.java:177"
        },
        {
          "method": "sun.reflect.NativeMethodAccessorImpl.invoke0",
          "source": "Native Method"
        },
        {
          "method": "sun.reflect.NativeMethodAccessorImpl.invoke",
          "source": "NativeMethodAccessorImpl.java:39"
        },
        {
          "method": "sun.reflect.DelegatingMethodAccessorImpl.invoke",
          "source": "DelegatingMethodAccessorImpl.java:25"
        },
        {
          "method": "java.lang.reflect.Method.invoke",
          "source": "Method.java:585"
        },
        {
          "method": "org.eclipse.core.launcher.Main.invokeFramework",
          "source": "Main.java:336"
        },
        {
          "method": "org.eclipse.core.launcher.Main.basicRun",
          "source": "Main.java:280"
        },
        {
          "method": "org.eclipse.core.launcher.Main.run",
          "source": "Main.java:977"
        },
        {
          "method": "org.eclipse.core.launcher.Main.main",
          "source": "Main.java:952"
        }
      ],
      "number": 0,
      "commentIndex": 0,
      "bugId": "149545",
      "duplicateId": "149440",
      "date": "2006-07-04T12:01:22+02:00",
      "product": "JDT",
      "component": "UI",
      "severity": "normal"
    }
  ],
  "groupId": "149440",
  "bugId": "149545",
  "duplicateId": "149440",
  "date": "2006-07-04T12:01:22+02:00",
  "product": "JDT",
  "component": "UI",
  "severity": "normal"
}