{
  "comments": [
    "I20060628\n\nMay be related to bug 142932. When I run Help \u003e Software Updates \u003e Find \u0026 Install \u003e Search for updates, I get the following log contents. The exceptions in the log are not really helpful - I guess update should report misbehaving update sites and protect itself against problems.\n\nNote that the default platform encoding on linux is UTF8, whereas it is Latin1 on westernly win32 installtations.\n\n--\n\n!ENTRY org.eclipse.update.core 4 0 2006-07-05 12:04:18.396\n!MESSAGE Error processing update site mirror. [The version is required in the XML declaration.]\n!STACK 0\norg.xml.sax.SAXParseException: The version is required in the XML declaration.\n\tat com.sun.org.apache.xerces.internal.parsers.DOMParser.parse(DOMParser.java:264)\n\tat com.sun.org.apache.xerces.internal.jaxp.DocumentBuilderImpl.parse(DocumentBuilderImpl.java:292)\n\tat javax.xml.parsers.DocumentBuilder.parse(DocumentBuilder.java:146)\n\tat org.eclipse.update.core.model.DefaultSiteParser.getMirrors(DefaultSiteParser.java:829)\n\tat org.eclipse.update.core.model.SiteModel.getMirrorSiteEntryModels(SiteModel.java:416)\n\tat org.eclipse.update.core.Site.getMirrorSiteEntries(Site.java:547)\n\tat org.eclipse.update.ui.UpdateJob$ResultCollectorWithMirrors.getMirror(UpdateJob.java:306)\n\tat org.eclipse.update.search.UpdateSearchRequest.searchOneSite(UpdateSearchRequest.java:465)\n\tat org.eclipse.update.search.UpdateSearchRequest.performSearch(UpdateSearchRequest.java:294)\n\tat org.eclipse.update.ui.UpdateJob.runUpdates(UpdateJob.java:207)\n\tat org.eclipse.update.ui.UpdateJob.run(UpdateJob.java:168)\n\tat org.eclipse.core.internal.jobs.Worker.run(Worker.java:58)\n[Fatal Error] mirrors.xml?countryCode\u003dus\u0026timeZone\u003d1\u0026responseType\u003dxml:1:28: The version is required in the XML declaration.\n\n\nOther exceptions I have seen:\n\n!ENTRY org.eclipse.update.core 4 0 2006-07-05 11:59:58.112\n!MESSAGE Error processing update site mirror. [Character conversion error: \"Malf ormed UTF-8 char -- is an XML encoding declaration missing?\" (line number may be  too low).]\n!STACK 0\norg.xml.sax.SAXParseException: Character conversion error: \"Malformed UTF-8 char  -- is an XML encoding declaration missing?\" (line number may be too low).\n        at org.apache.crimson.parser.InputEntity.fatal(InputEntity.java:1100)\n        at org.apache.crimson.parser.InputEntity.fillbuf(InputEntity.java:1072)\n        at org.apache.crimson.parser.InputEntity.isXmlDeclOrTextDeclPrefix(Input Entity.java:914)\n        at org.apache.crimson.parser.Parser2.maybeXmlDecl(Parser2.java:1183)\n        at org.apache.crimson.parser.Parser2.parseInternal(Parser2.java:653)\n        at org.apache.crimson.parser.Parser2.parse(Parser2.java:337)\n        at org.apache.crimson.parser.XMLReaderImpl.parse(XMLReaderImpl.java:448)\n        at org.apache.crimson.jaxp.DocumentBuilderImpl.parse(DocumentBuilderImpl .java:185)\n        at javax.xml.parsers.DocumentBuilder.parse(DocumentBuilder.java:124)\n        at org.eclipse.update.core.model.DefaultSiteParser.getMirrors(DefaultSit eParser.java:829)\n        at org.eclipse.update.core.model.DefaultSiteParser.processSite(DefaultSi teParser.java:514)\n        at org.eclipse.update.core.model.DefaultSiteParser.handleInitialState(De faultSiteParser.java:396)\n        at org.eclipse.update.core.model.DefaultSiteParser.startElement(DefaultS iteParser.java:200)\n        at org.apache.crimson.parser.Parser2.maybeElement(Parser2.java:1672)\n        at org.apache.crimson.parser.Parser2.parseInternal(Parser2.java:667)\n        at org.apache.crimson.parser.Parser2.parse(Parser2.java:337)\n        at org.apache.crimson.parser.XMLReaderImpl.parse(XMLReaderImpl.java:448)\n        at javax.xml.parsers.SAXParser.parse(SAXParser.java:345)\n        at org.eclipse.update.core.model.DefaultSiteParser.parse(DefaultSitePars er.java:156)\n        at org.eclipse.update.core.model.SiteModelFactory.parseSite(SiteModelFac tory.java:81)\n        at org.eclipse.update.internal.core.SiteURLFactory.createSite(SiteURLFac tory.java:80)\n        at org.eclipse.update.internal.core.InternalSiteManager.createSite(Inter nalSiteManager.java:334)\n        at org.eclipse.update.internal.core.InternalSiteManager.createSite(Inter nalSiteManager.java:326)\n        at org.eclipse.update.internal.core.InternalSiteManager.createSite(Inter nalSiteManager.java:291)\n        at org.eclipse.update.internal.core.InternalSiteManager.attemptCreateSit e(InternalSiteManager.java:222)\n        at org.eclipse.update.internal.core.InternalSiteManager.getSite(Internal SiteManager.java:162)\n        at org.eclipse.update.core.SiteManager.getSite(SiteManager.java:78)\n        at org.eclipse.update.search.UpdateSearchRequest.searchOneSite(UpdateSea rchRequest.java:447)\n        at org.eclipse.update.search.UpdateSearchRequest.performSearch(UpdateSea rchRequest.java:294)\n        at org.eclipse.update.ui.UpdateJob.runUpdates(UpdateJob.java:207)\n        at org.eclipse.update.ui.UpdateJob.run(UpdateJob.java:168)\n        at org.eclipse.core.internal.jobs.Worker.run(Worker.java:58)",
    "You found before me, Tom, but I\u0027ve already documented issues in bug 149771. \n\n\n*** This bug has been marked as a duplicate of 149771 ***"
  ],
  "commentCreationDates": [
    "2006-07-05T12:24:00+02:00",
    "2006-07-07T02:51:13+02:00"
  ],
  "traces": [
    {
      "exceptionType": "org.xml.sax.SAXParseException",
      "message": "The version is required in the XML declaration.",
      "elements": [
        {
          "method": "com.sun.org.apache.xerces.internal.parsers.DOMParser.parse",
          "source": "DOMParser.java:264"
        },
        {
          "method": "com.sun.org.apache.xerces.internal.jaxp.DocumentBuilderImpl.parse",
          "source": "DocumentBuilderImpl.java:292"
        },
        {
          "method": "javax.xml.parsers.DocumentBuilder.parse",
          "source": "DocumentBuilder.java:146"
        },
        {
          "method": "org.eclipse.update.core.model.DefaultSiteParser.getMirrors",
          "source": "DefaultSiteParser.java:829"
        },
        {
          "method": "org.eclipse.update.core.model.SiteModel.getMirrorSiteEntryModels",
          "source": "SiteModel.java:416"
        },
        {
          "method": "org.eclipse.update.core.Site.getMirrorSiteEntries",
          "source": "Site.java:547"
        },
        {
          "method": "org.eclipse.update.ui.UpdateJob$ResultCollectorWithMirrors.getMirror",
          "source": "UpdateJob.java:306"
        },
        {
          "method": "org.eclipse.update.search.UpdateSearchRequest.searchOneSite",
          "source": "UpdateSearchRequest.java:465"
        },
        {
          "method": "org.eclipse.update.search.UpdateSearchRequest.performSearch",
          "source": "UpdateSearchRequest.java:294"
        },
        {
          "method": "org.eclipse.update.ui.UpdateJob.runUpdates",
          "source": "UpdateJob.java:207"
        },
        {
          "method": "org.eclipse.update.ui.UpdateJob.run",
          "source": "UpdateJob.java:168"
        },
        {
          "method": "org.eclipse.core.internal.jobs.Worker.run",
          "source": "Worker.java:58"
        }
      ],
      "number": 0,
      "commentIndex": 0,
      "bugId": "149651",
      "duplicateId": "149771",
      "date": "2006-07-05T12:24:00+02:00",
      "product": "Platform",
      "component": "Update",
      "severity": "normal"
    },
    {
      "exceptionType": "org.xml.sax.SAXParseException",
      "message": "Character conversion error: \"Malformed UTF-8 char  -- is an XML encoding declaration missing?\" (line number may be too low).",
      "elements": [
        {
          "method": "org.apache.crimson.parser.InputEntity.fatal",
          "source": "InputEntity.java:1100"
        },
        {
          "method": "org.apache.crimson.parser.InputEntity.fillbuf",
          "source": "InputEntity.java:1072"
        },
        {
          "method": "org.apache.crimson.parser.InputEntity.isXmlDeclOrTextDeclPrefix",
          "source": "Input Entity.java:914"
        },
        {
          "method": "org.apache.crimson.parser.Parser2.maybeXmlDecl",
          "source": "Parser2.java:1183"
        },
        {
          "method": "org.apache.crimson.parser.Parser2.parseInternal",
          "source": "Parser2.java:653"
        },
        {
          "method": "org.apache.crimson.parser.Parser2.parse",
          "source": "Parser2.java:337"
        },
        {
          "method": "org.apache.crimson.parser.XMLReaderImpl.parse",
          "source": "XMLReaderImpl.java:448"
        },
        {
          "method": "org.apache.crimson.jaxp.DocumentBuilderImpl.parse",
          "source": "DocumentBuilderImpl .java:185"
        },
        {
          "method": "javax.xml.parsers.DocumentBuilder.parse",
          "source": "DocumentBuilder.java:124"
        },
        {
          "method": "org.eclipse.update.core.model.DefaultSiteParser.getMirrors",
          "source": "DefaultSit eParser.java:829"
        },
        {
          "method": "org.eclipse.update.core.model.DefaultSiteParser.processSite",
          "source": "DefaultSi teParser.java:514"
        },
        {
          "method": "org.eclipse.update.core.model.DefaultSiteParser.handleInitialState",
          "source": "De faultSiteParser.java:396"
        },
        {
          "method": "org.eclipse.update.core.model.DefaultSiteParser.startElement",
          "source": "DefaultS iteParser.java:200"
        },
        {
          "method": "org.apache.crimson.parser.Parser2.maybeElement",
          "source": "Parser2.java:1672"
        },
        {
          "method": "org.apache.crimson.parser.Parser2.parseInternal",
          "source": "Parser2.java:667"
        },
        {
          "method": "org.apache.crimson.parser.Parser2.parse",
          "source": "Parser2.java:337"
        },
        {
          "method": "org.apache.crimson.parser.XMLReaderImpl.parse",
          "source": "XMLReaderImpl.java:448"
        },
        {
          "method": "javax.xml.parsers.SAXParser.parse",
          "source": "SAXParser.java:345"
        },
        {
          "method": "org.eclipse.update.core.model.DefaultSiteParser.parse",
          "source": "DefaultSitePars er.java:156"
        },
        {
          "method": "org.eclipse.update.core.model.SiteModelFactory.parseSite",
          "source": "SiteModelFac tory.java:81"
        },
        {
          "method": "org.eclipse.update.internal.core.SiteURLFactory.createSite",
          "source": "SiteURLFac tory.java:80"
        },
        {
          "method": "org.eclipse.update.internal.core.InternalSiteManager.createSite",
          "source": "Inter nalSiteManager.java:334"
        },
        {
          "method": "org.eclipse.update.internal.core.InternalSiteManager.createSite",
          "source": "Inter nalSiteManager.java:326"
        },
        {
          "method": "org.eclipse.update.internal.core.InternalSiteManager.createSite",
          "source": "Inter nalSiteManager.java:291"
        },
        {
          "method": "org.eclipse.update.internal.core.InternalSiteManager.attemptCreateSite",
          "source": "InternalSiteManager.java:222"
        },
        {
          "method": "org.eclipse.update.internal.core.InternalSiteManager.getSite",
          "source": "Internal SiteManager.java:162"
        },
        {
          "method": "org.eclipse.update.core.SiteManager.getSite",
          "source": "SiteManager.java:78"
        },
        {
          "method": "org.eclipse.update.search.UpdateSearchRequest.searchOneSite",
          "source": "UpdateSea rchRequest.java:447"
        },
        {
          "method": "org.eclipse.update.search.UpdateSearchRequest.performSearch",
          "source": "UpdateSea rchRequest.java:294"
        },
        {
          "method": "org.eclipse.update.ui.UpdateJob.runUpdates",
          "source": "UpdateJob.java:207"
        },
        {
          "method": "org.eclipse.update.ui.UpdateJob.run",
          "source": "UpdateJob.java:168"
        },
        {
          "method": "org.eclipse.core.internal.jobs.Worker.run",
          "source": "Worker.java:58"
        }
      ],
      "number": 1,
      "commentIndex": 0,
      "bugId": "149651",
      "duplicateId": "149771",
      "date": "2006-07-05T12:24:00+02:00",
      "product": "Platform",
      "component": "Update",
      "severity": "normal"
    }
  ],
  "groupId": "149771",
  "bugId": "149651",
  "duplicateId": "149771",
  "date": "2006-07-05T12:24:00+02:00",
  "product": "Platform",
  "component": "Update",
  "severity": "normal"
}