{
  "comments": [
    "I20060704-0800\n\n- select a Java project in the Package Explorer\n- choose File \u003e Properties\n- press OK\n\nChanges on other properties pages are also not saved because of this exception.\n\njava.lang.ClassCastException: org.eclipse.jdt.internal.core.JavaProject\n        at org.eclipse.ui.internal.ide.dialogs.ResourceInfoPage.performOk(ResourceInfoPage.java:537)\n        at org.eclipse.jface.preference.PreferenceDialog$11.run(PreferenceDialog.java:889)\n        at org.eclipse.core.runtime.SafeRunner.run(SafeRunner.java:37)\n        at org.eclipse.core.runtime.Platform.run(Platform.java:843)\n        at org.eclipse.ui.internal.JFaceUtil$1.run(JFaceUtil.java:44)\n        at org.eclipse.jface.util.SafeRunnable.run(SafeRunnable.java:149)\n        at org.eclipse.jface.preference.PreferenceDialog.okPressed(PreferenceDialog.java:869)\n        at org.eclipse.ui.internal.dialogs.FilteredPreferenceDialog.okPressed(FilteredPreferenceDialog.java:377)\n        at org.eclipse.jface.preference.PreferenceDialog.buttonPressed(PreferenceDialog.java:230)\n        at org.eclipse.jface.dialogs.Dialog$3.widgetSelected(Dialog.java:660)\n        at org.eclipse.swt.widgets.TypedListener.handleEvent(TypedListener.java:90)\n        at org.eclipse.swt.widgets.EventTable.sendEvent(EventTable.java:66)\n        at org.eclipse.swt.widgets.Widget.sendEvent(Widget.java:928)\n        at org.eclipse.swt.widgets.Display.runDeferredEvents(Display.java:3375)\n        at org.eclipse.swt.widgets.Display.readAndDispatch(Display.java:2995)\n        at org.eclipse.jface.window.Window.runEventLoop(Window.java:820)\n        at org.eclipse.jface.window.Window.open(Window.java:796)\n        at org.eclipse.ui.dialogs.PropertyDialogAction.run(PropertyDialogAction.java:156)\n        at org.eclipse.jface.action.Action.runWithEvent(Action.java:499)\n        at org.eclipse.jface.action.ActionContributionItem.handleWidgetSelection(ActionContributionItem.java:539)\n        at org.eclipse.jface.action.ActionContributionItem.access$2(ActionContributionItem.java:488)\n        at org.eclipse.jface.action.ActionContributionItem$5.handleEvent(ActionContributionItem.java:400)\n        at org.eclipse.swt.widgets.EventTable.sendEvent(EventTable.java:66)\n        at org.eclipse.swt.widgets.Widget.sendEvent(Widget.java:928)\n        at org.eclipse.swt.widgets.Display.runDeferredEvents(Display.java:3375)\n        at org.eclipse.swt.widgets.Display.readAndDispatch(Display.java:2995)\n        at org.eclipse.ui.internal.Workbench.runEventLoop(Workbench.java:1914)\n        at org.eclipse.ui.internal.Workbench.runUI(Workbench.java:1878)\n        at org.eclipse.ui.internal.Workbench.createAndRunWorkbench(Workbench.java:419)\n        at org.eclipse.ui.PlatformUI.createAndRunWorkbench(PlatformUI.java:149)\n        at org.eclipse.ui.internal.ide.IDEApplication.run(IDEApplication.java:95)\n        at org.eclipse.core.internal.runtime.PlatformActivator$1.run(PlatformActivator.java:78)\n        at org.eclipse.core.runtime.internal.adaptor.EclipseAppLauncher.runApplication(EclipseAppLauncher.java:92)\n        at org.eclipse.core.runtime.internal.adaptor.EclipseAppLauncher.start(EclipseAppLauncher.java:68)\n        at org.eclipse.core.runtime.adaptor.EclipseStarter.run(EclipseStarter.java:400)\n        at org.eclipse.core.runtime.adaptor.EclipseStarter.run(EclipseStarter.java:177)\n        at sun.reflect.NativeMethodAccessorImpl.invoke0(Native Method)\n        at sun.reflect.NativeMethodAccessorImpl.invoke(NativeMethodAccessorImpl.java:39)\n        at sun.reflect.DelegatingMethodAccessorImpl.invoke(DelegatingMethodAccessorImpl.java:25)\n        at java.lang.reflect.Method.invoke(Method.java:585)\n        at org.eclipse.core.launcher.Main.invokeFramework(Main.java:336)\n        at org.eclipse.core.launcher.Main.basicRun(Main.java:280)\n        at org.eclipse.core.launcher.Main.run(Main.java:977)\n        at org.eclipse.core.launcher.Main.main(Main.java:952)",
    "Probably caused by the fix for bug 148674.",
    "FIXED in build \u003e20060705",
    "*** Bug 149678 has been marked as a duplicate of this bug. ***",
    "Verified in 20060807-2000"
  ],
  "commentCreationDates": [
    "2006-07-05T15:06:44+02:00",
    "2006-07-05T15:10:59+02:00",
    "2006-07-05T19:40:21+02:00",
    "2006-07-24T10:11:28+02:00",
    "2006-08-08T21:34:04+02:00"
  ],
  "traces": [
    {
      "exceptionType": "java.lang.ClassCastException",
      "message": "org.eclipse.jdt.internal.core.JavaProject",
      "elements": [
        {
          "method": "org.eclipse.ui.internal.ide.dialogs.ResourceInfoPage.performOk",
          "source": "ResourceInfoPage.java:537"
        },
        {
          "method": "org.eclipse.jface.preference.PreferenceDialog$11.run",
          "source": "PreferenceDialog.java:889"
        },
        {
          "method": "org.eclipse.core.runtime.SafeRunner.run",
          "source": "SafeRunner.java:37"
        },
        {
          "method": "org.eclipse.core.runtime.Platform.run",
          "source": "Platform.java:843"
        },
        {
          "method": "org.eclipse.ui.internal.JFaceUtil$1.run",
          "source": "JFaceUtil.java:44"
        },
        {
          "method": "org.eclipse.jface.util.SafeRunnable.run",
          "source": "SafeRunnable.java:149"
        },
        {
          "method": "org.eclipse.jface.preference.PreferenceDialog.okPressed",
          "source": "PreferenceDialog.java:869"
        },
        {
          "method": "org.eclipse.ui.internal.dialogs.FilteredPreferenceDialog.okPressed",
          "source": "FilteredPreferenceDialog.java:377"
        },
        {
          "method": "org.eclipse.jface.preference.PreferenceDialog.buttonPressed",
          "source": "PreferenceDialog.java:230"
        },
        {
          "method": "org.eclipse.jface.dialogs.Dialog$3.widgetSelected",
          "source": "Dialog.java:660"
        },
        {
          "method": "org.eclipse.swt.widgets.TypedListener.handleEvent",
          "source": "TypedListener.java:90"
        },
        {
          "method": "org.eclipse.swt.widgets.EventTable.sendEvent",
          "source": "EventTable.java:66"
        },
        {
          "method": "org.eclipse.swt.widgets.Widget.sendEvent",
          "source": "Widget.java:928"
        },
        {
          "method": "org.eclipse.swt.widgets.Display.runDeferredEvents",
          "source": "Display.java:3375"
        },
        {
          "method": "org.eclipse.swt.widgets.Display.readAndDispatch",
          "source": "Display.java:2995"
        },
        {
          "method": "org.eclipse.jface.window.Window.runEventLoop",
          "source": "Window.java:820"
        },
        {
          "method": "org.eclipse.jface.window.Window.open",
          "source": "Window.java:796"
        },
        {
          "method": "org.eclipse.ui.dialogs.PropertyDialogAction.run",
          "source": "PropertyDialogAction.java:156"
        },
        {
          "method": "org.eclipse.jface.action.Action.runWithEvent",
          "source": "Action.java:499"
        },
        {
          "method": "org.eclipse.jface.action.ActionContributionItem.handleWidgetSelection",
          "source": "ActionContributionItem.java:539"
        },
        {
          "method": "org.eclipse.jface.action.ActionContributionItem.access$2",
          "source": "ActionContributionItem.java:488"
        },
        {
          "method": "org.eclipse.jface.action.ActionContributionItem$5.handleEvent",
          "source": "ActionContributionItem.java:400"
        },
        {
          "method": "org.eclipse.swt.widgets.EventTable.sendEvent",
          "source": "EventTable.java:66"
        },
        {
          "method": "org.eclipse.swt.widgets.Widget.sendEvent",
          "source": "Widget.java:928"
        },
        {
          "method": "org.eclipse.swt.widgets.Display.runDeferredEvents",
          "source": "Display.java:3375"
        },
        {
          "method": "org.eclipse.swt.widgets.Display.readAndDispatch",
          "source": "Display.java:2995"
        },
        {
          "method": "org.eclipse.ui.internal.Workbench.runEventLoop",
          "source": "Workbench.java:1914"
        },
        {
          "method": "org.eclipse.ui.internal.Workbench.runUI",
          "source": "Workbench.java:1878"
        },
        {
          "method": "org.eclipse.ui.internal.Workbench.createAndRunWorkbench",
          "source": "Workbench.java:419"
        },
        {
          "method": "org.eclipse.ui.PlatformUI.createAndRunWorkbench",
          "source": "PlatformUI.java:149"
        },
        {
          "method": "org.eclipse.ui.internal.ide.IDEApplication.run",
          "source": "IDEApplication.java:95"
        },
        {
          "method": "org.eclipse.core.internal.runtime.PlatformActivator$1.run",
          "source": "PlatformActivator.java:78"
        },
        {
          "method": "org.eclipse.core.runtime.internal.adaptor.EclipseAppLauncher.runApplication",
          "source": "EclipseAppLauncher.java:92"
        },
        {
          "method": "org.eclipse.core.runtime.internal.adaptor.EclipseAppLauncher.start",
          "source": "EclipseAppLauncher.java:68"
        },
        {
          "method": "org.eclipse.core.runtime.adaptor.EclipseStarter.run",
          "source": "EclipseStarter.java:400"
        },
        {
          "method": "org.eclipse.core.runtime.adaptor.EclipseStarter.run",
          "source": "EclipseStarter.java:177"
        },
        {
          "method": "sun.reflect.NativeMethodAccessorImpl.invoke0",
          "source": "Native Method"
        },
        {
          "method": "sun.reflect.NativeMethodAccessorImpl.invoke",
          "source": "NativeMethodAccessorImpl.java:39"
        },
        {
          "method": "sun.reflect.DelegatingMethodAccessorImpl.invoke",
          "source": "DelegatingMethodAccessorImpl.java:25"
        },
        {
          "method": "java.lang.reflect.Method.invoke",
          "source": "Method.java:585"
        },
        {
          "method": "org.eclipse.core.launcher.Main.invokeFramework",
          "source": "Main.java:336"
        },
        {
          "method": "org.eclipse.core.launcher.Main.basicRun",
          "source": "Main.java:280"
        },
        {
          "method": "org.eclipse.core.launcher.Main.run",
          "source": "Main.java:977"
        },
        {
          "method": "org.eclipse.core.launcher.Main.main",
          "source": "Main.java:952"
        }
      ],
      "number": 0,
      "commentIndex": 0,
      "bugId": "149663",
      "date": "2006-07-05T15:06:44+02:00",
      "product": "Platform",
      "component": "UI",
      "severity": "major"
    }
  ],
  "groupId": "149663",
  "bugId": "149663",
  "date": "2006-07-05T15:06:44+02:00",
  "product": "Platform",
  "component": "UI",
  "severity": "major"
}