{
  "comments": [
    "Build 20020430\n\nStarted from a full-source Eclipse workspace 20020425, which I upgraded\ninto a 20020430 one (first imported existing library projects - apache, xerces, \netc) then selected all other projects (but jdt/core) as source ones). Got the \nfollowing exception.\n\n!ENTRY org.eclipse.jdt.ui 4 1 Wed May 01 01:26:10 CEST 2002\n!MESSAGE Internal Error\n!STACK org.eclipse.core.internal.resources.ResourceException: \nResource /org.eclipse.core.resources/os does not exist.\n        at org.eclipse.core.internal.resources.Resource.checkExists\n(Resource.java:174)\n        at org.eclipse.core.internal.resources.Resource.checkAccessible\n(Resource.java:89)\n        at org.eclipse.core.internal.resources.Resource.findMarkers\n(Resource.java:550)\n        at \norg.eclipse.jdt.internal.ui.viewsupport.ErrorTickAdornmentProvider.getErrorTicks\nFromMarkers(ErrorTickAdornmentProvider.java:90)\n        at \norg.eclipse.jdt.internal.ui.viewsupport.ErrorTickAdornmentProvider.computeAdornm\nentFlags(ErrorTickAdornmentProvider.java:70)\n        at org.eclipse.jdt.internal.ui.viewsupport.JavaUILabelProvider.getImage\n(JavaUILabelProvider.java:82)\n        at org.eclipse.jface.viewers.DecoratingLabelProvider.getImage\n(DecoratingLabelProvider.java:65)\n        at org.eclipse.jface.viewers.StructuredViewer.getLabel\n(StructuredViewer.java:1089)\n        at org.eclipse.jface.viewers.TreeViewer.doUpdateItem(TreeViewer.java:88)\n        at org.eclipse.jface.viewers.AbstractTreeViewer.doUpdateItem\n(AbstractTreeViewer.java:352)\n        at org.eclipse.jface.viewers.StructuredViewer.updateItem\n(StructuredViewer.java:1044)\n        at org.eclipse.jface.viewers.AbstractTreeViewer.internalRefresh\n(AbstractTreeViewer.java:846)\n        at org.eclipse.jface.viewers.AbstractTreeViewer.internalRefresh\n(AbstractTreeViewer.java:860)\n        at org.eclipse.jface.viewers.AbstractTreeViewer.internalRefresh\n(AbstractTreeViewer.java:860)\n        at org.eclipse.jface.viewers.AbstractTreeViewer.internalRefresh\n(AbstractTreeViewer.java:829)\n        at org.eclipse.jface.viewers.StructuredViewer$1.run\n(StructuredViewer.java:676)\n        at org.eclipse.jface.viewers.StructuredViewer.preservingSelection\n(StructuredViewer.java:616)\n        at org.eclipse.jface.viewers.StructuredViewer.refresh\n(StructuredViewer.java:674)\n        at org.eclipse.jdt.ui.JavaElementContentProvider$2.run\n(JavaElementContentProvider.java:255)\n        at org.eclipse.swt.widgets.RunnableLock.run(RunnableLock.java:29)\n        at org.eclipse.swt.widgets.Synchronizer.runAsyncMessages\n(Synchronizer.java:93)\n        at org.eclipse.swt.widgets.Display.runAsyncMessages(Display.java:1389)\n        at org.eclipse.swt.widgets.Display.readAndDispatch(Display.java:1211)\n        at org.eclipse.jface.operation.ModalContext$ModalContextThread.block\n(ModalContext.java:133)\n        at org.eclipse.jface.operation.ModalContext.run(ModalContext.java:258)\n        at org.eclipse.jface.wizard.WizardDialog.run(WizardDialog.java:720)\n        at \norg.eclipse.pde.internal.ui.wizards.imports.PluginImportWizard.performFinish\n(PluginImportWizard.java:100)\n        at org.eclipse.jface.wizard.WizardDialog.finishPressed\n(WizardDialog.java:577)\n        at org.eclipse.jface.wizard.WizardDialog.buttonPressed\n(WizardDialog.java:312)\n        at org.eclipse.jface.dialogs.Dialog$1.widgetSelected(Dialog.java:379)\n        at org.eclipse.swt.widgets.TypedListener.handleEvent\n(TypedListener.java:85)\n        at org.eclipse.swt.widgets.EventTable.sendEvent(EventTable.java:75)\n        at org.eclipse.swt.widgets.Widget.notifyListeners(Widget.java:637)\n        at org.eclipse.swt.widgets.Display.runDeferredEvents(Display.java:1412)\n        at org.eclipse.swt.widgets.Display.readAndDispatch(Display.java:1208)\n        at org.eclipse.jface.window.Window.runEventLoop(Window.java:538)\n        at org.eclipse.jface.window.Window.open(Window.java:525)\n        at org.eclipse.ui.actions.ImportResourcesAction.run\n(ImportResourcesAction.java:117)\n        at org.eclipse.jface.action.Action.runWithEvent(Action.java:590)\n        at org.eclipse.jface.action.ActionContributionItem.handleWidgetSelection\n(ActionContributionItem.java:407)\n        at org.eclipse.jface.action.ActionContributionItem.handleWidgetEvent\n(ActionContributionItem.java:361)\n        at org.eclipse.jface.action.ActionContributionItem.access$0\n(ActionContributionItem.java:352)\n        at \norg.eclipse.jface.action.ActionContributionItem$ActionListener.handleEvent\n(ActionContributionItem.java:47)\n        at org.eclipse.swt.widgets.EventTable.sendEvent(EventTable.java:75)\n        at org.eclipse.swt.widgets.Widget.notifyListeners(Widget.java:637)\n        at org.eclipse.swt.widgets.Display.runDeferredEvents(Display.java:1412)\n        at org.eclipse.swt.widgets.Display.readAndDispatch(Display.java:1208)\n        at org.eclipse.ui.internal.Workbench.runEventLoop(Workbench.java:883)\n        at org.eclipse.ui.internal.Workbench.run(Workbench.java:866)\n        at org.eclipse.core.internal.boot.InternalBootLoader.run\n(InternalBootLoader.java:733)\n        at org.eclipse.core.boot.BootLoader.run(BootLoader.java:349)\n        at java.lang.reflect.Method.invoke(Native Method)\n        at org.eclipse.core.launcher.Main.basicRun(Main.java:162)\n        at org.eclipse.core.launcher.Main.run(Main.java:588)\n        at org.eclipse.core.launcher.UIMain.main(UIMain.java:52)",
    "fixed \u003e 20020430"
  ],
  "commentCreationDates": [
    "2002-05-01T01:29:29+02:00",
    "2002-05-01T12:02:53+02:00"
  ],
  "traces": [
    {
      "exceptionType": "org.eclipse.core.internal.resources.ResourceException",
      "message": "Resource /org.eclipse.core.resources/os does not exist.",
      "elements": [
        {
          "method": "org.eclipse.core.internal.resources.Resource.checkExists",
          "source": "Resource.java:174"
        },
        {
          "method": "org.eclipse.core.internal.resources.Resource.checkAccessible",
          "source": "Resource.java:89"
        },
        {
          "method": "org.eclipse.core.internal.resources.Resource.findMarkers",
          "source": "Resource.java:550"
        },
        {
          "method": "org.eclipse.jdt.internal.ui.viewsupport.ErrorTickAdornmentProvider.getErrorTicksFromMarkers",
          "source": "ErrorTickAdornmentProvider.java:90"
        },
        {
          "method": "org.eclipse.jdt.internal.ui.viewsupport.ErrorTickAdornmentProvider.computeAdornmentFlags",
          "source": "ErrorTickAdornmentProvider.java:70"
        },
        {
          "method": "org.eclipse.jdt.internal.ui.viewsupport.JavaUILabelProvider.getImage",
          "source": "JavaUILabelProvider.java:82"
        },
        {
          "method": "org.eclipse.jface.viewers.DecoratingLabelProvider.getImage",
          "source": "DecoratingLabelProvider.java:65"
        },
        {
          "method": "org.eclipse.jface.viewers.StructuredViewer.getLabel",
          "source": "StructuredViewer.java:1089"
        },
        {
          "method": "org.eclipse.jface.viewers.TreeViewer.doUpdateItem",
          "source": "TreeViewer.java:88"
        },
        {
          "method": "org.eclipse.jface.viewers.AbstractTreeViewer.doUpdateItem",
          "source": "AbstractTreeViewer.java:352"
        },
        {
          "method": "org.eclipse.jface.viewers.StructuredViewer.updateItem",
          "source": "StructuredViewer.java:1044"
        },
        {
          "method": "org.eclipse.jface.viewers.AbstractTreeViewer.internalRefresh",
          "source": "AbstractTreeViewer.java:846"
        },
        {
          "method": "org.eclipse.jface.viewers.AbstractTreeViewer.internalRefresh",
          "source": "AbstractTreeViewer.java:860"
        },
        {
          "method": "org.eclipse.jface.viewers.AbstractTreeViewer.internalRefresh",
          "source": "AbstractTreeViewer.java:860"
        },
        {
          "method": "org.eclipse.jface.viewers.AbstractTreeViewer.internalRefresh",
          "source": "AbstractTreeViewer.java:829"
        },
        {
          "method": "org.eclipse.jface.viewers.StructuredViewer$1.run",
          "source": "StructuredViewer.java:676"
        },
        {
          "method": "org.eclipse.jface.viewers.StructuredViewer.preservingSelection",
          "source": "StructuredViewer.java:616"
        },
        {
          "method": "org.eclipse.jface.viewers.StructuredViewer.refresh",
          "source": "StructuredViewer.java:674"
        },
        {
          "method": "org.eclipse.jdt.ui.JavaElementContentProvider$2.run",
          "source": "JavaElementContentProvider.java:255"
        },
        {
          "method": "org.eclipse.swt.widgets.RunnableLock.run",
          "source": "RunnableLock.java:29"
        },
        {
          "method": "org.eclipse.swt.widgets.Synchronizer.runAsyncMessages",
          "source": "Synchronizer.java:93"
        },
        {
          "method": "org.eclipse.swt.widgets.Display.runAsyncMessages",
          "source": "Display.java:1389"
        },
        {
          "method": "org.eclipse.swt.widgets.Display.readAndDispatch",
          "source": "Display.java:1211"
        },
        {
          "method": "org.eclipse.jface.operation.ModalContext$ModalContextThread.block",
          "source": "ModalContext.java:133"
        },
        {
          "method": "org.eclipse.jface.operation.ModalContext.run",
          "source": "ModalContext.java:258"
        },
        {
          "method": "org.eclipse.jface.wizard.WizardDialog.run",
          "source": "WizardDialog.java:720"
        },
        {
          "method": "org.eclipse.pde.internal.ui.wizards.imports.PluginImportWizard.performFinish",
          "source": "PluginImportWizard.java:100"
        },
        {
          "method": "org.eclipse.jface.wizard.WizardDialog.finishPressed",
          "source": "WizardDialog.java:577"
        },
        {
          "method": "org.eclipse.jface.wizard.WizardDialog.buttonPressed",
          "source": "WizardDialog.java:312"
        },
        {
          "method": "org.eclipse.jface.dialogs.Dialog$1.widgetSelected",
          "source": "Dialog.java:379"
        },
        {
          "method": "org.eclipse.swt.widgets.TypedListener.handleEvent",
          "source": "TypedListener.java:85"
        },
        {
          "method": "org.eclipse.swt.widgets.EventTable.sendEvent",
          "source": "EventTable.java:75"
        },
        {
          "method": "org.eclipse.swt.widgets.Widget.notifyListeners",
          "source": "Widget.java:637"
        },
        {
          "method": "org.eclipse.swt.widgets.Display.runDeferredEvents",
          "source": "Display.java:1412"
        },
        {
          "method": "org.eclipse.swt.widgets.Display.readAndDispatch",
          "source": "Display.java:1208"
        },
        {
          "method": "org.eclipse.jface.window.Window.runEventLoop",
          "source": "Window.java:538"
        },
        {
          "method": "org.eclipse.jface.window.Window.open",
          "source": "Window.java:525"
        },
        {
          "method": "org.eclipse.ui.actions.ImportResourcesAction.run",
          "source": "ImportResourcesAction.java:117"
        },
        {
          "method": "org.eclipse.jface.action.Action.runWithEvent",
          "source": "Action.java:590"
        },
        {
          "method": "org.eclipse.jface.action.ActionContributionItem.handleWidgetSelection",
          "source": "ActionContributionItem.java:407"
        },
        {
          "method": "org.eclipse.jface.action.ActionContributionItem.handleWidgetEvent",
          "source": "ActionContributionItem.java:361"
        },
        {
          "method": "org.eclipse.jface.action.ActionContributionItem.access$0",
          "source": "ActionContributionItem.java:352"
        },
        {
          "method": "org.eclipse.jface.action.ActionContributionItem$ActionListener.handleEvent",
          "source": "ActionContributionItem.java:47"
        },
        {
          "method": "org.eclipse.swt.widgets.EventTable.sendEvent",
          "source": "EventTable.java:75"
        },
        {
          "method": "org.eclipse.swt.widgets.Widget.notifyListeners",
          "source": "Widget.java:637"
        },
        {
          "method": "org.eclipse.swt.widgets.Display.runDeferredEvents",
          "source": "Display.java:1412"
        },
        {
          "method": "org.eclipse.swt.widgets.Display.readAndDispatch",
          "source": "Display.java:1208"
        },
        {
          "method": "org.eclipse.ui.internal.Workbench.runEventLoop",
          "source": "Workbench.java:883"
        },
        {
          "method": "org.eclipse.ui.internal.Workbench.run",
          "source": "Workbench.java:866"
        },
        {
          "method": "org.eclipse.core.internal.boot.InternalBootLoader.run",
          "source": "InternalBootLoader.java:733"
        },
        {
          "method": "org.eclipse.core.boot.BootLoader.run",
          "source": "BootLoader.java:349"
        },
        {
          "method": "java.lang.reflect.Method.invoke",
          "source": "Native Method"
        },
        {
          "method": "org.eclipse.core.launcher.Main.basicRun",
          "source": "Main.java:162"
        },
        {
          "method": "org.eclipse.core.launcher.Main.run",
          "source": "Main.java:588"
        },
        {
          "method": "org.eclipse.core.launcher.UIMain.main",
          "source": "UIMain.java:52"
        }
      ],
      "number": 0,
      "commentIndex": 0,
      "bugId": "14975",
      "date": "2002-05-01T01:29:29+02:00",
      "product": "JDT",
      "component": "UI",
      "severity": "normal"
    }
  ],
  "groupId": "14975",
  "bugId": "14975",
  "date": "2002-05-01T01:29:29+02:00",
  "product": "JDT",
  "component": "UI",
  "severity": "normal"
}