{
  "comments": [
    "skoke test setup for 20020430\n\nFound it in the console, can\u0027t reproduce.\nPrinted directly to the console (not the log)\n\n\njava.lang.ArrayIndexOutOfBoundsException: 21094\n        at java.lang.StringBuffer.append(StringBuffer.java(Compiled Code))\n        at org.eclipse.jface.text.GapTextStore.get(GapTextStore.java(Compiled Co\nde))\n        at org.eclipse.jface.text.AbstractDocument.get(AbstractDocument.java:716\n)\n        at org.eclipse.jdt.internal.ui.javaeditor.DocumentAdapter.getContents(Do\ncumentAdapter.java:270)\n        at org.eclipse.jdt.internal.core.CompilationUnit.getSource(CompilationUn\nit.java:532)\n        at org.eclipse.jdt.internal.core.CompilationUnitProblemFinder.resolve(Co\nmpilationUnitProblemFinder.java:153)\n        at org.eclipse.jdt.internal.core.CompilationUnit.buildStructure(Compilat\nionUnit.java(Compiled Code))\n        at org.eclipse.jdt.internal.core.CompilationUnit.makeConsistent(Compilat\nionUnit.java:668)\n        at org.eclipse.jdt.internal.core.WorkingCopy.reconcile(WorkingCopy.java:\n342)\n        at org.eclipse.jdt.internal.ui.text.java.JavaReconcilingStrategy.reconci\nle(JavaReconcilingStrategy.java:62)\n        at org.eclipse.jdt.internal.ui.text.java.JavaReconcilingStrategy.reconci\nle(JavaReconcilingStrategy.java:80)\n        at org.eclipse.jface.text.reconciler.MonoReconciler.process(MonoReconcil\ner.java:66)\n        at org.eclipse.jface.text.reconciler.AbstractReconciler$BackgroundThread\n.run(AbstractReconciler.java:153)",
    "Build F2. JDT uses PartiallySynchronizedDocument.",
    "Can\u0027t be verified since there isn\u0027t a repeatable test case.\n\nClosing"
  ],
  "commentCreationDates": [
    "2002-05-01T13:26:08+02:00",
    "2002-06-04T18:12:30+02:00",
    "2002-06-13T16:45:52+02:00"
  ],
  "traces": [
    {
      "exceptionType": "java.lang.ArrayIndexOutOfBoundsException",
      "message": "21094",
      "elements": [
        {
          "method": "java.lang.StringBuffer.append",
          "source": "StringBuffer.java(Compiled Code)"
        },
        {
          "method": "org.eclipse.jface.text.GapTextStore.get",
          "source": "GapTextStore.java(Compiled Co de)"
        },
        {
          "method": "org.eclipse.jface.text.AbstractDocument.get",
          "source": "AbstractDocument.java:716 "
        },
        {
          "method": "org.eclipse.jdt.internal.ui.javaeditor.DocumentAdapter.getContents",
          "source": "Do cumentAdapter.java:270"
        },
        {
          "method": "org.eclipse.jdt.internal.core.CompilationUnit.getSource",
          "source": "CompilationUn it.java:532"
        },
        {
          "method": "org.eclipse.jdt.internal.core.CompilationUnitProblemFinder.resolve",
          "source": "Co mpilationUnitProblemFinder.java:153"
        },
        {
          "method": "org.eclipse.jdt.internal.core.CompilationUnit.buildStructure",
          "source": "Compilat ionUnit.java(Compiled Code)"
        },
        {
          "method": "org.eclipse.jdt.internal.core.CompilationUnit.makeConsistent",
          "source": "Compilat ionUnit.java:668"
        },
        {
          "method": "org.eclipse.jdt.internal.core.WorkingCopy.reconcile",
          "source": "WorkingCopy.java: 342"
        },
        {
          "method": "org.eclipse.jdt.internal.ui.text.java.JavaReconcilingStrategy.reconcile",
          "source": "JavaReconcilingStrategy.java:62"
        },
        {
          "method": "org.eclipse.jdt.internal.ui.text.java.JavaReconcilingStrategy.reconcile",
          "source": "JavaReconcilingStrategy.java:80"
        },
        {
          "method": "org.eclipse.jface.text.reconciler.MonoReconciler.process",
          "source": "MonoReconcil er.java:66"
        },
        {
          "method": "org.eclipse.jface.text.reconciler.AbstractReconciler$BackgroundThread.run",
          "source": "AbstractReconciler.java:153"
        }
      ],
      "number": 0,
      "commentIndex": 0,
      "bugId": "14982",
      "date": "2002-05-01T13:26:08+02:00",
      "product": "JDT",
      "component": "UI",
      "severity": "normal"
    }
  ],
  "groupId": "14982",
  "bugId": "14982",
  "date": "2002-05-01T13:26:08+02:00",
  "product": "JDT",
  "component": "UI",
  "severity": "normal"
}