{
  "comments": [
    "Hi Everyone,\n\n   I am trying to connect to a AIX (UNIX) server, and i changed the daemom port to connect via 21. But still when i try to connect it, it tell me that i connectiong fail at \"Failed to connect to the daemon on SPOON using port 4035 with an unexpected exception\". the 4035 is what is set as default, does this prefence not work or what? has any body tested this? If is this a error in error representation or are the preferences not getting carried around. Please let me know? \n\nhere is stack trace.\n\norg.eclipse.rse.services.clientserver.messages.SystemMessageException: Failed to connect to the daemon on SPOON using port 4035 with an unexpected exception\nat org.eclipse.rse.connectorservice.dstore.DStoreConnectorService.internalConnect(DStoreConnectorService.java:1028)\nat org.eclipse.rse.core.subsystems.AbstractConnectorService.connect(AbstractConnectorService.java:739)\nat org.eclipse.rse.core.subsystems.SubSystem.internalConnect(SubSystem.java:2783)\nat org.eclipse.rse.core.subsystems.SubSystem$ConnectJob.performOperation(SubSystem.java:1617)\nat org.eclipse.rse.core.subsystems.SubSystem$SubSystemOperationJob.run(SubSystem.java:1332)\nat org.eclipse.core.internal.jobs.Worker.run(Worker.java:58)\n\n\nThanks,\nPratik",
    "Reassigned to Target Management - Pratik please report against Product: Target Management in the future. You can use the \"Submit New\" bugzilla Link from \nhttp://www.eclipse.org/dsdp/tm/",
    "\n\n*** This bug has been marked as a duplicate of 152503 ***"
  ],
  "commentCreationDates": [
    "2006-07-14T23:43:09+02:00",
    "2006-08-04T11:24:48+02:00",
    "2006-08-04T11:44:13+02:00"
  ],
  "traces": [
    {
      "exceptionType": "org.eclipse.rse.services.clientserver.messages.SystemMessageException",
      "message": "Failed to connect to the daemon on SPOON using port 4035 with an unexpected exception",
      "elements": [
        {
          "method": "org.eclipse.rse.connectorservice.dstore.DStoreConnectorService.internalConnect",
          "source": "DStoreConnectorService.java:1028"
        },
        {
          "method": "org.eclipse.rse.core.subsystems.AbstractConnectorService.connect",
          "source": "AbstractConnectorService.java:739"
        },
        {
          "method": "org.eclipse.rse.core.subsystems.SubSystem.internalConnect",
          "source": "SubSystem.java:2783"
        },
        {
          "method": "org.eclipse.rse.core.subsystems.SubSystem$ConnectJob.performOperation",
          "source": "SubSystem.java:1617"
        },
        {
          "method": "org.eclipse.rse.core.subsystems.SubSystem$SubSystemOperationJob.run",
          "source": "SubSystem.java:1332"
        },
        {
          "method": "org.eclipse.core.internal.jobs.Worker.run",
          "source": "Worker.java:58"
        }
      ],
      "number": 0,
      "commentIndex": 0,
      "bugId": "150719",
      "duplicateId": "152503",
      "date": "2006-07-14T23:43:09+02:00",
      "product": "Target Management",
      "component": "RSE",
      "severity": "critical"
    }
  ],
  "groupId": "152503",
  "bugId": "150719",
  "duplicateId": "152503",
  "date": "2006-07-14T23:43:09+02:00",
  "product": "Target Management",
  "component": "RSE",
  "severity": "critical"
}