{
  "comments": [
    "OS: Windows XP with SP2\nLanguage: English\nBuild: epf-composer-1.0-M4-N20060718-win32\n\t    \nSteps to Reproduce:\n1. Create a new Method Library\n2. Create a new Method Configurations\n3. Create a new Method Plug-in\n4. Create another new Method Plug-in, click File-\u003eClose all to save all items\n5. Create a new Delivery Process belong to Plug-in A\n6. Right click on it, press Move\n7. Select Delivery Process of Plug-in B as target\n8. Click OK.\n   --\u003eProblem: An error window popup with  \"Error during move\"\n\nExpected Result: The Delivery Process should be moved correctly.\n\nRemarks:\n1. The same problem on RHEL4U3(en_US.UTF-8)\n2. This is the details error info:\n\n  Error saving file(s)\n    org.eclipse.epf.persistence.MultiFileIOException: Resource is out of synch and needs to be reloaded: D:\\TempWS\\plugin1\\plugin.xmi\n\tat org.eclipse.epf.persistence.MultiFileSaveUtil.checkOutOfSynch(MultiFileSaveUtil.java:453)\n\tat org.eclipse.epf.persistence.MethodLibraryPersister$FailSafePersister.adjustLocation(MethodLibraryPersister.java:634)\n\tat org.eclipse.epf.library.edit.command.MethodElementAddCommand$MoveOperation.save(MethodElementAddCommand.java:1768)\n\tat org.eclipse.epf.library.edit.command.MethodElementAddCommand$MoveOperation.access$3(MethodElementAddCommand.java:1751)\n\tat org.eclipse.epf.library.edit.command.MethodElementAddCommand$4.run(MethodElementAddCommand.java:1537)\n\tat org.eclipse.jface.operation.ModalContext$ModalContextThread.run(ModalContext.java:113)",
    "Last modified timestamp for newly created plugin is not set and this triggered false alarm about \"out of synch\"",
    "Verified on build epf-composer-1.0-M4-N20060719-1630-win32, this defect is fixed. Thanks."
  ],
  "commentCreationDates": [
    "2006-07-19T10:42:53+02:00",
    "2006-07-20T00:21:38+02:00",
    "2006-07-20T07:24:06+02:00"
  ],
  "traces": [
    {
      "exceptionType": "org.eclipse.epf.persistence.MultiFileIOException",
      "message": "Resource is out of synch and needs to be reloaded: D:\\TempWS\\plugin1\\plugin.xmi",
      "elements": [
        {
          "method": "org.eclipse.epf.persistence.MultiFileSaveUtil.checkOutOfSynch",
          "source": "MultiFileSaveUtil.java:453"
        },
        {
          "method": "org.eclipse.epf.persistence.MethodLibraryPersister$FailSafePersister.adjustLocation",
          "source": "MethodLibraryPersister.java:634"
        },
        {
          "method": "org.eclipse.epf.library.edit.command.MethodElementAddCommand$MoveOperation.save",
          "source": "MethodElementAddCommand.java:1768"
        },
        {
          "method": "org.eclipse.epf.library.edit.command.MethodElementAddCommand$MoveOperation.access$3",
          "source": "MethodElementAddCommand.java:1751"
        },
        {
          "method": "org.eclipse.epf.library.edit.command.MethodElementAddCommand$4.run",
          "source": "MethodElementAddCommand.java:1537"
        },
        {
          "method": "org.eclipse.jface.operation.ModalContext$ModalContextThread.run",
          "source": "ModalContext.java:113"
        }
      ],
      "number": 0,
      "commentIndex": 0,
      "bugId": "151052",
      "date": "2006-07-19T10:42:53+02:00",
      "product": "EPF",
      "component": "Tool",
      "severity": "major"
    }
  ],
  "groupId": "151052",
  "bugId": "151052",
  "date": "2006-07-19T10:42:53+02:00",
  "product": "EPF",
  "component": "Tool",
  "severity": "major"
}