{
  "comments": [
    "Hi,\n\nUnder different circumstances ( Opening an XML file, running the update manager, opening a \u0027rename file\u0027 dialog ), eclipse hangs, and there is no way of making it return control.\n\nEclipse:\nVersion: 3.2.0\nBuild id: M20060629-1905\n\nuname -a:\nLinux nazgul 2.6.13-15.10-default #1 Fri May 12 16:27:12 UTC 2006 i686 i686 i386 GNU/Linux\n\njava -version: \njava version \"1.5.0_06\"\nJava(TM) 2 Runtime Environment, Standard Edition (build 1.5.0_06-b05)\nJava HotSpot(TM) Client VM (build 1.5.0_06-b05, mixed mode, sharing)\n\n\nStack trace:\n!ENTRY org.eclipse.ui 4 4 2006-07-18 23:02:57.523\n!MESSAGE Unhandled event loop exception\n\n!ENTRY org.eclipse.ui 4 0 2006-07-18 23:02:57.526\n!MESSAGE Failed to execute runnable (org.eclipse.jface.text.Assert$AssertionFailedException: Assertion failed: )\n!STACK 0\norg.eclipse.swt.SWTException: Failed to execute runnable (org.eclipse.jface.text.Assert$AssertionFailedException: Assertion failed: )\n        at org.eclipse.swt.SWT.error(SWT.java:3374)\n        at org.eclipse.swt.SWT.error(SWT.java:3297)\n        at org.eclipse.swt.widgets.Synchronizer.runAsyncMessages(Synchronizer.java:126)\n        at org.eclipse.swt.widgets.Display.runAsyncMessages(Display.java:3141)\n        at org.eclipse.swt.widgets.Display.readAndDispatch(Display.java:2843)\n        at org.eclipse.ui.internal.Workbench.runEventLoop(Workbench.java:1914)\n        at org.eclipse.ui.internal.Workbench.runUI(Workbench.java:1878)\n        at org.eclipse.ui.internal.Workbench.createAndRunWorkbench(Workbench.java:419)\n        at org.eclipse.ui.PlatformUI.createAndRunWorkbench(PlatformUI.java:149)\n        at org.eclipse.ui.internal.ide.IDEApplication.run(IDEApplication.java:95)\n        at org.eclipse.core.internal.runtime.PlatformActivator$1.run(PlatformActivator.java:78)\n        at org.eclipse.core.runtime.internal.adaptor.EclipseAppLauncher.runApplication(EclipseAppLauncher.java:92)\n        at org.eclipse.core.runtime.internal.adaptor.EclipseAppLauncher.start(EclipseAppLauncher.java:68)\n        at org.eclipse.core.runtime.adaptor.EclipseStarter.run(EclipseStarter.java:400)\n        at org.eclipse.core.runtime.adaptor.EclipseStarter.run(EclipseStarter.java:177)\n        at sun.reflect.NativeMethodAccessorImpl.invoke0(Native Method)\n        at sun.reflect.NativeMethodAccessorImpl.invoke(NativeMethodAccessorImpl.java:39)\n        at sun.reflect.DelegatingMethodAccessorImpl.invoke(DelegatingMethodAccessorImpl.java:25)\n        at java.lang.reflect.Method.invoke(Method.java:585)\n        at org.eclipse.core.launcher.Main.invokeFramework(Main.java:336)\n        at org.eclipse.core.launcher.Main.basicRun(Main.java:280)\n        at org.eclipse.core.launcher.Main.run(Main.java:977)\n        at org.eclipse.core.launcher.Main.main(Main.java:952)\nCaused by: org.eclipse.jface.text.Assert$AssertionFailedException: Assertion failed:\n        at org.eclipse.jface.text.Assert.isTrue(Assert.java:188)\n        at org.eclipse.jface.text.Assert.isTrue(Assert.java:173)\n        at org.eclipse.text.edits.TextEdit.\u003cinit\u003e(TextEdit.java:145)\n        at org.eclipse.text.edits.MultiTextEdit.\u003cinit\u003e(MultiTextEdit.java:61)\n        at org.eclipse.text.edits.CopySourceEdit.performSourceComputation(CopySourceEdit.java:258)\n        at org.eclipse.text.edits.CopySourceEdit.traverseSourceComputation(CopySourceEdit.java:253)\n        at org.eclipse.text.edits.TextEditProcessor.computeSources(TextEditProcessor.java:201)\n        at org.eclipse.text.edits.TextEditProcessor.executeDo(TextEditProcessor.java:184)\n        at org.eclipse.text.edits.TextEdit.dispatchPerformEdits(TextEdit.java:700)\n        at org.eclipse.text.edits.TextEditProcessor.performEdits(TextEditProcessor.java:153)\n        at org.eclipse.ltk.core.refactoring.TextChange.getPreviewDocument(TextChange.java:507)\n        at org.eclipse.ltk.core.refactoring.TextChange.getPreviewDocument(TextChange.java:376)\n        at org.eclipse.jdt.internal.ui.text.correction.CUCorrectionProposal.getAdditionalProposalInfo(CUCorrectionProposal.java:133)\n        at org.eclipse.jface.text.contentassist.AdditionalInfoController$6.run(AdditionalInfoController.java:162)\n        at org.eclipse.swt.widgets.RunnableLock.run(RunnableLock.java:35)\n        at org.eclipse.swt.widgets.Synchronizer.runAsyncMessages(Synchronizer.java:123)\n        ... 20 more",
    "Do you still see this? If so, please provide more information. The attacked .log shows a bug when preparing a preview but I cannot reproduce this. \n\n\u003eeclipse hangs, and there is no way\n\u003eof making it return control.\nHangs forever, for a second?\n\nIf you can still reproduce this using 3.2.2 or 3.3 M7 please create stack dumps and attach them here. See also:\nhttp://www.eclipse.org/eclipse/platform-text/development/bug-incomplete.htm",
    "No, I cannot reproduce this using later builds.",
    "Thanks Robert."
  ],
  "commentCreationDates": [
    "2006-07-18T22:56:25+02:00",
    "2007-03-26T09:21:43+02:00",
    "2007-03-26T10:00:10+02:00",
    "2007-03-26T10:05:43+02:00"
  ],
  "traces": [
    {
      "exceptionType": "org.eclipse.jface.text.Assert$AssertionFailedException",
      "message": "Assertion failed: )",
      "elements": [
        {
          "method": "org.eclipse.swt.SWT.error",
          "source": "SWT.java:3374"
        },
        {
          "method": "org.eclipse.swt.SWT.error",
          "source": "SWT.java:3297"
        },
        {
          "method": "org.eclipse.swt.widgets.Synchronizer.runAsyncMessages",
          "source": "Synchronizer.java:126"
        },
        {
          "method": "org.eclipse.swt.widgets.Display.runAsyncMessages",
          "source": "Display.java:3141"
        },
        {
          "method": "org.eclipse.swt.widgets.Display.readAndDispatch",
          "source": "Display.java:2843"
        },
        {
          "method": "org.eclipse.ui.internal.Workbench.runEventLoop",
          "source": "Workbench.java:1914"
        },
        {
          "method": "org.eclipse.ui.internal.Workbench.runUI",
          "source": "Workbench.java:1878"
        },
        {
          "method": "org.eclipse.ui.internal.Workbench.createAndRunWorkbench",
          "source": "Workbench.java:419"
        },
        {
          "method": "org.eclipse.ui.PlatformUI.createAndRunWorkbench",
          "source": "PlatformUI.java:149"
        },
        {
          "method": "org.eclipse.ui.internal.ide.IDEApplication.run",
          "source": "IDEApplication.java:95"
        },
        {
          "method": "org.eclipse.core.internal.runtime.PlatformActivator$1.run",
          "source": "PlatformActivator.java:78"
        },
        {
          "method": "org.eclipse.core.runtime.internal.adaptor.EclipseAppLauncher.runApplication",
          "source": "EclipseAppLauncher.java:92"
        },
        {
          "method": "org.eclipse.core.runtime.internal.adaptor.EclipseAppLauncher.start",
          "source": "EclipseAppLauncher.java:68"
        },
        {
          "method": "org.eclipse.core.runtime.adaptor.EclipseStarter.run",
          "source": "EclipseStarter.java:400"
        },
        {
          "method": "org.eclipse.core.runtime.adaptor.EclipseStarter.run",
          "source": "EclipseStarter.java:177"
        },
        {
          "method": "sun.reflect.NativeMethodAccessorImpl.invoke0",
          "source": "Native Method"
        },
        {
          "method": "sun.reflect.NativeMethodAccessorImpl.invoke",
          "source": "NativeMethodAccessorImpl.java:39"
        },
        {
          "method": "sun.reflect.DelegatingMethodAccessorImpl.invoke",
          "source": "DelegatingMethodAccessorImpl.java:25"
        },
        {
          "method": "java.lang.reflect.Method.invoke",
          "source": "Method.java:585"
        },
        {
          "method": "org.eclipse.core.launcher.Main.invokeFramework",
          "source": "Main.java:336"
        },
        {
          "method": "org.eclipse.core.launcher.Main.basicRun",
          "source": "Main.java:280"
        },
        {
          "method": "org.eclipse.core.launcher.Main.run",
          "source": "Main.java:977"
        },
        {
          "method": "org.eclipse.core.launcher.Main.main",
          "source": "Main.java:952"
        }
      ],
      "causedBy": {
        "exceptionType": "org.eclipse.jface.text.Assert$AssertionFailedException",
        "message": "Assertion failed:",
        "elements": [
          {
            "method": "org.eclipse.jface.text.Assert.isTrue",
            "source": "Assert.java:188"
          },
          {
            "method": "org.eclipse.jface.text.Assert.isTrue",
            "source": "Assert.java:173"
          },
          {
            "method": "org.eclipse.text.edits.TextEdit.\u003cinit\u003e",
            "source": "TextEdit.java:145"
          },
          {
            "method": "org.eclipse.text.edits.MultiTextEdit.\u003cinit\u003e",
            "source": "MultiTextEdit.java:61"
          },
          {
            "method": "org.eclipse.text.edits.CopySourceEdit.performSourceComputation",
            "source": "CopySourceEdit.java:258"
          },
          {
            "method": "org.eclipse.text.edits.CopySourceEdit.traverseSourceComputation",
            "source": "CopySourceEdit.java:253"
          },
          {
            "method": "org.eclipse.text.edits.TextEditProcessor.computeSources",
            "source": "TextEditProcessor.java:201"
          },
          {
            "method": "org.eclipse.text.edits.TextEditProcessor.executeDo",
            "source": "TextEditProcessor.java:184"
          },
          {
            "method": "org.eclipse.text.edits.TextEdit.dispatchPerformEdits",
            "source": "TextEdit.java:700"
          },
          {
            "method": "org.eclipse.text.edits.TextEditProcessor.performEdits",
            "source": "TextEditProcessor.java:153"
          },
          {
            "method": "org.eclipse.ltk.core.refactoring.TextChange.getPreviewDocument",
            "source": "TextChange.java:507"
          },
          {
            "method": "org.eclipse.ltk.core.refactoring.TextChange.getPreviewDocument",
            "source": "TextChange.java:376"
          },
          {
            "method": "org.eclipse.jdt.internal.ui.text.correction.CUCorrectionProposal.getAdditionalProposalInfo",
            "source": "CUCorrectionProposal.java:133"
          },
          {
            "method": "org.eclipse.jface.text.contentassist.AdditionalInfoController$6.run",
            "source": "AdditionalInfoController.java:162"
          },
          {
            "method": "org.eclipse.swt.widgets.RunnableLock.run",
            "source": "RunnableLock.java:35"
          },
          {
            "method": "org.eclipse.swt.widgets.Synchronizer.runAsyncMessages",
            "source": "Synchronizer.java:123"
          }
        ],
        "number": 0,
        "commentIndex": 0
      },
      "number": 0,
      "commentIndex": 0,
      "bugId": "151008",
      "date": "2006-07-18T22:56:25+02:00",
      "product": "Platform",
      "component": "Text",
      "severity": "major"
    }
  ],
  "groupId": "151008",
  "bugId": "151008",
  "date": "2006-07-18T22:56:25+02:00",
  "product": "Platform",
  "component": "Text",
  "severity": "major"
}