{
  "comments": [
    "Build 20020502\n\nFound the following NPE in my console. Couldn\u0027t reproduce.\n\nAn exception occurred while writing to the platform log:\njava.lang.NullPointerException: null\nLogging to the console instead.\nAn exception occurred while logging to the console:\njava.lang.NullPointerException: null\njava.lang.ArrayIndexOutOfBoundsException\n        at java.lang.System.arraycopy(Native Method)\n        at org.eclipse.jdt.internal.core.index.impl.GammaCompressedIndexBlock.ne\nxtEntry(GammaCompressedIndexBlock.java:79)\n        at org.eclipse.jdt.internal.core.index.impl.BlocksIndexInput.moveToNextW\nordEntry(BlocksIndexInput.java:181)\n        at org.eclipse.jdt.internal.core.index.impl.MergeFactory.mergeReferences\n(MergeFactory.java:170)\n        at org.eclipse.jdt.internal.core.index.impl.MergeFactory.merge(MergeFact\nory.java:79)\n        at org.eclipse.jdt.internal.core.index.impl.Index.merge(Index.java:236)\n        at org.eclipse.jdt.internal.core.index.impl.Index.save(Index.java:341)\n        at org.eclipse.jdt.internal.core.search.indexing.IndexManager.saveIndexe\ns(IndexManager.java:408)\n        at org.eclipse.jdt.internal.core.search.indexing.IndexManager.notifyIdle\n(IndexManager.java:313)\n        at org.eclipse.jdt.internal.core.search.processing.JobManager.run(JobMan\nager.java:302)\n        at java.lang.Thread.run(Thread.java:484)",
    "Which runtime where you using ? IBM jdk1.3.1 ?",
    "No, I am using Sun JDK 1.3.1_01",
    "Not identical... just a few lines earlier.\n\n*** This bug has been marked as a duplicate of 15262 ***"
  ],
  "commentCreationDates": [
    "2002-05-03T12:19:51+02:00",
    "2002-05-03T22:54:12+02:00",
    "2002-05-06T09:54:08+02:00",
    "2002-05-08T21:05:30+02:00"
  ],
  "traces": [
    {
      "exceptionType": "java.lang.ArrayIndexOutOfBoundsException",
      "elements": [
        {
          "method": "java.lang.System.arraycopy",
          "source": "Native Method"
        },
        {
          "method": "org.eclipse.jdt.internal.core.index.impl.GammaCompressedIndexBlock.nextEntry",
          "source": "GammaCompressedIndexBlock.java:79"
        },
        {
          "method": "org.eclipse.jdt.internal.core.index.impl.BlocksIndexInput.moveToNextWordEntry",
          "source": "BlocksIndexInput.java:181"
        },
        {
          "method": "org.eclipse.jdt.internal.core.index.impl.MergeFactory.mergeReferences",
          "source": "MergeFactory.java:170"
        },
        {
          "method": "org.eclipse.jdt.internal.core.index.impl.MergeFactory.merge",
          "source": "MergeFact ory.java:79"
        },
        {
          "method": "org.eclipse.jdt.internal.core.index.impl.Index.merge",
          "source": "Index.java:236"
        },
        {
          "method": "org.eclipse.jdt.internal.core.index.impl.Index.save",
          "source": "Index.java:341"
        },
        {
          "method": "org.eclipse.jdt.internal.core.search.indexing.IndexManager.saveIndexes",
          "source": "IndexManager.java:408"
        },
        {
          "method": "org.eclipse.jdt.internal.core.search.indexing.IndexManager.notifyIdle",
          "source": "IndexManager.java:313"
        },
        {
          "method": "org.eclipse.jdt.internal.core.search.processing.JobManager.run",
          "source": "JobMan ager.java:302"
        },
        {
          "method": "java.lang.Thread.run",
          "source": "Thread.java:484"
        }
      ],
      "number": 0,
      "commentIndex": 0,
      "bugId": "15174",
      "duplicateId": "15262",
      "date": "2002-05-03T12:19:51+02:00",
      "product": "JDT",
      "component": "Core",
      "severity": "normal"
    }
  ],
  "groupId": "15262",
  "bugId": "15174",
  "duplicateId": "15262",
  "date": "2002-05-03T12:19:51+02:00",
  "product": "JDT",
  "component": "Core",
  "severity": "normal"
}