{
  "comments": [
    "I20060725-0800\n\n2 CCEs on PDE Properties pages for plugin projects:\n\n- aPluginProject \u003e Properties \u003e Plug-in Development page\n- press OK\n\njava.lang.ClassCastException: org.eclipse.jdt.internal.core.JavaProject\n        at org.eclipse.pde.internal.ui.properties.PluginDevelopmentPage.performOk(PluginDevelopmentPage.java:76)\n        at org.eclipse.jface.preference.PreferenceDialog$11.run(PreferenceDialog.java:889)\n        at org.eclipse.core.runtime.SafeRunner.run(SafeRunner.java:37)\n        at org.eclipse.core.runtime.Platform.run(Platform.java:843)\n        at org.eclipse.ui.internal.JFaceUtil$1.run(JFaceUtil.java:44)\n        at org.eclipse.jface.util.SafeRunnable.run(SafeRunnable.java:149)\n        at org.eclipse.jface.preference.PreferenceDialog.okPressed(PreferenceDialog.java:869)\n[..]\n\n- a similar CCE with Runtime Classpath page:\n!MESSAGE java.lang.ClassCastException: org.eclipse.jdt.internal.core.JavaProject\n!STACK 0\njava.lang.ClassCastException: org.eclipse.jdt.internal.core.JavaProject\n        at org.eclipse.pde.internal.ui.properties.SelfHostingPropertyPage.performOk(SelfHostingPropertyPage.java:169)\n        at org.eclipse.jface.preference.PreferenceDialog$11.run(PreferenceDialog.java:889)\n        at org.eclipse.core.runtime.SafeRunner.run(SafeRunner.java:37)\n        at org.eclipse.core.runtime.Platform.run(Platform.java:843)\n        at org.eclipse.ui.internal.JFaceUtil$1.run(JFaceUtil.java:44)\n        at org.eclipse.jface.util.SafeRunnable.run(SafeRunnable.java:149)\n        at org.eclipse.jface.preference.PreferenceDialog.okPressed(PreferenceDialog.java:869)\n[..]",
    "Created an attachment (id\u003d46837)\norg.eclipse.pde.ui.patch\n\nForgive me Markus, for I have sinned against JDT productivity ;)",
    "patch released.\n\nChris, one more ugly incident like this one and you will get the tofu turkey for thanksgiving."
  ],
  "commentCreationDates": [
    "2006-07-26T19:44:29+02:00",
    "2006-07-26T20:48:47+02:00",
    "2006-07-26T21:03:59+02:00"
  ],
  "traces": [
    {
      "exceptionType": "java.lang.ClassCastException",
      "message": "org.eclipse.jdt.internal.core.JavaProject",
      "elements": [
        {
          "method": "org.eclipse.pde.internal.ui.properties.PluginDevelopmentPage.performOk",
          "source": "PluginDevelopmentPage.java:76"
        },
        {
          "method": "org.eclipse.jface.preference.PreferenceDialog$11.run",
          "source": "PreferenceDialog.java:889"
        },
        {
          "method": "org.eclipse.core.runtime.SafeRunner.run",
          "source": "SafeRunner.java:37"
        },
        {
          "method": "org.eclipse.core.runtime.Platform.run",
          "source": "Platform.java:843"
        },
        {
          "method": "org.eclipse.ui.internal.JFaceUtil$1.run",
          "source": "JFaceUtil.java:44"
        },
        {
          "method": "org.eclipse.jface.util.SafeRunnable.run",
          "source": "SafeRunnable.java:149"
        },
        {
          "method": "org.eclipse.jface.preference.PreferenceDialog.okPressed",
          "source": "PreferenceDialog.java:869"
        }
      ],
      "number": 0,
      "commentIndex": 0,
      "bugId": "151885",
      "date": "2006-07-26T19:44:29+02:00",
      "product": "PDE",
      "component": "UI",
      "severity": "normal"
    },
    {
      "exceptionType": "java.lang.ClassCastException",
      "message": "org.eclipse.jdt.internal.core.JavaProject",
      "elements": [
        {
          "method": "org.eclipse.pde.internal.ui.properties.SelfHostingPropertyPage.performOk",
          "source": "SelfHostingPropertyPage.java:169"
        },
        {
          "method": "org.eclipse.jface.preference.PreferenceDialog$11.run",
          "source": "PreferenceDialog.java:889"
        },
        {
          "method": "org.eclipse.core.runtime.SafeRunner.run",
          "source": "SafeRunner.java:37"
        },
        {
          "method": "org.eclipse.core.runtime.Platform.run",
          "source": "Platform.java:843"
        },
        {
          "method": "org.eclipse.ui.internal.JFaceUtil$1.run",
          "source": "JFaceUtil.java:44"
        },
        {
          "method": "org.eclipse.jface.util.SafeRunnable.run",
          "source": "SafeRunnable.java:149"
        },
        {
          "method": "org.eclipse.jface.preference.PreferenceDialog.okPressed",
          "source": "PreferenceDialog.java:869"
        }
      ],
      "number": 1,
      "commentIndex": 0,
      "bugId": "151885",
      "date": "2006-07-26T19:44:29+02:00",
      "product": "PDE",
      "component": "UI",
      "severity": "normal"
    }
  ],
  "groupId": "151885",
  "bugId": "151885",
  "date": "2006-07-26T19:44:29+02:00",
  "product": "PDE",
  "component": "UI",
  "severity": "normal"
}