{
  "comments": [
    "I\u0027m using SuSE 10.1 x86_64 and eclipse-SDK-3.2-linux-gtk-x86_64.tar.gz. When I execute eclipse I get:\n\n!SESSION 2006-08-01 18:37:53.131 -----------------------------------------------\neclipse.buildId\u003dM20060629-1905\njava.version\u003d1.5.0_07\njava.vendor\u003dSun Microsystems Inc.\nBootLoader constants: OS\u003dlinux, ARCH\u003dx86_64, WS\u003dgtk, NL\u003dpt_BR\nCommand-line arguments:  -os linux -ws gtk -arch x86_64\n\n!ENTRY org.eclipse.osgi 4 0 2006-08-01 18:37:56.719\n!MESSAGE Application error\n!STACK 1\njava.lang.UnsatisfiedLinkError: /usr/local/eclipse/configuration/org.eclipse.osgi/bundles/15/1/.cp/libswt-pi-gtk-3232.so: /usr/local/eclipse/configuration/org.eclipse.osgi/bundles/15/1/.cp/libswt-pi-gtk-3232.so: wrong ELF class: ELFCLASS64\n        at java.lang.ClassLoader$NativeLibrary.load(Native Method)\n        at java.lang.ClassLoader.loadLibrary0(ClassLoader.java:1751)\n        at java.lang.ClassLoader.loadLibrary(ClassLoader.java:1660)\n        at java.lang.Runtime.loadLibrary0(Runtime.java:822)\n        at java.lang.System.loadLibrary(System.java:992)\n        at org.eclipse.swt.internal.Library.loadLibrary(Library.java:123)\n        at org.eclipse.swt.internal.gtk.OS.\u003cclinit\u003e(OS.java:22)\n        at org.eclipse.swt.internal.Converter.wcsToMbcs(Converter.java:63)\n        at org.eclipse.swt.internal.Converter.wcsToMbcs(Converter.java:54)\n        at org.eclipse.swt.widgets.Display.\u003cclinit\u003e(Display.java:126)\n        at org.eclipse.ui.internal.Workbench.createDisplay(Workbench.java:433)\n        at org.eclipse.ui.PlatformUI.createDisplay(PlatformUI.java:161)\n        at org.eclipse.ui.internal.ide.IDEApplication.createDisplay(IDEApplication.java:122)\n        at org.eclipse.ui.internal.ide.IDEApplication.run(IDEApplication.java:75)\n        at org.eclipse.core.internal.runtime.PlatformActivator$1.run(PlatformActivator.java:78)\n        at org.eclipse.core.runtime.internal.adaptor.EclipseAppLauncher.runApplication(EclipseAppLauncher.java:92)\n        at org.eclipse.core.runtime.internal.adaptor.EclipseAppLauncher.start(EclipseAppLauncher.java:68)\n        at org.eclipse.core.runtime.adaptor.EclipseStarter.run(EclipseStarter.java:400)\n        at org.eclipse.core.runtime.adaptor.EclipseStarter.run(EclipseStarter.java:177)\n        at sun.reflect.NativeMethodAccessorImpl.invoke0(Native Method)\n        at sun.reflect.NativeMethodAccessorImpl.invoke(NativeMethodAccessorImpl.java:39)\n        at sun.reflect.DelegatingMethodAccessorImpl.invoke(DelegatingMethodAccessorImpl.java:25)\n        at java.lang.reflect.Method.invoke(Method.java:585)\n        at org.eclipse.core.launcher.Main.invokeFramework(Main.java:336)\n        at org.eclipse.core.launcher.Main.basicRun(Main.java:280)\n        at org.eclipse.core.launcher.Main.run(Main.java:977)\n        at org.eclipse.core.launcher.Main.main(Main.java:952)",
    "I solved SDB:ZEN-Update System problem in SuSE Linux 10.1, did the online update, and now Eclipse is working fine.",
    "great, closing report\n",
    "*** Bug 152913 has been marked as a duplicate of this bug. ***"
  ],
  "commentCreationDates": [
    "2006-08-02T00:26:14+02:00",
    "2006-08-03T14:02:23+02:00",
    "2006-08-03T14:31:27+02:00",
    "2006-08-08T21:54:29+02:00"
  ],
  "traces": [
    {
      "exceptionType": "java.lang.UnsatisfiedLinkError",
      "message": "/usr/local/eclipse/configuration/org.eclipse.osgi/bundles/15/1/.cp/libswt-pi-gtk-3232.so: /usr/local/eclipse/configuration/org.eclipse.osgi/bundles/15/1/.cp/libswt-pi-gtk-3232.so: wrong ELF class: ELFCLASS64",
      "elements": [
        {
          "method": "java.lang.ClassLoader$NativeLibrary.load",
          "source": "Native Method"
        },
        {
          "method": "java.lang.ClassLoader.loadLibrary0",
          "source": "ClassLoader.java:1751"
        },
        {
          "method": "java.lang.ClassLoader.loadLibrary",
          "source": "ClassLoader.java:1660"
        },
        {
          "method": "java.lang.Runtime.loadLibrary0",
          "source": "Runtime.java:822"
        },
        {
          "method": "java.lang.System.loadLibrary",
          "source": "System.java:992"
        },
        {
          "method": "org.eclipse.swt.internal.Library.loadLibrary",
          "source": "Library.java:123"
        },
        {
          "method": "org.eclipse.swt.internal.gtk.OS.\u003cclinit\u003e",
          "source": "OS.java:22"
        },
        {
          "method": "org.eclipse.swt.internal.Converter.wcsToMbcs",
          "source": "Converter.java:63"
        },
        {
          "method": "org.eclipse.swt.internal.Converter.wcsToMbcs",
          "source": "Converter.java:54"
        },
        {
          "method": "org.eclipse.swt.widgets.Display.\u003cclinit\u003e",
          "source": "Display.java:126"
        },
        {
          "method": "org.eclipse.ui.internal.Workbench.createDisplay",
          "source": "Workbench.java:433"
        },
        {
          "method": "org.eclipse.ui.PlatformUI.createDisplay",
          "source": "PlatformUI.java:161"
        },
        {
          "method": "org.eclipse.ui.internal.ide.IDEApplication.createDisplay",
          "source": "IDEApplication.java:122"
        },
        {
          "method": "org.eclipse.ui.internal.ide.IDEApplication.run",
          "source": "IDEApplication.java:75"
        },
        {
          "method": "org.eclipse.core.internal.runtime.PlatformActivator$1.run",
          "source": "PlatformActivator.java:78"
        },
        {
          "method": "org.eclipse.core.runtime.internal.adaptor.EclipseAppLauncher.runApplication",
          "source": "EclipseAppLauncher.java:92"
        },
        {
          "method": "org.eclipse.core.runtime.internal.adaptor.EclipseAppLauncher.start",
          "source": "EclipseAppLauncher.java:68"
        },
        {
          "method": "org.eclipse.core.runtime.adaptor.EclipseStarter.run",
          "source": "EclipseStarter.java:400"
        },
        {
          "method": "org.eclipse.core.runtime.adaptor.EclipseStarter.run",
          "source": "EclipseStarter.java:177"
        },
        {
          "method": "sun.reflect.NativeMethodAccessorImpl.invoke0",
          "source": "Native Method"
        },
        {
          "method": "sun.reflect.NativeMethodAccessorImpl.invoke",
          "source": "NativeMethodAccessorImpl.java:39"
        },
        {
          "method": "sun.reflect.DelegatingMethodAccessorImpl.invoke",
          "source": "DelegatingMethodAccessorImpl.java:25"
        },
        {
          "method": "java.lang.reflect.Method.invoke",
          "source": "Method.java:585"
        },
        {
          "method": "org.eclipse.core.launcher.Main.invokeFramework",
          "source": "Main.java:336"
        },
        {
          "method": "org.eclipse.core.launcher.Main.basicRun",
          "source": "Main.java:280"
        },
        {
          "method": "org.eclipse.core.launcher.Main.run",
          "source": "Main.java:977"
        },
        {
          "method": "org.eclipse.core.launcher.Main.main",
          "source": "Main.java:952"
        }
      ],
      "number": 0,
      "commentIndex": 0,
      "bugId": "152527",
      "date": "2006-08-02T00:26:14+02:00",
      "product": "Platform",
      "component": "SWT",
      "severity": "normal"
    }
  ],
  "groupId": "152527",
  "bugId": "152527",
  "date": "2006-08-02T00:26:14+02:00",
  "product": "Platform",
  "component": "SWT",
  "severity": "normal"
}