{
  "comments": [
    "Build id: I20060801-0900\n\nNoticed this exception in my DOS console. Not sure how to reproduce:\n\norg.eclipse.swt.SWTException: Invalid thread access\n        at org.eclipse.swt.SWT.error(SWT.java:3374)\n        at org.eclipse.swt.SWT.error(SWT.java:3297)\n        at org.eclipse.swt.SWT.error(SWT.java:3268)\n        at org.eclipse.swt.widgets.Widget.error(Widget.java:435)\n        at org.eclipse.swt.widgets.Widget.checkWidget(Widget.java:331)\n        at org.eclipse.swt.widgets.Tree.getSelection(Tree.java:2909)\n        at org.eclipse.jface.viewers.TreeViewer.getSelection(TreeViewer.java:471\n)\n        at org.eclipse.jface.viewers.TreeViewer.setSelection(TreeViewer.java:686\n)\n        at org.eclipse.jface.viewers.AbstractTreeViewer.setSelectionToWidget(Abs\ntractTreeViewer.java:2221)\n        at org.eclipse.jface.viewers.StructuredViewer.setSelectionToWidget(Struc\nturedViewer.java:1621)\n        at org.eclipse.jface.viewers.AbstractTreeViewer.setSelectionToWidget(Abs\ntractTreeViewer.java:2596)\n        at org.eclipse.jface.viewers.StructuredViewer.preservingSelection(Struct\nuredViewer.java:1330)\n        at org.eclipse.jface.viewers.StructuredViewer.refresh(StructuredViewer.j\nava:1386)\n        at org.eclipse.jface.viewers.StructuredViewer.refresh(StructuredViewer.j\nava:1345)\n        at org.eclipse.pde.internal.ui.editor.FormOutlinePage.refresh(FormOutlin\nePage.java:152)\n        at org.eclipse.pde.internal.ui.editor.FormOutlinePage.modelChanged(FormO\nutlinePage.java:147)\n        at org.eclipse.pde.internal.core.AbstractModel.fireModelChanged(Abstract\nModel.java:89)\n        at org.eclipse.pde.internal.core.bundle.BundlePluginModelBase.fireModelC\nhanged(BundlePluginModelBase.java:151)\n        at org.eclipse.pde.internal.core.bundle.BundlePluginBase.modelChanged(Bu\nndlePluginBase.java:82)\n        at org.eclipse.pde.internal.core.text.AbstractEditingModel.fireModelChan\nged(AbstractEditingModel.java:211)\n        at org.eclipse.pde.internal.core.text.AbstractEditingModel.reload(Abstra\nctEditingModel.java:130)\n        at org.eclipse.pde.internal.core.text.AbstractEditingModel.reconciled(Ab\nstractEditingModel.java:157)\n        at org.eclipse.pde.internal.ui.editor.text.ReconcilingStrategy.notifyPar\nticipants(ReconcilingStrategy.java:51)\n        at org.eclipse.pde.internal.ui.editor.text.ReconcilingStrategy.reconcile\n(ReconcilingStrategy.java:46)\n        at org.eclipse.jface.text.reconciler.MonoReconciler.process(MonoReconcil\ner.java:75)\n        at org.eclipse.jface.text.reconciler.AbstractReconciler$BackgroundThread\n.run(AbstractReconciler.java:204)",
    "attempt to modify the UI via a non-UI thread.  Fixed."
  ],
  "commentCreationDates": [
    "2006-08-01T23:19:23+02:00",
    "2006-08-05T08:16:34+02:00"
  ],
  "traces": [
    {
      "exceptionType": "org.eclipse.swt.SWTException",
      "message": "Invalid thread access",
      "elements": [
        {
          "method": "org.eclipse.swt.SWT.error",
          "source": "SWT.java:3374"
        },
        {
          "method": "org.eclipse.swt.SWT.error",
          "source": "SWT.java:3297"
        },
        {
          "method": "org.eclipse.swt.SWT.error",
          "source": "SWT.java:3268"
        },
        {
          "method": "org.eclipse.swt.widgets.Widget.error",
          "source": "Widget.java:435"
        },
        {
          "method": "org.eclipse.swt.widgets.Widget.checkWidget",
          "source": "Widget.java:331"
        },
        {
          "method": "org.eclipse.swt.widgets.Tree.getSelection",
          "source": "Tree.java:2909"
        },
        {
          "method": "org.eclipse.jface.viewers.TreeViewer.getSelection",
          "source": "TreeViewer.java:471 "
        },
        {
          "method": "org.eclipse.jface.viewers.TreeViewer.setSelection",
          "source": "TreeViewer.java:686 "
        },
        {
          "method": "org.eclipse.jface.viewers.AbstractTreeViewer.setSelectionToWidget",
          "source": "Abs tractTreeViewer.java:2221"
        },
        {
          "method": "org.eclipse.jface.viewers.StructuredViewer.setSelectionToWidget",
          "source": "Struc turedViewer.java:1621"
        },
        {
          "method": "org.eclipse.jface.viewers.AbstractTreeViewer.setSelectionToWidget",
          "source": "Abs tractTreeViewer.java:2596"
        },
        {
          "method": "org.eclipse.jface.viewers.StructuredViewer.preservingSelection",
          "source": "Struct uredViewer.java:1330"
        },
        {
          "method": "org.eclipse.jface.viewers.StructuredViewer.refresh",
          "source": "StructuredViewer.j ava:1386"
        },
        {
          "method": "org.eclipse.jface.viewers.StructuredViewer.refresh",
          "source": "StructuredViewer.j ava:1345"
        },
        {
          "method": "org.eclipse.pde.internal.ui.editor.FormOutlinePage.refresh",
          "source": "FormOutlin ePage.java:152"
        },
        {
          "method": "org.eclipse.pde.internal.ui.editor.FormOutlinePage.modelChanged",
          "source": "FormO utlinePage.java:147"
        },
        {
          "method": "org.eclipse.pde.internal.core.AbstractModel.fireModelChanged",
          "source": "Abstract Model.java:89"
        },
        {
          "method": "org.eclipse.pde.internal.core.bundle.BundlePluginModelBase.fireModelChanged",
          "source": "BundlePluginModelBase.java:151"
        },
        {
          "method": "org.eclipse.pde.internal.core.bundle.BundlePluginBase.modelChanged",
          "source": "Bu ndlePluginBase.java:82"
        },
        {
          "method": "org.eclipse.pde.internal.core.text.AbstractEditingModel.fireModelChanged",
          "source": "AbstractEditingModel.java:211"
        },
        {
          "method": "org.eclipse.pde.internal.core.text.AbstractEditingModel.reload",
          "source": "Abstra ctEditingModel.java:130"
        },
        {
          "method": "org.eclipse.pde.internal.core.text.AbstractEditingModel.reconciled",
          "source": "Ab stractEditingModel.java:157"
        },
        {
          "method": "org.eclipse.pde.internal.ui.editor.text.ReconcilingStrategy.notifyParticipants",
          "source": "ReconcilingStrategy.java:51"
        },
        {
          "method": "org.eclipse.pde.internal.ui.editor.text.ReconcilingStrategy.reconcile",
          "source": "ReconcilingStrategy.java:46"
        },
        {
          "method": "org.eclipse.jface.text.reconciler.MonoReconciler.process",
          "source": "MonoReconcil er.java:75"
        },
        {
          "method": "org.eclipse.jface.text.reconciler.AbstractReconciler$BackgroundThread.run",
          "source": "AbstractReconciler.java:204"
        }
      ],
      "number": 0,
      "commentIndex": 0,
      "bugId": "152518",
      "date": "2006-08-01T23:19:23+02:00",
      "product": "PDE",
      "component": "UI",
      "severity": "normal"
    }
  ],
  "groupId": "152518",
  "bugId": "152518",
  "date": "2006-08-01T23:19:23+02:00",
  "product": "PDE",
  "component": "UI",
  "severity": "normal"
}