{
  "comments": [
    "I\u0027m running Suse 10.1 x86_64.\n\nJust downloaded GTK x86_64 eclipse, version 3.2.  I unzipped it and tried to run it, with this exception in .metadata/.log:\n\n!SESSION 2006-08-05 22:41:31.405 -----------------------------------------------\neclipse.buildId\u003dM20060629-1905\njava.version\u003d1.4.2_11\njava.vendor\u003dSun Microsystems Inc.\nBootLoader constants: OS\u003dlinux, ARCH\u003dx86_64, WS\u003dgtk, NL\u003den_US\nCommand-line arguments:  -os linux -ws gtk -arch x86_64\n\n!ENTRY org.eclipse.osgi 4 0 2006-08-05 22:41:34.249\n!MESSAGE Application error\n!STACK 1\njava.lang.UnsatisfiedLinkError: /home/scott/eclipse/configuration/org.eclipse.osgi/bundles/15/1/.cp/libswt-pi-gtk-3232.so: /home/scott/eclips\ne/configuration/org.eclipse.osgi/bundles/15/1/.cp/libswt-pi-gtk-3232.so: wrong ELF class: ELFCLASS64\n        at java.lang.ClassLoader$NativeLibrary.load(Native Method)\n        at java.lang.ClassLoader.loadLibrary0(ClassLoader.java:1586)\n        at java.lang.ClassLoader.loadLibrary(ClassLoader.java:1495)\n        at java.lang.Runtime.loadLibrary0(Runtime.java:788)\n        at java.lang.System.loadLibrary(System.java:834)\n        at org.eclipse.swt.internal.Library.loadLibrary(Library.java:123)\n        at org.eclipse.swt.internal.gtk.OS.\u003cclinit\u003e(OS.java:22)\n        at org.eclipse.swt.internal.Converter.wcsToMbcs(Converter.java:63)\n        at org.eclipse.swt.internal.Converter.wcsToMbcs(Converter.java:54)\n        at org.eclipse.swt.widgets.Display.\u003cclinit\u003e(Display.java:126)\n        at org.eclipse.ui.internal.Workbench.createDisplay(Workbench.java:433)\n        at org.eclipse.ui.PlatformUI.createDisplay(PlatformUI.java:161)\n        at org.eclipse.ui.internal.ide.IDEApplication.createDisplay(IDEApplication.java:122)\n        at org.eclipse.ui.internal.ide.IDEApplication.run(IDEApplication.java:75)\n        at org.eclipse.core.internal.runtime.PlatformActivator$1.run(PlatformActivator.java:78)\n        at org.eclipse.core.runtime.internal.adaptor.EclipseAppLauncher.runApplication(EclipseAppLauncher.java:92)\n        at org.eclipse.core.runtime.internal.adaptor.EclipseAppLauncher.start(EclipseAppLauncher.java:68)\n        at org.eclipse.core.runtime.adaptor.EclipseStarter.run(EclipseStarter.java:400)\n        at org.eclipse.core.runtime.adaptor.EclipseStarter.run(EclipseStarter.java:177)\n        at sun.reflect.NativeMethodAccessorImpl.invoke0(Native Method)\n        at sun.reflect.NativeMethodAccessorImpl.invoke(NativeMethodAccessorImpl.java:39)\n        at sun.reflect.DelegatingMethodAccessorImpl.invoke(DelegatingMethodAccessorImpl.java:25)\n        at java.lang.reflect.Method.invoke(Method.java:324)\n        at org.eclipse.core.launcher.Main.invokeFramework(Main.java:336)\n        at org.eclipse.core.launcher.Main.basicRun(Main.java:280)\n        at org.eclipse.core.launcher.Main.run(Main.java:977)\n        at org.eclipse.core.launcher.Main.main(Main.java:952)\n\n!ENTRY org.eclipse.osgi 2 0 2006-08-05 22:41:34.276\n!MESSAGE The following is a complete list of bundles which are not resolved, see the prior log entry for the root cause if it exists:\n!SUBENTRY 1 org.eclipse.osgi 2 0 2006-08-05 22:41:34.276\n!MESSAGE Bundle update@plugins/org.eclipse.jdt.apt.core_3.2.0.v20060602-1740.jar [47] was not resolved.\n!SUBENTRY 2 org.eclipse.jdt.apt.core 2 0 2006-08-05 22:41:34.276\n!MESSAGE Missing Constraint: Bundle-RequiredExecutionEnvironment: J2SE-1.5\n!SUBENTRY 1 org.eclipse.osgi 2 0 2006-08-05 22:41:34.276\n!MESSAGE Bundle update@plugins/org.eclipse.jdt.junit4.runtime_1.0.0.v20060605-1400.jar [52] was not resolved.\n!SUBENTRY 2 org.eclipse.jdt.junit4.runtime 2 0 2006-08-05 22:41:34.276\n!MESSAGE Missing required bundle org.junit4_[4.1.0,4.2.0).\n!SUBENTRY 1 org.eclipse.osgi 2 0 2006-08-05 22:41:34.276\n!MESSAGE Bundle update@plugins/org.eclipse.jdt.apt.ui_3.2.0.v20060602-1740.jar [92] was not resolved.\n!SUBENTRY 2 org.eclipse.jdt.apt.ui 2 0 2006-08-05 22:41:34.277\n!MESSAGE Missing required bundle org.eclipse.jdt.apt.core_[3.2.0,4.0.0).\n!SUBENTRY 1 org.eclipse.osgi 2 0 2006-08-05 22:41:34.277\n!MESSAGE Bundle update@plugins/org.junit4_4.1.0/ [103] was not resolved.\n!SUBENTRY 2 org.junit4 2 0 2006-08-05 22:41:34.277\n!MESSAGE Missing Constraint: Bundle-RequiredExecutionEnvironment: J2SE-1.5",
    "This is apparently an issue in Suse 10.1 x86_64, see bug 152527.\n\n\n*** This bug has been marked as a duplicate of 152527 ***"
  ],
  "commentCreationDates": [
    "2006-08-06T06:44:47+02:00",
    "2006-08-08T21:54:29+02:00"
  ],
  "traces": [
    {
      "exceptionType": "java.lang.UnsatisfiedLinkError",
      "message": "/home/scott/eclipse/configuration/org.eclipse.osgi/bundles/15/1/.cp/libswt-pi-gtk-3232.so: /home/scott/eclips e/configuration/org.eclipse.osgi/bundles/15/1/.cp/libswt-pi-gtk-3232.so: wrong ELF class: ELFCLASS64",
      "elements": [
        {
          "method": "java.lang.ClassLoader$NativeLibrary.load",
          "source": "Native Method"
        },
        {
          "method": "java.lang.ClassLoader.loadLibrary0",
          "source": "ClassLoader.java:1586"
        },
        {
          "method": "java.lang.ClassLoader.loadLibrary",
          "source": "ClassLoader.java:1495"
        },
        {
          "method": "java.lang.Runtime.loadLibrary0",
          "source": "Runtime.java:788"
        },
        {
          "method": "java.lang.System.loadLibrary",
          "source": "System.java:834"
        },
        {
          "method": "org.eclipse.swt.internal.Library.loadLibrary",
          "source": "Library.java:123"
        },
        {
          "method": "org.eclipse.swt.internal.gtk.OS.\u003cclinit\u003e",
          "source": "OS.java:22"
        },
        {
          "method": "org.eclipse.swt.internal.Converter.wcsToMbcs",
          "source": "Converter.java:63"
        },
        {
          "method": "org.eclipse.swt.internal.Converter.wcsToMbcs",
          "source": "Converter.java:54"
        },
        {
          "method": "org.eclipse.swt.widgets.Display.\u003cclinit\u003e",
          "source": "Display.java:126"
        },
        {
          "method": "org.eclipse.ui.internal.Workbench.createDisplay",
          "source": "Workbench.java:433"
        },
        {
          "method": "org.eclipse.ui.PlatformUI.createDisplay",
          "source": "PlatformUI.java:161"
        },
        {
          "method": "org.eclipse.ui.internal.ide.IDEApplication.createDisplay",
          "source": "IDEApplication.java:122"
        },
        {
          "method": "org.eclipse.ui.internal.ide.IDEApplication.run",
          "source": "IDEApplication.java:75"
        },
        {
          "method": "org.eclipse.core.internal.runtime.PlatformActivator$1.run",
          "source": "PlatformActivator.java:78"
        },
        {
          "method": "org.eclipse.core.runtime.internal.adaptor.EclipseAppLauncher.runApplication",
          "source": "EclipseAppLauncher.java:92"
        },
        {
          "method": "org.eclipse.core.runtime.internal.adaptor.EclipseAppLauncher.start",
          "source": "EclipseAppLauncher.java:68"
        },
        {
          "method": "org.eclipse.core.runtime.adaptor.EclipseStarter.run",
          "source": "EclipseStarter.java:400"
        },
        {
          "method": "org.eclipse.core.runtime.adaptor.EclipseStarter.run",
          "source": "EclipseStarter.java:177"
        },
        {
          "method": "sun.reflect.NativeMethodAccessorImpl.invoke0",
          "source": "Native Method"
        },
        {
          "method": "sun.reflect.NativeMethodAccessorImpl.invoke",
          "source": "NativeMethodAccessorImpl.java:39"
        },
        {
          "method": "sun.reflect.DelegatingMethodAccessorImpl.invoke",
          "source": "DelegatingMethodAccessorImpl.java:25"
        },
        {
          "method": "java.lang.reflect.Method.invoke",
          "source": "Method.java:324"
        },
        {
          "method": "org.eclipse.core.launcher.Main.invokeFramework",
          "source": "Main.java:336"
        },
        {
          "method": "org.eclipse.core.launcher.Main.basicRun",
          "source": "Main.java:280"
        },
        {
          "method": "org.eclipse.core.launcher.Main.run",
          "source": "Main.java:977"
        },
        {
          "method": "org.eclipse.core.launcher.Main.main",
          "source": "Main.java:952"
        }
      ],
      "number": 0,
      "commentIndex": 0,
      "bugId": "152913",
      "duplicateId": "152527",
      "date": "2006-08-06T06:44:47+02:00",
      "product": "Platform",
      "component": "SWT",
      "severity": "blocker"
    }
  ],
  "groupId": "152527",
  "bugId": "152913",
  "duplicateId": "152527",
  "date": "2006-08-06T06:44:47+02:00",
  "product": "Platform",
  "component": "SWT",
  "severity": "blocker"
}