{
  "comments": [
    "I think this is problem with the build mechanism in Eclipse.\nRAD/RWD/WSAD product should show similar behaviour :\n\nWhen building, if a needed JAR file is corrupt, you get an error of the form:\n\n\"Internal Error\", with an entry in the \".log\" file like:\njava.lang.InternalError: jzentry \u003d\u003d 0 \n        at java.lang.Throwable.\u003cinit\u003e(Throwable.java) \n        at java.lang.Throwable.\u003cinit\u003e(Throwable.java) \n        at java.util.zip.ZipFile$2.nextElement(ZipFile.java) \n        at org.eclipse.jdt.internal.core.builder.ClasspathJar.findPackageSet(ClasspathJar.java) \n        at org.eclipse.jdt.internal.core.builder.ClasspathJar.isPackage(ClasspathJar.java:148) \n        at org.eclipse.jdt.internal.core.builder.ClasspathJar.findClass(ClasspathJar.java:124) \n\nWouldn\u0027t it be better to actually get the name of the JAR file the build is having a problem with ?\nRunning RAD (or eclipse) with \"-debug\" will get you the information in the \".log\" file, but one must KNOW to use it:\n\nUnhandled exception caught in event loop.\nReason:\njzentry \u003d\u003d 0,\n jzfile \u003d 73862504,\n total \u003d 10,\n name \u003d C:\\appl\\as\\tis\\dslreg\\lib\\CommonHelper.jar,\n i \u003d 2,\n message \u003d invalid LOC header (bad signature)"
  ],
  "commentCreationDates": [
    "2006-08-08T21:32:24+02:00"
  ],
  "traces": [
    {
      "exceptionType": "java.lang.InternalError",
      "message": "jzentry \u003d\u003d 0",
      "elements": [
        {
          "method": "java.lang.Throwable.\u003cinit\u003e",
          "source": "Throwable.java"
        },
        {
          "method": "java.lang.Throwable.\u003cinit\u003e",
          "source": "Throwable.java"
        },
        {
          "method": "java.util.zip.ZipFile$2.nextElement",
          "source": "ZipFile.java"
        },
        {
          "method": "org.eclipse.jdt.internal.core.builder.ClasspathJar.findPackageSet",
          "source": "ClasspathJar.java"
        },
        {
          "method": "org.eclipse.jdt.internal.core.builder.ClasspathJar.isPackage",
          "source": "ClasspathJar.java:148"
        },
        {
          "method": "org.eclipse.jdt.internal.core.builder.ClasspathJar.findClass",
          "source": "ClasspathJar.java:124"
        }
      ],
      "number": 0,
      "commentIndex": 0,
      "bugId": "153168",
      "date": "2006-08-08T21:32:24+02:00",
      "product": "JDT",
      "component": "Core",
      "severity": "normal"
    }
  ],
  "groupId": "153168",
  "bugId": "153168",
  "date": "2006-08-08T21:32:24+02:00",
  "product": "JDT",
  "component": "Core",
  "severity": "normal"
}