{
  "comments": [
    "Running SWT Snippet 133 (print text to printer) throws this exception:\n\nException in thread \"Printing\" org.eclipse.swt.SWTException: Invalid thread access\n        at org.eclipse.swt.SWT.error(SWT.java:3374)\n        at org.eclipse.swt.SWT.error(SWT.java:3297)\n        at org.eclipse.swt.SWT.error(SWT.java:3268)\n        at org.eclipse.swt.widgets.Widget.error(Widget.java:435)\n        at org.eclipse.swt.widgets.Widget.checkWidget(Widget.java:331)\n        at org.eclipse.swt.widgets.Control.getFont(Control.java:939)\n        at org.eclipse.swt.snippets.Snippet133.print(Snippet133.java:230)\n        at org.eclipse.swt.snippets.Snippet133$7.run(Snippet133.java:204)\n\nIt works if you patch the line:\nprintingThread.start();\nwith this:\ndisplay.syncExec(printingThread);",
    "FH to investigate.  Note that I did not see this error when I tried running the snippet on my win2000.\n",
    "thanks, fixed in head \u003e 20060814\n\ndisplay.syncExec(printingThread); will cause the printer job to run in the UI thread, which can cause the UI to freeze.\nthe fix is to cache all data before starting the print job.\n"
  ],
  "commentCreationDates": [
    "2006-08-10T09:26:55+02:00",
    "2006-08-14T17:03:52+02:00",
    "2006-08-14T17:41:09+02:00"
  ],
  "traces": [
    {
      "exceptionType": "org.eclipse.swt.SWTException",
      "message": "Invalid thread access",
      "elements": [
        {
          "method": "org.eclipse.swt.SWT.error",
          "source": "SWT.java:3374"
        },
        {
          "method": "org.eclipse.swt.SWT.error",
          "source": "SWT.java:3297"
        },
        {
          "method": "org.eclipse.swt.SWT.error",
          "source": "SWT.java:3268"
        },
        {
          "method": "org.eclipse.swt.widgets.Widget.error",
          "source": "Widget.java:435"
        },
        {
          "method": "org.eclipse.swt.widgets.Widget.checkWidget",
          "source": "Widget.java:331"
        },
        {
          "method": "org.eclipse.swt.widgets.Control.getFont",
          "source": "Control.java:939"
        },
        {
          "method": "org.eclipse.swt.snippets.Snippet133.print",
          "source": "Snippet133.java:230"
        },
        {
          "method": "org.eclipse.swt.snippets.Snippet133$7.run",
          "source": "Snippet133.java:204"
        }
      ],
      "number": 0,
      "commentIndex": 0,
      "bugId": "153398",
      "date": "2006-08-10T09:26:55+02:00",
      "product": "Platform",
      "component": "SWT",
      "severity": "normal"
    }
  ],
  "groupId": "153398",
  "bugId": "153398",
  "date": "2006-08-10T09:26:55+02:00",
  "product": "Platform",
  "component": "SWT",
  "severity": "normal"
}