{
  "comments": [
    "Double clicked on a file to open it and got (after a while):\n\n!ENTRY org.eclipse.ui 4 4 2006-08-10 16:02:15.467\n!MESSAGE Internal plug-in action delegate error on creation.\n!STACK 0\njava.lang.OutOfMemoryError: PermGen space\n        at org.eclipse.search.internal.ui.OpenSearchDialogAction.\u003cinit\u003e(OpenSearchDialogAction.java:30)\n        at sun.reflect.NativeConstructorAccessorImpl.newInstance0(Native Method)\n        at sun.reflect.NativeConstructorAccessorImpl.newInstance(NativeConstructorAccessorImpl.java:39)\n        at sun.reflect.DelegatingConstructorAccessorImpl.newInstance(DelegatingConstructorAccessorImpl.java:27)\n        at java.lang.reflect.Constructor.newInstance(Constructor.java:506)\n        at java.lang.Class.newInstance0(Class.java:355)\n        at java.lang.Class.newInstance(Class.java:308)\n        at org.eclipse.core.internal.registry.osgi.RegistryStrategyOSGI.createExecutableExtension(RegistryStrategyOSGI.java:157)\n        at org.eclipse.core.internal.registry.ExtensionRegistry.createExecutableExtension(ExtensionRegistry.java:759)\n        at org.eclipse.core.internal.registry.ConfigurationElement.createExecutableExtension(ConfigurationElement.java:243)\n        at org.eclipse.core.internal.registry.ConfigurationElementHandle.createExecutableExtension(ConfigurationElementHandle.java:51)\n        at org.eclipse.ui.internal.WorkbenchPlugin.createExtension(WorkbenchPlugin.java:234)\n        at org.eclipse.ui.internal.PluginAction.createDelegate(PluginAction.java:120)\n        at org.eclipse.ui.internal.PluginAction.selectionChanged(PluginAction.java:278)\n        at org.eclipse.ui.internal.PluginAction.selectionChanged(PluginAction.java:302)\n        at org.eclipse.ui.internal.AbstractSelectionService.fireSelection(AbstractSelectionService.java:156)\n        at org.eclipse.ui.internal.AbstractSelectionService.setActivePart(AbstractSelectionService.java:282)\n        at org.eclipse.ui.internal.WWinPartService.updateActivePart(WWinPartService.java:125)\n        at org.eclipse.ui.internal.WWinPartService.access$0(WWinPartService.java:115)\n        at org.eclipse.ui.internal.WWinPartService$1.partDeactivated(WWinPartService.java:48)\n        at org.eclipse.ui.internal.PartListenerList2$4.run(PartListenerList2.java:113)\n        at org.eclipse.core.runtime.SafeRunner.run(SafeRunner.java:37)\n        at org.eclipse.core.runtime.Platform.run(Platform.java:843)\n        at org.eclipse.ui.internal.PartListenerList2.fireEvent(PartListenerList2.java:53)\n        at org.eclipse.ui.internal.PartListenerList2.firePartDeactivated(PartListenerList2.java:111)\n        at org.eclipse.ui.internal.PartService.firePartDeactivated(PartService.java:116)\n        at org.eclipse.ui.internal.PartService.setActivePart(PartService.java:165)\n        at org.eclipse.ui.internal.WorkbenchPagePartList.fireActivePartChanged(WorkbenchPagePartList.java:56)\n        at org.eclipse.ui.internal.PartList.setActivePart(PartList.java:126)\n        at org.eclipse.ui.internal.WorkbenchPage.setActivePart(WorkbenchPage.java:3190)\n        at org.eclipse.ui.internal.WorkbenchPage.activate(WorkbenchPage.java:588)\n        at org.eclipse.ui.internal.WorkbenchPage.busyOpenEditorBatched(WorkbenchPage.java:2597)\n\n!ENTRY org.eclipse.ui 4 4 2006-08-10 16:02:22.743\n!MESSAGE Could not create action delegate for id: org.eclipse.search.TextSearchWorkingSet\n\n!ENTRY org.eclipse.ui 4 4 2006-08-10 16:02:22.743\n!MESSAGE Internal plug-in action delegate error on creation.\n\n!ENTRY org.eclipse.ui 4 4 2006-08-10 16:02:24.579\n!MESSAGE Unhandled event loop exception\n\n!ENTRY org.eclipse.ui 4 0 2006-08-10 16:02:24.581\n!MESSAGE PermGen space\n\n!ENTRY system.bundle 4 0 2006-08-10 16:02:39.152\n!MESSAGE FrameworkEvent.ERROR\n!STACK 0\njava.lang.OutOfMemoryError: PermGen space\n!SESSION Thu Aug 10 16:02:47 PDT 2006 ------------------------------------------\n!ENTRY org.eclipse.core.launcher 4 0 2006-08-10 16:02:47.958\n!MESSAGE Exception launching the Eclipse Platform:\n!STACK\njava.lang.OutOfMemoryError: PermGen space",
    "\n\n*** This bug has been marked as a duplicate of 153485 ***"
  ],
  "commentCreationDates": [
    "2006-08-11T01:04:15+02:00",
    "2006-08-14T14:03:53+02:00"
  ],
  "traces": [
    {
      "exceptionType": "java.lang.OutOfMemoryError",
      "message": "PermGen space",
      "elements": [
        {
          "method": "org.eclipse.search.internal.ui.OpenSearchDialogAction.\u003cinit\u003e",
          "source": "OpenSearchDialogAction.java:30"
        },
        {
          "method": "sun.reflect.NativeConstructorAccessorImpl.newInstance0",
          "source": "Native Method"
        },
        {
          "method": "sun.reflect.NativeConstructorAccessorImpl.newInstance",
          "source": "NativeConstructorAccessorImpl.java:39"
        },
        {
          "method": "sun.reflect.DelegatingConstructorAccessorImpl.newInstance",
          "source": "DelegatingConstructorAccessorImpl.java:27"
        },
        {
          "method": "java.lang.reflect.Constructor.newInstance",
          "source": "Constructor.java:506"
        },
        {
          "method": "java.lang.Class.newInstance0",
          "source": "Class.java:355"
        },
        {
          "method": "java.lang.Class.newInstance",
          "source": "Class.java:308"
        },
        {
          "method": "org.eclipse.core.internal.registry.osgi.RegistryStrategyOSGI.createExecutableExtension",
          "source": "RegistryStrategyOSGI.java:157"
        },
        {
          "method": "org.eclipse.core.internal.registry.ExtensionRegistry.createExecutableExtension",
          "source": "ExtensionRegistry.java:759"
        },
        {
          "method": "org.eclipse.core.internal.registry.ConfigurationElement.createExecutableExtension",
          "source": "ConfigurationElement.java:243"
        },
        {
          "method": "org.eclipse.core.internal.registry.ConfigurationElementHandle.createExecutableExtension",
          "source": "ConfigurationElementHandle.java:51"
        },
        {
          "method": "org.eclipse.ui.internal.WorkbenchPlugin.createExtension",
          "source": "WorkbenchPlugin.java:234"
        },
        {
          "method": "org.eclipse.ui.internal.PluginAction.createDelegate",
          "source": "PluginAction.java:120"
        },
        {
          "method": "org.eclipse.ui.internal.PluginAction.selectionChanged",
          "source": "PluginAction.java:278"
        },
        {
          "method": "org.eclipse.ui.internal.PluginAction.selectionChanged",
          "source": "PluginAction.java:302"
        },
        {
          "method": "org.eclipse.ui.internal.AbstractSelectionService.fireSelection",
          "source": "AbstractSelectionService.java:156"
        },
        {
          "method": "org.eclipse.ui.internal.AbstractSelectionService.setActivePart",
          "source": "AbstractSelectionService.java:282"
        },
        {
          "method": "org.eclipse.ui.internal.WWinPartService.updateActivePart",
          "source": "WWinPartService.java:125"
        },
        {
          "method": "org.eclipse.ui.internal.WWinPartService.access$0",
          "source": "WWinPartService.java:115"
        },
        {
          "method": "org.eclipse.ui.internal.WWinPartService$1.partDeactivated",
          "source": "WWinPartService.java:48"
        },
        {
          "method": "org.eclipse.ui.internal.PartListenerList2$4.run",
          "source": "PartListenerList2.java:113"
        },
        {
          "method": "org.eclipse.core.runtime.SafeRunner.run",
          "source": "SafeRunner.java:37"
        },
        {
          "method": "org.eclipse.core.runtime.Platform.run",
          "source": "Platform.java:843"
        },
        {
          "method": "org.eclipse.ui.internal.PartListenerList2.fireEvent",
          "source": "PartListenerList2.java:53"
        },
        {
          "method": "org.eclipse.ui.internal.PartListenerList2.firePartDeactivated",
          "source": "PartListenerList2.java:111"
        },
        {
          "method": "org.eclipse.ui.internal.PartService.firePartDeactivated",
          "source": "PartService.java:116"
        },
        {
          "method": "org.eclipse.ui.internal.PartService.setActivePart",
          "source": "PartService.java:165"
        },
        {
          "method": "org.eclipse.ui.internal.WorkbenchPagePartList.fireActivePartChanged",
          "source": "WorkbenchPagePartList.java:56"
        },
        {
          "method": "org.eclipse.ui.internal.PartList.setActivePart",
          "source": "PartList.java:126"
        },
        {
          "method": "org.eclipse.ui.internal.WorkbenchPage.setActivePart",
          "source": "WorkbenchPage.java:3190"
        },
        {
          "method": "org.eclipse.ui.internal.WorkbenchPage.activate",
          "source": "WorkbenchPage.java:588"
        },
        {
          "method": "org.eclipse.ui.internal.WorkbenchPage.busyOpenEditorBatched",
          "source": "WorkbenchPage.java:2597"
        }
      ],
      "number": 0,
      "commentIndex": 0,
      "bugId": "153505",
      "duplicateId": "153485",
      "date": "2006-08-11T01:04:15+02:00",
      "product": "Platform",
      "component": "UI",
      "severity": "major"
    }
  ],
  "groupId": "153485",
  "bugId": "153505",
  "duplicateId": "153485",
  "date": "2006-08-11T01:04:15+02:00",
  "product": "Platform",
  "component": "UI",
  "severity": "major"
}