{
  "comments": [
    "Build 20020502.05\n\nFound the following exception in the console:\n\njava.lang.ArrayIndexOutOfBoundsException\n        at org.eclipse.jdt.internal.core.index.impl.CodeByteStream.readUnary(Cod\neByteStream.java:168)\n        at org.eclipse.jdt.internal.core.index.impl.CodeByteStream.readGamma(Cod\neByteStream.java:107)\n        at org.eclipse.jdt.internal.core.index.impl.GammaCompressedIndexBlock.ne\nxtEntry(GammaCompressedIndexBlock.java:90)\n        at org.eclipse.jdt.internal.core.index.impl.BlocksIndexInput.moveToNextW\nordEntry(BlocksIndexInput.java:176)\n        at org.eclipse.jdt.internal.core.index.impl.MergeFactory.mergeReferences\n(MergeFactory.java:170)\n        at org.eclipse.jdt.internal.core.index.impl.MergeFactory.merge(MergeFact\nory.java:79)\n        at org.eclipse.jdt.internal.core.index.impl.Index.merge(Index.java:236)\n        at org.eclipse.jdt.internal.core.index.impl.Index.save(Index.java:341)\n        at org.eclipse.jdt.internal.core.search.indexing.IndexManager.saveIndexe\ns(IndexManager.java:408)\n        at org.eclipse.jdt.internal.core.search.indexing.IndexManager.notifyIdle\n(IndexManager.java:313)\n        at org.eclipse.jdt.internal.core.search.processing.JobManager.run(JobMan\nager.java:302)\n        at java.lang.Thread.run(Thread.java:484)\njava.lang.ArrayIndexOutOfBoundsException\n        at org.eclipse.jdt.internal.core.index.impl.WordEntry.mapRefs(WordEntry.\njava:128)\n        at org.eclipse.jdt.internal.core.index.impl.MergeFactory.mergeReferences\n(MergeFactory.java:168)\n        at org.eclipse.jdt.internal.core.index.impl.MergeFactory.merge(MergeFact\nory.java:79)\n        at org.eclipse.jdt.internal.core.index.impl.Index.merge(Index.java:236)\n        at org.eclipse.jdt.internal.core.index.impl.Index.save(Index.java:341)\n        at org.eclipse.jdt.internal.core.search.indexing.IndexManager.saveIndexe\ns(IndexManager.java:408)\n        at org.eclipse.jdt.internal.core.search.indexing.IndexManager.notifyIdle\n(IndexManager.java:313)\n        at org.eclipse.jdt.internal.core.search.processing.JobManager.run(JobMan\nager.java:302)\n        at java.lang.Thread.run(Thread.java:484)\n\n\nI am not running on IBM JDK \u003cg\u003e.",
    "\n\n*** This bug has been marked as a duplicate of 15262 ***"
  ],
  "commentCreationDates": [
    "2002-05-07T16:47:32+02:00",
    "2002-05-08T20:10:01+02:00"
  ],
  "traces": [
    {
      "exceptionType": "java.lang.ArrayIndexOutOfBoundsException",
      "elements": [
        {
          "method": "org.eclipse.jdt.internal.core.index.impl.CodeByteStream.readUnary",
          "source": "Cod eByteStream.java:168"
        },
        {
          "method": "org.eclipse.jdt.internal.core.index.impl.CodeByteStream.readGamma",
          "source": "Cod eByteStream.java:107"
        },
        {
          "method": "org.eclipse.jdt.internal.core.index.impl.GammaCompressedIndexBlock.nextEntry",
          "source": "GammaCompressedIndexBlock.java:90"
        },
        {
          "method": "org.eclipse.jdt.internal.core.index.impl.BlocksIndexInput.moveToNextWordEntry",
          "source": "BlocksIndexInput.java:176"
        },
        {
          "method": "org.eclipse.jdt.internal.core.index.impl.MergeFactory.mergeReferences",
          "source": "MergeFactory.java:170"
        },
        {
          "method": "org.eclipse.jdt.internal.core.index.impl.MergeFactory.merge",
          "source": "MergeFact ory.java:79"
        },
        {
          "method": "org.eclipse.jdt.internal.core.index.impl.Index.merge",
          "source": "Index.java:236"
        },
        {
          "method": "org.eclipse.jdt.internal.core.index.impl.Index.save",
          "source": "Index.java:341"
        },
        {
          "method": "org.eclipse.jdt.internal.core.search.indexing.IndexManager.saveIndexes",
          "source": "IndexManager.java:408"
        },
        {
          "method": "org.eclipse.jdt.internal.core.search.indexing.IndexManager.notifyIdle",
          "source": "IndexManager.java:313"
        },
        {
          "method": "org.eclipse.jdt.internal.core.search.processing.JobManager.run",
          "source": "JobMan ager.java:302"
        },
        {
          "method": "java.lang.Thread.run",
          "source": "Thread.java:484"
        }
      ],
      "number": 0,
      "commentIndex": 0,
      "bugId": "15426",
      "duplicateId": "15262",
      "date": "2002-05-07T16:47:32+02:00",
      "product": "JDT",
      "component": "Core",
      "severity": "normal"
    },
    {
      "exceptionType": "java.lang.ArrayIndexOutOfBoundsException",
      "elements": [
        {
          "method": "org.eclipse.jdt.internal.core.index.impl.WordEntry.mapRefs",
          "source": "WordEntry. java:128"
        },
        {
          "method": "org.eclipse.jdt.internal.core.index.impl.MergeFactory.mergeReferences",
          "source": "MergeFactory.java:168"
        },
        {
          "method": "org.eclipse.jdt.internal.core.index.impl.MergeFactory.merge",
          "source": "MergeFact ory.java:79"
        },
        {
          "method": "org.eclipse.jdt.internal.core.index.impl.Index.merge",
          "source": "Index.java:236"
        },
        {
          "method": "org.eclipse.jdt.internal.core.index.impl.Index.save",
          "source": "Index.java:341"
        },
        {
          "method": "org.eclipse.jdt.internal.core.search.indexing.IndexManager.saveIndexes",
          "source": "IndexManager.java:408"
        },
        {
          "method": "org.eclipse.jdt.internal.core.search.indexing.IndexManager.notifyIdle",
          "source": "IndexManager.java:313"
        },
        {
          "method": "org.eclipse.jdt.internal.core.search.processing.JobManager.run",
          "source": "JobMan ager.java:302"
        },
        {
          "method": "java.lang.Thread.run",
          "source": "Thread.java:484"
        }
      ],
      "number": 1,
      "commentIndex": 0,
      "bugId": "15426",
      "duplicateId": "15262",
      "date": "2002-05-07T16:47:32+02:00",
      "product": "JDT",
      "component": "Core",
      "severity": "normal"
    }
  ],
  "groupId": "15262",
  "bugId": "15426",
  "duplicateId": "15262",
  "date": "2002-05-07T16:47:32+02:00",
  "product": "JDT",
  "component": "Core",
  "severity": "normal"
}