{
  "comments": [
    "I have a vanilla bugzilla 2.22 install with no customization.\n\nI have added it to the task repositories, and the settings validate; however, I am unable to add a new task or query the server. The message says it is unable to get products. It also does not work on other repositories that I used to connect to in older versions of mylar.\n\nIn the log file is the following exception:\n\n\n\n!ENTRY org.eclipse.mylar.core 1 0 2006-08-18 10:01:14.093\n!MESSAGE Failed to retrieve products from server\n\n!STACK 0\njava.io.IOException: Attribute name \"rdf:about\" associated with an element type \"bz:installation\" must be followed by the \u0027 \u003d \u0027 character.\n        at org.eclipse.mylar.internal.bugzilla.core.AbstractReportFactory.collectResults(AbstractReportFactory.java:134)\n        at org.eclipse.mylar.internal.bugzilla.core.RepositoryConfigurationFactory.getConfiguration(RepositoryConfigurationFactory.java:42)\n        at org.eclipse.mylar.internal.bugzilla.core.BugzillaPlugin.getRepositoryConfiguration(BugzillaPlugin.java:116)\n        at org.eclipse.mylar.internal.bugzilla.core.BugzillaServerFacade.getProductList(BugzillaServerFacade.java:124)\n        at org.eclipse.mylar.internal.bugzilla.ui.wizard.BugzillaProductPage.initProducts(BugzillaProductPage.java:260)\n        at org.eclipse.mylar.internal.bugzilla.ui.wizard.BugzillaProductPage.populateList(BugzillaProductPage.java:288)\n        at org.eclipse.mylar.internal.bugzilla.ui.wizard.BugzillaProductPage.createControl(BugzillaProductPage.java:169)\n        at org.eclipse.jface.wizard.Wizard.createPageControls(Wizard.java:180)\n        at org.eclipse.jface.wizard.WizardDialog.createPageControls(WizardDialog.java:614)\n        at org.eclipse.jface.wizard.WizardDialog.setWizard(WizardDialog.java:989)\n        at org.eclipse.jface.wizard.WizardDialog.updateForPage(WizardDialog.java:1041)\n        at org.eclipse.jface.wizard.WizardDialog.access$2(WizardDialog.java:1038)\n        at org.eclipse.jface.wizard.WizardDialog$4.run(WizardDialog.java:1028)\n        at org.eclipse.swt.custom.BusyIndicator.showWhile(BusyIndicator.java:67)\n        at org.eclipse.jface.wizard.WizardDialog.showPage(WizardDialog.java:1026)\n        at org.eclipse.jface.wizard.WizardDialog.nextPressed(WizardDialog.java:757)\n        at org.eclipse.jface.wizard.WizardDialog.buttonPressed(WizardDialog.java:351)\n        at org.eclipse.jface.dialogs.Dialog$3.widgetSelected(Dialog.java:660)\n        at org.eclipse.swt.widgets.TypedListener.handleEvent(TypedListener.java:90)\n        at org.eclipse.swt.widgets.EventTable.sendEvent(EventTable.java:66)\n        at org.eclipse.swt.widgets.Widget.sendEvent(Widget.java:1085)\n        at org.eclipse.swt.widgets.Display.runDeferredEvents(Display.java:3164)\n        at org.eclipse.swt.widgets.Display.readAndDispatch(Display.java:2840)\n        at org.eclipse.jface.window.Window.runEventLoop(Window.java:820)\n        at org.eclipse.jface.window.Window.open(Window.java:796)\n        at org.eclipse.mylar.internal.tasks.ui.actions.NewRepositoryTaskAction.run(NewRepositoryTaskAction.java:47)\n        at org.eclipse.mylar.internal.tasks.ui.actions.NewRepositoryTaskAction.run(NewRepositoryTaskAction.java:55)\n        at org.eclipse.ui.internal.PluginAction.runWithEvent(PluginAction.java:254)\n        at org.eclipse.jface.action.ActionContributionItem.handleWidgetSelection(ActionContributionItem.java:539)\n        at org.eclipse.jface.action.ActionContributionItem.access$2(ActionContributionItem.java:488)\n        at org.eclipse.jface.action.ActionContributionItem$5.handleEvent(ActionContributionItem.java:400)\n        at org.eclipse.swt.widgets.EventTable.sendEvent(EventTable.java:66)\n        at org.eclipse.swt.widgets.Widget.sendEvent(Widget.java:1085)\n        at org.eclipse.swt.widgets.Display.runDeferredEvents(Display.java:3164)\n        at org.eclipse.swt.widgets.Display.readAndDispatch(Display.java:2840)\n        at org.eclipse.ui.internal.Workbench.runEventLoop(Workbench.java:1914)\n        at org.eclipse.ui.internal.Workbench.runUI(Workbench.java:1878)\n        at org.eclipse.ui.internal.Workbench.createAndRunWorkbench(Workbench.java:419)\n        at org.eclipse.ui.PlatformUI.createAndRunWorkbench(PlatformUI.java:149)\n        at org.eclipse.ui.internal.ide.IDEApplication.run(IDEApplication.java:95)\n        at org.eclipse.core.internal.runtime.PlatformActivator$1.run(PlatformActivator.java:78)\n        at org.eclipse.core.runtime.internal.adaptor.EclipseAppLauncher.runApplication(EclipseAppLauncher.java:92)\n        at org.eclipse.core.runtime.internal.adaptor.EclipseAppLauncher.start(EclipseAppLauncher.java:68)\n        at org.eclipse.core.runtime.adaptor.EclipseStarter.run(EclipseStarter.java:400)\n        at org.eclipse.core.runtime.adaptor.EclipseStarter.run(EclipseStarter.java:177)\n        at sun.reflect.NativeMethodAccessorImpl.invoke0(Native Method)\n        at sun.reflect.NativeMethodAccessorImpl.invoke(NativeMethodAccessorImpl.java:39)\n        at sun.reflect.DelegatingMethodAccessorImpl.invoke(DelegatingMethodAccessorImpl.java:25)\n        at java.lang.reflect.Method.invoke(Method.java:585)\n        at org.eclipse.core.launcher.Main.invokeFramework(Main.java:336)\n        at org.eclipse.core.launcher.Main.basicRun(Main.java:280)\n        at org.eclipse.core.launcher.Main.run(Main.java:977)\n        at org.eclipse.core.launcher.Main.main(Main.java:952)",
    "Have you tried the trouble shooting tips here:http://wiki.eclipse.org/index.php/Mylar_FAQ#Bugzilla_Connector_troubleshooting ?\n",
    "Created an attachment (id\u003d48185)\nOutput of the /config.cgi?ctype\u003drdf url\n\n",
    "The FAQ did not help. I attached the output of the \u003cyour-repository-url\u003e/config.cgi?ctype\u003drdf .",
    "Could you go to the same url but do a \u0027view source\u0027 on the resulting page and attach that as well? Thanks.",
    "Created an attachment (id\u003d48191)\nsource output of the previous attachment\n\n",
    "Okay it doesn\u0027t look like the rdf output is problematic. Perhaps the stream is getting terminated prematurely.  Could you give me some details about your os and jdk version? Is the web server using https/certificates?",
    "The webserver is not using https.\n\nMy jdk is:\njava version \"1.5.0_07\"\nJava(TM) 2 Runtime Environment, Standard Edition (build 1.5.0_07-b03)\nJava HotSpot(TM) Server VM (build 1.5.0_07-b03, mixed mode)\n\nI am using redhat enterprise WS 4 update 4.\n\nI am using eclipse 3.2.",
    "Okay thanks and I assume you\u0027re using Mylar release 0.6.1? Bumping up to P1.",
    "From the rdf config you posted it appears as though your urlbase isn\u0027t set. I found a bug in our parser that was corrupting the config when the urlbase (rdf:about) value is empty. The work around is to set the urlbase in the bugzilla server parameters to something. Can you confirm that your urlbase was/is in fact empty in the bugzilla parameters? ",
    "That was my problem. Sorry about that; I was checking the wrong server when I verified that parameter. ",
    "No worries, thanks for confirming. The fix for handling an empty urlbase will be in the next release (this evening or Monday I believe).",
    "Created an attachment (id\u003d48212)\nmylar/context/zip\n\n"
  ],
  "commentCreationDates": [
    "2006-08-18T17:49:21+02:00",
    "2006-08-18T18:21:42+02:00",
    "2006-08-18T18:46:35+02:00",
    "2006-08-18T18:50:17+02:00",
    "2006-08-18T19:03:02+02:00",
    "2006-08-18T19:13:18+02:00",
    "2006-08-18T19:37:48+02:00",
    "2006-08-18T20:16:26+02:00",
    "2006-08-18T20:27:17+02:00",
    "2006-08-18T23:52:59+02:00",
    "2006-08-19T00:32:20+02:00",
    "2006-08-19T00:39:12+02:00",
    "2006-08-19T01:08:36+02:00"
  ],
  "traces": [
    {
      "exceptionType": "java.io.IOException",
      "message": "Attribute name \"rdf:about\" associated with an element type \"bz:installation\" must be followed by the \u0027 \u003d \u0027 character.",
      "elements": [
        {
          "method": "org.eclipse.mylar.internal.bugzilla.core.AbstractReportFactory.collectResults",
          "source": "AbstractReportFactory.java:134"
        },
        {
          "method": "org.eclipse.mylar.internal.bugzilla.core.RepositoryConfigurationFactory.getConfiguration",
          "source": "RepositoryConfigurationFactory.java:42"
        },
        {
          "method": "org.eclipse.mylar.internal.bugzilla.core.BugzillaPlugin.getRepositoryConfiguration",
          "source": "BugzillaPlugin.java:116"
        },
        {
          "method": "org.eclipse.mylar.internal.bugzilla.core.BugzillaServerFacade.getProductList",
          "source": "BugzillaServerFacade.java:124"
        },
        {
          "method": "org.eclipse.mylar.internal.bugzilla.ui.wizard.BugzillaProductPage.initProducts",
          "source": "BugzillaProductPage.java:260"
        },
        {
          "method": "org.eclipse.mylar.internal.bugzilla.ui.wizard.BugzillaProductPage.populateList",
          "source": "BugzillaProductPage.java:288"
        },
        {
          "method": "org.eclipse.mylar.internal.bugzilla.ui.wizard.BugzillaProductPage.createControl",
          "source": "BugzillaProductPage.java:169"
        },
        {
          "method": "org.eclipse.jface.wizard.Wizard.createPageControls",
          "source": "Wizard.java:180"
        },
        {
          "method": "org.eclipse.jface.wizard.WizardDialog.createPageControls",
          "source": "WizardDialog.java:614"
        },
        {
          "method": "org.eclipse.jface.wizard.WizardDialog.setWizard",
          "source": "WizardDialog.java:989"
        },
        {
          "method": "org.eclipse.jface.wizard.WizardDialog.updateForPage",
          "source": "WizardDialog.java:1041"
        },
        {
          "method": "org.eclipse.jface.wizard.WizardDialog.access$2",
          "source": "WizardDialog.java:1038"
        },
        {
          "method": "org.eclipse.jface.wizard.WizardDialog$4.run",
          "source": "WizardDialog.java:1028"
        },
        {
          "method": "org.eclipse.swt.custom.BusyIndicator.showWhile",
          "source": "BusyIndicator.java:67"
        },
        {
          "method": "org.eclipse.jface.wizard.WizardDialog.showPage",
          "source": "WizardDialog.java:1026"
        },
        {
          "method": "org.eclipse.jface.wizard.WizardDialog.nextPressed",
          "source": "WizardDialog.java:757"
        },
        {
          "method": "org.eclipse.jface.wizard.WizardDialog.buttonPressed",
          "source": "WizardDialog.java:351"
        },
        {
          "method": "org.eclipse.jface.dialogs.Dialog$3.widgetSelected",
          "source": "Dialog.java:660"
        },
        {
          "method": "org.eclipse.swt.widgets.TypedListener.handleEvent",
          "source": "TypedListener.java:90"
        },
        {
          "method": "org.eclipse.swt.widgets.EventTable.sendEvent",
          "source": "EventTable.java:66"
        },
        {
          "method": "org.eclipse.swt.widgets.Widget.sendEvent",
          "source": "Widget.java:1085"
        },
        {
          "method": "org.eclipse.swt.widgets.Display.runDeferredEvents",
          "source": "Display.java:3164"
        },
        {
          "method": "org.eclipse.swt.widgets.Display.readAndDispatch",
          "source": "Display.java:2840"
        },
        {
          "method": "org.eclipse.jface.window.Window.runEventLoop",
          "source": "Window.java:820"
        },
        {
          "method": "org.eclipse.jface.window.Window.open",
          "source": "Window.java:796"
        },
        {
          "method": "org.eclipse.mylar.internal.tasks.ui.actions.NewRepositoryTaskAction.run",
          "source": "NewRepositoryTaskAction.java:47"
        },
        {
          "method": "org.eclipse.mylar.internal.tasks.ui.actions.NewRepositoryTaskAction.run",
          "source": "NewRepositoryTaskAction.java:55"
        },
        {
          "method": "org.eclipse.ui.internal.PluginAction.runWithEvent",
          "source": "PluginAction.java:254"
        },
        {
          "method": "org.eclipse.jface.action.ActionContributionItem.handleWidgetSelection",
          "source": "ActionContributionItem.java:539"
        },
        {
          "method": "org.eclipse.jface.action.ActionContributionItem.access$2",
          "source": "ActionContributionItem.java:488"
        },
        {
          "method": "org.eclipse.jface.action.ActionContributionItem$5.handleEvent",
          "source": "ActionContributionItem.java:400"
        },
        {
          "method": "org.eclipse.swt.widgets.EventTable.sendEvent",
          "source": "EventTable.java:66"
        },
        {
          "method": "org.eclipse.swt.widgets.Widget.sendEvent",
          "source": "Widget.java:1085"
        },
        {
          "method": "org.eclipse.swt.widgets.Display.runDeferredEvents",
          "source": "Display.java:3164"
        },
        {
          "method": "org.eclipse.swt.widgets.Display.readAndDispatch",
          "source": "Display.java:2840"
        },
        {
          "method": "org.eclipse.ui.internal.Workbench.runEventLoop",
          "source": "Workbench.java:1914"
        },
        {
          "method": "org.eclipse.ui.internal.Workbench.runUI",
          "source": "Workbench.java:1878"
        },
        {
          "method": "org.eclipse.ui.internal.Workbench.createAndRunWorkbench",
          "source": "Workbench.java:419"
        },
        {
          "method": "org.eclipse.ui.PlatformUI.createAndRunWorkbench",
          "source": "PlatformUI.java:149"
        },
        {
          "method": "org.eclipse.ui.internal.ide.IDEApplication.run",
          "source": "IDEApplication.java:95"
        },
        {
          "method": "org.eclipse.core.internal.runtime.PlatformActivator$1.run",
          "source": "PlatformActivator.java:78"
        },
        {
          "method": "org.eclipse.core.runtime.internal.adaptor.EclipseAppLauncher.runApplication",
          "source": "EclipseAppLauncher.java:92"
        },
        {
          "method": "org.eclipse.core.runtime.internal.adaptor.EclipseAppLauncher.start",
          "source": "EclipseAppLauncher.java:68"
        },
        {
          "method": "org.eclipse.core.runtime.adaptor.EclipseStarter.run",
          "source": "EclipseStarter.java:400"
        },
        {
          "method": "org.eclipse.core.runtime.adaptor.EclipseStarter.run",
          "source": "EclipseStarter.java:177"
        },
        {
          "method": "sun.reflect.NativeMethodAccessorImpl.invoke0",
          "source": "Native Method"
        },
        {
          "method": "sun.reflect.NativeMethodAccessorImpl.invoke",
          "source": "NativeMethodAccessorImpl.java:39"
        },
        {
          "method": "sun.reflect.DelegatingMethodAccessorImpl.invoke",
          "source": "DelegatingMethodAccessorImpl.java:25"
        },
        {
          "method": "java.lang.reflect.Method.invoke",
          "source": "Method.java:585"
        },
        {
          "method": "org.eclipse.core.launcher.Main.invokeFramework",
          "source": "Main.java:336"
        },
        {
          "method": "org.eclipse.core.launcher.Main.basicRun",
          "source": "Main.java:280"
        },
        {
          "method": "org.eclipse.core.launcher.Main.run",
          "source": "Main.java:977"
        },
        {
          "method": "org.eclipse.core.launcher.Main.main",
          "source": "Main.java:952"
        }
      ],
      "number": 0,
      "commentIndex": 0,
      "bugId": "154365",
      "date": "2006-08-18T17:49:21+02:00",
      "product": "Mylyn",
      "component": "Bugzilla",
      "severity": "major"
    }
  ],
  "groupId": "154365",
  "bugId": "154365",
  "date": "2006-08-18T17:49:21+02:00",
  "product": "Mylyn",
  "component": "Bugzilla",
  "severity": "major"
}