{
  "comments": [
    "\u003cNote by rosy (Palermo Jr, Rocco F.           ), 2006/08/17 15:20:00, seq: 1 rel: 0  action: open\u003e\nIllegalStateException deleting a project when WEB DD open\n\nIf I have the Web Deployment Descriptor open\nand delete the project that contains it, I get\nthe following error.\n\n1) Create a Dynamic Web Project\n2) Open Deployment Descriptor\n3) Right-Click Project and select\n   Delete\n\n!ENTRY org.eclipse.ui.workbench 4 0 2006-08-17 15:57:04.750\n!MESSAGE Edit Model already disposed\n!STACK 0\njava.lang.IllegalStateException: Edit Model already disposed\n       at org.eclipse.wst.common.internal.emfworkbench.integration.EditModel.getEmfContext(EditModel.java:958)\n       at org.eclipse.wst.common.internal.emfworkbench.integration.EditModel.getResourceSet(EditModel.java:698)\n       at org.eclipse.wst.common.internal.emfworkbench.integration.EditModel.getResource(EditModel.java:717)\n       at org.eclipse.wst.common.componentcore.internal.ArtifactEditModel.getResource(ArtifactEditModel.java:173)\n       at org.eclipse.wst.common.internal.emfworkbench.integration.EditModel.getPrimaryResource(EditModel.java:1550)\n       at org.eclipse.wst.common.internal.emfworkbench.integration.EditModel.getPrimaryRootObject(EditModel.java:1531)\n       at org.eclipse.wst.common.componentcore.ArtifactEdit.getContentModelRoot(ArtifactEdit.java:461)\n       at com.ibm.etools.emf.workbench.ui.presentation.ArtifactEditMultiPageEditorPart.dispose(ArtifactEditMultiPageEditorPart.java:937)\n       at org.eclipse.ui.internal.WorkbenchPartReference.doDisposePart(WorkbenchPartReference.java:687)\n       at org.eclipse.ui.internal.EditorReference.doDisposePart(EditorReference.java:256)\n       at org.eclipse.ui.internal.WorkbenchPartReference.dispose(WorkbenchPartReference.java:642)\n       at org.eclipse.ui.internal.WorkbenchPage.disposePart(WorkbenchPage.java:1541)\n       at org.eclipse.ui.internal.WorkbenchPage.handleDeferredEvents(WorkbenchPage.java:1311)\n       at org.eclipse.ui.internal.WorkbenchPage.deferUpdates(WorkbenchPage.java:1295)\n       at org.eclipse.ui.internal.WorkbenchPage.closeEditors(WorkbenchPage.java:1269)\n       at org.eclipse.ui.internal.WorkbenchPage.closeEditor(WorkbenchPage.java:1333)\n       at com.ibm.etools.emf.workbench.ui.presentation.BaseMultiPageEditorPart$2.run(BaseMultiPageEditorPart.java:255)\n       at org.eclipse.swt.widgets.RunnableLock.run(RunnableLock.java:35)\n       at org.eclipse.swt.widgets.Synchronizer.runAsyncMessages(Synchronizer.java:123)\n       at org.eclipse.swt.widgets.Display.runAsyncMessages(Display.java:3325)\n       at org.eclipse.swt.widgets.Display.readAndDispatch(Display.java:2971)\n       at org.eclipse.ui.internal.Workbench.runEventLoop(Workbench.java:1914)\n       at org.eclipse.ui.internal.Workbench.runUI(Workbench.java:1878)\n       at org.eclipse.ui.internal.Workbench.createAndRunWorkbench(Workbench.java:419)\n       at org.eclipse.ui.PlatformUI.createAndRunWorkbench(PlatformUI.java:149)\n       at org.eclipse.ui.internal.ide.IDEApplication.run(IDEApplication.java:95)\n       at org.eclipse.core.internal.runtime.PlatformActivator$1.run(PlatformActivator.java:78)\n       at org.eclipse.core.runtime.internal.adaptor.EclipseAppLauncher.runApplication(EclipseAppLauncher.java:92)\n       at org.eclipse.core.runtime.internal.adaptor.EclipseAppLauncher.start(EclipseAppLauncher.java:68)\n       at org.eclipse.core.runtime.adaptor.EclipseStarter.run(EclipseStarter.java:400)\n       at org.eclipse.core.runtime.adaptor.EclipseStarter.run(EclipseStarter.java:177)\n       at sun.reflect.NativeMethodAccessorImpl.invoke0(Native Method)\n       at sun.reflect.NativeMethodAccessorImpl.invoke(NativeMethodAccessorImpl.java:64)\n       at sun.reflect.DelegatingMethodAccessorImpl.invoke(DelegatingMethodAccessorImpl.java:43)\n       at java.lang.reflect.Method.invoke(Method.java:615)\n       at org.eclipse.core.launcher.Main.invokeFramework(Main.java:334)\n       at org.eclipse.core.launcher.Main.basicRun(Main.java:278)\n       at org.eclipse.core.launcher.Main.run(Main.java:973)\n       at org.eclipse.core.launcher.Main.main(Main.java:948)",
    "This is a problem with IBM editor part which is not checking that the edit model is disposed already.  This is not a WTP issue.",
    "Does not seem to happen anymore."
  ],
  "commentCreationDates": [
    "2006-08-23T20:35:47+02:00",
    "2006-08-24T19:24:47+02:00",
    "2006-09-25T19:12:25+02:00"
  ],
  "traces": [
    {
      "exceptionType": "java.lang.IllegalStateException",
      "message": "Edit Model already disposed",
      "elements": [
        {
          "method": "org.eclipse.wst.common.internal.emfworkbench.integration.EditModel.getEmfContext",
          "source": "EditModel.java:958"
        },
        {
          "method": "org.eclipse.wst.common.internal.emfworkbench.integration.EditModel.getResourceSet",
          "source": "EditModel.java:698"
        },
        {
          "method": "org.eclipse.wst.common.internal.emfworkbench.integration.EditModel.getResource",
          "source": "EditModel.java:717"
        },
        {
          "method": "org.eclipse.wst.common.componentcore.internal.ArtifactEditModel.getResource",
          "source": "ArtifactEditModel.java:173"
        },
        {
          "method": "org.eclipse.wst.common.internal.emfworkbench.integration.EditModel.getPrimaryResource",
          "source": "EditModel.java:1550"
        },
        {
          "method": "org.eclipse.wst.common.internal.emfworkbench.integration.EditModel.getPrimaryRootObject",
          "source": "EditModel.java:1531"
        },
        {
          "method": "org.eclipse.wst.common.componentcore.ArtifactEdit.getContentModelRoot",
          "source": "ArtifactEdit.java:461"
        },
        {
          "method": "com.ibm.etools.emf.workbench.ui.presentation.ArtifactEditMultiPageEditorPart.dispose",
          "source": "ArtifactEditMultiPageEditorPart.java:937"
        },
        {
          "method": "org.eclipse.ui.internal.WorkbenchPartReference.doDisposePart",
          "source": "WorkbenchPartReference.java:687"
        },
        {
          "method": "org.eclipse.ui.internal.EditorReference.doDisposePart",
          "source": "EditorReference.java:256"
        },
        {
          "method": "org.eclipse.ui.internal.WorkbenchPartReference.dispose",
          "source": "WorkbenchPartReference.java:642"
        },
        {
          "method": "org.eclipse.ui.internal.WorkbenchPage.disposePart",
          "source": "WorkbenchPage.java:1541"
        },
        {
          "method": "org.eclipse.ui.internal.WorkbenchPage.handleDeferredEvents",
          "source": "WorkbenchPage.java:1311"
        },
        {
          "method": "org.eclipse.ui.internal.WorkbenchPage.deferUpdates",
          "source": "WorkbenchPage.java:1295"
        },
        {
          "method": "org.eclipse.ui.internal.WorkbenchPage.closeEditors",
          "source": "WorkbenchPage.java:1269"
        },
        {
          "method": "org.eclipse.ui.internal.WorkbenchPage.closeEditor",
          "source": "WorkbenchPage.java:1333"
        },
        {
          "method": "com.ibm.etools.emf.workbench.ui.presentation.BaseMultiPageEditorPart$2.run",
          "source": "BaseMultiPageEditorPart.java:255"
        },
        {
          "method": "org.eclipse.swt.widgets.RunnableLock.run",
          "source": "RunnableLock.java:35"
        },
        {
          "method": "org.eclipse.swt.widgets.Synchronizer.runAsyncMessages",
          "source": "Synchronizer.java:123"
        },
        {
          "method": "org.eclipse.swt.widgets.Display.runAsyncMessages",
          "source": "Display.java:3325"
        },
        {
          "method": "org.eclipse.swt.widgets.Display.readAndDispatch",
          "source": "Display.java:2971"
        },
        {
          "method": "org.eclipse.ui.internal.Workbench.runEventLoop",
          "source": "Workbench.java:1914"
        },
        {
          "method": "org.eclipse.ui.internal.Workbench.runUI",
          "source": "Workbench.java:1878"
        },
        {
          "method": "org.eclipse.ui.internal.Workbench.createAndRunWorkbench",
          "source": "Workbench.java:419"
        },
        {
          "method": "org.eclipse.ui.PlatformUI.createAndRunWorkbench",
          "source": "PlatformUI.java:149"
        },
        {
          "method": "org.eclipse.ui.internal.ide.IDEApplication.run",
          "source": "IDEApplication.java:95"
        },
        {
          "method": "org.eclipse.core.internal.runtime.PlatformActivator$1.run",
          "source": "PlatformActivator.java:78"
        },
        {
          "method": "org.eclipse.core.runtime.internal.adaptor.EclipseAppLauncher.runApplication",
          "source": "EclipseAppLauncher.java:92"
        },
        {
          "method": "org.eclipse.core.runtime.internal.adaptor.EclipseAppLauncher.start",
          "source": "EclipseAppLauncher.java:68"
        },
        {
          "method": "org.eclipse.core.runtime.adaptor.EclipseStarter.run",
          "source": "EclipseStarter.java:400"
        },
        {
          "method": "org.eclipse.core.runtime.adaptor.EclipseStarter.run",
          "source": "EclipseStarter.java:177"
        },
        {
          "method": "sun.reflect.NativeMethodAccessorImpl.invoke0",
          "source": "Native Method"
        },
        {
          "method": "sun.reflect.NativeMethodAccessorImpl.invoke",
          "source": "NativeMethodAccessorImpl.java:64"
        },
        {
          "method": "sun.reflect.DelegatingMethodAccessorImpl.invoke",
          "source": "DelegatingMethodAccessorImpl.java:43"
        },
        {
          "method": "java.lang.reflect.Method.invoke",
          "source": "Method.java:615"
        },
        {
          "method": "org.eclipse.core.launcher.Main.invokeFramework",
          "source": "Main.java:334"
        },
        {
          "method": "org.eclipse.core.launcher.Main.basicRun",
          "source": "Main.java:278"
        },
        {
          "method": "org.eclipse.core.launcher.Main.run",
          "source": "Main.java:973"
        },
        {
          "method": "org.eclipse.core.launcher.Main.main",
          "source": "Main.java:948"
        }
      ],
      "number": 0,
      "commentIndex": 0,
      "bugId": "154905",
      "date": "2006-08-23T20:35:47+02:00",
      "product": "Web Tools",
      "component": "wst.common",
      "severity": "normal"
    }
  ],
  "groupId": "154905",
  "bugId": "154905",
  "date": "2006-08-23T20:35:47+02:00",
  "product": "Web Tools",
  "component": "wst.common",
  "severity": "normal"
}