{
  "comments": [
    "I have changed the config.ini and the swt plugin as said in the bug report #148614.\n\nThanks to these modifications, I am capable of launching demos but I have\nexperienced some problems : \n\n1) I can\u0027t see the view \"preferences\", nothing appears on the screen when I\nselect \"preferences\" and this log is generated\n\n!ENTRY org.eclipse.ui 4 4 2006-08-24 14:34:43.546\n!MESSAGE Unhandled event loop exception\n\n!ENTRY org.eclipse.ui 4 0 2006-08-24 14:34:43.593\n!MESSAGE Subclassing not allowed\n!STACK 0\norg.eclipse.swt.SWTException: Subclassing not allowed\n        at org.eclipse.swt.SWT.error(Unknown Source)\n        at org.eclipse.swt.SWT.error(Unknown Source)\n        at org.eclipse.swt.SWT.error(Unknown Source)\n        at org.eclipse.ercp.swt.mobile.MultiPageDialog.\u003cinit\u003e(Unknown Source)\n        at org.eclipse.ercp.swt.mobile.MultiPageDialog.\u003cinit\u003e(Unknown Source)\n        at org.eclipse.jface.preference.PreferenceDialog.\u003cinit\u003e(Unknown Source)\n        at\norg.eclipse.ui.internal.dialogs.WorkbenchPreferenceDialog.\u003cinit\u003e(Unknown\nSource)\n        at\norg.eclipse.ui.internal.dialogs.WorkbenchPreferenceDialog.createDialogOn(Unknown\nSource)\n        at\norg.eclipse.ui.dialogs.PreferencesUtil.createPreferenceDialogOn(Unknown Source)\n        at org.eclipse.ercp.eworkbench.DefaultView.widgetSelected(Unknown\nSource)\n        at org.eclipse.swt.widgets.TypedListener.handleEvent(Unknown Source)\n        at org.eclipse.swt.widgets.EventTable.sendEvent(Unknown Source)\n        at org.eclipse.swt.widgets.Widget.sendEvent(Unknown Source)\n        at org.eclipse.swt.widgets.Widget.internal_sendEvent(Unknown Source)\n        at org.eclipse.swt.internal.symbian.OS.Display_ReadAndDispatch(Native\nMethod)\n        at org.eclipse.swt.widgets.Display.readAndDispatch(Unknown Source)\n        at org.eclipse.ui.internal.Workbench.runEventLoop(Unknown Source)\n        at org.eclipse.ui.internal.Workbench.runUI(Unknown Source)\n        at org.eclipse.ui.internal.Workbench.createAndRunWorkbench(Unknown\nSource)\n        at org.eclipse.ui.PlatformUI.createAndRunWorkbench(Unknown Source)\n        at org.eclipse.ercp.eworkbench.eWorkbench.run(Unknown Source)\n        at org.eclipse.core.internal.runtime.PlatformActivator$1.run(Unknown\nSource)\n        at\norg.eclipse.core.runtime.internal.adaptor.EclipseAppLauncher.runApplication(Unknown\nSource)\n        at\norg.eclipse.core.runtime.internal.adaptor.EclipseAppLauncher.start(Unknown\nSource)\n        at org.eclipse.core.runtime.adaptor.EclipseStarter.run(Unknown Source)\n        at org.eclipse.core.runtime.adaptor.EclipseStarter.run(Unknown Source)\n        at java.lang.reflect.AccessibleObject.invokeL(Unknown Source)\n        at java.lang.reflect.Method.invoke(Unknown Source)\n        at org.eclipse.core.launcher.Main.invokeFramework(Unknown Source)\n        at org.eclipse.core.launcher.Main.basicRun(Unknown Source)\n        at org.eclipse.core.launcher.Main.run(Unknown Source)\n        at org.eclipse.core.launcher.Main.main(Unknown Source)\n\nThis error appears both on emulator and on the phone.\n\n2) I can\u0027t exit the application properly.\n\nOn the phone, this message appears :\nProgramme : J9 VM Thread\nCode de Motif  : KERN-EXEC\nNumero de motif : 0\n\nMoreover after this error message, the application isn\u0027t closed, it must be closed manually.\n\nOn the emulator, the emulator is closed by Windows XP when I try to exit.\n\nThis second problem does not generate any log.",
    "There is a third problem. Concerning the update manager, the choice between \"Install new applications/Features\", \"Update all applications/features\" and \"manage Applications/features\" must be done by pushing a button. It works well on adapted device (like PDA) but it is not possible to use Button on a phone. Buttons simply don\u0027t appear.\nI suggest to replace these buttons by Commands in order to make Update Manager work on every kinds of devices.",
    "I have just updated to eRCP-RC1 and I\u0027m still noticing the same problems with the same error logs.",
    "The fix for this issue is not released yet. ",
    "fix dropped to HEAD, WorkbenchPreferenceDialog still needs to overwrite checksubclass() passing to Mark for further fixes.",
    "Change to eJFace PreferenceDialog has been made. Gorkem, please test against S80 implementation."
  ],
  "commentCreationDates": [
    "2006-08-24T15:32:11+02:00",
    "2006-08-24T17:57:38+02:00",
    "2006-08-29T11:47:20+02:00",
    "2006-08-29T13:00:18+02:00",
    "2006-08-29T15:42:40+02:00",
    "2006-08-29T17:23:54+02:00"
  ],
  "traces": [
    {
      "exceptionType": "org.eclipse.swt.SWTException",
      "message": "Subclassing not allowed",
      "elements": [
        {
          "method": "org.eclipse.swt.SWT.error",
          "source": "Unknown Source"
        },
        {
          "method": "org.eclipse.swt.SWT.error",
          "source": "Unknown Source"
        },
        {
          "method": "org.eclipse.swt.SWT.error",
          "source": "Unknown Source"
        },
        {
          "method": "org.eclipse.ercp.swt.mobile.MultiPageDialog.\u003cinit\u003e",
          "source": "Unknown Source"
        },
        {
          "method": "org.eclipse.ercp.swt.mobile.MultiPageDialog.\u003cinit\u003e",
          "source": "Unknown Source"
        },
        {
          "method": "org.eclipse.jface.preference.PreferenceDialog.\u003cinit\u003e",
          "source": "Unknown Source"
        },
        {
          "method": "org.eclipse.ui.internal.dialogs.WorkbenchPreferenceDialog.\u003cinit\u003e",
          "source": "Unknown Source"
        },
        {
          "method": "org.eclipse.ui.internal.dialogs.WorkbenchPreferenceDialog.createDialogOn",
          "source": "Unknown Source"
        },
        {
          "method": "org.eclipse.ui.dialogs.PreferencesUtil.createPreferenceDialogOn",
          "source": "Unknown Source"
        },
        {
          "method": "org.eclipse.ercp.eworkbench.DefaultView.widgetSelected",
          "source": "Unknown Source"
        },
        {
          "method": "org.eclipse.swt.widgets.TypedListener.handleEvent",
          "source": "Unknown Source"
        },
        {
          "method": "org.eclipse.swt.widgets.EventTable.sendEvent",
          "source": "Unknown Source"
        },
        {
          "method": "org.eclipse.swt.widgets.Widget.sendEvent",
          "source": "Unknown Source"
        },
        {
          "method": "org.eclipse.swt.widgets.Widget.internal_sendEvent",
          "source": "Unknown Source"
        },
        {
          "method": "org.eclipse.swt.internal.symbian.OS.Display_ReadAndDispatch",
          "source": "Native Method"
        },
        {
          "method": "org.eclipse.swt.widgets.Display.readAndDispatch",
          "source": "Unknown Source"
        },
        {
          "method": "org.eclipse.ui.internal.Workbench.runEventLoop",
          "source": "Unknown Source"
        },
        {
          "method": "org.eclipse.ui.internal.Workbench.runUI",
          "source": "Unknown Source"
        },
        {
          "method": "org.eclipse.ui.internal.Workbench.createAndRunWorkbench",
          "source": "Unknown Source"
        },
        {
          "method": "org.eclipse.ui.PlatformUI.createAndRunWorkbench",
          "source": "Unknown Source"
        },
        {
          "method": "org.eclipse.ercp.eworkbench.eWorkbench.run",
          "source": "Unknown Source"
        },
        {
          "method": "org.eclipse.core.internal.runtime.PlatformActivator$1.run",
          "source": "Unknown Source"
        },
        {
          "method": "org.eclipse.core.runtime.internal.adaptor.EclipseAppLauncher.runApplication",
          "source": "Unknown Source"
        },
        {
          "method": "org.eclipse.core.runtime.internal.adaptor.EclipseAppLauncher.start",
          "source": "Unknown Source"
        },
        {
          "method": "org.eclipse.core.runtime.adaptor.EclipseStarter.run",
          "source": "Unknown Source"
        },
        {
          "method": "org.eclipse.core.runtime.adaptor.EclipseStarter.run",
          "source": "Unknown Source"
        },
        {
          "method": "java.lang.reflect.AccessibleObject.invokeL",
          "source": "Unknown Source"
        },
        {
          "method": "java.lang.reflect.Method.invoke",
          "source": "Unknown Source"
        },
        {
          "method": "org.eclipse.core.launcher.Main.invokeFramework",
          "source": "Unknown Source"
        },
        {
          "method": "org.eclipse.core.launcher.Main.basicRun",
          "source": "Unknown Source"
        },
        {
          "method": "org.eclipse.core.launcher.Main.run",
          "source": "Unknown Source"
        },
        {
          "method": "org.eclipse.core.launcher.Main.main",
          "source": "Unknown Source"
        }
      ],
      "number": 0,
      "commentIndex": 0,
      "bugId": "155032",
      "date": "2006-08-24T15:32:11+02:00",
      "product": "ERCP",
      "component": "eSWT",
      "severity": "normal"
    }
  ],
  "groupId": "155032",
  "bugId": "155032",
  "date": "2006-08-24T15:32:11+02:00",
  "product": "ERCP",
  "component": "eSWT",
  "severity": "normal"
}