{
  "comments": [
    "The suite() method is not picked up by projects using junit 4.0\n\nSteps to reproduce:\n\n1.\nCreate a Java Project and add Libraries-\u003eAdd Library-\u003eJunit 4\n\n2. \nAdd the following 2 classes\n\n--RunMe.java\nimport junit.framework.Test;\nimport junit.framework.TestSuite;\n\npublic class RunMe {\n\tpublic static Test suite() {\n\t\tTestSuite suite \u003d new TestSuite();\n\t\tsuite.addTestSuite(MyTest.class);\n\t\treturn suite;\n\t}\n}\n\n\n--MyTest\nimport junit.framework.TestCase;\n\npublic class MyTest extends TestCase {\n\tpublic void testFoo() {\n\t\tSystem.out.println(\"foo\");\n\t}\n}\n\n3.\nTry and run test RunMe, fails with following exception\njava.lang.Exception: No runnable methods\n\tat org.junit.internal.runners.TestClassMethodsRunner.testAborted(TestClassMethodsRunner.java:42)\n\tat org.junit.internal.runners.TestClassMethodsRunner.run(TestClassMethodsRunner.java:33)\n\tat org.junit.internal.runners.TestClassRunner$1.runUnprotected(TestClassRunner.java:42)\n\tat org.junit.internal.runners.BeforeAndAfterRunner.runProtected(BeforeAndAfterRunner.java:34)\n\tat org.junit.internal.runners.TestClassRunner.run(TestClassRunner.java:52)\n\tat org.eclipse.jdt.internal.junit4.runner.JUnit4TestReference.run(JUnit4TestReference.java:38)\n\tat org.eclipse.jdt.internal.junit.runner.TestExecution.run(TestExecution.java:38)\n\tat org.eclipse.jdt.internal.junit.runner.RemoteTestRunner.runTests(RemoteTestRunner.java:460)\n\tat org.eclipse.jdt.internal.junit.runner.RemoteTestRunner.runTests(RemoteTestRunner.java:673)\n\tat org.eclipse.jdt.internal.junit.runner.RemoteTestRunner.run(RemoteTestRunner.java:386)\n\tat org.eclipse.jdt.internal.junit.runner.RemoteTestRunner.main(RemoteTestRunner.java:196)\n\n\nThis works fine, if junit 3.8.1 is selected instead of junit 4.0.\nFurthermore, even if I start out by choosing 4.0 and then try to switch to 3.8.1 in project properties I get this error when trying to run RunMe\n\nCannot find \u0027org.junit.Test\u0027 on project build path. JUnit 4 tests can only be run if JUnit 4 is on the build path",
    "Moving to JDT/UI",
    "JUnit 4 eliminated \u0027suite\u0027: It is not supported anymore. Have a look at JUnit 4 documentation on the net how multiple tests are executed now.",
    "That\u0027s not correct. JUnit 4 didn\u0027t eliminate suite() it just provided a new alternative the Suite annotation. JUnit 4 is fully backwards compatible with JUnit 3.8.x. \n",
    "So how exactly do you use JUnit 4 so that you can run \u0027RunMe\u0027 as listed in comment 0?\n\nAFAIK, you can still have a static method suite, but you will have to annotate your type with\n@RunWith(AllTests.class)\n\nUnfortunatly that doesn\u0027t work at the moment due to a bug in JUnit (NPE in Descriptor.hashCode). So you have to name your test suite\n@RunWith(AllTests.class)\npublic class RunMe {\n        public static Test suite() {\n                TestSuite suite \u003d new TestSuite();\n                suite.setName(\"MySuite\"); \n                suite.addTestSuite(MyTest.class);\n                return suite;\n        }\n}",
    "(In reply to comment #4)\n\u003e So how exactly do you use JUnit 4 so that you can run \u0027RunMe\u0027 as listed in\n\u003e comment 0?\n\nHow I use JUnit 4? You mean like Run-\u003eRun As-\u003eJUnit Test ?\n\nThe option to run them as JUnit Test is still shown for JUnit 4 projects if a static suite() method is available.\n",
    "As far I know and just verified, JUnit 4 can not run the class as specified in comment 4. For example JUnitCore.main(\"pack.RunMe\") does not find any tests. I was wondering if you know more about the JUnit4 framework and I missed a way to do it. Yes, I also heard that Junit 4 is \u0027backward compatible\u0027 but it doesn\u0027t seem to be in that aspect.\n\nDavid, is that a JUnit bug?",
    "So I assume this is a JUnit 4 shortcoming. Setting to remind unless I hear something else.",
    "Martin,\n\nI\u0027ve been unable to do much with JUnit over the summer, so I haven\u0027t had a lot of time to think about this until now.  It appears that Eclipse 3.2 M2 does correctly run the code indicated in comment 4.  Is this new behavior?\n\nThank you for noting the NPE bug--we\u0027ll fix that in the next release of JUnit.",
    "The code from comment 4 always workes in Eclipse, but it does\u0027n run when you leave the line \u0027suite.setName(\"MySuite\")\u0027 away: Then you get the NPE.\nWith \u0027shortcoming\u0027 I meant the fact that \u0027@RunWith(AllTests.class)\u0027 is required here. You can\u0027t just run your old class with suite anymore. So JUnit 4 isn\u0027t exactly backwards compatible. So I\u0027m not sure if this is a JUnit 4 oversight or by design."
  ],
  "commentCreationDates": [
    "2006-08-28T20:04:50+02:00",
    "2006-08-28T20:07:47+02:00",
    "2006-08-29T17:56:32+02:00",
    "2006-08-29T23:25:44+02:00",
    "2006-08-31T18:35:03+02:00",
    "2006-09-01T08:01:36+02:00",
    "2006-09-01T09:20:23+02:00",
    "2006-09-19T17:47:17+02:00",
    "2006-09-26T21:16:32+02:00",
    "2006-09-27T09:17:53+02:00"
  ],
  "traces": [
    {
      "exceptionType": "java.lang.Exception",
      "message": "No runnable methods",
      "elements": [
        {
          "method": "org.junit.internal.runners.TestClassMethodsRunner.testAborted",
          "source": "TestClassMethodsRunner.java:42"
        },
        {
          "method": "org.junit.internal.runners.TestClassMethodsRunner.run",
          "source": "TestClassMethodsRunner.java:33"
        },
        {
          "method": "org.junit.internal.runners.TestClassRunner$1.runUnprotected",
          "source": "TestClassRunner.java:42"
        },
        {
          "method": "org.junit.internal.runners.BeforeAndAfterRunner.runProtected",
          "source": "BeforeAndAfterRunner.java:34"
        },
        {
          "method": "org.junit.internal.runners.TestClassRunner.run",
          "source": "TestClassRunner.java:52"
        },
        {
          "method": "org.eclipse.jdt.internal.junit4.runner.JUnit4TestReference.run",
          "source": "JUnit4TestReference.java:38"
        },
        {
          "method": "org.eclipse.jdt.internal.junit.runner.TestExecution.run",
          "source": "TestExecution.java:38"
        },
        {
          "method": "org.eclipse.jdt.internal.junit.runner.RemoteTestRunner.runTests",
          "source": "RemoteTestRunner.java:460"
        },
        {
          "method": "org.eclipse.jdt.internal.junit.runner.RemoteTestRunner.runTests",
          "source": "RemoteTestRunner.java:673"
        },
        {
          "method": "org.eclipse.jdt.internal.junit.runner.RemoteTestRunner.run",
          "source": "RemoteTestRunner.java:386"
        },
        {
          "method": "org.eclipse.jdt.internal.junit.runner.RemoteTestRunner.main",
          "source": "RemoteTestRunner.java:196"
        }
      ],
      "number": 0,
      "commentIndex": 0,
      "bugId": "155438",
      "date": "2006-08-28T20:04:50+02:00",
      "product": "JDT",
      "component": "UI",
      "severity": "normal"
    }
  ],
  "groupId": "155438",
  "bugId": "155438",
  "date": "2006-08-28T20:04:50+02:00",
  "product": "JDT",
  "component": "UI",
  "severity": "normal"
}