{
  "comments": [
    "After upgrading from eclipse 3.1.2 (debian 3.1.2-2) to 3.2, my external ant\nbuilders were not recognised any more.\n\nAnd whenever I try to add a new one (either via Properties -\u003e Builders -\u003e New or via Import) there is brief disk activity and no dialog appears.\n\nThis only happens with one of my projects, i.e. when I create a new project I can add new external builders to it without problems. I\u0027d be happy about an idea how I could track this down further or a workaround. Especially I\u0027d like to be able to remove the offending setting from my project settings, if I could only find it.\n\nSince the backtrace starts with org.eclipse.debug.internal.core.LaunchConfigurationWorkingCopy.writeN\newFile I filed this against the \"Debug\" component, because I had no idea where else to file it.\n\nThe logfile contains the following backtrace:\n\n-------\n!ENTRY org.eclipse.ui 4 0 2006-08-29 00:13:15.050\n!MESSAGE java.lang.NullPointerException\n!STACK 0\njava.lang.NullPointerException\n        at org.eclipse.debug.internal.core.LaunchConfigurationWorkingCopy.writeN\newFile(LaunchConfigurationWorkingCopy.java:256)\n        at org.eclipse.debug.internal.core.LaunchConfigurationWorkingCopy.doSave\n0(LaunchConfigurationWorkingCopy.java:196)\n        at org.eclipse.debug.internal.core.LaunchConfigurationWorkingCopy.access\n$0(LaunchConfigurationWorkingCopy.java:182)\n        at org.eclipse.debug.internal.core.LaunchConfigurationWorkingCopy$1.run(\nLaunchConfigurationWorkingCopy.java:165)\n        at org.eclipse.core.internal.resources.Workspace.run(Workspace.java:1737\n)\n        at org.eclipse.debug.internal.core.LaunchConfigurationWorkingCopy.doSave\n(LaunchConfigurationWorkingCopy.java:169)\n        at org.eclipse.ui.externaltools.internal.model.BuilderUtils.duplicateCon\nfiguration(BuilderUtils.java:285)\n        at org.eclipse.ui.externaltools.internal.ui.BuilderPropertyPage.handleIm\nportButtonPressed(BuilderPropertyPage.java:509)\n        at org.eclipse.ui.externaltools.internal.ui.BuilderPropertyPage.handleBu\nttonPressed(BuilderPropertyPage.java:394)\n        at org.eclipse.ui.externaltools.internal.ui.BuilderPropertyPage.access$0\n(BuilderPropertyPage.java:390)\n        at org.eclipse.ui.externaltools.internal.ui.BuilderPropertyPage$1.widget\nSelected(BuilderPropertyPage.java:129)\n        at org.eclipse.swt.widgets.TypedListener.handleEvent(TypedListener.java:\n90)\n        at org.eclipse.swt.widgets.EventTable.sendEvent(EventTable.java:66)\n        at org.eclipse.swt.widgets.Widget.sendEvent(Widget.java:1085)\n        at org.eclipse.swt.widgets.Display.runDeferredEvents(Display.java:3164)\n        at org.eclipse.swt.widgets.Display.readAndDispatch(Display.java:2840)\n        at org.eclipse.jface.window.Window.runEventLoop(Window.java:820)\n        at org.eclipse.jface.window.Window.open(Window.java:796)\n        at org.eclipse.ui.dialogs.PropertyDialogAction.run(PropertyDialogAction.\njava:156)\n        at org.eclipse.ui.internal.ide.actions.ProjectPropertyDialogAction.run(P\nrojectPropertyDialogAction.java:77)\n        at org.eclipse.jface.action.Action.runWithEvent(Action.java:499)\n        at org.eclipse.jface.action.ActionContributionItem.handleWidgetSelection\n(ActionContributionItem.java:539)\n        at org.eclipse.jface.action.ActionContributionItem.access$2(ActionContri\nbutionItem.java:488)\n        at org.eclipse.jface.action.ActionContributionItem$5.handleEvent(ActionC\nontributionItem.java:400)\n        at org.eclipse.swt.widgets.EventTable.sendEvent(EventTable.java:66)\n        at org.eclipse.swt.widgets.Widget.sendEvent(Widget.java:1085)\n        at org.eclipse.swt.widgets.Display.runDeferredEvents(Display.java:3164)\n        at org.eclipse.swt.widgets.Display.readAndDispatch(Display.java:2840)\n        at org.eclipse.ui.internal.Workbench.runEventLoop(Workbench.java:1914)\n        at org.eclipse.ui.internal.Workbench.runUI(Workbench.java:1878)\n        at org.eclipse.ui.internal.Workbench.createAndRunWorkbench(Workbench.jav\na:419)\n        at org.eclipse.ui.PlatformUI.createAndRunWorkbench(PlatformUI.java:149)\n        at org.eclipse.ui.internal.ide.IDEApplication.run(IDEApplication.java:95\n)\n        at org.eclipse.core.internal.runtime.PlatformActivator$1.run(PlatformAct\nivator.java:78)\n        at org.eclipse.core.runtime.internal.adaptor.EclipseAppLauncher.runAppli\ncation(EclipseAppLauncher.java:92)\n        at org.eclipse.core.runtime.internal.adaptor.EclipseAppLauncher.start(Ec\nlipseAppLauncher.java:68)\n        at org.eclipse.core.runtime.adaptor.EclipseStarter.run(EclipseStarter.ja\nva:400)\n        at org.eclipse.core.runtime.adaptor.EclipseStarter.run(EclipseStarter.ja\nva:177)\n        at sun.reflect.NativeMethodAccessorImpl.invoke0(Native Method)\n        at sun.reflect.NativeMethodAccessorImpl.invoke(NativeMethodAccessorImpl.\njava:39)\n        at sun.reflect.DelegatingMethodAccessorImpl.invoke(DelegatingMethodAcces\nsorImpl.java:25)\n        at java.lang.reflect.Method.invoke(Method.java:585)\n        at org.eclipse.core.launcher.Main.invokeFramework(Main.java:336)\n        at org.eclipse.core.launcher.Main.basicRun(Main.java:280)\n        at org.eclipse.core.launcher.Main.run(Main.java:977)\n        at org.eclipse.core.launcher.Main.main(Main.java:952)\n\n-------\n\nKind regards\nFDF",
    "Meanwhile I\u0027ve discovered that this faulty behaviour occurs, when the root of my project tree is a symbolic link. I\u0027ve relocated my project to the source of the link, and everything is ok again (more or less, since I had to reconfigure some of my preferences).\n\nIf you have any other questions about how to reproduce that bug, feel free to ask. I\u0027m an eclipse newbie and I there\u0027s no way I could possibly know which information is relevant for you.\n\nHTH",
    "hmm, I am having trouble reproducing this one. I created a project with its root as a symbolic link as you described, and have not experienced the error.\n\nCan you still reproduce this error?\n\nIf so, can you outline the exact steps to produce it?\n\nIf you open the launch dialog can you view and edit the builder from 3.1?",
    "If you try this on 3.3M2 or later does the problem still occur?\nWe made changes to writeNewFile to address a synchronization issue much like the one you are describing (bug 153428).",
    "this is the same synchronization issue as 153428...marking as dupe\n\n*** This bug has been marked as a duplicate of 153428 ***"
  ],
  "commentCreationDates": [
    "2006-08-29T00:45:15+02:00",
    "2006-08-31T11:23:23+02:00",
    "2006-10-18T18:41:58+02:00",
    "2006-11-01T15:08:00+01:00",
    "2006-11-08T16:36:27+01:00"
  ],
  "traces": [
    {
      "exceptionType": "java.lang.NullPointerException",
      "elements": [
        {
          "method": "org.eclipse.debug.internal.core.LaunchConfigurationWorkingCopy.writeNewFile",
          "source": "LaunchConfigurationWorkingCopy.java:256"
        },
        {
          "method": "org.eclipse.debug.internal.core.LaunchConfigurationWorkingCopy.doSave0",
          "source": "LaunchConfigurationWorkingCopy.java:196"
        },
        {
          "method": "org.eclipse.debug.internal.core.LaunchConfigurationWorkingCopy.access$0",
          "source": "LaunchConfigurationWorkingCopy.java:182"
        },
        {
          "method": "org.eclipse.debug.internal.core.LaunchConfigurationWorkingCopy$1.run",
          "source": " LaunchConfigurationWorkingCopy.java:165"
        },
        {
          "method": "org.eclipse.core.internal.resources.Workspace.run",
          "source": "Workspace.java:1737 "
        },
        {
          "method": "org.eclipse.debug.internal.core.LaunchConfigurationWorkingCopy.doSave",
          "source": "LaunchConfigurationWorkingCopy.java:169"
        },
        {
          "method": "org.eclipse.ui.externaltools.internal.model.BuilderUtils.duplicateConfiguration",
          "source": "BuilderUtils.java:285"
        },
        {
          "method": "org.eclipse.ui.externaltools.internal.ui.BuilderPropertyPage.handleImportButtonPressed",
          "source": "BuilderPropertyPage.java:509"
        },
        {
          "method": "org.eclipse.ui.externaltools.internal.ui.BuilderPropertyPage.handleButtonPressed",
          "source": "BuilderPropertyPage.java:394"
        },
        {
          "method": "org.eclipse.ui.externaltools.internal.ui.BuilderPropertyPage.access$0",
          "source": "BuilderPropertyPage.java:390"
        },
        {
          "method": "org.eclipse.ui.externaltools.internal.ui.BuilderPropertyPage$1.widgetSelected",
          "source": "BuilderPropertyPage.java:129"
        },
        {
          "method": "org.eclipse.swt.widgets.TypedListener.handleEvent",
          "source": "TypedListener.java: 90"
        },
        {
          "method": "org.eclipse.swt.widgets.EventTable.sendEvent",
          "source": "EventTable.java:66"
        },
        {
          "method": "org.eclipse.swt.widgets.Widget.sendEvent",
          "source": "Widget.java:1085"
        },
        {
          "method": "org.eclipse.swt.widgets.Display.runDeferredEvents",
          "source": "Display.java:3164"
        },
        {
          "method": "org.eclipse.swt.widgets.Display.readAndDispatch",
          "source": "Display.java:2840"
        },
        {
          "method": "org.eclipse.jface.window.Window.runEventLoop",
          "source": "Window.java:820"
        },
        {
          "method": "org.eclipse.jface.window.Window.open",
          "source": "Window.java:796"
        },
        {
          "method": "org.eclipse.ui.dialogs.PropertyDialogAction.run",
          "source": "PropertyDialogAction. java:156"
        },
        {
          "method": "org.eclipse.ui.internal.ide.actions.ProjectPropertyDialogAction.run",
          "source": "P rojectPropertyDialogAction.java:77"
        },
        {
          "method": "org.eclipse.jface.action.Action.runWithEvent",
          "source": "Action.java:499"
        },
        {
          "method": "org.eclipse.jface.action.ActionContributionItem.handleWidgetSelection",
          "source": "ActionContributionItem.java:539"
        },
        {
          "method": "org.eclipse.jface.action.ActionContributionItem.access$2",
          "source": "ActionContri butionItem.java:488"
        },
        {
          "method": "org.eclipse.jface.action.ActionContributionItem$5.handleEvent",
          "source": "ActionC ontributionItem.java:400"
        },
        {
          "method": "org.eclipse.swt.widgets.EventTable.sendEvent",
          "source": "EventTable.java:66"
        },
        {
          "method": "org.eclipse.swt.widgets.Widget.sendEvent",
          "source": "Widget.java:1085"
        },
        {
          "method": "org.eclipse.swt.widgets.Display.runDeferredEvents",
          "source": "Display.java:3164"
        },
        {
          "method": "org.eclipse.swt.widgets.Display.readAndDispatch",
          "source": "Display.java:2840"
        },
        {
          "method": "org.eclipse.ui.internal.Workbench.runEventLoop",
          "source": "Workbench.java:1914"
        },
        {
          "method": "org.eclipse.ui.internal.Workbench.runUI",
          "source": "Workbench.java:1878"
        },
        {
          "method": "org.eclipse.ui.internal.Workbench.createAndRunWorkbench",
          "source": "Workbench.jav a:419"
        },
        {
          "method": "org.eclipse.ui.PlatformUI.createAndRunWorkbench",
          "source": "PlatformUI.java:149"
        },
        {
          "method": "org.eclipse.ui.internal.ide.IDEApplication.run",
          "source": "IDEApplication.java:95 "
        },
        {
          "method": "org.eclipse.core.internal.runtime.PlatformActivator$1.run",
          "source": "PlatformAct ivator.java:78"
        },
        {
          "method": "org.eclipse.core.runtime.internal.adaptor.EclipseAppLauncher.runApplication",
          "source": "EclipseAppLauncher.java:92"
        },
        {
          "method": "org.eclipse.core.runtime.internal.adaptor.EclipseAppLauncher.start",
          "source": "Ec lipseAppLauncher.java:68"
        },
        {
          "method": "org.eclipse.core.runtime.adaptor.EclipseStarter.run",
          "source": "EclipseStarter.ja va:400"
        },
        {
          "method": "org.eclipse.core.runtime.adaptor.EclipseStarter.run",
          "source": "EclipseStarter.ja va:177"
        },
        {
          "method": "sun.reflect.NativeMethodAccessorImpl.invoke0",
          "source": "Native Method"
        },
        {
          "method": "sun.reflect.NativeMethodAccessorImpl.invoke",
          "source": "NativeMethodAccessorImpl. java:39"
        },
        {
          "method": "sun.reflect.DelegatingMethodAccessorImpl.invoke",
          "source": "DelegatingMethodAcces sorImpl.java:25"
        },
        {
          "method": "java.lang.reflect.Method.invoke",
          "source": "Method.java:585"
        },
        {
          "method": "org.eclipse.core.launcher.Main.invokeFramework",
          "source": "Main.java:336"
        },
        {
          "method": "org.eclipse.core.launcher.Main.basicRun",
          "source": "Main.java:280"
        },
        {
          "method": "org.eclipse.core.launcher.Main.run",
          "source": "Main.java:977"
        },
        {
          "method": "org.eclipse.core.launcher.Main.main",
          "source": "Main.java:952"
        }
      ],
      "number": 0,
      "commentIndex": 0,
      "bugId": "155472",
      "duplicateId": "153428",
      "date": "2006-08-29T00:45:15+02:00",
      "product": "Platform",
      "component": "Debug",
      "severity": "normal"
    }
  ],
  "groupId": "153428",
  "bugId": "155472",
  "duplicateId": "153428",
  "date": "2006-08-29T00:45:15+02:00",
  "product": "Platform",
  "component": "Debug",
  "severity": "normal"
}