{
  "comments": [
    "To recreate:\n Prereq: Have a java project created in the workspace\n 1. File-\u003eNew-\u003eOther...\n 2. Select Dojo Application from the Dojo folder\n 3. Type in the name of the java project in the project field\n 4. Click finish\n \nThe Dojo Application wizard accepts project names typed in that are not present in the drop-down menu.  Also the following stack trace occurs:\njava.lang.NullPointerException\n\tat org.eclipse.atf.templates.operation.CreateFileOperation.execute(CreateFileOperation.java:80)\n\tat org.eclipse.atf.templates.ui.wizard.ModelDrivenWizard.performFinish(ModelDrivenWizard.java:51)\n\tat org.eclipse.atf.personality.dojo.ui.wizard.DojoApplicationWizard.performFinish(DojoApplicationWizard.java:71)",
    "The combo is read only and it will show faceted and PHP projects"
  ],
  "commentCreationDates": [
    "2006-09-07T16:46:04+02:00",
    "2006-09-07T22:50:33+02:00"
  ],
  "traces": [
    {
      "exceptionType": "java.lang.NullPointerException",
      "elements": [
        {
          "method": "org.eclipse.atf.templates.operation.CreateFileOperation.execute",
          "source": "CreateFileOperation.java:80"
        },
        {
          "method": "org.eclipse.atf.templates.ui.wizard.ModelDrivenWizard.performFinish",
          "source": "ModelDrivenWizard.java:51"
        },
        {
          "method": "org.eclipse.atf.personality.dojo.ui.wizard.DojoApplicationWizard.performFinish",
          "source": "DojoApplicationWizard.java:71"
        }
      ],
      "number": 0,
      "commentIndex": 0,
      "bugId": "156526",
      "date": "2006-09-07T16:46:04+02:00",
      "product": "ATF",
      "component": "personality",
      "severity": "normal"
    }
  ],
  "groupId": "156526",
  "bugId": "156526",
  "date": "2006-09-07T16:46:04+02:00",
  "product": "ATF",
  "component": "personality",
  "severity": "normal"
}