{
  "comments": [
    "To recreate:\n 1. File-\u003eNew-\u003eOther\n 2. Select Dojo Application from the Dojo folder\n 3. Delete the text from the Project field\n\nThe following error is logged:\njava.lang.IllegalArgumentException: Path for project must have only one segment.\n\tat org.eclipse.core.runtime.Assert.isLegal(Assert.java:62)\n\tat org.eclipse.core.internal.resources.WorkspaceRoot.getProject(WorkspaceRoot.java:164)\n\tat org.eclipse.atf.templates.variable.ProjectVariable.getProjectNamed(ProjectVariable.java:126)\n\tat org.eclipse.atf.templates.ui.variablerenderer.ProjectVariableRenderer$1.modifyText(ProjectVariableRenderer.java:66)\n\n\nThe call to getProject should probably have a check to make sure it is valid so that error does not show up.",
    "fixed by making the combo read only"
  ],
  "commentCreationDates": [
    "2006-09-07T16:40:22+02:00",
    "2006-09-07T22:49:22+02:00"
  ],
  "traces": [
    {
      "exceptionType": "java.lang.IllegalArgumentException",
      "message": "Path for project must have only one segment.",
      "elements": [
        {
          "method": "org.eclipse.core.runtime.Assert.isLegal",
          "source": "Assert.java:62"
        },
        {
          "method": "org.eclipse.core.internal.resources.WorkspaceRoot.getProject",
          "source": "WorkspaceRoot.java:164"
        },
        {
          "method": "org.eclipse.atf.templates.variable.ProjectVariable.getProjectNamed",
          "source": "ProjectVariable.java:126"
        },
        {
          "method": "org.eclipse.atf.templates.ui.variablerenderer.ProjectVariableRenderer$1.modifyText",
          "source": "ProjectVariableRenderer.java:66"
        }
      ],
      "number": 0,
      "commentIndex": 0,
      "bugId": "156524",
      "date": "2006-09-07T16:40:22+02:00",
      "product": "ATF",
      "component": "personality",
      "severity": "normal"
    }
  ],
  "groupId": "156524",
  "bugId": "156524",
  "date": "2006-09-07T16:40:22+02:00",
  "product": "ATF",
  "component": "personality",
  "severity": "normal"
}