{
  "comments": [
    "!SESSION 2006-09-07 15:00:22.244 -----------------------------------------------\neclipse.buildId\u003dM20050929-0840\njava.version\u003d1.5.0_04\njava.vendor\u003dSun Microsystems Inc.\nBootLoader constants: OS\u003dlinux, ARCH\u003dx86_64, WS\u003dgtk, NL\u003den_US\nCommand-line arguments:  -os linux -ws gtk -arch x86_64\n\n!ENTRY org.eclipse.osgi 2006-09-07 15:00:27.24\n!MESSAGE Application error\n!STACK 1\njava.lang.UnsatisfiedLinkError: /home/tony/software/eclipse/configuration/org.eclipse.osgi/bundles/55/1/.cp/libswt-pi-gtk-3139.so: /home/tony/software/eclipse/configuration/org.eclipse.osgi/bundles/55/1/.cp/libswt-pi-gtk-3139.so: cannot open shared object file: No such file or directory\n        at java.lang.ClassLoader$NativeLibrary.load(Native Method)\n        at java.lang.ClassLoader.loadLibrary0(ClassLoader.java:1751)\n        at java.lang.ClassLoader.loadLibrary(ClassLoader.java:1660)\n        at java.lang.Runtime.loadLibrary0(Runtime.java:822)\n        at java.lang.System.loadLibrary(System.java:992)\n        at org.eclipse.swt.internal.Library.loadLibrary(Library.java:123)\n        at org.eclipse.swt.internal.gtk.OS.\u003cclinit\u003e(OS.java:19)\n        at org.eclipse.swt.internal.Converter.wcsToMbcs(Converter.java:63)\n        at org.eclipse.swt.internal.Converter.wcsToMbcs(Converter.java:54)\n        at org.eclipse.swt.widgets.Display.\u003cclinit\u003e(Display.java:122)\n        at org.eclipse.ui.internal.Workbench.createDisplay(Workbench.java:381)\n        at org.eclipse.ui.PlatformUI.createDisplay(PlatformUI.java:155)\n        at org.eclipse.ui.internal.ide.IDEApplication.createDisplay(IDEApplication.java:128)\n        at org.eclipse.ui.internal.ide.IDEApplication.run(IDEApplication.java:79)\n        at org.eclipse.core.internal.runtime.PlatformActivator$1.run(PlatformActivator.java:226)\n        at org.eclipse.core.runtime.adaptor.EclipseStarter.run(EclipseStarter.java:376)\n        at org.eclipse.core.runtime.adaptor.EclipseStarter.run(EclipseStarter.java:163)\n        at sun.reflect.NativeMethodAccessorImpl.invoke0(Native Method)\n        at sun.reflect.NativeMethodAccessorImpl.invoke(NativeMethodAccessorImpl.java:39)\n        at sun.reflect.DelegatingMethodAccessorImpl.invoke(DelegatingMethodAccessorImpl.java:25)\n        at java.lang.reflect.Method.invoke(Method.java:585)\n        at org.eclipse.core.launcher.Main.invokeFramework(Main.java:334)\n        at org.eclipse.core.launcher.Main.basicRun(Main.java:278)\n        at org.eclipse.core.launcher.Main.run(Main.java:973)\n        at org.eclipse.core.launcher.Main.main(Main.java:948)\n!SESSION 2006-09-07 15:07:34.478 -----------------------------------------------\neclipse.buildId\u003dM20050929-0840\njava.version\u003d1.5.0_04\njava.vendor\u003dSun Microsystems Inc.\nBootLoader constants: OS\u003dlinux, ARCH\u003dx86_64, WS\u003dgtk, NL\u003den_US\nCommand-line arguments:  -os linux -ws gtk -arch x86_64\n\n!ENTRY org.eclipse.osgi 2006-09-07 15:07:36.537\n!MESSAGE Application error\n!STACK 1\njava.lang.UnsatisfiedLinkError: /home/tony/software/eclipse/configuration/org.eclipse.osgi/bundles/55/1/.cp/libswt-pi-gtk-3139.so: /home/tony/software/eclipse/configuration/org.eclipse.osgi/bundles/55/1/.cp/libswt-pi-gtk-3139.so: cannot open shared object file: No such file or directory\n        at java.lang.ClassLoader$NativeLibrary.load(Native Method)\n        at java.lang.ClassLoader.loadLibrary0(ClassLoader.java:1751)\n        at java.lang.ClassLoader.loadLibrary(ClassLoader.java:1660)\n        at java.lang.Runtime.loadLibrary0(Runtime.java:822)\n        at java.lang.System.loadLibrary(System.java:992)\n        at org.eclipse.swt.internal.Library.loadLibrary(Library.java:123)\n        at org.eclipse.swt.internal.gtk.OS.\u003cclinit\u003e(OS.java:19)\n        at org.eclipse.swt.internal.Converter.wcsToMbcs(Converter.java:63)\n        at org.eclipse.swt.internal.Converter.wcsToMbcs(Converter.java:54)\n        at org.eclipse.swt.widgets.Display.\u003cclinit\u003e(Display.java:122)\n        at org.eclipse.ui.internal.Workbench.createDisplay(Workbench.java:381)\n        at org.eclipse.ui.PlatformUI.createDisplay(PlatformUI.java:155)",
    "It looks like it\u0027s failing to load the gtk libraries.  Please confirm the following:\n\n- your linux distro has gtk+ \u003e\u003d 2.2 properly installed, and in a place where it will be found\n- your hardware and linux distro is 64-bit (if it\u0027s not then use a 32-bit eclipse release)\n- this still happens for you with a recent eclipse release such as 3.2 or 3.3M1, as the 3.1 stream is no longer active\n",
    "Closing this bug with a WORKSFORME. Tony, if you are still having problems, feel free to reopen this with the requested info attached. Thanks!"
  ],
  "commentCreationDates": [
    "2006-09-07T22:38:03+02:00",
    "2006-09-12T19:16:02+02:00",
    "2006-11-20T20:50:36+01:00"
  ],
  "traces": [
    {
      "exceptionType": "java.lang.UnsatisfiedLinkError",
      "message": "/home/tony/software/eclipse/configuration/org.eclipse.osgi/bundles/55/1/.cp/libswt-pi-gtk-3139.so: /home/tony/software/eclipse/configuration/org.eclipse.osgi/bundles/55/1/.cp/libswt-pi-gtk-3139.so: cannot open shared object file: No such file or directory",
      "elements": [
        {
          "method": "java.lang.ClassLoader$NativeLibrary.load",
          "source": "Native Method"
        },
        {
          "method": "java.lang.ClassLoader.loadLibrary0",
          "source": "ClassLoader.java:1751"
        },
        {
          "method": "java.lang.ClassLoader.loadLibrary",
          "source": "ClassLoader.java:1660"
        },
        {
          "method": "java.lang.Runtime.loadLibrary0",
          "source": "Runtime.java:822"
        },
        {
          "method": "java.lang.System.loadLibrary",
          "source": "System.java:992"
        },
        {
          "method": "org.eclipse.swt.internal.Library.loadLibrary",
          "source": "Library.java:123"
        },
        {
          "method": "org.eclipse.swt.internal.gtk.OS.\u003cclinit\u003e",
          "source": "OS.java:19"
        },
        {
          "method": "org.eclipse.swt.internal.Converter.wcsToMbcs",
          "source": "Converter.java:63"
        },
        {
          "method": "org.eclipse.swt.internal.Converter.wcsToMbcs",
          "source": "Converter.java:54"
        },
        {
          "method": "org.eclipse.swt.widgets.Display.\u003cclinit\u003e",
          "source": "Display.java:122"
        },
        {
          "method": "org.eclipse.ui.internal.Workbench.createDisplay",
          "source": "Workbench.java:381"
        },
        {
          "method": "org.eclipse.ui.PlatformUI.createDisplay",
          "source": "PlatformUI.java:155"
        },
        {
          "method": "org.eclipse.ui.internal.ide.IDEApplication.createDisplay",
          "source": "IDEApplication.java:128"
        },
        {
          "method": "org.eclipse.ui.internal.ide.IDEApplication.run",
          "source": "IDEApplication.java:79"
        },
        {
          "method": "org.eclipse.core.internal.runtime.PlatformActivator$1.run",
          "source": "PlatformActivator.java:226"
        },
        {
          "method": "org.eclipse.core.runtime.adaptor.EclipseStarter.run",
          "source": "EclipseStarter.java:376"
        },
        {
          "method": "org.eclipse.core.runtime.adaptor.EclipseStarter.run",
          "source": "EclipseStarter.java:163"
        },
        {
          "method": "sun.reflect.NativeMethodAccessorImpl.invoke0",
          "source": "Native Method"
        },
        {
          "method": "sun.reflect.NativeMethodAccessorImpl.invoke",
          "source": "NativeMethodAccessorImpl.java:39"
        },
        {
          "method": "sun.reflect.DelegatingMethodAccessorImpl.invoke",
          "source": "DelegatingMethodAccessorImpl.java:25"
        },
        {
          "method": "java.lang.reflect.Method.invoke",
          "source": "Method.java:585"
        },
        {
          "method": "org.eclipse.core.launcher.Main.invokeFramework",
          "source": "Main.java:334"
        },
        {
          "method": "org.eclipse.core.launcher.Main.basicRun",
          "source": "Main.java:278"
        },
        {
          "method": "org.eclipse.core.launcher.Main.run",
          "source": "Main.java:973"
        },
        {
          "method": "org.eclipse.core.launcher.Main.main",
          "source": "Main.java:948"
        }
      ],
      "number": 0,
      "commentIndex": 0,
      "bugId": "156602",
      "date": "2006-09-07T22:38:03+02:00",
      "product": "Platform",
      "component": "SWT",
      "severity": "normal"
    },
    {
      "exceptionType": "java.lang.UnsatisfiedLinkError",
      "message": "/home/tony/software/eclipse/configuration/org.eclipse.osgi/bundles/55/1/.cp/libswt-pi-gtk-3139.so: /home/tony/software/eclipse/configuration/org.eclipse.osgi/bundles/55/1/.cp/libswt-pi-gtk-3139.so: cannot open shared object file: No such file or directory",
      "elements": [
        {
          "method": "java.lang.ClassLoader$NativeLibrary.load",
          "source": "Native Method"
        },
        {
          "method": "java.lang.ClassLoader.loadLibrary0",
          "source": "ClassLoader.java:1751"
        },
        {
          "method": "java.lang.ClassLoader.loadLibrary",
          "source": "ClassLoader.java:1660"
        },
        {
          "method": "java.lang.Runtime.loadLibrary0",
          "source": "Runtime.java:822"
        },
        {
          "method": "java.lang.System.loadLibrary",
          "source": "System.java:992"
        },
        {
          "method": "org.eclipse.swt.internal.Library.loadLibrary",
          "source": "Library.java:123"
        },
        {
          "method": "org.eclipse.swt.internal.gtk.OS.\u003cclinit\u003e",
          "source": "OS.java:19"
        },
        {
          "method": "org.eclipse.swt.internal.Converter.wcsToMbcs",
          "source": "Converter.java:63"
        },
        {
          "method": "org.eclipse.swt.internal.Converter.wcsToMbcs",
          "source": "Converter.java:54"
        },
        {
          "method": "org.eclipse.swt.widgets.Display.\u003cclinit\u003e",
          "source": "Display.java:122"
        },
        {
          "method": "org.eclipse.ui.internal.Workbench.createDisplay",
          "source": "Workbench.java:381"
        },
        {
          "method": "org.eclipse.ui.PlatformUI.createDisplay",
          "source": "PlatformUI.java:155"
        }
      ],
      "number": 1,
      "commentIndex": 0,
      "bugId": "156602",
      "date": "2006-09-07T22:38:03+02:00",
      "product": "Platform",
      "component": "SWT",
      "severity": "normal"
    }
  ],
  "groupId": "156602",
  "bugId": "156602",
  "date": "2006-09-07T22:38:03+02:00",
  "product": "Platform",
  "component": "SWT",
  "severity": "normal"
}