{
  "comments": [
    "On Suse 7.3 with Eclipse SDK GTK2 M5 build, and with 20020509 nightly build.\n\nIn the first run of Eclipse help does not work (help action does not launch \nMozilla, F1 does not work, help preference page does not display), and messages \nin the console say that org.eclipse.help.ui plugin is deactivated.\n\nOn the subsequent runs of Eclipse, problem does not occur.",
    "Please attach the log file with the messages.\nThanks.",
    "The .log:\n\n!SESSION ----------------------------------------------------------------------\njava.fullversion\u003dJ2RE 1.3.0 IBM build cx130-20010925 (JIT enabled: jitc)\nBootLoader constants: OS\u003dlinux, ARCH\u003dx86, WS\u003dmotif, NL\u003den_US\nCommand-line arguments: -ws motif -install file:/home/eclipse/eclipse/\n!ENTRY org.eclipse.core.runtime 2 2 !ENTRY org.eclipse.core.resources 1 4 !ENTRY\norg.eclipse.ui 4 0 !ENTRY org.eclipse.core.resources 1 4 !ENTRY org.eclipse.ui 4\n1 !ENTRY org.eclipse.core.runtime 2 2 !ENTRY org.eclipse.core.runtime 2 2 ",
    "The console:\n\neclipse@help2:~/eclipse\u003e ./eclipse\nAn exception occurred while writing to the platform log:\njava.lang.NullPointerException: null\nLogging to the console instead.\nAn exception occurred while logging to the console:\njava.lang.NullPointerException: null\nAn exception occurred while writing to the platform log:\njava.lang.NullPointerException: null\nLogging to the console instead.\nAn exception occurred while logging to the console:\njava.lang.NullPointerException: null\nUnhandled exception caught in event loop.\nReason:\nAn exception occurred while writing to the platform log:\njava.lang.NullPointerException: null\nLogging to the console instead.\nAn exception occurred while logging to the console:\njava.lang.NullPointerException: null\nPlugin org.eclipse.help.ui activation failed while loading class\norg.eclipse.help.internal.ui.HelpContentsAction\norg.eclipse.core.internal.boot.DelegatingURLClassLoader$DelegatingLoaderException:\nAttempt to load class org.eclipse.help.internal.ui.util.WorkbenchResources from\ndeactivated plug-in org.eclipse.help.ui.\n        at\norg.eclipse.core.internal.plugins.PluginClassLoader.shouldLookForClass(PluginClassLoader.java:200)\n        at\norg.eclipse.core.internal.plugins.PluginClassLoader.findClassParentsSelf(PluginClassLoader.java(Compiled\nCode))\n        at\norg.eclipse.core.internal.boot.DelegatingURLClassLoader.loadClass(DelegatingURLClassLoader.java(Compiled\nCode))\n        at\norg.eclipse.core.internal.boot.DelegatingURLClassLoader.loadClass(DelegatingURLClassLoader.java(Compiled\nCode))\n        at java.lang.ClassLoader.loadClass(ClassLoader.java(Compiled Code))\n        at\norg.eclipse.help.internal.ui.util.StreamConsumer.run(StreamConsumer.java:23)\nAn exception occurred while writing to the platform log:\njava.lang.NullPointerException: null\nLogging to the console instead.\nAn exception occurred while logging to the console:\njava.lang.NullPointerException: null\nProblems saving workspace\nReason:\nAn exception occurred while writing to the platform log:\njava.lang.NullPointerException: null\nLogging to the console instead.\nAn exception occurred while logging to the console:\njava.lang.NullPointerException: null\nProblems occurred while trying to save the state of the workbench.\nAn exception occurred while writing to the platform log:\njava.lang.NullPointerException: null\nLogging to the console instead.\nAn exception occurred while logging to the console:\njava.lang.NullPointerException: null\nAn exception occurred while writing to the platform log:\njava.lang.NullPointerException: null\nLogging to the console instead.\nAn exception occurred while logging to the console:\njava.lang.NullPointerException: null\nException launching the Eclipse Platform:\njava.lang.reflect.InvocationTargetException: java.lang.NullPointerException\n        at\njava.text.resources.DateFormatZoneData.getContents(DateFormatZoneData.java:129)\n        at\njava.text.resources.DateFormatZoneData.loadLookup(DateFormatZoneData.java:111)\n        at\njava.text.resources.DateFormatZoneData.getKeys(DateFormatZoneData.java:70)\n        at\njava.text.resources.DateFormatZoneData.getKeys(DateFormatZoneData.java:75)\n        at java.text.DateFormatSymbols.loadZoneStrings(DateFormatSymbols.java:450)\n        at java.text.DateFormatSymbols.initializeData(DateFormatSymbols.java:490)\n        at java.text.DateFormatSymbols.\u003cinit\u003e(DateFormatSymbols.java:92)\n        at java.text.SimpleDateFormat.\u003cinit\u003e(SimpleDateFormat.java:279)\n        at java.util.Date.toString(Date.java:1003)\n        at\norg.eclipse.core.internal.boot.PlatformConfiguration.write(PlatformConfiguration.java:2188)\n        at\norg.eclipse.core.internal.boot.PlatformConfiguration.save(PlatformConfiguration.java:1199)\n        at\norg.eclipse.core.internal.boot.PlatformConfiguration.save(PlatformConfiguration.java:1171)\n        at\norg.eclipse.core.internal.boot.PlatformConfiguration.shutdown(PlatformConfiguration.java:1278)\n        at\norg.eclipse.core.internal.boot.InternalBootLoader.shutdown(InternalBootLoader.java:839)\n        at\norg.eclipse.core.internal.boot.InternalBootLoader.run(InternalBootLoader.java:744)\n        at org.eclipse.core.boot.BootLoader.run(BootLoader.java:450)\n        at java.lang.reflect.Method.invoke(Native Method)\n        at org.eclipse.core.launcher.Main.basicRun(Main.java:174)\n        at org.eclipse.core.launcher.Main.run(Main.java:605)\n        at org.eclipse.core.launcher.Main.main(Main.java:449)\neclipse@help2:~/eclipse\u003e",
    "Which build are you running....motif or gtk?\nThe OS selection in the bug report and the .log indicate motif but your initial\nreport says GTK.\n\nI am able to startup ok and run help on both the motif and gtk 0509 nightly\nbuilds on RH7.2. Will try and reproduce the problem on Suse.",
    "I ran GTK build on Suse.  Changing OS field to Linux-GTK.",
    "The .log that you included was from a Linux-Motif run. Was the log from the \nGTK run the same? Thanks.",
    "I see 2 problems here:\n\n1). There was an NPE in calling (new Date().toString()) in the \nPlatformConfiguration.write method.\n\n2). There was an NPE when writing to the platform log and console. Maybe in \nthe same (new Date().toString()) call as above?\n\nWhat happens on your machine when you do a new Date().toString() in a \nscrapbook page? Does it work?\n\nI have modified the log writer to print stack traces rather than just \nclass/messages of problems when writing to log file (in case console writing \nfails too)",
    "There was a bit of mess on our test machine:  The driver installed was the\n20020509 motif (not GTK) nightly.\nWith this driver the Scrappbook does not work, there were errors in the workbench.\nDate().toString() worked O.K. when I tried running a Test program from the\ncommand line.\nUpgraded jdk to IBM1.3.1, this had no effect on how Eclipse run.\n\nI have tried the same with the 20020510 motif integration build.  Works like a\ncharm.\n\nSo the bug is not really valid anymore if510 driver has later code than 509\nnightly.  Feel free to close the bug.  Thanks.\n\nI cannot try gtk build 20020510, it complains that cannot find swt library, but\nit is a different problem I suppose.\n\n",
    "Closing bug at originator\u0027s request.\n\nFixed log file so it better reports errors writing to console/log.\nAlso fixed it so not being able to print out the Date doesn\u0027t kill it.\nCore ready to be reviewed and released."
  ],
  "commentCreationDates": [
    "2002-05-09T22:39:37+02:00",
    "2002-05-10T00:43:52+02:00",
    "2002-05-10T01:05:33+02:00",
    "2002-05-10T01:07:21+02:00",
    "2002-05-10T17:48:48+02:00",
    "2002-05-10T17:54:19+02:00",
    "2002-05-10T18:19:48+02:00",
    "2002-05-10T18:46:32+02:00",
    "2002-05-10T20:41:19+02:00",
    "2002-05-10T21:17:36+02:00"
  ],
  "traces": [
    {
      "exceptionType": "org.eclipse.core.internal.boot.DelegatingURLClassLoader$DelegatingLoaderException",
      "message": "Attempt to load class org.eclipse.help.internal.ui.util.WorkbenchResources from deactivated plug-in org.eclipse.help.ui.",
      "elements": [
        {
          "method": "org.eclipse.core.internal.plugins.PluginClassLoader.shouldLookForClass",
          "source": "PluginClassLoader.java:200"
        },
        {
          "method": "org.eclipse.core.internal.plugins.PluginClassLoader.findClassParentsSelf",
          "source": "PluginClassLoader.java(Compiled Code)"
        },
        {
          "method": "org.eclipse.core.internal.boot.DelegatingURLClassLoader.loadClass",
          "source": "DelegatingURLClassLoader.java(Compiled Code)"
        },
        {
          "method": "org.eclipse.core.internal.boot.DelegatingURLClassLoader.loadClass",
          "source": "DelegatingURLClassLoader.java(Compiled Code)"
        },
        {
          "method": "java.lang.ClassLoader.loadClass",
          "source": "ClassLoader.java(Compiled Code)"
        },
        {
          "method": "org.eclipse.help.internal.ui.util.StreamConsumer.run",
          "source": "StreamConsumer.java:23"
        }
      ],
      "number": 0,
      "commentIndex": 3,
      "bugId": "15676",
      "date": "2002-05-10T01:07:21+02:00",
      "product": "Platform",
      "component": "Resources",
      "severity": "normal"
    },
    {
      "exceptionType": "java.lang.NullPointerException",
      "elements": [
        {
          "method": "java.text.resources.DateFormatZoneData.getContents",
          "source": "DateFormatZoneData.java:129"
        },
        {
          "method": "java.text.resources.DateFormatZoneData.loadLookup",
          "source": "DateFormatZoneData.java:111"
        },
        {
          "method": "java.text.resources.DateFormatZoneData.getKeys",
          "source": "DateFormatZoneData.java:70"
        },
        {
          "method": "java.text.resources.DateFormatZoneData.getKeys",
          "source": "DateFormatZoneData.java:75"
        },
        {
          "method": "java.text.DateFormatSymbols.loadZoneStrings",
          "source": "DateFormatSymbols.java:450"
        },
        {
          "method": "java.text.DateFormatSymbols.initializeData",
          "source": "DateFormatSymbols.java:490"
        },
        {
          "method": "java.text.DateFormatSymbols.\u003cinit\u003e",
          "source": "DateFormatSymbols.java:92"
        },
        {
          "method": "java.text.SimpleDateFormat.\u003cinit\u003e",
          "source": "SimpleDateFormat.java:279"
        },
        {
          "method": "java.util.Date.toString",
          "source": "Date.java:1003"
        },
        {
          "method": "org.eclipse.core.internal.boot.PlatformConfiguration.write",
          "source": "PlatformConfiguration.java:2188"
        },
        {
          "method": "org.eclipse.core.internal.boot.PlatformConfiguration.save",
          "source": "PlatformConfiguration.java:1199"
        },
        {
          "method": "org.eclipse.core.internal.boot.PlatformConfiguration.save",
          "source": "PlatformConfiguration.java:1171"
        },
        {
          "method": "org.eclipse.core.internal.boot.PlatformConfiguration.shutdown",
          "source": "PlatformConfiguration.java:1278"
        },
        {
          "method": "org.eclipse.core.internal.boot.InternalBootLoader.shutdown",
          "source": "InternalBootLoader.java:839"
        },
        {
          "method": "org.eclipse.core.internal.boot.InternalBootLoader.run",
          "source": "InternalBootLoader.java:744"
        },
        {
          "method": "org.eclipse.core.boot.BootLoader.run",
          "source": "BootLoader.java:450"
        },
        {
          "method": "java.lang.reflect.Method.invoke",
          "source": "Native Method"
        },
        {
          "method": "org.eclipse.core.launcher.Main.basicRun",
          "source": "Main.java:174"
        },
        {
          "method": "org.eclipse.core.launcher.Main.run",
          "source": "Main.java:605"
        },
        {
          "method": "org.eclipse.core.launcher.Main.main",
          "source": "Main.java:449"
        }
      ],
      "number": 1,
      "commentIndex": 3,
      "bugId": "15676",
      "date": "2002-05-10T01:07:21+02:00",
      "product": "Platform",
      "component": "Resources",
      "severity": "normal"
    }
  ],
  "groupId": "15676",
  "bugId": "15676",
  "date": "2002-05-09T22:39:37+02:00",
  "product": "Platform",
  "component": "Resources",
  "severity": "normal"
}