{
  "comments": [
    "Create new server and configuration. Start it and stop it. Close the workbench. \ncheck log.\n\n!MESSAGE Problems occurred when invoking code from plug-in: \norg.eclipse.core.runtime.\n!STACK java.lang.NullPointerException\n        at \norg.eclipse.debug.internal.ui.DebugUIPlugin.setNewAttributes(DebugUIPlugin.java:\n1181)\n        at \norg.eclipse.debug.internal.ui.DebugUIPlugin.setAttributes(DebugUIPlugin.java:117\n0)\n        at \norg.eclipse.debug.internal.ui.DebugUIPlugin.getHistoryEntryAsXMLElement(DebugUIP\nlugin.java:1158)\n        at \norg.eclipse.debug.internal.ui.DebugUIPlugin.getHistoryAsXML(DebugUIPlugin.java:1\n136)\n        at \norg.eclipse.debug.internal.ui.DebugUIPlugin.persistLaunchHistory(DebugUIPlugin.j\nava:1214)\n        at \norg.eclipse.debug.internal.ui.DebugUIPlugin.shutdown(DebugUIPlugin.java:380)\n        at \norg.eclipse.core.internal.plugins.PluginRegistry$2.run(PluginRegistry.java:268)\n        at \norg.eclipse.core.internal.runtime.InternalPlatform.run(InternalPlatform.java(Com\npiled Code))\n        at \norg.eclipse.core.internal.plugins.PluginRegistry$1.visit(PluginRegistry.java:281\n)\n        at \norg.eclipse.core.internal.plugins.PluginRegistry.accept(PluginRegistry.java:45)\n        at \norg.eclipse.core.internal.plugins.PluginRegistry.shutdownPlugins(PluginRegistry.\njava:284)\n        at \norg.eclipse.core.internal.plugins.PluginRegistry.shutdown(PluginRegistry.java:25\n0)\n        at \norg.eclipse.core.internal.runtime.InternalPlatform.loaderShutdown(InternalPlatfo\nrm.java:531)\n        at java.lang.reflect.Method.invoke(Native Method)\n        at \norg.eclipse.core.internal.boot.InternalBootLoader.shutdown(InternalBootLoader.ja\nva:859)\n        at \norg.eclipse.core.internal.boot.InternalBootLoader.run(InternalBootLoader.java:78\n2)\n        at org.eclipse.core.boot.BootLoader.run(BootLoader.java:319)\n        at java.lang.reflect.Method.invoke(Native Method)\n        at org.eclipse.core.launcher.Main.basicRun(Main.java:190)\n        at org.eclipse.core.launcher.Main.run(Main.java:549)\n        at org.eclipse.core.launcher.Main.main(Main.java:390)",
    "Please indicate which build you were running.",
    "I was running WSAD V5 Preview version 4.8.1 \"refresh\" (aka reBayta).",
    "This is a duplicate that has been fixed, but I can\u0027t find the original bug \nyet...",
    "I believe you\u0027re talking about Bug 14877.",
    "\n\n*** This bug has been marked as a duplicate of 14877 ***"
  ],
  "commentCreationDates": [
    "2002-05-13T13:26:34+02:00",
    "2002-05-13T14:46:28+02:00",
    "2002-05-13T14:48:49+02:00",
    "2002-05-13T15:41:05+02:00",
    "2002-05-13T17:52:15+02:00",
    "2002-05-14T05:43:29+02:00"
  ],
  "traces": [
    {
      "exceptionType": "java.lang.NullPointerException",
      "elements": [
        {
          "method": "org.eclipse.debug.internal.ui.DebugUIPlugin.setNewAttributes",
          "source": "DebugUIPlugin.java: 1181"
        },
        {
          "method": "org.eclipse.debug.internal.ui.DebugUIPlugin.setAttributes",
          "source": "DebugUIPlugin.java:117 0"
        },
        {
          "method": "org.eclipse.debug.internal.ui.DebugUIPlugin.getHistoryEntryAsXMLElement",
          "source": "DebugUIP lugin.java:1158"
        },
        {
          "method": "org.eclipse.debug.internal.ui.DebugUIPlugin.getHistoryAsXML",
          "source": "DebugUIPlugin.java:1 136"
        },
        {
          "method": "org.eclipse.debug.internal.ui.DebugUIPlugin.persistLaunchHistory",
          "source": "DebugUIPlugin.j ava:1214"
        },
        {
          "method": "org.eclipse.debug.internal.ui.DebugUIPlugin.shutdown",
          "source": "DebugUIPlugin.java:380"
        },
        {
          "method": "org.eclipse.core.internal.plugins.PluginRegistry$2.run",
          "source": "PluginRegistry.java:268"
        },
        {
          "method": "org.eclipse.core.internal.runtime.InternalPlatform.run",
          "source": "InternalPlatform.java(Com piled Code)"
        },
        {
          "method": "org.eclipse.core.internal.plugins.PluginRegistry$1.visit",
          "source": "PluginRegistry.java:281 "
        },
        {
          "method": "org.eclipse.core.internal.plugins.PluginRegistry.accept",
          "source": "PluginRegistry.java:45"
        },
        {
          "method": "org.eclipse.core.internal.plugins.PluginRegistry.shutdownPlugins",
          "source": "PluginRegistry. java:284"
        },
        {
          "method": "org.eclipse.core.internal.plugins.PluginRegistry.shutdown",
          "source": "PluginRegistry.java:25 0"
        },
        {
          "method": "org.eclipse.core.internal.runtime.InternalPlatform.loaderShutdown",
          "source": "InternalPlatfo rm.java:531"
        },
        {
          "method": "java.lang.reflect.Method.invoke",
          "source": "Native Method"
        },
        {
          "method": "org.eclipse.core.internal.boot.InternalBootLoader.shutdown",
          "source": "InternalBootLoader.ja va:859"
        },
        {
          "method": "org.eclipse.core.internal.boot.InternalBootLoader.run",
          "source": "InternalBootLoader.java:78 2"
        },
        {
          "method": "org.eclipse.core.boot.BootLoader.run",
          "source": "BootLoader.java:319"
        },
        {
          "method": "java.lang.reflect.Method.invoke",
          "source": "Native Method"
        },
        {
          "method": "org.eclipse.core.launcher.Main.basicRun",
          "source": "Main.java:190"
        },
        {
          "method": "org.eclipse.core.launcher.Main.run",
          "source": "Main.java:549"
        },
        {
          "method": "org.eclipse.core.launcher.Main.main",
          "source": "Main.java:390"
        }
      ],
      "number": 0,
      "commentIndex": 0,
      "bugId": "15842",
      "duplicateId": "14877",
      "date": "2002-05-13T13:26:34+02:00",
      "product": "Platform",
      "component": "Debug",
      "severity": "normal"
    }
  ],
  "groupId": "14877",
  "bugId": "15842",
  "duplicateId": "14877",
  "date": "2002-05-13T13:26:34+02:00",
  "product": "Platform",
  "component": "Debug",
  "severity": "normal"
}