{
  "comments": [
    "New \u003e Project \u003e General \u003e Project\ndeselect default location, select RSE EFS\nRemote location on ssh-unix/My Home/RSETest/remote\n  --\u003e 3 files are already in this folder\nProject is created. Dbl click on a text file --\u003e it loads in editor\nChange the file and Save\n--\u003e Exception is thrown:\n\njava.lang.IllegalArgumentException: Attempted to beginRule: F/RemoteSystemsTempF\niles/LOCALHOST/folk/mober/cdt-remote-rsefs, does not match outer scope rule: L/c\ndt-remote-rsefs/test.txt\n        at org.eclipse.core.runtime.Assert.isLegal(Assert.java:62)\n        at org.eclipse.core.internal.jobs.ThreadJob.illegalPush(ThreadJob.java:1\n16)\n        at org.eclipse.core.internal.jobs.ThreadJob.push(ThreadJob.java:225)\n        at org.eclipse.core.internal.jobs.ImplicitJobs.begin(ImplicitJobs.java:5\n8)\n        at org.eclipse.core.internal.jobs.JobManager.beginRule(JobManager.java:2\n19)\n        at org.eclipse.core.internal.resources.WorkManager.checkIn(WorkManager.j\nava:96)\n        at org.eclipse.core.internal.resources.Workspace.prepareOperation(Worksp\nace.java:1684)\n        at org.eclipse.core.internal.resources.Resource.refreshLocal(Resource.ja\nva:1392)\n        at org.eclipse.core.internal.resources.File.refreshLocal(File.java:334)\n        at org.eclipse.rse.eclipse.filesystem.RSEFileStoreRemoteFileWrapper.open\nInputStream(RSEFileStoreRemoteFileWrapper.java:245)\n        at org.eclipse.core.internal.localstore.FileSystemResourceManager.read(F\nileSystemResourceManager.java:609)\n        at org.eclipse.core.internal.resources.File.getContents(File.java:290)\n        at org.eclipse.core.internal.resources.File.getContents(File.java:279)\n        at org.eclipse.ui.internal.editors.quickdiff.LastSaveReferenceProvider.s\netDocumentContent(LastSaveReferenceProvider.java:367)\n        at org.eclipse.ui.internal.editors.quickdiff.LastSaveReferenceProvider.r\neadDocument(LastSaveReferenceProvider.java:252)\n        at org.eclipse.ui.internal.editors.quickdiff.LastSaveReferenceProvider.a\nccess$0(LastSaveReferenceProvider.java:203)\n        at org.eclipse.ui.internal.editors.quickdiff.LastSaveReferenceProvider$R\neadJob.run(LastSaveReferenceProvider.java:113)\n        at org.eclipse.core.internal.jobs.Worker.run(Worker.java:58)\n\n-----------Enter bugs above this line-----------\nRSE 1.0 Testing round 1\ninstallation : eclipse-platform-3.3M2 (I20060922-0010)\nRSE install  : download rse-runtime-core,dstore,local,ssh\njava.runtime : Sun 1.5.0_06-b05\nos.name:     : Red Hat Enterprise Linux WS release 4 (Nahant Update 3)\n------------------------------------------------\nsystemtype   : Dstore-windows, Linux-local, Ssh\ntargetos     : Windows XP SP2, and others\ntargetuname  : Windows\ntargetvm     : Sun 1.5.0_08-b03\n------------------------------------------------",
    "\n\n*** This bug has been marked as a duplicate of bug 170916 ***"
  ],
  "commentCreationDates": [
    "2006-09-26T17:09:32+02:00",
    "2007-01-31T10:53:53+01:00"
  ],
  "traces": [
    {
      "exceptionType": "java.lang.IllegalArgumentException",
      "message": "Attempted to beginRule: F/RemoteSystemsTempF iles/LOCALHOST/folk/mober/cdt-remote-rsefs, does not match outer scope rule: L/c dt-remote-rsefs/test.txt",
      "elements": [
        {
          "method": "org.eclipse.core.runtime.Assert.isLegal",
          "source": "Assert.java:62"
        },
        {
          "method": "org.eclipse.core.internal.jobs.ThreadJob.illegalPush",
          "source": "ThreadJob.java:1 16"
        },
        {
          "method": "org.eclipse.core.internal.jobs.ThreadJob.push",
          "source": "ThreadJob.java:225"
        },
        {
          "method": "org.eclipse.core.internal.jobs.ImplicitJobs.begin",
          "source": "ImplicitJobs.java:5 8"
        },
        {
          "method": "org.eclipse.core.internal.jobs.JobManager.beginRule",
          "source": "JobManager.java:2 19"
        },
        {
          "method": "org.eclipse.core.internal.resources.WorkManager.checkIn",
          "source": "WorkManager.j ava:96"
        },
        {
          "method": "org.eclipse.core.internal.resources.Workspace.prepareOperation",
          "source": "Worksp ace.java:1684"
        },
        {
          "method": "org.eclipse.core.internal.resources.Resource.refreshLocal",
          "source": "Resource.ja va:1392"
        },
        {
          "method": "org.eclipse.core.internal.resources.File.refreshLocal",
          "source": "File.java:334"
        },
        {
          "method": "org.eclipse.rse.eclipse.filesystem.RSEFileStoreRemoteFileWrapper.openInputStream",
          "source": "RSEFileStoreRemoteFileWrapper.java:245"
        },
        {
          "method": "org.eclipse.core.internal.localstore.FileSystemResourceManager.read",
          "source": "F ileSystemResourceManager.java:609"
        },
        {
          "method": "org.eclipse.core.internal.resources.File.getContents",
          "source": "File.java:290"
        },
        {
          "method": "org.eclipse.core.internal.resources.File.getContents",
          "source": "File.java:279"
        },
        {
          "method": "org.eclipse.ui.internal.editors.quickdiff.LastSaveReferenceProvider.setDocumentContent",
          "source": "LastSaveReferenceProvider.java:367"
        },
        {
          "method": "org.eclipse.ui.internal.editors.quickdiff.LastSaveReferenceProvider.readDocument",
          "source": "LastSaveReferenceProvider.java:252"
        },
        {
          "method": "org.eclipse.ui.internal.editors.quickdiff.LastSaveReferenceProvider.access$0",
          "source": "LastSaveReferenceProvider.java:203"
        },
        {
          "method": "org.eclipse.ui.internal.editors.quickdiff.LastSaveReferenceProvider$ReadJob.run",
          "source": "LastSaveReferenceProvider.java:113"
        },
        {
          "method": "org.eclipse.core.internal.jobs.Worker.run",
          "source": "Worker.java:58"
        }
      ],
      "number": 0,
      "commentIndex": 0,
      "bugId": "158773",
      "duplicateId": "170916",
      "date": "2006-09-26T17:09:32+02:00",
      "product": "Target Management",
      "component": "RSE",
      "severity": "normal"
    }
  ],
  "groupId": "170916",
  "bugId": "158773",
  "duplicateId": "170916",
  "date": "2006-09-26T17:09:32+02:00",
  "product": "Target Management",
  "component": "RSE",
  "severity": "normal"
}