{
  "comments": [
    "Go to servers tab on j2ee perspective, and select New-\u003eserver, you get the following dialog and wizard does not come up.  Run on server also does nothing.  I simply started new workspace, did an ear creation with all default modules targetted to generic WAS, then went to server tab and tried to create a server.  Got the error.\n\n!ENTRY org.eclipse.ui 4 0 2006-10-06 12:55:39.073\n!MESSAGE Array index out of range: 1\n!STACK 0\njava.lang.ArrayIndexOutOfBoundsException: Array index out of range: 1\n        at org.eclipse.wst.server.ui.internal.wizard.page.ModifyModulesComposite\n.setServer(ModifyModulesComposite.java:329)\n        at org.eclipse.wst.server.ui.internal.wizard.fragment.ModifyModulesWizar\ndFragment.updateModules(ModifyModulesWizardFragment.java:73)\n        at org.eclipse.wst.server.ui.internal.wizard.fragment.ModifyModulesWizar\ndFragment.getChildFragments(ModifyModulesWizardFragment.java:62)\n        at org.eclipse.wst.server.ui.internal.wizard.TaskWizard.addSubWizardFrag\nments(TaskWizard.java:313)\n        at org.eclipse.wst.server.ui.internal.wizard.TaskWizard.addSubWizardFrag\nments(TaskWizard.java:317)\n        at org.eclipse.wst.server.ui.internal.wizard.TaskWizard.getAllWizardFrag\nments(TaskWizard.java:301)\n        at org.eclipse.wst.server.ui.internal.wizard.TaskWizard.switchWizardFrag\nment(TaskWizard.java:266)\n        at org.eclipse.wst.server.ui.internal.wizard.TaskWizardPage.setVisible(T\naskWizardPage.java:93)\n        at org.eclipse.jface.wizard.WizardDialog.showStartingPage(WizardDialog.j\nava:1083)\n        at org.eclipse.jface.wizard.WizardDialog.createContents(WizardDialog.jav\na:504)\n        at org.eclipse.jface.window.Window.create(Window.java:426)\n        at org.eclipse.jface.dialogs.Dialog.create(Dialog.java:1124)\n        at org.eclipse.jface.window.Window.open(Window.java:785)\n        at org.eclipse.wst.server.ui.internal.actions.LaunchWizardAction.run(Lau\nnchWizardAction.java:57)\n        at org.eclipse.jface.action.Action.runWithEvent(Action.java:499)\n        at org.eclipse.jface.action.ActionContributionItem.handleWidgetSelection\n(ActionContributionItem.java:539)\n        at org.eclipse.jface.action.ActionContributionItem.access$2(ActionContri\nbutionItem.java:488)\n        at org.eclipse.jface.action.ActionContributionItem$5.handleEvent(ActionC\nontributionItem.java:400)\n        at org.eclipse.swt.widgets.EventTable.sendEvent(EventTable.java:66)\n        at org.eclipse.swt.widgets.Widget.sendEvent(Widget.java:928)\n        at org.eclipse.swt.widgets.Display.runDeferredEvents(Display.java:3348)\n        at org.eclipse.swt.widgets.Display.readAndDispatch(Display.java:2968)\n        at org.eclipse.ui.internal.Workbench.runEventLoop(Workbench.java:1914)\n        at org.eclipse.ui.internal.Workbench.runUI(Workbench.java:1878)\n        at org.eclipse.ui.internal.Workbench.createAndRunWorkbench(Workbench.jav\na:419)\n        at org.eclipse.ui.PlatformUI.createAndRunWorkbench(PlatformUI.java:149)\n        at org.eclipse.ui.internal.ide.IDEApplication.run(IDEApplication.java:95\n)\n        at org.eclipse.core.internal.runtime.PlatformActivator$1.run(PlatformAct\nivator.java:78)\n        at org.eclipse.core.runtime.internal.adaptor.EclipseAppLauncher.runAppli\ncation(EclipseAppLauncher.java:92)\n        at org.eclipse.core.runtime.internal.adaptor.EclipseAppLauncher.start(Ec\nlipseAppLauncher.java:68)\n        at org.eclipse.core.runtime.adaptor.EclipseStarter.run(EclipseStarter.ja\nva:400)\n        at org.eclipse.core.runtime.adaptor.EclipseStarter.run(EclipseStarter.ja\nva:177)\n        at sun.reflect.NativeMethodAccessorImpl.invoke0(Native Method)\n        at sun.reflect.NativeMethodAccessorImpl.invoke(NativeMethodAccessorImpl.\njava:64)\n        at sun.reflect.DelegatingMethodAccessorImpl.invoke(DelegatingMethodAcces\nsorImpl.java:43)\n        at java.lang.reflect.Method.invoke(Method.java:615)\n        at org.eclipse.core.launcher.Main.invokeFramework(Main.java:336)\n        at org.eclipse.core.launcher.Main.basicRun(Main.java:280)\n        at org.eclipse.core.launcher.Main.run(Main.java:977)\n        at org.eclipse.core.launcher.Main.main(Main.java:952)",
    "If I delete all my projects, I can then create a server.  If I create modules without an EAR I can create a server.  However, if I have an EAR, the dialog fails to come up.  This was on today\u0027s 0213 AM build, I am trying with the new build with your fix for the junit, don\u0027t know if its related?",
    "Same problem appears on http://download.eclipse.org/webtools/committers/drops/R1.5/M-1.5.2-200610061513/\n\nIt seems to be if you have an EAR project, it fails with the stacktrace.",
    "*** Bug 160054 has been marked as a duplicate of this bug. ***",
    "Sorry, I missed the bad array size in my code and managed to somehow test only on workspaces that wouldn\u0027t hit this scenario. That was my first mistake...\n\nMistake #2, PMC review missed catching it.\n\nMistake #3, I listened to the PMC ;-) when they had an issue with my try/catch block and I narrowed it, exposing the new exception.\n\nI\u0027ve fixed the problem and released to 1.5.2 and 2.0 streams.",
    "For the records, the problem was only hit when you create a EJB project with no EJB inside of the module. If you only had a web project, as we typically do for the smoke test you will not see this problem. I will watch to improve the scenario for the smoke test",
    "(In reply to comment #4)\n\n\u003e \n\u003e Mistake #2, PMC review missed catching it.\n\u003e \n\n  Hey! ... its not purpose of our review to insure correctness! :) \n\n\u003e\n\u003e Mistake #3, I listened to the PMC ;-) when they had an issue with my try/catch\n\u003e block and I narrowed it, exposing the new exception.\n\u003e \n  That\u0027s the main problem with catching every exception and ignoring it, \n  ... it hides bugs!\n\n\u003e \n\u003e I\u0027ve fixed the problem and released to 1.5.2 and 2.0 streams.\n\u003e \n\nThanks for the fix! \n",
    "Verified in 1.5.2"
  ],
  "commentCreationDates": [
    "2006-10-06T19:20:53+02:00",
    "2006-10-06T19:21:10+02:00",
    "2006-10-06T19:34:38+02:00",
    "2006-10-06T19:53:03+02:00",
    "2006-10-06T21:30:20+02:00",
    "2006-10-06T21:37:36+02:00",
    "2006-10-06T21:43:19+02:00",
    "2006-11-02T18:39:50+01:00"
  ],
  "traces": [
    {
      "exceptionType": "java.lang.ArrayIndexOutOfBoundsException",
      "message": "Array index out of range: 1",
      "elements": [
        {
          "method": "org.eclipse.wst.server.ui.internal.wizard.page.ModifyModulesComposite.setServer",
          "source": "ModifyModulesComposite.java:329"
        },
        {
          "method": "org.eclipse.wst.server.ui.internal.wizard.fragment.ModifyModulesWizardFragment.updateModules",
          "source": "ModifyModulesWizardFragment.java:73"
        },
        {
          "method": "org.eclipse.wst.server.ui.internal.wizard.fragment.ModifyModulesWizardFragment.getChildFragments",
          "source": "ModifyModulesWizardFragment.java:62"
        },
        {
          "method": "org.eclipse.wst.server.ui.internal.wizard.TaskWizard.addSubWizardFragments",
          "source": "TaskWizard.java:313"
        },
        {
          "method": "org.eclipse.wst.server.ui.internal.wizard.TaskWizard.addSubWizardFragments",
          "source": "TaskWizard.java:317"
        },
        {
          "method": "org.eclipse.wst.server.ui.internal.wizard.TaskWizard.getAllWizardFragments",
          "source": "TaskWizard.java:301"
        },
        {
          "method": "org.eclipse.wst.server.ui.internal.wizard.TaskWizard.switchWizardFragment",
          "source": "TaskWizard.java:266"
        },
        {
          "method": "org.eclipse.wst.server.ui.internal.wizard.TaskWizardPage.setVisible",
          "source": "T askWizardPage.java:93"
        },
        {
          "method": "org.eclipse.jface.wizard.WizardDialog.showStartingPage",
          "source": "WizardDialog.j ava:1083"
        },
        {
          "method": "org.eclipse.jface.wizard.WizardDialog.createContents",
          "source": "WizardDialog.jav a:504"
        },
        {
          "method": "org.eclipse.jface.window.Window.create",
          "source": "Window.java:426"
        },
        {
          "method": "org.eclipse.jface.dialogs.Dialog.create",
          "source": "Dialog.java:1124"
        },
        {
          "method": "org.eclipse.jface.window.Window.open",
          "source": "Window.java:785"
        },
        {
          "method": "org.eclipse.wst.server.ui.internal.actions.LaunchWizardAction.run",
          "source": "Lau nchWizardAction.java:57"
        },
        {
          "method": "org.eclipse.jface.action.Action.runWithEvent",
          "source": "Action.java:499"
        },
        {
          "method": "org.eclipse.jface.action.ActionContributionItem.handleWidgetSelection",
          "source": "ActionContributionItem.java:539"
        },
        {
          "method": "org.eclipse.jface.action.ActionContributionItem.access$2",
          "source": "ActionContri butionItem.java:488"
        },
        {
          "method": "org.eclipse.jface.action.ActionContributionItem$5.handleEvent",
          "source": "ActionC ontributionItem.java:400"
        },
        {
          "method": "org.eclipse.swt.widgets.EventTable.sendEvent",
          "source": "EventTable.java:66"
        },
        {
          "method": "org.eclipse.swt.widgets.Widget.sendEvent",
          "source": "Widget.java:928"
        },
        {
          "method": "org.eclipse.swt.widgets.Display.runDeferredEvents",
          "source": "Display.java:3348"
        },
        {
          "method": "org.eclipse.swt.widgets.Display.readAndDispatch",
          "source": "Display.java:2968"
        },
        {
          "method": "org.eclipse.ui.internal.Workbench.runEventLoop",
          "source": "Workbench.java:1914"
        },
        {
          "method": "org.eclipse.ui.internal.Workbench.runUI",
          "source": "Workbench.java:1878"
        },
        {
          "method": "org.eclipse.ui.internal.Workbench.createAndRunWorkbench",
          "source": "Workbench.jav a:419"
        },
        {
          "method": "org.eclipse.ui.PlatformUI.createAndRunWorkbench",
          "source": "PlatformUI.java:149"
        },
        {
          "method": "org.eclipse.ui.internal.ide.IDEApplication.run",
          "source": "IDEApplication.java:95 "
        },
        {
          "method": "org.eclipse.core.internal.runtime.PlatformActivator$1.run",
          "source": "PlatformAct ivator.java:78"
        },
        {
          "method": "org.eclipse.core.runtime.internal.adaptor.EclipseAppLauncher.runApplication",
          "source": "EclipseAppLauncher.java:92"
        },
        {
          "method": "org.eclipse.core.runtime.internal.adaptor.EclipseAppLauncher.start",
          "source": "Ec lipseAppLauncher.java:68"
        },
        {
          "method": "org.eclipse.core.runtime.adaptor.EclipseStarter.run",
          "source": "EclipseStarter.ja va:400"
        },
        {
          "method": "org.eclipse.core.runtime.adaptor.EclipseStarter.run",
          "source": "EclipseStarter.ja va:177"
        },
        {
          "method": "sun.reflect.NativeMethodAccessorImpl.invoke0",
          "source": "Native Method"
        },
        {
          "method": "sun.reflect.NativeMethodAccessorImpl.invoke",
          "source": "NativeMethodAccessorImpl. java:64"
        },
        {
          "method": "sun.reflect.DelegatingMethodAccessorImpl.invoke",
          "source": "DelegatingMethodAcces sorImpl.java:43"
        },
        {
          "method": "java.lang.reflect.Method.invoke",
          "source": "Method.java:615"
        },
        {
          "method": "org.eclipse.core.launcher.Main.invokeFramework",
          "source": "Main.java:336"
        },
        {
          "method": "org.eclipse.core.launcher.Main.basicRun",
          "source": "Main.java:280"
        },
        {
          "method": "org.eclipse.core.launcher.Main.run",
          "source": "Main.java:977"
        },
        {
          "method": "org.eclipse.core.launcher.Main.main",
          "source": "Main.java:952"
        }
      ],
      "number": 0,
      "commentIndex": 0,
      "bugId": "160058",
      "date": "2006-10-06T19:20:53+02:00",
      "product": "Web Tools",
      "component": "wst.server",
      "severity": "critical"
    }
  ],
  "groupId": "160058",
  "bugId": "160058",
  "date": "2006-10-06T19:20:53+02:00",
  "product": "Web Tools",
  "component": "wst.server",
  "severity": "critical"
}