{
  "comments": [
    "This issue is related to bug 102266 \n\nWhen using a paerticular plugin (WOLips) with a project shared through a particular Team provider (Perforce) I get a \"Attempted to beginRule: R/, does not match outer scope rule: P/\" error (stack trace below, if it helps).\n\nThe sequence of actions is emminently reproducible.\n\nFrom bug 102266, it seems likely that a particular RuleFactory involved in the explicit sequence of actions is not overriding a specific method.\n\nIs the stack trace below sufficient to disgnose the problem Factory (and indeed to confirm that the factory is at fault)? Or do I need to hassle the providers of the Team provider plugin or the WOLips plugin?\n\njava.lang.IllegalArgumentException: Attempted to beginRule: R/, does not match outer scope rule: P/Testing\n        at org.eclipse.core.runtime.Assert.isLegal(Assert.java:62)\n        at org.eclipse.core.internal.jobs.ThreadJob.illegalPush(ThreadJob.java:116)\n        at org.eclipse.core.internal.jobs.ThreadJob.push(ThreadJob.java:225)\n        at org.eclipse.core.internal.jobs.ImplicitJobs.begin(ImplicitJobs.java:80)\n        at org.eclipse.core.internal.jobs.JobManager.beginRule(JobManager.java:219)\n        at org.eclipse.core.internal.resources.WorkManager.checkIn(WorkManager.java:96)\n        at org.eclipse.core.internal.resources.Workspace.prepareOperation(Workspace.java:1684)\n        at org.eclipse.core.internal.resources.File.setContents(File.java:358)\n        at org.eclipse.core.internal.resources.File.setContents(File.java:462)\n        at org.objectstyle.wolips.jdt.ant.UpdateOtherClasspathIncludeFiles.buildIncludeFiles(UpdateOtherClasspathIncludeFiles.java:148)\n        at org.objectstyle.wolips.jdt.ant.UpdateOtherClasspathIncludeFiles.execute(UpdateOtherClasspathIncludeFiles.java:89)\n        at org.objectstyle.wolips.jdt.listener.UpdateIncludeFilesJob.runInWorkspace(UpdateIncludeFilesJob.java:90)\n        at org.eclipse.core.internal.resources.InternalWorkspaceJob.run(InternalWorkspaceJob.java:38)\n        at org.eclipse.core.internal.jobs.Worker.run(Worker.java:58)",
    "This does no appear to be an Eclipse Platform problem. Since the exception trace mentions WOLips, that is probably the best place to send the trace."
  ],
  "commentCreationDates": [
    "2006-10-13T13:28:36+02:00",
    "2006-10-13T15:49:27+02:00"
  ],
  "traces": [
    {
      "exceptionType": "java.lang.IllegalArgumentException",
      "message": "Attempted to beginRule: R/, does not match outer scope rule: P/Testing",
      "elements": [
        {
          "method": "org.eclipse.core.runtime.Assert.isLegal",
          "source": "Assert.java:62"
        },
        {
          "method": "org.eclipse.core.internal.jobs.ThreadJob.illegalPush",
          "source": "ThreadJob.java:116"
        },
        {
          "method": "org.eclipse.core.internal.jobs.ThreadJob.push",
          "source": "ThreadJob.java:225"
        },
        {
          "method": "org.eclipse.core.internal.jobs.ImplicitJobs.begin",
          "source": "ImplicitJobs.java:80"
        },
        {
          "method": "org.eclipse.core.internal.jobs.JobManager.beginRule",
          "source": "JobManager.java:219"
        },
        {
          "method": "org.eclipse.core.internal.resources.WorkManager.checkIn",
          "source": "WorkManager.java:96"
        },
        {
          "method": "org.eclipse.core.internal.resources.Workspace.prepareOperation",
          "source": "Workspace.java:1684"
        },
        {
          "method": "org.eclipse.core.internal.resources.File.setContents",
          "source": "File.java:358"
        },
        {
          "method": "org.eclipse.core.internal.resources.File.setContents",
          "source": "File.java:462"
        },
        {
          "method": "org.objectstyle.wolips.jdt.ant.UpdateOtherClasspathIncludeFiles.buildIncludeFiles",
          "source": "UpdateOtherClasspathIncludeFiles.java:148"
        },
        {
          "method": "org.objectstyle.wolips.jdt.ant.UpdateOtherClasspathIncludeFiles.execute",
          "source": "UpdateOtherClasspathIncludeFiles.java:89"
        },
        {
          "method": "org.objectstyle.wolips.jdt.listener.UpdateIncludeFilesJob.runInWorkspace",
          "source": "UpdateIncludeFilesJob.java:90"
        },
        {
          "method": "org.eclipse.core.internal.resources.InternalWorkspaceJob.run",
          "source": "InternalWorkspaceJob.java:38"
        },
        {
          "method": "org.eclipse.core.internal.jobs.Worker.run",
          "source": "Worker.java:58"
        }
      ],
      "number": 0,
      "commentIndex": 0,
      "bugId": "160844",
      "date": "2006-10-13T13:28:36+02:00",
      "product": "Platform",
      "component": "Team",
      "severity": "normal"
    }
  ],
  "groupId": "160844",
  "bugId": "160844",
  "date": "2006-10-13T13:28:36+02:00",
  "product": "Platform",
  "component": "Team",
  "severity": "normal"
}