{
  "comments": [
    "Within the IDE, if an Equinox OSGi Framework launch configuration is pointed to an OSGiMin1.1/RM JRE (within the Settings tab on the IDe window), the runtime fails to launch with the following error:\n\nException in thread \"main\" java.lang.NoClassDefFoundError: java.io.FileFilter\n\tat java.lang.J9VMInternals.verifyImpl(Native Method)\n\tat java.lang.J9VMInternals.verify(J9VMInternals.java:54)\n\tat java.lang.J9VMInternals.initialize(J9VMInternals.java:115)\n\nIf a -noverify JVM command line argument is added, the runtime fails to launch with the following exception:\n\njava.lang.NoSuchMethodError: java/lang/Runtime.removeShutdownHook(Ljava/lang/Thread;)Z\n\tat org.eclipse.core.launcher.Main.takeDownSplash(Main.java:1604)\n\tat org.eclipse.core.launcher.Main.run(Main.java:1003)\n\tat org.eclipse.core.launcher.Main.main(Main.java:952)\n\nThe JRE used to create this condition was based on the IBM WECE 6.1.1 Max/RM distribution.\n\nThe minimum JRE needed in order to successfully launch an Eclipse OSGi Framework using a launch configuration within the IDE appears to be Foundation 1.0.",
    "\n\n*** This bug has been marked as a duplicate of 150669 ***",
    "(In reply to comment #1)\n\u003e *** This bug has been marked as a duplicate of 150669 ***\n\nThank you. I never would have made the connection.\n\nThe other bug report was issued against 3.2. The fix apparently did not get into 3.2.1 and there is no target milestone listed. Will this be applied to 3.3?",
    "John, the patch did not make it into 3.2.x.  Please voice your request to include a fix in bug 150669.  We need to get a committer of the org.eclipse.platform team to review and release the fix.",
    "Note that bug 159122 calls for this statup.jar code to be moved to org.eclipse.equinox.startup.  We should take action on that but it still does not solve the 3.2.x problem."
  ],
  "commentCreationDates": [
    "2006-10-30T16:37:12+01:00",
    "2006-10-30T17:57:28+01:00",
    "2006-10-30T18:46:15+01:00",
    "2006-10-30T19:23:04+01:00",
    "2006-10-31T01:23:30+01:00"
  ],
  "traces": [
    {
      "exceptionType": "java.lang.NoClassDefFoundError",
      "message": "java.io.FileFilter",
      "elements": [
        {
          "method": "java.lang.J9VMInternals.verifyImpl",
          "source": "Native Method"
        },
        {
          "method": "java.lang.J9VMInternals.verify",
          "source": "J9VMInternals.java:54"
        },
        {
          "method": "java.lang.J9VMInternals.initialize",
          "source": "J9VMInternals.java:115"
        }
      ],
      "number": 0,
      "commentIndex": 0,
      "bugId": "162764",
      "duplicateId": "150669",
      "date": "2006-10-30T16:37:12+01:00",
      "product": "Equinox",
      "component": "Framework",
      "severity": "normal"
    },
    {
      "exceptionType": "java.lang.NoSuchMethodError",
      "message": "java/lang/Runtime.removeShutdownHook(Ljava/lang/Thread;)Z",
      "elements": [
        {
          "method": "org.eclipse.core.launcher.Main.takeDownSplash",
          "source": "Main.java:1604"
        },
        {
          "method": "org.eclipse.core.launcher.Main.run",
          "source": "Main.java:1003"
        },
        {
          "method": "org.eclipse.core.launcher.Main.main",
          "source": "Main.java:952"
        }
      ],
      "number": 1,
      "commentIndex": 0,
      "bugId": "162764",
      "duplicateId": "150669",
      "date": "2006-10-30T16:37:12+01:00",
      "product": "Equinox",
      "component": "Framework",
      "severity": "normal"
    }
  ],
  "groupId": "150669",
  "bugId": "162764",
  "duplicateId": "150669",
  "date": "2006-10-30T16:37:12+01:00",
  "product": "Equinox",
  "component": "Framework",
  "severity": "normal"
}