{
  "comments": [
    "Hi, \nI\u0027m using AJDT(the latest) for Eclipse 3.2.1 \nAnd when i\u0027m trying to apply aspect:\n-----------------------------\npublic aspect AbafAspect extends SequenceAspect {\n\tpublic pointcut anyCall():\n\t\t(call(* MojaMinimalnaABAFAplikacija.*(..)) || call(MojaMinimalnaABAFAplikacija.new(..)) \n\t\t\t\t|| call(* com.ibm.abaf..*.*(..)) || call(com.ibm.abaf..*.new(..))\t\t\t\t\n\t\t);\n\t\n\tpublic pointcut anyExecution():\n\t\t(execution(* MojaMinimalnaABAFAplikacija.*(..)) \n\t\t\t\t|| execution(MojaMinimalnaABAFAplikacija.new(..)) \n\t\t\t\t|| execution(* com.ibm.abaf..*.*(..)) || execution(com.ibm.abaf..*.new(..))\t\t\t\t\n\t\t);\n\n}\n\n------------------------------------\nI get this exception:\n\n------------------------------------\njava.lang.IllegalStateException\nat org.aspectj.weaver.Shadow.getThisType(Shadow.java:94)\nat org.aspectj.weaver.bcel.BcelShadow.createMethodGen(BcelShadow.java:3398)\nat org.aspectj.weaver.bcel.BcelShadow.extractMethod(BcelShadow.java:3252)\nat org.aspectj.weaver.bcel.BcelShadow.weaveAroundInline(BcelShadow.java:2285)\nat org.aspectj.weaver.bcel.BcelAdvice.implementOn(BcelAdvice.java:272)\nat org.aspectj.weaver.Shadow.implementMungers(Shadow.java:684)\nat org.aspectj.weaver.Shadow.implement(Shadow.java:471)\nat org.aspectj.weaver.bcel.BcelClassWeaver.implement(BcelClassWeaver.java:2825)\nat org.aspectj.weaver.bcel.BcelClassWeaver.weave(BcelClassWeaver.java:502)\nat org.aspectj.weaver.bcel.BcelClassWeaver.weave(BcelClassWeaver.java:115)\nat org.aspectj.weaver.bcel.BcelWeaver.weave(BcelWeaver.java:1574)\nat org.aspectj.weaver.bcel.BcelWeaver.weaveWithoutDump(BcelWeaver.java:1525)\nat org.aspectj.weaver.bcel.BcelWeaver.weaveAndNotify(BcelWeaver.java:1305)\nat org.aspectj.weaver.bcel.BcelWeaver.weave(BcelWeaver.java:1127)\nat org.aspectj.ajdt.internal.compiler.AjCompilerAdapter.weave(AjCompilerAdapter.java:321)\nat org.aspectj.ajdt.internal.compiler.AjCompilerAdapter.afterCompiling(AjCompilerAdapter.java:192)\nat org.aspectj.ajdt.internal.compiler.CompilerAdapter.ajc$afterReturning$org_aspectj_ajdt_internal_compiler_CompilerAdapter$2$f9cc9ca0(CompilerAdapter.aj:70)\nat org.aspectj.org.eclipse.jdt.internal.compiler.Compiler.compile(Compiler.java:367)\nat org.aspectj.ajdt.internal.core.builder.AjBuildManager.performCompilation(AjBuildManager.java:887)\nat org.aspectj.ajdt.internal.core.builder.AjBuildManager.doBuild(AjBuildManager.java:244)\nat org.aspectj.ajdt.internal.core.builder.AjBuildManager.batchBuild(AjBuildManager.java:163)\nat org.aspectj.ajde.internal.CompilerAdapter.compile(CompilerAdapter.java:122)\nat org.aspectj.ajde.internal.AspectJBuildManager$CompilerThread.run(AspectJBuildManager.java:191)\n\ntrouble in: \npublic class com.ibm.abaf.ui.controller.defaults.BooleanController extends com.ibm.abaf.ui.controller.abstracts.PropertyController:\n  boolean disableChangeEvents\n  private static final org.aspectj.lang.JoinPoint$StaticPart ajc$tjp_0 [Synthetic]\n  private static final org.aspectj.lang.JoinPoint$StaticPart ajc$tjp_1 [Synthetic]\n  private static final org.aspectj.lang.JoinPoint$StaticPart ajc$tjp_2 [Synthetic]\n  private static final org.aspectj.lang.JoinPoint$StaticPart ajc$tjp_3 [Synthetic]\n  private static final org.aspectj.lang.JoinPoint$StaticPart ajc$tjp_4 [Synthetic]\n  private static final org.aspectj.lang.JoinPoint$StaticPart ajc$tjp_5 [Synthetic]\n  private static final org.aspectj.lang.JoinPoint$StaticPart ajc$tjp_6 [Synthetic]\n  private static final org.aspectj.lang.JoinPoint$StaticPart ajc$tjp_7 [Synthetic]\n  private static final org.aspectj.lang.JoinPoint$StaticPart ajc$tjp_8 [Synthetic]\n  private static final org.aspectj.lang.JoinPoint$StaticPart ajc$tjp_9 [Synthetic]\n  private static final org.aspectj.lang.JoinPoint$StaticPart ajc$tjp_10 [Synthetic]\n  private static final org.aspectj.lang.JoinPoint$StaticPart ajc$tjp_11 [Synthetic]\n  private static final org.aspectj.lang.JoinPoint$StaticPart ajc$tjp_12 [Synthetic]\n  private static final org.aspectj.lang.JoinPoint$StaticPart ajc$tjp_13 [Synthetic]\n  private static final org.aspectj.lang.JoinPoint$StaticPart ajc$tjp_14 [Synthetic]\n  private static final org.aspectj.lang.JoinPoint$StaticPart ajc$tjp_15 [Synthetic]\n  private static final org.aspectj.lang.JoinPoint$StaticPart ajc$tjp_16 [Synthetic]\n  private static final org.aspectj.lang.JoinPoint$StaticPart ajc$tjp_17 [Synthetic]\n  private static final org.aspectj.lang.JoinPoint$StaticPart ajc$tjp_18 [Synthetic]\n  private static final org.aspectj.lang.JoinPoint$StaticPart ajc$tjp_19 [Synthetic]\n  private static final org.aspectj.lang.JoinPoint$StaticPart ajc$tjp_20 [Synthetic]\n  private static final org.aspectj.lang.JoinPoint$StaticPart ajc$tjp_21 [Synthetic]\n  private static final org.aspectj.lang.JoinPoint$StaticPart ajc$tjp_22 [Synthetic]\n  private static final org.aspectj.lang.JoinPoint$StaticPart ajc$tjp_23 [Synthetic]\n  private static final org.aspectj.lang.JoinPoint$StaticPart ajc$tjp_24 [Synthetic]\n  private static final org.aspectj.lang.JoinPoint$StaticPart ajc$tjp_25 [Synthetic]\n  public void \u003cinit\u003e()    org.aspectj.weaver.MethodDeclarationLineNumber: 48:1345\n:\n                    ALOAD_0     // Lcom/ibm/abaf/ui/controller/defaults/BooleanController; this   (line 49)\n                    ACONST_NULL\n                    INVOKESPECIAL com.ibm.abaf.ui.controller.abstracts.PropertyController.\u003cinit\u003e (Lcom/ibm/abaf/ui/controller/abstracts/BaseController;)V\n                    GETSTATIC com.ibm.abaf.ui.controller.defaults.BooleanController.ajc$tjp_1 Lorg/aspectj/lang/JoinPoint$StaticPart;\n                    ALOAD_0\n                    ALOAD_0\n                    INVOKESTATIC org.aspectj.runtime.reflect.Factory.makeJP (Lorg/aspectj/lang/JoinPoint$StaticPart;Ljava/lang/Object;Ljava/lang/Object;)Lorg/aspectj/lang/JoinPoint;\n                    ASTORE_3\n    constructor-execution(void com.ibm.abaf.ui.controller.defaults.BooleanController.\u003cinit\u003e())\n    |               ALOAD_0\n    |               ALOAD_3\n    |               INVOKESTATIC AbafAspect.aspectOf ()LAbafAspect;\n    |               ACONST_NULL\n    |               GETSTATIC com.ibm.abaf.ui.controller.defaults.BooleanController.ajc$tjp_1 Lorg/aspectj/lang/JoinPoint$StaticPart;\n    |               ALOAD_3\n    |               GETSTATIC com.ibm.abaf.ui.controller.defaults.BooleanController.ajc$tjp_1 Lorg/aspectj/lang/JoinPoint$StaticPart;\n    |               INVOKESTATIC com.ibm.abaf.ui.controller.defaults.BooleanController.init$_aroundBody3$advice (Lcom/ibm/abaf/ui/controller/defaults/BooleanController;Lorg/aspectj/lang/JoinPoint;Lcom/maintainj/aspect/SequenceAspect;Lorg/aspectj/runtime/internal/AroundClosure;Lorg/aspectj/lang/JoinPoint$StaticPart;Lorg/aspectj/lang/JoinPoint;Lorg/aspectj/lang/JoinPoint$StaticPart;)Ljava/lang/Object;\n    |               POP\n    |               RETURN\n    constructor-execution(void com.ibm.abaf.ui.controller.defaults.BooleanController.\u003cinit\u003e())\n  end public void \u003cinit\u003e()\n.\n.\n.\n.  end private static final Object self_aroundBody47$advice(com.ibm.abaf.ui.controller.defaults.BooleanController, org.aspectj.lang.JoinPoint, com.maintainj.aspect.SequenceAspect, org.aspectj.runtime.internal.AroundClosure, org.aspectj.lang.JoinPoint$StaticPart, org.aspectj.lang.JoinPoint, org.aspectj.lang.JoinPoint$StaticPart)\nend public class com.ibm.abaf.ui.controller.defaults.BooleanController\n\nwhen implementing on shadow method-call(void com.ibm.abaf.ui.controller.abstracts.BaseController.signalBecomeActiv())\nwhen weaving classes \nwhen weaving \nwhen batch building BuildConfig[C:\\java\\MyWork\\icms\\.metadata\\.plugins\\org.eclipse.ajdt.core\\IBM ABAF UI 3.1.0 Build004.generated.lst] #Files\u003d561\n\nI try compiling on IBM 1.4.2 SR1 and sun JRE1.5.0_06 and result is same.",
    "might be the same as 197719 - a problem due to an accessor being created"
  ],
  "commentCreationDates": [
    "2006-11-08T12:27:57+01:00",
    "2007-10-25T16:47:12+02:00"
  ],
  "traces": [
    {
      "exceptionType": "java.lang.IllegalStateException",
      "elements": [
        {
          "method": "org.aspectj.weaver.Shadow.getThisType",
          "source": "Shadow.java:94"
        },
        {
          "method": "org.aspectj.weaver.bcel.BcelShadow.createMethodGen",
          "source": "BcelShadow.java:3398"
        },
        {
          "method": "org.aspectj.weaver.bcel.BcelShadow.extractMethod",
          "source": "BcelShadow.java:3252"
        },
        {
          "method": "org.aspectj.weaver.bcel.BcelShadow.weaveAroundInline",
          "source": "BcelShadow.java:2285"
        },
        {
          "method": "org.aspectj.weaver.bcel.BcelAdvice.implementOn",
          "source": "BcelAdvice.java:272"
        },
        {
          "method": "org.aspectj.weaver.Shadow.implementMungers",
          "source": "Shadow.java:684"
        },
        {
          "method": "org.aspectj.weaver.Shadow.implement",
          "source": "Shadow.java:471"
        },
        {
          "method": "org.aspectj.weaver.bcel.BcelClassWeaver.implement",
          "source": "BcelClassWeaver.java:2825"
        },
        {
          "method": "org.aspectj.weaver.bcel.BcelClassWeaver.weave",
          "source": "BcelClassWeaver.java:502"
        },
        {
          "method": "org.aspectj.weaver.bcel.BcelClassWeaver.weave",
          "source": "BcelClassWeaver.java:115"
        },
        {
          "method": "org.aspectj.weaver.bcel.BcelWeaver.weave",
          "source": "BcelWeaver.java:1574"
        },
        {
          "method": "org.aspectj.weaver.bcel.BcelWeaver.weaveWithoutDump",
          "source": "BcelWeaver.java:1525"
        },
        {
          "method": "org.aspectj.weaver.bcel.BcelWeaver.weaveAndNotify",
          "source": "BcelWeaver.java:1305"
        },
        {
          "method": "org.aspectj.weaver.bcel.BcelWeaver.weave",
          "source": "BcelWeaver.java:1127"
        },
        {
          "method": "org.aspectj.ajdt.internal.compiler.AjCompilerAdapter.weave",
          "source": "AjCompilerAdapter.java:321"
        },
        {
          "method": "org.aspectj.ajdt.internal.compiler.AjCompilerAdapter.afterCompiling",
          "source": "AjCompilerAdapter.java:192"
        },
        {
          "method": "org.aspectj.ajdt.internal.compiler.CompilerAdapter.ajc$afterReturning$org_aspectj_ajdt_internal_compiler_CompilerAdapter$2$f9cc9ca0",
          "source": "CompilerAdapter.aj:70"
        },
        {
          "method": "org.aspectj.org.eclipse.jdt.internal.compiler.Compiler.compile",
          "source": "Compiler.java:367"
        },
        {
          "method": "org.aspectj.ajdt.internal.core.builder.AjBuildManager.performCompilation",
          "source": "AjBuildManager.java:887"
        },
        {
          "method": "org.aspectj.ajdt.internal.core.builder.AjBuildManager.doBuild",
          "source": "AjBuildManager.java:244"
        },
        {
          "method": "org.aspectj.ajdt.internal.core.builder.AjBuildManager.batchBuild",
          "source": "AjBuildManager.java:163"
        },
        {
          "method": "org.aspectj.ajde.internal.CompilerAdapter.compile",
          "source": "CompilerAdapter.java:122"
        },
        {
          "method": "org.aspectj.ajde.internal.AspectJBuildManager$CompilerThread.run",
          "source": "AspectJBuildManager.java:191"
        }
      ],
      "number": 0,
      "commentIndex": 0,
      "bugId": "163792",
      "date": "2006-11-08T12:27:57+01:00",
      "product": "AspectJ",
      "component": "Compiler",
      "severity": "normal"
    }
  ],
  "groupId": "163792",
  "bugId": "163792",
  "date": "2006-11-08T12:27:57+01:00",
  "product": "AspectJ",
  "component": "Compiler",
  "severity": "normal"
}