{
  "comments": [
    "Upon creating a dyn. web project i see:\n\neclipse.buildId\u003dI20061031-0656\njava.version\u003d1.5.0_06\njava.vendor\u003dSun Microsystems Inc.\nBootLoader constants: OS\u003dwin32, ARCH\u003dx86, WS\u003dwin32, NL\u003den_US\nCommand-line arguments:  -data C:\\Documents and Settings\\Administrator\\workspace\n1 -os win32 -ws win32 -arch x86 -clean -consoleLog\n\n!ENTRY org.eclipse.ui 4 4 2006-11-10 13:50:21.278\n!MESSAGE Exception in org.eclipse.ui.internal.FolderLayout.addView(String): org.\neclipse.ui.PartInitException: View descriptor not found: org.eclipse.wst.rdb.ser\nver.ui.navigator.serverExplorer\n\n!ENTRY org.eclipse.ui 4 4 2006-11-10 13:50:21.298\n!MESSAGE Exception in org.eclipse.ui.internal.FolderLayout.addView(String): org.\neclipse.ui.PartInitException: View descriptor not found: org.eclipse.wst.rdb.ser\nver.ui.navigator.serverExplorer\n!STACK 1\norg.eclipse.ui.PartInitException: View descriptor not found: org.eclipse.wst.rdb\n.server.ui.navigator.serverExplorer\n        at org.eclipse.ui.internal.FolderLayout.addView(FolderLayout.java:74)\n        at org.eclipse.jst.j2ee.internal.perspective.J2EEPerspective.defineLayou\nt(J2EEPerspective.java:122)\n        at org.eclipse.jst.j2ee.internal.perspective.J2EEPerspective.createIniti\nalLayout(J2EEPerspective.java:56)\n        at org.eclipse.ui.internal.Perspective.loadPredefinedPersp(Perspective.j\nava:708)\n        at org.eclipse.ui.internal.Perspective.createPresentation(Perspective.ja\nva:238)\n        at org.eclipse.ui.internal.Perspective.\u003cinit\u003e(Perspective.java:133)\n        at org.eclipse.ui.internal.WorkbenchPage.createPerspective(WorkbenchPage\n.java:1484)\n        at org.eclipse.ui.internal.WorkbenchPage.busySetPerspective(WorkbenchPag\ne.java:947)\n        at org.eclipse.ui.internal.WorkbenchPage.access$12(WorkbenchPage.java:93\n8)\n        at org.eclipse.ui.internal.WorkbenchPage$12.run(WorkbenchPage.java:3384)\n\n        at org.eclipse.swt.custom.BusyIndicator.showWhile(BusyIndicator.java:67)\n\n        at org.eclipse.ui.internal.WorkbenchPage.setPerspective(WorkbenchPage.ja\nva:3382)\n        at org.eclipse.ui.wizards.newresource.BasicNewProjectResourceWizard.repl\naceCurrentPerspective(BasicNewProjectResourceWizard.java:336)\n        at org.eclipse.ui.wizards.newresource.BasicNewProjectResourceWizard.upda\ntePerspective(BasicNewProjectResourceWizard.java:485)\n        at org.eclipse.wst.web.ui.internal.wizards.NewProjectDataModelFacetWizar\nd.postPerformFinish(NewProjectDataModelFacetWizard.java:412)\n        at org.eclipse.wst.web.ui.internal.wizards.NewProjectDataModelFacetWizar\nd.performFinish(NewProjectDataModelFacetWizard.java:312)\n        at org.eclipse.jface.wizard.WizardDialog.finishPressed(WizardDialog.java\n:695)\n        at org.eclipse.jface.wizard.WizardDialog.buttonPressed(WizardDialog.java\n:367)\n        at org.eclipse.jface.dialogs.Dialog$3.widgetSelected(Dialog.java:638)\n        at org.eclipse.swt.widgets.TypedListener.handleEvent(TypedListener.java:\n90)\n        at org.eclipse.swt.widgets.EventTable.sendEvent(EventTable.java:66)\n        at org.eclipse.swt.widgets.Widget.sendEvent(Widget.java:925)\n        at org.eclipse.swt.widgets.Display.runDeferredEvents(Display.java:3463)\n        at org.eclipse.swt.widgets.Display.readAndDispatch(Display.java:3077)\n        at org.eclipse.jface.window.Window.runEventLoop(Window.java:820)\n        at org.eclipse.jface.window.Window.open(Window.java:796)\n        at org.eclipse.ui.actions.NewProjectAction.run(NewProjectAction.java:116\n)\n        at org.eclipse.jface.action.Action.runWithEvent(Action.java:499)\n        at org.eclipse.jface.action.ActionContributionItem.handleWidgetSelection\n(ActionContributionItem.java:539)\n        at org.eclipse.jface.action.ActionContributionItem.access$2(ActionContri\nbutionItem.java:488)\n        at org.eclipse.jface.action.ActionContributionItem$5.handleEvent(ActionC\nontributionItem.java:400)\n        at org.eclipse.swt.widgets.EventTable.sendEvent(EventTable.java:66)\n        at org.eclipse.swt.widgets.Widget.sendEvent(Widget.java:925)\n        at org.eclipse.swt.widgets.Display.runDeferredEvents(Display.java:3463)\n        at org.eclipse.swt.widgets.Display.readAndDispatch(Display.java:3077)\n        at org.eclipse.ui.internal.Workbench.runEventLoop(Workbench.java:1924)\n        at org.eclipse.ui.internal.Workbench.runUI(Workbench.java:1888)\n        at org.eclipse.ui.internal.Workbench.createAndRunWorkbench(Workbench.jav\na:419)\n        at org.eclipse.ui.PlatformUI.createAndRunWorkbench(PlatformUI.java:149)\n        at org.eclipse.ui.internal.ide.IDEApplication.run(IDEApplication.java:95\n)\n        at org.eclipse.core.internal.runtime.PlatformActivator$1.run(PlatformAct\nivator.java:78)\n        at org.eclipse.core.runtime.internal.adaptor.EclipseAppLauncher.runAppli\ncation(EclipseAppLauncher.java:104)\n        at org.eclipse.core.runtime.internal.adaptor.EclipseAppLauncher.start(Ec\nlipseAppLauncher.java:74)\n        at org.eclipse.core.runtime.adaptor.EclipseStarter.run(EclipseStarter.ja\nva:348)\n        at org.eclipse.core.runtime.adaptor.EclipseStarter.run(EclipseStarter.ja\nva:165)\n        at sun.reflect.NativeMethodAccessorImpl.invoke0(Native Method)\n        at sun.reflect.NativeMethodAccessorImpl.invoke(Unknown Source)\n        at sun.reflect.DelegatingMethodAccessorImpl.invoke(Unknown Source)\n        at java.lang.reflect.Method.invoke(Unknown Source)\n        at org.eclipse.core.launcher.Main.invokeFramework(Main.java:341)\n        at org.eclipse.core.launcher.Main.basicRun(Main.java:285)\n        at org.eclipse.core.launcher.Main.run(Main.java:987)\n        at org.eclipse.core.launcher.Main.main(Main.java:962)\n!SUBENTRY 1 org.eclipse.ui 4 0 2006-11-10 13:50:21.308\n!MESSAGE View descriptor not found: org.eclipse.wst.rdb.server.ui.navigator.serv\nerExplorer",
    "works in latest build.",
    "Closing as fixed since M2.  Please reopen if closed in error."
  ],
  "commentCreationDates": [
    "2006-11-10T18:48:08+01:00",
    "2007-02-20T17:16:02+01:00",
    "2007-04-03T18:07:34+02:00"
  ],
  "traces": [
    {
      "exceptionType": "org.eclipse.ui.PartInitException",
      "message": "View descriptor not found: org.eclipse.wst.rdb .server.ui.navigator.serverExplorer",
      "elements": [
        {
          "method": "org.eclipse.ui.internal.FolderLayout.addView",
          "source": "FolderLayout.java:74"
        },
        {
          "method": "org.eclipse.jst.j2ee.internal.perspective.J2EEPerspective.defineLayout",
          "source": "J2EEPerspective.java:122"
        },
        {
          "method": "org.eclipse.jst.j2ee.internal.perspective.J2EEPerspective.createInitialLayout",
          "source": "J2EEPerspective.java:56"
        },
        {
          "method": "org.eclipse.ui.internal.Perspective.loadPredefinedPersp",
          "source": "Perspective.j ava:708"
        },
        {
          "method": "org.eclipse.ui.internal.Perspective.createPresentation",
          "source": "Perspective.ja va:238"
        },
        {
          "method": "org.eclipse.ui.internal.Perspective.\u003cinit\u003e",
          "source": "Perspective.java:133"
        },
        {
          "method": "org.eclipse.ui.internal.WorkbenchPage.createPerspective",
          "source": "WorkbenchPage .java:1484"
        },
        {
          "method": "org.eclipse.ui.internal.WorkbenchPage.busySetPerspective",
          "source": "WorkbenchPag e.java:947"
        },
        {
          "method": "org.eclipse.ui.internal.WorkbenchPage.access$12",
          "source": "WorkbenchPage.java:93 8"
        },
        {
          "method": "org.eclipse.ui.internal.WorkbenchPage$12.run",
          "source": "WorkbenchPage.java:3384"
        },
        {
          "method": "org.eclipse.swt.custom.BusyIndicator.showWhile",
          "source": "BusyIndicator.java:67"
        },
        {
          "method": "org.eclipse.ui.internal.WorkbenchPage.setPerspective",
          "source": "WorkbenchPage.ja va:3382"
        },
        {
          "method": "org.eclipse.ui.wizards.newresource.BasicNewProjectResourceWizard.replaceCurrentPerspective",
          "source": "BasicNewProjectResourceWizard.java:336"
        },
        {
          "method": "org.eclipse.ui.wizards.newresource.BasicNewProjectResourceWizard.updatePerspective",
          "source": "BasicNewProjectResourceWizard.java:485"
        },
        {
          "method": "org.eclipse.wst.web.ui.internal.wizards.NewProjectDataModelFacetWizard.postPerformFinish",
          "source": "NewProjectDataModelFacetWizard.java:412"
        },
        {
          "method": "org.eclipse.wst.web.ui.internal.wizards.NewProjectDataModelFacetWizard.performFinish",
          "source": "NewProjectDataModelFacetWizard.java:312"
        },
        {
          "method": "org.eclipse.jface.wizard.WizardDialog.finishPressed",
          "source": "WizardDialog.java :695"
        },
        {
          "method": "org.eclipse.jface.wizard.WizardDialog.buttonPressed",
          "source": "WizardDialog.java :367"
        },
        {
          "method": "org.eclipse.jface.dialogs.Dialog$3.widgetSelected",
          "source": "Dialog.java:638"
        },
        {
          "method": "org.eclipse.swt.widgets.TypedListener.handleEvent",
          "source": "TypedListener.java: 90"
        },
        {
          "method": "org.eclipse.swt.widgets.EventTable.sendEvent",
          "source": "EventTable.java:66"
        },
        {
          "method": "org.eclipse.swt.widgets.Widget.sendEvent",
          "source": "Widget.java:925"
        },
        {
          "method": "org.eclipse.swt.widgets.Display.runDeferredEvents",
          "source": "Display.java:3463"
        },
        {
          "method": "org.eclipse.swt.widgets.Display.readAndDispatch",
          "source": "Display.java:3077"
        },
        {
          "method": "org.eclipse.jface.window.Window.runEventLoop",
          "source": "Window.java:820"
        },
        {
          "method": "org.eclipse.jface.window.Window.open",
          "source": "Window.java:796"
        },
        {
          "method": "org.eclipse.ui.actions.NewProjectAction.run",
          "source": "NewProjectAction.java:116 "
        },
        {
          "method": "org.eclipse.jface.action.Action.runWithEvent",
          "source": "Action.java:499"
        },
        {
          "method": "org.eclipse.jface.action.ActionContributionItem.handleWidgetSelection",
          "source": "ActionContributionItem.java:539"
        },
        {
          "method": "org.eclipse.jface.action.ActionContributionItem.access$2",
          "source": "ActionContri butionItem.java:488"
        },
        {
          "method": "org.eclipse.jface.action.ActionContributionItem$5.handleEvent",
          "source": "ActionC ontributionItem.java:400"
        },
        {
          "method": "org.eclipse.swt.widgets.EventTable.sendEvent",
          "source": "EventTable.java:66"
        },
        {
          "method": "org.eclipse.swt.widgets.Widget.sendEvent",
          "source": "Widget.java:925"
        },
        {
          "method": "org.eclipse.swt.widgets.Display.runDeferredEvents",
          "source": "Display.java:3463"
        },
        {
          "method": "org.eclipse.swt.widgets.Display.readAndDispatch",
          "source": "Display.java:3077"
        },
        {
          "method": "org.eclipse.ui.internal.Workbench.runEventLoop",
          "source": "Workbench.java:1924"
        },
        {
          "method": "org.eclipse.ui.internal.Workbench.runUI",
          "source": "Workbench.java:1888"
        },
        {
          "method": "org.eclipse.ui.internal.Workbench.createAndRunWorkbench",
          "source": "Workbench.jav a:419"
        },
        {
          "method": "org.eclipse.ui.PlatformUI.createAndRunWorkbench",
          "source": "PlatformUI.java:149"
        },
        {
          "method": "org.eclipse.ui.internal.ide.IDEApplication.run",
          "source": "IDEApplication.java:95 "
        },
        {
          "method": "org.eclipse.core.internal.runtime.PlatformActivator$1.run",
          "source": "PlatformAct ivator.java:78"
        },
        {
          "method": "org.eclipse.core.runtime.internal.adaptor.EclipseAppLauncher.runApplication",
          "source": "EclipseAppLauncher.java:104"
        },
        {
          "method": "org.eclipse.core.runtime.internal.adaptor.EclipseAppLauncher.start",
          "source": "Ec lipseAppLauncher.java:74"
        },
        {
          "method": "org.eclipse.core.runtime.adaptor.EclipseStarter.run",
          "source": "EclipseStarter.ja va:348"
        },
        {
          "method": "org.eclipse.core.runtime.adaptor.EclipseStarter.run",
          "source": "EclipseStarter.ja va:165"
        },
        {
          "method": "sun.reflect.NativeMethodAccessorImpl.invoke0",
          "source": "Native Method"
        },
        {
          "method": "sun.reflect.NativeMethodAccessorImpl.invoke",
          "source": "Unknown Source"
        },
        {
          "method": "sun.reflect.DelegatingMethodAccessorImpl.invoke",
          "source": "Unknown Source"
        },
        {
          "method": "java.lang.reflect.Method.invoke",
          "source": "Unknown Source"
        },
        {
          "method": "org.eclipse.core.launcher.Main.invokeFramework",
          "source": "Main.java:341"
        },
        {
          "method": "org.eclipse.core.launcher.Main.basicRun",
          "source": "Main.java:285"
        },
        {
          "method": "org.eclipse.core.launcher.Main.run",
          "source": "Main.java:987"
        },
        {
          "method": "org.eclipse.core.launcher.Main.main",
          "source": "Main.java:962"
        }
      ],
      "number": 0,
      "commentIndex": 0,
      "bugId": "164155",
      "date": "2006-11-10T18:48:08+01:00",
      "product": "Web Tools",
      "component": "jst.j2ee",
      "severity": "normal"
    }
  ],
  "groupId": "164155",
  "bugId": "164155",
  "date": "2006-11-10T18:48:08+01:00",
  "product": "Web Tools",
  "component": "jst.j2ee",
  "severity": "normal"
}