{
  "comments": [
    "I20061114-1636\n\nWhen I start I20061114-1636 with the YourKit Plug-in (5.5.4.934), I get a bunch of NPEs, and YourKit\u0027s IDE integration does not work. A problem could be that the YourKit plug-in uses the deprecated form\n    \u003cextension point\u003d\"org.eclipse.ui.startup\"/\u003e\n, which has already caused the problems in bug 128178.\n\nExactly the same configuration worked without problems in I20061108-1600.\n\nFirst NPEs:\n\njava.lang.NullPointerException\n        at org.eclipse.core.internal.compatibility.PluginActivator.start(PluginActivator.java:34)\n        at org.eclipse.osgi.framework.internal.core.BundleContextImpl$2.run(BundleContextImpl.java:999)\n        at java.security.AccessController.doPrivileged(Native Method)\n        at org.eclipse.osgi.framework.internal.core.BundleContextImpl.startActivator(BundleContextImpl.java:993)\n        at org.eclipse.osgi.framework.internal.core.BundleContextImpl.start(BundleContextImpl.java:974)\n        at org.eclipse.osgi.framework.internal.core.BundleHost.startWorker(BundleHost.java:327)\n        at org.eclipse.osgi.framework.internal.core.AbstractBundle.start(AbstractBundle.java:260)\n        at org.eclipse.osgi.framework.util.SecureAction.start(SecureAction.java:385)\n        at org.eclipse.core.runtime.internal.adaptor.EclipseLazyStarter.postFindLocalClass(EclipseLazyStarter.java:110)\n        at org.eclipse.osgi.baseadaptor.loader.ClasspathManager.findLocalClass(ClasspathManager.java:415)\n        at org.eclipse.osgi.internal.baseadaptor.DefaultClassLoader.findLocalClass(DefaultClassLoader.java:189)\n        at org.eclipse.osgi.framework.internal.core.BundleLoader.findLocalClass(BundleLoader.java:335)\n        at org.eclipse.osgi.framework.internal.core.BundleLoader.findClass(BundleLoader.java:393)\n        at org.eclipse.osgi.framework.internal.core.BundleLoader.findClass(BundleLoader.java:352)\n        at org.eclipse.osgi.internal.baseadaptor.DefaultClassLoader.loadClass(DefaultClassLoader.java:83)\n        at java.lang.ClassLoader.loadClass(ClassLoader.java:251)\n        at org.eclipse.osgi.framework.internal.core.BundleLoader.loadClass(BundleLoader.java:278)\n        at org.eclipse.osgi.framework.internal.core.BundleHost.loadClass(BundleHost.java:227)\n        at org.eclipse.osgi.framework.internal.core.AbstractBundle.loadClass(AbstractBundle.java:1269)\n        at org.eclipse.core.internal.plugins.PluginDescriptor.internalDoPluginActivation(PluginDescriptor.java:406)\n        at org.eclipse.core.internal.plugins.PluginDescriptor.doPluginActivation(PluginDescriptor.java:371)\n        at org.eclipse.core.internal.plugins.PluginDescriptor.getPlugin(PluginDescriptor.java:340)\n        at sun.reflect.NativeMethodAccessorImpl.invoke0(Native Method)\n        at sun.reflect.NativeMethodAccessorImpl.invoke(NativeMethodAccessorImpl.java:39)\n        at sun.reflect.DelegatingMethodAccessorImpl.invoke(DelegatingMethodAccessorImpl.java:25)\n        at java.lang.reflect.Method.invoke(Method.java:585)\n        at org.eclipse.ui.internal.EarlyStartupRunnable.getPluginForCompatibility(EarlyStartupRunnable.java:149)\n        at org.eclipse.ui.internal.EarlyStartupRunnable.run(EarlyStartupRunnable.java:73)\n        at org.eclipse.core.runtime.SafeRunner.run(SafeRunner.java:37)\n        at org.eclipse.ui.internal.Workbench$21.run(Workbench.java:1781)\n        at org.eclipse.core.internal.jobs.Worker.run(Worker.java:58)\n\n!ENTRY org.eclipse.osgi 4 0 2006-11-15 10:36:20.851\n!MESSAGE An error occurred while automatically activating bundle com.yourkit.profiler (122).\n!STACK 0\norg.osgi.framework.BundleException: Exception in org.eclipse.core.internal.compatibility.PluginActivator.start() of bundle com.yourkit.profiler.\n        at org.eclipse.osgi.framework.internal.core.BundleContextImpl.startActivator(BundleContextImpl.java:1018)\n        at org.eclipse.osgi.framework.internal.core.BundleContextImpl.start(BundleContextImpl.java:974)\n        at org.eclipse.osgi.framework.internal.core.BundleHost.startWorker(BundleHost.java:327)\n        at org.eclipse.osgi.framework.internal.core.AbstractBundle.start(AbstractBundle.java:260)\n        at org.eclipse.osgi.framework.util.SecureAction.start(SecureAction.java:385)\n        at org.eclipse.core.runtime.internal.adaptor.EclipseLazyStarter.postFindLocalClass(EclipseLazyStarter.java:110)\n        at org.eclipse.osgi.baseadaptor.loader.ClasspathManager.findLocalClass(ClasspathManager.java:415)\n        at org.eclipse.osgi.internal.baseadaptor.DefaultClassLoader.findLocalClass(DefaultClassLoader.java:189)\n        at org.eclipse.osgi.framework.internal.core.BundleLoader.findLocalClass(BundleLoader.java:335)\n        at org.eclipse.osgi.framework.internal.core.BundleLoader.findClass(BundleLoader.java:393)\n        at org.eclipse.osgi.framework.internal.core.BundleLoader.findClass(BundleLoader.java:352)\n        at org.eclipse.osgi.internal.baseadaptor.DefaultClassLoader.loadClass(DefaultClassLoader.java:83)\n        at java.lang.ClassLoader.loadClass(ClassLoader.java:251)\n        at org.eclipse.osgi.framework.internal.core.BundleLoader.loadClass(BundleLoader.java:278)\n        at org.eclipse.osgi.framework.internal.core.BundleHost.loadClass(BundleHost.java:227)\n        at org.eclipse.osgi.framework.internal.core.AbstractBundle.loadClass(AbstractBundle.java:1269)\n        at org.eclipse.core.internal.plugins.PluginDescriptor.internalDoPluginActivation(PluginDescriptor.java:406)\n        at org.eclipse.core.internal.plugins.PluginDescriptor.doPluginActivation(PluginDescriptor.java:371)\n        at org.eclipse.core.internal.plugins.PluginDescriptor.getPlugin(PluginDescriptor.java:340)\n        at sun.reflect.NativeMethodAccessorImpl.invoke0(Native Method)\n        at sun.reflect.NativeMethodAccessorImpl.invoke(NativeMethodAccessorImpl.java:39)\n        at sun.reflect.DelegatingMethodAccessorImpl.invoke(DelegatingMethodAccessorImpl.java:25)\n        at java.lang.reflect.Method.invoke(Method.java:585)\n        at org.eclipse.ui.internal.EarlyStartupRunnable.getPluginForCompatibility(EarlyStartupRunnable.java:149)\n        at org.eclipse.ui.internal.EarlyStartupRunnable.run(EarlyStartupRunnable.java:73)\n        at org.eclipse.core.runtime.SafeRunner.run(SafeRunner.java:37)\n        at org.eclipse.ui.internal.Workbench$21.run(Workbench.java:1781)\n        at org.eclipse.core.internal.jobs.Worker.run(Worker.java:58)\nCaused by: java.lang.NullPointerException\n        at org.eclipse.core.internal.compatibility.PluginActivator.start(PluginActivator.java:30)\n        at org.eclipse.osgi.framework.internal.core.BundleContextImpl$2.run(BundleContextImpl.java:999)\n        at java.security.AccessController.doPrivileged(Native Method)\n        at org.eclipse.osgi.framework.internal.core.BundleContextImpl.startActivator(BundleContextImpl.java:993)\n        ... 27 more\nRoot exception:\njava.lang.NullPointerException\n        at org.eclipse.core.internal.compatibility.PluginActivator.start(PluginActivator.java:30)\n        at org.eclipse.osgi.framework.internal.core.BundleContextImpl$2.run(BundleContextImpl.java:999)\n        at java.security.AccessController.doPrivileged(Native Method)\n        at org.eclipse.osgi.framework.internal.core.BundleContextImpl.startActivator(BundleContextImpl.java:993)\n        at org.eclipse.osgi.framework.internal.core.BundleContextImpl.start(BundleContextImpl.java:974)\n        at org.eclipse.osgi.framework.internal.core.BundleHost.startWorker(BundleHost.java:327)\n        at org.eclipse.osgi.framework.internal.core.AbstractBundle.start(AbstractBundle.java:260)\n        at org.eclipse.osgi.framework.util.SecureAction.start(SecureAction.java:385)\n        at org.eclipse.core.runtime.internal.adaptor.EclipseLazyStarter.postFindLocalClass(EclipseLazyStarter.java:110)\n        at org.eclipse.osgi.baseadaptor.loader.ClasspathManager.findLocalClass(ClasspathManager.java:415)\n        at org.eclipse.osgi.internal.baseadaptor.DefaultClassLoader.findLocalClass(DefaultClassLoader.java:189)\n        at org.eclipse.osgi.framework.internal.core.BundleLoader.findLocalClass(BundleLoader.java:335)\n        at org.eclipse.osgi.framework.internal.core.BundleLoader.findClass(BundleLoader.java:393)\n        at org.eclipse.osgi.framework.internal.core.BundleLoader.findClass(BundleLoader.java:352)\n        at org.eclipse.osgi.internal.baseadaptor.DefaultClassLoader.loadClass(DefaultClassLoader.java:83)\n        at java.lang.ClassLoader.loadClass(ClassLoader.java:251)\n        at org.eclipse.osgi.framework.internal.core.BundleLoader.loadClass(BundleLoader.java:278)\n        at org.eclipse.osgi.framework.internal.core.BundleHost.loadClass(BundleHost.java:227)\n        at org.eclipse.osgi.framework.internal.core.AbstractBundle.loadClass(AbstractBundle.java:1269)\n        at org.eclipse.core.internal.plugins.PluginDescriptor.internalDoPluginActivation(PluginDescriptor.java:406)\n        at org.eclipse.core.internal.plugins.PluginDescriptor.doPluginActivation(PluginDescriptor.java:371)\n        at org.eclipse.core.internal.plugins.PluginDescriptor.getPlugin(PluginDescriptor.java:340)\n        at sun.reflect.NativeMethodAccessorImpl.invoke0(Native Method)\n        at sun.reflect.NativeMethodAccessorImpl.invoke(NativeMethodAccessorImpl.java:39)\n        at sun.reflect.DelegatingMethodAccessorImpl.invoke(DelegatingMethodAccessorImpl.java:25)\n        at java.lang.reflect.Method.invoke(Method.java:585)\n        at org.eclipse.ui.internal.EarlyStartupRunnable.getPluginForCompatibility(EarlyStartupRunnable.java:149)\n        at org.eclipse.ui.internal.EarlyStartupRunnable.run(EarlyStartupRunnable.java:73)\n        at org.eclipse.core.runtime.SafeRunner.run(SafeRunner.java:37)\n        at org.eclipse.ui.internal.Workbench$21.run(Workbench.java:1781)\n        at org.eclipse.core.internal.jobs.Worker.run(Worker.java:58)",
    "Created an attachment (id\u003d53894)\nComplete console log\n\n",
    "Tom could not that be caused by the change in boot delegation?",
    "No, this is being caused by the changes to lazy-start and the Bundle.STARTING state that all bundles are in.  I will investigate a fix.\n\nBJ, this is one of the scenarios where it is difficult to tell if a bundle is in the STARTING state because it is waiting to lazy-start or because it is actually activating.",
    "Created an attachment (id\u003d53913)\npatch\n\nHere is a fix.  This patch uses the new Bundle.start(START_TRANSIENT) method to activate bundles instead of calling Bundle.loadClass.  Pascal, please review.",
    "Patch looks good.",
    "Released fix to HEAD.\n\nMarkus, the fix is to the following plug-ins.\n\norg.eclipse.core.runtime\norg.eclipse.core.runtime.compatibility\n\nYou can build from head or do you think this demands a rebuild of the I-Build?",
    "I don\u0027t need a rebuild.\n\nProfiling still works fine, I just can\u0027t jump from YourKit to Eclipse with a single click any more. I\u0027ll verify the fix in the next usable N-build.\n\nI can only speak for myself, since I don\u0027t know under what circumstances other users/plug-ins are affected. But if have not heard from many others, I guess it\u0027s not an urgent problem.",
    "Verified in I20061121-1845."
  ],
  "commentCreationDates": [
    "2006-11-15T10:09:16+01:00",
    "2006-11-15T10:09:55+01:00",
    "2006-11-15T13:03:43+01:00",
    "2006-11-15T14:22:17+01:00",
    "2006-11-15T15:07:16+01:00",
    "2006-11-15T15:20:26+01:00",
    "2006-11-15T16:02:03+01:00",
    "2006-11-15T16:26:53+01:00",
    "2006-11-22T18:57:06+01:00"
  ],
  "traces": [
    {
      "exceptionType": "java.lang.NullPointerException",
      "elements": [
        {
          "method": "org.eclipse.core.internal.compatibility.PluginActivator.start",
          "source": "PluginActivator.java:34"
        },
        {
          "method": "org.eclipse.osgi.framework.internal.core.BundleContextImpl$2.run",
          "source": "BundleContextImpl.java:999"
        },
        {
          "method": "java.security.AccessController.doPrivileged",
          "source": "Native Method"
        },
        {
          "method": "org.eclipse.osgi.framework.internal.core.BundleContextImpl.startActivator",
          "source": "BundleContextImpl.java:993"
        },
        {
          "method": "org.eclipse.osgi.framework.internal.core.BundleContextImpl.start",
          "source": "BundleContextImpl.java:974"
        },
        {
          "method": "org.eclipse.osgi.framework.internal.core.BundleHost.startWorker",
          "source": "BundleHost.java:327"
        },
        {
          "method": "org.eclipse.osgi.framework.internal.core.AbstractBundle.start",
          "source": "AbstractBundle.java:260"
        },
        {
          "method": "org.eclipse.osgi.framework.util.SecureAction.start",
          "source": "SecureAction.java:385"
        },
        {
          "method": "org.eclipse.core.runtime.internal.adaptor.EclipseLazyStarter.postFindLocalClass",
          "source": "EclipseLazyStarter.java:110"
        },
        {
          "method": "org.eclipse.osgi.baseadaptor.loader.ClasspathManager.findLocalClass",
          "source": "ClasspathManager.java:415"
        },
        {
          "method": "org.eclipse.osgi.internal.baseadaptor.DefaultClassLoader.findLocalClass",
          "source": "DefaultClassLoader.java:189"
        },
        {
          "method": "org.eclipse.osgi.framework.internal.core.BundleLoader.findLocalClass",
          "source": "BundleLoader.java:335"
        },
        {
          "method": "org.eclipse.osgi.framework.internal.core.BundleLoader.findClass",
          "source": "BundleLoader.java:393"
        },
        {
          "method": "org.eclipse.osgi.framework.internal.core.BundleLoader.findClass",
          "source": "BundleLoader.java:352"
        },
        {
          "method": "org.eclipse.osgi.internal.baseadaptor.DefaultClassLoader.loadClass",
          "source": "DefaultClassLoader.java:83"
        },
        {
          "method": "java.lang.ClassLoader.loadClass",
          "source": "ClassLoader.java:251"
        },
        {
          "method": "org.eclipse.osgi.framework.internal.core.BundleLoader.loadClass",
          "source": "BundleLoader.java:278"
        },
        {
          "method": "org.eclipse.osgi.framework.internal.core.BundleHost.loadClass",
          "source": "BundleHost.java:227"
        },
        {
          "method": "org.eclipse.osgi.framework.internal.core.AbstractBundle.loadClass",
          "source": "AbstractBundle.java:1269"
        },
        {
          "method": "org.eclipse.core.internal.plugins.PluginDescriptor.internalDoPluginActivation",
          "source": "PluginDescriptor.java:406"
        },
        {
          "method": "org.eclipse.core.internal.plugins.PluginDescriptor.doPluginActivation",
          "source": "PluginDescriptor.java:371"
        },
        {
          "method": "org.eclipse.core.internal.plugins.PluginDescriptor.getPlugin",
          "source": "PluginDescriptor.java:340"
        },
        {
          "method": "sun.reflect.NativeMethodAccessorImpl.invoke0",
          "source": "Native Method"
        },
        {
          "method": "sun.reflect.NativeMethodAccessorImpl.invoke",
          "source": "NativeMethodAccessorImpl.java:39"
        },
        {
          "method": "sun.reflect.DelegatingMethodAccessorImpl.invoke",
          "source": "DelegatingMethodAccessorImpl.java:25"
        },
        {
          "method": "java.lang.reflect.Method.invoke",
          "source": "Method.java:585"
        },
        {
          "method": "org.eclipse.ui.internal.EarlyStartupRunnable.getPluginForCompatibility",
          "source": "EarlyStartupRunnable.java:149"
        },
        {
          "method": "org.eclipse.ui.internal.EarlyStartupRunnable.run",
          "source": "EarlyStartupRunnable.java:73"
        },
        {
          "method": "org.eclipse.core.runtime.SafeRunner.run",
          "source": "SafeRunner.java:37"
        },
        {
          "method": "org.eclipse.ui.internal.Workbench$21.run",
          "source": "Workbench.java:1781"
        },
        {
          "method": "org.eclipse.core.internal.jobs.Worker.run",
          "source": "Worker.java:58"
        }
      ],
      "number": 0,
      "commentIndex": 0,
      "bugId": "164612",
      "date": "2006-11-15T10:09:16+01:00",
      "product": "Equinox",
      "component": "Framework",
      "severity": "major"
    },
    {
      "exceptionType": "org.osgi.framework.BundleException",
      "message": "Exception in org.eclipse.core.internal.compatibility.PluginActivator.start() of bundle com.yourkit.profiler.",
      "elements": [
        {
          "method": "org.eclipse.osgi.framework.internal.core.BundleContextImpl.startActivator",
          "source": "BundleContextImpl.java:1018"
        },
        {
          "method": "org.eclipse.osgi.framework.internal.core.BundleContextImpl.start",
          "source": "BundleContextImpl.java:974"
        },
        {
          "method": "org.eclipse.osgi.framework.internal.core.BundleHost.startWorker",
          "source": "BundleHost.java:327"
        },
        {
          "method": "org.eclipse.osgi.framework.internal.core.AbstractBundle.start",
          "source": "AbstractBundle.java:260"
        },
        {
          "method": "org.eclipse.osgi.framework.util.SecureAction.start",
          "source": "SecureAction.java:385"
        },
        {
          "method": "org.eclipse.core.runtime.internal.adaptor.EclipseLazyStarter.postFindLocalClass",
          "source": "EclipseLazyStarter.java:110"
        },
        {
          "method": "org.eclipse.osgi.baseadaptor.loader.ClasspathManager.findLocalClass",
          "source": "ClasspathManager.java:415"
        },
        {
          "method": "org.eclipse.osgi.internal.baseadaptor.DefaultClassLoader.findLocalClass",
          "source": "DefaultClassLoader.java:189"
        },
        {
          "method": "org.eclipse.osgi.framework.internal.core.BundleLoader.findLocalClass",
          "source": "BundleLoader.java:335"
        },
        {
          "method": "org.eclipse.osgi.framework.internal.core.BundleLoader.findClass",
          "source": "BundleLoader.java:393"
        },
        {
          "method": "org.eclipse.osgi.framework.internal.core.BundleLoader.findClass",
          "source": "BundleLoader.java:352"
        },
        {
          "method": "org.eclipse.osgi.internal.baseadaptor.DefaultClassLoader.loadClass",
          "source": "DefaultClassLoader.java:83"
        },
        {
          "method": "java.lang.ClassLoader.loadClass",
          "source": "ClassLoader.java:251"
        },
        {
          "method": "org.eclipse.osgi.framework.internal.core.BundleLoader.loadClass",
          "source": "BundleLoader.java:278"
        },
        {
          "method": "org.eclipse.osgi.framework.internal.core.BundleHost.loadClass",
          "source": "BundleHost.java:227"
        },
        {
          "method": "org.eclipse.osgi.framework.internal.core.AbstractBundle.loadClass",
          "source": "AbstractBundle.java:1269"
        },
        {
          "method": "org.eclipse.core.internal.plugins.PluginDescriptor.internalDoPluginActivation",
          "source": "PluginDescriptor.java:406"
        },
        {
          "method": "org.eclipse.core.internal.plugins.PluginDescriptor.doPluginActivation",
          "source": "PluginDescriptor.java:371"
        },
        {
          "method": "org.eclipse.core.internal.plugins.PluginDescriptor.getPlugin",
          "source": "PluginDescriptor.java:340"
        },
        {
          "method": "sun.reflect.NativeMethodAccessorImpl.invoke0",
          "source": "Native Method"
        },
        {
          "method": "sun.reflect.NativeMethodAccessorImpl.invoke",
          "source": "NativeMethodAccessorImpl.java:39"
        },
        {
          "method": "sun.reflect.DelegatingMethodAccessorImpl.invoke",
          "source": "DelegatingMethodAccessorImpl.java:25"
        },
        {
          "method": "java.lang.reflect.Method.invoke",
          "source": "Method.java:585"
        },
        {
          "method": "org.eclipse.ui.internal.EarlyStartupRunnable.getPluginForCompatibility",
          "source": "EarlyStartupRunnable.java:149"
        },
        {
          "method": "org.eclipse.ui.internal.EarlyStartupRunnable.run",
          "source": "EarlyStartupRunnable.java:73"
        },
        {
          "method": "org.eclipse.core.runtime.SafeRunner.run",
          "source": "SafeRunner.java:37"
        },
        {
          "method": "org.eclipse.ui.internal.Workbench$21.run",
          "source": "Workbench.java:1781"
        },
        {
          "method": "org.eclipse.core.internal.jobs.Worker.run",
          "source": "Worker.java:58"
        }
      ],
      "causedBy": {
        "exceptionType": "java.lang.NullPointerException",
        "elements": [
          {
            "method": "org.eclipse.core.internal.compatibility.PluginActivator.start",
            "source": "PluginActivator.java:30"
          },
          {
            "method": "org.eclipse.osgi.framework.internal.core.BundleContextImpl$2.run",
            "source": "BundleContextImpl.java:999"
          },
          {
            "method": "java.security.AccessController.doPrivileged",
            "source": "Native Method"
          },
          {
            "method": "org.eclipse.osgi.framework.internal.core.BundleContextImpl.startActivator",
            "source": "BundleContextImpl.java:993"
          }
        ],
        "number": 0,
        "commentIndex": 0
      },
      "number": 1,
      "commentIndex": 0,
      "bugId": "164612",
      "date": "2006-11-15T10:09:16+01:00",
      "product": "Equinox",
      "component": "Framework",
      "severity": "major"
    },
    {
      "exceptionType": "java.lang.NullPointerException",
      "elements": [
        {
          "method": "org.eclipse.core.internal.compatibility.PluginActivator.start",
          "source": "PluginActivator.java:30"
        },
        {
          "method": "org.eclipse.osgi.framework.internal.core.BundleContextImpl$2.run",
          "source": "BundleContextImpl.java:999"
        },
        {
          "method": "java.security.AccessController.doPrivileged",
          "source": "Native Method"
        },
        {
          "method": "org.eclipse.osgi.framework.internal.core.BundleContextImpl.startActivator",
          "source": "BundleContextImpl.java:993"
        },
        {
          "method": "org.eclipse.osgi.framework.internal.core.BundleContextImpl.start",
          "source": "BundleContextImpl.java:974"
        },
        {
          "method": "org.eclipse.osgi.framework.internal.core.BundleHost.startWorker",
          "source": "BundleHost.java:327"
        },
        {
          "method": "org.eclipse.osgi.framework.internal.core.AbstractBundle.start",
          "source": "AbstractBundle.java:260"
        },
        {
          "method": "org.eclipse.osgi.framework.util.SecureAction.start",
          "source": "SecureAction.java:385"
        },
        {
          "method": "org.eclipse.core.runtime.internal.adaptor.EclipseLazyStarter.postFindLocalClass",
          "source": "EclipseLazyStarter.java:110"
        },
        {
          "method": "org.eclipse.osgi.baseadaptor.loader.ClasspathManager.findLocalClass",
          "source": "ClasspathManager.java:415"
        },
        {
          "method": "org.eclipse.osgi.internal.baseadaptor.DefaultClassLoader.findLocalClass",
          "source": "DefaultClassLoader.java:189"
        },
        {
          "method": "org.eclipse.osgi.framework.internal.core.BundleLoader.findLocalClass",
          "source": "BundleLoader.java:335"
        },
        {
          "method": "org.eclipse.osgi.framework.internal.core.BundleLoader.findClass",
          "source": "BundleLoader.java:393"
        },
        {
          "method": "org.eclipse.osgi.framework.internal.core.BundleLoader.findClass",
          "source": "BundleLoader.java:352"
        },
        {
          "method": "org.eclipse.osgi.internal.baseadaptor.DefaultClassLoader.loadClass",
          "source": "DefaultClassLoader.java:83"
        },
        {
          "method": "java.lang.ClassLoader.loadClass",
          "source": "ClassLoader.java:251"
        },
        {
          "method": "org.eclipse.osgi.framework.internal.core.BundleLoader.loadClass",
          "source": "BundleLoader.java:278"
        },
        {
          "method": "org.eclipse.osgi.framework.internal.core.BundleHost.loadClass",
          "source": "BundleHost.java:227"
        },
        {
          "method": "org.eclipse.osgi.framework.internal.core.AbstractBundle.loadClass",
          "source": "AbstractBundle.java:1269"
        },
        {
          "method": "org.eclipse.core.internal.plugins.PluginDescriptor.internalDoPluginActivation",
          "source": "PluginDescriptor.java:406"
        },
        {
          "method": "org.eclipse.core.internal.plugins.PluginDescriptor.doPluginActivation",
          "source": "PluginDescriptor.java:371"
        },
        {
          "method": "org.eclipse.core.internal.plugins.PluginDescriptor.getPlugin",
          "source": "PluginDescriptor.java:340"
        },
        {
          "method": "sun.reflect.NativeMethodAccessorImpl.invoke0",
          "source": "Native Method"
        },
        {
          "method": "sun.reflect.NativeMethodAccessorImpl.invoke",
          "source": "NativeMethodAccessorImpl.java:39"
        },
        {
          "method": "sun.reflect.DelegatingMethodAccessorImpl.invoke",
          "source": "DelegatingMethodAccessorImpl.java:25"
        },
        {
          "method": "java.lang.reflect.Method.invoke",
          "source": "Method.java:585"
        },
        {
          "method": "org.eclipse.ui.internal.EarlyStartupRunnable.getPluginForCompatibility",
          "source": "EarlyStartupRunnable.java:149"
        },
        {
          "method": "org.eclipse.ui.internal.EarlyStartupRunnable.run",
          "source": "EarlyStartupRunnable.java:73"
        },
        {
          "method": "org.eclipse.core.runtime.SafeRunner.run",
          "source": "SafeRunner.java:37"
        },
        {
          "method": "org.eclipse.ui.internal.Workbench$21.run",
          "source": "Workbench.java:1781"
        },
        {
          "method": "org.eclipse.core.internal.jobs.Worker.run",
          "source": "Worker.java:58"
        }
      ],
      "number": 2,
      "commentIndex": 0,
      "bugId": "164612",
      "date": "2006-11-15T10:09:16+01:00",
      "product": "Equinox",
      "component": "Framework",
      "severity": "major"
    }
  ],
  "groupId": "164612",
  "bugId": "164612",
  "date": "2006-11-15T10:09:16+01:00",
  "product": "Equinox",
  "component": "Framework",
  "severity": "major"
}