{
  "comments": [
    "Build: 20020519\n\nVM: IBM JDK 1.3.1 20020403\n\nThe following stack trace appeared in the console (not in the log!).  I don\u0027t\nknow when it occured, but I thought it looked important.  Sorry, I don\u0027t have a\ntest case.\n\njava.lang.ArrayIndexOutOfBoundsException: 15787\n        at java.lang.StringBuffer.append(StringBuffer.java(Compiled Code))\n        at java.lang.StringBuffer.append(StringBuffer.java(Compiled Code))\n        at org.eclipse.jface.text.GapTextStore.get(GapTextStore.java(Compiled Code))\n        at org.eclipse.jface.text.AbstractDocument.get(AbstractDocument.java:716)\n        at\norg.eclipse.jdt.internal.ui.javaeditor.DocumentAdapter.getContents(DocumentAdapter.java:358)\n        at\norg.eclipse.jdt.internal.ui.javaeditor.DocumentAdapter.getCharacters(DocumentAdapter.java:350)\n        at\norg.eclipse.jdt.internal.core.CompilationUnit.getContents(CompilationUnit.java:409)\n        at org.eclipse.jdt.internal.compiler.parser.Parser.parse(Parser.java:6967)\n        at\norg.eclipse.jdt.internal.compiler.SourceElementParser.parseCompilationUnit(SourceElementParser.java:1036)\n        at\norg.eclipse.jdt.internal.core.CompilationUnit.generateInfos(CompilationUnit.java:363)\n        at\norg.eclipse.jdt.internal.core.CompilationUnit.buildStructure(CompilationUnit.java:102)\n        at\norg.eclipse.jdt.internal.core.CompilationUnit.makeConsistent(CompilationUnit.java:700)\n        at org.eclipse.jdt.internal.core.WorkingCopy.reconcile(WorkingCopy.java:380)\n        at\norg.eclipse.jdt.internal.ui.text.java.JavaReconcilingStrategy.reconcile(JavaReconcilingStrategy.java:71)\n        at\norg.eclipse.jdt.internal.ui.text.java.JavaReconcilingStrategy.reconcile(JavaReconcilingStrategy.java:93)\n        at\norg.eclipse.jface.text.reconciler.MonoReconciler.process(MonoReconciler.java:68)\n        at\norg.eclipse.jface.text.reconciler.AbstractReconciler$BackgroundThread.run(AbstractReconciler.java:168)",
    "The comilation unit editor now uses a synchronized document. I.e. reading and \ncontent modification are mutally excluded. Build F2.",
    "pls verify",
    "pls ignore",
    "pls ignore",
    "Cannot verify with reasonable effort.",
    "Closing since there isn\u0027t a repeatable test case"
  ],
  "commentCreationDates": [
    "2002-05-21T02:18:07+02:00",
    "2002-05-31T12:08:16+02:00",
    "2002-06-02T23:28:38+02:00",
    "2002-06-04T11:59:56+02:00",
    "2002-06-04T12:00:18+02:00",
    "2002-06-04T12:00:55+02:00",
    "2002-06-13T16:52:42+02:00"
  ],
  "traces": [
    {
      "exceptionType": "java.lang.ArrayIndexOutOfBoundsException",
      "message": "15787",
      "elements": [
        {
          "method": "java.lang.StringBuffer.append",
          "source": "StringBuffer.java(Compiled Code)"
        },
        {
          "method": "java.lang.StringBuffer.append",
          "source": "StringBuffer.java(Compiled Code)"
        },
        {
          "method": "org.eclipse.jface.text.GapTextStore.get",
          "source": "GapTextStore.java(Compiled Code)"
        },
        {
          "method": "org.eclipse.jface.text.AbstractDocument.get",
          "source": "AbstractDocument.java:716"
        },
        {
          "method": "org.eclipse.jdt.internal.ui.javaeditor.DocumentAdapter.getContents",
          "source": "DocumentAdapter.java:358"
        },
        {
          "method": "org.eclipse.jdt.internal.ui.javaeditor.DocumentAdapter.getCharacters",
          "source": "DocumentAdapter.java:350"
        },
        {
          "method": "org.eclipse.jdt.internal.core.CompilationUnit.getContents",
          "source": "CompilationUnit.java:409"
        },
        {
          "method": "org.eclipse.jdt.internal.compiler.parser.Parser.parse",
          "source": "Parser.java:6967"
        },
        {
          "method": "org.eclipse.jdt.internal.compiler.SourceElementParser.parseCompilationUnit",
          "source": "SourceElementParser.java:1036"
        },
        {
          "method": "org.eclipse.jdt.internal.core.CompilationUnit.generateInfos",
          "source": "CompilationUnit.java:363"
        },
        {
          "method": "org.eclipse.jdt.internal.core.CompilationUnit.buildStructure",
          "source": "CompilationUnit.java:102"
        },
        {
          "method": "org.eclipse.jdt.internal.core.CompilationUnit.makeConsistent",
          "source": "CompilationUnit.java:700"
        },
        {
          "method": "org.eclipse.jdt.internal.core.WorkingCopy.reconcile",
          "source": "WorkingCopy.java:380"
        },
        {
          "method": "org.eclipse.jdt.internal.ui.text.java.JavaReconcilingStrategy.reconcile",
          "source": "JavaReconcilingStrategy.java:71"
        },
        {
          "method": "org.eclipse.jdt.internal.ui.text.java.JavaReconcilingStrategy.reconcile",
          "source": "JavaReconcilingStrategy.java:93"
        },
        {
          "method": "org.eclipse.jface.text.reconciler.MonoReconciler.process",
          "source": "MonoReconciler.java:68"
        },
        {
          "method": "org.eclipse.jface.text.reconciler.AbstractReconciler$BackgroundThread.run",
          "source": "AbstractReconciler.java:168"
        }
      ],
      "number": 0,
      "commentIndex": 0,
      "bugId": "16508",
      "date": "2002-05-21T02:18:07+02:00",
      "product": "JDT",
      "component": "UI",
      "severity": "normal"
    }
  ],
  "groupId": "16508",
  "bugId": "16508",
  "date": "2002-05-21T02:18:07+02:00",
  "product": "JDT",
  "component": "UI",
  "severity": "normal"
}