{
  "comments": [
    "I20061121-1845\n\n- new workspace\n- create Java project with a main class\n- switch to Debug perspective, debug the main class\n- in Debug view, enable Show Monitors\n- export all preferences\n- disable Show Monitors\n- import all preferences\n\n\u003d\u003e Error dialog with CCE:\n\n!ENTRY org.eclipse.ui.workbench 4 2 2006-11-28 13:06:49.849\n!MESSAGE Problems occurred when invoking code from plug-in: \"org.eclipse.ui.workbench\".\n!STACK 0\njava.lang.ClassCastException: java.lang.String\n        at org.eclipse.jdt.internal.debug.ui.monitors.JavaElementContentProvider$1.propertyChange(JavaElementContentProvider.java:38)\n        at org.eclipse.ui.preferences.ScopedPreferenceStore$3.run(ScopedPreferenceStore.java:371)\n        at org.eclipse.core.runtime.SafeRunner.run(SafeRunner.java:37)\n        at org.eclipse.ui.preferences.ScopedPreferenceStore.firePropertyChangeEvent(ScopedPreferenceStore.java:368)\n        at org.eclipse.ui.preferences.ScopedPreferenceStore$2.preferenceChange(ScopedPreferenceStore.java:192)\n        at org.eclipse.core.internal.preferences.EclipsePreferences$2.run(EclipsePreferences.java:746)\n        at org.eclipse.core.runtime.SafeRunner.run(SafeRunner.java:37)\n        at org.eclipse.core.internal.preferences.EclipsePreferences.firePreferenceEvent(EclipsePreferences.java:749)\n        at org.eclipse.core.internal.preferences.EclipsePreferences.put(EclipsePreferences.java:762)\n        at org.eclipse.core.internal.preferences.PreferencesService.copyFromTo(PreferencesService.java:325)\n        at org.eclipse.core.internal.preferences.PreferencesService$5.visit(PreferencesService.java:667)\n        at org.eclipse.core.internal.preferences.EclipsePreferences.accept(EclipsePreferences.java:105)\n        at org.eclipse.core.internal.preferences.EclipsePreferences.accept(EclipsePreferences.java:109)\n        at org.eclipse.core.internal.preferences.EclipsePreferences.accept(EclipsePreferences.java:109)\n        at org.eclipse.core.internal.preferences.PreferencesService.internalApply(PreferencesService.java:671)\n        at org.eclipse.core.internal.preferences.PreferencesService.applyPreferences(PreferencesService.java:91)\n        at org.eclipse.ui.internal.wizards.preferences.WizardPreferencesImportPage1.transfer(WizardPreferencesImportPage1.java:182)\n        at org.eclipse.ui.internal.wizards.preferences.WizardPreferencesPage.finish(WizardPreferencesPage.java:595)\n        at org.eclipse.ui.internal.wizards.preferences.PreferencesImportWizard.performFinish(PreferencesImportWizard.java:88)\n        at org.eclipse.jface.wizard.WizardDialog.finishPressed(WizardDialog.java:695)\n        at org.eclipse.jface.wizard.WizardDialog.buttonPressed(WizardDialog.java:367)\n        at org.eclipse.jface.dialogs.Dialog$3.widgetSelected(Dialog.java:638)\n        at org.eclipse.swt.widgets.TypedListener.handleEvent(TypedListener.java:90)\n        at org.eclipse.swt.widgets.EventTable.sendEvent(EventTable.java:66)\n        at org.eclipse.swt.widgets.Widget.sendEvent(Widget.java:927)\n        at org.eclipse.swt.widgets.Display.runDeferredEvents(Display.java:3463)\n        at org.eclipse.swt.widgets.Display.readAndDispatch(Display.java:3077)\n        at org.eclipse.jface.window.Window.runEventLoop(Window.java:820)\n        at org.eclipse.jface.window.Window.open(Window.java:796)\n        at org.eclipse.ui.actions.ImportResourcesAction.run(ImportResourcesAction.java:159)\n        at org.eclipse.ui.actions.BaseSelectionListenerAction.runWithEvent(BaseSelectionListenerAction.java:168)\n        at org.eclipse.jface.action.ActionContributionItem.handleWidgetSelection(ActionContributionItem.java:545)\n        at org.eclipse.jface.action.ActionContributionItem.access$2(ActionContributionItem.java:490)\n        at org.eclipse.jface.action.ActionContributionItem$5.handleEvent(ActionContributionItem.java:402)\n        at org.eclipse.swt.widgets.EventTable.sendEvent(EventTable.java:66)\n        at org.eclipse.swt.widgets.Widget.sendEvent(Widget.java:927)\n        at org.eclipse.swt.widgets.Display.runDeferredEvents(Display.java:3463)\n        at org.eclipse.swt.widgets.Display.readAndDispatch(Display.java:3077)\n        at org.eclipse.ui.internal.Workbench.runEventLoop(Workbench.java:1945)\n        at org.eclipse.ui.internal.Workbench.runUI(Workbench.java:1909)\n        at org.eclipse.ui.internal.Workbench.createAndRunWorkbench(Workbench.java:425)\n        at org.eclipse.ui.PlatformUI.createAndRunWorkbench(PlatformUI.java:149)\n        at org.eclipse.ui.internal.ide.IDEApplication.run(IDEApplication.java:95)\n        at org.eclipse.core.internal.runtime.PlatformActivator$1.run(PlatformActivator.java:78)\n        at org.eclipse.core.runtime.internal.adaptor.EclipseAppLauncher.runApplication(EclipseAppLauncher.java:104)\n        at org.eclipse.core.runtime.internal.adaptor.EclipseAppLauncher.start(EclipseAppLauncher.java:74)\n        at org.eclipse.core.runtime.adaptor.EclipseStarter.run(EclipseStarter.java:348)\n        at org.eclipse.core.runtime.adaptor.EclipseStarter.run(EclipseStarter.java:165)\n        at sun.reflect.NativeMethodAccessorImpl.invoke0(Native Method)\n        at sun.reflect.NativeMethodAccessorImpl.invoke(NativeMethodAccessorImpl.java:39)\n        at sun.reflect.DelegatingMethodAccessorImpl.invoke(DelegatingMethodAccessorImpl.java:25)\n        at java.lang.reflect.Method.invoke(Method.java:585)\n        at org.eclipse.core.launcher.Main.invokeFramework(Main.java:341)\n        at org.eclipse.core.launcher.Main.basicRun(Main.java:285)\n        at org.eclipse.core.launcher.Main.run(Main.java:987)\n        at org.eclipse.core.launcher.Main.main(Main.java:962)",
    "Moving to platform for comment. When I toggle the preference manually (i.e. via \"Show Monitors\" action in debug view drop down menu), the value of the property is a Boolean. When I store the preference it is a \"boolean\". But, on import, it is a String.",
    "See the \"Note\" class comment on Preferences$IPropertyChangeListener.",
    "In this case you are using the JFace preference API, but it is also specified there (see the \"Note\" on org.eclipse.jface.preference.IPreferenceStore.addPropertyChangeListener)",
    "Fixed. Found a few places where this was a problem. Changes to:\n\n* JavaElementContentProvider\n* ThreadMonitorManager\n* JavaThreadEventHandler\n* JDIDebugUIPreferenceInitializer",
    "Please verify, Curtis.",
    "Also fixed ViewerFilterAction to update its toggle (checked) state to refelt its preference after the import.",
    "Verified"
  ],
  "commentCreationDates": [
    "2006-11-28T12:09:56+01:00",
    "2006-11-28T14:20:03+01:00",
    "2006-11-28T15:10:16+01:00",
    "2006-11-28T15:26:49+01:00",
    "2006-11-28T19:10:16+01:00",
    "2006-11-28T19:10:38+01:00",
    "2006-11-28T19:26:31+01:00",
    "2006-11-29T23:06:32+01:00"
  ],
  "traces": [
    {
      "exceptionType": "java.lang.ClassCastException",
      "message": "java.lang.String",
      "elements": [
        {
          "method": "org.eclipse.jdt.internal.debug.ui.monitors.JavaElementContentProvider$1.propertyChange",
          "source": "JavaElementContentProvider.java:38"
        },
        {
          "method": "org.eclipse.ui.preferences.ScopedPreferenceStore$3.run",
          "source": "ScopedPreferenceStore.java:371"
        },
        {
          "method": "org.eclipse.core.runtime.SafeRunner.run",
          "source": "SafeRunner.java:37"
        },
        {
          "method": "org.eclipse.ui.preferences.ScopedPreferenceStore.firePropertyChangeEvent",
          "source": "ScopedPreferenceStore.java:368"
        },
        {
          "method": "org.eclipse.ui.preferences.ScopedPreferenceStore$2.preferenceChange",
          "source": "ScopedPreferenceStore.java:192"
        },
        {
          "method": "org.eclipse.core.internal.preferences.EclipsePreferences$2.run",
          "source": "EclipsePreferences.java:746"
        },
        {
          "method": "org.eclipse.core.runtime.SafeRunner.run",
          "source": "SafeRunner.java:37"
        },
        {
          "method": "org.eclipse.core.internal.preferences.EclipsePreferences.firePreferenceEvent",
          "source": "EclipsePreferences.java:749"
        },
        {
          "method": "org.eclipse.core.internal.preferences.EclipsePreferences.put",
          "source": "EclipsePreferences.java:762"
        },
        {
          "method": "org.eclipse.core.internal.preferences.PreferencesService.copyFromTo",
          "source": "PreferencesService.java:325"
        },
        {
          "method": "org.eclipse.core.internal.preferences.PreferencesService$5.visit",
          "source": "PreferencesService.java:667"
        },
        {
          "method": "org.eclipse.core.internal.preferences.EclipsePreferences.accept",
          "source": "EclipsePreferences.java:105"
        },
        {
          "method": "org.eclipse.core.internal.preferences.EclipsePreferences.accept",
          "source": "EclipsePreferences.java:109"
        },
        {
          "method": "org.eclipse.core.internal.preferences.EclipsePreferences.accept",
          "source": "EclipsePreferences.java:109"
        },
        {
          "method": "org.eclipse.core.internal.preferences.PreferencesService.internalApply",
          "source": "PreferencesService.java:671"
        },
        {
          "method": "org.eclipse.core.internal.preferences.PreferencesService.applyPreferences",
          "source": "PreferencesService.java:91"
        },
        {
          "method": "org.eclipse.ui.internal.wizards.preferences.WizardPreferencesImportPage1.transfer",
          "source": "WizardPreferencesImportPage1.java:182"
        },
        {
          "method": "org.eclipse.ui.internal.wizards.preferences.WizardPreferencesPage.finish",
          "source": "WizardPreferencesPage.java:595"
        },
        {
          "method": "org.eclipse.ui.internal.wizards.preferences.PreferencesImportWizard.performFinish",
          "source": "PreferencesImportWizard.java:88"
        },
        {
          "method": "org.eclipse.jface.wizard.WizardDialog.finishPressed",
          "source": "WizardDialog.java:695"
        },
        {
          "method": "org.eclipse.jface.wizard.WizardDialog.buttonPressed",
          "source": "WizardDialog.java:367"
        },
        {
          "method": "org.eclipse.jface.dialogs.Dialog$3.widgetSelected",
          "source": "Dialog.java:638"
        },
        {
          "method": "org.eclipse.swt.widgets.TypedListener.handleEvent",
          "source": "TypedListener.java:90"
        },
        {
          "method": "org.eclipse.swt.widgets.EventTable.sendEvent",
          "source": "EventTable.java:66"
        },
        {
          "method": "org.eclipse.swt.widgets.Widget.sendEvent",
          "source": "Widget.java:927"
        },
        {
          "method": "org.eclipse.swt.widgets.Display.runDeferredEvents",
          "source": "Display.java:3463"
        },
        {
          "method": "org.eclipse.swt.widgets.Display.readAndDispatch",
          "source": "Display.java:3077"
        },
        {
          "method": "org.eclipse.jface.window.Window.runEventLoop",
          "source": "Window.java:820"
        },
        {
          "method": "org.eclipse.jface.window.Window.open",
          "source": "Window.java:796"
        },
        {
          "method": "org.eclipse.ui.actions.ImportResourcesAction.run",
          "source": "ImportResourcesAction.java:159"
        },
        {
          "method": "org.eclipse.ui.actions.BaseSelectionListenerAction.runWithEvent",
          "source": "BaseSelectionListenerAction.java:168"
        },
        {
          "method": "org.eclipse.jface.action.ActionContributionItem.handleWidgetSelection",
          "source": "ActionContributionItem.java:545"
        },
        {
          "method": "org.eclipse.jface.action.ActionContributionItem.access$2",
          "source": "ActionContributionItem.java:490"
        },
        {
          "method": "org.eclipse.jface.action.ActionContributionItem$5.handleEvent",
          "source": "ActionContributionItem.java:402"
        },
        {
          "method": "org.eclipse.swt.widgets.EventTable.sendEvent",
          "source": "EventTable.java:66"
        },
        {
          "method": "org.eclipse.swt.widgets.Widget.sendEvent",
          "source": "Widget.java:927"
        },
        {
          "method": "org.eclipse.swt.widgets.Display.runDeferredEvents",
          "source": "Display.java:3463"
        },
        {
          "method": "org.eclipse.swt.widgets.Display.readAndDispatch",
          "source": "Display.java:3077"
        },
        {
          "method": "org.eclipse.ui.internal.Workbench.runEventLoop",
          "source": "Workbench.java:1945"
        },
        {
          "method": "org.eclipse.ui.internal.Workbench.runUI",
          "source": "Workbench.java:1909"
        },
        {
          "method": "org.eclipse.ui.internal.Workbench.createAndRunWorkbench",
          "source": "Workbench.java:425"
        },
        {
          "method": "org.eclipse.ui.PlatformUI.createAndRunWorkbench",
          "source": "PlatformUI.java:149"
        },
        {
          "method": "org.eclipse.ui.internal.ide.IDEApplication.run",
          "source": "IDEApplication.java:95"
        },
        {
          "method": "org.eclipse.core.internal.runtime.PlatformActivator$1.run",
          "source": "PlatformActivator.java:78"
        },
        {
          "method": "org.eclipse.core.runtime.internal.adaptor.EclipseAppLauncher.runApplication",
          "source": "EclipseAppLauncher.java:104"
        },
        {
          "method": "org.eclipse.core.runtime.internal.adaptor.EclipseAppLauncher.start",
          "source": "EclipseAppLauncher.java:74"
        },
        {
          "method": "org.eclipse.core.runtime.adaptor.EclipseStarter.run",
          "source": "EclipseStarter.java:348"
        },
        {
          "method": "org.eclipse.core.runtime.adaptor.EclipseStarter.run",
          "source": "EclipseStarter.java:165"
        },
        {
          "method": "sun.reflect.NativeMethodAccessorImpl.invoke0",
          "source": "Native Method"
        },
        {
          "method": "sun.reflect.NativeMethodAccessorImpl.invoke",
          "source": "NativeMethodAccessorImpl.java:39"
        },
        {
          "method": "sun.reflect.DelegatingMethodAccessorImpl.invoke",
          "source": "DelegatingMethodAccessorImpl.java:25"
        },
        {
          "method": "java.lang.reflect.Method.invoke",
          "source": "Method.java:585"
        },
        {
          "method": "org.eclipse.core.launcher.Main.invokeFramework",
          "source": "Main.java:341"
        },
        {
          "method": "org.eclipse.core.launcher.Main.basicRun",
          "source": "Main.java:285"
        },
        {
          "method": "org.eclipse.core.launcher.Main.run",
          "source": "Main.java:987"
        },
        {
          "method": "org.eclipse.core.launcher.Main.main",
          "source": "Main.java:962"
        }
      ],
      "number": 0,
      "commentIndex": 0,
      "bugId": "166040",
      "date": "2006-11-28T12:09:56+01:00",
      "product": "JDT",
      "component": "Debug",
      "severity": "normal"
    }
  ],
  "groupId": "166040",
  "bugId": "166040",
  "date": "2006-11-28T12:09:56+01:00",
  "product": "JDT",
  "component": "Debug",
  "severity": "normal"
}