{
  "comments": [
    "When working with eclipse which have corona plugins installed, after several hours (without restarting the Workbench) OutOfMemoryError appears.\nWe need to use a profiler (TPTP?) to check where the memory leaks can be.\n\nThe problem is that the memory leaks might be in 3rd party libraries (like the bug with broken images).\n\nStack trace:\n------------------------------------------------------\nhEvent(EventAdminImpl.java:58)\n        at org.eclipse.osgi.framework.eventmgr.EventManager.dispatchEvent(EventM\nanager.java:189)\n        at org.eclipse.osgi.framework.eventmgr.EventManager$EventThread.run(Even\ntManager.java:291)\n(trace)org.eclipse.ecf.provider.Trace.err[11/28/06;18:12:54:113]StringID[coronaC\nlient[cwpl-pjaworow]: cwpl-0134(172.18.131.133)-1164733974113]:org.eclipse.coron\na.client.ecf.CoronaClientSOContainer:Exception in connect\njava.net.UnknownHostException: corona\n        at java.net.PlainSocketImpl.connect(Unknown Source)\n        at java.net.SocksSocketImpl.connect(Unknown Source)\n        at java.net.Socket.connect(Unknown Source)\n        at org.eclipse.ecf.provider.comm.tcp.SocketFactory.createSocket(SocketFa\nctory.java:30)\n        at org.eclipse.ecf.provider.comm.tcp.Client.connect(Client.java:218)\n        at org.eclipse.ecf.provider.generic.ClientSOContainer.connect(ClientSOCo\nntainer.java:130)\n        at org.eclipse.corona.client.ecf.Topic.createContainer(Unknown Source)\n        at org.eclipse.corona.collaboration.ecf.AbstractTopic.initTopic(Unknown\nSource)\n        at org.eclipse.corona.client.ecf.Topic.\u003cinit\u003e(Unknown Source)\n        at org.eclipse.corona.client.ecf.EventRouter.createLocalTopic(Unknown So\nurce)\n        at org.eclipse.corona.client.ecf.EventRouter.createTopic(Unknown Source)\n\n        at org.eclipse.corona.client.ecf.EventRouter.handleEvent(Unknown Source)\n\n        at org.eclipse.corona.collaboration.Activator.handleEvent(Unknown Source\n)\n        at org.eclipse.equinox.event.EventAdminImpl$EventAdminDispatcher.dispatc\nhEvent(EventAdminImpl.java:58)\n        at org.eclipse.osgi.framework.eventmgr.EventManager.dispatchEvent(EventM\nanager.java:189)\n        at org.eclipse.osgi.framework.eventmgr.EventManager$EventThread.run(Even\ntManager.java:291)\nFatal error happened during workbench emergency close.\njava.lang.OutOfMemoryError: PermGen space\njava.lang.OutOfMemoryError: PermGen space\nError while logging event loop exception:\njava.lang.IllegalArgumentException:\n        at org.eclipse.core.runtime.Assert.isLegal(Assert.java:62)\n        at org.eclipse.core.runtime.Assert.isLegal(Assert.java:46)\n        at org.eclipse.core.internal.jobs.ImplicitJobs.transfer(ImplicitJobs.jav\na:235)\n        at org.eclipse.core.internal.jobs.JobManager.transferRule(JobManager.jav\na:1154)\n        at null\n(authors comment: about 30 times at null appears here)\n        at null\nLogging exception:\njava.lang.OutOfMemoryError: PermGen space\nError while logging event loop exception:\njava.lang.IllegalArgumentException:\n        at org.eclipse.core.runtime.Assert.isLegal(Assert.java:62)\n        at org.eclipse.core.runtime.Assert.isLegal(Assert.java:46)\n        at org.eclipse.core.internal.jobs.ImplicitJobs.transfer(ImplicitJobs.jav\na:235)\n        at org.eclipse.core.internal.jobs.JobManager.transferRule(JobManager.jav\na:1154)\n        at null\n(authors comment: about 30 times at null appears here)\n        at null\nLogging exception:\njava.lang.OutOfMemoryError: PermGen space",
    "After some investigation, no proofs were found that the bug was caused by Corona plugins. \nIt seams that bug occur only when some \"stub\" projects builds are performed with ant task downloading required jar files.\nWhen I turned off that build mechanism the OutOfMemoryError did not occur anymore.\n\nI\u0027ll keep this bug open, to check whether this is the real reason.",
    "Decided to postpone the bug. If error occurs again, will have to reopen it."
  ],
  "commentCreationDates": [
    "2006-11-29T11:24:34+01:00",
    "2006-12-20T09:35:53+01:00",
    "2006-12-20T09:54:40+01:00"
  ],
  "traces": [
    {
      "exceptionType": "java.net.UnknownHostException",
      "message": "corona",
      "elements": [
        {
          "method": "java.net.PlainSocketImpl.connect",
          "source": "Unknown Source"
        },
        {
          "method": "java.net.SocksSocketImpl.connect",
          "source": "Unknown Source"
        },
        {
          "method": "java.net.Socket.connect",
          "source": "Unknown Source"
        },
        {
          "method": "org.eclipse.ecf.provider.comm.tcp.SocketFactory.createSocket",
          "source": "SocketFa ctory.java:30"
        },
        {
          "method": "org.eclipse.ecf.provider.comm.tcp.Client.connect",
          "source": "Client.java:218"
        },
        {
          "method": "org.eclipse.ecf.provider.generic.ClientSOContainer.connect",
          "source": "ClientSOCo ntainer.java:130"
        },
        {
          "method": "org.eclipse.corona.client.ecf.Topic.createContainer",
          "source": "Unknown Source"
        },
        {
          "method": "org.eclipse.corona.collaboration.ecf.AbstractTopic.initTopic",
          "source": "Unknown Source"
        },
        {
          "method": "org.eclipse.corona.client.ecf.Topic.\u003cinit\u003e",
          "source": "Unknown Source"
        },
        {
          "method": "org.eclipse.corona.client.ecf.EventRouter.createLocalTopic",
          "source": "Unknown So urce"
        },
        {
          "method": "org.eclipse.corona.client.ecf.EventRouter.createTopic",
          "source": "Unknown Source"
        },
        {
          "method": "org.eclipse.corona.client.ecf.EventRouter.handleEvent",
          "source": "Unknown Source"
        },
        {
          "method": "org.eclipse.corona.collaboration.Activator.handleEvent",
          "source": "Unknown Source "
        },
        {
          "method": "org.eclipse.equinox.event.EventAdminImpl$EventAdminDispatcher.dispatchEvent",
          "source": "EventAdminImpl.java:58"
        },
        {
          "method": "org.eclipse.osgi.framework.eventmgr.EventManager.dispatchEvent",
          "source": "EventM anager.java:189"
        },
        {
          "method": "org.eclipse.osgi.framework.eventmgr.EventManager$EventThread.run",
          "source": "Even tManager.java:291"
        }
      ],
      "number": 0,
      "commentIndex": 0,
      "bugId": "166180",
      "date": "2006-11-29T11:24:34+01:00",
      "product": "Corona",
      "component": "collaboration",
      "severity": "normal"
    },
    {
      "exceptionType": "java.lang.IllegalArgumentException",
      "message": "",
      "elements": [
        {
          "method": "org.eclipse.core.runtime.Assert.isLegal",
          "source": "Assert.java:62"
        },
        {
          "method": "org.eclipse.core.runtime.Assert.isLegal",
          "source": "Assert.java:46"
        },
        {
          "method": "org.eclipse.core.internal.jobs.ImplicitJobs.transfer",
          "source": "ImplicitJobs.jav a:235"
        },
        {
          "method": "org.eclipse.core.internal.jobs.JobManager.transferRule",
          "source": "JobManager.jav a:1154"
        }
      ],
      "number": 1,
      "commentIndex": 0,
      "bugId": "166180",
      "date": "2006-11-29T11:24:34+01:00",
      "product": "Corona",
      "component": "collaboration",
      "severity": "normal"
    },
    {
      "exceptionType": "java.lang.IllegalArgumentException",
      "message": "",
      "elements": [
        {
          "method": "org.eclipse.core.runtime.Assert.isLegal",
          "source": "Assert.java:62"
        },
        {
          "method": "org.eclipse.core.runtime.Assert.isLegal",
          "source": "Assert.java:46"
        },
        {
          "method": "org.eclipse.core.internal.jobs.ImplicitJobs.transfer",
          "source": "ImplicitJobs.jav a:235"
        },
        {
          "method": "org.eclipse.core.internal.jobs.JobManager.transferRule",
          "source": "JobManager.jav a:1154"
        }
      ],
      "number": 2,
      "commentIndex": 0,
      "bugId": "166180",
      "date": "2006-11-29T11:24:34+01:00",
      "product": "Corona",
      "component": "collaboration",
      "severity": "normal"
    }
  ],
  "groupId": "166180",
  "bugId": "166180",
  "date": "2006-11-29T11:24:34+01:00",
  "product": "Corona",
  "component": "collaboration",
  "severity": "normal"
}