{
  "comments": [
    "1. install aperi on Linux\nroot@tpc-d23-int configure]# ./cfgaperi easy\n\nAperi Storage Manager Configuration\n\nThis program will configure Aperi using default values.\n\n\nChecking Java installation...passed: 1.5.0_09\n\nReady to configure.\n\n\nConfiguring the agent...\n ../agent/configuration/setup.properties\n ../agent/configuration/agent.config\n ../agent/agent\n\nConfiguring derby...\n ../db/derby\n ../db/derbystop\n ../db/aperi-schema\n ../db/aperi-ij\n\nConfiguring the device server...\n devsvr/configuration/setup.properties\n devsvr/configuration/tsnmdbparms.properties\n ../devsvr/devsvr\n\nConfiguring the data server...\n datasvr/configuration/server.config\n ../datasvr/datasvr\n\nConfiguring the gui...\n ../gui/gui\n\nGenerating start script...\n ../aperi\nGUID is 0ad02226-4ac0-457f-ad03-d54a11027648\nStoring in /home/aperi/guid.txt\n\nNext, the Derby RDBMS will be started\nand the Aperi schema created.\n..\nNow the schema will be loaded.\nRunning ./aperi-schema\n----\nError while configuring.\njava.io.IOException: java.io.IOException: ./aperi-schema: not found\n        at java.lang.UNIXProcess.\u003cinit\u003e(Unknown Source)\n        at java.lang.ProcessImpl.start(Unknown Source)\n        at java.lang.ProcessBuilder.start(Unknown Source)\n        at java.lang.Runtime.exec(Unknown Source)\n        at java.lang.Runtime.exec(Unknown Source)\n        at java.lang.Runtime.exec(Unknown Source)\n        at org.eclipse.aperi.configure.ConfigureAperi.runCmd(ConfigureAperi.java:1429)\n        at org.eclipse.aperi.configure.ConfigureAperi.runSilentDatabaseInstall(ConfigureAperi.java:1193)\n        at org.eclipse.aperi.configure.ConfigureAperi.schema(ConfigureAperi.java:1172)\n        at org.eclipse.aperi.configure.ConfigureAperi.run(ConfigureAperi.java:409)\n        at org.eclipse.aperi.configure.ConfigureAperi.configure(ConfigureAperi.java:231)\n        at org.eclipse.aperi.configure.ConfigureAperi.main(ConfigureAperi.java:211)\n[root@tpc-d23-int configure]#\n\nThe file is in \u003cinstalldir\u003e/db.",
    "Created an attachment (id\u003d54844)\nthe aperi-schema in ../db/aperi-schema\n\nshould access  ../db/aperi-schema",
    "aperi-schema was trying to \n",
    "aperi-schema was trying to \n   cd $DERBY_HOME\n\nbut DERBY_HOME was not set. On Windows, \"cd \" stays where you are, but on Unix, \"cd \" takes you home. So the failure to set DERBY_HOME in this script was not noticed on Windows.\n\nI added the appropriate EXPORT DERBY_HOME\u003d\u003cblah\u003e to the script generator. cfgaperi can now configure aperi \u0026 invoke aperi-schema fine.",
    "verified"
  ],
  "commentCreationDates": [
    "2006-12-01T00:21:53+01:00",
    "2006-12-01T00:30:33+01:00",
    "2006-12-06T01:11:32+01:00",
    "2006-12-06T01:12:58+01:00",
    "2006-12-15T05:00:45+01:00"
  ],
  "traces": [
    {
      "exceptionType": "java.io.IOException",
      "message": "./aperi-schema: not found",
      "elements": [
        {
          "method": "java.lang.UNIXProcess.\u003cinit\u003e",
          "source": "Unknown Source"
        },
        {
          "method": "java.lang.ProcessImpl.start",
          "source": "Unknown Source"
        },
        {
          "method": "java.lang.ProcessBuilder.start",
          "source": "Unknown Source"
        },
        {
          "method": "java.lang.Runtime.exec",
          "source": "Unknown Source"
        },
        {
          "method": "java.lang.Runtime.exec",
          "source": "Unknown Source"
        },
        {
          "method": "java.lang.Runtime.exec",
          "source": "Unknown Source"
        },
        {
          "method": "org.eclipse.aperi.configure.ConfigureAperi.runCmd",
          "source": "ConfigureAperi.java:1429"
        },
        {
          "method": "org.eclipse.aperi.configure.ConfigureAperi.runSilentDatabaseInstall",
          "source": "ConfigureAperi.java:1193"
        },
        {
          "method": "org.eclipse.aperi.configure.ConfigureAperi.schema",
          "source": "ConfigureAperi.java:1172"
        },
        {
          "method": "org.eclipse.aperi.configure.ConfigureAperi.run",
          "source": "ConfigureAperi.java:409"
        },
        {
          "method": "org.eclipse.aperi.configure.ConfigureAperi.configure",
          "source": "ConfigureAperi.java:231"
        },
        {
          "method": "org.eclipse.aperi.configure.ConfigureAperi.main",
          "source": "ConfigureAperi.java:211"
        }
      ],
      "number": 0,
      "commentIndex": 0,
      "bugId": "166429",
      "date": "2006-12-01T00:21:53+01:00",
      "product": "Aperi",
      "component": "Aperi",
      "severity": "normal"
    }
  ],
  "groupId": "166429",
  "bugId": "166429",
  "date": "2006-12-01T00:21:53+01:00",
  "product": "Aperi",
  "component": "Aperi",
  "severity": "normal"
}