{
  "comments": [
    "I20061205-0800\n\n- Preferences \u003e Team \u003e CVS \u003e Synchronize/Compare:\n    check \"Show revision comparisons in dialog\"\n\n- have org.eclipse.core.expressions from CVS\n- context menu on org.eclipse.core.expressions/ElementHandler.java, choose\n    Compare With \u003e History\n- doubleclick an old revision\n\n\u003d\u003e Eclipse enters neverending loop of StackOverflowErrors and starts hundreds of \"ModalContext\" threads. I had to kill the process.\n\n\nUnhandled event loop exception during blocked modal context.\norg.eclipse.swt.SWTException: Failed to execute runnable (java.lang.StackOverflowError)\n        at org.eclipse.swt.SWT.error(SWT.java:3450)\n        at org.eclipse.swt.SWT.error(SWT.java:3373)\n        at org.eclipse.swt.widgets.Synchronizer.runAsyncMessages(Synchronizer.java:126)\n        at org.eclipse.swt.widgets.Display.runAsyncMessages(Display.java:3442)\n        at org.eclipse.swt.widgets.Display.readAndDispatch(Display.java:3082)\n        at org.eclipse.jface.operation.ModalContext$ModalContextThread.block(ModalContext.java:158)\n        at org.eclipse.jface.operation.ModalContext.run(ModalContext.java:326)\n        at org.eclipse.jface.dialogs.ProgressMonitorDialog.run(ProgressMonitorDialog.java:495)\n        at org.eclipse.ui.internal.progress.ProgressMonitorJobsDialog.run(ProgressMonitorJobsDialog.java:265)\n        at org.eclipse.ui.internal.progress.ProgressManager$3.run(ProgressManager.java:890)\n        at org.eclipse.swt.custom.BusyIndicator.showWhile(BusyIndicator.java:67)\n        at org.eclipse.ui.internal.progress.ProgressManager.busyCursorWhile(ProgressManager.java:925)\n        at org.eclipse.ui.internal.progress.ProgressManager.busyCursorWhile(ProgressManager.java:900)\n        at org.eclipse.ui.internal.progress.ProgressManager.run(ProgressManager.java:1108)\n        at org.eclipse.compare.internal.WorkerJob$1.run(WorkerJob.java:64)\n        at org.eclipse.swt.widgets.RunnableLock.run(RunnableLock.java:35)\n        at org.eclipse.swt.widgets.Synchronizer.runAsyncMessages(Synchronizer.java:123)\n        at org.eclipse.swt.widgets.Display.runAsyncMessages(Display.java:3442)\n        at org.eclipse.swt.widgets.Display.readAndDispatch(Display.java:3082)\n        at org.eclipse.jface.operation.ModalContext$ModalContextThread.block(ModalContext.java:158)\n        at org.eclipse.jface.operation.ModalContext.run(ModalContext.java:326)\n        at org.eclipse.jface.dialogs.ProgressMonitorDialog.run(ProgressMonitorDialog.java:495)\n        at org.eclipse.ui.internal.progress.ProgressMonitorJobsDialog.run(ProgressMonitorJobsDialog.java:265)\n        at org.eclipse.ui.internal.progress.ProgressManager$3.run(ProgressManager.java:890)\n        at org.eclipse.swt.custom.BusyIndicator.showWhile(BusyIndicator.java:67)\n        at org.eclipse.ui.internal.progress.ProgressManager.busyCursorWhile(ProgressManager.java:925)\n        at org.eclipse.ui.internal.progress.ProgressManager.busyCursorWhile(ProgressManager.java:900)",
    "Fix released to HEAD",
    "*** Bug 167375 has been marked as a duplicate of this bug. ***",
    "Verified",
    "*** Bug 168274 has been marked as a duplicate of this bug. ***"
  ],
  "commentCreationDates": [
    "2006-12-06T18:50:45+01:00",
    "2006-12-06T19:15:10+01:00",
    "2006-12-11T13:43:19+01:00",
    "2006-12-12T15:00:42+01:00",
    "2006-12-15T20:43:02+01:00"
  ],
  "traces": [
    {
      "exceptionType": "org.eclipse.swt.SWTException",
      "message": "Failed to execute runnable (java.lang.StackOverflowError)",
      "elements": [
        {
          "method": "org.eclipse.swt.SWT.error",
          "source": "SWT.java:3450"
        },
        {
          "method": "org.eclipse.swt.SWT.error",
          "source": "SWT.java:3373"
        },
        {
          "method": "org.eclipse.swt.widgets.Synchronizer.runAsyncMessages",
          "source": "Synchronizer.java:126"
        },
        {
          "method": "org.eclipse.swt.widgets.Display.runAsyncMessages",
          "source": "Display.java:3442"
        },
        {
          "method": "org.eclipse.swt.widgets.Display.readAndDispatch",
          "source": "Display.java:3082"
        },
        {
          "method": "org.eclipse.jface.operation.ModalContext$ModalContextThread.block",
          "source": "ModalContext.java:158"
        },
        {
          "method": "org.eclipse.jface.operation.ModalContext.run",
          "source": "ModalContext.java:326"
        },
        {
          "method": "org.eclipse.jface.dialogs.ProgressMonitorDialog.run",
          "source": "ProgressMonitorDialog.java:495"
        },
        {
          "method": "org.eclipse.ui.internal.progress.ProgressMonitorJobsDialog.run",
          "source": "ProgressMonitorJobsDialog.java:265"
        },
        {
          "method": "org.eclipse.ui.internal.progress.ProgressManager$3.run",
          "source": "ProgressManager.java:890"
        },
        {
          "method": "org.eclipse.swt.custom.BusyIndicator.showWhile",
          "source": "BusyIndicator.java:67"
        },
        {
          "method": "org.eclipse.ui.internal.progress.ProgressManager.busyCursorWhile",
          "source": "ProgressManager.java:925"
        },
        {
          "method": "org.eclipse.ui.internal.progress.ProgressManager.busyCursorWhile",
          "source": "ProgressManager.java:900"
        },
        {
          "method": "org.eclipse.ui.internal.progress.ProgressManager.run",
          "source": "ProgressManager.java:1108"
        },
        {
          "method": "org.eclipse.compare.internal.WorkerJob$1.run",
          "source": "WorkerJob.java:64"
        },
        {
          "method": "org.eclipse.swt.widgets.RunnableLock.run",
          "source": "RunnableLock.java:35"
        },
        {
          "method": "org.eclipse.swt.widgets.Synchronizer.runAsyncMessages",
          "source": "Synchronizer.java:123"
        },
        {
          "method": "org.eclipse.swt.widgets.Display.runAsyncMessages",
          "source": "Display.java:3442"
        },
        {
          "method": "org.eclipse.swt.widgets.Display.readAndDispatch",
          "source": "Display.java:3082"
        },
        {
          "method": "org.eclipse.jface.operation.ModalContext$ModalContextThread.block",
          "source": "ModalContext.java:158"
        },
        {
          "method": "org.eclipse.jface.operation.ModalContext.run",
          "source": "ModalContext.java:326"
        },
        {
          "method": "org.eclipse.jface.dialogs.ProgressMonitorDialog.run",
          "source": "ProgressMonitorDialog.java:495"
        },
        {
          "method": "org.eclipse.ui.internal.progress.ProgressMonitorJobsDialog.run",
          "source": "ProgressMonitorJobsDialog.java:265"
        },
        {
          "method": "org.eclipse.ui.internal.progress.ProgressManager$3.run",
          "source": "ProgressManager.java:890"
        },
        {
          "method": "org.eclipse.swt.custom.BusyIndicator.showWhile",
          "source": "BusyIndicator.java:67"
        },
        {
          "method": "org.eclipse.ui.internal.progress.ProgressManager.busyCursorWhile",
          "source": "ProgressManager.java:925"
        },
        {
          "method": "org.eclipse.ui.internal.progress.ProgressManager.busyCursorWhile",
          "source": "ProgressManager.java:900"
        }
      ],
      "number": 0,
      "commentIndex": 0,
      "bugId": "166985",
      "date": "2006-12-06T18:50:45+01:00",
      "product": "Platform",
      "component": "CVS",
      "severity": "critical"
    }
  ],
  "groupId": "166985",
  "bugId": "166985",
  "date": "2006-12-06T18:50:45+01:00",
  "product": "Platform",
  "component": "CVS",
  "severity": "critical"
}