{
  "comments": [
    "I20061205-1200\n\n- new workspace\n- paste to Package Explorer:\n\npackage p;\nimport java.util.ArrayList;\npublic class Struct {\n\tpublic static void main(String[] args) {\n\t\tArrayList\u003cInteger\u003e list \u003d new ArrayList\u003cInteger\u003e();\n\t\tlist.add(1);\n\t\tlist.add(2); //breakpoint\n\t\tlist.add(3);\n\t}\n}\n\n- set breakpoint\n- debug\n- in Variables view, press \u0027Show Logical Structure\u0027\n- expand \u0027list\u0027 by clicking on +\n\n\u003d\u003e child is:\n    Name: Error\n    Value: Exception occurred: Evaluation failed - thread not suspended..\n\n\u003d\u003e clicking into the value field of the error child writes this to log:\n\njava.lang.NullPointerException\n        at org.eclipse.jdt.internal.debug.ui.variables.JavaVariableCellModifier.canModify(JavaVariableCellModifier.java:37)\n        at org.eclipse.debug.internal.ui.viewers.model.InternalTreeModelViewer$CellModifierProxy.canModify(InternalTreeModelViewer.java:175)\n        at org.eclipse.jface.viewers.ColumnViewer$2.canEdit(ColumnViewer.java:194)\n        at org.eclipse.jface.viewers.AbstractViewerEditor.activateCellEditor(AbstractViewerEditor.java:99)\n        at org.eclipse.jface.viewers.AbstractViewerEditor.activateCellEditor(AbstractViewerEditor.java:192)\n        at org.eclipse.jface.viewers.AbstractViewerEditor.handleMouseDown(AbstractViewerEditor.java:292)\n        at org.eclipse.jface.viewers.ColumnViewer$1.mouseDown(ColumnViewer.java:79)\n        at org.eclipse.swt.widgets.TypedListener.handleEvent(TypedListener.java:133)\n        at org.eclipse.swt.widgets.EventTable.sendEvent(EventTable.java:66)\n        at org.eclipse.swt.widgets.Widget.sendEvent(Widget.java:929)\n        at org.eclipse.swt.widgets.Display.runDeferredEvents(Display.java:3465)\n        at org.eclipse.swt.widgets.Display.readAndDispatch(Display.java:3079)\n        at org.eclipse.ui.internal.Workbench.runEventLoop(Workbench.java:1945)\n        at org.eclipse.ui.internal.Workbench.runUI(Workbench.java:1909)\n        at org.eclipse.ui.internal.Workbench.createAndRunWorkbench(Workbench.java:425)\n        at org.eclipse.ui.PlatformUI.createAndRunWorkbench(PlatformUI.java:149)\n        at org.eclipse.ui.internal.ide.IDEApplication.run(IDEApplication.java:95)\n        at sun.reflect.NativeMethodAccessorImpl.invoke0(Native Method)\n        at sun.reflect.NativeMethodAccessorImpl.invoke(NativeMethodAccessorImpl.java:39)\n        at sun.reflect.DelegatingMethodAccessorImpl.invoke(DelegatingMethodAccessorImpl.java:25)\n        at java.lang.reflect.Method.invoke(Method.java:585)\n        at org.eclipse.equinox.internal.app.EclipseAppContainer.callMethod(EclipseAppContainer.java:522)\n        at org.eclipse.equinox.internal.app.EclipseAppHandle.run(EclipseAppHandle.java:147)\n        at org.eclipse.core.runtime.internal.adaptor.EclipseAppLauncher.runApplication(EclipseAppLauncher.java:104)\n        at org.eclipse.core.runtime.internal.adaptor.EclipseAppLauncher.start(EclipseAppLauncher.java:74)\n        at org.eclipse.core.runtime.adaptor.EclipseStarter.run(EclipseStarter.java:353)\n        at org.eclipse.core.runtime.adaptor.EclipseStarter.run(EclipseStarter.java:170)\n        at sun.reflect.NativeMethodAccessorImpl.invoke0(Native Method)\n        at sun.reflect.NativeMethodAccessorImpl.invoke(NativeMethodAccessorImpl.java:39)\n        at sun.reflect.DelegatingMethodAccessorImpl.invoke(DelegatingMethodAccessorImpl.java:25)\n        at java.lang.reflect.Method.invoke(Method.java:585)\n        at org.eclipse.core.launcher.Main.invokeFramework(Main.java:339)\n        at org.eclipse.core.launcher.Main.basicRun(Main.java:283)\n        at org.eclipse.core.launcher.Main.run(Main.java:984)\n        at org.eclipse.core.launcher.Main.main(Main.java:959)",
    "Fixed NPE. I was unable to get the \"error\" to show up in the variables view. I saw it once, but could not reproduce. The time it did happend the NPE did not occurr (I had the fix in). The error occurrs if the type of the variable is not yet loaded in the target VM (and I\u0027m not sure how that could be).",
    "Fixed in JavaVariableCellModifier. Please verify, Mike.",
    "verified the NPE fix",
    "I can consistently reproduce the \"Exception occurred\" by following the steps slowly (and not clicking elsewhere). I use a JDK 1.5.0_10-b02.\n\nI filed bug 167259 for the \"Exception occurred\" and adapted the summary here."
  ],
  "commentCreationDates": [
    "2006-12-08T16:04:30+01:00",
    "2006-12-08T17:01:57+01:00",
    "2006-12-08T17:14:19+01:00",
    "2006-12-08T17:26:59+01:00",
    "2006-12-08T17:27:54+01:00"
  ],
  "traces": [
    {
      "exceptionType": "java.lang.NullPointerException",
      "elements": [
        {
          "method": "org.eclipse.jdt.internal.debug.ui.variables.JavaVariableCellModifier.canModify",
          "source": "JavaVariableCellModifier.java:37"
        },
        {
          "method": "org.eclipse.debug.internal.ui.viewers.model.InternalTreeModelViewer$CellModifierProxy.canModify",
          "source": "InternalTreeModelViewer.java:175"
        },
        {
          "method": "org.eclipse.jface.viewers.ColumnViewer$2.canEdit",
          "source": "ColumnViewer.java:194"
        },
        {
          "method": "org.eclipse.jface.viewers.AbstractViewerEditor.activateCellEditor",
          "source": "AbstractViewerEditor.java:99"
        },
        {
          "method": "org.eclipse.jface.viewers.AbstractViewerEditor.activateCellEditor",
          "source": "AbstractViewerEditor.java:192"
        },
        {
          "method": "org.eclipse.jface.viewers.AbstractViewerEditor.handleMouseDown",
          "source": "AbstractViewerEditor.java:292"
        },
        {
          "method": "org.eclipse.jface.viewers.ColumnViewer$1.mouseDown",
          "source": "ColumnViewer.java:79"
        },
        {
          "method": "org.eclipse.swt.widgets.TypedListener.handleEvent",
          "source": "TypedListener.java:133"
        },
        {
          "method": "org.eclipse.swt.widgets.EventTable.sendEvent",
          "source": "EventTable.java:66"
        },
        {
          "method": "org.eclipse.swt.widgets.Widget.sendEvent",
          "source": "Widget.java:929"
        },
        {
          "method": "org.eclipse.swt.widgets.Display.runDeferredEvents",
          "source": "Display.java:3465"
        },
        {
          "method": "org.eclipse.swt.widgets.Display.readAndDispatch",
          "source": "Display.java:3079"
        },
        {
          "method": "org.eclipse.ui.internal.Workbench.runEventLoop",
          "source": "Workbench.java:1945"
        },
        {
          "method": "org.eclipse.ui.internal.Workbench.runUI",
          "source": "Workbench.java:1909"
        },
        {
          "method": "org.eclipse.ui.internal.Workbench.createAndRunWorkbench",
          "source": "Workbench.java:425"
        },
        {
          "method": "org.eclipse.ui.PlatformUI.createAndRunWorkbench",
          "source": "PlatformUI.java:149"
        },
        {
          "method": "org.eclipse.ui.internal.ide.IDEApplication.run",
          "source": "IDEApplication.java:95"
        },
        {
          "method": "sun.reflect.NativeMethodAccessorImpl.invoke0",
          "source": "Native Method"
        },
        {
          "method": "sun.reflect.NativeMethodAccessorImpl.invoke",
          "source": "NativeMethodAccessorImpl.java:39"
        },
        {
          "method": "sun.reflect.DelegatingMethodAccessorImpl.invoke",
          "source": "DelegatingMethodAccessorImpl.java:25"
        },
        {
          "method": "java.lang.reflect.Method.invoke",
          "source": "Method.java:585"
        },
        {
          "method": "org.eclipse.equinox.internal.app.EclipseAppContainer.callMethod",
          "source": "EclipseAppContainer.java:522"
        },
        {
          "method": "org.eclipse.equinox.internal.app.EclipseAppHandle.run",
          "source": "EclipseAppHandle.java:147"
        },
        {
          "method": "org.eclipse.core.runtime.internal.adaptor.EclipseAppLauncher.runApplication",
          "source": "EclipseAppLauncher.java:104"
        },
        {
          "method": "org.eclipse.core.runtime.internal.adaptor.EclipseAppLauncher.start",
          "source": "EclipseAppLauncher.java:74"
        },
        {
          "method": "org.eclipse.core.runtime.adaptor.EclipseStarter.run",
          "source": "EclipseStarter.java:353"
        },
        {
          "method": "org.eclipse.core.runtime.adaptor.EclipseStarter.run",
          "source": "EclipseStarter.java:170"
        },
        {
          "method": "sun.reflect.NativeMethodAccessorImpl.invoke0",
          "source": "Native Method"
        },
        {
          "method": "sun.reflect.NativeMethodAccessorImpl.invoke",
          "source": "NativeMethodAccessorImpl.java:39"
        },
        {
          "method": "sun.reflect.DelegatingMethodAccessorImpl.invoke",
          "source": "DelegatingMethodAccessorImpl.java:25"
        },
        {
          "method": "java.lang.reflect.Method.invoke",
          "source": "Method.java:585"
        },
        {
          "method": "org.eclipse.core.launcher.Main.invokeFramework",
          "source": "Main.java:339"
        },
        {
          "method": "org.eclipse.core.launcher.Main.basicRun",
          "source": "Main.java:283"
        },
        {
          "method": "org.eclipse.core.launcher.Main.run",
          "source": "Main.java:984"
        },
        {
          "method": "org.eclipse.core.launcher.Main.main",
          "source": "Main.java:959"
        }
      ],
      "number": 0,
      "commentIndex": 0,
      "bugId": "167244",
      "date": "2006-12-08T16:04:30+01:00",
      "product": "JDT",
      "component": "Debug",
      "severity": "normal"
    }
  ],
  "groupId": "167244",
  "bugId": "167244",
  "date": "2006-12-08T16:04:30+01:00",
  "product": "JDT",
  "component": "Debug",
  "severity": "normal"
}