{
  "comments": [
    "I20061212\n\n1.  Create a Remote Java Application launch config\n2.  Select any project and take the default settings to connect to localhost.\n3.  Click Debug.  \n\nYou will find this exception in the error log.  But the \"fail to connect dialog\" does not show up.  \n\nI tested with IBM JVM 1.4.2 on Linux and IBM 1.5 SR3 on Windows.  No dialog showed up in both cases.\n\n\njava.net.ConnectException: Connection refused: connect\n\tat java.net.PlainSocketImpl.socketConnect(Native Method)\n\tat java.net.PlainSocketImpl.doConnect(PlainSocketImpl.java:372)\n\tat java.net.PlainSocketImpl.connectToAddress(PlainSocketImpl.java:233)\n\tat java.net.PlainSocketImpl.connect(PlainSocketImpl.java:220)\n\tat java.net.SocksSocketImpl.connect(SocksSocketImpl.java:385)\n\tat java.net.Socket.connect(Socket.java:536)\n\tat java.net.Socket.connect(Socket.java:486)\n\tat java.net.Socket.\u003cinit\u003e(Socket.java:394)\n\tat java.net.Socket.\u003cinit\u003e(Socket.java:207)\n\tat org.eclipse.jdi.internal.connect.SocketTransportService$2.run(SocketTransportService.java:134)\n\tat java.lang.Thread.run(Thread.java:799)",
    "\n\n*** This bug has been marked as a duplicate of bug 167641 ***"
  ],
  "commentCreationDates": [
    "2006-12-13T00:24:45+01:00",
    "2006-12-13T14:23:55+01:00"
  ],
  "traces": [
    {
      "exceptionType": "java.net.ConnectException",
      "message": "Connection refused: connect",
      "elements": [
        {
          "method": "java.net.PlainSocketImpl.socketConnect",
          "source": "Native Method"
        },
        {
          "method": "java.net.PlainSocketImpl.doConnect",
          "source": "PlainSocketImpl.java:372"
        },
        {
          "method": "java.net.PlainSocketImpl.connectToAddress",
          "source": "PlainSocketImpl.java:233"
        },
        {
          "method": "java.net.PlainSocketImpl.connect",
          "source": "PlainSocketImpl.java:220"
        },
        {
          "method": "java.net.SocksSocketImpl.connect",
          "source": "SocksSocketImpl.java:385"
        },
        {
          "method": "java.net.Socket.connect",
          "source": "Socket.java:536"
        },
        {
          "method": "java.net.Socket.connect",
          "source": "Socket.java:486"
        },
        {
          "method": "java.net.Socket.\u003cinit\u003e",
          "source": "Socket.java:394"
        },
        {
          "method": "java.net.Socket.\u003cinit\u003e",
          "source": "Socket.java:207"
        },
        {
          "method": "org.eclipse.jdi.internal.connect.SocketTransportService$2.run",
          "source": "SocketTransportService.java:134"
        },
        {
          "method": "java.lang.Thread.run",
          "source": "Thread.java:799"
        }
      ],
      "number": 0,
      "commentIndex": 0,
      "bugId": "167770",
      "duplicateId": "167641",
      "date": "2006-12-13T00:24:45+01:00",
      "product": "JDT",
      "component": "Debug",
      "severity": "normal"
    }
  ],
  "groupId": "167641",
  "bugId": "167770",
  "duplicateId": "167641",
  "date": "2006-12-13T00:24:45+01:00",
  "product": "JDT",
  "component": "Debug",
  "severity": "normal"
}