{
  "comments": [
    "I built a TableTree with three nested TableTreeItems.  \n\nIf I close the tree entirely and call showItem() on the \ninnermost child, I get a null argument exception even though \nthe child is not null.  \n\nI don\u0027t get an exception if I expand the tree entirely, or if \nI call showItem() on the first or second level child items.  \n\nI get the same results if I use setSelection().\nAlso calling showItem() successively from the higher level to lower level \nitems (to \"gradually\" open the tree) produces the same exception.\n\ni.e.\n   ...\n   TableTree     tree  \u003d new TableTree(composite,SWT.FULL_SELECTION);\n   TableTreeItem root  \u003d new TableTreeItem(tree,SWT.NONE);  \n                 root.setText(\"root\");\n   TableTreeItem child \u003d new TableTreeItem(root,SWT.NONE);\n                 child.setText(\"child\");\n   TableTreeItem child2 \u003d new TableTreeItem(child,SWT.NONE);\n                 child2.setText(\"child2\");\n   ...\n   if ( child2!\u003dnull )\n     tree.showItem(child2);  // raises exception if child2 is unexpanded\n   ...\n\ngives\n\njava.lang.IllegalArgumentException: Argument cannot be null\n\tat org.eclipse.swt.SWT.error(SWT.java:1873)\n\tat org.eclipse.swt.SWT.error(SWT.java:1819)\n\tat org.eclipse.swt.widgets.Widget.error(Widget.java:368)\n\tat org.eclipse.swt.widgets.Table.indexOf(Table.java:962)\n\tat org.eclipse.swt.widgets.Table.setSelection(Table.java:1834)\n\tat org.eclipse.swt.custom.TableTree.setSelection(TableTree.java:664)\n        ...\n\nI\u0027m using SWT that came with Eclipse build 20020416, on a Windows 98\nmachine.",
    "VI has a fix for this. We should release it once test pass one is over.\n",
    "Fixed \u003e 0528"
  ],
  "commentCreationDates": [
    "2002-05-22T15:34:03+02:00",
    "2002-05-22T16:10:44+02:00",
    "2002-05-28T21:41:49+02:00"
  ],
  "traces": [
    {
      "exceptionType": "java.lang.IllegalArgumentException",
      "message": "Argument cannot be null",
      "elements": [
        {
          "method": "org.eclipse.swt.SWT.error",
          "source": "SWT.java:1873"
        },
        {
          "method": "org.eclipse.swt.SWT.error",
          "source": "SWT.java:1819"
        },
        {
          "method": "org.eclipse.swt.widgets.Widget.error",
          "source": "Widget.java:368"
        },
        {
          "method": "org.eclipse.swt.widgets.Table.indexOf",
          "source": "Table.java:962"
        },
        {
          "method": "org.eclipse.swt.widgets.Table.setSelection",
          "source": "Table.java:1834"
        },
        {
          "method": "org.eclipse.swt.custom.TableTree.setSelection",
          "source": "TableTree.java:664"
        }
      ],
      "number": 0,
      "commentIndex": 0,
      "bugId": "16775",
      "date": "2002-05-22T15:34:03+02:00",
      "product": "Platform",
      "component": "SWT",
      "severity": "normal"
    }
  ],
  "groupId": "16775",
  "bugId": "16775",
  "date": "2002-05-22T15:34:03+02:00",
  "product": "Platform",
  "component": "SWT",
  "severity": "normal"
}