{
  "comments": [
    "F1 on XP\nConnect to download.eclipse.org/updates\nExpand 200205211339\nClick on Show Matching Features\nSelect Platform [QNX Photon], install in platform:/base\nEclipse doesn\u0027t restart, no log\n\nC:\\Eclipse F1\\eclipse\u003ejava -cp startup.jar org.eclipse.core.launcher.Main -data\nC:\\Install\njava.lang.UnsatisfiedLinkError: no swt-pi-gtk-2040 in java.library.path\n        at java.lang.ClassLoader.loadLibrary(ClassLoader.java:1410)\n        at java.lang.Runtime.loadLibrary0(Runtime.java:772)\n        at java.lang.System.loadLibrary(System.java:832)\n        at org.eclipse.swt.internal.Library.loadLibrary(Library.java:102)\n        at org.eclipse.swt.internal.gtk.OS.\u003cclinit\u003e(OS.java:20)\n        at java.lang.Class.forName0(Native Method)\n        at java.lang.Class.forName(Class.java:130)\n        at org.eclipse.swt.internal.Library.getPlatform(Library.java:47)\n        at org.eclipse.swt.internal.Library.loadLibrary(Library.java:81)\n        at org.eclipse.swt.internal.win32.OS.\u003cclinit\u003e(OS.java:40)\n        at org.eclipse.swt.widgets.Display.internal_new_GC(Display.java:1107)\n        at org.eclipse.swt.graphics.Device.init(Device.java:533)\n        at org.eclipse.swt.widgets.Display.init(Display.java:1126)\n        at org.eclipse.swt.graphics.Device.\u003cinit\u003e(Device.java:82)\n        at org.eclipse.swt.widgets.Display.\u003cinit\u003e(Display.java:277)\n        at org.eclipse.swt.widgets.Display.\u003cinit\u003e(Display.java:273)\n        at org.eclipse.ui.internal.Workbench.run(Workbench.java:1050)\n        at org.eclipse.core.internal.boot.InternalBootLoader.run\n(InternalBootLoa\nder.java:739)\n        at org.eclipse.core.boot.BootLoader.run(BootLoader.java:462)\n        at sun.reflect.NativeMethodAccessorImpl.invoke0(Native Method)\n        at sun.reflect.NativeMethodAccessorImpl.invoke\n(NativeMethodAccessorImpl.\njava:39)\n        at sun.reflect.DelegatingMethodAccessorImpl.invoke\n(DelegatingMethodAcces\nsorImpl.java:25)\n        at java.lang.reflect.Method.invoke(Method.java:324)\n        at org.eclipse.core.launcher.Main.basicRun(Main.java:200)\n        at org.eclipse.core.launcher.Main.run(Main.java:643)\n        at org.eclipse.core.launcher.Main.main(Main.java:476)",
    "Delating .config doesn\u0027t work",
    "Well, I would not expect to be able to execute the QNX code on XP, so the \ninability to restart is obvious.\n\nHowever, this points out a more serious problem .... we actually allowed the \ninstall to proceed. We should not. We are not just downloading .zips to some \ndownload folder ... we are actually applying the changes to the running \nconfiguration, so we should not allow a feature that does not match the \nenvironment to be installed.",
    "The checking should be done in [Install] enabling, as well as delta processing",
    "*** Bug 17124 has been marked as a duplicate of this bug. ***",
    "F3 candidate",
    "Will handle this as part of the ActivityConstraints work for bug 18656",
    "released in HEAD"
  ],
  "commentCreationDates": [
    "2002-05-22T15:47:08+02:00",
    "2002-05-22T15:48:23+02:00",
    "2002-06-04T16:41:14+02:00",
    "2002-06-04T16:43:08+02:00",
    "2002-06-04T16:46:02+02:00",
    "2002-06-04T19:02:16+02:00",
    "2002-06-05T22:43:45+02:00",
    "2002-06-08T20:37:03+02:00"
  ],
  "traces": [
    {
      "exceptionType": "java.lang.UnsatisfiedLinkError",
      "message": "no swt-pi-gtk-2040 in java.library.path",
      "elements": [
        {
          "method": "java.lang.ClassLoader.loadLibrary",
          "source": "ClassLoader.java:1410"
        },
        {
          "method": "java.lang.Runtime.loadLibrary0",
          "source": "Runtime.java:772"
        },
        {
          "method": "java.lang.System.loadLibrary",
          "source": "System.java:832"
        },
        {
          "method": "org.eclipse.swt.internal.Library.loadLibrary",
          "source": "Library.java:102"
        },
        {
          "method": "org.eclipse.swt.internal.gtk.OS.\u003cclinit\u003e",
          "source": "OS.java:20"
        },
        {
          "method": "java.lang.Class.forName0",
          "source": "Native Method"
        },
        {
          "method": "java.lang.Class.forName",
          "source": "Class.java:130"
        },
        {
          "method": "org.eclipse.swt.internal.Library.getPlatform",
          "source": "Library.java:47"
        },
        {
          "method": "org.eclipse.swt.internal.Library.loadLibrary",
          "source": "Library.java:81"
        },
        {
          "method": "org.eclipse.swt.internal.win32.OS.\u003cclinit\u003e",
          "source": "OS.java:40"
        },
        {
          "method": "org.eclipse.swt.widgets.Display.internal_new_GC",
          "source": "Display.java:1107"
        },
        {
          "method": "org.eclipse.swt.graphics.Device.init",
          "source": "Device.java:533"
        },
        {
          "method": "org.eclipse.swt.widgets.Display.init",
          "source": "Display.java:1126"
        },
        {
          "method": "org.eclipse.swt.graphics.Device.\u003cinit\u003e",
          "source": "Device.java:82"
        },
        {
          "method": "org.eclipse.swt.widgets.Display.\u003cinit\u003e",
          "source": "Display.java:277"
        },
        {
          "method": "org.eclipse.swt.widgets.Display.\u003cinit\u003e",
          "source": "Display.java:273"
        },
        {
          "method": "org.eclipse.ui.internal.Workbench.run",
          "source": "Workbench.java:1050"
        },
        {
          "method": "org.eclipse.core.internal.boot.InternalBootLoader.run",
          "source": "InternalBootLoa der.java:739"
        },
        {
          "method": "org.eclipse.core.boot.BootLoader.run",
          "source": "BootLoader.java:462"
        },
        {
          "method": "sun.reflect.NativeMethodAccessorImpl.invoke0",
          "source": "Native Method"
        },
        {
          "method": "sun.reflect.NativeMethodAccessorImpl.invoke",
          "source": "NativeMethodAccessorImpl. java:39"
        },
        {
          "method": "sun.reflect.DelegatingMethodAccessorImpl.invoke",
          "source": "DelegatingMethodAcces sorImpl.java:25"
        },
        {
          "method": "java.lang.reflect.Method.invoke",
          "source": "Method.java:324"
        },
        {
          "method": "org.eclipse.core.launcher.Main.basicRun",
          "source": "Main.java:200"
        },
        {
          "method": "org.eclipse.core.launcher.Main.run",
          "source": "Main.java:643"
        },
        {
          "method": "org.eclipse.core.launcher.Main.main",
          "source": "Main.java:476"
        }
      ],
      "number": 0,
      "commentIndex": 0,
      "bugId": "16784",
      "date": "2002-05-22T15:47:08+02:00",
      "product": "Platform",
      "component": "Update",
      "severity": "critical"
    }
  ],
  "groupId": "16784",
  "bugId": "16784",
  "date": "2002-05-22T15:47:08+02:00",
  "product": "Platform",
  "component": "Update",
  "severity": "critical"
}