{
  "comments": [
    "Build 20020521\n\nGot the following stack trace while opening a project:\n\n!MESSAGE The resource tree is locked for modifications.\n!ENTRY org.eclipse.debug.core 4 120 May 22, 2002 16:41:20.832\n!MESSAGE Error logged from Debug Core:\n!STACK 1\norg.eclipse.debug.core.DebugException: The resource tree is locked for \nmodifications.\n        at org.eclipse.debug.internal.core.BreakpointManager.createBreakpoint\n(BreakpointManager.java:330)\n        at org.eclipse.debug.internal.core.BreakpointManager.loadBreakpoints\n(BreakpointManager.java:127)\n        at \norg.eclipse.debug.internal.core.BreakpointManager.handleProjectResourceOpenState\nChange(BreakpointManager.java:433)\n        at org.eclipse.debug.internal.core.BreakpointManager.access$0\n(BreakpointManager.java:415)\n        at \norg.eclipse.debug.internal.core.BreakpointManager$BreakpointManagerVisitor.visit\n(BreakpointManager.java:452)\n        at org.eclipse.core.internal.events.ResourceDelta.accept\n(ResourceDelta.java:71)\n        at org.eclipse.core.internal.events.ResourceDelta.accept\n(ResourceDelta.java:80)\n        at org.eclipse.core.internal.events.ResourceDelta.accept\n(ResourceDelta.java:52)\n        at org.eclipse.debug.internal.core.BreakpointManager.resourceChanged\n(BreakpointManager.java:393)\n        at org.eclipse.core.internal.events.NotificationManager$1.run\n(NotificationManager.java:128)\n        at org.eclipse.core.internal.runtime.InternalPlatform.run\n(InternalPlatform.java:802)\n        at org.eclipse.core.runtime.Platform.run(Platform.java:416)\n        at org.eclipse.core.internal.events.NotificationManager.notify\n(NotificationManager.java:143)\n        at org.eclipse.core.internal.events.NotificationManager.broadcastChanges\n(NotificationManager.java:67)\n        at org.eclipse.core.internal.resources.Workspace.broadcastChanges\n(Workspace.java:133)\n        at org.eclipse.core.internal.resources.Workspace.endOperation\n(Workspace.java:741)\n        at org.eclipse.core.internal.resources.Project.open(Project.java:623)\n        at org.eclipse.jdt.ui.actions.OpenProjectAction$1.run\n(OpenProjectAction.java:123)\n        at org.eclipse.jface.operation.ModalContext$ModalContextThread.run\n(ModalContext.java:98)",
    "Our old friend... loading breakpoints in response to a resource delta. \n\nSteps:\n(1) Create a breakpoint\n(2) Debug to the breakpoint (so it is installed)\n(3) Close the associated project (while target is running)\n(4) The breakpoint is discarded from the breakpoint manager (in an installed \nstate)\n(5) close workspace\n(6) restart workspace\n(7) Make sure breakpoints view is open\n(8) Re-open the closed project - the breakpoint is created and tries to re-set \nits installed state to uninstalled, which causes the problem (cannot modify a \nresource)",
    "With the existing resource delta/change reporting from Core, there is nothing \nwe can do about this. During the PRE_CLOSE change notification for projects, \nthe resource tree is locked. There is no post open notification.\n\nMarking as LATER for post 2.0 feature requests.\n\nJared, do you agree?",
    "I\u0027d have to look at the code in more detail, but I believe we can actually do\nbetter here. \n\nI believe we add POST_AUTO_BUILD to the type of resource deltas that we listen\nto and we can process the project deltas during this callback.\n\nReopening for more detailed evaluation of this possibility.",
    "Consider for M3.",
    "*** Bug 24903 has been marked as a duplicate of this bug. ***",
    "This has already been fixed - the Breakpoint manager listens for \npost_auto_build notifications. Noted that bug 24903 is not actually a \nduplicate, and it has been re-opened.",
    "Please verify, Jared.",
    "I believe this is the right fix. Verified."
  ],
  "commentCreationDates": [
    "2002-05-22T16:39:14+02:00",
    "2002-05-24T23:22:02+02:00",
    "2002-05-24T23:28:54+02:00",
    "2002-05-25T02:15:41+02:00",
    "2002-10-15T16:12:00+02:00",
    "2002-10-17T14:40:29+02:00",
    "2002-10-23T17:54:55+02:00",
    "2002-10-23T17:55:06+02:00",
    "2002-10-23T21:43:54+02:00"
  ],
  "traces": [
    {
      "exceptionType": "org.eclipse.debug.core.DebugException",
      "message": "The resource tree is locked for  modifications.",
      "elements": [
        {
          "method": "org.eclipse.debug.internal.core.BreakpointManager.createBreakpoint",
          "source": "BreakpointManager.java:330"
        },
        {
          "method": "org.eclipse.debug.internal.core.BreakpointManager.loadBreakpoints",
          "source": "BreakpointManager.java:127"
        },
        {
          "method": "org.eclipse.debug.internal.core.BreakpointManager.handleProjectResourceOpenStateChange",
          "source": "BreakpointManager.java:433"
        },
        {
          "method": "org.eclipse.debug.internal.core.BreakpointManager.access$0",
          "source": "BreakpointManager.java:415"
        },
        {
          "method": "org.eclipse.debug.internal.core.BreakpointManager$BreakpointManagerVisitor.visit",
          "source": "BreakpointManager.java:452"
        },
        {
          "method": "org.eclipse.core.internal.events.ResourceDelta.accept",
          "source": "ResourceDelta.java:71"
        },
        {
          "method": "org.eclipse.core.internal.events.ResourceDelta.accept",
          "source": "ResourceDelta.java:80"
        },
        {
          "method": "org.eclipse.core.internal.events.ResourceDelta.accept",
          "source": "ResourceDelta.java:52"
        },
        {
          "method": "org.eclipse.debug.internal.core.BreakpointManager.resourceChanged",
          "source": "BreakpointManager.java:393"
        },
        {
          "method": "org.eclipse.core.internal.events.NotificationManager$1.run",
          "source": "NotificationManager.java:128"
        },
        {
          "method": "org.eclipse.core.internal.runtime.InternalPlatform.run",
          "source": "InternalPlatform.java:802"
        },
        {
          "method": "org.eclipse.core.runtime.Platform.run",
          "source": "Platform.java:416"
        },
        {
          "method": "org.eclipse.core.internal.events.NotificationManager.notify",
          "source": "NotificationManager.java:143"
        },
        {
          "method": "org.eclipse.core.internal.events.NotificationManager.broadcastChanges",
          "source": "NotificationManager.java:67"
        },
        {
          "method": "org.eclipse.core.internal.resources.Workspace.broadcastChanges",
          "source": "Workspace.java:133"
        },
        {
          "method": "org.eclipse.core.internal.resources.Workspace.endOperation",
          "source": "Workspace.java:741"
        },
        {
          "method": "org.eclipse.core.internal.resources.Project.open",
          "source": "Project.java:623"
        },
        {
          "method": "org.eclipse.jdt.ui.actions.OpenProjectAction$1.run",
          "source": "OpenProjectAction.java:123"
        },
        {
          "method": "org.eclipse.jface.operation.ModalContext$ModalContextThread.run",
          "source": "ModalContext.java:98"
        }
      ],
      "number": 0,
      "commentIndex": 0,
      "bugId": "16817",
      "date": "2002-05-22T16:39:14+02:00",
      "product": "Platform",
      "component": "Debug",
      "severity": "normal"
    }
  ],
  "groupId": "16817",
  "bugId": "16817",
  "date": "2002-05-22T16:39:14+02:00",
  "product": "Platform",
  "component": "Debug",
  "severity": "normal"
}