{
  "comments": [
    "Reported by Tom Schindl on the newsgroup; some are probably fixed by patch last night:\n\n-----\n\nSnippet 1:\n\u003d\u003d\u003d\u003d\u003d\u003d\u003d\u003d\u003d\u003d\nI. Issue\n--------\nOn WinXP:\n1. Entering text in First Name and Last Name in Row 1\n2. Scrolling down to the bottom (the first line reoccurs at certain\npositions)\n3. Scrolling up the first line is empty and my text occurs in 2nd line\n4. Scrolling down to bottom (the first line reoccurs at certain positions)\n5. Scrolling up the first 6 lines are empty and my text occurs in the\n7th line\n\nII. Issue\n---------\nOn Gtk2:\n1. Entering text in First Name and Last Name in Row 1\n2. Scrolling down to the bottom (the first line reoccurs at certain\npositions)\n3. Scrolling up the first line empty and my text occurs in 2nd line\n4. Scrolling down to bottom (the first line reoccurs at certain positions)\n5. Scrolling up the first line empty and my text occurs in 2nd line\n\nIII. Issue\n----------\nOn Gtk2+WinXP: Scrolling fast throws an exception\n\u003e Exception in thread \"main\" java.lang.IndexOutOfBoundsException: Request for a nonexistent row\n\u003e\n\n\t\n\nat org.eclipse.swt.nebula.widgets.compositetable.InternalCompositeTable.getControl(InternalCompositeTable.java:2059)\n\u003e\n\n\t\n\nat org.eclipse.swt.nebula.widgets.compositetable.InternalCompositeTable.resetFocus(InternalCompositeTable.java:783)\n\u003e\n\n\t\n\nat org.eclipse.swt.nebula.widgets.compositetable.InternalCompositeTable.refreshAllRows(InternalCompositeTable.java:758)\n\u003e\n\n\t\n\nat org.eclipse.swt.nebula.widgets.compositetable.InternalCompositeTable.updateVisibleRows(InternalCompositeTable.java:607)\n\u003e\n\n\t\n\nat org.eclipse.swt.nebula.widgets.compositetable.InternalCompositeTable.setTopRow(InternalCompositeTable.java:951)\n\u003e\n\n\t\n\nat org.eclipse.swt.nebula.widgets.compositetable.InternalCompositeTable$3.widgetSelected(InternalCompositeTable.java:1472)\n\u003e\n\n\t\n\nat org.eclipse.swt.widgets.TypedListener.handleEvent(TypedListener.java:90)\n\u003e\n\n\t\n\nat org.eclipse.swt.widgets.EventTable.sendEvent(EventTable.java:66)\n\u003e\n\n\t\n\nat org.eclipse.swt.widgets.Widget.sendEvent(Widget.java:1085)\n\u003e\n\n\t\n\nat org.eclipse.swt.widgets.Display.runDeferredEvents(Display.java:3164)\n\u003e\n\n\t\n\nat org.eclipse.swt.widgets.Display.readAndDispatch(Display.java:2840)\n\u003e\n\n\t\n\nat org.eclipse.swt.nebula.snippets.compositetable.CompositeTableSnippet0.main(CompositeTableSnippet0.java:59)\n\nIV. Issue\n---------\nOn Gtk2+WinXP: Scrolling by clicking in Empty space in scrollbar throws\nan exception",
    "Fixed\u003eHEAD: 20061215\n\nI found and fixed the IndexOutOfBoundsException.  I\u0027ve tested on both Linux/GTK and on Windows XP and have no more of these reported issues.\n\nNote that Snippet 1 hasn\u0027t hooked up the editing features yet.  Snippet 2 does that.  So the editing bugs you\u0027re reporting here are just because Snippet 1 doesn\u0027t support editing yet.\n\nI think this should get you running again.  Please let me know if you still have issues.\n"
  ],
  "commentCreationDates": [
    "2006-12-15T14:31:10+01:00",
    "2006-12-15T18:52:15+01:00"
  ],
  "traces": [
    {
      "exceptionType": "java.lang.IndexOutOfBoundsException",
      "message": "Request for a nonexistent row \u003e",
      "elements": [
        {
          "method": "org.eclipse.swt.nebula.widgets.compositetable.InternalCompositeTable.getControl",
          "source": "InternalCompositeTable.java:2059"
        }
      ],
      "number": 0,
      "commentIndex": 0,
      "bugId": "168205",
      "date": "2006-12-15T14:31:10+01:00",
      "product": "Nebula",
      "component": "CompositeTable",
      "severity": "major"
    }
  ],
  "groupId": "168205",
  "bugId": "168205",
  "date": "2006-12-15T14:31:10+01:00",
  "product": "Nebula",
  "component": "CompositeTable",
  "severity": "major"
}