{
  "comments": [
    "Build 20020521 running on JDK 1.3.1\nTarget: JDK 1.4.1\n\nIt must be a timing issue as I cannot reproduce. All I was doing was to open a \njava editor in the runtime workbench when I got the following exceptions in the \nDOS console of the development workbench:\n\n!ENTRY org.eclipse.jdt.debug 4 120 May 22, 2002 17:00:53.698\n!MESSAGE Internal error logged from JDI Debug:\n!STACK 0\ncom.sun.jdi.ObjectCollectedException\n        at org.eclipse.jdi.internal.MirrorImpl.defaultReplyErrorHandler\n(MirrorImpl.java:235)\n        at org.eclipse.jdi.internal.ThreadReferenceImpl.isSuspended\n(ThreadReferenceImpl.java:236)\n        at org.eclipse.jdt.internal.debug.core.model.JDIThread.initialize\n(JDIThread.java:192)\n        at org.eclipse.jdt.internal.debug.core.model.JDIThread.\u003cinit\u003e\n(JDIThread.java:160)\n        at org.eclipse.jdt.internal.debug.core.model.JDIDebugTarget.createThread\n(JDIDebugTarget.java:422)\n        at \norg.eclipse.jdt.internal.debug.core.model.JDIDebugTarget$ThreadStartHandler.hand\nleEvent(JDIDebugTarget.java:1790)\n        at org.eclipse.jdt.internal.debug.core.EventDispatcher.dispatch\n(EventDispatcher.java:129)\n        at org.eclipse.jdt.internal.debug.core.EventDispatcher.run\n(EventDispatcher.java:202)\n        at java.lang.Thread.run(Thread.java:484)\n!ENTRY org.eclipse.jdt.debug.ui 4 150 May 22, 2002 17:00:53.859\n!MESSAGE Internal Error\n!STACK 1\norg.eclipse.debug.core.DebugException[5010]: \ncom.sun.jdi.ObjectCollectedException\n        at org.eclipse.jdi.internal.MirrorImpl.defaultReplyErrorHandler\n(MirrorImpl.java:235)\n        at org.eclipse.jdi.internal.ThreadReferenceImpl.name\n(ThreadReferenceImpl.java:262)\n        at org.eclipse.jdt.internal.debug.core.model.JDIThread.getName\n(JDIThread.java:788)\n        at org.eclipse.jdt.internal.debug.ui.JDIModelPresentation.getThreadText\n(JDIModelPresentation.java:369)\n        at org.eclipse.jdt.internal.debug.ui.JDIModelPresentation.getText\n(JDIModelPresentation.java:198)\n        at org.eclipse.debug.internal.ui.LazyModelPresentation.getText\n(LazyModelPresentation.java:69)\n        at org.eclipse.debug.internal.ui.DelegatingModelPresentation.getText\n(DelegatingModelPresentation.java:122)\n        at org.eclipse.jface.viewers.TreeViewer.doUpdateItem(TreeViewer.java:82)\n        at org.eclipse.jface.viewers.AbstractTreeViewer.doUpdateItem\n(AbstractTreeViewer.java:354)\n        at org.eclipse.jface.viewers.StructuredViewer.updateItem\n(StructuredViewer.java:1134)\n        at org.eclipse.jface.viewers.AbstractTreeViewer.createTreeItem\n(AbstractTreeViewer.java:258)\n        at org.eclipse.jface.viewers.AbstractTreeViewer.add\n(AbstractTreeViewer.java:130)\n        at org.eclipse.jface.viewers.AbstractTreeViewer.add\n(AbstractTreeViewer.java:163)\n        at org.eclipse.debug.internal.ui.views.AbstractDebugEventHandler.insert\n(AbstractDebugEventHandler.java:74)\n        at \norg.eclipse.debug.internal.ui.views.launch.LaunchViewEventHandler.doHandleDebugE\nvents(LaunchViewEventHandler.java:73)\n        at org.eclipse.debug.internal.ui.views.AbstractDebugEventHandler$1.run\n(AbstractDebugEventHandler.java:49)\n        at org.eclipse.swt.widgets.RunnableLock.run(RunnableLock.java:29)\n        at org.eclipse.swt.widgets.Synchronizer.runAsyncMessages\n(Synchronizer.java:93)\n        at org.eclipse.swt.widgets.Display.runAsyncMessages(Display.java:1504)\n        at org.eclipse.swt.widgets.Display.readAndDispatch(Display.java:1292)\n        at org.eclipse.ui.internal.Workbench.runEventLoop(Workbench.java:1085)\n        at org.eclipse.ui.internal.Workbench.run(Workbench.java:1068)\n        at org.eclipse.core.internal.boot.InternalBootLoader.run\n(InternalBootLoader.java:739)\n        at org.eclipse.core.boot.BootLoader.run(BootLoader.java:462)\n        at java.lang.reflect.Method.invoke(Native Method)\n        at org.eclipse.core.launcher.Main.basicRun(Main.java:200)\n        at org.eclipse.core.launcher.Main.run(Main.java:643)\n        at org.eclipse.core.launcher.Main.main(Main.java:476)\n!ENTRY org.eclipse.jdt.debug 4 5010 May 22, 2002 17:00:53.859\n!MESSAGE com.sun.jdi.ObjectCollectedException occurred retrieving thread name.\n!STACK 0\ncom.sun.jdi.ObjectCollectedException\n        at org.eclipse.jdi.internal.MirrorImpl.defaultReplyErrorHandler\n(MirrorImpl.java:235)\n        at org.eclipse.jdi.internal.ThreadReferenceImpl.name\n(ThreadReferenceImpl.java:262)\n        at org.eclipse.jdt.internal.debug.core.model.JDIThread.getName\n(JDIThread.java:788)\n        at org.eclipse.jdt.internal.debug.ui.JDIModelPresentation.getThreadText\n(JDIModelPresentation.java:369)\n        at org.eclipse.jdt.internal.debug.ui.JDIModelPresentation.getText\n(JDIModelPresentation.java:198)\n        at org.eclipse.debug.internal.ui.LazyModelPresentation.getText\n(LazyModelPresentation.java:69)\n        at org.eclipse.debug.internal.ui.DelegatingModelPresentation.getText\n(DelegatingModelPresentation.java:122)\n        at org.eclipse.jface.viewers.TreeViewer.doUpdateItem(TreeViewer.java:82)\n        at org.eclipse.jface.viewers.AbstractTreeViewer.doUpdateItem\n(AbstractTreeViewer.java:354)\n        at org.eclipse.jface.viewers.StructuredViewer.updateItem\n(StructuredViewer.java:1134)\n        at org.eclipse.jface.viewers.AbstractTreeViewer.createTreeItem\n(AbstractTreeViewer.java:258)\n        at org.eclipse.jface.viewers.AbstractTreeViewer.add\n(AbstractTreeViewer.java:130)\n        at org.eclipse.jface.viewers.AbstractTreeViewer.add\n(AbstractTreeViewer.java:163)\n        at org.eclipse.debug.internal.ui.views.AbstractDebugEventHandler.insert\n(AbstractDebugEventHandler.java:74)\n        at \norg.eclipse.debug.internal.ui.views.launch.LaunchViewEventHandler.doHandleDebugE\nvents(LaunchViewEventHandler.java:73)\n        at org.eclipse.debug.internal.ui.views.AbstractDebugEventHandler$1.run\n(AbstractDebugEventHandler.java:49)\n        at org.eclipse.swt.widgets.RunnableLock.run(RunnableLock.java:29)\n        at org.eclipse.swt.widgets.Synchronizer.runAsyncMessages\n(Synchronizer.java:93)\n        at org.eclipse.swt.widgets.Display.runAsyncMessages(Display.java:1504)\n        at org.eclipse.swt.widgets.Display.readAndDispatch(Display.java:1292)\n        at org.eclipse.ui.internal.Workbench.runEventLoop(Workbench.java:1085)\n        at org.eclipse.ui.internal.Workbench.run(Workbench.java:1068)\n        at org.eclipse.core.internal.boot.InternalBootLoader.run\n(InternalBootLoader.java:739)\n        at org.eclipse.core.boot.BootLoader.run(BootLoader.java:462)\n        at java.lang.reflect.Method.invoke(Native Method)\n        at org.eclipse.core.launcher.Main.basicRun(Main.java:200)\n        at org.eclipse.core.launcher.Main.run(Main.java:643)\n        at org.eclipse.core.launcher.Main.main(Main.java:476)",
    "*** Bug 16991 has been marked as a duplicate of this bug. ***",
    "This can happen if we get a thread start event, but by the time we get around \nto creating the thread in our model, the thread is gone.\n\nFixed in JDIDebugTarget.createThread().\n\nPlease verify.",
    "Verified."
  ],
  "commentCreationDates": [
    "2002-05-22T17:02:54+02:00",
    "2002-05-22T21:39:06+02:00",
    "2002-05-24T18:34:19+02:00",
    "2002-05-25T23:18:03+02:00"
  ],
  "traces": [
    {
      "exceptionType": "com.sun.jdi.ObjectCollectedException",
      "elements": [
        {
          "method": "org.eclipse.jdi.internal.MirrorImpl.defaultReplyErrorHandler",
          "source": "MirrorImpl.java:235"
        },
        {
          "method": "org.eclipse.jdi.internal.ThreadReferenceImpl.isSuspended",
          "source": "ThreadReferenceImpl.java:236"
        },
        {
          "method": "org.eclipse.jdt.internal.debug.core.model.JDIThread.initialize",
          "source": "JDIThread.java:192"
        },
        {
          "method": "org.eclipse.jdt.internal.debug.core.model.JDIThread.\u003cinit\u003e",
          "source": "JDIThread.java:160"
        },
        {
          "method": "org.eclipse.jdt.internal.debug.core.model.JDIDebugTarget.createThread",
          "source": "JDIDebugTarget.java:422"
        },
        {
          "method": "org.eclipse.jdt.internal.debug.core.model.JDIDebugTarget$ThreadStartHandler.handleEvent",
          "source": "JDIDebugTarget.java:1790"
        },
        {
          "method": "org.eclipse.jdt.internal.debug.core.EventDispatcher.dispatch",
          "source": "EventDispatcher.java:129"
        },
        {
          "method": "org.eclipse.jdt.internal.debug.core.EventDispatcher.run",
          "source": "EventDispatcher.java:202"
        },
        {
          "method": "java.lang.Thread.run",
          "source": "Thread.java:484"
        }
      ],
      "number": 0,
      "commentIndex": 0,
      "bugId": "16834",
      "date": "2002-05-22T17:02:54+02:00",
      "product": "JDT",
      "component": "Debug",
      "severity": "normal"
    },
    {
      "exceptionType": "com.sun.jdi.ObjectCollectedException",
      "elements": [
        {
          "method": "org.eclipse.jdi.internal.MirrorImpl.defaultReplyErrorHandler",
          "source": "MirrorImpl.java:235"
        },
        {
          "method": "org.eclipse.jdi.internal.ThreadReferenceImpl.name",
          "source": "ThreadReferenceImpl.java:262"
        },
        {
          "method": "org.eclipse.jdt.internal.debug.core.model.JDIThread.getName",
          "source": "JDIThread.java:788"
        },
        {
          "method": "org.eclipse.jdt.internal.debug.ui.JDIModelPresentation.getThreadText",
          "source": "JDIModelPresentation.java:369"
        },
        {
          "method": "org.eclipse.jdt.internal.debug.ui.JDIModelPresentation.getText",
          "source": "JDIModelPresentation.java:198"
        },
        {
          "method": "org.eclipse.debug.internal.ui.LazyModelPresentation.getText",
          "source": "LazyModelPresentation.java:69"
        },
        {
          "method": "org.eclipse.debug.internal.ui.DelegatingModelPresentation.getText",
          "source": "DelegatingModelPresentation.java:122"
        },
        {
          "method": "org.eclipse.jface.viewers.TreeViewer.doUpdateItem",
          "source": "TreeViewer.java:82"
        },
        {
          "method": "org.eclipse.jface.viewers.AbstractTreeViewer.doUpdateItem",
          "source": "AbstractTreeViewer.java:354"
        },
        {
          "method": "org.eclipse.jface.viewers.StructuredViewer.updateItem",
          "source": "StructuredViewer.java:1134"
        },
        {
          "method": "org.eclipse.jface.viewers.AbstractTreeViewer.createTreeItem",
          "source": "AbstractTreeViewer.java:258"
        },
        {
          "method": "org.eclipse.jface.viewers.AbstractTreeViewer.add",
          "source": "AbstractTreeViewer.java:130"
        },
        {
          "method": "org.eclipse.jface.viewers.AbstractTreeViewer.add",
          "source": "AbstractTreeViewer.java:163"
        },
        {
          "method": "org.eclipse.debug.internal.ui.views.AbstractDebugEventHandler.insert",
          "source": "AbstractDebugEventHandler.java:74"
        },
        {
          "method": "org.eclipse.debug.internal.ui.views.launch.LaunchViewEventHandler.doHandleDebugEvents",
          "source": "LaunchViewEventHandler.java:73"
        },
        {
          "method": "org.eclipse.debug.internal.ui.views.AbstractDebugEventHandler$1.run",
          "source": "AbstractDebugEventHandler.java:49"
        },
        {
          "method": "org.eclipse.swt.widgets.RunnableLock.run",
          "source": "RunnableLock.java:29"
        },
        {
          "method": "org.eclipse.swt.widgets.Synchronizer.runAsyncMessages",
          "source": "Synchronizer.java:93"
        },
        {
          "method": "org.eclipse.swt.widgets.Display.runAsyncMessages",
          "source": "Display.java:1504"
        },
        {
          "method": "org.eclipse.swt.widgets.Display.readAndDispatch",
          "source": "Display.java:1292"
        },
        {
          "method": "org.eclipse.ui.internal.Workbench.runEventLoop",
          "source": "Workbench.java:1085"
        },
        {
          "method": "org.eclipse.ui.internal.Workbench.run",
          "source": "Workbench.java:1068"
        },
        {
          "method": "org.eclipse.core.internal.boot.InternalBootLoader.run",
          "source": "InternalBootLoader.java:739"
        },
        {
          "method": "org.eclipse.core.boot.BootLoader.run",
          "source": "BootLoader.java:462"
        },
        {
          "method": "java.lang.reflect.Method.invoke",
          "source": "Native Method"
        },
        {
          "method": "org.eclipse.core.launcher.Main.basicRun",
          "source": "Main.java:200"
        },
        {
          "method": "org.eclipse.core.launcher.Main.run",
          "source": "Main.java:643"
        },
        {
          "method": "org.eclipse.core.launcher.Main.main",
          "source": "Main.java:476"
        }
      ],
      "number": 1,
      "commentIndex": 0,
      "bugId": "16834",
      "date": "2002-05-22T17:02:54+02:00",
      "product": "JDT",
      "component": "Debug",
      "severity": "normal"
    },
    {
      "exceptionType": "com.sun.jdi.ObjectCollectedException",
      "elements": [
        {
          "method": "org.eclipse.jdi.internal.MirrorImpl.defaultReplyErrorHandler",
          "source": "MirrorImpl.java:235"
        },
        {
          "method": "org.eclipse.jdi.internal.ThreadReferenceImpl.name",
          "source": "ThreadReferenceImpl.java:262"
        },
        {
          "method": "org.eclipse.jdt.internal.debug.core.model.JDIThread.getName",
          "source": "JDIThread.java:788"
        },
        {
          "method": "org.eclipse.jdt.internal.debug.ui.JDIModelPresentation.getThreadText",
          "source": "JDIModelPresentation.java:369"
        },
        {
          "method": "org.eclipse.jdt.internal.debug.ui.JDIModelPresentation.getText",
          "source": "JDIModelPresentation.java:198"
        },
        {
          "method": "org.eclipse.debug.internal.ui.LazyModelPresentation.getText",
          "source": "LazyModelPresentation.java:69"
        },
        {
          "method": "org.eclipse.debug.internal.ui.DelegatingModelPresentation.getText",
          "source": "DelegatingModelPresentation.java:122"
        },
        {
          "method": "org.eclipse.jface.viewers.TreeViewer.doUpdateItem",
          "source": "TreeViewer.java:82"
        },
        {
          "method": "org.eclipse.jface.viewers.AbstractTreeViewer.doUpdateItem",
          "source": "AbstractTreeViewer.java:354"
        },
        {
          "method": "org.eclipse.jface.viewers.StructuredViewer.updateItem",
          "source": "StructuredViewer.java:1134"
        },
        {
          "method": "org.eclipse.jface.viewers.AbstractTreeViewer.createTreeItem",
          "source": "AbstractTreeViewer.java:258"
        },
        {
          "method": "org.eclipse.jface.viewers.AbstractTreeViewer.add",
          "source": "AbstractTreeViewer.java:130"
        },
        {
          "method": "org.eclipse.jface.viewers.AbstractTreeViewer.add",
          "source": "AbstractTreeViewer.java:163"
        },
        {
          "method": "org.eclipse.debug.internal.ui.views.AbstractDebugEventHandler.insert",
          "source": "AbstractDebugEventHandler.java:74"
        },
        {
          "method": "org.eclipse.debug.internal.ui.views.launch.LaunchViewEventHandler.doHandleDebugEvents",
          "source": "LaunchViewEventHandler.java:73"
        },
        {
          "method": "org.eclipse.debug.internal.ui.views.AbstractDebugEventHandler$1.run",
          "source": "AbstractDebugEventHandler.java:49"
        },
        {
          "method": "org.eclipse.swt.widgets.RunnableLock.run",
          "source": "RunnableLock.java:29"
        },
        {
          "method": "org.eclipse.swt.widgets.Synchronizer.runAsyncMessages",
          "source": "Synchronizer.java:93"
        },
        {
          "method": "org.eclipse.swt.widgets.Display.runAsyncMessages",
          "source": "Display.java:1504"
        },
        {
          "method": "org.eclipse.swt.widgets.Display.readAndDispatch",
          "source": "Display.java:1292"
        },
        {
          "method": "org.eclipse.ui.internal.Workbench.runEventLoop",
          "source": "Workbench.java:1085"
        },
        {
          "method": "org.eclipse.ui.internal.Workbench.run",
          "source": "Workbench.java:1068"
        },
        {
          "method": "org.eclipse.core.internal.boot.InternalBootLoader.run",
          "source": "InternalBootLoader.java:739"
        },
        {
          "method": "org.eclipse.core.boot.BootLoader.run",
          "source": "BootLoader.java:462"
        },
        {
          "method": "java.lang.reflect.Method.invoke",
          "source": "Native Method"
        },
        {
          "method": "org.eclipse.core.launcher.Main.basicRun",
          "source": "Main.java:200"
        },
        {
          "method": "org.eclipse.core.launcher.Main.run",
          "source": "Main.java:643"
        },
        {
          "method": "org.eclipse.core.launcher.Main.main",
          "source": "Main.java:476"
        }
      ],
      "number": 2,
      "commentIndex": 0,
      "bugId": "16834",
      "date": "2002-05-22T17:02:54+02:00",
      "product": "JDT",
      "component": "Debug",
      "severity": "normal"
    }
  ],
  "groupId": "16834",
  "bugId": "16834",
  "date": "2002-05-22T17:02:54+02:00",
  "product": "JDT",
  "component": "Debug",
  "severity": "normal"
}