{
  "comments": [
    "0521 Integration Win32\n\nIf I select a constructor in the outline and choose refactor -\u003e modify \nparameters, I receive the following:\n\norg.eclipse.jdt.internal.corext.refactoring.Assert$AssertionFailedException: \nassertion failed; element not found\n        at org.eclipse.jdt.internal.corext.refactoring.Assert.isTrue\n(Assert.java:132)\n        at \norg.eclipse.jdt.internal.corext.refactoring.structure.ReorderParametersRefactor\ning.getIndexOf(ReorderParametersRefactoring.java:203)\n        at \norg.eclipse.jdt.internal.corext.refactoring.structure.ReorderParametersRefactor\ning.getNewParameterPosition(ReorderParametersRefactoring.java:93)\n        at \norg.eclipse.jdt.internal.corext.refactoring.structure.ModifyParametersRefactori\nng.getNewParameterPosition(ModifyParametersRefactoring.java:49)\n        at \norg.eclipse.jdt.internal.ui.refactoring.ModifyParametersInputPage$ParameterInfo\nComparator.compare(ModifyParametersInputPage.java:470)\n        at \norg.eclipse.jdt.internal.ui.refactoring.ModifyParametersInputPage$ParameterInfo\nListSorter.compare(ModifyParametersInputPage.java:483)\n        at org.eclipse.jface.viewers.ViewerSorter$1.compare(ViewerSorter.java\n(Compiled Code))\n        at java.util.Arrays.mergeSort(Arrays.java(Compiled Code))\n        at java.util.Arrays.sort(Arrays.java:1137)\n        at org.eclipse.jface.viewers.ViewerSorter.sort(ViewerSorter.java:160)\n        at org.eclipse.jface.viewers.StructuredViewer.getSortedChildren\n(StructuredViewer.java:451)\n        at org.eclipse.jface.viewers.TableViewer.internalRefresh\n(TableViewer.java:424)\n        at org.eclipse.jface.viewers.TableViewer.internalRefresh\n(TableViewer.java:408)\n        at org.eclipse.jface.viewers.StructuredViewer$4.run\n(StructuredViewer.java:748)\n        at org.eclipse.jface.viewers.StructuredViewer.preservingSelection\n(StructuredViewer.java:688)\n        at org.eclipse.jface.viewers.StructuredViewer.refresh\n(StructuredViewer.java:746)\n        at org.eclipse.jface.viewers.StructuredViewer.refresh\n(StructuredViewer.java:708)\n        at org.eclipse.jface.viewers.TableViewer.inputChanged\n(TableViewer.java:375)\n        at org.eclipse.jface.viewers.ContentViewer.setInput\n(ContentViewer.java:234)\n        at org.eclipse.jface.viewers.StructuredViewer.setInput\n(StructuredViewer.java:875)\n        at \norg.eclipse.jdt.internal.ui.refactoring.ModifyParametersInputPage.createParamet\nerList(ModifyParametersInputPage.java:138)\n        at \norg.eclipse.jdt.internal.ui.refactoring.ModifyParametersInputPage.createParamet\nerTableComposite(ModifyParametersInputPage.java:110)\n        at \norg.eclipse.jdt.internal.ui.refactoring.ModifyParametersInputPage.createControl\n(ModifyParametersInputPage.java:81)\n        at org.eclipse.jface.wizard.Wizard.createPageControls(Wizard.java:164)\n        at org.eclipse.jface.wizard.WizardDialog.createPageControls\n(WizardDialog.java:505)\n        at org.eclipse.jface.wizard.WizardDialog.createContents\n(WizardDialog.java:456)\n        at org.eclipse.jface.window.Window.create(Window.java:278)\n        at org.eclipse.jface.window.Window.open(Window.java:527)\n        at \norg.eclipse.jdt.internal.ui.refactoring.actions.RefactoringStarter.activate\n(RefactoringStarter.java:79)\n        at \norg.eclipse.jdt.ui.actions.OpenRefactoringWizardAction.startRefactoring\n(OpenRefactoringWizardAction.java:142)\n        at org.eclipse.jdt.ui.actions.OpenRefactoringWizardAction.run\n(OpenRefactoringWizardAction.java:67)\n        at org.eclipse.jdt.ui.actions.SelectionDispatchAction.dispatchRun\n(SelectionDispatchAction.java:178)\n        at org.eclipse.jdt.ui.actions.SelectionDispatchAction.run\n(SelectionDispatchAction.java:156)\n        at org.eclipse.jface.action.Action.runWithEvent(Action.java:590)\n        at \norg.eclipse.jface.action.ActionContributionItem.handleWidgetSelection\n(ActionContributionItem.java:407)\n        at \norg.eclipse.jface.action.ActionContributionItem$ActionListener.handleEvent\n(ActionContributionItem.java(Compiled Code))\n        at \norg.eclipse.jface.action.ActionContributionItem$ActionListener.handleEvent\n(ActionContributionItem.java(Compiled Code))\n        at \norg.eclipse.jface.action.ActionContributionItem$ActionListener.handleEvent\n(ActionContributionItem.java(Compiled Code))\n        at org.eclipse.swt.widgets.Display.runDeferredEvents(Display.java\n(Compiled Code))\n        at org.eclipse.swt.widgets.Display.runDeferredEvents(Display.java\n(Compiled Code))\n        at org.eclipse.swt.widgets.Display.runDeferredEvents(Display.java\n(Compiled Code))\n        at org.eclipse.swt.widgets.Display.readAndDispatch(Display.java\n(Compiled Code))\n        at org.eclipse.ui.internal.Workbench.runEventLoop(Workbench.java\n(Compiled Code))\n        at org.eclipse.ui.internal.Workbench.run(Workbench.java:1068)\n        at org.eclipse.core.internal.boot.InternalBootLoader.run\n(InternalBootLoader.java:739)\n        at org.eclipse.core.boot.BootLoader.run(BootLoader.java:462)\n        at java.lang.reflect.Method.invoke(Native Method)\n        at org.eclipse.core.launcher.Main.basicRun(Main.java:200)\n        at org.eclipse.core.launcher.Main.run(Main.java:643)\n        at org.eclipse.core.launcher.Main.main(Main.java:476)",
    "Move to JDT/UI. This looks like a refactoring problem.",
    "cannot reproduce on F1 (but i don\u0027t think the code changed)\ncan you send me the file you see this error in?",
    "sorry, cannot reproduce - i tried F1 and 0528\ni tried many constructors and methods :)\n\nalso, by looking at the code i\u0027m not sure how this could happen.\nplease, by all means, reopen if you can isolate a test case (i\u0027d need no \ncontext, probably, just the contstructor)\n",
    "changed milestone from F1 to F2"
  ],
  "commentCreationDates": [
    "2002-05-22T17:42:06+02:00",
    "2002-05-22T18:29:16+02:00",
    "2002-05-27T12:19:08+02:00",
    "2002-05-29T18:53:28+02:00",
    "2002-06-02T22:49:08+02:00"
  ],
  "traces": [
    {
      "exceptionType": "org.eclipse.jdt.internal.corext.refactoring.Assert$AssertionFailedException",
      "message": "assertion failed; element not found",
      "elements": [
        {
          "method": "org.eclipse.jdt.internal.corext.refactoring.Assert.isTrue",
          "source": "Assert.java:132"
        },
        {
          "method": "org.eclipse.jdt.internal.corext.refactoring.structure.ReorderParametersRefactoring.getIndexOf",
          "source": "ReorderParametersRefactoring.java:203"
        },
        {
          "method": "org.eclipse.jdt.internal.corext.refactoring.structure.ReorderParametersRefactoring.getNewParameterPosition",
          "source": "ReorderParametersRefactoring.java:93"
        },
        {
          "method": "org.eclipse.jdt.internal.corext.refactoring.structure.ModifyParametersRefactoring.getNewParameterPosition",
          "source": "ModifyParametersRefactoring.java:49"
        },
        {
          "method": "org.eclipse.jdt.internal.ui.refactoring.ModifyParametersInputPage$ParameterInfoComparator.compare",
          "source": "ModifyParametersInputPage.java:470"
        },
        {
          "method": "org.eclipse.jdt.internal.ui.refactoring.ModifyParametersInputPage$ParameterInfoListSorter.compare",
          "source": "ModifyParametersInputPage.java:483"
        },
        {
          "method": "org.eclipse.jface.viewers.ViewerSorter$1.compare",
          "source": "ViewerSorter.java (Compiled Code)"
        },
        {
          "method": "java.util.Arrays.mergeSort",
          "source": "Arrays.java(Compiled Code)"
        },
        {
          "method": "java.util.Arrays.sort",
          "source": "Arrays.java:1137"
        },
        {
          "method": "org.eclipse.jface.viewers.ViewerSorter.sort",
          "source": "ViewerSorter.java:160"
        },
        {
          "method": "org.eclipse.jface.viewers.StructuredViewer.getSortedChildren",
          "source": "StructuredViewer.java:451"
        },
        {
          "method": "org.eclipse.jface.viewers.TableViewer.internalRefresh",
          "source": "TableViewer.java:424"
        },
        {
          "method": "org.eclipse.jface.viewers.TableViewer.internalRefresh",
          "source": "TableViewer.java:408"
        },
        {
          "method": "org.eclipse.jface.viewers.StructuredViewer$4.run",
          "source": "StructuredViewer.java:748"
        },
        {
          "method": "org.eclipse.jface.viewers.StructuredViewer.preservingSelection",
          "source": "StructuredViewer.java:688"
        },
        {
          "method": "org.eclipse.jface.viewers.StructuredViewer.refresh",
          "source": "StructuredViewer.java:746"
        },
        {
          "method": "org.eclipse.jface.viewers.StructuredViewer.refresh",
          "source": "StructuredViewer.java:708"
        },
        {
          "method": "org.eclipse.jface.viewers.TableViewer.inputChanged",
          "source": "TableViewer.java:375"
        },
        {
          "method": "org.eclipse.jface.viewers.ContentViewer.setInput",
          "source": "ContentViewer.java:234"
        },
        {
          "method": "org.eclipse.jface.viewers.StructuredViewer.setInput",
          "source": "StructuredViewer.java:875"
        },
        {
          "method": "org.eclipse.jdt.internal.ui.refactoring.ModifyParametersInputPage.createParameterList",
          "source": "ModifyParametersInputPage.java:138"
        },
        {
          "method": "org.eclipse.jdt.internal.ui.refactoring.ModifyParametersInputPage.createParameterTableComposite",
          "source": "ModifyParametersInputPage.java:110"
        },
        {
          "method": "org.eclipse.jdt.internal.ui.refactoring.ModifyParametersInputPage.createControl",
          "source": "ModifyParametersInputPage.java:81"
        },
        {
          "method": "org.eclipse.jface.wizard.Wizard.createPageControls",
          "source": "Wizard.java:164"
        },
        {
          "method": "org.eclipse.jface.wizard.WizardDialog.createPageControls",
          "source": "WizardDialog.java:505"
        },
        {
          "method": "org.eclipse.jface.wizard.WizardDialog.createContents",
          "source": "WizardDialog.java:456"
        },
        {
          "method": "org.eclipse.jface.window.Window.create",
          "source": "Window.java:278"
        },
        {
          "method": "org.eclipse.jface.window.Window.open",
          "source": "Window.java:527"
        },
        {
          "method": "org.eclipse.jdt.internal.ui.refactoring.actions.RefactoringStarter.activate",
          "source": "RefactoringStarter.java:79"
        },
        {
          "method": "org.eclipse.jdt.ui.actions.OpenRefactoringWizardAction.startRefactoring",
          "source": "OpenRefactoringWizardAction.java:142"
        },
        {
          "method": "org.eclipse.jdt.ui.actions.OpenRefactoringWizardAction.run",
          "source": "OpenRefactoringWizardAction.java:67"
        },
        {
          "method": "org.eclipse.jdt.ui.actions.SelectionDispatchAction.dispatchRun",
          "source": "SelectionDispatchAction.java:178"
        },
        {
          "method": "org.eclipse.jdt.ui.actions.SelectionDispatchAction.run",
          "source": "SelectionDispatchAction.java:156"
        },
        {
          "method": "org.eclipse.jface.action.Action.runWithEvent",
          "source": "Action.java:590"
        },
        {
          "method": "org.eclipse.jface.action.ActionContributionItem.handleWidgetSelection",
          "source": "ActionContributionItem.java:407"
        },
        {
          "method": "org.eclipse.jface.action.ActionContributionItem$ActionListener.handleEvent",
          "source": "ActionContributionItem.java(Compiled Code)"
        },
        {
          "method": "org.eclipse.jface.action.ActionContributionItem$ActionListener.handleEvent",
          "source": "ActionContributionItem.java(Compiled Code)"
        },
        {
          "method": "org.eclipse.jface.action.ActionContributionItem$ActionListener.handleEvent",
          "source": "ActionContributionItem.java(Compiled Code)"
        },
        {
          "method": "org.eclipse.swt.widgets.Display.runDeferredEvents",
          "source": "Display.java (Compiled Code)"
        },
        {
          "method": "org.eclipse.swt.widgets.Display.runDeferredEvents",
          "source": "Display.java (Compiled Code)"
        },
        {
          "method": "org.eclipse.swt.widgets.Display.runDeferredEvents",
          "source": "Display.java (Compiled Code)"
        },
        {
          "method": "org.eclipse.swt.widgets.Display.readAndDispatch",
          "source": "Display.java (Compiled Code)"
        },
        {
          "method": "org.eclipse.ui.internal.Workbench.runEventLoop",
          "source": "Workbench.java (Compiled Code)"
        },
        {
          "method": "org.eclipse.ui.internal.Workbench.run",
          "source": "Workbench.java:1068"
        },
        {
          "method": "org.eclipse.core.internal.boot.InternalBootLoader.run",
          "source": "InternalBootLoader.java:739"
        },
        {
          "method": "org.eclipse.core.boot.BootLoader.run",
          "source": "BootLoader.java:462"
        },
        {
          "method": "java.lang.reflect.Method.invoke",
          "source": "Native Method"
        },
        {
          "method": "org.eclipse.core.launcher.Main.basicRun",
          "source": "Main.java:200"
        },
        {
          "method": "org.eclipse.core.launcher.Main.run",
          "source": "Main.java:643"
        },
        {
          "method": "org.eclipse.core.launcher.Main.main",
          "source": "Main.java:476"
        }
      ],
      "number": 0,
      "commentIndex": 0,
      "bugId": "16870",
      "date": "2002-05-22T17:42:06+02:00",
      "product": "JDT",
      "component": "UI",
      "severity": "major"
    }
  ],
  "groupId": "16870",
  "bugId": "16870",
  "date": "2002-05-22T17:42:06+02:00",
  "product": "JDT",
  "component": "UI",
  "severity": "major"
}