{
  "comments": [
    "I20061219-0800 and I20061219-1300\n\nI can\u0027t startup eclipse with this weeks integration builds. Reason:\n\n!MESSAGE An error occurred while automatically activating bundle org.eclipse.equinox.app (32).\n!STACK 0\norg.osgi.framework.BundleException: Exception in org.eclipse.equinox.internal.app.Activator.start() of bundle org.eclipse.equinox.app.\n        at org.eclipse.osgi.framework.internal.core.BundleContextImpl.startActivator(BundleContextImpl.java:1018)\n        at org.eclipse.osgi.framework.internal.core.BundleContextImpl.start(BundleContextImpl.java:974)\n        at org.eclipse.osgi.framework.internal.core.BundleHost.startWorker(BundleHost.java:327)\n        at org.eclipse.osgi.framework.internal.core.AbstractBundle.start(AbstractBundle.java:260)\n        at org.eclipse.osgi.framework.util.SecureAction.start(SecureAction.java:400)\n        at org.eclipse.core.runtime.internal.adaptor.EclipseLazyStarter.postFindLocalClass(EclipseLazyStarter.java:111)\n        at org.eclipse.osgi.baseadaptor.loader.ClasspathManager.findLocalClass(ClasspathManager.java:417)\n        at org.eclipse.osgi.internal.baseadaptor.DefaultClassLoader.findLocalClass(DefaultClassLoader.java:189)\n        at org.eclipse.osgi.framework.internal.core.BundleLoader.findLocalClass(BundleLoader.java:340)\n        at org.eclipse.osgi.framework.internal.core.SingleSourcePackage.loadClass(SingleSourcePackage.java:37)\n        at org.eclipse.osgi.framework.internal.core.BundleLoader.findClassInternal(BundleLoader.java:405)\n        at org.eclipse.osgi.framework.internal.core.BundleLoader.findClass(BundleLoader.java:369)\n        at org.eclipse.osgi.framework.internal.core.BundleLoader.findClass(BundleLoader.java:357)\n        at org.eclipse.osgi.internal.baseadaptor.DefaultClassLoader.loadClass(DefaultClassLoader.java:83)\n        at java.lang.ClassLoader.loadClass(ClassLoader.java:251)\n        at java.lang.ClassLoader.loadClassInternal(ClassLoader.java:319)\n        at org.eclipse.core.internal.runtime.PlatformActivator.startAppContainer(PlatformActivator.java:47)\n        at org.eclipse.core.internal.runtime.PlatformActivator.start(PlatformActivator.java:32)\n        at org.eclipse.osgi.framework.internal.core.BundleContextImpl$2.run(BundleContextImpl.java:999)\n        at java.security.AccessController.doPrivileged(Native Method)\n        at org.eclipse.osgi.framework.internal.core.BundleContextImpl.startActivator(BundleContextImpl.java:993)\n        at org.eclipse.osgi.framework.internal.core.BundleContextImpl.start(BundleContextImpl.java:974)\n        at org.eclipse.osgi.framework.internal.core.BundleHost.startWorker(BundleHost.java:327)\n        at org.eclipse.osgi.framework.internal.core.AbstractBundle.resume(AbstractBundle.java:350)\n        at org.eclipse.osgi.framework.internal.core.Framework.resumeBundle(Framework.java:1115)\n        at org.eclipse.osgi.framework.internal.core.StartLevelManager.resumeBundles(StartLevelManager.java:629)\n        at org.eclipse.osgi.framework.internal.core.StartLevelManager.incFWSL(StartLevelManager.java:503)\n        at org.eclipse.osgi.framework.internal.core.StartLevelManager.doSetStartLevel(StartLevelManager.java:279)\n        at org.eclipse.osgi.framework.internal.core.StartLevelManager.dispatchEvent(StartLevelManager.java:463)\n        at org.eclipse.osgi.framework.eventmgr.EventManager.dispatchEvent(EventManager.java:189)\n        at org.eclipse.osgi.framework.eventmgr.EventManager$EventThread.run(EventManager.java:291)\nCaused by: java.lang.ArrayIndexOutOfBoundsException: 3\n        at org.eclipse.equinox.internal.app.CommandLineArgs.processCommandLine(CommandLineArgs.java:68)\n        at org.eclipse.equinox.internal.app.Activator.processCommandLineArgs(Activator.java:109)\n        at org.eclipse.equinox.internal.app.Activator.start(Activator.java:52)\n        at org.eclipse.osgi.framework.internal.core.BundleContextImpl$2.run(BundleContextImpl.java:999)\n        at java.security.AccessController.doPrivileged(Native Method)\n        at org.eclipse.osgi.framework.internal.core.BundleContextImpl.startActivator(BundleContextImpl.java:993)\n        ... 30 more\nRoot exception:\njava.lang.ArrayIndexOutOfBoundsException: 3\n        at org.eclipse.equinox.internal.app.CommandLineArgs.processCommandLine(CommandLineArgs.java:68)\n        at org.eclipse.equinox.internal.app.Activator.processCommandLineArgs(Activator.java:109)\n        at org.eclipse.equinox.internal.app.Activator.start(Activator.java:52)\n        at org.eclipse.osgi.framework.internal.core.BundleContextImpl$2.run(BundleContextImpl.java:999)\n        at java.security.AccessController.doPrivileged(Native Method)\n        at org.eclipse.osgi.framework.internal.core.BundleContextImpl.startActivator(BundleContextImpl.java:993)\n        at org.eclipse.osgi.framework.internal.core.BundleContextImpl.start(BundleContextImpl.java:974)\n        at org.eclipse.osgi.framework.internal.core.BundleHost.startWorker(BundleHost.java:327)\n        at org.eclipse.osgi.framework.internal.core.AbstractBundle.start(AbstractBundle.java:260)\n        at org.eclipse.osgi.framework.util.SecureAction.start(SecureAction.java:400)\n        at org.eclipse.core.runtime.internal.adaptor.EclipseLazyStarter.postFindLocalClass(EclipseLazyStarter.java:111)\n        at org.eclipse.osgi.baseadaptor.loader.ClasspathManager.findLocalClass(ClasspathManager.java:417)\n        at org.eclipse.osgi.internal.baseadaptor.DefaultClassLoader.findLocalClass(DefaultClassLoader.java:189)\n        at org.eclipse.osgi.framework.internal.core.BundleLoader.findLocalClass(BundleLoader.java:340)\n        at org.eclipse.osgi.framework.internal.core.SingleSourcePackage.loadClass(SingleSourcePackage.java:37)\n        at org.eclipse.osgi.framework.internal.core.BundleLoader.findClassInternal(BundleLoader.java:405)\n        at org.eclipse.osgi.framework.internal.core.BundleLoader.findClass(BundleLoader.java:369)\n        at org.eclipse.osgi.framework.internal.core.BundleLoader.findClass(BundleLoader.java:357)\n        at org.eclipse.osgi.internal.baseadaptor.DefaultClassLoader.loadClass(DefaultClassLoader.java:83)\n        at java.lang.ClassLoader.loadClass(ClassLoader.java:251)\n        at java.lang.ClassLoader.loadClassInternal(ClassLoader.java:319)\n        at org.eclipse.core.internal.runtime.PlatformActivator.startAppContainer(PlatformActivator.java:47)\n        at org.eclipse.core.internal.runtime.PlatformActivator.start(PlatformActivator.java:32)\n        at org.eclipse.osgi.framework.internal.core.BundleContextImpl$2.run(BundleContextImpl.java:999)\n        at java.security.AccessController.doPrivileged(Native Method)\n        at org.eclipse.osgi.framework.internal.core.BundleContextImpl.startActivator(BundleContextImpl.java:993)\n        at org.eclipse.osgi.framework.internal.core.BundleContextImpl.start(BundleContextImpl.java:974)\n        at org.eclipse.osgi.framework.internal.core.BundleHost.startWorker(BundleHost.java:327)\n        at org.eclipse.osgi.framework.internal.core.AbstractBundle.resume(AbstractBundle.java:350)\n        at org.eclipse.osgi.framework.internal.core.Framework.resumeBundle(Framework.java:1115)\n        at org.eclipse.osgi.framework.internal.core.StartLevelManager.resumeBundles(StartLevelManager.java:629)\n        at org.eclipse.osgi.framework.internal.core.StartLevelManager.incFWSL(StartLevelManager.java:503)\n        at org.eclipse.osgi.framework.internal.core.StartLevelManager.doSetStartLevel(StartLevelManager.java:279)\n        at org.eclipse.osgi.framework.internal.core.StartLevelManager.dispatchEvent(StartLevelManager.java:463)\n        at org.eclipse.osgi.framework.eventmgr.EventManager.dispatchEvent(EventManager.java:189)\n        at org.eclipse.osgi.framework.eventmgr.EventManager$EventThread.run(EventManager.java:291)\n\nI\u0027ll attach my startup script",
    "Created an attachment (id\u003d56032)\nstartup script\n\n",
    "removing the \u0027-update\u0027 argument seams to solve the problem. Seams like update is not a valid eclipse program argument anyway... ",
    "Fixed in HEAD."
  ],
  "commentCreationDates": [
    "2006-12-21T08:22:26+01:00",
    "2006-12-21T08:23:28+01:00",
    "2006-12-21T08:52:38+01:00",
    "2006-12-21T13:10:04+01:00"
  ],
  "traces": [
    {
      "exceptionType": "org.osgi.framework.BundleException",
      "message": "Exception in org.eclipse.equinox.internal.app.Activator.start() of bundle org.eclipse.equinox.app.",
      "elements": [
        {
          "method": "org.eclipse.osgi.framework.internal.core.BundleContextImpl.startActivator",
          "source": "BundleContextImpl.java:1018"
        },
        {
          "method": "org.eclipse.osgi.framework.internal.core.BundleContextImpl.start",
          "source": "BundleContextImpl.java:974"
        },
        {
          "method": "org.eclipse.osgi.framework.internal.core.BundleHost.startWorker",
          "source": "BundleHost.java:327"
        },
        {
          "method": "org.eclipse.osgi.framework.internal.core.AbstractBundle.start",
          "source": "AbstractBundle.java:260"
        },
        {
          "method": "org.eclipse.osgi.framework.util.SecureAction.start",
          "source": "SecureAction.java:400"
        },
        {
          "method": "org.eclipse.core.runtime.internal.adaptor.EclipseLazyStarter.postFindLocalClass",
          "source": "EclipseLazyStarter.java:111"
        },
        {
          "method": "org.eclipse.osgi.baseadaptor.loader.ClasspathManager.findLocalClass",
          "source": "ClasspathManager.java:417"
        },
        {
          "method": "org.eclipse.osgi.internal.baseadaptor.DefaultClassLoader.findLocalClass",
          "source": "DefaultClassLoader.java:189"
        },
        {
          "method": "org.eclipse.osgi.framework.internal.core.BundleLoader.findLocalClass",
          "source": "BundleLoader.java:340"
        },
        {
          "method": "org.eclipse.osgi.framework.internal.core.SingleSourcePackage.loadClass",
          "source": "SingleSourcePackage.java:37"
        },
        {
          "method": "org.eclipse.osgi.framework.internal.core.BundleLoader.findClassInternal",
          "source": "BundleLoader.java:405"
        },
        {
          "method": "org.eclipse.osgi.framework.internal.core.BundleLoader.findClass",
          "source": "BundleLoader.java:369"
        },
        {
          "method": "org.eclipse.osgi.framework.internal.core.BundleLoader.findClass",
          "source": "BundleLoader.java:357"
        },
        {
          "method": "org.eclipse.osgi.internal.baseadaptor.DefaultClassLoader.loadClass",
          "source": "DefaultClassLoader.java:83"
        },
        {
          "method": "java.lang.ClassLoader.loadClass",
          "source": "ClassLoader.java:251"
        },
        {
          "method": "java.lang.ClassLoader.loadClassInternal",
          "source": "ClassLoader.java:319"
        },
        {
          "method": "org.eclipse.core.internal.runtime.PlatformActivator.startAppContainer",
          "source": "PlatformActivator.java:47"
        },
        {
          "method": "org.eclipse.core.internal.runtime.PlatformActivator.start",
          "source": "PlatformActivator.java:32"
        },
        {
          "method": "org.eclipse.osgi.framework.internal.core.BundleContextImpl$2.run",
          "source": "BundleContextImpl.java:999"
        },
        {
          "method": "java.security.AccessController.doPrivileged",
          "source": "Native Method"
        },
        {
          "method": "org.eclipse.osgi.framework.internal.core.BundleContextImpl.startActivator",
          "source": "BundleContextImpl.java:993"
        },
        {
          "method": "org.eclipse.osgi.framework.internal.core.BundleContextImpl.start",
          "source": "BundleContextImpl.java:974"
        },
        {
          "method": "org.eclipse.osgi.framework.internal.core.BundleHost.startWorker",
          "source": "BundleHost.java:327"
        },
        {
          "method": "org.eclipse.osgi.framework.internal.core.AbstractBundle.resume",
          "source": "AbstractBundle.java:350"
        },
        {
          "method": "org.eclipse.osgi.framework.internal.core.Framework.resumeBundle",
          "source": "Framework.java:1115"
        },
        {
          "method": "org.eclipse.osgi.framework.internal.core.StartLevelManager.resumeBundles",
          "source": "StartLevelManager.java:629"
        },
        {
          "method": "org.eclipse.osgi.framework.internal.core.StartLevelManager.incFWSL",
          "source": "StartLevelManager.java:503"
        },
        {
          "method": "org.eclipse.osgi.framework.internal.core.StartLevelManager.doSetStartLevel",
          "source": "StartLevelManager.java:279"
        },
        {
          "method": "org.eclipse.osgi.framework.internal.core.StartLevelManager.dispatchEvent",
          "source": "StartLevelManager.java:463"
        },
        {
          "method": "org.eclipse.osgi.framework.eventmgr.EventManager.dispatchEvent",
          "source": "EventManager.java:189"
        },
        {
          "method": "org.eclipse.osgi.framework.eventmgr.EventManager$EventThread.run",
          "source": "EventManager.java:291"
        }
      ],
      "causedBy": {
        "exceptionType": "java.lang.ArrayIndexOutOfBoundsException",
        "message": "3",
        "elements": [
          {
            "method": "org.eclipse.equinox.internal.app.CommandLineArgs.processCommandLine",
            "source": "CommandLineArgs.java:68"
          },
          {
            "method": "org.eclipse.equinox.internal.app.Activator.processCommandLineArgs",
            "source": "Activator.java:109"
          },
          {
            "method": "org.eclipse.equinox.internal.app.Activator.start",
            "source": "Activator.java:52"
          },
          {
            "method": "org.eclipse.osgi.framework.internal.core.BundleContextImpl$2.run",
            "source": "BundleContextImpl.java:999"
          },
          {
            "method": "java.security.AccessController.doPrivileged",
            "source": "Native Method"
          },
          {
            "method": "org.eclipse.osgi.framework.internal.core.BundleContextImpl.startActivator",
            "source": "BundleContextImpl.java:993"
          }
        ],
        "number": 0,
        "commentIndex": 0
      },
      "number": 0,
      "commentIndex": 0,
      "bugId": "168820",
      "date": "2006-12-21T08:22:26+01:00",
      "product": "Equinox",
      "component": "Framework",
      "severity": "blocker"
    },
    {
      "exceptionType": "java.lang.ArrayIndexOutOfBoundsException",
      "message": "3",
      "elements": [
        {
          "method": "org.eclipse.equinox.internal.app.CommandLineArgs.processCommandLine",
          "source": "CommandLineArgs.java:68"
        },
        {
          "method": "org.eclipse.equinox.internal.app.Activator.processCommandLineArgs",
          "source": "Activator.java:109"
        },
        {
          "method": "org.eclipse.equinox.internal.app.Activator.start",
          "source": "Activator.java:52"
        },
        {
          "method": "org.eclipse.osgi.framework.internal.core.BundleContextImpl$2.run",
          "source": "BundleContextImpl.java:999"
        },
        {
          "method": "java.security.AccessController.doPrivileged",
          "source": "Native Method"
        },
        {
          "method": "org.eclipse.osgi.framework.internal.core.BundleContextImpl.startActivator",
          "source": "BundleContextImpl.java:993"
        },
        {
          "method": "org.eclipse.osgi.framework.internal.core.BundleContextImpl.start",
          "source": "BundleContextImpl.java:974"
        },
        {
          "method": "org.eclipse.osgi.framework.internal.core.BundleHost.startWorker",
          "source": "BundleHost.java:327"
        },
        {
          "method": "org.eclipse.osgi.framework.internal.core.AbstractBundle.start",
          "source": "AbstractBundle.java:260"
        },
        {
          "method": "org.eclipse.osgi.framework.util.SecureAction.start",
          "source": "SecureAction.java:400"
        },
        {
          "method": "org.eclipse.core.runtime.internal.adaptor.EclipseLazyStarter.postFindLocalClass",
          "source": "EclipseLazyStarter.java:111"
        },
        {
          "method": "org.eclipse.osgi.baseadaptor.loader.ClasspathManager.findLocalClass",
          "source": "ClasspathManager.java:417"
        },
        {
          "method": "org.eclipse.osgi.internal.baseadaptor.DefaultClassLoader.findLocalClass",
          "source": "DefaultClassLoader.java:189"
        },
        {
          "method": "org.eclipse.osgi.framework.internal.core.BundleLoader.findLocalClass",
          "source": "BundleLoader.java:340"
        },
        {
          "method": "org.eclipse.osgi.framework.internal.core.SingleSourcePackage.loadClass",
          "source": "SingleSourcePackage.java:37"
        },
        {
          "method": "org.eclipse.osgi.framework.internal.core.BundleLoader.findClassInternal",
          "source": "BundleLoader.java:405"
        },
        {
          "method": "org.eclipse.osgi.framework.internal.core.BundleLoader.findClass",
          "source": "BundleLoader.java:369"
        },
        {
          "method": "org.eclipse.osgi.framework.internal.core.BundleLoader.findClass",
          "source": "BundleLoader.java:357"
        },
        {
          "method": "org.eclipse.osgi.internal.baseadaptor.DefaultClassLoader.loadClass",
          "source": "DefaultClassLoader.java:83"
        },
        {
          "method": "java.lang.ClassLoader.loadClass",
          "source": "ClassLoader.java:251"
        },
        {
          "method": "java.lang.ClassLoader.loadClassInternal",
          "source": "ClassLoader.java:319"
        },
        {
          "method": "org.eclipse.core.internal.runtime.PlatformActivator.startAppContainer",
          "source": "PlatformActivator.java:47"
        },
        {
          "method": "org.eclipse.core.internal.runtime.PlatformActivator.start",
          "source": "PlatformActivator.java:32"
        },
        {
          "method": "org.eclipse.osgi.framework.internal.core.BundleContextImpl$2.run",
          "source": "BundleContextImpl.java:999"
        },
        {
          "method": "java.security.AccessController.doPrivileged",
          "source": "Native Method"
        },
        {
          "method": "org.eclipse.osgi.framework.internal.core.BundleContextImpl.startActivator",
          "source": "BundleContextImpl.java:993"
        },
        {
          "method": "org.eclipse.osgi.framework.internal.core.BundleContextImpl.start",
          "source": "BundleContextImpl.java:974"
        },
        {
          "method": "org.eclipse.osgi.framework.internal.core.BundleHost.startWorker",
          "source": "BundleHost.java:327"
        },
        {
          "method": "org.eclipse.osgi.framework.internal.core.AbstractBundle.resume",
          "source": "AbstractBundle.java:350"
        },
        {
          "method": "org.eclipse.osgi.framework.internal.core.Framework.resumeBundle",
          "source": "Framework.java:1115"
        },
        {
          "method": "org.eclipse.osgi.framework.internal.core.StartLevelManager.resumeBundles",
          "source": "StartLevelManager.java:629"
        },
        {
          "method": "org.eclipse.osgi.framework.internal.core.StartLevelManager.incFWSL",
          "source": "StartLevelManager.java:503"
        },
        {
          "method": "org.eclipse.osgi.framework.internal.core.StartLevelManager.doSetStartLevel",
          "source": "StartLevelManager.java:279"
        },
        {
          "method": "org.eclipse.osgi.framework.internal.core.StartLevelManager.dispatchEvent",
          "source": "StartLevelManager.java:463"
        },
        {
          "method": "org.eclipse.osgi.framework.eventmgr.EventManager.dispatchEvent",
          "source": "EventManager.java:189"
        },
        {
          "method": "org.eclipse.osgi.framework.eventmgr.EventManager$EventThread.run",
          "source": "EventManager.java:291"
        }
      ],
      "number": 1,
      "commentIndex": 0,
      "bugId": "168820",
      "date": "2006-12-21T08:22:26+01:00",
      "product": "Equinox",
      "component": "Framework",
      "severity": "blocker"
    }
  ],
  "groupId": "168820",
  "bugId": "168820",
  "date": "2006-12-21T08:22:26+01:00",
  "product": "Equinox",
  "component": "Framework",
  "severity": "blocker"
}