{
  "comments": [
    "After searching through a dozen reports on this I always find report on mismatching 32/64 VM/Eclispe but in my case it is pure 64 system.\n\nI get permission denied when trying to launch eclipse executable and launching startup.jar manually don\u0027t get me much further both with 64 bit jdk 1.5 and 1.6.\n\nThe system is an Ubuntu 6.10 (edgy) AMD64 and the PC is an Intel Core Duo 2.\n\nTried to gather as much information as my limited knowledge allowed me.\n\nRegards.\n\n\n\nldng@localhost:~/Work$ uname -a\nLinux localhost 2.6.17-10-generic #2 SMP Fri Oct 13 15:34:39 UTC 2006 x86_64 GNU/Linux\n\nldng@localhost:~/Work$ apt-cache show libgtk2.0-0\nArchitecture: amd64\nVersion: 2.10.6-0ubuntu1\n\nldng@localhost:~/Work$ apt-cache show libc6\nArchitecture: amd64\nVersion: 2.4-1ubuntu12\n\nldng@localhost:~/Work$ apt-cache show sun-java5-jre\nArchitecture: all\nVersion: 1.5.0-08-0ubuntu1\nDepends: java-common, locales, sun-java5-bin (\u003d 1.5.0-08-0ubuntu1) | ia32-sun-java5-bin (\u003d 1.5.0-08-0ubuntu1), debconf (\u003e\u003d 0.5) | debconf-2.0\n\nldng@localhost:~/Work$ apt-cache show sun-java5-bin\nArchitecture: amd64\nVersion: 1.5.0-08-0ubuntu1\nDepends: sun-java5-jre (\u003d 1.5.0-08-0ubuntu1), unixodbc, libc6, debconf (\u003e\u003d 0.5) | debconf-2.0\n\n\nldng@localhost:~/Work$ apt-cache show sun-j2sdk1.6\nArchitecture: amd64\nVersion: 1.6.0+update00\n\njdk-6-linux-amd64.bin\n\neclipse-SDK-3.2.1-linux-gtk-x86_64.tar.gz\n\nldng@localhost:~/Work/eclipse$ java -version\njava version \"1.6.0\"\nJava(TM) SE Runtime Environment (build 1.6.0-b105)\nJava HotSpot(TM) 64-Bit Server VM (build 1.6.0-b105, mixed mode)\n\nldng@localhost:~/Work/eclipse$ ./eclipse\nbash: ./eclipse: Permission non accord?e\nldng@localhost:~/Work/eclipse$ cat /home/ldng/workspace/.metadata/.log \nldng@localhost:~/Work/eclipse$ strace ./eclipse\nexecve(\"./eclipse\", [\"./eclipse\"], [/* 34 vars */]) \u003d -1 EACCES (Permission denied)\ndup(2)                                  \u003d 3\nfcntl(3, F_GETFL)                       \u003d 0x8002 (flags O_RDWR|O_LARGEFILE)\nfstat(3, {st_mode\u003dS_IFCHR|0620, st_rdev\u003dmakedev(136, 1), ...}) \u003d 0\nmmap(NULL, 4096, PROT_READ|PROT_WRITE, MAP_PRIVATE|MAP_ANONYMOUS, -1, 0) \u003d 0x2ae0e5e35000\nlseek(3, 0, SEEK_CUR)                   \u003d -1 ESPIPE (Illegal seek)\nwrite(3, \"strace: exec: Permission denied\\n\", 32strace: exec: Permission denied\n) \u003d 32\nclose(3)                                \u003d 0\nmunmap(0x2ae0e5e35000, 4096)            \u003d 0\nexit_group(1)                           \u003d ?\nProcess 10044 detached\nldng@localhost:~/Work/eclipse$\n\nldng@localhost:~/Work/eclipse$ java -jar startup.jar\nldng@localhost:~/Work/eclipse$ cat /home/ldng/workspace/.metadata/.log \n!SESSION 2006-12-24 13:49:07.654 -----------------------------------------------\neclipse.buildId\u003dM20060921-0945\njava.version\u003d1.6.0\njava.vendor\u003dSun Microsystems Inc.\nBootLoader constants: OS\u003dlinux, ARCH\u003dx86_64, WS\u003dgtk, NL\u003dfr_FR\n\n!ENTRY org.eclipse.osgi 4 0 2006-12-24 13:49:08.348\n!MESSAGE Application error\n!STACK 1\njava.lang.UnsatisfiedLinkError: /home/ldng/Work/eclipse/configuration/org.eclipse.osgi/bundles/29/1/.cp/libswt-pi-gtk-3235.so: /home/ldng/Work/eclipse/configuration/org.eclipse.osgi/bundles/29/1/.cp/libswt-pi-gtk-3235.so: failed to map segment from shared object: Operation not permitted\n        at java.lang.ClassLoader$NativeLibrary.load(Native Method)\n        at java.lang.ClassLoader.loadLibrary0(ClassLoader.java:1751)\n        at java.lang.ClassLoader.loadLibrary(ClassLoader.java:1660)\n        at java.lang.Runtime.loadLibrary0(Runtime.java:823)\n        at java.lang.System.loadLibrary(System.java:1030)\n        at org.eclipse.swt.internal.Library.loadLibrary(Library.java:123)\n        at org.eclipse.swt.internal.gtk.OS.\u003cclinit\u003e(OS.java:22)\n        at org.eclipse.swt.internal.Converter.wcsToMbcs(Converter.java:63)\n        at org.eclipse.swt.internal.Converter.wcsToMbcs(Converter.java:54)\n        at org.eclipse.swt.widgets.Display.\u003cclinit\u003e(Display.java:126)\n        at org.eclipse.ui.internal.Workbench.createDisplay(Workbench.java:433)\n        at org.eclipse.ui.PlatformUI.createDisplay(PlatformUI.java:161)\n        at org.eclipse.ui.internal.ide.IDEApplication.createDisplay(IDEApplication.java:122)\n        at org.eclipse.ui.internal.ide.IDEApplication.run(IDEApplication.java:75)\n        at org.eclipse.core.internal.runtime.PlatformActivator$1.run(PlatformActivator.java:78)\n        at org.eclipse.core.runtime.internal.adaptor.EclipseAppLauncher.runApplication(EclipseAppLauncher.java:92)\n        at org.eclipse.core.runtime.internal.adaptor.EclipseAppLauncher.start(EclipseAppLauncher.java:68)\n        at org.eclipse.core.runtime.adaptor.EclipseStarter.run(EclipseStarter.java:400)\n        at org.eclipse.core.runtime.adaptor.EclipseStarter.run(EclipseStarter.java:177)\n        at sun.reflect.NativeMethodAccessorImpl.invoke0(Native Method)\n        at sun.reflect.NativeMethodAccessorImpl.invoke(NativeMethodAccessorImpl.java:39)\n        at sun.reflect.DelegatingMethodAccessorImpl.invoke(DelegatingMethodAccessorImpl.java:25)\n        at java.lang.reflect.Method.invoke(Method.java:597)\n        at org.eclipse.core.launcher.Main.invokeFramework(Main.java:336)\n        at org.eclipse.core.launcher.Main.basicRun(Main.java:280)\n        at org.eclipse.core.launcher.Main.run(Main.java:977)\n        at org.eclipse.core.launcher.Main.main(Main.java:952)\nldng@localhost:~/Work/eclipse$\n\n\nroot@localhost:/home/ldng/Desktop# update-alternatives --set java /usr/lib/jvm/java-1.5.0-sun/jre/bin/java\nUtilisation de ? /usr/lib/jvm/java-1.5.0-sun/jre/bin/java ? pour fournir ? java ?.\n\nldng@localhost:~/Work/eclipse$ java -version\njava version \"1.5.0_08\"\nJava(TM) 2 Runtime Environment, Standard Edition (build 1.5.0_08-b03)\nJava HotSpot(TM) 64-Bit Server VM (build 1.5.0_08-b03, mixed mode)\n\nldng@localhost:~/Work/eclipse$ cat /home/ldng/workspace/.metadata/.log \n!SESSION 2006-12-24 13:53:11.343 -----------------------------------------------\neclipse.buildId\u003dM20060921-0945\njava.version\u003d1.5.0_08\njava.vendor\u003dSun Microsystems Inc.\nBootLoader constants: OS\u003dlinux, ARCH\u003dx86_64, WS\u003dgtk, NL\u003dfr_FR\n\n!ENTRY org.eclipse.osgi 4 0 2006-12-24 13:53:15.528\n!MESSAGE Application error\n!STACK 1\njava.lang.UnsatisfiedLinkError: /home/ldng/Work/eclipse/configuration/org.eclipse.osgi/bundles/29/1/.cp/libswt-pi-gtk-3235.so: /home/ldng/Work/eclipse/configuration/org.eclipse.osgi/bundles/29/1/.cp/libswt-pi-gtk-3235.so: failed to map segment from shared object: Operation not permitted\n        at java.lang.ClassLoader$NativeLibrary.load(Native Method)\n        at java.lang.ClassLoader.loadLibrary0(ClassLoader.java:1751)\n        at java.lang.ClassLoader.loadLibrary(ClassLoader.java:1660)\n        at java.lang.Runtime.loadLibrary0(Runtime.java:822)\n        at java.lang.System.loadLibrary(System.java:993)\n        at org.eclipse.swt.internal.Library.loadLibrary(Library.java:123)\n        at org.eclipse.swt.internal.gtk.OS.\u003cclinit\u003e(OS.java:22)\n        at org.eclipse.swt.internal.Converter.wcsToMbcs(Converter.java:63)\n        at org.eclipse.swt.internal.Converter.wcsToMbcs(Converter.java:54)\n        at org.eclipse.swt.widgets.Display.\u003cclinit\u003e(Display.java:126)\n        at org.eclipse.ui.internal.Workbench.createDisplay(Workbench.java:433)\n        at org.eclipse.ui.PlatformUI.createDisplay(PlatformUI.java:161)\n        at org.eclipse.ui.internal.ide.IDEApplication.createDisplay(IDEApplication.java:122)\n        at org.eclipse.ui.internal.ide.IDEApplication.run(IDEApplication.java:75)\n        at org.eclipse.core.internal.runtime.PlatformActivator$1.run(PlatformActivator.java:78)\n        at org.eclipse.core.runtime.internal.adaptor.EclipseAppLauncher.runApplication(EclipseAppLauncher.java:92)\n        at org.eclipse.core.runtime.internal.adaptor.EclipseAppLauncher.start(EclipseAppLauncher.java:68)\n        at org.eclipse.core.runtime.adaptor.EclipseStarter.run(EclipseStarter.java:400)\n        at org.eclipse.core.runtime.adaptor.EclipseStarter.run(EclipseStarter.java:177)\n        at sun.reflect.NativeMethodAccessorImpl.invoke0(Native Method)\n        at sun.reflect.NativeMethodAccessorImpl.invoke(NativeMethodAccessorImpl.java:39)\n        at sun.reflect.DelegatingMethodAccessorImpl.invoke(DelegatingMethodAccessorImpl.java:25)\n        at java.lang.reflect.Method.invoke(Method.java:585)\n        at org.eclipse.core.launcher.Main.invokeFramework(Main.java:336)\n        at org.eclipse.core.launcher.Main.basicRun(Main.java:280)\n        at org.eclipse.core.launcher.Main.run(Main.java:977)\n        at org.eclipse.core.launcher.Main.main(Main.java:952)",
    "Created an attachment (id\u003d56142)\nLaunching startup.jar with strace, java 1.5\n\n",
    "Created an attachment (id\u003d56143)\nLaunching startup.jar with strace, java 1.6\n\n",
    "Ouch, that\u0027s a stupid one !\n\nMy ext3 home partition was mounted with user attribute but without the exec attribute. Adding the exec attribute to the /etc/fstab solved the problem as ./script won\u0027t work on a non executable filesystem.\n\nClosing as INVALID sorry about the burden."
  ],
  "commentCreationDates": [
    "2006-12-24T13:19:21+01:00",
    "2006-12-24T13:20:56+01:00",
    "2006-12-24T13:22:38+01:00",
    "2006-12-25T15:32:52+01:00"
  ],
  "traces": [
    {
      "exceptionType": "java.lang.UnsatisfiedLinkError",
      "message": "/home/ldng/Work/eclipse/configuration/org.eclipse.osgi/bundles/29/1/.cp/libswt-pi-gtk-3235.so: /home/ldng/Work/eclipse/configuration/org.eclipse.osgi/bundles/29/1/.cp/libswt-pi-gtk-3235.so: failed to map segment from shared object: Operation not permitted",
      "elements": [
        {
          "method": "java.lang.ClassLoader$NativeLibrary.load",
          "source": "Native Method"
        },
        {
          "method": "java.lang.ClassLoader.loadLibrary0",
          "source": "ClassLoader.java:1751"
        },
        {
          "method": "java.lang.ClassLoader.loadLibrary",
          "source": "ClassLoader.java:1660"
        },
        {
          "method": "java.lang.Runtime.loadLibrary0",
          "source": "Runtime.java:823"
        },
        {
          "method": "java.lang.System.loadLibrary",
          "source": "System.java:1030"
        },
        {
          "method": "org.eclipse.swt.internal.Library.loadLibrary",
          "source": "Library.java:123"
        },
        {
          "method": "org.eclipse.swt.internal.gtk.OS.\u003cclinit\u003e",
          "source": "OS.java:22"
        },
        {
          "method": "org.eclipse.swt.internal.Converter.wcsToMbcs",
          "source": "Converter.java:63"
        },
        {
          "method": "org.eclipse.swt.internal.Converter.wcsToMbcs",
          "source": "Converter.java:54"
        },
        {
          "method": "org.eclipse.swt.widgets.Display.\u003cclinit\u003e",
          "source": "Display.java:126"
        },
        {
          "method": "org.eclipse.ui.internal.Workbench.createDisplay",
          "source": "Workbench.java:433"
        },
        {
          "method": "org.eclipse.ui.PlatformUI.createDisplay",
          "source": "PlatformUI.java:161"
        },
        {
          "method": "org.eclipse.ui.internal.ide.IDEApplication.createDisplay",
          "source": "IDEApplication.java:122"
        },
        {
          "method": "org.eclipse.ui.internal.ide.IDEApplication.run",
          "source": "IDEApplication.java:75"
        },
        {
          "method": "org.eclipse.core.internal.runtime.PlatformActivator$1.run",
          "source": "PlatformActivator.java:78"
        },
        {
          "method": "org.eclipse.core.runtime.internal.adaptor.EclipseAppLauncher.runApplication",
          "source": "EclipseAppLauncher.java:92"
        },
        {
          "method": "org.eclipse.core.runtime.internal.adaptor.EclipseAppLauncher.start",
          "source": "EclipseAppLauncher.java:68"
        },
        {
          "method": "org.eclipse.core.runtime.adaptor.EclipseStarter.run",
          "source": "EclipseStarter.java:400"
        },
        {
          "method": "org.eclipse.core.runtime.adaptor.EclipseStarter.run",
          "source": "EclipseStarter.java:177"
        },
        {
          "method": "sun.reflect.NativeMethodAccessorImpl.invoke0",
          "source": "Native Method"
        },
        {
          "method": "sun.reflect.NativeMethodAccessorImpl.invoke",
          "source": "NativeMethodAccessorImpl.java:39"
        },
        {
          "method": "sun.reflect.DelegatingMethodAccessorImpl.invoke",
          "source": "DelegatingMethodAccessorImpl.java:25"
        },
        {
          "method": "java.lang.reflect.Method.invoke",
          "source": "Method.java:597"
        },
        {
          "method": "org.eclipse.core.launcher.Main.invokeFramework",
          "source": "Main.java:336"
        },
        {
          "method": "org.eclipse.core.launcher.Main.basicRun",
          "source": "Main.java:280"
        },
        {
          "method": "org.eclipse.core.launcher.Main.run",
          "source": "Main.java:977"
        },
        {
          "method": "org.eclipse.core.launcher.Main.main",
          "source": "Main.java:952"
        }
      ],
      "number": 0,
      "commentIndex": 0,
      "bugId": "168995",
      "date": "2006-12-24T13:19:21+01:00",
      "product": "Platform",
      "component": "SWT",
      "severity": "normal"
    },
    {
      "exceptionType": "java.lang.UnsatisfiedLinkError",
      "message": "/home/ldng/Work/eclipse/configuration/org.eclipse.osgi/bundles/29/1/.cp/libswt-pi-gtk-3235.so: /home/ldng/Work/eclipse/configuration/org.eclipse.osgi/bundles/29/1/.cp/libswt-pi-gtk-3235.so: failed to map segment from shared object: Operation not permitted",
      "elements": [
        {
          "method": "java.lang.ClassLoader$NativeLibrary.load",
          "source": "Native Method"
        },
        {
          "method": "java.lang.ClassLoader.loadLibrary0",
          "source": "ClassLoader.java:1751"
        },
        {
          "method": "java.lang.ClassLoader.loadLibrary",
          "source": "ClassLoader.java:1660"
        },
        {
          "method": "java.lang.Runtime.loadLibrary0",
          "source": "Runtime.java:822"
        },
        {
          "method": "java.lang.System.loadLibrary",
          "source": "System.java:993"
        },
        {
          "method": "org.eclipse.swt.internal.Library.loadLibrary",
          "source": "Library.java:123"
        },
        {
          "method": "org.eclipse.swt.internal.gtk.OS.\u003cclinit\u003e",
          "source": "OS.java:22"
        },
        {
          "method": "org.eclipse.swt.internal.Converter.wcsToMbcs",
          "source": "Converter.java:63"
        },
        {
          "method": "org.eclipse.swt.internal.Converter.wcsToMbcs",
          "source": "Converter.java:54"
        },
        {
          "method": "org.eclipse.swt.widgets.Display.\u003cclinit\u003e",
          "source": "Display.java:126"
        },
        {
          "method": "org.eclipse.ui.internal.Workbench.createDisplay",
          "source": "Workbench.java:433"
        },
        {
          "method": "org.eclipse.ui.PlatformUI.createDisplay",
          "source": "PlatformUI.java:161"
        },
        {
          "method": "org.eclipse.ui.internal.ide.IDEApplication.createDisplay",
          "source": "IDEApplication.java:122"
        },
        {
          "method": "org.eclipse.ui.internal.ide.IDEApplication.run",
          "source": "IDEApplication.java:75"
        },
        {
          "method": "org.eclipse.core.internal.runtime.PlatformActivator$1.run",
          "source": "PlatformActivator.java:78"
        },
        {
          "method": "org.eclipse.core.runtime.internal.adaptor.EclipseAppLauncher.runApplication",
          "source": "EclipseAppLauncher.java:92"
        },
        {
          "method": "org.eclipse.core.runtime.internal.adaptor.EclipseAppLauncher.start",
          "source": "EclipseAppLauncher.java:68"
        },
        {
          "method": "org.eclipse.core.runtime.adaptor.EclipseStarter.run",
          "source": "EclipseStarter.java:400"
        },
        {
          "method": "org.eclipse.core.runtime.adaptor.EclipseStarter.run",
          "source": "EclipseStarter.java:177"
        },
        {
          "method": "sun.reflect.NativeMethodAccessorImpl.invoke0",
          "source": "Native Method"
        },
        {
          "method": "sun.reflect.NativeMethodAccessorImpl.invoke",
          "source": "NativeMethodAccessorImpl.java:39"
        },
        {
          "method": "sun.reflect.DelegatingMethodAccessorImpl.invoke",
          "source": "DelegatingMethodAccessorImpl.java:25"
        },
        {
          "method": "java.lang.reflect.Method.invoke",
          "source": "Method.java:585"
        },
        {
          "method": "org.eclipse.core.launcher.Main.invokeFramework",
          "source": "Main.java:336"
        },
        {
          "method": "org.eclipse.core.launcher.Main.basicRun",
          "source": "Main.java:280"
        },
        {
          "method": "org.eclipse.core.launcher.Main.run",
          "source": "Main.java:977"
        },
        {
          "method": "org.eclipse.core.launcher.Main.main",
          "source": "Main.java:952"
        }
      ],
      "number": 1,
      "commentIndex": 0,
      "bugId": "168995",
      "date": "2006-12-24T13:19:21+01:00",
      "product": "Platform",
      "component": "SWT",
      "severity": "normal"
    }
  ],
  "groupId": "168995",
  "bugId": "168995",
  "date": "2006-12-24T13:19:21+01:00",
  "product": "Platform",
  "component": "SWT",
  "severity": "normal"
}