{
  "comments": [
    "Overview Description:  \nDeleted a volume from a DS4000 Storage Subsystem using Aperi GUI wizard, received the following error messages:\n1/3/07 3:41:56 PM BTACS0000I Starting Control Process: deleteStorageVolumes, Device Server RUN ID\u003d6, Job ID\u003d64.\n1/3/07 3:41:56 PM HWN021684I Started deletion of volume 11 on subsystem FAStT500-TPC_L2_FASTT-600A0B80000C50E200000000440F238D-LSI.\n1/3/07 3:41:56 PM HWN021686E Volume deletion failed. Volume 11 on subsystem FAStT500-TPC_L2_FASTT-600A0B80000C50E200000000440F238D-LSI could not be deleted.\n1/3/07 3:41:56 PM HWN021503E An internal error occurred, please try again. If the problem persist, please contact IBM service.\n1/3/07 3:41:56 PM BTACS0001I Finished Control Process: Device Server RUN ID\u003d6, Job ID\u003d64, Status\u003d0, Return Code\u003d10007.\n \n\nSteps to Reproduce:\n            Using Aperi Disk Manager GUI wizard to unassign the ports associated to the volume, then delete it.\n\nActual Results:\n\nThe delete job failed with the trace records as follows:\norg.eclipse.aperi.disk.api.impl.DiskManagerService deleteStorageVolumes\n2007.01.03 15:41:56.750-08:00 Msg: HWN021684I Started deletion of volume 11 on subsystem FAStT500-TPC_L2_FASTT-600A0B80000C50E200000000440F238D-LSI. @(-9223372036854771931;[-9223372036854775700,0,1];6;DiskManagerThread-5 - deleteStorageVolumes([org.eclipse.aperi.disk.control.util.DeleteStorageVolumesParameter: {CIMOM: null; Storage Volume IDs: {}}]))   org.eclipse.aperi.disk.control.StorageConfigurationPluginFAStT11 deleteStorageVolumes\n2007.01.03 15:41:56.750-08:00 Msg: HWN021686E Volume deletion failed. Volume 11 on subsystem FAStT500-TPC_L2_FASTT-600A0B80000C50E200000000440F238D-LSI could not be deleted. @(-9223372036854771931;[-9223372036854775700,0,1];6;DiskManagerThread-5 - deleteStorageVolumes([org.eclipse.aperi.disk.control.util.DeleteStorageVolumesParameter: {CIMOM: null; Storage Volume IDs: {}}]))   org.eclipse.aperi.disk.control.StorageConfigurationPluginFAStT11 deleteStorageVolumes\n2007.01.03 15:41:56.750-08:00 HWN099993E HWN021503E @(-9223372036854771931;[-9223372036854775700,0,1];6;DiskManagerThread-5 - deleteStorageVolumes([org.eclipse.aperi.disk.control.util.DeleteStorageVolumesParameter: {CIMOM: null; Storage Volume IDs: {}}]))\n  org.eclipse.aperi.common.api.ServerException: HWN021503E An internal error occurred, please try again. If the problem persist, please contact IBM service.\n\tat org.eclipse.aperi.disk.common.util.DiskMessageHelper.getServerException(DiskMessageHelper.java:149)\n\tat org.eclipse.aperi.disk.control.StorageConfigurationPlugin.setVolumeDeletionSubjobFailed(StorageConfigurationPlugin.java:1406)\n\tat org.eclipse.aperi.disk.control.StorageConfigurationPlugin.deleteStorageVolumes(StorageConfigurationPlugin.java:636)\n\tat sun.reflect.NativeMethodAccessorImpl.invoke0(Native Method)\n\tat sun.reflect.NativeMethodAccessorImpl.invoke(Unknown Source)\n\tat sun.reflect.DelegatingMethodAccessorImpl.invoke(Unknown Source)\n\tat java.lang.reflect.Method.invoke(Unknown Source)\n\tat org.eclipse.aperi.disk.common.util.thread.DiskMgrThread.run(DiskMgrThread.java:257)   org.eclipse.aperi.disk.control.StorageConfigurationPluginFAStT11 deleteStorageVolumes\n2007.01.03 15:41:56.750-08:00 Msg: HWN021503E An internal error occurred, please try again. If the problem persist, please contact IBM service. @(-9223372036854771931;[-9223372036854775700,0,1];6;DiskManagerThread-5 - deleteStorageVolumes([org.eclipse.aperi.disk.control.util.DeleteStorageVolumesParameter: {CIMOM: null; Storage Volume IDs: {}}]))   org.eclipse.aperi.disk.control.StorageConfigurationPluginFAStT11 deleteStorageVolumes                                  \n     \nExpected Results:\n\ndelete job will run successfully\n                                 \nBuild Date \u0026 Platform: \n     Aperi-20070103.085736.zip",
    "Unfortunately the provided portion of the logs does not show the information\nthat identifies the root cause for the problem.\nIf the problem was not a temporary issue, please recreate and provide the full device server logs and the access info to the CIMOM.\n",
    "Please increase the tracelevel for the Disk component by following these instructions:\n\n1) stop Aperi Device Server\n2) edit the file \u003caperi_install\u003e/devsvr/configuration/logging.properties\n3) add or edit the following line:\naperi.logger.trace.DiskManager.level\u003dALL\n4) start Aperi Device Server",
    "Once I stopped and restarted the Aperi device server, I was not able to recreate the problem."
  ],
  "commentCreationDates": [
    "2007-01-04T00:26:21+01:00",
    "2007-01-04T15:08:47+01:00",
    "2007-01-05T15:22:06+01:00",
    "2007-01-05T18:28:57+01:00"
  ],
  "traces": [
    {
      "exceptionType": "org.eclipse.aperi.common.api.ServerException",
      "message": "HWN021503E An internal error occurred, please try again. If the problem persist, please contact IBM service.",
      "elements": [
        {
          "method": "org.eclipse.aperi.disk.common.util.DiskMessageHelper.getServerException",
          "source": "DiskMessageHelper.java:149"
        },
        {
          "method": "org.eclipse.aperi.disk.control.StorageConfigurationPlugin.setVolumeDeletionSubjobFailed",
          "source": "StorageConfigurationPlugin.java:1406"
        },
        {
          "method": "org.eclipse.aperi.disk.control.StorageConfigurationPlugin.deleteStorageVolumes",
          "source": "StorageConfigurationPlugin.java:636"
        },
        {
          "method": "sun.reflect.NativeMethodAccessorImpl.invoke0",
          "source": "Native Method"
        },
        {
          "method": "sun.reflect.NativeMethodAccessorImpl.invoke",
          "source": "Unknown Source"
        },
        {
          "method": "sun.reflect.DelegatingMethodAccessorImpl.invoke",
          "source": "Unknown Source"
        },
        {
          "method": "java.lang.reflect.Method.invoke",
          "source": "Unknown Source"
        },
        {
          "method": "org.eclipse.aperi.disk.common.util.thread.DiskMgrThread.run",
          "source": "DiskMgrThread.java:257"
        }
      ],
      "number": 0,
      "commentIndex": 0,
      "bugId": "169490",
      "date": "2007-01-04T00:26:21+01:00",
      "product": "Aperi",
      "component": "aperi.device",
      "severity": "major"
    }
  ],
  "groupId": "169490",
  "bugId": "169490",
  "date": "2007-01-04T00:26:21+01:00",
  "product": "Aperi",
  "component": "aperi.device",
  "severity": "major"
}