{
  "comments": [
    "SDOUtil.java does not support attribute name including character \u0027.\u0027  in Xpath.\nFor example:\nDataobject mydataObject has a array attribute \"BO.attribute\". I want to get the first Object in the array using:\nSDOUtil.get(mydataObject, \"BO.attribute.0\");\nI get exception: \nException in thread \"main\" java.lang.IllegalArgumentException: Class \u0027BO\u0027 does not have a feature named  \n\u0027BO\u0027\n\tat org.eclipse.emf.ecore.sdo.util.SDOUtil.getEStructuralFeature(SDOUtil.java:115)\n\tat org.eclipse.emf.ecore.sdo.util.SDOUtil$Accessor.setFeatureName(SDOUtil.java:834)\n\tat org.eclipse.emf.ecore.sdo.util.SDOUtil$Accessor.process(SDOUtil.java:933)\n\tat org.eclipse.emf.ecore.sdo.util.SDOUtil$Accessor.init(SDOUtil.java:725)\n\tat org.eclipse.emf.ecore.sdo.util.SDOUtil$Accessor.create(SDOUtil.java:645)\n\tat org.eclipse.emf.ecore.sdo.util.SDOUtil.get(SDOUtil.java:162)\n\nCould you please help to resolve the problem? \nBy the way, in current SDO implement, are there any \".\" limitation in other classes and any other characters limitation? Thank you very much for your help.",
    "\n\n*** This bug has been marked as a duplicate of bug 169815 ***"
  ],
  "commentCreationDates": [
    "2007-01-08T07:43:37+01:00",
    "2007-01-08T14:14:03+01:00"
  ],
  "traces": [
    {
      "exceptionType": "java.lang.IllegalArgumentException",
      "message": "Class \u0027BO\u0027 does not have a feature named   \u0027BO\u0027",
      "elements": [
        {
          "method": "org.eclipse.emf.ecore.sdo.util.SDOUtil.getEStructuralFeature",
          "source": "SDOUtil.java:115"
        },
        {
          "method": "org.eclipse.emf.ecore.sdo.util.SDOUtil$Accessor.setFeatureName",
          "source": "SDOUtil.java:834"
        },
        {
          "method": "org.eclipse.emf.ecore.sdo.util.SDOUtil$Accessor.process",
          "source": "SDOUtil.java:933"
        },
        {
          "method": "org.eclipse.emf.ecore.sdo.util.SDOUtil$Accessor.init",
          "source": "SDOUtil.java:725"
        },
        {
          "method": "org.eclipse.emf.ecore.sdo.util.SDOUtil$Accessor.create",
          "source": "SDOUtil.java:645"
        },
        {
          "method": "org.eclipse.emf.ecore.sdo.util.SDOUtil.get",
          "source": "SDOUtil.java:162"
        }
      ],
      "number": 0,
      "commentIndex": 0,
      "bugId": "169816",
      "duplicateId": "169815",
      "date": "2007-01-08T07:43:37+01:00",
      "product": "EMF",
      "component": "SDO",
      "severity": "critical"
    }
  ],
  "groupId": "169815",
  "bugId": "169816",
  "duplicateId": "169815",
  "date": "2007-01-08T07:43:37+01:00",
  "product": "EMF",
  "component": "SDO",
  "severity": "critical"
}