{
  "comments": [
    "I was launching a eclipse form a target and I got the following stack trace in\nthe log file of the target (eclipse host -\u003e eclipse target -\u003e eclipse).\nI didn\u0027t see any other problem, just the trace in the log. \n\n!ENTRY org.eclipse.jdt.debug 4 120 May 22, 2002 13:43:36.225\n!MESSAGE Internal error logged from JDI Debug: \n!STACK 0\ncom.sun.jdi.ObjectCollectedException\n        at\norg.eclipse.jdi.internal.MirrorImpl.defaultReplyErrorHandler(MirrorImpl.java:235)\n        at\norg.eclipse.jdi.internal.ThreadReferenceImpl.isSuspended(ThreadReferenceImpl.java:236)\n        at\norg.eclipse.jdt.internal.debug.core.model.JDIThread.initialize(JDIThread.java:192)\n        at\norg.eclipse.jdt.internal.debug.core.model.JDIThread.\u003cinit\u003e(JDIThread.java:160)\n        at\norg.eclipse.jdt.internal.debug.core.model.JDIDebugTarget.createThread(JDIDebugTarget.java:422)\n        at\norg.eclipse.jdt.internal.debug.core.model.JDIDebugTarget$ThreadStartHandler.handleEvent(JDIDebugTarget.java:1790)\n        at\norg.eclipse.jdt.internal.debug.core.EventDispatcher.dispatch(EventDispatcher.java:129)\n        at\norg.eclipse.jdt.internal.debug.core.EventDispatcher.run(EventDispatcher.java:202)\n        at java.lang.Thread.run(Thread.java:536)",
    "\n\n*** This bug has been marked as a duplicate of 16834 ***"
  ],
  "commentCreationDates": [
    "2002-05-22T21:00:17+02:00",
    "2002-05-22T21:39:06+02:00"
  ],
  "traces": [
    {
      "exceptionType": "com.sun.jdi.ObjectCollectedException",
      "elements": [
        {
          "method": "org.eclipse.jdi.internal.MirrorImpl.defaultReplyErrorHandler",
          "source": "MirrorImpl.java:235"
        },
        {
          "method": "org.eclipse.jdi.internal.ThreadReferenceImpl.isSuspended",
          "source": "ThreadReferenceImpl.java:236"
        },
        {
          "method": "org.eclipse.jdt.internal.debug.core.model.JDIThread.initialize",
          "source": "JDIThread.java:192"
        },
        {
          "method": "org.eclipse.jdt.internal.debug.core.model.JDIThread.\u003cinit\u003e",
          "source": "JDIThread.java:160"
        },
        {
          "method": "org.eclipse.jdt.internal.debug.core.model.JDIDebugTarget.createThread",
          "source": "JDIDebugTarget.java:422"
        },
        {
          "method": "org.eclipse.jdt.internal.debug.core.model.JDIDebugTarget$ThreadStartHandler.handleEvent",
          "source": "JDIDebugTarget.java:1790"
        },
        {
          "method": "org.eclipse.jdt.internal.debug.core.EventDispatcher.dispatch",
          "source": "EventDispatcher.java:129"
        },
        {
          "method": "org.eclipse.jdt.internal.debug.core.EventDispatcher.run",
          "source": "EventDispatcher.java:202"
        },
        {
          "method": "java.lang.Thread.run",
          "source": "Thread.java:536"
        }
      ],
      "number": 0,
      "commentIndex": 0,
      "bugId": "16991",
      "duplicateId": "16834",
      "date": "2002-05-22T21:00:17+02:00",
      "product": "JDT",
      "component": "Debug",
      "severity": "normal"
    }
  ],
  "groupId": "16834",
  "bugId": "16991",
  "duplicateId": "16834",
  "date": "2002-05-22T21:00:17+02:00",
  "product": "JDT",
  "component": "Debug",
  "severity": "normal"
}