{
  "comments": [
    "Description:\nNoClassDefFound when generate report by genReport in BIRT runtime package.\n\nBuild number:2.2.0.v20070112\n\nSteps to reproduce:\n1. Using genReport in Report Engine folder inside BIRT RUNTIME package to generate attached report.\n\nExpected result:\nThe report is rendered without errors.\n\nActual result:\nException throws out.\n\nError log:\nException in thread \"main\" java.lang.NoClassDefFoundError: org/eclipse/birt/repo\nrt/engine/script/internal/IHideRuleMethod\n        at java.lang.ClassLoader.defineClass1(Native Method)\n        at java.lang.ClassLoader.defineClass(ClassLoader.java:620)\n        at java.security.SecureClassLoader.defineClass(SecureClassLoader.java:12\n4)\n        at java.net.URLClassLoader.defineClass(URLClassLoader.java:260)\n        at java.net.URLClassLoader.access$100(URLClassLoader.java:56)\n        at java.net.URLClassLoader$1.run(URLClassLoader.java:195)\n        at java.security.AccessController.doPrivileged(Native Method)\n        at java.net.URLClassLoader.findClass(URLClassLoader.java:188)\n        at java.lang.ClassLoader.loadClass(ClassLoader.java:306)\n        at sun.misc.Launcher$AppClassLoader.loadClass(Launcher.java:268)\n        at java.lang.ClassLoader.loadClass(ClassLoader.java:251)\n        at java.lang.ClassLoader.loadClassInternal(ClassLoader.java:319)\n        at java.lang.ClassLoader.defineClass1(Native Method)\n        at java.lang.ClassLoader.defineClass(ClassLoader.java:620)\n        at java.security.SecureClassLoader.defineClass(SecureClassLoader.java:12\n4)\n        at java.net.URLClassLoader.defineClass(URLClassLoader.java:260)\n        at java.net.URLClassLoader.access$100(URLClassLoader.java:56)\n        at java.net.URLClassLoader$1.run(URLClassLoader.java:195)\n        at java.security.AccessController.doPrivileged(Native Method)\n        at java.net.URLClassLoader.findClass(URLClassLoader.java:188)\n        at java.lang.ClassLoader.loadClass(ClassLoader.java:306)\n        at sun.misc.Launcher$AppClassLoader.loadClass(Launcher.java:268)\n        at java.lang.ClassLoader.loadClass(ClassLoader.java:251)\n        at java.lang.ClassLoader.loadClassInternal(ClassLoader.java:319)\n        at java.lang.ClassLoader.defineClass1(Native Method)\n        at java.lang.ClassLoader.defineClass(ClassLoader.java:620)\n        at java.security.SecureClassLoader.defineClass(SecureClassLoader.java:12\n4)\n        at java.net.URLClassLoader.defineClass(URLClassLoader.java:260)\n        at java.net.URLClassLoader.access$100(URLClassLoader.java:56)\n        at java.net.URLClassLoader$1.run(URLClassLoader.java:195)\n        at java.security.AccessController.doPrivileged(Native Method)\n        at java.net.URLClassLoader.findClass(URLClassLoader.java:188)\n        at java.lang.ClassLoader.loadClass(ClassLoader.java:306)\n        at sun.misc.Launcher$AppClassLoader.loadClass(Launcher.java:268)\n        at java.lang.ClassLoader.loadClass(ClassLoader.java:299)\n        at java.lang.ClassLoader.loadClass(ClassLoader.java:251)\n        at org.eclipse.osgi.framework.internal.core.BundleLoader.findClassIntern\nal(BundleLoader.java:395)\n        at org.eclipse.osgi.framework.internal.core.BundleLoader.findClass(Bundl\neLoader.java:379)\n        at org.eclipse.osgi.framework.internal.core.BundleLoader.findClass(Bundl\neLoader.java:367)\n        at org.eclipse.osgi.internal.baseadaptor.DefaultClassLoader.loadClass(De\nfaultClassLoader.java:83)\n        at java.lang.ClassLoader.loadClass(ClassLoader.java:251)",
    "Created an attachment (id\u003d56815)\nreport design\n\n",
    "If this is only an interface for implementation, please remove this interface. Add methods to the element interface directly.",
    "fix it. delete IHideRuleMethod and IHighlightRuleMethod in engine.script.internal",
    "Verify in build 2.2.0.v20070117"
  ],
  "commentCreationDates": [
    "2007-01-12T07:33:48+01:00",
    "2007-01-12T07:36:30+01:00",
    "2007-01-12T07:58:09+01:00",
    "2007-01-12T08:24:35+01:00",
    "2007-01-17T10:39:44+01:00"
  ],
  "traces": [
    {
      "exceptionType": "java.lang.NoClassDefFoundError",
      "message": "org/eclipse/birt/repo rt/engine/script/internal/IHideRuleMethod",
      "elements": [
        {
          "method": "java.lang.ClassLoader.defineClass1",
          "source": "Native Method"
        },
        {
          "method": "java.lang.ClassLoader.defineClass",
          "source": "ClassLoader.java:620"
        },
        {
          "method": "java.security.SecureClassLoader.defineClass",
          "source": "SecureClassLoader.java:12 4"
        },
        {
          "method": "java.net.URLClassLoader.defineClass",
          "source": "URLClassLoader.java:260"
        },
        {
          "method": "java.net.URLClassLoader.access$100",
          "source": "URLClassLoader.java:56"
        },
        {
          "method": "java.net.URLClassLoader$1.run",
          "source": "URLClassLoader.java:195"
        },
        {
          "method": "java.security.AccessController.doPrivileged",
          "source": "Native Method"
        },
        {
          "method": "java.net.URLClassLoader.findClass",
          "source": "URLClassLoader.java:188"
        },
        {
          "method": "java.lang.ClassLoader.loadClass",
          "source": "ClassLoader.java:306"
        },
        {
          "method": "sun.misc.Launcher$AppClassLoader.loadClass",
          "source": "Launcher.java:268"
        },
        {
          "method": "java.lang.ClassLoader.loadClass",
          "source": "ClassLoader.java:251"
        },
        {
          "method": "java.lang.ClassLoader.loadClassInternal",
          "source": "ClassLoader.java:319"
        },
        {
          "method": "java.lang.ClassLoader.defineClass1",
          "source": "Native Method"
        },
        {
          "method": "java.lang.ClassLoader.defineClass",
          "source": "ClassLoader.java:620"
        },
        {
          "method": "java.security.SecureClassLoader.defineClass",
          "source": "SecureClassLoader.java:12 4"
        },
        {
          "method": "java.net.URLClassLoader.defineClass",
          "source": "URLClassLoader.java:260"
        },
        {
          "method": "java.net.URLClassLoader.access$100",
          "source": "URLClassLoader.java:56"
        },
        {
          "method": "java.net.URLClassLoader$1.run",
          "source": "URLClassLoader.java:195"
        },
        {
          "method": "java.security.AccessController.doPrivileged",
          "source": "Native Method"
        },
        {
          "method": "java.net.URLClassLoader.findClass",
          "source": "URLClassLoader.java:188"
        },
        {
          "method": "java.lang.ClassLoader.loadClass",
          "source": "ClassLoader.java:306"
        },
        {
          "method": "sun.misc.Launcher$AppClassLoader.loadClass",
          "source": "Launcher.java:268"
        },
        {
          "method": "java.lang.ClassLoader.loadClass",
          "source": "ClassLoader.java:251"
        },
        {
          "method": "java.lang.ClassLoader.loadClassInternal",
          "source": "ClassLoader.java:319"
        },
        {
          "method": "java.lang.ClassLoader.defineClass1",
          "source": "Native Method"
        },
        {
          "method": "java.lang.ClassLoader.defineClass",
          "source": "ClassLoader.java:620"
        },
        {
          "method": "java.security.SecureClassLoader.defineClass",
          "source": "SecureClassLoader.java:12 4"
        },
        {
          "method": "java.net.URLClassLoader.defineClass",
          "source": "URLClassLoader.java:260"
        },
        {
          "method": "java.net.URLClassLoader.access$100",
          "source": "URLClassLoader.java:56"
        },
        {
          "method": "java.net.URLClassLoader$1.run",
          "source": "URLClassLoader.java:195"
        },
        {
          "method": "java.security.AccessController.doPrivileged",
          "source": "Native Method"
        },
        {
          "method": "java.net.URLClassLoader.findClass",
          "source": "URLClassLoader.java:188"
        },
        {
          "method": "java.lang.ClassLoader.loadClass",
          "source": "ClassLoader.java:306"
        },
        {
          "method": "sun.misc.Launcher$AppClassLoader.loadClass",
          "source": "Launcher.java:268"
        },
        {
          "method": "java.lang.ClassLoader.loadClass",
          "source": "ClassLoader.java:299"
        },
        {
          "method": "java.lang.ClassLoader.loadClass",
          "source": "ClassLoader.java:251"
        },
        {
          "method": "org.eclipse.osgi.framework.internal.core.BundleLoader.findClassInternal",
          "source": "BundleLoader.java:395"
        },
        {
          "method": "org.eclipse.osgi.framework.internal.core.BundleLoader.findClass",
          "source": "Bundl eLoader.java:379"
        },
        {
          "method": "org.eclipse.osgi.framework.internal.core.BundleLoader.findClass",
          "source": "Bundl eLoader.java:367"
        },
        {
          "method": "org.eclipse.osgi.internal.baseadaptor.DefaultClassLoader.loadClass",
          "source": "De faultClassLoader.java:83"
        },
        {
          "method": "java.lang.ClassLoader.loadClass",
          "source": "ClassLoader.java:251"
        }
      ],
      "number": 0,
      "commentIndex": 0,
      "bugId": "170298",
      "date": "2007-01-12T07:33:48+01:00",
      "product": "BIRT",
      "component": "Report",
      "severity": "major"
    }
  ],
  "groupId": "170298",
  "bugId": "170298",
  "date": "2007-01-12T07:33:48+01:00",
  "product": "BIRT",
  "component": "Report",
  "severity": "major"
}