{
  "comments": [
    "Observed in the F1 driver\n\norg.eclipse.core.internal.runtime.AssertionFailedException: assertion failed: \nThe application has not been initialized.\n        at org.eclipse.core.internal.runtime.Assert.isTrue(Assert.java(Compiled \nCode))\n        at org.eclipse.core.internal.runtime.InternalPlatform.assertInitialized\n(InternalPlatform.java:161)\n        at org.eclipse.core.internal.runtime.InternalPlatform.log\n(InternalPlatform.java:670)\n        at org.eclipse.core.internal.runtime.Log.log(Log.java:66)\n        at org.eclipse.jdt.internal.core.Util.log(Util.java:558)\n        at org.eclipse.jdt.internal.core.search.processing.JobManager.run\n(JobManager.java:342)\n        at java.lang.Thread.run(Thread.java:512)",
    "We should not be logging during shutdown. Please add protection (guessing this \nis the indexer attempting to restart - we should also make sure it doesn\u0027t go \nanywhere there either).",
    "Added protection and ensures that JobManager.shutDown() doesn\u0027t return until \nthe indexing thread has died.",
    "Verified."
  ],
  "commentCreationDates": [
    "2002-05-22T23:36:41+02:00",
    "2002-05-22T23:38:43+02:00",
    "2002-05-24T14:49:00+02:00",
    "2002-06-03T14:53:36+02:00"
  ],
  "traces": [
    {
      "exceptionType": "org.eclipse.core.internal.runtime.AssertionFailedException",
      "message": "assertion failed:  The application has not been initialized.",
      "elements": [
        {
          "method": "org.eclipse.core.internal.runtime.Assert.isTrue",
          "source": "Assert.java(Compiled  Code)"
        },
        {
          "method": "org.eclipse.core.internal.runtime.InternalPlatform.assertInitialized",
          "source": "InternalPlatform.java:161"
        },
        {
          "method": "org.eclipse.core.internal.runtime.InternalPlatform.log",
          "source": "InternalPlatform.java:670"
        },
        {
          "method": "org.eclipse.core.internal.runtime.Log.log",
          "source": "Log.java:66"
        },
        {
          "method": "org.eclipse.jdt.internal.core.Util.log",
          "source": "Util.java:558"
        },
        {
          "method": "org.eclipse.jdt.internal.core.search.processing.JobManager.run",
          "source": "JobManager.java:342"
        },
        {
          "method": "java.lang.Thread.run",
          "source": "Thread.java:512"
        }
      ],
      "number": 0,
      "commentIndex": 0,
      "bugId": "17101",
      "date": "2002-05-22T23:36:41+02:00",
      "product": "JDT",
      "component": "Core",
      "severity": "normal"
    }
  ],
  "groupId": "17101",
  "bugId": "17101",
  "date": "2002-05-22T23:36:41+02:00",
  "product": "JDT",
  "component": "Core",
  "severity": "normal"
}