{
  "comments": [
    "3.3M2\n\nThis has been reported by a user of SWT on OSX after resizing a SashForm with a Table within it.\n\njava.lang.IllegalArgumentException: Argument not valid\n        at org.eclipse.swt.SWT.error(SWT.java:3391)\n        at org.eclipse.swt.SWT.error(SWT.java:3330)\n        at org.eclipse.swt.SWT.error(SWT.java:3301)\n        at org.eclipse.swt.graphics.Region.add(Region.java:132)\n        at org.eclipse.swt.widgets.Table.drawItemProc(Table.java:968)\n        at org.eclipse.swt.widgets.Display.drawItemProc(Display.java:1086)\n        at org.eclipse.swt.internal.carbon.OS.CallNextEventHandler(Native Method)\n        at org.eclipse.swt.widgets.Widget.callPaintEventHandler(Widget.java:170)\n        at org.eclipse.swt.widgets.Table.callPaintEventHandler(Table.java:184)\n        at org.eclipse.swt.widgets.Widget.kEventControlDraw(Widget.java:1000)\n        at org.eclipse.swt.widgets.Widget.controlProc(Widget.java:352)\n        at org.eclipse.swt.widgets.Display.controlProc(Display.java:839)\n        at org.eclipse.swt.internal.carbon.OS.TrackMouseLocationWithOptions(Native Method)\n        at org.eclipse.swt.widgets.Sash.kEventMouseDown(Sash.java:227)\n        at org.eclipse.swt.widgets.Widget.mouseProc(Widget.java:1246)\n        at org.eclipse.swt.widgets.Display.mouseProc(Display.java:2811)\n        at org.eclipse.swt.internal.carbon.OS.SendEventToEventTarget(Native Method)\n        at org.eclipse.swt.widgets.Display.readAndDispatch(Display.java:2950)",
    "Fixed \u003e 20070220"
  ],
  "commentCreationDates": [
    "2007-01-24T16:23:53+01:00",
    "2007-02-20T20:37:04+01:00"
  ],
  "traces": [
    {
      "exceptionType": "java.lang.IllegalArgumentException",
      "message": "Argument not valid",
      "elements": [
        {
          "method": "org.eclipse.swt.SWT.error",
          "source": "SWT.java:3391"
        },
        {
          "method": "org.eclipse.swt.SWT.error",
          "source": "SWT.java:3330"
        },
        {
          "method": "org.eclipse.swt.SWT.error",
          "source": "SWT.java:3301"
        },
        {
          "method": "org.eclipse.swt.graphics.Region.add",
          "source": "Region.java:132"
        },
        {
          "method": "org.eclipse.swt.widgets.Table.drawItemProc",
          "source": "Table.java:968"
        },
        {
          "method": "org.eclipse.swt.widgets.Display.drawItemProc",
          "source": "Display.java:1086"
        },
        {
          "method": "org.eclipse.swt.internal.carbon.OS.CallNextEventHandler",
          "source": "Native Method"
        },
        {
          "method": "org.eclipse.swt.widgets.Widget.callPaintEventHandler",
          "source": "Widget.java:170"
        },
        {
          "method": "org.eclipse.swt.widgets.Table.callPaintEventHandler",
          "source": "Table.java:184"
        },
        {
          "method": "org.eclipse.swt.widgets.Widget.kEventControlDraw",
          "source": "Widget.java:1000"
        },
        {
          "method": "org.eclipse.swt.widgets.Widget.controlProc",
          "source": "Widget.java:352"
        },
        {
          "method": "org.eclipse.swt.widgets.Display.controlProc",
          "source": "Display.java:839"
        },
        {
          "method": "org.eclipse.swt.internal.carbon.OS.TrackMouseLocationWithOptions",
          "source": "Native Method"
        },
        {
          "method": "org.eclipse.swt.widgets.Sash.kEventMouseDown",
          "source": "Sash.java:227"
        },
        {
          "method": "org.eclipse.swt.widgets.Widget.mouseProc",
          "source": "Widget.java:1246"
        },
        {
          "method": "org.eclipse.swt.widgets.Display.mouseProc",
          "source": "Display.java:2811"
        },
        {
          "method": "org.eclipse.swt.internal.carbon.OS.SendEventToEventTarget",
          "source": "Native Method"
        },
        {
          "method": "org.eclipse.swt.widgets.Display.readAndDispatch",
          "source": "Display.java:2950"
        }
      ],
      "number": 0,
      "commentIndex": 0,
      "bugId": "171562",
      "date": "2007-01-24T16:23:53+01:00",
      "product": "Platform",
      "component": "SWT",
      "severity": "normal"
    }
  ],
  "groupId": "171562",
  "bugId": "171562",
  "date": "2007-01-24T16:23:53+01:00",
  "product": "Platform",
  "component": "SWT",
  "severity": "normal"
}