{
  "comments": [
    "The device server console showed the following db error messages when using DB2 as repository running Aperi-20070124-190706.zip build\n\ndelete from t_view_vhost2port where host_id \u003d ?\n insert into t_view_vhost2port    SELECT HOST.PREFIX_ID PREFIX_ID, HOST.COMPUTER\n_ID HOST_ID, PORT.PORT_ID   PORT_ID FROM T_VIEW_VHOST HOST, T_RES_HBA HBA, T_RES\n_PORT PORT WHERE   HOST.PREFIX_ID \u003d \u0027server:\u0027 and HOST.COMPUTER_ID \u003d HBA.HOST_ID\n and   HBA.HBA_ID \u003d PORT.HBA_ID AND HOST.computer_id \u003d ?\n insert into t_view_vhost2port    SELECT HOST.PREFIX_ID PREFIX_ID,   HOST.COMPUT\nER_ID HOST_ID, PORT.PORT_ID PORT_ID FROM T_VIEW_VHOST HOST,   T_RES_CONTROLLER C\nONTROLLER, T_RES_PORT PORT WHERE HOST.PREFIX_ID \u003d   \u0027server:\u0027 and HOST.COMPUTER_\nID \u003d CONTROLLER.COMPUTER_ID and   CONTROLLER.WWN_STR \u003d PORT.NAME AND HOST.comput\ner_id \u003d ?\n insert into t_view_vhost2port    SELECT HOST.PREFIX_ID PREFIX_ID,   HOST.COMPUT\nER_ID HOST_ID, UNKNOWN2PORT.PORT_ID PORT_ID FROM T_VIEW_VHOST   HOST, T_VIEW_VUN\nKNOWN2PORT UNKNOWN2PORT WHERE HOST.PREFIX_ID \u003d   UNKNOWN2PORT.PREFIX_ID and HOST\n.COMPUTER_ID \u003d UNKNOWN2PORT.UNKNOWN_ID AND HOST.computer_id \u003d ?\ncom.ibm.db2.jcc.b.SqlException: DB2 SQL error: SQLCODE: -805, SQLSTATE: 51002, S\nQLERRMC: NULLID.SYSLH203 0X5359534C564C3031\n        at com.ibm.db2.jcc.b.zc.e(zc.java:1606)\n        at com.ibm.db2.jcc.a.db.p(db.java:634)\n        at com.ibm.db2.jcc.a.db.h(db.java:152)\n        at com.ibm.db2.jcc.a.db.a(db.java:43)\n        at com.ibm.db2.jcc.a.r.a(r.java:30)\n        at com.ibm.db2.jcc.a.sb.g(sb.java:152)\n        at com.ibm.db2.jcc.b.zc.n(zc.java:1186)\n        at com.ibm.db2.jcc.b.ad.db(ad.java:1761)\n        at com.ibm.db2.jcc.b.ad.d(ad.java:2203)\n        at com.ibm.db2.jcc.b.ad.V(ad.java:521)\n        at com.ibm.db2.jcc.b.ad.executeUpdate(ad.java:504)\n        at org.eclipse.aperi.infrastructure.database.DBPreparedStatement.execute\nUpdate(DBPreparedStatement.java:250)\n        at org.eclipse.aperi.common.dbaccess.ViewReportTablesUpdater.handleUpdat\ne(ViewReportTablesUpdater.java:1324)\n        at org.eclipse.aperi.common.dbaccess.ViewReportTablesUpdater.updateHostT\nables(ViewReportTablesUpdater.java:1090)\n        at org.eclipse.aperi.common.dbaccess.ViewReportTablesUpdater.updateOther\nTables(ViewReportTablesUpdater.java:1033)\n        at org.eclipse.aperi.common.dbaccess.ViewReportTablesUpdater.updateViewT\nables(ViewReportTablesUpdater.java:927)\n        at org.eclipse.aperi.common.dbaccess.ViewReportTablesUpdater.processView\n(ViewReportTablesUpdater.java:837)\n        at org.eclipse.aperi.infrastructure.history.detectability.ChangeDetectio\nn.complete(ChangeDetection.java:1585)\n        at org.eclipse.aperi.discovery.parser.Processor.end(Processor.java:278)\n        at org.eclipse.aperi.discovery.parser.TSANMLegacyParser$Worker.parse(TSA\nNMLegacyParser.java:333)\n        at org.eclipse.aperi.discovery.parser.Parser.processJob(Parser.java:17)\n        at org.eclipse.aperi.discovery.parser.TSANMLegacyParser.run(TSANMLegacyP\narser.java:131)",
    "Checked in DB2 configuration scripts that will make sure the SQL error does not happen - this involves change to cfgAperi (the DB2 configuration portion part)\n",
    "*** Bug 177038 has been marked as a duplicate of this bug. ***"
  ],
  "commentCreationDates": [
    "2007-01-30T19:51:01+01:00",
    "2007-03-23T21:38:19+01:00",
    "2007-03-23T21:39:00+01:00"
  ],
  "traces": [
    {
      "exceptionType": "com.ibm.db2.jcc.b.SqlException",
      "message": "DB2 SQL error: SQLCODE: -805, SQLSTATE: 51002, S QLERRMC: NULLID.SYSLH203 0X5359534C564C3031",
      "elements": [
        {
          "method": "com.ibm.db2.jcc.b.zc.e",
          "source": "zc.java:1606"
        },
        {
          "method": "com.ibm.db2.jcc.a.db.p",
          "source": "db.java:634"
        },
        {
          "method": "com.ibm.db2.jcc.a.db.h",
          "source": "db.java:152"
        },
        {
          "method": "com.ibm.db2.jcc.a.db.a",
          "source": "db.java:43"
        },
        {
          "method": "com.ibm.db2.jcc.a.r.a",
          "source": "r.java:30"
        },
        {
          "method": "com.ibm.db2.jcc.a.sb.g",
          "source": "sb.java:152"
        },
        {
          "method": "com.ibm.db2.jcc.b.zc.n",
          "source": "zc.java:1186"
        },
        {
          "method": "com.ibm.db2.jcc.b.ad.db",
          "source": "ad.java:1761"
        },
        {
          "method": "com.ibm.db2.jcc.b.ad.d",
          "source": "ad.java:2203"
        },
        {
          "method": "com.ibm.db2.jcc.b.ad.V",
          "source": "ad.java:521"
        },
        {
          "method": "com.ibm.db2.jcc.b.ad.executeUpdate",
          "source": "ad.java:504"
        },
        {
          "method": "org.eclipse.aperi.infrastructure.database.DBPreparedStatement.executeUpdate",
          "source": "DBPreparedStatement.java:250"
        },
        {
          "method": "org.eclipse.aperi.common.dbaccess.ViewReportTablesUpdater.handleUpdate",
          "source": "ViewReportTablesUpdater.java:1324"
        },
        {
          "method": "org.eclipse.aperi.common.dbaccess.ViewReportTablesUpdater.updateHostTables",
          "source": "ViewReportTablesUpdater.java:1090"
        },
        {
          "method": "org.eclipse.aperi.common.dbaccess.ViewReportTablesUpdater.updateOtherTables",
          "source": "ViewReportTablesUpdater.java:1033"
        },
        {
          "method": "org.eclipse.aperi.common.dbaccess.ViewReportTablesUpdater.updateViewTables",
          "source": "ViewReportTablesUpdater.java:927"
        },
        {
          "method": "org.eclipse.aperi.common.dbaccess.ViewReportTablesUpdater.processView",
          "source": "ViewReportTablesUpdater.java:837"
        },
        {
          "method": "org.eclipse.aperi.infrastructure.history.detectability.ChangeDetection.complete",
          "source": "ChangeDetection.java:1585"
        },
        {
          "method": "org.eclipse.aperi.discovery.parser.Processor.end",
          "source": "Processor.java:278"
        },
        {
          "method": "org.eclipse.aperi.discovery.parser.TSANMLegacyParser$Worker.parse",
          "source": "TSA NMLegacyParser.java:333"
        },
        {
          "method": "org.eclipse.aperi.discovery.parser.Parser.processJob",
          "source": "Parser.java:17"
        },
        {
          "method": "org.eclipse.aperi.discovery.parser.TSANMLegacyParser.run",
          "source": "TSANMLegacyP arser.java:131"
        }
      ],
      "number": 0,
      "commentIndex": 0,
      "bugId": "172220",
      "date": "2007-01-30T19:51:01+01:00",
      "product": "Aperi",
      "component": "aperi.db",
      "severity": "normal"
    }
  ],
  "groupId": "172220",
  "bugId": "172220",
  "date": "2007-01-30T19:51:01+01:00",
  "product": "Aperi",
  "component": "aperi.db",
  "severity": "normal"
}