{
  "comments": [
    "F1 on Win32\n\nSo I have this bogus plugin which is failing with the following:\n\njava.lang.NoClassDefFoundError: org/eclipse/team/ui/actions/TeamAction\n...\n        at org.eclipse.ui.internal.WorkbenchPlugin.createExtension\n(WorkbenchPlugin.java:109)\n        at org.eclipse.ui.internal.PluginAction.createDelegate\n(PluginAction.java:84)\n        at org.eclipse.ui.internal.PluginAction.selectionChanged\n(PluginAction.java:230)\n        at \norg.eclipse.ui.internal.ObjectActionContributor.contributeObjectActions\n(ObjectActionContributor.java:67)\n        at \norg.eclipse.ui.internal.ObjectActionContributorManager.contributeObjectActions\n(ObjectActionContributorManager.java:108)\n        at org.eclipse.ui.internal.PopupMenuExtender.addObjectActions\n(PopupMenuExtender.java:48)\n        at org.eclipse.ui.internal.PopupMenuExtender.menuAboutToShow\n(PopupMenuExtender.java:68)\n        at org.eclipse.jface.action.MenuManager.fireAboutToShow\n(MenuManager.java:235)\n        at org.eclipse.jface.action.MenuManager.handleAboutToShow\n(MenuManager.java:306)\n        at org.eclipse.jface.action.MenuManager.access$0(MenuManager.java:303)\n        at org.eclipse.jface.action.MenuManager$2.menuShown\n(MenuManager.java:333)\n        at org.eclipse.swt.widgets.TypedListener.handleEvent\n(TypedListener.java:112)\n        at org.eclipse.swt.widgets.EventTable.sendEvent(EventTable.java\n(Compiled Code))\n        at org.eclipse.swt.widgets.Widget.sendEvent(Widget.java(Compiled Code))\n        at org.eclipse.swt.widgets.Widget.sendEvent(Widget.java(Compiled Code))\n        at org.eclipse.swt.widgets.Control.WM_INITMENUPOPUP(Control.java:3004)\n        at org.eclipse.swt.widgets.Control.windowProc(Control.java(Compiled \nCode))\n        at org.eclipse.swt.widgets.Decorations.windowProc(Decorations.java\n(Compiled Code))\n        at org.eclipse.swt.widgets.Display.windowProc(Display.java(Compiled \nCode))\n        at org.eclipse.swt.internal.win32.OS.TrackPopupMenu(Native Method)\n        at org.eclipse.swt.widgets.Menu.setVisible(Menu.java:810)\n        at org.eclipse.swt.widgets.Control.WM_CONTEXTMENU(Control.java:2815)\n        at org.eclipse.swt.widgets.Control.windowProc(Control.java(Compiled \nCode))\n        at org.eclipse.swt.widgets.Display.windowProc(Display.java(Compiled \nCode))\n        at org.eclipse.swt.internal.win32.OS.CallWindowProcW(Native Method)\n        at org.eclipse.swt.widgets.Tree.callWindowProc(Tree.java(Compiled \nCode))\n        at org.eclipse.swt.widgets.Tree.callWindowProc(Tree.java(Compiled \nCode))\n        at org.eclipse.swt.widgets.Control.WM_RBUTTONUP(Control.java:3704)\n        at org.eclipse.swt.widgets.Control.windowProc(Control.java(Compiled \nCode))\n        at org.eclipse.swt.widgets.Display.windowProc(Display.java(Compiled \nCode))\n        at org.eclipse.swt.internal.win32.OS.DispatchMessageW(Native Method)\n        at org.eclipse.swt.widgets.Display.readAndDispatch(Display.java\n(Compiled Code))\n        at org.eclipse.swt.widgets.Display.readAndDispatch(Display.java\n(Compiled Code))\n        at org.eclipse.ui.internal.Workbench.runEventLoop(Workbench.java\n(Compiled Code))\n        at org.eclipse.ui.internal.Workbench.run(Workbench.java:1068)\n        at org.eclipse.core.internal.boot.InternalBootLoader.run\n(InternalBootLoader.java:739)\n        at org.eclipse.core.boot.BootLoader.run(BootLoader.java:462)\n        at java.lang.reflect.Method.invoke(Native Method)\n        at org.eclipse.core.launcher.Main.basicRun(Main.java:200)\n        at org.eclipse.core.launcher.Main.run(Main.java:643)\n        at org.eclipse.core.launcher.Main.main(Main.java:476)\n\nThis randomly causes Eclipse to crash which leaves the following tidbit in the \njavacore:\n\n---------------------- Exception Information ---------------------------\nApplication aborted in thread \"main\" (TID:0x9F19D8)\n    \"main\" (TID:0x9F19D8, sys_thread_t:0x3E9D0, state:R, native ID:0x1D38) \nprio\u003d5: pending\u003djava.lang.NoClassDefFoundError\n        at org.eclipse.swt.internal.win32.OS.TrackPopupMenu(Native Method)\n        at org.eclipse.swt.widgets.Menu.setVisible(Menu.java:810)\n        at org.eclipse.swt.widgets.Control.WM_CONTEXTMENU(Control.java:2815)\n        at org.eclipse.swt.widgets.Control.windowProc(Control.java(Compiled \nCode))\n        at org.eclipse.swt.widgets.Display.windowProc(Display.java(Compiled \nCode))\n        at org.eclipse.swt.internal.win32.OS.CallWindowProcW(Native Method)\n        at org.eclipse.swt.internal.win32.OS.CallWindowProc(OS.java(Compiled \nCode))\n        at org.eclipse.swt.widgets.Tree.callWindowProc(Tree.java(Compiled \nCode))\n        at org.eclipse.swt.widgets.Control.WM_RBUTTONUP(Control.java:3704)\n        at org.eclipse.swt.widgets.Control.windowProc(Control.java(Compiled \nCode))\n        at org.eclipse.swt.widgets.Display.windowProc(Display.java(Compiled \nCode))\n        at org.eclipse.swt.internal.win32.OS.DispatchMessageW(Native Method)\n        at org.eclipse.swt.internal.win32.OS.DispatchMessage(OS.java(Compiled \nCode))\n        at org.eclipse.swt.widgets.Display.readAndDispatch(Display.java\n(Compiled Code))\n        at org.eclipse.ui.internal.Workbench.runEventLoop(Workbench.java\n(Compiled Code))\n        at org.eclipse.ui.internal.Workbench.run(Workbench.java:1068)\n        at org.eclipse.core.internal.boot.InternalBootLoader.run\n(InternalBootLoader.java:739)\n        at org.eclipse.core.boot.BootLoader.run(BootLoader.java:462)\n        at java.lang.reflect.Method.invoke(Native Method)\n        at org.eclipse.core.launcher.Main.basicRun(Main.java:200)\n        at org.eclipse.core.launcher.Main.run(Main.java:643)\n        at org.eclipse.core.launcher.Main.main(Main.java:476)",
    "Not sure what\u0027s going on, but obviously if Eclipse is in a bad state, then \nbad things can happen. SN to look at stack trace.",
    "Does this happen every time or did it only happen once?",
    "It doesn\u0027t happen every time.  More like every 2nd or 3rd but it will always \neventually happen.",
    "Can\u0027t recreate it.  Feel free to reopen this PR if it happens again."
  ],
  "commentCreationDates": [
    "2002-05-23T15:50:28+02:00",
    "2002-05-23T17:03:36+02:00",
    "2002-05-28T02:57:23+02:00",
    "2002-05-28T03:08:34+02:00",
    "2002-07-05T00:02:07+02:00"
  ],
  "traces": [
    {
      "exceptionType": "java.lang.NoClassDefFoundError",
      "message": "org/eclipse/team/ui/actions/TeamAction ...",
      "elements": [
        {
          "method": "org.eclipse.ui.internal.WorkbenchPlugin.createExtension",
          "source": "WorkbenchPlugin.java:109"
        },
        {
          "method": "org.eclipse.ui.internal.PluginAction.createDelegate",
          "source": "PluginAction.java:84"
        },
        {
          "method": "org.eclipse.ui.internal.PluginAction.selectionChanged",
          "source": "PluginAction.java:230"
        },
        {
          "method": "org.eclipse.ui.internal.ObjectActionContributor.contributeObjectActions",
          "source": "ObjectActionContributor.java:67"
        },
        {
          "method": "org.eclipse.ui.internal.ObjectActionContributorManager.contributeObjectActions",
          "source": "ObjectActionContributorManager.java:108"
        },
        {
          "method": "org.eclipse.ui.internal.PopupMenuExtender.addObjectActions",
          "source": "PopupMenuExtender.java:48"
        },
        {
          "method": "org.eclipse.ui.internal.PopupMenuExtender.menuAboutToShow",
          "source": "PopupMenuExtender.java:68"
        },
        {
          "method": "org.eclipse.jface.action.MenuManager.fireAboutToShow",
          "source": "MenuManager.java:235"
        },
        {
          "method": "org.eclipse.jface.action.MenuManager.handleAboutToShow",
          "source": "MenuManager.java:306"
        },
        {
          "method": "org.eclipse.jface.action.MenuManager.access$0",
          "source": "MenuManager.java:303"
        },
        {
          "method": "org.eclipse.jface.action.MenuManager$2.menuShown",
          "source": "MenuManager.java:333"
        },
        {
          "method": "org.eclipse.swt.widgets.TypedListener.handleEvent",
          "source": "TypedListener.java:112"
        },
        {
          "method": "org.eclipse.swt.widgets.EventTable.sendEvent",
          "source": "EventTable.java (Compiled Code)"
        },
        {
          "method": "org.eclipse.swt.widgets.Widget.sendEvent",
          "source": "Widget.java(Compiled Code)"
        },
        {
          "method": "org.eclipse.swt.widgets.Widget.sendEvent",
          "source": "Widget.java(Compiled Code)"
        },
        {
          "method": "org.eclipse.swt.widgets.Control.WM_INITMENUPOPUP",
          "source": "Control.java:3004"
        },
        {
          "method": "org.eclipse.swt.widgets.Control.windowProc",
          "source": "Control.java(Compiled  Code)"
        },
        {
          "method": "org.eclipse.swt.widgets.Decorations.windowProc",
          "source": "Decorations.java (Compiled Code)"
        },
        {
          "method": "org.eclipse.swt.widgets.Display.windowProc",
          "source": "Display.java(Compiled  Code)"
        },
        {
          "method": "org.eclipse.swt.internal.win32.OS.TrackPopupMenu",
          "source": "Native Method"
        },
        {
          "method": "org.eclipse.swt.widgets.Menu.setVisible",
          "source": "Menu.java:810"
        },
        {
          "method": "org.eclipse.swt.widgets.Control.WM_CONTEXTMENU",
          "source": "Control.java:2815"
        },
        {
          "method": "org.eclipse.swt.widgets.Control.windowProc",
          "source": "Control.java(Compiled  Code)"
        },
        {
          "method": "org.eclipse.swt.widgets.Display.windowProc",
          "source": "Display.java(Compiled  Code)"
        },
        {
          "method": "org.eclipse.swt.internal.win32.OS.CallWindowProcW",
          "source": "Native Method"
        },
        {
          "method": "org.eclipse.swt.widgets.Tree.callWindowProc",
          "source": "Tree.java(Compiled  Code)"
        },
        {
          "method": "org.eclipse.swt.widgets.Tree.callWindowProc",
          "source": "Tree.java(Compiled  Code)"
        },
        {
          "method": "org.eclipse.swt.widgets.Control.WM_RBUTTONUP",
          "source": "Control.java:3704"
        },
        {
          "method": "org.eclipse.swt.widgets.Control.windowProc",
          "source": "Control.java(Compiled  Code)"
        },
        {
          "method": "org.eclipse.swt.widgets.Display.windowProc",
          "source": "Display.java(Compiled  Code)"
        },
        {
          "method": "org.eclipse.swt.internal.win32.OS.DispatchMessageW",
          "source": "Native Method"
        },
        {
          "method": "org.eclipse.swt.widgets.Display.readAndDispatch",
          "source": "Display.java (Compiled Code)"
        },
        {
          "method": "org.eclipse.swt.widgets.Display.readAndDispatch",
          "source": "Display.java (Compiled Code)"
        },
        {
          "method": "org.eclipse.ui.internal.Workbench.runEventLoop",
          "source": "Workbench.java (Compiled Code)"
        },
        {
          "method": "org.eclipse.ui.internal.Workbench.run",
          "source": "Workbench.java:1068"
        },
        {
          "method": "org.eclipse.core.internal.boot.InternalBootLoader.run",
          "source": "InternalBootLoader.java:739"
        },
        {
          "method": "org.eclipse.core.boot.BootLoader.run",
          "source": "BootLoader.java:462"
        },
        {
          "method": "java.lang.reflect.Method.invoke",
          "source": "Native Method"
        },
        {
          "method": "org.eclipse.core.launcher.Main.basicRun",
          "source": "Main.java:200"
        },
        {
          "method": "org.eclipse.core.launcher.Main.run",
          "source": "Main.java:643"
        },
        {
          "method": "org.eclipse.core.launcher.Main.main",
          "source": "Main.java:476"
        }
      ],
      "number": 0,
      "commentIndex": 0,
      "bugId": "17258",
      "date": "2002-05-23T15:50:28+02:00",
      "product": "Platform",
      "component": "SWT",
      "severity": "normal"
    },
    {
      "exceptionType": "java.lang.NoClassDefFoundError",
      "elements": [
        {
          "method": "org.eclipse.swt.internal.win32.OS.TrackPopupMenu",
          "source": "Native Method"
        },
        {
          "method": "org.eclipse.swt.widgets.Menu.setVisible",
          "source": "Menu.java:810"
        },
        {
          "method": "org.eclipse.swt.widgets.Control.WM_CONTEXTMENU",
          "source": "Control.java:2815"
        },
        {
          "method": "org.eclipse.swt.widgets.Control.windowProc",
          "source": "Control.java(Compiled  Code)"
        },
        {
          "method": "org.eclipse.swt.widgets.Display.windowProc",
          "source": "Display.java(Compiled  Code)"
        },
        {
          "method": "org.eclipse.swt.internal.win32.OS.CallWindowProcW",
          "source": "Native Method"
        },
        {
          "method": "org.eclipse.swt.internal.win32.OS.CallWindowProc",
          "source": "OS.java(Compiled  Code)"
        },
        {
          "method": "org.eclipse.swt.widgets.Tree.callWindowProc",
          "source": "Tree.java(Compiled  Code)"
        },
        {
          "method": "org.eclipse.swt.widgets.Control.WM_RBUTTONUP",
          "source": "Control.java:3704"
        },
        {
          "method": "org.eclipse.swt.widgets.Control.windowProc",
          "source": "Control.java(Compiled  Code)"
        },
        {
          "method": "org.eclipse.swt.widgets.Display.windowProc",
          "source": "Display.java(Compiled  Code)"
        },
        {
          "method": "org.eclipse.swt.internal.win32.OS.DispatchMessageW",
          "source": "Native Method"
        },
        {
          "method": "org.eclipse.swt.internal.win32.OS.DispatchMessage",
          "source": "OS.java(Compiled  Code)"
        },
        {
          "method": "org.eclipse.swt.widgets.Display.readAndDispatch",
          "source": "Display.java (Compiled Code)"
        },
        {
          "method": "org.eclipse.ui.internal.Workbench.runEventLoop",
          "source": "Workbench.java (Compiled Code)"
        },
        {
          "method": "org.eclipse.ui.internal.Workbench.run",
          "source": "Workbench.java:1068"
        },
        {
          "method": "org.eclipse.core.internal.boot.InternalBootLoader.run",
          "source": "InternalBootLoader.java:739"
        },
        {
          "method": "org.eclipse.core.boot.BootLoader.run",
          "source": "BootLoader.java:462"
        },
        {
          "method": "java.lang.reflect.Method.invoke",
          "source": "Native Method"
        },
        {
          "method": "org.eclipse.core.launcher.Main.basicRun",
          "source": "Main.java:200"
        },
        {
          "method": "org.eclipse.core.launcher.Main.run",
          "source": "Main.java:643"
        },
        {
          "method": "org.eclipse.core.launcher.Main.main",
          "source": "Main.java:476"
        }
      ],
      "number": 1,
      "commentIndex": 0,
      "bugId": "17258",
      "date": "2002-05-23T15:50:28+02:00",
      "product": "Platform",
      "component": "SWT",
      "severity": "normal"
    }
  ],
  "groupId": "17258",
  "bugId": "17258",
  "date": "2002-05-23T15:50:28+02:00",
  "product": "Platform",
  "component": "SWT",
  "severity": "normal"
}