{
  "comments": [
    "Feb 2, 2007 3:09:35 PM org.eclipse.birt.report.model.metadata.StructRefPropertyT\nype validateValue\nINFO: The value of the structure property is a string\nFeb 2, 2007 3:09:42 PM org.apache.coyote.http11.Http11Protocol init\nINFO: Initializing Coyote HTTP/1.1 on port 61031\nFeb 2, 2007 3:09:42 PM org.apache.coyote.http11.Http11Protocol start\nINFO: Starting Coyote HTTP/1.1 on port 61031\nFeb 2, 2007 3:09:43 PM org.apache.axis.utils.JavaUtils isAttachmentSupported\nWARNING: Unable to find required classes (javax.activation.DataHandler and javax\n.mail.internet.MimeMultipart). Attachment support is disabled.\njava.io.IOException: Couldn\u0027t get lock for C:\\birt\\builds\\birt2.2M4\\birt-report-\ndesigner-all-in-one-2.2M4\\eclipse\\plugins\\org.eclipse.birt.report.viewer_2.2.0.v\n20070109\\birt\\logs\\ReportEngine_2007_02_02_15_09_43.log\n        at java.util.logging.FileHandler.openFiles(FileHandler.java:372)\n        at java.util.logging.FileHandler.\u003cinit\u003e(FileHandler.java:270)\n        at org.eclipse.birt.report.engine.api.impl.EngineLogger.startEngineLoggi\nng(EngineLogger.java:56)\n        at org.eclipse.birt.report.engine.api.impl.ReportEngineHelper.setupLoggi\nng(ReportEngineHelper.java:348)\n        at org.eclipse.birt.report.engine.api.impl.ReportEngine.setupLogging(Rep\nortEngine.java:108)\n        at org.eclipse.birt.report.engine.api.impl.ReportEngine.\u003cinit\u003e(ReportEng\nine.java:89)\n        at org.eclipse.birt.report.engine.api.impl.ReportEngineFactory.createRep\nortEngine(ReportEngineFactory.java:13)\n        at org.eclipse.birt.report.service.ReportEngineService.setEngineContext(\nUnknown Source)\n        at org.eclipse.birt.report.service.BirtViewerReportService.setContext(Un\nknown Source)\n        at org.eclipse.birt.report.servlet.ViewerServlet.__getContext(Unknown So\nurce)\n        at org.eclipse.birt.report.servlet.BirtSoapMessageDispatcherServlet.doGe\nt(Unknown Source)\n        at javax.servlet.http.HttpServlet.service(HttpServlet.java:740)\n        at org.apache.axis.transport.http.AxisServletBase.service(AxisServletBas\ne.java:327)\n        at javax.servlet.http.HttpServlet.service(HttpServlet.java:853)\n        at org.apache.catalina.core.ApplicationFilterChain.internalDoFilter(Appl\nicationFilterChain.java:247)\n        at org.apache.catalina.core.ApplicationFilterChain.doFilter(ApplicationF\nilterChain.java:193)\n        at org.apache.catalina.core.StandardWrapperValve.invoke(StandardWrapperV\nalve.java:256)\n        at org.apache.catalina.core.StandardPipeline$StandardPipelineValveContex\nt.invokeNext(StandardPipeline.java:643)\n        at org.apache.catalina.core.StandardPipeline.invoke(StandardPipeline.jav\na:480)\n        at org.apache.catalina.core.ContainerBase.invoke(ContainerBase.java:995)\n\n        at org.apache.catalina.core.StandardContextValve.invoke(StandardContextV\nalve.java:191)\n        at org.apache.catalina.core.StandardPipeline$StandardPipelineValveContex\nt.invokeNext(StandardPipeline.java:643)\n        at org.apache.catalina.valves.CertificatesValve.invoke(CertificatesValve\n.java:246)\n        at org.apache.catalina.core.StandardPipeline$StandardPipelineValveContex\nt.invokeNext(StandardPipeline.java:641)\n        at org.apache.catalina.core.StandardPipeline.invoke(StandardPipeline.jav\na:480)\n        at org.apache.catalina.core.ContainerBase.invoke(ContainerBase.java:995)\n\n        at org.apache.catalina.core.StandardContext.invoke(StandardContext.java:\n2422)\n        at org.apache.catalina.core.StandardHostValve.invoke(StandardHostValve.j\nava:180)\n        at org.apache.catalina.core.StandardPipeline$StandardPipelineValveContex\nt.invokeNext(StandardPipeline.java:643)\n        at org.apache.catalina.valves.ErrorDispatcherValve.invoke(ErrorDispatche\nrValve.java:171)\n        at org.apache.catalina.core.StandardPipeline$StandardPipelineValveContex\nt.invokeNext(StandardPipeline.java:641)\n        at org.eclipse.tomcat.internal.EclipseErrorReportValve.invoke(EclipseErr\norReportValve.java:153)\n        at org.apache.catalina.core.StandardPipeline$StandardPipelineValveContex\nt.invokeNext(StandardPipeline.java:641)\n        at org.apache.catalina.core.StandardPipeline.invoke(StandardPipeline.jav\na:480)\n        at org.apache.catalina.core.ContainerBase.invoke(ContainerBase.java:995)\n\n        at org.apache.catalina.core.StandardEngineValve.invoke(StandardEngineVal\nve.java:174)\n        at org.apache.catalina.core.StandardPipeline$StandardPipelineValveContex\nt.invokeNext(StandardPipeline.java:643)\n        at org.apache.catalina.core.StandardPipeline.invoke(StandardPipeline.jav\na:480)\n        at org.apache.catalina.core.ContainerBase.invoke(ContainerBase.java:995)\n\n        at org.apache.coyote.tomcat4.CoyoteAdapter.service(CoyoteAdapter.java:19\n9)\n        at org.apache.coyote.http11.Http11Processor.process(Http11Processor.java\n:828)\n        at org.apache.coyote.http11.Http11Protocol$Http11ConnectionHandler.proce\nssConnection(Http11Protocol.java:700)\n        at org.apache.tomcat.util.net.TcpWorkerThread.runIt(PoolTcpEndpoint.java\n:584)\n        at org.apache.tomcat.util.threads.ThreadPool$ControlRunnable.run(ThreadP\nool.java:683)\n        at java.lang.Thread.run(Thread.java:595)\nFeb 2, 2007 3:09:58 PM org.apache.axis.transport.http.AxisServlet logException\nINFO: Exception:\njava.lang.OutOfMemoryError: PermGen space\nError while informing user about event loop exception:\njava.lang.OutOfMemoryError: PermGen space\nDialog open exception:\njava.lang.OutOfMemoryError: PermGen space\nError while informing user about event loop exception:\njava.lang.OutOfMemoryError: PermGen space\nDialog open exception:\njava.lang.OutOfMemoryError: PermGen space\nError while informing user about event loop exception:\njava.lang.OutOfMemoryError: PermGen space\nDialog open exception:\njava.lang.OutOfMemoryError: PermGen space\nError while informing user about event loop exception:\njava.lang.OutOfMemoryError: PermGen space\nDialog open exception:\njava.lang.OutOfMemoryError: PermGen space\nError while informing user about event loop exception:\njava.lang.OutOfMemoryError: PermGen space\nDialog open exception:\njava.lang.OutOfMemoryError: PermGen space\nError while informing user about event loop exception:\njava.lang.OutOfMemoryError: PermGen space\nDialog open exception:\njava.lang.OutOfMemoryError: PermGen space\nError while informing user about event loop exception:\njava.lang.OutOfMemoryError: PermGen space\nDialog open exception:\njava.lang.OutOfMemoryError: PermGen space",
    "- Using BIRT 2.2 M4 build\n- I have not changed the eclipse default vm max size while starting the eclipse env.\n- Created a BIRT Web project and added a report design to it\n- View the report using viewer.( VIew Report -\u003e Viewer/HTML )\n- Problem is inconsistent.\n\nBut eventually the BIRT designer exits with out of memory errors.\n\n",
    "\n\n*** This bug has been marked as a duplicate of bug 172636 ***"
  ],
  "commentCreationDates": [
    "2007-02-02T23:13:26+01:00",
    "2007-02-02T23:16:17+01:00",
    "2007-02-05T01:40:33+01:00"
  ],
  "traces": [
    {
      "exceptionType": "java.io.IOException",
      "message": "Couldn\u0027t get lock for C:\\birt\\builds\\birt2.2M4\\birt-report- designer-all-in-one-2.2M4\\eclipse\\plugins\\org.eclipse.birt.report.viewer_2.2.0.v 20070109\\birt\\logs\\ReportEngine_2007_02_02_15_09_43.log",
      "elements": [
        {
          "method": "java.util.logging.FileHandler.openFiles",
          "source": "FileHandler.java:372"
        },
        {
          "method": "java.util.logging.FileHandler.\u003cinit\u003e",
          "source": "FileHandler.java:270"
        },
        {
          "method": "org.eclipse.birt.report.engine.api.impl.EngineLogger.startEngineLogging",
          "source": "EngineLogger.java:56"
        },
        {
          "method": "org.eclipse.birt.report.engine.api.impl.ReportEngineHelper.setupLogging",
          "source": "ReportEngineHelper.java:348"
        },
        {
          "method": "org.eclipse.birt.report.engine.api.impl.ReportEngine.setupLogging",
          "source": "Rep ortEngine.java:108"
        },
        {
          "method": "org.eclipse.birt.report.engine.api.impl.ReportEngine.\u003cinit\u003e",
          "source": "ReportEng ine.java:89"
        },
        {
          "method": "org.eclipse.birt.report.engine.api.impl.ReportEngineFactory.createReportEngine",
          "source": "ReportEngineFactory.java:13"
        },
        {
          "method": "org.eclipse.birt.report.service.ReportEngineService.setEngineContext",
          "source": " Unknown Source"
        },
        {
          "method": "org.eclipse.birt.report.service.BirtViewerReportService.setContext",
          "source": "Un known Source"
        },
        {
          "method": "org.eclipse.birt.report.servlet.ViewerServlet.__getContext",
          "source": "Unknown So urce"
        },
        {
          "method": "org.eclipse.birt.report.servlet.BirtSoapMessageDispatcherServlet.doGet",
          "source": "Unknown Source"
        },
        {
          "method": "javax.servlet.http.HttpServlet.service",
          "source": "HttpServlet.java:740"
        },
        {
          "method": "org.apache.axis.transport.http.AxisServletBase.service",
          "source": "AxisServletBas e.java:327"
        },
        {
          "method": "javax.servlet.http.HttpServlet.service",
          "source": "HttpServlet.java:853"
        },
        {
          "method": "org.apache.catalina.core.ApplicationFilterChain.internalDoFilter",
          "source": "Appl icationFilterChain.java:247"
        },
        {
          "method": "org.apache.catalina.core.ApplicationFilterChain.doFilter",
          "source": "ApplicationF ilterChain.java:193"
        },
        {
          "method": "org.apache.catalina.core.StandardWrapperValve.invoke",
          "source": "StandardWrapperV alve.java:256"
        },
        {
          "method": "org.apache.catalina.core.StandardPipeline$StandardPipelineValveContext.invokeNext",
          "source": "StandardPipeline.java:643"
        },
        {
          "method": "org.apache.catalina.core.StandardPipeline.invoke",
          "source": "StandardPipeline.jav a:480"
        },
        {
          "method": "org.apache.catalina.core.ContainerBase.invoke",
          "source": "ContainerBase.java:995"
        },
        {
          "method": "org.apache.catalina.core.StandardContextValve.invoke",
          "source": "StandardContextV alve.java:191"
        },
        {
          "method": "org.apache.catalina.core.StandardPipeline$StandardPipelineValveContext.invokeNext",
          "source": "StandardPipeline.java:643"
        },
        {
          "method": "org.apache.catalina.valves.CertificatesValve.invoke",
          "source": "CertificatesValve .java:246"
        },
        {
          "method": "org.apache.catalina.core.StandardPipeline$StandardPipelineValveContext.invokeNext",
          "source": "StandardPipeline.java:641"
        },
        {
          "method": "org.apache.catalina.core.StandardPipeline.invoke",
          "source": "StandardPipeline.jav a:480"
        },
        {
          "method": "org.apache.catalina.core.ContainerBase.invoke",
          "source": "ContainerBase.java:995"
        },
        {
          "method": "org.apache.catalina.core.StandardContext.invoke",
          "source": "StandardContext.java: 2422"
        },
        {
          "method": "org.apache.catalina.core.StandardHostValve.invoke",
          "source": "StandardHostValve.j ava:180"
        },
        {
          "method": "org.apache.catalina.core.StandardPipeline$StandardPipelineValveContext.invokeNext",
          "source": "StandardPipeline.java:643"
        },
        {
          "method": "org.apache.catalina.valves.ErrorDispatcherValve.invoke",
          "source": "ErrorDispatche rValve.java:171"
        },
        {
          "method": "org.apache.catalina.core.StandardPipeline$StandardPipelineValveContext.invokeNext",
          "source": "StandardPipeline.java:641"
        },
        {
          "method": "org.eclipse.tomcat.internal.EclipseErrorReportValve.invoke",
          "source": "EclipseErr orReportValve.java:153"
        },
        {
          "method": "org.apache.catalina.core.StandardPipeline$StandardPipelineValveContext.invokeNext",
          "source": "StandardPipeline.java:641"
        },
        {
          "method": "org.apache.catalina.core.StandardPipeline.invoke",
          "source": "StandardPipeline.jav a:480"
        },
        {
          "method": "org.apache.catalina.core.ContainerBase.invoke",
          "source": "ContainerBase.java:995"
        },
        {
          "method": "org.apache.catalina.core.StandardEngineValve.invoke",
          "source": "StandardEngineVal ve.java:174"
        },
        {
          "method": "org.apache.catalina.core.StandardPipeline$StandardPipelineValveContext.invokeNext",
          "source": "StandardPipeline.java:643"
        },
        {
          "method": "org.apache.catalina.core.StandardPipeline.invoke",
          "source": "StandardPipeline.jav a:480"
        },
        {
          "method": "org.apache.catalina.core.ContainerBase.invoke",
          "source": "ContainerBase.java:995"
        },
        {
          "method": "org.apache.coyote.tomcat4.CoyoteAdapter.service",
          "source": "CoyoteAdapter.java:19 9"
        },
        {
          "method": "org.apache.coyote.http11.Http11Processor.process",
          "source": "Http11Processor.java :828"
        },
        {
          "method": "org.apache.coyote.http11.Http11Protocol$Http11ConnectionHandler.processConnection",
          "source": "Http11Protocol.java:700"
        },
        {
          "method": "org.apache.tomcat.util.net.TcpWorkerThread.runIt",
          "source": "PoolTcpEndpoint.java :584"
        },
        {
          "method": "org.apache.tomcat.util.threads.ThreadPool$ControlRunnable.run",
          "source": "ThreadP ool.java:683"
        },
        {
          "method": "java.lang.Thread.run",
          "source": "Thread.java:595"
        }
      ],
      "number": 0,
      "commentIndex": 0,
      "bugId": "172737",
      "duplicateId": "172636",
      "date": "2007-02-02T23:13:26+01:00",
      "product": "BIRT",
      "component": "Report Engine",
      "severity": "normal"
    }
  ],
  "groupId": "172636",
  "bugId": "172737",
  "duplicateId": "172636",
  "date": "2007-02-02T23:13:26+01:00",
  "product": "BIRT",
  "component": "Report Engine",
  "severity": "normal"
}