{
  "comments": [
    "Hi, \n\nI have a RCP 3.2 based application (M20060628-1325) that sometimes experience the following error when updating:\n\nava.lang.IllegalStateException: zip file closed\n        at java.util.zip.ZipFile.ensureOpen(ZipFile.java:518)\n        at java.util.zip.ZipFile.access$400(ZipFile.java:35)\n        at java.util.zip.ZipFile$3.hasMoreElements(ZipFile.java:411)\n        at java.util.jar.JarFile$1.hasMoreElements(JarFile.java:218)\n        at org.eclipse.update.core.JarContentReference.unpack(JarContentReference.java:185)\n        at org.eclipse.update.internal.core.FeaturePackagedContentProvider.getFeatureManifestReference(FeaturePackagedContentProvider.java:91)\n        at org.eclipse.update.internal.core.FeaturePackagedFactory.createFeature(FeaturePackagedFactory.java:39)\n        at org.eclipse.update.core.Site.createFeature(Site.java:527)\n        at org.eclipse.update.core.FeatureReference.createFeature(FeatureReference.java:122)\n        at org.eclipse.update.core.FeatureReference.getFeature(FeatureReference.java:110)\n        at org.eclipse.update.core.FeatureReference.getFeature(FeatureReference.java:97)\n        at org.eclipse.update.internal.search.SiteSearchCategory$FeatureDownloader.run(SiteSearchCategory.java:224)\n        at java.lang.Thread.run(Thread.java:595)\norg.eclipse.core.runtime.CoreException: Error creating feature \"http://10.20.20.200:4062/client/features/com.mycompany.application.feature_0.9.5.jar\". [zip file closed]\n\nI have tried to debug but I have not been able to see who is closing the zip-file when JarContentReference.unpack() is iterating through it.\n\nThe exception does not occur all of the time, not on all features in the update-site and it does not occur on the same feature every time. I just love these kind of errors..\n\nRegards, \n\nMarcus Ludvigson"
  ],
  "commentCreationDates": [
    "2007-02-08T14:42:10+01:00"
  ],
  "traces": [
    {
      "exceptionType": "ava.lang.IllegalStateException",
      "message": "zip file closed",
      "elements": [
        {
          "method": "java.util.zip.ZipFile.ensureOpen",
          "source": "ZipFile.java:518"
        },
        {
          "method": "java.util.zip.ZipFile.access$400",
          "source": "ZipFile.java:35"
        },
        {
          "method": "java.util.zip.ZipFile$3.hasMoreElements",
          "source": "ZipFile.java:411"
        },
        {
          "method": "java.util.jar.JarFile$1.hasMoreElements",
          "source": "JarFile.java:218"
        },
        {
          "method": "org.eclipse.update.core.JarContentReference.unpack",
          "source": "JarContentReference.java:185"
        },
        {
          "method": "org.eclipse.update.internal.core.FeaturePackagedContentProvider.getFeatureManifestReference",
          "source": "FeaturePackagedContentProvider.java:91"
        },
        {
          "method": "org.eclipse.update.internal.core.FeaturePackagedFactory.createFeature",
          "source": "FeaturePackagedFactory.java:39"
        },
        {
          "method": "org.eclipse.update.core.Site.createFeature",
          "source": "Site.java:527"
        },
        {
          "method": "org.eclipse.update.core.FeatureReference.createFeature",
          "source": "FeatureReference.java:122"
        },
        {
          "method": "org.eclipse.update.core.FeatureReference.getFeature",
          "source": "FeatureReference.java:110"
        },
        {
          "method": "org.eclipse.update.core.FeatureReference.getFeature",
          "source": "FeatureReference.java:97"
        },
        {
          "method": "org.eclipse.update.internal.search.SiteSearchCategory$FeatureDownloader.run",
          "source": "SiteSearchCategory.java:224"
        },
        {
          "method": "java.lang.Thread.run",
          "source": "Thread.java:595"
        }
      ],
      "number": 0,
      "commentIndex": 0,
      "bugId": "173450",
      "date": "2007-02-08T14:42:10+01:00",
      "product": "Platform",
      "component": "Update",
      "severity": "critical"
    }
  ],
  "groupId": "173450",
  "bugId": "173450",
  "date": "2007-02-08T14:42:10+01:00",
  "product": "Platform",
  "component": "Update",
  "severity": "critical"
}