{
  "comments": [
    "Using Build F1 (2020521)\nRedhat 7.2, GTK2, KDE 2.2-10\n\n(This only happens in GTK2)\n\n1. Clear workspace (may not be necessary)\n2. In Eclipse, click the \"Open a prespective\" icon on the left toolbar.\n3. Select \"Other..\" and a dialog will pop-up\n4. Double-click (important) on any perspective (say, java)\n5. The perspective will come up and immediately after an internal error shows up\n\nNOTE: This will NOT happen if you select one then click \u0027Ok\u0027, only when you\ndouble-click. \n\nThe error dialog says:\nInternal Error\nAn SWT error has occured.\nIt is recommended to exit the workbench.\nSubsequent errors may happen and may terminate the workbench without warning.\nSee error log for details.\nExit Workspace? (Y/N)\n\nThe following message is printed to standard output:\nUnhandled exception caught in event loop.\nReason:\nWidget is disposed\n\nThe log file (shown below) refers to a Table. I\u0027m assuming this table is the one\nI double clicked on to select the perspective. (I could be wrong)\n\nThe .log file contains the following:\n!SESSION May 23, 2002 14:03:56.368 ---------------------------------------------\njava.fullversion\u003dJ2RE 1.3.1 IBM build cxia32131-20020410 (JIT enabled: jitc)\nBootLoader constants: OS\u003dlinux, ARCH\u003dx86, WS\u003dgtk, NL\u003den_US\nCommand-line arguments: -os linux -ws gtk -arch x86 -feature\norg.eclipse.platform -install\nfile:/bluebird/teamswt/cdentrem/eclipse0521gtk/eclipse/\n!ENTRY org.eclipse.core.resources 1 4 May 23, 2002 14:03:56.370\n!MESSAGE Reference action not found: additions\n!ENTRY org.eclipse.core.resources 1 4 May 23, 2002 14:04:10.100\n!MESSAGE Unhandled exception caught in event loop.\n!ENTRY org.eclipse.ui 4 0 May 23, 2002 14:04:10.103\n!MESSAGE Widget is disposed\n!STACK 0\norg.eclipse.swt.SWTError: Widget is disposed\n        at org.eclipse.swt.widgets.Widget.error(Widget.java:289)\n        at org.eclipse.swt.widgets.Control.getDisplay(Control.java(Compiled\nCode))\n        at org.eclipse.swt.widgets.Widget.checkWidget(Widget.java(Compiled\nCode))\n        at org.eclipse.swt.widgets.Widget.checkWidget(Widget.java(Compiled\nCode))\n        at org.eclipse.swt.widgets.Table.getColumnCount(Table.java:484)\n        at\norg.eclipse.jface.viewers.TableViewer$2.getColumnCount(TableViewer.java:347)\n        at\norg.eclipse.jface.viewers.TableViewerImpl.activateCellEditor(TableViewerImpl.java:79)\n        at\norg.eclipse.jface.viewers.TableViewerImpl.access$1(TableViewerImpl.java:73)\n        at\norg.eclipse.jface.viewers.TableViewerImpl$4.run(TableViewerImpl.java:249)\n        at org.eclipse.swt.widgets.RunnableLock.run(RunnableLock.java:29)\n        at\norg.eclipse.swt.widgets.Synchronizer.runAsyncMessages(Synchronizer.java:93)\n        at org.eclipse.swt.widgets.Display.runAsyncMessages(Display.java:1356)\n        at org.eclipse.swt.widgets.Display.readAndDispatch(Display.java:1226)\n        at org.eclipse.ui.internal.Workbench.runEventLoop(Workbench.java:1085)\n        at org.eclipse.ui.internal.Workbench.run(Workbench.java:1068)\n        at\norg.eclipse.core.internal.boot.InternalBootLoader.run(InternalBootLoader.java:739)\n        at org.eclipse.core.boot.BootLoader.run(BootLoader.java:462)\n        at java.lang.reflect.Method.invoke(Native Method)\n        at org.eclipse.core.launcher.Main.basicRun(Main.java:200)\n        at org.eclipse.core.launcher.Main.run(Main.java:643)\n        at org.eclipse.core.launcher.Main.main(Main.java:476)",
    "Curtis, can you repeat this?\n",
    "It doesn\u0027t happen in F2.",
    "Since it\u0027s no longer repeatable, we will not do any more investigation of \nthis for R2.0. However, Boris thinks there may still be an underlying error \ncase which we should handle, so I\u0027m marking this as LATER to remind \nus to look at it again.\n",
    "Post 2.0. Re-opening bug reports for review.",
    "I am assuming this is a bug in the old implementation of Table (GtkCList) and\nI am going to close this bug. Check Bug#25212."
  ],
  "commentCreationDates": [
    "2002-05-23T20:05:49+02:00",
    "2002-06-03T20:46:00+02:00",
    "2002-06-03T21:12:09+02:00",
    "2002-06-03T21:24:47+02:00",
    "2002-09-10T16:34:55+02:00",
    "2002-10-23T08:44:23+02:00"
  ],
  "traces": [
    {
      "exceptionType": "org.eclipse.swt.SWTError",
      "message": "Widget is disposed",
      "elements": [
        {
          "method": "org.eclipse.swt.widgets.Widget.error",
          "source": "Widget.java:289"
        },
        {
          "method": "org.eclipse.swt.widgets.Control.getDisplay",
          "source": "Control.java(Compiled Code)"
        },
        {
          "method": "org.eclipse.swt.widgets.Widget.checkWidget",
          "source": "Widget.java(Compiled Code)"
        },
        {
          "method": "org.eclipse.swt.widgets.Widget.checkWidget",
          "source": "Widget.java(Compiled Code)"
        },
        {
          "method": "org.eclipse.swt.widgets.Table.getColumnCount",
          "source": "Table.java:484"
        },
        {
          "method": "org.eclipse.jface.viewers.TableViewer$2.getColumnCount",
          "source": "TableViewer.java:347"
        },
        {
          "method": "org.eclipse.jface.viewers.TableViewerImpl.activateCellEditor",
          "source": "TableViewerImpl.java:79"
        },
        {
          "method": "org.eclipse.jface.viewers.TableViewerImpl.access$1",
          "source": "TableViewerImpl.java:73"
        },
        {
          "method": "org.eclipse.jface.viewers.TableViewerImpl$4.run",
          "source": "TableViewerImpl.java:249"
        },
        {
          "method": "org.eclipse.swt.widgets.RunnableLock.run",
          "source": "RunnableLock.java:29"
        },
        {
          "method": "org.eclipse.swt.widgets.Synchronizer.runAsyncMessages",
          "source": "Synchronizer.java:93"
        },
        {
          "method": "org.eclipse.swt.widgets.Display.runAsyncMessages",
          "source": "Display.java:1356"
        },
        {
          "method": "org.eclipse.swt.widgets.Display.readAndDispatch",
          "source": "Display.java:1226"
        },
        {
          "method": "org.eclipse.ui.internal.Workbench.runEventLoop",
          "source": "Workbench.java:1085"
        },
        {
          "method": "org.eclipse.ui.internal.Workbench.run",
          "source": "Workbench.java:1068"
        },
        {
          "method": "org.eclipse.core.internal.boot.InternalBootLoader.run",
          "source": "InternalBootLoader.java:739"
        },
        {
          "method": "org.eclipse.core.boot.BootLoader.run",
          "source": "BootLoader.java:462"
        },
        {
          "method": "java.lang.reflect.Method.invoke",
          "source": "Native Method"
        },
        {
          "method": "org.eclipse.core.launcher.Main.basicRun",
          "source": "Main.java:200"
        },
        {
          "method": "org.eclipse.core.launcher.Main.run",
          "source": "Main.java:643"
        },
        {
          "method": "org.eclipse.core.launcher.Main.main",
          "source": "Main.java:476"
        }
      ],
      "number": 0,
      "commentIndex": 0,
      "bugId": "17428",
      "date": "2002-05-23T20:05:49+02:00",
      "product": "Platform",
      "component": "SWT",
      "severity": "normal"
    }
  ],
  "groupId": "17428",
  "bugId": "17428",
  "date": "2002-05-23T20:05:49+02:00",
  "product": "Platform",
  "component": "SWT",
  "severity": "normal"
}