{
  "comments": [
    "Below a snippet from a customers logfile, I wasn\u0027t able to exactly reproduce\nthis exception, but apparantly it is somehow possible that when the\nBuildConsolePage.setInitialSelection() method is called the getConsole().getConsoleManager().getLastBuiltProject() returns null.\n\n ...\n        at org.eclipse.core.launcher.Main.invokeFramework(Main.java:336)\n        at org.eclipse.core.launcher.Main.basicRun(Main.java:280)\n        at org.eclipse.core.launcher.Main.run(Main.java:977)\n        at org.eclipse.core.launcher.Main.main(Main.java:952)\nCaused by: org.eclipse.jface.util.Assert$AssertionFailedException: null argument;\n        at org.eclipse.jface.util.Assert.isNotNull(Assert.java:150)\n        at org.eclipse.jface.util.Assert.isNotNull(Assert.java:126)\n        at org.eclipse.jface.viewers.StructuredSelection.\u003cinit\u003e(StructuredSelection.java:66)\n        at org.eclipse.cdt.internal.ui.buildconsole.BuildConsolePage.setInitialSelection(BuildConsolePage.java:353)\n        at org.eclipse.cdt.internal.ui.buildconsole.BuildConsolePage.createControl(BuildConsolePage.java:203)\n        at org.eclipse.ui.internal.console.ConsoleView.doCreatePage(ConsoleView.java:276)\n        at org.eclipse.ui.part.PageBookView.createPage(PageBookView.java:399)\n        at org.eclipse.ui.part.PageBookView.partActivated(PageBookView.java:743)\n        at org.eclipse.ui.internal.console.ConsoleView$1.run(ConsoleView.java:347)\n        at org.eclipse.swt.widgets.RunnableLock.run(RunnableLock.java:35)\n        at org.eclipse.swt.widgets.Synchronizer.runAsyncMessages(Synchronizer.java:123)\n        ... 20 more",
    "Created an attachment (id\u003d59127)\nPatch proposal\n\n",
    "Patch applied. Thanks!",
    "*** Bug 146830 has been marked as a duplicate of this bug. ***"
  ],
  "commentCreationDates": [
    "2007-02-16T11:35:31+01:00",
    "2007-02-16T11:37:20+01:00",
    "2007-05-16T21:56:12+02:00",
    "2007-06-19T16:32:45+02:00"
  ],
  "traces": [
    {
      "exceptionType": "org.eclipse.jface.util.Assert$AssertionFailedException",
      "message": "null argument;",
      "elements": [
        {
          "method": "org.eclipse.jface.util.Assert.isNotNull",
          "source": "Assert.java:150"
        },
        {
          "method": "org.eclipse.jface.util.Assert.isNotNull",
          "source": "Assert.java:126"
        },
        {
          "method": "org.eclipse.jface.viewers.StructuredSelection.\u003cinit\u003e",
          "source": "StructuredSelection.java:66"
        },
        {
          "method": "org.eclipse.cdt.internal.ui.buildconsole.BuildConsolePage.setInitialSelection",
          "source": "BuildConsolePage.java:353"
        },
        {
          "method": "org.eclipse.cdt.internal.ui.buildconsole.BuildConsolePage.createControl",
          "source": "BuildConsolePage.java:203"
        },
        {
          "method": "org.eclipse.ui.internal.console.ConsoleView.doCreatePage",
          "source": "ConsoleView.java:276"
        },
        {
          "method": "org.eclipse.ui.part.PageBookView.createPage",
          "source": "PageBookView.java:399"
        },
        {
          "method": "org.eclipse.ui.part.PageBookView.partActivated",
          "source": "PageBookView.java:743"
        },
        {
          "method": "org.eclipse.ui.internal.console.ConsoleView$1.run",
          "source": "ConsoleView.java:347"
        },
        {
          "method": "org.eclipse.swt.widgets.RunnableLock.run",
          "source": "RunnableLock.java:35"
        },
        {
          "method": "org.eclipse.swt.widgets.Synchronizer.runAsyncMessages",
          "source": "Synchronizer.java:123"
        }
      ],
      "number": 0,
      "commentIndex": 0,
      "bugId": "174425",
      "date": "2007-02-16T11:35:31+01:00",
      "product": "CDT",
      "component": "cdt-core",
      "severity": "normal"
    }
  ],
  "groupId": "174425",
  "bugId": "174425",
  "date": "2007-02-16T11:35:31+01:00",
  "product": "CDT",
  "component": "cdt-core",
  "severity": "normal"
}