{
  "comments": [
    "Received the following DB sql errors running the latest build Aperi-20070220-084443.zip using either DB2 or derby as db\n\nDELETE FROM T_VIEW_HOST2PORT WHERE HOST_ID \u003d ?\nINSERT INTO T_VIEW_HOST2PORT SELECT PORT_ID, HOST_ID, HOST_URL FROM T_VIEW_HOST2\nPORT_TEMP2 AND HOST_ID \u003d ?\nINSERT INTO T_VIEW_HOST2PORT SELECT PORT_ID, HOST_ID, HOST_URL FROM T_VIEW_HOST2\nPORT_TEMP1 WHERE PORT_ID NOT IN (SELECT PORT_ID FROM T_VIEW_HOST2PORT_TEMP2) AND\n HOST_ID \u003d ?\norg.apache.derby.client.am.SqlException: Syntax error: Encountered \"AND\" at line\n 1, column 92.\n        at org.apache.derby.client.am.Statement.completeSqlca(Unknown Source)\n        at org.apache.derby.client.net.NetStatementReply.parsePrepareError(Unkno\nwn Source)\n        at org.apache.derby.client.net.NetStatementReply.parsePRPSQLSTTreply(Unk\nnown Source)\n        at org.apache.derby.client.net.NetStatementReply.readPrepareDescribeOutp\nut(Unknown Source)\n        at org.apache.derby.client.net.StatementReply.readPrepareDescribeOutput(\nUnknown Source)\n        at org.apache.derby.client.net.NetStatement.readPrepareDescribeOutput_(U\nnknown Source)\n        at org.apache.derby.client.am.Statement.readPrepareDescribeOutput(Unknow\nn Source)\n        at org.apache.derby.client.am.PreparedStatement.readPrepareDescribeInput\nOutput(Unknown Source)\n        at org.apache.derby.client.am.PreparedStatement.flowPrepareDescribeInput\nOutput(Unknown Source)\n        at org.apache.derby.client.am.PreparedStatement.prepare(Unknown Source)\n        at org.apache.derby.client.am.Connection.prepareStatementX(Unknown Sourc\ne)\n        at org.apache.derby.client.am.Connection.prepareStatement(Unknown Source\n)\n        at org.eclipse.aperi.infrastructure.database.DBConnection.prepareStateme\nnt(DBConnection.java:418)\n        at org.eclipse.aperi.common.dbaccess.ViewReportTablesUpdater.handleUpdat\ne(ViewReportTablesUpdater.java:1633)\n        at org.eclipse.aperi.common.dbaccess.ViewReportTablesUpdater.updateHostT\nables(ViewReportTablesUpdater.java:1365)\n        at org.eclipse.aperi.common.dbaccess.ViewReportTablesUpdater.updateOther\nTables(ViewReportTablesUpdater.java:1275)\n        at org.eclipse.aperi.common.dbaccess.ViewReportTablesUpdater.updateViewT\nables(ViewReportTablesUpdater.java:1130)\n        at org.eclipse.aperi.common.dbaccess.ViewReportTablesUpdater.processView\n(ViewReportTablesUpdater.java:1038)\n        at org.eclipse.aperi.infrastructure.history.detectability.ChangeDetectio\nn.startNew(ChangeDetection.java:857)\n        at org.eclipse.aperi.discovery.parser.Processor.end(Processor.java:273)\n        at org.eclipse.aperi.discovery.parser.TSANMLegacyParser$Worker.parse(TSA\nNMLegacyParser.java:333)\n        at org.eclipse.aperi.discovery.parser.Parser.processJob(Parser.java:17)\n        at org.eclipse.aperi.discovery.parser.TSANMLegacyParser.run(TSANMLegacyP\narser.java:131)\nDELETE FROM T_VIEW_HOST2PORT_TEMP1 WHERE PORT_ID \u003d ?\nINSERT INTO T_VIEW_HOST2PORT_TEMP1  SELECT CAST (NULL AS {0}) HOST_ID, PORT.HOST\n_URL_BY_SUBSYSTEM HOST_URL, PORT.PORT_ID PORT_ID FROM T_RES_PORT PORT LEFT OUTER\n JOIN T_RES_NODE AS NODE ON (PORT.NODE_ID \u003d NODE.NODE_ID) WHERE PORT.NODE_ID IS\nNULL and PORT.HOST_URL_BY_SUBSYSTEM IS NOT NULL AND PORT.PORT_ID \u003d ?\norg.apache.derby.client.am.SqlException: Syntax error: Encountered \"\" at line 1,\n column 58.\n        at org.apache.derby.client.am.Statement.completeSqlca(Unknown Source)\n        at org.apache.derby.client.net.NetStatementReply.parsePrepareError(Unkno\nwn Source)\n        at org.apache.derby.client.net.NetStatementReply.parsePRPSQLSTTreply(Unk\nnown Source)\n        at org.apache.derby.client.net.NetStatementReply.readPrepareDescribeOutp\nut(Unknown Source)\n        at org.apache.derby.client.net.StatementReply.readPrepareDescribeOutput(\nUnknown Source)\n        at org.apache.derby.client.net.NetStatement.readPrepareDescribeOutput_(U\nnknown Source)\n        at org.apache.derby.client.am.Statement.readPrepareDescribeOutput(Unknow\nn Source)\n        at org.apache.derby.client.am.PreparedStatement.readPrepareDescribeInput\nOutput(Unknown Source)\n        at org.apache.derby.client.am.PreparedStatement.flowPrepareDescribeInput\nOutput(Unknown Source)\n        at org.apache.derby.client.am.PreparedStatement.prepare(Unknown Source)\n        at org.apache.derby.client.am.Connection.prepareStatementX(Unknown Sourc\ne)\n        at org.apache.derby.client.am.Connection.prepareStatement(Unknown Source\n)\n        at org.eclipse.aperi.infrastructure.database.DBConnection.prepareStateme\nnt(DBConnection.java:418)\n        at org.eclipse.aperi.common.dbaccess.ViewReportTablesUpdater.handleUpdat\ne(ViewReportTablesUpdater.java:1633)\n        at org.eclipse.aperi.common.dbaccess.ViewReportTablesUpdater.updateOther\nTables(ViewReportTablesUpdater.java:1222)\n        at org.eclipse.aperi.common.dbaccess.ViewReportTablesUpdater.updateViewT\nables(ViewReportTablesUpdater.java:1130)\n        at org.eclipse.aperi.common.dbaccess.ViewReportTablesUpdater.processView\n(ViewReportTablesUpdater.java:1034)\n        at org.eclipse.aperi.infrastructure.history.detectability.ChangeDetectio\nn.startNew(ChangeDetection.java:857)\n        at org.eclipse.aperi.discovery.parser.Processor.end(Processor.java:273)\n        at org.eclipse.aperi.discovery.parser.TSANMLegacyParser$Worker.parse(TSA\nNMLegacyParser.java:333)\n        at org.eclipse.aperi.discovery.parser.Parser.processJob(Parser.java:17)\n        at org.eclipse.aperi.discovery.parser.TSANMLegacyParser.run(TSANMLegacyP\narser.java:131)\nDELETE FROM T_VIEW_HOST2PORT WHERE HOST_ID \u003d ?\nINSERT INTO T_VIEW_HOST2PORT SELECT PORT_ID, HOST_ID, HOST_URL FROM T_VIEW_HOST2\nPORT_TEMP2 AND HOST_ID \u003d ?\nINSERT INTO T_VIEW_HOST2PORT SELECT PORT_ID, HOST_ID, HOST_URL FROM T_VIEW_HOST2\nPORT_TEMP1 WHERE PORT_ID NOT IN (SELECT PORT_ID FROM T_VIEW_HOST2PORT_TEMP2) AND\n HOST_ID \u003d ?\norg.apache.derby.client.am.SqlException: Syntax error: Encountered \"AND\" at line\n 1, column 92.\n        at org.apache.derby.client.am.Statement.completeSqlca(Unknown Source)\n        at org.apache.derby.client.net.NetStatementReply.parsePrepareError(Unkno\nwn Source)\n        at org.apache.derby.client.net.NetStatementReply.parsePRPSQLSTTreply(Unk\nnown Source)\n        at org.apache.derby.client.net.NetStatementReply.readPrepareDescribeOutp\nut(Unknown Source)\n        at org.apache.derby.client.net.StatementReply.readPrepareDescribeOutput(\nUnknown Source)\n        at org.apache.derby.client.net.NetStatement.readPrepareDescribeOutput_(U\nnknown Source)\n        at org.apache.derby.client.am.Statement.readPrepareDescribeOutput(Unknow\nn Source)\n        at org.apache.derby.client.am.PreparedStatement.readPrepareDescribeInput\nOutput(Unknown Source)\n        at org.apache.derby.client.am.PreparedStatement.flowPrepareDescribeInput\nOutput(Unknown Source)\n        at org.apache.derby.client.am.PreparedStatement.prepare(Unknown Source)\n        at org.apache.derby.client.am.Connection.prepareStatementX(Unknown Sourc\ne)\n        at org.apache.derby.client.am.Connection.prepareStatement(Unknown Source\n)\n        at org.eclipse.aperi.infrastructure.database.DBConnection.prepareStateme\nnt(DBConnection.java:418)\n        at org.eclipse.aperi.common.dbaccess.ViewReportTablesUpdater.handleUpdat\ne(ViewReportTablesUpdater.java:1633)\n        at org.eclipse.aperi.common.dbaccess.ViewReportTablesUpdater.updateHostT\nables(ViewReportTablesUpdater.java:1365)\n        at org.eclipse.aperi.common.dbaccess.ViewReportTablesUpdater.updateOther\nTables(ViewReportTablesUpdater.java:1275)\n        at org.eclipse.aperi.common.dbaccess.ViewReportTablesUpdater.updateViewT\nables(ViewReportTablesUpdater.java:1130)\n        at org.eclipse.aperi.common.dbaccess.ViewReportTablesUpdater.processView\n(ViewReportTablesUpdater.java:1036)\n        at org.eclipse.aperi.infrastructure.history.detectability.ChangeDetectio\nn.startNew(ChangeDetection.java:857)\n        at org.eclipse.aperi.discovery.parser.Processor.end(Processor.java:273)\n        at org.eclipse.aperi.discovery.parser.TSANMLegacyParser$Worker.parse(TSA\nNMLegacyParser.java:333)\n        at org.eclipse.aperi.discovery.parser.Parser.processJob(Parser.java:17)\n        at org.eclipse.aperi.discovery.parser.TSANMLegacyParser.run(TSANMLegacyP\narser.java:131)\nDELETE FROM T_VIEW_HOST2PORT WHERE HOST_ID \u003d ?\nINSERT INTO T_VIEW_HOST2PORT SELECT PORT_ID, HOST_ID, HOST_URL FROM T_VIEW_HOST2\nPORT_TEMP2 AND HOST_ID \u003d ?\nINSERT INTO T_VIEW_HOST2PORT SELECT PORT_ID, HOST_ID, HOST_URL FROM T_VIEW_HOST2\nPORT_TEMP1 WHERE PORT_ID NOT IN (SELECT PORT_ID FROM T_VIEW_HOST2PORT_TEMP2) AND\n HOST_ID \u003d ?\norg.apache.derby.client.am.SqlException: Syntax error: Encountered \"AND\" at line\n 1, column 92.\n        at org.apache.derby.client.am.Statement.completeSqlca(Unknown Source)\n        at org.apache.derby.client.net.NetStatementReply.parsePrepareError(Unkno\nwn Source)\n        at org.apache.derby.client.net.NetStatementReply.parsePRPSQLSTTreply(Unk\nnown Source)\n        at org.apache.derby.client.net.NetStatementReply.readPrepareDescribeOutp\nut(Unknown Source)\n        at org.apache.derby.client.net.StatementReply.readPrepareDescribeOutput(\nUnknown Source)\n        at org.apache.derby.client.net.NetStatement.readPrepareDescribeOutput_(U\nnknown Source)\n        at org.apache.derby.client.am.Statement.readPrepareDescribeOutput(Unknow\nn Source)\n        at org.apache.derby.client.am.PreparedStatement.readPrepareDescribeInput\nOutput(Unknown Source)\n        at org.apache.derby.client.am.PreparedStatement.flowPrepareDescribeInput\nOutput(Unknown Source)\n        at org.apache.derby.client.am.PreparedStatement.prepare(Unknown Source)\n        at org.apache.derby.client.am.Connection.prepareStatementX(Unknown Sourc\ne)\n        at org.apache.derby.client.am.Connection.prepareStatement(Unknown Source\n)\n        at org.eclipse.aperi.infrastructure.database.DBConnection.prepareStateme\nnt(DBConnection.java:418)\n        at org.eclipse.aperi.common.dbaccess.ViewReportTablesUpdater.handleUpdat\ne(ViewReportTablesUpdater.java:1633)\n        at org.eclipse.aperi.common.dbaccess.ViewReportTablesUpdater.updateHostT\nables(ViewReportTablesUpdater.java:1365)\n        at org.eclipse.aperi.common.dbaccess.ViewReportTablesUpdater.updateOther\nTables(ViewReportTablesUpdater.java:1275)\n        at org.eclipse.aperi.common.dbaccess.ViewReportTablesUpdater.updateViewT\nables(ViewReportTablesUpdater.java:1130)\n        at org.eclipse.aperi.common.dbaccess.ViewReportTablesUpdater.processView\n(ViewReportTablesUpdater.java:1038)\n        at org.eclipse.aperi.infrastructure.history.detectability.ChangeDetectio\nn.complete(ChangeDetection.java:1585)\n        at org.eclipse.aperi.discovery.parser.Processor.end(Processor.java:277)\n        at org.eclipse.aperi.discovery.parser.TSANMLegacyParser$Worker.parse(TSA\nNMLegacyParser.java:333)\n        at org.eclipse.aperi.discovery.parser.Parser.processJob(Parser.java:17)\n        at org.eclipse.aperi.discovery.parser.TSANMLegacyParser.run(TSANMLegacyP\narser.java:131)\nDELETE FROM T_VIEW_HOST2PORT_TEMP1 WHERE PORT_ID \u003d ?\nINSERT INTO T_VIEW_HOST2PORT_TEMP1  SELECT CAST (NULL AS {0}) HOST_ID, PORT.HOST\n_URL_BY_SUBSYSTEM HOST_URL, PORT.PORT_ID PORT_ID FROM T_RES_PORT PORT LEFT OUTER\n JOIN T_RES_NODE AS NODE ON (PORT.NODE_ID \u003d NODE.NODE_ID) WHERE PORT.NODE_ID IS\nNULL and PORT.HOST_URL_BY_SUBSYSTEM IS NOT NULL AND PORT.PORT_ID \u003d ?\norg.apache.derby.client.am.SqlException: Syntax error: Encountered \"\" at line 1,\n column 58.\n        at org.apache.derby.client.am.Statement.completeSqlca(Unknown Source)\n        at org.apache.derby.client.net.NetStatementReply.parsePrepareError(Unkno\nwn Source)\n        at org.apache.derby.client.net.NetStatementReply.parsePRPSQLSTTreply(Unk\nnown Source)\n        at org.apache.derby.client.net.NetStatementReply.readPrepareDescribeOutp\nut(Unknown Source)\n        at org.apache.derby.client.net.StatementReply.readPrepareDescribeOutput(\nUnknown Source)\n        at org.apache.derby.client.net.NetStatement.readPrepareDescribeOutput_(U\nnknown Source)\n        at org.apache.derby.client.am.Statement.readPrepareDescribeOutput(Unknow\nn Source)\n        at org.apache.derby.client.am.PreparedStatement.readPrepareDescribeInput\nOutput(Unknown Source)\n        at org.apache.derby.client.am.PreparedStatement.flowPrepareDescribeInput\nOutput(Unknown Source)\n        at org.apache.derby.client.am.PreparedStatement.prepare(Unknown Source)\n        at org.apache.derby.client.am.Connection.prepareStatementX(Unknown Sourc\ne)\n        at org.apache.derby.client.am.Connection.prepareStatement(Unknown Source\n)\n        at org.eclipse.aperi.infrastructure.database.DBConnection.prepareStateme\nnt(DBConnection.java:418)\n        at org.eclipse.aperi.common.dbaccess.ViewReportTablesUpdater.handleUpdat\ne(ViewReportTablesUpdater.java:1633)\n        at org.eclipse.aperi.common.dbaccess.ViewReportTablesUpdater.updateOther\nTables(ViewReportTablesUpdater.java:1222)\n        at org.eclipse.aperi.common.dbaccess.ViewReportTablesUpdater.updateViewT\nables(ViewReportTablesUpdater.java:1130)\n        at org.eclipse.aperi.common.dbaccess.ViewReportTablesUpdater.processView\n(ViewReportTablesUpdater.java:1034)\n        at org.eclipse.aperi.infrastructure.history.detectability.ChangeDetectio\nn.complete(ChangeDetection.java:1585)\n        at org.eclipse.aperi.discovery.parser.Processor.end(Processor.java:277)\n        at org.eclipse.aperi.discovery.parser.TSANMLegacyParser$Worker.parse(TSA\nNMLegacyParser.java:333)\n        at org.eclipse.aperi.discovery.parser.Parser.processJob(Parser.java:17)\n        at org.eclipse.aperi.discovery.parser.TSANMLegacyParser.run(TSANMLegacyP\narser.java:131)\nDELETE FROM T_VIEW_HOST2PORT WHERE HOST_ID \u003d ?\nINSERT INTO T_VIEW_HOST2PORT SELECT PORT_ID, HOST_ID, HOST_URL FROM T_VIEW_HOST2\nPORT_TEMP2 AND HOST_ID \u003d ?\nINSERT INTO T_VIEW_HOST2PORT SELECT PORT_ID, HOST_ID, HOST_URL FROM T_VIEW_HOST2\nPORT_TEMP1 WHERE PORT_ID NOT IN (SELECT PORT_ID FROM T_VIEW_HOST2PORT_TEMP2) AND\n HOST_ID \u003d ?\norg.apache.derby.client.am.SqlException: Syntax error: Encountered \"AND\" at line\n 1, column 92.\n        at org.apache.derby.client.am.Statement.completeSqlca(Unknown Source)\n        at org.apache.derby.client.net.NetStatementReply.parsePrepareError(Unkno\nwn Source)\n        at org.apache.derby.client.net.NetStatementReply.parsePRPSQLSTTreply(Unk\nnown Source)\n        at org.apache.derby.client.net.NetStatementReply.readPrepareDescribeOutp\nut(Unknown Source)\n        at org.apache.derby.client.net.StatementReply.readPrepareDescribeOutput(\nUnknown Source)\n        at org.apache.derby.client.net.NetStatement.readPrepareDescribeOutput_(U\nnknown Source)\n        at org.apache.derby.client.am.Statement.readPrepareDescribeOutput(Unknow\nn Source)\n        at org.apache.derby.client.am.PreparedStatement.readPrepareDescribeInput\nOutput(Unknown Source)\n        at org.apache.derby.client.am.PreparedStatement.flowPrepareDescribeInput\nOutput(Unknown Source)\n        at org.apache.derby.client.am.PreparedStatement.prepare(Unknown Source)\n        at org.apache.derby.client.am.Connection.prepareStatementX(Unknown Sourc\ne)\n        at org.apache.derby.client.am.Connection.prepareStatement(Unknown Source\n)\n        at org.eclipse.aperi.infrastructure.database.DBConnection.prepareStateme\nnt(DBConnection.java:418)\n        at org.eclipse.aperi.common.dbaccess.ViewReportTablesUpdater.handleUpdat\ne(ViewReportTablesUpdater.java:1633)\n        at org.eclipse.aperi.common.dbaccess.ViewReportTablesUpdater.updateHostT\nables(ViewReportTablesUpdater.java:1365)\n        at org.eclipse.aperi.common.dbaccess.ViewReportTablesUpdater.updateOther\nTables(ViewReportTablesUpdater.java:1275)\n        at org.eclipse.aperi.common.dbaccess.ViewReportTablesUpdater.updateViewT\nables(ViewReportTablesUpdater.java:1130)\n        at org.eclipse.aperi.common.dbaccess.ViewReportTablesUpdater.processView\n(ViewReportTablesUpdater.java:1036)\n        at org.eclipse.aperi.infrastructure.history.detectability.ChangeDetectio\nn.complete(ChangeDetection.java:1585)\n        at org.eclipse.aperi.discovery.parser.Processor.end(Processor.java:277)\n        at org.eclipse.aperi.discovery.parser.TSANMLegacyParser$Worker.parse(TSA\nNMLegacyParser.java:333)\n        at org.eclipse.aperi.discovery.parser.Parser.processJob(Parser.java:17)\n        at org.eclipse.aperi.discovery.parser.TSANMLegacyParser.run(TSANMLegacyP\narser.java:131)\nDELETE FROM T_VIEW_HOST2PORT WHERE HOST_ID \u003d ?\nINSERT INTO T_VIEW_HOST2PORT SELECT PORT_ID, HOST_ID, HOST_URL FROM T_VIEW_HOST2\nPORT_TEMP2 AND HOST_ID \u003d ?\nINSERT INTO T_VIEW_HOST2PORT SELECT PORT_ID, HOST_ID, HOST_URL FROM T_VIEW_HOST2\nPORT_TEMP1 WHERE PORT_ID NOT IN (SELECT PORT_ID FROM T_VIEW_HOST2PORT_TEMP2) AND\n HOST_ID \u003d ?\norg.apache.derby.client.am.SqlException: Syntax error: Encountered \"AND\" at line\n 1, column 92.\n        at org.apache.derby.client.am.Statement.completeSqlca(Unknown Source)\n        at org.apache.derby.client.net.NetStatementReply.parsePrepareError(Unkno\nwn Source)\n        at org.apache.derby.client.net.NetStatementReply.parsePRPSQLSTTreply(Unk\nnown Source)\n        at org.apache.derby.client.net.NetStatementReply.readPrepareDescribeOutp\nut(Unknown Source)\n        at org.apache.derby.client.net.StatementReply.readPrepareDescribeOutput(\nUnknown Source)\n        at org.apache.derby.client.net.NetStatement.readPrepareDescribeOutput_(U\nnknown Source)\n        at org.apache.derby.client.am.Statement.readPrepareDescribeOutput(Unknow\nn Source)\n        at org.apache.derby.client.am.PreparedStatement.readPrepareDescribeInput\nOutput(Unknown Source)\n        at org.apache.derby.client.am.PreparedStatement.flowPrepareDescribeInput\nOutput(Unknown Source)\n        at org.apache.derby.client.am.PreparedStatement.prepare(Unknown Source)\n        at org.apache.derby.client.am.Connection.prepareStatementX(Unknown Sourc\ne)\n        at org.apache.derby.client.am.Connection.prepareStatement(Unknown Source\n)\n        at org.eclipse.aperi.infrastructure.database.DBConnection.prepareStateme\nnt(DBConnection.java:418)\n        at org.eclipse.aperi.common.dbaccess.ViewReportTablesUpdater.handleUpdat\ne(ViewReportTablesUpdater.java:1633)\n        at org.eclipse.aperi.common.dbaccess.ViewReportTablesUpdater.updateHostT\nables(ViewReportTablesUpdater.java:1365)\n        at org.eclipse.aperi.common.dbaccess.ViewReportTablesUpdater.updateViewT\nables(ViewReportTablesUpdater.java:1119)\n        at org.eclipse.aperi.common.dbaccess.ViewReportTablesUpdater.processEnti\ntyView(ViewReportTablesUpdater.java:1057)\n        at org.eclipse.aperi.discovery.parser.Processor.end(Processor.java:300)\n        at org.eclipse.aperi.discovery.parser.TSANMLegacyParser$Worker.parse(TSA\nNMLegacyParser.java:333)\n        at org.eclipse.aperi.discovery.parser.Parser.processJob(Parser.java:17)\n        at org.eclipse.aperi.discovery.parser.TSANMLegacyParser.run(TSANMLegacyP\narser.java:131)\nDELETE FROM T_VIEW_HOST2PORT_TEMP1 WHERE PORT_ID \u003d ?\nINSERT INTO T_VIEW_HOST2PORT_TEMP1  SELECT CAST (NULL AS {0}) HOST_ID, PORT.HOST\n_URL_BY_SUBSYSTEM HOST_URL, PORT.PORT_ID PORT_ID FROM T_RES_PORT PORT LEFT OUTER\n JOIN T_RES_NODE AS NODE ON (PORT.NODE_ID \u003d NODE.NODE_ID) WHERE PORT.NODE_ID IS\nNULL and PORT.HOST_URL_BY_SUBSYSTEM IS NOT NULL AND PORT.PORT_ID \u003d ?\norg.apache.derby.client.am.SqlException: Syntax error: Encountered \"\" at line 1,\n column 58.\n        at org.apache.derby.client.am.Statement.completeSqlca(Unknown Source)\n        at org.apache.derby.client.net.NetStatementReply.parsePrepareError(Unkno\nwn Source)\n        at org.apache.derby.client.net.NetStatementReply.parsePRPSQLSTTreply(Unk\nnown Source)\n        at org.apache.derby.client.net.NetStatementReply.readPrepareDescribeOutp\nut(Unknown Source)\n        at org.apache.derby.client.net.StatementReply.readPrepareDescribeOutput(\nUnknown Source)\n        at org.apache.derby.client.net.NetStatement.readPrepareDescribeOutput_(U\nnknown Source)\n        at org.apache.derby.client.am.Statement.readPrepareDescribeOutput(Unknow\nn Source)\n        at org.apache.derby.client.am.PreparedStatement.readPrepareDescribeInput\nOutput(Unknown Source)\n        at org.apache.derby.client.am.PreparedStatement.flowPrepareDescribeInput\nOutput(Unknown Source)\n        at org.apache.derby.client.am.PreparedStatement.prepare(Unknown Source)\n        at org.apache.derby.client.am.Connection.prepareStatementX(Unknown Sourc\ne)\n        at org.apache.derby.client.am.Connection.prepareStatement(Unknown Source\n)\n        at org.eclipse.aperi.infrastructure.database.DBConnection.prepareStateme\nnt(DBConnection.java:418)\n        at org.eclipse.aperi.common.dbaccess.ViewReportTablesUpdater.handleUpdat\ne(ViewReportTablesUpdater.java:1633)\n        at org.eclipse.aperi.common.dbaccess.ViewReportTablesUpdater.updateOther\nTables(ViewReportTablesUpdater.java:1222)\n        at org.eclipse.aperi.common.dbaccess.ViewReportTablesUpdater.updateViewT\nables(ViewReportTablesUpdater.java:1130)\n        at org.eclipse.aperi.common.dbaccess.ViewReportTablesUpdater.processView\n(ViewReportTablesUpdater.java:1034)\n        at org.eclipse.aperi.infrastructure.history.detectability.ChangeDetectio\nn.startNew(ChangeDetection.java:857)\n        at org.eclipse.aperi.discovery.parser.Processor.end(Processor.java:273)\n        at org.eclipse.aperi.discovery.parser.TSANMLegacyParser$Worker.parse(TSA\nNMLegacyParser.java:333)\n        at org.eclipse.aperi.discovery.parser.Parser.processJob(Parser.java:17)\n        at org.eclipse.aperi.discovery.parser.TSANMLegacyParser.run(TSANMLegacyP\narser.java:131)\nDELETE FROM T_VIEW_PORT2PORT WHERE PORT2PORT_ID \u003d ?\nINSERT INTO T_VIEW_PORT2PORT  SELECT PORT2PORT.PORT2PORT_ID PORT2PORT_ID, PORT2P\nORT.PORT_ID1 PORT_ID1, PORT2PORT.PORT_ID2 PORT_ID2, PORT2PORT.DETECTABLE DETECTA\nBLE FROM T_RES_PORT2PORT PORT2PORT AND PORT2PORT.PORT2PORT_ID \u003d ?\nINSERT INTO T_VIEW_PORT2PORT  PORT2PORT.PORT2PORT_ID PORT2PORT_ID, PORT2PORT.POR\nT_ID2 PORT_ID1, PORT2PORT.PORT_ID1 PORT_ID2, PORT2PORT.DETECTABLE DETECTABLE FRO\nM T_RES_PORT2PORT PORT2PORT AND PORT2PORT.PORT2PORT_ID \u003d ?\norg.apache.derby.client.am.SqlException: Syntax error: Encountered \"AND\" at line\n 1, column 196.\n        at org.apache.derby.client.am.Statement.completeSqlca(Unknown Source)\n        at org.apache.derby.client.net.NetStatementReply.parsePrepareError(Unkno\nwn Source)\n        at org.apache.derby.client.net.NetStatementReply.parsePRPSQLSTTreply(Unk\nnown Source)\n        at org.apache.derby.client.net.NetStatementReply.readPrepareDescribeOutp\nut(Unknown Source)\n        at org.apache.derby.client.net.StatementReply.readPrepareDescribeOutput(\nUnknown Source)\n        at org.apache.derby.client.net.NetStatement.readPrepareDescribeOutput_(U\nnknown Source)\n        at org.apache.derby.client.am.Statement.readPrepareDescribeOutput(Unknow\nn Source)\n        at org.apache.derby.client.am.PreparedStatement.readPrepareDescribeInput\nOutput(Unknown Source)\n        at org.apache.derby.client.am.PreparedStatement.flowPrepareDescribeInput\nOutput(Unknown Source)\n        at org.apache.derby.client.am.PreparedStatement.prepare(Unknown Source)\n        at org.apache.derby.client.am.Connection.prepareStatementX(Unknown Sourc\ne)\n        at org.apache.derby.client.am.Connection.prepareStatement(Unknown Source\n)\n        at org.eclipse.aperi.infrastructure.database.DBConnection.prepareStateme\nnt(DBConnection.java:418)\n        at org.eclipse.aperi.common.dbaccess.ViewReportTablesUpdater.handleUpdat\ne(ViewReportTablesUpdater.java:1633)\n        at org.eclipse.aperi.common.dbaccess.ViewReportTablesUpdater.updatePort2\nportTables(ViewReportTablesUpdater.java:1157)\n        at org.eclipse.aperi.common.dbaccess.ViewReportTablesUpdater.updateViewT\nables(ViewReportTablesUpdater.java:1133)\n        at org.eclipse.aperi.common.dbaccess.ViewReportTablesUpdater.processView\n(ViewReportTablesUpdater.java:1040)\n        at org.eclipse.aperi.infrastructure.history.detectability.ChangeDetectio\nn.startNew(ChangeDetection.java:857)\n        at org.eclipse.aperi.discovery.parser.Processor.end(Processor.java:273)\n        at org.eclipse.aperi.discovery.parser.TSANMLegacyParser$Worker.parse(TSA\nNMLegacyParser.java:333)\n        at org.eclipse.aperi.discovery.parser.Parser.processJob(Parser.java:17)\n        at org.eclipse.aperi.discovery.parser.TSANMLegacyParser.run(TSANMLegacyP\narser.java:131)\nDELETE FROM T_VIEW_SWITCH2FABRIC WHERE switch_id \u003d ?\nINSERT INTO T_VIEW_SWITCH2FABRIC  SELECT SWITCH.SWITCH_ID SWITCH_ID, FABRIC.FABR\nIC_ID FABRIC_ID FROM T_RES_FABRIC2SWITCH FABRIC2SWITCH, T_RES_FABRIC FABRIC, T_R\nES_SWITCH SWITCH left outer join T_RES_SWITCH SWITCH2 on SWITCH.SWITCH_WWN \u003d SWI\nTCH2.PARENT_SWITCH_WWN WHERE SWITCH2.SWITCH_WWN IS NULL and SWITCH.SWITCH_WWN \u003d\nFABRIC2SWITCH.SWITCH_WWN and FABRIC2SWITCH.FABRIC_WWN \u003d FABRIC.FABRIC_WWN ) AND\nSWITCH.SWITCH_ID \u003d ?\norg.apache.derby.client.am.SqlException: Syntax error: Encountered \")\" at line 1\n, column 395.\n        at org.apache.derby.client.am.Statement.completeSqlca(Unknown Source)\n        at org.apache.derby.client.net.NetStatementReply.parsePrepareError(Unkno\nwn Source)\n        at org.apache.derby.client.net.NetStatementReply.parsePRPSQLSTTreply(Unk\nnown Source)\n        at org.apache.derby.client.net.NetStatementReply.readPrepareDescribeOutp\nut(Unknown Source)\n        at org.apache.derby.client.net.StatementReply.readPrepareDescribeOutput(\nUnknown Source)\n        at org.apache.derby.client.net.NetStatement.readPrepareDescribeOutput_(U\nnknown Source)\n        at org.apache.derby.client.am.Statement.readPrepareDescribeOutput(Unknow\nn Source)\n        at org.apache.derby.client.am.PreparedStatement.readPrepareDescribeInput\nOutput(Unknown Source)\n        at org.apache.derby.client.am.PreparedStatement.flowPrepareDescribeInput\nOutput(Unknown Source)\n        at org.apache.derby.client.am.PreparedStatement.prepare(Unknown Source)\n        at org.apache.derby.client.am.Connection.prepareStatementX(Unknown Sourc\ne)\n        at org.apache.derby.client.am.Connection.prepareStatement(Unknown Source\n)\n        at org.eclipse.aperi.infrastructure.database.DBConnection.prepareStateme\nnt(DBConnection.java:418)\n        at org.eclipse.aperi.common.dbaccess.ViewReportTablesUpdater.handleUpdat\ne(ViewReportTablesUpdater.java:1633)\n        at org.eclipse.aperi.common.dbaccess.ViewReportTablesUpdater.updateSwitc\nhTables(ViewReportTablesUpdater.java:1597)\n        at org.eclipse.aperi.common.dbaccess.ViewReportTablesUpdater.updateViewT\nables(ViewReportTablesUpdater.java:1126)\n        at org.eclipse.aperi.common.dbaccess.ViewReportTablesUpdater.processView\n(ViewReportTablesUpdater.java:1032)\n        at org.eclipse.aperi.infrastructure.history.detectability.ChangeDetectio\nn.startNew(ChangeDetection.java:857)\n        at org.eclipse.aperi.discovery.parser.Processor.end(Processor.java:273)\n        at org.eclipse.aperi.discovery.parser.TSANMLegacyParser$Worker.parse(TSA\nNMLegacyParser.java:333)\n        at org.eclipse.aperi.discovery.parser.Parser.processJob(Parser.java:17)\n        at org.eclipse.aperi.discovery.parser.TSANMLegacyParser.run(TSANMLegacyP\narser.java:131)\nDELETE FROM T_VIEW_HOST2PORT_TEMP1 WHERE PORT_ID \u003d ?\nINSERT INTO T_VIEW_HOST2PORT_TEMP1  SELECT CAST (NULL AS {0}) HOST_ID, PORT.HOST\n_URL_BY_SUBSYSTEM HOST_URL, PORT.PORT_ID PORT_ID FROM T_RES_PORT PORT LEFT OUTER\n JOIN T_RES_NODE AS NODE ON (PORT.NODE_ID \u003d NODE.NODE_ID) WHERE PORT.NODE_ID IS\nNULL and PORT.HOST_URL_BY_SUBSYSTEM IS NOT NULL AND PORT.PORT_ID \u003d ?\norg.apache.derby.client.am.SqlException: Syntax error: Encountered \"\" at line 1,\n column 58.\n        at org.apache.derby.client.am.Statement.completeSqlca(Unknown Source)\n        at org.apache.derby.client.net.NetStatementReply.parsePrepareError(Unkno\nwn Source)\n        at org.apache.derby.client.net.NetStatementReply.parsePRPSQLSTTreply(Unk\nnown Source)\n        at org.apache.derby.client.net.NetStatementReply.readPrepareDescribeOutp\nut(Unknown Source)\n        at org.apache.derby.client.net.StatementReply.readPrepareDescribeOutput(\nUnknown Source)\n        at org.apache.derby.client.net.NetStatement.readPrepareDescribeOutput_(U\nnknown Source)\n        at org.apache.derby.client.am.Statement.readPrepareDescribeOutput(Unknow\nn Source)\n        at org.apache.derby.client.am.PreparedStatement.readPrepareDescribeInput\nOutput(Unknown Source)\n        at org.apache.derby.client.am.PreparedStatement.flowPrepareDescribeInput\nOutput(Unknown Source)\n        at org.apache.derby.client.am.PreparedStatement.prepare(Unknown Source)\n        at org.apache.derby.client.am.Connection.prepareStatementX(Unknown Sourc\ne)\n        at org.apache.derby.client.am.Connection.prepareStatement(Unknown Source\n)\n        at org.eclipse.aperi.infrastructure.database.DBConnection.prepareStateme\nnt(DBConnection.java:418)\n        at org.eclipse.aperi.common.dbaccess.ViewReportTablesUpdater.handleUpdat\ne(ViewReportTablesUpdater.java:1633)\n        at org.eclipse.aperi.common.dbaccess.ViewReportTablesUpdater.updateOther\nTables(ViewReportTablesUpdater.java:1222)\n        at org.eclipse.aperi.common.dbaccess.ViewReportTablesUpdater.updateViewT\nables(ViewReportTablesUpdater.java:1130)\n        at org.eclipse.aperi.common.dbaccess.ViewReportTablesUpdater.processView\n(ViewReportTablesUpdater.java:1034)\n        at org.eclipse.aperi.infrastructure.history.detectability.ChangeDetectio\nn.complete(ChangeDetection.java:1585)\n        at org.eclipse.aperi.discovery.parser.Processor.end(Processor.java:277)\n        at org.eclipse.aperi.discovery.parser.TSANMLegacyParser$Worker.parse(TSA\nNMLegacyParser.java:333)\n        at org.eclipse.aperi.discovery.parser.Parser.processJob(Parser.java:17)\n        at org.eclipse.aperi.discovery.parser.TSANMLegacyParser.run(TSANMLegacyP\narser.java:131)\nDELETE FROM T_VIEW_PORT2PORT WHERE PORT2PORT_ID \u003d ?\nINSERT INTO T_VIEW_PORT2PORT  SELECT PORT2PORT.PORT2PORT_ID PORT2PORT_ID, PORT2P\nORT.PORT_ID1 PORT_ID1, PORT2PORT.PORT_ID2 PORT_ID2, PORT2PORT.DETECTABLE DETECTA\nBLE FROM T_RES_PORT2PORT PORT2PORT AND PORT2PORT.PORT2PORT_ID \u003d ?\nINSERT INTO T_VIEW_PORT2PORT  PORT2PORT.PORT2PORT_ID PORT2PORT_ID, PORT2PORT.POR\nT_ID2 PORT_ID1, PORT2PORT.PORT_ID1 PORT_ID2, PORT2PORT.DETECTABLE DETECTABLE FRO\nM T_RES_PORT2PORT PORT2PORT AND PORT2PORT.PORT2PORT_ID \u003d ?\norg.apache.derby.client.am.SqlException: Syntax error: Encountered \"AND\" at line\n 1, column 196.\n        at org.apache.derby.client.am.Statement.completeSqlca(Unknown Source)\n        at org.apache.derby.client.net.NetStatementReply.parsePrepareError(Unkno\nwn Source)\n        at org.apache.derby.client.net.NetStatementReply.parsePRPSQLSTTreply(Unk\nnown Source)\n        at org.apache.derby.client.net.NetStatementReply.readPrepareDescribeOutp\nut(Unknown Source)\n        at org.apache.derby.client.net.StatementReply.readPrepareDescribeOutput(\nUnknown Source)\n        at org.apache.derby.client.net.NetStatement.readPrepareDescribeOutput_(U\nnknown Source)\n        at org.apache.derby.client.am.Statement.readPrepareDescribeOutput(Unknow\nn Source)\n        at org.apache.derby.client.am.PreparedStatement.readPrepareDescribeInput\nOutput(Unknown Source)\n        at org.apache.derby.client.am.PreparedStatement.flowPrepareDescribeInput\nOutput(Unknown Source)\n        at org.apache.derby.client.am.PreparedStatement.prepare(Unknown Source)\n        at org.apache.derby.client.am.Connection.prepareStatementX(Unknown Sourc\ne)\n        at org.apache.derby.client.am.Connection.prepareStatement(Unknown Source\n)\n        at org.eclipse.aperi.infrastructure.database.DBConnection.prepareStateme\nnt(DBConnection.java:418)\n        at org.eclipse.aperi.common.dbaccess.ViewReportTablesUpdater.handleUpdat\ne(ViewReportTablesUpdater.java:1633)\n        at org.eclipse.aperi.common.dbaccess.ViewReportTablesUpdater.updatePort2\nportTables(ViewReportTablesUpdater.java:1157)\n        at org.eclipse.aperi.common.dbaccess.ViewReportTablesUpdater.updateViewT\nables(ViewReportTablesUpdater.java:1133)\n        at org.eclipse.aperi.common.dbaccess.ViewReportTablesUpdater.processView\n(ViewReportTablesUpdater.java:1040)\n        at org.eclipse.aperi.infrastructure.history.detectability.ChangeDetectio\nn.complete(ChangeDetection.java:1585)\n        at org.eclipse.aperi.discovery.parser.Processor.end(Processor.java:277)\n        at org.eclipse.aperi.discovery.parser.TSANMLegacyParser$Worker.parse(TSA\nNMLegacyParser.java:333)\n        at org.eclipse.aperi.discovery.parser.Parser.processJob(Parser.java:17)\n        at org.eclipse.aperi.discovery.parser.TSANMLegacyParser.run(TSANMLegacyP\narser.java:131)\nDELETE FROM T_VIEW_HOST2PORT WHERE HOST_ID \u003d ?\nINSERT INTO T_VIEW_HOST2PORT SELECT PORT_ID, HOST_ID, HOST_URL FROM T_VIEW_HOST2\nPORT_TEMP2 AND HOST_ID \u003d ?\nINSERT INTO T_VIEW_HOST2PORT SELECT PORT_ID, HOST_ID, HOST_URL FROM T_VIEW_HOST2\nPORT_TEMP1 WHERE PORT_ID NOT IN (SELECT PORT_ID FROM T_VIEW_HOST2PORT_TEMP2) AND\n HOST_ID \u003d ?\norg.apache.derby.client.am.SqlException: Syntax error: Encountered \"AND\" at line\n 1, column 92.\n        at org.apache.derby.client.am.Statement.completeSqlca(Unknown Source)\n        at org.apache.derby.client.net.NetStatementReply.parsePrepareError(Unkno\nwn Source)\n        at org.apache.derby.client.net.NetStatementReply.parsePRPSQLSTTreply(Unk\nnown Source)\n        at org.apache.derby.client.net.NetStatementReply.readPrepareDescribeOutp\nut(Unknown Source)\n        at org.apache.derby.client.net.StatementReply.readPrepareDescribeOutput(\nUnknown Source)\n        at org.apache.derby.client.net.NetStatement.readPrepareDescribeOutput_(U\nnknown Source)\n        at org.apache.derby.client.am.Statement.readPrepareDescribeOutput(Unknow\nn Source)\n        at org.apache.derby.client.am.PreparedStatement.readPrepareDescribeInput\nOutput(Unknown Source)\n        at org.apache.derby.client.am.PreparedStatement.flowPrepareDescribeInput\nOutput(Unknown Source)\n        at org.apache.derby.client.am.PreparedStatement.prepare(Unknown Source)\n        at org.apache.derby.client.am.Connection.prepareStatementX(Unknown Sourc\ne)\n        at org.apache.derby.client.am.Connection.prepareStatement(Unknown Source\n)\n        at org.eclipse.aperi.infrastructure.database.DBConnection.prepareStateme\nnt(DBConnection.java:418)\n        at org.eclipse.aperi.common.dbaccess.ViewReportTablesUpdater.handleUpdat\ne(ViewReportTablesUpdater.java:1633)\n        at org.eclipse.aperi.common.dbaccess.ViewReportTablesUpdater.updateHostT\nables(ViewReportTablesUpdater.java:1365)\n        at org.eclipse.aperi.common.dbaccess.ViewReportTablesUpdater.updateOther\nTables(ViewReportTablesUpdater.java:1275)\n        at org.eclipse.aperi.common.dbaccess.ViewReportTablesUpdater.updateViewT\nables(ViewReportTablesUpdater.java:1130)\n        at org.eclipse.aperi.common.dbaccess.ViewReportTablesUpdater.processView\n(ViewReportTablesUpdater.java:1036)\n        at org.eclipse.aperi.infrastructure.history.detectability.ChangeDetectio\nn.complete(ChangeDetection.java:1585)\n        at org.eclipse.aperi.discovery.parser.Processor.end(Processor.java:277)\n        at org.eclipse.aperi.discovery.parser.TSANMLegacyParser$Worker.parse(TSA\nNMLegacyParser.java:333)\n        at org.eclipse.aperi.discovery.parser.Parser.processJob(Parser.java:17)\n        at org.eclipse.aperi.discovery.parser.TSANMLegacyParser.run(TSANMLegacyP\narser.java:131)\nDELETE FROM T_VIEW_SWITCH2FABRIC WHERE switch_id \u003d ?\nINSERT INTO T_VIEW_SWITCH2FABRIC  SELECT SWITCH.SWITCH_ID SWITCH_ID, FABRIC.FABR\nIC_ID FABRIC_ID FROM T_RES_FABRIC2SWITCH FABRIC2SWITCH, T_RES_FABRIC FABRIC, T_R\nES_SWITCH SWITCH left outer join T_RES_SWITCH SWITCH2 on SWITCH.SWITCH_WWN \u003d SWI\nTCH2.PARENT_SWITCH_WWN WHERE SWITCH2.SWITCH_WWN IS NULL and SWITCH.SWITCH_WWN \u003d\nFABRIC2SWITCH.SWITCH_WWN and FABRIC2SWITCH.FABRIC_WWN \u003d FABRIC.FABRIC_WWN ) AND\nSWITCH.SWITCH_ID \u003d ?\norg.apache.derby.client.am.SqlException: Syntax error: Encountered \")\" at line 1\n, column 395.\n        at org.apache.derby.client.am.Statement.completeSqlca(Unknown Source)\n        at org.apache.derby.client.net.NetStatementReply.parsePrepareError(Unkno\nwn Source)\n        at org.apache.derby.client.net.NetStatementReply.parsePRPSQLSTTreply(Unk\nnown Source)\n        at org.apache.derby.client.net.NetStatementReply.readPrepareDescribeOutp\nut(Unknown Source)\n        at org.apache.derby.client.net.StatementReply.readPrepareDescribeOutput(\nUnknown Source)\n        at org.apache.derby.client.net.NetStatement.readPrepareDescribeOutput_(U\nnknown Source)\n        at org.apache.derby.client.am.Statement.readPrepareDescribeOutput(Unknow\nn Source)\n        at org.apache.derby.client.am.PreparedStatement.readPrepareDescribeInput\nOutput(Unknown Source)\n        at org.apache.derby.client.am.PreparedStatement.flowPrepareDescribeInput\nOutput(Unknown Source)\n        at org.apache.derby.client.am.PreparedStatement.prepare(Unknown Source)\n        at org.apache.derby.client.am.Connection.prepareStatementX(Unknown Sourc\ne)\n        at org.apache.derby.client.am.Connection.prepareStatement(Unknown Source\n)\n        at org.eclipse.aperi.infrastructure.database.DBConnection.prepareStateme\nnt(DBConnection.java:418)\n        at org.eclipse.aperi.common.dbaccess.ViewReportTablesUpdater.handleUpdat\ne(ViewReportTablesUpdater.java:1633)\n        at org.eclipse.aperi.common.dbaccess.ViewReportTablesUpdater.updateSwitc\nhTables(ViewReportTablesUpdater.java:1597)\n        at org.eclipse.aperi.common.dbaccess.ViewReportTablesUpdater.updateViewT\nables(ViewReportTablesUpdater.java:1126)\n        at org.eclipse.aperi.common.dbaccess.ViewReportTablesUpdater.processView\n(ViewReportTablesUpdater.java:1032)\n        at org.eclipse.aperi.infrastructure.history.detectability.ChangeDetectio\nn.complete(ChangeDetection.java:1585)\n        at org.eclipse.aperi.discovery.parser.Processor.end(Processor.java:277)\n        at org.eclipse.aperi.discovery.parser.TSANMLegacyParser$Worker.parse(TSA\nNMLegacyParser.java:333)\n        at org.eclipse.aperi.discovery.parser.Parser.processJob(Parser.java:17)\n        at org.eclipse.aperi.discovery.parser.TSANMLegacyParser.run(TSANMLegacyP\narser.java:131)",
    "I\u0027ve checked some fixes in. However, now the out-of-band fabric discovery hangs even before it reaches the ViewReportTablesPopulator code -- so I need some help from Hans for some unit testing. Also, my laptop has died, so I\u0027m in some communication limbo also - will coordinate thru bugzilla.",
    "The bug had been fixed on build Aperi-20070227-100302.zip "
  ],
  "commentCreationDates": [
    "2007-02-20T19:14:07+01:00",
    "2007-02-25T20:00:08+01:00",
    "2007-03-09T23:05:34+01:00"
  ],
  "traces": [
    {
      "exceptionType": "org.apache.derby.client.am.SqlException",
      "message": "Syntax error: Encountered \"AND\" at line  1, column 92.",
      "elements": [
        {
          "method": "org.apache.derby.client.am.Statement.completeSqlca",
          "source": "Unknown Source"
        },
        {
          "method": "org.apache.derby.client.net.NetStatementReply.parsePrepareError",
          "source": "Unkno wn Source"
        },
        {
          "method": "org.apache.derby.client.net.NetStatementReply.parsePRPSQLSTTreply",
          "source": "Unk nown Source"
        },
        {
          "method": "org.apache.derby.client.net.NetStatementReply.readPrepareDescribeOutput",
          "source": "Unknown Source"
        },
        {
          "method": "org.apache.derby.client.net.StatementReply.readPrepareDescribeOutput",
          "source": " Unknown Source"
        },
        {
          "method": "org.apache.derby.client.net.NetStatement.readPrepareDescribeOutput_",
          "source": "U nknown Source"
        },
        {
          "method": "org.apache.derby.client.am.Statement.readPrepareDescribeOutput",
          "source": "Unknow n Source"
        },
        {
          "method": "org.apache.derby.client.am.PreparedStatement.readPrepareDescribeInputOutput",
          "source": "Unknown Source"
        },
        {
          "method": "org.apache.derby.client.am.PreparedStatement.flowPrepareDescribeInputOutput",
          "source": "Unknown Source"
        },
        {
          "method": "org.apache.derby.client.am.PreparedStatement.prepare",
          "source": "Unknown Source"
        },
        {
          "method": "org.apache.derby.client.am.Connection.prepareStatementX",
          "source": "Unknown Sourc e"
        },
        {
          "method": "org.apache.derby.client.am.Connection.prepareStatement",
          "source": "Unknown Source "
        },
        {
          "method": "org.eclipse.aperi.infrastructure.database.DBConnection.prepareStatement",
          "source": "DBConnection.java:418"
        },
        {
          "method": "org.eclipse.aperi.common.dbaccess.ViewReportTablesUpdater.handleUpdate",
          "source": "ViewReportTablesUpdater.java:1633"
        },
        {
          "method": "org.eclipse.aperi.common.dbaccess.ViewReportTablesUpdater.updateHostTables",
          "source": "ViewReportTablesUpdater.java:1365"
        },
        {
          "method": "org.eclipse.aperi.common.dbaccess.ViewReportTablesUpdater.updateOtherTables",
          "source": "ViewReportTablesUpdater.java:1275"
        },
        {
          "method": "org.eclipse.aperi.common.dbaccess.ViewReportTablesUpdater.updateViewTables",
          "source": "ViewReportTablesUpdater.java:1130"
        },
        {
          "method": "org.eclipse.aperi.common.dbaccess.ViewReportTablesUpdater.processView",
          "source": "ViewReportTablesUpdater.java:1038"
        },
        {
          "method": "org.eclipse.aperi.infrastructure.history.detectability.ChangeDetection.startNew",
          "source": "ChangeDetection.java:857"
        },
        {
          "method": "org.eclipse.aperi.discovery.parser.Processor.end",
          "source": "Processor.java:273"
        },
        {
          "method": "org.eclipse.aperi.discovery.parser.TSANMLegacyParser$Worker.parse",
          "source": "TSA NMLegacyParser.java:333"
        },
        {
          "method": "org.eclipse.aperi.discovery.parser.Parser.processJob",
          "source": "Parser.java:17"
        },
        {
          "method": "org.eclipse.aperi.discovery.parser.TSANMLegacyParser.run",
          "source": "TSANMLegacyP arser.java:131"
        }
      ],
      "number": 0,
      "commentIndex": 0,
      "bugId": "174837",
      "date": "2007-02-20T19:14:07+01:00",
      "product": "Aperi",
      "component": "aperi.db",
      "severity": "critical"
    },
    {
      "exceptionType": "org.apache.derby.client.am.SqlException",
      "message": "Syntax error: Encountered \"\" at line 1,  column 58.",
      "elements": [
        {
          "method": "org.apache.derby.client.am.Statement.completeSqlca",
          "source": "Unknown Source"
        },
        {
          "method": "org.apache.derby.client.net.NetStatementReply.parsePrepareError",
          "source": "Unkno wn Source"
        },
        {
          "method": "org.apache.derby.client.net.NetStatementReply.parsePRPSQLSTTreply",
          "source": "Unk nown Source"
        },
        {
          "method": "org.apache.derby.client.net.NetStatementReply.readPrepareDescribeOutput",
          "source": "Unknown Source"
        },
        {
          "method": "org.apache.derby.client.net.StatementReply.readPrepareDescribeOutput",
          "source": " Unknown Source"
        },
        {
          "method": "org.apache.derby.client.net.NetStatement.readPrepareDescribeOutput_",
          "source": "U nknown Source"
        },
        {
          "method": "org.apache.derby.client.am.Statement.readPrepareDescribeOutput",
          "source": "Unknow n Source"
        },
        {
          "method": "org.apache.derby.client.am.PreparedStatement.readPrepareDescribeInputOutput",
          "source": "Unknown Source"
        },
        {
          "method": "org.apache.derby.client.am.PreparedStatement.flowPrepareDescribeInputOutput",
          "source": "Unknown Source"
        },
        {
          "method": "org.apache.derby.client.am.PreparedStatement.prepare",
          "source": "Unknown Source"
        },
        {
          "method": "org.apache.derby.client.am.Connection.prepareStatementX",
          "source": "Unknown Sourc e"
        },
        {
          "method": "org.apache.derby.client.am.Connection.prepareStatement",
          "source": "Unknown Source "
        },
        {
          "method": "org.eclipse.aperi.infrastructure.database.DBConnection.prepareStatement",
          "source": "DBConnection.java:418"
        },
        {
          "method": "org.eclipse.aperi.common.dbaccess.ViewReportTablesUpdater.handleUpdate",
          "source": "ViewReportTablesUpdater.java:1633"
        },
        {
          "method": "org.eclipse.aperi.common.dbaccess.ViewReportTablesUpdater.updateOtherTables",
          "source": "ViewReportTablesUpdater.java:1222"
        },
        {
          "method": "org.eclipse.aperi.common.dbaccess.ViewReportTablesUpdater.updateViewTables",
          "source": "ViewReportTablesUpdater.java:1130"
        },
        {
          "method": "org.eclipse.aperi.common.dbaccess.ViewReportTablesUpdater.processView",
          "source": "ViewReportTablesUpdater.java:1034"
        },
        {
          "method": "org.eclipse.aperi.infrastructure.history.detectability.ChangeDetection.startNew",
          "source": "ChangeDetection.java:857"
        },
        {
          "method": "org.eclipse.aperi.discovery.parser.Processor.end",
          "source": "Processor.java:273"
        },
        {
          "method": "org.eclipse.aperi.discovery.parser.TSANMLegacyParser$Worker.parse",
          "source": "TSA NMLegacyParser.java:333"
        },
        {
          "method": "org.eclipse.aperi.discovery.parser.Parser.processJob",
          "source": "Parser.java:17"
        },
        {
          "method": "org.eclipse.aperi.discovery.parser.TSANMLegacyParser.run",
          "source": "TSANMLegacyP arser.java:131"
        }
      ],
      "number": 1,
      "commentIndex": 0,
      "bugId": "174837",
      "date": "2007-02-20T19:14:07+01:00",
      "product": "Aperi",
      "component": "aperi.db",
      "severity": "critical"
    },
    {
      "exceptionType": "org.apache.derby.client.am.SqlException",
      "message": "Syntax error: Encountered \"AND\" at line  1, column 92.",
      "elements": [
        {
          "method": "org.apache.derby.client.am.Statement.completeSqlca",
          "source": "Unknown Source"
        },
        {
          "method": "org.apache.derby.client.net.NetStatementReply.parsePrepareError",
          "source": "Unkno wn Source"
        },
        {
          "method": "org.apache.derby.client.net.NetStatementReply.parsePRPSQLSTTreply",
          "source": "Unk nown Source"
        },
        {
          "method": "org.apache.derby.client.net.NetStatementReply.readPrepareDescribeOutput",
          "source": "Unknown Source"
        },
        {
          "method": "org.apache.derby.client.net.StatementReply.readPrepareDescribeOutput",
          "source": " Unknown Source"
        },
        {
          "method": "org.apache.derby.client.net.NetStatement.readPrepareDescribeOutput_",
          "source": "U nknown Source"
        },
        {
          "method": "org.apache.derby.client.am.Statement.readPrepareDescribeOutput",
          "source": "Unknow n Source"
        },
        {
          "method": "org.apache.derby.client.am.PreparedStatement.readPrepareDescribeInputOutput",
          "source": "Unknown Source"
        },
        {
          "method": "org.apache.derby.client.am.PreparedStatement.flowPrepareDescribeInputOutput",
          "source": "Unknown Source"
        },
        {
          "method": "org.apache.derby.client.am.PreparedStatement.prepare",
          "source": "Unknown Source"
        },
        {
          "method": "org.apache.derby.client.am.Connection.prepareStatementX",
          "source": "Unknown Sourc e"
        },
        {
          "method": "org.apache.derby.client.am.Connection.prepareStatement",
          "source": "Unknown Source "
        },
        {
          "method": "org.eclipse.aperi.infrastructure.database.DBConnection.prepareStatement",
          "source": "DBConnection.java:418"
        },
        {
          "method": "org.eclipse.aperi.common.dbaccess.ViewReportTablesUpdater.handleUpdate",
          "source": "ViewReportTablesUpdater.java:1633"
        },
        {
          "method": "org.eclipse.aperi.common.dbaccess.ViewReportTablesUpdater.updateHostTables",
          "source": "ViewReportTablesUpdater.java:1365"
        },
        {
          "method": "org.eclipse.aperi.common.dbaccess.ViewReportTablesUpdater.updateOtherTables",
          "source": "ViewReportTablesUpdater.java:1275"
        },
        {
          "method": "org.eclipse.aperi.common.dbaccess.ViewReportTablesUpdater.updateViewTables",
          "source": "ViewReportTablesUpdater.java:1130"
        },
        {
          "method": "org.eclipse.aperi.common.dbaccess.ViewReportTablesUpdater.processView",
          "source": "ViewReportTablesUpdater.java:1036"
        },
        {
          "method": "org.eclipse.aperi.infrastructure.history.detectability.ChangeDetection.startNew",
          "source": "ChangeDetection.java:857"
        },
        {
          "method": "org.eclipse.aperi.discovery.parser.Processor.end",
          "source": "Processor.java:273"
        },
        {
          "method": "org.eclipse.aperi.discovery.parser.TSANMLegacyParser$Worker.parse",
          "source": "TSA NMLegacyParser.java:333"
        },
        {
          "method": "org.eclipse.aperi.discovery.parser.Parser.processJob",
          "source": "Parser.java:17"
        },
        {
          "method": "org.eclipse.aperi.discovery.parser.TSANMLegacyParser.run",
          "source": "TSANMLegacyP arser.java:131"
        }
      ],
      "number": 2,
      "commentIndex": 0,
      "bugId": "174837",
      "date": "2007-02-20T19:14:07+01:00",
      "product": "Aperi",
      "component": "aperi.db",
      "severity": "critical"
    },
    {
      "exceptionType": "org.apache.derby.client.am.SqlException",
      "message": "Syntax error: Encountered \"AND\" at line  1, column 92.",
      "elements": [
        {
          "method": "org.apache.derby.client.am.Statement.completeSqlca",
          "source": "Unknown Source"
        },
        {
          "method": "org.apache.derby.client.net.NetStatementReply.parsePrepareError",
          "source": "Unkno wn Source"
        },
        {
          "method": "org.apache.derby.client.net.NetStatementReply.parsePRPSQLSTTreply",
          "source": "Unk nown Source"
        },
        {
          "method": "org.apache.derby.client.net.NetStatementReply.readPrepareDescribeOutput",
          "source": "Unknown Source"
        },
        {
          "method": "org.apache.derby.client.net.StatementReply.readPrepareDescribeOutput",
          "source": " Unknown Source"
        },
        {
          "method": "org.apache.derby.client.net.NetStatement.readPrepareDescribeOutput_",
          "source": "U nknown Source"
        },
        {
          "method": "org.apache.derby.client.am.Statement.readPrepareDescribeOutput",
          "source": "Unknow n Source"
        },
        {
          "method": "org.apache.derby.client.am.PreparedStatement.readPrepareDescribeInputOutput",
          "source": "Unknown Source"
        },
        {
          "method": "org.apache.derby.client.am.PreparedStatement.flowPrepareDescribeInputOutput",
          "source": "Unknown Source"
        },
        {
          "method": "org.apache.derby.client.am.PreparedStatement.prepare",
          "source": "Unknown Source"
        },
        {
          "method": "org.apache.derby.client.am.Connection.prepareStatementX",
          "source": "Unknown Sourc e"
        },
        {
          "method": "org.apache.derby.client.am.Connection.prepareStatement",
          "source": "Unknown Source "
        },
        {
          "method": "org.eclipse.aperi.infrastructure.database.DBConnection.prepareStatement",
          "source": "DBConnection.java:418"
        },
        {
          "method": "org.eclipse.aperi.common.dbaccess.ViewReportTablesUpdater.handleUpdate",
          "source": "ViewReportTablesUpdater.java:1633"
        },
        {
          "method": "org.eclipse.aperi.common.dbaccess.ViewReportTablesUpdater.updateHostTables",
          "source": "ViewReportTablesUpdater.java:1365"
        },
        {
          "method": "org.eclipse.aperi.common.dbaccess.ViewReportTablesUpdater.updateOtherTables",
          "source": "ViewReportTablesUpdater.java:1275"
        },
        {
          "method": "org.eclipse.aperi.common.dbaccess.ViewReportTablesUpdater.updateViewTables",
          "source": "ViewReportTablesUpdater.java:1130"
        },
        {
          "method": "org.eclipse.aperi.common.dbaccess.ViewReportTablesUpdater.processView",
          "source": "ViewReportTablesUpdater.java:1038"
        },
        {
          "method": "org.eclipse.aperi.infrastructure.history.detectability.ChangeDetection.complete",
          "source": "ChangeDetection.java:1585"
        },
        {
          "method": "org.eclipse.aperi.discovery.parser.Processor.end",
          "source": "Processor.java:277"
        },
        {
          "method": "org.eclipse.aperi.discovery.parser.TSANMLegacyParser$Worker.parse",
          "source": "TSA NMLegacyParser.java:333"
        },
        {
          "method": "org.eclipse.aperi.discovery.parser.Parser.processJob",
          "source": "Parser.java:17"
        },
        {
          "method": "org.eclipse.aperi.discovery.parser.TSANMLegacyParser.run",
          "source": "TSANMLegacyP arser.java:131"
        }
      ],
      "number": 3,
      "commentIndex": 0,
      "bugId": "174837",
      "date": "2007-02-20T19:14:07+01:00",
      "product": "Aperi",
      "component": "aperi.db",
      "severity": "critical"
    },
    {
      "exceptionType": "org.apache.derby.client.am.SqlException",
      "message": "Syntax error: Encountered \"\" at line 1,  column 58.",
      "elements": [
        {
          "method": "org.apache.derby.client.am.Statement.completeSqlca",
          "source": "Unknown Source"
        },
        {
          "method": "org.apache.derby.client.net.NetStatementReply.parsePrepareError",
          "source": "Unkno wn Source"
        },
        {
          "method": "org.apache.derby.client.net.NetStatementReply.parsePRPSQLSTTreply",
          "source": "Unk nown Source"
        },
        {
          "method": "org.apache.derby.client.net.NetStatementReply.readPrepareDescribeOutput",
          "source": "Unknown Source"
        },
        {
          "method": "org.apache.derby.client.net.StatementReply.readPrepareDescribeOutput",
          "source": " Unknown Source"
        },
        {
          "method": "org.apache.derby.client.net.NetStatement.readPrepareDescribeOutput_",
          "source": "U nknown Source"
        },
        {
          "method": "org.apache.derby.client.am.Statement.readPrepareDescribeOutput",
          "source": "Unknow n Source"
        },
        {
          "method": "org.apache.derby.client.am.PreparedStatement.readPrepareDescribeInputOutput",
          "source": "Unknown Source"
        },
        {
          "method": "org.apache.derby.client.am.PreparedStatement.flowPrepareDescribeInputOutput",
          "source": "Unknown Source"
        },
        {
          "method": "org.apache.derby.client.am.PreparedStatement.prepare",
          "source": "Unknown Source"
        },
        {
          "method": "org.apache.derby.client.am.Connection.prepareStatementX",
          "source": "Unknown Sourc e"
        },
        {
          "method": "org.apache.derby.client.am.Connection.prepareStatement",
          "source": "Unknown Source "
        },
        {
          "method": "org.eclipse.aperi.infrastructure.database.DBConnection.prepareStatement",
          "source": "DBConnection.java:418"
        },
        {
          "method": "org.eclipse.aperi.common.dbaccess.ViewReportTablesUpdater.handleUpdate",
          "source": "ViewReportTablesUpdater.java:1633"
        },
        {
          "method": "org.eclipse.aperi.common.dbaccess.ViewReportTablesUpdater.updateOtherTables",
          "source": "ViewReportTablesUpdater.java:1222"
        },
        {
          "method": "org.eclipse.aperi.common.dbaccess.ViewReportTablesUpdater.updateViewTables",
          "source": "ViewReportTablesUpdater.java:1130"
        },
        {
          "method": "org.eclipse.aperi.common.dbaccess.ViewReportTablesUpdater.processView",
          "source": "ViewReportTablesUpdater.java:1034"
        },
        {
          "method": "org.eclipse.aperi.infrastructure.history.detectability.ChangeDetection.complete",
          "source": "ChangeDetection.java:1585"
        },
        {
          "method": "org.eclipse.aperi.discovery.parser.Processor.end",
          "source": "Processor.java:277"
        },
        {
          "method": "org.eclipse.aperi.discovery.parser.TSANMLegacyParser$Worker.parse",
          "source": "TSA NMLegacyParser.java:333"
        },
        {
          "method": "org.eclipse.aperi.discovery.parser.Parser.processJob",
          "source": "Parser.java:17"
        },
        {
          "method": "org.eclipse.aperi.discovery.parser.TSANMLegacyParser.run",
          "source": "TSANMLegacyP arser.java:131"
        }
      ],
      "number": 4,
      "commentIndex": 0,
      "bugId": "174837",
      "date": "2007-02-20T19:14:07+01:00",
      "product": "Aperi",
      "component": "aperi.db",
      "severity": "critical"
    },
    {
      "exceptionType": "org.apache.derby.client.am.SqlException",
      "message": "Syntax error: Encountered \"AND\" at line  1, column 92.",
      "elements": [
        {
          "method": "org.apache.derby.client.am.Statement.completeSqlca",
          "source": "Unknown Source"
        },
        {
          "method": "org.apache.derby.client.net.NetStatementReply.parsePrepareError",
          "source": "Unkno wn Source"
        },
        {
          "method": "org.apache.derby.client.net.NetStatementReply.parsePRPSQLSTTreply",
          "source": "Unk nown Source"
        },
        {
          "method": "org.apache.derby.client.net.NetStatementReply.readPrepareDescribeOutput",
          "source": "Unknown Source"
        },
        {
          "method": "org.apache.derby.client.net.StatementReply.readPrepareDescribeOutput",
          "source": " Unknown Source"
        },
        {
          "method": "org.apache.derby.client.net.NetStatement.readPrepareDescribeOutput_",
          "source": "U nknown Source"
        },
        {
          "method": "org.apache.derby.client.am.Statement.readPrepareDescribeOutput",
          "source": "Unknow n Source"
        },
        {
          "method": "org.apache.derby.client.am.PreparedStatement.readPrepareDescribeInputOutput",
          "source": "Unknown Source"
        },
        {
          "method": "org.apache.derby.client.am.PreparedStatement.flowPrepareDescribeInputOutput",
          "source": "Unknown Source"
        },
        {
          "method": "org.apache.derby.client.am.PreparedStatement.prepare",
          "source": "Unknown Source"
        },
        {
          "method": "org.apache.derby.client.am.Connection.prepareStatementX",
          "source": "Unknown Sourc e"
        },
        {
          "method": "org.apache.derby.client.am.Connection.prepareStatement",
          "source": "Unknown Source "
        },
        {
          "method": "org.eclipse.aperi.infrastructure.database.DBConnection.prepareStatement",
          "source": "DBConnection.java:418"
        },
        {
          "method": "org.eclipse.aperi.common.dbaccess.ViewReportTablesUpdater.handleUpdate",
          "source": "ViewReportTablesUpdater.java:1633"
        },
        {
          "method": "org.eclipse.aperi.common.dbaccess.ViewReportTablesUpdater.updateHostTables",
          "source": "ViewReportTablesUpdater.java:1365"
        },
        {
          "method": "org.eclipse.aperi.common.dbaccess.ViewReportTablesUpdater.updateOtherTables",
          "source": "ViewReportTablesUpdater.java:1275"
        },
        {
          "method": "org.eclipse.aperi.common.dbaccess.ViewReportTablesUpdater.updateViewTables",
          "source": "ViewReportTablesUpdater.java:1130"
        },
        {
          "method": "org.eclipse.aperi.common.dbaccess.ViewReportTablesUpdater.processView",
          "source": "ViewReportTablesUpdater.java:1036"
        },
        {
          "method": "org.eclipse.aperi.infrastructure.history.detectability.ChangeDetection.complete",
          "source": "ChangeDetection.java:1585"
        },
        {
          "method": "org.eclipse.aperi.discovery.parser.Processor.end",
          "source": "Processor.java:277"
        },
        {
          "method": "org.eclipse.aperi.discovery.parser.TSANMLegacyParser$Worker.parse",
          "source": "TSA NMLegacyParser.java:333"
        },
        {
          "method": "org.eclipse.aperi.discovery.parser.Parser.processJob",
          "source": "Parser.java:17"
        },
        {
          "method": "org.eclipse.aperi.discovery.parser.TSANMLegacyParser.run",
          "source": "TSANMLegacyP arser.java:131"
        }
      ],
      "number": 5,
      "commentIndex": 0,
      "bugId": "174837",
      "date": "2007-02-20T19:14:07+01:00",
      "product": "Aperi",
      "component": "aperi.db",
      "severity": "critical"
    },
    {
      "exceptionType": "org.apache.derby.client.am.SqlException",
      "message": "Syntax error: Encountered \"AND\" at line  1, column 92.",
      "elements": [
        {
          "method": "org.apache.derby.client.am.Statement.completeSqlca",
          "source": "Unknown Source"
        },
        {
          "method": "org.apache.derby.client.net.NetStatementReply.parsePrepareError",
          "source": "Unkno wn Source"
        },
        {
          "method": "org.apache.derby.client.net.NetStatementReply.parsePRPSQLSTTreply",
          "source": "Unk nown Source"
        },
        {
          "method": "org.apache.derby.client.net.NetStatementReply.readPrepareDescribeOutput",
          "source": "Unknown Source"
        },
        {
          "method": "org.apache.derby.client.net.StatementReply.readPrepareDescribeOutput",
          "source": " Unknown Source"
        },
        {
          "method": "org.apache.derby.client.net.NetStatement.readPrepareDescribeOutput_",
          "source": "U nknown Source"
        },
        {
          "method": "org.apache.derby.client.am.Statement.readPrepareDescribeOutput",
          "source": "Unknow n Source"
        },
        {
          "method": "org.apache.derby.client.am.PreparedStatement.readPrepareDescribeInputOutput",
          "source": "Unknown Source"
        },
        {
          "method": "org.apache.derby.client.am.PreparedStatement.flowPrepareDescribeInputOutput",
          "source": "Unknown Source"
        },
        {
          "method": "org.apache.derby.client.am.PreparedStatement.prepare",
          "source": "Unknown Source"
        },
        {
          "method": "org.apache.derby.client.am.Connection.prepareStatementX",
          "source": "Unknown Sourc e"
        },
        {
          "method": "org.apache.derby.client.am.Connection.prepareStatement",
          "source": "Unknown Source "
        },
        {
          "method": "org.eclipse.aperi.infrastructure.database.DBConnection.prepareStatement",
          "source": "DBConnection.java:418"
        },
        {
          "method": "org.eclipse.aperi.common.dbaccess.ViewReportTablesUpdater.handleUpdate",
          "source": "ViewReportTablesUpdater.java:1633"
        },
        {
          "method": "org.eclipse.aperi.common.dbaccess.ViewReportTablesUpdater.updateHostTables",
          "source": "ViewReportTablesUpdater.java:1365"
        },
        {
          "method": "org.eclipse.aperi.common.dbaccess.ViewReportTablesUpdater.updateViewTables",
          "source": "ViewReportTablesUpdater.java:1119"
        },
        {
          "method": "org.eclipse.aperi.common.dbaccess.ViewReportTablesUpdater.processEntityView",
          "source": "ViewReportTablesUpdater.java:1057"
        },
        {
          "method": "org.eclipse.aperi.discovery.parser.Processor.end",
          "source": "Processor.java:300"
        },
        {
          "method": "org.eclipse.aperi.discovery.parser.TSANMLegacyParser$Worker.parse",
          "source": "TSA NMLegacyParser.java:333"
        },
        {
          "method": "org.eclipse.aperi.discovery.parser.Parser.processJob",
          "source": "Parser.java:17"
        },
        {
          "method": "org.eclipse.aperi.discovery.parser.TSANMLegacyParser.run",
          "source": "TSANMLegacyP arser.java:131"
        }
      ],
      "number": 6,
      "commentIndex": 0,
      "bugId": "174837",
      "date": "2007-02-20T19:14:07+01:00",
      "product": "Aperi",
      "component": "aperi.db",
      "severity": "critical"
    },
    {
      "exceptionType": "org.apache.derby.client.am.SqlException",
      "message": "Syntax error: Encountered \"\" at line 1,  column 58.",
      "elements": [
        {
          "method": "org.apache.derby.client.am.Statement.completeSqlca",
          "source": "Unknown Source"
        },
        {
          "method": "org.apache.derby.client.net.NetStatementReply.parsePrepareError",
          "source": "Unkno wn Source"
        },
        {
          "method": "org.apache.derby.client.net.NetStatementReply.parsePRPSQLSTTreply",
          "source": "Unk nown Source"
        },
        {
          "method": "org.apache.derby.client.net.NetStatementReply.readPrepareDescribeOutput",
          "source": "Unknown Source"
        },
        {
          "method": "org.apache.derby.client.net.StatementReply.readPrepareDescribeOutput",
          "source": " Unknown Source"
        },
        {
          "method": "org.apache.derby.client.net.NetStatement.readPrepareDescribeOutput_",
          "source": "U nknown Source"
        },
        {
          "method": "org.apache.derby.client.am.Statement.readPrepareDescribeOutput",
          "source": "Unknow n Source"
        },
        {
          "method": "org.apache.derby.client.am.PreparedStatement.readPrepareDescribeInputOutput",
          "source": "Unknown Source"
        },
        {
          "method": "org.apache.derby.client.am.PreparedStatement.flowPrepareDescribeInputOutput",
          "source": "Unknown Source"
        },
        {
          "method": "org.apache.derby.client.am.PreparedStatement.prepare",
          "source": "Unknown Source"
        },
        {
          "method": "org.apache.derby.client.am.Connection.prepareStatementX",
          "source": "Unknown Sourc e"
        },
        {
          "method": "org.apache.derby.client.am.Connection.prepareStatement",
          "source": "Unknown Source "
        },
        {
          "method": "org.eclipse.aperi.infrastructure.database.DBConnection.prepareStatement",
          "source": "DBConnection.java:418"
        },
        {
          "method": "org.eclipse.aperi.common.dbaccess.ViewReportTablesUpdater.handleUpdate",
          "source": "ViewReportTablesUpdater.java:1633"
        },
        {
          "method": "org.eclipse.aperi.common.dbaccess.ViewReportTablesUpdater.updateOtherTables",
          "source": "ViewReportTablesUpdater.java:1222"
        },
        {
          "method": "org.eclipse.aperi.common.dbaccess.ViewReportTablesUpdater.updateViewTables",
          "source": "ViewReportTablesUpdater.java:1130"
        },
        {
          "method": "org.eclipse.aperi.common.dbaccess.ViewReportTablesUpdater.processView",
          "source": "ViewReportTablesUpdater.java:1034"
        },
        {
          "method": "org.eclipse.aperi.infrastructure.history.detectability.ChangeDetection.startNew",
          "source": "ChangeDetection.java:857"
        },
        {
          "method": "org.eclipse.aperi.discovery.parser.Processor.end",
          "source": "Processor.java:273"
        },
        {
          "method": "org.eclipse.aperi.discovery.parser.TSANMLegacyParser$Worker.parse",
          "source": "TSA NMLegacyParser.java:333"
        },
        {
          "method": "org.eclipse.aperi.discovery.parser.Parser.processJob",
          "source": "Parser.java:17"
        },
        {
          "method": "org.eclipse.aperi.discovery.parser.TSANMLegacyParser.run",
          "source": "TSANMLegacyP arser.java:131"
        }
      ],
      "number": 7,
      "commentIndex": 0,
      "bugId": "174837",
      "date": "2007-02-20T19:14:07+01:00",
      "product": "Aperi",
      "component": "aperi.db",
      "severity": "critical"
    },
    {
      "exceptionType": "org.apache.derby.client.am.SqlException",
      "message": "Syntax error: Encountered \"AND\" at line  1, column 196.",
      "elements": [
        {
          "method": "org.apache.derby.client.am.Statement.completeSqlca",
          "source": "Unknown Source"
        },
        {
          "method": "org.apache.derby.client.net.NetStatementReply.parsePrepareError",
          "source": "Unkno wn Source"
        },
        {
          "method": "org.apache.derby.client.net.NetStatementReply.parsePRPSQLSTTreply",
          "source": "Unk nown Source"
        },
        {
          "method": "org.apache.derby.client.net.NetStatementReply.readPrepareDescribeOutput",
          "source": "Unknown Source"
        },
        {
          "method": "org.apache.derby.client.net.StatementReply.readPrepareDescribeOutput",
          "source": " Unknown Source"
        },
        {
          "method": "org.apache.derby.client.net.NetStatement.readPrepareDescribeOutput_",
          "source": "U nknown Source"
        },
        {
          "method": "org.apache.derby.client.am.Statement.readPrepareDescribeOutput",
          "source": "Unknow n Source"
        },
        {
          "method": "org.apache.derby.client.am.PreparedStatement.readPrepareDescribeInputOutput",
          "source": "Unknown Source"
        },
        {
          "method": "org.apache.derby.client.am.PreparedStatement.flowPrepareDescribeInputOutput",
          "source": "Unknown Source"
        },
        {
          "method": "org.apache.derby.client.am.PreparedStatement.prepare",
          "source": "Unknown Source"
        },
        {
          "method": "org.apache.derby.client.am.Connection.prepareStatementX",
          "source": "Unknown Sourc e"
        },
        {
          "method": "org.apache.derby.client.am.Connection.prepareStatement",
          "source": "Unknown Source "
        },
        {
          "method": "org.eclipse.aperi.infrastructure.database.DBConnection.prepareStatement",
          "source": "DBConnection.java:418"
        },
        {
          "method": "org.eclipse.aperi.common.dbaccess.ViewReportTablesUpdater.handleUpdate",
          "source": "ViewReportTablesUpdater.java:1633"
        },
        {
          "method": "org.eclipse.aperi.common.dbaccess.ViewReportTablesUpdater.updatePort2portTables",
          "source": "ViewReportTablesUpdater.java:1157"
        },
        {
          "method": "org.eclipse.aperi.common.dbaccess.ViewReportTablesUpdater.updateViewTables",
          "source": "ViewReportTablesUpdater.java:1133"
        },
        {
          "method": "org.eclipse.aperi.common.dbaccess.ViewReportTablesUpdater.processView",
          "source": "ViewReportTablesUpdater.java:1040"
        },
        {
          "method": "org.eclipse.aperi.infrastructure.history.detectability.ChangeDetection.startNew",
          "source": "ChangeDetection.java:857"
        },
        {
          "method": "org.eclipse.aperi.discovery.parser.Processor.end",
          "source": "Processor.java:273"
        },
        {
          "method": "org.eclipse.aperi.discovery.parser.TSANMLegacyParser$Worker.parse",
          "source": "TSA NMLegacyParser.java:333"
        },
        {
          "method": "org.eclipse.aperi.discovery.parser.Parser.processJob",
          "source": "Parser.java:17"
        },
        {
          "method": "org.eclipse.aperi.discovery.parser.TSANMLegacyParser.run",
          "source": "TSANMLegacyP arser.java:131"
        }
      ],
      "number": 8,
      "commentIndex": 0,
      "bugId": "174837",
      "date": "2007-02-20T19:14:07+01:00",
      "product": "Aperi",
      "component": "aperi.db",
      "severity": "critical"
    },
    {
      "exceptionType": "org.apache.derby.client.am.SqlException",
      "message": "Syntax error: Encountered \")\" at line 1 , column 395.",
      "elements": [
        {
          "method": "org.apache.derby.client.am.Statement.completeSqlca",
          "source": "Unknown Source"
        },
        {
          "method": "org.apache.derby.client.net.NetStatementReply.parsePrepareError",
          "source": "Unkno wn Source"
        },
        {
          "method": "org.apache.derby.client.net.NetStatementReply.parsePRPSQLSTTreply",
          "source": "Unk nown Source"
        },
        {
          "method": "org.apache.derby.client.net.NetStatementReply.readPrepareDescribeOutput",
          "source": "Unknown Source"
        },
        {
          "method": "org.apache.derby.client.net.StatementReply.readPrepareDescribeOutput",
          "source": " Unknown Source"
        },
        {
          "method": "org.apache.derby.client.net.NetStatement.readPrepareDescribeOutput_",
          "source": "U nknown Source"
        },
        {
          "method": "org.apache.derby.client.am.Statement.readPrepareDescribeOutput",
          "source": "Unknow n Source"
        },
        {
          "method": "org.apache.derby.client.am.PreparedStatement.readPrepareDescribeInputOutput",
          "source": "Unknown Source"
        },
        {
          "method": "org.apache.derby.client.am.PreparedStatement.flowPrepareDescribeInputOutput",
          "source": "Unknown Source"
        },
        {
          "method": "org.apache.derby.client.am.PreparedStatement.prepare",
          "source": "Unknown Source"
        },
        {
          "method": "org.apache.derby.client.am.Connection.prepareStatementX",
          "source": "Unknown Sourc e"
        },
        {
          "method": "org.apache.derby.client.am.Connection.prepareStatement",
          "source": "Unknown Source "
        },
        {
          "method": "org.eclipse.aperi.infrastructure.database.DBConnection.prepareStatement",
          "source": "DBConnection.java:418"
        },
        {
          "method": "org.eclipse.aperi.common.dbaccess.ViewReportTablesUpdater.handleUpdate",
          "source": "ViewReportTablesUpdater.java:1633"
        },
        {
          "method": "org.eclipse.aperi.common.dbaccess.ViewReportTablesUpdater.updateSwitchTables",
          "source": "ViewReportTablesUpdater.java:1597"
        },
        {
          "method": "org.eclipse.aperi.common.dbaccess.ViewReportTablesUpdater.updateViewTables",
          "source": "ViewReportTablesUpdater.java:1126"
        },
        {
          "method": "org.eclipse.aperi.common.dbaccess.ViewReportTablesUpdater.processView",
          "source": "ViewReportTablesUpdater.java:1032"
        },
        {
          "method": "org.eclipse.aperi.infrastructure.history.detectability.ChangeDetection.startNew",
          "source": "ChangeDetection.java:857"
        },
        {
          "method": "org.eclipse.aperi.discovery.parser.Processor.end",
          "source": "Processor.java:273"
        },
        {
          "method": "org.eclipse.aperi.discovery.parser.TSANMLegacyParser$Worker.parse",
          "source": "TSA NMLegacyParser.java:333"
        },
        {
          "method": "org.eclipse.aperi.discovery.parser.Parser.processJob",
          "source": "Parser.java:17"
        },
        {
          "method": "org.eclipse.aperi.discovery.parser.TSANMLegacyParser.run",
          "source": "TSANMLegacyP arser.java:131"
        }
      ],
      "number": 9,
      "commentIndex": 0,
      "bugId": "174837",
      "date": "2007-02-20T19:14:07+01:00",
      "product": "Aperi",
      "component": "aperi.db",
      "severity": "critical"
    },
    {
      "exceptionType": "org.apache.derby.client.am.SqlException",
      "message": "Syntax error: Encountered \"\" at line 1,  column 58.",
      "elements": [
        {
          "method": "org.apache.derby.client.am.Statement.completeSqlca",
          "source": "Unknown Source"
        },
        {
          "method": "org.apache.derby.client.net.NetStatementReply.parsePrepareError",
          "source": "Unkno wn Source"
        },
        {
          "method": "org.apache.derby.client.net.NetStatementReply.parsePRPSQLSTTreply",
          "source": "Unk nown Source"
        },
        {
          "method": "org.apache.derby.client.net.NetStatementReply.readPrepareDescribeOutput",
          "source": "Unknown Source"
        },
        {
          "method": "org.apache.derby.client.net.StatementReply.readPrepareDescribeOutput",
          "source": " Unknown Source"
        },
        {
          "method": "org.apache.derby.client.net.NetStatement.readPrepareDescribeOutput_",
          "source": "U nknown Source"
        },
        {
          "method": "org.apache.derby.client.am.Statement.readPrepareDescribeOutput",
          "source": "Unknow n Source"
        },
        {
          "method": "org.apache.derby.client.am.PreparedStatement.readPrepareDescribeInputOutput",
          "source": "Unknown Source"
        },
        {
          "method": "org.apache.derby.client.am.PreparedStatement.flowPrepareDescribeInputOutput",
          "source": "Unknown Source"
        },
        {
          "method": "org.apache.derby.client.am.PreparedStatement.prepare",
          "source": "Unknown Source"
        },
        {
          "method": "org.apache.derby.client.am.Connection.prepareStatementX",
          "source": "Unknown Sourc e"
        },
        {
          "method": "org.apache.derby.client.am.Connection.prepareStatement",
          "source": "Unknown Source "
        },
        {
          "method": "org.eclipse.aperi.infrastructure.database.DBConnection.prepareStatement",
          "source": "DBConnection.java:418"
        },
        {
          "method": "org.eclipse.aperi.common.dbaccess.ViewReportTablesUpdater.handleUpdate",
          "source": "ViewReportTablesUpdater.java:1633"
        },
        {
          "method": "org.eclipse.aperi.common.dbaccess.ViewReportTablesUpdater.updateOtherTables",
          "source": "ViewReportTablesUpdater.java:1222"
        },
        {
          "method": "org.eclipse.aperi.common.dbaccess.ViewReportTablesUpdater.updateViewTables",
          "source": "ViewReportTablesUpdater.java:1130"
        },
        {
          "method": "org.eclipse.aperi.common.dbaccess.ViewReportTablesUpdater.processView",
          "source": "ViewReportTablesUpdater.java:1034"
        },
        {
          "method": "org.eclipse.aperi.infrastructure.history.detectability.ChangeDetection.complete",
          "source": "ChangeDetection.java:1585"
        },
        {
          "method": "org.eclipse.aperi.discovery.parser.Processor.end",
          "source": "Processor.java:277"
        },
        {
          "method": "org.eclipse.aperi.discovery.parser.TSANMLegacyParser$Worker.parse",
          "source": "TSA NMLegacyParser.java:333"
        },
        {
          "method": "org.eclipse.aperi.discovery.parser.Parser.processJob",
          "source": "Parser.java:17"
        },
        {
          "method": "org.eclipse.aperi.discovery.parser.TSANMLegacyParser.run",
          "source": "TSANMLegacyP arser.java:131"
        }
      ],
      "number": 10,
      "commentIndex": 0,
      "bugId": "174837",
      "date": "2007-02-20T19:14:07+01:00",
      "product": "Aperi",
      "component": "aperi.db",
      "severity": "critical"
    },
    {
      "exceptionType": "org.apache.derby.client.am.SqlException",
      "message": "Syntax error: Encountered \"AND\" at line  1, column 196.",
      "elements": [
        {
          "method": "org.apache.derby.client.am.Statement.completeSqlca",
          "source": "Unknown Source"
        },
        {
          "method": "org.apache.derby.client.net.NetStatementReply.parsePrepareError",
          "source": "Unkno wn Source"
        },
        {
          "method": "org.apache.derby.client.net.NetStatementReply.parsePRPSQLSTTreply",
          "source": "Unk nown Source"
        },
        {
          "method": "org.apache.derby.client.net.NetStatementReply.readPrepareDescribeOutput",
          "source": "Unknown Source"
        },
        {
          "method": "org.apache.derby.client.net.StatementReply.readPrepareDescribeOutput",
          "source": " Unknown Source"
        },
        {
          "method": "org.apache.derby.client.net.NetStatement.readPrepareDescribeOutput_",
          "source": "U nknown Source"
        },
        {
          "method": "org.apache.derby.client.am.Statement.readPrepareDescribeOutput",
          "source": "Unknow n Source"
        },
        {
          "method": "org.apache.derby.client.am.PreparedStatement.readPrepareDescribeInputOutput",
          "source": "Unknown Source"
        },
        {
          "method": "org.apache.derby.client.am.PreparedStatement.flowPrepareDescribeInputOutput",
          "source": "Unknown Source"
        },
        {
          "method": "org.apache.derby.client.am.PreparedStatement.prepare",
          "source": "Unknown Source"
        },
        {
          "method": "org.apache.derby.client.am.Connection.prepareStatementX",
          "source": "Unknown Sourc e"
        },
        {
          "method": "org.apache.derby.client.am.Connection.prepareStatement",
          "source": "Unknown Source "
        },
        {
          "method": "org.eclipse.aperi.infrastructure.database.DBConnection.prepareStatement",
          "source": "DBConnection.java:418"
        },
        {
          "method": "org.eclipse.aperi.common.dbaccess.ViewReportTablesUpdater.handleUpdate",
          "source": "ViewReportTablesUpdater.java:1633"
        },
        {
          "method": "org.eclipse.aperi.common.dbaccess.ViewReportTablesUpdater.updatePort2portTables",
          "source": "ViewReportTablesUpdater.java:1157"
        },
        {
          "method": "org.eclipse.aperi.common.dbaccess.ViewReportTablesUpdater.updateViewTables",
          "source": "ViewReportTablesUpdater.java:1133"
        },
        {
          "method": "org.eclipse.aperi.common.dbaccess.ViewReportTablesUpdater.processView",
          "source": "ViewReportTablesUpdater.java:1040"
        },
        {
          "method": "org.eclipse.aperi.infrastructure.history.detectability.ChangeDetection.complete",
          "source": "ChangeDetection.java:1585"
        },
        {
          "method": "org.eclipse.aperi.discovery.parser.Processor.end",
          "source": "Processor.java:277"
        },
        {
          "method": "org.eclipse.aperi.discovery.parser.TSANMLegacyParser$Worker.parse",
          "source": "TSA NMLegacyParser.java:333"
        },
        {
          "method": "org.eclipse.aperi.discovery.parser.Parser.processJob",
          "source": "Parser.java:17"
        },
        {
          "method": "org.eclipse.aperi.discovery.parser.TSANMLegacyParser.run",
          "source": "TSANMLegacyP arser.java:131"
        }
      ],
      "number": 11,
      "commentIndex": 0,
      "bugId": "174837",
      "date": "2007-02-20T19:14:07+01:00",
      "product": "Aperi",
      "component": "aperi.db",
      "severity": "critical"
    },
    {
      "exceptionType": "org.apache.derby.client.am.SqlException",
      "message": "Syntax error: Encountered \"AND\" at line  1, column 92.",
      "elements": [
        {
          "method": "org.apache.derby.client.am.Statement.completeSqlca",
          "source": "Unknown Source"
        },
        {
          "method": "org.apache.derby.client.net.NetStatementReply.parsePrepareError",
          "source": "Unkno wn Source"
        },
        {
          "method": "org.apache.derby.client.net.NetStatementReply.parsePRPSQLSTTreply",
          "source": "Unk nown Source"
        },
        {
          "method": "org.apache.derby.client.net.NetStatementReply.readPrepareDescribeOutput",
          "source": "Unknown Source"
        },
        {
          "method": "org.apache.derby.client.net.StatementReply.readPrepareDescribeOutput",
          "source": " Unknown Source"
        },
        {
          "method": "org.apache.derby.client.net.NetStatement.readPrepareDescribeOutput_",
          "source": "U nknown Source"
        },
        {
          "method": "org.apache.derby.client.am.Statement.readPrepareDescribeOutput",
          "source": "Unknow n Source"
        },
        {
          "method": "org.apache.derby.client.am.PreparedStatement.readPrepareDescribeInputOutput",
          "source": "Unknown Source"
        },
        {
          "method": "org.apache.derby.client.am.PreparedStatement.flowPrepareDescribeInputOutput",
          "source": "Unknown Source"
        },
        {
          "method": "org.apache.derby.client.am.PreparedStatement.prepare",
          "source": "Unknown Source"
        },
        {
          "method": "org.apache.derby.client.am.Connection.prepareStatementX",
          "source": "Unknown Sourc e"
        },
        {
          "method": "org.apache.derby.client.am.Connection.prepareStatement",
          "source": "Unknown Source "
        },
        {
          "method": "org.eclipse.aperi.infrastructure.database.DBConnection.prepareStatement",
          "source": "DBConnection.java:418"
        },
        {
          "method": "org.eclipse.aperi.common.dbaccess.ViewReportTablesUpdater.handleUpdate",
          "source": "ViewReportTablesUpdater.java:1633"
        },
        {
          "method": "org.eclipse.aperi.common.dbaccess.ViewReportTablesUpdater.updateHostTables",
          "source": "ViewReportTablesUpdater.java:1365"
        },
        {
          "method": "org.eclipse.aperi.common.dbaccess.ViewReportTablesUpdater.updateOtherTables",
          "source": "ViewReportTablesUpdater.java:1275"
        },
        {
          "method": "org.eclipse.aperi.common.dbaccess.ViewReportTablesUpdater.updateViewTables",
          "source": "ViewReportTablesUpdater.java:1130"
        },
        {
          "method": "org.eclipse.aperi.common.dbaccess.ViewReportTablesUpdater.processView",
          "source": "ViewReportTablesUpdater.java:1036"
        },
        {
          "method": "org.eclipse.aperi.infrastructure.history.detectability.ChangeDetection.complete",
          "source": "ChangeDetection.java:1585"
        },
        {
          "method": "org.eclipse.aperi.discovery.parser.Processor.end",
          "source": "Processor.java:277"
        },
        {
          "method": "org.eclipse.aperi.discovery.parser.TSANMLegacyParser$Worker.parse",
          "source": "TSA NMLegacyParser.java:333"
        },
        {
          "method": "org.eclipse.aperi.discovery.parser.Parser.processJob",
          "source": "Parser.java:17"
        },
        {
          "method": "org.eclipse.aperi.discovery.parser.TSANMLegacyParser.run",
          "source": "TSANMLegacyP arser.java:131"
        }
      ],
      "number": 12,
      "commentIndex": 0,
      "bugId": "174837",
      "date": "2007-02-20T19:14:07+01:00",
      "product": "Aperi",
      "component": "aperi.db",
      "severity": "critical"
    },
    {
      "exceptionType": "org.apache.derby.client.am.SqlException",
      "message": "Syntax error: Encountered \")\" at line 1 , column 395.",
      "elements": [
        {
          "method": "org.apache.derby.client.am.Statement.completeSqlca",
          "source": "Unknown Source"
        },
        {
          "method": "org.apache.derby.client.net.NetStatementReply.parsePrepareError",
          "source": "Unkno wn Source"
        },
        {
          "method": "org.apache.derby.client.net.NetStatementReply.parsePRPSQLSTTreply",
          "source": "Unk nown Source"
        },
        {
          "method": "org.apache.derby.client.net.NetStatementReply.readPrepareDescribeOutput",
          "source": "Unknown Source"
        },
        {
          "method": "org.apache.derby.client.net.StatementReply.readPrepareDescribeOutput",
          "source": " Unknown Source"
        },
        {
          "method": "org.apache.derby.client.net.NetStatement.readPrepareDescribeOutput_",
          "source": "U nknown Source"
        },
        {
          "method": "org.apache.derby.client.am.Statement.readPrepareDescribeOutput",
          "source": "Unknow n Source"
        },
        {
          "method": "org.apache.derby.client.am.PreparedStatement.readPrepareDescribeInputOutput",
          "source": "Unknown Source"
        },
        {
          "method": "org.apache.derby.client.am.PreparedStatement.flowPrepareDescribeInputOutput",
          "source": "Unknown Source"
        },
        {
          "method": "org.apache.derby.client.am.PreparedStatement.prepare",
          "source": "Unknown Source"
        },
        {
          "method": "org.apache.derby.client.am.Connection.prepareStatementX",
          "source": "Unknown Sourc e"
        },
        {
          "method": "org.apache.derby.client.am.Connection.prepareStatement",
          "source": "Unknown Source "
        },
        {
          "method": "org.eclipse.aperi.infrastructure.database.DBConnection.prepareStatement",
          "source": "DBConnection.java:418"
        },
        {
          "method": "org.eclipse.aperi.common.dbaccess.ViewReportTablesUpdater.handleUpdate",
          "source": "ViewReportTablesUpdater.java:1633"
        },
        {
          "method": "org.eclipse.aperi.common.dbaccess.ViewReportTablesUpdater.updateSwitchTables",
          "source": "ViewReportTablesUpdater.java:1597"
        },
        {
          "method": "org.eclipse.aperi.common.dbaccess.ViewReportTablesUpdater.updateViewTables",
          "source": "ViewReportTablesUpdater.java:1126"
        },
        {
          "method": "org.eclipse.aperi.common.dbaccess.ViewReportTablesUpdater.processView",
          "source": "ViewReportTablesUpdater.java:1032"
        },
        {
          "method": "org.eclipse.aperi.infrastructure.history.detectability.ChangeDetection.complete",
          "source": "ChangeDetection.java:1585"
        },
        {
          "method": "org.eclipse.aperi.discovery.parser.Processor.end",
          "source": "Processor.java:277"
        },
        {
          "method": "org.eclipse.aperi.discovery.parser.TSANMLegacyParser$Worker.parse",
          "source": "TSA NMLegacyParser.java:333"
        },
        {
          "method": "org.eclipse.aperi.discovery.parser.Parser.processJob",
          "source": "Parser.java:17"
        },
        {
          "method": "org.eclipse.aperi.discovery.parser.TSANMLegacyParser.run",
          "source": "TSANMLegacyP arser.java:131"
        }
      ],
      "number": 13,
      "commentIndex": 0,
      "bugId": "174837",
      "date": "2007-02-20T19:14:07+01:00",
      "product": "Aperi",
      "component": "aperi.db",
      "severity": "critical"
    }
  ],
  "groupId": "174837",
  "bugId": "174837",
  "date": "2007-02-20T19:14:07+01:00",
  "product": "Aperi",
  "component": "aperi.db",
  "severity": "critical"
}