{
  "comments": [
    "I recently wrote my own program to generate reports from command line. The program works fine in eclipse but does not work on HP-UX. I have pasted the error i get when i run the program under unix below. Any Ideas on what is causing the problem. \n\n\njava.lang.ExceptionInInitializerError\n        at org.eclipse.birt.data.engine.odaconsumer.DataTypeUtil.toTypeClass(DataTypeUtil.java:67)\n        at org.eclipse.birt.data.engine.odaconsumer.ResultSetMetaData.getColumnTypeAsJavaClass(ResultSetMetaData.java:230)\n        at org.eclipse.birt.data.engine.odaconsumer.ProjectedColumns.\u003cinit\u003e(ProjectedColumns.java:57)\n        at org.eclipse.birt.data.engine.odaconsumer.PreparedStatement.doGetProjectedColumns(PreparedStatement.java:400)\n        at org.eclipse.birt.data.engine.odaconsumer.PreparedStatement.getProjectedColumns(PreparedStatement.java:340)\n        at org.eclipse.birt.data.engine.odaconsumer.PreparedStatement.setColumnsProjection(PreparedStatement.java:1028)\n        at org.eclipse.birt.data.engine.executor.DataSourceQuery.prepare(DataSourceQuery.java:262)\n        at org.eclipse.birt.data.engine.impl.PreparedOdaDSQuery$OdaDSQueryExecutor.prepareOdiQuery(PreparedOdaDSQuery.java:344\n)\n        at org.eclipse.birt.data.engine.impl.QueryExecutor.prepareExecution(QueryExecutor.java:213)\n        at org.eclipse.birt.data.engine.impl.PreparedQuery.doPrepare(PreparedQuery.java:396)\n        at org.eclipse.birt.data.engine.impl.PreparedDataSourceQuery.execute(PreparedDataSourceQuery.java:145)\n        at org.eclipse.birt.data.engine.impl.PreparedOdaDSQuery.execute(PreparedOdaDSQuery.java:134)\n        at org.eclipse.birt.data.engine.impl.PreparedDataSourceQuery.execute(PreparedDataSourceQuery.java:125)\n        at org.eclipse.birt.report.engine.data.dte.DteDataEngine.doExecuteQuery(DteDataEngine.java:119)\n        at org.eclipse.birt.report.engine.data.dte.AbstractDataEngine.execute(AbstractDataEngine.java:210)\n        at org.eclipse.birt.report.engine.executor.ExecutionContext.executeQuery(ExecutionContext.java:1641)\n        at org.eclipse.birt.report.engine.executor.QueryItemExecutor.executeQuery(QueryItemExecutor.java:62)\n        at org.eclipse.birt.report.engine.executor.TableItemExecutor.execute(TableItemExecutor.java:73)\n        at org.eclipse.birt.report.engine.internal.executor.l18n.LocalizedReportItemExecutor.execute(LocalizedReportItemExecut\nor.java:35)\n        at org.eclipse.birt.report.engine.layout.html.HTMLPageLM.layoutChildren(HTMLPageLM.java:123)\n        at org.eclipse.birt.report.engine.layout.html.HTMLPageLM.layout(HTMLPageLM.java:81)\n        at org.eclipse.birt.report.engine.layout.html.HTMLReportLayoutEngine.layout(HTMLReportLayoutEngine.java:85)\n        at org.eclipse.birt.report.engine.api.impl.RunAndRenderTask.doRun(RunAndRenderTask.java:205)\n        at org.eclipse.birt.report.engine.api.impl.RunAndRenderTask.run(RunAndRenderTask.java:142)\n        at script.BatchReport.runAndRenderReport(BatchReport.java:174)\n        at script.BatchReport.executeReport(BatchReport.java:91)\n        at script.BatchReport.run(BatchReport.java:413)\n        at script.BatchReport.main(BatchReport.java:434)\nCaused by: java.lang.NullPointerException\n        at com.ibm.icu.impl.ICUData.getStream(ICUData.java:70)\n        at com.ibm.icu.impl.ICUData.getStream(ICUData.java:79)\n        at com.ibm.icu.impl.ICUResourceBundleReader.getReader(ICUResourceBundleReader.java:190)\n        at com.ibm.icu.impl.ICUResourceBundleImpl.createBundle(ICUResourceBundleImpl.java:58)\n        at com.ibm.icu.impl.ICUResourceBundle.instantiateBundle(ICUResourceBundle.java:1173)\n        at com.ibm.icu.impl.ICUResourceBundle.getBundleInstance(ICUResourceBundle.java:1140)\n        at com.ibm.icu.util.UResourceBundle.getRootType(UResourceBundle.java:429)\n        at com.ibm.icu.util.UResourceBundle.instantiateBundle(UResourceBundle.java:479)\n        at com.ibm.icu.util.UResourceBundle.getBundleInstance(UResourceBundle.java:127)\n        at com.ibm.icu.util.UResourceBundle.getBundleInstance(UResourceBundle.java:108)\n        at com.ibm.icu.util.UResourceBundle.getBundleInstance(UResourceBundle.java:227)\n        at org.eclipse.birt.core.i18n.ResourceHandle.\u003cinit\u003e(ResourceHandle.java:82)\n        at org.eclipse.birt.core.data.DataTypeUtil.\u003cclinit\u003e(DataTypeUtil.java:54)\n        ... 28 more",
    "Hi Ravi,\n\nIt looks as if org.eclipse.birt.core.data.DataTypeUtil has not be successfully initialized.\n\nI am not sure how you run the program on HP-UX. Do you mean the program is runable in eclipse in windows but failed in eclipse in HP-UX?\n\nAny further information would be helpful.\n\nThanks.\nLin",
    "Hi Ravi,\n\nAs I\u0027ve not received your reply yet, I assume that you have fixed the problem. This bug will be closed. Please feel free to reopen it in case of necessary.\n\nThanks.\nLin"
  ],
  "commentCreationDates": [
    "2007-02-26T17:05:49+01:00",
    "2007-02-27T05:56:47+01:00",
    "2007-03-16T03:55:40+01:00"
  ],
  "traces": [
    {
      "exceptionType": "java.lang.ExceptionInInitializerError",
      "elements": [
        {
          "method": "org.eclipse.birt.data.engine.odaconsumer.DataTypeUtil.toTypeClass",
          "source": "DataTypeUtil.java:67"
        },
        {
          "method": "org.eclipse.birt.data.engine.odaconsumer.ResultSetMetaData.getColumnTypeAsJavaClass",
          "source": "ResultSetMetaData.java:230"
        },
        {
          "method": "org.eclipse.birt.data.engine.odaconsumer.ProjectedColumns.\u003cinit\u003e",
          "source": "ProjectedColumns.java:57"
        },
        {
          "method": "org.eclipse.birt.data.engine.odaconsumer.PreparedStatement.doGetProjectedColumns",
          "source": "PreparedStatement.java:400"
        },
        {
          "method": "org.eclipse.birt.data.engine.odaconsumer.PreparedStatement.getProjectedColumns",
          "source": "PreparedStatement.java:340"
        },
        {
          "method": "org.eclipse.birt.data.engine.odaconsumer.PreparedStatement.setColumnsProjection",
          "source": "PreparedStatement.java:1028"
        },
        {
          "method": "org.eclipse.birt.data.engine.executor.DataSourceQuery.prepare",
          "source": "DataSourceQuery.java:262"
        },
        {
          "method": "org.eclipse.birt.data.engine.impl.PreparedOdaDSQuery$OdaDSQueryExecutor.prepareOdiQuery",
          "source": "PreparedOdaDSQuery.java:344 "
        },
        {
          "method": "org.eclipse.birt.data.engine.impl.QueryExecutor.prepareExecution",
          "source": "QueryExecutor.java:213"
        },
        {
          "method": "org.eclipse.birt.data.engine.impl.PreparedQuery.doPrepare",
          "source": "PreparedQuery.java:396"
        },
        {
          "method": "org.eclipse.birt.data.engine.impl.PreparedDataSourceQuery.execute",
          "source": "PreparedDataSourceQuery.java:145"
        },
        {
          "method": "org.eclipse.birt.data.engine.impl.PreparedOdaDSQuery.execute",
          "source": "PreparedOdaDSQuery.java:134"
        },
        {
          "method": "org.eclipse.birt.data.engine.impl.PreparedDataSourceQuery.execute",
          "source": "PreparedDataSourceQuery.java:125"
        },
        {
          "method": "org.eclipse.birt.report.engine.data.dte.DteDataEngine.doExecuteQuery",
          "source": "DteDataEngine.java:119"
        },
        {
          "method": "org.eclipse.birt.report.engine.data.dte.AbstractDataEngine.execute",
          "source": "AbstractDataEngine.java:210"
        },
        {
          "method": "org.eclipse.birt.report.engine.executor.ExecutionContext.executeQuery",
          "source": "ExecutionContext.java:1641"
        },
        {
          "method": "org.eclipse.birt.report.engine.executor.QueryItemExecutor.executeQuery",
          "source": "QueryItemExecutor.java:62"
        },
        {
          "method": "org.eclipse.birt.report.engine.executor.TableItemExecutor.execute",
          "source": "TableItemExecutor.java:73"
        },
        {
          "method": "org.eclipse.birt.report.engine.internal.executor.l18n.LocalizedReportItemExecutor.execute",
          "source": "LocalizedReportItemExecut or.java:35"
        },
        {
          "method": "org.eclipse.birt.report.engine.layout.html.HTMLPageLM.layoutChildren",
          "source": "HTMLPageLM.java:123"
        },
        {
          "method": "org.eclipse.birt.report.engine.layout.html.HTMLPageLM.layout",
          "source": "HTMLPageLM.java:81"
        },
        {
          "method": "org.eclipse.birt.report.engine.layout.html.HTMLReportLayoutEngine.layout",
          "source": "HTMLReportLayoutEngine.java:85"
        },
        {
          "method": "org.eclipse.birt.report.engine.api.impl.RunAndRenderTask.doRun",
          "source": "RunAndRenderTask.java:205"
        },
        {
          "method": "org.eclipse.birt.report.engine.api.impl.RunAndRenderTask.run",
          "source": "RunAndRenderTask.java:142"
        },
        {
          "method": "script.BatchReport.runAndRenderReport",
          "source": "BatchReport.java:174"
        },
        {
          "method": "script.BatchReport.executeReport",
          "source": "BatchReport.java:91"
        },
        {
          "method": "script.BatchReport.run",
          "source": "BatchReport.java:413"
        },
        {
          "method": "script.BatchReport.main",
          "source": "BatchReport.java:434"
        }
      ],
      "causedBy": {
        "exceptionType": "java.lang.NullPointerException",
        "elements": [
          {
            "method": "com.ibm.icu.impl.ICUData.getStream",
            "source": "ICUData.java:70"
          },
          {
            "method": "com.ibm.icu.impl.ICUData.getStream",
            "source": "ICUData.java:79"
          },
          {
            "method": "com.ibm.icu.impl.ICUResourceBundleReader.getReader",
            "source": "ICUResourceBundleReader.java:190"
          },
          {
            "method": "com.ibm.icu.impl.ICUResourceBundleImpl.createBundle",
            "source": "ICUResourceBundleImpl.java:58"
          },
          {
            "method": "com.ibm.icu.impl.ICUResourceBundle.instantiateBundle",
            "source": "ICUResourceBundle.java:1173"
          },
          {
            "method": "com.ibm.icu.impl.ICUResourceBundle.getBundleInstance",
            "source": "ICUResourceBundle.java:1140"
          },
          {
            "method": "com.ibm.icu.util.UResourceBundle.getRootType",
            "source": "UResourceBundle.java:429"
          },
          {
            "method": "com.ibm.icu.util.UResourceBundle.instantiateBundle",
            "source": "UResourceBundle.java:479"
          },
          {
            "method": "com.ibm.icu.util.UResourceBundle.getBundleInstance",
            "source": "UResourceBundle.java:127"
          },
          {
            "method": "com.ibm.icu.util.UResourceBundle.getBundleInstance",
            "source": "UResourceBundle.java:108"
          },
          {
            "method": "com.ibm.icu.util.UResourceBundle.getBundleInstance",
            "source": "UResourceBundle.java:227"
          },
          {
            "method": "org.eclipse.birt.core.i18n.ResourceHandle.\u003cinit\u003e",
            "source": "ResourceHandle.java:82"
          },
          {
            "method": "org.eclipse.birt.core.data.DataTypeUtil.\u003cclinit\u003e",
            "source": "DataTypeUtil.java:54"
          }
        ],
        "number": 0,
        "commentIndex": 0
      },
      "number": 0,
      "commentIndex": 0,
      "bugId": "175565",
      "date": "2007-02-26T17:05:49+01:00",
      "product": "BIRT",
      "component": "Data",
      "severity": "normal"
    }
  ],
  "groupId": "175565",
  "bugId": "175565",
  "date": "2007-02-26T17:05:49+01:00",
  "product": "BIRT",
  "component": "Data",
  "severity": "normal"
}