{
  "comments": [
    "My project is hosed.  Even cleaning and getting rid of metadata won\u0027t get rid of this exception on building.  UTR on the command line.  Sorry, no time to narrow.  Don\u0027t say I never did nothin\u0027 for you.\n\n--------------------------------------\n\n-------------------- DirtyTracking.java\n\n/**\n * DirtyTracking\n */\npublic class DirtyTracking {\n    public static void main(String[] args) {  \n        \n    }\n        C c \u003d new C();\n        c.run();\n        c.run();\n        c.clearCached();\n        c.run();\n        new B().run();\n        new B().run();\n    }\n    static class B implements TrackingCached.ICachedTracked {\n        boolean run;\n        void run() {\n            run \u003d true;\n        }\n    }\n    static class C {\n        long time;\n        void run() {\n            time \u003d System.currentTimeMillis();\n        }\n    }\n    /**\n     * We\u0027d like to track in C\n     */\n    static aspect TrackingC {\n        declare parents: C implements TrackingCached.ICachedTracked;\n    }\n\n    /** \n     * Track dirtiness in any ICachedTracked implementation.\n     */\n    static aspect TrackingCached {\n        public interface ICachedTracked {};\n        boolean ICachedTracked.cached \u003d true;\n        public boolean ICachedTracked.getCached() {\n            return cached;\n        }\n        void ICachedTracked.clearCached() {\n            if (!cached) {\n                cached \u003d true;\n            } \n        }\n        after(ICachedTracked tracked) returning : target(tracked) \n                \u0026\u0026 set(* *)  \u0026\u0026 !set(boolean ICachedTracked.cache) {\n            if (tracked.cached) {\n                tracked.cached \u003d false;\n            }\n        }\n    }\n\n    /** signal when something is out of sync wrt the cache */\n    static aspect SignalCacheIncoherence {\n        before(TrackingCached.ICachedTracked tracked, Boolean arg) : \n            set(boolean TrackingCached.ICachedTracked.cached)\n            \u0026\u0026 args(arg) \u0026\u0026 target(tracked) \u0026\u0026 if(!arg.booleanValue()) {\n            System.out.println(tracked + \" changed from cache\");\n        }\n    }\n    static aspect trace {\n        before() : withincode(void main(String[])) || within(TrackingCached) {\n            System.out.println(\"---- \" + thisJoinPointStaticPart);\n        }\n    }\n}\n\n\n\n---------------- Also getting message\neclipse.buildId\u003dM20060921-0945\njava.version\u003d1.5.0_06\njava.vendor\u003dSun Microsystems Inc.\nBootLoader constants: OS\u003dwin32, ARCH\u003dx86, WS\u003dwin32, NL\u003den_US\nCommand-line arguments:  -os win32 -ws win32 -arch x86 -clean -data c:\\home\\ws\\main-31\n\nError\nTue Feb 27 21:28:15 PST 2007\nProblems occurred when invoking code from plug-in: \"org.eclipse.jdt.ui\".\n\njava.lang.NoSuchMethodError: org.eclipse.jdt.internal.compiler.problem.DefaultProblem.\u003cinit\u003e([CLjava/lang/String;I[Ljava/lang/String;IIII)V\n\tat org.eclipse.ajdt.internal.ui.editor.CompilationUnitAnnotationModelWrapper.beginReporting(CompilationUnitAnnotationModelWrapper.java:244)\n\tat org.eclipse.jdt.internal.core.JavaModelManager$PerWorkingCopyInfo.beginReporting(JavaModelManager.java:988)\n\tat org.eclipse.jdt.internal.core.ReconcileWorkingCopyOperation.executeOperation(ReconcileWorkingCopyOperation.java:84)\n\tat org.eclipse.jdt.internal.core.JavaModelOperation.run(JavaModelOperation.java:720)\n\tat org.eclipse.jdt.internal.core.JavaModelOperation.runOperation(JavaModelOperation.java:779)\n\tat org.eclipse.jdt.internal.core.CompilationUnit.reconcile(CompilationUnit.java:1122)\n\tat org.eclipse.jdt.internal.ui.text.java.JavaReconcilingStrategy$1.run(JavaReconcilingStrategy.java:97)\n\tat org.eclipse.core.runtime.SafeRunner.run(SafeRunner.java:37)\n\tat org.eclipse.jdt.internal.ui.text.java.JavaReconcilingStrategy.reconcile(JavaReconcilingStrategy.java:82)\n\tat org.eclipse.jdt.internal.ui.text.java.JavaReconcilingStrategy.reconcile(JavaReconcilingStrategy.java:145)\n\tat org.eclipse.jdt.internal.ui.text.CompositeReconcilingStrategy.reconcile(CompositeReconcilingStrategy.java:86)\n\tat org.eclipse.jdt.internal.ui.text.JavaCompositeReconcilingStrategy.reconcile(JavaCompositeReconcilingStrategy.java:94)\n\tat org.eclipse.jface.text.reconciler.MonoReconciler.process(MonoReconciler.java:75)\n\tat org.eclipse.jdt.internal.ui.text.JavaReconciler.process(JavaReconciler.java:342)\n\tat org.eclipse.jface.text.reconciler.AbstractReconciler$BackgroundThread.run(AbstractReconciler.java:204)",
    "Created an attachment (id\u003d59944)\nsweet nothings whispered from AJDT\n\n",
    "The NoSuchMethodError is caused by a mismatch between Eclipse and AJDT versions.\nPlease try either Eclipse 3.2.2 and the latest dev build of AJDT 1.4.2 (1.4.2.200703020612) or alternatively Eclipse 3.3M5 and the latest dev build of AJDT 1.5, then reopen this bug if you still get the bcel exception.\n\n"
  ],
  "commentCreationDates": [
    "2007-02-28T05:35:53+01:00",
    "2007-02-28T05:39:04+01:00",
    "2007-03-02T13:51:31+01:00"
  ],
  "traces": [
    {
      "exceptionType": "java.lang.NoSuchMethodError",
      "message": "org.eclipse.jdt.internal.compiler.problem.DefaultProblem.\u003cinit\u003e([CLjava/lang/String;I[Ljava/lang/String;IIII)V",
      "elements": [
        {
          "method": "org.eclipse.ajdt.internal.ui.editor.CompilationUnitAnnotationModelWrapper.beginReporting",
          "source": "CompilationUnitAnnotationModelWrapper.java:244"
        },
        {
          "method": "org.eclipse.jdt.internal.core.JavaModelManager$PerWorkingCopyInfo.beginReporting",
          "source": "JavaModelManager.java:988"
        },
        {
          "method": "org.eclipse.jdt.internal.core.ReconcileWorkingCopyOperation.executeOperation",
          "source": "ReconcileWorkingCopyOperation.java:84"
        },
        {
          "method": "org.eclipse.jdt.internal.core.JavaModelOperation.run",
          "source": "JavaModelOperation.java:720"
        },
        {
          "method": "org.eclipse.jdt.internal.core.JavaModelOperation.runOperation",
          "source": "JavaModelOperation.java:779"
        },
        {
          "method": "org.eclipse.jdt.internal.core.CompilationUnit.reconcile",
          "source": "CompilationUnit.java:1122"
        },
        {
          "method": "org.eclipse.jdt.internal.ui.text.java.JavaReconcilingStrategy$1.run",
          "source": "JavaReconcilingStrategy.java:97"
        },
        {
          "method": "org.eclipse.core.runtime.SafeRunner.run",
          "source": "SafeRunner.java:37"
        },
        {
          "method": "org.eclipse.jdt.internal.ui.text.java.JavaReconcilingStrategy.reconcile",
          "source": "JavaReconcilingStrategy.java:82"
        },
        {
          "method": "org.eclipse.jdt.internal.ui.text.java.JavaReconcilingStrategy.reconcile",
          "source": "JavaReconcilingStrategy.java:145"
        },
        {
          "method": "org.eclipse.jdt.internal.ui.text.CompositeReconcilingStrategy.reconcile",
          "source": "CompositeReconcilingStrategy.java:86"
        },
        {
          "method": "org.eclipse.jdt.internal.ui.text.JavaCompositeReconcilingStrategy.reconcile",
          "source": "JavaCompositeReconcilingStrategy.java:94"
        },
        {
          "method": "org.eclipse.jface.text.reconciler.MonoReconciler.process",
          "source": "MonoReconciler.java:75"
        },
        {
          "method": "org.eclipse.jdt.internal.ui.text.JavaReconciler.process",
          "source": "JavaReconciler.java:342"
        },
        {
          "method": "org.eclipse.jface.text.reconciler.AbstractReconciler$BackgroundThread.run",
          "source": "AbstractReconciler.java:204"
        }
      ],
      "number": 0,
      "commentIndex": 0,
      "bugId": "175787",
      "date": "2007-02-28T05:35:53+01:00",
      "product": "AJDT",
      "component": "Core",
      "severity": "normal"
    }
  ],
  "groupId": "175787",
  "bugId": "175787",
  "date": "2007-02-28T05:35:53+01:00",
  "product": "AJDT",
  "component": "Core",
  "severity": "normal"
}