{
  "comments": [
    "Description:\nDocument can not be generated through runtime package.\n\nSteps to reproduce:\n1. Get runtime package.\n2. Deploy birt use frameset to preview or use genReport.bat to generate document\n\nExpected result:\nFrameset servlet works ok or document can be generated.\n\nActual result:\nNoClassDefFoundException.\n\nError log:\nException in thread \"main\" java.lang.NoClassDefFoundError: org/eclipse/birt/core\n/archive/compound/ArchiveWriter\n        at java.lang.ClassLoader.defineClass1(Native Method)\n        at java.lang.ClassLoader.defineClass(ClassLoader.java:620)\n        at java.security.SecureClassLoader.defineClass(SecureClassLoader.java:12\n4)\n        at java.net.URLClassLoader.defineClass(URLClassLoader.java:260)\n        at java.net.URLClassLoader.access$100(URLClassLoader.java:56)\n        at java.net.URLClassLoader$1.run(URLClassLoader.java:195)\n        at java.security.AccessController.doPrivileged(Native Method)\n        at java.net.URLClassLoader.findClass(URLClassLoader.java:188)\n        at java.lang.ClassLoader.loadClass(ClassLoader.java:306)\n        at sun.misc.Launcher$AppClassLoader.loadClass(Launcher.java:268)\n        at java.lang.ClassLoader.loadClass(ClassLoader.java:251)\n        at org.eclipse.birt.core.framework.osgi.OSGILauncher$ChildFirstURLClassL\noader.loadClass(OSGILauncher.java:634)\n        at java.lang.ClassLoader.loadClass(ClassLoader.java:251)\n        at org.eclipse.osgi.framework.internal.core.SystemBundleLoader.findLocal\nClass(SystemBundleLoader.java:66)\n        at org.eclipse.osgi.framework.internal.core.SingleSourcePackage.loadClas\ns(SingleSourcePackage.java:37)\n        at org.eclipse.osgi.framework.internal.core.MultiSourcePackage.loadClass\n(MultiSourcePackage.java:31)\n        at org.eclipse.osgi.framework.internal.core.BundleLoader.findClassIntern\nal(BundleLoader.java:405)\n        at org.eclipse.osgi.framework.internal.core.BundleLoader.findClass(Bundl\neLoader.java:369)\n        at org.eclipse.osgi.framework.internal.core.BundleLoader.findClass(Bundl\neLoader.java:357)\n        at org.eclipse.osgi.internal.baseadaptor.DefaultClassLoader.loadClass(De\nfaultClassLoader.java:83)\n        at java.lang.ClassLoader.loadClass(ClassLoader.java:251)\n        at java.lang.ClassLoader.loadClassInternal(ClassLoader.java:319)\n        at org.eclipse.birt.report.engine.api.impl.RunTask.run(RunTask.java:104)\n\n        at org.eclipse.birt.report.engine.api.ReportRunner.runReport(ReportRunne\nr.java:251)\n        at org.eclipse.birt.report.engine.api.ReportRunner.execute(ReportRunner.\njava:153)\n        at org.eclipse.birt.report.engine.api.ReportRunner.main(ReportRunner.jav\na:117)",
    "Fixed.\nAdd classes in archive/compound to customBuildCallbacks.xml.",
    "Verify in build 2.2.0.v200703021053."
  ],
  "commentCreationDates": [
    "2007-03-01T07:01:14+01:00",
    "2007-03-01T09:27:40+01:00",
    "2007-03-02T03:52:35+01:00"
  ],
  "traces": [
    {
      "exceptionType": "java.lang.NoClassDefFoundError",
      "message": "org/eclipse/birt/core /archive/compound/ArchiveWriter",
      "elements": [
        {
          "method": "java.lang.ClassLoader.defineClass1",
          "source": "Native Method"
        },
        {
          "method": "java.lang.ClassLoader.defineClass",
          "source": "ClassLoader.java:620"
        },
        {
          "method": "java.security.SecureClassLoader.defineClass",
          "source": "SecureClassLoader.java:12 4"
        },
        {
          "method": "java.net.URLClassLoader.defineClass",
          "source": "URLClassLoader.java:260"
        },
        {
          "method": "java.net.URLClassLoader.access$100",
          "source": "URLClassLoader.java:56"
        },
        {
          "method": "java.net.URLClassLoader$1.run",
          "source": "URLClassLoader.java:195"
        },
        {
          "method": "java.security.AccessController.doPrivileged",
          "source": "Native Method"
        },
        {
          "method": "java.net.URLClassLoader.findClass",
          "source": "URLClassLoader.java:188"
        },
        {
          "method": "java.lang.ClassLoader.loadClass",
          "source": "ClassLoader.java:306"
        },
        {
          "method": "sun.misc.Launcher$AppClassLoader.loadClass",
          "source": "Launcher.java:268"
        },
        {
          "method": "java.lang.ClassLoader.loadClass",
          "source": "ClassLoader.java:251"
        },
        {
          "method": "org.eclipse.birt.core.framework.osgi.OSGILauncher$ChildFirstURLClassLoader.loadClass",
          "source": "OSGILauncher.java:634"
        },
        {
          "method": "java.lang.ClassLoader.loadClass",
          "source": "ClassLoader.java:251"
        },
        {
          "method": "org.eclipse.osgi.framework.internal.core.SystemBundleLoader.findLocalClass",
          "source": "SystemBundleLoader.java:66"
        },
        {
          "method": "org.eclipse.osgi.framework.internal.core.SingleSourcePackage.loadClass",
          "source": "SingleSourcePackage.java:37"
        },
        {
          "method": "org.eclipse.osgi.framework.internal.core.MultiSourcePackage.loadClass",
          "source": "MultiSourcePackage.java:31"
        },
        {
          "method": "org.eclipse.osgi.framework.internal.core.BundleLoader.findClassInternal",
          "source": "BundleLoader.java:405"
        },
        {
          "method": "org.eclipse.osgi.framework.internal.core.BundleLoader.findClass",
          "source": "Bundl eLoader.java:369"
        },
        {
          "method": "org.eclipse.osgi.framework.internal.core.BundleLoader.findClass",
          "source": "Bundl eLoader.java:357"
        },
        {
          "method": "org.eclipse.osgi.internal.baseadaptor.DefaultClassLoader.loadClass",
          "source": "De faultClassLoader.java:83"
        },
        {
          "method": "java.lang.ClassLoader.loadClass",
          "source": "ClassLoader.java:251"
        },
        {
          "method": "java.lang.ClassLoader.loadClassInternal",
          "source": "ClassLoader.java:319"
        },
        {
          "method": "org.eclipse.birt.report.engine.api.impl.RunTask.run",
          "source": "RunTask.java:104"
        },
        {
          "method": "org.eclipse.birt.report.engine.api.ReportRunner.runReport",
          "source": "ReportRunne r.java:251"
        },
        {
          "method": "org.eclipse.birt.report.engine.api.ReportRunner.execute",
          "source": "ReportRunner. java:153"
        },
        {
          "method": "org.eclipse.birt.report.engine.api.ReportRunner.main",
          "source": "ReportRunner.jav a:117"
        }
      ],
      "number": 0,
      "commentIndex": 0,
      "bugId": "175982",
      "date": "2007-03-01T07:01:14+01:00",
      "product": "BIRT",
      "component": "Report Engine",
      "severity": "major"
    }
  ],
  "groupId": "175982",
  "bugId": "175982",
  "date": "2007-03-01T07:01:14+01:00",
  "product": "BIRT",
  "component": "Report Engine",
  "severity": "major"
}