{
  "comments": [
    "Build ID: M20070212-1330\n\nSteps To Reproduce:\n1.install IBM JRE 5 in Power PC based system with Linux\n2.extract the \"eclipse-SDK-3.2.2-linux-gtk-ppc.tar.tar\"\n3.Launch the eclipse by using \n./eclipse -vmargs -Djava.compiler\u003dnone or just ./eclipse\n\n\nMore information:\nI Downloaded the Eclipse 3.2.2 for power pc from Eclipse site, the name of the tar file is \n\"eclipse-SDK-3.2.2-linux-gtk-ppc.tar.tar\". I extarcted this into /usr/local/ide/ \nMy Linux server is a power PC based machine (not x86/Intel), and IBM JRE 1.5 \u0026 1.4 installed in it under the following locations\n\nJRE 1.5   ---- /opt/ibm/java2-ppc64-50/jre/bin\nJRE 1.4.2 ---- /opt/IBMJava2-ppc64-142/jre/bin/\n\nI have \"/opt/ibm/java2-ppc64-50/jre/bin\" in PATH also.\n\nI am trying to connect the linux server by using the putty from the windows xp machine, and installed the XServer (Xming) in my windows xp machine which will help to see the GUI aplications of Linux Server on windows desk top.\n\nThen I did cd /usr/local/ide/eclipse \nThere I have launched the eclipse by using the following command\n\"./eclipse -vmargs -Djava.compiler\u003dnone\"(Found this option while downloading the eclipse).\n\nBut the eclipse is not launched, it gives the error window saying that \"An error has occured, see the log file under \"/home/userdir/workspace/.metadata/.log\".\nThe log file contains the following error.\nI tried in many different ways by giving the options for eclipse as  \"-vmargs -Djava.compiler\u003dnone\" , given the JRE 1.4 as -VM arguement, increased the heap size (XMx) so on.\n\n!SESSION 2007-02-27 19:15:13.631 -----------------------------------------------\neclipse.buildId\u003dM20070212-1330\njava.fullversion\u003dJ2RE 1.5.0 IBM J9 2.3 Linux ppc64-64 j9vmxp6423-20061001 (JIT e\nnabled)\nJ9VM - 20060915_08260_BHdSMr\nJIT  - 20060908_1811_r8\nGC   - 20060906_AA\nBootLoader constants: OS\u003dlinux, ARCH\u003dppc, WS\u003dgtk, NL\u003den_US\nCommand-line arguments:  -os linux -ws gtk -arch ppc\n\n!ENTRY org.eclipse.osgi 4 0 2007-02-27 19:15:15.458\n!MESSAGE Application error\n!STACK 1\njava.lang.UnsatisfiedLinkError: /usr/local/ide/eclipse/configuration/org.eclipse\n.osgi/bundles/87/1/.cp/libswt-pi-gtk-3236.so (/usr/local/ide/eclipse/configurati\non/org.eclipse.osgi/bundles/87/1/.cp/libswt-pi-gtk-3236.so: cannot open shared o\nbject file: No such file or directory)\n        at java.lang.ClassLoader.loadLibraryWithPath(ClassLoader.java:956)\n        at java.lang.ClassLoader.loadLibraryWithClassLoader(ClassLoader.java:921\n)\n        at java.lang.System.loadLibrary(System.java:452)\n        at org.eclipse.swt.internal.Library.loadLibrary(Library.java:123)\n        at org.eclipse.swt.internal.gtk.OS.\u003cclinit\u003e(OS.java:22)\n        at java.lang.J9VMInternals.initializeImpl(Native Method)\n        at java.lang.J9VMInternals.initialize(J9VMInternals.java:177)\n        at org.eclipse.swt.internal.Converter.wcsToMbcs(Converter.java:63)\n        at org.eclipse.swt.internal.Converter.wcsToMbcs(Converter.java:54)\n        at org.eclipse.swt.widgets.Display.\u003cclinit\u003e(Display.java:126)\n        at java.lang.J9VMInternals.initializeImpl(Native Method)\n        at java.lang.J9VMInternals.initialize(J9VMInternals.java:177)\n        at org.eclipse.ui.internal.Workbench.createDisplay(Workbench.java:436)\n        at org.eclipse.ui.PlatformUI.createDisplay(PlatformUI.java:161)\n        at org.eclipse.ui.internal.ide.IDEApplication.createDisplay(IDEApplicati\non.java:122)\n        at org.eclipse.ui.internal.ide.IDEApplication.run(IDEApplication.java:75\n)\n        at org.eclipse.core.internal.runtime.PlatformActivator$1.run(PlatformAct\nivator.java:78)\n        at org.eclipse.core.runtime.internal.adaptor.EclipseAppLauncher.runAppli\ncation(EclipseAppLauncher.java:92)\n        at org.eclipse.core.runtime.internal.adaptor.EclipseAppLauncher.start(Ec\nlipseAppLauncher.java:68)\n        at org.eclipse.core.runtime.adaptor.EclipseStarter.run(EclipseStarter.ja\nva:400)\n        at org.eclipse.core.runtime.adaptor.EclipseStarter.run(EclipseStarter.ja\nva:177)\n        at sun.reflect.NativeMethodAccessorImpl.invoke0(Native Method)\n        at sun.reflect.NativeMethodAccessorImpl.invoke(NativeMethodAccessorImpl.\njava:64)\n        at sun.reflect.DelegatingMethodAccessorImpl.invoke(DelegatingMethodAcces\nsorImpl.java:43)",
    "Looks like a problem loading the SWT library. Moving to SWT.",
    "First a detail, the downloaded file should have been eclipse-SDK-3.2.2-linux-gtk-ppc.tar.gz not eclipse-SDK-3.2.2-linux-gtk-ppc.tar.tar.  I assume this was just a typo.\n\nDoes the following indicate any dependent libraries are missing?\n%\u003e cd /usr/local/ide/eclipse/configuration/org.eclipse.osgi/bundles/87/1/.cp/\n%\u003e ldd libswt-pi-gtk-3236.so\n",
    "Just wanted to point out that you are forgetting an argument in your startup. Even if you got your vm issue sorted out, Eclipse would not be able to open a workspace.\n\nFrom the Eclipse 3.2.2 PPC download click through:\n\nEclipse fails to create a lock file with reason \"No locks available.\"  To launch eclipse you must disable file \nlocking using the osgi.locking property. For example, you could launch eclipse as follows:\n\n\"eclipse -vmargs -Dosgi.locking\u003dnone\".\n",
    "You\u0027re using a 64 bit VM.\nTry using a 32 bit VM instead.",
    "Please try running with the 32 bit JVM. BTW, if you are using the IBM 5 JRE, you might need to use the -Xnojit option (see Bug 116730)."
  ],
  "commentCreationDates": [
    "2007-03-05T09:39:54+01:00",
    "2007-04-25T20:10:22+02:00",
    "2007-05-08T23:46:37+02:00",
    "2007-05-09T15:38:29+02:00",
    "2007-05-11T22:34:05+02:00",
    "2007-05-14T16:27:58+02:00"
  ],
  "traces": [
    {
      "exceptionType": "java.lang.UnsatisfiedLinkError",
      "message": "/usr/local/ide/eclipse/configuration/org.eclipse .osgi/bundles/87/1/.cp/libswt-pi-gtk-3236.so (/usr/local/ide/eclipse/configurati on/org.eclipse.osgi/bundles/87/1/.cp/libswt-pi-gtk-3236.so: cannot open shared o bject file: No such file or directory)",
      "elements": [
        {
          "method": "java.lang.ClassLoader.loadLibraryWithPath",
          "source": "ClassLoader.java:956"
        },
        {
          "method": "java.lang.ClassLoader.loadLibraryWithClassLoader",
          "source": "ClassLoader.java:921 "
        },
        {
          "method": "java.lang.System.loadLibrary",
          "source": "System.java:452"
        },
        {
          "method": "org.eclipse.swt.internal.Library.loadLibrary",
          "source": "Library.java:123"
        },
        {
          "method": "org.eclipse.swt.internal.gtk.OS.\u003cclinit\u003e",
          "source": "OS.java:22"
        },
        {
          "method": "java.lang.J9VMInternals.initializeImpl",
          "source": "Native Method"
        },
        {
          "method": "java.lang.J9VMInternals.initialize",
          "source": "J9VMInternals.java:177"
        },
        {
          "method": "org.eclipse.swt.internal.Converter.wcsToMbcs",
          "source": "Converter.java:63"
        },
        {
          "method": "org.eclipse.swt.internal.Converter.wcsToMbcs",
          "source": "Converter.java:54"
        },
        {
          "method": "org.eclipse.swt.widgets.Display.\u003cclinit\u003e",
          "source": "Display.java:126"
        },
        {
          "method": "java.lang.J9VMInternals.initializeImpl",
          "source": "Native Method"
        },
        {
          "method": "java.lang.J9VMInternals.initialize",
          "source": "J9VMInternals.java:177"
        },
        {
          "method": "org.eclipse.ui.internal.Workbench.createDisplay",
          "source": "Workbench.java:436"
        },
        {
          "method": "org.eclipse.ui.PlatformUI.createDisplay",
          "source": "PlatformUI.java:161"
        },
        {
          "method": "org.eclipse.ui.internal.ide.IDEApplication.createDisplay",
          "source": "IDEApplicati on.java:122"
        },
        {
          "method": "org.eclipse.ui.internal.ide.IDEApplication.run",
          "source": "IDEApplication.java:75 "
        },
        {
          "method": "org.eclipse.core.internal.runtime.PlatformActivator$1.run",
          "source": "PlatformAct ivator.java:78"
        },
        {
          "method": "org.eclipse.core.runtime.internal.adaptor.EclipseAppLauncher.runApplication",
          "source": "EclipseAppLauncher.java:92"
        },
        {
          "method": "org.eclipse.core.runtime.internal.adaptor.EclipseAppLauncher.start",
          "source": "Ec lipseAppLauncher.java:68"
        },
        {
          "method": "org.eclipse.core.runtime.adaptor.EclipseStarter.run",
          "source": "EclipseStarter.ja va:400"
        },
        {
          "method": "org.eclipse.core.runtime.adaptor.EclipseStarter.run",
          "source": "EclipseStarter.ja va:177"
        },
        {
          "method": "sun.reflect.NativeMethodAccessorImpl.invoke0",
          "source": "Native Method"
        },
        {
          "method": "sun.reflect.NativeMethodAccessorImpl.invoke",
          "source": "NativeMethodAccessorImpl. java:64"
        },
        {
          "method": "sun.reflect.DelegatingMethodAccessorImpl.invoke",
          "source": "DelegatingMethodAcces sorImpl.java:43"
        }
      ],
      "number": 0,
      "commentIndex": 0,
      "bugId": "176349",
      "date": "2007-03-05T09:39:54+01:00",
      "product": "Platform",
      "component": "SWT",
      "severity": "major"
    }
  ],
  "groupId": "176349",
  "bugId": "176349",
  "date": "2007-03-05T09:39:54+01:00",
  "product": "Platform",
  "component": "SWT",
  "severity": "major"
}