{
  "comments": [
    "How can I find out, which reference is broken, from such exception? Please always specify argument in such exceptions. Thanks\n\n13:26:19,300 ERROR [STDERR] 12.3.2007 13:26:19 org.eclipse.birt.report.engine.data.dte.DteResultSet next\nSEVERE: Some columns reference in column binding do not exist.\norg.eclipse.birt.data.engine.core.DataException: Some columns reference in column binding do not exist.\n        at org.eclipse.birt.data.engine.executor.ResultClass.doSave(ResultClass.java:196)\n        at org.eclipse.birt.data.engine.executor.transform.CachedResultSet.doSave(CachedResultSet.java:225)\n        at org.eclipse.birt.data.engine.impl.document.RDSaveUtil.saveForGeneration(RDSaveUtil.java:95)\n        at org.eclipse.birt.data.engine.impl.document.RDSaveUtil.saveResultIterator(RDSaveUtil.java:60)\n        at org.eclipse.birt.data.engine.impl.document.RDSave.saveResultIterator(RDSave.java:160)\n        at org.eclipse.birt.data.engine.impl.ResultIterator$RDSaveHelper.doSave(ResultIterator.java:788)\n        at org.eclipse.birt.data.engine.impl.ResultIterator$RDSaveHelper.doSaveExpr(ResultIterator.java:753)\n        at org.eclipse.birt.data.engine.impl.BindingColumnsEvalUtil.getColumnsValue(BindingColumnsEvalUtil.java:160)\n        at org.eclipse.birt.data.engine.impl.ResultIterator.prepareCurrentRow(ResultIterator.java:338)\n        at org.eclipse.birt.data.engine.impl.ResultIterator.next(ResultIterator.java:192)\n        at org.eclipse.birt.report.engine.data.dte.DteResultSet.next(DteResultSet.java:195)\n        at org.eclipse.birt.report.engine.executor.QueryItemExecutor.executeQuery(QueryItemExecutor.java:65)\n        at org.eclipse.birt.report.engine.executor.TableItemExecutor.execute(TableItemExecutor.java:73)\n        at org.eclipse.birt.report.engine.layout.html.HTMLPageLM.layoutChildren(HTMLPageLM.java:123)\n        at org.eclipse.birt.report.engine.layout.html.HTMLPageLM.layout(HTMLPageLM.java:81)\n        at org.eclipse.birt.report.engine.layout.html.HTMLReportLayoutEngine.layout(HTMLReportLayoutEngine.java:85)\n        at org.eclipse.birt.report.engine.presentation.ReportDocumentBuilder.build(ReportDocumentBuilder.java:143)\n        at org.eclipse.birt.report.engine.api.impl.RunTask.doRun(RunTask.java:241)\n        at org.eclipse.birt.report.engine.api.impl.RunTask.run(RunTask.java:140)",
    "Collect the invalid column reference names and throw an exception to notify the end user which columns are broken."
  ],
  "commentCreationDates": [
    "2007-03-12T13:42:36+01:00",
    "2007-03-20T04:34:25+01:00"
  ],
  "traces": [
    {
      "exceptionType": "org.eclipse.birt.data.engine.core.DataException",
      "message": "Some columns reference in column binding do not exist.",
      "elements": [
        {
          "method": "org.eclipse.birt.data.engine.executor.ResultClass.doSave",
          "source": "ResultClass.java:196"
        },
        {
          "method": "org.eclipse.birt.data.engine.executor.transform.CachedResultSet.doSave",
          "source": "CachedResultSet.java:225"
        },
        {
          "method": "org.eclipse.birt.data.engine.impl.document.RDSaveUtil.saveForGeneration",
          "source": "RDSaveUtil.java:95"
        },
        {
          "method": "org.eclipse.birt.data.engine.impl.document.RDSaveUtil.saveResultIterator",
          "source": "RDSaveUtil.java:60"
        },
        {
          "method": "org.eclipse.birt.data.engine.impl.document.RDSave.saveResultIterator",
          "source": "RDSave.java:160"
        },
        {
          "method": "org.eclipse.birt.data.engine.impl.ResultIterator$RDSaveHelper.doSave",
          "source": "ResultIterator.java:788"
        },
        {
          "method": "org.eclipse.birt.data.engine.impl.ResultIterator$RDSaveHelper.doSaveExpr",
          "source": "ResultIterator.java:753"
        },
        {
          "method": "org.eclipse.birt.data.engine.impl.BindingColumnsEvalUtil.getColumnsValue",
          "source": "BindingColumnsEvalUtil.java:160"
        },
        {
          "method": "org.eclipse.birt.data.engine.impl.ResultIterator.prepareCurrentRow",
          "source": "ResultIterator.java:338"
        },
        {
          "method": "org.eclipse.birt.data.engine.impl.ResultIterator.next",
          "source": "ResultIterator.java:192"
        },
        {
          "method": "org.eclipse.birt.report.engine.data.dte.DteResultSet.next",
          "source": "DteResultSet.java:195"
        },
        {
          "method": "org.eclipse.birt.report.engine.executor.QueryItemExecutor.executeQuery",
          "source": "QueryItemExecutor.java:65"
        },
        {
          "method": "org.eclipse.birt.report.engine.executor.TableItemExecutor.execute",
          "source": "TableItemExecutor.java:73"
        },
        {
          "method": "org.eclipse.birt.report.engine.layout.html.HTMLPageLM.layoutChildren",
          "source": "HTMLPageLM.java:123"
        },
        {
          "method": "org.eclipse.birt.report.engine.layout.html.HTMLPageLM.layout",
          "source": "HTMLPageLM.java:81"
        },
        {
          "method": "org.eclipse.birt.report.engine.layout.html.HTMLReportLayoutEngine.layout",
          "source": "HTMLReportLayoutEngine.java:85"
        },
        {
          "method": "org.eclipse.birt.report.engine.presentation.ReportDocumentBuilder.build",
          "source": "ReportDocumentBuilder.java:143"
        },
        {
          "method": "org.eclipse.birt.report.engine.api.impl.RunTask.doRun",
          "source": "RunTask.java:241"
        },
        {
          "method": "org.eclipse.birt.report.engine.api.impl.RunTask.run",
          "source": "RunTask.java:140"
        }
      ],
      "number": 0,
      "commentIndex": 0,
      "bugId": "176979",
      "date": "2007-03-12T13:42:36+01:00",
      "product": "BIRT",
      "component": "Data",
      "severity": "normal"
    }
  ],
  "groupId": "176979",
  "bugId": "176979",
  "date": "2007-03-12T13:42:36+01:00",
  "product": "BIRT",
  "component": "Data",
  "severity": "normal"
}