{
  "comments": [
    "Hi,\nI work upon aplication in SWT. When I try to put more then 48 layers of Composite I receive SWTError: No more hendles.\n\nSimple example to reproduce:\n\nimport org.eclipse.swt.SWT;\nimport org.eclipse.swt.SWTError;\nimport org.eclipse.swt.graphics.Point;\nimport org.eclipse.swt.layout.FillLayout;\nimport org.eclipse.swt.widgets.Composite;\nimport org.eclipse.swt.widgets.Display;\nimport org.eclipse.swt.widgets.Shell;\npublic class NoMoreHandlesError {\n    public static void main(String[] args) {\n        int layer \u003d 0;\n        try {\n            final Display display \u003d Display.getDefault();\n            Shell shell \u003d new Shell(display);\n            shell.setSize(new Point(300, 300));\n            shell.setLayout(new FillLayout());\n            Composite parent \u003d shell;\n            for (layer \u003d 2; layer \u003c 100; layer++) {\n                Composite composite \u003d new Composite(parent, SWT.BORDER);\n                composite.setLayout(new FillLayout());\n                parent \u003d composite;\n            }\n            shell.open();\n            while (!display.isDisposed()) {\n                if (!display.readAndDispatch())\n                    display.sleep();\n            }\n        } catch (SWTError error) {\n            System.out.println(\"SWTError: \" + error.getMessage() + \" at layer \"\n                    + layer + \"!\");\n            error.printStackTrace();\n        }\n    }\n}\n\nError stack trace:\n\norg.eclipse.swt.SWTError: No more handles\n\tat org.eclipse.swt.SWT.error(SWT.java:3400)\n\tat org.eclipse.swt.SWT.error(SWT.java:3297)\n\tat org.eclipse.swt.SWT.error(SWT.java:3268)\n\tat org.eclipse.swt.widgets.Widget.error(Widget.java:435)\n\tat org.eclipse.swt.widgets.Control.createHandle(Control.java:508)\n\tat org.eclipse.swt.widgets.Composite.createHandle(Composite.java:235)\n\tat org.eclipse.swt.widgets.Control.createWidget(Control.java:523)\n\tat org.eclipse.swt.widgets.Scrollable.createWidget(Scrollable.java:131)\n\tat org.eclipse.swt.widgets.Control.\u003cinit\u003e(Control.java:98)\n\tat org.eclipse.swt.widgets.Scrollable.\u003cinit\u003e(Scrollable.java:72)\n\tat org.eclipse.swt.widgets.Composite.\u003cinit\u003e(Composite.java:93)\n\tat NoMoreHandlesError.main(NoMoreHandlesError.java:37)\n\nI have checked that amount of composites created with the same parent is limited by operating system (in Windows XP this is 10000 hendles per user).\n\nThanks for any help!",
    "SN this sounds familiar, is this a known platform limitation or known problem?\n",
    "This is a Windows limitation that we can\u0027t work around.  The equivalent C code would also run out of handles."
  ],
  "commentCreationDates": [
    "2007-03-19T11:01:17+01:00",
    "2007-03-19T16:06:04+01:00",
    "2007-07-18T21:51:25+02:00"
  ],
  "traces": [
    {
      "exceptionType": "org.eclipse.swt.SWTError",
      "message": "No more handles",
      "elements": [
        {
          "method": "org.eclipse.swt.SWT.error",
          "source": "SWT.java:3400"
        },
        {
          "method": "org.eclipse.swt.SWT.error",
          "source": "SWT.java:3297"
        },
        {
          "method": "org.eclipse.swt.SWT.error",
          "source": "SWT.java:3268"
        },
        {
          "method": "org.eclipse.swt.widgets.Widget.error",
          "source": "Widget.java:435"
        },
        {
          "method": "org.eclipse.swt.widgets.Control.createHandle",
          "source": "Control.java:508"
        },
        {
          "method": "org.eclipse.swt.widgets.Composite.createHandle",
          "source": "Composite.java:235"
        },
        {
          "method": "org.eclipse.swt.widgets.Control.createWidget",
          "source": "Control.java:523"
        },
        {
          "method": "org.eclipse.swt.widgets.Scrollable.createWidget",
          "source": "Scrollable.java:131"
        },
        {
          "method": "org.eclipse.swt.widgets.Control.\u003cinit\u003e",
          "source": "Control.java:98"
        },
        {
          "method": "org.eclipse.swt.widgets.Scrollable.\u003cinit\u003e",
          "source": "Scrollable.java:72"
        },
        {
          "method": "org.eclipse.swt.widgets.Composite.\u003cinit\u003e",
          "source": "Composite.java:93"
        },
        {
          "method": "NoMoreHandlesError.main",
          "source": "NoMoreHandlesError.java:37"
        }
      ],
      "number": 0,
      "commentIndex": 0,
      "bugId": "178024",
      "date": "2007-03-19T11:01:17+01:00",
      "product": "Platform",
      "component": "SWT",
      "severity": "critical"
    }
  ],
  "groupId": "178024",
  "bugId": "178024",
  "date": "2007-03-19T11:01:17+01:00",
  "product": "Platform",
  "component": "SWT",
  "severity": "critical"
}