{
  "comments": [
    "Starting eclipse allows my to choose a workspace, once you choose ok and eclipse continues to load the splashscreen disappears and doesn\u0027t continue to load.  The log inside the chosen workspace has the following:\n\n[yeknom@cave-usi .metadata]$ /home/yeknom/Desktop/eclipse/eclipse \n[yeknom@cave-usi .metadata]$ cat .log \n!SESSION 2007-03-22 09:45:27.889 -----------------------------------------------\neclipse.buildId\u003dM20070212-1330\njava.version\u003d1.6.0\njava.vendor\u003dSun Microsystems Inc.\nBootLoader constants: OS\u003dlinux, ARCH\u003dx86, WS\u003dgtk, NL\u003den_US\nCommand-line arguments:  -os linux -ws gtk -arch x86\n \n!ENTRY org.eclipse.ui 4 4 2007-03-22 09:45:30.710\n!MESSAGE Unhandled event loop exception\n \n!ENTRY org.eclipse.ui 4 0 2007-03-22 09:45:30.711\n!MESSAGE Widget is disposed\n!STACK 0\norg.eclipse.swt.SWTException: Widget is disposed\n        at org.eclipse.swt.SWT.error(SWT.java:3374)\n        at org.eclipse.swt.SWT.error(SWT.java:3297)\n        at org.eclipse.swt.SWT.error(SWT.java:3268)\n        at org.eclipse.swt.widgets.Widget.error(Widget.java:434)\n        at org.eclipse.swt.widgets.Widget.checkWidget(Widget.java:372)\n        at org.eclipse.swt.widgets.ToolBar.getItems(ToolBar.java:252)\n        at org.eclipse.swt.widgets.ToolBar.relayout(ToolBar.java:384)\n        at org.eclipse.swt.widgets.ToolItem.dispose(ToolItem.java:275)\n        at org.eclipse.swt.widgets.CoolItem.calculateChevronTrim(CoolItem.java:179)\n        at org.eclipse.swt.widgets.CoolItem.\u003cinit\u003e(CoolItem.java:86)\n        at org.eclipse.ui.internal.PerspectiveSwitcher.createControlForTop(PerspectiveSwitcher.java:842)\n        at org.eclipse.ui.internal.PerspectiveSwitcher.createControlForLocation(PerspectiveSwitcher.java:515)\n        at org.eclipse.ui.internal.PerspectiveSwitcher.setPerspectiveBarLocation(PerspectiveSwitcher.java:319)\n        at org.eclipse.ui.internal.PerspectiveSwitcher.createControl(PerspectiveSwitcher.java:240)\n        at org.eclipse.ui.internal.WorkbenchWindow.createDefaultContents(WorkbenchWindow.java:990)\n        at org.eclipse.ui.internal.WorkbenchWindowConfigurer.createDefaultContents(WorkbenchWindowConfigurer.java:610)\n        at org.eclipse.ui.application.WorkbenchWindowAdvisor.createWindowContents(WorkbenchWindowAdvisor.java:267)\n        at org.eclipse.ui.internal.WorkbenchWindow.createContents(WorkbenchWindow.java:898)\n        at org.eclipse.jface.window.Window.create(Window.java:426)\n        at org.eclipse.ui.internal.Workbench.busyOpenWorkbenchWindow(Workbench.java:805)\n        at org.eclipse.ui.internal.Workbench.doOpenFirstTimeWindow(Workbench.java:1453)\n        at org.eclipse.ui.internal.Workbench.access$10(Workbench.java:1451)\n        at org.eclipse.ui.internal.Workbench$17.run(Workbench.java:1415)\n        at org.eclipse.ui.internal.Workbench.runStartupWithProgress(Workbench.java:1437)\n        at org.eclipse.ui.internal.Workbench.openFirstTimeWindow(Workbench.java:1413)\n        at org.eclipse.ui.internal.WorkbenchConfigurer.openFirstTimeWindow(WorkbenchConfigurer.java:190)\n        at org.eclipse.ui.application.WorkbenchAdvisor.openWindows(WorkbenchAdvisor.java:708)\n        at org.eclipse.ui.internal.Workbench.init(Workbench.java:1101)\n        at org.eclipse.ui.internal.Workbench.runUI(Workbench.java:1863)\n        at org.eclipse.ui.internal.Workbench.createAndRunWorkbench(Workbench.java:422)\n        at org.eclipse.ui.PlatformUI.createAndRunWorkbench(PlatformUI.java:149)\n        at org.eclipse.ui.internal.ide.IDEApplication.run(IDEApplication.java:95)\n        at org.eclipse.core.internal.runtime.PlatformActivator$1.run(PlatformActivator.java:78)\n        at org.eclipse.core.runtime.internal.adaptor.EclipseAppLauncher.runApplication(EclipseAppLauncher.java:92)\n        at org.eclipse.core.runtime.internal.adaptor.EclipseAppLauncher.start(EclipseAppLauncher.java:68)\n        at org.eclipse.core.runtime.adaptor.EclipseStarter.run(EclipseStarter.java:400)\n        at org.eclipse.core.runtime.adaptor.EclipseStarter.run(EclipseStarter.java:177)\n        at sun.reflect.NativeMethodAccessorImpl.invoke0(Native Method)\n        at sun.reflect.NativeMethodAccessorImpl.invoke(Unknown Source)\n        at sun.reflect.DelegatingMethodAccessorImpl.invoke(Unknown Source)\n        at java.lang.reflect.Method.invoke(Unknown Source)\n        at org.eclipse.core.launcher.Main.invokeFramework(Main.java:336)\n        at org.eclipse.core.launcher.Main.basicRun(Main.java:280)\n        at org.eclipse.core.launcher.Main.run(Main.java:977)\n        at org.eclipse.core.launcher.Main.main(Main.java:952)\n[yeknom@cave-usi .metadata]$\n\nTalking to Pookzilla on irc he concluded.\n\n\u003cPookzilla\u003e what version of GTK are you running?\n\u003cyeknom\u003e Pookzilla: 2.10.11\n\u003cPookzilla\u003e you should probably log a bug against SWT.  Looking at the code from 3.2.1 (trying to get 3.2.2 now) it looks like the cool item creates a toolbar and tool item to do some calculations and then disposes of the bar and item.  The problem is that the disposal of the item then triggers a re-layout of the bar which is already disposed... I\u0027m not sure why this is a problem for you and no one else.\n\nNote: the log was from a 3.2.2 setup but the same behavior happens with 3.3",
    "Bizarre, this has not been reported before.  Have any other releases of eclipse (older or newer) worked for you with this setup?  BG note gtk 2.10.11, java 6.\n",
    "Yes, some previous versions have worked but i have no clue which ones they where since in the past i\u0027d just use the fedora provided eclipse.  When this first started happening i figured it was just some brokeness from an upgrade or something but it\u0027s never started to work again.",
    "I think the cause of this bug was a rogue library that ended up in /usr/local.  Once removed everything seems happy.  So unless you think this needs more investigation all seems good now.",
    "If you\u0027re happy, then we\u0027re happy. Please reopen if you run into this again.\n\nClosing as WORKSFORME."
  ],
  "commentCreationDates": [
    "2007-03-22T17:20:33+01:00",
    "2007-03-22T17:43:53+01:00",
    "2007-03-22T18:06:00+01:00",
    "2007-03-24T21:04:20+01:00",
    "2007-04-12T23:57:22+02:00"
  ],
  "traces": [
    {
      "exceptionType": "org.eclipse.swt.SWTException",
      "message": "Widget is disposed",
      "elements": [
        {
          "method": "org.eclipse.swt.SWT.error",
          "source": "SWT.java:3374"
        },
        {
          "method": "org.eclipse.swt.SWT.error",
          "source": "SWT.java:3297"
        },
        {
          "method": "org.eclipse.swt.SWT.error",
          "source": "SWT.java:3268"
        },
        {
          "method": "org.eclipse.swt.widgets.Widget.error",
          "source": "Widget.java:434"
        },
        {
          "method": "org.eclipse.swt.widgets.Widget.checkWidget",
          "source": "Widget.java:372"
        },
        {
          "method": "org.eclipse.swt.widgets.ToolBar.getItems",
          "source": "ToolBar.java:252"
        },
        {
          "method": "org.eclipse.swt.widgets.ToolBar.relayout",
          "source": "ToolBar.java:384"
        },
        {
          "method": "org.eclipse.swt.widgets.ToolItem.dispose",
          "source": "ToolItem.java:275"
        },
        {
          "method": "org.eclipse.swt.widgets.CoolItem.calculateChevronTrim",
          "source": "CoolItem.java:179"
        },
        {
          "method": "org.eclipse.swt.widgets.CoolItem.\u003cinit\u003e",
          "source": "CoolItem.java:86"
        },
        {
          "method": "org.eclipse.ui.internal.PerspectiveSwitcher.createControlForTop",
          "source": "PerspectiveSwitcher.java:842"
        },
        {
          "method": "org.eclipse.ui.internal.PerspectiveSwitcher.createControlForLocation",
          "source": "PerspectiveSwitcher.java:515"
        },
        {
          "method": "org.eclipse.ui.internal.PerspectiveSwitcher.setPerspectiveBarLocation",
          "source": "PerspectiveSwitcher.java:319"
        },
        {
          "method": "org.eclipse.ui.internal.PerspectiveSwitcher.createControl",
          "source": "PerspectiveSwitcher.java:240"
        },
        {
          "method": "org.eclipse.ui.internal.WorkbenchWindow.createDefaultContents",
          "source": "WorkbenchWindow.java:990"
        },
        {
          "method": "org.eclipse.ui.internal.WorkbenchWindowConfigurer.createDefaultContents",
          "source": "WorkbenchWindowConfigurer.java:610"
        },
        {
          "method": "org.eclipse.ui.application.WorkbenchWindowAdvisor.createWindowContents",
          "source": "WorkbenchWindowAdvisor.java:267"
        },
        {
          "method": "org.eclipse.ui.internal.WorkbenchWindow.createContents",
          "source": "WorkbenchWindow.java:898"
        },
        {
          "method": "org.eclipse.jface.window.Window.create",
          "source": "Window.java:426"
        },
        {
          "method": "org.eclipse.ui.internal.Workbench.busyOpenWorkbenchWindow",
          "source": "Workbench.java:805"
        },
        {
          "method": "org.eclipse.ui.internal.Workbench.doOpenFirstTimeWindow",
          "source": "Workbench.java:1453"
        },
        {
          "method": "org.eclipse.ui.internal.Workbench.access$10",
          "source": "Workbench.java:1451"
        },
        {
          "method": "org.eclipse.ui.internal.Workbench$17.run",
          "source": "Workbench.java:1415"
        },
        {
          "method": "org.eclipse.ui.internal.Workbench.runStartupWithProgress",
          "source": "Workbench.java:1437"
        },
        {
          "method": "org.eclipse.ui.internal.Workbench.openFirstTimeWindow",
          "source": "Workbench.java:1413"
        },
        {
          "method": "org.eclipse.ui.internal.WorkbenchConfigurer.openFirstTimeWindow",
          "source": "WorkbenchConfigurer.java:190"
        },
        {
          "method": "org.eclipse.ui.application.WorkbenchAdvisor.openWindows",
          "source": "WorkbenchAdvisor.java:708"
        },
        {
          "method": "org.eclipse.ui.internal.Workbench.init",
          "source": "Workbench.java:1101"
        },
        {
          "method": "org.eclipse.ui.internal.Workbench.runUI",
          "source": "Workbench.java:1863"
        },
        {
          "method": "org.eclipse.ui.internal.Workbench.createAndRunWorkbench",
          "source": "Workbench.java:422"
        },
        {
          "method": "org.eclipse.ui.PlatformUI.createAndRunWorkbench",
          "source": "PlatformUI.java:149"
        },
        {
          "method": "org.eclipse.ui.internal.ide.IDEApplication.run",
          "source": "IDEApplication.java:95"
        },
        {
          "method": "org.eclipse.core.internal.runtime.PlatformActivator$1.run",
          "source": "PlatformActivator.java:78"
        },
        {
          "method": "org.eclipse.core.runtime.internal.adaptor.EclipseAppLauncher.runApplication",
          "source": "EclipseAppLauncher.java:92"
        },
        {
          "method": "org.eclipse.core.runtime.internal.adaptor.EclipseAppLauncher.start",
          "source": "EclipseAppLauncher.java:68"
        },
        {
          "method": "org.eclipse.core.runtime.adaptor.EclipseStarter.run",
          "source": "EclipseStarter.java:400"
        },
        {
          "method": "org.eclipse.core.runtime.adaptor.EclipseStarter.run",
          "source": "EclipseStarter.java:177"
        },
        {
          "method": "sun.reflect.NativeMethodAccessorImpl.invoke0",
          "source": "Native Method"
        },
        {
          "method": "sun.reflect.NativeMethodAccessorImpl.invoke",
          "source": "Unknown Source"
        },
        {
          "method": "sun.reflect.DelegatingMethodAccessorImpl.invoke",
          "source": "Unknown Source"
        },
        {
          "method": "java.lang.reflect.Method.invoke",
          "source": "Unknown Source"
        },
        {
          "method": "org.eclipse.core.launcher.Main.invokeFramework",
          "source": "Main.java:336"
        },
        {
          "method": "org.eclipse.core.launcher.Main.basicRun",
          "source": "Main.java:280"
        },
        {
          "method": "org.eclipse.core.launcher.Main.run",
          "source": "Main.java:977"
        },
        {
          "method": "org.eclipse.core.launcher.Main.main",
          "source": "Main.java:952"
        }
      ],
      "number": 0,
      "commentIndex": 0,
      "bugId": "178824",
      "date": "2007-03-22T17:20:33+01:00",
      "product": "Platform",
      "component": "SWT",
      "severity": "normal"
    }
  ],
  "groupId": "178824",
  "bugId": "178824",
  "date": "2007-03-22T17:20:33+01:00",
  "product": "Platform",
  "component": "SWT",
  "severity": "normal"
}