{
  "comments": [
    "!SESSION 2007-03-24 21:20:18.032 -----------------------------------------------\neclipse.buildId\u003dI20070323-1616\njava.version\u003d1.5.0_07\njava.vendor\u003dApple Computer, Inc.\nBootLoader constants: OS\u003dmacosx, ARCH\u003dx86, WS\u003dcarbon, NL\u003den_US\nFramework arguments:  -startup /Users/dragonfly/Desktop/eclipse_3.3m6/Eclipse.app/Contents/MacOS/../../../plugins/org.eclipse.equinox.launcher_1.0.0.v20070319.jar -keyring /Users/dragonfly/.eclipse_keyring -showlocation\nCommand-line arguments:  -os macosx -ws carbon -arch x86 -startup /Users/dragonfly/Desktop/eclipse_3.3m6/Eclipse.app/Contents/MacOS/../../../plugins/org.eclipse.equinox.launcher_1.0.0.v20070319.jar -keyring /Users/dragonfly/.eclipse_ke\nyring -consoleLog -showlocation\n\n!ENTRY org.eclipse.ui 4 0 2007-03-24 21:23:08.141\n!MESSAGE Unhandled event loop exception\n!STACK 0\njava.lang.IllegalArgumentException: Argument cannot be null\n        at org.eclipse.swt.SWT.error(SWT.java:3483)\n        at org.eclipse.swt.SWT.error(SWT.java:3422)\n        at org.eclipse.swt.SWT.error(SWT.java:3393)\n        at org.eclipse.swt.widgets.Display.error(Display.java:1090)\n        at org.eclipse.swt.widgets.Display.removeListener(Display.java:3160)\n        at org.eclipse.ui.internal.ide.application.IDEWorkbenchAdvisor.preShutdown(IDEWorkbenchAdvisor.java:331)\n        at org.eclipse.ui.internal.Workbench.busyClose(Workbench.java:822)\n        at org.eclipse.ui.internal.Workbench.access$15(Workbench.java:819)\n        at org.eclipse.ui.internal.Workbench$22.run(Workbench.java:1063)\n        at org.eclipse.swt.custom.BusyIndicator.showWhile(BusyIndicator.java:67)\n        at org.eclipse.ui.internal.Workbench.close(Workbench.java:1061)\n        at org.eclipse.ui.internal.Workbench.close(Workbench.java:1033)\n        at org.eclipse.ui.internal.Workbench$53.handleEvent(Workbench.java:2231)\n        at org.eclipse.swt.widgets.EventTable.sendEvent(EventTable.java:66)\n        at org.eclipse.swt.widgets.Display.sendEvent(Display.java:3437)\n        at org.eclipse.swt.widgets.Display.appleEventProc(Display.java:390)\n        at org.eclipse.swt.internal.carbon.OS.SendEventToEventTarget(Native Method)\n        at org.eclipse.swt.widgets.Display.readAndDispatch(Display.java:2917)\n        at org.eclipse.jface.window.Window.runEventLoop(Window.java:820)\n        at org.eclipse.jface.window.Window.open(Window.java:796)\n        at org.eclipse.jface.dialogs.ErrorDialog.open(ErrorDialog.java:333)\n        at org.eclipse.jface.dialogs.ErrorDialog.openError(ErrorDialog.java:397)\n        at org.eclipse.jface.dialogs.ErrorDialog.openError(ErrorDialog.java:362)\n        at org.eclipse.ui.internal.Workbench$46.runWithException(Workbench.java:1904)\n        at org.eclipse.ui.internal.StartupThreading$StartupRunnable.run(StartupThreading.java:31)\n        at org.eclipse.swt.widgets.RunnableLock.run(RunnableLock.java:35)\n        at org.eclipse.swt.widgets.Synchronizer.runAsyncMessages(Synchronizer.java:123)\n        at org.eclipse.swt.widgets.Display.runAsyncMessages(Display.java:3198)\n        at org.eclipse.swt.widgets.Display.readAndDispatch(Display.java:2943)\n        at org.eclipse.ui.internal.Workbench.runUI(Workbench.java:2260)\n        at org.eclipse.ui.internal.Workbench.access$4(Workbench.java:2176)\n        at org.eclipse.ui.internal.Workbench$4.run(Workbench.java:463)\n        at org.eclipse.core.databinding.observable.Realm.runWithDefault(Realm.java:289)\n        at org.eclipse.ui.internal.Workbench.createAndRunWorkbench(Workbench.java:458)\n        at org.eclipse.ui.PlatformUI.createAndRunWorkbench(PlatformUI.java:149)\n        at org.eclipse.ui.internal.ide.application.IDEApplication.start(IDEApplication.java:101)\n        at org.eclipse.equinox.internal.app.EclipseAppHandle.run(EclipseAppHandle.java:146)\n        at org.eclipse.core.runtime.internal.adaptor.EclipseAppLauncher.runApplication(EclipseAppLauncher.java:106)\n        at org.eclipse.core.runtime.internal.adaptor.EclipseAppLauncher.start(EclipseAppLauncher.java:76)\n        at org.eclipse.core.runtime.adaptor.EclipseStarter.run(EclipseStarter.java:356)\n        at org.eclipse.core.runtime.adaptor.EclipseStarter.run(EclipseStarter.java:171)\n        at sun.reflect.NativeMethodAccessorImpl.invoke0(Native Method)\n        at sun.reflect.NativeMethodAccessorImpl.invoke(NativeMethodAccessorImpl.java:39)\n        at sun.reflect.DelegatingMethodAccessorImpl.invoke(DelegatingMethodAccessorImpl.java:25)\n        at java.lang.reflect.Method.invoke(Method.java:585)\n        at org.eclipse.equinox.launcher.Main.invokeFramework(Main.java:476)\n        at org.eclipse.equinox.launcher.Main.basicRun(Main.java:416)\n        at org.eclipse.equinox.launcher.Main.run(Main.java:1141)\n\n@@@@\n\nAnother thing which happened ... I\u0027m not sure if this was the cause ... the menu entries in the Application menu were missing: Quit, About, Preferences.\n\nCould not reproduce both, yet.",
    "Looks like the app was quit while an error happened on startup. Kim?",
    "Changing OS from Mac OS to Mac OS X as per bug 185991"
  ],
  "commentCreationDates": [
    "2007-03-24T21:36:33+01:00",
    "2007-03-26T17:20:26+02:00",
    "2007-07-29T15:22:12+02:00"
  ],
  "traces": [
    {
      "exceptionType": "java.lang.IllegalArgumentException",
      "message": "Argument cannot be null",
      "elements": [
        {
          "method": "org.eclipse.swt.SWT.error",
          "source": "SWT.java:3483"
        },
        {
          "method": "org.eclipse.swt.SWT.error",
          "source": "SWT.java:3422"
        },
        {
          "method": "org.eclipse.swt.SWT.error",
          "source": "SWT.java:3393"
        },
        {
          "method": "org.eclipse.swt.widgets.Display.error",
          "source": "Display.java:1090"
        },
        {
          "method": "org.eclipse.swt.widgets.Display.removeListener",
          "source": "Display.java:3160"
        },
        {
          "method": "org.eclipse.ui.internal.ide.application.IDEWorkbenchAdvisor.preShutdown",
          "source": "IDEWorkbenchAdvisor.java:331"
        },
        {
          "method": "org.eclipse.ui.internal.Workbench.busyClose",
          "source": "Workbench.java:822"
        },
        {
          "method": "org.eclipse.ui.internal.Workbench.access$15",
          "source": "Workbench.java:819"
        },
        {
          "method": "org.eclipse.ui.internal.Workbench$22.run",
          "source": "Workbench.java:1063"
        },
        {
          "method": "org.eclipse.swt.custom.BusyIndicator.showWhile",
          "source": "BusyIndicator.java:67"
        },
        {
          "method": "org.eclipse.ui.internal.Workbench.close",
          "source": "Workbench.java:1061"
        },
        {
          "method": "org.eclipse.ui.internal.Workbench.close",
          "source": "Workbench.java:1033"
        },
        {
          "method": "org.eclipse.ui.internal.Workbench$53.handleEvent",
          "source": "Workbench.java:2231"
        },
        {
          "method": "org.eclipse.swt.widgets.EventTable.sendEvent",
          "source": "EventTable.java:66"
        },
        {
          "method": "org.eclipse.swt.widgets.Display.sendEvent",
          "source": "Display.java:3437"
        },
        {
          "method": "org.eclipse.swt.widgets.Display.appleEventProc",
          "source": "Display.java:390"
        },
        {
          "method": "org.eclipse.swt.internal.carbon.OS.SendEventToEventTarget",
          "source": "Native Method"
        },
        {
          "method": "org.eclipse.swt.widgets.Display.readAndDispatch",
          "source": "Display.java:2917"
        },
        {
          "method": "org.eclipse.jface.window.Window.runEventLoop",
          "source": "Window.java:820"
        },
        {
          "method": "org.eclipse.jface.window.Window.open",
          "source": "Window.java:796"
        },
        {
          "method": "org.eclipse.jface.dialogs.ErrorDialog.open",
          "source": "ErrorDialog.java:333"
        },
        {
          "method": "org.eclipse.jface.dialogs.ErrorDialog.openError",
          "source": "ErrorDialog.java:397"
        },
        {
          "method": "org.eclipse.jface.dialogs.ErrorDialog.openError",
          "source": "ErrorDialog.java:362"
        },
        {
          "method": "org.eclipse.ui.internal.Workbench$46.runWithException",
          "source": "Workbench.java:1904"
        },
        {
          "method": "org.eclipse.ui.internal.StartupThreading$StartupRunnable.run",
          "source": "StartupThreading.java:31"
        },
        {
          "method": "org.eclipse.swt.widgets.RunnableLock.run",
          "source": "RunnableLock.java:35"
        },
        {
          "method": "org.eclipse.swt.widgets.Synchronizer.runAsyncMessages",
          "source": "Synchronizer.java:123"
        },
        {
          "method": "org.eclipse.swt.widgets.Display.runAsyncMessages",
          "source": "Display.java:3198"
        },
        {
          "method": "org.eclipse.swt.widgets.Display.readAndDispatch",
          "source": "Display.java:2943"
        },
        {
          "method": "org.eclipse.ui.internal.Workbench.runUI",
          "source": "Workbench.java:2260"
        },
        {
          "method": "org.eclipse.ui.internal.Workbench.access$4",
          "source": "Workbench.java:2176"
        },
        {
          "method": "org.eclipse.ui.internal.Workbench$4.run",
          "source": "Workbench.java:463"
        },
        {
          "method": "org.eclipse.core.databinding.observable.Realm.runWithDefault",
          "source": "Realm.java:289"
        },
        {
          "method": "org.eclipse.ui.internal.Workbench.createAndRunWorkbench",
          "source": "Workbench.java:458"
        },
        {
          "method": "org.eclipse.ui.PlatformUI.createAndRunWorkbench",
          "source": "PlatformUI.java:149"
        },
        {
          "method": "org.eclipse.ui.internal.ide.application.IDEApplication.start",
          "source": "IDEApplication.java:101"
        },
        {
          "method": "org.eclipse.equinox.internal.app.EclipseAppHandle.run",
          "source": "EclipseAppHandle.java:146"
        },
        {
          "method": "org.eclipse.core.runtime.internal.adaptor.EclipseAppLauncher.runApplication",
          "source": "EclipseAppLauncher.java:106"
        },
        {
          "method": "org.eclipse.core.runtime.internal.adaptor.EclipseAppLauncher.start",
          "source": "EclipseAppLauncher.java:76"
        },
        {
          "method": "org.eclipse.core.runtime.adaptor.EclipseStarter.run",
          "source": "EclipseStarter.java:356"
        },
        {
          "method": "org.eclipse.core.runtime.adaptor.EclipseStarter.run",
          "source": "EclipseStarter.java:171"
        },
        {
          "method": "sun.reflect.NativeMethodAccessorImpl.invoke0",
          "source": "Native Method"
        },
        {
          "method": "sun.reflect.NativeMethodAccessorImpl.invoke",
          "source": "NativeMethodAccessorImpl.java:39"
        },
        {
          "method": "sun.reflect.DelegatingMethodAccessorImpl.invoke",
          "source": "DelegatingMethodAccessorImpl.java:25"
        },
        {
          "method": "java.lang.reflect.Method.invoke",
          "source": "Method.java:585"
        },
        {
          "method": "org.eclipse.equinox.launcher.Main.invokeFramework",
          "source": "Main.java:476"
        },
        {
          "method": "org.eclipse.equinox.launcher.Main.basicRun",
          "source": "Main.java:416"
        },
        {
          "method": "org.eclipse.equinox.launcher.Main.run",
          "source": "Main.java:1141"
        }
      ],
      "number": 0,
      "commentIndex": 0,
      "bugId": "179164",
      "date": "2007-03-24T21:36:33+01:00",
      "product": "Platform",
      "component": "UI",
      "severity": "normal"
    }
  ],
  "groupId": "179164",
  "bugId": "179164",
  "date": "2007-03-24T21:36:33+01:00",
  "product": "Platform",
  "component": "UI",
  "severity": "normal"
}