{
  "comments": [
    "1. Select a folder containing SML documents to export\n2. Select Export... from the context menu\n3. Fill in appropriate values so you can advance to the 2nd page of the wizard\n4. On page 2, select one of the detected documents\n5. Add 4 aliases for the document\n6. Holding down the Ctrl key, select the 2nd and 3rd aliases in the list\n7. Click the Remove button\n\nObserve that the resulting list does not result in the 1st and 4th alias from before, as expected.\n\nHere\u0027s a relevant exception stack from the error log:\n\njava.lang.IndexOutOfBoundsException: Index: 1, Size: 1\n\tat java.util.ArrayList.RangeCheck(ArrayList.java:572)\n\tat java.util.ArrayList.remove(ArrayList.java:415)\n\tat org.eclipse.cosmos.rm.smlif.internal.artifacts.ModelUnitFile.removeAlias(ModelUnitFile.java:148)\n\tat org.eclipse.cosmos.rm.smlif.internal.export.ui.ExportToSMLIFWizardPage2$4.widgetSelected(ExportToSMLIFWizardPage2.java:338)\n\tat org.eclipse.swt.widgets.TypedListener.handleEvent(TypedListener.java:90)\n\tat org.eclipse.swt.widgets.EventTable.sendEvent(EventTable.java:66)\n\tat org.eclipse.swt.widgets.Widget.sendEvent(Widget.java:928)\n\tat org.eclipse.swt.widgets.Display.runDeferredEvents(Display.java:3348)\n\tat org.eclipse.swt.widgets.Display.readAndDispatch(Display.java:2968)\n\tat org.eclipse.jface.window.Window.runEventLoop(Window.java:820)\n\tat org.eclipse.jface.window.Window.open(Window.java:796)\n    ...",
    "There was a logic error in calculating the selected index when multiple items were selected.",
    "update target to i2"
  ],
  "commentCreationDates": [
    "2007-03-26T23:00:53+02:00",
    "2007-03-27T00:57:55+02:00",
    "2007-04-03T16:56:32+02:00"
  ],
  "traces": [
    {
      "exceptionType": "java.lang.IndexOutOfBoundsException",
      "message": "Index: 1, Size: 1",
      "elements": [
        {
          "method": "java.util.ArrayList.RangeCheck",
          "source": "ArrayList.java:572"
        },
        {
          "method": "java.util.ArrayList.remove",
          "source": "ArrayList.java:415"
        },
        {
          "method": "org.eclipse.cosmos.rm.smlif.internal.artifacts.ModelUnitFile.removeAlias",
          "source": "ModelUnitFile.java:148"
        },
        {
          "method": "org.eclipse.cosmos.rm.smlif.internal.export.ui.ExportToSMLIFWizardPage2$4.widgetSelected",
          "source": "ExportToSMLIFWizardPage2.java:338"
        },
        {
          "method": "org.eclipse.swt.widgets.TypedListener.handleEvent",
          "source": "TypedListener.java:90"
        },
        {
          "method": "org.eclipse.swt.widgets.EventTable.sendEvent",
          "source": "EventTable.java:66"
        },
        {
          "method": "org.eclipse.swt.widgets.Widget.sendEvent",
          "source": "Widget.java:928"
        },
        {
          "method": "org.eclipse.swt.widgets.Display.runDeferredEvents",
          "source": "Display.java:3348"
        },
        {
          "method": "org.eclipse.swt.widgets.Display.readAndDispatch",
          "source": "Display.java:2968"
        },
        {
          "method": "org.eclipse.jface.window.Window.runEventLoop",
          "source": "Window.java:820"
        },
        {
          "method": "org.eclipse.jface.window.Window.open",
          "source": "Window.java:796"
        }
      ],
      "number": 0,
      "commentIndex": 0,
      "bugId": "179390",
      "date": "2007-03-26T23:00:53+02:00",
      "product": "Cosmos",
      "component": "ResourceModeling",
      "severity": "normal"
    }
  ],
  "groupId": "179390",
  "bugId": "179390",
  "date": "2007-03-26T23:00:53+02:00",
  "product": "Cosmos",
  "component": "ResourceModeling",
  "severity": "normal"
}