{
  "comments": [
    "With attachment 62215, when trying to create Axis2 Web service client with a non-existing project, the Axis2 core facet got installed and the Client configuration page is properly filled in.  However, when I click Finish, I got:\n\nException occured while code generation the wsdl\n    java.lang.reflect.InvocationTargetException\n    at sun.reflect.NativeMethodAccessorImpl.invoke0(Native Method)\n    at sun.reflect.NativeMethodAccessorImpl.invoke(NativeMethodAccessorImpl.java:39)\n    at sun.reflect.DelegatingMethodAccessorImpl.invoke(DelegatingMethodAccessorImpl.java:25)\n    at java.lang.reflect.Method.invoke(Method.java:585)\n    at org.eclipse.jst.ws.axis2.consumption.core.utils.WSDL2JavaGenerator.getAxisService(WSDL2JavaGenerator.java:378)\n    at org.eclipse.jst.ws.axis2.consumption.core.command.Axis2ClientCodegenCommand.execute(Axis2ClientCodegenCommand.java:85)",
    "(In reply to comment #0)\n\u003e With attachment 62215 [details], when trying to create Axis2 Web service client with a\n\u003e non-existing project, the Axis2 core facet got installed and the Client\n\u003e configuration page is properly filled in.  However, when I click Finish, I got:\n\u003e \n\u003e Exception occured while code generation the wsdl\n\u003e     java.lang.reflect.InvocationTargetException\n\u003e     at sun.reflect.NativeMethodAccessorImpl.invoke0(Native Method)\n\u003e     at\n\u003e sun.reflect.NativeMethodAccessorImpl.invoke(NativeMethodAccessorImpl.java:39)\n\u003e     at\n\u003e sun.reflect.DelegatingMethodAccessorImpl.invoke(DelegatingMethodAccessorImpl.java:25)\n\u003e     at java.lang.reflect.Method.invoke(Method.java:585)\n\u003e     at\n\u003e org.eclipse.jst.ws.axis2.consumption.core.utils.WSDL2JavaGenerator.getAxisService(WSDL2JavaGenerator.java:378)\n\u003e     at\n\u003e org.eclipse.jst.ws.axis2.consumption.core.command.Axis2ClientCodegenCommand.execute(Axis2ClientCodegenCommand.java:85)\n\u003e \n\nHi ,  \n\nI guess we have two options for this \n\n1) generate a the code into a default generated project (As normally named WebServiceProject) \n2) We inform the user \ni) at the end of the scenario that there has been no existing project selected -\u003e so aboart\nii) Invalidate the page if there is no project selected at the start\n\nI guess the first one is the correct solution for this also there can be no 2)ii) even we can live with having 2)i) \n\njust for clarifying things. \n\nThanks \n\nLahiru\n       \n\n\n\n",
    "This problem does not exist with the 05/02 WTP 2.0 driver.",
    "Closing."
  ],
  "commentCreationDates": [
    "2007-03-30T20:55:11+02:00",
    "2007-04-03T06:52:03+02:00",
    "2007-05-02T19:17:54+02:00",
    "2007-05-02T19:18:06+02:00"
  ],
  "traces": [
    {
      "exceptionType": "java.lang.reflect.InvocationTargetException",
      "elements": [
        {
          "method": "sun.reflect.NativeMethodAccessorImpl.invoke0",
          "source": "Native Method"
        },
        {
          "method": "sun.reflect.NativeMethodAccessorImpl.invoke",
          "source": "NativeMethodAccessorImpl.java:39"
        },
        {
          "method": "sun.reflect.DelegatingMethodAccessorImpl.invoke",
          "source": "DelegatingMethodAccessorImpl.java:25"
        },
        {
          "method": "java.lang.reflect.Method.invoke",
          "source": "Method.java:585"
        },
        {
          "method": "org.eclipse.jst.ws.axis2.consumption.core.utils.WSDL2JavaGenerator.getAxisService",
          "source": "WSDL2JavaGenerator.java:378"
        },
        {
          "method": "org.eclipse.jst.ws.axis2.consumption.core.command.Axis2ClientCodegenCommand.execute",
          "source": "Axis2ClientCodegenCommand.java:85"
        }
      ],
      "number": 0,
      "commentIndex": 0,
      "bugId": "180275",
      "date": "2007-03-30T20:55:11+02:00",
      "product": "Web Tools",
      "component": "jst.ws",
      "severity": "normal"
    }
  ],
  "groupId": "180275",
  "bugId": "180275",
  "date": "2007-03-30T20:55:11+02:00",
  "product": "Web Tools",
  "component": "jst.ws",
  "severity": "normal"
}