{
  "comments": [
    "Hi,\n\nI have a SQL statement that returns three columns for a line chart:  time (X-axis), rate (Y-axis) and entity (each value is a line over time).  When the SQL statement returns a result set with a least one row, I will see a line chart under \"View Report in Web Viewer\" (or the other options).  However, if the result set is empty, the following exception gets thrown:\n\norg.eclipse.birt.chart.exception.ChartException: Unable to use a non-datetime data to render a datetime axis.  \nat org.eclipse.birt.chart.factory.Generator.build(Generator.java:983)\nat org.eclipse.birt.chart.reportitem.ChartReportItemPresentationImpl.onRowSets(ChartReportItemPresentationImpl.java:453)\nat org.eclipse.birt.report.engine.presentation.LocalizedContentVisitor.processExtendedContent(LocalizedContentVisitor.java:651)\nat org.eclipse.birt.report.engine.presentation.LocalizedContentVisior.visitForeign(LocalizedContentVisitor.java:359)\n...\n\n\nHowever, when I preview the query in the Dataset dialog box in \"Preview Results\", no exception is thrown (whether there are any rows or not).\n\nThanks.\n\nFred",
    "Reassign to chart team for further research.",
    "I think this bug has been resolved with #160517(null empty dataset won\u0027t been used to render chart). You could try 2.2M6 or 2.1.3 build or nightly build after 20070225.\nThanks."
  ],
  "commentCreationDates": [
    "2007-04-03T00:41:14+02:00",
    "2007-04-03T05:22:33+02:00",
    "2007-04-06T05:13:45+02:00"
  ],
  "traces": [
    {
      "exceptionType": "org.eclipse.birt.chart.exception.ChartException",
      "message": "Unable to use a non-datetime data to render a datetime axis.",
      "elements": [
        {
          "method": "org.eclipse.birt.chart.factory.Generator.build",
          "source": "Generator.java:983"
        },
        {
          "method": "org.eclipse.birt.chart.reportitem.ChartReportItemPresentationImpl.onRowSets",
          "source": "ChartReportItemPresentationImpl.java:453"
        },
        {
          "method": "org.eclipse.birt.report.engine.presentation.LocalizedContentVisitor.processExtendedContent",
          "source": "LocalizedContentVisitor.java:651"
        },
        {
          "method": "org.eclipse.birt.report.engine.presentation.LocalizedContentVisior.visitForeign",
          "source": "LocalizedContentVisitor.java:359"
        }
      ],
      "number": 0,
      "commentIndex": 0,
      "bugId": "180589",
      "date": "2007-04-03T00:41:14+02:00",
      "product": "BIRT",
      "component": "Chart",
      "severity": "critical"
    }
  ],
  "groupId": "180589",
  "bugId": "180589",
  "date": "2007-04-03T00:41:14+02:00",
  "product": "BIRT",
  "component": "Chart",
  "severity": "critical"
}