{
  "comments": [
    "Build: I20070403\n\nThis WPF build fails to start the workbench. There are hundreds of errors on stdout/stderr, and a number of errors in the log. Here is a sample of the errors that appear on stderr:\n\nLEAK -\u003e 99\u003d#FF5F3F5F type\u003dSystem.Windows.Media.Color\njava.lang.Exception\n        at org.eclipse.swt.internal.wpf.OS.Color_FromArgb(Native Method)\n        at org.eclipse.swt.graphics.Color.init(Color.java:234)\n        at org.eclipse.swt.graphics.Color.\u003cinit\u003e(Color.java:79)\n        at org.eclipse.ui.internal.WorkbenchColors.initWorkbenchColors(Workbench\nColors.java:61)\n        at org.eclipse.ui.internal.WorkbenchColors.startup(WorkbenchColors.java:\n101)\n        at org.eclipse.ui.internal.Workbench$28.runWithException(Workbench.java:\n1467)\n        at org.eclipse.ui.internal.StartupThreading$StartupRunnable.run(StartupT\nhreading.java:31)\n        at org.eclipse.swt.widgets.RunnableLock.run(RunnableLock.java:35)\n        at org.eclipse.swt.widgets.Synchronizer.runAsyncMessages(Synchronizer.ja\nva:123)\n        at org.eclipse.swt.widgets.Display.runAsyncMessages(Display.java:2390)\n        at org.eclipse.swt.widgets.Display.HandleDispatcherInactive(Display.java\n:1698)\n        at org.eclipse.swt.internal.wpf.OS.Dispatcher_PushFrame(Native Method)\n        at org.eclipse.swt.widgets.Display.readAndDispatch(Display.java:2162)\n        at org.eclipse.ui.internal.Workbench.runUI(Workbench.java:2284)\n        at org.eclipse.ui.internal.Workbench.access$4(Workbench.java:2200)\n        at org.eclipse.ui.internal.Workbench$4.run(Workbench.java:466)\n        at org.eclipse.core.databinding.observable.Realm.runWithDefault(Realm.ja\nva:289)\n        at org.eclipse.ui.internal.Workbench.createAndRunWorkbench(Workbench.jav\na:461)\n        at org.eclipse.ui.PlatformUI.createAndRunWorkbench(PlatformUI.java:149)\n        at org.eclipse.ui.internal.ide.application.IDEApplication.start(IDEAppli\ncation.java:101)\n        at org.eclipse.equinox.internal.app.EclipseAppHandle.run(EclipseAppHandl\ne.java:152)\n        at org.eclipse.core.runtime.internal.adaptor.EclipseAppLauncher.runAppli\ncation(EclipseAppLauncher.java:106)\n        at org.eclipse.core.runtime.internal.adaptor.EclipseAppLauncher.start(Ec\nlipseAppLauncher.java:76)\n        at org.eclipse.core.runtime.adaptor.EclipseStarter.run(EclipseStarter.ja\nva:359)\n        at org.eclipse.core.runtime.adaptor.EclipseStarter.run(EclipseStarter.ja\nva:174)\n        at sun.reflect.NativeMethodAccessorImpl.invoke0(Native Method)\n        at sun.reflect.NativeMethodAccessorImpl.invoke(NativeMethodAccessorImpl.\njava:64)",
    "Created an attachment (id\u003d62844)\nLog file\n\n",
    "Not sure what\u0027s going on here. \nThe attached log file (comment #1) includes a call to WM_PAINT, which is win32, not wpf, but the \"LEAK-\u003e\" spew is definitely from WPF specific code. \nI\u0027ve installed I20070403-1110 and both win32 and wpf versions are starting up fine for me.",
    "Created an attachment (id\u003d62935)\nUpdated log\n\nIt turns out the previously attached log was from my session just before upgrading to the WPF build. This log is my actual stdout output from running with WPF.",
    "It turns out it only fails to start with certain Eclipse preference settings. I will attach my pref file.",
    "Created an attachment (id\u003d62954)\nPreference file\n\n",
    "fixed \u003e 20070404\nThe preference file was created on win32, and when imported to wpf no default stretch value was getting assigned to the font data."
  ],
  "commentCreationDates": [
    "2007-04-04T00:35:03+02:00",
    "2007-04-04T00:35:26+02:00",
    "2007-04-04T16:30:11+02:00",
    "2007-04-04T16:56:02+02:00",
    "2007-04-04T18:33:45+02:00",
    "2007-04-04T18:34:58+02:00",
    "2007-04-04T20:30:23+02:00"
  ],
  "traces": [
    {
      "exceptionType": "java.lang.Exception",
      "elements": [
        {
          "method": "org.eclipse.swt.internal.wpf.OS.Color_FromArgb",
          "source": "Native Method"
        },
        {
          "method": "org.eclipse.swt.graphics.Color.init",
          "source": "Color.java:234"
        },
        {
          "method": "org.eclipse.swt.graphics.Color.\u003cinit\u003e",
          "source": "Color.java:79"
        },
        {
          "method": "org.eclipse.ui.internal.WorkbenchColors.initWorkbenchColors",
          "source": "Workbench Colors.java:61"
        },
        {
          "method": "org.eclipse.ui.internal.WorkbenchColors.startup",
          "source": "WorkbenchColors.java: 101"
        },
        {
          "method": "org.eclipse.ui.internal.Workbench$28.runWithException",
          "source": "Workbench.java: 1467"
        },
        {
          "method": "org.eclipse.ui.internal.StartupThreading$StartupRunnable.run",
          "source": "StartupT hreading.java:31"
        },
        {
          "method": "org.eclipse.swt.widgets.RunnableLock.run",
          "source": "RunnableLock.java:35"
        },
        {
          "method": "org.eclipse.swt.widgets.Synchronizer.runAsyncMessages",
          "source": "Synchronizer.ja va:123"
        },
        {
          "method": "org.eclipse.swt.widgets.Display.runAsyncMessages",
          "source": "Display.java:2390"
        },
        {
          "method": "org.eclipse.swt.widgets.Display.HandleDispatcherInactive",
          "source": "Display.java :1698"
        },
        {
          "method": "org.eclipse.swt.internal.wpf.OS.Dispatcher_PushFrame",
          "source": "Native Method"
        },
        {
          "method": "org.eclipse.swt.widgets.Display.readAndDispatch",
          "source": "Display.java:2162"
        },
        {
          "method": "org.eclipse.ui.internal.Workbench.runUI",
          "source": "Workbench.java:2284"
        },
        {
          "method": "org.eclipse.ui.internal.Workbench.access$4",
          "source": "Workbench.java:2200"
        },
        {
          "method": "org.eclipse.ui.internal.Workbench$4.run",
          "source": "Workbench.java:466"
        },
        {
          "method": "org.eclipse.core.databinding.observable.Realm.runWithDefault",
          "source": "Realm.ja va:289"
        },
        {
          "method": "org.eclipse.ui.internal.Workbench.createAndRunWorkbench",
          "source": "Workbench.jav a:461"
        },
        {
          "method": "org.eclipse.ui.PlatformUI.createAndRunWorkbench",
          "source": "PlatformUI.java:149"
        },
        {
          "method": "org.eclipse.ui.internal.ide.application.IDEApplication.start",
          "source": "IDEAppli cation.java:101"
        },
        {
          "method": "org.eclipse.equinox.internal.app.EclipseAppHandle.run",
          "source": "EclipseAppHandl e.java:152"
        },
        {
          "method": "org.eclipse.core.runtime.internal.adaptor.EclipseAppLauncher.runApplication",
          "source": "EclipseAppLauncher.java:106"
        },
        {
          "method": "org.eclipse.core.runtime.internal.adaptor.EclipseAppLauncher.start",
          "source": "Ec lipseAppLauncher.java:76"
        },
        {
          "method": "org.eclipse.core.runtime.adaptor.EclipseStarter.run",
          "source": "EclipseStarter.ja va:359"
        },
        {
          "method": "org.eclipse.core.runtime.adaptor.EclipseStarter.run",
          "source": "EclipseStarter.ja va:174"
        },
        {
          "method": "sun.reflect.NativeMethodAccessorImpl.invoke0",
          "source": "Native Method"
        },
        {
          "method": "sun.reflect.NativeMethodAccessorImpl.invoke",
          "source": "NativeMethodAccessorImpl. java:64"
        }
      ],
      "number": 0,
      "commentIndex": 0,
      "bugId": "180821",
      "date": "2007-04-04T00:35:03+02:00",
      "product": "Platform",
      "component": "SWT",
      "severity": "critical"
    }
  ],
  "groupId": "180821",
  "bugId": "180821",
  "date": "2007-04-04T00:35:03+02:00",
  "product": "Platform",
  "component": "SWT",
  "severity": "critical"
}