{
  "comments": [
    "When running a large report with 6million rows ,each row is about 10 columns , and 100 bytes, render fails with an i/o exception. \n\nEnv: ibm1.5 jvm, BIRT runtime 2.2M5, Machine- Linux RHEL AS4, database - derby 10.3\nTestEnv: scsi 10K RPM disks,4GRAM,2.8Ghz 2cpu , HT IntelXeon,RHEL Linux kernel2.6\n\nThe stack trace is below.\n                      \nsh-3.00$ . ./run2.2.ksh 1 200 10 3000                                           \n                                         \njava version \"1.5.0\"                                                            \nJava(TM) 2 Runtime Environment, Standard Edition (build pxi32dev-20060222 (SR1))\nIBM J9 VM (build 2.3, J2RE 1.5.0 IBM J9 2.3 Linux x86-32 j9vmxi3223-20060222a (J\nIT enabled)                                                                     \nJ9VM - 20060220_05389_lHdSMR                                                    \nJIT  - 20060220_2133_r8                                                         \nGC   - 20060214_AA)                                                             \nJCL  - 20060222a                                                                \niteration\u003d0run\u003d2228611Exception in thread \"main\" org.eclipse.birt.report.engine.\napi.EngineException: document refresh failed                                    \n        at org.eclipse.birt.report.engine.api.impl.ReportDocumentReader.doRefres\nh(ReportDocumentReader.java:281)                                                \n        at org.eclipse.birt.report.engine.api.impl.ReportDocumentReader.\u003cinit\u003e(R\neportDocumentReader.java:113)                                                   \n        at org.eclipse.birt.report.engine.api.impl.ReportEngineHelper.openReport\nDocument(ReportEngineHelper.java:447)                                           \n        at org.eclipse.birt.report.engine.api.impl.ReportEngineHelper.openReport\nDocument(ReportEngineHelper.java:429)                                           \n        at org.eclipse.birt.report.engine.api.impl.ReportEngineHelper.openReport\nDocument(ReportEngineHelper.java:373)                                           \n        at org.eclipse.birt.report.engine.api.impl.ReportEngine.openReportDocume\nnt(ReportEngine.java:406)                                                       \n        at TaskTest.render(TaskTest.java:103)                                   \n        at TaskTest.main(TaskTest.java:153)                                     \nCaused by: java.io.IOException: Invalid argument                                \n        at java.io.RandomAccessFile.seek(Native Method)                         \n        at org.eclipse.birt.core.archive.RAFileInputStream.readToBuffer(RAFileIn\nputStream.java:69)                                                              \n        at org.eclipse.birt.core.archive.RAFileInputStream.read(RAFileInputStrea\nm.java:94)                                                                      \n        at java.io.FilterInputStream.read(FilterInputStream.java:89)            \n        at org.eclipse.birt.core.util.IOUtil.readInt(IOUtil.java:96)            \n        at org.eclipse.birt.report.engine.api.impl.ReportDocumentReader.doRefres\nh(ReportDocumentReader.java:212)                                                \n        ... 7 more   \n\n---------------------------\n\nrptdocument was created successfully.                                                           \nsh-3.00$ ls -l *.rptdocument                                                                                                                 \n-rw-rw-r--  1 cloudtst RAND 3904474296 Mar 24 19:09 T1_SmallQuery.rptdocument   \n\n---------------------------",
    "Created an attachment (id\u003d62846)\ndesign that failed to render for a large report.\n\nT1_SmallQuery.rptdesign is the report design file. \nParameters are w\u003d200, d\u003d10, c\u003d3000\n",
    "Created an attachment (id\u003d62847)\nT1_SmallQuery.rptconfig..\n\n",
    "Fixed."
  ],
  "commentCreationDates": [
    "2007-04-04T01:34:18+02:00",
    "2007-04-04T01:37:16+02:00",
    "2007-04-04T01:38:29+02:00",
    "2007-05-28T14:47:27+02:00"
  ],
  "traces": [
    {
      "exceptionType": "api.EngineException",
      "message": "document refresh failed",
      "elements": [
        {
          "method": "org.eclipse.birt.report.engine.api.impl.ReportDocumentReader.doRefresh",
          "source": "ReportDocumentReader.java:281"
        },
        {
          "method": "org.eclipse.birt.report.engine.api.impl.ReportDocumentReader.\u003cinit\u003e",
          "source": "R eportDocumentReader.java:113"
        },
        {
          "method": "org.eclipse.birt.report.engine.api.impl.ReportEngineHelper.openReportDocument",
          "source": "ReportEngineHelper.java:447"
        },
        {
          "method": "org.eclipse.birt.report.engine.api.impl.ReportEngineHelper.openReportDocument",
          "source": "ReportEngineHelper.java:429"
        },
        {
          "method": "org.eclipse.birt.report.engine.api.impl.ReportEngineHelper.openReportDocument",
          "source": "ReportEngineHelper.java:373"
        },
        {
          "method": "org.eclipse.birt.report.engine.api.impl.ReportEngine.openReportDocument",
          "source": "ReportEngine.java:406"
        },
        {
          "method": "TaskTest.render",
          "source": "TaskTest.java:103"
        },
        {
          "method": "TaskTest.main",
          "source": "TaskTest.java:153"
        }
      ],
      "causedBy": {
        "exceptionType": "java.io.IOException",
        "message": "Invalid argument",
        "elements": [
          {
            "method": "java.io.RandomAccessFile.seek",
            "source": "Native Method"
          },
          {
            "method": "org.eclipse.birt.core.archive.RAFileInputStream.readToBuffer",
            "source": "RAFileIn putStream.java:69"
          },
          {
            "method": "org.eclipse.birt.core.archive.RAFileInputStream.read",
            "source": "RAFileInputStrea m.java:94"
          },
          {
            "method": "java.io.FilterInputStream.read",
            "source": "FilterInputStream.java:89"
          },
          {
            "method": "org.eclipse.birt.core.util.IOUtil.readInt",
            "source": "IOUtil.java:96"
          },
          {
            "method": "org.eclipse.birt.report.engine.api.impl.ReportDocumentReader.doRefresh",
            "source": "ReportDocumentReader.java:212"
          }
        ],
        "number": 0,
        "commentIndex": 0
      },
      "number": 0,
      "commentIndex": 0,
      "bugId": "180827",
      "date": "2007-04-04T01:34:18+02:00",
      "product": "BIRT",
      "component": "Data",
      "severity": "normal"
    }
  ],
  "groupId": "180827",
  "bugId": "180827",
  "date": "2007-04-04T01:34:18+02:00",
  "product": "BIRT",
  "component": "Data",
  "severity": "normal"
}