{
  "comments": [
    "Build ID: 200702150621\n\nSteps To Reproduce:\nUse following code to execute a file with CDT Spawner\n\nProcessFactory factory \u003d ProcessFactory.getFactory();\nProcess process \u003d factory.exec(commandArray, environment, workDir);\nif (! (process instanceof Spawner)) {\n   throw new Exception(\"CDT does not support Spawner on this platform\");\n}\nprocess.waitFor();\n\nTry to run (as non root user) a file that is executable, but not readable, like:\n\n$ ls -la /opt/.../bin/file\n---x--x--x 1 root root 4396 2007-03-20 13:18 /opt/.../bin/file\n\nThe process will not be created and following exception will be thrown: \"Exec error:Cannot run /opt/ibm/systemsim-cell/bin/snif\"\nUnable to find full path for \"/opt/ibm/systemsim-cell/bin/snif\"\njava.io.IOException: Exec error:Cannot run /opt/ibm/systemsim-cell/bin/snif\n\tat org.eclipse.cdt.utils.spawner.Spawner.exec(Spawner.java:243)\n\tat org.eclipse.cdt.utils.spawner.Spawner.\u003cinit\u003e(Spawner.java:57)\n\tat org.eclipse.cdt.utils.spawner.Spawner.\u003cinit\u003e(Spawner.java:85)\n\tat org.eclipse.cdt.utils.spawner.ProcessFactory.exec(ProcessFactory.java:65)\n...\n\nAdditionally, following message is printed on stderr:\nUnable to find full path for \"/opt/.../bin/file\"\n\nSetting the +r flags on the file solves the problem.\n\nThe file can be executed from command line. The file can be executed with Runtime.getRuntime().exec(...).\n\nSince Spawner extends java.lang.Process, it would be reasonable to expect that a file that can be executed with Process should also be able to be executed with Spawner, since Spawner extends Process.\n\nSome files (specially files with suid) may be packaged and installed without read permissions.\n\nMore information:\n$ uname -a\nLinux dfferber 2.6.17-11-generic #2 SMP Thu Feb 1 19:52:28 UTC 2007 i686 GNU/Linux\n\nEclipse Java Development Tools SDK\nVersion: 3.2.1.r321_v20060905-R4CM1Znkvre9wC-\nBuild id: M20060921-0945\n\nEclipse C/C++ Development Tools SDK\nVersion: 3.1.2.200702150621\nBuild id: 200702150621"
  ],
  "commentCreationDates": [
    "2007-04-04T21:52:00+02:00"
  ],
  "traces": [
    {
      "exceptionType": "java.io.IOException",
      "message": "Exec error:Cannot run /opt/ibm/systemsim-cell/bin/snif",
      "elements": [
        {
          "method": "org.eclipse.cdt.utils.spawner.Spawner.exec",
          "source": "Spawner.java:243"
        },
        {
          "method": "org.eclipse.cdt.utils.spawner.Spawner.\u003cinit\u003e",
          "source": "Spawner.java:57"
        },
        {
          "method": "org.eclipse.cdt.utils.spawner.Spawner.\u003cinit\u003e",
          "source": "Spawner.java:85"
        },
        {
          "method": "org.eclipse.cdt.utils.spawner.ProcessFactory.exec",
          "source": "ProcessFactory.java:65"
        }
      ],
      "number": 0,
      "commentIndex": 0,
      "bugId": "181047",
      "date": "2007-04-04T21:52:00+02:00",
      "product": "CDT",
      "component": "cdt-core",
      "severity": "normal"
    }
  ],
  "groupId": "181047",
  "bugId": "181047",
  "date": "2007-04-04T21:52:00+02:00",
  "product": "CDT",
  "component": "cdt-core",
  "severity": "normal"
}