{
  "comments": [
    "With eclipse-platorm-3.3m6-win32 on Windows XP SP1, Sun 1.4.2_13:\n\nHelp \u003e Software Updates \u003e Find and Install \u003e Search for New Features\n  Add 2 remote sites:\n    1: Eclipse 3.3 Milestone Updates, \n    2: TM testUpdates\n  Select both sites, press next, select the original Eclipse site.\n\nExpand the TM testUpdates site, select a feature. UM detects that the feature depends on something which is available on the other (3.3 Milestone Updates Site). Observe following NPE, which is not critical since it is just logged but everything else works as expected:\n\njava.lang.NullPointerException\n\tat org.eclipse.update.internal.ui.wizards.ReviewPage$TreeContentProvider.getParent(ReviewPage.java:185)\n\tat org.eclipse.update.internal.ui.wizards.ReviewPage.getSite(ReviewPage.java:1398)\n\tat org.eclipse.update.internal.ui.wizards.ReviewPage.access$29(ReviewPage.java:1395)\n\tat org.eclipse.update.internal.ui.wizards.ReviewPage$14.run(ReviewPage.java:837)\n\tat org.eclipse.jface.operation.ModalContext$ModalContextThread.run(ModalContext.java:113)",
    "I am seeing this error even when updating from single update site. The NPE pops up when I check individual features (even those that are perfectly valid on their own), and when I close NPE error dialog Next button is not enabled. The only workaround is to check parent node and then uncheck features you don\u0027t want to install, which is quite time consuming and users will hit into it every time when updating from Callisto/Europa update site.\n\nSo, I believe severity of this issue should be increased.",
    "Using the scenario in bug #188318, I could not reproduce the issue any more -- no NPEs seen anywhere. But I did not test the original error report.\n\nEugene could you give it a try with 3.3RC1 so it can be marked WORKSFORM, hopefully?",
    "I\u0027ve just had this NPE in I20070625-1500 (3.3) after checking all update site and then trying to check\nEuropa Discovery Site \u003e  Web and JEE Dev. \u003e Eclipse XML Editors and Tools.\n\n(See problem analysis below.)\n\n!ENTRY org.eclipse.update.ui 4 0 2007-07-24 16:32:13.953\n!MESSAGE java.lang.NullPointerException\n!STACK 0\njava.lang.NullPointerException\n        at org.eclipse.update.internal.ui.wizards.ReviewPage$TreeContentProvider.getParent(ReviewPage.java:181)\n        at org.eclipse.update.internal.ui.wizards.ReviewPage.getSite(ReviewPage.java:1402)\n        at org.eclipse.update.internal.ui.wizards.ReviewPage.access$29(ReviewPage.java:1399)\n        at org.eclipse.update.internal.ui.wizards.ReviewPage$14.run(ReviewPage.java:840)\n        at org.eclipse.jface.operation.ModalContext$ModalContextThread.run(ModalContext.java:113)\n\n\nThe install I used had a probably outdated version of GEF installed, which resulted in a bunch of messages like the one below in the log.\n\nThe problem is that SiteBookmark.getSite(boolean, IProgressMonitor) catches and logs the CoreException, and then returns null, which must result in an NPE in ReviewPage.TreeContentProvider.getParent(Object):\n  if (sites[i].getSite(false, null).getURL() !\u003d \n      f.getSite().getSiteContentProvider().getURL()) {\n\n\n!MESSAGE Unable to access site: \"http://download.eclipse.org/tools/gef/milestones/update-site/site.xml\" [Server returned HTTP response code: \"404 Not\nFound\" for URL: http://download.eclipse.org/tools/gef/milestones/update-site/site.xml.]\n!STACK 0\norg.eclipse.update.internal.core.FatalIOException: Server returned HTTP response code: \"404 Not Found\" for URL: http://download.eclipse.org/tools/gef/\nmilestones/update-site/site.xml.\n        at org.eclipse.update.internal.core.UpdateManagerUtils.checkConnectionResult(UpdateManagerUtils.java:562)\n        at org.eclipse.update.internal.core.SiteURLFactory.createSite(SiteURLFactory.java:74)\n        at org.eclipse.update.internal.core.InternalSiteManager.createSite(InternalSiteManager.java:334)\n        at org.eclipse.update.internal.core.InternalSiteManager.createSite(InternalSiteManager.java:326)\n        at org.eclipse.update.internal.core.InternalSiteManager.createSite(InternalSiteManager.java:291)\n        at org.eclipse.update.internal.core.InternalSiteManager.attemptCreateSite(InternalSiteManager.java:222)\n        at org.eclipse.update.internal.core.InternalSiteManager.getSite(InternalSiteManager.java:162)\n        at org.eclipse.update.core.SiteManager.getSite(SiteManager.java:115)\n        at org.eclipse.update.internal.ui.model.SiteBookmark.connect(SiteBookmark.java:138)\n        at org.eclipse.update.internal.ui.model.SiteBookmark.connect(SiteBookmark.java:130)\n        at org.eclipse.update.internal.ui.model.SiteBookmark.getSite(SiteBookmark.java:116)\n        at org.eclipse.update.internal.ui.wizards.ReviewPage$TreeContentProvider.getParent(ReviewPage.java:181)\n        at org.eclipse.update.internal.ui.wizards.ReviewPage.getSite(ReviewPage.java:1402)\n        at org.eclipse.update.internal.ui.wizards.ReviewPage.access$29(ReviewPage.java:1399)\n        at org.eclipse.update.internal.ui.wizards.ReviewPage$14.run(ReviewPage.java:840)\n        at org.eclipse.jface.operation.ModalContext$ModalContextThread.run(ModalContext.java:113)\n",
    "*** Bug 191060 has been marked as a duplicate of this bug. ***"
  ],
  "commentCreationDates": [
    "2007-04-05T13:53:15+02:00",
    "2007-04-19T15:52:37+02:00",
    "2007-05-22T16:13:16+02:00",
    "2007-07-24T16:54:02+02:00",
    "2007-11-20T15:35:29+01:00"
  ],
  "traces": [
    {
      "exceptionType": "java.lang.NullPointerException",
      "elements": [
        {
          "method": "org.eclipse.update.internal.ui.wizards.ReviewPage$TreeContentProvider.getParent",
          "source": "ReviewPage.java:185"
        },
        {
          "method": "org.eclipse.update.internal.ui.wizards.ReviewPage.getSite",
          "source": "ReviewPage.java:1398"
        },
        {
          "method": "org.eclipse.update.internal.ui.wizards.ReviewPage.access$29",
          "source": "ReviewPage.java:1395"
        },
        {
          "method": "org.eclipse.update.internal.ui.wizards.ReviewPage$14.run",
          "source": "ReviewPage.java:837"
        },
        {
          "method": "org.eclipse.jface.operation.ModalContext$ModalContextThread.run",
          "source": "ModalContext.java:113"
        }
      ],
      "number": 0,
      "commentIndex": 0,
      "bugId": "181183",
      "date": "2007-04-05T13:53:15+02:00",
      "product": "Platform",
      "component": "Update",
      "severity": "major"
    },
    {
      "exceptionType": "java.lang.NullPointerException",
      "elements": [
        {
          "method": "org.eclipse.update.internal.ui.wizards.ReviewPage$TreeContentProvider.getParent",
          "source": "ReviewPage.java:181"
        },
        {
          "method": "org.eclipse.update.internal.ui.wizards.ReviewPage.getSite",
          "source": "ReviewPage.java:1402"
        },
        {
          "method": "org.eclipse.update.internal.ui.wizards.ReviewPage.access$29",
          "source": "ReviewPage.java:1399"
        },
        {
          "method": "org.eclipse.update.internal.ui.wizards.ReviewPage$14.run",
          "source": "ReviewPage.java:840"
        },
        {
          "method": "org.eclipse.jface.operation.ModalContext$ModalContextThread.run",
          "source": "ModalContext.java:113"
        }
      ],
      "number": 1,
      "commentIndex": 3,
      "bugId": "181183",
      "date": "2007-07-24T16:54:02+02:00",
      "product": "Platform",
      "component": "Update",
      "severity": "major"
    },
    {
      "exceptionType": "org.eclipse.update.internal.core.FatalIOException",
      "message": "Server returned HTTP response code: \"404 Not Found\" for URL: http://download.eclipse.org/tools/gef/ milestones/update-site/site.xml.",
      "elements": [
        {
          "method": "org.eclipse.update.internal.core.UpdateManagerUtils.checkConnectionResult",
          "source": "UpdateManagerUtils.java:562"
        },
        {
          "method": "org.eclipse.update.internal.core.SiteURLFactory.createSite",
          "source": "SiteURLFactory.java:74"
        },
        {
          "method": "org.eclipse.update.internal.core.InternalSiteManager.createSite",
          "source": "InternalSiteManager.java:334"
        },
        {
          "method": "org.eclipse.update.internal.core.InternalSiteManager.createSite",
          "source": "InternalSiteManager.java:326"
        },
        {
          "method": "org.eclipse.update.internal.core.InternalSiteManager.createSite",
          "source": "InternalSiteManager.java:291"
        },
        {
          "method": "org.eclipse.update.internal.core.InternalSiteManager.attemptCreateSite",
          "source": "InternalSiteManager.java:222"
        },
        {
          "method": "org.eclipse.update.internal.core.InternalSiteManager.getSite",
          "source": "InternalSiteManager.java:162"
        },
        {
          "method": "org.eclipse.update.core.SiteManager.getSite",
          "source": "SiteManager.java:115"
        },
        {
          "method": "org.eclipse.update.internal.ui.model.SiteBookmark.connect",
          "source": "SiteBookmark.java:138"
        },
        {
          "method": "org.eclipse.update.internal.ui.model.SiteBookmark.connect",
          "source": "SiteBookmark.java:130"
        },
        {
          "method": "org.eclipse.update.internal.ui.model.SiteBookmark.getSite",
          "source": "SiteBookmark.java:116"
        },
        {
          "method": "org.eclipse.update.internal.ui.wizards.ReviewPage$TreeContentProvider.getParent",
          "source": "ReviewPage.java:181"
        },
        {
          "method": "org.eclipse.update.internal.ui.wizards.ReviewPage.getSite",
          "source": "ReviewPage.java:1402"
        },
        {
          "method": "org.eclipse.update.internal.ui.wizards.ReviewPage.access$29",
          "source": "ReviewPage.java:1399"
        },
        {
          "method": "org.eclipse.update.internal.ui.wizards.ReviewPage$14.run",
          "source": "ReviewPage.java:840"
        },
        {
          "method": "org.eclipse.jface.operation.ModalContext$ModalContextThread.run",
          "source": "ModalContext.java:113"
        }
      ],
      "number": 2,
      "commentIndex": 3,
      "bugId": "181183",
      "date": "2007-07-24T16:54:02+02:00",
      "product": "Platform",
      "component": "Update",
      "severity": "major"
    }
  ],
  "groupId": "181183",
  "bugId": "181183",
  "date": "2007-04-05T13:53:15+02:00",
  "product": "Platform",
  "component": "Update",
  "severity": "major"
}