{
  "comments": [
    "Build 20020528\n\nStarting a 20020527 workspace where jdtcore was already using classpath \ncontainer, I got the following exception (which prevented the package view from \nbeing created).\n\n!ENTRY org.eclipse.core.resources 1 4 May 28, 2002 23:54:53.694\n!MESSAGE Unable to find Action Set: org.eclipse.jdt.debug.ui.JDTLaunchActionSet\nUnable to find Action Set: org.eclipse.jdt.debug.ui.JDTLaunchActionSet\n!ENTRY org.eclipse.core.resources 1 4 May 28, 2002 23:54:53.704\n!MESSAGE Unable to find Action Set: org.eclipse.jdt.junit.JUnitLaunchActionSet\nUnable to find Action Set: org.eclipse.jdt.junit.JUnitLaunchActionSet\n!ENTRY org.eclipse.ui 4 2 May 28, 2002 23:54:57.259\n!MESSAGE Problems occurred when invoking code from plug-in: org.eclipse.ui.\n!STACK 0\njava.lang.IllegalArgumentException: Duplicate VM: 0\n        at org.eclipse.jdt.launching.AbstractVMInstallType.createVMInstall\n(AbstractVMInstallType.java:87)\n        at org.eclipse.jdt.launching.JavaRuntime.detectVMConfiguration\n(JavaRuntime.java:1176)\n        at org.eclipse.jdt.launching.JavaRuntime.getDefaultVMInstall\n(JavaRuntime.java:402)\n        at org.eclipse.jdt.internal.launching.JREContainerInitializer.resolveVM\n(JREContainerInitializer.java:122)\n        at org.eclipse.jdt.internal.launching.JREContainerInitializer.initialize\n(JREContainerInitializer.java:53)\n        at org.eclipse.jdt.core.JavaCore.getClasspathContainer\n(JavaCore.java:455)\n        at org.eclipse.jdt.internal.core.JavaProject.getResolvedClasspath\n(JavaProject.java:1366)\n        at org.eclipse.jdt.internal.core.JavaProject.getResolvedClasspath\n(JavaProject.java:1306)\n        at org.eclipse.jdt.internal.core.JavaProject.getResolvedClasspath\n(JavaProject.java:1278)\n        at org.eclipse.jdt.internal.core.JavaProject.updatePackageFragmentRoots\n(JavaProject.java:2177)\n        at org.eclipse.jdt.internal.core.JavaProject.setRawClasspath0\n(JavaProject.java:2063)\n        at org.eclipse.jdt.internal.core.JavaProject.generateInfos\n(JavaProject.java:800)\n        at org.eclipse.jdt.internal.core.Openable.buildStructure\n(Openable.java:83)\n        at org.eclipse.jdt.internal.core.Openable.openWhenClosed\n(Openable.java:404)\n        at org.eclipse.jdt.internal.core.JavaProject.openWhenClosed\n(JavaProject.java:1667)\n        at org.eclipse.jdt.internal.core.JavaElement.openHierarchy\n(JavaElement.java:523)\n        at org.eclipse.jdt.internal.core.JavaElement.getElementInfo\n(JavaElement.java:310)\n        at org.eclipse.jdt.internal.core.JavaElement.getChildren\n(JavaElement.java:264)\n        at org.eclipse.jdt.internal.core.Openable.hasChildren(Openable.java:284)\n        at org.eclipse.jdt.ui.StandardJavaElementContentProvider.hasChildren\n(StandardJavaElementContentProvider.java:194)\n        at org.eclipse.jface.viewers.AbstractTreeViewer.isExpandable\n(AbstractTreeViewer.java:926)\n        at org.eclipse.jface.viewers.AbstractTreeViewer.updatePlus\n(AbstractTreeViewer.java:1269)\n        at org.eclipse.jface.viewers.AbstractTreeViewer.createTreeItem\n(AbstractTreeViewer.java:259)\n        at org.eclipse.jface.viewers.AbstractTreeViewer.createChildren\n(AbstractTreeViewer.java:243)\n        at org.eclipse.jface.viewers.AbstractTreeViewer$2.run\n(AbstractTreeViewer.java:646)\n        at org.eclipse.jface.viewers.StructuredViewer.preservingSelection\n(StructuredViewer.java:688)\n        at org.eclipse.jface.viewers.AbstractTreeViewer.inputChanged\n(AbstractTreeViewer.java:638)\n        at org.eclipse.jface.viewers.ContentViewer.setInput\n(ContentViewer.java:234)\n        at org.eclipse.jface.viewers.StructuredViewer.setInput\n(StructuredViewer.java:875)\n        at \norg.eclipse.jdt.internal.ui.packageview.PackageExplorerPart.createPartControl\n(PackageExplorerPart.java:278)\n        at org.eclipse.ui.internal.PartPane$4.run(PartPane.java:133)\n        at org.eclipse.core.internal.runtime.InternalPlatform.run\n(InternalPlatform.java:802)\n        at org.eclipse.core.runtime.Platform.run(Platform.java:416)\n        at org.eclipse.ui.internal.PartPane.createChildControl\n(PartPane.java:131)\n        at org.eclipse.ui.internal.PartPane.createControl(PartPane.java:175)\n        at org.eclipse.ui.internal.ViewPane.createControl(ViewPane.java:179)\n        at org.eclipse.ui.internal.PartTabFolder.createPartTab\n(PartTabFolder.java:245)\n        at org.eclipse.ui.internal.PartTabFolder.createControl\n(PartTabFolder.java:217)\n        at org.eclipse.ui.internal.PartSashContainer.createControl\n(PartSashContainer.java:177)\n        at org.eclipse.ui.internal.PerspectivePresentation.activate\n(PerspectivePresentation.java:94)\n        at org.eclipse.ui.internal.Perspective.onActivate(Perspective.java:657)\n        at org.eclipse.ui.internal.WorkbenchPage.onActivate\n(WorkbenchPage.java:1545)\n        at org.eclipse.ui.internal.WorkbenchWindow$7.run\n(WorkbenchWindow.java:1150)\n        at org.eclipse.swt.custom.BusyIndicator.showWhile(BusyIndicator.java:56)\n        at org.eclipse.ui.internal.WorkbenchWindow.setActivePage\n(WorkbenchWindow.java:1137)\n        at org.eclipse.ui.internal.WorkbenchWindow.restoreState\n(WorkbenchWindow.java:1050)\n        at org.eclipse.ui.internal.Workbench.restoreState(Workbench.java:988)\n        at org.eclipse.ui.internal.Workbench.access$7(Workbench.java:968)\n        at org.eclipse.ui.internal.Workbench$6.run(Workbench.java:793)\n        at org.eclipse.core.internal.runtime.InternalPlatform.run\n(InternalPlatform.java:802)\n        at org.eclipse.core.runtime.Platform.run(Platform.java:416)\n        at org.eclipse.ui.internal.Workbench.openPreviousWorkbenchState\n(Workbench.java:745)\n        at org.eclipse.ui.internal.Workbench.init(Workbench.java:559)\n        at org.eclipse.ui.internal.Workbench.run(Workbench.java:1061)\n        at org.eclipse.core.internal.boot.InternalBootLoader.run\n(InternalBootLoader.java:739)\n        at org.eclipse.core.boot.BootLoader.run(BootLoader.java:462)\n        at java.lang.reflect.Method.invoke(Native Method)\n        at org.eclipse.core.launcher.Main.basicRun(Main.java:200)\n        at org.eclipse.core.launcher.Main.run(Main.java:643)\n        at org.eclipse.core.launcher.Main.main(Main.java:476)",
    "I can see what happenned, but i do not know how to reproduce the problem. There \nmust have been (at least) two different VM install types, both of which at some \npoint detected a default VM install (assigning an ID of 0). Then, one of the \ninstalls went missing, and we re-detected a VM install of the other type, with \nthe same Id.\n\nCan put a fix in the code.",
    "I zipped up my workspace. Let me know if you want it (or part of it, since it \nis more than 100MB big)",
    "For now, keep your workspace. When I believe I have a patch I will send it to \nyou to try it out.",
    "Fixed.",
    "Please verify code (I will send patch to Jerome for testing). See \nJavaRuntime.detectVMConfiguration().",
    "Verified code.  Jerome, if the patch works for you, please set status to verified.",
    "Verified."
  ],
  "commentCreationDates": [
    "2002-05-28T23:50:22+02:00",
    "2002-05-29T03:51:22+02:00",
    "2002-05-29T10:37:50+02:00",
    "2002-05-29T14:26:10+02:00",
    "2002-05-29T15:55:15+02:00",
    "2002-05-29T15:55:53+02:00",
    "2002-05-29T18:49:58+02:00",
    "2002-05-30T11:21:45+02:00"
  ],
  "traces": [
    {
      "exceptionType": "java.lang.IllegalArgumentException",
      "message": "Duplicate VM: 0",
      "elements": [
        {
          "method": "org.eclipse.jdt.launching.AbstractVMInstallType.createVMInstall",
          "source": "AbstractVMInstallType.java:87"
        },
        {
          "method": "org.eclipse.jdt.launching.JavaRuntime.detectVMConfiguration",
          "source": "JavaRuntime.java:1176"
        },
        {
          "method": "org.eclipse.jdt.launching.JavaRuntime.getDefaultVMInstall",
          "source": "JavaRuntime.java:402"
        },
        {
          "method": "org.eclipse.jdt.internal.launching.JREContainerInitializer.resolveVM",
          "source": "JREContainerInitializer.java:122"
        },
        {
          "method": "org.eclipse.jdt.internal.launching.JREContainerInitializer.initialize",
          "source": "JREContainerInitializer.java:53"
        },
        {
          "method": "org.eclipse.jdt.core.JavaCore.getClasspathContainer",
          "source": "JavaCore.java:455"
        },
        {
          "method": "org.eclipse.jdt.internal.core.JavaProject.getResolvedClasspath",
          "source": "JavaProject.java:1366"
        },
        {
          "method": "org.eclipse.jdt.internal.core.JavaProject.getResolvedClasspath",
          "source": "JavaProject.java:1306"
        },
        {
          "method": "org.eclipse.jdt.internal.core.JavaProject.getResolvedClasspath",
          "source": "JavaProject.java:1278"
        },
        {
          "method": "org.eclipse.jdt.internal.core.JavaProject.updatePackageFragmentRoots",
          "source": "JavaProject.java:2177"
        },
        {
          "method": "org.eclipse.jdt.internal.core.JavaProject.setRawClasspath0",
          "source": "JavaProject.java:2063"
        },
        {
          "method": "org.eclipse.jdt.internal.core.JavaProject.generateInfos",
          "source": "JavaProject.java:800"
        },
        {
          "method": "org.eclipse.jdt.internal.core.Openable.buildStructure",
          "source": "Openable.java:83"
        },
        {
          "method": "org.eclipse.jdt.internal.core.Openable.openWhenClosed",
          "source": "Openable.java:404"
        },
        {
          "method": "org.eclipse.jdt.internal.core.JavaProject.openWhenClosed",
          "source": "JavaProject.java:1667"
        },
        {
          "method": "org.eclipse.jdt.internal.core.JavaElement.openHierarchy",
          "source": "JavaElement.java:523"
        },
        {
          "method": "org.eclipse.jdt.internal.core.JavaElement.getElementInfo",
          "source": "JavaElement.java:310"
        },
        {
          "method": "org.eclipse.jdt.internal.core.JavaElement.getChildren",
          "source": "JavaElement.java:264"
        },
        {
          "method": "org.eclipse.jdt.internal.core.Openable.hasChildren",
          "source": "Openable.java:284"
        },
        {
          "method": "org.eclipse.jdt.ui.StandardJavaElementContentProvider.hasChildren",
          "source": "StandardJavaElementContentProvider.java:194"
        },
        {
          "method": "org.eclipse.jface.viewers.AbstractTreeViewer.isExpandable",
          "source": "AbstractTreeViewer.java:926"
        },
        {
          "method": "org.eclipse.jface.viewers.AbstractTreeViewer.updatePlus",
          "source": "AbstractTreeViewer.java:1269"
        },
        {
          "method": "org.eclipse.jface.viewers.AbstractTreeViewer.createTreeItem",
          "source": "AbstractTreeViewer.java:259"
        },
        {
          "method": "org.eclipse.jface.viewers.AbstractTreeViewer.createChildren",
          "source": "AbstractTreeViewer.java:243"
        },
        {
          "method": "org.eclipse.jface.viewers.AbstractTreeViewer$2.run",
          "source": "AbstractTreeViewer.java:646"
        },
        {
          "method": "org.eclipse.jface.viewers.StructuredViewer.preservingSelection",
          "source": "StructuredViewer.java:688"
        },
        {
          "method": "org.eclipse.jface.viewers.AbstractTreeViewer.inputChanged",
          "source": "AbstractTreeViewer.java:638"
        },
        {
          "method": "org.eclipse.jface.viewers.ContentViewer.setInput",
          "source": "ContentViewer.java:234"
        },
        {
          "method": "org.eclipse.jface.viewers.StructuredViewer.setInput",
          "source": "StructuredViewer.java:875"
        },
        {
          "method": "org.eclipse.jdt.internal.ui.packageview.PackageExplorerPart.createPartControl",
          "source": "PackageExplorerPart.java:278"
        },
        {
          "method": "org.eclipse.ui.internal.PartPane$4.run",
          "source": "PartPane.java:133"
        },
        {
          "method": "org.eclipse.core.internal.runtime.InternalPlatform.run",
          "source": "InternalPlatform.java:802"
        },
        {
          "method": "org.eclipse.core.runtime.Platform.run",
          "source": "Platform.java:416"
        },
        {
          "method": "org.eclipse.ui.internal.PartPane.createChildControl",
          "source": "PartPane.java:131"
        },
        {
          "method": "org.eclipse.ui.internal.PartPane.createControl",
          "source": "PartPane.java:175"
        },
        {
          "method": "org.eclipse.ui.internal.ViewPane.createControl",
          "source": "ViewPane.java:179"
        },
        {
          "method": "org.eclipse.ui.internal.PartTabFolder.createPartTab",
          "source": "PartTabFolder.java:245"
        },
        {
          "method": "org.eclipse.ui.internal.PartTabFolder.createControl",
          "source": "PartTabFolder.java:217"
        },
        {
          "method": "org.eclipse.ui.internal.PartSashContainer.createControl",
          "source": "PartSashContainer.java:177"
        },
        {
          "method": "org.eclipse.ui.internal.PerspectivePresentation.activate",
          "source": "PerspectivePresentation.java:94"
        },
        {
          "method": "org.eclipse.ui.internal.Perspective.onActivate",
          "source": "Perspective.java:657"
        },
        {
          "method": "org.eclipse.ui.internal.WorkbenchPage.onActivate",
          "source": "WorkbenchPage.java:1545"
        },
        {
          "method": "org.eclipse.ui.internal.WorkbenchWindow$7.run",
          "source": "WorkbenchWindow.java:1150"
        },
        {
          "method": "org.eclipse.swt.custom.BusyIndicator.showWhile",
          "source": "BusyIndicator.java:56"
        },
        {
          "method": "org.eclipse.ui.internal.WorkbenchWindow.setActivePage",
          "source": "WorkbenchWindow.java:1137"
        },
        {
          "method": "org.eclipse.ui.internal.WorkbenchWindow.restoreState",
          "source": "WorkbenchWindow.java:1050"
        },
        {
          "method": "org.eclipse.ui.internal.Workbench.restoreState",
          "source": "Workbench.java:988"
        },
        {
          "method": "org.eclipse.ui.internal.Workbench.access$7",
          "source": "Workbench.java:968"
        },
        {
          "method": "org.eclipse.ui.internal.Workbench$6.run",
          "source": "Workbench.java:793"
        },
        {
          "method": "org.eclipse.core.internal.runtime.InternalPlatform.run",
          "source": "InternalPlatform.java:802"
        },
        {
          "method": "org.eclipse.core.runtime.Platform.run",
          "source": "Platform.java:416"
        },
        {
          "method": "org.eclipse.ui.internal.Workbench.openPreviousWorkbenchState",
          "source": "Workbench.java:745"
        },
        {
          "method": "org.eclipse.ui.internal.Workbench.init",
          "source": "Workbench.java:559"
        },
        {
          "method": "org.eclipse.ui.internal.Workbench.run",
          "source": "Workbench.java:1061"
        },
        {
          "method": "org.eclipse.core.internal.boot.InternalBootLoader.run",
          "source": "InternalBootLoader.java:739"
        },
        {
          "method": "org.eclipse.core.boot.BootLoader.run",
          "source": "BootLoader.java:462"
        },
        {
          "method": "java.lang.reflect.Method.invoke",
          "source": "Native Method"
        },
        {
          "method": "org.eclipse.core.launcher.Main.basicRun",
          "source": "Main.java:200"
        },
        {
          "method": "org.eclipse.core.launcher.Main.run",
          "source": "Main.java:643"
        },
        {
          "method": "org.eclipse.core.launcher.Main.main",
          "source": "Main.java:476"
        }
      ],
      "number": 0,
      "commentIndex": 0,
      "bugId": "18115",
      "date": "2002-05-28T23:50:22+02:00",
      "product": "JDT",
      "component": "Debug",
      "severity": "normal"
    }
  ],
  "groupId": "18115",
  "bugId": "18115",
  "date": "2002-05-28T23:50:22+02:00",
  "product": "JDT",
  "component": "Debug",
  "severity": "normal"
}