{
  "comments": [
    "This problem was reported by Brian Moyle, and I have reproduced it with our \nlatest code on top of Windows F1:\n\nSteps:\n 1) New C/C++ project (\"test\")\n 2) New Directory (\"src\")\n 3) New File (\"src/hello.c\")\n 4) Edit hello.c:  main(){printf(\"hello world\\n\");}\n 5) Type \u003cctrl-s\u003e to save the editor\u0027s contents.\n\nError Box:\n Save Failed:org.eclipse.cdt.dstore.ui.resource.ElementMarker\n\nStack:\n java.lang.ClassCastException: \norg.eclipse.cdt.dstore.ui.resource.ElementMarker\n         at \norg.eclipse.debug.internal.ui.DefaultLabelProvider.getImage\n(DefaultLabelProvider.java:43)\n         at \norg.eclipse.debug.internal.ui.DelegatingModelPresentation.getDefaultImage\n(DelegatingModelPresentation.java:176)\n         at \norg.eclipse.debug.internal.ui.DelegatingModelPresentation.getImage\n(DelegatingModelPresentation.java:112)\n         at \norg.eclipse.cdt.cpp.ui.internal.editor.CppMarkerAnnotation.initialize\n(CppMarkerAnnotation.java:48)\n         at \norg.eclipse.ui.texteditor.MarkerAnnotation.\u003cinit\u003e(MarkerAnnotation.java:89)\n         at \norg.eclipse.cdt.cpp.ui.internal.editor.CppMarkerAnnotation.\u003cinit\u003e\n(CppMarkerAnnotation.java:24)\n         at \norg.eclipse.cdt.cpp.ui.internal.editor.CppDocumentProvider$CppMarkerAnnotationMo\ndel.createMarkerAnnotation(CppDocumentProvider.java:48)\n         at \norg.eclipse.ui.texteditor.AbstractMarkerAnnotationModel.addMarkerAnnotation\n(AbstractMarkerAnnotationModel.java:208)\n         at \norg.eclipse.ui.texteditor.AbstractMarkerAnnotationModel.catchupWithMarkers\n(AbstractMarkerAnnotationModel.java:386)\n         at \norg.eclipse.ui.texteditor.AbstractMarkerAnnotationModel.connected\n(AbstractMarkerAnnotationModel.java:221)\n         at \norg.eclipse.jface.text.source.AnnotationModel.connect(AnnotationModel.java:116)\n         at \ncom.ibm.lpex.alef.LpexAbstractTextEditor.saveToDocument\n(LpexAbstractTextEditor.java:1523)\n         at \ncom.ibm.lpex.alef.LpexAbstractTextEditor.performSaveOperation\n(LpexAbstractTextEditor.java:1549)\n         at \ncom.ibm.lpex.alef.LpexAbstractTextEditor.doSave\n(LpexAbstractTextEditor.java:1417)\n         at \norg.eclipse.cdt.cpp.ui.internal.editor.CppEditor.doSave(CppEditor.java:159)\n         at \norg.eclipse.ui.internal.EditorManager$10.run(EditorManager.java:960)\n         at \norg.eclipse.jface.operation.ModalContext.runInCurrentThread\n(ModalContext.java:296)\n         at \norg.eclipse.jface.operation.ModalContext.run(ModalContext.java:249)\n         at \norg.eclipse.jface.dialogs.ProgressMonitorDialog.run\n(ProgressMonitorDialog.java:335)\n         at \norg.eclipse.ui.internal.EditorManager.runProgressMonitorOperation\n(EditorManager.java:838)\n         at \norg.eclipse.ui.internal.EditorManager.saveEditor(EditorManager.java:965)\n         at \norg.eclipse.ui.internal.WorkbenchPage.saveEditor(WorkbenchPage.java:1945)\n         at org.eclipse.ui.internal.SaveAction.run(SaveAction.java:32)\n         at org.eclipse.jface.action.Action.runWithEvent(Action.java:590)\n         at \norg.eclipse.jface.action.ActionContributionItem.handleWidgetSelection\n(ActionContributionItem.java:407)\n         at \norg.eclipse.jface.action.ActionContributionItem.handleWidgetEvent\n(ActionContributionItem.java:361)\n         at \norg.eclipse.jface.action.ActionContributionItem.access$0\n(ActionContributionItem.java:352)\n         at \norg.eclipse.jface.action.ActionContributionItem$ActionListener.handleEvent\n(ActionContributionItem.java:47)\n         at org.eclipse.swt.widgets.EventTable.sendEvent(EventTable.java:75)\n         at org.eclipse.swt.widgets.Widget.sendEvent(Widget.java:825)\n         at \norg.eclipse.swt.widgets.Display.runDeferredEvents(Display.java:1527)\n         at \norg.eclipse.swt.widgets.Display.readAndDispatch(Display.java:1289)\n         at \norg.eclipse.ui.internal.Workbench.runEventLoop(Workbench.java:1085)\n         at org.eclipse.ui.internal.Workbench.run(Workbench.java:1068)\n         at \norg.eclipse.core.internal.boot.InternalBootLoader.run\n(InternalBootLoader.java:739)\n         at org.eclipse.core.boot.BootLoader.run(BootLoader.java:462)\n         at java.lang.reflect.Method.invoke(Native Method)\n         at org.eclipse.core.launcher.Main.basicRun(Main.java:200)\n         at org.eclipse.core.launcher.Main.run(Main.java:643)\n         at org.eclipse.core.launcher.Main.main(Main.java:476)",
    "ElementMarker should not be used for these new files.  The problem is that CDT \ndepends on Hosts which contributes the action for creating new files.  Hosts \ndoesn\u0027t know about Eclipse resources.  Eclipse resources are what should be used \n when we open the file from the CDT, so we need make use of CDT action loader, \ninstead of the Hosts action loader when using this command from the C projects \nview.    \n\nI\u0027ve put a fix in for this to make use of the CDT action loader for opening \nfiles.   The changes are in CVS.",
    "Closing"
  ],
  "commentCreationDates": [
    "2002-05-29T04:50:38+02:00",
    "2002-05-29T21:54:48+02:00",
    "2003-09-10T15:00:37+02:00"
  ],
  "traces": [
    {
      "exceptionType": "java.lang.ClassCastException",
      "message": "org.eclipse.cdt.dstore.ui.resource.ElementMarker",
      "elements": [
        {
          "method": "org.eclipse.debug.internal.ui.DefaultLabelProvider.getImage",
          "source": "DefaultLabelProvider.java:43"
        },
        {
          "method": "org.eclipse.debug.internal.ui.DelegatingModelPresentation.getDefaultImage",
          "source": "DelegatingModelPresentation.java:176"
        },
        {
          "method": "org.eclipse.debug.internal.ui.DelegatingModelPresentation.getImage",
          "source": "DelegatingModelPresentation.java:112"
        },
        {
          "method": "org.eclipse.cdt.cpp.ui.internal.editor.CppMarkerAnnotation.initialize",
          "source": "CppMarkerAnnotation.java:48"
        },
        {
          "method": "org.eclipse.ui.texteditor.MarkerAnnotation.\u003cinit\u003e",
          "source": "MarkerAnnotation.java:89"
        },
        {
          "method": "org.eclipse.cdt.cpp.ui.internal.editor.CppMarkerAnnotation.\u003cinit\u003e",
          "source": "CppMarkerAnnotation.java:24"
        },
        {
          "method": "org.eclipse.cdt.cpp.ui.internal.editor.CppDocumentProvider$CppMarkerAnnotationModel.createMarkerAnnotation",
          "source": "CppDocumentProvider.java:48"
        },
        {
          "method": "org.eclipse.ui.texteditor.AbstractMarkerAnnotationModel.addMarkerAnnotation",
          "source": "AbstractMarkerAnnotationModel.java:208"
        },
        {
          "method": "org.eclipse.ui.texteditor.AbstractMarkerAnnotationModel.catchupWithMarkers",
          "source": "AbstractMarkerAnnotationModel.java:386"
        },
        {
          "method": "org.eclipse.ui.texteditor.AbstractMarkerAnnotationModel.connected",
          "source": "AbstractMarkerAnnotationModel.java:221"
        },
        {
          "method": "org.eclipse.jface.text.source.AnnotationModel.connect",
          "source": "AnnotationModel.java:116"
        },
        {
          "method": "com.ibm.lpex.alef.LpexAbstractTextEditor.saveToDocument",
          "source": "LpexAbstractTextEditor.java:1523"
        },
        {
          "method": "com.ibm.lpex.alef.LpexAbstractTextEditor.performSaveOperation",
          "source": "LpexAbstractTextEditor.java:1549"
        },
        {
          "method": "com.ibm.lpex.alef.LpexAbstractTextEditor.doSave",
          "source": "LpexAbstractTextEditor.java:1417"
        },
        {
          "method": "org.eclipse.cdt.cpp.ui.internal.editor.CppEditor.doSave",
          "source": "CppEditor.java:159"
        },
        {
          "method": "org.eclipse.ui.internal.EditorManager$10.run",
          "source": "EditorManager.java:960"
        },
        {
          "method": "org.eclipse.jface.operation.ModalContext.runInCurrentThread",
          "source": "ModalContext.java:296"
        },
        {
          "method": "org.eclipse.jface.operation.ModalContext.run",
          "source": "ModalContext.java:249"
        },
        {
          "method": "org.eclipse.jface.dialogs.ProgressMonitorDialog.run",
          "source": "ProgressMonitorDialog.java:335"
        },
        {
          "method": "org.eclipse.ui.internal.EditorManager.runProgressMonitorOperation",
          "source": "EditorManager.java:838"
        },
        {
          "method": "org.eclipse.ui.internal.EditorManager.saveEditor",
          "source": "EditorManager.java:965"
        },
        {
          "method": "org.eclipse.ui.internal.WorkbenchPage.saveEditor",
          "source": "WorkbenchPage.java:1945"
        },
        {
          "method": "org.eclipse.ui.internal.SaveAction.run",
          "source": "SaveAction.java:32"
        },
        {
          "method": "org.eclipse.jface.action.Action.runWithEvent",
          "source": "Action.java:590"
        },
        {
          "method": "org.eclipse.jface.action.ActionContributionItem.handleWidgetSelection",
          "source": "ActionContributionItem.java:407"
        },
        {
          "method": "org.eclipse.jface.action.ActionContributionItem.handleWidgetEvent",
          "source": "ActionContributionItem.java:361"
        },
        {
          "method": "org.eclipse.jface.action.ActionContributionItem.access$0",
          "source": "ActionContributionItem.java:352"
        },
        {
          "method": "org.eclipse.jface.action.ActionContributionItem$ActionListener.handleEvent",
          "source": "ActionContributionItem.java:47"
        },
        {
          "method": "org.eclipse.swt.widgets.EventTable.sendEvent",
          "source": "EventTable.java:75"
        },
        {
          "method": "org.eclipse.swt.widgets.Widget.sendEvent",
          "source": "Widget.java:825"
        },
        {
          "method": "org.eclipse.swt.widgets.Display.runDeferredEvents",
          "source": "Display.java:1527"
        },
        {
          "method": "org.eclipse.swt.widgets.Display.readAndDispatch",
          "source": "Display.java:1289"
        },
        {
          "method": "org.eclipse.ui.internal.Workbench.runEventLoop",
          "source": "Workbench.java:1085"
        },
        {
          "method": "org.eclipse.ui.internal.Workbench.run",
          "source": "Workbench.java:1068"
        },
        {
          "method": "org.eclipse.core.internal.boot.InternalBootLoader.run",
          "source": "InternalBootLoader.java:739"
        },
        {
          "method": "org.eclipse.core.boot.BootLoader.run",
          "source": "BootLoader.java:462"
        },
        {
          "method": "java.lang.reflect.Method.invoke",
          "source": "Native Method"
        },
        {
          "method": "org.eclipse.core.launcher.Main.basicRun",
          "source": "Main.java:200"
        },
        {
          "method": "org.eclipse.core.launcher.Main.run",
          "source": "Main.java:643"
        },
        {
          "method": "org.eclipse.core.launcher.Main.main",
          "source": "Main.java:476"
        }
      ],
      "number": 0,
      "commentIndex": 0,
      "bugId": "18129",
      "date": "2002-05-29T04:50:38+02:00",
      "product": "CDT",
      "component": "UI",
      "severity": "major"
    }
  ],
  "groupId": "18129",
  "bugId": "18129",
  "date": "2002-05-29T04:50:38+02:00",
  "product": "CDT",
  "component": "UI",
  "severity": "major"
}