{
  "comments": [
    "Build ID: I20070323-1616\n\nSteps To Reproduce:\nI\u0027m using EMF 2.3.0.v200704050200.\n\n1. Follow the instructions at http://help.eclipse.org/help32/index.jsp?topic\u003d/org.eclipse.jet.doc/tasks/usingJetWithEMF.xhtml\n2. Run a JET Transformation using an ecore Model as input.\n3. Observe the dialog coming up with an internal error. The log output is below.\n\nI added the project \"org.eclipse.emf.ecore\" to the project dependencies, but it didn\u0027t help. It seems JET launcher uses another classpath, where it cannot find org.eclipse.emf.ecore.\n\n\nMore information:\n!ENTRY org.eclipse.core.jobs 4 2 2007-04-05 17:04:38.312\n!MESSAGE An internal error occurred during: \"Launching W2-JET\".\n!STACK 0\njava.lang.NoClassDefFoundError: org/eclipse/emf/ecore/EClassifier\n        at org.eclipse.jet.compiled._jet_main.generate(_jet_main.java:102)\n        at org.eclipse.jet.transform.TransformContextExtender.execute(TransformContextExtender.java:147)\n        at org.eclipse.jet.transform.TransformContextExtender.execute(TransformContextExtender.java:120)\n        at org.eclipse.jet.JET2Platform$4.run(JET2Platform.java:449)\n        at org.eclipse.jet.internal.runtime.JETBundleManager.run(JETBundleManager.java:331)\n        at org.eclipse.jet.JET2Platform.runTransform(JET2Platform.java:417)\n        at org.eclipse.jet.internal.launch.JETProcess.run(JETProcess.java:157)\n        at org.eclipse.jet.internal.launch.JET2TransformationDelegate.launch(JET2TransformationDelegate.java:60)\n        at org.eclipse.debug.internal.core.LaunchConfiguration.launch(LaunchConfiguration.java:766)\n        at org.eclipse.debug.internal.core.LaunchConfiguration.launch(LaunchConfiguration.java:608)\n        at org.eclipse.debug.internal.ui.DebugUIPlugin.buildAndLaunch(DebugUIPlugin.java:911)\n        at org.eclipse.debug.internal.ui.DebugUIPlugin$7.run(DebugUIPlugin.java:1114)\n        at org.eclipse.core.internal.jobs.Worker.run(Worker.java:58)",
    "This, of course, works on my machine :-(\n\nJET is using the standard Eclipse/OSGi bundle loader to load the JET project - there should be no difference from any other plug-in.\n\nThe message you are getting is consistent with not having org.eclipse.emf.ecore in your dependencies list, and running the transformation in spite of the compiler error. Are you should you saved the modified plug-in manifest?\n\n\n",
    "Resolving as works for me. If you can provide more information, or a test case, please re-open. "
  ],
  "commentCreationDates": [
    "2007-04-05T17:12:07+02:00",
    "2007-04-05T18:55:09+02:00",
    "2007-05-08T20:55:56+02:00"
  ],
  "traces": [
    {
      "exceptionType": "java.lang.NoClassDefFoundError",
      "message": "org/eclipse/emf/ecore/EClassifier",
      "elements": [
        {
          "method": "org.eclipse.jet.compiled._jet_main.generate",
          "source": "_jet_main.java:102"
        },
        {
          "method": "org.eclipse.jet.transform.TransformContextExtender.execute",
          "source": "TransformContextExtender.java:147"
        },
        {
          "method": "org.eclipse.jet.transform.TransformContextExtender.execute",
          "source": "TransformContextExtender.java:120"
        },
        {
          "method": "org.eclipse.jet.JET2Platform$4.run",
          "source": "JET2Platform.java:449"
        },
        {
          "method": "org.eclipse.jet.internal.runtime.JETBundleManager.run",
          "source": "JETBundleManager.java:331"
        },
        {
          "method": "org.eclipse.jet.JET2Platform.runTransform",
          "source": "JET2Platform.java:417"
        },
        {
          "method": "org.eclipse.jet.internal.launch.JETProcess.run",
          "source": "JETProcess.java:157"
        },
        {
          "method": "org.eclipse.jet.internal.launch.JET2TransformationDelegate.launch",
          "source": "JET2TransformationDelegate.java:60"
        },
        {
          "method": "org.eclipse.debug.internal.core.LaunchConfiguration.launch",
          "source": "LaunchConfiguration.java:766"
        },
        {
          "method": "org.eclipse.debug.internal.core.LaunchConfiguration.launch",
          "source": "LaunchConfiguration.java:608"
        },
        {
          "method": "org.eclipse.debug.internal.ui.DebugUIPlugin.buildAndLaunch",
          "source": "DebugUIPlugin.java:911"
        },
        {
          "method": "org.eclipse.debug.internal.ui.DebugUIPlugin$7.run",
          "source": "DebugUIPlugin.java:1114"
        },
        {
          "method": "org.eclipse.core.internal.jobs.Worker.run",
          "source": "Worker.java:58"
        }
      ],
      "number": 0,
      "commentIndex": 0,
      "bugId": "181216",
      "date": "2007-04-05T17:12:07+02:00",
      "product": "M2T",
      "component": "Jet",
      "severity": "normal"
    }
  ],
  "groupId": "181216",
  "bugId": "181216",
  "date": "2007-04-05T17:12:07+02:00",
  "product": "M2T",
  "component": "Jet",
  "severity": "normal"
}