{
  "comments": [
    "Version: 3.3.0\nBuild id: I20070410-1043\n\nJ2RE 5.0 IBM J9 2.3 Windows XP x86-32 build j9vmwi3223-20070201\n\ntest scenario (though hardly reproducible)\n- debug some code and stop at some BP\n- open a second Debug perspective\n- wait some time\n- play with views (maximize / minimize)\n\n--\u003e error msg on screen and AIOOBE in the console (to be attached files)",
    "Created an attachment (id\u003d63584)\nscreen shot\n\n",
    "Created an attachment (id\u003d63586)\n.log file\n\n",
    "Fixed in FilterTransform. We do a binary search for a number in a sorted array of integers. We were checking for a result of \"\u003e 0\" when we should be checking for \"\u003e\u003d 0\" (as 0 indicates the element was found at the first position in the array). The code was bailing to a section where it assumed the element was not found, and caused the error.",
    "Please verify, Mike.",
    "verified",
    "Re-opening. This fix exposed another problem:\n\nCaused by: java.lang.IllegalArgumentException: Index out of bounds\n        at org.eclipse.swt.SWT.error(SWT.java:3518)\n        at org.eclipse.swt.SWT.error(SWT.java:3457)\n        at org.eclipse.swt.SWT.error(SWT.java:3428)\n        at org.eclipse.swt.widgets.Widget.error(Widget.java:432)\n        at org.eclipse.swt.widgets.TreeItem.getItem(TreeItem.java:718)\n        at\norg.eclipse.debug.internal.ui.viewers.model.InternalTreeModelViewer$3.run(InternalTreeModelViewer.java:1084)\n        at\norg.eclipse.jface.viewers.StructuredViewer.preservingSelection(StructuredViewer.java:1333)\n        at\norg.eclipse.debug.internal.ui.viewers.model.InternalTreeModelViewer.replace(InternalTreeModelViewer.java:1073)\n        at\norg.eclipse.debug.internal.ui.viewers.model.TreeModelContentProvider.expand(TreeModelContentProvider.java:159)\n        at\norg.eclipse.debug.internal.ui.viewers.model.TreeModelContentProvider.handleExpand(TreeModelContentProvider.java:141)\n        at\norg.eclipse.debug.internal.ui.viewers.model.ModelContentProvider.updateNodes(ModelContentProvider.java:608)\n        at\norg.eclipse.debug.internal.ui.viewers.model.ModelContentProvider.updateNodes(ModelContentProvider.java:634)\n        at\norg.eclipse.debug.internal.ui.viewers.model.ModelContentProvider.updateNodes(ModelContentProvider.java:634)\n        at\norg.eclipse.debug.internal.ui.viewers.model.ModelContentProvider.updateNodes(ModelContentProvider.java:634)\n        at\norg.eclipse.debug.internal.ui.viewers.model.ModelContentProvider$7.runInUIThread(ModelContentProvider.java:583)\n        at org.eclipse.ui.progress.UIJob$1.run(UIJob.java:94)\n",
    "Marking fixed/verified again. This was not causing the IIOB.",
    "Verified."
  ],
  "commentCreationDates": [
    "2007-04-12T09:02:13+02:00",
    "2007-04-12T09:02:55+02:00",
    "2007-04-12T09:03:31+02:00",
    "2007-04-12T16:44:22+02:00",
    "2007-04-12T16:48:35+02:00",
    "2007-04-12T18:16:30+02:00",
    "2007-04-12T18:28:07+02:00",
    "2007-04-12T18:47:26+02:00",
    "2007-04-12T18:47:38+02:00"
  ],
  "traces": [
    {
      "exceptionType": "java.lang.IllegalArgumentException",
      "message": "Index out of bounds",
      "elements": [
        {
          "method": "org.eclipse.swt.SWT.error",
          "source": "SWT.java:3518"
        },
        {
          "method": "org.eclipse.swt.SWT.error",
          "source": "SWT.java:3457"
        },
        {
          "method": "org.eclipse.swt.SWT.error",
          "source": "SWT.java:3428"
        },
        {
          "method": "org.eclipse.swt.widgets.Widget.error",
          "source": "Widget.java:432"
        },
        {
          "method": "org.eclipse.swt.widgets.TreeItem.getItem",
          "source": "TreeItem.java:718"
        },
        {
          "method": "org.eclipse.debug.internal.ui.viewers.model.InternalTreeModelViewer$3.run",
          "source": "InternalTreeModelViewer.java:1084"
        },
        {
          "method": "org.eclipse.jface.viewers.StructuredViewer.preservingSelection",
          "source": "StructuredViewer.java:1333"
        },
        {
          "method": "org.eclipse.debug.internal.ui.viewers.model.InternalTreeModelViewer.replace",
          "source": "InternalTreeModelViewer.java:1073"
        },
        {
          "method": "org.eclipse.debug.internal.ui.viewers.model.TreeModelContentProvider.expand",
          "source": "TreeModelContentProvider.java:159"
        },
        {
          "method": "org.eclipse.debug.internal.ui.viewers.model.TreeModelContentProvider.handleExpand",
          "source": "TreeModelContentProvider.java:141"
        },
        {
          "method": "org.eclipse.debug.internal.ui.viewers.model.ModelContentProvider.updateNodes",
          "source": "ModelContentProvider.java:608"
        },
        {
          "method": "org.eclipse.debug.internal.ui.viewers.model.ModelContentProvider.updateNodes",
          "source": "ModelContentProvider.java:634"
        },
        {
          "method": "org.eclipse.debug.internal.ui.viewers.model.ModelContentProvider.updateNodes",
          "source": "ModelContentProvider.java:634"
        },
        {
          "method": "org.eclipse.debug.internal.ui.viewers.model.ModelContentProvider.updateNodes",
          "source": "ModelContentProvider.java:634"
        },
        {
          "method": "org.eclipse.debug.internal.ui.viewers.model.ModelContentProvider$7.runInUIThread",
          "source": "ModelContentProvider.java:583"
        },
        {
          "method": "org.eclipse.ui.progress.UIJob$1.run",
          "source": "UIJob.java:94"
        }
      ],
      "number": 0,
      "commentIndex": 6,
      "bugId": "182084",
      "date": "2007-04-12T18:28:07+02:00",
      "product": "JDT",
      "component": "Debug",
      "severity": "normal"
    }
  ],
  "groupId": "182084",
  "bugId": "182084",
  "date": "2007-04-12T09:02:13+02:00",
  "product": "JDT",
  "component": "Debug",
  "severity": "normal"
}