{
  "comments": [
    "I see the following exception running the test suite. It indicates we\u0027re trying to expand a filtered element in the tree. Looks like a timing issue in the test suite where we are expanding a thread but the target has already terminated.\n\n\nCaused by: java.lang.IllegalArgumentException: Index out of bounds\n        at org.eclipse.swt.SWT.error(SWT.java:3518)\n        at org.eclipse.swt.SWT.error(SWT.java:3457)\n        at org.eclipse.swt.SWT.error(SWT.java:3428)\n        at org.eclipse.swt.widgets.Widget.error(Widget.java:432)\n        at org.eclipse.swt.widgets.TreeItem.getItem(TreeItem.java:718)\n        at\norg.eclipse.debug.internal.ui.viewers.model.InternalTreeModelViewer$3.run(InternalTreeModelViewer.java:1084)\n        at\norg.eclipse.jface.viewers.StructuredViewer.preservingSelection(StructuredViewer.java:1333)\n        at\norg.eclipse.debug.internal.ui.viewers.model.InternalTreeModelViewer.replace(InternalTreeModelViewer.java:1073)\n        at\norg.eclipse.debug.internal.ui.viewers.model.TreeModelContentProvider.expand(TreeModelContentProvider.java:159)\n        at\norg.eclipse.debug.internal.ui.viewers.model.TreeModelContentProvider.handleExpand(TreeModelContentProvider.java:141)\n        at\norg.eclipse.debug.internal.ui.viewers.model.ModelContentProvider.updateNodes(ModelContentProvider.java:608)\n        at\norg.eclipse.debug.internal.ui.viewers.model.ModelContentProvider.updateNodes(ModelContentProvider.java:634)\n        at\norg.eclipse.debug.internal.ui.viewers.model.ModelContentProvider.updateNodes(ModelContentProvider.java:634)\n        at\norg.eclipse.debug.internal.ui.viewers.model.ModelContentProvider.updateNodes(ModelContentProvider.java:634)\n        at\norg.eclipse.debug.internal.ui.viewers.model.ModelContentProvider$7.runInUIThread(ModelContentProvider.java:583)\n        at org.eclipse.ui.progress.UIJob$1.run(UIJob.java:94)",
    "Fixed in TreeModelContentProvider. It is possible for a delta to request an expand for a filtered element. The content provider did not account for this. In practice I cannot make this happen - but the test suite makes it happen in race conditions (we terminate the target as soon as it suspends - which leaves the filters/deltas in a tranisent state).",
    "Please verify, Mike.",
    "verified, the testsuite runs fine now."
  ],
  "commentCreationDates": [
    "2007-04-12T18:49:54+02:00",
    "2007-04-12T20:06:38+02:00",
    "2007-04-12T20:06:51+02:00",
    "2007-04-16T20:55:47+02:00"
  ],
  "traces": [
    {
      "exceptionType": "java.lang.IllegalArgumentException",
      "message": "Index out of bounds",
      "elements": [
        {
          "method": "org.eclipse.swt.SWT.error",
          "source": "SWT.java:3518"
        },
        {
          "method": "org.eclipse.swt.SWT.error",
          "source": "SWT.java:3457"
        },
        {
          "method": "org.eclipse.swt.SWT.error",
          "source": "SWT.java:3428"
        },
        {
          "method": "org.eclipse.swt.widgets.Widget.error",
          "source": "Widget.java:432"
        },
        {
          "method": "org.eclipse.swt.widgets.TreeItem.getItem",
          "source": "TreeItem.java:718"
        },
        {
          "method": "org.eclipse.debug.internal.ui.viewers.model.InternalTreeModelViewer$3.run",
          "source": "InternalTreeModelViewer.java:1084"
        },
        {
          "method": "org.eclipse.jface.viewers.StructuredViewer.preservingSelection",
          "source": "StructuredViewer.java:1333"
        },
        {
          "method": "org.eclipse.debug.internal.ui.viewers.model.InternalTreeModelViewer.replace",
          "source": "InternalTreeModelViewer.java:1073"
        },
        {
          "method": "org.eclipse.debug.internal.ui.viewers.model.TreeModelContentProvider.expand",
          "source": "TreeModelContentProvider.java:159"
        },
        {
          "method": "org.eclipse.debug.internal.ui.viewers.model.TreeModelContentProvider.handleExpand",
          "source": "TreeModelContentProvider.java:141"
        },
        {
          "method": "org.eclipse.debug.internal.ui.viewers.model.ModelContentProvider.updateNodes",
          "source": "ModelContentProvider.java:608"
        },
        {
          "method": "org.eclipse.debug.internal.ui.viewers.model.ModelContentProvider.updateNodes",
          "source": "ModelContentProvider.java:634"
        },
        {
          "method": "org.eclipse.debug.internal.ui.viewers.model.ModelContentProvider.updateNodes",
          "source": "ModelContentProvider.java:634"
        },
        {
          "method": "org.eclipse.debug.internal.ui.viewers.model.ModelContentProvider.updateNodes",
          "source": "ModelContentProvider.java:634"
        },
        {
          "method": "org.eclipse.debug.internal.ui.viewers.model.ModelContentProvider$7.runInUIThread",
          "source": "ModelContentProvider.java:583"
        },
        {
          "method": "org.eclipse.ui.progress.UIJob$1.run",
          "source": "UIJob.java:94"
        }
      ],
      "number": 0,
      "commentIndex": 0,
      "bugId": "182170",
      "date": "2007-04-12T18:49:54+02:00",
      "product": "Platform",
      "component": "Debug",
      "severity": "normal"
    }
  ],
  "groupId": "182170",
  "bugId": "182170",
  "date": "2007-04-12T18:49:54+02:00",
  "product": "Platform",
  "component": "Debug",
  "severity": "normal"
}