{
  "comments": [
    "1) I create some design, it works\n2) I modify data set, e.g. rename some column\n3) I display preview - everything is OK, no error displayed\n4) I deploy the report to the engine and sometimes it prints error, sometimes it does not process the report at all (probably it depends on severity of undefine column).\n\nWhen there is such error, the designer must warn the user during preview.\n\n14:45:16,382 ERROR [STDERR] 13.4.2007 14:45:16 org.eclipse.birt.report.engine.data.dte.DteResultSet close\nSEVERE: Some columns reference in column binding do not exist.\norg.eclipse.birt.data.engine.core.DataException: Some columns reference in column binding do not exist.\n        at org.eclipse.birt.data.engine.executor.ResultClass.doSave(ResultClass.java:196)\n        at org.eclipse.birt.data.engine.executor.transform.CachedResultSet.doSave(CachedResultSet.java:225)\n        at org.eclipse.birt.data.engine.impl.document.RDSaveUtil.saveForGeneration(RDSaveUtil.java:95)\n        at org.eclipse.birt.data.engine.impl.document.RDSaveUtil.saveResultIterator(RDSaveUtil.java:60)\n        at org.eclipse.birt.data.engine.impl.document.RDSave.saveResultIterator(RDSave.java:160)\n        at org.eclipse.birt.data.engine.impl.ResultIterator$RDSaveHelper.doSave(ResultIterator.java:788)\n        at org.eclipse.birt.data.engine.impl.ResultIterator$RDSaveHelper.doSaveFinish(ResultIterator.java:761)\n        at org.eclipse.birt.data.engine.impl.ResultIterator.close(ResultIterator.java:520)\n        at org.eclipse.birt.data.engine.impl.QueryResults.close(QueryResults.java:204)\n        at org.eclipse.birt.report.engine.data.dte.DteResultSet.close(DteResultSet.java:132)\n        at org.eclipse.birt.report.engine.executor.QueryItemExecutor.closeQuery(QueryItemExecutor.java:35)\n        at org.eclipse.birt.report.engine.executor.TableItemExecutor.close(TableItemExecutor.java:122)\n        at org.eclipse.birt.report.engine.layout.html.HTMLPageLM.layoutChildren(HTMLPageLM.java:154)\n        at org.eclipse.birt.report.engine.layout.html.HTMLPageLM.layout(HTMLPageLM.java:81)\n        at org.eclipse.birt.report.engine.layout.html.HTMLReportLayoutEngine.layout(HTMLReportLayoutEngine.java:85)\n        at org.eclipse.birt.report.engine.presentation.ReportDocumentBuilder.build(ReportDocumentBuilder.java:143)\n        at org.eclipse.birt.report.engine.api.impl.RunTask.doRun(RunTask.java:241)",
    "Hi Leos,\n\nHave you tried latest build? The error reporting has been improved since M6 so that in current BIRT build we should be able to report problems as you mentioned in the bug report.\n\nThanks.\nLin",
    "Hi Leos,\n    Any updates?\nThanks.\n",
    "well, it is not easy to download nightly builds. We have fast internet connection, but these BIRT builds take hours or even days to complete :-( Well, I will schedule it over night, lets see, if I suceed",
    "Hi Leos,\n\nAny update?\n\nThanks.\nLin",
    "Hi Leos,\n\nAs we have not got your feedback yet we assume that you\u0027ve fixed the problem yourself. This bug will be marked as WORKSFORME.\n\nThanks.\nLin"
  ],
  "commentCreationDates": [
    "2007-04-13T15:07:16+02:00",
    "2007-04-16T07:28:32+02:00",
    "2007-04-23T04:22:25+02:00",
    "2007-04-23T10:39:52+02:00",
    "2007-05-08T12:39:08+02:00",
    "2007-05-15T13:37:18+02:00"
  ],
  "traces": [
    {
      "exceptionType": "org.eclipse.birt.data.engine.core.DataException",
      "message": "Some columns reference in column binding do not exist.",
      "elements": [
        {
          "method": "org.eclipse.birt.data.engine.executor.ResultClass.doSave",
          "source": "ResultClass.java:196"
        },
        {
          "method": "org.eclipse.birt.data.engine.executor.transform.CachedResultSet.doSave",
          "source": "CachedResultSet.java:225"
        },
        {
          "method": "org.eclipse.birt.data.engine.impl.document.RDSaveUtil.saveForGeneration",
          "source": "RDSaveUtil.java:95"
        },
        {
          "method": "org.eclipse.birt.data.engine.impl.document.RDSaveUtil.saveResultIterator",
          "source": "RDSaveUtil.java:60"
        },
        {
          "method": "org.eclipse.birt.data.engine.impl.document.RDSave.saveResultIterator",
          "source": "RDSave.java:160"
        },
        {
          "method": "org.eclipse.birt.data.engine.impl.ResultIterator$RDSaveHelper.doSave",
          "source": "ResultIterator.java:788"
        },
        {
          "method": "org.eclipse.birt.data.engine.impl.ResultIterator$RDSaveHelper.doSaveFinish",
          "source": "ResultIterator.java:761"
        },
        {
          "method": "org.eclipse.birt.data.engine.impl.ResultIterator.close",
          "source": "ResultIterator.java:520"
        },
        {
          "method": "org.eclipse.birt.data.engine.impl.QueryResults.close",
          "source": "QueryResults.java:204"
        },
        {
          "method": "org.eclipse.birt.report.engine.data.dte.DteResultSet.close",
          "source": "DteResultSet.java:132"
        },
        {
          "method": "org.eclipse.birt.report.engine.executor.QueryItemExecutor.closeQuery",
          "source": "QueryItemExecutor.java:35"
        },
        {
          "method": "org.eclipse.birt.report.engine.executor.TableItemExecutor.close",
          "source": "TableItemExecutor.java:122"
        },
        {
          "method": "org.eclipse.birt.report.engine.layout.html.HTMLPageLM.layoutChildren",
          "source": "HTMLPageLM.java:154"
        },
        {
          "method": "org.eclipse.birt.report.engine.layout.html.HTMLPageLM.layout",
          "source": "HTMLPageLM.java:81"
        },
        {
          "method": "org.eclipse.birt.report.engine.layout.html.HTMLReportLayoutEngine.layout",
          "source": "HTMLReportLayoutEngine.java:85"
        },
        {
          "method": "org.eclipse.birt.report.engine.presentation.ReportDocumentBuilder.build",
          "source": "ReportDocumentBuilder.java:143"
        },
        {
          "method": "org.eclipse.birt.report.engine.api.impl.RunTask.doRun",
          "source": "RunTask.java:241"
        }
      ],
      "number": 0,
      "commentIndex": 0,
      "bugId": "182317",
      "date": "2007-04-13T15:07:16+02:00",
      "product": "BIRT",
      "component": "Data",
      "severity": "major"
    }
  ],
  "groupId": "182317",
  "bugId": "182317",
  "date": "2007-04-13T15:07:16+02:00",
  "product": "BIRT",
  "component": "Data",
  "severity": "major"
}