{
  "comments": [
    "Using HEAD, I was able to get an illegal argument exception updating a label in the debug view. I had launched and quickly terminated a target. It looks like it\u0027s possible to set a label to \"null\" in this case.\n\nCaused by: java.lang.IllegalArgumentException: Argument cannot be null\n    at org.eclipse.swt.SWT.error(SWT.java:3518)\n    at org.eclipse.swt.SWT.error(SWT.java:3457)\n    at org.eclipse.swt.SWT.error(SWT.java:3428)\n    at org.eclipse.swt.widgets.Widget.error(Widget.java:432)\n    at org.eclipse.swt.widgets.TreeItem.setText(TreeItem.java:1752)\n    at org.eclipse.debug.internal.ui.viewers.model.LabelUpdate.update(LabelUpdate.java:164)\n    at org.eclipse.debug.internal.ui.viewers.model.TreeModelLabelProvider$1.runInUIThread(TreeModelLabelProvider.java:255)\n    at org.eclipse.ui.progress.UIJob$1.run(UIJob.java:94)\n    at org.eclipse.swt.widgets.RunnableLock.run(RunnableLock.java:35)\n    at org.eclipse.swt.widgets.Synchronizer.runAsyncMessages(Synchronizer.java:123)",
    "Fixed in HEAD\n\nIf the label text is null, it is changed to an empty string.\n\nSee LabelUpdate.",
    "Mike, please verify.",
    "To reproduce, have a breakpoint set at which a lot of variables are displayed in the variables view.  Launch the program and use the keyboard shortcut to terminate it.  If you get the timing correctly, the program will terminate part way through displaying the variables, producing the error.",
    "verified"
  ],
  "commentCreationDates": [
    "2007-04-16T16:16:27+02:00",
    "2007-04-16T18:09:30+02:00",
    "2007-04-16T18:10:17+02:00",
    "2007-04-16T18:13:45+02:00",
    "2007-04-16T20:58:32+02:00"
  ],
  "traces": [
    {
      "exceptionType": "java.lang.IllegalArgumentException",
      "message": "Argument cannot be null",
      "elements": [
        {
          "method": "org.eclipse.swt.SWT.error",
          "source": "SWT.java:3518"
        },
        {
          "method": "org.eclipse.swt.SWT.error",
          "source": "SWT.java:3457"
        },
        {
          "method": "org.eclipse.swt.SWT.error",
          "source": "SWT.java:3428"
        },
        {
          "method": "org.eclipse.swt.widgets.Widget.error",
          "source": "Widget.java:432"
        },
        {
          "method": "org.eclipse.swt.widgets.TreeItem.setText",
          "source": "TreeItem.java:1752"
        },
        {
          "method": "org.eclipse.debug.internal.ui.viewers.model.LabelUpdate.update",
          "source": "LabelUpdate.java:164"
        },
        {
          "method": "org.eclipse.debug.internal.ui.viewers.model.TreeModelLabelProvider$1.runInUIThread",
          "source": "TreeModelLabelProvider.java:255"
        },
        {
          "method": "org.eclipse.ui.progress.UIJob$1.run",
          "source": "UIJob.java:94"
        },
        {
          "method": "org.eclipse.swt.widgets.RunnableLock.run",
          "source": "RunnableLock.java:35"
        },
        {
          "method": "org.eclipse.swt.widgets.Synchronizer.runAsyncMessages",
          "source": "Synchronizer.java:123"
        }
      ],
      "number": 0,
      "commentIndex": 0,
      "bugId": "182554",
      "date": "2007-04-16T16:16:27+02:00",
      "product": "Platform",
      "component": "Debug",
      "severity": "normal"
    }
  ],
  "groupId": "182554",
  "bugId": "182554",
  "date": "2007-04-16T16:16:27+02:00",
  "product": "Platform",
  "component": "Debug",
  "severity": "normal"
}