{
  "comments": [
    "Build 20020528\n\nWhile building a full source workspace with a lot of optional warnings enabled, \nI got the following entry logged. No apparent inconsistency in the task list \npassed that point (but did not check carefully the thousands problems).\n\n!ENTRY org.eclipse.core.resources 4 2 May 30, 2002 13:50:44.698\n!MESSAGE Problems occurred when invoking code from plug-in: \norg.eclipse.core.resources.\n!STACK 0\norg.eclipse.swt.SWTException: Invalid thread access\n        at org.eclipse.swt.SWT.error(SWT.java:1887)\n        at org.eclipse.swt.SWT.error(SWT.java:1819)\n        at org.eclipse.swt.widgets.Widget.error(Widget.java:368)\n        at org.eclipse.swt.widgets.Widget.checkWidget(Widget.java:299)\n        at org.eclipse.swt.widgets.Table.deselectAll(Table.java:441)\n        at org.eclipse.jface.viewers.TableViewer.setSelectionToWidget\n(TableViewer.java:607)\n        at org.eclipse.jface.viewers.StructuredViewer.setSelectionToWidget\n(StructuredViewer.java:937)\n        at org.eclipse.jface.viewers.StructuredViewer.setSelection\n(StructuredViewer.java:902)\n        at org.eclipse.jface.viewers.Viewer.setSelection(Viewer.java:342)\n        at org.eclipse.ui.views.tasklist.TaskList.setMarkerLimitExceeded\n(TaskList.java:313)\n        at org.eclipse.ui.views.tasklist.TaskListContentProvider.resourceChanged\n(TaskListContentProvider.java:\n        at org.eclipse.core.internal.events.NotificationManager$1.run\n(NotificationManager.java:128)\n        at org.eclipse.core.internal.runtime.InternalPlatform.run\n(InternalPlatform.java:802)\n        at org.eclipse.core.runtime.Platform.run(Platform.java:416)\n        at org.eclipse.core.internal.events.NotificationManager.notify\n(NotificationManager.java:143)\n        at org.eclipse.core.internal.events.NotificationManager.broadcastChanges\n(NotificationManager.java:67)\n        at org.eclipse.core.internal.resources.Workspace.broadcastChanges\n(Workspace.java:133)\n        at org.eclipse.core.internal.resources.Workspace.endOperation\n(Workspace.java:741)\n        at org.eclipse.core.internal.resources.Workspace.build\n(Workspace.java:145)\n        at org.eclipse.ui.actions.GlobalBuildAction$1.run\n(GlobalBuildAction.java:156)\n        at org.eclipse.jface.operation.ModalContext$ModalContextThread.run\n(ModalContext.java:98)",
    "\n\n*** This bug has been marked as a duplicate of 17247 ***"
  ],
  "commentCreationDates": [
    "2002-05-30T14:39:29+02:00",
    "2002-05-30T21:01:41+02:00"
  ],
  "traces": [
    {
      "exceptionType": "org.eclipse.swt.SWTException",
      "message": "Invalid thread access",
      "elements": [
        {
          "method": "org.eclipse.swt.SWT.error",
          "source": "SWT.java:1887"
        },
        {
          "method": "org.eclipse.swt.SWT.error",
          "source": "SWT.java:1819"
        },
        {
          "method": "org.eclipse.swt.widgets.Widget.error",
          "source": "Widget.java:368"
        },
        {
          "method": "org.eclipse.swt.widgets.Widget.checkWidget",
          "source": "Widget.java:299"
        },
        {
          "method": "org.eclipse.swt.widgets.Table.deselectAll",
          "source": "Table.java:441"
        },
        {
          "method": "org.eclipse.jface.viewers.TableViewer.setSelectionToWidget",
          "source": "TableViewer.java:607"
        },
        {
          "method": "org.eclipse.jface.viewers.StructuredViewer.setSelectionToWidget",
          "source": "StructuredViewer.java:937"
        },
        {
          "method": "org.eclipse.jface.viewers.StructuredViewer.setSelection",
          "source": "StructuredViewer.java:902"
        },
        {
          "method": "org.eclipse.jface.viewers.Viewer.setSelection",
          "source": "Viewer.java:342"
        },
        {
          "method": "org.eclipse.ui.views.tasklist.TaskList.setMarkerLimitExceeded",
          "source": "TaskList.java:313"
        }
      ],
      "number": 0,
      "commentIndex": 0,
      "bugId": "18293",
      "duplicateId": "17247",
      "date": "2002-05-30T14:39:29+02:00",
      "product": "Platform",
      "component": "UI",
      "severity": "normal"
    }
  ],
  "groupId": "17247",
  "bugId": "18293",
  "duplicateId": "17247",
  "date": "2002-05-30T14:39:29+02:00",
  "product": "Platform",
  "component": "UI",
  "severity": "normal"
}