{
  "comments": [
    "Build ID: I20070417-0800\n\nSteps To Reproduce:\n1. debug mode, \n2. stop at a breakpoint\n\n\nMore information:\n!ENTRY org.eclipse.ui 4 0 2007-04-18 23:19:18.359\n!MESSAGE Unhandled event loop exception\n!STACK 0\norg.eclipse.swt.SWTException: Failed to execute runnable (java.lang.ArrayIndexOu\ntOfBoundsException)\n        at org.eclipse.swt.SWT.error(SWT.java:3534)\n        at org.eclipse.swt.SWT.error(SWT.java:3457)\n        at org.eclipse.swt.widgets.Synchronizer.runAsyncMessages(Synchronizer.ja\nva:126)\n        at org.eclipse.swt.widgets.Display.runAsyncMessages(Display.java:3650)\n        at org.eclipse.swt.widgets.Display.readAndDispatch(Display.java:3287)\n        at org.eclipse.ui.internal.Workbench.runEventLoop(Workbench.java:2365)\n        at org.eclipse.ui.internal.Workbench.runUI(Workbench.java:2329)\n        at org.eclipse.ui.internal.Workbench.access$4(Workbench.java:2204)\n        at org.eclipse.ui.internal.Workbench$4.run(Workbench.java:466)\n        at org.eclipse.core.databinding.observable.Realm.runWithDefault(Realm.ja\nva:289)\n        at org.eclipse.ui.internal.Workbench.createAndRunWorkbench(Workbench.jav\na:461)\n        at org.eclipse.ui.PlatformUI.createAndRunWorkbench(PlatformUI.java:149)\n        at org.eclipse.ui.internal.ide.application.IDEApplication.start(IDEAppli\ncation.java:101)\n        at org.eclipse.equinox.internal.app.EclipseAppHandle.run(EclipseAppHandl\ne.java:153)\n        at org.eclipse.core.runtime.internal.adaptor.EclipseAppLauncher.runAppli\ncation(EclipseAppLauncher.java:106)\n        at org.eclipse.core.runtime.internal.adaptor.EclipseAppLauncher.start(Ec\nlipseAppLauncher.java:76)\n        at org.eclipse.core.runtime.adaptor.EclipseStarter.run(EclipseStarter.ja\nva:359)\n        at org.eclipse.core.runtime.adaptor.EclipseStarter.run(EclipseStarter.ja\nva:174)\n        at sun.reflect.NativeMethodAccessorImpl.invoke0(Native Method)\n        at sun.reflect.NativeMethodAccessorImpl.invoke(NativeMethodAccessorImpl.\njava:39)\n        at sun.reflect.DelegatingMethodAccessorImpl.invoke(DelegatingMethodAcces\nsorImpl.java:25)\n        at java.lang.reflect.Method.invoke(Method.java:585)\n        at org.eclipse.equinox.launcher.Main.invokeFramework(Main.java:475)\n        at org.eclipse.equinox.launcher.Main.basicRun(Main.java:415)\nCaused by: java.lang.ArrayIndexOutOfBoundsException\n        at org.eclipse.debug.internal.ui.viewers.model.FilterTransform$Node.remo\nveElementFromFilters(FilterTransform.java:304)\n        at org.eclipse.debug.internal.ui.viewers.model.FilterTransform.removeEle\nmentFromFilters(FilterTransform.java:495)\n        at org.eclipse.debug.internal.ui.viewers.model.ModelContentProvider.remo\nveElementFromFilters(ModelContentProvider.java:794)\n        at org.eclipse.debug.internal.ui.viewers.model.TreeModelContentProvider.\nhandleRemove(TreeModelContentProvider.java:197)\n        at org.eclipse.debug.internal.ui.viewers.model.ModelContentProvider.upda\nteNodes(ModelContentProvider.java:602)\n        at org.eclipse.debug.internal.ui.viewers.model.ModelContentProvider.upda\nteNodes(ModelContentProvider.java:634)\n        at org.eclipse.debug.internal.ui.viewers.model.ModelContentProvider.upda\nteNodes(ModelContentProvider.java:634)\n        at org.eclipse.debug.internal.ui.viewers.model.ModelContentProvider.upda\nteNodes(ModelContentProvider.java:634)\n        at org.eclipse.debug.internal.ui.viewers.model.ModelContentProvider$7.ru\nnInUIThread(ModelContentProvider.java:583)\n        at org.eclipse.ui.progress.UIJob$1.run(UIJob.java:94)\n        at org.eclipse.swt.widgets.RunnableLock.run(RunnableLock.java:35)\n        at org.eclipse.swt.widgets.Synchronizer.runAsyncMessages(Synchronizer.ja\nva:123)\n        at org.eclipse.swt.widgets.Display.runAsyncMessages(Display.java:3650)\n        at org.eclipse.swt.widgets.Display.readAndDispatch(Display.java:3287)\n        at org.eclipse.ui.internal.Workbench.runEventLoop(Workbench.java:2365)\n        at org.eclipse.ui.internal.Workbench.runUI(Workbench.java:2329)\n        at org.eclipse.ui.internal.Workbench.access$4(Workbench.java:2204)\n        at org.eclipse.ui.internal.Workbench$4.run(Workbench.java:466)\n        at org.eclipse.core.databinding.observable.Realm.runWithDefault(Realm.ja\nva:289)\n        at org.eclipse.ui.internal.Workbench.createAndRunWorkbench(Workbench.jav\na:461)\n        at org.eclipse.ui.PlatformUI.createAndRunWorkbench(PlatformUI.java:149)\n        at org.eclipse.ui.internal.ide.application.IDEApplication.start(IDEAppli\ncation.java:101)\n        at org.eclipse.equinox.internal.app.EclipseAppHandle.run(EclipseAppHandl\ne.java:153)\n        at org.eclipse.core.runtime.internal.adaptor.EclipseAppLauncher.runAppli\ncation(EclipseAppLauncher.java:106)\n        at org.eclipse.core.runtime.internal.adaptor.EclipseAppLauncher.start(Ec\nlipseAppLauncher.java:76)\n        at org.eclipse.core.runtime.adaptor.EclipseStarter.run(EclipseStarter.ja\nva:359)\n        at org.eclipse.core.runtime.adaptor.EclipseStarter.run(EclipseStarter.ja\nva:174)\n        at sun.reflect.NativeMethodAccessorImpl.invoke0(Native Method)",
    "Fixed in FilterTransform. Added FilterTransformTests to the test suite.",
    "Please verify, Mike.",
    "verified"
  ],
  "commentCreationDates": [
    "2007-04-18T22:42:26+02:00",
    "2007-04-19T18:14:18+02:00",
    "2007-04-19T18:14:34+02:00",
    "2007-04-26T16:54:12+02:00"
  ],
  "traces": [
    {
      "exceptionType": "org.eclipse.swt.SWTException",
      "message": "Failed to execute runnable (java.lang.ArrayIndexOu tOfBoundsException)",
      "elements": [
        {
          "method": "org.eclipse.swt.SWT.error",
          "source": "SWT.java:3534"
        },
        {
          "method": "org.eclipse.swt.SWT.error",
          "source": "SWT.java:3457"
        },
        {
          "method": "org.eclipse.swt.widgets.Synchronizer.runAsyncMessages",
          "source": "Synchronizer.ja va:126"
        },
        {
          "method": "org.eclipse.swt.widgets.Display.runAsyncMessages",
          "source": "Display.java:3650"
        },
        {
          "method": "org.eclipse.swt.widgets.Display.readAndDispatch",
          "source": "Display.java:3287"
        },
        {
          "method": "org.eclipse.ui.internal.Workbench.runEventLoop",
          "source": "Workbench.java:2365"
        },
        {
          "method": "org.eclipse.ui.internal.Workbench.runUI",
          "source": "Workbench.java:2329"
        },
        {
          "method": "org.eclipse.ui.internal.Workbench.access$4",
          "source": "Workbench.java:2204"
        },
        {
          "method": "org.eclipse.ui.internal.Workbench$4.run",
          "source": "Workbench.java:466"
        },
        {
          "method": "org.eclipse.core.databinding.observable.Realm.runWithDefault",
          "source": "Realm.ja va:289"
        },
        {
          "method": "org.eclipse.ui.internal.Workbench.createAndRunWorkbench",
          "source": "Workbench.jav a:461"
        },
        {
          "method": "org.eclipse.ui.PlatformUI.createAndRunWorkbench",
          "source": "PlatformUI.java:149"
        },
        {
          "method": "org.eclipse.ui.internal.ide.application.IDEApplication.start",
          "source": "IDEAppli cation.java:101"
        },
        {
          "method": "org.eclipse.equinox.internal.app.EclipseAppHandle.run",
          "source": "EclipseAppHandl e.java:153"
        },
        {
          "method": "org.eclipse.core.runtime.internal.adaptor.EclipseAppLauncher.runApplication",
          "source": "EclipseAppLauncher.java:106"
        },
        {
          "method": "org.eclipse.core.runtime.internal.adaptor.EclipseAppLauncher.start",
          "source": "Ec lipseAppLauncher.java:76"
        },
        {
          "method": "org.eclipse.core.runtime.adaptor.EclipseStarter.run",
          "source": "EclipseStarter.ja va:359"
        },
        {
          "method": "org.eclipse.core.runtime.adaptor.EclipseStarter.run",
          "source": "EclipseStarter.ja va:174"
        },
        {
          "method": "sun.reflect.NativeMethodAccessorImpl.invoke0",
          "source": "Native Method"
        },
        {
          "method": "sun.reflect.NativeMethodAccessorImpl.invoke",
          "source": "NativeMethodAccessorImpl. java:39"
        },
        {
          "method": "sun.reflect.DelegatingMethodAccessorImpl.invoke",
          "source": "DelegatingMethodAcces sorImpl.java:25"
        },
        {
          "method": "java.lang.reflect.Method.invoke",
          "source": "Method.java:585"
        },
        {
          "method": "org.eclipse.equinox.launcher.Main.invokeFramework",
          "source": "Main.java:475"
        },
        {
          "method": "org.eclipse.equinox.launcher.Main.basicRun",
          "source": "Main.java:415"
        }
      ],
      "causedBy": {
        "exceptionType": "java.lang.ArrayIndexOutOfBoundsException",
        "elements": [
          {
            "method": "org.eclipse.debug.internal.ui.viewers.model.FilterTransform$Node.removeElementFromFilters",
            "source": "FilterTransform.java:304"
          },
          {
            "method": "org.eclipse.debug.internal.ui.viewers.model.FilterTransform.removeElementFromFilters",
            "source": "FilterTransform.java:495"
          },
          {
            "method": "org.eclipse.debug.internal.ui.viewers.model.ModelContentProvider.removeElementFromFilters",
            "source": "ModelContentProvider.java:794"
          },
          {
            "method": "org.eclipse.debug.internal.ui.viewers.model.TreeModelContentProvider.handleRemove",
            "source": "TreeModelContentProvider.java:197"
          },
          {
            "method": "org.eclipse.debug.internal.ui.viewers.model.ModelContentProvider.updateNodes",
            "source": "ModelContentProvider.java:602"
          },
          {
            "method": "org.eclipse.debug.internal.ui.viewers.model.ModelContentProvider.updateNodes",
            "source": "ModelContentProvider.java:634"
          },
          {
            "method": "org.eclipse.debug.internal.ui.viewers.model.ModelContentProvider.updateNodes",
            "source": "ModelContentProvider.java:634"
          },
          {
            "method": "org.eclipse.debug.internal.ui.viewers.model.ModelContentProvider.updateNodes",
            "source": "ModelContentProvider.java:634"
          },
          {
            "method": "org.eclipse.debug.internal.ui.viewers.model.ModelContentProvider$7.runInUIThread",
            "source": "ModelContentProvider.java:583"
          },
          {
            "method": "org.eclipse.ui.progress.UIJob$1.run",
            "source": "UIJob.java:94"
          },
          {
            "method": "org.eclipse.swt.widgets.RunnableLock.run",
            "source": "RunnableLock.java:35"
          },
          {
            "method": "org.eclipse.swt.widgets.Synchronizer.runAsyncMessages",
            "source": "Synchronizer.ja va:123"
          },
          {
            "method": "org.eclipse.swt.widgets.Display.runAsyncMessages",
            "source": "Display.java:3650"
          },
          {
            "method": "org.eclipse.swt.widgets.Display.readAndDispatch",
            "source": "Display.java:3287"
          },
          {
            "method": "org.eclipse.ui.internal.Workbench.runEventLoop",
            "source": "Workbench.java:2365"
          },
          {
            "method": "org.eclipse.ui.internal.Workbench.runUI",
            "source": "Workbench.java:2329"
          },
          {
            "method": "org.eclipse.ui.internal.Workbench.access$4",
            "source": "Workbench.java:2204"
          },
          {
            "method": "org.eclipse.ui.internal.Workbench$4.run",
            "source": "Workbench.java:466"
          },
          {
            "method": "org.eclipse.core.databinding.observable.Realm.runWithDefault",
            "source": "Realm.ja va:289"
          },
          {
            "method": "org.eclipse.ui.internal.Workbench.createAndRunWorkbench",
            "source": "Workbench.jav a:461"
          },
          {
            "method": "org.eclipse.ui.PlatformUI.createAndRunWorkbench",
            "source": "PlatformUI.java:149"
          },
          {
            "method": "org.eclipse.ui.internal.ide.application.IDEApplication.start",
            "source": "IDEAppli cation.java:101"
          },
          {
            "method": "org.eclipse.equinox.internal.app.EclipseAppHandle.run",
            "source": "EclipseAppHandl e.java:153"
          },
          {
            "method": "org.eclipse.core.runtime.internal.adaptor.EclipseAppLauncher.runApplication",
            "source": "EclipseAppLauncher.java:106"
          },
          {
            "method": "org.eclipse.core.runtime.internal.adaptor.EclipseAppLauncher.start",
            "source": "Ec lipseAppLauncher.java:76"
          },
          {
            "method": "org.eclipse.core.runtime.adaptor.EclipseStarter.run",
            "source": "EclipseStarter.ja va:359"
          },
          {
            "method": "org.eclipse.core.runtime.adaptor.EclipseStarter.run",
            "source": "EclipseStarter.ja va:174"
          },
          {
            "method": "sun.reflect.NativeMethodAccessorImpl.invoke0",
            "source": "Native Method"
          }
        ],
        "number": 0,
        "commentIndex": 0
      },
      "number": 0,
      "commentIndex": 0,
      "bugId": "183059",
      "date": "2007-04-18T22:42:26+02:00",
      "product": "Platform",
      "component": "Debug",
      "severity": "normal"
    }
  ],
  "groupId": "183059",
  "bugId": "183059",
  "date": "2007-04-18T22:42:26+02:00",
  "product": "Platform",
  "component": "Debug",
  "severity": "normal"
}