{
  "comments": [
    "20020529 and 30 build\nlibswt-cde-motif-2041.sl and libswt-motif-2041.sl do not have execute \npermission set, I needed to change it manually after installing eclipse.\n\n\njava.lang.UnsatisfiedLinkError: /bluebird/teamswt/kkolosow/eclipse0530ihp/plugin\ns/org.eclipse.swt.motif_2.0.0/os/hpux/hp9000/libswt-motif-2041.sl: Permission \ndenied\n        at java.lang.ClassLoader$NativeLibrary.load(Native Method)\n        at java.lang.ClassLoader.loadLibrary0(Unknown Source)\n        at java.lang.ClassLoader.loadLibrary(Unknown Source)\n        at java.lang.Runtime.loadLibrary0(Unknown Source)\n        at java.lang.System.loadLibrary(Unknown Source)\n        at org.eclipse.swt.internal.Library.loadLibrary(Library.java:102)\n        at org.eclipse.swt.internal.motif.OS.\u003cclinit\u003e(OS.java:14)\n        at org.eclipse.swt.widgets.Display.createDisplay(Display.java:506)\n        at org.eclipse.swt.widgets.Display.create(Display.java:492)\n        at org.eclipse.swt.graphics.Device.\u003cinit\u003e(Device.java:104)\n        at org.eclipse.swt.widgets.Display.\u003cinit\u003e(Display.java:318)\n        at org.eclipse.swt.widgets.Display.\u003cinit\u003e(Display.java:315)\n        at org.eclipse.ui.internal.Workbench.run(Workbench.java:1110)\n        at org.eclipse.core.internal.boot.InternalBootLoader.run\n(InternalBootLoader.java:739)\n        at org.eclipse.core.boot.BootLoader.run(BootLoader.java:462)\n        at java.lang.reflect.Method.invoke(Native Method)\n        at org.eclipse.core.launcher.Main.basicRun(Main.java:200)\n        at org.eclipse.core.launcher.Main.run(Main.java:643)\n        at org.eclipse.core.launcher.Main.main(Main.java:476)",
    "This is likely a side-effect of them being sent in a zip from rational. I talked \nto MV about it. He said that Eclipse doesn\u0027t deal with the file permissions \nbut leaves them the same as whatever is initially set to, so you will need \nto SSH to the server (or use the command line client) to fix this.",
    "The only time the execute bit of a local file can be set by the CVS client is \nwhen it is first added to CVS control and committed. After that the only way to \nset the bit is to log onto the server.",
    "Fixed on the cvs server, so should take effect for the F2 build."
  ],
  "commentCreationDates": [
    "2002-05-30T22:38:32+02:00",
    "2002-05-31T15:27:29+02:00",
    "2002-05-31T15:52:17+02:00",
    "2002-05-31T16:02:01+02:00"
  ],
  "traces": [
    {
      "exceptionType": "java.lang.UnsatisfiedLinkError",
      "message": "/bluebird/teamswt/kkolosow/eclipse0530ihp/plugin s/org.eclipse.swt.motif_2.0.0/os/hpux/hp9000/libswt-motif-2041.sl: Permission  denied",
      "elements": [
        {
          "method": "java.lang.ClassLoader$NativeLibrary.load",
          "source": "Native Method"
        },
        {
          "method": "java.lang.ClassLoader.loadLibrary0",
          "source": "Unknown Source"
        },
        {
          "method": "java.lang.ClassLoader.loadLibrary",
          "source": "Unknown Source"
        },
        {
          "method": "java.lang.Runtime.loadLibrary0",
          "source": "Unknown Source"
        },
        {
          "method": "java.lang.System.loadLibrary",
          "source": "Unknown Source"
        },
        {
          "method": "org.eclipse.swt.internal.Library.loadLibrary",
          "source": "Library.java:102"
        },
        {
          "method": "org.eclipse.swt.internal.motif.OS.\u003cclinit\u003e",
          "source": "OS.java:14"
        },
        {
          "method": "org.eclipse.swt.widgets.Display.createDisplay",
          "source": "Display.java:506"
        },
        {
          "method": "org.eclipse.swt.widgets.Display.create",
          "source": "Display.java:492"
        },
        {
          "method": "org.eclipse.swt.graphics.Device.\u003cinit\u003e",
          "source": "Device.java:104"
        },
        {
          "method": "org.eclipse.swt.widgets.Display.\u003cinit\u003e",
          "source": "Display.java:318"
        },
        {
          "method": "org.eclipse.swt.widgets.Display.\u003cinit\u003e",
          "source": "Display.java:315"
        },
        {
          "method": "org.eclipse.ui.internal.Workbench.run",
          "source": "Workbench.java:1110"
        },
        {
          "method": "org.eclipse.core.internal.boot.InternalBootLoader.run",
          "source": "InternalBootLoader.java:739"
        },
        {
          "method": "org.eclipse.core.boot.BootLoader.run",
          "source": "BootLoader.java:462"
        },
        {
          "method": "java.lang.reflect.Method.invoke",
          "source": "Native Method"
        },
        {
          "method": "org.eclipse.core.launcher.Main.basicRun",
          "source": "Main.java:200"
        },
        {
          "method": "org.eclipse.core.launcher.Main.run",
          "source": "Main.java:643"
        },
        {
          "method": "org.eclipse.core.launcher.Main.main",
          "source": "Main.java:476"
        }
      ],
      "number": 0,
      "commentIndex": 0,
      "bugId": "18376",
      "date": "2002-05-30T22:38:32+02:00",
      "product": "Platform",
      "component": "SWT",
      "severity": "normal"
    }
  ],
  "groupId": "18376",
  "bugId": "18376",
  "date": "2002-05-30T22:38:32+02:00",
  "product": "Platform",
  "component": "SWT",
  "severity": "normal"
}