{
  "comments": [
    "Received the following error messages during the configuration of report server using Derby db\n\n DEBUG SDI doInstall 9 CREATE TABLE T_BIRT_REPORT_DESCR  (             TITLE\n                VARCHAR(256) NOT NULL,           NAME                   VARCHAR(\n1024) NOT NULL,                  PATH                   VARCHAR(2048) NOT NULL,\n                 ROLES                  INTEGER NOT NULL,                DESCRIP\nTION    VARCHAR(4096) NOT NULL,                  CREATOR                VARCHAR(\n256) NOT NULL,                   CREATION_DATE  DECIMAL(13,0) NOT NULL,\n         EDITOR                 VARCHAR(256) NOT NULL,                   EDIT_DA\nTE              DECIMAL(13,0) NOT NULL)\n   DEBUG SDI doInstall 9 CREATE UNIQUE INDEX T_BIRT_REPORT_DESCR_IX ON T_BIRT_RE\nPORT_DESCR              (PATH ASC,               NAME ASC)\n   DEBUG SDI doInstall 11\n   DEBUG SDI doInstall 12 status true\n   DEBUG SDI doInstall 14\n   DEBUG SDI doInstall 15\n   Database installation successful.\n   Aperi Bulk Report Processor: Loader\n   repository directory \u003d C:\\Aperi\\reports\n   zip file             \u003d ../reporting/configuration/canned-reports.zip\n   jdbcDriver           \u003d org.apache.derby.jdbc.ClientDriver\n   jdbcUrl              \u003d jdbc:derby://tivoli14:1527/Aperi\n   jdbcUser             \u003d Aperi\n   Error cleaning out repository: Report repository directory C:\\Aperi\\reports c\nannot be scanned.\n----\nThe output above should indicate that the schema was created\nsuccessfully on your system. If there was an error,\nAperi will not function correctly. Consult the installation\ndocumentation for more information.\n\nShutting Derby down.\n\nConfiguring the report server...\n ../reporting/reporting.bat\nError occurred while performing the configuration updates.\njava.lang.RuntimeException: Directory ../plugins/org.eclipse.aperi.reporting/web\n cannot be scanned.\n        at org.eclipse.aperi.configure.SearchAndReplace.replace(SearchAndReplace\n.java:107)\n        at org.eclipse.aperi.configure.ConfigureAperi.reportServer(ConfigureAper\ni.java:756)\n        at org.eclipse.aperi.configure.ConfigureAperi.configure(ConfigureAperi.j\nava:300)\n        at org.eclipse.aperi.configure.ConfigureAperi.configureAperi(ConfigureAp\neri.java:145)\n        at org.eclipse.aperi.configure.ConfigureAperi.main(ConfigureAperi.java:1\n22)",
    "The defect was fixed at build Aperi-20070430-121518.zip "
  ],
  "commentCreationDates": [
    "2007-04-26T18:38:25+02:00",
    "2007-05-02T19:50:26+02:00"
  ],
  "traces": [
    {
      "exceptionType": "java.lang.RuntimeException",
      "message": "Directory ../plugins/org.eclipse.aperi.reporting/web  cannot be scanned.",
      "elements": [
        {
          "method": "org.eclipse.aperi.configure.SearchAndReplace.replace",
          "source": "SearchAndReplace .java:107"
        },
        {
          "method": "org.eclipse.aperi.configure.ConfigureAperi.reportServer",
          "source": "ConfigureAper i.java:756"
        },
        {
          "method": "org.eclipse.aperi.configure.ConfigureAperi.configure",
          "source": "ConfigureAperi.j ava:300"
        },
        {
          "method": "org.eclipse.aperi.configure.ConfigureAperi.configureAperi",
          "source": "ConfigureAp eri.java:145"
        },
        {
          "method": "org.eclipse.aperi.configure.ConfigureAperi.main",
          "source": "ConfigureAperi.java:1 22"
        }
      ],
      "number": 0,
      "commentIndex": 0,
      "bugId": "184271",
      "date": "2007-04-26T18:38:25+02:00",
      "product": "Aperi",
      "component": "aperi.gui",
      "severity": "major"
    }
  ],
  "groupId": "184271",
  "bugId": "184271",
  "date": "2007-04-26T18:38:25+02:00",
  "product": "Aperi",
  "component": "aperi.gui",
  "severity": "major"
}