{
  "comments": [
    "Steps to reproduce:\n1. Create short Ruby source file (say less than 10 lines of code)\n2. Select some code at end of file.\n3. Cut selected code\n4. Immediately paste code back\n\nThe following exception is thrown\norg.eclipse.jface.text.BadLocationException\n\tat org.eclipse.jface.text.AbstractDocument.getChar(AbstractDocument.java:732)\n\tat org.eclipse.core.internal.filebuffers.SynchronizableDocument.getChar(SynchronizableDocument.java:106)\n\tat org.eclipse.dltk.ui.text.util.AutoEditUtils.findEndOfWhiteSpace(AutoEditUtils.java:221)\n\tat org.eclipse.dltk.ruby.internal.ui.text.RubyAutoEditStrategy.handleSmartPaste(RubyAutoEditStrategy.java:253)\n\tat org.eclipse.dltk.ruby.internal.ui.text.RubyAutoEditStrategy.customizeDocumentCommand(RubyAutoEditStrategy.java:39)\n......\n\nA simple patch is (obviously the document is out of sync at this point, so\nthere is probably a better solution):\n\npublic static int findEndOfWhiteSpace(IDocument document, int offset, int end)\n\t\t\tthrows BadLocationException {\nwhile (offset \u003c end) {\n  //Start of patch\n  if (offset \u003e\u003d document.getLength()) {\n      return document.getLength();\n   }\n   //End of patch\n   char c \u003d document.getChar(offset);\n.....",
    "Fixed. No patch and check was required: requested offset really was wrong due to misprint in AutoEditStrategy."
  ],
  "commentCreationDates": [
    "2007-04-30T19:17:52+02:00",
    "2007-05-07T14:55:31+02:00"
  ],
  "traces": [
    {
      "exceptionType": "org.eclipse.jface.text.BadLocationException",
      "elements": [
        {
          "method": "org.eclipse.jface.text.AbstractDocument.getChar",
          "source": "AbstractDocument.java:732"
        },
        {
          "method": "org.eclipse.core.internal.filebuffers.SynchronizableDocument.getChar",
          "source": "SynchronizableDocument.java:106"
        },
        {
          "method": "org.eclipse.dltk.ui.text.util.AutoEditUtils.findEndOfWhiteSpace",
          "source": "AutoEditUtils.java:221"
        },
        {
          "method": "org.eclipse.dltk.ruby.internal.ui.text.RubyAutoEditStrategy.handleSmartPaste",
          "source": "RubyAutoEditStrategy.java:253"
        },
        {
          "method": "org.eclipse.dltk.ruby.internal.ui.text.RubyAutoEditStrategy.customizeDocumentCommand",
          "source": "RubyAutoEditStrategy.java:39"
        }
      ],
      "number": 0,
      "commentIndex": 0,
      "bugId": "184743",
      "date": "2007-04-30T19:17:52+02:00",
      "product": "DLTK",
      "component": "Ruby",
      "severity": "normal"
    }
  ],
  "groupId": "184743",
  "bugId": "184743",
  "date": "2007-04-30T19:17:52+02:00",
  "product": "DLTK",
  "component": "Ruby",
  "severity": "normal"
}