{
  "comments": [
    "cfgaperi.bat has the Derby JDBC drivers on the classpath, but not the DB2 drivers, so when you configure with DB2 it blows cookies as below.\nI tried adding the drivers to the class, but ran into other class loading problems:\n\nNext, the Aperi schema will be created.\nRunning \"C:\\Program Files\\IBM\\SQLLIB\\BIN\\db2cmd\" /c scripts/db2config.bat administrator tpc6test Aperi Create 2500 -1 65537 1\n000 10240 1024 40000 4096 10240 50 10000 150 8 16\n----\n----\nWaiting 15 seconds for the configuration to be updated\nDEBUG SDI calling analyzeParameters\njava.lang.ClassNotFoundException: com.ibm.db2.jcc.DB2Driver\n        at java.net.URLClassLoader$1.run(URLClassLoader.java:200)\n        at java.security.AccessController.doPrivileged(Native Method)\n        at java.net.URLClassLoader.findClass(URLClassLoader.java:188)\n        at java.lang.ClassLoader.loadClass(ClassLoader.java:306)\n        at sun.misc.Launcher$AppClassLoader.loadClass(Launcher.java:268)\n        at java.lang.ClassLoader.loadClass(ClassLoader.java:251)\n        at java.lang.ClassLoader.loadClassInternal(ClassLoader.java:319)\n        at java.lang.Class.forName0(Native Method)\n        at java.lang.Class.forName(Class.java:164)\n        at org.eclipse.aperi.infrastructure.database.Database.loadDriver(Database.java:125)\n        at org.eclipse.aperi.infrastructure.database.Database.getConnection(Database.java:268)\n        at org.eclipse.aperi.infrastructure.database.Database.getConnection(Database.java:245)\n        at org.eclipse.aperi.infrastructure.database.DBConnPoolDataSource$Pool.remove(DBConnPoolDataSource.java:311)\n        at org.eclipse.aperi.infrastructure.database.DBConnPoolDataSource.getPooledConnection(DBConnPoolDataSource.java:114)\n        at org.eclipse.aperi.install.SilentDatabaseInstall.initializeApi(SilentDatabaseInstall.java:1049)\n        at org.eclipse.aperi.install.SilentDatabaseInstall.main(SilentDatabaseInstall.java:971)\n        at org.eclipse.aperi.configure.ConfigureAperi.runSilentDatabaseInstall(ConfigureAperi.java:1471)\n        at org.eclipse.aperi.configure.ConfigureAperi.schema(ConfigureAperi.java:1414)\n        at org.eclipse.aperi.configure.ConfigureAperi.configure(ConfigureAperi.java:308)\n        at org.eclipse.aperi.configure.ConfigureAperi.configureAperi(ConfigureAperi.java:155)\n        at org.eclipse.aperi.configure.ConfigureAperi.main(ConfigureAperi.java:137)\njava.sql.SQLException: No suitable driver\n        at java.sql.DriverManager.getConnection(DriverManager.java:545)\n        at java.sql.DriverManager.getConnection(DriverManager.java:140)\n        at org.eclipse.aperi.infrastructure.database.Database.getConnection(Database.java:276)\n        at org.eclipse.aperi.infrastructure.database.Database.getConnection(Database.java:245)\n        at org.eclipse.aperi.infrastructure.database.DBConnPoolDataSource$Pool.remove(DBConnPoolDataSource.java:311)\n        at org.eclipse.aperi.infrastructure.database.DBConnPoolDataSource.getPooledConnection(DBConnPoolDataSource.java:114)\n        at org.eclipse.aperi.install.SilentDatabaseInstall.initializeApi(SilentDatabaseInstall.java:1049)\n        at org.eclipse.aperi.install.SilentDatabaseInstall.main(SilentDatabaseInstall.java:971)\n        at org.eclipse.aperi.configure.ConfigureAperi.runSilentDatabaseInstall(ConfigureAperi.java:1471)\n        at org.eclipse.aperi.configure.ConfigureAperi.schema(ConfigureAperi.java:1414)\n        at org.eclipse.aperi.configure.ConfigureAperi.configure(ConfigureAperi.java:308)\n        at org.eclipse.aperi.configure.ConfigureAperi.configureAperi(ConfigureAperi.java:155)\n        at org.eclipse.aperi.configure.ConfigureAperi.main(ConfigureAperi.java:137)\njava.lang.Exception: 5/1/07 9:17:57 PM INS2071E: \u003ctext unavailable\u003e\n                         SQLSTATE: 08001, Vendor error code: 0\n                         No suitable driver initializeApi failed in getPooledConnection\n        at org.eclipse.aperi.install.SilentDatabaseInstall.initializeApi(SilentDatabaseInstall.java:1056)\n        at org.eclipse.aperi.install.SilentDatabaseInstall.main(SilentDatabaseInstall.java:971)\n        at org.eclipse.aperi.configure.ConfigureAperi.runSilentDatabaseInstall(ConfigureAperi.java:1471)\n        at org.eclipse.aperi.configure.ConfigureAperi.schema(ConfigureAperi.java:1414)\n        at org.eclipse.aperi.configure.ConfigureAperi.configure(ConfigureAperi.java:308)\n        at org.eclipse.aperi.configure.ConfigureAperi.configureAperi(ConfigureAperi.java:155)\n        at org.eclipse.aperi.configure.ConfigureAperi.main(ConfigureAperi.java:137)\nDatabase installation successful.",
    "Updated cfgaperi scripts"
  ],
  "commentCreationDates": [
    "2007-05-02T06:29:43+02:00",
    "2007-05-05T00:24:15+02:00"
  ],
  "traces": [
    {
      "exceptionType": "java.lang.ClassNotFoundException",
      "message": "com.ibm.db2.jcc.DB2Driver",
      "elements": [
        {
          "method": "java.net.URLClassLoader$1.run",
          "source": "URLClassLoader.java:200"
        },
        {
          "method": "java.security.AccessController.doPrivileged",
          "source": "Native Method"
        },
        {
          "method": "java.net.URLClassLoader.findClass",
          "source": "URLClassLoader.java:188"
        },
        {
          "method": "java.lang.ClassLoader.loadClass",
          "source": "ClassLoader.java:306"
        },
        {
          "method": "sun.misc.Launcher$AppClassLoader.loadClass",
          "source": "Launcher.java:268"
        },
        {
          "method": "java.lang.ClassLoader.loadClass",
          "source": "ClassLoader.java:251"
        },
        {
          "method": "java.lang.ClassLoader.loadClassInternal",
          "source": "ClassLoader.java:319"
        },
        {
          "method": "java.lang.Class.forName0",
          "source": "Native Method"
        },
        {
          "method": "java.lang.Class.forName",
          "source": "Class.java:164"
        },
        {
          "method": "org.eclipse.aperi.infrastructure.database.Database.loadDriver",
          "source": "Database.java:125"
        },
        {
          "method": "org.eclipse.aperi.infrastructure.database.Database.getConnection",
          "source": "Database.java:268"
        },
        {
          "method": "org.eclipse.aperi.infrastructure.database.Database.getConnection",
          "source": "Database.java:245"
        },
        {
          "method": "org.eclipse.aperi.infrastructure.database.DBConnPoolDataSource$Pool.remove",
          "source": "DBConnPoolDataSource.java:311"
        },
        {
          "method": "org.eclipse.aperi.infrastructure.database.DBConnPoolDataSource.getPooledConnection",
          "source": "DBConnPoolDataSource.java:114"
        },
        {
          "method": "org.eclipse.aperi.install.SilentDatabaseInstall.initializeApi",
          "source": "SilentDatabaseInstall.java:1049"
        },
        {
          "method": "org.eclipse.aperi.install.SilentDatabaseInstall.main",
          "source": "SilentDatabaseInstall.java:971"
        },
        {
          "method": "org.eclipse.aperi.configure.ConfigureAperi.runSilentDatabaseInstall",
          "source": "ConfigureAperi.java:1471"
        },
        {
          "method": "org.eclipse.aperi.configure.ConfigureAperi.schema",
          "source": "ConfigureAperi.java:1414"
        },
        {
          "method": "org.eclipse.aperi.configure.ConfigureAperi.configure",
          "source": "ConfigureAperi.java:308"
        },
        {
          "method": "org.eclipse.aperi.configure.ConfigureAperi.configureAperi",
          "source": "ConfigureAperi.java:155"
        },
        {
          "method": "org.eclipse.aperi.configure.ConfigureAperi.main",
          "source": "ConfigureAperi.java:137"
        }
      ],
      "number": 0,
      "commentIndex": 0,
      "bugId": "185028",
      "date": "2007-05-02T06:29:43+02:00",
      "product": "Aperi",
      "component": "Aperi",
      "severity": "normal"
    },
    {
      "exceptionType": "java.sql.SQLException",
      "message": "No suitable driver",
      "elements": [
        {
          "method": "java.sql.DriverManager.getConnection",
          "source": "DriverManager.java:545"
        },
        {
          "method": "java.sql.DriverManager.getConnection",
          "source": "DriverManager.java:140"
        },
        {
          "method": "org.eclipse.aperi.infrastructure.database.Database.getConnection",
          "source": "Database.java:276"
        },
        {
          "method": "org.eclipse.aperi.infrastructure.database.Database.getConnection",
          "source": "Database.java:245"
        },
        {
          "method": "org.eclipse.aperi.infrastructure.database.DBConnPoolDataSource$Pool.remove",
          "source": "DBConnPoolDataSource.java:311"
        },
        {
          "method": "org.eclipse.aperi.infrastructure.database.DBConnPoolDataSource.getPooledConnection",
          "source": "DBConnPoolDataSource.java:114"
        },
        {
          "method": "org.eclipse.aperi.install.SilentDatabaseInstall.initializeApi",
          "source": "SilentDatabaseInstall.java:1049"
        },
        {
          "method": "org.eclipse.aperi.install.SilentDatabaseInstall.main",
          "source": "SilentDatabaseInstall.java:971"
        },
        {
          "method": "org.eclipse.aperi.configure.ConfigureAperi.runSilentDatabaseInstall",
          "source": "ConfigureAperi.java:1471"
        },
        {
          "method": "org.eclipse.aperi.configure.ConfigureAperi.schema",
          "source": "ConfigureAperi.java:1414"
        },
        {
          "method": "org.eclipse.aperi.configure.ConfigureAperi.configure",
          "source": "ConfigureAperi.java:308"
        },
        {
          "method": "org.eclipse.aperi.configure.ConfigureAperi.configureAperi",
          "source": "ConfigureAperi.java:155"
        },
        {
          "method": "org.eclipse.aperi.configure.ConfigureAperi.main",
          "source": "ConfigureAperi.java:137"
        }
      ],
      "number": 1,
      "commentIndex": 0,
      "bugId": "185028",
      "date": "2007-05-02T06:29:43+02:00",
      "product": "Aperi",
      "component": "Aperi",
      "severity": "normal"
    },
    {
      "exceptionType": "java.lang.Exception",
      "message": "5/1/07 9:17:57 PM INS2071E: \u003ctext unavailable\u003e                          SQLSTATE: 08001, Vendor error code: 0                          No suitable driver initializeApi failed in getPooledConnection",
      "elements": [
        {
          "method": "org.eclipse.aperi.install.SilentDatabaseInstall.initializeApi",
          "source": "SilentDatabaseInstall.java:1056"
        },
        {
          "method": "org.eclipse.aperi.install.SilentDatabaseInstall.main",
          "source": "SilentDatabaseInstall.java:971"
        },
        {
          "method": "org.eclipse.aperi.configure.ConfigureAperi.runSilentDatabaseInstall",
          "source": "ConfigureAperi.java:1471"
        },
        {
          "method": "org.eclipse.aperi.configure.ConfigureAperi.schema",
          "source": "ConfigureAperi.java:1414"
        },
        {
          "method": "org.eclipse.aperi.configure.ConfigureAperi.configure",
          "source": "ConfigureAperi.java:308"
        },
        {
          "method": "org.eclipse.aperi.configure.ConfigureAperi.configureAperi",
          "source": "ConfigureAperi.java:155"
        },
        {
          "method": "org.eclipse.aperi.configure.ConfigureAperi.main",
          "source": "ConfigureAperi.java:137"
        }
      ],
      "number": 2,
      "commentIndex": 0,
      "bugId": "185028",
      "date": "2007-05-02T06:29:43+02:00",
      "product": "Aperi",
      "component": "Aperi",
      "severity": "normal"
    }
  ],
  "groupId": "185028",
  "bugId": "185028",
  "date": "2007-05-02T06:29:43+02:00",
  "product": "Aperi",
  "component": "Aperi",
  "severity": "normal"
}