{
  "comments": [
    "Received the following error messages when deleting an empty directory from BIRT report viewer\n\nMay 2, 2007 10:26:50 AM org.mortbay.jetty.servlet.ServletHandler handle\nSEVERE: /aperi-reports/Delete:\njava.lang.RuntimeException: Directory test3 not empty.\n        at org.eclipse.aperi.reporting.ReportManager.deleteReport(ReportManager.\njava:202)\n        at org.eclipse.aperi.reporting.Delete.doGet(Delete.java:31)\n        at org.eclipse.aperi.reporting.Delete.doPost(Delete.java:36)\n        at javax.servlet.http.HttpServlet.service(HttpServlet.java:616)\n        at javax.servlet.http.HttpServlet.service(HttpServlet.java:689)\n        at org.mortbay.jetty.servlet.ServletHolder.handle(ServletHolder.java:428\n)\n        at org.mortbay.jetty.servlet.WebApplicationHandler.dispatch(WebApplicati\nonHandler.java:473)\n        at org.mortbay.jetty.servlet.ServletHandler.handle(ServletHandler.java:5\n68)\n        at org.mortbay.http.HttpContext.handle(HttpContext.java:1530)\n        at org.mortbay.jetty.servlet.WebApplicationContext.handle(WebApplication\nContext.java:633)\n        at org.mortbay.http.HttpContext.handle(HttpContext.java:1482)\n        at org.mortbay.http.HttpServer.service(HttpServer.java:909)\n        at org.mortbay.http.HttpConnection.service(HttpConnection.java:820)\n        at org.mortbay.http.HttpConnection.handleNext(HttpConnection.java:986)\n        at org.mortbay.http.HttpConnection.handle(HttpConnection.java:837)\n        at org.mortbay.http.SocketListener.handleConnection(SocketListener.java:\n245)\n        at org.mortbay.util.ThreadedServer.handle(ThreadedServer.java:357)\n        at org.mortbay.util.ThreadPool$PoolThread.run(ThreadPool.java:534)",
    "Hey Hans, can you do me a favor and take a look in C:\\Aperi\\reports\\test3 and see if anything is in there?\n",
    "Hi Dave,\n   C:\\Aperi\\reports\\test3 is not empty but BIRT report viewer should not give me the option to delete it when I right-click the test3 directory.",
    "User should not load any xx.rptdesign files into \u003cAperi-dir\u003e\\reports\\ folder manually, it should be done through \u0027upload\u0027 using BIRT viewer GUI "
  ],
  "commentCreationDates": [
    "2007-05-02T19:55:59+02:00",
    "2007-05-02T20:48:45+02:00",
    "2007-05-02T21:05:49+02:00",
    "2007-05-03T20:33:57+02:00"
  ],
  "traces": [
    {
      "exceptionType": "java.lang.RuntimeException",
      "message": "Directory test3 not empty.",
      "elements": [
        {
          "method": "org.eclipse.aperi.reporting.ReportManager.deleteReport",
          "source": "ReportManager. java:202"
        },
        {
          "method": "org.eclipse.aperi.reporting.Delete.doGet",
          "source": "Delete.java:31"
        },
        {
          "method": "org.eclipse.aperi.reporting.Delete.doPost",
          "source": "Delete.java:36"
        },
        {
          "method": "javax.servlet.http.HttpServlet.service",
          "source": "HttpServlet.java:616"
        },
        {
          "method": "javax.servlet.http.HttpServlet.service",
          "source": "HttpServlet.java:689"
        },
        {
          "method": "org.mortbay.jetty.servlet.ServletHolder.handle",
          "source": "ServletHolder.java:428 "
        },
        {
          "method": "org.mortbay.jetty.servlet.WebApplicationHandler.dispatch",
          "source": "WebApplicati onHandler.java:473"
        },
        {
          "method": "org.mortbay.jetty.servlet.ServletHandler.handle",
          "source": "ServletHandler.java:5 68"
        },
        {
          "method": "org.mortbay.http.HttpContext.handle",
          "source": "HttpContext.java:1530"
        },
        {
          "method": "org.mortbay.jetty.servlet.WebApplicationContext.handle",
          "source": "WebApplication Context.java:633"
        },
        {
          "method": "org.mortbay.http.HttpContext.handle",
          "source": "HttpContext.java:1482"
        },
        {
          "method": "org.mortbay.http.HttpServer.service",
          "source": "HttpServer.java:909"
        },
        {
          "method": "org.mortbay.http.HttpConnection.service",
          "source": "HttpConnection.java:820"
        },
        {
          "method": "org.mortbay.http.HttpConnection.handleNext",
          "source": "HttpConnection.java:986"
        },
        {
          "method": "org.mortbay.http.HttpConnection.handle",
          "source": "HttpConnection.java:837"
        },
        {
          "method": "org.mortbay.http.SocketListener.handleConnection",
          "source": "SocketListener.java: 245"
        },
        {
          "method": "org.mortbay.util.ThreadedServer.handle",
          "source": "ThreadedServer.java:357"
        },
        {
          "method": "org.mortbay.util.ThreadPool$PoolThread.run",
          "source": "ThreadPool.java:534"
        }
      ],
      "number": 0,
      "commentIndex": 0,
      "bugId": "185188",
      "date": "2007-05-02T19:55:59+02:00",
      "product": "Aperi",
      "component": "aperi.gui",
      "severity": "normal"
    }
  ],
  "groupId": "185188",
  "bugId": "185188",
  "date": "2007-05-02T19:55:59+02:00",
  "product": "Aperi",
  "component": "aperi.gui",
  "severity": "normal"
}