{
  "comments": [
    "1. Launch a program in debug mode.\n2. Hit a breakpoint\n3. Evaluated \"0x80000000\". No result are return and the log contains the\nfollowing trace :\n\n!ENTRY org.eclipse.core.resources 1 4 May 31, 2002 16:55:56.229\n!MESSAGE Unhandled exception caught in event loop.\n!ENTRY org.eclipse.ui 4 0 May 31, 2002 16:55:56.237\n!MESSAGE For input string: \"80000000\"\n!STACK 0\njava.lang.NumberFormatException: For input string: \"80000000\"\n        at\njava.lang.NumberFormatException.forInputString(NumberFormatException.java:48)\n        at java.lang.Integer.parseInt(Integer.java:438)\n        at java.lang.Integer.valueOf(Integer.java:505)\n        at java.lang.Integer.decode(Integer.java:866)\n        at\norg.eclipse.jdt.internal.debug.eval.ast.engine.ASTInstructionCompiler.visit(ASTInstructionCompiler.java:1821)\n        at org.eclipse.jdt.core.dom.NumberLiteral.accept0(NumberLiteral.java:71)\n        at org.eclipse.jdt.core.dom.ASTNode.accept(ASTNode.java:1330)\n        at org.eclipse.jdt.core.dom.ASTNode.acceptChild(ASTNode.java:1377)\n        at\norg.eclipse.jdt.core.dom.PrefixExpression.accept0(PrefixExpression.java:175)\n        at org.eclipse.jdt.core.dom.ASTNode.accept(ASTNode.java:1330)\n        at org.eclipse.jdt.core.dom.ASTNode.acceptChild(ASTNode.java:1377)\n        at org.eclipse.jdt.core.dom.ReturnStatement.accept0(ReturnStatement.java:73)\n        at org.eclipse.jdt.core.dom.ASTNode.accept(ASTNode.java:1330)\n        at org.eclipse.jdt.core.dom.ASTNode.acceptChildren(ASTNode.java:1400)\n        at org.eclipse.jdt.core.dom.Block.accept0(Block.java:80)\n        at org.eclipse.jdt.core.dom.ASTNode.accept(ASTNode.java:1330)\n        at org.eclipse.jdt.core.dom.ASTNode.acceptChild(ASTNode.java:1377)\n        at\norg.eclipse.jdt.core.dom.MethodDeclaration.accept0(MethodDeclaration.java:180)\n        at org.eclipse.jdt.core.dom.ASTNode.accept(ASTNode.java:1330)\n        at org.eclipse.jdt.core.dom.ASTNode.acceptChildren(ASTNode.java:1400)\n        at\norg.eclipse.jdt.core.dom.TypeDeclaration.accept0(TypeDeclaration.java:160)\n        at org.eclipse.jdt.core.dom.ASTNode.accept(ASTNode.java:1330)\n        at org.eclipse.jdt.core.dom.ASTNode.acceptChildren(ASTNode.java:1400)\n        at\norg.eclipse.jdt.core.dom.CompilationUnit.accept0(CompilationUnit.java:145)\n        at org.eclipse.jdt.core.dom.ASTNode.accept(ASTNode.java:1330)\n        at\norg.eclipse.jdt.internal.debug.eval.ast.engine.ASTEvaluationEngine.createExpressionFromAST(ASTEvaluationEngine.java:268)\n        at\norg.eclipse.jdt.internal.debug.eval.ast.engine.ASTEvaluationEngine.getCompiledExpression(ASTEvaluationEngine.java:187)\n        at\norg.eclipse.jdt.internal.debug.eval.ast.engine.ASTEvaluationEngine.evaluate(ASTEvaluationEngine.java:65)\n        at\norg.eclipse.jdt.internal.debug.ui.actions.EvaluateAction.run(EvaluateAction.java:240)\n        at\norg.eclipse.jdt.internal.debug.ui.actions.DisplayAction.run(DisplayAction.java:144)\n        at\norg.eclipse.jdt.internal.debug.ui.actions.EvaluateAction.run(EvaluateAction.java:508)\n\nThe problem is tools from the standart Java API doesn\u0027t managed such numbers, we\nneed to find a way to parse these numbers and get their values (may be copy a\npiece of code for the compiler).\n\nThe same probleme appears when we try to evaluate \"-2147483648\" (-2^31) and\n\"-9223372036854775808L\" (-2^63)\n\nA workaround is to used the equivalent signed number, i.e. :\n\n-0x7ffffffe instaed of 0x80000001\n-0x00000001 instaed of 0xffffffff\n...\n\nThis workaround doesn\u0027t work for the most negative literal of type int or long\n(i.e. : 0x80000000, -2147483648, -9223372036854775808L, ...)",
    "Marking as F3 candidate",
    "Fixed in ASTInstructionCompiler.\n\nAlso, added tests to the eval test suite.",
    "Please verify.",
    "Verified."
  ],
  "commentCreationDates": [
    "2002-06-01T00:28:55+02:00",
    "2002-06-04T18:08:15+02:00",
    "2002-06-07T17:39:40+02:00",
    "2002-06-07T17:39:58+02:00",
    "2002-06-09T21:50:44+02:00"
  ],
  "traces": [
    {
      "exceptionType": "java.lang.NumberFormatException",
      "message": "For input string: \"80000000\"",
      "elements": [
        {
          "method": "java.lang.NumberFormatException.forInputString",
          "source": "NumberFormatException.java:48"
        },
        {
          "method": "java.lang.Integer.parseInt",
          "source": "Integer.java:438"
        },
        {
          "method": "java.lang.Integer.valueOf",
          "source": "Integer.java:505"
        },
        {
          "method": "java.lang.Integer.decode",
          "source": "Integer.java:866"
        },
        {
          "method": "org.eclipse.jdt.internal.debug.eval.ast.engine.ASTInstructionCompiler.visit",
          "source": "ASTInstructionCompiler.java:1821"
        },
        {
          "method": "org.eclipse.jdt.core.dom.NumberLiteral.accept0",
          "source": "NumberLiteral.java:71"
        },
        {
          "method": "org.eclipse.jdt.core.dom.ASTNode.accept",
          "source": "ASTNode.java:1330"
        },
        {
          "method": "org.eclipse.jdt.core.dom.ASTNode.acceptChild",
          "source": "ASTNode.java:1377"
        },
        {
          "method": "org.eclipse.jdt.core.dom.PrefixExpression.accept0",
          "source": "PrefixExpression.java:175"
        },
        {
          "method": "org.eclipse.jdt.core.dom.ASTNode.accept",
          "source": "ASTNode.java:1330"
        },
        {
          "method": "org.eclipse.jdt.core.dom.ASTNode.acceptChild",
          "source": "ASTNode.java:1377"
        },
        {
          "method": "org.eclipse.jdt.core.dom.ReturnStatement.accept0",
          "source": "ReturnStatement.java:73"
        },
        {
          "method": "org.eclipse.jdt.core.dom.ASTNode.accept",
          "source": "ASTNode.java:1330"
        },
        {
          "method": "org.eclipse.jdt.core.dom.ASTNode.acceptChildren",
          "source": "ASTNode.java:1400"
        },
        {
          "method": "org.eclipse.jdt.core.dom.Block.accept0",
          "source": "Block.java:80"
        },
        {
          "method": "org.eclipse.jdt.core.dom.ASTNode.accept",
          "source": "ASTNode.java:1330"
        },
        {
          "method": "org.eclipse.jdt.core.dom.ASTNode.acceptChild",
          "source": "ASTNode.java:1377"
        },
        {
          "method": "org.eclipse.jdt.core.dom.MethodDeclaration.accept0",
          "source": "MethodDeclaration.java:180"
        },
        {
          "method": "org.eclipse.jdt.core.dom.ASTNode.accept",
          "source": "ASTNode.java:1330"
        },
        {
          "method": "org.eclipse.jdt.core.dom.ASTNode.acceptChildren",
          "source": "ASTNode.java:1400"
        },
        {
          "method": "org.eclipse.jdt.core.dom.TypeDeclaration.accept0",
          "source": "TypeDeclaration.java:160"
        },
        {
          "method": "org.eclipse.jdt.core.dom.ASTNode.accept",
          "source": "ASTNode.java:1330"
        },
        {
          "method": "org.eclipse.jdt.core.dom.ASTNode.acceptChildren",
          "source": "ASTNode.java:1400"
        },
        {
          "method": "org.eclipse.jdt.core.dom.CompilationUnit.accept0",
          "source": "CompilationUnit.java:145"
        },
        {
          "method": "org.eclipse.jdt.core.dom.ASTNode.accept",
          "source": "ASTNode.java:1330"
        },
        {
          "method": "org.eclipse.jdt.internal.debug.eval.ast.engine.ASTEvaluationEngine.createExpressionFromAST",
          "source": "ASTEvaluationEngine.java:268"
        },
        {
          "method": "org.eclipse.jdt.internal.debug.eval.ast.engine.ASTEvaluationEngine.getCompiledExpression",
          "source": "ASTEvaluationEngine.java:187"
        },
        {
          "method": "org.eclipse.jdt.internal.debug.eval.ast.engine.ASTEvaluationEngine.evaluate",
          "source": "ASTEvaluationEngine.java:65"
        },
        {
          "method": "org.eclipse.jdt.internal.debug.ui.actions.EvaluateAction.run",
          "source": "EvaluateAction.java:240"
        },
        {
          "method": "org.eclipse.jdt.internal.debug.ui.actions.DisplayAction.run",
          "source": "DisplayAction.java:144"
        },
        {
          "method": "org.eclipse.jdt.internal.debug.ui.actions.EvaluateAction.run",
          "source": "EvaluateAction.java:508"
        }
      ],
      "number": 0,
      "commentIndex": 0,
      "bugId": "18536",
      "date": "2002-06-01T00:28:55+02:00",
      "product": "JDT",
      "component": "Debug",
      "severity": "normal"
    }
  ],
  "groupId": "18536",
  "bugId": "18536",
  "date": "2002-06-01T00:28:55+02:00",
  "product": "JDT",
  "component": "Debug",
  "severity": "normal"
}