{
  "comments": [
    "Bild aperi-20070508-212505\nLinux with derby\n\nShutting Derby down.\njava.lang.InterruptedException\n        at org.apache.derby.impl.drda.DRDAConnThread.markCommunicationsFailure(Unknown Source)\n        at org.apache.derby.impl.drda.DDMReader.fill(Unknown Source)\n        at org.apache.derby.impl.drda.DDMReader.ensureALayerDataInBuffer(Unknown Source)\n        at org.apache.derby.impl.drda.DDMReader.readDssHeader(Unknown Source)\n        at org.apache.derby.impl.drda.DRDAConnThread.processCommands(Unknown Source)\n        at org.apache.derby.impl.drda.DRDAConnThread.run(Unknown Source)\nException in thread \"DRDAConnThread_3\" java.lang.NullPointerException\n        at java.lang.Throwable.printStackTrace(Throwable.java:509)\n        at org.apache.derby.impl.drda.DRDAProtocolException.\u003cinit\u003e(Unknown Source)\n        at org.apache.derby.impl.drda.DRDAProtocolException.newAgentError(Unknown Source)\n        at org.apache.derby.impl.drda.DRDAConnThread.sendUnexpectedException(Unknown Source)\n        at org.apache.derby.impl.drda.DRDAConnThread.handleException(Unknown Source)\n        at org.apache.derby.impl.drda.DRDAConnThread.run(Unknown Source)",
    "Didn\u0027t seem to have any impact on running the product.\nLowering severity to minor"
  ],
  "commentCreationDates": [
    "2007-05-09T16:05:11+02:00",
    "2007-05-09T19:22:04+02:00"
  ],
  "traces": [
    {
      "exceptionType": "java.lang.InterruptedException",
      "elements": [
        {
          "method": "org.apache.derby.impl.drda.DRDAConnThread.markCommunicationsFailure",
          "source": "Unknown Source"
        },
        {
          "method": "org.apache.derby.impl.drda.DDMReader.fill",
          "source": "Unknown Source"
        },
        {
          "method": "org.apache.derby.impl.drda.DDMReader.ensureALayerDataInBuffer",
          "source": "Unknown Source"
        },
        {
          "method": "org.apache.derby.impl.drda.DDMReader.readDssHeader",
          "source": "Unknown Source"
        },
        {
          "method": "org.apache.derby.impl.drda.DRDAConnThread.processCommands",
          "source": "Unknown Source"
        },
        {
          "method": "org.apache.derby.impl.drda.DRDAConnThread.run",
          "source": "Unknown Source"
        }
      ],
      "number": 0,
      "commentIndex": 0,
      "bugId": "186160",
      "date": "2007-05-09T16:05:11+02:00",
      "product": "Aperi",
      "component": "Aperi",
      "severity": "minor"
    },
    {
      "exceptionType": "java.lang.NullPointerException",
      "elements": [
        {
          "method": "java.lang.Throwable.printStackTrace",
          "source": "Throwable.java:509"
        },
        {
          "method": "org.apache.derby.impl.drda.DRDAProtocolException.\u003cinit\u003e",
          "source": "Unknown Source"
        },
        {
          "method": "org.apache.derby.impl.drda.DRDAProtocolException.newAgentError",
          "source": "Unknown Source"
        },
        {
          "method": "org.apache.derby.impl.drda.DRDAConnThread.sendUnexpectedException",
          "source": "Unknown Source"
        },
        {
          "method": "org.apache.derby.impl.drda.DRDAConnThread.handleException",
          "source": "Unknown Source"
        },
        {
          "method": "org.apache.derby.impl.drda.DRDAConnThread.run",
          "source": "Unknown Source"
        }
      ],
      "number": 1,
      "commentIndex": 0,
      "bugId": "186160",
      "date": "2007-05-09T16:05:11+02:00",
      "product": "Aperi",
      "component": "Aperi",
      "severity": "minor"
    }
  ],
  "groupId": "186160",
  "bugId": "186160",
  "date": "2007-05-09T16:05:11+02:00",
  "product": "Aperi",
  "component": "Aperi",
  "severity": "minor"
}