{
  "comments": [
    "Build ID: I20070503-1400\n\nSteps To Reproduce:\n1. Start Eclipse without internal browser available (Linux without Mozilla installed or without MOZILLA_FIVE_PATH)\n2. Navigate to Preferences -\u003e Java -\u003e Code Style -\u003e Clean Up\n3. See broken widgets, and press various buttons\n4. Eclipse crashes with SWT error\n\n\n\nMore information:\nAs the internal browser support is optional (everything  works without internal browser so far) preferences page must not use internal browser without checking and falling back to the pre-M7 behavior.\n\nHere is the error message from the log file:\n\n!ENTRY org.eclipse.ui 4 0 2007-05-09 20:38:24.656\n!MESSAGE Unhandled event loop exception\n!STACK 0\norg.eclipse.swt.SWTException: Failed to execute runnable (org.eclipse.swt.SWTError: No more handles [Unknown Mozilla path (MOZILLA_FIVE_HOME not set)])\n        at org.eclipse.swt.SWT.error(SWT.java:3547)\n        at org.eclipse.swt.SWT.error(SWT.java:3465)\n        at org.eclipse.swt.widgets.Synchronizer.runAsyncMessages(Synchronizer.java:126)\n        at org.eclipse.swt.widgets.Display.runAsyncMessages(Display.java:3297)\n        at org.eclipse.swt.widgets.Display.readAndDispatch(Display.java:2975)\n        at org.eclipse.jface.window.Window.runEventLoop(Window.java:820)\n        at org.eclipse.jface.window.Window.open(Window.java:796)\n        at org.eclipse.ui.internal.OpenPreferencesAction.run(OpenPreferencesAction.java:65)\n        at org.eclipse.jface.action.Action.runWithEvent(Action.java:498)\n        at org.eclipse.jface.action.ActionContributionItem.handleWidgetSelection(ActionContributionItem.java:545)\n        at org.eclipse.jface.action.ActionContributionItem.access$2(ActionContributionItem.java:490)\n        at org.eclipse.jface.action.ActionContributionItem$5.handleEvent(ActionContributionItem.java:402)\n        at org.eclipse.swt.widgets.EventTable.sendEvent(EventTable.java:66)\n        at org.eclipse.swt.widgets.Widget.sendEvent(Widget.java:1101)\n        at org.eclipse.swt.widgets.Display.runDeferredEvents(Display.java:3320)\n        at org.eclipse.swt.widgets.Display.readAndDispatch(Display.java:2972)\n        at org.eclipse.ui.internal.Workbench.runEventLoop(Workbench.java:2365)\n        at org.eclipse.ui.internal.Workbench.runUI(Workbench.java:2329)\n        at org.eclipse.ui.internal.Workbench.access$4(Workbench.java:2204)\n        at org.eclipse.ui.internal.Workbench$4.run(Workbench.java:466)\n        at org.eclipse.core.databinding.observable.Realm.runWithDefault(Realm.java:289)\n        at org.eclipse.ui.internal.Workbench.createAndRunWorkbench(Workbench.java:461)\n        at org.eclipse.ui.PlatformUI.createAndRunWorkbench(PlatformUI.java:149)\n        at org.eclipse.ui.internal.ide.application.IDEApplication.start(IDEApplication.java:106)\n        at org.eclipse.equinox.internal.app.EclipseAppHandle.run(EclipseAppHandle.java:153)\n        at org.eclipse.core.runtime.internal.adaptor.EclipseAppLauncher.runApplication(EclipseAppLauncher.java:106)\n        at org.eclipse.core.runtime.internal.adaptor.EclipseAppLauncher.start(EclipseAppLauncher.java:76)\n        at org.eclipse.core.runtime.adaptor.EclipseStarter.run(EclipseStarter.java:363)\n        at org.eclipse.core.runtime.adaptor.EclipseStarter.run(EclipseStarter.java:176)\n        at sun.reflect.NativeMethodAccessorImpl.invoke0(Native Method)\n        at sun.reflect.NativeMethodAccessorImpl.invoke(NativeMethodAccessorImpl.java:39)\n        at sun.reflect.DelegatingMethodAccessorImpl.invoke(DelegatingMethodAccessorImpl.java:25)\n        at java.lang.reflect.Method.invoke(Method.java:597)\n        at org.eclipse.equinox.launcher.Main.invokeFramework(Main.java:497)\n        at org.eclipse.equinox.launcher.Main.basicRun(Main.java:436)\n        at org.eclipse.equinox.launcher.Main.run(Main.java:1162)\nCaused by: org.eclipse.swt.SWTError: No more handles [Unknown Mozilla path (MOZILLA_FIVE_HOME not set)]\n        at org.eclipse.swt.SWT.error(SWT.java:3573)\n        at org.eclipse.swt.browser.Mozilla.create(Mozilla.java:302)\n        at org.eclipse.swt.browser.Browser.\u003cinit\u003e(Browser.java:109)\n        at org.eclipse.jdt.internal.ui.preferences.cleanup.DialogBrowserConfigurationBlock.createControl(DialogBrowserConfigurationBlock.java:27)\n        at org.eclipse.jdt.internal.ui.fix.CleanUpSaveParticipantPreferenceConfiguration.createAdvancedComposite(CleanUpSaveParticipantPreferenceConfiguration.java:159)\n        at org.eclipse.jdt.internal.ui.fix.CleanUpSaveParticipantPreferenceConfiguration.createConfigControl(CleanUpSaveParticipantPreferenceConfiguration.java:138)\n        at org.eclipse.jdt.internal.ui.javaeditor.saveparticipant.AbstractSaveParticipantPreferenceConfiguration.createControl(AbstractSaveParticipantPreferenceConfiguration.java:84)\n        at org.eclipse.jdt.internal.ui.preferences.SaveParticipantConfigurationBlock.createControl(SaveParticipantConfigurationBlock.java:91)\n        at org.eclipse.jdt.internal.ui.preferences.AbstractConfigurationBlockPreferenceAndPropertyPage.createPreferenceContent(AbstractConfigurationBlockPreferenceAndPropertyPage.jav\n        at org.eclipse.jdt.internal.ui.preferences.PropertyAndPreferencePage.createContents(PropertyAndPreferencePage.java:149)\n        at org.eclipse.jface.preference.PreferencePage.createControl(PreferencePage.java:233)\n        at org.eclipse.jdt.internal.ui.preferences.AbstractConfigurationBlockPreferenceAndPropertyPage.createControl(AbstractConfigurationBlockPreferenceAndPropertyPage.java:60)\n        at org.eclipse.jface.preference.PreferenceDialog.createPageControl(PreferenceDialog.java:1438)\n        at org.eclipse.jface.preference.PreferenceDialog$13.run(PreferenceDialog.java:1195)\n        at org.eclipse.core.runtime.SafeRunner.run(SafeRunner.java:37)\n        at org.eclipse.core.runtime.Platform.run(Platform.java:850)\n        at org.eclipse.ui.internal.JFaceUtil$1.run(JFaceUtil.java:46)\n        at org.eclipse.jface.util.SafeRunnable.run(SafeRunnable.java:193)\n        at org.eclipse.jface.preference.PreferenceDialog.showPage(PreferenceDialog.java:1189)\n        at org.eclipse.ui.internal.dialogs.FilteredPreferenceDialog.showPage(FilteredPreferenceDialog.java:433)\n        at org.eclipse.jface.preference.PreferenceDialog$9.selectionChanged(PreferenceDialog.java:694)\n        at org.eclipse.jface.viewers.StructuredViewer$3.run(StructuredViewer.java:842)\n        at org.eclipse.core.runtime.SafeRunner.run(SafeRunner.java:37)\n        at org.eclipse.core.runtime.Platform.run(Platform.java:850)\n        at org.eclipse.ui.internal.JFaceUtil$1.run(JFaceUtil.java:46)\n        at org.eclipse.jface.util.SafeRunnable.run(SafeRunnable.java:193)\n        at org.eclipse.jface.viewers.StructuredViewer.firePostSelectionChanged(StructuredViewer.java:840)\n        at org.eclipse.jface.viewers.StructuredViewer.handlePostSelect(StructuredViewer.java:1153)\n        at org.eclipse.jface.viewers.StructuredViewer$5.widgetSelected(StructuredViewer.java:1173)\n        at org.eclipse.jface.util.OpenStrategy.firePostSelectionEvent(OpenStrategy.java:250)\n        at org.eclipse.jface.util.OpenStrategy.access$4(OpenStrategy.java:244)\n        at org.eclipse.jface.util.OpenStrategy$3.run(OpenStrategy.java:418)\n        at org.eclipse.swt.widgets.RunnableLock.run(RunnableLock.java:35)\n        at org.eclipse.swt.widgets.Synchronizer.runAsyncMessages(Synchronizer.java:123)\n        ... 33 more",
    "Have to change to StyledText here anyway. Martin, just for the records, can you attach a screen shot of the page how it looks like on vista?",
    "Created an attachment (id\u003d66647)\nfix\n\nUse StyledText",
    "Martin? I think I should better use some system default color for enabled/disabled. But I can\u0027t find the constants.",
    "Created an attachment (id\u003d66663)\nupdated patch\n\nI didn\u0027t find a better solution for the \u0027disabled\u0027 color. But I simplified the code so you don\u0027t need to reference the normal foreground and background color.\n\nI also added a copyright for the new file",
    "Your patch looks good, can I release it for RC1? \n\nSee Bug 186161 for the missing copyright issue...",
    "Bug 186377 of course",
    "Aahh, sorry, I see you set the review flag to + on the attachment.\n\nFixed \u003e I20070508-0800",
    "You should use SWT.COLOR_WIDGET_BACKGROUND for \"disabled\" background instead of SWT.COLOR_GREY.",
    "Sebastian: could you file issue with disabled background color as separate bug, to make sure it won\u0027t be lost?\n",
    "opened bug 186976",
    "verified in 20070517-1700"
  ],
  "commentCreationDates": [
    "2007-05-09T16:08:20+02:00",
    "2007-05-09T16:14:04+02:00",
    "2007-05-10T13:58:06+02:00",
    "2007-05-10T14:00:28+02:00",
    "2007-05-10T15:26:43+02:00",
    "2007-05-10T16:58:32+02:00",
    "2007-05-10T16:59:01+02:00",
    "2007-05-10T17:01:39+02:00",
    "2007-05-15T12:30:11+02:00",
    "2007-05-15T12:37:33+02:00",
    "2007-05-15T12:46:25+02:00",
    "2007-05-18T17:36:12+02:00"
  ],
  "traces": [
    {
      "exceptionType": "org.eclipse.swt.SWTError",
      "message": "No more handles [Unknown Mozilla path (MOZILLA_FIVE_HOME not set)])",
      "elements": [
        {
          "method": "org.eclipse.swt.SWT.error",
          "source": "SWT.java:3547"
        },
        {
          "method": "org.eclipse.swt.SWT.error",
          "source": "SWT.java:3465"
        },
        {
          "method": "org.eclipse.swt.widgets.Synchronizer.runAsyncMessages",
          "source": "Synchronizer.java:126"
        },
        {
          "method": "org.eclipse.swt.widgets.Display.runAsyncMessages",
          "source": "Display.java:3297"
        },
        {
          "method": "org.eclipse.swt.widgets.Display.readAndDispatch",
          "source": "Display.java:2975"
        },
        {
          "method": "org.eclipse.jface.window.Window.runEventLoop",
          "source": "Window.java:820"
        },
        {
          "method": "org.eclipse.jface.window.Window.open",
          "source": "Window.java:796"
        },
        {
          "method": "org.eclipse.ui.internal.OpenPreferencesAction.run",
          "source": "OpenPreferencesAction.java:65"
        },
        {
          "method": "org.eclipse.jface.action.Action.runWithEvent",
          "source": "Action.java:498"
        },
        {
          "method": "org.eclipse.jface.action.ActionContributionItem.handleWidgetSelection",
          "source": "ActionContributionItem.java:545"
        },
        {
          "method": "org.eclipse.jface.action.ActionContributionItem.access$2",
          "source": "ActionContributionItem.java:490"
        },
        {
          "method": "org.eclipse.jface.action.ActionContributionItem$5.handleEvent",
          "source": "ActionContributionItem.java:402"
        },
        {
          "method": "org.eclipse.swt.widgets.EventTable.sendEvent",
          "source": "EventTable.java:66"
        },
        {
          "method": "org.eclipse.swt.widgets.Widget.sendEvent",
          "source": "Widget.java:1101"
        },
        {
          "method": "org.eclipse.swt.widgets.Display.runDeferredEvents",
          "source": "Display.java:3320"
        },
        {
          "method": "org.eclipse.swt.widgets.Display.readAndDispatch",
          "source": "Display.java:2972"
        },
        {
          "method": "org.eclipse.ui.internal.Workbench.runEventLoop",
          "source": "Workbench.java:2365"
        },
        {
          "method": "org.eclipse.ui.internal.Workbench.runUI",
          "source": "Workbench.java:2329"
        },
        {
          "method": "org.eclipse.ui.internal.Workbench.access$4",
          "source": "Workbench.java:2204"
        },
        {
          "method": "org.eclipse.ui.internal.Workbench$4.run",
          "source": "Workbench.java:466"
        },
        {
          "method": "org.eclipse.core.databinding.observable.Realm.runWithDefault",
          "source": "Realm.java:289"
        },
        {
          "method": "org.eclipse.ui.internal.Workbench.createAndRunWorkbench",
          "source": "Workbench.java:461"
        },
        {
          "method": "org.eclipse.ui.PlatformUI.createAndRunWorkbench",
          "source": "PlatformUI.java:149"
        },
        {
          "method": "org.eclipse.ui.internal.ide.application.IDEApplication.start",
          "source": "IDEApplication.java:106"
        },
        {
          "method": "org.eclipse.equinox.internal.app.EclipseAppHandle.run",
          "source": "EclipseAppHandle.java:153"
        },
        {
          "method": "org.eclipse.core.runtime.internal.adaptor.EclipseAppLauncher.runApplication",
          "source": "EclipseAppLauncher.java:106"
        },
        {
          "method": "org.eclipse.core.runtime.internal.adaptor.EclipseAppLauncher.start",
          "source": "EclipseAppLauncher.java:76"
        },
        {
          "method": "org.eclipse.core.runtime.adaptor.EclipseStarter.run",
          "source": "EclipseStarter.java:363"
        },
        {
          "method": "org.eclipse.core.runtime.adaptor.EclipseStarter.run",
          "source": "EclipseStarter.java:176"
        },
        {
          "method": "sun.reflect.NativeMethodAccessorImpl.invoke0",
          "source": "Native Method"
        },
        {
          "method": "sun.reflect.NativeMethodAccessorImpl.invoke",
          "source": "NativeMethodAccessorImpl.java:39"
        },
        {
          "method": "sun.reflect.DelegatingMethodAccessorImpl.invoke",
          "source": "DelegatingMethodAccessorImpl.java:25"
        },
        {
          "method": "java.lang.reflect.Method.invoke",
          "source": "Method.java:597"
        },
        {
          "method": "org.eclipse.equinox.launcher.Main.invokeFramework",
          "source": "Main.java:497"
        },
        {
          "method": "org.eclipse.equinox.launcher.Main.basicRun",
          "source": "Main.java:436"
        },
        {
          "method": "org.eclipse.equinox.launcher.Main.run",
          "source": "Main.java:1162"
        }
      ],
      "causedBy": {
        "exceptionType": "org.eclipse.swt.SWTError",
        "message": "No more handles [Unknown Mozilla path (MOZILLA_FIVE_HOME not set)]",
        "elements": [
          {
            "method": "org.eclipse.swt.SWT.error",
            "source": "SWT.java:3573"
          },
          {
            "method": "org.eclipse.swt.browser.Mozilla.create",
            "source": "Mozilla.java:302"
          },
          {
            "method": "org.eclipse.swt.browser.Browser.\u003cinit\u003e",
            "source": "Browser.java:109"
          },
          {
            "method": "org.eclipse.jdt.internal.ui.preferences.cleanup.DialogBrowserConfigurationBlock.createControl",
            "source": "DialogBrowserConfigurationBlock.java:27"
          },
          {
            "method": "org.eclipse.jdt.internal.ui.fix.CleanUpSaveParticipantPreferenceConfiguration.createAdvancedComposite",
            "source": "CleanUpSaveParticipantPreferenceConfiguration.java:159"
          },
          {
            "method": "org.eclipse.jdt.internal.ui.fix.CleanUpSaveParticipantPreferenceConfiguration.createConfigControl",
            "source": "CleanUpSaveParticipantPreferenceConfiguration.java:138"
          },
          {
            "method": "org.eclipse.jdt.internal.ui.javaeditor.saveparticipant.AbstractSaveParticipantPreferenceConfiguration.createControl",
            "source": "AbstractSaveParticipantPreferenceConfiguration.java:84"
          },
          {
            "method": "org.eclipse.jdt.internal.ui.preferences.SaveParticipantConfigurationBlock.createControl",
            "source": "SaveParticipantConfigurationBlock.java:91"
          }
        ],
        "number": 0,
        "commentIndex": 0
      },
      "number": 0,
      "commentIndex": 0,
      "bugId": "186161",
      "date": "2007-05-09T16:08:20+02:00",
      "product": "JDT",
      "component": "UI",
      "severity": "normal"
    }
  ],
  "groupId": "186161",
  "bugId": "186161",
  "date": "2007-05-09T16:08:20+02:00",
  "product": "JDT",
  "component": "UI",
  "severity": "normal"
}