{
  "comments": [
    "Build ID: I20070503-1400\n\nSteps To Reproduce:\n1. I created a Hello World RCP and made a product.\n2. When I want to export the product, it fails with an Error (Reason: Problems during export / Details: BUILD FAILED java.lang.IllegalArgumentException)\n3. If I try it with 3.3M6, it works.\n\n\nMore information:\nI added some branding (default Icons, that come with the Hello World RCP).",
    "I tried again with the \"-consoleLog\" Parameter...\n\n\n!ENTRY org.eclipse.ant.core 4 1 2007-05-10 16:59:51.090\n!MESSAGE BUILD FAILED\n!STACK 0\njava.lang.IllegalArgumentException\n        at java.net.URI.create(Unknown Source)\n        at sun.reflect.NativeMethodAccessorImpl.invoke0(Native Method)\n        at sun.reflect.NativeMethodAccessorImpl.invoke(Unknown Source)\n        at sun.reflect.DelegatingMethodAccessorImpl.invoke(Unknown Source)\n        at java.lang.reflect.Method.invoke(Unknown Source)\n        at org.apache.tools.ant.launch.Locator.fromURI(Locator.java:162)\n        at org.apache.tools.ant.launch.Locator.getResourceSource(Locator.java:11\n9)\n        at org.apache.tools.ant.launch.Locator.getClassSource(Locator.java:90)\n        at org.apache.tools.ant.Project.setAntLib(Project.java:313)\n        at org.apache.tools.ant.Project.initProperties(Project.java:309)\n        at org.apache.tools.ant.Project.init(Project.java:295)\n        at org.eclipse.ant.internal.core.ant.InternalAntRunner.run(InternalAntRu\nnner.java:520)\n        at org.eclipse.ant.internal.core.ant.InternalAntRunner.run(InternalAntRu\nnner.java:456)\n        at sun.reflect.NativeMethodAccessorImpl.invoke0(Native Method)\n        at sun.reflect.NativeMethodAccessorImpl.invoke(Unknown Source)\n        at sun.reflect.DelegatingMethodAccessorImpl.invoke(Unknown Source)\n        at java.lang.reflect.Method.invoke(Unknown Source)\n        at org.eclipse.ant.core.AntRunner.run(AntRunner.java:377)\n        at org.eclipse.pde.internal.core.exports.FeatureExportOperation.cleanup(\nFeatureExportOperation.java:576)\n        at org.eclipse.pde.internal.core.exports.ProductExportOperation.run(Prod\nuctExportOperation.java:113)\n        at org.eclipse.pde.internal.ui.build.FeatureExportJob.run(FeatureExportJ\nob.java:55)\n        at org.eclipse.core.internal.jobs.Worker.run(Worker.java:55)\nCaused by: java.net.URISyntaxException: Illegal character in path at index 13: f\nile:/C:/Java Dev/Eclipse/eclipse-SDK-3.3M7-win32/eclipse/plugins/org.apache.ant_\n1.7.0.v200704241635/lib/ant.jar\n        at java.net.URI$Parser.fail(Unknown Source)\n        at java.net.URI$Parser.checkChars(Unknown Source)\n        at java.net.URI$Parser.parseHierarchical(Unknown Source)\n        at java.net.URI$Parser.parse(Unknown Source)\n        at java.net.URI.\u003cinit\u003e(Unknown Source)\n        ... 22 more",
    "The product export works fine for me. Could you please provide us with a detailed setup (or even an archive) to reproduce the problem. Thx.",
    "Created an attachment (id\u003d66812)\nComplete project, that fails to export a product on my machine.\n\nAttached you find the project, that fails to export the product on my machine.\n\nSetup on my machine\n-------------------\nOS: Windows XP Professional SP2. English/International Version with german language pack (company version).\nComputer: IBM ThinkPad R50, Pentium M 1.5 GHz, 768 MB Ram\nJava: 1.5.0_09\nEclipse: Freshly downloaded - \"out of the box\".\n\nIf you need any more info, just contact me.",
    "Thanks for the example. I have tried it and the export completes successfully. Make sure that you have not installed M7 over an M6 install without deleting M6 before. Moving to the Ant component because the stack track indicates something in that space.",
    "This is a bug in the Ant 1.7.0 release if attempting to run a build in a location that has spaces in the path.\n\n*** This bug has been marked as a duplicate of bug 183283 ***"
  ],
  "commentCreationDates": [
    "2007-05-10T16:51:17+02:00",
    "2007-05-10T17:02:57+02:00",
    "2007-05-11T01:53:09+02:00",
    "2007-05-11T08:46:43+02:00",
    "2007-05-11T17:05:15+02:00",
    "2007-05-11T17:19:09+02:00"
  ],
  "traces": [
    {
      "exceptionType": "java.lang.IllegalArgumentException",
      "elements": [
        {
          "method": "java.net.URI.create",
          "source": "Unknown Source"
        },
        {
          "method": "sun.reflect.NativeMethodAccessorImpl.invoke0",
          "source": "Native Method"
        },
        {
          "method": "sun.reflect.NativeMethodAccessorImpl.invoke",
          "source": "Unknown Source"
        },
        {
          "method": "sun.reflect.DelegatingMethodAccessorImpl.invoke",
          "source": "Unknown Source"
        },
        {
          "method": "java.lang.reflect.Method.invoke",
          "source": "Unknown Source"
        },
        {
          "method": "org.apache.tools.ant.launch.Locator.fromURI",
          "source": "Locator.java:162"
        },
        {
          "method": "org.apache.tools.ant.launch.Locator.getResourceSource",
          "source": "Locator.java:11 9"
        },
        {
          "method": "org.apache.tools.ant.launch.Locator.getClassSource",
          "source": "Locator.java:90"
        },
        {
          "method": "org.apache.tools.ant.Project.setAntLib",
          "source": "Project.java:313"
        },
        {
          "method": "org.apache.tools.ant.Project.initProperties",
          "source": "Project.java:309"
        },
        {
          "method": "org.apache.tools.ant.Project.init",
          "source": "Project.java:295"
        },
        {
          "method": "org.eclipse.ant.internal.core.ant.InternalAntRunner.run",
          "source": "InternalAntRu nner.java:520"
        },
        {
          "method": "org.eclipse.ant.internal.core.ant.InternalAntRunner.run",
          "source": "InternalAntRu nner.java:456"
        },
        {
          "method": "sun.reflect.NativeMethodAccessorImpl.invoke0",
          "source": "Native Method"
        },
        {
          "method": "sun.reflect.NativeMethodAccessorImpl.invoke",
          "source": "Unknown Source"
        },
        {
          "method": "sun.reflect.DelegatingMethodAccessorImpl.invoke",
          "source": "Unknown Source"
        },
        {
          "method": "java.lang.reflect.Method.invoke",
          "source": "Unknown Source"
        },
        {
          "method": "org.eclipse.ant.core.AntRunner.run",
          "source": "AntRunner.java:377"
        },
        {
          "method": "org.eclipse.pde.internal.core.exports.FeatureExportOperation.cleanup",
          "source": " FeatureExportOperation.java:576"
        },
        {
          "method": "org.eclipse.pde.internal.core.exports.ProductExportOperation.run",
          "source": "Prod uctExportOperation.java:113"
        },
        {
          "method": "org.eclipse.pde.internal.ui.build.FeatureExportJob.run",
          "source": "FeatureExportJ ob.java:55"
        },
        {
          "method": "org.eclipse.core.internal.jobs.Worker.run",
          "source": "Worker.java:55"
        }
      ],
      "causedBy": {
        "exceptionType": "java.net.URISyntaxException",
        "message": "Illegal character in path at index 13: f ile:/C:/Java Dev/Eclipse/eclipse-SDK-3.3M7-win32/eclipse/plugins/org.apache.ant_ 1.7.0.v200704241635/lib/ant.jar",
        "elements": [
          {
            "method": "java.net.URI$Parser.fail",
            "source": "Unknown Source"
          },
          {
            "method": "java.net.URI$Parser.checkChars",
            "source": "Unknown Source"
          },
          {
            "method": "java.net.URI$Parser.parseHierarchical",
            "source": "Unknown Source"
          },
          {
            "method": "java.net.URI$Parser.parse",
            "source": "Unknown Source"
          },
          {
            "method": "java.net.URI.\u003cinit\u003e",
            "source": "Unknown Source"
          }
        ],
        "number": 0,
        "commentIndex": 0
      },
      "number": 0,
      "commentIndex": 1,
      "bugId": "186374",
      "duplicateId": "183283",
      "date": "2007-05-10T17:02:57+02:00",
      "product": "Platform",
      "component": "Ant",
      "severity": "normal"
    }
  ],
  "groupId": "183283",
  "bugId": "186374",
  "duplicateId": "183283",
  "date": "2007-05-10T16:51:17+02:00",
  "product": "Platform",
  "component": "Ant",
  "severity": "normal"
}