{
  "comments": [
    "When trying to show a status instastance that has the severity IStatus.OK, I get an NullPointerException as shown below.\n\nIStatus status \u003d new Status( IStatus.OK, // severity\n                             Activator.PLUGIN_ID, \n                             IStatus.OK, \n                             \"Message\", \n                             null );\nStatusManager.getManager().handle( status, StatusManager.SHOW );\n\nProduces the following exception:\n\norg.eclipse.swt.SWTException: Failed to execute runnable (java.lang.NullPointerException)\n\tat org.eclipse.swt.SWT.error(SWT.java:3547)\n\tat org.eclipse.swt.SWT.error(SWT.java:3465)\n\tat org.eclipse.swt.widgets.Synchronizer.runAsyncMessages(Synchronizer.java:126)\n\tat org.eclipse.swt.widgets.Display.runAsyncMessages(Display.java:3650)\n\tat org.eclipse.swt.widgets.Display.readAndDispatch(Display.java:3287)\n\tat org.eclipse.ui.internal.Workbench.runEventLoop(Workbench.java:2365)\n\tat org.eclipse.ui.internal.Workbench.runUI(Workbench.java:2329)\n\tat org.eclipse.ui.internal.Workbench.access$4(Workbench.java:2204)\n\tat org.eclipse.ui.internal.Workbench$4.run(Workbench.java:466)\n\tat org.eclipse.core.databinding.observable.Realm.runWithDefault(Realm.java:289)\n\tat org.eclipse.ui.internal.Workbench.createAndRunWorkbench(Workbench.java:461)\n\tat org.eclipse.ui.PlatformUI.createAndRunWorkbench(PlatformUI.java:149)\n\tat org.eclipse.ui.internal.ide.application.IDEApplication.start(IDEApplication.java:106)\n\tat org.eclipse.equinox.internal.app.EclipseAppHandle.run(EclipseAppHandle.java:153)\n\tat org.eclipse.core.runtime.internal.adaptor.EclipseAppLauncher.runApplication(EclipseAppLauncher.java:106)\n\tat org.eclipse.core.runtime.internal.adaptor.EclipseAppLauncher.start(EclipseAppLauncher.java:76)\n\tat org.eclipse.core.runtime.adaptor.EclipseStarter.run(EclipseStarter.java:363)\n\tat org.eclipse.core.runtime.adaptor.EclipseStarter.run(EclipseStarter.java:176)\n\tat sun.reflect.NativeMethodAccessorImpl.invoke0(Native Method)\n\tat sun.reflect.NativeMethodAccessorImpl.invoke(Unknown Source)\n\tat sun.reflect.DelegatingMethodAccessorImpl.invoke(Unknown Source)\n\tat java.lang.reflect.Method.invoke(Unknown Source)\n\tat org.eclipse.equinox.launcher.Main.invokeFramework(Main.java:497)\n\tat org.eclipse.equinox.launcher.Main.basicRun(Main.java:436)\n\tat org.eclipse.equinox.launcher.Main.run(Main.java:1162)\n\tat org.eclipse.equinox.launcher.Main.main(Main.java:1137)\nCaused by: java.lang.NullPointerException\n\tat org.eclipse.ui.internal.statushandlers.StatusNotificationManager$3.run(StatusNotificationManager.java:134)\n\tat org.eclipse.swt.widgets.RunnableLock.run(RunnableLock.java:35)\n\tat org.eclipse.swt.widgets.Synchronizer.runAsyncMessages(Synchronizer.java:123)\n\t... 23 more\n\nInterestingly, if one changes the severity to IStatus.ERROR the status is handled correctly (e.g. the dialog is shown). BTW, I am not using any custom error handler.",
    "Created an attachment (id\u003d66998)\nSample plug-in containing an action that exposes this issue.\n\n",
    "BTW, I\u0027m using Eclipse 3.3 M7.",
    "Created an attachment (id\u003d67482)\nFix 01\n\n",
    "+1",
    "Created an attachment (id\u003d67484)\nSample plug-in that does BLOCK and SHOW\n\n",
    "Patch released for build \u003e20070516",
    "Great, thanks for fixing this! \n"
  ],
  "commentCreationDates": [
    "2007-05-14T02:17:38+02:00",
    "2007-05-14T02:20:39+02:00",
    "2007-05-14T02:23:39+02:00",
    "2007-05-16T20:55:26+02:00",
    "2007-05-16T21:05:25+02:00",
    "2007-05-16T21:07:00+02:00",
    "2007-05-16T21:35:04+02:00",
    "2007-05-18T20:57:31+02:00"
  ],
  "traces": [
    {
      "exceptionType": "org.eclipse.swt.SWTException",
      "message": "Failed to execute runnable (java.lang.NullPointerException)",
      "elements": [
        {
          "method": "org.eclipse.swt.SWT.error",
          "source": "SWT.java:3547"
        },
        {
          "method": "org.eclipse.swt.SWT.error",
          "source": "SWT.java:3465"
        },
        {
          "method": "org.eclipse.swt.widgets.Synchronizer.runAsyncMessages",
          "source": "Synchronizer.java:126"
        },
        {
          "method": "org.eclipse.swt.widgets.Display.runAsyncMessages",
          "source": "Display.java:3650"
        },
        {
          "method": "org.eclipse.swt.widgets.Display.readAndDispatch",
          "source": "Display.java:3287"
        },
        {
          "method": "org.eclipse.ui.internal.Workbench.runEventLoop",
          "source": "Workbench.java:2365"
        },
        {
          "method": "org.eclipse.ui.internal.Workbench.runUI",
          "source": "Workbench.java:2329"
        },
        {
          "method": "org.eclipse.ui.internal.Workbench.access$4",
          "source": "Workbench.java:2204"
        },
        {
          "method": "org.eclipse.ui.internal.Workbench$4.run",
          "source": "Workbench.java:466"
        },
        {
          "method": "org.eclipse.core.databinding.observable.Realm.runWithDefault",
          "source": "Realm.java:289"
        },
        {
          "method": "org.eclipse.ui.internal.Workbench.createAndRunWorkbench",
          "source": "Workbench.java:461"
        },
        {
          "method": "org.eclipse.ui.PlatformUI.createAndRunWorkbench",
          "source": "PlatformUI.java:149"
        },
        {
          "method": "org.eclipse.ui.internal.ide.application.IDEApplication.start",
          "source": "IDEApplication.java:106"
        },
        {
          "method": "org.eclipse.equinox.internal.app.EclipseAppHandle.run",
          "source": "EclipseAppHandle.java:153"
        },
        {
          "method": "org.eclipse.core.runtime.internal.adaptor.EclipseAppLauncher.runApplication",
          "source": "EclipseAppLauncher.java:106"
        },
        {
          "method": "org.eclipse.core.runtime.internal.adaptor.EclipseAppLauncher.start",
          "source": "EclipseAppLauncher.java:76"
        },
        {
          "method": "org.eclipse.core.runtime.adaptor.EclipseStarter.run",
          "source": "EclipseStarter.java:363"
        },
        {
          "method": "org.eclipse.core.runtime.adaptor.EclipseStarter.run",
          "source": "EclipseStarter.java:176"
        },
        {
          "method": "sun.reflect.NativeMethodAccessorImpl.invoke0",
          "source": "Native Method"
        },
        {
          "method": "sun.reflect.NativeMethodAccessorImpl.invoke",
          "source": "Unknown Source"
        },
        {
          "method": "sun.reflect.DelegatingMethodAccessorImpl.invoke",
          "source": "Unknown Source"
        },
        {
          "method": "java.lang.reflect.Method.invoke",
          "source": "Unknown Source"
        },
        {
          "method": "org.eclipse.equinox.launcher.Main.invokeFramework",
          "source": "Main.java:497"
        },
        {
          "method": "org.eclipse.equinox.launcher.Main.basicRun",
          "source": "Main.java:436"
        },
        {
          "method": "org.eclipse.equinox.launcher.Main.run",
          "source": "Main.java:1162"
        },
        {
          "method": "org.eclipse.equinox.launcher.Main.main",
          "source": "Main.java:1137"
        }
      ],
      "causedBy": {
        "exceptionType": "java.lang.NullPointerException",
        "elements": [
          {
            "method": "org.eclipse.ui.internal.statushandlers.StatusNotificationManager$3.run",
            "source": "StatusNotificationManager.java:134"
          },
          {
            "method": "org.eclipse.swt.widgets.RunnableLock.run",
            "source": "RunnableLock.java:35"
          },
          {
            "method": "org.eclipse.swt.widgets.Synchronizer.runAsyncMessages",
            "source": "Synchronizer.java:123"
          }
        ],
        "number": 0,
        "commentIndex": 0
      },
      "number": 0,
      "commentIndex": 0,
      "bugId": "186727",
      "date": "2007-05-14T02:17:38+02:00",
      "product": "Platform",
      "component": "UI",
      "severity": "major"
    }
  ],
  "groupId": "186727",
  "bugId": "186727",
  "date": "2007-05-14T02:17:38+02:00",
  "product": "Platform",
  "component": "UI",
  "severity": "major"
}