{
  "comments": [
    "NoClassDefFoundError will be thrown when run report with BIRT-Runtime even a simple report.\n\nFollowed is the error message:\nSEVERE: Error happened while running the report.\njava.lang.NoClassDefFoundError: org/eclipse/birt/data/engine/olap/data/document/\nDocumentManagerFactory\n        at org.eclipse.birt.data.engine.olap.api.cube.CubeMaterializer.\u003cinit\u003e(Cu\nbeMaterializer.java:47)\n        at org.eclipse.birt.report.data.adapter.impl.DataRequestSessionImpl.crea\nteCubeMaterializer(DataRequestSessionImpl.java:498)\n        at org.eclipse.birt.report.data.adapter.impl.DataRequestSessionImpl.defi\nneCube(DataRequestSessionImpl.java:466)\n        at org.eclipse.birt.report.engine.data.dte.AbstractDataEngine.prepare(Ab\nstractDataEngine.java:138)\n        at org.eclipse.birt.report.engine.executor.ReportExecutor.execute(Report\nExecutor.java:104)\n        at org.eclipse.birt.report.engine.internal.executor.l18n.LocalizedReport\nExecutor.execute(LocalizedReportExecutor.java:50)\n        at org.eclipse.birt.report.engine.layout.html.HTMLReportLayoutEngine.lay\nout(HTMLReportLayoutEngine.java:76)\n        at org.eclipse.birt.report.engine.api.impl.RunAndRenderTask.doRun(RunAnd\nRenderTask.java:205)\n        at org.eclipse.birt.report.engine.api.impl.RunAndRenderTask.run(RunAndRe\nnderTask.java:125)\n        at org.eclipse.birt.report.engine.api.ReportRunner.runAndRenderReport(Re\nportRunner.java:221)\n        at org.eclipse.birt.report.engine.api.ReportRunner.execute(ReportRunner.\njava:161)\n        at org.eclipse.birt.report.engine.api.ReportRunner.main(ReportRunner.jav\na:117)\nMay 17, 2007 1:41:43 PM org.eclipse.birt.report.engine.api.ReportRunner runAndRe\nnderReport",
    "Fixed.",
    "*** Bug 187151 has been marked as a duplicate of this bug. ***"
  ],
  "commentCreationDates": [
    "2007-05-17T07:55:28+02:00",
    "2007-05-17T15:23:28+02:00",
    "2007-05-18T07:53:39+02:00"
  ],
  "traces": [
    {
      "exceptionType": "java.lang.NoClassDefFoundError",
      "message": "org/eclipse/birt/data/engine/olap/data/document/ DocumentManagerFactory",
      "elements": [
        {
          "method": "org.eclipse.birt.data.engine.olap.api.cube.CubeMaterializer.\u003cinit\u003e",
          "source": "Cu beMaterializer.java:47"
        },
        {
          "method": "org.eclipse.birt.report.data.adapter.impl.DataRequestSessionImpl.createCubeMaterializer",
          "source": "DataRequestSessionImpl.java:498"
        },
        {
          "method": "org.eclipse.birt.report.data.adapter.impl.DataRequestSessionImpl.defineCube",
          "source": "DataRequestSessionImpl.java:466"
        },
        {
          "method": "org.eclipse.birt.report.engine.data.dte.AbstractDataEngine.prepare",
          "source": "Ab stractDataEngine.java:138"
        },
        {
          "method": "org.eclipse.birt.report.engine.executor.ReportExecutor.execute",
          "source": "Report Executor.java:104"
        },
        {
          "method": "org.eclipse.birt.report.engine.internal.executor.l18n.LocalizedReportExecutor.execute",
          "source": "LocalizedReportExecutor.java:50"
        },
        {
          "method": "org.eclipse.birt.report.engine.layout.html.HTMLReportLayoutEngine.layout",
          "source": "HTMLReportLayoutEngine.java:76"
        },
        {
          "method": "org.eclipse.birt.report.engine.api.impl.RunAndRenderTask.doRun",
          "source": "RunAnd RenderTask.java:205"
        },
        {
          "method": "org.eclipse.birt.report.engine.api.impl.RunAndRenderTask.run",
          "source": "RunAndRe nderTask.java:125"
        },
        {
          "method": "org.eclipse.birt.report.engine.api.ReportRunner.runAndRenderReport",
          "source": "Re portRunner.java:221"
        },
        {
          "method": "org.eclipse.birt.report.engine.api.ReportRunner.execute",
          "source": "ReportRunner. java:161"
        },
        {
          "method": "org.eclipse.birt.report.engine.api.ReportRunner.main",
          "source": "ReportRunner.jav a:117"
        }
      ],
      "number": 0,
      "commentIndex": 0,
      "bugId": "187463",
      "date": "2007-05-17T07:55:28+02:00",
      "product": "BIRT",
      "component": "Data",
      "severity": "normal"
    }
  ],
  "groupId": "187463",
  "bugId": "187463",
  "date": "2007-05-17T07:55:28+02:00",
  "product": "BIRT",
  "component": "Data",
  "severity": "normal"
}