{
  "comments": [
    "The following error occurs when viewing a report on linux.  This does not seem to break any of the reporting function.\n\njava.io.IOException: Couldn\u0027t get lock for /home/aperidev/Aperi3/plugins/org.eclipse.aperi.reporting_5.0.0/web/birt-viewer/logs/ReportEngine_2007_05_18_15_13_53.log\n        at java.util.logging.FileHandler.openFiles(FileHandler.java:372)\n        at java.util.logging.FileHandler.\u003cinit\u003e(FileHandler.java:270)\n        at org.eclipse.birt.report.engine.api.impl.EngineLogger.startEngineLogging(EngineLogger.java:56)\n        at org.eclipse.birt.report.engine.api.impl.ReportEngineHelper.setupLogging(ReportEngineHelper.java:338)\n        at org.eclipse.birt.report.engine.api.impl.ReportEngine.setupLogging(ReportEngine.java:108)\n        at org.eclipse.birt.report.engine.api.impl.ReportEngine.\u003cinit\u003e(ReportEngine.java:89)\n        at org.eclipse.birt.report.engine.api.impl.ReportEngineFactory.createReportEngine(ReportEngineFactory.java:13)\n        at org.eclipse.birt.report.service.ReportEngineService.setEngineContext(Unknown Source)\n        at org.eclipse.birt.report.service.BirtViewerReportService.setContext(Unknown Source)\n        at org.eclipse.birt.report.servlet.BirtEngineServlet.__getContext(Unknown Source)\n        at org.eclipse.birt.report.servlet.BaseReportEngineServlet.doGet(Unknown Source)\n        at javax.servlet.http.HttpServlet.service(HttpServlet.java:596)\n        at org.apache.axis.transport.http.AxisServletBase.service(AxisServletBase.java:327)\n        at javax.servlet.http.HttpServlet.service(HttpServlet.java:689)\n        at org.mortbay.jetty.servlet.ServletHolder.handle(ServletHolder.java:428)\n        at org.mortbay.jetty.servlet.WebApplicationHandler.dispatch(WebApplicationHandler.java:473)\n        at org.mortbay.jetty.servlet.ServletHandler.handle(ServletHandler.java:568)\n        at org.mortbay.http.HttpContext.handle(HttpContext.java:1530)\n        at org.mortbay.jetty.servlet.WebApplicationContext.handle(WebApplicationContext.java:633)\n        at org.mortbay.http.HttpContext.handle(HttpContext.java:1482)\n        at org.mortbay.http.HttpServer.service(HttpServer.java:909)\n        at org.mortbay.http.HttpConnection.service(HttpConnection.java:820)\n        at org.mortbay.http.HttpConnection.handleNext(HttpConnection.java:986)\n        at org.mortbay.http.HttpConnection.handle(HttpConnection.java:837)\n        at org.mortbay.http.SocketListener.handleConnection(SocketListener.java:245)\n        at org.mortbay.util.ThreadedServer.handle(ThreadedServer.java:357)\n        at org.mortbay.util.ThreadPool$PoolThread.run(ThreadPool.java:534)"
  ],
  "commentCreationDates": [
    "2007-05-19T00:31:41+02:00"
  ],
  "traces": [
    {
      "exceptionType": "java.io.IOException",
      "message": "Couldn\u0027t get lock for /home/aperidev/Aperi3/plugins/org.eclipse.aperi.reporting_5.0.0/web/birt-viewer/logs/ReportEngine_2007_05_18_15_13_53.log",
      "elements": [
        {
          "method": "java.util.logging.FileHandler.openFiles",
          "source": "FileHandler.java:372"
        },
        {
          "method": "java.util.logging.FileHandler.\u003cinit\u003e",
          "source": "FileHandler.java:270"
        },
        {
          "method": "org.eclipse.birt.report.engine.api.impl.EngineLogger.startEngineLogging",
          "source": "EngineLogger.java:56"
        },
        {
          "method": "org.eclipse.birt.report.engine.api.impl.ReportEngineHelper.setupLogging",
          "source": "ReportEngineHelper.java:338"
        },
        {
          "method": "org.eclipse.birt.report.engine.api.impl.ReportEngine.setupLogging",
          "source": "ReportEngine.java:108"
        },
        {
          "method": "org.eclipse.birt.report.engine.api.impl.ReportEngine.\u003cinit\u003e",
          "source": "ReportEngine.java:89"
        },
        {
          "method": "org.eclipse.birt.report.engine.api.impl.ReportEngineFactory.createReportEngine",
          "source": "ReportEngineFactory.java:13"
        },
        {
          "method": "org.eclipse.birt.report.service.ReportEngineService.setEngineContext",
          "source": "Unknown Source"
        },
        {
          "method": "org.eclipse.birt.report.service.BirtViewerReportService.setContext",
          "source": "Unknown Source"
        },
        {
          "method": "org.eclipse.birt.report.servlet.BirtEngineServlet.__getContext",
          "source": "Unknown Source"
        },
        {
          "method": "org.eclipse.birt.report.servlet.BaseReportEngineServlet.doGet",
          "source": "Unknown Source"
        },
        {
          "method": "javax.servlet.http.HttpServlet.service",
          "source": "HttpServlet.java:596"
        },
        {
          "method": "org.apache.axis.transport.http.AxisServletBase.service",
          "source": "AxisServletBase.java:327"
        },
        {
          "method": "javax.servlet.http.HttpServlet.service",
          "source": "HttpServlet.java:689"
        },
        {
          "method": "org.mortbay.jetty.servlet.ServletHolder.handle",
          "source": "ServletHolder.java:428"
        },
        {
          "method": "org.mortbay.jetty.servlet.WebApplicationHandler.dispatch",
          "source": "WebApplicationHandler.java:473"
        },
        {
          "method": "org.mortbay.jetty.servlet.ServletHandler.handle",
          "source": "ServletHandler.java:568"
        },
        {
          "method": "org.mortbay.http.HttpContext.handle",
          "source": "HttpContext.java:1530"
        },
        {
          "method": "org.mortbay.jetty.servlet.WebApplicationContext.handle",
          "source": "WebApplicationContext.java:633"
        },
        {
          "method": "org.mortbay.http.HttpContext.handle",
          "source": "HttpContext.java:1482"
        },
        {
          "method": "org.mortbay.http.HttpServer.service",
          "source": "HttpServer.java:909"
        },
        {
          "method": "org.mortbay.http.HttpConnection.service",
          "source": "HttpConnection.java:820"
        },
        {
          "method": "org.mortbay.http.HttpConnection.handleNext",
          "source": "HttpConnection.java:986"
        },
        {
          "method": "org.mortbay.http.HttpConnection.handle",
          "source": "HttpConnection.java:837"
        },
        {
          "method": "org.mortbay.http.SocketListener.handleConnection",
          "source": "SocketListener.java:245"
        },
        {
          "method": "org.mortbay.util.ThreadedServer.handle",
          "source": "ThreadedServer.java:357"
        },
        {
          "method": "org.mortbay.util.ThreadPool$PoolThread.run",
          "source": "ThreadPool.java:534"
        }
      ],
      "number": 0,
      "commentIndex": 0,
      "bugId": "187930",
      "date": "2007-05-19T00:31:41+02:00",
      "product": "Aperi",
      "component": "aperi.reporting",
      "severity": "normal"
    }
  ],
  "groupId": "187930",
  "bugId": "187930",
  "date": "2007-05-19T00:31:41+02:00",
  "product": "Aperi",
  "component": "aperi.reporting",
  "severity": "normal"
}