{
  "comments": [
    "build i0523-0010\n\njava version \"1.5.0\"\nJava(TM) 2 Runtime Environment, Standard Edition (build pxi32dev-20070201 (SR4))IBM J9 VM (build 2.3, J2RE 1.5.0 IBM J9 2.3 Linux x86-32 j9vmxi3223-20070201 (JIT enabled)\nJ9VM - 20070131_11312_lHdSMR\nJIT  - 20070109_1805ifx1_r8\nGC   - 200701_09)\nJCL  - 20070126\n\n- download build\n- start with: ./eclipse -console -consoleLog \u0026\n\nI get the following stack trace and Eclipse freezes. I have to kill the process. This all happens before the workspace chooser dialog. Might have to press Enter in the console to get it to happen.\n\njava.io.IOException: Unknown error 512\n        at java.io.FileInputStream.read(FileInputStream.java:229)\n        at java.io.BufferedInputStream.read1(BufferedInputStream.java:265)\n        at java.io.BufferedInputStream.read(BufferedInputStream.java:324)\n        at java.io.FilterInputStream.read(FilterInputStream.java:134)\n        at java.io.FilterInputStream.read(FilterInputStream.java:113)\n        at sun.nio.cs.StreamDecoder$ConverterSD.implRead(StreamDecoder.java:352)\n        at sun.nio.cs.StreamDecoder.read(StreamDecoder.java:250)\n        at java.io.InputStreamReader.read(InputStreamReader.java:212)\n        at java.io.BufferedReader.fill(BufferedReader.java:157)\n        at java.io.BufferedReader.readLine(BufferedReader.java:320)\n        at java.io.BufferedReader.readLine(BufferedReader.java:383)\n        at org.eclipse.osgi.framework.internal.core.FrameworkConsole.console(FrameworkConsole.java:273)\n        at org.eclipse.osgi.framework.internal.core.FrameworkConsole.run(FrameworkConsole.java:218)\n        at java.lang.Thread.run(Thread.java:803)",
    "This maybe related to bug 192361.  I\u0027m not sure why this is failing, but I am not sure what the expected behavior should be either.  If the process is run in the background then where will the console get its input from?  I suspect java (or maybe jni from the launcher) is getting confused when it tries to figure out what the input stream should be for a background process.\n\none workaround is to specify a port for the console.  For example\n\n  ./eclipse -console 8082 -consoleLog \u0026\n\nThen telnet into the console for input\n\n  telnet localhost 8082\n\n"
  ],
  "commentCreationDates": [
    "2007-05-23T22:21:13+02:00",
    "2007-06-22T00:35:06+02:00"
  ],
  "traces": [
    {
      "exceptionType": "java.io.IOException",
      "message": "Unknown error 512",
      "elements": [
        {
          "method": "java.io.FileInputStream.read",
          "source": "FileInputStream.java:229"
        },
        {
          "method": "java.io.BufferedInputStream.read1",
          "source": "BufferedInputStream.java:265"
        },
        {
          "method": "java.io.BufferedInputStream.read",
          "source": "BufferedInputStream.java:324"
        },
        {
          "method": "java.io.FilterInputStream.read",
          "source": "FilterInputStream.java:134"
        },
        {
          "method": "java.io.FilterInputStream.read",
          "source": "FilterInputStream.java:113"
        },
        {
          "method": "sun.nio.cs.StreamDecoder$ConverterSD.implRead",
          "source": "StreamDecoder.java:352"
        },
        {
          "method": "sun.nio.cs.StreamDecoder.read",
          "source": "StreamDecoder.java:250"
        },
        {
          "method": "java.io.InputStreamReader.read",
          "source": "InputStreamReader.java:212"
        },
        {
          "method": "java.io.BufferedReader.fill",
          "source": "BufferedReader.java:157"
        },
        {
          "method": "java.io.BufferedReader.readLine",
          "source": "BufferedReader.java:320"
        },
        {
          "method": "java.io.BufferedReader.readLine",
          "source": "BufferedReader.java:383"
        },
        {
          "method": "org.eclipse.osgi.framework.internal.core.FrameworkConsole.console",
          "source": "FrameworkConsole.java:273"
        },
        {
          "method": "org.eclipse.osgi.framework.internal.core.FrameworkConsole.run",
          "source": "FrameworkConsole.java:218"
        },
        {
          "method": "java.lang.Thread.run",
          "source": "Thread.java:803"
        }
      ],
      "number": 0,
      "commentIndex": 0,
      "bugId": "188763",
      "date": "2007-05-23T22:21:13+02:00",
      "product": "Equinox",
      "component": "Framework",
      "severity": "normal"
    }
  ],
  "groupId": "188763",
  "bugId": "188763",
  "date": "2007-05-23T22:21:13+02:00",
  "product": "Equinox",
  "component": "Framework",
  "severity": "normal"
}