{
  "comments": [
    "This is not reproducible but here is wat I did to trigger it the 1st time:\n\nOpened the site explorer view with an FTP \u0026 a DAV site already configured.\nDeleted them both then tried to create a new FTP site using the same server but\nno username or pwd.\nThe dialog vanished then reappeared with the URL still filled in but did not\ncreate a new site. Clicking on Finish did not make it go away.\n\nI looked in the log file \u0026 found this stack trace for each time I had hit\nFinish:\n\n!ENTRY org.eclipse.ui 4 4 Jun 03, 2002 15:48:17.361\n!MESSAGE Unhandled exception caught in event loop.\n!ENTRY org.eclipse.ui 4 0 Jun 03, 2002 15:48:17.363\n!MESSAGE Assertion failed: ContentViewer must have a content provider when input\nis set.\n!STACK 0\norg.eclipse.jface.util.Assert$AssertionFailedException: Assertion failed:\nContentViewer must have a content provider when input is set.\n        at org.eclipse.jface.util.Assert.isTrue(Assert.java:162)\n        at\norg.eclipse.jface.viewers.ContentViewer.setInput(ContentViewer.java:225)\n        at\norg.eclipse.jface.viewers.StructuredViewer.setInput(StructuredViewer.java:875)\n        at\norg.eclipse.team.internal.ui.target.SiteExplorerView.initializeTreeInput(SiteExplorerView.java:487)\n        at\norg.eclipse.team.internal.ui.target.SiteExplorerView.siteAdded(SiteExplorerView.java:465)\n        at\norg.eclipse.team.core.target.TargetManager.addSite(TargetManager.java:76)\n        at\norg.eclipse.team.internal.ftp.ui.FTPConfigurationWizard.performFinish(FTPConfigurationWizard.java:72)\n        at\norg.eclipse.jface.wizard.WizardDialog.finishPressed(WizardDialog.java:577)\n        at\norg.eclipse.jface.wizard.WizardDialog.buttonPressed(WizardDialog.java:312)\n        at org.eclipse.jface.dialogs.Dialog$1.widgetSelected(Dialog.java:398)\n        at\norg.eclipse.swt.widgets.TypedListener.handleEvent(TypedListener.java(Compiled\nCode))\n        at org.eclipse.swt.widgets.EventTable.sendEvent(EventTable.java(Compiled\nCode))\n        at\norg.eclipse.swt.widgets.Display.runDeferredEvents(Display.java(Compiled Code))\n        at\norg.eclipse.swt.widgets.Display.runDeferredEvents(Display.java(Compiled Code))\n        at org.eclipse.swt.widgets.Display.readAndDispatch(Display.java(Compiled\nCode))\n        at org.eclipse.jface.window.Window.runEventLoop(Window.java(Compiled\nCode))\n        at org.eclipse.jface.window.Window.open(Window.java:538)\n        at\norg.eclipse.team.internal.ui.target.SiteExplorerView$8.run(SiteExplorerView.java:387)\n        at org.eclipse.jface.action.Action.runWithEvent(Action.java:749)\n        at\norg.eclipse.jface.action.ActionContributionItem.handleWidgetSelection(ActionContributionItem.java:407)\n        at\norg.eclipse.jface.action.ActionContributionItem$ActionListener.handleEvent(ActionContributionItem.java(Compiled\nCode))\n        at\norg.eclipse.jface.action.ActionContributionItem$ActionListener.handleEvent(ActionContributionItem.java(Compiled\nCode))\n        at\norg.eclipse.jface.action.ActionContributionItem$ActionListener.handleEvent(ActionContributionItem.java(Compiled\nCode))\n        at org.eclipse.swt.widgets.EventTable.sendEvent(EventTable.java(Compiled\nCode))\n        at\norg.eclipse.swt.widgets.Display.runDeferredEvents(Display.java(Compiled Code))\n        at\norg.eclipse.swt.widgets.Display.runDeferredEvents(Display.java(Compiled Code))\n        at org.eclipse.swt.widgets.Display.readAndDispatch(Display.java(Compiled\nCode))\n        at\norg.eclipse.ui.internal.Workbench.runEventLoop(Workbench.java(Compiled Code))\n        at org.eclipse.ui.internal.Workbench.run(Workbench.java:1160)\n        at\norg.eclipse.core.internal.boot.InternalBootLoader.run(InternalBootLoader.java:739)\n        at org.eclipse.core.boot.BootLoader.run(BootLoader.java:462)\n        at java.lang.reflect.Method.invoke(Native Method)\n        at org.eclipse.core.launcher.Main.basicRun(Main.java:244)\n        at org.eclipse.core.launcher.Main.run(Main.java:693)\n        at org.eclipse.core.launcher.Main.main(Main.java:526)",
    "JM to investigate",
    "I\u0027ve duplicated this problem but haven\u0027t been able to determine how the content\nprovider for the folderTree gets nulled. When the tree is created it is\ninitialized with a content provider, so it should exist is the siteAdded() method.",
    "I\u0027ve changed the site added method and have not been able to duplicated since. I\nthink that this was the problem. Closing.",
    "Seems to have been squished."
  ],
  "commentCreationDates": [
    "2002-06-03T21:53:51+02:00",
    "2002-06-04T00:05:21+02:00",
    "2002-06-04T18:07:05+02:00",
    "2002-06-05T18:30:59+02:00",
    "2002-06-25T17:45:46+02:00"
  ],
  "traces": [
    {
      "exceptionType": "org.eclipse.jface.util.Assert$AssertionFailedException",
      "message": "Assertion failed: ContentViewer must have a content provider when input is set.",
      "elements": [
        {
          "method": "org.eclipse.jface.util.Assert.isTrue",
          "source": "Assert.java:162"
        },
        {
          "method": "org.eclipse.jface.viewers.ContentViewer.setInput",
          "source": "ContentViewer.java:225"
        },
        {
          "method": "org.eclipse.jface.viewers.StructuredViewer.setInput",
          "source": "StructuredViewer.java:875"
        },
        {
          "method": "org.eclipse.team.internal.ui.target.SiteExplorerView.initializeTreeInput",
          "source": "SiteExplorerView.java:487"
        },
        {
          "method": "org.eclipse.team.internal.ui.target.SiteExplorerView.siteAdded",
          "source": "SiteExplorerView.java:465"
        },
        {
          "method": "org.eclipse.team.core.target.TargetManager.addSite",
          "source": "TargetManager.java:76"
        },
        {
          "method": "org.eclipse.team.internal.ftp.ui.FTPConfigurationWizard.performFinish",
          "source": "FTPConfigurationWizard.java:72"
        },
        {
          "method": "org.eclipse.jface.wizard.WizardDialog.finishPressed",
          "source": "WizardDialog.java:577"
        },
        {
          "method": "org.eclipse.jface.wizard.WizardDialog.buttonPressed",
          "source": "WizardDialog.java:312"
        },
        {
          "method": "org.eclipse.jface.dialogs.Dialog$1.widgetSelected",
          "source": "Dialog.java:398"
        },
        {
          "method": "org.eclipse.swt.widgets.TypedListener.handleEvent",
          "source": "TypedListener.java(Compiled Code)"
        },
        {
          "method": "org.eclipse.swt.widgets.EventTable.sendEvent",
          "source": "EventTable.java(Compiled Code)"
        },
        {
          "method": "org.eclipse.swt.widgets.Display.runDeferredEvents",
          "source": "Display.java(Compiled Code)"
        },
        {
          "method": "org.eclipse.swt.widgets.Display.runDeferredEvents",
          "source": "Display.java(Compiled Code)"
        },
        {
          "method": "org.eclipse.swt.widgets.Display.readAndDispatch",
          "source": "Display.java(Compiled Code)"
        },
        {
          "method": "org.eclipse.jface.window.Window.runEventLoop",
          "source": "Window.java(Compiled Code)"
        },
        {
          "method": "org.eclipse.jface.window.Window.open",
          "source": "Window.java:538"
        },
        {
          "method": "org.eclipse.team.internal.ui.target.SiteExplorerView$8.run",
          "source": "SiteExplorerView.java:387"
        },
        {
          "method": "org.eclipse.jface.action.Action.runWithEvent",
          "source": "Action.java:749"
        },
        {
          "method": "org.eclipse.jface.action.ActionContributionItem.handleWidgetSelection",
          "source": "ActionContributionItem.java:407"
        },
        {
          "method": "org.eclipse.jface.action.ActionContributionItem$ActionListener.handleEvent",
          "source": "ActionContributionItem.java(Compiled Code)"
        },
        {
          "method": "org.eclipse.jface.action.ActionContributionItem$ActionListener.handleEvent",
          "source": "ActionContributionItem.java(Compiled Code)"
        },
        {
          "method": "org.eclipse.jface.action.ActionContributionItem$ActionListener.handleEvent",
          "source": "ActionContributionItem.java(Compiled Code)"
        },
        {
          "method": "org.eclipse.swt.widgets.EventTable.sendEvent",
          "source": "EventTable.java(Compiled Code)"
        },
        {
          "method": "org.eclipse.swt.widgets.Display.runDeferredEvents",
          "source": "Display.java(Compiled Code)"
        },
        {
          "method": "org.eclipse.swt.widgets.Display.runDeferredEvents",
          "source": "Display.java(Compiled Code)"
        },
        {
          "method": "org.eclipse.swt.widgets.Display.readAndDispatch",
          "source": "Display.java(Compiled Code)"
        },
        {
          "method": "org.eclipse.ui.internal.Workbench.runEventLoop",
          "source": "Workbench.java(Compiled Code)"
        },
        {
          "method": "org.eclipse.ui.internal.Workbench.run",
          "source": "Workbench.java:1160"
        },
        {
          "method": "org.eclipse.core.internal.boot.InternalBootLoader.run",
          "source": "InternalBootLoader.java:739"
        },
        {
          "method": "org.eclipse.core.boot.BootLoader.run",
          "source": "BootLoader.java:462"
        },
        {
          "method": "java.lang.reflect.Method.invoke",
          "source": "Native Method"
        },
        {
          "method": "org.eclipse.core.launcher.Main.basicRun",
          "source": "Main.java:244"
        },
        {
          "method": "org.eclipse.core.launcher.Main.run",
          "source": "Main.java:693"
        },
        {
          "method": "org.eclipse.core.launcher.Main.main",
          "source": "Main.java:526"
        }
      ],
      "number": 0,
      "commentIndex": 0,
      "bugId": "18903",
      "date": "2002-06-03T21:53:51+02:00",
      "product": "Platform",
      "component": "Team",
      "severity": "normal"
    }
  ],
  "groupId": "18903",
  "bugId": "18903",
  "date": "2002-06-03T21:53:51+02:00",
  "product": "Platform",
  "component": "Team",
  "severity": "normal"
}