{
  "comments": [
    "Connection refused when lauching tests on Linux.\n\nUsing the TPTP-4.4.0-200705080100Y on SLES 10 running in 32bit mode on EM64T, the following exception is thrown when lauching tests locally using the IAC or from a remote machine (XP) using the Agent Controller:\n\njava.net.ConnectException: Connection refused\n        at sun.nio.ch.Net.connect(Native Method)\n        at sun.nio.ch.SocketChannelImpl.connect(SocketChannelImpl.java:491)\n        at org.eclipse.hyades.internal.execution.core.file.socket.SocketChannelFactory.create(SocketChannelFactory.java:78)\n        at org.eclipse.hyades.internal.execution.core.file.socket.SocketChannelFactory.create(SocketChannelFactory.java:63)\n        at org.eclipse.hyades.internal.execution.core.file.dynamic.FileServerCommandFactory.connectSocketChannel(FileServerCommandFactory.java:300)\n        at org.eclipse.hyades.internal.execution.core.file.dynamic.FileServerCommandFactory.connectSocketChannel(FileServerCommandFactory.java:269)\n        at org.eclipse.hyades.internal.execution.core.file.dynamic.FileServerCommandFactory.createDetermineServerReachCommand(FileServerCommandFactory.java:402)        at org.eclipse.hyades.execution.local.file.FileManagerExtendedImpl.determineServerReach(FileManagerExtendedImpl.java:683)\n        at org.eclipse.hyades.internal.execution.local.common.Console.run(Console.java:181)\norg.eclipse.hyades.execution.core.DaemonConnectException\n        at org.eclipse.hyades.execution.local.NodeImpl._connect(NodeImpl.java:225)\n        at org.eclipse.hyades.execution.local.NodeImpl.connect(NodeImpl.java:359)\n        at org.eclipse.hyades.execution.local.NodeImpl.connect(NodeImpl.java:347)\n        at org.eclipse.hyades.execution.harness.TestExecutionHarness$4.run(TestExecutionHarness.java:2433)\n        at java.lang.Thread.run(Thread.java:803)\nCaused by: org.eclipse.hyades.internal.execution.local.control.InactiveProcessException\n        at org.eclipse.hyades.internal.execution.local.control.ProcessImpl.getProcessId(ProcessImpl.java:487)\n        at org.eclipse.hyades.execution.local.NodeImpl._connect(NodeImpl.java:220)\n        ... 4 more\n\nOS:\n\nLinux paules 2.6.16.27-0.9-smp #1 SMP Tue Feb 13 09:35:18 UTC 2007 x86_64 x86_64 x86_64 GNU/Linux\n\nJRE:\n\njava version \"1.5.0\"\nJava(TM) 2 Runtime Environment, Standard Edition (build pxi32dev-20070201 (SR4))IBM J9 VM (build 2.3, J2RE 1.5.0 IBM J9 2.3 Linux x86-32 j9vmxi3223-20070201 (JIT enabled)\nJ9VM - 20070131_11312_lHdSMR\nJIT  - 20070109_1805ifx1_r8\nGC   - 200701_09)\nJCL  - 20070126\n\nLauching the test again works fine.\n\nNote: I am keeping the severity as normal since I can not consistently reproduce this defect.",
    "There is no firewall running on either machine.",
    "Hi Bing. I have transferred my bugs to you for triage. Thanks."
  ],
  "commentCreationDates": [
    "2007-05-25T18:49:38+02:00",
    "2007-05-25T18:50:24+02:00",
    "2007-11-27T14:33:22+01:00"
  ],
  "traces": [
    {
      "exceptionType": "java.net.ConnectException",
      "message": "Connection refused",
      "elements": [
        {
          "method": "sun.nio.ch.Net.connect",
          "source": "Native Method"
        },
        {
          "method": "sun.nio.ch.SocketChannelImpl.connect",
          "source": "SocketChannelImpl.java:491"
        },
        {
          "method": "org.eclipse.hyades.internal.execution.core.file.socket.SocketChannelFactory.create",
          "source": "SocketChannelFactory.java:78"
        },
        {
          "method": "org.eclipse.hyades.internal.execution.core.file.socket.SocketChannelFactory.create",
          "source": "SocketChannelFactory.java:63"
        },
        {
          "method": "org.eclipse.hyades.internal.execution.core.file.dynamic.FileServerCommandFactory.connectSocketChannel",
          "source": "FileServerCommandFactory.java:300"
        },
        {
          "method": "org.eclipse.hyades.internal.execution.core.file.dynamic.FileServerCommandFactory.connectSocketChannel",
          "source": "FileServerCommandFactory.java:269"
        },
        {
          "method": "org.eclipse.hyades.internal.execution.core.file.dynamic.FileServerCommandFactory.createDetermineServerReachCommand",
          "source": "FileServerCommandFactory.java:402"
        },
        {
          "method": "org.eclipse.hyades.execution.local.file.FileManagerExtendedImpl.determineServerReach",
          "source": "FileManagerExtendedImpl.java:683"
        },
        {
          "method": "org.eclipse.hyades.internal.execution.local.common.Console.run",
          "source": "Console.java:181"
        }
      ],
      "number": 0,
      "commentIndex": 0,
      "bugId": "189175",
      "date": "2007-05-25T18:49:38+02:00",
      "product": "TPTP Agent Controller",
      "component": "Platform.Execution.Framework",
      "severity": "normal"
    },
    {
      "exceptionType": "org.eclipse.hyades.execution.core.DaemonConnectException",
      "elements": [
        {
          "method": "org.eclipse.hyades.execution.local.NodeImpl._connect",
          "source": "NodeImpl.java:225"
        },
        {
          "method": "org.eclipse.hyades.execution.local.NodeImpl.connect",
          "source": "NodeImpl.java:359"
        },
        {
          "method": "org.eclipse.hyades.execution.local.NodeImpl.connect",
          "source": "NodeImpl.java:347"
        },
        {
          "method": "org.eclipse.hyades.execution.harness.TestExecutionHarness$4.run",
          "source": "TestExecutionHarness.java:2433"
        },
        {
          "method": "java.lang.Thread.run",
          "source": "Thread.java:803"
        }
      ],
      "causedBy": {
        "exceptionType": "org.eclipse.hyades.internal.execution.local.control.InactiveProcessException",
        "elements": [
          {
            "method": "org.eclipse.hyades.internal.execution.local.control.ProcessImpl.getProcessId",
            "source": "ProcessImpl.java:487"
          },
          {
            "method": "org.eclipse.hyades.execution.local.NodeImpl._connect",
            "source": "NodeImpl.java:220"
          }
        ],
        "number": 0,
        "commentIndex": 0
      },
      "number": 1,
      "commentIndex": 0,
      "bugId": "189175",
      "date": "2007-05-25T18:49:38+02:00",
      "product": "TPTP Agent Controller",
      "component": "Platform.Execution.Framework",
      "severity": "normal"
    }
  ],
  "groupId": "189175",
  "bugId": "189175",
  "date": "2007-05-25T18:49:38+02:00",
  "product": "TPTP Agent Controller",
  "component": "Platform.Execution.Framework",
  "severity": "normal"
}