{
  "comments": [
    "F2 build, A3.2 test Clicking on \"Class\" scrolls editor up.  Only the next click \non \"Class\" opens editor, but error appear in the console:\nUnhandled exception caught in event loop.\nReason:\nWidget is disposed\n\n\nThe log:\n!SESSION Jun 04, 2002 18:38:30.317 ---------------------------------------------\njava.version\u003d1.3.1_01\njava.vendor\u003dSun Microsystems Inc.\nBootLoader constants: OS\u003dsolaris, ARCH\u003dsparc, WS\u003dmotif, NL\u003den_US\nCommand-line arguments: -os solaris -ws motif -arch sparc -install \nfile:/export/home/\neclipse/eclipse/\n!ENTRY org.eclipse.core.resources 1 1 Jun 04, 2002 18:38:30.319\n!MESSAGE Could not load library: libcore_2_0_5.so.  This library provides \nplatform-sp\necific optimizations for certain file-system operations.  This library is not \npresent\n on all platforms, so this may not be an error.  The resources plugin will \nsafely fal\nl back to using java.io.File functionality.\n!ENTRY org.eclipse.ui 4 4 Jun 04, 2002 18:39:57.240\n!MESSAGE Unhandled exception caught in event loop.\n!ENTRY org.eclipse.ui 4 0 Jun 04, 2002 18:39:57.251\n!MESSAGE Widget is disposed\n!STACK 0\norg.eclipse.swt.SWTException: Widget is disposed\n        at org.eclipse.swt.SWT.error(SWT.java:1887)\n        at org.eclipse.swt.SWT.error(SWT.java:1819)\n        at org.eclipse.swt.widgets.Widget.error(Widget.java:283)\n        at org.eclipse.swt.widgets.MenuItem.getDisplay(MenuItem.java:278)\n        at org.eclipse.swt.widgets.Widget.isValidThread(Widget.java:442)\n        at org.eclipse.swt.widgets.Widget.checkWidget(Widget.java:221)\n        at org.eclipse.swt.widgets.MenuItem.setText(MenuItem.java:700)\n        at org.eclipse.jface.action.MenuManager.fill(MenuManager.java:176)\n        at org.eclipse.jface.action.SubContributionItem.fill\n(SubContributionItem.java\n:45)\n        at org.eclipse.jface.action.MenuManager.update(MenuManager.java:528)\n        at org.eclipse.jface.action.MenuManager.updateAll(MenuManager.java:575)\n        at org.eclipse.ui.internal.WorkbenchWindow.updateActionBars\n(WorkbenchWindow.j\nava:1357)\n        at org.eclipse.ui.internal.WorkbenchWindow.updateActionSets\n(WorkbenchWindow.j\nava:1375)\n        at org.eclipse.ui.internal.WorkbenchPage$ActionSwitcher.updateActionSets\n(Work\nbenchPage.java:272)\n        at org.eclipse.ui.internal.WorkbenchPage$ActionSwitcher.updateTopEditor\n(Workb\nenchPage.java:178)\n        at org.eclipse.ui.internal.WorkbenchPage.bringToTop\n(WorkbenchPage.java:448)\n        at org.eclipse.ui.internal.WorkbenchPage.activate\n(WorkbenchPage.java:329)\n        at org.eclipse.ui.internal.WorkbenchPage.openEditor\n(WorkbenchPage.java:1686)\n        at org.eclipse.ui.internal.WorkbenchPage.openEditor\n(WorkbenchPage.java:1582)\n        at org.eclipse.jdt.internal.ui.javaeditor.EditorUtility.openInEditor\n(EditorUt\nility.java:126)\n        at org.eclipse.jdt.internal.ui.javaeditor.EditorUtility.openInEditor\n(EditorUt\nility.java:104)\n        at org.eclipse.jdt.internal.ui.javaeditor.EditorUtility.openInEditor\n(EditorUt\nility.java:89)\n        at org.eclipse.jdt.ui.JavaUI.openInEditor(JavaUI.java:453)\n        at \norg.eclipse.pde.internal.ui.editor.manifest.PluginSpecSection.handleOpen(P\nluginSpecSection.java:297)\n        at \norg.eclipse.pde.internal.ui.editor.manifest.PluginSpecSection.access$1(Plu\nginSpecSection.java:282)\n        at \norg.eclipse.pde.internal.ui.editor.manifest.PluginSpecSection$8.linkActiva\nted(PluginSpecSection.java:239)\n        at org.eclipse.update.ui.forms.internal.HyperlinkHandler.linkActivated\n(Hyperl\ninkHandler.java:98)\n        at org.eclipse.update.ui.forms.internal.HyperlinkHandler.mouseUp\n(HyperlinkHan\ndler.java:76)\n        at org.eclipse.swt.widgets.TypedListener.handleEvent\n(TypedListener.java:128)\n        at org.eclipse.swt.widgets.EventTable.sendEvent(EventTable.java:75)\n        at org.eclipse.swt.widgets.Widget.sendEvent(Widget.java:789)\n        at org.eclipse.swt.widgets.Display.runDeferredEvents(Display.java:1678)\n        at org.eclipse.swt.widgets.Display.readAndDispatch(Display.java:1501)\n        at org.eclipse.ui.internal.Workbench.runEventLoop(Workbench.java:1177)\n        at org.eclipse.ui.internal.Workbench.run(Workbench.java:1160)\n        at org.eclipse.core.internal.boot.InternalBootLoader.run\n(InternalBootLoader.j\nava:739)\n        at org.eclipse.core.boot.BootLoader.run(BootLoader.java:462)\n        at java.lang.reflect.Method.invoke(Native Method)\n        at org.eclipse.core.launcher.Main.basicRun(Main.java:244)\n        at org.eclipse.core.launcher.Main.run(Main.java:693)\n        at org.eclipse.core.launcher.Main.main(Main.java:526)\n!ENTRY org.eclipse.ui 4 4 Jun 04, 2002 18:40:11.313\n!MESSAGE Unhandled exception caught in event loop.\n!ENTRY org.eclipse.ui 4 0 Jun 04, 2002 18:40:11.320\n!MESSAGE Widget is disposed\n!STACK 0\norg.eclipse.swt.SWTException: Widget is disposed\n        at org.eclipse.swt.SWT.error(SWT.java:1887)\n        at org.eclipse.swt.SWT.error(SWT.java:1819)\n        at org.eclipse.swt.widgets.Widget.error(Widget.java:283)\n        at org.eclipse.swt.widgets.MenuItem.getDisplay(MenuItem.java:278)\n        at org.eclipse.swt.widgets.Widget.isValidThread(Widget.java:442)\n        at org.eclipse.swt.widgets.Widget.checkWidget(Widget.java:221)\n        at org.eclipse.swt.widgets.MenuItem.setText(MenuItem.java:700)\n        at org.eclipse.jface.action.MenuManager.fill(MenuManager.java:176)\n        at org.eclipse.jface.action.SubContributionItem.fill\n(SubContributionItem.java\n:45)\n        at org.eclipse.jface.action.MenuManager.update(MenuManager.java:528)\n        at org.eclipse.jface.action.MenuManager.updateAll(MenuManager.java:575)\n        at org.eclipse.ui.internal.WorkbenchWindow.updateActionBars\n(WorkbenchWindow.j\nava:1357)\n        at org.eclipse.ui.internal.WorkbenchWindow.updateActionSets\n(WorkbenchWindow.j\nava:1375)\n        at org.eclipse.ui.internal.WorkbenchPage$ActionSwitcher.updateActionSets\n(Work\nbenchPage.java:272)\n        at org.eclipse.ui.internal.WorkbenchPage$ActionSwitcher.updateTopEditor\n(Workb\nenchPage.java:178)\n        at org.eclipse.ui.internal.WorkbenchPage.bringToTop\n(WorkbenchPage.java:448)\n        at org.eclipse.ui.internal.WorkbenchPage.activate\n(WorkbenchPage.java:329)\n        at org.eclipse.ui.internal.WorkbenchPage.openEditor\n(WorkbenchPage.java:1651)\n        at org.eclipse.ui.internal.WorkbenchPage.openEditor\n(WorkbenchPage.java:1582)\n        at org.eclipse.jdt.internal.ui.javaeditor.EditorUtility.openInEditor\n(EditorUt\nility.java:126)\n        at org.eclipse.jdt.internal.ui.javaeditor.EditorUtility.openInEditor\n(EditorUt\nility.java:104)\n        at org.eclipse.jdt.internal.ui.javaeditor.EditorUtility.openInEditor\n(EditorUt\nility.java:89)\n        at org.eclipse.jdt.ui.JavaUI.openInEditor(JavaUI.java:453)\n        at \norg.eclipse.pde.internal.ui.editor.manifest.PluginSpecSection.handleOpen(P\nluginSpecSection.java:297)\n        at \norg.eclipse.pde.internal.ui.editor.manifest.PluginSpecSection.access$1(Plu\nginSpecSection.java:282)\n        at \norg.eclipse.pde.internal.ui.editor.manifest.PluginSpecSection$8.linkActiva\n        at org.eclipse.ui.internal.WorkbenchPage$ActionSwitcher.updateActionSets\n(Work\nbenchPage.java:272)\n        at org.eclipse.ui.internal.WorkbenchPage$ActionSwitcher.updateTopEditor\n(Workb\nenchPage.java:178)\n        at org.eclipse.ui.internal.WorkbenchPage.bringToTop\n(WorkbenchPage.java:448)\n        at org.eclipse.ui.internal.WorkbenchPage.activate\n(WorkbenchPage.java:329)\n        at org.eclipse.ui.internal.WorkbenchPage.openEditor\n(WorkbenchPage.java:1651)\n        at org.eclipse.ui.internal.WorkbenchPage.openEditor\n(WorkbenchPage.java:1582)\n        at org.eclipse.jdt.internal.ui.javaeditor.EditorUtility.openInEditor\n(EditorUt\nility.java:126)\n        at org.eclipse.jdt.internal.ui.javaeditor.EditorUtility.openInEditor\n(EditorUt\nility.java:104)\n        at org.eclipse.jdt.internal.ui.javaeditor.EditorUtility.openInEditor\n(EditorUt\nility.java:89)\n        at org.eclipse.jdt.ui.JavaUI.openInEditor(JavaUI.java:453)\n        at \norg.eclipse.pde.internal.ui.editor.manifest.PluginSpecSection.handleOpen(P\nluginSpecSection.java:297)\n        at \norg.eclipse.pde.internal.ui.editor.manifest.PluginSpecSection.access$1(Plu\nginSpecSection.java:282)\n        at \norg.eclipse.pde.internal.ui.editor.manifest.PluginSpecSection$8.linkActiva\nted(PluginSpecSection.java:239)\n        at org.eclipse.update.ui.forms.internal.HyperlinkHandler.linkActivated\n(Hyperl\ninkHandler.java:98)\n        at org.eclipse.update.ui.forms.internal.HyperlinkHandler.mouseUp\n(HyperlinkHan\ndler.java:76)\n        at org.eclipse.swt.widgets.TypedListener.handleEvent\n(TypedListener.java:128)\n        at org.eclipse.swt.widgets.EventTable.sendEvent(EventTable.java:75)\n        at org.eclipse.swt.widgets.Widget.sendEvent(Widget.java:789)\n        at org.eclipse.swt.widgets.Display.runDeferredEvents(Display.java:1678)\n        at org.eclipse.swt.widgets.Display.readAndDispatch(Display.java:1501)\n        at org.eclipse.ui.internal.Workbench.runEventLoop(Workbench.java:1177)\n        at org.eclipse.ui.internal.Workbench.run(Workbench.java:1160)\n        at org.eclipse.core.internal.boot.InternalBootLoader.run\n(InternalBootLoader.j\nava:739)\n        at org.eclipse.core.boot.BootLoader.run(BootLoader.java:462)\n        at java.lang.reflect.Method.invoke(Native Method)\n        at org.eclipse.core.launcher.Main.basicRun(Main.java:244)\n        at org.eclipse.core.launcher.Main.run(Main.java:693)\n        at org.eclipse.core.launcher.Main.main(Main.java:526)",
    "Clicking on \"More\" in the Runtime libary section also scrolls.  My more button \nwas fully visible, only the title of the section was partially hidden.  It \nscrolled (escaped from under my mouse) quite a big distance, such that Runtime \nsection appeared in the middle of the editor (verticaly).  I do not think, the \nscrolling is needed at all for the buttons, as clicking these buttons is taking \nme to another editor or page.",
    "Scrolling is needed when focus moves to the control that is currently not \nshowing in the scrolled composite. The support should scroll the client to \nreveal the control in focus. That means that controls that are already visible \nshould be left alone, which is clearly not the case. We know about the problem \nin the \u0027reveal\u0027 method and are trying to fix.",
    "\n\n*** This bug has been marked as a duplicate of 17873 ***"
  ],
  "commentCreationDates": [
    "2002-06-04T16:41:03+02:00",
    "2002-06-04T16:48:09+02:00",
    "2002-06-04T17:33:11+02:00",
    "2002-06-05T16:09:14+02:00"
  ],
  "traces": [
    {
      "exceptionType": "org.eclipse.swt.SWTException",
      "message": "Widget is disposed",
      "elements": [
        {
          "method": "org.eclipse.swt.SWT.error",
          "source": "SWT.java:1887"
        },
        {
          "method": "org.eclipse.swt.SWT.error",
          "source": "SWT.java:1819"
        },
        {
          "method": "org.eclipse.swt.widgets.Widget.error",
          "source": "Widget.java:283"
        },
        {
          "method": "org.eclipse.swt.widgets.MenuItem.getDisplay",
          "source": "MenuItem.java:278"
        },
        {
          "method": "org.eclipse.swt.widgets.Widget.isValidThread",
          "source": "Widget.java:442"
        },
        {
          "method": "org.eclipse.swt.widgets.Widget.checkWidget",
          "source": "Widget.java:221"
        },
        {
          "method": "org.eclipse.swt.widgets.MenuItem.setText",
          "source": "MenuItem.java:700"
        },
        {
          "method": "org.eclipse.jface.action.MenuManager.fill",
          "source": "MenuManager.java:176"
        },
        {
          "method": "org.eclipse.jface.action.SubContributionItem.fill",
          "source": "SubContributionItem.java :45"
        },
        {
          "method": "org.eclipse.jface.action.MenuManager.update",
          "source": "MenuManager.java:528"
        },
        {
          "method": "org.eclipse.jface.action.MenuManager.updateAll",
          "source": "MenuManager.java:575"
        },
        {
          "method": "org.eclipse.ui.internal.WorkbenchWindow.updateActionBars",
          "source": "WorkbenchWindow.j ava:1357"
        },
        {
          "method": "org.eclipse.ui.internal.WorkbenchWindow.updateActionSets",
          "source": "WorkbenchWindow.j ava:1375"
        },
        {
          "method": "org.eclipse.ui.internal.WorkbenchPage$ActionSwitcher.updateActionSets",
          "source": "Work benchPage.java:272"
        },
        {
          "method": "org.eclipse.ui.internal.WorkbenchPage$ActionSwitcher.updateTopEditor",
          "source": "Workb enchPage.java:178"
        },
        {
          "method": "org.eclipse.ui.internal.WorkbenchPage.bringToTop",
          "source": "WorkbenchPage.java:448"
        },
        {
          "method": "org.eclipse.ui.internal.WorkbenchPage.activate",
          "source": "WorkbenchPage.java:329"
        },
        {
          "method": "org.eclipse.ui.internal.WorkbenchPage.openEditor",
          "source": "WorkbenchPage.java:1686"
        },
        {
          "method": "org.eclipse.ui.internal.WorkbenchPage.openEditor",
          "source": "WorkbenchPage.java:1582"
        },
        {
          "method": "org.eclipse.jdt.internal.ui.javaeditor.EditorUtility.openInEditor",
          "source": "EditorUt ility.java:126"
        },
        {
          "method": "org.eclipse.jdt.internal.ui.javaeditor.EditorUtility.openInEditor",
          "source": "EditorUt ility.java:104"
        },
        {
          "method": "org.eclipse.jdt.internal.ui.javaeditor.EditorUtility.openInEditor",
          "source": "EditorUt ility.java:89"
        },
        {
          "method": "org.eclipse.jdt.ui.JavaUI.openInEditor",
          "source": "JavaUI.java:453"
        },
        {
          "method": "org.eclipse.pde.internal.ui.editor.manifest.PluginSpecSection.handleOpen",
          "source": "P luginSpecSection.java:297"
        },
        {
          "method": "org.eclipse.pde.internal.ui.editor.manifest.PluginSpecSection.access$1",
          "source": "Plu ginSpecSection.java:282"
        },
        {
          "method": "org.eclipse.pde.internal.ui.editor.manifest.PluginSpecSection$8.linkActivated",
          "source": "PluginSpecSection.java:239"
        },
        {
          "method": "org.eclipse.update.ui.forms.internal.HyperlinkHandler.linkActivated",
          "source": "Hyperl inkHandler.java:98"
        },
        {
          "method": "org.eclipse.update.ui.forms.internal.HyperlinkHandler.mouseUp",
          "source": "HyperlinkHan dler.java:76"
        },
        {
          "method": "org.eclipse.swt.widgets.TypedListener.handleEvent",
          "source": "TypedListener.java:128"
        },
        {
          "method": "org.eclipse.swt.widgets.EventTable.sendEvent",
          "source": "EventTable.java:75"
        },
        {
          "method": "org.eclipse.swt.widgets.Widget.sendEvent",
          "source": "Widget.java:789"
        },
        {
          "method": "org.eclipse.swt.widgets.Display.runDeferredEvents",
          "source": "Display.java:1678"
        },
        {
          "method": "org.eclipse.swt.widgets.Display.readAndDispatch",
          "source": "Display.java:1501"
        },
        {
          "method": "org.eclipse.ui.internal.Workbench.runEventLoop",
          "source": "Workbench.java:1177"
        },
        {
          "method": "org.eclipse.ui.internal.Workbench.run",
          "source": "Workbench.java:1160"
        },
        {
          "method": "org.eclipse.core.internal.boot.InternalBootLoader.run",
          "source": "InternalBootLoader.j ava:739"
        },
        {
          "method": "org.eclipse.core.boot.BootLoader.run",
          "source": "BootLoader.java:462"
        },
        {
          "method": "java.lang.reflect.Method.invoke",
          "source": "Native Method"
        },
        {
          "method": "org.eclipse.core.launcher.Main.basicRun",
          "source": "Main.java:244"
        },
        {
          "method": "org.eclipse.core.launcher.Main.run",
          "source": "Main.java:693"
        },
        {
          "method": "org.eclipse.core.launcher.Main.main",
          "source": "Main.java:526"
        }
      ],
      "number": 0,
      "commentIndex": 0,
      "bugId": "19072",
      "duplicateId": "17873",
      "date": "2002-06-04T16:41:03+02:00",
      "product": "PDE",
      "component": "UI",
      "severity": "normal"
    },
    {
      "exceptionType": "org.eclipse.swt.SWTException",
      "message": "Widget is disposed",
      "elements": [
        {
          "method": "org.eclipse.swt.SWT.error",
          "source": "SWT.java:1887"
        },
        {
          "method": "org.eclipse.swt.SWT.error",
          "source": "SWT.java:1819"
        },
        {
          "method": "org.eclipse.swt.widgets.Widget.error",
          "source": "Widget.java:283"
        },
        {
          "method": "org.eclipse.swt.widgets.MenuItem.getDisplay",
          "source": "MenuItem.java:278"
        },
        {
          "method": "org.eclipse.swt.widgets.Widget.isValidThread",
          "source": "Widget.java:442"
        },
        {
          "method": "org.eclipse.swt.widgets.Widget.checkWidget",
          "source": "Widget.java:221"
        },
        {
          "method": "org.eclipse.swt.widgets.MenuItem.setText",
          "source": "MenuItem.java:700"
        },
        {
          "method": "org.eclipse.jface.action.MenuManager.fill",
          "source": "MenuManager.java:176"
        },
        {
          "method": "org.eclipse.jface.action.SubContributionItem.fill",
          "source": "SubContributionItem.java :45"
        },
        {
          "method": "org.eclipse.jface.action.MenuManager.update",
          "source": "MenuManager.java:528"
        },
        {
          "method": "org.eclipse.jface.action.MenuManager.updateAll",
          "source": "MenuManager.java:575"
        },
        {
          "method": "org.eclipse.ui.internal.WorkbenchWindow.updateActionBars",
          "source": "WorkbenchWindow.j ava:1357"
        },
        {
          "method": "org.eclipse.ui.internal.WorkbenchWindow.updateActionSets",
          "source": "WorkbenchWindow.j ava:1375"
        },
        {
          "method": "org.eclipse.ui.internal.WorkbenchPage$ActionSwitcher.updateActionSets",
          "source": "Work benchPage.java:272"
        },
        {
          "method": "org.eclipse.ui.internal.WorkbenchPage$ActionSwitcher.updateTopEditor",
          "source": "Workb enchPage.java:178"
        },
        {
          "method": "org.eclipse.ui.internal.WorkbenchPage.bringToTop",
          "source": "WorkbenchPage.java:448"
        },
        {
          "method": "org.eclipse.ui.internal.WorkbenchPage.activate",
          "source": "WorkbenchPage.java:329"
        },
        {
          "method": "org.eclipse.ui.internal.WorkbenchPage.openEditor",
          "source": "WorkbenchPage.java:1651"
        },
        {
          "method": "org.eclipse.ui.internal.WorkbenchPage.openEditor",
          "source": "WorkbenchPage.java:1582"
        },
        {
          "method": "org.eclipse.jdt.internal.ui.javaeditor.EditorUtility.openInEditor",
          "source": "EditorUt ility.java:126"
        },
        {
          "method": "org.eclipse.jdt.internal.ui.javaeditor.EditorUtility.openInEditor",
          "source": "EditorUt ility.java:104"
        },
        {
          "method": "org.eclipse.jdt.internal.ui.javaeditor.EditorUtility.openInEditor",
          "source": "EditorUt ility.java:89"
        },
        {
          "method": "org.eclipse.jdt.ui.JavaUI.openInEditor",
          "source": "JavaUI.java:453"
        },
        {
          "method": "org.eclipse.pde.internal.ui.editor.manifest.PluginSpecSection.handleOpen",
          "source": "P luginSpecSection.java:297"
        },
        {
          "method": "org.eclipse.pde.internal.ui.editor.manifest.PluginSpecSection.access$1",
          "source": "Plu ginSpecSection.java:282"
        },
        {
          "method": "org.eclipse.pde.internal.ui.editor.manifest.PluginSpecSection$8.linkActivaatorg.eclipse.ui.internal.WorkbenchPage$ActionSwitcher.updateActionSets",
          "source": "Work benchPage.java:272"
        },
        {
          "method": "org.eclipse.ui.internal.WorkbenchPage$ActionSwitcher.updateTopEditor",
          "source": "Workb enchPage.java:178"
        },
        {
          "method": "org.eclipse.ui.internal.WorkbenchPage.bringToTop",
          "source": "WorkbenchPage.java:448"
        },
        {
          "method": "org.eclipse.ui.internal.WorkbenchPage.activate",
          "source": "WorkbenchPage.java:329"
        },
        {
          "method": "org.eclipse.ui.internal.WorkbenchPage.openEditor",
          "source": "WorkbenchPage.java:1651"
        },
        {
          "method": "org.eclipse.ui.internal.WorkbenchPage.openEditor",
          "source": "WorkbenchPage.java:1582"
        },
        {
          "method": "org.eclipse.jdt.internal.ui.javaeditor.EditorUtility.openInEditor",
          "source": "EditorUt ility.java:126"
        },
        {
          "method": "org.eclipse.jdt.internal.ui.javaeditor.EditorUtility.openInEditor",
          "source": "EditorUt ility.java:104"
        },
        {
          "method": "org.eclipse.jdt.internal.ui.javaeditor.EditorUtility.openInEditor",
          "source": "EditorUt ility.java:89"
        },
        {
          "method": "org.eclipse.jdt.ui.JavaUI.openInEditor",
          "source": "JavaUI.java:453"
        },
        {
          "method": "org.eclipse.pde.internal.ui.editor.manifest.PluginSpecSection.handleOpen",
          "source": "P luginSpecSection.java:297"
        },
        {
          "method": "org.eclipse.pde.internal.ui.editor.manifest.PluginSpecSection.access$1",
          "source": "Plu ginSpecSection.java:282"
        },
        {
          "method": "org.eclipse.pde.internal.ui.editor.manifest.PluginSpecSection$8.linkActivated",
          "source": "PluginSpecSection.java:239"
        },
        {
          "method": "org.eclipse.update.ui.forms.internal.HyperlinkHandler.linkActivated",
          "source": "Hyperl inkHandler.java:98"
        },
        {
          "method": "org.eclipse.update.ui.forms.internal.HyperlinkHandler.mouseUp",
          "source": "HyperlinkHan dler.java:76"
        },
        {
          "method": "org.eclipse.swt.widgets.TypedListener.handleEvent",
          "source": "TypedListener.java:128"
        },
        {
          "method": "org.eclipse.swt.widgets.EventTable.sendEvent",
          "source": "EventTable.java:75"
        },
        {
          "method": "org.eclipse.swt.widgets.Widget.sendEvent",
          "source": "Widget.java:789"
        },
        {
          "method": "org.eclipse.swt.widgets.Display.runDeferredEvents",
          "source": "Display.java:1678"
        },
        {
          "method": "org.eclipse.swt.widgets.Display.readAndDispatch",
          "source": "Display.java:1501"
        },
        {
          "method": "org.eclipse.ui.internal.Workbench.runEventLoop",
          "source": "Workbench.java:1177"
        },
        {
          "method": "org.eclipse.ui.internal.Workbench.run",
          "source": "Workbench.java:1160"
        },
        {
          "method": "org.eclipse.core.internal.boot.InternalBootLoader.run",
          "source": "InternalBootLoader.j ava:739"
        },
        {
          "method": "org.eclipse.core.boot.BootLoader.run",
          "source": "BootLoader.java:462"
        },
        {
          "method": "java.lang.reflect.Method.invoke",
          "source": "Native Method"
        },
        {
          "method": "org.eclipse.core.launcher.Main.basicRun",
          "source": "Main.java:244"
        },
        {
          "method": "org.eclipse.core.launcher.Main.run",
          "source": "Main.java:693"
        },
        {
          "method": "org.eclipse.core.launcher.Main.main",
          "source": "Main.java:526"
        }
      ],
      "number": 1,
      "commentIndex": 0,
      "bugId": "19072",
      "duplicateId": "17873",
      "date": "2002-06-04T16:41:03+02:00",
      "product": "PDE",
      "component": "UI",
      "severity": "normal"
    }
  ],
  "groupId": "17873",
  "bugId": "19072",
  "duplicateId": "17873",
  "date": "2002-06-04T16:41:03+02:00",
  "product": "PDE",
  "component": "UI",
  "severity": "normal"
}