{
  "comments": [
    "I20070606-0010\n\nI got the following already twice today in I20070606-0010 when starting my develop workspace (64 Java projects in the workspace):\n\n!ENTRY org.eclipse.osgi 2 0 2007-06-06 10:27:40.534\n!MESSAGE While loading class \"org.eclipse.jdt.internal.ui.InitializeAfterLoadJob$RealJob\", \nthread \"Thread[main,6,main]\" timed out waiting (5000ms) for thread \"Thread[Worker-3,5,main]\" to finish starting bundle \"update@plugins/org.eclipse.jdt.ui_3.3.0.v20070606-0010.jar [102]\". \nTo avoid deadlock, thread \"Thread[main,6,main]\" is proceeding but \"org.eclipse.jdt.internal.ui.InitializeAfterLoadJob$RealJob\" may not be fully initialized.\n\n!STACK 0\norg.osgi.framework.BundleException: State change in progress for bundle \"update@plugins/org.eclipse.jdt.ui_3.3.0.v20070606-0010.jar\" by thread \"Worker\n-3\".\n        at org.eclipse.osgi.framework.internal.core.AbstractBundle.beginStateChange(AbstractBundle.java:1141)\n        at org.eclipse.osgi.framework.internal.core.AbstractBundle.start(AbstractBundle.java:258)\n        at org.eclipse.osgi.framework.util.SecureAction.start(SecureAction.java:400)\n        at org.eclipse.core.runtime.internal.adaptor.EclipseLazyStarter.postFindLocalClass(EclipseLazyStarter.java:111)\n        at org.eclipse.osgi.baseadaptor.loader.ClasspathManager.findLocalClass(ClasspathManager.java:417)\n        at org.eclipse.osgi.internal.baseadaptor.DefaultClassLoader.findLocalClass(DefaultClassLoader.java:189)\n        at org.eclipse.osgi.framework.internal.core.BundleLoader.findLocalClass(BundleLoader.java:340)\n        at org.eclipse.osgi.framework.internal.core.BundleLoader.findClassInternal(BundleLoader.java:408)\n        at org.eclipse.osgi.framework.internal.core.BundleLoader.findClass(BundleLoader.java:369)\n        at org.eclipse.osgi.framework.internal.core.BundleLoader.findClass(BundleLoader.java:357)\n        at org.eclipse.osgi.internal.baseadaptor.DefaultClassLoader.loadClass(DefaultClassLoader.java:83)\n        at java.lang.ClassLoader.loadClass(ClassLoader.java:251)\n        at java.lang.ClassLoader.loadClassInternal(ClassLoader.java:319)\n        at org.eclipse.jdt.internal.ui.InitializeAfterLoadJob.runInUIThread(InitializeAfterLoadJob.java:53)\n        at org.eclipse.ui.progress.UIJob$1.run(UIJob.java:94)\n        at org.eclipse.swt.widgets.RunnableLock.run(RunnableLock.java:35)\n        at org.eclipse.swt.widgets.Synchronizer.runAsyncMessages(Synchronizer.java:123)\n        at org.eclipse.swt.widgets.Display.runAsyncMessages(Display.java:3659)\n        at org.eclipse.swt.widgets.Display.readAndDispatch(Display.java:3296)\n        at org.eclipse.ui.internal.Workbench.runEventLoop(Workbench.java:2389)\n        at org.eclipse.ui.internal.Workbench.runUI(Workbench.java:2353)\n        at org.eclipse.ui.internal.Workbench.access$4(Workbench.java:2219)\n        at org.eclipse.ui.internal.Workbench$4.run(Workbench.java:466)\n        at org.eclipse.core.databinding.observable.Realm.runWithDefault(Realm.java:289)\n        at org.eclipse.ui.internal.Workbench.createAndRunWorkbench(Workbench.java:461)\n        at org.eclipse.ui.PlatformUI.createAndRunWorkbench(PlatformUI.java:149)\n        at org.eclipse.ui.internal.ide.application.IDEApplication.start(IDEApplication.java:106)\n        at org.eclipse.equinox.internal.app.EclipseAppHandle.run(EclipseAppHandle.java:153)\n        at org.eclipse.core.runtime.internal.adaptor.EclipseAppLauncher.runApplication(EclipseAppLauncher.java:106)\n        at org.eclipse.core.runtime.internal.adaptor.EclipseAppLauncher.start(EclipseAppLauncher.java:76)\n        at org.eclipse.core.runtime.adaptor.EclipseStarter.run(EclipseStarter.java:363)\n        at org.eclipse.core.runtime.adaptor.EclipseStarter.run(EclipseStarter.java:176)\n        at sun.reflect.NativeMethodAccessorImpl.invoke0(Native Method)\n        at sun.reflect.NativeMethodAccessorImpl.invoke(NativeMethodAccessorImpl.java:39)\n        at sun.reflect.DelegatingMethodAccessorImpl.invoke(DelegatingMethodAccessorImpl.java:25)\n        at java.lang.reflect.Method.invoke(Method.java:597)\n        at org.eclipse.equinox.launcher.Main.invokeFramework(Main.java:504)\n        at org.eclipse.equinox.launcher.Main.basicRun(Main.java:443)\n        at org.eclipse.equinox.launcher.Main.run(Main.java:1169)\n        at org.eclipse.equinox.launcher.Main.main(Main.java:1144)\n        at org.eclipse.core.launcher.Main.main(Main.java:30)\nCaused by: org.eclipse.osgi.framework.internal.core.AbstractBundle$BundleStatusException\n        ... 41 more\nRoot exception:\norg.eclipse.osgi.framework.internal.core.AbstractBundle$BundleStatusException\n        at org.eclipse.osgi.framework.internal.core.AbstractBundle.beginStateChange(AbstractBundle.java:1141)\n        at org.eclipse.osgi.framework.internal.core.AbstractBundle.start(AbstractBundle.java:258)\n        at org.eclipse.osgi.framework.util.SecureAction.start(SecureAction.java:400)\n        at org.eclipse.core.runtime.internal.adaptor.EclipseLazyStarter.postFindLocalClass(EclipseLazyStarter.java:111)\n        at org.eclipse.osgi.baseadaptor.loader.ClasspathManager.findLocalClass(ClasspathManager.java:417)\n        at org.eclipse.osgi.internal.baseadaptor.DefaultClassLoader.findLocalClass(DefaultClassLoader.java:189)\n        at org.eclipse.osgi.framework.internal.core.BundleLoader.findLocalClass(BundleLoader.java:340)\n        at org.eclipse.osgi.framework.internal.core.BundleLoader.findClassInternal(BundleLoader.java:408)\n        at org.eclipse.osgi.framework.internal.core.BundleLoader.findClass(BundleLoader.java:369)\n        at org.eclipse.osgi.framework.internal.core.BundleLoader.findClass(BundleLoader.java:357)\n        at org.eclipse.osgi.internal.baseadaptor.DefaultClassLoader.loadClass(DefaultClassLoader.java:83)\n        at java.lang.ClassLoader.loadClass(ClassLoader.java:251)\n        at java.lang.ClassLoader.loadClassInternal(ClassLoader.java:319)\n        at org.eclipse.jdt.internal.ui.InitializeAfterLoadJob.runInUIThread(InitializeAfterLoadJob.java:53)\n        at org.eclipse.ui.progress.UIJob$1.run(UIJob.java:94)\n        at org.eclipse.swt.widgets.RunnableLock.run(RunnableLock.java:35)\n        at org.eclipse.swt.widgets.Synchronizer.runAsyncMessages(Synchronizer.java:123)\n        at org.eclipse.swt.widgets.Display.runAsyncMessages(Display.java:3659)\n        at org.eclipse.swt.widgets.Display.readAndDispatch(Display.java:3296)\n        at org.eclipse.ui.internal.Workbench.runEventLoop(Workbench.java:2389)\n        at org.eclipse.ui.internal.Workbench.runUI(Workbench.java:2353)\n        at org.eclipse.ui.internal.Workbench.access$4(Workbench.java:2219)\n        at org.eclipse.ui.internal.Workbench$4.run(Workbench.java:466)\n        at org.eclipse.core.databinding.observable.Realm.runWithDefault(Realm.java:289)\n        at org.eclipse.ui.internal.Workbench.createAndRunWorkbench(Workbench.java:461)\n        at org.eclipse.ui.PlatformUI.createAndRunWorkbench(PlatformUI.java:149)\n        at org.eclipse.ui.internal.ide.application.IDEApplication.start(IDEApplication.java:106)\n        at org.eclipse.equinox.internal.app.EclipseAppHandle.run(EclipseAppHandle.java:153)\n        at org.eclipse.core.runtime.internal.adaptor.EclipseAppLauncher.runApplication(EclipseAppLauncher.java:106)\n        at org.eclipse.core.runtime.internal.adaptor.EclipseAppLauncher.start(EclipseAppLauncher.java:76)\n        at org.eclipse.core.runtime.adaptor.EclipseStarter.run(EclipseStarter.java:363)\n        at org.eclipse.core.runtime.adaptor.EclipseStarter.run(EclipseStarter.java:176)\n        at sun.reflect.NativeMethodAccessorImpl.invoke0(Native Method)\n        at sun.reflect.NativeMethodAccessorImpl.invoke(NativeMethodAccessorImpl.java:39)\n        at sun.reflect.DelegatingMethodAccessorImpl.invoke(DelegatingMethodAccessorImpl.java:25)\n        at java.lang.reflect.Method.invoke(Method.java:597)\n        at org.eclipse.equinox.launcher.Main.invokeFramework(Main.java:504)\n        at org.eclipse.equinox.launcher.Main.basicRun(Main.java:443)\n        at org.eclipse.equinox.launcher.Main.run(Main.java:1169)\n        at org.eclipse.equinox.launcher.Main.main(Main.java:1144)\n        at org.eclipse.core.launcher.Main.main(Main.java:30)\n\nThis is on a Intel Core2 2.33GHz with 2GB RAM, WinXP",
    "Created an attachment (id\u003d70292)\ndump\n\nThis is a thread dump taken immediately after eclipse has been started.",
    "According to the trace, the timeout happens while loading one of the class referenced on line 53:\nJob job \u003d new RealJob(JavaUIMessages.JavaPlugin_initializing_ui);\n\nSince these are JDT/UI class, moving to JDT/UI to investigate.",
    "We don\u0027t understand this exception, we haven\u0027t change anything in this area since 3.2. Is it possible that this is caused because the InitializeAfterLoadJob is run before start has been finished? Is there a way to ensure that the async exec is executed after the bundle has started?",
    "What VM are you using?  It looks like the infamous VM classloader lock from the call to ClassLoader.loadClassInternal.  This can cause dead lock if one thread is attempting to activate the bundle while another thread has locked the classloader object attempting to load a class from the bundle that is activating.  If the activating thread needs to load another class then it will block on the classloader object.  Meanwhile the other thread is blocked waiting for the bundle to finish starting.\n\nThis is an issue on the Sun VM where the classloader object is locked natively and out of our control.  To avoid endless deadlock we timeout waiting for the bundle to start so that things can continue.\n\nCan the following call be moved to the last line of the JavaPlugin.start method?\n\n new InitializeAfterLoadJob().schedule();\n\nThis should ensure that the starting thread does not need to load any more classes before it is allowed to finish activation.\nIf that is not possible then you will have to use a SynchronousBundleListener to listen for when your bundle has finished loading before allowing the job to start.  I can help with a patch if that is required.\n\nSee bug 86713 and bug 121737 for more details on the VM bug.\n",
    "Hi Thomas\n\nMy VM is java.runtime.version\u003d1.6.0_01-b06\n\nMoving the line down to the end is no problem, and I think we should do that for RC4. But isn\u0027t it still possible that the job runs before start finished (unlikely but possible)?. Maybe for 3.4 we should use the listener approach, or I thought maybe something like:\n\nInitializeAfterLoadJob.RealJob.class.toString();\nnew InitializeAfterLoadJob().schedule();\n\ncould also work since it forces to load the class certainly before the job is executed. Would that work?",
    "Created an attachment (id\u003d70470)\nfix\n\n",
    "(In reply to comment #5)\n\u003e Hi Thomas\n\u003e My VM is java.runtime.version\u003d1.6.0_01-b06\nThat is the a Sun VM, right?\n\nYour patch should do the trick because once the job is scheduled the thread which is activating the bundle does not need to load any more classes before your JavaPlugin.start method returns.  This will allow it to finish without having to obtain the classloader lock.  The job thread may wait for a very short time for your start method to return but this should not cause deadlock as long as your start method is not doing any real work after the schedule.\n",
    "(In reply to comment #7)\n\u003e That is the a Sun VM, right?\n\nYes, Sun.\n\n\u003e Your patch should do the trick because once the job is scheduled the thread\n\u003e which is activating the bundle does not need to load any more classes before\n\u003e your JavaPlugin.start method returns.  This will allow it to finish without\n\u003e having to obtain the classloader lock.  The job thread may wait for a very\n\u003e short time for your start method to return but this should not cause deadlock\n\u003e as long as your start method is not doing any real work after the schedule.\n\nI see, we\u0027ll do that for 3.3.1 then. Thanks\n\n",
    "The VM bug is http://bugs.sun.com/bugdatabase/view_bug.do?bug_id\u003d4670071",
    "Changing target to 3.4 as we haven\u0027t seen this anymore and we should avoid risky fixes for 3.3.1 if there no urge for it.",
    "fixed \u003e 20070827\n\n",
    "start verification...",
    "verified that new InitializeAfterLoadJob().schedule(); is the last stmt in start method."
  ],
  "commentCreationDates": [
    "2007-06-06T10:43:49+02:00",
    "2007-06-06T10:47:08+02:00",
    "2007-06-06T11:27:32+02:00",
    "2007-06-06T12:09:19+02:00",
    "2007-06-07T05:29:14+02:00",
    "2007-06-07T09:37:03+02:00",
    "2007-06-07T09:37:38+02:00",
    "2007-06-07T14:57:44+02:00",
    "2007-06-07T15:07:33+02:00",
    "2007-06-08T14:47:07+02:00",
    "2007-08-22T15:34:45+02:00",
    "2007-08-27T13:16:01+02:00",
    "2007-09-18T15:15:11+02:00",
    "2007-09-18T15:16:57+02:00"
  ],
  "traces": [
    {
      "exceptionType": "org.osgi.framework.BundleException",
      "message": "State change in progress for bundle \"update@plugins/org.eclipse.jdt.ui_3.3.0.v20070606-0010.jar\" by thread \"Worker -3\".",
      "elements": [
        {
          "method": "org.eclipse.osgi.framework.internal.core.AbstractBundle.beginStateChange",
          "source": "AbstractBundle.java:1141"
        },
        {
          "method": "org.eclipse.osgi.framework.internal.core.AbstractBundle.start",
          "source": "AbstractBundle.java:258"
        },
        {
          "method": "org.eclipse.osgi.framework.util.SecureAction.start",
          "source": "SecureAction.java:400"
        },
        {
          "method": "org.eclipse.core.runtime.internal.adaptor.EclipseLazyStarter.postFindLocalClass",
          "source": "EclipseLazyStarter.java:111"
        },
        {
          "method": "org.eclipse.osgi.baseadaptor.loader.ClasspathManager.findLocalClass",
          "source": "ClasspathManager.java:417"
        },
        {
          "method": "org.eclipse.osgi.internal.baseadaptor.DefaultClassLoader.findLocalClass",
          "source": "DefaultClassLoader.java:189"
        },
        {
          "method": "org.eclipse.osgi.framework.internal.core.BundleLoader.findLocalClass",
          "source": "BundleLoader.java:340"
        },
        {
          "method": "org.eclipse.osgi.framework.internal.core.BundleLoader.findClassInternal",
          "source": "BundleLoader.java:408"
        },
        {
          "method": "org.eclipse.osgi.framework.internal.core.BundleLoader.findClass",
          "source": "BundleLoader.java:369"
        },
        {
          "method": "org.eclipse.osgi.framework.internal.core.BundleLoader.findClass",
          "source": "BundleLoader.java:357"
        },
        {
          "method": "org.eclipse.osgi.internal.baseadaptor.DefaultClassLoader.loadClass",
          "source": "DefaultClassLoader.java:83"
        },
        {
          "method": "java.lang.ClassLoader.loadClass",
          "source": "ClassLoader.java:251"
        },
        {
          "method": "java.lang.ClassLoader.loadClassInternal",
          "source": "ClassLoader.java:319"
        },
        {
          "method": "org.eclipse.jdt.internal.ui.InitializeAfterLoadJob.runInUIThread",
          "source": "InitializeAfterLoadJob.java:53"
        },
        {
          "method": "org.eclipse.ui.progress.UIJob$1.run",
          "source": "UIJob.java:94"
        },
        {
          "method": "org.eclipse.swt.widgets.RunnableLock.run",
          "source": "RunnableLock.java:35"
        },
        {
          "method": "org.eclipse.swt.widgets.Synchronizer.runAsyncMessages",
          "source": "Synchronizer.java:123"
        },
        {
          "method": "org.eclipse.swt.widgets.Display.runAsyncMessages",
          "source": "Display.java:3659"
        },
        {
          "method": "org.eclipse.swt.widgets.Display.readAndDispatch",
          "source": "Display.java:3296"
        },
        {
          "method": "org.eclipse.ui.internal.Workbench.runEventLoop",
          "source": "Workbench.java:2389"
        },
        {
          "method": "org.eclipse.ui.internal.Workbench.runUI",
          "source": "Workbench.java:2353"
        },
        {
          "method": "org.eclipse.ui.internal.Workbench.access$4",
          "source": "Workbench.java:2219"
        },
        {
          "method": "org.eclipse.ui.internal.Workbench$4.run",
          "source": "Workbench.java:466"
        },
        {
          "method": "org.eclipse.core.databinding.observable.Realm.runWithDefault",
          "source": "Realm.java:289"
        },
        {
          "method": "org.eclipse.ui.internal.Workbench.createAndRunWorkbench",
          "source": "Workbench.java:461"
        },
        {
          "method": "org.eclipse.ui.PlatformUI.createAndRunWorkbench",
          "source": "PlatformUI.java:149"
        },
        {
          "method": "org.eclipse.ui.internal.ide.application.IDEApplication.start",
          "source": "IDEApplication.java:106"
        },
        {
          "method": "org.eclipse.equinox.internal.app.EclipseAppHandle.run",
          "source": "EclipseAppHandle.java:153"
        },
        {
          "method": "org.eclipse.core.runtime.internal.adaptor.EclipseAppLauncher.runApplication",
          "source": "EclipseAppLauncher.java:106"
        },
        {
          "method": "org.eclipse.core.runtime.internal.adaptor.EclipseAppLauncher.start",
          "source": "EclipseAppLauncher.java:76"
        },
        {
          "method": "org.eclipse.core.runtime.adaptor.EclipseStarter.run",
          "source": "EclipseStarter.java:363"
        },
        {
          "method": "org.eclipse.core.runtime.adaptor.EclipseStarter.run",
          "source": "EclipseStarter.java:176"
        },
        {
          "method": "sun.reflect.NativeMethodAccessorImpl.invoke0",
          "source": "Native Method"
        },
        {
          "method": "sun.reflect.NativeMethodAccessorImpl.invoke",
          "source": "NativeMethodAccessorImpl.java:39"
        },
        {
          "method": "sun.reflect.DelegatingMethodAccessorImpl.invoke",
          "source": "DelegatingMethodAccessorImpl.java:25"
        },
        {
          "method": "java.lang.reflect.Method.invoke",
          "source": "Method.java:597"
        },
        {
          "method": "org.eclipse.equinox.launcher.Main.invokeFramework",
          "source": "Main.java:504"
        },
        {
          "method": "org.eclipse.equinox.launcher.Main.basicRun",
          "source": "Main.java:443"
        },
        {
          "method": "org.eclipse.equinox.launcher.Main.run",
          "source": "Main.java:1169"
        },
        {
          "method": "org.eclipse.equinox.launcher.Main.main",
          "source": "Main.java:1144"
        },
        {
          "method": "org.eclipse.core.launcher.Main.main",
          "source": "Main.java:30"
        }
      ],
      "causedBy": {
        "exceptionType": "org.eclipse.osgi.framework.internal.core.AbstractBundle$BundleStatusException",
        "elements": [
          {
            "method": "org.eclipse.osgi.framework.internal.core.AbstractBundle.beginStateChange",
            "source": "AbstractBundle.java:1141"
          },
          {
            "method": "org.eclipse.osgi.framework.internal.core.AbstractBundle.start",
            "source": "AbstractBundle.java:258"
          },
          {
            "method": "org.eclipse.osgi.framework.util.SecureAction.start",
            "source": "SecureAction.java:400"
          },
          {
            "method": "org.eclipse.core.runtime.internal.adaptor.EclipseLazyStarter.postFindLocalClass",
            "source": "EclipseLazyStarter.java:111"
          },
          {
            "method": "org.eclipse.osgi.baseadaptor.loader.ClasspathManager.findLocalClass",
            "source": "ClasspathManager.java:417"
          },
          {
            "method": "org.eclipse.osgi.internal.baseadaptor.DefaultClassLoader.findLocalClass",
            "source": "DefaultClassLoader.java:189"
          },
          {
            "method": "org.eclipse.osgi.framework.internal.core.BundleLoader.findLocalClass",
            "source": "BundleLoader.java:340"
          },
          {
            "method": "org.eclipse.osgi.framework.internal.core.BundleLoader.findClassInternal",
            "source": "BundleLoader.java:408"
          },
          {
            "method": "org.eclipse.osgi.framework.internal.core.BundleLoader.findClass",
            "source": "BundleLoader.java:369"
          },
          {
            "method": "org.eclipse.osgi.framework.internal.core.BundleLoader.findClass",
            "source": "BundleLoader.java:357"
          },
          {
            "method": "org.eclipse.osgi.internal.baseadaptor.DefaultClassLoader.loadClass",
            "source": "DefaultClassLoader.java:83"
          },
          {
            "method": "java.lang.ClassLoader.loadClass",
            "source": "ClassLoader.java:251"
          },
          {
            "method": "java.lang.ClassLoader.loadClassInternal",
            "source": "ClassLoader.java:319"
          },
          {
            "method": "org.eclipse.jdt.internal.ui.InitializeAfterLoadJob.runInUIThread",
            "source": "InitializeAfterLoadJob.java:53"
          },
          {
            "method": "org.eclipse.ui.progress.UIJob$1.run",
            "source": "UIJob.java:94"
          },
          {
            "method": "org.eclipse.swt.widgets.RunnableLock.run",
            "source": "RunnableLock.java:35"
          },
          {
            "method": "org.eclipse.swt.widgets.Synchronizer.runAsyncMessages",
            "source": "Synchronizer.java:123"
          },
          {
            "method": "org.eclipse.swt.widgets.Display.runAsyncMessages",
            "source": "Display.java:3659"
          },
          {
            "method": "org.eclipse.swt.widgets.Display.readAndDispatch",
            "source": "Display.java:3296"
          },
          {
            "method": "org.eclipse.ui.internal.Workbench.runEventLoop",
            "source": "Workbench.java:2389"
          },
          {
            "method": "org.eclipse.ui.internal.Workbench.runUI",
            "source": "Workbench.java:2353"
          },
          {
            "method": "org.eclipse.ui.internal.Workbench.access$4",
            "source": "Workbench.java:2219"
          },
          {
            "method": "org.eclipse.ui.internal.Workbench$4.run",
            "source": "Workbench.java:466"
          },
          {
            "method": "org.eclipse.core.databinding.observable.Realm.runWithDefault",
            "source": "Realm.java:289"
          },
          {
            "method": "org.eclipse.ui.internal.Workbench.createAndRunWorkbench",
            "source": "Workbench.java:461"
          },
          {
            "method": "org.eclipse.ui.PlatformUI.createAndRunWorkbench",
            "source": "PlatformUI.java:149"
          },
          {
            "method": "org.eclipse.ui.internal.ide.application.IDEApplication.start",
            "source": "IDEApplication.java:106"
          },
          {
            "method": "org.eclipse.equinox.internal.app.EclipseAppHandle.run",
            "source": "EclipseAppHandle.java:153"
          },
          {
            "method": "org.eclipse.core.runtime.internal.adaptor.EclipseAppLauncher.runApplication",
            "source": "EclipseAppLauncher.java:106"
          },
          {
            "method": "org.eclipse.core.runtime.internal.adaptor.EclipseAppLauncher.start",
            "source": "EclipseAppLauncher.java:76"
          },
          {
            "method": "org.eclipse.core.runtime.adaptor.EclipseStarter.run",
            "source": "EclipseStarter.java:363"
          },
          {
            "method": "org.eclipse.core.runtime.adaptor.EclipseStarter.run",
            "source": "EclipseStarter.java:176"
          },
          {
            "method": "sun.reflect.NativeMethodAccessorImpl.invoke0",
            "source": "Native Method"
          },
          {
            "method": "sun.reflect.NativeMethodAccessorImpl.invoke",
            "source": "NativeMethodAccessorImpl.java:39"
          },
          {
            "method": "sun.reflect.DelegatingMethodAccessorImpl.invoke",
            "source": "DelegatingMethodAccessorImpl.java:25"
          },
          {
            "method": "java.lang.reflect.Method.invoke",
            "source": "Method.java:597"
          },
          {
            "method": "org.eclipse.equinox.launcher.Main.invokeFramework",
            "source": "Main.java:504"
          },
          {
            "method": "org.eclipse.equinox.launcher.Main.basicRun",
            "source": "Main.java:443"
          },
          {
            "method": "org.eclipse.equinox.launcher.Main.run",
            "source": "Main.java:1169"
          },
          {
            "method": "org.eclipse.equinox.launcher.Main.main",
            "source": "Main.java:1144"
          },
          {
            "method": "org.eclipse.core.launcher.Main.main",
            "source": "Main.java:30"
          }
        ],
        "number": 0,
        "commentIndex": 0
      },
      "number": 0,
      "commentIndex": 0,
      "bugId": "191193",
      "date": "2007-06-06T10:43:49+02:00",
      "product": "JDT",
      "component": "UI",
      "severity": "major"
    }
  ],
  "groupId": "191193",
  "bugId": "191193",
  "date": "2007-06-06T10:43:49+02:00",
  "product": "JDT",
  "component": "UI",
  "severity": "major"
}