{
  "comments": [
    "Build F2\n\nIf a project is deleted, but referenced by others which prereq a classfile \nfolder from it, and which happens to be missing; the following NPE may occur \nwhile the project is being deleted.\n\n!ENTRY org.eclipse.core.resources 4 2 Jun 04, 2002 18:53:53.837\n!MESSAGE Problems occurred when invoking code from plug-\nin: \"org.eclipse.core.resources\".\n!STACK 0\njava.lang.NullPointerException\n        at \norg.eclipse.jdt.internal.core.DeltaProcessor.updateCurrentDeltaAndIndex\n(DeltaProcessor.java:1149)\n        at org.eclipse.jdt.internal.core.DeltaProcessor.updateRoots\n(DeltaProcessor.java:1784)\n        at org.eclipse.jdt.internal.core.DeltaProcessor.elementRemoved\n(DeltaProcessor.java:766)\n        at \norg.eclipse.jdt.internal.core.DeltaProcessor.updateCurrentDeltaAndIndex\n(DeltaProcessor.java:1160)\n        at org.eclipse.jdt.internal.core.DeltaProcessor.traverseDelta\n(DeltaProcessor.java:1330)\n        at org.eclipse.jdt.internal.core.DeltaProcessor.processResourceDelta\n(DeltaProcessor.java:1122)\n        at org.eclipse.jdt.internal.core.DeltaProcessor.resourceChanged\n(DeltaProcessor.java:1289)\n        at org.eclipse.core.internal.events.NotificationManager$1.run\n(NotificationManager.java:128)\n        at org.eclipse.core.internal.runtime.InternalPlatform.run\n(InternalPlatform.java:802)\n        at org.eclipse.core.runtime.Platform.run(Platform.java:416)\n        at org.eclipse.core.internal.events.NotificationManager.notify\n(NotificationManager.java:143)\n        at org.eclipse.core.internal.events.NotificationManager.broadcastChanges\n(NotificationManager.java:67)\n        at org.eclipse.core.internal.resources.Workspace.broadcastChanges\n(Workspace.java:133)\n        at org.eclipse.core.internal.resources.Workspace.endOperation\n(Workspace.java:741)\n        at org.eclipse.core.internal.resources.Workspace.run\n(Workspace.java:1366)\n        at org.eclipse.ui.actions.WorkspaceModifyOperation.run\n(WorkspaceModifyOperation.java:78)\n        at org.eclipse.jface.operation.ModalContext$ModalContextThread.run\n(ModalContext.java:98)",
    "There is no protection on the delta findMember action since the target root is \nmissing.\n\nSteps:\n\n1. Define P1\n2. Define P2\n3. Add P2/lib folder\n4. Prereq P2/lib folder on P1 classpath\n5. In navigator, delete lib folder from P2\n6. In package view, delete P2 project",
    "Added regression test.",
    "Null check was added.\n\nFixed.",
    "Could not reproduce the NPE following the steps above.",
    "Verified."
  ],
  "commentCreationDates": [
    "2002-06-04T18:55:12+02:00",
    "2002-06-04T18:57:01+02:00",
    "2002-06-04T19:30:25+02:00",
    "2002-06-04T19:34:51+02:00",
    "2002-06-04T19:41:41+02:00",
    "2002-06-13T15:15:37+02:00"
  ],
  "traces": [
    {
      "exceptionType": "java.lang.NullPointerException",
      "elements": [
        {
          "method": "org.eclipse.jdt.internal.core.DeltaProcessor.updateCurrentDeltaAndIndex",
          "source": "DeltaProcessor.java:1149"
        },
        {
          "method": "org.eclipse.jdt.internal.core.DeltaProcessor.updateRoots",
          "source": "DeltaProcessor.java:1784"
        },
        {
          "method": "org.eclipse.jdt.internal.core.DeltaProcessor.elementRemoved",
          "source": "DeltaProcessor.java:766"
        },
        {
          "method": "org.eclipse.jdt.internal.core.DeltaProcessor.updateCurrentDeltaAndIndex",
          "source": "DeltaProcessor.java:1160"
        },
        {
          "method": "org.eclipse.jdt.internal.core.DeltaProcessor.traverseDelta",
          "source": "DeltaProcessor.java:1330"
        },
        {
          "method": "org.eclipse.jdt.internal.core.DeltaProcessor.processResourceDelta",
          "source": "DeltaProcessor.java:1122"
        },
        {
          "method": "org.eclipse.jdt.internal.core.DeltaProcessor.resourceChanged",
          "source": "DeltaProcessor.java:1289"
        },
        {
          "method": "org.eclipse.core.internal.events.NotificationManager$1.run",
          "source": "NotificationManager.java:128"
        },
        {
          "method": "org.eclipse.core.internal.runtime.InternalPlatform.run",
          "source": "InternalPlatform.java:802"
        },
        {
          "method": "org.eclipse.core.runtime.Platform.run",
          "source": "Platform.java:416"
        },
        {
          "method": "org.eclipse.core.internal.events.NotificationManager.notify",
          "source": "NotificationManager.java:143"
        },
        {
          "method": "org.eclipse.core.internal.events.NotificationManager.broadcastChanges",
          "source": "NotificationManager.java:67"
        },
        {
          "method": "org.eclipse.core.internal.resources.Workspace.broadcastChanges",
          "source": "Workspace.java:133"
        },
        {
          "method": "org.eclipse.core.internal.resources.Workspace.endOperation",
          "source": "Workspace.java:741"
        },
        {
          "method": "org.eclipse.core.internal.resources.Workspace.run",
          "source": "Workspace.java:1366"
        },
        {
          "method": "org.eclipse.ui.actions.WorkspaceModifyOperation.run",
          "source": "WorkspaceModifyOperation.java:78"
        },
        {
          "method": "org.eclipse.jface.operation.ModalContext$ModalContextThread.run",
          "source": "ModalContext.java:98"
        }
      ],
      "number": 0,
      "commentIndex": 0,
      "bugId": "19131",
      "date": "2002-06-04T18:55:12+02:00",
      "product": "JDT",
      "component": "Core",
      "severity": "normal"
    }
  ],
  "groupId": "19131",
  "bugId": "19131",
  "date": "2002-06-04T18:55:12+02:00",
  "product": "JDT",
  "component": "Core",
  "severity": "normal"
}