{
  "comments": [
    "The 3.2.x test suite\u0027s content type test fails when the used XML parser is the eRCP\u0027s microXML. The failing method is the following:\n\ntestRootElementAndDTDDescriber(org.eclipse.core.tests.runtime.content.IContentTypeManagerTest) from org.eclipse.core.tests.runtime.content.IContentTypeManagerTest testclass\n\n    testRootElementAndDTDDescriber(org.eclipse.core.tests.runtime.content.IContentTypeManagerTest)\n      junit.framework.AssertionFailedError: 3.1 expected:\u003corg.eclipse.core.tests.runtime.dtd\u003e but was:\u003corg.eclipse.core.runtime.xml\u003e\n      \tat junit.framework.Assert.fail(Assert.java:47)\n      \tat junit.framework.Assert.failNotEquals(Assert.java:282)\n      \tat junit.framework.Assert.assertEquals(Assert.java:64)\n      \tat org.eclipse.core.tests.runtime.content.IContentTypeManagerTest.testRootElementAndDTDDescriber(IContentTypeManagerTest.java:1196)\n      \tat sun.reflect.NativeMethodAccessorImpl.invoke0(Native Method)\n      \tat sun.reflect.NativeMethodAccessorImpl.invoke(NativeMethodAccessorImpl.java:39)\n      \tat sun.reflect.DelegatingMethodAccessorImpl.invoke(DelegatingMethodAccessorImpl.java:25)\n      \tat junit.framework.TestCase.runTest(TestCase.java:154)\n      \tat junit.framework.TestCase.runBare(TestCase.java:127)\n      \tat junit.framework.TestResult$1.protect(TestResult.java:106)\n      \tat junit.framework.TestResult.runProtected(TestResult.java:124)\n      \tat junit.framework.TestResult.run(TestResult.java:109)\n      \tat junit.framework.TestCase.run(TestCase.java:118)\n      \tat junit.framework.TestSuite.runTest(TestSuite.java:208)\n      \tat junit.framework.TestSuite.run(TestSuite.java:203)\n      \tat junit.framework.TestSuite.runTest(TestSuite.java:208)\n      \tat junit.framework.TestSuite.run(TestSuite.java:203)\n\nThe test fails with both 3.2 and 3.3 contenttype.\n\nThe problem is that microXML doesn\u0027t fire events for DTD elements. I posted this issue some ago in the dsdp-ercp-dev mail list, but I was redirected to the platform group. So here I am.\n\nI wish to note that I\u0027m not using the standard Eclipse way of running the tests. However, I think it should be easy to reproduce the failing by using microXML as the XML parser.\n\nIf you need additional info, please ask. I\u0027m not quite sure what information should provide. I hope that this is enough for start.",
    "Content type is is platform core.",
    "\u003e The problem is that microXML doesn\u0027t fire events for DTD elements.\n\nIsn\u0027t this a bug in \"microXML\" then? Our tests run fine with the XML parsers bundled in the JRE.",
    "I\u0027m not very sure about the correct action, which should be taken in this situation. Because the problem is indeed in the microXML, I posted this issue in the dsdp-ercp-dev mail list:\n\nhttp://dev.eclipse.org/mhonarc/lists/dsdp-ercp-dev/msg00039.html\n\nThey suggested that I make you aware of this issue. I\u0027m not very involved with the content type bundle, so I cannot help much beyond that."
  ],
  "commentCreationDates": [
    "2007-06-07T18:29:53+02:00",
    "2007-06-07T19:12:41+02:00",
    "2007-06-08T21:15:17+02:00",
    "2007-06-10T16:59:31+02:00"
  ],
  "traces": [
    {
      "exceptionType": "junit.framework.AssertionFailedError",
      "message": "3.1 expected:\u003corg.eclipse.core.tests.runtime.dtd\u003e but was:\u003corg.eclipse.core.runtime.xml\u003e",
      "elements": [
        {
          "method": "junit.framework.Assert.fail",
          "source": "Assert.java:47"
        },
        {
          "method": "junit.framework.Assert.failNotEquals",
          "source": "Assert.java:282"
        },
        {
          "method": "junit.framework.Assert.assertEquals",
          "source": "Assert.java:64"
        },
        {
          "method": "org.eclipse.core.tests.runtime.content.IContentTypeManagerTest.testRootElementAndDTDDescriber",
          "source": "IContentTypeManagerTest.java:1196"
        },
        {
          "method": "sun.reflect.NativeMethodAccessorImpl.invoke0",
          "source": "Native Method"
        },
        {
          "method": "sun.reflect.NativeMethodAccessorImpl.invoke",
          "source": "NativeMethodAccessorImpl.java:39"
        },
        {
          "method": "sun.reflect.DelegatingMethodAccessorImpl.invoke",
          "source": "DelegatingMethodAccessorImpl.java:25"
        },
        {
          "method": "junit.framework.TestCase.runTest",
          "source": "TestCase.java:154"
        },
        {
          "method": "junit.framework.TestCase.runBare",
          "source": "TestCase.java:127"
        },
        {
          "method": "junit.framework.TestResult$1.protect",
          "source": "TestResult.java:106"
        },
        {
          "method": "junit.framework.TestResult.runProtected",
          "source": "TestResult.java:124"
        },
        {
          "method": "junit.framework.TestResult.run",
          "source": "TestResult.java:109"
        },
        {
          "method": "junit.framework.TestCase.run",
          "source": "TestCase.java:118"
        },
        {
          "method": "junit.framework.TestSuite.runTest",
          "source": "TestSuite.java:208"
        },
        {
          "method": "junit.framework.TestSuite.run",
          "source": "TestSuite.java:203"
        },
        {
          "method": "junit.framework.TestSuite.runTest",
          "source": "TestSuite.java:208"
        },
        {
          "method": "junit.framework.TestSuite.run",
          "source": "TestSuite.java:203"
        }
      ],
      "number": 0,
      "commentIndex": 0,
      "bugId": "191516",
      "date": "2007-06-07T18:29:53+02:00",
      "product": "Platform",
      "component": "Runtime",
      "severity": "normal"
    }
  ],
  "groupId": "191516",
  "bugId": "191516",
  "date": "2007-06-07T18:29:53+02:00",
  "product": "Platform",
  "component": "Runtime",
  "severity": "normal"
}