{
  "comments": [
    "OS: Freebsd 6.2\n\nAttempt to create a managed make C or C++ projects fails without any visible effect, no messages or warnings except for this found in the .log file:\n\n!SESSION 2007-06-11 10:30:44.051 -----------------------------------------------\neclipse.buildId\u003dM20060921-0945\njava.version\u003d1.5.0\njava.vendor\u003dSun Microsystems Inc.\nBootLoader constants: OS\u003dfreebsd, ARCH\u003dx86, WS\u003dgtk, NL\u003den\nCommand-line arguments:  -os freebsd -ws gtk -arch x86\n\n!ENTRY org.eclipse.ui 4 4 2007-06-11 10:36:20.861\n!MESSAGE Unhandled event loop exception\n\n!ENTRY org.eclipse.ui 4 0 2007-06-11 10:36:20.863\n!MESSAGE Index: 0, Size: 0\n!STACK 0\njava.lang.IndexOutOfBoundsException: Index: 0, Size: 0\n        at java.util.ArrayList.RangeCheck(ArrayList.java:546)\n        at java.util.ArrayList.get(ArrayList.java:321)\n        at org.eclipse.cdt.managedbuilder.ui.wizards.CProjectPlatformPage.createControl(CProjectPlatformPage.java:211)\n        at org.eclipse.jface.wizard.Wizard.createPageControls(Wizard.java:180)\n        at org.eclipse.cdt.managedbuilder.ui.wizards.NewManagedProjectWizard.createPageControls(NewManagedProjectWizard.java:99)\n        at org.eclipse.jface.wizard.WizardDialog.createPageControls(WizardDialog.java:614)\n        at org.eclipse.jface.wizard.WizardDialog.setWizard(WizardDialog.java:989)\n        at org.eclipse.jface.wizard.WizardDialog.updateForPage(WizardDialog.java:1041)\n        at org.eclipse.jface.wizard.WizardDialog.access$2(WizardDialog.java:1038)\n        at org.eclipse.jface.wizard.WizardDialog$4.run(WizardDialog.java:1028)\n        at org.eclipse.swt.custom.BusyIndicator.showWhile(BusyIndicator.java:67)\n        at org.eclipse.jface.wizard.WizardDialog.showPage(WizardDialog.java:1026)\n        at org.eclipse.jface.wizard.WizardDialog.nextPressed(WizardDialog.java:757)\n        at org.eclipse.jface.wizard.WizardDialog.buttonPressed(WizardDialog.java:351)\n        at org.eclipse.jface.dialogs.Dialog$3.widgetSelected(Dialog.java:660)\n        at org.eclipse.swt.widgets.TypedListener.handleEvent(TypedListener.java:90)\n        at org.eclipse.swt.widgets.EventTable.sendEvent(EventTable.java:66)\n        at org.eclipse.swt.widgets.Widget.sendEvent(Widget.java:1085)\n        at org.eclipse.swt.widgets.Display.runDeferredEvents(Display.java:3166)\n        at org.eclipse.swt.widgets.Display.readAndDispatch(Display.java:2842)\n        at org.eclipse.jface.window.Window.runEventLoop(Window.java:820)\n        at org.eclipse.jface.window.Window.open(Window.java:796)\n        at org.eclipse.ui.actions.NewProjectAction.run(NewProjectAction.java:116)\n        at org.eclipse.jface.action.Action.runWithEvent(Action.java:499)\n        at org.eclipse.jface.action.ActionContributionItem.handleWidgetSelection(ActionContributionItem.java:539)\n        at org.eclipse.jface.action.ActionContributionItem.access$2(ActionContributionItem.java:488)\n        at org.eclipse.jface.action.ActionContributionItem$5.handleEvent(ActionContributionItem.java:400)\n        at org.eclipse.swt.widgets.EventTable.sendEvent(EventTable.java:66)\n        at org.eclipse.swt.widgets.Widget.sendEvent(Widget.java:1085)\n        at org.eclipse.swt.widgets.Display.runDeferredEvents(Display.java:3166)\n        at org.eclipse.swt.widgets.Display.readAndDispatch(Display.java:2842)\n        at org.eclipse.ui.internal.Workbench.runEventLoop(Workbench.java:1930)\n        at org.eclipse.ui.internal.Workbench.runUI(Workbench.java:1894)\n        at org.eclipse.ui.internal.Workbench.createAndRunWorkbench(Workbench.java:422)\n        at org.eclipse.ui.PlatformUI.createAndRunWorkbench(PlatformUI.java:149)\n        at org.eclipse.ui.internal.ide.IDEApplication.run(IDEApplication.java:95)\n        at org.eclipse.core.internal.runtime.PlatformActivator$1.run(PlatformActivator.java:78)\n        at org.eclipse.core.runtime.internal.adaptor.EclipseAppLauncher.runApplication(EclipseAppLauncher.java:92)\n        at org.eclipse.core.runtime.internal.adaptor.EclipseAppLauncher.start(EclipseAppLauncher.java:68)\n        at org.eclipse.core.runtime.adaptor.EclipseStarter.run(EclipseStarter.java:400)\n        at org.eclipse.core.runtime.adaptor.EclipseStarter.run(EclipseStarter.java:177)\n        at sun.reflect.NativeMethodAccessorImpl.invoke0(Native Method)\n        at sun.reflect.NativeMethodAccessorImpl.invoke(NativeMethodAccessorImpl.java:39)\n        at sun.reflect.DelegatingMethodAccessorImpl.invoke(DelegatingMethodAccessorImpl.java:25)\n        at java.lang.reflect.Method.invoke(Method.java:585)\n        at org.eclipse.core.launcher.Main.invokeFramework(Main.java:336)\n        at org.eclipse.core.launcher.Main.basicRun(Main.java:280)\n        at org.eclipse.core.launcher.Main.run(Main.java:977)\n        at org.eclipse.core.launcher.Main.main(Main.java:952)",
    "which version of eclipse and CDT are you using?",
    "According to the stack trace this is definitely NOT the 4.0 branch\n\nsetting version to 3.0 for now..",
    "Eclipse SDK Version: 3.2.2\n\nCDT Version: 3.1.2"
  ],
  "commentCreationDates": [
    "2007-06-11T11:30:06+02:00",
    "2007-06-13T12:52:16+02:00",
    "2007-06-13T14:44:21+02:00",
    "2007-06-13T14:54:05+02:00"
  ],
  "traces": [
    {
      "exceptionType": "java.lang.IndexOutOfBoundsException",
      "message": "Index: 0, Size: 0",
      "elements": [
        {
          "method": "java.util.ArrayList.RangeCheck",
          "source": "ArrayList.java:546"
        },
        {
          "method": "java.util.ArrayList.get",
          "source": "ArrayList.java:321"
        },
        {
          "method": "org.eclipse.cdt.managedbuilder.ui.wizards.CProjectPlatformPage.createControl",
          "source": "CProjectPlatformPage.java:211"
        },
        {
          "method": "org.eclipse.jface.wizard.Wizard.createPageControls",
          "source": "Wizard.java:180"
        },
        {
          "method": "org.eclipse.cdt.managedbuilder.ui.wizards.NewManagedProjectWizard.createPageControls",
          "source": "NewManagedProjectWizard.java:99"
        },
        {
          "method": "org.eclipse.jface.wizard.WizardDialog.createPageControls",
          "source": "WizardDialog.java:614"
        },
        {
          "method": "org.eclipse.jface.wizard.WizardDialog.setWizard",
          "source": "WizardDialog.java:989"
        },
        {
          "method": "org.eclipse.jface.wizard.WizardDialog.updateForPage",
          "source": "WizardDialog.java:1041"
        },
        {
          "method": "org.eclipse.jface.wizard.WizardDialog.access$2",
          "source": "WizardDialog.java:1038"
        },
        {
          "method": "org.eclipse.jface.wizard.WizardDialog$4.run",
          "source": "WizardDialog.java:1028"
        },
        {
          "method": "org.eclipse.swt.custom.BusyIndicator.showWhile",
          "source": "BusyIndicator.java:67"
        },
        {
          "method": "org.eclipse.jface.wizard.WizardDialog.showPage",
          "source": "WizardDialog.java:1026"
        },
        {
          "method": "org.eclipse.jface.wizard.WizardDialog.nextPressed",
          "source": "WizardDialog.java:757"
        },
        {
          "method": "org.eclipse.jface.wizard.WizardDialog.buttonPressed",
          "source": "WizardDialog.java:351"
        },
        {
          "method": "org.eclipse.jface.dialogs.Dialog$3.widgetSelected",
          "source": "Dialog.java:660"
        },
        {
          "method": "org.eclipse.swt.widgets.TypedListener.handleEvent",
          "source": "TypedListener.java:90"
        },
        {
          "method": "org.eclipse.swt.widgets.EventTable.sendEvent",
          "source": "EventTable.java:66"
        },
        {
          "method": "org.eclipse.swt.widgets.Widget.sendEvent",
          "source": "Widget.java:1085"
        },
        {
          "method": "org.eclipse.swt.widgets.Display.runDeferredEvents",
          "source": "Display.java:3166"
        },
        {
          "method": "org.eclipse.swt.widgets.Display.readAndDispatch",
          "source": "Display.java:2842"
        },
        {
          "method": "org.eclipse.jface.window.Window.runEventLoop",
          "source": "Window.java:820"
        },
        {
          "method": "org.eclipse.jface.window.Window.open",
          "source": "Window.java:796"
        },
        {
          "method": "org.eclipse.ui.actions.NewProjectAction.run",
          "source": "NewProjectAction.java:116"
        },
        {
          "method": "org.eclipse.jface.action.Action.runWithEvent",
          "source": "Action.java:499"
        },
        {
          "method": "org.eclipse.jface.action.ActionContributionItem.handleWidgetSelection",
          "source": "ActionContributionItem.java:539"
        },
        {
          "method": "org.eclipse.jface.action.ActionContributionItem.access$2",
          "source": "ActionContributionItem.java:488"
        },
        {
          "method": "org.eclipse.jface.action.ActionContributionItem$5.handleEvent",
          "source": "ActionContributionItem.java:400"
        },
        {
          "method": "org.eclipse.swt.widgets.EventTable.sendEvent",
          "source": "EventTable.java:66"
        },
        {
          "method": "org.eclipse.swt.widgets.Widget.sendEvent",
          "source": "Widget.java:1085"
        },
        {
          "method": "org.eclipse.swt.widgets.Display.runDeferredEvents",
          "source": "Display.java:3166"
        },
        {
          "method": "org.eclipse.swt.widgets.Display.readAndDispatch",
          "source": "Display.java:2842"
        },
        {
          "method": "org.eclipse.ui.internal.Workbench.runEventLoop",
          "source": "Workbench.java:1930"
        },
        {
          "method": "org.eclipse.ui.internal.Workbench.runUI",
          "source": "Workbench.java:1894"
        },
        {
          "method": "org.eclipse.ui.internal.Workbench.createAndRunWorkbench",
          "source": "Workbench.java:422"
        },
        {
          "method": "org.eclipse.ui.PlatformUI.createAndRunWorkbench",
          "source": "PlatformUI.java:149"
        },
        {
          "method": "org.eclipse.ui.internal.ide.IDEApplication.run",
          "source": "IDEApplication.java:95"
        },
        {
          "method": "org.eclipse.core.internal.runtime.PlatformActivator$1.run",
          "source": "PlatformActivator.java:78"
        },
        {
          "method": "org.eclipse.core.runtime.internal.adaptor.EclipseAppLauncher.runApplication",
          "source": "EclipseAppLauncher.java:92"
        },
        {
          "method": "org.eclipse.core.runtime.internal.adaptor.EclipseAppLauncher.start",
          "source": "EclipseAppLauncher.java:68"
        },
        {
          "method": "org.eclipse.core.runtime.adaptor.EclipseStarter.run",
          "source": "EclipseStarter.java:400"
        },
        {
          "method": "org.eclipse.core.runtime.adaptor.EclipseStarter.run",
          "source": "EclipseStarter.java:177"
        },
        {
          "method": "sun.reflect.NativeMethodAccessorImpl.invoke0",
          "source": "Native Method"
        },
        {
          "method": "sun.reflect.NativeMethodAccessorImpl.invoke",
          "source": "NativeMethodAccessorImpl.java:39"
        },
        {
          "method": "sun.reflect.DelegatingMethodAccessorImpl.invoke",
          "source": "DelegatingMethodAccessorImpl.java:25"
        },
        {
          "method": "java.lang.reflect.Method.invoke",
          "source": "Method.java:585"
        },
        {
          "method": "org.eclipse.core.launcher.Main.invokeFramework",
          "source": "Main.java:336"
        },
        {
          "method": "org.eclipse.core.launcher.Main.basicRun",
          "source": "Main.java:280"
        },
        {
          "method": "org.eclipse.core.launcher.Main.run",
          "source": "Main.java:977"
        },
        {
          "method": "org.eclipse.core.launcher.Main.main",
          "source": "Main.java:952"
        }
      ],
      "number": 0,
      "commentIndex": 0,
      "bugId": "191911",
      "date": "2007-06-11T11:30:06+02:00",
      "product": "CDT",
      "component": "cdt-build",
      "severity": "normal"
    }
  ],
  "groupId": "191911",
  "bugId": "191911",
  "date": "2007-06-11T11:30:06+02:00",
  "product": "CDT",
  "component": "cdt-build",
  "severity": "normal"
}