{
  "comments": [
    "steps to reproduce:\n\n   - use the attached report\n   - preview in deployed web viewer\n   - check tomcat console or birt log file\n\nexpected bahavior:\n\n   - report is rendered properly\n   - no exception thrown out in console or log file\n\nactual behavior:\n\n   - report was rendered properly\n   - but got following exception,\n\njava.lang.IndexOutOfBoundsException: Index: 0, Size: 0\n        at org.eclipse.birt.data.engine.olap.data.impl.CachedAggregationResultSe\nt.seek(CachedAggregationResultSet.java:406)\n        at org.eclipse.birt.data.engine.olap.data.impl.CachedAggregationResultSe\nt.\u003cinit\u003e(CachedAggregationResultSet.java:92)\n        at org.eclipse.birt.data.engine.olap.data.impl.AggregationResultSetSaveU\ntil.loadOneResultSet(AggregationResultSetSaveUtil.java:119)\n        at org.eclipse.birt.data.engine.olap.data.impl.AggregationResultSetSaveU\ntil.load(AggregationResultSetSaveUtil.java:83)\n        at org.eclipse.birt.data.engine.olap.query.view.QueryExecutor.execute(Qu\neryExecutor.java:95)\n        at org.eclipse.birt.data.engine.olap.query.view.BirtCubeView.getCubeCurs\nor(BirtCubeView.java:90)\n        at org.eclipse.birt.data.engine.olap.impl.query.CubeQueryResults.getCube\nCursor(CubeQueryResults.java:65)\n        at org.eclipse.birt.report.engine.data.dte.CubeResultSet.\u003cinit\u003e(CubeResu\nltSet.java:78)\n        at org.eclipse.birt.report.engine.data.dte.DataPresentationEngine.doExec\nuteCube(DataPresentationEngine.java:236)\n        at org.eclipse.birt.report.engine.data.dte.DataPresentationEngine.doExec\nuteQuery(DataPresentationEngine.java:161)\n        at org.eclipse.birt.report.engine.data.dte.AbstractDataEngine.execute(Ab\nstractDataEngine.java:178)\n        at org.eclipse.birt.report.engine.executor.ExecutionContext.executeQuery\n(ExecutionContext.java:1669)\n        at org.eclipse.birt.report.engine.internal.document.v4.ExtendedItemExecu\ntor.executeQuery(ExtendedItemExecutor.java:241)\n        at org.eclipse.birt.report.engine.internal.document.v4.ExtendedItemExecu\ntor.doExecute(ExtendedItemExecutor.java:221)\n        at org.eclipse.birt.report.engine.internal.document.v4.ExtendedItemExecu\ntor.execute(ExtendedItemExecutor.java:177)\n        at org.eclipse.birt.report.engine.internal.document.v4.ContainerExecutor\n.prepareChildExecutor(ContainerExecutor.java:213)\n        at org.eclipse.birt.report.engine.internal.document.v4.ContainerExecutor\n.hasNextChild(ContainerExecutor.java:98)\n        at org.eclipse.birt.report.engine.internal.document.v4.ReportPageExecuto\nrV4.hasNextChild(ReportPageExecutorV4.java:92)\n        at org.eclipse.birt.report.engine.internal.document.ReportExecutorWrappe\nr.hasNextChild(ReportExecutorWrapper.java:108)\n        at org.eclipse.birt.report.engine.internal.executor.wrap.WrappedReportEx\necutor.hasNextChild(WrappedReportExecutor.java:74)\n        at org.eclipse.birt.report.engine.internal.executor.wrap.WrappedReportEx\necutor.hasNextChild(WrappedReportExecutor.java:74)\n        at org.eclipse.birt.report.engine.layout.html.HTMLPageLM$1.hasNextChild(\nHTMLPageLM.java:64)\n        at org.eclipse.birt.report.engine.layout.html.HTMLPageLM.layoutChildren(\nHTMLPageLM.java:123)\n        at org.eclipse.birt.report.engine.layout.html.HTMLPageLM.layout(HTMLPage\nLM.java:84)\n        at org.eclipse.birt.report.engine.layout.html.HTMLReportLayoutEngine.lay\nout(HTMLReportLayoutEngine.java:90)\n        at org.eclipse.birt.report.engine.api.impl.RenderTask$PageRangeRender.re\nnder(RenderTask.java:532)\n        at org.eclipse.birt.report.engine.api.impl.RenderTask.render(RenderTask.\njava:254)\n        at org.eclipse.birt.report.service.ReportEngineService.renderReport(Unkn\nown Source)\n        at org.eclipse.birt.report.service.ReportEngineService.renderReport(Unkn\nown Source)\n        at org.eclipse.birt.report.service.BirtViewerReportService.getPage(Unkno\nwn Source)\n        at org.eclipse.birt.report.service.actionhandler.AbstractGetPageActionHa\nndler.doExecution(Unknown Source)\n        at org.eclipse.birt.report.service.actionhandler.AbstractGetPageActionHa\nndler.__execute(Unknown Source)\n        at org.eclipse.birt.report.service.actionhandler.AbstractBaseActionHandl\ner.execute(Unknown Source)\n        at org.eclipse.birt.report.soapengine.processor.AbstractBaseDocumentProc\nessor.__executeAction(Unknown Source)\n        at org.eclipse.birt.report.soapengine.processor.AbstractBaseComponentPro\ncessor.executeAction(Unknown Source)\n        at org.eclipse.birt.report.soapengine.processor.BirtDocumentProcessor.ha\nndleGetPage(Unknown Source)\n        at sun.reflect.NativeMethodAccessorImpl.invoke0(Native Method)\n        at sun.reflect.NativeMethodAccessorImpl.invoke(NativeMethodAccessorImpl.\njava:39)\n        at sun.reflect.DelegatingMethodAccessorImpl.invoke(DelegatingMethodAcces\nsorImpl.java:25)\n        at java.lang.reflect.Method.invoke(Method.java:585)\n        at org.eclipse.birt.report.soapengine.processor.AbstractBaseComponentPro\ncessor.process(Unknown Source)\n        at org.eclipse.birt.report.soapengine.endpoint.BirtSoapBindingImpl.getUp\ndatedObjects(Unknown Source)\n        at sun.reflect.NativeMethodAccessorImpl.invoke0(Native Method)\n        at sun.reflect.NativeMethodAccessorImpl.invoke(NativeMethodAccessorImpl.\njava:39)\n        at sun.reflect.DelegatingMethodAccessorImpl.invoke(DelegatingMethodAcces\nsorImpl.java:25)\n        at java.lang.reflect.Method.invoke(Method.java:585)\n        at org.apache.axis.providers.java.RPCProvider.invokeMethod(RPCProvider.j\nava:397)\n        at org.apache.axis.providers.java.RPCProvider.processMessage(RPCProvider\n.java:186)\n        at org.apache.axis.providers.java.JavaProvider.invoke(JavaProvider.java:\n323)\n        at org.apache.axis.strategies.InvocationStrategy.visit(InvocationStrateg\ny.java:32)\n        at org.apache.axis.SimpleChain.doVisiting(SimpleChain.java:118)\n        at org.apache.axis.SimpleChain.invoke(SimpleChain.java:83)\n        at org.apache.axis.handlers.soap.SOAPService.invoke(SOAPService.java:453\n)\n        at org.apache.axis.server.AxisServer.invoke(AxisServer.java:281)\n        at org.apache.axis.transport.http.AxisServlet.doPost(AxisServlet.java:69\n9)\n        at org.eclipse.birt.report.servlet.BirtSoapMessageDispatcherServlet.doPo\nst(Unknown Source)\n        at javax.servlet.http.HttpServlet.service(HttpServlet.java:709)\n        at org.apache.axis.transport.http.AxisServletBase.service(AxisServletBas\ne.java:327)\n        at javax.servlet.http.HttpServlet.service(HttpServlet.java:802)\n        at org.apache.catalina.core.ApplicationFilterChain.internalDoFilter(Appl\nicationFilterChain.java:252)\n        at org.apache.catalina.core.ApplicationFilterChain.doFilter(ApplicationF\nilterChain.java:173)\n        at org.apache.catalina.core.StandardWrapperValve.invoke(StandardWrapperV\nalve.java:214)\n        at org.apache.catalina.core.StandardContextValve.invoke(StandardContextV\nalve.java:178)\n        at org.apache.catalina.core.StandardHostValve.invoke(StandardHostValve.j\nava:126)\n        at org.apache.catalina.valves.ErrorReportValve.invoke(ErrorReportValve.j\nava:105)\n        at org.apache.catalina.core.StandardEngineValve.invoke(StandardEngineVal\nve.java:107)\n        at org.apache.catalina.connector.CoyoteAdapter.service(CoyoteAdapter.jav\na:148)\n        at org.apache.coyote.http11.Http11Processor.process(Http11Processor.java\n:825)\n        at org.apache.coyote.http11.Http11Protocol$Http11ConnectionHandler.proce\nssConnection(Http11Protocol.java:738)\n        at org.apache.tomcat.util.net.PoolTcpEndpoint.processSocket(PoolTcpEndpo\nint.java:526)\n        at org.apache.tomcat.util.net.LeaderFollowerWorkerThread.runIt(LeaderFol\nlowerWorkerThread.java:80)\n        at org.apache.tomcat.util.threads.ThreadPool$ControlRunnable.run(ThreadP\nool.java:684)\n        at java.lang.Thread.run(Thread.java:595)",
    "Created an attachment (id\u003d70938)\nreport design\n\n",
    "Add check for empty aggregation result. Fix the bug.",
    "Verified, 20070614"
  ],
  "commentCreationDates": [
    "2007-06-12T03:58:23+02:00",
    "2007-06-12T03:59:47+02:00",
    "2007-06-12T09:09:50+02:00",
    "2007-06-14T11:50:26+02:00"
  ],
  "traces": [
    {
      "exceptionType": "java.lang.IndexOutOfBoundsException",
      "message": "Index: 0, Size: 0",
      "elements": [
        {
          "method": "org.eclipse.birt.data.engine.olap.data.impl.CachedAggregationResultSet.seek",
          "source": "CachedAggregationResultSet.java:406"
        },
        {
          "method": "org.eclipse.birt.data.engine.olap.data.impl.CachedAggregationResultSet.\u003cinit\u003e",
          "source": "CachedAggregationResultSet.java:92"
        },
        {
          "method": "org.eclipse.birt.data.engine.olap.data.impl.AggregationResultSetSaveUtil.loadOneResultSet",
          "source": "AggregationResultSetSaveUtil.java:119"
        },
        {
          "method": "org.eclipse.birt.data.engine.olap.data.impl.AggregationResultSetSaveUtil.load",
          "source": "AggregationResultSetSaveUtil.java:83"
        },
        {
          "method": "org.eclipse.birt.data.engine.olap.query.view.QueryExecutor.execute",
          "source": "Qu eryExecutor.java:95"
        },
        {
          "method": "org.eclipse.birt.data.engine.olap.query.view.BirtCubeView.getCubeCursor",
          "source": "BirtCubeView.java:90"
        },
        {
          "method": "org.eclipse.birt.data.engine.olap.impl.query.CubeQueryResults.getCubeCursor",
          "source": "CubeQueryResults.java:65"
        },
        {
          "method": "org.eclipse.birt.report.engine.data.dte.CubeResultSet.\u003cinit\u003e",
          "source": "CubeResu ltSet.java:78"
        },
        {
          "method": "org.eclipse.birt.report.engine.data.dte.DataPresentationEngine.doExecuteCube",
          "source": "DataPresentationEngine.java:236"
        },
        {
          "method": "org.eclipse.birt.report.engine.data.dte.DataPresentationEngine.doExecuteQuery",
          "source": "DataPresentationEngine.java:161"
        },
        {
          "method": "org.eclipse.birt.report.engine.data.dte.AbstractDataEngine.execute",
          "source": "Ab stractDataEngine.java:178"
        },
        {
          "method": "org.eclipse.birt.report.engine.executor.ExecutionContext.executeQuery",
          "source": "ExecutionContext.java:1669"
        },
        {
          "method": "org.eclipse.birt.report.engine.internal.document.v4.ExtendedItemExecutor.executeQuery",
          "source": "ExtendedItemExecutor.java:241"
        },
        {
          "method": "org.eclipse.birt.report.engine.internal.document.v4.ExtendedItemExecutor.doExecute",
          "source": "ExtendedItemExecutor.java:221"
        },
        {
          "method": "org.eclipse.birt.report.engine.internal.document.v4.ExtendedItemExecutor.execute",
          "source": "ExtendedItemExecutor.java:177"
        },
        {
          "method": "org.eclipse.birt.report.engine.internal.document.v4.ContainerExecutor.prepareChildExecutor",
          "source": "ContainerExecutor.java:213"
        },
        {
          "method": "org.eclipse.birt.report.engine.internal.document.v4.ContainerExecutor.hasNextChild",
          "source": "ContainerExecutor.java:98"
        },
        {
          "method": "org.eclipse.birt.report.engine.internal.document.v4.ReportPageExecutorV4.hasNextChild",
          "source": "ReportPageExecutorV4.java:92"
        },
        {
          "method": "org.eclipse.birt.report.engine.internal.document.ReportExecutorWrapper.hasNextChild",
          "source": "ReportExecutorWrapper.java:108"
        },
        {
          "method": "org.eclipse.birt.report.engine.internal.executor.wrap.WrappedReportExecutor.hasNextChild",
          "source": "WrappedReportExecutor.java:74"
        },
        {
          "method": "org.eclipse.birt.report.engine.internal.executor.wrap.WrappedReportExecutor.hasNextChild",
          "source": "WrappedReportExecutor.java:74"
        },
        {
          "method": "org.eclipse.birt.report.engine.layout.html.HTMLPageLM$1.hasNextChild",
          "source": " HTMLPageLM.java:64"
        },
        {
          "method": "org.eclipse.birt.report.engine.layout.html.HTMLPageLM.layoutChildren",
          "source": " HTMLPageLM.java:123"
        },
        {
          "method": "org.eclipse.birt.report.engine.layout.html.HTMLPageLM.layout",
          "source": "HTMLPage LM.java:84"
        },
        {
          "method": "org.eclipse.birt.report.engine.layout.html.HTMLReportLayoutEngine.layout",
          "source": "HTMLReportLayoutEngine.java:90"
        },
        {
          "method": "org.eclipse.birt.report.engine.api.impl.RenderTask$PageRangeRender.render",
          "source": "RenderTask.java:532"
        },
        {
          "method": "org.eclipse.birt.report.engine.api.impl.RenderTask.render",
          "source": "RenderTask. java:254"
        },
        {
          "method": "org.eclipse.birt.report.service.ReportEngineService.renderReport",
          "source": "Unkn own Source"
        },
        {
          "method": "org.eclipse.birt.report.service.ReportEngineService.renderReport",
          "source": "Unkn own Source"
        },
        {
          "method": "org.eclipse.birt.report.service.BirtViewerReportService.getPage",
          "source": "Unkno wn Source"
        },
        {
          "method": "org.eclipse.birt.report.service.actionhandler.AbstractGetPageActionHandler.doExecution",
          "source": "Unknown Source"
        },
        {
          "method": "org.eclipse.birt.report.service.actionhandler.AbstractGetPageActionHandler.__execute",
          "source": "Unknown Source"
        },
        {
          "method": "org.eclipse.birt.report.service.actionhandler.AbstractBaseActionHandler.execute",
          "source": "Unknown Source"
        },
        {
          "method": "org.eclipse.birt.report.soapengine.processor.AbstractBaseDocumentProcessor.__executeAction",
          "source": "Unknown Source"
        },
        {
          "method": "org.eclipse.birt.report.soapengine.processor.AbstractBaseComponentProcessor.executeAction",
          "source": "Unknown Source"
        },
        {
          "method": "org.eclipse.birt.report.soapengine.processor.BirtDocumentProcessor.handleGetPage",
          "source": "Unknown Source"
        },
        {
          "method": "sun.reflect.NativeMethodAccessorImpl.invoke0",
          "source": "Native Method"
        },
        {
          "method": "sun.reflect.NativeMethodAccessorImpl.invoke",
          "source": "NativeMethodAccessorImpl. java:39"
        },
        {
          "method": "sun.reflect.DelegatingMethodAccessorImpl.invoke",
          "source": "DelegatingMethodAcces sorImpl.java:25"
        },
        {
          "method": "java.lang.reflect.Method.invoke",
          "source": "Method.java:585"
        },
        {
          "method": "org.eclipse.birt.report.soapengine.processor.AbstractBaseComponentProcessor.process",
          "source": "Unknown Source"
        },
        {
          "method": "org.eclipse.birt.report.soapengine.endpoint.BirtSoapBindingImpl.getUpdatedObjects",
          "source": "Unknown Source"
        },
        {
          "method": "sun.reflect.NativeMethodAccessorImpl.invoke0",
          "source": "Native Method"
        },
        {
          "method": "sun.reflect.NativeMethodAccessorImpl.invoke",
          "source": "NativeMethodAccessorImpl. java:39"
        },
        {
          "method": "sun.reflect.DelegatingMethodAccessorImpl.invoke",
          "source": "DelegatingMethodAcces sorImpl.java:25"
        },
        {
          "method": "java.lang.reflect.Method.invoke",
          "source": "Method.java:585"
        },
        {
          "method": "org.apache.axis.providers.java.RPCProvider.invokeMethod",
          "source": "RPCProvider.j ava:397"
        },
        {
          "method": "org.apache.axis.providers.java.RPCProvider.processMessage",
          "source": "RPCProvider .java:186"
        },
        {
          "method": "org.apache.axis.providers.java.JavaProvider.invoke",
          "source": "JavaProvider.java: 323"
        },
        {
          "method": "org.apache.axis.strategies.InvocationStrategy.visit",
          "source": "InvocationStrateg y.java:32"
        },
        {
          "method": "org.apache.axis.SimpleChain.doVisiting",
          "source": "SimpleChain.java:118"
        },
        {
          "method": "org.apache.axis.SimpleChain.invoke",
          "source": "SimpleChain.java:83"
        },
        {
          "method": "org.apache.axis.handlers.soap.SOAPService.invoke",
          "source": "SOAPService.java:453 "
        },
        {
          "method": "org.apache.axis.server.AxisServer.invoke",
          "source": "AxisServer.java:281"
        },
        {
          "method": "org.apache.axis.transport.http.AxisServlet.doPost",
          "source": "AxisServlet.java:69 9"
        },
        {
          "method": "org.eclipse.birt.report.servlet.BirtSoapMessageDispatcherServlet.doPost",
          "source": "Unknown Source"
        },
        {
          "method": "javax.servlet.http.HttpServlet.service",
          "source": "HttpServlet.java:709"
        },
        {
          "method": "org.apache.axis.transport.http.AxisServletBase.service",
          "source": "AxisServletBas e.java:327"
        },
        {
          "method": "javax.servlet.http.HttpServlet.service",
          "source": "HttpServlet.java:802"
        },
        {
          "method": "org.apache.catalina.core.ApplicationFilterChain.internalDoFilter",
          "source": "Appl icationFilterChain.java:252"
        },
        {
          "method": "org.apache.catalina.core.ApplicationFilterChain.doFilter",
          "source": "ApplicationF ilterChain.java:173"
        },
        {
          "method": "org.apache.catalina.core.StandardWrapperValve.invoke",
          "source": "StandardWrapperV alve.java:214"
        },
        {
          "method": "org.apache.catalina.core.StandardContextValve.invoke",
          "source": "StandardContextV alve.java:178"
        },
        {
          "method": "org.apache.catalina.core.StandardHostValve.invoke",
          "source": "StandardHostValve.j ava:126"
        },
        {
          "method": "org.apache.catalina.valves.ErrorReportValve.invoke",
          "source": "ErrorReportValve.j ava:105"
        },
        {
          "method": "org.apache.catalina.core.StandardEngineValve.invoke",
          "source": "StandardEngineVal ve.java:107"
        },
        {
          "method": "org.apache.catalina.connector.CoyoteAdapter.service",
          "source": "CoyoteAdapter.jav a:148"
        },
        {
          "method": "org.apache.coyote.http11.Http11Processor.process",
          "source": "Http11Processor.java :825"
        },
        {
          "method": "org.apache.coyote.http11.Http11Protocol$Http11ConnectionHandler.processConnection",
          "source": "Http11Protocol.java:738"
        },
        {
          "method": "org.apache.tomcat.util.net.PoolTcpEndpoint.processSocket",
          "source": "PoolTcpEndpo int.java:526"
        },
        {
          "method": "org.apache.tomcat.util.net.LeaderFollowerWorkerThread.runIt",
          "source": "LeaderFol lowerWorkerThread.java:80"
        },
        {
          "method": "org.apache.tomcat.util.threads.ThreadPool$ControlRunnable.run",
          "source": "ThreadP ool.java:684"
        },
        {
          "method": "java.lang.Thread.run",
          "source": "Thread.java:595"
        }
      ],
      "number": 0,
      "commentIndex": 0,
      "bugId": "192074",
      "date": "2007-06-12T03:58:23+02:00",
      "product": "BIRT",
      "component": "Data",
      "severity": "normal"
    }
  ],
  "groupId": "192074",
  "bugId": "192074",
  "date": "2007-06-12T03:58:23+02:00",
  "product": "BIRT",
  "component": "Data",
  "severity": "normal"
}