{
  "comments": [
    "I downloaded F2 and chmod\u0027ed the files:\n\n   ./plugins/org.eclipse.swt.motif_2.0.0/os/hpux/hp9000/libswt-cde-motif-2043.sl\n   ./plugins/org.eclipse.swt.motif_2.0.0/os/hpux/hp9000/libswt-motif-2043.sl\n\nUname output:\n\n   uname -a\n   HP-UX jefe B.11.11 U 9000/800 686349373 unlimited-user license\n\nThe output from the command line:\n\n./eclipse -nosplash -debug\nStart VM: /opt/java1.3/bin/java\n-classpath /aoi/troym/eclipse/./startup.jar org.eclipse.core.launcher.Main\n-os hpux\n-ws motif\n-arch hp9000\n-debug\nStartup: using configuration file:/aoi/troym/eclipse/workspace/.metadata/.config/plat\nform.cfg\nBoot URL: file:/aoi/troym/eclipse/plugins/org.eclipse.core.boot_2.0.0/boot.jar\nWorkspace location:\n   /aoi/troym/eclipse/workspace\nDebug-Options:\n    file:/aoi/troym/eclipse/.options\nInstall URL:\n    file:/aoi/troym/eclipse/\njava.lang.NullPointerException\n        at org.eclipse.swt.graphics.Device.\u003cinit\u003e(Device.java:113)\n        at org.eclipse.swt.widgets.Display.\u003cinit\u003e(Display.java:318)\n        at org.eclipse.swt.widgets.Display.\u003cinit\u003e(Display.java:315)\n        at org.eclipse.ui.internal.Workbench.run(Workbench.java:1142)\n        at org.eclipse.core.internal.boot.InternalBootLoader.run(InternalBootLoader.j\nava:739)\n        at org.eclipse.core.boot.BootLoader.run(BootLoader.java:462)\n        at java.lang.reflect.Method.invoke(Native Method)\n        at org.eclipse.core.launcher.Main.basicRun(Main.java:244)\n        at org.eclipse.core.launcher.Main.run(Main.java:693)\n        at org.eclipse.core.launcher.Main.main(Main.java:526)\n\n\nIn the file \"workspace/.metadata/.log\":\n\n!SESSION Jun 04, 2002 11:10:31.946 ---------------------------------------------\njava.version\u003d1.3.1.02\njava.vendor\u003dHewlett-Packard Co.\nBootLoader constants: OS\u003dhpux, ARCH\u003dhp9000, WS\u003dmotif, NL\u003den\nCommand-line arguments: -os hpux -ws motif -arch hp9000 -install file:/aoi/troym\n/eclipse/\n!ENTRY org.eclipse.update.core 4 0 Jun 04, 2002 11:10:31.948\n!MESSAGE The URL:platform:/base/plugins/org.eclipse.platform.hpux.motif_2.0.0.jar doesn\u0027t point to a valid platform plugin.The URL will not be written in the platform configuration [java.lang.Exception]\n!STACK 0\njava.lang.Exception\n        at org.eclipse.update.internal.core.InstallConfiguration.getRuntimeConfigurationURL(InstallConfiguration.java:826)\n        at org.eclipse.update.internal.core.InstallConfiguration.saveFeatureEntry(InstallConfiguration.java:469)\n        at org.eclipse.update.internal.core.InstallConfiguration.save(InstallConfiguration.java:386)\n        at org.eclipse.update.internal.core.SiteLocal.save(SiteLocal.java:213)\n        at org.eclipse.update.internal.core.SiteReconciler.reconcile(SiteReconciler.java:205)\n        at org.eclipse.update.internal.core.SiteLocal.reconcile(SiteLocal.java:558)\n        at org.eclipse.update.internal.core.SiteLocal.internalGetLocalSite(SiteLocal.java:90)\n        at org.eclipse.update.internal.core.InternalSiteManager.internalGetLocalSite(InternalSiteManager.java:65)\n        at org.eclipse.update.internal.core.InternalSiteManager.reconcile(InternalSiteManager.java:412)\n        at org.eclipse.update.internal.core.UpdateManagerReconciler.reconcile(UpdateManagerReconciler.java:136)\n        at org.eclipse.update.internal.core.UpdateManagerReconciler.run(UpdateManagerReconciler.java:80)\n        at org.eclipse.core.internal.boot.InternalBootLoader.run(InternalBootLoader.java:739)\n        at org.eclipse.core.boot.BootLoader.run(BootLoader.java:462)\n        at java.lang.reflect.Method.invoke(Native Method)\n        at org.eclipse.core.launcher.Main.basicRun(Main.java:244)\n        at org.eclipse.core.launcher.Main.run(Main.java:693)\n        at org.eclipse.core.launcher.Main.main(Main.java:526)",
    "Workspace log shows install problem. GG to look at NPE in Display creation \ncode.\n",
    "... just passing the buck back (with additional info).\n\nThe F2 HP-UX build has a bogus org.eclipse.platform.hpux.motif_2.0.0 plugin (is \nan empty directory). This was reported in bug 19230.\n\nThe update message in the log was reported in bug 18952 and fix is in HEAD \n(\"low hanging fruit\" trivial problem). The problem was us incorrectly logging \nwhat should have been just a warning trace message (were calling our log() \ninstead of warn() internal methods). We were detecting the problem above (bug \n19230). Eclipse continues to start up after this (have observed this in our own \nHP-UX testing).\n\nSo apart from the build problem, the only remaining thing is the NPE.\n\nBack to SWT ...",
    "Not sure why this is happening. Sridhar to investigate. Remember, if we want \nthis fixed it has to get ok\u0027ed by 2 TLs at this point. Let me know asap.\n",
    "Interestingly a question with this exact trace was asked on EC recently, and \ngot the following response:\n\n   We had a similar problem a few months ago. Our problems was that in the\n   Solaris server we had only one font group and that was not the one Eclipse\n   search. I cannot remember which was the good but we had now a \u0027Default\u0027 and\n   a \u0027System\u0027 font group set in the Font Style manager. If you had only one of\n   these try to add the other one.\n\nThe shortcut to the thread is http://www.eclipse.org/newsportal/article.php3?\nid\u003d27217\u0026group\u003declipse.tools\n",
    "Ok! I am not able to get NullPointerException, it works perfectly\nfine once I fix those permissions. Here is my log...\n\nsbidigal (32) \u003e ./eclipse -nosplash -debug\nStart VM: /opt/java1.3/bin/java\n-classpath\n/tmp_mnt/net/ma-homes/homes/sbidigal/eclipse/20020602/eclipse/./startup.jar\norg.eclipse.core.launcher.Main\n-os hpux\n-ws motif\n-arch hp9000\n-debug \nStartup: using configuration\nfile:/tmp_mnt/net/ma-homes/homes/sbidigal/eclipse/20020602/eclipse/workspace/.metadata/.config/platform.cfg\nBoot URL:\nfile:/tmp_mnt/net/ma-homes/homes/sbidigal/eclipse/20020602/eclipse/plugins/org.eclipse.core.boot_2.0.0/boot.jar\nWorkspace location:\n   /tmp_mnt/net/ma-homes/homes/sbidigal/eclipse/20020602/eclipse/workspace\nDebug-Options:\n    file:/tmp_mnt/net/ma-homes/homes/sbidigal/eclipse/20020602/eclipse/.options\nInstall URL:\n    file:/tmp_mnt/net/ma-homes/homes/sbidigal/eclipse/20020602/eclipse/\n\nI suspect this has do with the monitor he is using. Can you please\nprovide me the xdpyinfo(X display info. or run SAM) and try running \neclipse on a different platform using the same monitor. I want to know,\nspecifically the depth and the colormap used, basically X server \nconfiguration of your system. Thanks!",
    "The X-Server is a PC running ReflectionX 8.05.  Here is the output:\n\nname of display:    troympc.rsn.hp.com:0.0\nversion number:    11.0\nvendor string:    WRQ, Inc.\nvendor release number:    8\nmaximum request size:  4194300 bytes\nmotion buffer size:  0\nbitmap unit, bit order, padding:    32, MSBFirst, 32\nimage byte order:    MSBFirst\nnumber of supported pixmap formats:    3\nsupported pixmap formats:\n    depth 1, bits_per_pixel 1, scanline_pad 32\n    depth 24, bits_per_pixel 32, scanline_pad 32\n    depth 8, bits_per_pixel 8, scanline_pad 32\nkeycode range:    minimum 9, maximum 254\nfocus:  window 0x200000e, revert to PointerRoot\nnumber of extensions:    18\n    BIG-REQUESTS\n    DEC-XTRAP\n    Extended-Visual-Information\n    GLX\n    LBX\n    MIT-SUNDRY-NONSTANDARD\n    Multi-Buffering\n    SECURITY\n    SGI-GLX\n    SHAPE\n    SYNC\n    TOG-CUP\n    WRQ-ADMIN\n    WRQ_XPrint\n    XC-APPGROUP\n    XIE\n    XInputExtension\n    XTEST\ndefault screen number:    0\nnumber of screens:    1\n\nscreen #0:\n  dimensions:    1280x1024 pixels (394x305 millimeters)\n  resolution:    83x85 dots per inch\n  depths (3):    1, 24, 8\n  root window id:    0x28\n  depth of root window:    24 planes\n  number of colormaps:    minimum 1, maximum 1\n  default colormap:    0x24\n  default number of colormap cells:    256\n  preallocated pixels:    black 0, white 16777215\n  options:    backing-store YES, save-unders NO\n  largest cursor:    32x32\n  current input event mask:    0x400000\n    PropertyChangeMask\n  number of visuals:    4\n  default visual id:  0x20\n  visual:\n    visual id:    0x20\n    class:    TrueColor\n    depth:    24 planes\n    available colormap entries:    256 per subfield\n    red, green, blue masks:    0xff, 0xff00, 0xff0000\n    significant bits in color specification:    8 bits\n  visual:\n    visual id:    0x21\n    class:    TrueColor\n    depth:    24 planes\n    available colormap entries:    256 per subfield\n    red, green, blue masks:    0xff, 0xff00, 0xff0000\n    significant bits in color specification:    8 bits\n  visual: \n    visual id:    0x22\n    class:    PseudoColor\n    depth:    8 planes\n    available colormap entries:    256\n    red, green, blue masks:    0x0, 0x0, 0x0\n    significant bits in color specification:    8 bits\n  visual:\n    visual id:    0x23    \n    class:    PseudoColor\n    depth:    8 planes\n    available colormap entries:    256\n    red, green, blue masks:    0x0, 0x0, 0x0 \n    significant bits in color specification:    8 bits",
    "On a stock hp712.  The build on the same host runs fine.  Here is the display info:\n\nname of display:    bball:0.0\nversion number:    11.0\nvendor string:    Hewlett-Packard Company\nvendor release number:    600000\nmaximum request size:  4194300 bytes\nmotion buffer size:  100\nbitmap unit, bit order, padding:    32, MSBFirst, 32\nimage byte order:    MSBFirst\nnumber of supported pixmap formats:    3\nsupported pixmap formats:\n    depth 1, bits_per_pixel 1, scanline_pad 32\n    depth 8, bits_per_pixel 8, scanline_pad 32\n    depth 16, bits_per_pixel 16, scanline_pad 32\nkeycode range:    minimum 16, maximum 141\nfocus:  window 0x200000e, revert to PointerRoot\nnumber of extensions:    13\n    BIG-REQUESTS\n    DOUBLE-BUFFER\n    HP-SMT\n    HPExtension\n    MIT-SHM\n    MIT-SUNDRY-NONSTANDARD\n    Multi-Buffering\n    SHAPE\n    X3D-PEX\n    XIE\n    XInputExtension\n    XTEST\n    XTestExtension1\ndefault screen number:    0\nnumber of screens:    1\n\nscreen #0:\n  dimensions:    1280x1024 pixels (342x273 millimeters)\n  resolution:    95x95 dots per inch\n  depths (3):    1, 8, 16\n  root window id:    0x24\n  depth of root window:    8 planes\n  number of colormaps:    minimum 1, maximum 2\n  default colormap:    0x22\n  default number of colormap cells:    256\n  preallocated pixels:    black 0, white 1\n  options:    backing-store YES, save-unders YES\n  largest cursor:    64x64\n  current input event mask:    0xd0001d\n    KeyPressMask             ButtonPressMask          ButtonReleaseMask        \n    EnterWindowMask          SubstructureRedirectMask PropertyChangeMask       \n    ColormapChangeMask       \n  number of visuals:    2\n  default visual id:  0x20\n  visual:\n    visual id:    0x20\n    class:    PseudoColor\n    depth:    8 planes\n    available colormap entries:    256\n    red, green, blue masks:    0x0, 0x0, 0x0\n    significant bits in color specification:    8 bits\n  visual:\n    visual id:    0x21\n    class:    TrueColor\n    depth:    8 planes\n    available colormap entries:    8 per subfield\n    red, green, blue masks:    0xe0, 0x1c, 0x3\n    significant bits in color specification:    8 bits\n",
    "\nI will have to try this on Monday, since I don\u0027t have a\nPC system at Rational, Lexington. Is it possible for \nanyone at OTI, to quickly  go thru. it and confirm. Thanks!",
    "You can close this bug.  I have it working.  I pulled the source and started\nlooking around and found that it was font related.\n\nI changed the ReflectionX font search path to;\n\n   100dpi 75dpi misc hp sun ibm dec\n\nand I have the GUI up.  Thanks for your help.",
    "User error, case closed."
  ],
  "commentCreationDates": [
    "2002-06-04T22:25:23+02:00",
    "2002-06-05T19:36:40+02:00",
    "2002-06-05T20:00:24+02:00",
    "2002-06-05T20:18:28+02:00",
    "2002-06-06T18:54:23+02:00",
    "2002-06-07T17:27:10+02:00",
    "2002-06-07T17:41:02+02:00",
    "2002-06-07T17:45:37+02:00",
    "2002-06-07T17:49:12+02:00",
    "2002-06-07T23:18:01+02:00",
    "2002-06-11T23:11:30+02:00"
  ],
  "traces": [
    {
      "exceptionType": "java.lang.NullPointerException",
      "elements": [
        {
          "method": "org.eclipse.swt.graphics.Device.\u003cinit\u003e",
          "source": "Device.java:113"
        },
        {
          "method": "org.eclipse.swt.widgets.Display.\u003cinit\u003e",
          "source": "Display.java:318"
        },
        {
          "method": "org.eclipse.swt.widgets.Display.\u003cinit\u003e",
          "source": "Display.java:315"
        },
        {
          "method": "org.eclipse.ui.internal.Workbench.run",
          "source": "Workbench.java:1142"
        },
        {
          "method": "org.eclipse.core.internal.boot.InternalBootLoader.run",
          "source": "InternalBootLoader.j ava:739"
        },
        {
          "method": "org.eclipse.core.boot.BootLoader.run",
          "source": "BootLoader.java:462"
        },
        {
          "method": "java.lang.reflect.Method.invoke",
          "source": "Native Method"
        },
        {
          "method": "org.eclipse.core.launcher.Main.basicRun",
          "source": "Main.java:244"
        },
        {
          "method": "org.eclipse.core.launcher.Main.run",
          "source": "Main.java:693"
        },
        {
          "method": "org.eclipse.core.launcher.Main.main",
          "source": "Main.java:526"
        }
      ],
      "number": 0,
      "commentIndex": 0,
      "bugId": "19209",
      "date": "2002-06-04T22:25:23+02:00",
      "product": "Platform",
      "component": "SWT",
      "severity": "major"
    },
    {
      "exceptionType": "java.lang.Exception",
      "elements": [
        {
          "method": "org.eclipse.update.internal.core.InstallConfiguration.getRuntimeConfigurationURL",
          "source": "InstallConfiguration.java:826"
        },
        {
          "method": "org.eclipse.update.internal.core.InstallConfiguration.saveFeatureEntry",
          "source": "InstallConfiguration.java:469"
        },
        {
          "method": "org.eclipse.update.internal.core.InstallConfiguration.save",
          "source": "InstallConfiguration.java:386"
        },
        {
          "method": "org.eclipse.update.internal.core.SiteLocal.save",
          "source": "SiteLocal.java:213"
        },
        {
          "method": "org.eclipse.update.internal.core.SiteReconciler.reconcile",
          "source": "SiteReconciler.java:205"
        },
        {
          "method": "org.eclipse.update.internal.core.SiteLocal.reconcile",
          "source": "SiteLocal.java:558"
        },
        {
          "method": "org.eclipse.update.internal.core.SiteLocal.internalGetLocalSite",
          "source": "SiteLocal.java:90"
        },
        {
          "method": "org.eclipse.update.internal.core.InternalSiteManager.internalGetLocalSite",
          "source": "InternalSiteManager.java:65"
        },
        {
          "method": "org.eclipse.update.internal.core.InternalSiteManager.reconcile",
          "source": "InternalSiteManager.java:412"
        },
        {
          "method": "org.eclipse.update.internal.core.UpdateManagerReconciler.reconcile",
          "source": "UpdateManagerReconciler.java:136"
        },
        {
          "method": "org.eclipse.update.internal.core.UpdateManagerReconciler.run",
          "source": "UpdateManagerReconciler.java:80"
        },
        {
          "method": "org.eclipse.core.internal.boot.InternalBootLoader.run",
          "source": "InternalBootLoader.java:739"
        },
        {
          "method": "org.eclipse.core.boot.BootLoader.run",
          "source": "BootLoader.java:462"
        },
        {
          "method": "java.lang.reflect.Method.invoke",
          "source": "Native Method"
        },
        {
          "method": "org.eclipse.core.launcher.Main.basicRun",
          "source": "Main.java:244"
        },
        {
          "method": "org.eclipse.core.launcher.Main.run",
          "source": "Main.java:693"
        },
        {
          "method": "org.eclipse.core.launcher.Main.main",
          "source": "Main.java:526"
        }
      ],
      "number": 1,
      "commentIndex": 0,
      "bugId": "19209",
      "date": "2002-06-04T22:25:23+02:00",
      "product": "Platform",
      "component": "SWT",
      "severity": "major"
    }
  ],
  "groupId": "19209",
  "bugId": "19209",
  "date": "2002-06-04T22:25:23+02:00",
  "product": "Platform",
  "component": "SWT",
  "severity": "major"
}