{
  "comments": [
    "Like Reported in the newsgroup on 12.06.2007 here is a code snipped to reproduce my Problem with refreshing a table.\nTry this ViewPart in the Workbench. Run it and enter one character in the criteria search composite. 4 Items wil be displayed. Select the last item in the list (ebay.de), it should be marked as selected. Enter a second character in the criteria text field. The table should be refreshed but an index out of bounds error in thrown.\n\nHere is the code snipped:\n\npublic class SMTPDomainSearchView extends ViewPart {\n\t\n\tprivate TableViewer tableViewer;\n\tprivate Table table;\n\tprivate Text criteria;\n\n\tpublic void createPartControl( final Composite parent ) {\n\n\t\tcriteria \u003d new Text ( parent, SWT.BORDER  );\n\t\tcriteria.setText( \"\" );\n\t\tcriteria.addModifyListener( new ModifyListener() {\n\t\t\tpublic void modifyText( final ModifyEvent e ) {\n\t\t\t\t\n\t\t\t\ttableViewer.setInput( criteria.getText() );\n\n\t\t\t}\n\t\t});\n\t\t\n\t\ttable \u003d new Table( parent, SWT.NONE );\n\t\ttableViewer \u003d new TableViewer( table );\n\t\ttableViewer.setContentProvider( new TableContentProvider() );\n\t\ttableViewer.setLabelProvider( new TableLabelProvider() );\n\t\t\n\t}\n\n\n\tpublic void setFocus() {\n\t\t\n\t}\n\n\tprivate class TableContentProvider implements IStructuredContentProvider {\n\n\t\tpublic Object[] getElements( final Object inputElement ) {\n\t\t\t\n\t\t\tString t1 \u003d \"todo.de\";\n\t\t\tString t2 \u003d \"code.de\";\n\t\t\tString t3 \u003d \"mock.de\";\n\t\t\tString t4 \u003d \"ebay.de\";\n\t\t\t\n\t\t\tif (((String) inputElement).length() \u003e 1) {\n\t\t\t\tObject[] o \u003d { t1, t2 };\n\t\t\t\treturn o;\n\t\t\t} else {\n\t\t\t\t\t\t\t\n\t\t\t\tObject[] o \u003d { t1, t2, t3, t4};\n\t\t\t\treturn o;\n\t\t\t}\n\t\t}\n\n\t\tpublic void dispose() {\n\t\t\t\n\t\t}\n\n\t\tpublic void inputChanged( final Viewer viewer,\n\t\t\t\tfinal Object oldInput,\n\t\t\t\tfinal Object newInput )\n\t\t{\n\n\t\t}\n\t}\n\n\tprivate class TableLabelProvider \n\textends LabelProvider\n\timplements ITableLabelProvider\n\t{ \n\n\t\tpublic Image getColumnImage( final Object element, \n\t\t\t\tfinal int columnIndex )\n\t\t{\n\t\t\treturn null;\n\t\t}\n\n\t\tpublic String getColumnText( final Object element, \n\t\t\t\tfinal int columnIndex )\n\t\t{\n\t\t\treturn (String) element;\n\t\t}\n\t}\n}\n\nAnd the error :\n\n\njava.lang.IllegalArgumentException: Index out of bounds\n\tat org.eclipse.swt.SWT.error(SWT.java:629)\n\tat org.eclipse.swt.SWT.error(SWT.java:588)\n\tat org.eclipse.swt.SWT.error(SWT.java:584)\n\tat org.eclipse.swt.internal.widgets.ItemHolder.getItem(ItemHolder.java:102)\n\tat org.eclipse.swt.widgets.Table.getItem(Table.java:387)\n\tat org.eclipse.swt.internal.widgets.tableitemkit.TableItemLCA.isFocused(TableItemLCA.java:231)\n\tat org.eclipse.swt.internal.widgets.tableitemkit.TableItemLCA.writeFocused(TableItemLCA.java:178)\n\tat org.eclipse.swt.internal.widgets.tableitemkit.TableItemLCA.renderChanges(TableItemLCA.java:96)\n\tat org.eclipse.swt.lifecycle.AbstractWidgetLCA.render(AbstractWidgetLCA.java:55)\n\tat org.eclipse.swt.internal.widgets.displaykit.DisplayLCA$RenderVisitor.render(DisplayLCA.java:63)\n\tat org.eclipse.swt.internal.widgets.displaykit.DisplayLCA$RenderVisitor.doVisit(DisplayLCA.java:47)\n\tat org.eclipse.swt.internal.widgets.WidgetTreeVisitor$AllWidgetTreeVisitor.visit(WidgetTreeVisitor.java:25)\n\tat org.eclipse.swt.internal.widgets.WidgetTreeVisitor.accept(WidgetTreeVisitor.java:56)\n\tat org.eclipse.swt.internal.widgets.WidgetTreeVisitor.handleItems(WidgetTreeVisitor.java:88)\n\tat org.eclipse.swt.internal.widgets.WidgetTreeVisitor.accept(WidgetTreeVisitor.java:45)\n\tat org.eclipse.swt.internal.widgets.WidgetTreeVisitor.accept(WidgetTreeVisitor.java:48)\n\tat org.eclipse.swt.internal.widgets.WidgetTreeVisitor.accept(WidgetTreeVisitor.java:48)\n\tat org.eclipse.swt.internal.widgets.WidgetTreeVisitor.accept(WidgetTreeVisitor.java:48)\n\tat org.eclipse.swt.internal.widgets.WidgetTreeVisitor.accept(WidgetTreeVisitor.java:48)\n\tat org.eclipse.swt.internal.widgets.WidgetTreeVisitor.accept(WidgetTreeVisitor.java:48)\n\tat org.eclipse.swt.internal.widgets.displaykit.DisplayLCA.render(DisplayLCA.java:133)\n\tat org.eclipse.swt.internal.lifecycle.Render.execute(Render.java:28)\n\tat org.eclipse.swt.internal.lifecycle.RWTLifeCycle.execute(RWTLifeCycle.java:81)\n\tat com.w4t.engine.W4TModel$ServiceAdapter.execute(W4TModel.java:47)\n\tat com.w4t.engine.service.FormRequestServiceHandler.service(FormRequestServiceHandler.java:65)\n\tat com.w4t.engine.service.ServiceManager$HandlerDispatcher.service(ServiceManager.java:104)\n\tat com.w4t.engine.W4TDelegate.doPost(W4TDelegate.java:75)",
    "Fixed in CVS HEAD"
  ],
  "commentCreationDates": [
    "2007-06-12T17:15:39+02:00",
    "2007-06-13T17:48:20+02:00"
  ],
  "traces": [
    {
      "exceptionType": "java.lang.IllegalArgumentException",
      "message": "Index out of bounds",
      "elements": [
        {
          "method": "org.eclipse.swt.SWT.error",
          "source": "SWT.java:629"
        },
        {
          "method": "org.eclipse.swt.SWT.error",
          "source": "SWT.java:588"
        },
        {
          "method": "org.eclipse.swt.SWT.error",
          "source": "SWT.java:584"
        },
        {
          "method": "org.eclipse.swt.internal.widgets.ItemHolder.getItem",
          "source": "ItemHolder.java:102"
        },
        {
          "method": "org.eclipse.swt.widgets.Table.getItem",
          "source": "Table.java:387"
        },
        {
          "method": "org.eclipse.swt.internal.widgets.tableitemkit.TableItemLCA.isFocused",
          "source": "TableItemLCA.java:231"
        },
        {
          "method": "org.eclipse.swt.internal.widgets.tableitemkit.TableItemLCA.writeFocused",
          "source": "TableItemLCA.java:178"
        },
        {
          "method": "org.eclipse.swt.internal.widgets.tableitemkit.TableItemLCA.renderChanges",
          "source": "TableItemLCA.java:96"
        },
        {
          "method": "org.eclipse.swt.lifecycle.AbstractWidgetLCA.render",
          "source": "AbstractWidgetLCA.java:55"
        },
        {
          "method": "org.eclipse.swt.internal.widgets.displaykit.DisplayLCA$RenderVisitor.render",
          "source": "DisplayLCA.java:63"
        },
        {
          "method": "org.eclipse.swt.internal.widgets.displaykit.DisplayLCA$RenderVisitor.doVisit",
          "source": "DisplayLCA.java:47"
        },
        {
          "method": "org.eclipse.swt.internal.widgets.WidgetTreeVisitor$AllWidgetTreeVisitor.visit",
          "source": "WidgetTreeVisitor.java:25"
        },
        {
          "method": "org.eclipse.swt.internal.widgets.WidgetTreeVisitor.accept",
          "source": "WidgetTreeVisitor.java:56"
        },
        {
          "method": "org.eclipse.swt.internal.widgets.WidgetTreeVisitor.handleItems",
          "source": "WidgetTreeVisitor.java:88"
        },
        {
          "method": "org.eclipse.swt.internal.widgets.WidgetTreeVisitor.accept",
          "source": "WidgetTreeVisitor.java:45"
        },
        {
          "method": "org.eclipse.swt.internal.widgets.WidgetTreeVisitor.accept",
          "source": "WidgetTreeVisitor.java:48"
        },
        {
          "method": "org.eclipse.swt.internal.widgets.WidgetTreeVisitor.accept",
          "source": "WidgetTreeVisitor.java:48"
        },
        {
          "method": "org.eclipse.swt.internal.widgets.WidgetTreeVisitor.accept",
          "source": "WidgetTreeVisitor.java:48"
        },
        {
          "method": "org.eclipse.swt.internal.widgets.WidgetTreeVisitor.accept",
          "source": "WidgetTreeVisitor.java:48"
        },
        {
          "method": "org.eclipse.swt.internal.widgets.WidgetTreeVisitor.accept",
          "source": "WidgetTreeVisitor.java:48"
        },
        {
          "method": "org.eclipse.swt.internal.widgets.displaykit.DisplayLCA.render",
          "source": "DisplayLCA.java:133"
        },
        {
          "method": "org.eclipse.swt.internal.lifecycle.Render.execute",
          "source": "Render.java:28"
        },
        {
          "method": "org.eclipse.swt.internal.lifecycle.RWTLifeCycle.execute",
          "source": "RWTLifeCycle.java:81"
        },
        {
          "method": "com.w4t.engine.W4TModel$ServiceAdapter.execute",
          "source": "W4TModel.java:47"
        },
        {
          "method": "com.w4t.engine.service.FormRequestServiceHandler.service",
          "source": "FormRequestServiceHandler.java:65"
        },
        {
          "method": "com.w4t.engine.service.ServiceManager$HandlerDispatcher.service",
          "source": "ServiceManager.java:104"
        },
        {
          "method": "com.w4t.engine.W4TDelegate.doPost",
          "source": "W4TDelegate.java:75"
        }
      ],
      "number": 0,
      "commentIndex": 0,
      "bugId": "192223",
      "date": "2007-06-12T17:15:39+02:00",
      "product": "RAP",
      "component": "Workbench",
      "severity": "normal"
    }
  ],
  "groupId": "192223",
  "bugId": "192223",
  "date": "2007-06-12T17:15:39+02:00",
  "product": "RAP",
  "component": "Workbench",
  "severity": "normal"
}