{
  "comments": [
    " ",
    "Hello,\n\nI am trying to upgrade my Birt viewer on Linux from Birt 2.0.1 to Birt 2.2RC2. I am using my own viewer.jsp file so that I can control the value of parameters among other things. \n\nThe error that I get from the tomcat is (from catalina.out):\n...\n\n\tat org.apache.tomcat.util.threads.ThreadPool$ControlRunnable.run(ThreadPool.java:684)\n\tat java.lang.Thread.run(Thread.java:595)\nCaused by: org.eclipse.birt.core.exception.BirtException: Could not find the Framework - org.eclipse.osgi\n\tat org.eclipse.birt.core.framework.osgi.OSGILauncher.startup(OSGILauncher.java:95)\n\tat org.eclipse.birt.core.framework.Platform.startup(Platform.java:77)\n\t... 22 more\nCan\u0027t load the report engine\n- Servlet.service() for servlet jsp threw exception\njava.lang.NullPointerException\n\tat org.eclipse.birt.report.engine.api.ReportEngine.openReportDesign(ReportEngine.java:121)\n\tat org.apache.jsp.viewer_jsp._jspService(viewer_jsp.java:123)\n\tat org.apache.jasper.runtime.HttpJspBase.service(HttpJspBase.java:97)\n....\n------------------------\n\nThe way that I invoke Birt from my viewer.jsp and fails at the \nIReportRunnable design \u003d reportEngine.openReportDesign(requestedReportNameAndPath); :\n\n(This code is working fine under Birt 2.0.1)\n.....\n\tString requestedReportNameAndPath \u003d request.getParameter(\"__report\");\n\n\tif(requestedReportNameAndPath \u003d\u003d null)\n\t\tthrow new Exception(\"__report parameter was not specified in the URL.  The full path to a .rptdesign file must be specified in the __report paramter so the viewer knows which report to open.\");\n\t\n\t// Ensure the requested report file actually exists\n\tFile reportDesignFile \u003d new File(requestedReportNameAndPath);\n\tif(reportDesignFile.exists() \u003d\u003d false)\n\t\tthrow new Exception(requestedReportNameAndPath + \" does not exist\");\n\treportDesignFile \u003d null;\n\t\n\t// Glean the name of the .rptdesign file from the __report parameter in case a path exists in the value\n\tString requestedReportName \u003d requestedReportNameAndPath.substring(requestedReportNameAndPath.lastIndexOf(\"/\") +1);\n\t\n\t// Open the requested report design file\n\tIReportRunnable design \u003d reportEngine.openReportDesign(requestedReportNameAndPath); \n\n\t// Create a task to get the reports parameters.  \n\tIGetParameterDefinitionTask paramTask \u003d  reportEngine.createGetParameterDefinitionTask( design );\n\tCollection reportParameters \u003d paramTask.getParameterDefns(false);\n\n...",
    "Please check whether BIRT works well( default install. Don\u0027t integrate your application ). I guess there are something wrong in your codes. How did your initialize report engine instance?",
    "Hello,\n\nBirt 2.2RC2 seems to be working fine. If I invoke the reports from the example they work OK.\n\nThe code that I am using works fine for Birt 2.0.1 and is as follows:\n-----------\nEngineConfig reportEngineConfig \u003d new EngineConfig();\nreportEngineConfig.setEngineHome(reportingConfiguration.getEngineHome()); \n\t//resolves to /data/penelope/tomcat-gratia-/webapps/birt\n\t\n//reportEngineConfig.setLogConfig(\"\", java.util.logging.Level.SEVERE);\n\t\nReportEngine reportEngine \u003d new ReportEngine(reportEngineConfig);\n\t\nString requestedReportNameAndPath \u003d request.getParameter(\"__report\");\nif(requestedReportNameAndPath \u003d\u003d null)\n\tthrow new Exception(\"__report parameter was not specified in the URL.\");\n\t\n// Ensure the requested report file actually exists\nFile reportDesignFile \u003d new File(requestedReportNameAndPath);\nif(reportDesignFile.exists() \u003d\u003d false)\n\tthrow new Exception(requestedReportNameAndPath + \" does not exist\");\n\t\n// Open the requested report design file\nIReportRunnable design \u003d    \n             reportEngine.openReportDesign(requestedReportNameAndPath); \n\n// Create a task to get the reports parameters.  \nIGetParameterDefinitionTask paramTask \u003d  \n            reportEngine.createGetParameterDefinitionTask(design);\n\n-------------------------\n\nThank you\nPenelope\n",
    "From 2.2, we have a great change on report engine. You can\u0027t create report engine like this. Please refer to ReportEngineService class in org.eclipse.birt.report.viewer plugin. \nYou should startup OSGI platform and then create report engine.\nFor example:\n\n  IPlatformContext platformContext \u003d new PlatformServletContext(servletContext );\n  config.setPlatformContext( platformContext );\n\n  // Startup OSGI Platform\n  Platform.startup( config );\n\n  IReportEngineFactory factory \u003d (IReportEngineFactory) Platform\n.createFactoryObject( IReportEngineFactory.EXTENSION_REPORT_ENGINE_FACTORY );\n  if ( factory \u003d\u003d null )\n  {\n    // if null, throw exception\n    throw new ViewerException(\t\t\t\t\t\tResourceConstants.REPORT_SERVICE_EXCEPTION_STARTUP_REPORTENGINE_ERROR );\n  }\n  engine \u003d factory.createReportEngine( config );"
  ],
  "commentCreationDates": [
    "2007-06-15T21:26:23+02:00",
    "2007-06-15T21:39:49+02:00",
    "2007-06-18T05:58:56+02:00",
    "2007-06-18T15:55:03+02:00",
    "2007-06-19T03:44:58+02:00"
  ],
  "traces": [
    {
      "exceptionType": "org.eclipse.birt.core.exception.BirtException",
      "message": "Could not find the Framework - org.eclipse.osgi",
      "elements": [
        {
          "method": "org.eclipse.birt.core.framework.osgi.OSGILauncher.startup",
          "source": "OSGILauncher.java:95"
        },
        {
          "method": "org.eclipse.birt.core.framework.Platform.startup",
          "source": "Platform.java:77"
        }
      ],
      "number": 0,
      "commentIndex": 1,
      "bugId": "192979",
      "date": "2007-06-15T21:39:49+02:00",
      "product": "BIRT",
      "component": "Report Viewer",
      "severity": "normal"
    },
    {
      "exceptionType": "java.lang.NullPointerException",
      "elements": [
        {
          "method": "org.eclipse.birt.report.engine.api.ReportEngine.openReportDesign",
          "source": "ReportEngine.java:121"
        },
        {
          "method": "org.apache.jsp.viewer_jsp._jspService",
          "source": "viewer_jsp.java:123"
        },
        {
          "method": "org.apache.jasper.runtime.HttpJspBase.service",
          "source": "HttpJspBase.java:97"
        }
      ],
      "number": 1,
      "commentIndex": 1,
      "bugId": "192979",
      "date": "2007-06-15T21:39:49+02:00",
      "product": "BIRT",
      "component": "Report Viewer",
      "severity": "normal"
    }
  ],
  "groupId": "192979",
  "bugId": "192979",
  "date": "2007-06-15T21:26:23+02:00",
  "product": "BIRT",
  "component": "Report Viewer",
  "severity": "normal"
}