{
  "comments": [
    "At first there was a system installed with all needed bundles.\nDuring the normal lifecycle of product there was an update of bundles which was finished ok and all bundles worked after this.\nThe second upgrade was done a few days later but unfortunately it caused some Framework errors:\nSEVERE: FrameworkEvent ERROR\njava.util.zip.ZipException: No such file or directory \u003cpath_removed\u003e../../conf/org.eclipse.osgi/bundles/57/2/bundlefile\n        at java.util.zip.ZipFile.open(Native Method)\n        at java.util.zip.ZipFile.\u003cinit\u003e(ZipFile.java(Compiled Code))\n        at java.util.zip.ZipFile.\u003cinit\u003e(ZipFile.java(Inlined Compiled Code))\n        at org.eclipse.osgi.framework.util.SecureAction.getZipFile(SecureAction.java(Compiled Code))\n        at org.eclipse.osgi.framework.adaptor.core.BundleFile$ZipBundleFile.basicOpen(BundleFile.java(Inlined Compiled Code))\n        at org.eclipse.osgi.framework.adaptor.core.BundleFile$ZipBundleFile.getZipFile(BundleFile.java(Inlined Compiled Code))\n        at org.eclipse.osgi.framework.adaptor.core.BundleFile$ZipBundleFile.checkedOpen(BundleFile.java(Compiled Code))\n        at org.eclipse.osgi.framework.adaptor.core.BundleFile$ZipBundleFile.getEntry(BundleFile.java(Compiled Code))\n        at org.eclipse.osgi.framework.adaptor.core.BundleFile.getResourceURL(BundleFile.java(Compiled Code))\n        at org.eclipse.osgi.framework.adaptor.core.DefaultClassLoader.findResourceImpl(DefaultClassLoader.java(Inlined Compiled Code))\n        at org.eclipse.osgi.framework.adaptor.core.DefaultClassLoader.findResourceImpl(DefaultClassLoader.java(Inlined Compiled Code))\n        at org.eclipse.osgi.framework.adaptor.core.DefaultClassLoader.findResource(DefaultClassLoader.java(Compiled Code))\n        at org.eclipse.osgi.framework.adaptor.core.AbstractClassLoader.findLocalResource(AbstractClassLoader.java(Compiled Code))\n        at org.eclipse.osgi.framework.internal.core.BundleLoader.findLocalResource(BundleLoader.java(Compiled Code))\n        at org.eclipse.osgi.framework.internal.core.BundleLoader.findResource(BundleLoader.java(Compiled Code))\n        at org.eclipse.osgi.framework.internal.core.BundleLoader.findResource(BundleLoader.java(Compiled Code))\n        at org.eclipse.osgi.framework.adaptor.core.AbstractClassLoader.getResource(AbstractClassLoader.java(Inlined Compiled Code))\n        at org.eclipse.core.runtime.adaptor.EclipseClassLoader.getResource(EclipseClassLoader.java(Compiled Code))\n        at java.lang.ClassLoader.getResourceAsStream(ClassLoader.java(Inlined Compiled Code))\n        at javax.xml.parsers.SecuritySupport12$4.run(Unknown Source)\n        at java.security.AccessController.doPrivileged1(Native Method)\n        at java.security.AccessController.doPrivileged(AccessController.java(Compiled Code))\n        at javax.xml.parsers.SecuritySupport12.getResourceAsStream(Unknown Source)\n        at javax.xml.parsers.FactoryFinder.findJarServiceProvider(Unknown Source)\n        at javax.xml.parsers.FactoryFinder.find(Unknown Source)\n        at javax.xml.parsers.SAXParserFactory.newInstance(Unknown Source)\n        at java.beans.XMLDecoder.\u003cinit\u003e(XMLDecoder.java(Compiled Code))\n        at java.beans.XMLDecoder.\u003cinit\u003e(XMLDecoder.java(Inlined Compiled Code))\n        at java.beans.XMLDecoder.\u003cinit\u003e(XMLDecoder.java(Inlined Compiled Code))\n        at com.ibm.scheduling.jea.persistence.XMLJobStore.queryJobFile(XMLJobStore.java(Compiled Code))\n\nAfter that looking at the cache structure we\u0027ve discovered multiple bundle generations for many bundles updated during second upgrade.\nHere is the cache tree of one of the bundles.\n|-- 57\n|   |-- 2\n|   |   `-- .cp\n|   |       |-- CASUtils.jar\n...\n|   |       `-- ecore.xmi.jar\n|   |-- 3\n|   |   |-- .cp\n|   |   |   |-- CASUtils.jar\n...\n|   |   |   `-- ecore.xmi.jar\n|   |   `-- bundlefile\n|   `-- data\n|       `-- bundle.properties\n\nWe are trying to investigate the problem to get more details about the cause of the problem. There is no delete file in the second generation.",
    "Need more information.  I have not been able to reproduce.  Have you been able to reproduce this issue?"
  ],
  "commentCreationDates": [
    "2007-06-21T15:36:41+02:00",
    "2007-07-30T17:58:16+02:00"
  ],
  "traces": [
    {
      "exceptionType": "java.util.zip.ZipException",
      "message": "No such file or directory \u003cpath_removed\u003e../../conf/org.eclipse.osgi/bundles/57/2/bundlefile",
      "elements": [
        {
          "method": "java.util.zip.ZipFile.open",
          "source": "Native Method"
        },
        {
          "method": "java.util.zip.ZipFile.\u003cinit\u003e",
          "source": "ZipFile.java(Compiled Code)"
        },
        {
          "method": "java.util.zip.ZipFile.\u003cinit\u003e",
          "source": "ZipFile.java(Inlined Compiled Code)"
        },
        {
          "method": "org.eclipse.osgi.framework.util.SecureAction.getZipFile",
          "source": "SecureAction.java(Compiled Code)"
        },
        {
          "method": "org.eclipse.osgi.framework.adaptor.core.BundleFile$ZipBundleFile.basicOpen",
          "source": "BundleFile.java(Inlined Compiled Code)"
        },
        {
          "method": "org.eclipse.osgi.framework.adaptor.core.BundleFile$ZipBundleFile.getZipFile",
          "source": "BundleFile.java(Inlined Compiled Code)"
        },
        {
          "method": "org.eclipse.osgi.framework.adaptor.core.BundleFile$ZipBundleFile.checkedOpen",
          "source": "BundleFile.java(Compiled Code)"
        },
        {
          "method": "org.eclipse.osgi.framework.adaptor.core.BundleFile$ZipBundleFile.getEntry",
          "source": "BundleFile.java(Compiled Code)"
        },
        {
          "method": "org.eclipse.osgi.framework.adaptor.core.BundleFile.getResourceURL",
          "source": "BundleFile.java(Compiled Code)"
        },
        {
          "method": "org.eclipse.osgi.framework.adaptor.core.DefaultClassLoader.findResourceImpl",
          "source": "DefaultClassLoader.java(Inlined Compiled Code)"
        },
        {
          "method": "org.eclipse.osgi.framework.adaptor.core.DefaultClassLoader.findResourceImpl",
          "source": "DefaultClassLoader.java(Inlined Compiled Code)"
        },
        {
          "method": "org.eclipse.osgi.framework.adaptor.core.DefaultClassLoader.findResource",
          "source": "DefaultClassLoader.java(Compiled Code)"
        },
        {
          "method": "org.eclipse.osgi.framework.adaptor.core.AbstractClassLoader.findLocalResource",
          "source": "AbstractClassLoader.java(Compiled Code)"
        },
        {
          "method": "org.eclipse.osgi.framework.internal.core.BundleLoader.findLocalResource",
          "source": "BundleLoader.java(Compiled Code)"
        },
        {
          "method": "org.eclipse.osgi.framework.internal.core.BundleLoader.findResource",
          "source": "BundleLoader.java(Compiled Code)"
        },
        {
          "method": "org.eclipse.osgi.framework.internal.core.BundleLoader.findResource",
          "source": "BundleLoader.java(Compiled Code)"
        },
        {
          "method": "org.eclipse.osgi.framework.adaptor.core.AbstractClassLoader.getResource",
          "source": "AbstractClassLoader.java(Inlined Compiled Code)"
        },
        {
          "method": "org.eclipse.core.runtime.adaptor.EclipseClassLoader.getResource",
          "source": "EclipseClassLoader.java(Compiled Code)"
        },
        {
          "method": "java.lang.ClassLoader.getResourceAsStream",
          "source": "ClassLoader.java(Inlined Compiled Code)"
        },
        {
          "method": "javax.xml.parsers.SecuritySupport12$4.run",
          "source": "Unknown Source"
        },
        {
          "method": "java.security.AccessController.doPrivileged1",
          "source": "Native Method"
        },
        {
          "method": "java.security.AccessController.doPrivileged",
          "source": "AccessController.java(Compiled Code)"
        },
        {
          "method": "javax.xml.parsers.SecuritySupport12.getResourceAsStream",
          "source": "Unknown Source"
        },
        {
          "method": "javax.xml.parsers.FactoryFinder.findJarServiceProvider",
          "source": "Unknown Source"
        },
        {
          "method": "javax.xml.parsers.FactoryFinder.find",
          "source": "Unknown Source"
        },
        {
          "method": "javax.xml.parsers.SAXParserFactory.newInstance",
          "source": "Unknown Source"
        },
        {
          "method": "java.beans.XMLDecoder.\u003cinit\u003e",
          "source": "XMLDecoder.java(Compiled Code)"
        },
        {
          "method": "java.beans.XMLDecoder.\u003cinit\u003e",
          "source": "XMLDecoder.java(Inlined Compiled Code)"
        },
        {
          "method": "java.beans.XMLDecoder.\u003cinit\u003e",
          "source": "XMLDecoder.java(Inlined Compiled Code)"
        },
        {
          "method": "com.ibm.scheduling.jea.persistence.XMLJobStore.queryJobFile",
          "source": "XMLJobStore.java(Compiled Code)"
        }
      ],
      "number": 0,
      "commentIndex": 0,
      "bugId": "193716",
      "date": "2007-06-21T15:36:41+02:00",
      "product": "Equinox",
      "component": "Framework",
      "severity": "major"
    }
  ],
  "groupId": "193716",
  "bugId": "193716",
  "date": "2007-06-21T15:36:41+02:00",
  "product": "Equinox",
  "component": "Framework",
  "severity": "major"
}