{
  "comments": [
    "1. I import several large project using Import from file system into my    \n   workspace.\n2. Validators such as HTML validator process begin to run.\n\n3. I decide to delete all the projects.\n\n4. The projects are deleted but many exceptions as the following are being thrown :\n*** ERROR ***: Thu Jun 21 15:51:53 IDT 2007    org.eclipse.core.internal.resources.ResourceException: Resource \u0027/test_remote_multi_cvs(PlayGround)_3/phpBB2-cvs2/templates/subSilver/groupcp_user_body.tpl\u0027 does not exist.\n    \tat org.eclipse.core.internal.resources.Resource.checkExists(Resource.java:310)\n    \tat org.eclipse.core.internal.resources.Resource.checkAccessible(Resource.java:193)\n    \tat org.eclipse.core.internal.resources.Resource.createMarker(Resource.java:637)\n    \tat org.eclipse.wst.validation.internal.TaskListUtility.addTask(TaskListUtility.java:81)\n    \tat org.eclipse.wst.validation.internal.operations.ValidationOperation$2.run(ValidationOperation.java:1744)\n    \tat org.eclipse.core.internal.resources.Workspace.run(Workspace.java:1797)\n    \tat org.eclipse.wst.validation.internal.operations.ValidationOperation$1.done(ValidationOperation.java:1767)\n    \tat org.eclipse.core.internal.jobs.JobListeners$3.notify(JobListeners.java:39)\n    \tat org.eclipse.core.internal.jobs.JobListeners.doNotify(JobListeners.java:112)\n    \tat org.eclipse.core.internal.jobs.JobListeners.done(JobListeners.java:152)\n    \tat org.eclipse.core.internal.jobs.JobManager.endJob(JobManager.java:550)\n    \tat org.eclipse.core.internal.jobs.WorkerPool.endJob(WorkerPool.java:105)\n    \tat org.eclipse.core.internal.jobs.Worker.run(Worker.java:71)\n\nIs seems that I managed to delete these files before the validator reached them\nand now, when they do not exist the validator fails.\n\nI suggest the following patches :\n1) org.eclipse.wst.validation.internal.TaskListUtility, line 62\n   add || !resource.exists() to the \"IF\" statement to verify that \n   the file really exists.\n2) org.eclipse.wst.validation.internal.ValidatorMetaData, line 349\n   add \u0026\u0026 ((IFile)resource).exists() . Again, to verify that the file \n   really exists.\n\nI just check and it fixes the error exception that was thrown.\n\nYaron",
    "\n\n*** This bug has been marked as a duplicate of bug 184295 ***"
  ],
  "commentCreationDates": [
    "2007-06-21T15:00:08+02:00",
    "2007-06-21T16:13:34+02:00"
  ],
  "traces": [
    {
      "exceptionType": "org.eclipse.core.internal.resources.ResourceException",
      "message": "Resource \u0027/test_remote_multi_cvs(PlayGround)_3/phpBB2-cvs2/templates/subSilver/groupcp_user_body.tpl\u0027 does not exist.",
      "elements": [
        {
          "method": "org.eclipse.core.internal.resources.Resource.checkExists",
          "source": "Resource.java:310"
        },
        {
          "method": "org.eclipse.core.internal.resources.Resource.checkAccessible",
          "source": "Resource.java:193"
        },
        {
          "method": "org.eclipse.core.internal.resources.Resource.createMarker",
          "source": "Resource.java:637"
        },
        {
          "method": "org.eclipse.wst.validation.internal.TaskListUtility.addTask",
          "source": "TaskListUtility.java:81"
        },
        {
          "method": "org.eclipse.wst.validation.internal.operations.ValidationOperation$2.run",
          "source": "ValidationOperation.java:1744"
        },
        {
          "method": "org.eclipse.core.internal.resources.Workspace.run",
          "source": "Workspace.java:1797"
        },
        {
          "method": "org.eclipse.wst.validation.internal.operations.ValidationOperation$1.done",
          "source": "ValidationOperation.java:1767"
        },
        {
          "method": "org.eclipse.core.internal.jobs.JobListeners$3.notify",
          "source": "JobListeners.java:39"
        },
        {
          "method": "org.eclipse.core.internal.jobs.JobListeners.doNotify",
          "source": "JobListeners.java:112"
        },
        {
          "method": "org.eclipse.core.internal.jobs.JobListeners.done",
          "source": "JobListeners.java:152"
        },
        {
          "method": "org.eclipse.core.internal.jobs.JobManager.endJob",
          "source": "JobManager.java:550"
        },
        {
          "method": "org.eclipse.core.internal.jobs.WorkerPool.endJob",
          "source": "WorkerPool.java:105"
        },
        {
          "method": "org.eclipse.core.internal.jobs.Worker.run",
          "source": "Worker.java:71"
        }
      ],
      "number": 0,
      "commentIndex": 0,
      "bugId": "193706",
      "duplicateId": "184295",
      "date": "2007-06-21T15:00:08+02:00",
      "product": "Web Tools",
      "component": "wst.validation",
      "severity": "normal"
    }
  ],
  "groupId": "189126",
  "bugId": "193706",
  "duplicateId": "184295",
  "date": "2007-06-21T15:00:08+02:00",
  "product": "Web Tools",
  "component": "wst.validation",
  "severity": "normal"
}