{
  "comments": [
    "Hi,\n\nThe summary says all. To reproduce:\n\n1. Open debug perspective.\n2. Select menu / show view / other / Problems\n\nNow the ide is locked. If you close, it will close normally and then reopen normally... without the Problems view.",
    "I can\u0027t reproduce this on XP, although your OS is Win2K its unlikely but vaguely possible its OS dependent (XP and Win2K are pretty close).  Is this bug consistent?  Do you have other plugins or is this just a straight eclipse SDK install? I am highly surprised that this bug could exist.\n\nIs there anything else you can add?",
    "Hi,\n\nI set a new workspace, and at the new one the problem doens\u0027t happens.\n\nI can send you my current eclipse folder and also the problematic workspace. Do you want it?\n\nthanks and regards",
    "Glad that sorted it for you.  Lowering severity from critical to normal and assigning bug. Could you please hang onto workspace for two weeks in case bug assignee wants to look at it?  In the interim if the problem reoccurs in the new workspace please let us know and up severity again.",
    "What would be more usefulk is a stack dump when this happens. I suspect another process is holding onto the workspace lock.",
    "And how can i generate such stack dump? I\u0027m calling eclipse.exe file",
    "run eclipse with the -consolelog option. You will get a second dos window which will give you a stack dump if you hi tCtrl+Break",
    "Here it goes:\n\n!SESSION 2007-06-25 09:21:41.764 -----------------------------------------------\n\neclipse.buildId\u003dM20070212-1330\njava.version\u003d1.4.2\njava.vendor\u003dSun Microsystems Inc.\nBootLoader constants: OS\u003dwin32, ARCH\u003dx86, WS\u003dwin32, NL\u003dpt_BR\nCommand-line arguments:  -os win32 -ws win32 -arch x86 -consolelog\n\n!ENTRY org.eclipse.ui 4 4 2007-06-25 09:23:09.510\n!MESSAGE Unhandled event loop exception\n\n!ENTRY org.eclipse.ui 4 0 2007-06-25 09:23:09.560\n!MESSAGE java.lang.NullPointerException\n!STACK 0\njava.lang.NullPointerException\n        at org.eclipse.ui.internal.PerspectiveHelper.derefPart(PerspectiveHelper\n.java:703)\n        at org.eclipse.ui.internal.ViewSashContainer.derefPart(ViewSashContainer\n.java:267)\n        at org.eclipse.ui.internal.PartSashContainer.stack(PartSashContainer.jav\na:1211)\n        at org.eclipse.ui.internal.PerspectiveHelper.addPart(PerspectiveHelper.j\nava:295)\n        at org.eclipse.ui.internal.Perspective.showView(Perspective.java:1693)\n        at org.eclipse.ui.internal.WorkbenchPage.busyShowView(WorkbenchPage.java\n:987)\n        at org.eclipse.ui.internal.WorkbenchPage.access$13(WorkbenchPage.java:96\n8)\n        at org.eclipse.ui.internal.WorkbenchPage$13.run(WorkbenchPage.java:3514)\n\n        at org.eclipse.swt.custom.BusyIndicator.showWhile(BusyIndicator.java:67)\n\n        at org.eclipse.ui.internal.WorkbenchPage.showView(WorkbenchPage.java:351\n1)\n        at org.eclipse.ui.internal.WorkbenchPage.showView(WorkbenchPage.java:348\n7)\n        at org.eclipse.ui.handlers.ShowViewHandler.openView(ShowViewHandler.java\n:148)\n        at org.eclipse.ui.handlers.ShowViewHandler.openOther(ShowViewHandler.jav\na:104)\n        at org.eclipse.ui.handlers.ShowViewHandler.execute(ShowViewHandler.java:\n70)\n        at org.eclipse.ui.internal.ShowViewMenu$3.run(ShowViewMenu.java:114)\n        at org.eclipse.jface.action.Action.runWithEvent(Action.java:499)\n        at org.eclipse.jface.action.ActionContributionItem.handleWidgetSelection\n(ActionContributionItem.java:539)\n        at org.eclipse.jface.action.ActionContributionItem.access$2(ActionContri\nbutionItem.java:488)\n        at org.eclipse.jface.action.ActionContributionItem$5.handleEvent(ActionC\nontributionItem.java:400)\n        at org.eclipse.swt.widgets.EventTable.sendEvent(EventTable.java:66)\n        at org.eclipse.swt.widgets.Widget.sendEvent(Widget.java:928)\n        at org.eclipse.swt.widgets.Display.runDeferredEvents(Display.java:3348)\n        at org.eclipse.swt.widgets.Display.readAndDispatch(Display.java:2968)\n        at org.eclipse.ui.internal.Workbench.runEventLoop(Workbench.java:1930)\n        at org.eclipse.ui.internal.Workbench.runUI(Workbench.java:1894)\n        at org.eclipse.ui.internal.Workbench.createAndRunWorkbench(Workbench.jav\na:422)\n        at org.eclipse.ui.PlatformUI.createAndRunWorkbench(PlatformUI.java:149)\n        at org.eclipse.ui.internal.ide.IDEApplication.run(IDEApplication.java:95\n)\n        at org.eclipse.core.internal.runtime.PlatformActivator$1.run(PlatformAct\nivator.java:78)\n        at org.eclipse.core.runtime.internal.adaptor.EclipseAppLauncher.runAppli\ncation(EclipseAppLauncher.java:92)\n        at org.eclipse.core.runtime.internal.adaptor.EclipseAppLauncher.start(Ec\nlipseAppLauncher.java:68)\n        at org.eclipse.core.runtime.adaptor.EclipseStarter.run(EclipseStarter.ja\nva:400)\n        at org.eclipse.core.runtime.adaptor.EclipseStarter.run(EclipseStarter.ja\nva:177)\n        at sun.reflect.NativeMethodAccessorImpl.invoke0(Native Method)\n        at sun.reflect.NativeMethodAccessorImpl.invoke(Unknown Source)\n        at sun.reflect.DelegatingMethodAccessorImpl.invoke(Unknown Source)\n        at java.lang.reflect.Method.invoke(Unknown Source)\n        at org.eclipse.core.launcher.Main.invokeFramework(Main.java:336)\n        at org.eclipse.core.launcher.Main.basicRun(Main.java:280)\n        at org.eclipse.core.launcher.Main.run(Main.java:977)\n        at org.eclipse.core.launcher.Main.main(Main.java:952)\n"
  ],
  "commentCreationDates": [
    "2007-06-21T18:22:27+02:00",
    "2007-06-21T20:18:46+02:00",
    "2007-06-21T20:48:45+02:00",
    "2007-06-22T16:12:01+02:00",
    "2007-06-22T17:15:48+02:00",
    "2007-06-22T17:19:36+02:00",
    "2007-06-25T14:11:08+02:00",
    "2007-06-25T14:23:00+02:00"
  ],
  "traces": [
    {
      "exceptionType": "java.lang.NullPointerException",
      "elements": [
        {
          "method": "org.eclipse.ui.internal.PerspectiveHelper.derefPart",
          "source": "PerspectiveHelper .java:703"
        },
        {
          "method": "org.eclipse.ui.internal.ViewSashContainer.derefPart",
          "source": "ViewSashContainer .java:267"
        },
        {
          "method": "org.eclipse.ui.internal.PartSashContainer.stack",
          "source": "PartSashContainer.jav a:1211"
        },
        {
          "method": "org.eclipse.ui.internal.PerspectiveHelper.addPart",
          "source": "PerspectiveHelper.j ava:295"
        },
        {
          "method": "org.eclipse.ui.internal.Perspective.showView",
          "source": "Perspective.java:1693"
        },
        {
          "method": "org.eclipse.ui.internal.WorkbenchPage.busyShowView",
          "source": "WorkbenchPage.java :987"
        },
        {
          "method": "org.eclipse.ui.internal.WorkbenchPage.access$13",
          "source": "WorkbenchPage.java:96 8"
        },
        {
          "method": "org.eclipse.ui.internal.WorkbenchPage$13.run",
          "source": "WorkbenchPage.java:3514"
        },
        {
          "method": "org.eclipse.swt.custom.BusyIndicator.showWhile",
          "source": "BusyIndicator.java:67"
        },
        {
          "method": "org.eclipse.ui.internal.WorkbenchPage.showView",
          "source": "WorkbenchPage.java:351 1"
        },
        {
          "method": "org.eclipse.ui.internal.WorkbenchPage.showView",
          "source": "WorkbenchPage.java:348 7"
        },
        {
          "method": "org.eclipse.ui.handlers.ShowViewHandler.openView",
          "source": "ShowViewHandler.java :148"
        },
        {
          "method": "org.eclipse.ui.handlers.ShowViewHandler.openOther",
          "source": "ShowViewHandler.jav a:104"
        },
        {
          "method": "org.eclipse.ui.handlers.ShowViewHandler.execute",
          "source": "ShowViewHandler.java: 70"
        },
        {
          "method": "org.eclipse.ui.internal.ShowViewMenu$3.run",
          "source": "ShowViewMenu.java:114"
        },
        {
          "method": "org.eclipse.jface.action.Action.runWithEvent",
          "source": "Action.java:499"
        },
        {
          "method": "org.eclipse.jface.action.ActionContributionItem.handleWidgetSelection",
          "source": "ActionContributionItem.java:539"
        },
        {
          "method": "org.eclipse.jface.action.ActionContributionItem.access$2",
          "source": "ActionContri butionItem.java:488"
        },
        {
          "method": "org.eclipse.jface.action.ActionContributionItem$5.handleEvent",
          "source": "ActionC ontributionItem.java:400"
        },
        {
          "method": "org.eclipse.swt.widgets.EventTable.sendEvent",
          "source": "EventTable.java:66"
        },
        {
          "method": "org.eclipse.swt.widgets.Widget.sendEvent",
          "source": "Widget.java:928"
        },
        {
          "method": "org.eclipse.swt.widgets.Display.runDeferredEvents",
          "source": "Display.java:3348"
        },
        {
          "method": "org.eclipse.swt.widgets.Display.readAndDispatch",
          "source": "Display.java:2968"
        },
        {
          "method": "org.eclipse.ui.internal.Workbench.runEventLoop",
          "source": "Workbench.java:1930"
        },
        {
          "method": "org.eclipse.ui.internal.Workbench.runUI",
          "source": "Workbench.java:1894"
        },
        {
          "method": "org.eclipse.ui.internal.Workbench.createAndRunWorkbench",
          "source": "Workbench.jav a:422"
        },
        {
          "method": "org.eclipse.ui.PlatformUI.createAndRunWorkbench",
          "source": "PlatformUI.java:149"
        },
        {
          "method": "org.eclipse.ui.internal.ide.IDEApplication.run",
          "source": "IDEApplication.java:95 "
        },
        {
          "method": "org.eclipse.core.internal.runtime.PlatformActivator$1.run",
          "source": "PlatformAct ivator.java:78"
        },
        {
          "method": "org.eclipse.core.runtime.internal.adaptor.EclipseAppLauncher.runApplication",
          "source": "EclipseAppLauncher.java:92"
        },
        {
          "method": "org.eclipse.core.runtime.internal.adaptor.EclipseAppLauncher.start",
          "source": "Ec lipseAppLauncher.java:68"
        },
        {
          "method": "org.eclipse.core.runtime.adaptor.EclipseStarter.run",
          "source": "EclipseStarter.ja va:400"
        },
        {
          "method": "org.eclipse.core.runtime.adaptor.EclipseStarter.run",
          "source": "EclipseStarter.ja va:177"
        },
        {
          "method": "sun.reflect.NativeMethodAccessorImpl.invoke0",
          "source": "Native Method"
        },
        {
          "method": "sun.reflect.NativeMethodAccessorImpl.invoke",
          "source": "Unknown Source"
        },
        {
          "method": "sun.reflect.DelegatingMethodAccessorImpl.invoke",
          "source": "Unknown Source"
        },
        {
          "method": "java.lang.reflect.Method.invoke",
          "source": "Unknown Source"
        },
        {
          "method": "org.eclipse.core.launcher.Main.invokeFramework",
          "source": "Main.java:336"
        },
        {
          "method": "org.eclipse.core.launcher.Main.basicRun",
          "source": "Main.java:280"
        },
        {
          "method": "org.eclipse.core.launcher.Main.run",
          "source": "Main.java:977"
        },
        {
          "method": "org.eclipse.core.launcher.Main.main",
          "source": "Main.java:952"
        }
      ],
      "number": 0,
      "commentIndex": 7,
      "bugId": "193778",
      "date": "2007-06-25T14:23:00+02:00",
      "product": "Platform",
      "component": "IDE",
      "severity": "normal"
    }
  ],
  "groupId": "193778",
  "bugId": "193778",
  "date": "2007-06-21T18:22:27+02:00",
  "product": "Platform",
  "component": "IDE",
  "severity": "normal"
}