{
  "comments": [
    "When starting the COSMOS data visualization web application, I get the following exception: \n\nSEVERE: IOException while loading persisted sessions: java.io.InvalidClassException: org.eclipse.cosmos.rm.repository.internal.application.impl.SMLFil\neResourceInstance; no valid constructor\njava.io.InvalidClassException: org.eclipse.cosmos.rm.repository.internal.application.impl.SMLFileResourceInstance; no valid constructor\n        at java.io.ObjectStreamClass.\u003cinit\u003e(ObjectStreamClass.java:455)\n        at java.io.ObjectStreamClass.lookup(ObjectStreamClass.java:297)\n        at java.io.ObjectStreamClass.initNonProxy(ObjectStreamClass.java:531)\n        at java.io.ObjectInputStream.readNonProxyDesc(ObjectInputStream.java:1552)\n        at java.io.ObjectInputStream.readClassDesc(ObjectInputStream.java:1466)\n        at java.io.ObjectInputStream.readOrdinaryObject(ObjectInputStream.java:1699)\n        at java.io.ObjectInputStream.readObject0(ObjectInputStream.java:1305)\n        at java.io.ObjectInputStream.readObject(ObjectInputStream.java:348)\n        at java.util.HashMap.readObject(HashMap.java:1067)\n        at sun.reflect.NativeMethodAccessorImpl.invoke0(Native Method)\n        at sun.reflect.NativeMethodAccessorImpl.invoke(NativeMethodAccessorImpl.java:39)\n        at sun.reflect.DelegatingMethodAccessorImpl.invoke(DelegatingMethodAccessorImpl.java:25)\n        at java.lang.reflect.Method.invoke(Method.java:585)\n        at java.io.ObjectStreamClass.invokeReadObject(ObjectStreamClass.java:946)\n        at java.io.ObjectInputStream.readSerialData(ObjectInputStream.java:1809)\n        at java.io.ObjectInputStream.readOrdinaryObject(ObjectInputStream.java:1719)\n        at java.io.ObjectInputStream.readObject0(ObjectInputStream.java:1305)\n        at java.io.ObjectInputStream.readObject(ObjectInputStream.java:348)\n        at org.apache.catalina.session.StandardSession.readObject(StandardSession.java:1402)\n        at org.apache.catalina.session.StandardSession.readObjectData(StandardSession.java:931)\n        at org.apache.catalina.session.StandardManager.doLoad(StandardManager.java:394)\n        at org.apache.catalina.session.StandardManager.load(StandardManager.java:321)\n        at org.apache.catalina.session.StandardManager.start(StandardManager.java:637)\n        at org.apache.catalina.core.ContainerBase.setManager(ContainerBase.java:432)\n        at org.apache.catalina.core.StandardContext.start(StandardContext.java:4160)\n        at org.apache.catalina.core.ContainerBase.addChildInternal(ContainerBase.java:760)\n        at org.apache.catalina.core.ContainerBase.addChild(ContainerBase.java:740)\n        at org.apache.catalina.core.StandardHost.addChild(StandardHost.java:544)\n        at org.apache.catalina.startup.HostConfig.deployDirectory(HostConfig.java:920)\n        at org.apache.catalina.startup.HostConfig.deployDirectories(HostConfig.java:883)\n        at org.apache.catalina.startup.HostConfig.deployApps(HostConfig.java:492)\n        at org.apache.catalina.startup.HostConfig.start(HostConfig.java:1138)\n        at org.apache.catalina.startup.HostConfig.lifecycleEvent(HostConfig.java:311)\n        at org.apache.catalina.util.LifecycleSupport.fireLifecycleEvent(LifecycleSupport.java:120)\n        at org.apache.catalina.core.ContainerBase.start(ContainerBase.java:1022)\n        at org.apache.catalina.core.StandardHost.start(StandardHost.java:736)\n        at org.apache.catalina.core.ContainerBase.start(ContainerBase.java:1014)\n        at org.apache.catalina.core.StandardEngine.start(StandardEngine.java:443)\n        at org.apache.catalina.core.StandardService.start(StandardService.java:448)\n        at org.apache.catalina.core.StandardServer.start(StandardServer.java:700)\n        at org.apache.catalina.startup.Catalina.start(Catalina.java:552)\n        at sun.reflect.NativeMethodAccessorImpl.invoke0(Native Method)\n        at sun.reflect.NativeMethodAccessorImpl.invoke(NativeMethodAccessorImpl.java:39)\n        at sun.reflect.DelegatingMethodAccessorImpl.invoke(DelegatingMethodAccessorImpl.java:25)\n        at java.lang.reflect.Method.invoke(Method.java:585)\n        at org.apache.catalina.startup.Bootstrap.start(Bootstrap.java:295)\n        at org.apache.catalina.startup.Bootstrap.main(Bootstrap.java:433)\nJun 21, 2007 2:49:19 PM org.apache.catalina.session.StandardManager start\nSEVERE: Exception loading sessions from persistent storage\njava.io.InvalidClassException: org.eclipse.cosmos.rm.repository.internal.application.impl.SMLFileResourceInstance; no valid constructor\n        at java.io.ObjectStreamClass.\u003cinit\u003e(ObjectStreamClass.java:455)\n        at java.io.ObjectStreamClass.lookup(ObjectStreamClass.java:297)\n        at java.io.ObjectStreamClass.initNonProxy(ObjectStreamClass.java:531)\n        at java.io.ObjectInputStream.readNonProxyDesc(ObjectInputStream.java:1552)\n        at java.io.ObjectInputStream.readClassDesc(ObjectInputStream.java:1466)\n        at java.io.ObjectInputStream.readOrdinaryObject(ObjectInputStream.java:1699)\n        at java.io.ObjectInputStream.readObject0(ObjectInputStream.java:1305)\n        at java.io.ObjectInputStream.readObject(ObjectInputStream.java:348)\n        at java.util.HashMap.readObject(HashMap.java:1067)\n        at sun.reflect.NativeMethodAccessorImpl.invoke0(Native Method)\n        at sun.reflect.NativeMethodAccessorImpl.invoke(NativeMethodAccessorImpl.java:39)\n        at sun.reflect.DelegatingMethodAccessorImpl.invoke(DelegatingMethodAccessorImpl.java:25)\n        at java.lang.reflect.Method.invoke(Method.java:585)\n        at java.io.ObjectStreamClass.invokeReadObject(ObjectStreamClass.java:946)\n        at java.io.ObjectInputStream.readSerialData(ObjectInputStream.java:1809)\n        at java.io.ObjectInputStream.readOrdinaryObject(ObjectInputStream.java:1719)\n        at java.io.ObjectInputStream.readObject0(ObjectInputStream.java:1305)\n        at java.io.ObjectInputStream.readObject(ObjectInputStream.java:348)\n        at org.apache.catalina.session.StandardSession.readObject(StandardSession.java:1402)\n        at org.apache.catalina.session.StandardSession.readObjectData(StandardSession.java:931)\n        at org.apache.catalina.session.StandardManager.doLoad(StandardManager.java:394)\n        at org.apache.catalina.session.StandardManager.load(StandardManager.java:321)\n        at org.apache.catalina.session.StandardManager.start(StandardManager.java:637)\n        at org.apache.catalina.core.ContainerBase.setManager(ContainerBase.java:432)\n        at org.apache.catalina.core.StandardContext.start(StandardContext.java:4160)\n        at org.apache.catalina.core.ContainerBase.addChildInternal(ContainerBase.java:760)\n        at org.apache.catalina.core.ContainerBase.addChild(ContainerBase.java:740)\n        at org.apache.catalina.core.StandardHost.addChild(StandardHost.java:544)\n        at org.apache.catalina.startup.HostConfig.deployDirectory(HostConfig.java:920)\n        at org.apache.catalina.startup.HostConfig.deployDirectories(HostConfig.java:883)\n        at org.apache.catalina.startup.HostConfig.deployApps(HostConfig.java:492)\n        at org.apache.catalina.startup.HostConfig.start(HostConfig.java:1138)\n        at org.apache.catalina.startup.HostConfig.lifecycleEvent(HostConfig.java:311)\n        at org.apache.catalina.util.LifecycleSupport.fireLifecycleEvent(LifecycleSupport.java:120)\n        at org.apache.catalina.core.ContainerBase.start(ContainerBase.java:1022)\n        at org.apache.catalina.core.StandardHost.start(StandardHost.java:736)\n        at org.apache.catalina.core.ContainerBase.start(ContainerBase.java:1014)\n        at org.apache.catalina.core.StandardEngine.start(StandardEngine.java:443)\n        at org.apache.catalina.core.StandardService.start(StandardService.java:448)\n        at org.apache.catalina.core.StandardServer.start(StandardServer.java:700)\n        at org.apache.catalina.startup.Catalina.start(Catalina.java:552)\n        at sun.reflect.NativeMethodAccessorImpl.invoke0(Native Method)\n        at sun.reflect.NativeMethodAccessorImpl.invoke(NativeMethodAccessorImpl.java:39)\n        at sun.reflect.DelegatingMethodAccessorImpl.invoke(DelegatingMethodAccessorImpl.java:25)\n        at java.lang.reflect.Method.invoke(Method.java:585)\n        at org.apache.catalina.startup.Bootstrap.start(Bootstrap.java:295)\n        at org.apache.catalina.startup.Bootstrap.main(Bootstrap.java:433)",
    "moving target to i8",
    "Is this still a problem, Hubert?"
  ],
  "commentCreationDates": [
    "2007-06-21T21:14:40+02:00",
    "2007-11-29T18:52:19+01:00",
    "2007-12-06T21:58:13+01:00"
  ],
  "traces": [
    {
      "exceptionType": "java.io.InvalidClassException",
      "message": "org.eclipse.cosmos.rm.repository.internal.application.impl.SMLFileResourceInstance; no valid constructor",
      "elements": [
        {
          "method": "java.io.ObjectStreamClass.\u003cinit\u003e",
          "source": "ObjectStreamClass.java:455"
        },
        {
          "method": "java.io.ObjectStreamClass.lookup",
          "source": "ObjectStreamClass.java:297"
        },
        {
          "method": "java.io.ObjectStreamClass.initNonProxy",
          "source": "ObjectStreamClass.java:531"
        },
        {
          "method": "java.io.ObjectInputStream.readNonProxyDesc",
          "source": "ObjectInputStream.java:1552"
        },
        {
          "method": "java.io.ObjectInputStream.readClassDesc",
          "source": "ObjectInputStream.java:1466"
        },
        {
          "method": "java.io.ObjectInputStream.readOrdinaryObject",
          "source": "ObjectInputStream.java:1699"
        },
        {
          "method": "java.io.ObjectInputStream.readObject0",
          "source": "ObjectInputStream.java:1305"
        },
        {
          "method": "java.io.ObjectInputStream.readObject",
          "source": "ObjectInputStream.java:348"
        },
        {
          "method": "java.util.HashMap.readObject",
          "source": "HashMap.java:1067"
        },
        {
          "method": "sun.reflect.NativeMethodAccessorImpl.invoke0",
          "source": "Native Method"
        },
        {
          "method": "sun.reflect.NativeMethodAccessorImpl.invoke",
          "source": "NativeMethodAccessorImpl.java:39"
        },
        {
          "method": "sun.reflect.DelegatingMethodAccessorImpl.invoke",
          "source": "DelegatingMethodAccessorImpl.java:25"
        },
        {
          "method": "java.lang.reflect.Method.invoke",
          "source": "Method.java:585"
        },
        {
          "method": "java.io.ObjectStreamClass.invokeReadObject",
          "source": "ObjectStreamClass.java:946"
        },
        {
          "method": "java.io.ObjectInputStream.readSerialData",
          "source": "ObjectInputStream.java:1809"
        },
        {
          "method": "java.io.ObjectInputStream.readOrdinaryObject",
          "source": "ObjectInputStream.java:1719"
        },
        {
          "method": "java.io.ObjectInputStream.readObject0",
          "source": "ObjectInputStream.java:1305"
        },
        {
          "method": "java.io.ObjectInputStream.readObject",
          "source": "ObjectInputStream.java:348"
        },
        {
          "method": "org.apache.catalina.session.StandardSession.readObject",
          "source": "StandardSession.java:1402"
        },
        {
          "method": "org.apache.catalina.session.StandardSession.readObjectData",
          "source": "StandardSession.java:931"
        },
        {
          "method": "org.apache.catalina.session.StandardManager.doLoad",
          "source": "StandardManager.java:394"
        },
        {
          "method": "org.apache.catalina.session.StandardManager.load",
          "source": "StandardManager.java:321"
        },
        {
          "method": "org.apache.catalina.session.StandardManager.start",
          "source": "StandardManager.java:637"
        },
        {
          "method": "org.apache.catalina.core.ContainerBase.setManager",
          "source": "ContainerBase.java:432"
        },
        {
          "method": "org.apache.catalina.core.StandardContext.start",
          "source": "StandardContext.java:4160"
        },
        {
          "method": "org.apache.catalina.core.ContainerBase.addChildInternal",
          "source": "ContainerBase.java:760"
        },
        {
          "method": "org.apache.catalina.core.ContainerBase.addChild",
          "source": "ContainerBase.java:740"
        },
        {
          "method": "org.apache.catalina.core.StandardHost.addChild",
          "source": "StandardHost.java:544"
        },
        {
          "method": "org.apache.catalina.startup.HostConfig.deployDirectory",
          "source": "HostConfig.java:920"
        },
        {
          "method": "org.apache.catalina.startup.HostConfig.deployDirectories",
          "source": "HostConfig.java:883"
        },
        {
          "method": "org.apache.catalina.startup.HostConfig.deployApps",
          "source": "HostConfig.java:492"
        },
        {
          "method": "org.apache.catalina.startup.HostConfig.start",
          "source": "HostConfig.java:1138"
        },
        {
          "method": "org.apache.catalina.startup.HostConfig.lifecycleEvent",
          "source": "HostConfig.java:311"
        },
        {
          "method": "org.apache.catalina.util.LifecycleSupport.fireLifecycleEvent",
          "source": "LifecycleSupport.java:120"
        },
        {
          "method": "org.apache.catalina.core.ContainerBase.start",
          "source": "ContainerBase.java:1022"
        },
        {
          "method": "org.apache.catalina.core.StandardHost.start",
          "source": "StandardHost.java:736"
        },
        {
          "method": "org.apache.catalina.core.ContainerBase.start",
          "source": "ContainerBase.java:1014"
        },
        {
          "method": "org.apache.catalina.core.StandardEngine.start",
          "source": "StandardEngine.java:443"
        },
        {
          "method": "org.apache.catalina.core.StandardService.start",
          "source": "StandardService.java:448"
        },
        {
          "method": "org.apache.catalina.core.StandardServer.start",
          "source": "StandardServer.java:700"
        },
        {
          "method": "org.apache.catalina.startup.Catalina.start",
          "source": "Catalina.java:552"
        },
        {
          "method": "sun.reflect.NativeMethodAccessorImpl.invoke0",
          "source": "Native Method"
        },
        {
          "method": "sun.reflect.NativeMethodAccessorImpl.invoke",
          "source": "NativeMethodAccessorImpl.java:39"
        },
        {
          "method": "sun.reflect.DelegatingMethodAccessorImpl.invoke",
          "source": "DelegatingMethodAccessorImpl.java:25"
        },
        {
          "method": "java.lang.reflect.Method.invoke",
          "source": "Method.java:585"
        },
        {
          "method": "org.apache.catalina.startup.Bootstrap.start",
          "source": "Bootstrap.java:295"
        },
        {
          "method": "org.apache.catalina.startup.Bootstrap.main",
          "source": "Bootstrap.java:433"
        }
      ],
      "number": 0,
      "commentIndex": 0,
      "bugId": "193820",
      "date": "2007-06-21T21:14:40+02:00",
      "product": "Cosmos",
      "component": "ResourceModeling",
      "severity": "normal"
    },
    {
      "exceptionType": "java.io.InvalidClassException",
      "message": "org.eclipse.cosmos.rm.repository.internal.application.impl.SMLFileResourceInstance; no valid constructor",
      "elements": [
        {
          "method": "java.io.ObjectStreamClass.\u003cinit\u003e",
          "source": "ObjectStreamClass.java:455"
        },
        {
          "method": "java.io.ObjectStreamClass.lookup",
          "source": "ObjectStreamClass.java:297"
        },
        {
          "method": "java.io.ObjectStreamClass.initNonProxy",
          "source": "ObjectStreamClass.java:531"
        },
        {
          "method": "java.io.ObjectInputStream.readNonProxyDesc",
          "source": "ObjectInputStream.java:1552"
        },
        {
          "method": "java.io.ObjectInputStream.readClassDesc",
          "source": "ObjectInputStream.java:1466"
        },
        {
          "method": "java.io.ObjectInputStream.readOrdinaryObject",
          "source": "ObjectInputStream.java:1699"
        },
        {
          "method": "java.io.ObjectInputStream.readObject0",
          "source": "ObjectInputStream.java:1305"
        },
        {
          "method": "java.io.ObjectInputStream.readObject",
          "source": "ObjectInputStream.java:348"
        },
        {
          "method": "java.util.HashMap.readObject",
          "source": "HashMap.java:1067"
        },
        {
          "method": "sun.reflect.NativeMethodAccessorImpl.invoke0",
          "source": "Native Method"
        },
        {
          "method": "sun.reflect.NativeMethodAccessorImpl.invoke",
          "source": "NativeMethodAccessorImpl.java:39"
        },
        {
          "method": "sun.reflect.DelegatingMethodAccessorImpl.invoke",
          "source": "DelegatingMethodAccessorImpl.java:25"
        },
        {
          "method": "java.lang.reflect.Method.invoke",
          "source": "Method.java:585"
        },
        {
          "method": "java.io.ObjectStreamClass.invokeReadObject",
          "source": "ObjectStreamClass.java:946"
        },
        {
          "method": "java.io.ObjectInputStream.readSerialData",
          "source": "ObjectInputStream.java:1809"
        },
        {
          "method": "java.io.ObjectInputStream.readOrdinaryObject",
          "source": "ObjectInputStream.java:1719"
        },
        {
          "method": "java.io.ObjectInputStream.readObject0",
          "source": "ObjectInputStream.java:1305"
        },
        {
          "method": "java.io.ObjectInputStream.readObject",
          "source": "ObjectInputStream.java:348"
        },
        {
          "method": "org.apache.catalina.session.StandardSession.readObject",
          "source": "StandardSession.java:1402"
        },
        {
          "method": "org.apache.catalina.session.StandardSession.readObjectData",
          "source": "StandardSession.java:931"
        },
        {
          "method": "org.apache.catalina.session.StandardManager.doLoad",
          "source": "StandardManager.java:394"
        },
        {
          "method": "org.apache.catalina.session.StandardManager.load",
          "source": "StandardManager.java:321"
        },
        {
          "method": "org.apache.catalina.session.StandardManager.start",
          "source": "StandardManager.java:637"
        },
        {
          "method": "org.apache.catalina.core.ContainerBase.setManager",
          "source": "ContainerBase.java:432"
        },
        {
          "method": "org.apache.catalina.core.StandardContext.start",
          "source": "StandardContext.java:4160"
        },
        {
          "method": "org.apache.catalina.core.ContainerBase.addChildInternal",
          "source": "ContainerBase.java:760"
        },
        {
          "method": "org.apache.catalina.core.ContainerBase.addChild",
          "source": "ContainerBase.java:740"
        },
        {
          "method": "org.apache.catalina.core.StandardHost.addChild",
          "source": "StandardHost.java:544"
        },
        {
          "method": "org.apache.catalina.startup.HostConfig.deployDirectory",
          "source": "HostConfig.java:920"
        },
        {
          "method": "org.apache.catalina.startup.HostConfig.deployDirectories",
          "source": "HostConfig.java:883"
        },
        {
          "method": "org.apache.catalina.startup.HostConfig.deployApps",
          "source": "HostConfig.java:492"
        },
        {
          "method": "org.apache.catalina.startup.HostConfig.start",
          "source": "HostConfig.java:1138"
        },
        {
          "method": "org.apache.catalina.startup.HostConfig.lifecycleEvent",
          "source": "HostConfig.java:311"
        },
        {
          "method": "org.apache.catalina.util.LifecycleSupport.fireLifecycleEvent",
          "source": "LifecycleSupport.java:120"
        },
        {
          "method": "org.apache.catalina.core.ContainerBase.start",
          "source": "ContainerBase.java:1022"
        },
        {
          "method": "org.apache.catalina.core.StandardHost.start",
          "source": "StandardHost.java:736"
        },
        {
          "method": "org.apache.catalina.core.ContainerBase.start",
          "source": "ContainerBase.java:1014"
        },
        {
          "method": "org.apache.catalina.core.StandardEngine.start",
          "source": "StandardEngine.java:443"
        },
        {
          "method": "org.apache.catalina.core.StandardService.start",
          "source": "StandardService.java:448"
        },
        {
          "method": "org.apache.catalina.core.StandardServer.start",
          "source": "StandardServer.java:700"
        },
        {
          "method": "org.apache.catalina.startup.Catalina.start",
          "source": "Catalina.java:552"
        },
        {
          "method": "sun.reflect.NativeMethodAccessorImpl.invoke0",
          "source": "Native Method"
        },
        {
          "method": "sun.reflect.NativeMethodAccessorImpl.invoke",
          "source": "NativeMethodAccessorImpl.java:39"
        },
        {
          "method": "sun.reflect.DelegatingMethodAccessorImpl.invoke",
          "source": "DelegatingMethodAccessorImpl.java:25"
        },
        {
          "method": "java.lang.reflect.Method.invoke",
          "source": "Method.java:585"
        },
        {
          "method": "org.apache.catalina.startup.Bootstrap.start",
          "source": "Bootstrap.java:295"
        },
        {
          "method": "org.apache.catalina.startup.Bootstrap.main",
          "source": "Bootstrap.java:433"
        }
      ],
      "number": 1,
      "commentIndex": 0,
      "bugId": "193820",
      "date": "2007-06-21T21:14:40+02:00",
      "product": "Cosmos",
      "component": "ResourceModeling",
      "severity": "normal"
    }
  ],
  "groupId": "193820",
  "bugId": "193820",
  "date": "2007-06-21T21:14:40+02:00",
  "product": "Cosmos",
  "component": "ResourceModeling",
  "severity": "normal"
}