{
  "comments": [
    "The BatchJobView does not appear in the Operator perspective and throws the following exception in the log:\n\n(This was observed on Mac OS X but not sure about other OS\u0027es)\n\n-----\n!ENTRY org.eclipse.ui 4 4 2007-06-22 09:42:17.521\n!MESSAGE Exception in org.eclipse.ui.internal.FolderLayout.addView(String): org.eclipse.ui.PartInitException: View descriptor not found: eu.geclipse.batch.ui.views.BatchJobView\n!STACK 1\norg.eclipse.ui.PartInitException: View descriptor not found: eu.geclipse.batch.ui.views.BatchJobView\n        at org.eclipse.ui.internal.FolderLayout.addView(FolderLayout.java:75)\n        at eu.geclipse.ui.internal.OperatorPerspectiveFactory.createInitialLayout(OperatorPerspectiveFactory.java:53)\n        at org.eclipse.ui.internal.Perspective.loadPredefinedPersp(Perspective.java:768)\n        at org.eclipse.ui.internal.Perspective.createPresentation(Perspective.java:258)\n        at org.eclipse.ui.internal.Perspective.\u003cinit\u003e(Perspective.java:146)\n        at org.eclipse.ui.internal.WorkbenchPage.createPerspective(WorkbenchPage.java:1537)\n        at org.eclipse.ui.internal.WorkbenchPage.busySetPerspective(WorkbenchPage.java:981)\n        at org.eclipse.ui.internal.WorkbenchPage.access$17(WorkbenchPage.java:972)\n        at org.eclipse.ui.internal.WorkbenchPage$18.run(WorkbenchPage.java:3560)\n        at org.eclipse.swt.custom.BusyIndicator.showWhile(BusyIndicator.java:67)\n        at org.eclipse.ui.internal.WorkbenchPage.setPerspective(WorkbenchPage.java:3558)\n        at org.eclipse.ui.internal.ChangeToPerspectiveMenu.run(ChangeToPerspectiveMenu.java:92)\n        at org.eclipse.ui.actions.PerspectiveMenu.run(PerspectiveMenu.java:336)\n        at org.eclipse.ui.actions.PerspectiveMenu.runOther(PerspectiveMenu.java:352)\n        at org.eclipse.ui.actions.PerspectiveMenu$3.runWithEvent(PerspectiveMenu.java:108)\n        at org.eclipse.jface.action.ActionContributionItem.handleWidgetSelection(ActionContributionItem.java:545)\n        at org.eclipse.jface.action.ActionContributionItem.access$2(ActionContributionItem.java:490)\n        at org.eclipse.jface.action.ActionContributionItem$5.handleEvent(ActionContributionItem.java:402)\n        at org.eclipse.swt.widgets.EventTable.sendEvent(EventTable.java:66)\n        at org.eclipse.swt.widgets.Widget.sendEvent(Widget.java:1495)\n        at org.eclipse.swt.widgets.Widget.sendEvent(Widget.java:1519)\n        at org.eclipse.swt.widgets.Widget.sendEvent(Widget.java:1504)\n        at org.eclipse.swt.widgets.Widget.notifyListeners(Widget.java:1295)\n        at org.eclipse.swt.widgets.Display.runDeferredEvents(Display.java:3349)\n        at org.eclipse.swt.widgets.Display.readAndDispatch(Display.java:2953)\n        at org.eclipse.ui.internal.Workbench.runEventLoop(Workbench.java:2389)\n        at org.eclipse.ui.internal.Workbench.runUI(Workbench.java:2353)\n        at org.eclipse.ui.internal.Workbench.access$4(Workbench.java:2219)\n        at org.eclipse.ui.internal.Workbench$4.run(Workbench.java:466)\n        at org.eclipse.core.databinding.observable.Realm.runWithDefault(Realm.java:289)\n        at org.eclipse.ui.internal.Workbench.createAndRunWorkbench(Workbench.java:461)\n        at org.eclipse.ui.PlatformUI.createAndRunWorkbench(PlatformUI.java:149)\n        at org.eclipse.ui.internal.ide.application.IDEApplication.start(IDEApplication.java:106)\n        at org.eclipse.equinox.internal.app.EclipseAppHandle.run(EclipseAppHandle.java:153)\n        at org.eclipse.core.runtime.internal.adaptor.EclipseAppLauncher.runApplication(EclipseAppLauncher.java:106)\n        at org.eclipse.core.runtime.internal.adaptor.EclipseAppLauncher.start(EclipseAppLauncher.java:76)\n        at org.eclipse.core.runtime.adaptor.EclipseStarter.run(EclipseStarter.java:363)\n        at org.eclipse.core.runtime.adaptor.EclipseStarter.run(EclipseStarter.java:176)\n        at sun.reflect.NativeMethodAccessorImpl.invoke0(Native Method)\n        at sun.reflect.NativeMethodAccessorImpl.invoke(NativeMethodAccessorImpl.java:39)\n        at sun.reflect.DelegatingMethodAccessorImpl.invoke(DelegatingMethodAccessorImpl.java:25)\n        at java.lang.reflect.Method.invoke(Method.java:585)\n        at org.eclipse.equinox.launcher.Main.invokeFramework(Main.java:504)\n        at org.eclipse.equinox.launcher.Main.basicRun(Main.java:443)\n        at org.eclipse.equinox.launcher.Main.run(Main.java:1169)\n!SUBENTRY 1 org.eclipse.ui 4 0 2007-06-22 09:42:17.523\n!MESSAGE View descriptor not found: eu.geclipse.batch.ui.views.BatchJobView\n\n-----",
    "This is important for RC0.\nPlease fix soon!",
    "(In reply to comment #1)\n\u003e This is important for RC0.\n\u003e Please fix soon!\n\u003e \n\nThe reason for this \"bug\" is that the two batch plugins are not part of the release. I have contacted Mathias and Markus about it. ",
    "The two batch plugins (eu.geclipse.batch and eu.geclipse.batch.ui) are now part of the pre-release build"
  ],
  "commentCreationDates": [
    "2007-06-22T11:02:44+02:00",
    "2007-06-22T14:30:49+02:00",
    "2007-06-22T19:44:56+02:00",
    "2007-06-27T11:25:16+02:00"
  ],
  "traces": [
    {
      "exceptionType": "org.eclipse.ui.PartInitException",
      "message": "View descriptor not found: eu.geclipse.batch.ui.views.BatchJobView",
      "elements": [
        {
          "method": "org.eclipse.ui.internal.FolderLayout.addView",
          "source": "FolderLayout.java:75"
        },
        {
          "method": "eu.geclipse.ui.internal.OperatorPerspectiveFactory.createInitialLayout",
          "source": "OperatorPerspectiveFactory.java:53"
        },
        {
          "method": "org.eclipse.ui.internal.Perspective.loadPredefinedPersp",
          "source": "Perspective.java:768"
        },
        {
          "method": "org.eclipse.ui.internal.Perspective.createPresentation",
          "source": "Perspective.java:258"
        },
        {
          "method": "org.eclipse.ui.internal.Perspective.\u003cinit\u003e",
          "source": "Perspective.java:146"
        },
        {
          "method": "org.eclipse.ui.internal.WorkbenchPage.createPerspective",
          "source": "WorkbenchPage.java:1537"
        },
        {
          "method": "org.eclipse.ui.internal.WorkbenchPage.busySetPerspective",
          "source": "WorkbenchPage.java:981"
        },
        {
          "method": "org.eclipse.ui.internal.WorkbenchPage.access$17",
          "source": "WorkbenchPage.java:972"
        },
        {
          "method": "org.eclipse.ui.internal.WorkbenchPage$18.run",
          "source": "WorkbenchPage.java:3560"
        },
        {
          "method": "org.eclipse.swt.custom.BusyIndicator.showWhile",
          "source": "BusyIndicator.java:67"
        },
        {
          "method": "org.eclipse.ui.internal.WorkbenchPage.setPerspective",
          "source": "WorkbenchPage.java:3558"
        },
        {
          "method": "org.eclipse.ui.internal.ChangeToPerspectiveMenu.run",
          "source": "ChangeToPerspectiveMenu.java:92"
        },
        {
          "method": "org.eclipse.ui.actions.PerspectiveMenu.run",
          "source": "PerspectiveMenu.java:336"
        },
        {
          "method": "org.eclipse.ui.actions.PerspectiveMenu.runOther",
          "source": "PerspectiveMenu.java:352"
        },
        {
          "method": "org.eclipse.ui.actions.PerspectiveMenu$3.runWithEvent",
          "source": "PerspectiveMenu.java:108"
        },
        {
          "method": "org.eclipse.jface.action.ActionContributionItem.handleWidgetSelection",
          "source": "ActionContributionItem.java:545"
        },
        {
          "method": "org.eclipse.jface.action.ActionContributionItem.access$2",
          "source": "ActionContributionItem.java:490"
        },
        {
          "method": "org.eclipse.jface.action.ActionContributionItem$5.handleEvent",
          "source": "ActionContributionItem.java:402"
        },
        {
          "method": "org.eclipse.swt.widgets.EventTable.sendEvent",
          "source": "EventTable.java:66"
        },
        {
          "method": "org.eclipse.swt.widgets.Widget.sendEvent",
          "source": "Widget.java:1495"
        },
        {
          "method": "org.eclipse.swt.widgets.Widget.sendEvent",
          "source": "Widget.java:1519"
        },
        {
          "method": "org.eclipse.swt.widgets.Widget.sendEvent",
          "source": "Widget.java:1504"
        },
        {
          "method": "org.eclipse.swt.widgets.Widget.notifyListeners",
          "source": "Widget.java:1295"
        },
        {
          "method": "org.eclipse.swt.widgets.Display.runDeferredEvents",
          "source": "Display.java:3349"
        },
        {
          "method": "org.eclipse.swt.widgets.Display.readAndDispatch",
          "source": "Display.java:2953"
        },
        {
          "method": "org.eclipse.ui.internal.Workbench.runEventLoop",
          "source": "Workbench.java:2389"
        },
        {
          "method": "org.eclipse.ui.internal.Workbench.runUI",
          "source": "Workbench.java:2353"
        },
        {
          "method": "org.eclipse.ui.internal.Workbench.access$4",
          "source": "Workbench.java:2219"
        },
        {
          "method": "org.eclipse.ui.internal.Workbench$4.run",
          "source": "Workbench.java:466"
        },
        {
          "method": "org.eclipse.core.databinding.observable.Realm.runWithDefault",
          "source": "Realm.java:289"
        },
        {
          "method": "org.eclipse.ui.internal.Workbench.createAndRunWorkbench",
          "source": "Workbench.java:461"
        },
        {
          "method": "org.eclipse.ui.PlatformUI.createAndRunWorkbench",
          "source": "PlatformUI.java:149"
        },
        {
          "method": "org.eclipse.ui.internal.ide.application.IDEApplication.start",
          "source": "IDEApplication.java:106"
        },
        {
          "method": "org.eclipse.equinox.internal.app.EclipseAppHandle.run",
          "source": "EclipseAppHandle.java:153"
        },
        {
          "method": "org.eclipse.core.runtime.internal.adaptor.EclipseAppLauncher.runApplication",
          "source": "EclipseAppLauncher.java:106"
        },
        {
          "method": "org.eclipse.core.runtime.internal.adaptor.EclipseAppLauncher.start",
          "source": "EclipseAppLauncher.java:76"
        },
        {
          "method": "org.eclipse.core.runtime.adaptor.EclipseStarter.run",
          "source": "EclipseStarter.java:363"
        },
        {
          "method": "org.eclipse.core.runtime.adaptor.EclipseStarter.run",
          "source": "EclipseStarter.java:176"
        },
        {
          "method": "sun.reflect.NativeMethodAccessorImpl.invoke0",
          "source": "Native Method"
        },
        {
          "method": "sun.reflect.NativeMethodAccessorImpl.invoke",
          "source": "NativeMethodAccessorImpl.java:39"
        },
        {
          "method": "sun.reflect.DelegatingMethodAccessorImpl.invoke",
          "source": "DelegatingMethodAccessorImpl.java:25"
        },
        {
          "method": "java.lang.reflect.Method.invoke",
          "source": "Method.java:585"
        },
        {
          "method": "org.eclipse.equinox.launcher.Main.invokeFramework",
          "source": "Main.java:504"
        },
        {
          "method": "org.eclipse.equinox.launcher.Main.basicRun",
          "source": "Main.java:443"
        },
        {
          "method": "org.eclipse.equinox.launcher.Main.run",
          "source": "Main.java:1169"
        }
      ],
      "number": 0,
      "commentIndex": 0,
      "bugId": "193920",
      "date": "2007-06-22T11:02:44+02:00",
      "product": "gEclipse",
      "component": "geclipse",
      "severity": "minor"
    }
  ],
  "groupId": "193920",
  "bugId": "193920",
  "date": "2007-06-22T11:02:44+02:00",
  "product": "gEclipse",
  "component": "geclipse",
  "severity": "minor"
}