{
  "comments": [
    "java.lang.NullPointerException\n    at org.eclipse.nebula.widgets.grid.Grid.onKeyDown(Grid.java:6918)\n    at org.eclipse.nebula.widgets.grid.Grid.access$4(Grid.java:6616)\n    at org.eclipse.nebula.widgets.grid.Grid$8.handleEvent(Grid.java:5877)\n    at org.eclipse.swt.widgets.EventTable.sendEvent(Unknown Source)\n    at org.eclipse.swt.widgets.Widget.sendEvent (Unknown Source)\n    at org.eclipse.swt.widgets.Widget.sendEvent(Unknown Source)\n    at org.eclipse.swt.widgets.Widget.sendEvent(Unknown Source)\n    at org.eclipse.swt.widgets.Widget.sendKeyEvent(Unknown Source)\n    at org.eclipse.swt.widgets.Widget.sendKeyEvent(Unknown Source)\n    at org.eclipse.swt.widgets.Widget.wmKeyDown(Unknown Source)\n    at org.eclipse.swt.widgets.Control.WM_KEYDOWN(Unknown Source)\n    at org.eclipse.swt.widgets.Control.windowProc (Unknown Source)\n    at org.eclipse.swt.widgets.Canvas.windowProc(Unknown Source)\n    at org.eclipse.swt.widgets.Display.windowProc(Unknown Source)\n    at org.eclipse.swt.internal.win32.OS.DispatchMessageW(Native Method)\n    at org.eclipse.swt.internal.win32.OS.DispatchMessage(Unknown Source)\n    at org.eclipse.swt.widgets.Display.readAndDispatch(Unknown Source)\n    at GridSnippet3.main(GridSnippet3.java:108)",
    "Fixed.  Please download a new nightly build.",
    "Nice! Thanks! ok, I know. next day only download. :-D",
    "Actually this one I fixed shortly after you mentioned it on the list.  So you can download it right away.  Just wanted to make sure we still get bugs entered for these things."
  ],
  "commentCreationDates": [
    "2007-06-28T12:08:20+02:00",
    "2007-06-28T15:43:18+02:00",
    "2007-06-28T15:47:04+02:00",
    "2007-06-28T15:55:50+02:00"
  ],
  "traces": [
    {
      "exceptionType": "java.lang.NullPointerException",
      "elements": [
        {
          "method": "org.eclipse.nebula.widgets.grid.Grid.onKeyDown",
          "source": "Grid.java:6918"
        },
        {
          "method": "org.eclipse.nebula.widgets.grid.Grid.access$4",
          "source": "Grid.java:6616"
        },
        {
          "method": "org.eclipse.nebula.widgets.grid.Grid$8.handleEvent",
          "source": "Grid.java:5877"
        },
        {
          "method": "org.eclipse.swt.widgets.EventTable.sendEvent",
          "source": "Unknown Source"
        },
        {
          "method": "org.eclipse.swt.widgets.Widget.sendEvent",
          "source": "Unknown Source"
        },
        {
          "method": "org.eclipse.swt.widgets.Widget.sendEvent",
          "source": "Unknown Source"
        },
        {
          "method": "org.eclipse.swt.widgets.Widget.sendEvent",
          "source": "Unknown Source"
        },
        {
          "method": "org.eclipse.swt.widgets.Widget.sendKeyEvent",
          "source": "Unknown Source"
        },
        {
          "method": "org.eclipse.swt.widgets.Widget.sendKeyEvent",
          "source": "Unknown Source"
        },
        {
          "method": "org.eclipse.swt.widgets.Widget.wmKeyDown",
          "source": "Unknown Source"
        },
        {
          "method": "org.eclipse.swt.widgets.Control.WM_KEYDOWN",
          "source": "Unknown Source"
        },
        {
          "method": "org.eclipse.swt.widgets.Control.windowProc",
          "source": "Unknown Source"
        },
        {
          "method": "org.eclipse.swt.widgets.Canvas.windowProc",
          "source": "Unknown Source"
        },
        {
          "method": "org.eclipse.swt.widgets.Display.windowProc",
          "source": "Unknown Source"
        },
        {
          "method": "org.eclipse.swt.internal.win32.OS.DispatchMessageW",
          "source": "Native Method"
        },
        {
          "method": "org.eclipse.swt.internal.win32.OS.DispatchMessage",
          "source": "Unknown Source"
        },
        {
          "method": "org.eclipse.swt.widgets.Display.readAndDispatch",
          "source": "Unknown Source"
        },
        {
          "method": "GridSnippet3.main",
          "source": "GridSnippet3.java:108"
        }
      ],
      "number": 0,
      "commentIndex": 0,
      "bugId": "194729",
      "date": "2007-06-28T12:08:20+02:00",
      "product": "Nebula",
      "component": "Grid",
      "severity": "normal"
    }
  ],
  "groupId": "194729",
  "bugId": "194729",
  "date": "2007-06-28T12:08:20+02:00",
  "product": "Nebula",
  "component": "Grid",
  "severity": "normal"
}