{
  "comments": [
    "F2\n\nFound the following NPE in log\n\njava.lang.NullPointerException\n        at org.eclipse.jdt.internal.core.index.impl.CodeByteStream.readUnary(Cod\neByteStream.java:174)\n        at org.eclipse.jdt.internal.core.index.impl.CodeByteStream.readGamma(Cod\neByteStream.java:113)\n        at org.eclipse.jdt.internal.core.index.impl.GammaCompressedIndexBlock.ne\nxtEntry(GammaCompressedIndexBlock.java:96)\n        at org.eclipse.jdt.internal.core.index.impl.BlocksIndexInput.moveToNextW\nordEntry(BlocksIndexInput.java:186)\n        at org.eclipse.jdt.internal.core.index.impl.MergeFactory.mergeReferences\n(MergeFactory.java:176)\n        at org.eclipse.jdt.internal.core.index.impl.MergeFactory.merge(MergeFact\nory.java:85)\n        at org.eclipse.jdt.internal.core.index.impl.Index.merge(Index.java:249)\n        at org.eclipse.jdt.internal.core.index.impl.Index.save(Index.java:354)\n        at org.eclipse.jdt.internal.core.search.indexing.IndexManager.saveIndexe\ns(IndexManager.java:392)\n        at org.eclipse.jdt.internal.core.search.indexing.IndexManager.notifyIdle\n(IndexManager.java:276)\n        at org.eclipse.jdt.internal.core.search.processing.JobManager.run(JobMan\nager.java:315)\n        at java.lang.Thread.run(Thread.java:484)",
    "I could not find a path that would set null to the bytes collection. And this is the only way to get \nthis exception. Maybe a JIT problem? Which VM are you using?",
    "\n\n*** This bug has been marked as a duplicate of 13988 ***",
    "Sun JDK 1.3.1_01"
  ],
  "commentCreationDates": [
    "2002-06-06T17:22:59+02:00",
    "2002-06-07T19:48:42+02:00",
    "2002-06-07T19:52:13+02:00",
    "2002-06-07T20:00:38+02:00"
  ],
  "traces": [
    {
      "exceptionType": "java.lang.NullPointerException",
      "elements": [
        {
          "method": "org.eclipse.jdt.internal.core.index.impl.CodeByteStream.readUnary",
          "source": "Cod eByteStream.java:174"
        },
        {
          "method": "org.eclipse.jdt.internal.core.index.impl.CodeByteStream.readGamma",
          "source": "Cod eByteStream.java:113"
        },
        {
          "method": "org.eclipse.jdt.internal.core.index.impl.GammaCompressedIndexBlock.nextEntry",
          "source": "GammaCompressedIndexBlock.java:96"
        },
        {
          "method": "org.eclipse.jdt.internal.core.index.impl.BlocksIndexInput.moveToNextWordEntry",
          "source": "BlocksIndexInput.java:186"
        },
        {
          "method": "org.eclipse.jdt.internal.core.index.impl.MergeFactory.mergeReferences",
          "source": "MergeFactory.java:176"
        },
        {
          "method": "org.eclipse.jdt.internal.core.index.impl.MergeFactory.merge",
          "source": "MergeFact ory.java:85"
        },
        {
          "method": "org.eclipse.jdt.internal.core.index.impl.Index.merge",
          "source": "Index.java:249"
        },
        {
          "method": "org.eclipse.jdt.internal.core.index.impl.Index.save",
          "source": "Index.java:354"
        },
        {
          "method": "org.eclipse.jdt.internal.core.search.indexing.IndexManager.saveIndexes",
          "source": "IndexManager.java:392"
        },
        {
          "method": "org.eclipse.jdt.internal.core.search.indexing.IndexManager.notifyIdle",
          "source": "IndexManager.java:276"
        },
        {
          "method": "org.eclipse.jdt.internal.core.search.processing.JobManager.run",
          "source": "JobMan ager.java:315"
        },
        {
          "method": "java.lang.Thread.run",
          "source": "Thread.java:484"
        }
      ],
      "number": 0,
      "commentIndex": 0,
      "bugId": "19501",
      "duplicateId": "13988",
      "date": "2002-06-06T17:22:59+02:00",
      "product": "JDT",
      "component": "Core",
      "severity": "normal"
    }
  ],
  "groupId": "13988",
  "bugId": "19501",
  "duplicateId": "13988",
  "date": "2002-06-06T17:22:59+02:00",
  "product": "JDT",
  "component": "Core",
  "severity": "normal"
}