{
  "comments": [
    "Build ID: I20070608-1718\n\nSteps To Reproduce:\n1.  Select a row\n2.  Right-click with a context menu action or some other way to trigger an action that will remove a column.  Be sure to make sure the entire row is selected.\n3.  Perform the action and an iob exception occurs.\n\n\nMore information:\nin the removeColumn() method it removes the column , then updateColumnSelection() and in there causes an index out of bounds exception because the column no longer exists\n\nthe offending call in updateColumnSelection(): \nGridColumn col \u003d getColumn(cell.x);\n\nBy then it is too late , the column previously got removed in the removeColumn() call",
    "Hi Mike,\n\nI cannot reproduce this.  There is code in removeColumn() that specifically removes all cells from the removed column from the selection list.  I created a quick snippet just to verify and it worked correctly.  Can you provide the exact stack trace?  The lines you indicate shouldn\u0027t ever throw an IOB.  Also, if you provide a snippet that reproduces the problem I should be able to solve it asap.  Please see the SWT snippet pages to see what I mean:\nhttp://www.eclipse.org/swt/snippets/\n\nI need a small class that I can run, free from any supporting code that I do not have access to.  \n\nThanks,\n-Chris",
    "Hi Chris\n\nI am facing the same problem of indexOutOfBound exception when i try to remove a Column and one row is fully selected.\n\nI am including the stack trace as requested by you ... \n\njava.lang.IllegalArgumentException: Index out of bounds\n\tat org.eclipse.swt.SWT.error(SWT.java:3547)\n\tat org.eclipse.swt.SWT.error(SWT.java:3481)\n\tat org.eclipse.swt.SWT.error(SWT.java:3452)\n\tat org.eclipse.nebula.widgets.grid.Grid.getColumn(Grid.java:1067)\n\tat org.eclipse.nebula.widgets.grid.Grid.updateColumnSelection(Grid.java:5840)\n\tat org.eclipse.nebula.widgets.grid.Grid.removeColumn(Grid.java:7441)\n\tat org.eclipse.nebula.widgets.grid.GridColumn.dispose(GridColumn.java:228)\n\nTo reproduce the error follow the same steps as mentioned by Mike.\n\n\n\n",
    "I\u0027ve been able to reproduce this bug. The following conditions must be true for the IOB exception to be thrown. \n\n1. Have cell selection enabled.\n2. Have at least one column to the right of the column being removed\n3. Select a cell in both the column being removed and a column on the right",
    "Created an attachment (id\u003d75342)\nfix defect\n\nAttached that will fix the defect. The problem was that the selected cells needed to update their column index values to reflect the removed column. ",
    "committed."
  ],
  "commentCreationDates": [
    "2007-07-03T01:14:16+02:00",
    "2007-07-03T17:42:48+02:00",
    "2007-07-20T17:49:21+02:00",
    "2007-08-02T23:08:09+02:00",
    "2007-08-03T19:20:25+02:00",
    "2007-08-20T19:55:09+02:00"
  ],
  "traces": [
    {
      "exceptionType": "java.lang.IllegalArgumentException",
      "message": "Index out of bounds",
      "elements": [
        {
          "method": "org.eclipse.swt.SWT.error",
          "source": "SWT.java:3547"
        },
        {
          "method": "org.eclipse.swt.SWT.error",
          "source": "SWT.java:3481"
        },
        {
          "method": "org.eclipse.swt.SWT.error",
          "source": "SWT.java:3452"
        },
        {
          "method": "org.eclipse.nebula.widgets.grid.Grid.getColumn",
          "source": "Grid.java:1067"
        },
        {
          "method": "org.eclipse.nebula.widgets.grid.Grid.updateColumnSelection",
          "source": "Grid.java:5840"
        },
        {
          "method": "org.eclipse.nebula.widgets.grid.Grid.removeColumn",
          "source": "Grid.java:7441"
        },
        {
          "method": "org.eclipse.nebula.widgets.grid.GridColumn.dispose",
          "source": "GridColumn.java:228"
        }
      ],
      "number": 0,
      "commentIndex": 2,
      "bugId": "195194",
      "date": "2007-07-20T17:49:21+02:00",
      "product": "Nebula",
      "component": "Grid",
      "severity": "normal"
    }
  ],
  "groupId": "195194",
  "bugId": "195194",
  "date": "2007-07-03T01:14:16+02:00",
  "product": "Nebula",
  "component": "Grid",
  "severity": "normal"
}