{
  "comments": [
    "Build 20020602\n\nGot the following exception after pression Ctrl+B:\njava.lang.ArrayIndexOutOfBoundsException\n        at org.eclipse.jdt.internal.core.builder.JavaBuilder.initializeBuilder\n(JavaBuilder.java:412)\n        at org.eclipse.jdt.internal.core.builder.JavaBuilder.build\n(JavaBuilder.java:90)\n        at org.eclipse.core.internal.events.BuildManager$2.run\n(BuildManager.java:386)\n        at org.eclipse.core.internal.runtime.InternalPlatform.run\n(InternalPlatform.java:802)\n        at org.eclipse.core.runtime.Platform.run(Platform.java:416)\n        at org.eclipse.core.internal.events.BuildManager.basicBuild\n(BuildManager.java:120)\n        at org.eclipse.core.internal.events.BuildManager.basicBuild\n(BuildManager.java:176)\n        at org.eclipse.core.internal.events.BuildManager.basicBuild\n(BuildManager.java:186)\n        at org.eclipse.core.internal.events.BuildManager$1.run\n(BuildManager.java:146)\n        at org.eclipse.core.internal.runtime.InternalPlatform.run\n(InternalPlatform.java:802)\n        at org.eclipse.core.runtime.Platform.run(Platform.java:416)\n        at org.eclipse.core.internal.events.BuildManager.basicBuild\n(BuildManager.java:160)\n        at org.eclipse.core.internal.events.BuildManager.build\n(BuildManager.java:211)\n        at org.eclipse.core.internal.resources.Workspace.build\n(Workspace.java:142)\n        at org.eclipse.ui.actions.GlobalBuildAction$1.run\n(GlobalBuildAction.java:156)\n        at org.eclipse.jface.operation.ModalContext$ModalContextThread.run\n(ModalContext.java:98)",
    "Created an attachment (id\u003d1295)\nBuilder trace since I started the workspace (please ignore debugger stack traces)\n",
    "I have the following filtered resources: \u0027*.launch,\u0027",
    "We should protect from empty filters, e.g. \",,,\"",
    "Fixed by ignoring empty filters.",
    "Verified."
  ],
  "commentCreationDates": [
    "2002-06-06T18:46:53+02:00",
    "2002-06-06T18:48:39+02:00",
    "2002-06-06T19:41:26+02:00",
    "2002-06-06T19:44:02+02:00",
    "2002-06-06T19:47:50+02:00",
    "2002-06-14T11:24:46+02:00"
  ],
  "traces": [
    {
      "exceptionType": "java.lang.ArrayIndexOutOfBoundsException",
      "elements": [
        {
          "method": "org.eclipse.jdt.internal.core.builder.JavaBuilder.initializeBuilder",
          "source": "JavaBuilder.java:412"
        },
        {
          "method": "org.eclipse.jdt.internal.core.builder.JavaBuilder.build",
          "source": "JavaBuilder.java:90"
        },
        {
          "method": "org.eclipse.core.internal.events.BuildManager$2.run",
          "source": "BuildManager.java:386"
        },
        {
          "method": "org.eclipse.core.internal.runtime.InternalPlatform.run",
          "source": "InternalPlatform.java:802"
        },
        {
          "method": "org.eclipse.core.runtime.Platform.run",
          "source": "Platform.java:416"
        },
        {
          "method": "org.eclipse.core.internal.events.BuildManager.basicBuild",
          "source": "BuildManager.java:120"
        },
        {
          "method": "org.eclipse.core.internal.events.BuildManager.basicBuild",
          "source": "BuildManager.java:176"
        },
        {
          "method": "org.eclipse.core.internal.events.BuildManager.basicBuild",
          "source": "BuildManager.java:186"
        },
        {
          "method": "org.eclipse.core.internal.events.BuildManager$1.run",
          "source": "BuildManager.java:146"
        },
        {
          "method": "org.eclipse.core.internal.runtime.InternalPlatform.run",
          "source": "InternalPlatform.java:802"
        },
        {
          "method": "org.eclipse.core.runtime.Platform.run",
          "source": "Platform.java:416"
        },
        {
          "method": "org.eclipse.core.internal.events.BuildManager.basicBuild",
          "source": "BuildManager.java:160"
        },
        {
          "method": "org.eclipse.core.internal.events.BuildManager.build",
          "source": "BuildManager.java:211"
        },
        {
          "method": "org.eclipse.core.internal.resources.Workspace.build",
          "source": "Workspace.java:142"
        },
        {
          "method": "org.eclipse.ui.actions.GlobalBuildAction$1.run",
          "source": "GlobalBuildAction.java:156"
        },
        {
          "method": "org.eclipse.jface.operation.ModalContext$ModalContextThread.run",
          "source": "ModalContext.java:98"
        }
      ],
      "number": 0,
      "commentIndex": 0,
      "bugId": "19512",
      "date": "2002-06-06T18:46:53+02:00",
      "product": "JDT",
      "component": "Core",
      "severity": "normal"
    }
  ],
  "groupId": "19512",
  "bugId": "19512",
  "date": "2002-06-06T18:46:53+02:00",
  "product": "JDT",
  "component": "Core",
  "severity": "normal"
}