{
  "comments": [
    "Build ID: I20070621-1340\n\nSteps To Reproduce:\n1.run an application in Debug mode (with breakpoints)\n2.reach a breakpoint.\n\nMore information:\nSome log messages which should be shown under the console log are not and an error dialog window \"pops up\".\nThe \"details\" message says just \"Error\", but the summary one is about IOConsoleHandler.\n\nThe .metadata/.log contains stack about Unhandled event loop exception :\n!ENTRY org.eclipse.ui 4 0 2007-07-02 11:30:49.028\n!MESSAGE Unhandled event loop exception\n!STACK 0\norg.eclipse.swt.SWTException: Failed to execute runnable (java.lang.ArrayIndexOutOfBoundsException)\n        at org.eclipse.swt.SWT.error(SWT.java:3563)\n        at org.eclipse.swt.SWT.error(SWT.java:3481)\n        at org.eclipse.swt.widgets.Synchronizer.runAsyncMessages(Synchronizer.java:126)\n        at org.eclipse.swt.widgets.Display.runAsyncMessages(Display.java:3296)\n        at org.eclipse.swt.widgets.Display.readAndDispatch(Display.java:2974)\n        at org.eclipse.ui.internal.Workbench.runEventLoop(Workbench.java:2389)\n        at org.eclipse.ui.internal.Workbench.runUI(Workbench.java:2353)\n        at org.eclipse.ui.internal.Workbench.access$4(Workbench.java:2219)\n        at org.eclipse.ui.internal.Workbench$4.run(Workbench.java:466)\n        at org.eclipse.core.databinding.observable.Realm.runWithDefault(Realm.java:289)\n        at org.eclipse.ui.internal.Workbench.createAndRunWorkbench(Workbench.java:461)\n        at org.eclipse.ui.PlatformUI.createAndRunWorkbench(PlatformUI.java:149)\n        at org.eclipse.ui.internal.ide.application.IDEApplication.start(IDEApplication.java:106)\n        at org.eclipse.equinox.internal.app.EclipseAppHandle.run(EclipseAppHandle.java:153)\n        at org.eclipse.core.runtime.internal.adaptor.EclipseAppLauncher.runApplication(EclipseAppLauncher.java:106)\n        at org.eclipse.core.runtime.internal.adaptor.EclipseAppLauncher.start(EclipseAppLauncher.java:76)\n        at org.eclipse.core.runtime.adaptor.EclipseStarter.run(EclipseStarter.java:363)\n        at org.eclipse.core.runtime.adaptor.EclipseStarter.run(EclipseStarter.java:176)\n        at sun.reflect.NativeMethodAccessorImpl.invoke0(Native Method)\n        at sun.reflect.NativeMethodAccessorImpl.invoke(NativeMethodAccessorImpl.java:39)\n        at sun.reflect.DelegatingMethodAccessorImpl.invoke(DelegatingMethodAccessorImpl.java:25)\n        at java.lang.reflect.Method.invoke(Method.java:597)\n        at org.eclipse.equinox.launcher.Main.invokeFramework(Main.java:504)\n        at org.eclipse.equinox.launcher.Main.basicRun(Main.java:443)\n        at org.eclipse.equinox.launcher.Main.run(Main.java:1169)\nCaused by: java.lang.ArrayIndexOutOfBoundsException\n        at java.lang.System.arraycopy(Native Method)\n        at org.eclipse.swt.custom.StyledTextRenderer.textChanging(StyledTextRenderer.java:1235)\n        at org.eclipse.swt.custom.StyledText.handleTextChanging(StyledText.java:5348)\n        at org.eclipse.swt.custom.StyledText$6.textChanging(StyledText.java:4777)\n        at org.eclipse.ui.internal.console.ConsoleDocumentAdapter.documentAboutToBeChanged(ConsoleDocumentAdapter.java:298)\n        at org.eclipse.jface.text.AbstractDocument.fireDocumentAboutToBeChanged(AbstractDocument.java:606)\n        at org.eclipse.jface.text.AbstractDocument.replace(AbstractDocument.java:1072)\n        at org.eclipse.jface.text.AbstractDocument.replace(AbstractDocument.java:1089)\n        at org.eclipse.ui.internal.console.ConsoleDocument.replace(ConsoleDocument.java:82)\n        at org.eclipse.ui.internal.console.IOConsolePartitioner$QueueProcessingJob.runInUIThread(IOConsolePartitioner.java:536)\n        at org.eclipse.ui.progress.UIJob$1.run(UIJob.java:94)\n        at org.eclipse.swt.widgets.RunnableLock.run(RunnableLock.java:35)\n        at org.eclipse.swt.widgets.Synchronizer.runAsyncMessages(Synchronizer.java:123)\n        ... 22 more",
    "The exact error String is: \"IOConsoleUpdater (Time of error: ...)\".\nThe bug occurs a new time but I have no more process under debug (even if I am still under the Debug Perspective).",
    "After analyse I have found the process I have spoken about opens an InputStreamReader on the standard input (System.in).\nPerhaps there is problem with concurrent input/output on the console ?",
    "Keeping on my analyse, I have just discovered that some logs are longer than 11000 characters !\nAfter having seriously reduced such log messages, the problem has not occured for a moment ...",
    "I\u0027ve got a similar error whilst having the fixed width console option enabled (was set to 200). Once I disabled this option, the problem was gone. My program makes a pretty long output to a standard out.\n\nBelow are error details:\n\neclipse.buildId\u003dI20070625-1500\njava.version\u003d1.5.0_11\njava.vendor\u003dSun Microsystems Inc.\nBootLoader constants: OS\u003dlinux, ARCH\u003dx86, WS\u003dgtk, NL\u003den_US\nCommand-line arguments:  -os linux -ws gtk -arch x86\n\nError\nThu Jul 05 17:23:39 CEST 2007\nUnhandled event loop exception\n\norg.eclipse.swt.SWTException: Failed to execute runnable (java.lang.ArrayIndexOutOfBoundsException)\nat org.eclipse.swt.SWT.error(SWT.java:3563)\nat org.eclipse.swt.SWT.error(SWT.java:3481)\nat org.eclipse.swt.widgets.Synchronizer.runAsyncMessages(Synchronizer.java:126)\nat org.eclipse.swt.widgets.Display.runAsyncMessages(Display.java:3296)\nat org.eclipse.swt.widgets.Display.readAndDispatch(Display.java:2974)\nat org.eclipse.ui.internal.Workbench.runEventLoop(Workbench.java:2389)\nat org.eclipse.ui.internal.Workbench.runUI(Workbench.java:2353)\nat org.eclipse.ui.internal.Workbench.access$4(Workbench.java:2219)\nat org.eclipse.ui.internal.Workbench$4.run(Workbench.java:466)\nat org.eclipse.core.databinding.observable.Realm.runWithDefault(Realm.java:289)\nat org.eclipse.ui.internal.Workbench.createAndRunWorkbench(Workbench.java:461)\nat org.eclipse.ui.PlatformUI.createAndRunWorkbench(PlatformUI.java:149)\nat org.eclipse.ui.internal.ide.application.IDEApplication.start(IDEApplication.java:106)\nat org.eclipse.equinox.internal.app.EclipseAppHandle.run(EclipseAppHandle.java:153)\nat org.eclipse.core.runtime.internal.adaptor.EclipseAppLauncher.runApplication(EclipseAppLauncher.java:106)\nat org.eclipse.core.runtime.internal.adaptor.EclipseAppLauncher.start(EclipseAppLauncher.java:76)\nat org.eclipse.core.runtime.adaptor.EclipseStarter.run(EclipseStarter.java:363)\nat org.eclipse.core.runtime.adaptor.EclipseStarter.run(EclipseStarter.java:176)\nat sun.reflect.NativeMethodAccessorImpl.invoke0(Native Method)\nat sun.reflect.NativeMethodAccessorImpl.invoke(NativeMethodAccessorImpl.java:39)\nat sun.reflect.DelegatingMethodAccessorImpl.invoke(DelegatingMethodAccessorImpl.java:25)\nat java.lang.reflect.Method.invoke(Method.java:585)\nat org.eclipse.equinox.launcher.Main.invokeFramework(Main.java:504)\nat org.eclipse.equinox.launcher.Main.basicRun(Main.java:443)\nat org.eclipse.equinox.launcher.Main.run(Main.java:1169)\nCaused by: java.lang.ArrayIndexOutOfBoundsException\nat java.lang.System.arraycopy(Native Method)\nat org.eclipse.swt.custom.StyledTextRenderer.textChanging(StyledTextRenderer.java:1235)\nat org.eclipse.swt.custom.StyledText.handleTextChanging(StyledText.java:5348)\nat org.eclipse.swt.custom.StyledText$6.textChanging(StyledText.java:4777)\nat org.eclipse.ui.internal.console.ConsoleDocumentAdapter.documentAboutToBeChanged(ConsoleDocumentAdapter.java:298)\nat org.eclipse.jface.text.AbstractDocument.fireDocumentAboutToBeChanged(AbstractDocument.java:606)\nat org.eclipse.jface.text.AbstractDocument.replace(AbstractDocument.java:1072)\nat org.eclipse.jface.text.AbstractDocument.replace(AbstractDocument.java:1091)\nat org.eclipse.ui.internal.console.ConsoleDocument.replace(ConsoleDocument.java:82)\nat org.eclipse.ui.internal.console.IOConsolePartitioner$QueueProcessingJob.runInUIThread(IOConsolePartitioner.java:536)\nat org.eclipse.ui.progress.UIJob$1.run(UIJob.java:94)\nat org.eclipse.swt.widgets.RunnableLock.run(RunnableLock.java:35)\nat org.eclipse.swt.widgets.Synchronizer.runAsyncMessages(Synchronizer.java:123)\n... 22 more\n\n",
    "I can confirm Simeon finding (btw, thanks for the workaround!!!). Removing the tick from \"Preferences \u003e Run/Debug \u003e Console \u003e Fixed width console\" did it for me. We run our application with JBoss and Tomcat and both output quite long lines.",
    "*** Bug 200717 has been marked as a duplicate of this bug. ***",
    "*** Bug 201075 has been marked as a duplicate of this bug. ***",
    "*** Bug 208239 has been marked as a duplicate of this bug. ***",
    "fixed in 3.3.2\n\n*** This bug has been marked as a duplicate of bug 208084 ***"
  ],
  "commentCreationDates": [
    "2007-07-02T11:57:47+02:00",
    "2007-07-02T13:29:18+02:00",
    "2007-07-02T14:21:21+02:00",
    "2007-07-03T09:31:17+02:00",
    "2007-07-05T20:31:31+02:00",
    "2007-08-07T19:10:06+02:00",
    "2007-08-21T20:03:00+02:00",
    "2007-09-13T20:49:04+02:00",
    "2007-11-01T19:35:34+01:00",
    "2007-11-07T19:42:30+01:00"
  ],
  "traces": [
    {
      "exceptionType": "org.eclipse.swt.SWTException",
      "message": "Failed to execute runnable (java.lang.ArrayIndexOutOfBoundsException)",
      "elements": [
        {
          "method": "org.eclipse.swt.SWT.error",
          "source": "SWT.java:3563"
        },
        {
          "method": "org.eclipse.swt.SWT.error",
          "source": "SWT.java:3481"
        },
        {
          "method": "org.eclipse.swt.widgets.Synchronizer.runAsyncMessages",
          "source": "Synchronizer.java:126"
        },
        {
          "method": "org.eclipse.swt.widgets.Display.runAsyncMessages",
          "source": "Display.java:3296"
        },
        {
          "method": "org.eclipse.swt.widgets.Display.readAndDispatch",
          "source": "Display.java:2974"
        },
        {
          "method": "org.eclipse.ui.internal.Workbench.runEventLoop",
          "source": "Workbench.java:2389"
        },
        {
          "method": "org.eclipse.ui.internal.Workbench.runUI",
          "source": "Workbench.java:2353"
        },
        {
          "method": "org.eclipse.ui.internal.Workbench.access$4",
          "source": "Workbench.java:2219"
        },
        {
          "method": "org.eclipse.ui.internal.Workbench$4.run",
          "source": "Workbench.java:466"
        },
        {
          "method": "org.eclipse.core.databinding.observable.Realm.runWithDefault",
          "source": "Realm.java:289"
        },
        {
          "method": "org.eclipse.ui.internal.Workbench.createAndRunWorkbench",
          "source": "Workbench.java:461"
        },
        {
          "method": "org.eclipse.ui.PlatformUI.createAndRunWorkbench",
          "source": "PlatformUI.java:149"
        },
        {
          "method": "org.eclipse.ui.internal.ide.application.IDEApplication.start",
          "source": "IDEApplication.java:106"
        },
        {
          "method": "org.eclipse.equinox.internal.app.EclipseAppHandle.run",
          "source": "EclipseAppHandle.java:153"
        },
        {
          "method": "org.eclipse.core.runtime.internal.adaptor.EclipseAppLauncher.runApplication",
          "source": "EclipseAppLauncher.java:106"
        },
        {
          "method": "org.eclipse.core.runtime.internal.adaptor.EclipseAppLauncher.start",
          "source": "EclipseAppLauncher.java:76"
        },
        {
          "method": "org.eclipse.core.runtime.adaptor.EclipseStarter.run",
          "source": "EclipseStarter.java:363"
        },
        {
          "method": "org.eclipse.core.runtime.adaptor.EclipseStarter.run",
          "source": "EclipseStarter.java:176"
        },
        {
          "method": "sun.reflect.NativeMethodAccessorImpl.invoke0",
          "source": "Native Method"
        },
        {
          "method": "sun.reflect.NativeMethodAccessorImpl.invoke",
          "source": "NativeMethodAccessorImpl.java:39"
        },
        {
          "method": "sun.reflect.DelegatingMethodAccessorImpl.invoke",
          "source": "DelegatingMethodAccessorImpl.java:25"
        },
        {
          "method": "java.lang.reflect.Method.invoke",
          "source": "Method.java:597"
        },
        {
          "method": "org.eclipse.equinox.launcher.Main.invokeFramework",
          "source": "Main.java:504"
        },
        {
          "method": "org.eclipse.equinox.launcher.Main.basicRun",
          "source": "Main.java:443"
        },
        {
          "method": "org.eclipse.equinox.launcher.Main.run",
          "source": "Main.java:1169"
        }
      ],
      "causedBy": {
        "exceptionType": "java.lang.ArrayIndexOutOfBoundsException",
        "elements": [
          {
            "method": "java.lang.System.arraycopy",
            "source": "Native Method"
          },
          {
            "method": "org.eclipse.swt.custom.StyledTextRenderer.textChanging",
            "source": "StyledTextRenderer.java:1235"
          },
          {
            "method": "org.eclipse.swt.custom.StyledText.handleTextChanging",
            "source": "StyledText.java:5348"
          },
          {
            "method": "org.eclipse.swt.custom.StyledText$6.textChanging",
            "source": "StyledText.java:4777"
          },
          {
            "method": "org.eclipse.ui.internal.console.ConsoleDocumentAdapter.documentAboutToBeChanged",
            "source": "ConsoleDocumentAdapter.java:298"
          },
          {
            "method": "org.eclipse.jface.text.AbstractDocument.fireDocumentAboutToBeChanged",
            "source": "AbstractDocument.java:606"
          },
          {
            "method": "org.eclipse.jface.text.AbstractDocument.replace",
            "source": "AbstractDocument.java:1072"
          },
          {
            "method": "org.eclipse.jface.text.AbstractDocument.replace",
            "source": "AbstractDocument.java:1089"
          },
          {
            "method": "org.eclipse.ui.internal.console.ConsoleDocument.replace",
            "source": "ConsoleDocument.java:82"
          },
          {
            "method": "org.eclipse.ui.internal.console.IOConsolePartitioner$QueueProcessingJob.runInUIThread",
            "source": "IOConsolePartitioner.java:536"
          },
          {
            "method": "org.eclipse.ui.progress.UIJob$1.run",
            "source": "UIJob.java:94"
          },
          {
            "method": "org.eclipse.swt.widgets.RunnableLock.run",
            "source": "RunnableLock.java:35"
          },
          {
            "method": "org.eclipse.swt.widgets.Synchronizer.runAsyncMessages",
            "source": "Synchronizer.java:123"
          }
        ],
        "number": 0,
        "commentIndex": 0
      },
      "number": 0,
      "commentIndex": 0,
      "bugId": "195100",
      "duplicateId": "208084",
      "date": "2007-07-02T11:57:47+02:00",
      "product": "JDT",
      "component": "Debug",
      "severity": "major"
    },
    {
      "exceptionType": "org.eclipse.swt.SWTException",
      "message": "Failed to execute runnable (java.lang.ArrayIndexOutOfBoundsException)",
      "elements": [
        {
          "method": "org.eclipse.swt.SWT.error",
          "source": "SWT.java:3563"
        },
        {
          "method": "org.eclipse.swt.SWT.error",
          "source": "SWT.java:3481"
        },
        {
          "method": "org.eclipse.swt.widgets.Synchronizer.runAsyncMessages",
          "source": "Synchronizer.java:126"
        },
        {
          "method": "org.eclipse.swt.widgets.Display.runAsyncMessages",
          "source": "Display.java:3296"
        },
        {
          "method": "org.eclipse.swt.widgets.Display.readAndDispatch",
          "source": "Display.java:2974"
        },
        {
          "method": "org.eclipse.ui.internal.Workbench.runEventLoop",
          "source": "Workbench.java:2389"
        },
        {
          "method": "org.eclipse.ui.internal.Workbench.runUI",
          "source": "Workbench.java:2353"
        },
        {
          "method": "org.eclipse.ui.internal.Workbench.access$4",
          "source": "Workbench.java:2219"
        },
        {
          "method": "org.eclipse.ui.internal.Workbench$4.run",
          "source": "Workbench.java:466"
        },
        {
          "method": "org.eclipse.core.databinding.observable.Realm.runWithDefault",
          "source": "Realm.java:289"
        },
        {
          "method": "org.eclipse.ui.internal.Workbench.createAndRunWorkbench",
          "source": "Workbench.java:461"
        },
        {
          "method": "org.eclipse.ui.PlatformUI.createAndRunWorkbench",
          "source": "PlatformUI.java:149"
        },
        {
          "method": "org.eclipse.ui.internal.ide.application.IDEApplication.start",
          "source": "IDEApplication.java:106"
        },
        {
          "method": "org.eclipse.equinox.internal.app.EclipseAppHandle.run",
          "source": "EclipseAppHandle.java:153"
        },
        {
          "method": "org.eclipse.core.runtime.internal.adaptor.EclipseAppLauncher.runApplication",
          "source": "EclipseAppLauncher.java:106"
        },
        {
          "method": "org.eclipse.core.runtime.internal.adaptor.EclipseAppLauncher.start",
          "source": "EclipseAppLauncher.java:76"
        },
        {
          "method": "org.eclipse.core.runtime.adaptor.EclipseStarter.run",
          "source": "EclipseStarter.java:363"
        },
        {
          "method": "org.eclipse.core.runtime.adaptor.EclipseStarter.run",
          "source": "EclipseStarter.java:176"
        },
        {
          "method": "sun.reflect.NativeMethodAccessorImpl.invoke0",
          "source": "Native Method"
        },
        {
          "method": "sun.reflect.NativeMethodAccessorImpl.invoke",
          "source": "NativeMethodAccessorImpl.java:39"
        },
        {
          "method": "sun.reflect.DelegatingMethodAccessorImpl.invoke",
          "source": "DelegatingMethodAccessorImpl.java:25"
        },
        {
          "method": "java.lang.reflect.Method.invoke",
          "source": "Method.java:585"
        },
        {
          "method": "org.eclipse.equinox.launcher.Main.invokeFramework",
          "source": "Main.java:504"
        },
        {
          "method": "org.eclipse.equinox.launcher.Main.basicRun",
          "source": "Main.java:443"
        },
        {
          "method": "org.eclipse.equinox.launcher.Main.run",
          "source": "Main.java:1169"
        }
      ],
      "causedBy": {
        "exceptionType": "java.lang.ArrayIndexOutOfBoundsException",
        "elements": [
          {
            "method": "java.lang.System.arraycopy",
            "source": "Native Method"
          },
          {
            "method": "org.eclipse.swt.custom.StyledTextRenderer.textChanging",
            "source": "StyledTextRenderer.java:1235"
          },
          {
            "method": "org.eclipse.swt.custom.StyledText.handleTextChanging",
            "source": "StyledText.java:5348"
          },
          {
            "method": "org.eclipse.swt.custom.StyledText$6.textChanging",
            "source": "StyledText.java:4777"
          },
          {
            "method": "org.eclipse.ui.internal.console.ConsoleDocumentAdapter.documentAboutToBeChanged",
            "source": "ConsoleDocumentAdapter.java:298"
          },
          {
            "method": "org.eclipse.jface.text.AbstractDocument.fireDocumentAboutToBeChanged",
            "source": "AbstractDocument.java:606"
          },
          {
            "method": "org.eclipse.jface.text.AbstractDocument.replace",
            "source": "AbstractDocument.java:1072"
          },
          {
            "method": "org.eclipse.jface.text.AbstractDocument.replace",
            "source": "AbstractDocument.java:1091"
          },
          {
            "method": "org.eclipse.ui.internal.console.ConsoleDocument.replace",
            "source": "ConsoleDocument.java:82"
          },
          {
            "method": "org.eclipse.ui.internal.console.IOConsolePartitioner$QueueProcessingJob.runInUIThread",
            "source": "IOConsolePartitioner.java:536"
          },
          {
            "method": "org.eclipse.ui.progress.UIJob$1.run",
            "source": "UIJob.java:94"
          },
          {
            "method": "org.eclipse.swt.widgets.RunnableLock.run",
            "source": "RunnableLock.java:35"
          },
          {
            "method": "org.eclipse.swt.widgets.Synchronizer.runAsyncMessages",
            "source": "Synchronizer.java:123"
          }
        ],
        "number": 0,
        "commentIndex": 0
      },
      "number": 1,
      "commentIndex": 4,
      "bugId": "195100",
      "duplicateId": "208084",
      "date": "2007-07-05T20:31:31+02:00",
      "product": "JDT",
      "component": "Debug",
      "severity": "major"
    }
  ],
  "groupId": "207743",
  "bugId": "195100",
  "duplicateId": "208084",
  "date": "2007-07-02T11:57:47+02:00",
  "product": "JDT",
  "component": "Debug",
  "severity": "major"
}