{
  "comments": [
    "I downloaded equinox and installed it.\n\nI then went to the update manager and installed everything from the equinox discovery site.\n\nAfter this, going to About Eclipse Platform Plug-ins triggers several errors:\n\nI have the following exception on the console:\n\n!ENTRY org.eclipse.birt.report.viewer 4 0 2007-07-02 15:45:32.584\n!MESSAGE\n!STACK 0\njava.util.zip.ZipException: error in opening zip file\n        at java.util.zip.ZipFile.open(Native Method)\n        at java.util.zip.ZipFile.\u003cinit\u003e(ZipFile.java:114)\n        at java.util.zip.ZipFile.\u003cinit\u003e(ZipFile.java:131)\n        at org.eclipse.osgi.framework.util.SecureAction.getZipFile(SecureAction.java:251)\n        at org.eclipse.osgi.baseadaptor.bundlefile.ZipBundleFile.basicOpen(ZipBundleFile.java:79)\n        at org.eclipse.osgi.baseadaptor.bundlefile.ZipBundleFile.getZipFile(ZipBundleFile.java:92)\n        at org.eclipse.osgi.baseadaptor.bundlefile.ZipBundleFile.checkedOpen(ZipBundleFile.java:65)\n        at org.eclipse.osgi.baseadaptor.bundlefile.ZipBundleFile.getEntry(ZipBundleFile.java:237)\n        at org.eclipse.osgi.baseadaptor.loader.ClasspathManager.findClassImpl(ClasspathManager.java:452)\n        at org.eclipse.osgi.baseadaptor.loader.ClasspathManager.findLocalClassImpl(ClasspathManager.java:430)\n        at org.eclipse.osgi.baseadaptor.loader.ClasspathManager.findLocalClass(ClasspathManager.java:413)\n        at org.eclipse.osgi.internal.baseadaptor.DefaultClassLoader.findLocalClass(DefaultClassLoader.java:189)\n        at org.eclipse.osgi.framework.internal.core.BundleLoader.findLocalClass(BundleLoader.java:340)\n        at org.eclipse.osgi.framework.internal.core.SingleSourcePackage.loadClass(SingleSourcePackage.java:37)\n        at org.eclipse.osgi.framework.internal.core.BundleLoader.findClassInternal(BundleLoader.java:405)\n        at org.eclipse.osgi.framework.internal.core.BundleLoader.findClass(BundleLoader.java:369)\n        at org.eclipse.osgi.framework.internal.core.BundleLoader.findClass(BundleLoader.java:357)\n        at org.eclipse.osgi.internal.baseadaptor.DefaultClassLoader.loadClass(DefaultClassLoader.java:83)\n        at java.lang.ClassLoader.loadClass(ClassLoader.java:251)\n        at java.lang.ClassLoader.loadClassInternal(ClassLoader.java:319)\n        at java.lang.Class.getDeclaredConstructors0(Native Method)\n        at java.lang.Class.privateGetDeclaredConstructors(Class.java:2389)\n        at java.lang.Class.getConstructor0(Class.java:2699)\n        at java.lang.Class.newInstance0(Class.java:326)\n        at java.lang.Class.newInstance(Class.java:308)\n        at org.eclipse.core.internal.registry.osgi.RegistryStrategyOSGI.createExecutableExtension(RegistryStrategyOSGI.java:170)\n        at org.eclipse.core.internal.registry.ExtensionRegistry.createExecutableExtension(ExtensionRegistry.java:788)\n        at org.eclipse.core.internal.registry.ConfigurationElement.createExecutableExtension(ConfigurationElement.java:243)\n        at org.eclipse.core.internal.registry.ConfigurationElementHandle.createExecutableExtension(ConfigurationElementHandle.java:51)\n        at org.eclipse.ui.internal.WorkbenchPlugin$1.run(WorkbenchPlugin.java:243)\n        at org.eclipse.swt.custom.BusyIndicator.showWhile(BusyIndicator.java:49)\n        at org.eclipse.ui.internal.WorkbenchPlugin.createExtension(WorkbenchPlugin.java:239)\n        at org.eclipse.ui.internal.EarlyStartupRunnable.getExecutableExtension(EarlyStartupRunnable.java:117)\n        at org.eclipse.ui.internal.EarlyStartupRunnable.run(EarlyStartupRunnable.java:66)\n        at org.eclipse.core.runtime.SafeRunner.run(SafeRunner.java:37)\n        at org.eclipse.ui.internal.Workbench$54.run(Workbench.java:2190)\n        at org.eclipse.core.internal.jobs.Worker.run(Worker.java:55)\n\nAnd a \"Multiple operations have reported errors\" window with many errors. The first few are:\n\nAn internal error occurred during: \"org.eclipse.tm.terminal.view.source\".\njava.lang.NullPointerException\n\nAn internal error occurred during: \"org.eclipse.hyades.test.core\".\njava.lang.IllegalStateException\n\nAn internal error occurred during: \"org.eclipse.jst.server.generic.jboss\".\njava.lang.NullPointerException\n\nAn internal error occurred during: \"org.eclipse.emf.cheatsheets\".\njava.lang.NullPointerException\n\nBut copying and pasting after that is getting dull...",
    "Accidentally reported twice.\n\n*** This bug has been marked as a duplicate of bug 195142 ***"
  ],
  "commentCreationDates": [
    "2007-07-02T16:55:11+02:00",
    "2007-07-02T16:56:05+02:00"
  ],
  "traces": [
    {
      "exceptionType": "java.util.zip.ZipException",
      "message": "error in opening zip file",
      "elements": [
        {
          "method": "java.util.zip.ZipFile.open",
          "source": "Native Method"
        },
        {
          "method": "java.util.zip.ZipFile.\u003cinit\u003e",
          "source": "ZipFile.java:114"
        },
        {
          "method": "java.util.zip.ZipFile.\u003cinit\u003e",
          "source": "ZipFile.java:131"
        },
        {
          "method": "org.eclipse.osgi.framework.util.SecureAction.getZipFile",
          "source": "SecureAction.java:251"
        },
        {
          "method": "org.eclipse.osgi.baseadaptor.bundlefile.ZipBundleFile.basicOpen",
          "source": "ZipBundleFile.java:79"
        },
        {
          "method": "org.eclipse.osgi.baseadaptor.bundlefile.ZipBundleFile.getZipFile",
          "source": "ZipBundleFile.java:92"
        },
        {
          "method": "org.eclipse.osgi.baseadaptor.bundlefile.ZipBundleFile.checkedOpen",
          "source": "ZipBundleFile.java:65"
        },
        {
          "method": "org.eclipse.osgi.baseadaptor.bundlefile.ZipBundleFile.getEntry",
          "source": "ZipBundleFile.java:237"
        },
        {
          "method": "org.eclipse.osgi.baseadaptor.loader.ClasspathManager.findClassImpl",
          "source": "ClasspathManager.java:452"
        },
        {
          "method": "org.eclipse.osgi.baseadaptor.loader.ClasspathManager.findLocalClassImpl",
          "source": "ClasspathManager.java:430"
        },
        {
          "method": "org.eclipse.osgi.baseadaptor.loader.ClasspathManager.findLocalClass",
          "source": "ClasspathManager.java:413"
        },
        {
          "method": "org.eclipse.osgi.internal.baseadaptor.DefaultClassLoader.findLocalClass",
          "source": "DefaultClassLoader.java:189"
        },
        {
          "method": "org.eclipse.osgi.framework.internal.core.BundleLoader.findLocalClass",
          "source": "BundleLoader.java:340"
        },
        {
          "method": "org.eclipse.osgi.framework.internal.core.SingleSourcePackage.loadClass",
          "source": "SingleSourcePackage.java:37"
        },
        {
          "method": "org.eclipse.osgi.framework.internal.core.BundleLoader.findClassInternal",
          "source": "BundleLoader.java:405"
        },
        {
          "method": "org.eclipse.osgi.framework.internal.core.BundleLoader.findClass",
          "source": "BundleLoader.java:369"
        },
        {
          "method": "org.eclipse.osgi.framework.internal.core.BundleLoader.findClass",
          "source": "BundleLoader.java:357"
        },
        {
          "method": "org.eclipse.osgi.internal.baseadaptor.DefaultClassLoader.loadClass",
          "source": "DefaultClassLoader.java:83"
        },
        {
          "method": "java.lang.ClassLoader.loadClass",
          "source": "ClassLoader.java:251"
        },
        {
          "method": "java.lang.ClassLoader.loadClassInternal",
          "source": "ClassLoader.java:319"
        },
        {
          "method": "java.lang.Class.getDeclaredConstructors0",
          "source": "Native Method"
        },
        {
          "method": "java.lang.Class.privateGetDeclaredConstructors",
          "source": "Class.java:2389"
        },
        {
          "method": "java.lang.Class.getConstructor0",
          "source": "Class.java:2699"
        },
        {
          "method": "java.lang.Class.newInstance0",
          "source": "Class.java:326"
        },
        {
          "method": "java.lang.Class.newInstance",
          "source": "Class.java:308"
        },
        {
          "method": "org.eclipse.core.internal.registry.osgi.RegistryStrategyOSGI.createExecutableExtension",
          "source": "RegistryStrategyOSGI.java:170"
        },
        {
          "method": "org.eclipse.core.internal.registry.ExtensionRegistry.createExecutableExtension",
          "source": "ExtensionRegistry.java:788"
        },
        {
          "method": "org.eclipse.core.internal.registry.ConfigurationElement.createExecutableExtension",
          "source": "ConfigurationElement.java:243"
        },
        {
          "method": "org.eclipse.core.internal.registry.ConfigurationElementHandle.createExecutableExtension",
          "source": "ConfigurationElementHandle.java:51"
        },
        {
          "method": "org.eclipse.ui.internal.WorkbenchPlugin$1.run",
          "source": "WorkbenchPlugin.java:243"
        },
        {
          "method": "org.eclipse.swt.custom.BusyIndicator.showWhile",
          "source": "BusyIndicator.java:49"
        },
        {
          "method": "org.eclipse.ui.internal.WorkbenchPlugin.createExtension",
          "source": "WorkbenchPlugin.java:239"
        },
        {
          "method": "org.eclipse.ui.internal.EarlyStartupRunnable.getExecutableExtension",
          "source": "EarlyStartupRunnable.java:117"
        },
        {
          "method": "org.eclipse.ui.internal.EarlyStartupRunnable.run",
          "source": "EarlyStartupRunnable.java:66"
        },
        {
          "method": "org.eclipse.core.runtime.SafeRunner.run",
          "source": "SafeRunner.java:37"
        },
        {
          "method": "org.eclipse.ui.internal.Workbench$54.run",
          "source": "Workbench.java:2190"
        },
        {
          "method": "org.eclipse.core.internal.jobs.Worker.run",
          "source": "Worker.java:55"
        }
      ],
      "number": 0,
      "commentIndex": 0,
      "bugId": "195143",
      "duplicateId": "195142",
      "date": "2007-07-02T16:55:11+02:00",
      "product": "Platform",
      "component": "UI",
      "severity": "normal"
    }
  ],
  "groupId": "195142",
  "bugId": "195143",
  "duplicateId": "195142",
  "date": "2007-07-02T16:55:11+02:00",
  "product": "Platform",
  "component": "UI",
  "severity": "normal"
}