{
  "comments": [
    "Build ID: I20070621-1340\n\nSteps To Reproduce:\n1. Clean install of Europa code\n2. Install all available packages from discovery site\n3. Some open some closed projects\n\nException appears at regular intervals on console:\n\n org.eclipse.core.internal.resources.ResourceException: Resource \u0027/myproject\u0027 is not open.\n        at org.eclipse.core.internal.resources.Project.checkAccessible(Project.java:97)\n        at org.eclipse.core.internal.resources.Project.hasNature(Project.java:467)\n        at org.eclipse.dltk.ruby.internal.ui.RubyProjectDecorator.decorate(RubyProjectDecorator.java:24)\n        at org.eclipse.ui.internal.decorators.LightweightDecoratorDefinition.decorate(LightweightDecoratorDefinition.java:259)\n        at org.eclipse.ui.internal.decorators.LightweightDecoratorManager$LightweightRunnable.run(LightweightDecoratorManager.java:71)\n        at org.eclipse.core.runtime.SafeRunner.run(SafeRunner.java:37)\n        at org.eclipse.core.runtime.Platform.run(Platform.java:857)\n        at org.eclipse.ui.internal.decorators.LightweightDecoratorManager.decorate(LightweightDecoratorManager.java:336)\n        at org.eclipse.ui.internal.decorators.LightweightDecoratorManager.getDecorations(LightweightDecoratorManager.java:322)\n        at org.eclipse.ui.internal.decorators.DecorationScheduler$1.ensureResultCached(DecorationScheduler.java:369)\n        at org.eclipse.ui.internal.decorators.DecorationScheduler$1.run(DecorationScheduler.java:329)\n        at org.eclipse.core.internal.jobs.Worker.run(Worker.java:55)\norg.eclipse.core.internal.resources.ResourceException: Resource \u0027/idesk\u0027 is not open.\n        at org.eclipse.core.internal.resources.Project.checkAccessible(Project.java:97)\n        at org.eclipse.core.internal.resources.Project.hasNature(Project.java:467)\n        at org.eclipse.dltk.tcl.internal.ui.TclProjectDecorator.decorate(TclProjectDecorator.java:24)\n        at org.eclipse.ui.internal.decorators.LightweightDecoratorDefinition.decorate(LightweightDecoratorDefinition.java:259)\n        at org.eclipse.ui.internal.decorators.LightweightDecoratorManager$LightweightRunnable.run(LightweightDecoratorManager.java:71)\n        at org.eclipse.core.runtime.SafeRunner.run(SafeRunner.java:37)\n        at org.eclipse.core.runtime.Platform.run(Platform.java:857)\n        at org.eclipse.ui.internal.decorators.LightweightDecoratorManager.decorate(LightweightDecoratorManager.java:336)\n        at org.eclipse.ui.internal.decorators.LightweightDecoratorManager.getDecorations(LightweightDecoratorManager.java:322)\n        at org.eclipse.ui.internal.decorators.DecorationScheduler$1.ensureResultCached(DecorationScheduler.java:369)\n        at org.eclipse.ui.internal.decorators.DecorationScheduler$1.run(DecorationScheduler.java:329)\n        at org.eclipse.core.internal.jobs.Worker.run(Worker.java:55)",
    "Created an attachment (id\u003d73008)\nmy eclipse configuration\n\n",
    "\n\n*** This bug has been marked as a duplicate of bug 194617 ***"
  ],
  "commentCreationDates": [
    "2007-07-04T11:15:43+02:00",
    "2007-07-04T11:16:35+02:00",
    "2007-07-04T15:19:39+02:00"
  ],
  "traces": [
    {
      "exceptionType": "org.eclipse.core.internal.resources.ResourceException",
      "message": "Resource \u0027/myproject\u0027 is not open.",
      "elements": [
        {
          "method": "org.eclipse.core.internal.resources.Project.checkAccessible",
          "source": "Project.java:97"
        },
        {
          "method": "org.eclipse.core.internal.resources.Project.hasNature",
          "source": "Project.java:467"
        },
        {
          "method": "org.eclipse.dltk.ruby.internal.ui.RubyProjectDecorator.decorate",
          "source": "RubyProjectDecorator.java:24"
        },
        {
          "method": "org.eclipse.ui.internal.decorators.LightweightDecoratorDefinition.decorate",
          "source": "LightweightDecoratorDefinition.java:259"
        },
        {
          "method": "org.eclipse.ui.internal.decorators.LightweightDecoratorManager$LightweightRunnable.run",
          "source": "LightweightDecoratorManager.java:71"
        },
        {
          "method": "org.eclipse.core.runtime.SafeRunner.run",
          "source": "SafeRunner.java:37"
        },
        {
          "method": "org.eclipse.core.runtime.Platform.run",
          "source": "Platform.java:857"
        },
        {
          "method": "org.eclipse.ui.internal.decorators.LightweightDecoratorManager.decorate",
          "source": "LightweightDecoratorManager.java:336"
        },
        {
          "method": "org.eclipse.ui.internal.decorators.LightweightDecoratorManager.getDecorations",
          "source": "LightweightDecoratorManager.java:322"
        },
        {
          "method": "org.eclipse.ui.internal.decorators.DecorationScheduler$1.ensureResultCached",
          "source": "DecorationScheduler.java:369"
        },
        {
          "method": "org.eclipse.ui.internal.decorators.DecorationScheduler$1.run",
          "source": "DecorationScheduler.java:329"
        },
        {
          "method": "org.eclipse.core.internal.jobs.Worker.run",
          "source": "Worker.java:55"
        }
      ],
      "number": 0,
      "commentIndex": 0,
      "bugId": "195355",
      "duplicateId": "194617",
      "date": "2007-07-04T11:15:43+02:00",
      "product": "DLTK",
      "component": "Ruby",
      "severity": "normal"
    },
    {
      "exceptionType": "org.eclipse.core.internal.resources.ResourceException",
      "message": "Resource \u0027/idesk\u0027 is not open.",
      "elements": [
        {
          "method": "org.eclipse.core.internal.resources.Project.checkAccessible",
          "source": "Project.java:97"
        },
        {
          "method": "org.eclipse.core.internal.resources.Project.hasNature",
          "source": "Project.java:467"
        },
        {
          "method": "org.eclipse.dltk.tcl.internal.ui.TclProjectDecorator.decorate",
          "source": "TclProjectDecorator.java:24"
        },
        {
          "method": "org.eclipse.ui.internal.decorators.LightweightDecoratorDefinition.decorate",
          "source": "LightweightDecoratorDefinition.java:259"
        },
        {
          "method": "org.eclipse.ui.internal.decorators.LightweightDecoratorManager$LightweightRunnable.run",
          "source": "LightweightDecoratorManager.java:71"
        },
        {
          "method": "org.eclipse.core.runtime.SafeRunner.run",
          "source": "SafeRunner.java:37"
        },
        {
          "method": "org.eclipse.core.runtime.Platform.run",
          "source": "Platform.java:857"
        },
        {
          "method": "org.eclipse.ui.internal.decorators.LightweightDecoratorManager.decorate",
          "source": "LightweightDecoratorManager.java:336"
        },
        {
          "method": "org.eclipse.ui.internal.decorators.LightweightDecoratorManager.getDecorations",
          "source": "LightweightDecoratorManager.java:322"
        },
        {
          "method": "org.eclipse.ui.internal.decorators.DecorationScheduler$1.ensureResultCached",
          "source": "DecorationScheduler.java:369"
        },
        {
          "method": "org.eclipse.ui.internal.decorators.DecorationScheduler$1.run",
          "source": "DecorationScheduler.java:329"
        },
        {
          "method": "org.eclipse.core.internal.jobs.Worker.run",
          "source": "Worker.java:55"
        }
      ],
      "number": 1,
      "commentIndex": 0,
      "bugId": "195355",
      "duplicateId": "194617",
      "date": "2007-07-04T11:15:43+02:00",
      "product": "DLTK",
      "component": "Ruby",
      "severity": "normal"
    }
  ],
  "groupId": "194617",
  "bugId": "195355",
  "duplicateId": "194617",
  "date": "2007-07-04T11:15:43+02:00",
  "product": "DLTK",
  "component": "Ruby",
  "severity": "normal"
}