{
  "comments": [
    "The following exceptions occur if you exit and restart the workbench when there \nis no disk space. The dialog that is presented to the user does not contain any \nusefull information \"... could not write meta data ...\"\n\n\nAn exception occurred while writing to the platform log:\njava.io.IOException: There is not enough space on the disk\n        at java.io.FileOutputStream.writeBytes(Native Method)\n        at java.io.FileOutputStream.write(FileOutputStream.java:228)\n        at java.io.OutputStreamWriter.flushBuffer(OutputStreamWriter.java:244)\n        at java.io.OutputStreamWriter.flush(OutputStreamWriter.java:258)\n        at java.io.BufferedWriter.flush(BufferedWriter.java:247)\n        at org.eclipse.core.internal.runtime.PlatformLogWriter.closeLogFile(Plat\nformLogWriter.java:54)\n        at org.eclipse.core.internal.runtime.PlatformLogWriter.logging(PlatformL\nogWriter.java:75)\n        at org.eclipse.core.internal.runtime.InternalPlatform.log(InternalPlatfo\nrm.java:678)\n        at org.eclipse.core.internal.runtime.Log.log(Log.java:66)\n        at org.eclipse.core.internal.resources.SaveManager.restoreSnapshots(Save\nManager.java:626)\n        at org.eclipse.core.internal.resources.SaveManager.restore(SaveManager.j\nava:463)\n        at org.eclipse.core.internal.resources.SaveManager.startup(SaveManager.j\nava:946)\n        at org.eclipse.core.internal.resources.Workspace.startup(Workspace.java:\n1487)\n        at org.eclipse.core.internal.resources.Workspace.open(Workspace.java:127\n9)\n        at org.eclipse.core.resources.ResourcesPlugin.startup(ResourcesPlugin.ja\nva:201)\n        at org.eclipse.core.internal.plugins.PluginDescriptor$1.run(PluginDescri\nptor.java:690)\n        at org.eclipse.core.internal.runtime.InternalPlatform.run(InternalPlatfo\nrm.java:802)\n        at org.eclipse.core.internal.plugins.PluginDescriptor.internalDoPluginAc\ntivation(PluginDescriptor.java:702)\n        at org.eclipse.core.internal.plugins.PluginDescriptor.doPluginActivation\n(PluginDescriptor.java:182)\n        at org.eclipse.core.internal.plugins.PluginClassLoader.activatePlugin(Pl\nuginClassLoader.java:58)\n        at org.eclipse.core.internal.plugins.PluginClassLoader.findClassParentsS\nelf(PluginClassLoader.java:136)\n        at org.eclipse.core.internal.boot.DelegatingURLClassLoader.loadClass(Del\negatingURLClassLoader.java:750)\n        at org.eclipse.core.internal.boot.DelegatingURLClassLoader.access$0(Dele\ngatingURLClassLoader.java:744)\n        at org.eclipse.core.internal.boot.DelegatingURLClassLoader$DelegateLoade\nr.loadClass(DelegatingURLClassLoader.java:70)\n        at org.eclipse.core.internal.boot.DelegatingURLClassLoader.findClassPrer\nequisites(DelegatingURLClassLoader.java:429)\n        at org.eclipse.core.internal.boot.DelegatingURLClassLoader.loadClass(Del\negatingURLClassLoader.java:758)\n        at org.eclipse.core.internal.boot.DelegatingURLClassLoader.loadClass(Del\negatingURLClassLoader.java:730)\n        at java.lang.ClassLoader.loadClass(ClassLoader.java:445)\n        at java.lang.Class.newInstance0(Native Method)\n        at java.lang.Class.newInstance(Class.java:262)\n        at org.eclipse.core.internal.plugins.PluginDescriptor.createExecutableEx\ntension(PluginDescriptor.java:134)\n        at org.eclipse.core.internal.plugins.PluginDescriptor.createExecutableEx\ntension(PluginDescriptor.java:163)\n        at org.eclipse.core.internal.plugins.ConfigurationElement.createExecutab\nleExtension(ConfigurationElement.java:102)\n        at org.eclipse.core.internal.runtime.InternalPlatform.loaderGetRunnable(\nInternalPlatform.java:449)\n        at java.lang.reflect.Method.invoke(Native Method)\n        at org.eclipse.core.internal.boot.InternalBootLoader.getRunnable(Interna\nlBootLoader.java:436)\n        at org.eclipse.core.internal.boot.InternalBootLoader.run(InternalBootLoa\nder.java:735)\n        at org.eclipse.core.boot.BootLoader.run(BootLoader.java:462)\n        at java.lang.reflect.Method.invoke(Native Method)\n        at org.eclipse.core.launcher.Main.basicRun(Main.java:244)\n        at org.eclipse.core.launcher.Main.run(Main.java:693)\n        at org.eclipse.core.launcher.Main.main(Main.java:526)\nLogging to the console instead.\n!ENTRY org.eclipse.core.resources 4 567 Jun 06, 2002 15:19:11.148\n!MESSAGE Could not read snapshot file.\n!STACK 0\njava.io.EOFException\n        at java.io.DataInputStream.readInt(DataInputStream.java(Compiled Code))\n        at org.eclipse.core.internal.resources.SaveManager.restoreSnapshots(Save\nManager.java:613)\n        at org.eclipse.core.internal.resources.SaveManager.restore(SaveManager.j\nava:463)\n        at org.eclipse.core.internal.resources.SaveManager.startup(SaveManager.j\nava:946)\n        at org.eclipse.core.internal.resources.Workspace.startup(Workspace.java:\n1487)\n        at org.eclipse.core.internal.resources.Workspace.open(Workspace.java:127\n9)\n        at org.eclipse.core.resources.ResourcesPlugin.startup(ResourcesPlugin.ja\nva:201)\n        at org.eclipse.core.internal.plugins.PluginDescriptor$1.run(PluginDescri\nptor.java:690)\n        at org.eclipse.core.internal.runtime.InternalPlatform.run(InternalPlatfo\nrm.java:802)\n        at org.eclipse.core.internal.plugins.PluginDescriptor.internalDoPluginAc\ntivation(PluginDescriptor.java:702)\n        at org.eclipse.core.internal.plugins.PluginDescriptor.doPluginActivation\n(PluginDescriptor.java:182)\n        at org.eclipse.core.internal.plugins.PluginClassLoader.activatePlugin(Pl\nuginClassLoader.java:58)\n        at org.eclipse.core.internal.plugins.PluginClassLoader.findClassParentsS\nelf(PluginClassLoader.java:136)\n        at org.eclipse.core.internal.boot.DelegatingURLClassLoader.loadClass(Del\negatingURLClassLoader.java:750)\n        at org.eclipse.core.internal.boot.DelegatingURLClassLoader.access$0(Dele\ngatingURLClassLoader.java:744)\n        at org.eclipse.core.internal.boot.DelegatingURLClassLoader$DelegateLoade\nr.loadClass(DelegatingURLClassLoader.java:70)\n        at org.eclipse.core.internal.boot.DelegatingURLClassLoader.findClassPrer\nequisites(DelegatingURLClassLoader.java:429)\n        at org.eclipse.core.internal.boot.DelegatingURLClassLoader.loadClass(Del\negatingURLClassLoader.java:758)\n        at org.eclipse.core.internal.boot.DelegatingURLClassLoader.loadClass(Del\negatingURLClassLoader.java:730)\n        at java.lang.ClassLoader.loadClass(ClassLoader.java:445)\n        at java.lang.Class.newInstance0(Native Method)\n        at java.lang.Class.newInstance(Class.java:262)\n        at org.eclipse.core.internal.plugins.PluginDescriptor.createExecutableEx\ntension(PluginDescriptor.java:134)\n        at org.eclipse.core.internal.plugins.PluginDescriptor.createExecutableEx\ntension(PluginDescriptor.java:163)\n        at org.eclipse.core.internal.plugins.ConfigurationElement.createExecutab\nleExtension(ConfigurationElement.java:102)\n        at org.eclipse.core.internal.runtime.InternalPlatform.loaderGetRunnable(\nInternalPlatform.java:449)\n        at java.lang.reflect.Method.invoke(Native Method)\n        at org.eclipse.core.internal.boot.InternalBootLoader.getRunnable(Interna\nlBootLoader.java:436)\n        at org.eclipse.core.internal.boot.InternalBootLoader.run(InternalBootLoa\nder.java:735)\n        at org.eclipse.core.boot.BootLoader.run(BootLoader.java:462)\n        at java.lang.reflect.Method.invoke(Native Method)\n        at org.eclipse.core.launcher.Main.basicRun(Main.java:244)\n        at org.eclipse.core.launcher.Main.run(Main.java:693)\n        at org.eclipse.core.launcher.Main.main(Main.java:526)\n[Fatal Error] :-1:-1: Premature end of file.\nAn exception occurred while writing to the platform log:\njava.io.IOException: There is not enough space on the disk\n        at java.io.FileOutputStream.writeBytes(Native Method)\n        at java.io.FileOutputStream.write(FileOutputStream.java:228)\n        at java.io.OutputStreamWriter.flushBuffer(OutputStreamWriter.java:244)\n        at java.io.OutputStreamWriter.flush(OutputStreamWriter.java:258)\n        at java.io.BufferedWriter.flush(BufferedWriter.java:247)\n        at org.eclipse.core.internal.runtime.PlatformLogWriter.closeLogFile(Plat\nformLogWriter.java:54)\n        at org.eclipse.core.internal.runtime.PlatformLogWriter.logging(PlatformL\nogWriter.java:75)\n        at org.eclipse.core.internal.runtime.InternalPlatform.log(InternalPlatfo\nrm.java:678)\n        at org.eclipse.core.internal.runtime.Log.log(Log.java:66)\n        at org.eclipse.core.internal.runtime.InternalPlatform.handleException(In\nternalPlatform.java:425)\n        at org.eclipse.core.internal.runtime.InternalPlatform.run(InternalPlatfo\nrm.java:804)\n        at org.eclipse.core.runtime.Platform.run(Platform.java:416)\n        at org.eclipse.ui.internal.Workbench.openPreviousWorkbenchState(Workbenc\nh.java:748)\n        at org.eclipse.ui.internal.Workbench.init(Workbench.java:562)\n        at org.eclipse.ui.internal.Workbench.run(Workbench.java:1153)\n        at org.eclipse.core.internal.boot.InternalBootLoader.run(InternalBootLoa\nder.java:739)\n        at org.eclipse.core.boot.BootLoader.run(BootLoader.java:462)\n        at java.lang.reflect.Method.invoke(Native Method)\n        at org.eclipse.core.launcher.Main.basicRun(Main.java:244)\n        at org.eclipse.core.launcher.Main.run(Main.java:693)\n        at org.eclipse.core.launcher.Main.main(Main.java:526)\nLogging to the console instead.\n!ENTRY org.eclipse.ui 4 2 Jun 06, 2002 15:19:11.949\n!MESSAGE Problems occurred when invoking code from plug-in: \"org.eclipse.ui\".\n!STACK 0\njava.lang.NullPointerException\n        at org.eclipse.ui.internal.Workbench$6.run(Workbench.java:755)\n        at org.eclipse.core.internal.runtime.InternalPlatform.run(InternalPlatfo\nrm.java:802)\n        at org.eclipse.core.runtime.Platform.run(Platform.java:416)\n        at org.eclipse.ui.internal.Workbench.openPreviousWorkbenchState(Workbenc\nh.java:748)\n        at org.eclipse.ui.internal.Workbench.init(Workbench.java:562)\n        at org.eclipse.ui.internal.Workbench.run(Workbench.java:1153)\n        at org.eclipse.core.internal.boot.InternalBootLoader.run(InternalBootLoa\nder.java:739)\n        at org.eclipse.core.boot.BootLoader.run(BootLoader.java:462)\n        at java.lang.reflect.Method.invoke(Native Method)\n        at org.eclipse.core.launcher.Main.basicRun(Main.java:244)\n        at org.eclipse.core.launcher.Main.run(Main.java:693)\n        at org.eclipse.core.launcher.Main.main(Main.java:526)",
    "The more critical problem here is the fact that the workspace is corrupted.\nFiled bug 19542 for this.\n\nFiled bug 19540 for the NPE in the last stack trace.\n",
    "Moving to Core since both EOFException are happening at Core level.",
    "\n\n*** This bug has been marked as a duplicate of 2699 ***"
  ],
  "commentCreationDates": [
    "2002-06-06T21:10:05+02:00",
    "2002-06-06T22:21:18+02:00",
    "2002-08-07T23:53:29+02:00",
    "2002-08-29T15:36:44+02:00"
  ],
  "traces": [
    {
      "exceptionType": "java.io.IOException",
      "message": "There is not enough space on the disk",
      "elements": [
        {
          "method": "java.io.FileOutputStream.writeBytes",
          "source": "Native Method"
        },
        {
          "method": "java.io.FileOutputStream.write",
          "source": "FileOutputStream.java:228"
        },
        {
          "method": "java.io.OutputStreamWriter.flushBuffer",
          "source": "OutputStreamWriter.java:244"
        },
        {
          "method": "java.io.OutputStreamWriter.flush",
          "source": "OutputStreamWriter.java:258"
        },
        {
          "method": "java.io.BufferedWriter.flush",
          "source": "BufferedWriter.java:247"
        },
        {
          "method": "org.eclipse.core.internal.runtime.PlatformLogWriter.closeLogFile",
          "source": "Plat formLogWriter.java:54"
        },
        {
          "method": "org.eclipse.core.internal.runtime.PlatformLogWriter.logging",
          "source": "PlatformL ogWriter.java:75"
        },
        {
          "method": "org.eclipse.core.internal.runtime.InternalPlatform.log",
          "source": "InternalPlatfo rm.java:678"
        },
        {
          "method": "org.eclipse.core.internal.runtime.Log.log",
          "source": "Log.java:66"
        },
        {
          "method": "org.eclipse.core.internal.resources.SaveManager.restoreSnapshots",
          "source": "Save Manager.java:626"
        },
        {
          "method": "org.eclipse.core.internal.resources.SaveManager.restore",
          "source": "SaveManager.j ava:463"
        },
        {
          "method": "org.eclipse.core.internal.resources.SaveManager.startup",
          "source": "SaveManager.j ava:946"
        },
        {
          "method": "org.eclipse.core.internal.resources.Workspace.startup",
          "source": "Workspace.java: 1487"
        },
        {
          "method": "org.eclipse.core.internal.resources.Workspace.open",
          "source": "Workspace.java:127 9"
        },
        {
          "method": "org.eclipse.core.resources.ResourcesPlugin.startup",
          "source": "ResourcesPlugin.ja va:201"
        },
        {
          "method": "org.eclipse.core.internal.plugins.PluginDescriptor$1.run",
          "source": "PluginDescri ptor.java:690"
        },
        {
          "method": "org.eclipse.core.internal.runtime.InternalPlatform.run",
          "source": "InternalPlatfo rm.java:802"
        },
        {
          "method": "org.eclipse.core.internal.plugins.PluginDescriptor.internalDoPluginActivation",
          "source": "PluginDescriptor.java:702"
        },
        {
          "method": "org.eclipse.core.internal.plugins.PluginDescriptor.doPluginActivation",
          "source": "PluginDescriptor.java:182"
        },
        {
          "method": "org.eclipse.core.internal.plugins.PluginClassLoader.activatePlugin",
          "source": "Pl uginClassLoader.java:58"
        },
        {
          "method": "org.eclipse.core.internal.plugins.PluginClassLoader.findClassParentsSelf",
          "source": "PluginClassLoader.java:136"
        },
        {
          "method": "org.eclipse.core.internal.boot.DelegatingURLClassLoader.loadClass",
          "source": "Del egatingURLClassLoader.java:750"
        },
        {
          "method": "org.eclipse.core.internal.boot.DelegatingURLClassLoader.access$0",
          "source": "Dele gatingURLClassLoader.java:744"
        },
        {
          "method": "org.eclipse.core.internal.boot.DelegatingURLClassLoader$DelegateLoader.loadClass",
          "source": "DelegatingURLClassLoader.java:70"
        },
        {
          "method": "org.eclipse.core.internal.boot.DelegatingURLClassLoader.findClassPrerequisites",
          "source": "DelegatingURLClassLoader.java:429"
        },
        {
          "method": "org.eclipse.core.internal.boot.DelegatingURLClassLoader.loadClass",
          "source": "Del egatingURLClassLoader.java:758"
        },
        {
          "method": "org.eclipse.core.internal.boot.DelegatingURLClassLoader.loadClass",
          "source": "Del egatingURLClassLoader.java:730"
        },
        {
          "method": "java.lang.ClassLoader.loadClass",
          "source": "ClassLoader.java:445"
        },
        {
          "method": "java.lang.Class.newInstance0",
          "source": "Native Method"
        },
        {
          "method": "java.lang.Class.newInstance",
          "source": "Class.java:262"
        },
        {
          "method": "org.eclipse.core.internal.plugins.PluginDescriptor.createExecutableExtension",
          "source": "PluginDescriptor.java:134"
        },
        {
          "method": "org.eclipse.core.internal.plugins.PluginDescriptor.createExecutableExtension",
          "source": "PluginDescriptor.java:163"
        },
        {
          "method": "org.eclipse.core.internal.plugins.ConfigurationElement.createExecutableExtension",
          "source": "ConfigurationElement.java:102"
        },
        {
          "method": "org.eclipse.core.internal.runtime.InternalPlatform.loaderGetRunnable",
          "source": " InternalPlatform.java:449"
        },
        {
          "method": "java.lang.reflect.Method.invoke",
          "source": "Native Method"
        },
        {
          "method": "org.eclipse.core.internal.boot.InternalBootLoader.getRunnable",
          "source": "Interna lBootLoader.java:436"
        },
        {
          "method": "org.eclipse.core.internal.boot.InternalBootLoader.run",
          "source": "InternalBootLoa der.java:735"
        },
        {
          "method": "org.eclipse.core.boot.BootLoader.run",
          "source": "BootLoader.java:462"
        },
        {
          "method": "java.lang.reflect.Method.invoke",
          "source": "Native Method"
        },
        {
          "method": "org.eclipse.core.launcher.Main.basicRun",
          "source": "Main.java:244"
        },
        {
          "method": "org.eclipse.core.launcher.Main.run",
          "source": "Main.java:693"
        },
        {
          "method": "org.eclipse.core.launcher.Main.main",
          "source": "Main.java:526"
        }
      ],
      "number": 0,
      "commentIndex": 0,
      "bugId": "19534",
      "duplicateId": "2699",
      "date": "2002-06-06T21:10:05+02:00",
      "product": "Platform",
      "component": "Resources",
      "severity": "major"
    },
    {
      "exceptionType": "java.io.EOFException",
      "elements": [
        {
          "method": "java.io.DataInputStream.readInt",
          "source": "DataInputStream.java(Compiled Code)"
        },
        {
          "method": "org.eclipse.core.internal.resources.SaveManager.restoreSnapshots",
          "source": "Save Manager.java:613"
        },
        {
          "method": "org.eclipse.core.internal.resources.SaveManager.restore",
          "source": "SaveManager.j ava:463"
        },
        {
          "method": "org.eclipse.core.internal.resources.SaveManager.startup",
          "source": "SaveManager.j ava:946"
        },
        {
          "method": "org.eclipse.core.internal.resources.Workspace.startup",
          "source": "Workspace.java: 1487"
        },
        {
          "method": "org.eclipse.core.internal.resources.Workspace.open",
          "source": "Workspace.java:127 9"
        },
        {
          "method": "org.eclipse.core.resources.ResourcesPlugin.startup",
          "source": "ResourcesPlugin.ja va:201"
        },
        {
          "method": "org.eclipse.core.internal.plugins.PluginDescriptor$1.run",
          "source": "PluginDescri ptor.java:690"
        },
        {
          "method": "org.eclipse.core.internal.runtime.InternalPlatform.run",
          "source": "InternalPlatfo rm.java:802"
        },
        {
          "method": "org.eclipse.core.internal.plugins.PluginDescriptor.internalDoPluginActivation",
          "source": "PluginDescriptor.java:702"
        },
        {
          "method": "org.eclipse.core.internal.plugins.PluginDescriptor.doPluginActivation",
          "source": "PluginDescriptor.java:182"
        },
        {
          "method": "org.eclipse.core.internal.plugins.PluginClassLoader.activatePlugin",
          "source": "Pl uginClassLoader.java:58"
        },
        {
          "method": "org.eclipse.core.internal.plugins.PluginClassLoader.findClassParentsSelf",
          "source": "PluginClassLoader.java:136"
        },
        {
          "method": "org.eclipse.core.internal.boot.DelegatingURLClassLoader.loadClass",
          "source": "Del egatingURLClassLoader.java:750"
        },
        {
          "method": "org.eclipse.core.internal.boot.DelegatingURLClassLoader.access$0",
          "source": "Dele gatingURLClassLoader.java:744"
        },
        {
          "method": "org.eclipse.core.internal.boot.DelegatingURLClassLoader$DelegateLoader.loadClass",
          "source": "DelegatingURLClassLoader.java:70"
        },
        {
          "method": "org.eclipse.core.internal.boot.DelegatingURLClassLoader.findClassPrerequisites",
          "source": "DelegatingURLClassLoader.java:429"
        },
        {
          "method": "org.eclipse.core.internal.boot.DelegatingURLClassLoader.loadClass",
          "source": "Del egatingURLClassLoader.java:758"
        },
        {
          "method": "org.eclipse.core.internal.boot.DelegatingURLClassLoader.loadClass",
          "source": "Del egatingURLClassLoader.java:730"
        },
        {
          "method": "java.lang.ClassLoader.loadClass",
          "source": "ClassLoader.java:445"
        },
        {
          "method": "java.lang.Class.newInstance0",
          "source": "Native Method"
        },
        {
          "method": "java.lang.Class.newInstance",
          "source": "Class.java:262"
        },
        {
          "method": "org.eclipse.core.internal.plugins.PluginDescriptor.createExecutableExtension",
          "source": "PluginDescriptor.java:134"
        },
        {
          "method": "org.eclipse.core.internal.plugins.PluginDescriptor.createExecutableExtension",
          "source": "PluginDescriptor.java:163"
        },
        {
          "method": "org.eclipse.core.internal.plugins.ConfigurationElement.createExecutableExtension",
          "source": "ConfigurationElement.java:102"
        },
        {
          "method": "org.eclipse.core.internal.runtime.InternalPlatform.loaderGetRunnable",
          "source": " InternalPlatform.java:449"
        },
        {
          "method": "java.lang.reflect.Method.invoke",
          "source": "Native Method"
        },
        {
          "method": "org.eclipse.core.internal.boot.InternalBootLoader.getRunnable",
          "source": "Interna lBootLoader.java:436"
        },
        {
          "method": "org.eclipse.core.internal.boot.InternalBootLoader.run",
          "source": "InternalBootLoa der.java:735"
        },
        {
          "method": "org.eclipse.core.boot.BootLoader.run",
          "source": "BootLoader.java:462"
        },
        {
          "method": "java.lang.reflect.Method.invoke",
          "source": "Native Method"
        },
        {
          "method": "org.eclipse.core.launcher.Main.basicRun",
          "source": "Main.java:244"
        },
        {
          "method": "org.eclipse.core.launcher.Main.run",
          "source": "Main.java:693"
        },
        {
          "method": "org.eclipse.core.launcher.Main.main",
          "source": "Main.java:526"
        }
      ],
      "number": 1,
      "commentIndex": 0,
      "bugId": "19534",
      "duplicateId": "2699",
      "date": "2002-06-06T21:10:05+02:00",
      "product": "Platform",
      "component": "Resources",
      "severity": "major"
    },
    {
      "exceptionType": "java.io.IOException",
      "message": "There is not enough space on the disk",
      "elements": [
        {
          "method": "java.io.FileOutputStream.writeBytes",
          "source": "Native Method"
        },
        {
          "method": "java.io.FileOutputStream.write",
          "source": "FileOutputStream.java:228"
        },
        {
          "method": "java.io.OutputStreamWriter.flushBuffer",
          "source": "OutputStreamWriter.java:244"
        },
        {
          "method": "java.io.OutputStreamWriter.flush",
          "source": "OutputStreamWriter.java:258"
        },
        {
          "method": "java.io.BufferedWriter.flush",
          "source": "BufferedWriter.java:247"
        },
        {
          "method": "org.eclipse.core.internal.runtime.PlatformLogWriter.closeLogFile",
          "source": "Plat formLogWriter.java:54"
        },
        {
          "method": "org.eclipse.core.internal.runtime.PlatformLogWriter.logging",
          "source": "PlatformL ogWriter.java:75"
        },
        {
          "method": "org.eclipse.core.internal.runtime.InternalPlatform.log",
          "source": "InternalPlatfo rm.java:678"
        },
        {
          "method": "org.eclipse.core.internal.runtime.Log.log",
          "source": "Log.java:66"
        },
        {
          "method": "org.eclipse.core.internal.runtime.InternalPlatform.handleException",
          "source": "In ternalPlatform.java:425"
        },
        {
          "method": "org.eclipse.core.internal.runtime.InternalPlatform.run",
          "source": "InternalPlatfo rm.java:804"
        },
        {
          "method": "org.eclipse.core.runtime.Platform.run",
          "source": "Platform.java:416"
        },
        {
          "method": "org.eclipse.ui.internal.Workbench.openPreviousWorkbenchState",
          "source": "Workbenc h.java:748"
        },
        {
          "method": "org.eclipse.ui.internal.Workbench.init",
          "source": "Workbench.java:562"
        },
        {
          "method": "org.eclipse.ui.internal.Workbench.run",
          "source": "Workbench.java:1153"
        },
        {
          "method": "org.eclipse.core.internal.boot.InternalBootLoader.run",
          "source": "InternalBootLoa der.java:739"
        },
        {
          "method": "org.eclipse.core.boot.BootLoader.run",
          "source": "BootLoader.java:462"
        },
        {
          "method": "java.lang.reflect.Method.invoke",
          "source": "Native Method"
        },
        {
          "method": "org.eclipse.core.launcher.Main.basicRun",
          "source": "Main.java:244"
        },
        {
          "method": "org.eclipse.core.launcher.Main.run",
          "source": "Main.java:693"
        },
        {
          "method": "org.eclipse.core.launcher.Main.main",
          "source": "Main.java:526"
        }
      ],
      "number": 2,
      "commentIndex": 0,
      "bugId": "19534",
      "duplicateId": "2699",
      "date": "2002-06-06T21:10:05+02:00",
      "product": "Platform",
      "component": "Resources",
      "severity": "major"
    },
    {
      "exceptionType": "java.lang.NullPointerException",
      "elements": [
        {
          "method": "org.eclipse.ui.internal.Workbench$6.run",
          "source": "Workbench.java:755"
        },
        {
          "method": "org.eclipse.core.internal.runtime.InternalPlatform.run",
          "source": "InternalPlatfo rm.java:802"
        },
        {
          "method": "org.eclipse.core.runtime.Platform.run",
          "source": "Platform.java:416"
        },
        {
          "method": "org.eclipse.ui.internal.Workbench.openPreviousWorkbenchState",
          "source": "Workbenc h.java:748"
        },
        {
          "method": "org.eclipse.ui.internal.Workbench.init",
          "source": "Workbench.java:562"
        },
        {
          "method": "org.eclipse.ui.internal.Workbench.run",
          "source": "Workbench.java:1153"
        },
        {
          "method": "org.eclipse.core.internal.boot.InternalBootLoader.run",
          "source": "InternalBootLoa der.java:739"
        },
        {
          "method": "org.eclipse.core.boot.BootLoader.run",
          "source": "BootLoader.java:462"
        },
        {
          "method": "java.lang.reflect.Method.invoke",
          "source": "Native Method"
        },
        {
          "method": "org.eclipse.core.launcher.Main.basicRun",
          "source": "Main.java:244"
        },
        {
          "method": "org.eclipse.core.launcher.Main.run",
          "source": "Main.java:693"
        },
        {
          "method": "org.eclipse.core.launcher.Main.main",
          "source": "Main.java:526"
        }
      ],
      "number": 3,
      "commentIndex": 0,
      "bugId": "19534",
      "duplicateId": "2699",
      "date": "2002-06-06T21:10:05+02:00",
      "product": "Platform",
      "component": "Resources",
      "severity": "major"
    }
  ],
  "groupId": "2699",
  "bugId": "19534",
  "duplicateId": "2699",
  "date": "2002-06-06T21:10:05+02:00",
  "product": "Platform",
  "component": "Resources",
  "severity": "major"
}