{
  "comments": [
    "A copy of the simplest bad workspace is available at http://bronzeagesoftware.com/AthenaBackup/workspace.bad2.tgz\n\nBuild ID: 20070625-1500\n\nSteps To Reproduce:\n1. Open the workspace provided\n2. Watch it crash with exception below\n3. This first happened with an upgrade from 3.2, so I rebuilt my workspace from scratch, but it happened again.\n\n\nMore information:\nandrew@athens:~$ eclipse\nException in thread \"Thread-1\" java.lang.NoClassDefFoundError: Could not initialize class org.eclipse.jface.preference.PreferenceConverter\n        at org.eclipse.ui.internal.themes.ThemeElementHelper.installFont(ThemeElementHelper.java:101)\n        at org.eclipse.ui.internal.themes.ThemeElementHelper.populateRegistry(ThemeElementHelper.java:57)\n        at org.eclipse.ui.internal.Workbench$28.runWithException(Workbench.java:1426)\n        at org.eclipse.ui.internal.StartupThreading$StartupRunnable.run(StartupThreading.java:31)\n        at org.eclipse.swt.widgets.RunnableLock.run(RunnableLock.java:35)\n        at org.eclipse.swt.widgets.Synchronizer.runAsyncMessages(Synchronizer.java:123)\n        at org.eclipse.swt.widgets.Display.runAsyncMessages(Display.java:3296)\n        at org.eclipse.swt.widgets.Display.readAndDispatch(Display.java:2974)\n        at org.eclipse.ui.internal.Workbench.runUI(Workbench.java:2309)\n        at org.eclipse.ui.internal.Workbench.access$4(Workbench.java:2219)\n        at org.eclipse.ui.internal.Workbench$4.run(Workbench.java:466)\n        at org.eclipse.core.databinding.observable.Realm.runWithDefault(Realm.java:289)\n        at org.eclipse.ui.internal.Workbench.createAndRunWorkbench(Workbench.java:461)\n        at org.eclipse.ui.PlatformUI.createAndRunWorkbench(PlatformUI.java:149)\n        at org.eclipse.ui.internal.ide.application.IDEApplication.start(IDEApplication.java:106)\n        at org.eclipse.equinox.internal.app.EclipseAppHandle.run(EclipseAppHandle.java:153)\n        at org.eclipse.core.runtime.internal.adaptor.EclipseAppLauncher.runApplication(EclipseAppLauncher.java:106)\n        at org.eclipse.core.runtime.internal.adaptor.EclipseAppLauncher.start(EclipseAppLauncher.java:76)\n        at org.eclipse.core.runtime.adaptor.EclipseStarter.run(EclipseStarter.java:363)\n        at org.eclipse.core.runtime.adaptor.EclipseStarter.run(EclipseStarter.java:176)\n        at sun.reflect.NativeMethodAccessorImpl.invoke0(Native Method)\n        at sun.reflect.NativeMethodAccessorImpl.invoke(NativeMethodAccessorImpl.java:39)\n        at sun.reflect.DelegatingMethodAccessorImpl.invoke(DelegatingMethodAccessorImpl.java:25)\n        at java.lang.reflect.Method.invoke(Method.java:589)\n        at org.eclipse.equinox.launcher.Main.invokeFramework(Main.java:504)\n        at org.eclipse.equinox.launcher.Main.basicRun(Main.java:443)\n        at org.eclipse.equinox.launcher.Main.run(Main.java:1169)\nandrew@athens:~$",
    "One other item.  I have the following plugins installed:\n- Perforce\n- Quantum DB\n- Jigloo GUI Builder",
    "I\u0027m also seeing this problem. Going to attach a log file - Root cause looks SWT related to me?",
    "Created an attachment (id\u003d73537)\nlogs of failed startup\n\nCaused by: org.eclipse.swt.SWTException: Invalid thread access\n        at org.eclipse.swt.SWT.error(SWT.java:3563)\n        at org.eclipse.swt.SWT.error(SWT.java:3481)\n        at org.eclipse.swt.SWT.error(SWT.java:3452)\n        at org.eclipse.swt.widgets.Display.error(Display.java:1109)\n        at org.eclipse.swt.widgets.Display.checkDevice(Display.java:703)\n        at org.eclipse.swt.widgets.Display.getSystemFont(Display.java:2182)\n        at org.eclipse.jface.preference.PreferenceConverter.\u003cclinit\u003e(PreferenceC\nonverter.java:83)\n        ... 56 more\n\nlooks like it might be important?",
    "Created an attachment (id\u003d73538)\nEclipse configuration of system with problem.\n\n",
    "The only common plugin we have is perforce, and that\u0027s showing up in my startup logs.",
    "I\u0027m having the same issue and I too have the perforce plugin.  \n\nI\u0027ve found that the only thing I can do to get the workspace to function again after a crash is\n\nrm -rf ~/$WORKSPACE/.metadata/.plugins/org.eclipse.core.resources/.snap\n\nOf course, that also means that I loose some of my workspace info.\n\n\nTo reproduce:\nCause Eclipse to crash (easy! I\u0027ll run out of PermGenSpace all the time.  Apparently this is common with WTP)\nTry to start eclipse using the same workspace.\n??? Be using perforce plugin as well??\n\nI\u0027m going to forward this issue to the perforce support team.\n\n\n\n\n\nException in thread \"Thread-1\" java.lang.NoClassDefFoundError\n        at org.eclipse.ui.internal.themes.ThemeElementHelper.installFont(ThemeElementHelper.java:101)\n        at org.eclipse.ui.internal.themes.ThemeElementHelper.populateRegistry(ThemeElementHelper.java:57)\n        at org.eclipse.ui.internal.Workbench$28.runWithException(Workbench.java:1426)\n        at org.eclipse.ui.internal.StartupThreading$StartupRunnable.run(StartupThreading.java:31)\n        at org.eclipse.swt.widgets.RunnableLock.run(RunnableLock.java:35)\n        at org.eclipse.swt.widgets.Synchronizer.runAsyncMessages(Synchronizer.java:123)\n        at org.eclipse.swt.widgets.Display.runAsyncMessages(Display.java:3296)\n        at org.eclipse.swt.widgets.Display.readAndDispatch(Display.java:2974)\n        at org.eclipse.ui.internal.Workbench.runUI(Workbench.java:2309)\n        at org.eclipse.ui.internal.Workbench.access$4(Workbench.java:2219)\n        at org.eclipse.ui.internal.Workbench$4.run(Workbench.java:466)\n        at org.eclipse.core.databinding.observable.Realm.runWithDefault(Realm.java:289)\n        at org.eclipse.ui.internal.Workbench.createAndRunWorkbench(Workbench.java:461)\n        at org.eclipse.ui.PlatformUI.createAndRunWorkbench(PlatformUI.java:149)\n        at org.eclipse.ui.internal.ide.application.IDEApplication.start(IDEApplication.java:106)\n        at org.eclipse.equinox.internal.app.EclipseAppHandle.run(EclipseAppHandle.java:153)\n        at org.eclipse.core.runtime.internal.adaptor.EclipseAppLauncher.runApplication(EclipseAppLauncher.java:106)\n        at org.eclipse.core.runtime.internal.adaptor.EclipseAppLauncher.start(EclipseAppLauncher.java:76)\n        at org.eclipse.core.runtime.adaptor.EclipseStarter.run(EclipseStarter.java:363)\n        at org.eclipse.core.runtime.adaptor.EclipseStarter.run(EclipseStarter.java:176)\n        at sun.reflect.NativeMethodAccessorImpl.invoke0(Native Method)\n        at sun.reflect.NativeMethodAccessorImpl.invoke(NativeMethodAccessorImpl.java:39)\n        at sun.reflect.DelegatingMethodAccessorImpl.invoke(DelegatingMethodAccessorImpl.java:25)\n        at java.lang.reflect.Method.invoke(Method.java:585)\n        at org.eclipse.equinox.launcher.Main.invokeFramework(Main.java:504)\n        at org.eclipse.equinox.launcher.Main.basicRun(Main.java:443)\n        at org.eclipse.equinox.launcher.Main.run(Main.java:1169)\n",
    "FYI, Perforce Software has already identified this issue as a high priority.",
    "I can\u0027t reproduce this in base Eclipse.  From the logs it appears that the preforce plugins have been accessing the jface classes from threads that cannot be guaranteed to be the UI thread.  We had to fix an instance of this faux pas ourselves in bug 183036.  I don\u0027t believe there is anything for us to fix - this should be addressed in the Perforce code.  "
  ],
  "commentCreationDates": [
    "2007-07-05T19:08:20+02:00",
    "2007-07-06T06:39:05+02:00",
    "2007-07-11T16:22:12+02:00",
    "2007-07-11T16:23:05+02:00",
    "2007-07-11T16:23:48+02:00",
    "2007-07-11T16:37:08+02:00",
    "2007-07-12T03:00:11+02:00",
    "2007-07-12T18:48:53+02:00",
    "2007-07-12T20:16:29+02:00"
  ],
  "traces": [
    {
      "exceptionType": "java.lang.NoClassDefFoundError",
      "message": "Could not initialize class org.eclipse.jface.preference.PreferenceConverter",
      "elements": [
        {
          "method": "org.eclipse.ui.internal.themes.ThemeElementHelper.installFont",
          "source": "ThemeElementHelper.java:101"
        },
        {
          "method": "org.eclipse.ui.internal.themes.ThemeElementHelper.populateRegistry",
          "source": "ThemeElementHelper.java:57"
        },
        {
          "method": "org.eclipse.ui.internal.Workbench$28.runWithException",
          "source": "Workbench.java:1426"
        },
        {
          "method": "org.eclipse.ui.internal.StartupThreading$StartupRunnable.run",
          "source": "StartupThreading.java:31"
        },
        {
          "method": "org.eclipse.swt.widgets.RunnableLock.run",
          "source": "RunnableLock.java:35"
        },
        {
          "method": "org.eclipse.swt.widgets.Synchronizer.runAsyncMessages",
          "source": "Synchronizer.java:123"
        },
        {
          "method": "org.eclipse.swt.widgets.Display.runAsyncMessages",
          "source": "Display.java:3296"
        },
        {
          "method": "org.eclipse.swt.widgets.Display.readAndDispatch",
          "source": "Display.java:2974"
        },
        {
          "method": "org.eclipse.ui.internal.Workbench.runUI",
          "source": "Workbench.java:2309"
        },
        {
          "method": "org.eclipse.ui.internal.Workbench.access$4",
          "source": "Workbench.java:2219"
        },
        {
          "method": "org.eclipse.ui.internal.Workbench$4.run",
          "source": "Workbench.java:466"
        },
        {
          "method": "org.eclipse.core.databinding.observable.Realm.runWithDefault",
          "source": "Realm.java:289"
        },
        {
          "method": "org.eclipse.ui.internal.Workbench.createAndRunWorkbench",
          "source": "Workbench.java:461"
        },
        {
          "method": "org.eclipse.ui.PlatformUI.createAndRunWorkbench",
          "source": "PlatformUI.java:149"
        },
        {
          "method": "org.eclipse.ui.internal.ide.application.IDEApplication.start",
          "source": "IDEApplication.java:106"
        },
        {
          "method": "org.eclipse.equinox.internal.app.EclipseAppHandle.run",
          "source": "EclipseAppHandle.java:153"
        },
        {
          "method": "org.eclipse.core.runtime.internal.adaptor.EclipseAppLauncher.runApplication",
          "source": "EclipseAppLauncher.java:106"
        },
        {
          "method": "org.eclipse.core.runtime.internal.adaptor.EclipseAppLauncher.start",
          "source": "EclipseAppLauncher.java:76"
        },
        {
          "method": "org.eclipse.core.runtime.adaptor.EclipseStarter.run",
          "source": "EclipseStarter.java:363"
        },
        {
          "method": "org.eclipse.core.runtime.adaptor.EclipseStarter.run",
          "source": "EclipseStarter.java:176"
        },
        {
          "method": "sun.reflect.NativeMethodAccessorImpl.invoke0",
          "source": "Native Method"
        },
        {
          "method": "sun.reflect.NativeMethodAccessorImpl.invoke",
          "source": "NativeMethodAccessorImpl.java:39"
        },
        {
          "method": "sun.reflect.DelegatingMethodAccessorImpl.invoke",
          "source": "DelegatingMethodAccessorImpl.java:25"
        },
        {
          "method": "java.lang.reflect.Method.invoke",
          "source": "Method.java:589"
        },
        {
          "method": "org.eclipse.equinox.launcher.Main.invokeFramework",
          "source": "Main.java:504"
        },
        {
          "method": "org.eclipse.equinox.launcher.Main.basicRun",
          "source": "Main.java:443"
        },
        {
          "method": "org.eclipse.equinox.launcher.Main.run",
          "source": "Main.java:1169"
        }
      ],
      "number": 0,
      "commentIndex": 0,
      "bugId": "195554",
      "date": "2007-07-05T19:08:20+02:00",
      "product": "Platform",
      "component": "IDE",
      "severity": "blocker"
    },
    {
      "exceptionType": "org.eclipse.swt.SWTException",
      "message": "Invalid thread access",
      "elements": [
        {
          "method": "org.eclipse.swt.SWT.error",
          "source": "SWT.java:3563"
        },
        {
          "method": "org.eclipse.swt.SWT.error",
          "source": "SWT.java:3481"
        },
        {
          "method": "org.eclipse.swt.SWT.error",
          "source": "SWT.java:3452"
        },
        {
          "method": "org.eclipse.swt.widgets.Display.error",
          "source": "Display.java:1109"
        },
        {
          "method": "org.eclipse.swt.widgets.Display.checkDevice",
          "source": "Display.java:703"
        },
        {
          "method": "org.eclipse.swt.widgets.Display.getSystemFont",
          "source": "Display.java:2182"
        },
        {
          "method": "org.eclipse.jface.preference.PreferenceConverter.\u003cclinit\u003e",
          "source": "PreferenceC onverter.java:83"
        }
      ],
      "number": 1,
      "commentIndex": 3,
      "bugId": "195554",
      "date": "2007-07-11T16:23:05+02:00",
      "product": "Platform",
      "component": "IDE",
      "severity": "blocker"
    },
    {
      "exceptionType": "java.lang.NoClassDefFoundError",
      "elements": [
        {
          "method": "org.eclipse.ui.internal.themes.ThemeElementHelper.installFont",
          "source": "ThemeElementHelper.java:101"
        },
        {
          "method": "org.eclipse.ui.internal.themes.ThemeElementHelper.populateRegistry",
          "source": "ThemeElementHelper.java:57"
        },
        {
          "method": "org.eclipse.ui.internal.Workbench$28.runWithException",
          "source": "Workbench.java:1426"
        },
        {
          "method": "org.eclipse.ui.internal.StartupThreading$StartupRunnable.run",
          "source": "StartupThreading.java:31"
        },
        {
          "method": "org.eclipse.swt.widgets.RunnableLock.run",
          "source": "RunnableLock.java:35"
        },
        {
          "method": "org.eclipse.swt.widgets.Synchronizer.runAsyncMessages",
          "source": "Synchronizer.java:123"
        },
        {
          "method": "org.eclipse.swt.widgets.Display.runAsyncMessages",
          "source": "Display.java:3296"
        },
        {
          "method": "org.eclipse.swt.widgets.Display.readAndDispatch",
          "source": "Display.java:2974"
        },
        {
          "method": "org.eclipse.ui.internal.Workbench.runUI",
          "source": "Workbench.java:2309"
        },
        {
          "method": "org.eclipse.ui.internal.Workbench.access$4",
          "source": "Workbench.java:2219"
        },
        {
          "method": "org.eclipse.ui.internal.Workbench$4.run",
          "source": "Workbench.java:466"
        },
        {
          "method": "org.eclipse.core.databinding.observable.Realm.runWithDefault",
          "source": "Realm.java:289"
        },
        {
          "method": "org.eclipse.ui.internal.Workbench.createAndRunWorkbench",
          "source": "Workbench.java:461"
        },
        {
          "method": "org.eclipse.ui.PlatformUI.createAndRunWorkbench",
          "source": "PlatformUI.java:149"
        },
        {
          "method": "org.eclipse.ui.internal.ide.application.IDEApplication.start",
          "source": "IDEApplication.java:106"
        },
        {
          "method": "org.eclipse.equinox.internal.app.EclipseAppHandle.run",
          "source": "EclipseAppHandle.java:153"
        },
        {
          "method": "org.eclipse.core.runtime.internal.adaptor.EclipseAppLauncher.runApplication",
          "source": "EclipseAppLauncher.java:106"
        },
        {
          "method": "org.eclipse.core.runtime.internal.adaptor.EclipseAppLauncher.start",
          "source": "EclipseAppLauncher.java:76"
        },
        {
          "method": "org.eclipse.core.runtime.adaptor.EclipseStarter.run",
          "source": "EclipseStarter.java:363"
        },
        {
          "method": "org.eclipse.core.runtime.adaptor.EclipseStarter.run",
          "source": "EclipseStarter.java:176"
        },
        {
          "method": "sun.reflect.NativeMethodAccessorImpl.invoke0",
          "source": "Native Method"
        },
        {
          "method": "sun.reflect.NativeMethodAccessorImpl.invoke",
          "source": "NativeMethodAccessorImpl.java:39"
        },
        {
          "method": "sun.reflect.DelegatingMethodAccessorImpl.invoke",
          "source": "DelegatingMethodAccessorImpl.java:25"
        },
        {
          "method": "java.lang.reflect.Method.invoke",
          "source": "Method.java:585"
        },
        {
          "method": "org.eclipse.equinox.launcher.Main.invokeFramework",
          "source": "Main.java:504"
        },
        {
          "method": "org.eclipse.equinox.launcher.Main.basicRun",
          "source": "Main.java:443"
        },
        {
          "method": "org.eclipse.equinox.launcher.Main.run",
          "source": "Main.java:1169"
        }
      ],
      "number": 2,
      "commentIndex": 6,
      "bugId": "195554",
      "date": "2007-07-12T03:00:11+02:00",
      "product": "Platform",
      "component": "IDE",
      "severity": "blocker"
    }
  ],
  "groupId": "195554",
  "bugId": "195554",
  "date": "2007-07-05T19:08:20+02:00",
  "product": "Platform",
  "component": "IDE",
  "severity": "blocker"
}