{
  "comments": [
    "I installed Eclipse 3.3 and pointed it to my Eclipse 3.2 workspace. Now my .log file is filling up with many, many messages like the one below --- one for each project in my workspace. They are generated during my workspace automatic incremental builds. These builds now take a very long time - much longer than under 3.2.\n\nOne thing I\u0027ve noticed: It seem to be happening with projects that have names with spaces in them, such as the one below:\n\n\"C:/projects/regatta-workbench/workspace/RW FinishLynx/plugin.xml\"\n\nPerhaps it\u0027s similar in some way to this: http://dev.eclipse.org/newslists/news.eclipse.modeling.m2t/msg00163.html\n\nIs this an EMF issue? If not, can you point me in the right direction?\n\n!ENTRY org.eclipse.jet 2 0 2007-07-09 15:27:20.687\n!MESSAGE Illegal character in opaque part at index 47: file:C:/projects/regatta-workbench/workspace/RW FinishLynx/plugin.xml\n!STACK 0\norg.eclipse.emf.ecore.resource.Resource$IOWrappedException: Illegal character in opaque part at index 47: file:C:/projects/regatta-workbench/workspace/RW FinishLynx/plugin.xml\n    at org.eclipse.emf.ecore.resource.impl.URIConverterImpl.createEFSInputStream(URIConverterImpl.java:671)\n    at org.eclipse.emf.ecore.resource.impl.URIConverterImpl.createInputStream(URIConverterImpl.java:542)\n    at org.eclipse.emf.ecore.resource.impl.ResourceImpl.load(ResourceImpl.java:1152)\n    at org.eclipse.jet.internal.runtime.model.EMFXMLModelLoader.load(EMFXMLModelLoader.java:151)\n    at org.eclipse.jet.internal.runtime.model.EMFXMLModelLoader.load(EMFXMLModelLoader.java:131)\n    at org.eclipse.jet.internal.extensionpoints.PluginProjectMonitor.updateProject(PluginProjectMonitor.java:208)\n    at org.eclipse.jet.internal.extensionpoints.PluginProjectMonitor.access$0(PluginProjectMonitor.java:196)\n    at org.eclipse.jet.internal.extensionpoints.PluginProjectMonitor$1.visit(PluginProjectMonitor.java:129)\n    at org.eclipse.core.internal.events.ResourceDelta.accept(ResourceDelta.java:67)\n    at org.eclipse.core.internal.events.ResourceDelta.accept(ResourceDelta.java:76)\n    at org.eclipse.core.internal.events.ResourceDelta.accept(ResourceDelta.java:48)\n    at org.eclipse.jet.internal.extensionpoints.PluginProjectMonitor.handleWorkspaceChange(PluginProjectMonitor.java:112)\n    at org.eclipse.jet.internal.extensionpoints.PluginProjectMonitor.resourceChanged(PluginProjectMonitor.java:103)\n    at org.eclipse.core.internal.events.NotificationManager$2.run(NotificationManager.java:282)\n    at org.eclipse.core.runtime.SafeRunner.run(SafeRunner.java:37)\n    at org.eclipse.core.internal.events.NotificationManager.notify(NotificationManager.java:276)\n    at org.eclipse.core.internal.events.NotificationManager.broadcastChanges(NotificationManager.java:148)\n    at org.eclipse.core.internal.resources.Workspace.broadcastPostChange(Workspace.java:311)\n    at org.eclipse.core.internal.resources.Workspace.endOperation(Workspace.java:1018)\n    at org.eclipse.core.internal.resources.Workspace.run(Workspace.java:1806)\n    at org.eclipse.core.internal.events.NotificationManager$NotifyJob.run(NotificationManager.java:39)\n    at org.eclipse.core.internal.jobs.Worker.run(Worker.java:55)\nCaused by: java.net.URISyntaxException: Illegal character in opaque part at index 47: file:C:/projects/regatta-workbench/workspace/RW FinishLynx/plugin.xml\n    at java.net.URI$Parser.fail(Unknown Source)\n    at java.net.URI$Parser.checkChars(Unknown Source)\n    at java.net.URI$Parser.parse(Unknown Source)\n    at java.net.URI.\u003cinit\u003e(Unknown Source)\n    at org.eclipse.emf.ecore.resource.impl.URIConverterImpl.createEFSInputStream(URIConverterImpl.java:663)\n    ... 21 more\n\n\n\nHere is Ed Merks\u0027 response to my message above:\n\nI\u0027m not sure where the URI \"file:C:/projects/regatta-workbench/workspace/RW FinishLynx/plugin.xml\" is being created, but it should be of the form \"file:/C:/projects/regatta-workbench/workspace/RW FinishLynx/plugin.xml\" (note the / after the file:) to be a proper hierarchical URI.  Perhaps this worked in the past because createURLInputStream was invoked where really createFileInputStream is what should be kicking in but now, with 2.3, createEFSInputStream is used instead.  I\u0027m confused though why this code wouldn\u0027t be using \"platform:/resource/RW FinishLynx/plugin.xml\" instead, because that would seem the proper way to access something in the workspace; using a file: URI for that will bypass the workspace and access the underlying file system directly instead...\n\nI\u0027ll add the M2T newsgroup to the reply since this appears to be a JET2 problem in this code:\n\n      private void updateProject(IProject project)\n      {\n        if(DEBUG) System.out.println(\"PluginProjectMonitor.updateProject(\" + project + \")\"); //$NON-NLS-1$ //$NON-NLS-2$\n        try\n        {\n         \n          final URL projectURL \u003d new URL(\"file\", \"\", project.getLocation() + \"/\"); //$NON-NLS-1$ //$NON-NLS-2$ //$NON-NLS-3$\n          final BundleManifest manifest \u003d JETBundleManager.loadManifest(projectURL);\n          Object pluginDocumentRoot \u003d null;\n          if(hasPluginManifest(project)) {\n            if(DEBUG)System.out.println(\"  has plugin.xml\"); //$NON-NLS-1$\n            URL extensionsURL \u003d new URL(projectURL, \"plugin.xml\"); //$NON-NLS-1$\n            pluginDocumentRoot \u003d JETActivatorWrapper.INSTANCE.getLoaderManager().getLoader(extensionsURL.toExternalForm(), null, \"xml\").load(extensionsURL); //$NON-NLS-1$\n          }",
    "Fix committed to CVS. Build will follow shortly.",
    "Fixed in build 0.8.1 M200707120943"
  ],
  "commentCreationDates": [
    "2007-07-10T04:58:56+02:00",
    "2007-07-11T20:37:16+02:00",
    "2007-07-12T17:21:21+02:00"
  ],
  "traces": [
    {
      "exceptionType": "org.eclipse.emf.ecore.resource.Resource$IOWrappedException",
      "message": "Illegal character in opaque part at index 47: file:C:/projects/regatta-workbench/workspace/RW FinishLynx/plugin.xml",
      "elements": [
        {
          "method": "org.eclipse.emf.ecore.resource.impl.URIConverterImpl.createEFSInputStream",
          "source": "URIConverterImpl.java:671"
        },
        {
          "method": "org.eclipse.emf.ecore.resource.impl.URIConverterImpl.createInputStream",
          "source": "URIConverterImpl.java:542"
        },
        {
          "method": "org.eclipse.emf.ecore.resource.impl.ResourceImpl.load",
          "source": "ResourceImpl.java:1152"
        },
        {
          "method": "org.eclipse.jet.internal.runtime.model.EMFXMLModelLoader.load",
          "source": "EMFXMLModelLoader.java:151"
        },
        {
          "method": "org.eclipse.jet.internal.runtime.model.EMFXMLModelLoader.load",
          "source": "EMFXMLModelLoader.java:131"
        },
        {
          "method": "org.eclipse.jet.internal.extensionpoints.PluginProjectMonitor.updateProject",
          "source": "PluginProjectMonitor.java:208"
        },
        {
          "method": "org.eclipse.jet.internal.extensionpoints.PluginProjectMonitor.access$0",
          "source": "PluginProjectMonitor.java:196"
        },
        {
          "method": "org.eclipse.jet.internal.extensionpoints.PluginProjectMonitor$1.visit",
          "source": "PluginProjectMonitor.java:129"
        },
        {
          "method": "org.eclipse.core.internal.events.ResourceDelta.accept",
          "source": "ResourceDelta.java:67"
        },
        {
          "method": "org.eclipse.core.internal.events.ResourceDelta.accept",
          "source": "ResourceDelta.java:76"
        },
        {
          "method": "org.eclipse.core.internal.events.ResourceDelta.accept",
          "source": "ResourceDelta.java:48"
        },
        {
          "method": "org.eclipse.jet.internal.extensionpoints.PluginProjectMonitor.handleWorkspaceChange",
          "source": "PluginProjectMonitor.java:112"
        },
        {
          "method": "org.eclipse.jet.internal.extensionpoints.PluginProjectMonitor.resourceChanged",
          "source": "PluginProjectMonitor.java:103"
        },
        {
          "method": "org.eclipse.core.internal.events.NotificationManager$2.run",
          "source": "NotificationManager.java:282"
        },
        {
          "method": "org.eclipse.core.runtime.SafeRunner.run",
          "source": "SafeRunner.java:37"
        },
        {
          "method": "org.eclipse.core.internal.events.NotificationManager.notify",
          "source": "NotificationManager.java:276"
        },
        {
          "method": "org.eclipse.core.internal.events.NotificationManager.broadcastChanges",
          "source": "NotificationManager.java:148"
        },
        {
          "method": "org.eclipse.core.internal.resources.Workspace.broadcastPostChange",
          "source": "Workspace.java:311"
        },
        {
          "method": "org.eclipse.core.internal.resources.Workspace.endOperation",
          "source": "Workspace.java:1018"
        },
        {
          "method": "org.eclipse.core.internal.resources.Workspace.run",
          "source": "Workspace.java:1806"
        },
        {
          "method": "org.eclipse.core.internal.events.NotificationManager$NotifyJob.run",
          "source": "NotificationManager.java:39"
        },
        {
          "method": "org.eclipse.core.internal.jobs.Worker.run",
          "source": "Worker.java:55"
        }
      ],
      "causedBy": {
        "exceptionType": "java.net.URISyntaxException",
        "message": "Illegal character in opaque part at index 47: file:C:/projects/regatta-workbench/workspace/RW FinishLynx/plugin.xml",
        "elements": [
          {
            "method": "java.net.URI$Parser.fail",
            "source": "Unknown Source"
          },
          {
            "method": "java.net.URI$Parser.checkChars",
            "source": "Unknown Source"
          },
          {
            "method": "java.net.URI$Parser.parse",
            "source": "Unknown Source"
          },
          {
            "method": "java.net.URI.\u003cinit\u003e",
            "source": "Unknown Source"
          },
          {
            "method": "org.eclipse.emf.ecore.resource.impl.URIConverterImpl.createEFSInputStream",
            "source": "URIConverterImpl.java:663"
          }
        ],
        "number": 0,
        "commentIndex": 0
      },
      "number": 0,
      "commentIndex": 0,
      "bugId": "195924",
      "date": "2007-07-10T04:58:56+02:00",
      "product": "M2T",
      "component": "Jet",
      "severity": "normal"
    }
  ],
  "groupId": "195924",
  "bugId": "195924",
  "date": "2007-07-10T04:58:56+02:00",
  "product": "M2T",
  "component": "Jet",
  "severity": "normal"
}