{
  "comments": [
    "Build ID: 200706261300\nCDT Build Version: 4.0.0.200706261300\n\nOpening a C/C++ file in the editor I obtain an error in CReconciler, the index is not working at all, and the outline\nis never completed and remains in a \"Pending...\" state.\n\nMore information:\nHere the stack-trace of the error:\nException in thread \"org.eclipse.cdt.internal.ui.text.CReconciler\" java.lang.NoC\nlassDefFoundError: org/eclipse/core/filebuffers/LocationKind\n        at org.eclipse.cdt.internal.ui.editor.DocumentAdapter.\u003cinit\u003e(DocumentAda\npter.java:194)\n        at org.eclipse.cdt.internal.ui.editor.CustomBufferFactory.createBuffer(C\nustomBufferFactory.java:48)\n        at org.eclipse.cdt.internal.core.model.WorkingCopy.openBuffer(WorkingCop\ny.java:305)\n        at org.eclipse.cdt.internal.core.model.Openable.getBuffer(Openable.java:\n114)\n        at org.eclipse.cdt.internal.core.model.TranslationUnit.getContents(Trans\nlationUnit.java:418)\n        at org.eclipse.cdt.internal.core.model.TranslationUnit.getCodeReader(Tra\nnslationUnit.java:866)\n        at org.eclipse.cdt.internal.core.model.TranslationUnit.getAST(Translatio\nnUnit.java:766)\n        at org.eclipse.cdt.internal.core.model.CModelBuilder2.parse(CModelBuilde\nr2.java:236)\n        at org.eclipse.cdt.internal.core.model.TranslationUnit.parseUsingCModelB\nuilder(TranslationUnit.java:615)\n        at org.eclipse.cdt.internal.core.model.TranslationUnit.parse(Translation\nUnit.java:603)\n        at org.eclipse.cdt.internal.core.model.TranslationUnit.buildStructure(Tr\nanslationUnit.java:400)\n        at org.eclipse.cdt.internal.core.model.Openable.generateInfos(Openable.j\nava:260)\n        at org.eclipse.cdt.internal.core.model.CElement.openWhenClosed(CElement.\njava:394)\n        at org.eclipse.cdt.internal.core.model.TranslationUnit.makeConsistent(Tr\nanslationUnit.java:518)\n        at org.eclipse.cdt.internal.core.model.ReconcileWorkingCopyOperation.exe\ncuteOperation(ReconcileWorkingCopyOperation.java:60)\n        at org.eclipse.cdt.internal.core.model.CModelOperation.execute(CModelOpe\nration.java:342)\n        at org.eclipse.cdt.internal.core.model.CModelOperation.run(CModelOperati\non.java:607)\n        at org.eclipse.cdt.internal.core.model.CModelOperation.runOperation(CMod\nelOperation.java:635)\n        at org.eclipse.cdt.internal.core.model.WorkingCopy.reconcile(WorkingCopy\n.java:405)\n        at org.eclipse.cdt.internal.ui.text.CReconcilingStrategy.reconcile(CReco\nncilingStrategy.java:127)\n        at org.eclipse.cdt.internal.ui.text.CReconcilingStrategy.initialReconcil\ne(CReconcilingStrategy.java:164)\n        at org.eclipse.jface.text.reconciler.MonoReconciler.initialProcess(MonoR\neconciler.java:103)\n        at org.eclipse.cdt.internal.ui.text.CReconciler.initialProcess(CReconcil\ner.java:382)\n        at org.eclipse.jface.text.reconciler.AbstractReconciler$BackgroundThread\n.run(AbstractReconciler.java:170)\nException in thread \"Text Viewer Hover Presenter\" java.lang.NoClassDefFoundError\n: org/eclipse/core/filebuffers/LocationKind\n        at org.eclipse.cdt.internal.ui.editor.DocumentAdapter.\u003cinit\u003e(DocumentAda\npter.java:194)\n        at org.eclipse.cdt.internal.ui.editor.CustomBufferFactory.createBuffer(C\nustomBufferFactory.java:48)\n        at org.eclipse.cdt.internal.core.model.WorkingCopy.openBuffer(WorkingCop\ny.java:305)\n        at org.eclipse.cdt.internal.core.model.Openable.getBuffer(Openable.java:\n114)\n        at org.eclipse.cdt.internal.core.model.TranslationUnit.getContents(Trans\nlationUnit.java:418)\n        at org.eclipse.cdt.internal.core.model.TranslationUnit.getCodeReader(Tra\nnslationUnit.java:866)\n        at org.eclipse.cdt.internal.core.model.TranslationUnit.getAST(Translatio\nnUnit.java:766)\n        at org.eclipse.cdt.internal.core.model.CModelBuilder2.parse(CModelBuilde\nr2.java:236)\n        at org.eclipse.cdt.internal.core.model.TranslationUnit.parseUsingCModelB\nuilder(TranslationUnit.java:615)\n        at org.eclipse.cdt.internal.core.model.TranslationUnit.parse(Translation\nUnit.java:603)\n        at org.eclipse.cdt.internal.core.model.TranslationUnit.buildStructure(Tr\nanslationUnit.java:400)\n        at org.eclipse.cdt.internal.core.model.Openable.generateInfos(Openable.j\nava:260)\n        at org.eclipse.cdt.internal.core.model.CElement.openWhenClosed(CElement.\njava:394)\n        at org.eclipse.cdt.internal.core.model.CElement.getElementInfo(CElement.\njava:274)\n        at org.eclipse.cdt.internal.core.model.TranslationUnit.getElementInfo(Tr\nanslationUnit.java:388)\n        at org.eclipse.cdt.internal.core.model.CElement.getElementInfo(CElement.\njava:264)\n        at org.eclipse.cdt.internal.core.model.Parent.getChildren(Parent.java:54\n)\n        at org.eclipse.cdt.internal.core.model.TranslationUnit.getElement(Transl\nationUnit.java:165)\n        at org.eclipse.cdt.internal.ui.text.c.hover.CSourceHover.getHoverInfo(CS\nourceHover.java:590)\n        at org.eclipse.cdt.internal.ui.text.c.hover.BestMatchHover.getHoverInfo(\nBestMatchHover.java:100)\n        at org.eclipse.cdt.internal.ui.text.c.hover.CEditorTextHoverProxy.getHov\nerInfo(CEditorTextHoverProxy.java:64)\n        at org.eclipse.jface.text.TextViewerHoverManager$4.run(TextViewerHoverMa\nnager.java:160)",
    "This looks like an installation problem, what version of the eclipse platform are you using (you need eclipse 3.3)?\nDoes the log contain other errors?\n",
    "I am using Eclipse 3.3, I could try to reinstall it.\nI\u0027m going to attach the .log file i find in .metadata/ in the Workspace.",
    "Created an attachment (id\u003d73646)\nLog file\n\n",
    "From the log I can see that you are using an older eclipse platform.\n\n!SESSION 2007-07-12 10:42:14.718 -----------------------------------------------\neclipse.buildId\u003dI20061214-1445\n",
    "Reinstalling eclipse worked. \n"
  ],
  "commentCreationDates": [
    "2007-07-12T11:12:14+02:00",
    "2007-07-12T11:22:30+02:00",
    "2007-07-12T12:06:46+02:00",
    "2007-07-12T12:16:35+02:00",
    "2007-07-12T13:05:51+02:00",
    "2007-07-12T13:08:25+02:00"
  ],
  "traces": [
    {
      "exceptionType": "lassDefFoundError",
      "message": "org/eclipse/core/filebuffers/LocationKind",
      "elements": [
        {
          "method": "org.eclipse.cdt.internal.ui.editor.DocumentAdapter.\u003cinit\u003e",
          "source": "DocumentAda pter.java:194"
        },
        {
          "method": "org.eclipse.cdt.internal.ui.editor.CustomBufferFactory.createBuffer",
          "source": "C ustomBufferFactory.java:48"
        },
        {
          "method": "org.eclipse.cdt.internal.core.model.WorkingCopy.openBuffer",
          "source": "WorkingCop y.java:305"
        },
        {
          "method": "org.eclipse.cdt.internal.core.model.Openable.getBuffer",
          "source": "Openable.java: 114"
        },
        {
          "method": "org.eclipse.cdt.internal.core.model.TranslationUnit.getContents",
          "source": "Trans lationUnit.java:418"
        },
        {
          "method": "org.eclipse.cdt.internal.core.model.TranslationUnit.getCodeReader",
          "source": "Tra nslationUnit.java:866"
        },
        {
          "method": "org.eclipse.cdt.internal.core.model.TranslationUnit.getAST",
          "source": "Translatio nUnit.java:766"
        },
        {
          "method": "org.eclipse.cdt.internal.core.model.CModelBuilder2.parse",
          "source": "CModelBuilde r2.java:236"
        },
        {
          "method": "org.eclipse.cdt.internal.core.model.TranslationUnit.parseUsingCModelBuilder",
          "source": "TranslationUnit.java:615"
        },
        {
          "method": "org.eclipse.cdt.internal.core.model.TranslationUnit.parse",
          "source": "Translation Unit.java:603"
        },
        {
          "method": "org.eclipse.cdt.internal.core.model.TranslationUnit.buildStructure",
          "source": "Tr anslationUnit.java:400"
        },
        {
          "method": "org.eclipse.cdt.internal.core.model.Openable.generateInfos",
          "source": "Openable.j ava:260"
        },
        {
          "method": "org.eclipse.cdt.internal.core.model.CElement.openWhenClosed",
          "source": "CElement. java:394"
        },
        {
          "method": "org.eclipse.cdt.internal.core.model.TranslationUnit.makeConsistent",
          "source": "Tr anslationUnit.java:518"
        },
        {
          "method": "org.eclipse.cdt.internal.core.model.ReconcileWorkingCopyOperation.executeOperation",
          "source": "ReconcileWorkingCopyOperation.java:60"
        },
        {
          "method": "org.eclipse.cdt.internal.core.model.CModelOperation.execute",
          "source": "CModelOpe ration.java:342"
        },
        {
          "method": "org.eclipse.cdt.internal.core.model.CModelOperation.run",
          "source": "CModelOperati on.java:607"
        },
        {
          "method": "org.eclipse.cdt.internal.core.model.CModelOperation.runOperation",
          "source": "CMod elOperation.java:635"
        },
        {
          "method": "org.eclipse.cdt.internal.core.model.WorkingCopy.reconcile",
          "source": "WorkingCopy .java:405"
        },
        {
          "method": "org.eclipse.cdt.internal.ui.text.CReconcilingStrategy.reconcile",
          "source": "CReco ncilingStrategy.java:127"
        },
        {
          "method": "org.eclipse.cdt.internal.ui.text.CReconcilingStrategy.initialReconcile",
          "source": "CReconcilingStrategy.java:164"
        },
        {
          "method": "org.eclipse.jface.text.reconciler.MonoReconciler.initialProcess",
          "source": "MonoR econciler.java:103"
        },
        {
          "method": "org.eclipse.cdt.internal.ui.text.CReconciler.initialProcess",
          "source": "CReconcil er.java:382"
        },
        {
          "method": "org.eclipse.jface.text.reconciler.AbstractReconciler$BackgroundThread.run",
          "source": "AbstractReconciler.java:170"
        }
      ],
      "number": 0,
      "commentIndex": 0,
      "bugId": "196277",
      "date": "2007-07-12T11:12:14+02:00",
      "product": "CDT",
      "component": "CDT-parser",
      "severity": "major"
    }
  ],
  "groupId": "196277",
  "bugId": "196277",
  "date": "2007-07-12T11:12:14+02:00",
  "product": "CDT",
  "component": "CDT-parser",
  "severity": "major"
}