{
  "comments": [
    "I20070724-0800\n\nNPE when using Show In \u003e ... in Java editor on repository file (old revision from CVS history):\n\n!ENTRY org.eclipse.ui 4 0 2007-07-25 15:25:43.546\n!MESSAGE Unhandled event loop exception\n!STACK 0\norg.eclipse.core.runtime.AssertionFailedException: null argument:\n        at org.eclipse.core.runtime.Assert.isNotNull(Assert.java:84)\n        at org.eclipse.core.runtime.Assert.isNotNull(Assert.java:72)\n        at org.eclipse.jface.viewers.StructuredSelection.\u003cinit\u003e(StructuredSelection.java:66)\n        at org.eclipse.jdt.internal.ui.javaeditor.JavaEditor$6.getSelection(JavaEditor.java:1804)\n        at org.eclipse.jdt.internal.ui.packageview.PackageExplorerPart.show(PackageExplorerPart.java:1338)\n        at org.eclipse.ui.internal.ShowInAction.run(ShowInAction.java:74)\n        at org.eclipse.jface.action.Action.runWithEvent(Action.java:498)\n        at org.eclipse.jface.action.ActionContributionItem.handleWidgetSelection(ActionContributionItem.java:545)\n        at org.eclipse.jface.action.ActionContributionItem.access$2(ActionContributionItem.java:490)\n        at org.eclipse.jface.action.ActionContributionItem$5.handleEvent(ActionContributionItem.java:402)\n        at org.eclipse.swt.widgets.EventTable.sendEvent(EventTable.java:66)\n        at org.eclipse.swt.widgets.Widget.sendEvent(Widget.java:938)\n        at org.eclipse.swt.widgets.Display.runDeferredEvents(Display.java:3688)\n        at org.eclipse.swt.widgets.Display.readAndDispatch(Display.java:3299)\n        at org.eclipse.ui.internal.Workbench.runEventLoop(Workbench.java:2389)\n        at org.eclipse.ui.internal.Workbench.runUI(Workbench.java:2353)\n        at org.eclipse.ui.internal.Workbench.access$4(Workbench.java:2219)\n        at org.eclipse.ui.internal.Workbench$4.run(Workbench.java:466)\n        at org.eclipse.core.databinding.observable.Realm.runWithDefault(Realm.java:289)\n        at org.eclipse.ui.internal.Workbench.createAndRunWorkbench(Workbench.java:461)\n        at org.eclipse.ui.PlatformUI.createAndRunWorkbench(PlatformUI.java:149)\n        at org.eclipse.ui.internal.ide.application.IDEApplication.start(IDEApplication.java:106)\n        at org.eclipse.equinox.internal.app.EclipseAppHandle.run(EclipseAppHandle.java:169)\n        at org.eclipse.core.runtime.internal.adaptor.EclipseAppLauncher.runApplication(EclipseAppLauncher.java:106)\n        at org.eclipse.core.runtime.internal.adaptor.EclipseAppLauncher.start(EclipseAppLauncher.java:76)\n        at org.eclipse.core.runtime.adaptor.EclipseStarter.run(EclipseStarter.java:363)\n        at org.eclipse.core.runtime.adaptor.EclipseStarter.run(EclipseStarter.java:176)\n        at sun.reflect.NativeMethodAccessorImpl.invoke0(Native Method)\n        at sun.reflect.NativeMethodAccessorImpl.invoke(NativeMethodAccessorImpl.java:39)\n        at sun.reflect.DelegatingMethodAccessorImpl.invoke(DelegatingMethodAccessorImpl.java:25)\n        at java.lang.reflect.Method.invoke(Method.java:597)\n        at org.eclipse.equinox.launcher.Main.invokeFramework(Main.java:508)\n        at org.eclipse.equinox.launcher.Main.basicRun(Main.java:447)\n        at org.eclipse.equinox.launcher.Main.run(Main.java:1173)\n        at org.eclipse.equinox.launcher.Main.main(Main.java:1148)",
    "Nicest solution would have been to not show \u0027Package Explorer\u0027 in the Show In list but that\u0027s not possible as this is contributed from outside via XML.\n\nBesides the AFE which has been introduced with 3.3, Show In \u003e Outline which worked in 3.2 also got broken.\n\nWe need to fix this for 3.3.1.",
    "Fixed in HEAD.\nAvailable in builds \u003e N20070725-0010.",
    "Fixed in R3_3_maintenance."
  ],
  "commentCreationDates": [
    "2007-07-25T15:34:03+02:00",
    "2007-07-25T17:52:19+02:00",
    "2007-07-25T17:55:19+02:00",
    "2007-07-26T15:14:27+02:00"
  ],
  "traces": [
    {
      "exceptionType": "org.eclipse.core.runtime.AssertionFailedException",
      "message": "null argument:",
      "elements": [
        {
          "method": "org.eclipse.core.runtime.Assert.isNotNull",
          "source": "Assert.java:84"
        },
        {
          "method": "org.eclipse.core.runtime.Assert.isNotNull",
          "source": "Assert.java:72"
        },
        {
          "method": "org.eclipse.jface.viewers.StructuredSelection.\u003cinit\u003e",
          "source": "StructuredSelection.java:66"
        },
        {
          "method": "org.eclipse.jdt.internal.ui.javaeditor.JavaEditor$6.getSelection",
          "source": "JavaEditor.java:1804"
        },
        {
          "method": "org.eclipse.jdt.internal.ui.packageview.PackageExplorerPart.show",
          "source": "PackageExplorerPart.java:1338"
        },
        {
          "method": "org.eclipse.ui.internal.ShowInAction.run",
          "source": "ShowInAction.java:74"
        },
        {
          "method": "org.eclipse.jface.action.Action.runWithEvent",
          "source": "Action.java:498"
        },
        {
          "method": "org.eclipse.jface.action.ActionContributionItem.handleWidgetSelection",
          "source": "ActionContributionItem.java:545"
        },
        {
          "method": "org.eclipse.jface.action.ActionContributionItem.access$2",
          "source": "ActionContributionItem.java:490"
        },
        {
          "method": "org.eclipse.jface.action.ActionContributionItem$5.handleEvent",
          "source": "ActionContributionItem.java:402"
        },
        {
          "method": "org.eclipse.swt.widgets.EventTable.sendEvent",
          "source": "EventTable.java:66"
        },
        {
          "method": "org.eclipse.swt.widgets.Widget.sendEvent",
          "source": "Widget.java:938"
        },
        {
          "method": "org.eclipse.swt.widgets.Display.runDeferredEvents",
          "source": "Display.java:3688"
        },
        {
          "method": "org.eclipse.swt.widgets.Display.readAndDispatch",
          "source": "Display.java:3299"
        },
        {
          "method": "org.eclipse.ui.internal.Workbench.runEventLoop",
          "source": "Workbench.java:2389"
        },
        {
          "method": "org.eclipse.ui.internal.Workbench.runUI",
          "source": "Workbench.java:2353"
        },
        {
          "method": "org.eclipse.ui.internal.Workbench.access$4",
          "source": "Workbench.java:2219"
        },
        {
          "method": "org.eclipse.ui.internal.Workbench$4.run",
          "source": "Workbench.java:466"
        },
        {
          "method": "org.eclipse.core.databinding.observable.Realm.runWithDefault",
          "source": "Realm.java:289"
        },
        {
          "method": "org.eclipse.ui.internal.Workbench.createAndRunWorkbench",
          "source": "Workbench.java:461"
        },
        {
          "method": "org.eclipse.ui.PlatformUI.createAndRunWorkbench",
          "source": "PlatformUI.java:149"
        },
        {
          "method": "org.eclipse.ui.internal.ide.application.IDEApplication.start",
          "source": "IDEApplication.java:106"
        },
        {
          "method": "org.eclipse.equinox.internal.app.EclipseAppHandle.run",
          "source": "EclipseAppHandle.java:169"
        },
        {
          "method": "org.eclipse.core.runtime.internal.adaptor.EclipseAppLauncher.runApplication",
          "source": "EclipseAppLauncher.java:106"
        },
        {
          "method": "org.eclipse.core.runtime.internal.adaptor.EclipseAppLauncher.start",
          "source": "EclipseAppLauncher.java:76"
        },
        {
          "method": "org.eclipse.core.runtime.adaptor.EclipseStarter.run",
          "source": "EclipseStarter.java:363"
        },
        {
          "method": "org.eclipse.core.runtime.adaptor.EclipseStarter.run",
          "source": "EclipseStarter.java:176"
        },
        {
          "method": "sun.reflect.NativeMethodAccessorImpl.invoke0",
          "source": "Native Method"
        },
        {
          "method": "sun.reflect.NativeMethodAccessorImpl.invoke",
          "source": "NativeMethodAccessorImpl.java:39"
        },
        {
          "method": "sun.reflect.DelegatingMethodAccessorImpl.invoke",
          "source": "DelegatingMethodAccessorImpl.java:25"
        },
        {
          "method": "java.lang.reflect.Method.invoke",
          "source": "Method.java:597"
        },
        {
          "method": "org.eclipse.equinox.launcher.Main.invokeFramework",
          "source": "Main.java:508"
        },
        {
          "method": "org.eclipse.equinox.launcher.Main.basicRun",
          "source": "Main.java:447"
        },
        {
          "method": "org.eclipse.equinox.launcher.Main.run",
          "source": "Main.java:1173"
        },
        {
          "method": "org.eclipse.equinox.launcher.Main.main",
          "source": "Main.java:1148"
        }
      ],
      "number": 0,
      "commentIndex": 0,
      "bugId": "197791",
      "date": "2007-07-25T15:34:03+02:00",
      "product": "JDT",
      "component": "Text",
      "severity": "normal"
    }
  ],
  "groupId": "197791",
  "bugId": "197791",
  "date": "2007-07-25T15:34:03+02:00",
  "product": "JDT",
  "component": "Text",
  "severity": "normal"
}