{
  "comments": [
    "Created an attachment (id\u003d75097)\nThe report design that caused the problem\n\nHi,\n\nI have a report with a bar chart in a group header. Preview and export to html is fine, but whenever I try to export it to pdf I get a NullPointerException (Stacktrace attached below).\n\nIf I remove the chart the export works.\n\nIt does not seem to be a general problem  of my environment, since I have other reports containing a bar chart that work. I tried using the eclipse Designer/Built in webviewer (pressing the \"Print report as PDF\"-Button) and standalone reporting engine, both with the same result.\n\nRegards,\nStefan\n\n\n31.07.2007 17:59:14 org.eclipse.birt.data.engine.impl.QueryResults close\nFEIN: QueryResults is closed\n31.07.2007 17:59:14 org.eclipse.birt.report.engine.api.impl.RunAndRenderTask doRun\nSCHWERWIEGEND: An error happened while running the report. Cause:\njava.lang.NullPointerException\n        at org.eclipse.birt.report.engine.internal.executor.dom.DOMReportItemExecutor.execute(DOMReportItemExecutor.java:39)\n        at org.eclipse.birt.report.engine.layout.content.ListContainerExecutor$ExecutorList.getNextChild(ListContainerExecutor.java:85)\n        at org.eclipse.birt.report.engine.layout.content.BlockStackingExecutor.getNextChild(BlockStackingExecutor.java:45)\n        at org.eclipse.birt.report.engine.layout.pdf.PDFBlockStackingLM.traverseChildren(PDFBlockStackingLM.java:86)\n        at org.eclipse.birt.report.engine.layout.pdf.PDFListLM.traverseChildren(PDFListLM.java:110)\n        at org.eclipse.birt.report.engine.layout.pdf.PDFStackingLM.layoutChildren(PDFStackingLM.java:118)\n        at org.eclipse.birt.report.engine.layout.pdf.PDFAbstractLM.layout(PDFAbstractLM.java:132)\n        at org.eclipse.birt.report.engine.layout.pdf.PDFBlockStackingLM.layoutChildNode(PDFBlockStackingLM.java:109)\n        at org.eclipse.birt.report.engine.layout.pdf.PDFBlockStackingLM.traverseChildren(PDFBlockStackingLM.java:89)\n        at org.eclipse.birt.report.engine.layout.pdf.PDFStackingLM.layoutChildren(PDFStackingLM.java:118)\n        at org.eclipse.birt.report.engine.layout.pdf.PDFAbstractLM.layout(PDFAbstractLM.java:132)\n        at org.eclipse.birt.report.engine.layout.pdf.PDFRowLM.traverseChildren(PDFRowLM.java:88)\n        at org.eclipse.birt.report.engine.layout.pdf.PDFStackingLM.layoutChildren(PDFStackingLM.java:118)\n        at org.eclipse.birt.report.engine.layout.pdf.PDFAbstractLM.layout(PDFAbstractLM.java:132)\n        at org.eclipse.birt.report.engine.layout.pdf.PDFBlockStackingLM.layoutChildNode(PDFBlockStackingLM.java:109)\n        at org.eclipse.birt.report.engine.layout.pdf.PDFBlockStackingLM.traverseChildren(PDFBlockStackingLM.java:89)\n        at org.eclipse.birt.report.engine.layout.pdf.PDFTableLM.traverseChildren(PDFTableLM.java:108)\n        at org.eclipse.birt.report.engine.layout.pdf.PDFStackingLM.layoutChildren(PDFStackingLM.java:118)\n        at org.eclipse.birt.report.engine.layout.pdf.PDFAbstractLM.layout(PDFAbstractLM.java:132)\n        at org.eclipse.birt.report.engine.layout.pdf.PDFBlockStackingLM.traverseChildren(PDFBlockStackingLM.java:68)\n        at org.eclipse.birt.report.engine.layout.pdf.PDFListLM.traverseChildren(PDFListLM.java:110)\n        at org.eclipse.birt.report.engine.layout.pdf.PDFStackingLM.layoutChildren(PDFStackingLM.java:118)\n        at org.eclipse.birt.report.engine.layout.pdf.PDFAbstractLM.layout(PDFAbstractLM.java:132)\n        at org.eclipse.birt.report.engine.layout.pdf.PDFBlockStackingLM.traverseChildren(PDFBlockStackingLM.java:68)\n        at org.eclipse.birt.report.engine.layout.pdf.PDFStackingLM.layoutChildren(PDFStackingLM.java:118)\n        at org.eclipse.birt.report.engine.layout.pdf.PDFAbstractLM.layout(PDFAbstractLM.java:132)\n        at org.eclipse.birt.report.engine.layout.pdf.PDFRowLM.traverseChildren(PDFRowLM.java:101)\n        at org.eclipse.birt.report.engine.layout.pdf.PDFStackingLM.layoutChildren(PDFStackingLM.java:118)\n        at org.eclipse.birt.report.engine.layout.pdf.PDFAbstractLM.layout(PDFAbstractLM.java:132)\n        at org.eclipse.birt.report.engine.layout.pdf.PDFBlockStackingLM.traverseChildren(PDFBlockStackingLM.java:68)\n        at org.eclipse.birt.report.engine.layout.pdf.PDFTableLM.traverseChildren(PDFTableLM.java:108)\n        at org.eclipse.birt.report.engine.layout.pdf.PDFStackingLM.layoutChildren(PDFStackingLM.java:118)\n        at org.eclipse.birt.report.engine.layout.pdf.PDFAbstractLM.layout(PDFAbstractLM.java:132)\n        at org.eclipse.birt.report.engine.layout.pdf.PDFBlockStackingLM.traverseChildren(PDFBlockStackingLM.java:68)\n        at org.eclipse.birt.report.engine.layout.pdf.PDFStackingLM.layoutChildren(PDFStackingLM.java:118)\n        at org.eclipse.birt.report.engine.layout.pdf.PDFPageLM.layout(PDFPageLM.java:212)\n        at org.eclipse.birt.report.engine.layout.pdf.PDFReportLayoutEngine.layoutReport(PDFReportLayoutEngine.java:64)\n        at org.eclipse.birt.report.engine.layout.pdf.PDFReportLayoutEngine.layout(PDFReportLayoutEngine.java:87)\n        at org.eclipse.birt.report.engine.api.impl.RunAndRenderTask.doRun(RunAndRenderTask.java:148)\n        at org.eclipse.birt.report.engine.api.impl.RunAndRenderTask.run(RunAndRenderTask.java:71)\n        at ExecuteReport.executeReport(ExecuteReport.java:107)\n        at ExecuteReport.main(ExecuteReport.java:119)",
    "Sorry for the double post\n\n*** This bug has been marked as a duplicate of bug 198479 ***",
    "Double Post"
  ],
  "commentCreationDates": [
    "2007-08-01T08:04:05+02:00",
    "2007-08-01T08:08:44+02:00",
    "2007-08-01T08:12:50+02:00"
  ],
  "traces": [
    {
      "exceptionType": "java.lang.NullPointerException",
      "elements": [
        {
          "method": "org.eclipse.birt.report.engine.internal.executor.dom.DOMReportItemExecutor.execute",
          "source": "DOMReportItemExecutor.java:39"
        },
        {
          "method": "org.eclipse.birt.report.engine.layout.content.ListContainerExecutor$ExecutorList.getNextChild",
          "source": "ListContainerExecutor.java:85"
        },
        {
          "method": "org.eclipse.birt.report.engine.layout.content.BlockStackingExecutor.getNextChild",
          "source": "BlockStackingExecutor.java:45"
        },
        {
          "method": "org.eclipse.birt.report.engine.layout.pdf.PDFBlockStackingLM.traverseChildren",
          "source": "PDFBlockStackingLM.java:86"
        },
        {
          "method": "org.eclipse.birt.report.engine.layout.pdf.PDFListLM.traverseChildren",
          "source": "PDFListLM.java:110"
        },
        {
          "method": "org.eclipse.birt.report.engine.layout.pdf.PDFStackingLM.layoutChildren",
          "source": "PDFStackingLM.java:118"
        },
        {
          "method": "org.eclipse.birt.report.engine.layout.pdf.PDFAbstractLM.layout",
          "source": "PDFAbstractLM.java:132"
        },
        {
          "method": "org.eclipse.birt.report.engine.layout.pdf.PDFBlockStackingLM.layoutChildNode",
          "source": "PDFBlockStackingLM.java:109"
        },
        {
          "method": "org.eclipse.birt.report.engine.layout.pdf.PDFBlockStackingLM.traverseChildren",
          "source": "PDFBlockStackingLM.java:89"
        },
        {
          "method": "org.eclipse.birt.report.engine.layout.pdf.PDFStackingLM.layoutChildren",
          "source": "PDFStackingLM.java:118"
        },
        {
          "method": "org.eclipse.birt.report.engine.layout.pdf.PDFAbstractLM.layout",
          "source": "PDFAbstractLM.java:132"
        },
        {
          "method": "org.eclipse.birt.report.engine.layout.pdf.PDFRowLM.traverseChildren",
          "source": "PDFRowLM.java:88"
        },
        {
          "method": "org.eclipse.birt.report.engine.layout.pdf.PDFStackingLM.layoutChildren",
          "source": "PDFStackingLM.java:118"
        },
        {
          "method": "org.eclipse.birt.report.engine.layout.pdf.PDFAbstractLM.layout",
          "source": "PDFAbstractLM.java:132"
        },
        {
          "method": "org.eclipse.birt.report.engine.layout.pdf.PDFBlockStackingLM.layoutChildNode",
          "source": "PDFBlockStackingLM.java:109"
        },
        {
          "method": "org.eclipse.birt.report.engine.layout.pdf.PDFBlockStackingLM.traverseChildren",
          "source": "PDFBlockStackingLM.java:89"
        },
        {
          "method": "org.eclipse.birt.report.engine.layout.pdf.PDFTableLM.traverseChildren",
          "source": "PDFTableLM.java:108"
        },
        {
          "method": "org.eclipse.birt.report.engine.layout.pdf.PDFStackingLM.layoutChildren",
          "source": "PDFStackingLM.java:118"
        },
        {
          "method": "org.eclipse.birt.report.engine.layout.pdf.PDFAbstractLM.layout",
          "source": "PDFAbstractLM.java:132"
        },
        {
          "method": "org.eclipse.birt.report.engine.layout.pdf.PDFBlockStackingLM.traverseChildren",
          "source": "PDFBlockStackingLM.java:68"
        },
        {
          "method": "org.eclipse.birt.report.engine.layout.pdf.PDFListLM.traverseChildren",
          "source": "PDFListLM.java:110"
        },
        {
          "method": "org.eclipse.birt.report.engine.layout.pdf.PDFStackingLM.layoutChildren",
          "source": "PDFStackingLM.java:118"
        },
        {
          "method": "org.eclipse.birt.report.engine.layout.pdf.PDFAbstractLM.layout",
          "source": "PDFAbstractLM.java:132"
        },
        {
          "method": "org.eclipse.birt.report.engine.layout.pdf.PDFBlockStackingLM.traverseChildren",
          "source": "PDFBlockStackingLM.java:68"
        },
        {
          "method": "org.eclipse.birt.report.engine.layout.pdf.PDFStackingLM.layoutChildren",
          "source": "PDFStackingLM.java:118"
        },
        {
          "method": "org.eclipse.birt.report.engine.layout.pdf.PDFAbstractLM.layout",
          "source": "PDFAbstractLM.java:132"
        },
        {
          "method": "org.eclipse.birt.report.engine.layout.pdf.PDFRowLM.traverseChildren",
          "source": "PDFRowLM.java:101"
        },
        {
          "method": "org.eclipse.birt.report.engine.layout.pdf.PDFStackingLM.layoutChildren",
          "source": "PDFStackingLM.java:118"
        },
        {
          "method": "org.eclipse.birt.report.engine.layout.pdf.PDFAbstractLM.layout",
          "source": "PDFAbstractLM.java:132"
        },
        {
          "method": "org.eclipse.birt.report.engine.layout.pdf.PDFBlockStackingLM.traverseChildren",
          "source": "PDFBlockStackingLM.java:68"
        },
        {
          "method": "org.eclipse.birt.report.engine.layout.pdf.PDFTableLM.traverseChildren",
          "source": "PDFTableLM.java:108"
        },
        {
          "method": "org.eclipse.birt.report.engine.layout.pdf.PDFStackingLM.layoutChildren",
          "source": "PDFStackingLM.java:118"
        },
        {
          "method": "org.eclipse.birt.report.engine.layout.pdf.PDFAbstractLM.layout",
          "source": "PDFAbstractLM.java:132"
        },
        {
          "method": "org.eclipse.birt.report.engine.layout.pdf.PDFBlockStackingLM.traverseChildren",
          "source": "PDFBlockStackingLM.java:68"
        },
        {
          "method": "org.eclipse.birt.report.engine.layout.pdf.PDFStackingLM.layoutChildren",
          "source": "PDFStackingLM.java:118"
        },
        {
          "method": "org.eclipse.birt.report.engine.layout.pdf.PDFPageLM.layout",
          "source": "PDFPageLM.java:212"
        },
        {
          "method": "org.eclipse.birt.report.engine.layout.pdf.PDFReportLayoutEngine.layoutReport",
          "source": "PDFReportLayoutEngine.java:64"
        },
        {
          "method": "org.eclipse.birt.report.engine.layout.pdf.PDFReportLayoutEngine.layout",
          "source": "PDFReportLayoutEngine.java:87"
        },
        {
          "method": "org.eclipse.birt.report.engine.api.impl.RunAndRenderTask.doRun",
          "source": "RunAndRenderTask.java:148"
        },
        {
          "method": "org.eclipse.birt.report.engine.api.impl.RunAndRenderTask.run",
          "source": "RunAndRenderTask.java:71"
        },
        {
          "method": "ExecuteReport.executeReport",
          "source": "ExecuteReport.java:107"
        },
        {
          "method": "ExecuteReport.main",
          "source": "ExecuteReport.java:119"
        }
      ],
      "number": 0,
      "commentIndex": 0,
      "bugId": "198480",
      "duplicateId": "198479",
      "date": "2007-08-01T08:04:05+02:00",
      "product": "BIRT",
      "component": "Report",
      "severity": "major"
    }
  ],
  "groupId": "198479",
  "bugId": "198480",
  "duplicateId": "198479",
  "date": "2007-08-01T08:04:05+02:00",
  "product": "BIRT",
  "component": "Report",
  "severity": "major"
}