{
  "comments": [
    "Received the following error message when bringing up Report Viewing GUI using the interim build - Aperi-R04-070802-233101.zip (replaces rhinojs.jar with js.jar, updates gui) \n\nAug 7, 2007 11:39:05 AM org.mortbay.jetty.servlet.ServletHandler handle\nSEVERE: /aperi-reports/TreeControl?action\u003dgetChildren\u0026data\u003d%7B%22node%22%3A%7B%2\n2widgetId%22%3A%22Root%20Node%22%2C%22objectId%22%3A%22%22%2C%22index%22%3A0%7D%\n2C%22tree%22%3A%7B%22widgetId%22%3A%22navTree%22%2C%22objectId%22%3A%22%22%7D%7D\n\u0026dojo.preventCache\u003d1186511945328:\njava.lang.RuntimeException: Check the JDBC configuration in web.xml\n        at org.eclipse.aperi.reporting.ReportManager.getReportManager(ReportMana\nger.java:65)\n        at org.eclipse.aperi.reporting.Directory2JSON.repository2JSON(Directory2\nJSON.java:27)\n        at org.eclipse.aperi.reporting.TreeControl.doPost(TreeControl.java:51)\n        at org.eclipse.aperi.reporting.TreeControl.doGet(TreeControl.java:37)\n        at javax.servlet.http.HttpServlet.service(HttpServlet.java:596)\n        at javax.servlet.http.HttpServlet.service(HttpServlet.java:689)\n        at org.mortbay.jetty.servlet.ServletHolder.handle(ServletHolder.java:428\n)\n        at org.mortbay.jetty.servlet.WebApplicationHandler.dispatch(WebApplicati\nonHandler.java:473)\n        at org.mortbay.jetty.servlet.ServletHandler.handle(ServletHandler.java:5\n68)\n        at org.mortbay.http.HttpContext.handle(HttpContext.java:1530)\n        at org.mortbay.jetty.servlet.WebApplicationContext.handle(WebApplication\nContext.java:633)\n        at org.mortbay.http.HttpContext.handle(HttpContext.java:1482)\n        at org.mortbay.http.HttpServer.service(HttpServer.java:909)\n        at org.mortbay.http.HttpConnection.service(HttpConnection.java:820)\n        at org.mortbay.http.HttpConnection.handleNext(HttpConnection.java:986)\n        at org.mortbay.http.HttpConnection.handle(HttpConnection.java:837)\n        at org.mortbay.http.SocketListener.handleConnection(SocketListener.java:\n245)\n        at org.mortbay.util.ThreadedServer.handle(ThreadedServer.java:357)\n        at org.mortbay.util.ThreadPool$PoolThread.run(ThreadPool.java:534)\nCaused by: javax.crypto.IllegalBlockSizeException: Input length must be multiple\n of 8 when decrypting with padded cipher\n        at com.sun.crypto.provider.SunJCE_h.b(DashoA12275)\n        at com.sun.crypto.provider.SunJCE_h.b(DashoA12275)\n        at com.sun.crypto.provider.SunJCE_ae.b(DashoA12275)\n        at com.sun.crypto.provider.PBEWithMD5AndDESCipher.engineDoFinal(DashoA12\n275)\n        at javax.crypto.Cipher.doFinal(DashoA12275)\n        at org.eclipse.aperi.util.SRMCrypto.decrypt(SRMCrypto.java:78)\n        at org.eclipse.aperi.reporting.ReportManager.getReportManager(ReportMana\nger.java:62)\n        ... 18 more",
    "Workaround:\n\nedit the web.xml file in \u003cAperi-install-dir\u003e\\plugins\\org.eclipse.aperi.reporting_5.0.0\\web\\aperi-reports\\WEB-INF\n\nand correct the pre-set jdbc-password \"YXBlcmk\u003d\" \n\t\u003ccontext-param\u003e\n\t\t\u003cparam-name\u003ejdbcPassword\u003c/param-name\u003e\n\t\t\u003cparam-value\u003eYXBlcmk\u003d\u003c/param-value\u003e\n\t\u003c/context-param\u003e\n\nwith the actual one copied from tsnmdbparms.properties file (located in \u003cAperi-install-dir\u003e\\devsvr\\configuration):\ntivoli.sanmgmt.jdbc.dbPassword\u003d\u003cactual-db-password\u003e\n\nThis should be done automatically by the installer, so change the bugzilla component to \"install\"?",
    "Take a look and see if the password update code in the installer is present and working. If its not an installer defect send it back to me...",
    "fixed in next build."
  ],
  "commentCreationDates": [
    "2007-08-07T21:13:26+02:00",
    "2007-08-27T11:15:37+02:00",
    "2007-10-17T17:47:02+02:00",
    "2007-11-05T06:17:52+01:00"
  ],
  "traces": [
    {
      "exceptionType": "java.lang.RuntimeException",
      "message": "Check the JDBC configuration in web.xml",
      "elements": [
        {
          "method": "org.eclipse.aperi.reporting.ReportManager.getReportManager",
          "source": "ReportMana ger.java:65"
        },
        {
          "method": "org.eclipse.aperi.reporting.Directory2JSON.repository2JSON",
          "source": "Directory2 JSON.java:27"
        },
        {
          "method": "org.eclipse.aperi.reporting.TreeControl.doPost",
          "source": "TreeControl.java:51"
        },
        {
          "method": "org.eclipse.aperi.reporting.TreeControl.doGet",
          "source": "TreeControl.java:37"
        },
        {
          "method": "javax.servlet.http.HttpServlet.service",
          "source": "HttpServlet.java:596"
        },
        {
          "method": "javax.servlet.http.HttpServlet.service",
          "source": "HttpServlet.java:689"
        },
        {
          "method": "org.mortbay.jetty.servlet.ServletHolder.handle",
          "source": "ServletHolder.java:428 "
        },
        {
          "method": "org.mortbay.jetty.servlet.WebApplicationHandler.dispatch",
          "source": "WebApplicati onHandler.java:473"
        },
        {
          "method": "org.mortbay.jetty.servlet.ServletHandler.handle",
          "source": "ServletHandler.java:5 68"
        },
        {
          "method": "org.mortbay.http.HttpContext.handle",
          "source": "HttpContext.java:1530"
        },
        {
          "method": "org.mortbay.jetty.servlet.WebApplicationContext.handle",
          "source": "WebApplication Context.java:633"
        },
        {
          "method": "org.mortbay.http.HttpContext.handle",
          "source": "HttpContext.java:1482"
        },
        {
          "method": "org.mortbay.http.HttpServer.service",
          "source": "HttpServer.java:909"
        },
        {
          "method": "org.mortbay.http.HttpConnection.service",
          "source": "HttpConnection.java:820"
        },
        {
          "method": "org.mortbay.http.HttpConnection.handleNext",
          "source": "HttpConnection.java:986"
        },
        {
          "method": "org.mortbay.http.HttpConnection.handle",
          "source": "HttpConnection.java:837"
        },
        {
          "method": "org.mortbay.http.SocketListener.handleConnection",
          "source": "SocketListener.java: 245"
        },
        {
          "method": "org.mortbay.util.ThreadedServer.handle",
          "source": "ThreadedServer.java:357"
        },
        {
          "method": "org.mortbay.util.ThreadPool$PoolThread.run",
          "source": "ThreadPool.java:534"
        }
      ],
      "causedBy": {
        "exceptionType": "javax.crypto.IllegalBlockSizeException",
        "message": "Input length must be multiple  of 8 when decrypting with padded cipher",
        "elements": [
          {
            "method": "com.sun.crypto.provider.SunJCE_h.b",
            "source": "DashoA12275"
          },
          {
            "method": "com.sun.crypto.provider.SunJCE_h.b",
            "source": "DashoA12275"
          },
          {
            "method": "com.sun.crypto.provider.SunJCE_ae.b",
            "source": "DashoA12275"
          },
          {
            "method": "com.sun.crypto.provider.PBEWithMD5AndDESCipher.engineDoFinal",
            "source": "DashoA12 275"
          },
          {
            "method": "javax.crypto.Cipher.doFinal",
            "source": "DashoA12275"
          },
          {
            "method": "org.eclipse.aperi.util.SRMCrypto.decrypt",
            "source": "SRMCrypto.java:78"
          },
          {
            "method": "org.eclipse.aperi.reporting.ReportManager.getReportManager",
            "source": "ReportMana ger.java:62"
          }
        ],
        "number": 0,
        "commentIndex": 0
      },
      "number": 0,
      "commentIndex": 0,
      "bugId": "199148",
      "date": "2007-08-07T21:13:26+02:00",
      "product": "Aperi",
      "component": "aperi.reporting",
      "severity": "major"
    }
  ],
  "groupId": "199148",
  "bugId": "199148",
  "date": "2007-08-07T21:13:26+02:00",
  "product": "Aperi",
  "component": "aperi.reporting",
  "severity": "major"
}