{
  "comments": [
    "I20070807-0010\n\nI started my development workspace and opened a few files I\u0027ve checked out from CVS. My QuickDiff provider is the CVS provider. Somehow, I lost my network connection to dev.eclipse.org, so the QuickDiff requests started to time out (but I didn\u0027t realize that). When I missed the QuickDiff information in an editor, I chose Compare With \u003e Latest from HEAD. This opened a dialog \"Progress Information\" with msg \"Processing \u003cpath-to-file\u003e\" and \"Connecting via SSH to dev.eclipse.org\".\n\nAfter a few seconds, I clicked Cancel, which disabled the Cancel button but did not cancel the operation. I had to wait for several minutes until the progress dialog finally disappeared. During this time, I got a new log entry like this about every minute:\n\n!ENTRY org.eclipse.team.cvs.core 4 -29 2007-08-08 11:03:55.656\n!MESSAGE Could not connect to :extssh:mkeller@dev.eclipse.org:/cvsroot/eclipse: CVS communication error: org.eclipse.team.internal.ccvs.ssh2.CVSSSH2Se\nrverConnection$SSH2IOException: A timeout occurred connecting to host dev.eclipse.org\n!STACK 0\norg.eclipse.team.internal.ccvs.ssh2.CVSSSH2ServerConnection$SSH2IOException: A timeout occurred connecting to host dev.eclipse.org\n        at org.eclipse.team.internal.ccvs.ssh2.CVSSSH2ServerConnection.internalOpen(CVSSSH2ServerConnection.java:193)\n        at org.eclipse.team.internal.ccvs.ssh2.CVSSSH2ServerConnection.open(CVSSSH2ServerConnection.java:107)\n        at org.eclipse.team.internal.ccvs.core.connection.Connection.open(Connection.java:132)\n        at org.eclipse.team.internal.ccvs.core.connection.CVSRepositoryLocation.createConnection(CVSRepositoryLocation.java:547)\n        at org.eclipse.team.internal.ccvs.core.connection.CVSRepositoryLocation.openConnection(CVSRepositoryLocation.java:791)\n        at org.eclipse.team.internal.ccvs.core.client.Session.open(Session.java:159)\n        at org.eclipse.team.internal.ccvs.core.resources.RemoteFile.internalFetchContents(RemoteFile.java:215)\n        at org.eclipse.team.internal.ccvs.core.resources.RemoteFile.fetchContents(RemoteFile.java:193)\n        at org.eclipse.team.core.variants.CachedResourceVariant.ensureContentsCached(CachedResourceVariant.java:111)\n        at org.eclipse.team.core.variants.CachedResourceVariant.getStorage(CachedResourceVariant.java:101)\n        at org.eclipse.team.internal.ccvs.core.resources.RemoteFile.getContents(RemoteFile.java:184)\n        at org.eclipse.team.internal.ccvs.ui.RemoteRevisionQuickDiffProvider.readDocument(RemoteRevisionQuickDiffProvider.java:254)\n        at org.eclipse.team.internal.ccvs.ui.RemoteRevisionQuickDiffProvider.getReference(RemoteRevisionQuickDiffProvider.java:131)\n        at org.eclipse.ui.internal.texteditor.quickdiff.DocumentLineDiffer$2.run(DocumentLineDiffer.java:496)\n        at org.eclipse.core.internal.jobs.Worker.run(Worker.java:55)\nCaused by: com.jcraft.jsch.JSchException: Session.connect: java.io.InterruptedIOException: A timeout occurred connecting to host dev.eclipse.org\n        at com.jcraft.jsch.Session.connect(Session.java:494)\n        at com.jcraft.jsch.Session.connect(Session.java:145)\n        at org.eclipse.jsch.internal.core.JSchProvider.connect(JSchProvider.java:52)\n        at org.eclipse.team.internal.ccvs.ssh2.JSchSession.createSession(JSchSession.java:361)\n        at org.eclipse.team.internal.ccvs.ssh2.JSchSession.getSession(JSchSession.java:326)\n        at org.eclipse.team.internal.ccvs.ssh2.CVSSSH2ServerConnection.internalOpen(CVSSSH2ServerConnection.java:122)\n        ... 14 more\n\n\n-------------------------------------------------\nHere\u0027s a stack trace taken while the blocking progress dialog was up:\n\nFull thread dump Java HotSpot(TM) Client VM (1.6.0_02-b06 mixed mode):\n\n\"Thread-64\" prio\u003d6 tid\u003d0x1c1b5400 nid\u003d0x91c runnable [0x1dd5f000..0x1dd5fd14]\n   java.lang.Thread.State: RUNNABLE\n        at java.net.PlainSocketImpl.$$YJP$$socketConnect(Native Method)\n        at java.net.PlainSocketImpl.socketConnect(PlainSocketImpl.java)\n        at java.net.PlainSocketImpl.doConnect(PlainSocketImpl.java:333)\n        - locked \u003c0x1289c740\u003e (a java.net.PlainSocketImpl)\n        at java.net.PlainSocketImpl.connectToAddress(PlainSocketImpl.java:195)\n        at java.net.PlainSocketImpl.connect(PlainSocketImpl.java:182)\n        at java.net.Socket.connect(Socket.java:518)\n        at org.eclipse.jsch.internal.core.ResponsiveSocketFactory.internalCreateSocket(ResponsiveSocketFactory.java:146)\n        at org.eclipse.jsch.internal.core.ResponsiveSocketFactory$1.run(ResponsiveSocketFactory.java:72)\n        at java.lang.Thread.run(Thread.java:619)\n\n\"Thread-63\" prio\u003d6 tid\u003d0x1af25400 nid\u003d0x120c runnable [0x1dcdf000..0x1dcdfd94]\n   java.lang.Thread.State: RUNNABLE\n        at java.net.PlainSocketImpl.$$YJP$$socketConnect(Native Method)\n        at java.net.PlainSocketImpl.socketConnect(PlainSocketImpl.java)\n        at java.net.PlainSocketImpl.doConnect(PlainSocketImpl.java:333)\n        - locked \u003c0x1289c8d8\u003e (a java.net.PlainSocketImpl)\n        at java.net.PlainSocketImpl.connectToAddress(PlainSocketImpl.java:195)\n        at java.net.PlainSocketImpl.connect(PlainSocketImpl.java:182)\n        at java.net.Socket.connect(Socket.java:518)\n        at org.eclipse.jsch.internal.core.ResponsiveSocketFactory.internalCreateSocket(ResponsiveSocketFactory.java:146)\n        at org.eclipse.jsch.internal.core.ResponsiveSocketFactory$1.run(ResponsiveSocketFactory.java:72)\n        at java.lang.Thread.run(Thread.java:619)\n\n\"Thread-62\" prio\u003d6 tid\u003d0x1c785c00 nid\u003d0x1064 runnable [0x2171f000..0x2171fa14]\n   java.lang.Thread.State: RUNNABLE\n        at java.net.PlainSocketImpl.$$YJP$$socketConnect(Native Method)\n        at java.net.PlainSocketImpl.socketConnect(PlainSocketImpl.java)\n        at java.net.PlainSocketImpl.doConnect(PlainSocketImpl.java:333)\n        - locked \u003c0x1289ca70\u003e (a java.net.PlainSocketImpl)\n        at java.net.PlainSocketImpl.connectToAddress(PlainSocketImpl.java:195)\n        at java.net.PlainSocketImpl.connect(PlainSocketImpl.java:182)\n        at java.net.Socket.connect(Socket.java:518)\n        at org.eclipse.jsch.internal.core.ResponsiveSocketFactory.internalCreateSocket(ResponsiveSocketFactory.java:146)\n        at org.eclipse.jsch.internal.core.ResponsiveSocketFactory$1.run(ResponsiveSocketFactory.java:72)\n        at java.lang.Thread.run(Thread.java:619)\n\n\"Thread-61\" prio\u003d6 tid\u003d0x1c785400 nid\u003d0xdd4 runnable [0x1f92f000..0x1f92fa94]\n   java.lang.Thread.State: RUNNABLE\n        at java.net.PlainSocketImpl.$$YJP$$socketConnect(Native Method)\n        at java.net.PlainSocketImpl.socketConnect(PlainSocketImpl.java)\n        at java.net.PlainSocketImpl.doConnect(PlainSocketImpl.java:333)\n        - locked \u003c0x12898b60\u003e (a java.net.PlainSocketImpl)\n        at java.net.PlainSocketImpl.connectToAddress(PlainSocketImpl.java:195)\n        at java.net.PlainSocketImpl.connect(PlainSocketImpl.java:182)\n        at java.net.Socket.connect(Socket.java:518)\n        at org.eclipse.jsch.internal.core.ResponsiveSocketFactory.internalCreateSocket(ResponsiveSocketFactory.java:146)\n        at org.eclipse.jsch.internal.core.ResponsiveSocketFactory$1.run(ResponsiveSocketFactory.java:72)\n        at java.lang.Thread.run(Thread.java:619)\n\n\"Thread-60\" prio\u003d6 tid\u003d0x1cad6400 nid\u003d0x1e74 runnable [0x1df3f000..0x1df3fb14]\n   java.lang.Thread.State: RUNNABLE\n        at java.net.PlainSocketImpl.$$YJP$$socketConnect(Native Method)\n        at java.net.PlainSocketImpl.socketConnect(PlainSocketImpl.java)\n        at java.net.PlainSocketImpl.doConnect(PlainSocketImpl.java:333)\n        - locked \u003c0x12898d00\u003e (a java.net.PlainSocketImpl)\n        at java.net.PlainSocketImpl.connectToAddress(PlainSocketImpl.java:195)\n        at java.net.PlainSocketImpl.connect(PlainSocketImpl.java:182)\n        at java.net.Socket.connect(Socket.java:518)\n        at org.eclipse.jsch.internal.core.ResponsiveSocketFactory.internalCreateSocket(ResponsiveSocketFactory.java:146)\n        at org.eclipse.jsch.internal.core.ResponsiveSocketFactory$1.run(ResponsiveSocketFactory.java:72)\n        at java.lang.Thread.run(Thread.java:619)\n\n\"Thread-59\" prio\u003d6 tid\u003d0x1c78b800 nid\u003d0x13c4 runnable [0x1ffef000..0x1ffefb94]\n   java.lang.Thread.State: RUNNABLE\n        at java.net.PlainSocketImpl.$$YJP$$socketConnect(Native Method)\n        at java.net.PlainSocketImpl.socketConnect(PlainSocketImpl.java)\n        at java.net.PlainSocketImpl.doConnect(PlainSocketImpl.java:333)\n        - locked \u003c0x12898ea0\u003e (a java.net.PlainSocketImpl)\n        at java.net.PlainSocketImpl.connectToAddress(PlainSocketImpl.java:195)\n        at java.net.PlainSocketImpl.connect(PlainSocketImpl.java:182)\n        at java.net.Socket.connect(Socket.java:518)\n        at org.eclipse.jsch.internal.core.ResponsiveSocketFactory.internalCreateSocket(ResponsiveSocketFactory.java:146)\n        at org.eclipse.jsch.internal.core.ResponsiveSocketFactory$1.run(ResponsiveSocketFactory.java:72)\n        at java.lang.Thread.run(Thread.java:619)\n\n\"ModalContext\" prio\u003d6 tid\u003d0x1cbcc400 nid\u003d0x1d84 in Object.wait() [0x1ff9f000..0x1ff9fc14]\n   java.lang.Thread.State: TIMED_WAITING (on object monitor)\n        at java.lang.Object.wait(Native Method)\n        - waiting on \u003c0x1286f3e0\u003e (a org.eclipse.core.internal.jobs.Semaphore)\n        at org.eclipse.core.internal.jobs.Semaphore.acquire(Semaphore.java:38)\n        - locked \u003c0x1286f3e0\u003e (a org.eclipse.core.internal.jobs.Semaphore)\n        at org.eclipse.core.internal.jobs.OrderedLock.doAcquire(OrderedLock.java:169)\n        at org.eclipse.core.internal.jobs.OrderedLock.acquire(OrderedLock.java:105)\n        at org.eclipse.core.internal.jobs.OrderedLock.acquire(OrderedLock.java:82)\n        at org.eclipse.team.internal.ccvs.core.connection.CVSRepositoryLocation.openConnection(CVSRepositoryLocation.java:766)\n        at org.eclipse.team.internal.ccvs.core.client.Session.open(Session.java:159)\n        at org.eclipse.team.internal.ccvs.core.resources.RemoteFolderTreeBuilder.buildTree(RemoteFolderTreeBuilder.java:294)\n        at org.eclipse.team.internal.ccvs.core.resources.RemoteFolderTreeBuilder.buildRemoteTree(RemoteFolderTreeBuilder.java:147)\n        at org.eclipse.team.internal.ccvs.core.resources.CVSWorkspaceRoot.getRemoteTree(CVSWorkspaceRoot.java:171)\n        at org.eclipse.team.internal.ccvs.core.syncinfo.CVSResourceVariantTree.fetchVariant(CVSResourceVariantTree.java:78)\n        at org.eclipse.team.core.variants.AbstractResourceVariantTree.refresh(AbstractResourceVariantTree.java:84)\n        at org.eclipse.team.internal.ccvs.core.syncinfo.CVSResourceVariantTree.refresh(CVSResourceVariantTree.java:334)\n        at org.eclipse.team.core.variants.AbstractResourceVariantTree.refresh(AbstractResourceVariantTree.java:54)\n        at org.eclipse.team.core.variants.ResourceVariantTreeSubscriber.refresh(ResourceVariantTreeSubscriber.java:162)\n        at org.eclipse.team.core.variants.ResourceVariantTreeSubscriber.refresh(ResourceVariantTreeSubscriber.java:126)\n        at org.eclipse.team.internal.ccvs.ui.actions.SyncAction$1.run(SyncAction.java:189)\n        at org.eclipse.jface.operation.ModalContext$ModalContextThread.run(ModalContext.java:113)\n\n\"Thread-58\" prio\u003d6 tid\u003d0x1c78c400 nid\u003d0x1ee4 runnable [0x1ff4f000..0x1ff4fd14]\n   java.lang.Thread.State: RUNNABLE\n        at java.net.PlainSocketImpl.$$YJP$$socketConnect(Native Method)\n        at java.net.PlainSocketImpl.socketConnect(PlainSocketImpl.java)\n        at java.net.PlainSocketImpl.doConnect(PlainSocketImpl.java:333)\n        - locked \u003c0x1283c040\u003e (a java.net.PlainSocketImpl)\n        at java.net.PlainSocketImpl.connectToAddress(PlainSocketImpl.java:195)\n        at java.net.PlainSocketImpl.connect(PlainSocketImpl.java:182)\n        at java.net.Socket.connect(Socket.java:518)\n        at org.eclipse.jsch.internal.core.ResponsiveSocketFactory.internalCreateSocket(ResponsiveSocketFactory.java:146)\n        at org.eclipse.jsch.internal.core.ResponsiveSocketFactory$1.run(ResponsiveSocketFactory.java:72)\n        at java.lang.Thread.run(Thread.java:619)\n\n\"org.eclipse.jdt.internal.ui.text.JavaReconciler\" daemon prio\u003d2 tid\u003d0x1c1b7000 nid\u003d0x13bc in Object.wait() [0x1ddff000..0x1ddffc94]\n   java.lang.Thread.State: TIMED_WAITING (on object monitor)\n        at java.lang.Object.wait(Native Method)\n        - waiting on \u003c0x122f43a0\u003e (a org.eclipse.jface.text.reconciler.DirtyRegionQueue)\n        at org.eclipse.jface.text.reconciler.AbstractReconciler$BackgroundThread.run(AbstractReconciler.java:176)\n        - locked \u003c0x122f43a0\u003e (a org.eclipse.jface.text.reconciler.DirtyRegionQueue)\n\n\"Worker-19\" prio\u003d6 tid\u003d0x1c61f400 nid\u003d0x10c4 in Object.wait() [0x1feff000..0x1feffa94]\n   java.lang.Thread.State: TIMED_WAITING (on object monitor)\n        at java.lang.Object.wait(Native Method)\n        - waiting on \u003c0x0b1baf68\u003e (a org.eclipse.core.internal.jobs.WorkerPool)\n        at org.eclipse.core.internal.jobs.WorkerPool.sleep(WorkerPool.java:185)\n        - locked \u003c0x0b1baf68\u003e (a org.eclipse.core.internal.jobs.WorkerPool)\n        at org.eclipse.core.internal.jobs.WorkerPool.startJob(WorkerPool.java:217)\n        at org.eclipse.core.internal.jobs.Worker.run(Worker.java:51)\n\n\"Thread-51\" prio\u003d6 tid\u003d0x1cba0400 nid\u003d0x1e7c runnable [0x1feaf000..0x1feafa14]\n   java.lang.Thread.State: RUNNABLE\n        at java.net.PlainSocketImpl.$$YJP$$socketConnect(Native Method)\n        at java.net.PlainSocketImpl.socketConnect(PlainSocketImpl.java)\n        at java.net.PlainSocketImpl.doConnect(PlainSocketImpl.java:333)\n        - locked \u003c0x11b406f8\u003e (a java.net.PlainSocketImpl)\n        at java.net.PlainSocketImpl.connectToAddress(PlainSocketImpl.java:195)\n        at java.net.PlainSocketImpl.connect(PlainSocketImpl.java:182)\n        at java.net.Socket.connect(Socket.java:518)\n        at org.eclipse.jsch.internal.core.ResponsiveSocketFactory.internalCreateSocket(ResponsiveSocketFactory.java:146)\n        at org.eclipse.jsch.internal.core.ResponsiveSocketFactory$1.run(ResponsiveSocketFactory.java:72)\n        at java.lang.Thread.run(Thread.java:619)\n\n\"org.eclipse.jdt.internal.ui.text.JavaReconciler\" daemon prio\u003d2 tid\u003d0x1caec400 nid\u003d0xc84 in Object.wait() [0x1fe5f000..0x1fe5fd94]\n   java.lang.Thread.State: TIMED_WAITING (on object monitor)\n        at java.lang.Object.wait(Native Method)\n        - waiting on \u003c0x11a345a0\u003e (a org.eclipse.jface.text.reconciler.DirtyRegionQueue)\n        at org.eclipse.jface.text.reconciler.AbstractReconciler$BackgroundThread.run(AbstractReconciler.java:176)\n        - locked \u003c0x11a345a0\u003e (a org.eclipse.jface.text.reconciler.DirtyRegionQueue)\n\n\"Thread-43\" prio\u003d6 tid\u003d0x1c68f800 nid\u003d0x1a88 runnable [0x1fdbf000..0x1fdbfb94]\n   java.lang.Thread.State: RUNNABLE\n        at java.net.PlainSocketImpl.$$YJP$$socketConnect(Native Method)\n        at java.net.PlainSocketImpl.socketConnect(PlainSocketImpl.java)\n        at java.net.PlainSocketImpl.doConnect(PlainSocketImpl.java:333)\n        - locked \u003c0x11952320\u003e (a java.net.PlainSocketImpl)\n        at java.net.PlainSocketImpl.connectToAddress(PlainSocketImpl.java:195)\n        at java.net.PlainSocketImpl.connect(PlainSocketImpl.java:182)\n        at java.net.Socket.connect(Socket.java:518)\n        at org.eclipse.jsch.internal.core.ResponsiveSocketFactory.internalCreateSocket(ResponsiveSocketFactory.java:146)\n        at org.eclipse.jsch.internal.core.ResponsiveSocketFactory$1.run(ResponsiveSocketFactory.java:72)\n        at java.lang.Thread.run(Thread.java:619)\n\n\"org.eclipse.jdt.internal.ui.text.JavaReconciler\" daemon prio\u003d2 tid\u003d0x1cb7ac00 nid\u003d0x1814 in Object.wait() [0x1fd6f000..0x1fd6fc14]\n   java.lang.Thread.State: TIMED_WAITING (on object monitor)\n        at java.lang.Object.wait(Native Method)\n        - waiting on \u003c0x11910b90\u003e (a org.eclipse.jface.text.reconciler.DirtyRegionQueue)\n        at org.eclipse.jface.text.reconciler.AbstractReconciler$BackgroundThread.run(AbstractReconciler.java:176)\n        - locked \u003c0x11910b90\u003e (a org.eclipse.jface.text.reconciler.DirtyRegionQueue)\n\n\"Worker-18\" prio\u003d6 tid\u003d0x1cad2400 nid\u003d0x199c in Object.wait() [0x1fcaf000..0x1fcafd94]\n   java.lang.Thread.State: TIMED_WAITING (on object monitor)\n        at java.lang.Object.wait(Native Method)\n        - waiting on \u003c0x1289cc50\u003e (a org.eclipse.core.internal.jobs.Semaphore)\n        at org.eclipse.core.internal.jobs.Semaphore.acquire(Semaphore.java:38)\n        - locked \u003c0x1289cc50\u003e (a org.eclipse.core.internal.jobs.Semaphore)\n        at org.eclipse.core.internal.jobs.OrderedLock.doAcquire(OrderedLock.java:169)\n        at org.eclipse.core.internal.jobs.OrderedLock.acquire(OrderedLock.java:105)\n        at org.eclipse.core.internal.jobs.OrderedLock.acquire(OrderedLock.java:82)\n        at org.eclipse.team.internal.ccvs.core.connection.CVSRepositoryLocation.openConnection(CVSRepositoryLocation.java:766)\n        at org.eclipse.team.internal.ccvs.core.client.Session.open(Session.java:159)\n        at org.eclipse.team.internal.ccvs.core.resources.RemoteFile.getLogEntries(RemoteFile.java:279)\n        at org.eclipse.team.internal.ccvs.core.resources.EclipseFile.getLogEntries(EclipseFile.java:295)\n        at org.eclipse.team.internal.ccvs.core.filehistory.CVSFileHistory.refresh(CVSFileHistory.java:99)\n        at org.eclipse.team.internal.ccvs.ui.CVSHistoryPage$RefreshCVSFileHistory.run(CVSHistoryPage.java:1319)\n        at org.eclipse.core.internal.jobs.Worker.run(Worker.java:55)\n\n\"org.eclipse.jdt.internal.ui.text.JavaReconciler\" daemon prio\u003d2 tid\u003d0x1c67fc00 nid\u003d0x1cc0 in Object.wait() [0x1fc2f000..0x1fc2fb14]\n   java.lang.Thread.State: TIMED_WAITING (on object monitor)\n        at java.lang.Object.wait(Native Method)\n        - waiting on \u003c0x116da720\u003e (a org.eclipse.jface.text.reconciler.DirtyRegionQueue)\n        at org.eclipse.jface.text.reconciler.AbstractReconciler$BackgroundThread.run(AbstractReconciler.java:176)\n        - locked \u003c0x116da720\u003e (a org.eclipse.jface.text.reconciler.DirtyRegionQueue)\n\n\"Worker-17\" prio\u003d6 tid\u003d0x1cacb800 nid\u003d0x18c0 in Object.wait() [0x1fbdf000..0x1fbdfc14]\n   java.lang.Thread.State: TIMED_WAITING (on object monitor)\n        at java.lang.Object.wait(Native Method)\n        - waiting on \u003c0x0b1baf68\u003e (a org.eclipse.core.internal.jobs.WorkerPool)\n        at org.eclipse.core.internal.jobs.WorkerPool.sleep(WorkerPool.java:185)\n        - locked \u003c0x0b1baf68\u003e (a org.eclipse.core.internal.jobs.WorkerPool)\n        at org.eclipse.core.internal.jobs.WorkerPool.startJob(WorkerPool.java:217)\n        at org.eclipse.core.internal.jobs.Worker.run(Worker.java:51)\n\n\"org.eclipse.jdt.internal.ui.text.JavaReconciler\" daemon prio\u003d2 tid\u003d0x1cb67400 nid\u003d0x11d8 in Object.wait() [0x1fb8f000..0x1fb8fd94]\n   java.lang.Thread.State: TIMED_WAITING (on object monitor)\n        at java.lang.Object.wait(Native Method)\n        - waiting on \u003c0x115c8600\u003e (a org.eclipse.jface.text.reconciler.DirtyRegionQueue)\n        at org.eclipse.jface.text.reconciler.AbstractReconciler$BackgroundThread.run(AbstractReconciler.java:176)\n        - locked \u003c0x115c8600\u003e (a org.eclipse.jface.text.reconciler.DirtyRegionQueue)\n\n\"Worker-16\" prio\u003d6 tid\u003d0x1cb5ec00 nid\u003d0x1a68 in Object.wait() [0x1faef000..0x1faefc14]\n   java.lang.Thread.State: TIMED_WAITING (on object monitor)\n        at java.lang.Object.wait(Native Method)\n        - waiting on \u003c0x1289c5d8\u003e (a java.lang.Thread)\n        at java.lang.Thread.join(Thread.java:1151)\n        - locked \u003c0x1289c5d8\u003e (a java.lang.Thread)\n        at org.eclipse.jsch.internal.core.ResponsiveSocketFactory.createSocket(ResponsiveSocketFactory.java:95)\n        at org.eclipse.jsch.internal.core.ResponsiveSocketFactory.createSocket(ResponsiveSocketFactory.java:49)\n        at com.jcraft.jsch.Session.connect(Session.java:191)\n        at com.jcraft.jsch.Session.connect(Session.java:145)\n        at org.eclipse.jsch.internal.core.JSchProvider.connect(JSchProvider.java:52)\n        at org.eclipse.team.internal.ccvs.ssh2.JSchSession.createSession(JSchSession.java:361)\n        at org.eclipse.team.internal.ccvs.ssh2.JSchSession.getSession(JSchSession.java:326)\n        at org.eclipse.team.internal.ccvs.ssh2.CVSSSH2ServerConnection.internalOpen(CVSSSH2ServerConnection.java:122)\n        at org.eclipse.team.internal.ccvs.ssh2.CVSSSH2ServerConnection.open(CVSSSH2ServerConnection.java:107)\n        at org.eclipse.team.internal.ccvs.core.connection.Connection.open(Connection.java:132)\n        at org.eclipse.team.internal.ccvs.core.connection.CVSRepositoryLocation.createConnection(CVSRepositoryLocation.java:547)\n        at org.eclipse.team.internal.ccvs.core.connection.CVSRepositoryLocation.openConnection(CVSRepositoryLocation.java:791)\n        at org.eclipse.team.internal.ccvs.core.client.Session.open(Session.java:159)\n        at org.eclipse.team.internal.ccvs.core.resources.RemoteFile.internalFetchContents(RemoteFile.java:215)\n        at org.eclipse.team.internal.ccvs.core.resources.RemoteFile.fetchContents(RemoteFile.java:193)\n        at org.eclipse.team.core.variants.CachedResourceVariant.ensureContentsCached(CachedResourceVariant.java:111)\n        at org.eclipse.team.core.variants.CachedResourceVariant.getStorage(CachedResourceVariant.java:101)\n        at org.eclipse.team.internal.ccvs.core.resources.RemoteFile.getContents(RemoteFile.java:184)\n        at org.eclipse.team.internal.ccvs.ui.RemoteRevisionQuickDiffProvider.readDocument(RemoteRevisionQuickDiffProvider.java:254)\n        at org.eclipse.team.internal.ccvs.ui.RemoteRevisionQuickDiffProvider.getReference(RemoteRevisionQuickDiffProvider.java:131)\n        at org.eclipse.ui.internal.texteditor.quickdiff.DocumentLineDiffer$2.run(DocumentLineDiffer.java:496)\n        at org.eclipse.core.internal.jobs.Worker.run(Worker.java:55)\n\n\"org.eclipse.jdt.internal.ui.text.JavaReconciler\" daemon prio\u003d2 tid\u003d0x1c68e800 nid\u003d0x144 in Object.wait() [0x1fa9f000..0x1fa9fc94]\n   java.lang.Thread.State: TIMED_WAITING (on object monitor)\n        at java.lang.Object.wait(Native Method)\n        - waiting on \u003c0x11475200\u003e (a org.eclipse.jface.text.reconciler.DirtyRegionQueue)\n        at org.eclipse.jface.text.reconciler.AbstractReconciler$BackgroundThread.run(AbstractReconciler.java:176)\n        - locked \u003c0x11475200\u003e (a org.eclipse.jface.text.reconciler.DirtyRegionQueue)\n\n\"org.eclipse.jdt.internal.ui.text.JavaReconciler\" daemon prio\u003d2 tid\u003d0x1c7a0400 nid\u003d0x13a4 in Object.wait() [0x1f9cf000..0x1f9cfa94]\n   java.lang.Thread.State: TIMED_WAITING (on object monitor)\n        at java.lang.Object.wait(Native Method)\n        - waiting on \u003c0x113b7bd0\u003e (a org.eclipse.jface.text.reconciler.DirtyRegionQueue)\n        at org.eclipse.jface.text.reconciler.AbstractReconciler$BackgroundThread.run(AbstractReconciler.java:176)\n        - locked \u003c0x113b7bd0\u003e (a org.eclipse.jface.text.reconciler.DirtyRegionQueue)\n\n\"Thread-27\" prio\u003d6 tid\u003d0x1c9bf000 nid\u003d0x16e4 runnable [0x1f97f000..0x1f97fc14]\n   java.lang.Thread.State: RUNNABLE\n        at java.net.PlainSocketImpl.$$YJP$$socketConnect(Native Method)\n        at java.net.PlainSocketImpl.socketConnect(PlainSocketImpl.java)\n        at java.net.PlainSocketImpl.doConnect(PlainSocketImpl.java:333)\n        - locked \u003c0x113740b0\u003e (a java.net.PlainSocketImpl)\n        at java.net.PlainSocketImpl.connectToAddress(PlainSocketImpl.java:195)\n        at java.net.PlainSocketImpl.connect(PlainSocketImpl.java:182)\n        at java.net.Socket.connect(Socket.java:518)\n        at org.eclipse.jsch.internal.core.ResponsiveSocketFactory.internalCreateSocket(ResponsiveSocketFactory.java:146)\n        at org.eclipse.jsch.internal.core.ResponsiveSocketFactory$1.run(ResponsiveSocketFactory.java:72)\n        at java.lang.Thread.run(Thread.java:619)\n\n\"org.eclipse.jdt.internal.ui.text.JavaReconciler\" daemon prio\u003d2 tid\u003d0x1ca29800 nid\u003d0x1860 in Object.wait() [0x1f8bf000..0x1f8bfa14]\n   java.lang.Thread.State: TIMED_WAITING (on object monitor)\n        at java.lang.Object.wait(Native Method)\n        - waiting on \u003c0x112b2858\u003e (a org.eclipse.jface.text.reconciler.DirtyRegionQueue)\n        at org.eclipse.jface.text.reconciler.AbstractReconciler$BackgroundThread.run(AbstractReconciler.java:176)\n        - locked \u003c0x112b2858\u003e (a org.eclipse.jface.text.reconciler.DirtyRegionQueue)\n\n\"org.eclipse.jdt.internal.ui.text.JavaReconciler\" daemon prio\u003d2 tid\u003d0x1c878c00 nid\u003d0x1ed0 in Object.wait() [0x1f7bf000..0x1f7bfa14]\n   java.lang.Thread.State: TIMED_WAITING (on object monitor)\n        at java.lang.Object.wait(Native Method)\n        - waiting on \u003c0x11176ce0\u003e (a org.eclipse.jface.text.reconciler.DirtyRegionQueue)\n        at org.eclipse.jface.text.reconciler.AbstractReconciler$BackgroundThread.run(AbstractReconciler.java:176)\n        - locked \u003c0x11176ce0\u003e (a org.eclipse.jface.text.reconciler.DirtyRegionQueue)\n\n\"Worker-13\" prio\u003d6 tid\u003d0x1caa3400 nid\u003d0xb40 in Object.wait() [0x1f75f000..0x1f75fc94]\n   java.lang.Thread.State: TIMED_WAITING (on object monitor)\n        at java.lang.Object.wait(Native Method)\n        - waiting on \u003c0x0b1baf68\u003e (a org.eclipse.core.internal.jobs.WorkerPool)\n        at org.eclipse.core.internal.jobs.WorkerPool.sleep(WorkerPool.java:185)\n        - locked \u003c0x0b1baf68\u003e (a org.eclipse.core.internal.jobs.WorkerPool)\n        at org.eclipse.core.internal.jobs.WorkerPool.startJob(WorkerPool.java:217)\n        at org.eclipse.core.internal.jobs.Worker.run(Worker.java:51)\n\n\"Thread-14\" prio\u003d6 tid\u003d0x1c8c3c00 nid\u003d0xbf4 runnable [0x1de9f000..0x1de9fb14]\n   java.lang.Thread.State: RUNNABLE\n        at java.net.PlainSocketImpl.$$YJP$$socketConnect(Native Method)\n        at java.net.PlainSocketImpl.socketConnect(PlainSocketImpl.java)\n        at java.net.PlainSocketImpl.doConnect(PlainSocketImpl.java:333)\n        - locked \u003c0x1059fbe0\u003e (a java.net.PlainSocketImpl)\n        at java.net.PlainSocketImpl.connectToAddress(PlainSocketImpl.java:195)\n        at java.net.PlainSocketImpl.connect(PlainSocketImpl.java:182)\n        at java.net.Socket.connect(Socket.java:518)\n        at org.eclipse.jsch.internal.core.ResponsiveSocketFactory.internalCreateSocket(ResponsiveSocketFactory.java:146)\n        at org.eclipse.jsch.internal.core.ResponsiveSocketFactory$1.run(ResponsiveSocketFactory.java:72)\n        at java.lang.Thread.run(Thread.java:619)\n\n\"Thread-12\" prio\u003d6 tid\u003d0x1c6b7c00 nid\u003d0x1c50 runnable [0x1d11f000..0x1d11fc94]\n   java.lang.Thread.State: RUNNABLE\n        at java.net.PlainSocketImpl.$$YJP$$socketConnect(Native Method)\n        at java.net.PlainSocketImpl.socketConnect(PlainSocketImpl.java)\n        at java.net.PlainSocketImpl.doConnect(PlainSocketImpl.java:333)\n        - locked \u003c0x104517b0\u003e (a java.net.PlainSocketImpl)\n        at java.net.PlainSocketImpl.connectToAddress(PlainSocketImpl.java:195)\n        at java.net.PlainSocketImpl.connect(PlainSocketImpl.java:182)\n        at java.net.Socket.connect(Socket.java:518)\n        at org.eclipse.jsch.internal.core.ResponsiveSocketFactory.internalCreateSocket(ResponsiveSocketFactory.java:146)\n        at org.eclipse.jsch.internal.core.ResponsiveSocketFactory$1.run(ResponsiveSocketFactory.java:72)\n        at java.lang.Thread.run(Thread.java:619)\n\n\"Thread-11\" prio\u003d6 tid\u003d0x1c205000 nid\u003d0x18a0 runnable [0x1d77f000..0x1d77fd14]\n   java.lang.Thread.State: RUNNABLE\n        at java.net.PlainSocketImpl.$$YJP$$socketConnect(Native Method)\n        at java.net.PlainSocketImpl.socketConnect(PlainSocketImpl.java)\n        at java.net.PlainSocketImpl.doConnect(PlainSocketImpl.java:333)\n        - locked \u003c0x10451948\u003e (a java.net.PlainSocketImpl)\n        at java.net.PlainSocketImpl.connectToAddress(PlainSocketImpl.java:195)\n        at java.net.PlainSocketImpl.connect(PlainSocketImpl.java:182)\n        at java.net.Socket.connect(Socket.java:518)\n        at org.eclipse.jsch.internal.core.ResponsiveSocketFactory.internalCreateSocket(ResponsiveSocketFactory.java:146)\n        at org.eclipse.jsch.internal.core.ResponsiveSocketFactory$1.run(ResponsiveSocketFactory.java:72)\n        at java.lang.Thread.run(Thread.java:619)\n\n\"Thread-8\" prio\u003d6 tid\u003d0x1c7af000 nid\u003d0x19f4 runnable [0x1dfdf000..0x1dfdfa94]\n   java.lang.Thread.State: RUNNABLE\n        at java.net.PlainSocketImpl.$$YJP$$socketConnect(Native Method)\n        at java.net.PlainSocketImpl.socketConnect(PlainSocketImpl.java)\n        at java.net.PlainSocketImpl.doConnect(PlainSocketImpl.java:333)\n        - locked \u003c0x0e4e2f90\u003e (a java.net.PlainSocketImpl)\n        at java.net.PlainSocketImpl.connectToAddress(PlainSocketImpl.java:195)\n        at java.net.PlainSocketImpl.connect(PlainSocketImpl.java:182)\n        at java.net.Socket.connect(Socket.java:518)\n        at org.eclipse.jsch.internal.core.ResponsiveSocketFactory.internalCreateSocket(ResponsiveSocketFactory.java:146)\n        at org.eclipse.jsch.internal.core.ResponsiveSocketFactory$1.run(ResponsiveSocketFactory.java:72)\n        at java.lang.Thread.run(Thread.java:619)\n\n\"YJP-Plugin-RequestListener\" daemon prio\u003d2 tid\u003d0x1c9f3400 nid\u003d0x1e0c runnable [0x1df8f000..0x1df8fb14]\n   java.lang.Thread.State: RUNNABLE\n        at java.net.PlainSocketImpl.$$YJP$$socketAccept(Native Method)\n        at java.net.PlainSocketImpl.socketAccept(PlainSocketImpl.java)\n        at java.net.PlainSocketImpl.accept(PlainSocketImpl.java:384)\n        - locked \u003c0x0de96ab8\u003e (a java.net.SocksSocketImpl)\n        at java.net.ServerSocket.implAccept(ServerSocket.java:453)\n        at java.net.ServerSocket.accept(ServerSocket.java:421)\n        at com.yourkit.b.h$1.run(a:8)\n        at java.lang.Thread.run(Thread.java:619)\n\n\"Worker-11\" prio\u003d6 tid\u003d0x1af48000 nid\u003d0x12f0 in Object.wait() [0x1deef000..0x1deefc14]\n   java.lang.Thread.State: TIMED_WAITING (on object monitor)\n        at java.lang.Object.wait(Native Method)\n        - waiting on \u003c0x0b1baf68\u003e (a org.eclipse.core.internal.jobs.WorkerPool)\n        at org.eclipse.core.internal.jobs.WorkerPool.sleep(WorkerPool.java:185)\n        - locked \u003c0x0b1baf68\u003e (a org.eclipse.core.internal.jobs.WorkerPool)\n        at org.eclipse.core.internal.jobs.WorkerPool.startJob(WorkerPool.java:217)\n        at org.eclipse.core.internal.jobs.Worker.run(Worker.java:51)\n\n\"Worker-9\" prio\u003d6 tid\u003d0x1c9a9400 nid\u003d0x1e3c in Object.wait() [0x1de4f000..0x1de4fd14]\n   java.lang.Thread.State: TIMED_WAITING (on object monitor)\n        at java.lang.Object.wait(Native Method)\n        - waiting on \u003c0x0b1baf68\u003e (a org.eclipse.core.internal.jobs.WorkerPool)\n        at org.eclipse.core.internal.jobs.WorkerPool.sleep(WorkerPool.java:185)\n        - locked \u003c0x0b1baf68\u003e (a org.eclipse.core.internal.jobs.WorkerPool)\n        at org.eclipse.core.internal.jobs.WorkerPool.startJob(WorkerPool.java:217)\n        at org.eclipse.core.internal.jobs.Worker.run(Worker.java:51)\n\n\"org.eclipse.jdt.internal.ui.text.JavaReconciler\" daemon prio\u003d2 tid\u003d0x1c6f1400 nid\u003d0x1b5c in Object.wait() [0x1daef000..0x1daefa94]\n   java.lang.Thread.State: TIMED_WAITING (on object monitor)\n        at java.lang.Object.wait(Native Method)\n        - waiting on \u003c0x0cb9cb98\u003e (a org.eclipse.jface.text.reconciler.DirtyRegionQueue)\n        at org.eclipse.jface.text.reconciler.AbstractReconciler$BackgroundThread.run(AbstractReconciler.java:176)\n        - locked \u003c0x0cb9cb98\u003e (a org.eclipse.jface.text.reconciler.DirtyRegionQueue)\n\n\"org.eclipse.jdt.internal.ui.text.JavaReconciler\" daemon prio\u003d2 tid\u003d0x1c6cc800 nid\u003d0x1bc0 in Object.wait() [0x1bc8f000..0x1bc8fb94]\n   java.lang.Thread.State: TIMED_WAITING (on object monitor)\n        at java.lang.Object.wait(Native Method)\n        - waiting on \u003c0x0c356e90\u003e (a org.eclipse.jface.text.reconciler.DirtyRegionQueue)\n        at org.eclipse.jface.text.reconciler.AbstractReconciler$BackgroundThread.run(AbstractReconciler.java:176)\n        - locked \u003c0x0c356e90\u003e (a org.eclipse.jface.text.reconciler.DirtyRegionQueue)\n\n\"Java indexing\" daemon prio\u003d4 tid\u003d0x1af37800 nid\u003d0x15f4 in Object.wait() [0x1d7cf000..0x1d7cfc94]\n   java.lang.Thread.State: WAITING (on object monitor)\n        at java.lang.Object.wait(Native Method)\n        - waiting on \u003c0x0bdb7d80\u003e (a org.eclipse.jdt.internal.core.search.indexing.IndexManager)\n        at java.lang.Object.wait(Object.java:485)\n        at org.eclipse.jdt.internal.core.search.processing.JobManager.run(JobManager.java:369)\n        - locked \u003c0x0bdb7d80\u003e (a org.eclipse.jdt.internal.core.search.indexing.IndexManager)\n        at java.lang.Thread.run(Thread.java:619)\n\n\"Bundle File Closer\" daemon prio\u003d6 tid\u003d0x1ae70000 nid\u003d0x1520 in Object.wait() [0x1c55f000..0x1c55fb14]\n   java.lang.Thread.State: WAITING (on object monitor)\n        at java.lang.Object.wait(Native Method)\n        - waiting on \u003c0x0ae80c38\u003e (a org.eclipse.osgi.framework.eventmgr.EventManager$EventThread)\n        at java.lang.Object.wait(Object.java:485)\n        at org.eclipse.osgi.framework.eventmgr.EventManager$EventThread.getNextEvent(EventManager.java:375)\n        - locked \u003c0x0ae80c38\u003e (a org.eclipse.osgi.framework.eventmgr.EventManager$EventThread)\n        at org.eclipse.osgi.framework.eventmgr.EventManager$EventThread.run(EventManager.java:315)\n\n\"Start Level Event Dispatcher\" daemon prio\u003d6 tid\u003d0x1afecc00 nid\u003d0x1ff4 in Object.wait() [0x1bcdf000..0x1bcdfc14]\n   java.lang.Thread.State: WAITING (on object monitor)\n        at java.lang.Object.wait(Native Method)\n        - waiting on \u003c0x0adc2980\u003e (a org.eclipse.osgi.framework.eventmgr.EventManager$EventThread)\n        at java.lang.Object.wait(Object.java:485)\n        at org.eclipse.osgi.framework.eventmgr.EventManager$EventThread.getNextEvent(EventManager.java:375)\n        - locked \u003c0x0adc2980\u003e (a org.eclipse.osgi.framework.eventmgr.EventManager$EventThread)\n        at org.eclipse.osgi.framework.eventmgr.EventManager$EventThread.run(EventManager.java:315)\n\n\"OSGi Console\" prio\u003d6 tid\u003d0x1b019400 nid\u003d0x1e44 runnable [0x1bc3f000..0x1bc3fd14]\n   java.lang.Thread.State: RUNNABLE\n        at java.io.FileInputStream.$$YJP$$readBytes(Native Method)\n        at java.io.FileInputStream.readBytes(FileInputStream.java)\n        at java.io.FileInputStream.read(FileInputStream.java:199)\n        at java.io.BufferedInputStream.read1(BufferedInputStream.java:256)\n        at java.io.BufferedInputStream.read(BufferedInputStream.java:317)\n        - locked \u003c0x0accdac0\u003e (a java.io.BufferedInputStream)\n        at java.io.FilterInputStream.read(FilterInputStream.java:116)\n        at sun.nio.cs.StreamDecoder.readBytes(StreamDecoder.java:264)\n        at sun.nio.cs.StreamDecoder.implRead(StreamDecoder.java:306)\n        at sun.nio.cs.StreamDecoder.read(StreamDecoder.java:158)\n        - locked \u003c0x0ade2fc8\u003e (a java.io.InputStreamReader)\n        at java.io.InputStreamReader.read(InputStreamReader.java:167)\n        at java.io.BufferedReader.fill(BufferedReader.java:136)\n        at java.io.BufferedReader.readLine(BufferedReader.java:299)\n        - locked \u003c0x0ade2fc8\u003e (a java.io.InputStreamReader)\n        at java.io.BufferedReader.readLine(BufferedReader.java:362)\n        at org.eclipse.osgi.framework.internal.core.FrameworkConsole.console(FrameworkConsole.java:273)\n        at org.eclipse.osgi.framework.internal.core.FrameworkConsole.run(FrameworkConsole.java:218)\n        at java.lang.Thread.run(Thread.java:619)\n\n\"Framework Event Dispatcher\" daemon prio\u003d6 tid\u003d0x1aff6000 nid\u003d0x1b48 in Object.wait() [0x1bbef000..0x1bbefd94]\n   java.lang.Thread.State: WAITING (on object monitor)\n        at java.lang.Object.wait(Native Method)\n        - waiting on \u003c0x0add8710\u003e (a org.eclipse.osgi.framework.eventmgr.EventManager$EventThread)\n        at java.lang.Object.wait(Object.java:485)\n        at org.eclipse.osgi.framework.eventmgr.EventManager$EventThread.getNextEvent(EventManager.java:375)\n        - locked \u003c0x0add8710\u003e (a org.eclipse.osgi.framework.eventmgr.EventManager$EventThread)\n        at org.eclipse.osgi.framework.eventmgr.EventManager$EventThread.run(EventManager.java:315)\n\n\"Low Memory Detector\" daemon prio\u003d6 tid\u003d0x1ae92000 nid\u003d0x16d8 runnable [0x00000000..0x00000000]\n   java.lang.Thread.State: RUNNABLE\n\n\"CompilerThread0\" daemon prio\u003d10 tid\u003d0x1ae90000 nid\u003d0xa54 waiting on condition [0x00000000..0x1b1ef798]\n   java.lang.Thread.State: RUNNABLE\n\n\"YJPAgent-OOMESnapshotDetector\" daemon prio\u003d6 tid\u003d0x1ae8e400 nid\u003d0x1d2c runnable [0x00000000..0x00000000]\n   java.lang.Thread.State: RUNNABLE\n\n\"YJPAgent-CPUSampler\" daemon prio\u003d6 tid\u003d0x1ae8d800 nid\u003d0x1808 runnable [0x00000000..0x00000000]\n   java.lang.Thread.State: RUNNABLE\n\n\"YJPAgent-RequestListener\" daemon prio\u003d2 tid\u003d0x1ae8bc00 nid\u003d0x224 runnable [0x1b0ff000..0x1b0ffc94]\n   java.lang.Thread.State: RUNNABLE\n        at java.net.PlainSocketImpl.$$YJP$$socketAccept(Native Method)\n        at java.net.PlainSocketImpl.socketAccept(PlainSocketImpl.java)\n        at java.net.PlainSocketImpl.accept(PlainSocketImpl.java:384)\n        - locked \u003c0x0adad478\u003e (a java.net.SocksSocketImpl)\n        at java.net.ServerSocket.implAccept(ServerSocket.java:453)\n        at java.net.ServerSocket.accept(ServerSocket.java:421)\n        at com.yourkit.runtime.Core$3.run(Core.java:546)\n        at java.lang.Thread.run(Thread.java:619)\n\n\"YJPAgent-Telemetry\" daemon prio\u003d2 tid\u003d0x1ae78400 nid\u003d0x1ab8 waiting on condition [0x1b0af000..0x1b0afd14]\n   java.lang.Thread.State: TIMED_WAITING (sleeping)\n        at java.lang.Thread.$$YJP$$sleep(Native Method)\n        at java.lang.Thread.sleep(Thread.java)\n        at com.yourkit.runtime.telemetry.TelemetryThreadJVMTI.run(TelemetryThreadJVMTI.java:271)\n\n\"JDWP Event Helper Thread\" daemon prio\u003d6 tid\u003d0x1a9bb400 nid\u003d0x11e8 runnable [0x00000000..0x00000000]\n   java.lang.Thread.State: RUNNABLE\n\n\"JDWP Transport Listener: dt_socket\" daemon prio\u003d6 tid\u003d0x1a9b8400 nid\u003d0x10c8 runnable [0x00000000..0x00000000]\n   java.lang.Thread.State: RUNNABLE\n\n\"Attach Listener\" daemon prio\u003d10 tid\u003d0x1a9ad800 nid\u003d0x1b70 runnable [0x00000000..0x00000000]\n   java.lang.Thread.State: RUNNABLE\n\n\"Signal Dispatcher\" daemon prio\u003d10 tid\u003d0x1a9ac800 nid\u003d0x7bc waiting on condition [0x00000000..0x00000000]\n   java.lang.Thread.State: RUNNABLE\n\n\"Finalizer\" daemon prio\u003d8 tid\u003d0x1a98d000 nid\u003d0x1b60 in Object.wait() [0x1acbf000..0x1acbfb94]\n   java.lang.Thread.State: WAITING (on object monitor)\n        at java.lang.Object.wait(Native Method)\n        - waiting on \u003c0x0adafa08\u003e (a java.lang.ref.ReferenceQueue$Lock)\n        at java.lang.ref.ReferenceQueue.remove(ReferenceQueue.java:116)\n        - locked \u003c0x0adafa08\u003e (a java.lang.ref.ReferenceQueue$Lock)\n        at java.lang.ref.ReferenceQueue.remove(ReferenceQueue.java:132)\n        at java.lang.ref.Finalizer$FinalizerThread.run(Finalizer.java:159)\n\n\"Reference Handler\" daemon prio\u003d10 tid\u003d0x1a98c000 nid\u003d0x178c in Object.wait() [0x1ac6f000..0x1ac6fc14]\n   java.lang.Thread.State: WAITING (on object monitor)\n        at java.lang.Object.wait(Native Method)\n        - waiting on \u003c0x0ad44080\u003e (a java.lang.ref.Reference$Lock)\n        at java.lang.Object.wait(Object.java:485)\n        at java.lang.ref.Reference$ReferenceHandler.run(Reference.java:116)\n        - locked \u003c0x0ad44080\u003e (a java.lang.ref.Reference$Lock)\n\n\"main\" prio\u003d6 tid\u003d0x00397800 nid\u003d0x1768 runnable [0x009de000..0x009dfe68]\n   java.lang.Thread.State: RUNNABLE\n        at org.eclipse.swt.internal.win32.OS.$$YJP$$WaitMessage(Native Method)\n        at org.eclipse.swt.internal.win32.OS.WaitMessage(OS.java)\n        at org.eclipse.swt.widgets.Display.sleep(Display.java:4096)\n        at org.eclipse.jface.operation.ModalContext$ModalContextThread.block(ModalContext.java:159)\n        at org.eclipse.jface.operation.ModalContext.run(ModalContext.java:326)\n        at org.eclipse.jface.dialogs.ProgressMonitorDialog.run(ProgressMonitorDialog.java:499)\n        at org.eclipse.ui.internal.progress.ProgressMonitorJobsDialog.run(ProgressMonitorJobsDialog.java:267)\n        at org.eclipse.ui.internal.progress.ProgressManager$3.run(ProgressManager.java:909)\n        at org.eclipse.swt.custom.BusyIndicator.showWhile(BusyIndicator.java:67)\n        at org.eclipse.ui.internal.progress.ProgressManager.busyCursorWhile(ProgressManager.java:944)\n        at org.eclipse.ui.internal.progress.ProgressManager.busyCursorWhile(ProgressManager.java:919)\n        at org.eclipse.team.internal.ccvs.ui.actions.SyncAction.showSingleFileComparison(SyncAction.java:186)\n        at org.eclipse.team.internal.ccvs.ui.actions.SyncAction.execute(SyncAction.java:50)\n        at org.eclipse.team.internal.ccvs.ui.actions.CVSAction.run(CVSAction.java:117)\n        at org.eclipse.team.internal.ui.actions.TeamAction.runWithEvent(TeamAction.java:515)\n        at org.eclipse.ui.internal.PluginAction.runWithEvent(PluginAction.java:246)\n        at org.eclipse.jface.action.ActionContributionItem.handleWidgetSelection(ActionContributionItem.java:545)\n        at org.eclipse.jface.action.ActionContributionItem.access$2(ActionContributionItem.java:490)\n        at org.eclipse.jface.action.ActionContributionItem$5.handleEvent(ActionContributionItem.java:402)\n        at org.eclipse.swt.widgets.EventTable.sendEvent(EventTable.java:66)\n        at org.eclipse.swt.widgets.Widget.sendEvent(Widget.java:938)\n        at org.eclipse.swt.widgets.Display.runDeferredEvents(Display.java:3708)\n        at org.eclipse.swt.widgets.Display.readAndDispatch(Display.java:3319)\n        at org.eclipse.ui.internal.Workbench.runEventLoop(Workbench.java:2389)\n        at org.eclipse.ui.internal.Workbench.runUI(Workbench.java:2353)\n        at org.eclipse.ui.internal.Workbench.access$4(Workbench.java:2219)\n        at org.eclipse.ui.internal.Workbench$4.run(Workbench.java:466)\n        at org.eclipse.core.databinding.observable.Realm.runWithDefault(Realm.java:289)\n        at org.eclipse.ui.internal.Workbench.createAndRunWorkbench(Workbench.java:461)\n        at org.eclipse.ui.PlatformUI.createAndRunWorkbench(PlatformUI.java:149)\n        at org.eclipse.ui.internal.ide.application.IDEApplication.start(IDEApplication.java:106)\n        at org.eclipse.equinox.internal.app.EclipseAppHandle.run(EclipseAppHandle.java:169)\n        at org.eclipse.core.runtime.internal.adaptor.EclipseAppLauncher.runApplication(EclipseAppLauncher.java:106)\n        at org.eclipse.core.runtime.internal.adaptor.EclipseAppLauncher.start(EclipseAppLauncher.java:76)\n        at org.eclipse.core.runtime.adaptor.EclipseStarter.run(EclipseStarter.java:363)\n        at org.eclipse.core.runtime.adaptor.EclipseStarter.run(EclipseStarter.java:176)\n        at sun.reflect.NativeMethodAccessorImpl.invoke0(Native Method)\n        at sun.reflect.NativeMethodAccessorImpl.invoke(NativeMethodAccessorImpl.java:39)\n        at sun.reflect.DelegatingMethodAccessorImpl.invoke(DelegatingMethodAccessorImpl.java:25)\n        at java.lang.reflect.Method.invoke(Method.java:597)\n        at org.eclipse.equinox.launcher.Main.invokeFramework(Main.java:508)\n        at org.eclipse.equinox.launcher.Main.basicRun(Main.java:447)\n        at org.eclipse.equinox.launcher.Main.run(Main.java:1173)\n        at org.eclipse.equinox.launcher.Main.main(Main.java:1148)\n\n\"VM Thread\" prio\u003d10 tid\u003d0x1a987400 nid\u003d0x1278 runnable\n\n\"GC task thread#0 (ParallelGC)\" prio\u003d6 tid\u003d0x0039d000 nid\u003d0x19fc runnable\n\n\"GC task thread#1 (ParallelGC)\" prio\u003d6 tid\u003d0x0039e000 nid\u003d0x1d50 runnable\n\n\"VM Periodic Task Thread\" prio\u003d10 tid\u003d0x1ae9cc00 nid\u003d0x1e84 waiting on condition\n\nJNI global references: 9811\n\nHeap\n PSYoungGen      total 13120K, used 5657K [0x19380000, 0x1a6b0000, 0x1a6b0000)\n  eden space 6592K, 85% used [0x19380000,0x19902738,0x199f0000)\n  from space 6528K, 0% used [0x199f0000,0x199f4000,0x1a050000)\n  to   space 6528K, 0% used [0x1a050000,0x1a050000,0x1a6b0000)\n PSOldGen        total 170304K, used 126933K [0x0acb0000, 0x15300000, 0x19380000)\n  object space 170304K, 74% used [0x0acb0000,0x128a55e8,0x15300000)\n PSPermGen       total 57600K, used 48601K [0x02cb0000, 0x064f0000, 0x0acb0000)\n  object space 57600K, 84% used [0x02cb0000,0x05c26428,0x064f0000)",
    "It looks like the user initiated connection is blocked on the QuickDiff connection which is not canceled. We should be able to use a non-blocking acquire on the repository location lock and check the progress monitor for cancellation.",
    "Fix released to HEAD",
    "Michael, could you give me some details about this fix (what classes did you change ?). There is no patch, so i need some information to verify this fix. At the same time I can\u0027t reproduce bug form original comment, so I would appreciate any tips in this matter too.",
    "The fix is in CVSRepositoryLocation. When acquiring the host lock, we use acquire(int) instead of acquire().",
    "Verified on I20070917-0010.",
    "Verified in I20070919-0010.\n\nTo reproduce,\n- set quick diff provider to CVS\n- check out a CVS project\n- in CVS Repositories view, change the host to download.eclipse.org (which does not run a cvs server and will therefore time out)\n- open a few files\n- make a change, save\n- Replace With \u003e Latest from HEAD, click OK to replace\n- click Cancel\n\u003d\u003e in 3.4M1, cancelling took a while, while in I20070919-0010, it happens promptly."
  ],
  "commentCreationDates": [
    "2007-08-08T11:17:01+02:00",
    "2007-08-09T22:45:06+02:00",
    "2007-09-10T20:25:17+02:00",
    "2007-09-19T13:51:16+02:00",
    "2007-09-19T14:52:35+02:00",
    "2007-09-19T15:25:48+02:00",
    "2007-09-19T15:30:31+02:00"
  ],
  "traces": [
    {
      "exceptionType": "org.eclipse.team.internal.ccvs.ssh2.CVSSSH2ServerConnection$SSH2IOException",
      "message": "A timeout occurred connecting to host dev.eclipse.org",
      "elements": [
        {
          "method": "org.eclipse.team.internal.ccvs.ssh2.CVSSSH2ServerConnection.internalOpen",
          "source": "CVSSSH2ServerConnection.java:193"
        },
        {
          "method": "org.eclipse.team.internal.ccvs.ssh2.CVSSSH2ServerConnection.open",
          "source": "CVSSSH2ServerConnection.java:107"
        },
        {
          "method": "org.eclipse.team.internal.ccvs.core.connection.Connection.open",
          "source": "Connection.java:132"
        },
        {
          "method": "org.eclipse.team.internal.ccvs.core.connection.CVSRepositoryLocation.createConnection",
          "source": "CVSRepositoryLocation.java:547"
        },
        {
          "method": "org.eclipse.team.internal.ccvs.core.connection.CVSRepositoryLocation.openConnection",
          "source": "CVSRepositoryLocation.java:791"
        },
        {
          "method": "org.eclipse.team.internal.ccvs.core.client.Session.open",
          "source": "Session.java:159"
        },
        {
          "method": "org.eclipse.team.internal.ccvs.core.resources.RemoteFile.internalFetchContents",
          "source": "RemoteFile.java:215"
        },
        {
          "method": "org.eclipse.team.internal.ccvs.core.resources.RemoteFile.fetchContents",
          "source": "RemoteFile.java:193"
        },
        {
          "method": "org.eclipse.team.core.variants.CachedResourceVariant.ensureContentsCached",
          "source": "CachedResourceVariant.java:111"
        },
        {
          "method": "org.eclipse.team.core.variants.CachedResourceVariant.getStorage",
          "source": "CachedResourceVariant.java:101"
        },
        {
          "method": "org.eclipse.team.internal.ccvs.core.resources.RemoteFile.getContents",
          "source": "RemoteFile.java:184"
        },
        {
          "method": "org.eclipse.team.internal.ccvs.ui.RemoteRevisionQuickDiffProvider.readDocument",
          "source": "RemoteRevisionQuickDiffProvider.java:254"
        },
        {
          "method": "org.eclipse.team.internal.ccvs.ui.RemoteRevisionQuickDiffProvider.getReference",
          "source": "RemoteRevisionQuickDiffProvider.java:131"
        },
        {
          "method": "org.eclipse.ui.internal.texteditor.quickdiff.DocumentLineDiffer$2.run",
          "source": "DocumentLineDiffer.java:496"
        },
        {
          "method": "org.eclipse.core.internal.jobs.Worker.run",
          "source": "Worker.java:55"
        }
      ],
      "causedBy": {
        "exceptionType": "java.io.InterruptedIOException",
        "message": "A timeout occurred connecting to host dev.eclipse.org",
        "elements": [
          {
            "method": "com.jcraft.jsch.Session.connect",
            "source": "Session.java:494"
          },
          {
            "method": "com.jcraft.jsch.Session.connect",
            "source": "Session.java:145"
          },
          {
            "method": "org.eclipse.jsch.internal.core.JSchProvider.connect",
            "source": "JSchProvider.java:52"
          },
          {
            "method": "org.eclipse.team.internal.ccvs.ssh2.JSchSession.createSession",
            "source": "JSchSession.java:361"
          },
          {
            "method": "org.eclipse.team.internal.ccvs.ssh2.JSchSession.getSession",
            "source": "JSchSession.java:326"
          },
          {
            "method": "org.eclipse.team.internal.ccvs.ssh2.CVSSSH2ServerConnection.internalOpen",
            "source": "CVSSSH2ServerConnection.java:122"
          }
        ],
        "number": 0,
        "commentIndex": 0
      },
      "number": 0,
      "commentIndex": 0,
      "bugId": "199224",
      "date": "2007-08-08T11:17:01+02:00",
      "product": "Platform",
      "component": "CVS",
      "severity": "normal"
    }
  ],
  "groupId": "199224",
  "bugId": "199224",
  "date": "2007-08-08T11:17:01+02:00",
  "product": "Platform",
  "component": "CVS",
  "severity": "normal"
}