{
  "comments": [
    "Created an attachment (id\u003d75745)\nWorkspace demonstrating the problem\n\nBuild ID: I20070625-1500\n\nSteps To Reproduce:\n1. Open workspace (unzip test.zip) demonstrating the problem\n\n2. Try to open MyClass (type \u0027M\u0027) - this fails with the described error\nmessage\n\n\nMore information:\nError message in Type dialog\n\n\u0027Items filtering (Time of error: July 13, 2007 9:39:21 AM GMT+2:00) \nReason:\nClass file name must end with .class\u0027\n\n\n--------------------------------------------------------------------\nSee below .log file from the workspace \n--------------------------------------------------------------------\n\n!ENTRY org.eclipse.core.jobs 4 2 2007-07-13 09:39:21.586\n!MESSAGE An internal error occurred during: \"Items filtering\".\n!STACK 0\njava.lang.IllegalArgumentException: Class file name must end with .class\n        at\norg.eclipse.jdt.internal.core.PackageFragment.getClassFile(PackageFragment.java:188)\n        at\norg.eclipse.jdt.internal.core.search.TypeNameMatchRequestorWrapper.createTypeFromJar(TypeNameMatchRequestorWrapper.java:146)\n        at\norg.eclipse.jdt.internal.core.search.TypeNameMatchRequestorWrapper.acceptType(TypeNameMatchRequestorWrapper.java:108)\n        at\norg.eclipse.jdt.internal.core.search.BasicSearchEngine$2.acceptIndexMatch(BasicSearchEngine.java:767)\n        at\norg.eclipse.jdt.internal.core.search.matching.InternalSearchPattern.acceptMatch(InternalSearchPattern.java:45)\n        at\norg.eclipse.jdt.internal.core.search.matching.InternalSearchPattern.findIndexMatches(InternalSearchPattern.java:89)\n        at\norg.eclipse.jdt.internal.core.search.matching.MatchLocator.findIndexMatches(MatchLocator.java:325)\n        at\norg.eclipse.jdt.internal.core.search.PatternSearchJob.search(PatternSearchJob.java:114)\n        at\norg.eclipse.jdt.internal.core.search.PatternSearchJob.execute(PatternSearchJob.java:64)\n        at\norg.eclipse.jdt.internal.core.search.processing.JobManager.performConcurrentJob(JobManager.java:279)\n        at\norg.eclipse.jdt.internal.core.search.BasicSearchEngine.searchAllTypeNames(BasicSearchEngine.java:778)\n        at\norg.eclipse.jdt.core.search.SearchEngine.searchAllTypeNames(SearchEngine.java:781)\n        at\norg.eclipse.jdt.internal.ui.dialogs.FilteredTypesSelectionDialog.fillContentProvider(FilteredTypesSelectionDialog.java:593)\n        at\norg.eclipse.ui.dialogs.FilteredItemsSelectionDialog$FilterJob.filterContent(FilteredItemsSelectionDialog.java:2059)\n        at\norg.eclipse.ui.dialogs.FilteredItemsSelectionDialog$FilterJob.internalRun(FilteredItemsSelectionDialog.java:2001)\n        at\norg.eclipse.ui.dialogs.FilteredItemsSelectionDialog$FilterJob.doRun(FilteredItemsSelectionDialog.java:1973)\n        at\norg.eclipse.ui.dialogs.FilteredItemsSelectionDialog$FilterJob.run(FilteredItemsSelectionDialog.java:1960)\n        at org.eclipse.core.internal.jobs.Worker.run(Worker.java:55)",
    "I\u0027ll investigate...",
    "Problem is while getting document path in InternalSearchPattern, it worngly assumes that the document belongs to an archive as the containerPath ends with \".jar\"...\n",
    "\n\n*** This bug has been marked as a duplicate of bug 138184 ***",
    "Verified for 3.4 M2 using build I20070917-0010."
  ],
  "commentCreationDates": [
    "2007-08-09T12:34:00+02:00",
    "2007-08-09T13:03:11+02:00",
    "2007-08-09T13:18:21+02:00",
    "2007-08-09T18:29:00+02:00",
    "2007-09-18T09:33:21+02:00"
  ],
  "traces": [
    {
      "exceptionType": "java.lang.IllegalArgumentException",
      "message": "Class file name must end with .class",
      "elements": [
        {
          "method": "org.eclipse.jdt.internal.core.PackageFragment.getClassFile",
          "source": "PackageFragment.java:188"
        },
        {
          "method": "org.eclipse.jdt.internal.core.search.TypeNameMatchRequestorWrapper.createTypeFromJar",
          "source": "TypeNameMatchRequestorWrapper.java:146"
        },
        {
          "method": "org.eclipse.jdt.internal.core.search.TypeNameMatchRequestorWrapper.acceptType",
          "source": "TypeNameMatchRequestorWrapper.java:108"
        },
        {
          "method": "org.eclipse.jdt.internal.core.search.BasicSearchEngine$2.acceptIndexMatch",
          "source": "BasicSearchEngine.java:767"
        },
        {
          "method": "org.eclipse.jdt.internal.core.search.matching.InternalSearchPattern.acceptMatch",
          "source": "InternalSearchPattern.java:45"
        },
        {
          "method": "org.eclipse.jdt.internal.core.search.matching.InternalSearchPattern.findIndexMatches",
          "source": "InternalSearchPattern.java:89"
        },
        {
          "method": "org.eclipse.jdt.internal.core.search.matching.MatchLocator.findIndexMatches",
          "source": "MatchLocator.java:325"
        },
        {
          "method": "org.eclipse.jdt.internal.core.search.PatternSearchJob.search",
          "source": "PatternSearchJob.java:114"
        },
        {
          "method": "org.eclipse.jdt.internal.core.search.PatternSearchJob.execute",
          "source": "PatternSearchJob.java:64"
        },
        {
          "method": "org.eclipse.jdt.internal.core.search.processing.JobManager.performConcurrentJob",
          "source": "JobManager.java:279"
        },
        {
          "method": "org.eclipse.jdt.internal.core.search.BasicSearchEngine.searchAllTypeNames",
          "source": "BasicSearchEngine.java:778"
        },
        {
          "method": "org.eclipse.jdt.core.search.SearchEngine.searchAllTypeNames",
          "source": "SearchEngine.java:781"
        },
        {
          "method": "org.eclipse.jdt.internal.ui.dialogs.FilteredTypesSelectionDialog.fillContentProvider",
          "source": "FilteredTypesSelectionDialog.java:593"
        },
        {
          "method": "org.eclipse.ui.dialogs.FilteredItemsSelectionDialog$FilterJob.filterContent",
          "source": "FilteredItemsSelectionDialog.java:2059"
        },
        {
          "method": "org.eclipse.ui.dialogs.FilteredItemsSelectionDialog$FilterJob.internalRun",
          "source": "FilteredItemsSelectionDialog.java:2001"
        },
        {
          "method": "org.eclipse.ui.dialogs.FilteredItemsSelectionDialog$FilterJob.doRun",
          "source": "FilteredItemsSelectionDialog.java:1973"
        },
        {
          "method": "org.eclipse.ui.dialogs.FilteredItemsSelectionDialog$FilterJob.run",
          "source": "FilteredItemsSelectionDialog.java:1960"
        },
        {
          "method": "org.eclipse.core.internal.jobs.Worker.run",
          "source": "Worker.java:55"
        }
      ],
      "number": 0,
      "commentIndex": 0,
      "bugId": "199392",
      "duplicateId": "138184",
      "date": "2007-08-09T12:34:00+02:00",
      "product": "JDT",
      "component": "Core",
      "severity": "normal"
    }
  ],
  "groupId": "138184",
  "bugId": "199392",
  "duplicateId": "138184",
  "date": "2007-08-09T12:34:00+02:00",
  "product": "JDT",
  "component": "Core",
  "severity": "normal"
}