{
  "comments": [
    "The probe of a DS8000 failed with CIM_ERR_INVALID_PARAMETER using build Aperi-R04-070802-233101.zip (replaces rhinojs.jar with js.jar, updates gui)\n\norg.sblim.wbem.cim.CIMException: CIM_ERR_INVALID_PARAMETER(Remote exception at t\nhe CIMOM:CIM_ERR_INVALID_PARAMETER: One or more parameter values passed to the m\nethod were invalid: \"CIM_PackagedComponent\")\n        at org.sblim.wbem.xml.XMLDefaultHandlerImpl.startElement(XMLDefaultHandl\nerImpl.java:1041)\n        at org.sblim.wbem.client.CIMEnumerationImpl.next(CIMEnumerationImpl.java\n:365)\n        at org.sblim.wbem.client.CIMEnumerationImpl.\u003cinit\u003e(CIMEnumerationImpl.ja\nva:119)\n        at org.sblim.wbem.client.CIMClientXML.getEnumeration(CIMClientXML.java:1\n590)\n        at org.sblim.wbem.client.CIMClientXML.associators(CIMClientXML.java:422)\n\n        at org.sblim.wbem.client.CIMClient.associators(CIMClient.java:556)\n        at sun.reflect.GeneratedMethodAccessor5.invoke(Unknown Source)\n        at sun.reflect.DelegatingMethodAccessorImpl.invoke(Unknown Source)\n        at java.lang.reflect.Method.invoke(Unknown Source)\n        at org.eclipse.aperi.disk.common.util.thread.DiskMgrThread.run(DiskMgrTh\nread.java:257)",
    "Received the same failure when probing an ESS-2105 subsystem\n\norg.sblim.wbem.cim.CIMException: CIM_ERR_INVALID_PARAMETER(Remote exception at t\nhe CIMOM:CIM_ERR_INVALID_PARAMETER: One or more parameter values passed to the m\nethod were invalid: \"CIM_PackagedComponent\")\n        at org.sblim.wbem.xml.XMLDefaultHandlerImpl.startElement(XMLDefaultHandl\nerImpl.java:1041)\n        at org.sblim.wbem.client.CIMEnumerationImpl.next(CIMEnumerationImpl.java\n:365)\n        at org.sblim.wbem.client.CIMEnumerationImpl.\u003cinit\u003e(CIMEnumerationImpl.ja\nva:119)\n        at org.sblim.wbem.client.CIMClientXML.getEnumeration(CIMClientXML.java:1\n590)\n        at org.sblim.wbem.client.CIMClientXML.associators(CIMClientXML.java:422)\n\n        at org.sblim.wbem.client.CIMClient.associators(CIMClient.java:556)\n        at sun.reflect.GeneratedMethodAccessor46.invoke(Unknown Source)\n        at sun.reflect.DelegatingMethodAccessorImpl.invoke(Unknown Source)\n        at java.lang.reflect.Method.invoke(Unknown Source)\n        at org.eclipse.aperi.disk.common.util.thread.DiskMgrThread.run(DiskMgrTh\nread.java:257)\n",
    "The error described appears with the latest IBM DS CIMOM version 5.2.\nWe should enhance Aperi to support the new 5.2 provider version, changing this bug to \"enhancement\".\n\nOld versions up-to version 5.1 are supported in Aperi 0.3 and pre. 0.4.",
    "code checkin complete",
    "unit-testing done"
  ],
  "commentCreationDates": [
    "2007-08-08T21:09:37+02:00",
    "2007-08-09T20:23:15+02:00",
    "2007-08-27T10:55:57+02:00",
    "2007-09-10T18:07:09+02:00",
    "2007-09-19T09:04:02+02:00"
  ],
  "traces": [
    {
      "exceptionType": "org.sblim.wbem.cim.CIMException",
      "message": "CIM_ERR_INVALID_PARAMETER(Remote exception at t he CIMOM:CIM_ERR_INVALID_PARAMETER: One or more parameter values passed to the m ethod were invalid: \"CIM_PackagedComponent\")",
      "elements": [
        {
          "method": "org.sblim.wbem.xml.XMLDefaultHandlerImpl.startElement",
          "source": "XMLDefaultHandl erImpl.java:1041"
        },
        {
          "method": "org.sblim.wbem.client.CIMEnumerationImpl.next",
          "source": "CIMEnumerationImpl.java :365"
        },
        {
          "method": "org.sblim.wbem.client.CIMEnumerationImpl.\u003cinit\u003e",
          "source": "CIMEnumerationImpl.ja va:119"
        },
        {
          "method": "org.sblim.wbem.client.CIMClientXML.getEnumeration",
          "source": "CIMClientXML.java:1 590"
        },
        {
          "method": "org.sblim.wbem.client.CIMClientXML.associators",
          "source": "CIMClientXML.java:422"
        },
        {
          "method": "org.sblim.wbem.client.CIMClient.associators",
          "source": "CIMClient.java:556"
        },
        {
          "method": "sun.reflect.GeneratedMethodAccessor5.invoke",
          "source": "Unknown Source"
        },
        {
          "method": "sun.reflect.DelegatingMethodAccessorImpl.invoke",
          "source": "Unknown Source"
        },
        {
          "method": "java.lang.reflect.Method.invoke",
          "source": "Unknown Source"
        },
        {
          "method": "org.eclipse.aperi.disk.common.util.thread.DiskMgrThread.run",
          "source": "DiskMgrTh read.java:257"
        }
      ],
      "number": 0,
      "commentIndex": 0,
      "bugId": "199312",
      "date": "2007-08-08T21:09:37+02:00",
      "product": "Aperi",
      "component": "aperi.device",
      "severity": "enhancement"
    },
    {
      "exceptionType": "org.sblim.wbem.cim.CIMException",
      "message": "CIM_ERR_INVALID_PARAMETER(Remote exception at t he CIMOM:CIM_ERR_INVALID_PARAMETER: One or more parameter values passed to the m ethod were invalid: \"CIM_PackagedComponent\")",
      "elements": [
        {
          "method": "org.sblim.wbem.xml.XMLDefaultHandlerImpl.startElement",
          "source": "XMLDefaultHandl erImpl.java:1041"
        },
        {
          "method": "org.sblim.wbem.client.CIMEnumerationImpl.next",
          "source": "CIMEnumerationImpl.java :365"
        },
        {
          "method": "org.sblim.wbem.client.CIMEnumerationImpl.\u003cinit\u003e",
          "source": "CIMEnumerationImpl.ja va:119"
        },
        {
          "method": "org.sblim.wbem.client.CIMClientXML.getEnumeration",
          "source": "CIMClientXML.java:1 590"
        },
        {
          "method": "org.sblim.wbem.client.CIMClientXML.associators",
          "source": "CIMClientXML.java:422"
        },
        {
          "method": "org.sblim.wbem.client.CIMClient.associators",
          "source": "CIMClient.java:556"
        },
        {
          "method": "sun.reflect.GeneratedMethodAccessor46.invoke",
          "source": "Unknown Source"
        },
        {
          "method": "sun.reflect.DelegatingMethodAccessorImpl.invoke",
          "source": "Unknown Source"
        },
        {
          "method": "java.lang.reflect.Method.invoke",
          "source": "Unknown Source"
        },
        {
          "method": "org.eclipse.aperi.disk.common.util.thread.DiskMgrThread.run",
          "source": "DiskMgrTh read.java:257"
        }
      ],
      "number": 1,
      "commentIndex": 1,
      "bugId": "199312",
      "date": "2007-08-09T20:23:15+02:00",
      "product": "Aperi",
      "component": "aperi.device",
      "severity": "enhancement"
    }
  ],
  "groupId": "199312",
  "bugId": "199312",
  "date": "2007-08-08T21:09:37+02:00",
  "product": "Aperi",
  "component": "aperi.device",
  "severity": "enhancement"
}