{
  "comments": [
    "I20070809-1105\n\n1. In the \u0027Java\u0027 Perspective detach \u0027Package Explorer\u0027 view\n2. Switch to the \u0027Java Browsing\u0027 Perspective\n3. Switch to the \u0027Java\u0027 Perspective\n4. Right-click on the \u0027Package Explorer\u0027 tab of the detached view (i.e. to attach it)\nIs:\n\njava.lang.IllegalArgumentException: Widget has the wrong parent\n        at org.eclipse.swt.SWT.error(SWT.java:3547)\n        at org.eclipse.swt.SWT.error(SWT.java:3481)\n        at org.eclipse.swt.SWT.error(SWT.java:3452)\n        at org.eclipse.swt.widgets.Widget.error(Widget.java:432)\n        at org.eclipse.swt.widgets.Composite.setTabList(Composite.java:890)\n        at org.eclipse.ui.internal.WorkbenchPage.updateTabList(WorkbenchPage.java:3858)\n        at org.eclipse.ui.internal.WorkbenchPage.access$8(WorkbenchPage.java:3851)\n        at org.eclipse.ui.internal.WorkbenchPage$3.run(WorkbenchPage.java:617)\n        at org.eclipse.core.runtime.SafeRunner.run(SafeRunner.java:37)\n        at org.eclipse.core.runtime.Platform.run(Platform.java:857)\n        at org.eclipse.ui.internal.WorkbenchPage.activatePart(WorkbenchPage.java:609)\n        at org.eclipse.ui.internal.WorkbenchPage.setActivePart(WorkbenchPage.java:3380)\n        at org.eclipse.ui.internal.WorkbenchPage.requestActivation(WorkbenchPage.java:2928)\n        at org.eclipse.ui.internal.PartPane.requestActivation(PartPane.java:265)\n        at org.eclipse.ui.internal.presentations.PresentablePart.setFocus(PresentablePart.java:191)\n        at org.eclipse.ui.internal.presentations.util.TabbedStackPresentation$1.handleEvent(TabbedStackPresentation.java:92)\n        at org.eclipse.ui.internal.presentations.util.AbstractTabFolder.fireEvent(AbstractTabFolder.java:267)\n        at org.eclipse.ui.internal.presentations.util.AbstractTabFolder.fireEvent(AbstractTabFolder.java:272)\n        at org.eclipse.ui.internal.presentations.util.AbstractTabFolder.handleMouseDown(AbstractTabFolder.java:342)\n        at org.eclipse.ui.internal.presentations.util.AbstractTabFolder$3.mouseDown(AbstractTabFolder.java:79)\n        at org.eclipse.swt.widgets.TypedListener.handleEvent(TypedListener.java:178)\n        at org.eclipse.swt.widgets.EventTable.sendEvent(EventTable.java:66)\n        at org.eclipse.swt.widgets.Widget.sendEvent(Widget.java:938)\n        at org.eclipse.swt.widgets.Display.runDeferredEvents(Display.java:3708)\n        at org.eclipse.swt.widgets.Display.readAndDispatch(Display.java:3319)\n        at org.eclipse.ui.internal.Workbench.runEventLoop(Workbench.java:2389)\n        at org.eclipse.ui.internal.Workbench.runUI(Workbench.java:2353)\n        at org.eclipse.ui.internal.Workbench.access$4(Workbench.java:2219)\n        at org.eclipse.ui.internal.Workbench$4.run(Workbench.java:466)\n        at org.eclipse.core.databinding.observable.Realm.runWithDefault(Realm.java:289)\n        at org.eclipse.ui.internal.Workbench.createAndRunWorkbench(Workbench.java:461)\n        at org.eclipse.ui.PlatformUI.createAndRunWorkbench(PlatformUI.java:149)\n        at org.eclipse.ui.internal.ide.application.IDEApplication.start(IDEApplication.java:106)\n        at org.eclipse.equinox.internal.app.EclipseAppHandle.run(EclipseAppHandle.java:169)\n        at org.eclipse.core.runtime.internal.adaptor.EclipseAppLauncher.runApplication(EclipseAppLauncher.java:106)\n        at org.eclipse.core.runtime.internal.adaptor.EclipseAppLauncher.start(EclipseAppLauncher.java:76)\n        at org.eclipse.core.runtime.adaptor.EclipseStarter.run(EclipseStarter.java:363)\n        at org.eclipse.core.runtime.adaptor.EclipseStarter.run(EclipseStarter.java:176)\n        at sun.reflect.NativeMethodAccessorImpl.invoke0(Native Method)\n        at sun.reflect.NativeMethodAccessorImpl.invoke(NativeMethodAccessorImpl.java:39)\n        at sun.reflect.DelegatingMethodAccessorImpl.invoke(DelegatingMethodAccessorImpl.java:25)\n        at java.lang.reflect.Method.invoke(Method.java:597)\n        at org.eclipse.equinox.launcher.Main.invokeFramework(Main.java:508)\n        at org.eclipse.equinox.launcher.Main.basicRun(Main.java:447)\n        at org.eclipse.equinox.launcher.Main.run(Main.java:1173)\n        at org.eclipse.equinox.launcher.Main.main(Main.java:1148)\n        at org.eclipse.core.launcher.Main.main(Main.java:30)",
    "This is even worse:\n3. Switch to the \u0027Java\u0027 Perspective\n4. Close all editors\nIs: Exception\n5. Switch to Java Browsing and back\nIs: Exception\n6. Open a fast view, click into empty editor area\nIs: Exception\n\nThis makes detached views unusable\n",
    "\nBenno, has this just started happening? I committed a \u0027fix\u0027 last week that could have affected the widget hierarchy. I can repro this using  I20070807-0010 but not with my new patches applied (see bug 180747).\n",
    "(In reply to comment #2)\n\u003e Benno, has this just started happening? I committed a \u0027fix\u0027 last week that\n\u003e could have affected the widget hierarchy. I can repro this using \n\u003e I20070807-0010 but not with my new patches applied (see bug 180747).\n\u003e \n\nI don\u0027t know, I usually never work with detached views. I can\u0027t reproduce it in 3.3.",
    "\nI\u0027ll re-test next I-build...\n",
    "\nThis is a second indication of the same defect...\n\n\n*** This bug has been marked as a duplicate of bug 199873 ***"
  ],
  "commentCreationDates": [
    "2007-08-10T10:42:24+02:00",
    "2007-08-10T14:43:10+02:00",
    "2007-08-10T20:30:53+02:00",
    "2007-08-13T09:36:13+02:00",
    "2007-08-13T15:35:12+02:00",
    "2007-08-15T15:27:49+02:00"
  ],
  "traces": [
    {
      "exceptionType": "java.lang.IllegalArgumentException",
      "message": "Widget has the wrong parent",
      "elements": [
        {
          "method": "org.eclipse.swt.SWT.error",
          "source": "SWT.java:3547"
        },
        {
          "method": "org.eclipse.swt.SWT.error",
          "source": "SWT.java:3481"
        },
        {
          "method": "org.eclipse.swt.SWT.error",
          "source": "SWT.java:3452"
        },
        {
          "method": "org.eclipse.swt.widgets.Widget.error",
          "source": "Widget.java:432"
        },
        {
          "method": "org.eclipse.swt.widgets.Composite.setTabList",
          "source": "Composite.java:890"
        },
        {
          "method": "org.eclipse.ui.internal.WorkbenchPage.updateTabList",
          "source": "WorkbenchPage.java:3858"
        },
        {
          "method": "org.eclipse.ui.internal.WorkbenchPage.access$8",
          "source": "WorkbenchPage.java:3851"
        },
        {
          "method": "org.eclipse.ui.internal.WorkbenchPage$3.run",
          "source": "WorkbenchPage.java:617"
        },
        {
          "method": "org.eclipse.core.runtime.SafeRunner.run",
          "source": "SafeRunner.java:37"
        },
        {
          "method": "org.eclipse.core.runtime.Platform.run",
          "source": "Platform.java:857"
        },
        {
          "method": "org.eclipse.ui.internal.WorkbenchPage.activatePart",
          "source": "WorkbenchPage.java:609"
        },
        {
          "method": "org.eclipse.ui.internal.WorkbenchPage.setActivePart",
          "source": "WorkbenchPage.java:3380"
        },
        {
          "method": "org.eclipse.ui.internal.WorkbenchPage.requestActivation",
          "source": "WorkbenchPage.java:2928"
        },
        {
          "method": "org.eclipse.ui.internal.PartPane.requestActivation",
          "source": "PartPane.java:265"
        },
        {
          "method": "org.eclipse.ui.internal.presentations.PresentablePart.setFocus",
          "source": "PresentablePart.java:191"
        },
        {
          "method": "org.eclipse.ui.internal.presentations.util.TabbedStackPresentation$1.handleEvent",
          "source": "TabbedStackPresentation.java:92"
        },
        {
          "method": "org.eclipse.ui.internal.presentations.util.AbstractTabFolder.fireEvent",
          "source": "AbstractTabFolder.java:267"
        },
        {
          "method": "org.eclipse.ui.internal.presentations.util.AbstractTabFolder.fireEvent",
          "source": "AbstractTabFolder.java:272"
        },
        {
          "method": "org.eclipse.ui.internal.presentations.util.AbstractTabFolder.handleMouseDown",
          "source": "AbstractTabFolder.java:342"
        },
        {
          "method": "org.eclipse.ui.internal.presentations.util.AbstractTabFolder$3.mouseDown",
          "source": "AbstractTabFolder.java:79"
        },
        {
          "method": "org.eclipse.swt.widgets.TypedListener.handleEvent",
          "source": "TypedListener.java:178"
        },
        {
          "method": "org.eclipse.swt.widgets.EventTable.sendEvent",
          "source": "EventTable.java:66"
        },
        {
          "method": "org.eclipse.swt.widgets.Widget.sendEvent",
          "source": "Widget.java:938"
        },
        {
          "method": "org.eclipse.swt.widgets.Display.runDeferredEvents",
          "source": "Display.java:3708"
        },
        {
          "method": "org.eclipse.swt.widgets.Display.readAndDispatch",
          "source": "Display.java:3319"
        },
        {
          "method": "org.eclipse.ui.internal.Workbench.runEventLoop",
          "source": "Workbench.java:2389"
        },
        {
          "method": "org.eclipse.ui.internal.Workbench.runUI",
          "source": "Workbench.java:2353"
        },
        {
          "method": "org.eclipse.ui.internal.Workbench.access$4",
          "source": "Workbench.java:2219"
        },
        {
          "method": "org.eclipse.ui.internal.Workbench$4.run",
          "source": "Workbench.java:466"
        },
        {
          "method": "org.eclipse.core.databinding.observable.Realm.runWithDefault",
          "source": "Realm.java:289"
        },
        {
          "method": "org.eclipse.ui.internal.Workbench.createAndRunWorkbench",
          "source": "Workbench.java:461"
        },
        {
          "method": "org.eclipse.ui.PlatformUI.createAndRunWorkbench",
          "source": "PlatformUI.java:149"
        },
        {
          "method": "org.eclipse.ui.internal.ide.application.IDEApplication.start",
          "source": "IDEApplication.java:106"
        },
        {
          "method": "org.eclipse.equinox.internal.app.EclipseAppHandle.run",
          "source": "EclipseAppHandle.java:169"
        },
        {
          "method": "org.eclipse.core.runtime.internal.adaptor.EclipseAppLauncher.runApplication",
          "source": "EclipseAppLauncher.java:106"
        },
        {
          "method": "org.eclipse.core.runtime.internal.adaptor.EclipseAppLauncher.start",
          "source": "EclipseAppLauncher.java:76"
        },
        {
          "method": "org.eclipse.core.runtime.adaptor.EclipseStarter.run",
          "source": "EclipseStarter.java:363"
        },
        {
          "method": "org.eclipse.core.runtime.adaptor.EclipseStarter.run",
          "source": "EclipseStarter.java:176"
        },
        {
          "method": "sun.reflect.NativeMethodAccessorImpl.invoke0",
          "source": "Native Method"
        },
        {
          "method": "sun.reflect.NativeMethodAccessorImpl.invoke",
          "source": "NativeMethodAccessorImpl.java:39"
        },
        {
          "method": "sun.reflect.DelegatingMethodAccessorImpl.invoke",
          "source": "DelegatingMethodAccessorImpl.java:25"
        },
        {
          "method": "java.lang.reflect.Method.invoke",
          "source": "Method.java:597"
        },
        {
          "method": "org.eclipse.equinox.launcher.Main.invokeFramework",
          "source": "Main.java:508"
        },
        {
          "method": "org.eclipse.equinox.launcher.Main.basicRun",
          "source": "Main.java:447"
        },
        {
          "method": "org.eclipse.equinox.launcher.Main.run",
          "source": "Main.java:1173"
        },
        {
          "method": "org.eclipse.equinox.launcher.Main.main",
          "source": "Main.java:1148"
        },
        {
          "method": "org.eclipse.core.launcher.Main.main",
          "source": "Main.java:30"
        }
      ],
      "number": 0,
      "commentIndex": 0,
      "bugId": "199530",
      "duplicateId": "199873",
      "date": "2007-08-10T10:42:24+02:00",
      "product": "Platform",
      "component": "UI",
      "severity": "major"
    }
  ],
  "groupId": "199873",
  "bugId": "199530",
  "duplicateId": "199873",
  "date": "2007-08-10T10:42:24+02:00",
  "product": "Platform",
  "component": "UI",
  "severity": "major"
}