{
  "comments": [
    "I am trying to run the metadata generator on Linux (as part of the build) against a built Windows version of the RCP Agent but am having problems. \n\nThere is currently code in:\n  EclipseInstallGeneratorInfoProvider#createLauncherBundleInfo\nwhich automatically adds a dependency to a fragment based on the current OS/WS/ARCH combination.\n\nThis causes problems when you try and use the Director on the generated metadata to install a new client on Windows. You get unsatisfied dependency errors.\n\nHere are the errors I get:\n\n !ENTRY org.eclipse.osgi 4 0 2007-08-14 14:55:28.805\n !MESSAGE Application error\n !STACK 1\n java.lang.IllegalStateException: Requirement not satisfied: requiredCapability: org.eclipse.equinox.prov.iunamespace/org.eclipse.equinox.launcher.gtk.linux.x86/0.0.0\n     at org.eclipse.equinox.prov.director.NewDependencyExpander.collectMatches(NewDependencyExpander.java:174)\n     at org.eclipse.equinox.prov.director.NewDependencyExpander.algo(NewDependencyExpander.java:305)\n     at org.eclipse.equinox.prov.director.NewDependencyExpander.expand(NewDependencyExpander.java:107)\n     at org.eclipse.equinox.prov.director.NewSimpleDirector.install(NewSimpleDirector.java:65)",
    "Pascal and I have released a fix for this to HEAD."
  ],
  "commentCreationDates": [
    "2007-08-14T22:32:43+02:00",
    "2007-08-16T14:57:08+02:00"
  ],
  "traces": [
    {
      "exceptionType": "java.lang.IllegalStateException",
      "message": "Requirement not satisfied: requiredCapability: org.eclipse.equinox.prov.iunamespace/org.eclipse.equinox.launcher.gtk.linux.x86/0.0.0",
      "elements": [
        {
          "method": "org.eclipse.equinox.prov.director.NewDependencyExpander.collectMatches",
          "source": "NewDependencyExpander.java:174"
        },
        {
          "method": "org.eclipse.equinox.prov.director.NewDependencyExpander.algo",
          "source": "NewDependencyExpander.java:305"
        },
        {
          "method": "org.eclipse.equinox.prov.director.NewDependencyExpander.expand",
          "source": "NewDependencyExpander.java:107"
        },
        {
          "method": "org.eclipse.equinox.prov.director.NewSimpleDirector.install",
          "source": "NewSimpleDirector.java:65"
        }
      ],
      "number": 0,
      "commentIndex": 0,
      "bugId": "199956",
      "date": "2007-08-14T22:32:43+02:00",
      "product": "Equinox",
      "component": "Incubator",
      "severity": "normal"
    }
  ],
  "groupId": "199956",
  "bugId": "199956",
  "date": "2007-08-14T22:32:43+02:00",
  "product": "Equinox",
  "component": "Incubator",
  "severity": "normal"
}