{
  "comments": [
    "Build ID: WST\u003d200706260303\n\nSteps To Reproduce:\nThe TLD file included in different JAR might not be\nopened at the same time.\nThe name of the TLD file not opened is the same. \n\nEX) Java Pet Store Reference Application uses bp-ui-14.jar\n    and bp-ui-5.jar. ui.tld is included in of each file.\n\n1. Two files are stored in\n   (Web project)/WebContent/WEB-INF/lib folder.\n2. The ui.tld file of bp-ui-14.jar is opened\n   from the project Explorer. \n\n   (Project) \u003e Java Resoures: src\n     \u003e Libraries \u003e Web App Libraries\n        \u003e bp-ui-14.jar \u003e META-INF \u003e ui.tld\n\n3. The ui.tld file of bp-ui-5.jar is opened\n   from the project Explorer. \n\n   (Project) \u003e Java Resoures: src\n     \u003e Libraries \u003e Web App Libraries\n        \u003e bp-ui-5.jar \u003e META-INF \u003e ui.tld\n\n\nMore information:\nThe content of the TLD file is not displayed.\nThe following are displayed. \n\norg.eclipse.ui.PartInitException: Editor could not be initialized.\n\tat org.eclipse.ui.texteditor.AbstractTextEditor.internalInit(AbstractTextEditor.java:3035)\n\tat org.eclipse.ui.texteditor.AbstractTextEditor.init(AbstractTextEditor.java:3046)\n\tat org.eclipse.wst.sse.ui.StructuredTextEditor.init(StructuredTextEditor.java:2615)\n\tat org.eclipse.ui.part.MultiPageEditorPart.addPage(MultiPageEditorPart.java:186)\n\tat org.eclipse.ui.part.MultiPageEditorPart.addPage(MultiPageEditorPart.java:160)\n\tat org.eclipse.wst.xml.ui.internal.tabletree.XMLMultiPageEditorPart.addSourcePage(XMLMultiPageEditorPart.java:373)\n\tat org.eclipse.wst.xml.ui.internal.tabletree.XMLMultiPageEditorPart.createPages(XMLMultiPageEditorPart.java:543)\n   :",
    "I think that the following parts were problems.\n\norg.eclipse.wst.sse.ui\n  /src/org/eclipse/wst/sse/ui/internal/\n    StorageModelProvider.java\n\nThe calculateID method returns the full path character string\nin the JAR file as ID.\nThe JAR file name is not included in the character string. \n\nIn the loadModel method, the first parameter of\nStructuredModelManager.getModelManager().getModelForEdit method\nshould be unique. \n\nHowever, ui.tld encompassed by different JAR becomes the same ID\ncharacter string (/META-INF/ui.tld). \n\nWhat do you think ?\n"
  ],
  "commentCreationDates": [
    "2007-09-10T17:19:21+02:00",
    "2007-09-10T17:29:31+02:00"
  ],
  "traces": [
    {
      "exceptionType": "org.eclipse.ui.PartInitException",
      "message": "Editor could not be initialized.",
      "elements": [
        {
          "method": "org.eclipse.ui.texteditor.AbstractTextEditor.internalInit",
          "source": "AbstractTextEditor.java:3035"
        },
        {
          "method": "org.eclipse.ui.texteditor.AbstractTextEditor.init",
          "source": "AbstractTextEditor.java:3046"
        },
        {
          "method": "org.eclipse.wst.sse.ui.StructuredTextEditor.init",
          "source": "StructuredTextEditor.java:2615"
        },
        {
          "method": "org.eclipse.ui.part.MultiPageEditorPart.addPage",
          "source": "MultiPageEditorPart.java:186"
        },
        {
          "method": "org.eclipse.ui.part.MultiPageEditorPart.addPage",
          "source": "MultiPageEditorPart.java:160"
        },
        {
          "method": "org.eclipse.wst.xml.ui.internal.tabletree.XMLMultiPageEditorPart.addSourcePage",
          "source": "XMLMultiPageEditorPart.java:373"
        },
        {
          "method": "org.eclipse.wst.xml.ui.internal.tabletree.XMLMultiPageEditorPart.createPages",
          "source": "XMLMultiPageEditorPart.java:543"
        }
      ],
      "number": 0,
      "commentIndex": 0,
      "bugId": "202804",
      "date": "2007-09-10T17:19:21+02:00",
      "product": "Web Tools",
      "component": "wst.sse",
      "severity": "normal"
    }
  ],
  "groupId": "202804",
  "bugId": "202804",
  "date": "2007-09-10T17:19:21+02:00",
  "product": "Web Tools",
  "component": "wst.sse",
  "severity": "normal"
}