{
  "comments": [
    "Platform Validation Test failed on Apollo because of no org.junit_3.8.2.jar.\n\nI tested Platform Validation Test in latest DeviceKit weekly build ( 20070910 ) on Apollo, and found the org.eclipse.soda.dk.platform.validation.test.agent can not be started because it need junit 3.8.2 bundle. Since the Platform Validation Test is for open source to validate general OSGi platforms, it should include the proper junit bundle in the build.\n\norg.osgi.framework.BundleException: The bundle could not be resolved. Reason: Missing Constraint: Import-Package: junit.framework; version\u003d\"3.8.2\"\n        at org.eclipse.osgi.framework.internal.core.BundleHost.startWorker(BundleHost.java:302)\n        at org.eclipse.osgi.framework.internal.core.AbstractBundle.start(AbstractBundle.java:260)\n        at org.eclipse.osgi.framework.internal.core.AbstractBundle.start(AbstractBundle.java:252)\n        at org.eclipse.osgi.framework.internal.core.FrameworkCommandProvider._start(FrameworkCommandProvider.java:239)\n        at sun.reflect.NativeMethodAccessorImpl.invoke0(Native Method)\n        at sun.reflect.NativeMethodAccessorImpl.invoke(NativeMethodAccessorImpl.java:85)\n        at sun.reflect.NativeMethodAccessorImpl.invoke(NativeMethodAccessorImpl.java:58)\n        at sun.reflect.DelegatingMethodAccessorImpl.invoke(DelegatingMethodAccessorImpl.java:60)\n        at java.lang.reflect.Method.invoke(Method.java:391)\n        at org.eclipse.osgi.framework.internal.core.FrameworkCommandInterpreter.execute(FrameworkCommandInterpreter.java:145)\n        at org.eclipse.osgi.framework.internal.core.FrameworkConsole.docommand(FrameworkConsole.java:290)\n        at org.eclipse.osgi.framework.internal.core.FrameworkConsole.console(FrameworkConsole.java:275)\n        at org.eclipse.osgi.framework.internal.core.FrameworkConsole.run(FrameworkConsole.java:210)\n        at java.lang.Thread.run(Thread.java:568)"
  ],
  "commentCreationDates": [
    "2007-09-13T09:50:47+02:00"
  ],
  "traces": [
    {
      "exceptionType": "org.osgi.framework.BundleException",
      "message": "The bundle could not be resolved. Reason: Missing Constraint: Import-Package: junit.framework; version\u003d\"3.8.2\"",
      "elements": [
        {
          "method": "org.eclipse.osgi.framework.internal.core.BundleHost.startWorker",
          "source": "BundleHost.java:302"
        },
        {
          "method": "org.eclipse.osgi.framework.internal.core.AbstractBundle.start",
          "source": "AbstractBundle.java:260"
        },
        {
          "method": "org.eclipse.osgi.framework.internal.core.AbstractBundle.start",
          "source": "AbstractBundle.java:252"
        },
        {
          "method": "org.eclipse.osgi.framework.internal.core.FrameworkCommandProvider._start",
          "source": "FrameworkCommandProvider.java:239"
        },
        {
          "method": "sun.reflect.NativeMethodAccessorImpl.invoke0",
          "source": "Native Method"
        },
        {
          "method": "sun.reflect.NativeMethodAccessorImpl.invoke",
          "source": "NativeMethodAccessorImpl.java:85"
        },
        {
          "method": "sun.reflect.NativeMethodAccessorImpl.invoke",
          "source": "NativeMethodAccessorImpl.java:58"
        },
        {
          "method": "sun.reflect.DelegatingMethodAccessorImpl.invoke",
          "source": "DelegatingMethodAccessorImpl.java:60"
        },
        {
          "method": "java.lang.reflect.Method.invoke",
          "source": "Method.java:391"
        },
        {
          "method": "org.eclipse.osgi.framework.internal.core.FrameworkCommandInterpreter.execute",
          "source": "FrameworkCommandInterpreter.java:145"
        },
        {
          "method": "org.eclipse.osgi.framework.internal.core.FrameworkConsole.docommand",
          "source": "FrameworkConsole.java:290"
        },
        {
          "method": "org.eclipse.osgi.framework.internal.core.FrameworkConsole.console",
          "source": "FrameworkConsole.java:275"
        },
        {
          "method": "org.eclipse.osgi.framework.internal.core.FrameworkConsole.run",
          "source": "FrameworkConsole.java:210"
        },
        {
          "method": "java.lang.Thread.run",
          "source": "Thread.java:568"
        }
      ],
      "number": 0,
      "commentIndex": 0,
      "bugId": "203216",
      "date": "2007-09-13T09:50:47+02:00",
      "product": "OHF",
      "component": "DeviceKit",
      "severity": "major"
    }
  ],
  "groupId": "203216",
  "bugId": "203216",
  "date": "2007-09-13T09:50:47+02:00",
  "product": "OHF",
  "component": "DeviceKit",
  "severity": "major"
}