{
  "comments": [
    "DeviceKit latest weekly build ( 20070910 ) on Apollo, the Platform Validation Test can not be started because several bundles need javax.xml.parsers .\n\nosgi\u003e ss\n\nFramework is launched.\n\nid      State       Bundle\n0       ACTIVE      org.eclipse.osgi_3.3.0.v20070530\n1       ACTIVE      javax.servlet_2.4.0.v200706111738\n2       ACTIVE      org.eclipse.equinox.common_3.3.0.v20070426\n3       ACTIVE      org.eclipse.equinox.event_1.0.100.v20070516\n4       ACTIVE      org.eclipse.equinox.http_1.0.100.v20070423\n5       INSTALLED   org.eclipse.equinox.metatype_1.0.0.v20070226\n6       ACTIVE      org.eclipse.osgi.services_3.1.200.v20070605\n7       ACTIVE      org.eclipse.osgi.util_3.1.200.v20070605\n9       ACTIVE      org.eclipse.soda.dk.connection.service_1.1.0.200709101748\n10      ACTIVE      org.eclipse.soda.dk.core.service_1.1.0.200709101748\n11      ACTIVE      org.eclipse.soda.dk.core_1.1.0.200709101748\n12      ACTIVE      org.eclipse.soda.dk.device.bundle.servlet_1.1.0.200709101748\n13      ACTIVE      org.eclipse.soda.dk.device.configuration.servlet_1.1.0.200709101748\n14      ACTIVE      org.eclipse.soda.dk.device.device.servlet_1.1.0.200709101748\n15      ACTIVE      org.eclipse.soda.dk.device.metadata.servlet_1.1.0.200709101748\n16      ACTIVE      org.eclipse.soda.dk.device.property.servlet_1.1.0.200709101748\n17      ACTIVE      org.eclipse.soda.dk.device.service.servlet_1.1.0.200709101748\n18      ACTIVE      org.eclipse.soda.dk.device.service_1.1.0.200709101748\n19      ACTIVE      org.eclipse.soda.dk.device.servlet_1.1.0.200709101748\n20      ACTIVE      org.eclipse.soda.dk.notification.service_1.1.0.200709101748\n21      ACTIVE      org.eclipse.soda.dk.notification_1.1.0.200709101748\n22      ACTIVE      org.eclipse.soda.dk.testagent.bundle_1.1.0.200709101748\n23      ACTIVE      org.eclipse.soda.dk.testagent_1.1.0.200709101748\n24      ACTIVE      org.eclipse.soda.dk.testcontroller.bundle_1.1.0.200709101748\n25      ACTIVE      org.eclipse.soda.dk.testcontroller_1.1.0.200709101748\n26      INSTALLED   org.eclipse.soda.dk.testmanager.bundle_1.1.0.200709101748\n27      INSTALLED   org.eclipse.soda.dk.testmanager.servlet_1.1.0.200709101748\n28      INSTALLED   org.eclipse.soda.dk.testmanager_1.1.0.200709101748\n29      ACTIVE      org.eclipse.soda.dk.transport.service_1.1.0.200709101748\n30      ACTIVE      org.eclipse.soda.sat.core_1.1.0.200709052157\n31      ACTIVE      org.junit_3.8.2.200709130949\n32      ACTIVE      org.eclipse.soda.dk.platform.validation.test.agent_1.1.0.200709101748\n\nosgi\u003e start 5\norg.osgi.framework.BundleException: The bundle could not be resolved. Reason: Missing Constraint: Import-Package: javax.xml.parsers; version\u003d\"0.0.0\"\n        at org.eclipse.osgi.framework.internal.core.BundleHost.startWorker(BundleHost.java:305)\n        at org.eclipse.osgi.framework.internal.core.AbstractBundle.start(AbstractBundle.java:260)\n        at org.eclipse.osgi.framework.internal.core.AbstractBundle.start(AbstractBundle.java:252)\n        at org.eclipse.osgi.framework.internal.core.FrameworkCommandProvider._start(FrameworkCommandProvider.java:260)\n        at sun.reflect.GeneratedMethodAccessor2.invoke(Unknown Source)\n        at sun.reflect.DelegatingMethodAccessorImpl.invoke(DelegatingMethodAccessorImpl.java:62)\n        at java.lang.reflect.Method.invoke(Method.java:391)\n        at org.eclipse.osgi.framework.internal.core.FrameworkCommandInterpreter.execute(FrameworkCommandInterpreter.java:145)\n        at org.eclipse.osgi.framework.internal.core.FrameworkConsole.docommand(FrameworkConsole.java:291)\n        at org.eclipse.osgi.framework.internal.core.FrameworkConsole.console(FrameworkConsole.java:276)\n        at org.eclipse.osgi.framework.internal.core.FrameworkConsole.run(FrameworkConsole.java:218)\n        at java.lang.Thread.run(Thread.java:568)\n\nosgi\u003e start 28\norg.osgi.framework.BundleException: The bundle could not be resolved. Reason: Missing Constraint: Import-Package: javax.xml.parsers; version\u003d\"0.0.0\"\n        at org.eclipse.osgi.framework.internal.core.BundleHost.startWorker(BundleHost.java:305)\n        at org.eclipse.osgi.framework.internal.core.AbstractBundle.start(AbstractBundle.java:260)\n        at org.eclipse.osgi.framework.internal.core.AbstractBundle.start(AbstractBundle.java:252)\n        at org.eclipse.osgi.framework.internal.core.FrameworkCommandProvider._start(FrameworkCommandProvider.java:260)\n        at sun.reflect.GeneratedMethodAccessor2.invoke(Unknown Source)\n        at sun.reflect.DelegatingMethodAccessorImpl.invoke(DelegatingMethodAccessorImpl.java:62)\n        at java.lang.reflect.Method.invoke(Method.java:391)\n        at org.eclipse.osgi.framework.internal.core.FrameworkCommandInterpreter.execute(FrameworkCommandInterpreter.java:145)\n        at org.eclipse.osgi.framework.internal.core.FrameworkConsole.docommand(FrameworkConsole.java:291)\n        at org.eclipse.osgi.framework.internal.core.FrameworkConsole.console(FrameworkConsole.java:276)\n        at org.eclipse.osgi.framework.internal.core.FrameworkConsole.run(FrameworkConsole.java:218)\n        at java.lang.Thread.run(Thread.java:568)",
    "Created an attachment (id\u003d80670)\npatch for documentation for xml issue\n\n",
    "Patch applied and committed.",
    "Fixed in latest DK build."
  ],
  "commentCreationDates": [
    "2007-09-14T04:53:03+02:00",
    "2007-10-18T17:21:05+02:00",
    "2007-10-18T17:25:49+02:00",
    "2007-12-10T19:28:53+01:00"
  ],
  "traces": [
    {
      "exceptionType": "org.osgi.framework.BundleException",
      "message": "The bundle could not be resolved. Reason: Missing Constraint: Import-Package: javax.xml.parsers; version\u003d\"0.0.0\"",
      "elements": [
        {
          "method": "org.eclipse.osgi.framework.internal.core.BundleHost.startWorker",
          "source": "BundleHost.java:305"
        },
        {
          "method": "org.eclipse.osgi.framework.internal.core.AbstractBundle.start",
          "source": "AbstractBundle.java:260"
        },
        {
          "method": "org.eclipse.osgi.framework.internal.core.AbstractBundle.start",
          "source": "AbstractBundle.java:252"
        },
        {
          "method": "org.eclipse.osgi.framework.internal.core.FrameworkCommandProvider._start",
          "source": "FrameworkCommandProvider.java:260"
        },
        {
          "method": "sun.reflect.GeneratedMethodAccessor2.invoke",
          "source": "Unknown Source"
        },
        {
          "method": "sun.reflect.DelegatingMethodAccessorImpl.invoke",
          "source": "DelegatingMethodAccessorImpl.java:62"
        },
        {
          "method": "java.lang.reflect.Method.invoke",
          "source": "Method.java:391"
        },
        {
          "method": "org.eclipse.osgi.framework.internal.core.FrameworkCommandInterpreter.execute",
          "source": "FrameworkCommandInterpreter.java:145"
        },
        {
          "method": "org.eclipse.osgi.framework.internal.core.FrameworkConsole.docommand",
          "source": "FrameworkConsole.java:291"
        },
        {
          "method": "org.eclipse.osgi.framework.internal.core.FrameworkConsole.console",
          "source": "FrameworkConsole.java:276"
        },
        {
          "method": "org.eclipse.osgi.framework.internal.core.FrameworkConsole.run",
          "source": "FrameworkConsole.java:218"
        },
        {
          "method": "java.lang.Thread.run",
          "source": "Thread.java:568"
        }
      ],
      "number": 0,
      "commentIndex": 0,
      "bugId": "203398",
      "date": "2007-09-14T04:53:03+02:00",
      "product": "OHF",
      "component": "DeviceKit",
      "severity": "critical"
    },
    {
      "exceptionType": "org.osgi.framework.BundleException",
      "message": "The bundle could not be resolved. Reason: Missing Constraint: Import-Package: javax.xml.parsers; version\u003d\"0.0.0\"",
      "elements": [
        {
          "method": "org.eclipse.osgi.framework.internal.core.BundleHost.startWorker",
          "source": "BundleHost.java:305"
        },
        {
          "method": "org.eclipse.osgi.framework.internal.core.AbstractBundle.start",
          "source": "AbstractBundle.java:260"
        },
        {
          "method": "org.eclipse.osgi.framework.internal.core.AbstractBundle.start",
          "source": "AbstractBundle.java:252"
        },
        {
          "method": "org.eclipse.osgi.framework.internal.core.FrameworkCommandProvider._start",
          "source": "FrameworkCommandProvider.java:260"
        },
        {
          "method": "sun.reflect.GeneratedMethodAccessor2.invoke",
          "source": "Unknown Source"
        },
        {
          "method": "sun.reflect.DelegatingMethodAccessorImpl.invoke",
          "source": "DelegatingMethodAccessorImpl.java:62"
        },
        {
          "method": "java.lang.reflect.Method.invoke",
          "source": "Method.java:391"
        },
        {
          "method": "org.eclipse.osgi.framework.internal.core.FrameworkCommandInterpreter.execute",
          "source": "FrameworkCommandInterpreter.java:145"
        },
        {
          "method": "org.eclipse.osgi.framework.internal.core.FrameworkConsole.docommand",
          "source": "FrameworkConsole.java:291"
        },
        {
          "method": "org.eclipse.osgi.framework.internal.core.FrameworkConsole.console",
          "source": "FrameworkConsole.java:276"
        },
        {
          "method": "org.eclipse.osgi.framework.internal.core.FrameworkConsole.run",
          "source": "FrameworkConsole.java:218"
        },
        {
          "method": "java.lang.Thread.run",
          "source": "Thread.java:568"
        }
      ],
      "number": 1,
      "commentIndex": 0,
      "bugId": "203398",
      "date": "2007-09-14T04:53:03+02:00",
      "product": "OHF",
      "component": "DeviceKit",
      "severity": "critical"
    }
  ],
  "groupId": "203398",
  "bugId": "203398",
  "date": "2007-09-14T04:53:03+02:00",
  "product": "OHF",
  "component": "DeviceKit",
  "severity": "critical"
}