{
  "comments": [
    "Build ID: I\n\nSteps To Reproduce:\n1. In RAP demo comment this line (in theme.properties):\n#shell.title.inactive.bgimage: /theme1/icons/titlebar.png\n2. Launch application\n3. Call application from browser and then It appears in console:\n\njava.lang.IllegalArgumentException: Resource \u0027resource/widget/rap/window/caption_inactive.gif\u0027 not found for theme \u0027Alternative Demo Theme\u0027\n\tat org.eclipse.rwt.internal.theme.ThemeManager.registerWidgetImages(ThemeManager.java:632)\n\tat org.eclipse.rwt.internal.theme.ThemeManager.registerThemeFiles(ThemeManager.java:561)\n\tat org.eclipse.rwt.internal.theme.ThemeManager.registerResources(ThemeManager.java:282)\n\tat org.eclipse.swt.internal.widgets.displaykit.DisplayLCA.writeLibraries(DisplayLCA.java:201)\n\n\n\nMore information:\nI\u0027m using the latest CVS version of RAP projects.\n\nThis problem only happens if you register a theme and don\u0027t define a value for \"shell.title.inactive.bgimage\" property then when RAP application tries to register default image for this property fails, but Image file is in project and all seems to be OK.",
    "The ThemeManager tried to load the image with the wrong ResourceLoader.\nFixed in CVS HEAD. "
  ],
  "commentCreationDates": [
    "2007-09-16T10:08:42+02:00",
    "2007-09-17T18:51:26+02:00"
  ],
  "traces": [
    {
      "exceptionType": "java.lang.IllegalArgumentException",
      "message": "Resource \u0027resource/widget/rap/window/caption_inactive.gif\u0027 not found for theme \u0027Alternative Demo Theme\u0027",
      "elements": [
        {
          "method": "org.eclipse.rwt.internal.theme.ThemeManager.registerWidgetImages",
          "source": "ThemeManager.java:632"
        },
        {
          "method": "org.eclipse.rwt.internal.theme.ThemeManager.registerThemeFiles",
          "source": "ThemeManager.java:561"
        },
        {
          "method": "org.eclipse.rwt.internal.theme.ThemeManager.registerResources",
          "source": "ThemeManager.java:282"
        },
        {
          "method": "org.eclipse.swt.internal.widgets.displaykit.DisplayLCA.writeLibraries",
          "source": "DisplayLCA.java:201"
        }
      ],
      "number": 0,
      "commentIndex": 0,
      "bugId": "203531",
      "date": "2007-09-16T10:08:42+02:00",
      "product": "RAP",
      "component": "RWT",
      "severity": "normal"
    }
  ],
  "groupId": "203531",
  "bugId": "203531",
  "date": "2007-09-16T10:08:42+02:00",
  "product": "RAP",
  "component": "RWT",
  "severity": "normal"
}