{
  "comments": [
    "I often get this in my .metafile/.log.\nThe easiest operation I know of that results in this is to create a new C Executable project with \"Linux GCC\" as Toolchain.\n\n!ENTRY org.eclipse.equinox.registry 4 1 2007-09-19 17:43:48.077\n!MESSAGE Plug-in com.intel.compiler.cdt.managedbuilder.ui was unable to load class \n\norg.eclipse.cdt.managedbuilder.internal.scannerconfig.DefaultGCCScannerInfoCollector.\n!STACK 0\njava.lang.ClassNotFoundException: org.eclipse.cdt.managedbuilder.internal.scannerconfig.DefaultGCCScannerInfoCollector\n        at java.lang.ClassLoader.findClass(ClassLoader.java:341)\n        at java.lang.ClassLoader.loadClass(ClassLoader.java:289)\n        at java.lang.ClassLoader.loadClass(ClassLoader.java:235)\n        at org.eclipse.osgi.framework.internal.core.BundleLoader.findClassInternal(BundleLoader.java:429)\n        at org.eclipse.osgi.framework.internal.core.BundleLoader.findClass(BundleLoader.java:369)\n        at org.eclipse.osgi.framework.internal.core.BundleLoader.findClass(BundleLoader.java:357)\n        at org.eclipse.osgi.internal.baseadaptor.DefaultClassLoader.loadClass(DefaultClassLoader.java:83)\n        at java.lang.ClassLoader.loadClass(ClassLoader.java:235)\n        at org.eclipse.osgi.framework.internal.core.BundleLoader.loadClass(BundleLoader.java:289)\n        at org.eclipse.osgi.framework.internal.core.BundleHost.loadClass(BundleHost.java:227)\n        at org.eclipse.osgi.framework.internal.core.AbstractBundle.loadClass(AbstractBundle.java:1269)\n        at org.eclipse.core.internal.registry.osgi.RegistryStrategyOSGI.createExecutableExtension(RegistryStrategyOSGI.java:160)\n        at org.eclipse.core.internal.registry.ExtensionRegistry.createExecutableExtension(ExtensionRegistry.java:788)\n        at org.eclipse.core.internal.registry.ConfigurationElement.createExecutableExtension(ConfigurationElement.java:243)\n        at org.eclipse.core.internal.registry.ConfigurationElementHandle.createExecutableExtension(ConfigurationElementHandle.java:51)",
    "My guess is that you\u0027re are referencing this class within Intel compiler plug-ins.\nThe class resides within internal package that is not exported, i.e. ISVs should not use it. You could implement your own one instead.\n\nMikhail\n",
    "(In reply to comment #1)\nI am sorry. I naively assumed it was a CDT problem since it reproduced with a gnu toolchain, but this does seem to be our problem since it does not reproduce without our plug-in, and I did find a reference in our code. Please close.",
    "(In reply to comment #2)\nNo problem.. closing"
  ],
  "commentCreationDates": [
    "2007-09-19T23:53:54+02:00",
    "2007-09-20T13:00:34+02:00",
    "2007-09-20T22:56:06+02:00",
    "2007-09-21T11:54:22+02:00"
  ],
  "traces": [
    {
      "exceptionType": "java.lang.ClassNotFoundException",
      "message": "org.eclipse.cdt.managedbuilder.internal.scannerconfig.DefaultGCCScannerInfoCollector",
      "elements": [
        {
          "method": "java.lang.ClassLoader.findClass",
          "source": "ClassLoader.java:341"
        },
        {
          "method": "java.lang.ClassLoader.loadClass",
          "source": "ClassLoader.java:289"
        },
        {
          "method": "java.lang.ClassLoader.loadClass",
          "source": "ClassLoader.java:235"
        },
        {
          "method": "org.eclipse.osgi.framework.internal.core.BundleLoader.findClassInternal",
          "source": "BundleLoader.java:429"
        },
        {
          "method": "org.eclipse.osgi.framework.internal.core.BundleLoader.findClass",
          "source": "BundleLoader.java:369"
        },
        {
          "method": "org.eclipse.osgi.framework.internal.core.BundleLoader.findClass",
          "source": "BundleLoader.java:357"
        },
        {
          "method": "org.eclipse.osgi.internal.baseadaptor.DefaultClassLoader.loadClass",
          "source": "DefaultClassLoader.java:83"
        },
        {
          "method": "java.lang.ClassLoader.loadClass",
          "source": "ClassLoader.java:235"
        },
        {
          "method": "org.eclipse.osgi.framework.internal.core.BundleLoader.loadClass",
          "source": "BundleLoader.java:289"
        },
        {
          "method": "org.eclipse.osgi.framework.internal.core.BundleHost.loadClass",
          "source": "BundleHost.java:227"
        },
        {
          "method": "org.eclipse.osgi.framework.internal.core.AbstractBundle.loadClass",
          "source": "AbstractBundle.java:1269"
        },
        {
          "method": "org.eclipse.core.internal.registry.osgi.RegistryStrategyOSGI.createExecutableExtension",
          "source": "RegistryStrategyOSGI.java:160"
        },
        {
          "method": "org.eclipse.core.internal.registry.ExtensionRegistry.createExecutableExtension",
          "source": "ExtensionRegistry.java:788"
        },
        {
          "method": "org.eclipse.core.internal.registry.ConfigurationElement.createExecutableExtension",
          "source": "ConfigurationElement.java:243"
        },
        {
          "method": "org.eclipse.core.internal.registry.ConfigurationElementHandle.createExecutableExtension",
          "source": "ConfigurationElementHandle.java:51"
        }
      ],
      "number": 0,
      "commentIndex": 0,
      "bugId": "204043",
      "date": "2007-09-19T23:53:54+02:00",
      "product": "CDT",
      "component": "cdt-build",
      "severity": "enhancement"
    }
  ],
  "groupId": "204043",
  "bugId": "204043",
  "date": "2007-09-19T23:53:54+02:00",
  "product": "CDT",
  "component": "cdt-build",
  "severity": "enhancement"
}