{
  "comments": [
    "Hi,\n\n        I have updated birt 2.2 runtime files. \n\nOS - linux\nwebserver - Tomcat\n\nI try to run birt report files, report files are created by eclipse 3.2 version.\n\nEclipse SDK\nVersion: 3.2.0\nBuild id: I20060602-1317\n\nI am getting this error like below\n\norg.eclipse.birt.report.engine.api.EngineException: Some required parameter values are not set or set to incompatible data type.\n        at org.eclipse.birt.report.engine.api.impl.RunTask.doRun(RunTask.java:182)\n        at org.eclipse.birt.report.engine.api.impl.RunTask.run(RunTask.java:87)\n        at com.efrontier.webapps.express.common.core.BirtUtils.runReport(BirtUtils.java:1887)\n        at com.efrontier.webapps.express.common.struts.BirtExpressAction.execute(BirtExpressAction.java:83)\n        at org.apache.struts.action.RequestProcessor.processActionPerform(RequestProcessor.java:484)\n        at org.apache.struts.action.RequestProcessor.process(RequestProcessor.java:274)\n        at org.apache.struts.action.ActionServlet.process(ActionServlet.java:1482)\n        at org.apache.struts.action.ActionServlet.doGet(ActionServlet.java:507)\n        at javax.servlet.http.HttpServlet.service(HttpServlet.java:690)\n        at javax.servlet.http.HttpServlet.service(HttpServlet.java:803)\n        at org.apache.catalina.core.ApplicationFilterChain.internalDoFilter(ApplicationFilterChain.java:290)\n        at org.apache.catalina.core.ApplicationFilterChain.doFilter(ApplicationFilterChain.java:206)\n        at com.efrontier.common.cas.sso.EFCASFilter.doFilter(EFCASFilter.java:457)\n        at org.apache.catalina.core.ApplicationFilterChain.internalDoFilter(ApplicationFilterChain.java:235)\n        at org.apache.catalina.core.ApplicationFilterChain.doFilter(ApplicationFilterChain.java:206)\n        at org.apache.webapp.balancer.BalancerFilter.doFilter(BalancerFilter.java:131)\n        at org.apache.catalina.core.ApplicationFilterChain.internalDoFilter(ApplicationFilterChain.java:235)\n        at org.apache.catalina.core.ApplicationFilterChain.doFilter(ApplicationFilterChain.java:206)\n        at com.efrontier.webapps.acm.common.struts.AccessLogFilter.doFilter(AccessLogFilter.java:172)\n        at org.apache.catalina.core.ApplicationFilterChain.internalDoFilter(ApplicationFilterChain.java:235)\n        at org.apache.catalina.core.ApplicationFilterChain.doFilter(ApplicationFilterChain.java:206)\n        at com.efrontier.webapps.acm.common.struts.EncodingEnforcingFilter.doFilter(EncodingEnforcingFilter.java:46)\n        at org.apache.catalina.core.ApplicationFilterChain.internalDoFilter(ApplicationFilterChain.java:235)\n        at org.apache.catalina.core.ApplicationFilterChain.doFilter(ApplicationFilterChain.java:206)\n        at org.apache.catalina.core.StandardWrapperValve.invoke(StandardWrapperValve.java:216)\n        at org.apache.catalina.core.StandardContextValve.invoke(StandardContextValve.java:175)\n        at org.apache.catalina.core.StandardHostValve.invoke(StandardHostValve.java:128)\n        at org.apache.catalina.valves.ErrorReportValve.invoke(ErrorReportValve.java:104)\n        at org.apache.catalina.valves.AccessLogValve.invoke(AccessLogValve.java:563)\n        at org.apache.catalina.core.StandardEngineValve.invoke(StandardEngineValve.java:109)\n        at org.apache.catalina.connector.CoyoteAdapter.service(CoyoteAdapter.java:261)\n        at org.apache.coyote.http11.Http11Processor.process(Http11Processor.java:844)\n        at org.apache.coyote.http11.Http11Protocol$Http11ConnectionHandler.process(Http11Protocol.java:581)\n        at org.apache.tomcat.util.net.JIoEndpoint$Worker.run(JIoEndpoint.java:447)\n        at java.lang.Thread.run(Thread.java:595)\n\n\n\nNote :\n\n        This problem occurs only report which contains scalar parameter.\n\n\ncan you suggest me if I missed anything.\n\nRegards\nEnnigo",
    "It seems that you defined some parameter in the report design but don\u0027t set the value in runTask.\n\n\n",
    "Hi wei yan,\n\n       The same report is working on BIRT 2.1 series. even I tried with sample report from birt runtime folder ie test1.rptdesign, its giving same error.\n\n-ennigo",
    "can you attach the report design?\n\nthanks.",
    "Created an attachment (id\u003d78950)\nrptdesign file\n\n",
    "I have tested your report design in both 2.2 release and 2.2.1 daily build 2007-09-20, it generates the report successfully.\n\nThere are two parameters in your report design, one is string type, not null, not blank, default to \"test\", the other is decimal type, default to 12.0. If you need set the value for those parameters, notice that parameter value should be String and Number.\n\nYou can run that report without any parameter setting as both of them has default values.\n\nFor the sample report, as the parameter has no default value, so it must be set before running, otherwise the exception will be thrown out.\n\nYou need ensure that the parameters are setting correct before running it. If there still exits problems, please try to download the latest build and re-try.\n\nAs it works in my build, so I set it works for me.\n\nthanks.\n\n\n\n",
    "Hi,\n\n1)   I have found another probelm in Birt 2.2, I have parameter with string type, not null,not blank, default to \"ask\", when I ran the report , it will disappears from UI.\n\n2) i have set default value as null in same parameter, it throws runtime exception\n\ncan you suggest me if I miss anything.\n\nRegards\nEnnigo",
    "If it is disappeared from the UI, the most possible reason is it is set to hidden. can you check your report design to see if the parameter is \"hidden\"?\n\nAs you has declare that the string parameter value to NOT NULL, NOT BLANK, you can\u0027t set the default value to NULL. You can either remove the NOT NULL/NOT BLANK or change the default value to not NULL.\n\nthanks.",
    "works for me"
  ],
  "commentCreationDates": [
    "2007-09-20T15:26:41+02:00",
    "2007-09-21T03:13:39+02:00",
    "2007-09-21T06:56:44+02:00",
    "2007-09-21T09:13:10+02:00",
    "2007-09-21T11:26:38+02:00",
    "2007-09-24T04:49:34+02:00",
    "2007-09-25T15:55:16+02:00",
    "2007-09-26T01:25:40+02:00",
    "2007-10-22T05:39:55+02:00"
  ],
  "traces": [
    {
      "exceptionType": "org.eclipse.birt.report.engine.api.EngineException",
      "message": "Some required parameter values are not set or set to incompatible data type.",
      "elements": [
        {
          "method": "org.eclipse.birt.report.engine.api.impl.RunTask.doRun",
          "source": "RunTask.java:182"
        },
        {
          "method": "org.eclipse.birt.report.engine.api.impl.RunTask.run",
          "source": "RunTask.java:87"
        },
        {
          "method": "com.efrontier.webapps.express.common.core.BirtUtils.runReport",
          "source": "BirtUtils.java:1887"
        },
        {
          "method": "com.efrontier.webapps.express.common.struts.BirtExpressAction.execute",
          "source": "BirtExpressAction.java:83"
        },
        {
          "method": "org.apache.struts.action.RequestProcessor.processActionPerform",
          "source": "RequestProcessor.java:484"
        },
        {
          "method": "org.apache.struts.action.RequestProcessor.process",
          "source": "RequestProcessor.java:274"
        },
        {
          "method": "org.apache.struts.action.ActionServlet.process",
          "source": "ActionServlet.java:1482"
        },
        {
          "method": "org.apache.struts.action.ActionServlet.doGet",
          "source": "ActionServlet.java:507"
        },
        {
          "method": "javax.servlet.http.HttpServlet.service",
          "source": "HttpServlet.java:690"
        },
        {
          "method": "javax.servlet.http.HttpServlet.service",
          "source": "HttpServlet.java:803"
        },
        {
          "method": "org.apache.catalina.core.ApplicationFilterChain.internalDoFilter",
          "source": "ApplicationFilterChain.java:290"
        },
        {
          "method": "org.apache.catalina.core.ApplicationFilterChain.doFilter",
          "source": "ApplicationFilterChain.java:206"
        },
        {
          "method": "com.efrontier.common.cas.sso.EFCASFilter.doFilter",
          "source": "EFCASFilter.java:457"
        },
        {
          "method": "org.apache.catalina.core.ApplicationFilterChain.internalDoFilter",
          "source": "ApplicationFilterChain.java:235"
        },
        {
          "method": "org.apache.catalina.core.ApplicationFilterChain.doFilter",
          "source": "ApplicationFilterChain.java:206"
        },
        {
          "method": "org.apache.webapp.balancer.BalancerFilter.doFilter",
          "source": "BalancerFilter.java:131"
        },
        {
          "method": "org.apache.catalina.core.ApplicationFilterChain.internalDoFilter",
          "source": "ApplicationFilterChain.java:235"
        },
        {
          "method": "org.apache.catalina.core.ApplicationFilterChain.doFilter",
          "source": "ApplicationFilterChain.java:206"
        },
        {
          "method": "com.efrontier.webapps.acm.common.struts.AccessLogFilter.doFilter",
          "source": "AccessLogFilter.java:172"
        },
        {
          "method": "org.apache.catalina.core.ApplicationFilterChain.internalDoFilter",
          "source": "ApplicationFilterChain.java:235"
        },
        {
          "method": "org.apache.catalina.core.ApplicationFilterChain.doFilter",
          "source": "ApplicationFilterChain.java:206"
        },
        {
          "method": "com.efrontier.webapps.acm.common.struts.EncodingEnforcingFilter.doFilter",
          "source": "EncodingEnforcingFilter.java:46"
        },
        {
          "method": "org.apache.catalina.core.ApplicationFilterChain.internalDoFilter",
          "source": "ApplicationFilterChain.java:235"
        },
        {
          "method": "org.apache.catalina.core.ApplicationFilterChain.doFilter",
          "source": "ApplicationFilterChain.java:206"
        },
        {
          "method": "org.apache.catalina.core.StandardWrapperValve.invoke",
          "source": "StandardWrapperValve.java:216"
        },
        {
          "method": "org.apache.catalina.core.StandardContextValve.invoke",
          "source": "StandardContextValve.java:175"
        },
        {
          "method": "org.apache.catalina.core.StandardHostValve.invoke",
          "source": "StandardHostValve.java:128"
        },
        {
          "method": "org.apache.catalina.valves.ErrorReportValve.invoke",
          "source": "ErrorReportValve.java:104"
        },
        {
          "method": "org.apache.catalina.valves.AccessLogValve.invoke",
          "source": "AccessLogValve.java:563"
        },
        {
          "method": "org.apache.catalina.core.StandardEngineValve.invoke",
          "source": "StandardEngineValve.java:109"
        },
        {
          "method": "org.apache.catalina.connector.CoyoteAdapter.service",
          "source": "CoyoteAdapter.java:261"
        },
        {
          "method": "org.apache.coyote.http11.Http11Processor.process",
          "source": "Http11Processor.java:844"
        },
        {
          "method": "org.apache.coyote.http11.Http11Protocol$Http11ConnectionHandler.process",
          "source": "Http11Protocol.java:581"
        },
        {
          "method": "org.apache.tomcat.util.net.JIoEndpoint$Worker.run",
          "source": "JIoEndpoint.java:447"
        },
        {
          "method": "java.lang.Thread.run",
          "source": "Thread.java:595"
        }
      ],
      "number": 0,
      "commentIndex": 0,
      "bugId": "204113",
      "date": "2007-09-20T15:26:41+02:00",
      "product": "BIRT",
      "component": "Report Engine",
      "severity": "normal"
    }
  ],
  "groupId": "204113",
  "bugId": "204113",
  "date": "2007-09-20T15:26:41+02:00",
  "product": "BIRT",
  "component": "Report Engine",
  "severity": "normal"
}