{
  "comments": [
    "Created an attachment (id\u003d79077)\nPlugins view in action\n\nBuild ID: M20070212-1330\n\nSteps To Reproduce:\n1. There is a plugin for Eclipse which displays graphical figures in its editor part and uses thumbnail view in the Outline View to show small version of the editor\u0027s content.\n\n2. Outline View is synchronized with the editor, if mouse selects same region in the Outline this region gets focus in the editor, dragging the region is available.\n\n3. Seldom when reopening the editor view and doing mouse clicking and dragging in the Outline the exception is thrown.\n\n4. During debugging in the event queue mouseDragged event comes before mouseClicked event. Thus startLocation variable is not initialized.\n\n5. My plugun\u0027s classes do NOT override the default behavior of the IFigure or other core Eclipse classes.\n\nIn other words:\nThis exception occurs in the private class ScrollSynchronizer of the ScrollableThumbnail  class when mouseDragged() method is called before mousePressed() method. The cause is that variable startLocation is set only in the mousePressed() method and than is used in mouseDragged(). If  mouseDragged() called first this variable is null and exception is thrown.\n\nSee also the same problem on dev.eclipse.org:\nhttp://dev.eclipse.org/newslists/news.eclipse.tools.gef/msg07255.html\n\n\nMore information - Exception Details:\njava.lang.NullPointerException\n        at org.eclipse.draw2d.geometry.Point.getDifference(Point.java:111)\n        at org.eclipse.draw2d.parts.ScrollableThumbnail.mouseDragged(ScrollableThumbnail.java:88)\n        at org.eclipse.draw2d.Figure.handleMouseDragged(Figure.java:823)\n        at org.eclipse.draw2d.SWTEventDispatcher.dispatchMouseMoved(SWTEventDispatcher.java:227)\n        at org.eclipse.draw2d.LightweightSystem.mouseMove(LightweightSystem.java:533)\n        at org.eclipse.swt.widgets.TypedListener.handleEvent(TypedListener.java:145)\n        at org.eclipse.swt.widgets.EventTable.sendEvent(EventTable.java:66)\n        at org.eclipse.swt.widgets.Widget.sendEvent(Widget.java:1085)\n        at org.eclipse.swt.widgets.Display.runDeferredEvents(Display.java:3166)\n        at org.eclipse.swt.widgets.Display.readAndDispatch(Display.java:2842)\n        at org.eclipse.ui.internal.Workbench.runEventLoop(Workbench.java:1914)\n        at org.eclipse.ui.internal.Workbench.runUI(Workbench.java:1878)\n        at org.eclipse.ui.internal.Workbench.createAndRunWorkbench(Workbench.java:419)\n        at org.eclipse.ui.PlatformUI.createAndRunWorkbench(PlatformUI.java:149)\n        at org.eclipse.ui.internal.ide.IDEApplication.run(IDEApplication.java:95)\n        at org.eclipse.core.internal.runtime.PlatformActivator$1.run(PlatformActivator.java:78)",
    "Moving to GEF"
  ],
  "commentCreationDates": [
    "2007-09-24T16:47:50+02:00",
    "2007-10-04T02:48:59+02:00"
  ],
  "traces": [
    {
      "exceptionType": "java.lang.NullPointerException",
      "elements": [
        {
          "method": "org.eclipse.draw2d.geometry.Point.getDifference",
          "source": "Point.java:111"
        },
        {
          "method": "org.eclipse.draw2d.parts.ScrollableThumbnail.mouseDragged",
          "source": "ScrollableThumbnail.java:88"
        },
        {
          "method": "org.eclipse.draw2d.Figure.handleMouseDragged",
          "source": "Figure.java:823"
        },
        {
          "method": "org.eclipse.draw2d.SWTEventDispatcher.dispatchMouseMoved",
          "source": "SWTEventDispatcher.java:227"
        },
        {
          "method": "org.eclipse.draw2d.LightweightSystem.mouseMove",
          "source": "LightweightSystem.java:533"
        },
        {
          "method": "org.eclipse.swt.widgets.TypedListener.handleEvent",
          "source": "TypedListener.java:145"
        },
        {
          "method": "org.eclipse.swt.widgets.EventTable.sendEvent",
          "source": "EventTable.java:66"
        },
        {
          "method": "org.eclipse.swt.widgets.Widget.sendEvent",
          "source": "Widget.java:1085"
        },
        {
          "method": "org.eclipse.swt.widgets.Display.runDeferredEvents",
          "source": "Display.java:3166"
        },
        {
          "method": "org.eclipse.swt.widgets.Display.readAndDispatch",
          "source": "Display.java:2842"
        },
        {
          "method": "org.eclipse.ui.internal.Workbench.runEventLoop",
          "source": "Workbench.java:1914"
        },
        {
          "method": "org.eclipse.ui.internal.Workbench.runUI",
          "source": "Workbench.java:1878"
        },
        {
          "method": "org.eclipse.ui.internal.Workbench.createAndRunWorkbench",
          "source": "Workbench.java:419"
        },
        {
          "method": "org.eclipse.ui.PlatformUI.createAndRunWorkbench",
          "source": "PlatformUI.java:149"
        },
        {
          "method": "org.eclipse.ui.internal.ide.IDEApplication.run",
          "source": "IDEApplication.java:95"
        },
        {
          "method": "org.eclipse.core.internal.runtime.PlatformActivator$1.run",
          "source": "PlatformActivator.java:78"
        }
      ],
      "number": 0,
      "commentIndex": 0,
      "bugId": "204460",
      "date": "2007-09-24T16:47:50+02:00",
      "product": "GEF",
      "component": "draw2d",
      "severity": "normal"
    }
  ],
  "groupId": "204460",
  "bugId": "204460",
  "date": "2007-09-24T16:47:50+02:00",
  "product": "GEF",
  "component": "draw2d",
  "severity": "normal"
}