{
  "comments": [
    "Build ID: I20070625-1500\n\nSteps To Reproduce:\nEnter the following code into an editor:\n\npackage net.lunglet.gridgain;\n\nimport java.io.Serializable;\nimport java.util.ArrayList;\nimport java.util.Arrays;\nimport java.util.Collection;\nimport java.util.List;\n\nimport org.gridgain.grid.Grid;\nimport org.gridgain.grid.GridException;\nimport org.gridgain.grid.GridJob;\nimport org.gridgain.grid.GridJobAdapter;\nimport org.gridgain.grid.GridJobResult;\nimport org.gridgain.grid.GridTaskSplitAdapter;\nimport org.gridgain.grid.resources.GridInstanceResource;\n\npublic final class GemmGridTask extends GridTaskSplitAdapter\u003cString\u003e {\n    private static final long serialVersionUID \u003d 1L;\n\n    @Override\n    public Collection\u003c? extends GridJob\u003e split(final int gridSize, final String arg) throws GridException {\n        List\u003cGridJob\u003e jobs \u003d new ArrayList\u003cGridJob\u003e();\n        for (int i \u003d 0; i \u003c 10; i++) {\n            jobs.add(new GridJobAdapter\u003cString\u003e(word) {\n                private static final long serialVersionUID \u003d 1L;\n\n                private Grid grid \u003d null;\n\n                public Serializable execute() throws GridException {\n                    return null;\n                }\n\n                @GridInstanceResource\n                public void setGrid(final Grid grid) {\n                    this.grid \u003d grid;\n                }\n            });\n        }\n        return jobs;\n    }\n\n    public Serializable reduce(List\u003cGridJobResult\u003e results) throws GridException {\n        return null;\n    }\n}\n\nWith all the class libraries in place, the only error in the above code is that in\n\njobs.add(new GridJobAdapter\u003cString\u003e(word) {\n\nword cannot be resolved.\n\nIf I now click on GridJobAdapter there and then do Open Declaration, I get a popup telling me to check the error log which then contains the following exception:\n\neclipse.buildId\u003dI20070625-1500\njava.version\u003d1.6.0_02\njava.vendor\u003dSun Microsystems Inc.\nBootLoader constants: OS\u003dwin32, ARCH\u003dx86, WS\u003dwin32, NL\u003den_ZA\nCommand-line arguments:  -os win32 -ws win32 -arch x86\n\nError\nMon Sep 24 10:40:20 CAT 2007\nUnhandled event loop exception\n\njava.lang.NullPointerException\nat org.eclipse.jdt.internal.codeassist.select.SelectionOnQualifiedAllocationExpression.resolveType(SelectionOnQualifiedAllocationExpression.java:75)\nat org.eclipse.jdt.internal.compiler.ast.Expression.resolve(Expression.java:906)\nat org.eclipse.jdt.internal.compiler.ast.Block.resolve(Block.java:101)\nat org.eclipse.jdt.internal.compiler.ast.AbstractMethodDeclaration.resolveStatements(AbstractMethodDeclaration.java:429)\nat org.eclipse.jdt.internal.compiler.ast.MethodDeclaration.resolveStatements(MethodDeclaration.java:196)\nat org.eclipse.jdt.internal.compiler.ast.AbstractMethodDeclaration.resolve(AbstractMethodDeclaration.java:400)\nat org.eclipse.jdt.internal.compiler.ast.TypeDeclaration.resolve(TypeDeclaration.java:1085)\nat org.eclipse.jdt.internal.compiler.ast.TypeDeclaration.resolve(TypeDeclaration.java:1164)\nat org.eclipse.jdt.internal.compiler.ast.CompilationUnitDeclaration.resolve(CompilationUnitDeclaration.java:366)\nat org.eclipse.jdt.internal.codeassist.SelectionEngine.select(SelectionEngine.java:691)\nat org.eclipse.jdt.internal.core.Openable.codeSelect(Openable.java:155)\nat org.eclipse.jdt.internal.core.CompilationUnit.codeSelect(CompilationUnit.java:340)\nat org.eclipse.jdt.internal.core.CompilationUnit.codeSelect(CompilationUnit.java:334)\nat org.eclipse.jdt.internal.ui.javaeditor.JavaElementHyperlinkDetector.detectHyperlinks(JavaElementHyperlinkDetector.java:62)\nat org.eclipse.ui.texteditor.HyperlinkDetectorRegistry$HyperlinkDetectorDelegate.detectHyperlinks(HyperlinkDetectorRegistry.java:80)\nat org.eclipse.jface.text.hyperlink.HyperlinkManager.findHyperlinks(HyperlinkManager.java:261)\nat org.eclipse.jface.text.hyperlink.HyperlinkManager.mouseMove(HyperlinkManager.java:458)\nat org.eclipse.swt.widgets.TypedListener.handleEvent(TypedListener.java:198)\nat org.eclipse.swt.widgets.EventTable.sendEvent(EventTable.java:66)\nat org.eclipse.swt.widgets.Widget.sendEvent(Widget.java:938)\nat org.eclipse.swt.widgets.Display.runDeferredEvents(Display.java:3682)\nat org.eclipse.swt.widgets.Display.readAndDispatch(Display.java:3293)\nat org.eclipse.ui.internal.Workbench.runEventLoop(Workbench.java:2389)\nat org.eclipse.ui.internal.Workbench.runUI(Workbench.java:2353)\nat org.eclipse.ui.internal.Workbench.access$4(Workbench.java:2219)\nat org.eclipse.ui.internal.Workbench$4.run(Workbench.java:466)\nat org.eclipse.core.databinding.observable.Realm.runWithDefault(Realm.java:289)\nat org.eclipse.ui.internal.Workbench.createAndRunWorkbench(Workbench.java:461)\nat org.eclipse.ui.PlatformUI.createAndRunWorkbench(PlatformUI.java:149)\nat org.eclipse.ui.internal.ide.application.IDEApplication.start(IDEApplication.java:106)\nat org.eclipse.equinox.internal.app.EclipseAppHandle.run(EclipseAppHandle.java:153)\nat org.eclipse.core.runtime.internal.adaptor.EclipseAppLauncher.runApplication(EclipseAppLauncher.java:106)\nat org.eclipse.core.runtime.internal.adaptor.EclipseAppLauncher.start(EclipseAppLauncher.java:76)\nat org.eclipse.core.runtime.adaptor.EclipseStarter.run(EclipseStarter.java:363)\nat org.eclipse.core.runtime.adaptor.EclipseStarter.run(EclipseStarter.java:176)\nat sun.reflect.NativeMethodAccessorImpl.invoke0(Native Method)\nat sun.reflect.NativeMethodAccessorImpl.invoke(Unknown Source)\nat sun.reflect.DelegatingMethodAccessorImpl.invoke(Unknown Source)\nat java.lang.reflect.Method.invoke(Unknown Source)\nat org.eclipse.equinox.launcher.Main.invokeFramework(Main.java:504)\nat org.eclipse.equinox.launcher.Main.basicRun(Main.java:443)\nat org.eclipse.equinox.launcher.Main.run(Main.java:1169)\n\nThis same exception also caused various \"Internal Error\" or \"Unexpected runtime error while computing a text hover\" entries in the error log.\n\nMore information:",
    "Reproduced with I20070918-0010.\n\nSimple test case:\n\npackage p;\n\npublic class X {\n    public void foo() {\n            new Y\u003cString\u003e(unknown) { // select Y and do F3\n\n            };\n    }\n}\nclass Y\u003cT\u003e {\n\n}",
    "Created an attachment (id\u003d79206)\nProposed fix\n\n",
    "Released for 3.4M3.\n\nTests added\n  ResolveTests#testConstructor3() -\u003etestConstructor4()",
    "Verified for 3.4M3 using I20071029-0010"
  ],
  "commentCreationDates": [
    "2007-09-24T10:52:02+02:00",
    "2007-09-24T12:51:46+02:00",
    "2007-09-26T16:18:28+02:00",
    "2007-09-26T16:23:28+02:00",
    "2007-10-29T13:43:58+01:00"
  ],
  "traces": [
    {
      "exceptionType": "java.lang.NullPointerException",
      "elements": [
        {
          "method": "org.eclipse.jdt.internal.codeassist.select.SelectionOnQualifiedAllocationExpression.resolveType",
          "source": "SelectionOnQualifiedAllocationExpression.java:75"
        },
        {
          "method": "org.eclipse.jdt.internal.compiler.ast.Expression.resolve",
          "source": "Expression.java:906"
        },
        {
          "method": "org.eclipse.jdt.internal.compiler.ast.Block.resolve",
          "source": "Block.java:101"
        },
        {
          "method": "org.eclipse.jdt.internal.compiler.ast.AbstractMethodDeclaration.resolveStatements",
          "source": "AbstractMethodDeclaration.java:429"
        },
        {
          "method": "org.eclipse.jdt.internal.compiler.ast.MethodDeclaration.resolveStatements",
          "source": "MethodDeclaration.java:196"
        },
        {
          "method": "org.eclipse.jdt.internal.compiler.ast.AbstractMethodDeclaration.resolve",
          "source": "AbstractMethodDeclaration.java:400"
        },
        {
          "method": "org.eclipse.jdt.internal.compiler.ast.TypeDeclaration.resolve",
          "source": "TypeDeclaration.java:1085"
        },
        {
          "method": "org.eclipse.jdt.internal.compiler.ast.TypeDeclaration.resolve",
          "source": "TypeDeclaration.java:1164"
        },
        {
          "method": "org.eclipse.jdt.internal.compiler.ast.CompilationUnitDeclaration.resolve",
          "source": "CompilationUnitDeclaration.java:366"
        },
        {
          "method": "org.eclipse.jdt.internal.codeassist.SelectionEngine.select",
          "source": "SelectionEngine.java:691"
        },
        {
          "method": "org.eclipse.jdt.internal.core.Openable.codeSelect",
          "source": "Openable.java:155"
        },
        {
          "method": "org.eclipse.jdt.internal.core.CompilationUnit.codeSelect",
          "source": "CompilationUnit.java:340"
        },
        {
          "method": "org.eclipse.jdt.internal.core.CompilationUnit.codeSelect",
          "source": "CompilationUnit.java:334"
        },
        {
          "method": "org.eclipse.jdt.internal.ui.javaeditor.JavaElementHyperlinkDetector.detectHyperlinks",
          "source": "JavaElementHyperlinkDetector.java:62"
        },
        {
          "method": "org.eclipse.ui.texteditor.HyperlinkDetectorRegistry$HyperlinkDetectorDelegate.detectHyperlinks",
          "source": "HyperlinkDetectorRegistry.java:80"
        },
        {
          "method": "org.eclipse.jface.text.hyperlink.HyperlinkManager.findHyperlinks",
          "source": "HyperlinkManager.java:261"
        },
        {
          "method": "org.eclipse.jface.text.hyperlink.HyperlinkManager.mouseMove",
          "source": "HyperlinkManager.java:458"
        },
        {
          "method": "org.eclipse.swt.widgets.TypedListener.handleEvent",
          "source": "TypedListener.java:198"
        },
        {
          "method": "org.eclipse.swt.widgets.EventTable.sendEvent",
          "source": "EventTable.java:66"
        },
        {
          "method": "org.eclipse.swt.widgets.Widget.sendEvent",
          "source": "Widget.java:938"
        },
        {
          "method": "org.eclipse.swt.widgets.Display.runDeferredEvents",
          "source": "Display.java:3682"
        },
        {
          "method": "org.eclipse.swt.widgets.Display.readAndDispatch",
          "source": "Display.java:3293"
        },
        {
          "method": "org.eclipse.ui.internal.Workbench.runEventLoop",
          "source": "Workbench.java:2389"
        },
        {
          "method": "org.eclipse.ui.internal.Workbench.runUI",
          "source": "Workbench.java:2353"
        },
        {
          "method": "org.eclipse.ui.internal.Workbench.access$4",
          "source": "Workbench.java:2219"
        },
        {
          "method": "org.eclipse.ui.internal.Workbench$4.run",
          "source": "Workbench.java:466"
        },
        {
          "method": "org.eclipse.core.databinding.observable.Realm.runWithDefault",
          "source": "Realm.java:289"
        },
        {
          "method": "org.eclipse.ui.internal.Workbench.createAndRunWorkbench",
          "source": "Workbench.java:461"
        },
        {
          "method": "org.eclipse.ui.PlatformUI.createAndRunWorkbench",
          "source": "PlatformUI.java:149"
        },
        {
          "method": "org.eclipse.ui.internal.ide.application.IDEApplication.start",
          "source": "IDEApplication.java:106"
        },
        {
          "method": "org.eclipse.equinox.internal.app.EclipseAppHandle.run",
          "source": "EclipseAppHandle.java:153"
        },
        {
          "method": "org.eclipse.core.runtime.internal.adaptor.EclipseAppLauncher.runApplication",
          "source": "EclipseAppLauncher.java:106"
        },
        {
          "method": "org.eclipse.core.runtime.internal.adaptor.EclipseAppLauncher.start",
          "source": "EclipseAppLauncher.java:76"
        },
        {
          "method": "org.eclipse.core.runtime.adaptor.EclipseStarter.run",
          "source": "EclipseStarter.java:363"
        },
        {
          "method": "org.eclipse.core.runtime.adaptor.EclipseStarter.run",
          "source": "EclipseStarter.java:176"
        },
        {
          "method": "sun.reflect.NativeMethodAccessorImpl.invoke0",
          "source": "Native Method"
        },
        {
          "method": "sun.reflect.NativeMethodAccessorImpl.invoke",
          "source": "Unknown Source"
        },
        {
          "method": "sun.reflect.DelegatingMethodAccessorImpl.invoke",
          "source": "Unknown Source"
        },
        {
          "method": "java.lang.reflect.Method.invoke",
          "source": "Unknown Source"
        },
        {
          "method": "org.eclipse.equinox.launcher.Main.invokeFramework",
          "source": "Main.java:504"
        },
        {
          "method": "org.eclipse.equinox.launcher.Main.basicRun",
          "source": "Main.java:443"
        },
        {
          "method": "org.eclipse.equinox.launcher.Main.run",
          "source": "Main.java:1169"
        }
      ],
      "number": 0,
      "commentIndex": 0,
      "bugId": "204417",
      "date": "2007-09-24T10:52:02+02:00",
      "product": "JDT",
      "component": "Core",
      "severity": "normal"
    }
  ],
  "groupId": "204417",
  "bugId": "204417",
  "date": "2007-09-24T10:52:02+02:00",
  "product": "JDT",
  "component": "Core",
  "severity": "normal"
}