{
  "comments": [
    "Build ID: 0925\n\nSteps To Reproduce:\nPresently the build file creates a folder for the wse. This is not neccessary and should be changed to a jar file. A small change is required in the build.properties file.\n\nMore information:",
    "Please also use this defect to remove unncessary files in the Web Services Explorer that was left from running on Tomcat.",
    "*** Bug 204802 has been marked as a duplicate of this bug. ***",
    "In the 20070926 WTP 3.0 I-build, the explorer source accounts for 690 files and 120 folder while the explorer plugin accounts for 552 files and 69 folders.  We definitely need to JAR those plugins.\n\nGil, could you please take care of this for M2 (to be declared next Wednesday)?  Which means checking in the change by early next week.",
    "Gil, I\u0027ve taken care of setting unpack\u003d\"false\" in the org.eclipse.wst.ws_ui.feature which contains the org.eclipse.wst.ws.explorer plugin.  So the source should be in zip format now.  You just have to JAR up the explorer plugin and make sure that the code still function correctly and the icons are all there after being JARred up.\n\nMore info can be found in:\n\nhttp://www.eclipse.org/eclipse/platform-core/documents/3.1/run_from_jars.html\n",
    "Created an attachment (id\u003d79489)\nchange in wse\n\n",
    "Gil,\n\nI made some modification to the proposed patch (removing bundle-classpath and removing some source-includes) and released the change to the explorer plugin.  The WTP 3.0 build S-3.0M2-20071001213732 contains this change.\n\nWhen I tried clicking on \"Run on WSE\" the first time resulted in:\n\nHTTP ERROR: 500\nException in JSP: /wsexplorer/wsexplorer.jsp:64\n\n61:     }\n62: \n63:     // controller.init()\n64:     controller.init(sessionId,application,request.getContextPath());\n65:     %\u003e\n66:   \u003c/jsp:useBean\u003e\n67:   \u003c%\n\n\nStacktrace:\nRequestURI\u003d/wse/wsexplorer/wsexplorer.jsp\n\nPowered by Jetty://\n\nClicking on \"Run on WSE\" a second time resulted in:\n\nHTTP ERROR: 500\nException in JSP: /uddi/navigator_content.jsp:47\n\n44: %\u003e\n45: \u003cbody dir\u003d\"\u003c%\u003dorg.eclipse.wst.ws.internal.explorer.platform.util.DirUtils.getDir()%\u003e\" onLoad\u003d\"self.location.hash\u003d\u0027#\u003c%\u003dfocusedAnchorName%\u003e\u0027;setSelectedAnchorName(\u0027\u003c%\u003dselectedAnchorName%\u003e\u0027)\" class\u003d\"contentbodymargin\"\u003e\n46: \u003cdiv id\u003d\"treecontentborder\"\u003e\n47: \u003c%\u003dnavigatorManager.renderTreeView(response)%\u003e\n48: \u003c/div\u003e\n49: \u003c/body\u003e\n50: \u003c/html\u003e\n\n\nStacktrace:\nRequestURI\u003d/wse/uddi/navigator_content.jsp\n\nPowered by Jetty://\n\nI checked the org.eclipse.wst.ws.explorer_1.0.305.v200710012116.jar in the build and it contain:\n\n- wsexplorer/wsexplorer.jsp\n- wsexplorer/uddi/navigator_content.jsp\n\nSo it looks like the WSE is somehow getting the Request URI wrong.  Please take a look.  \n\nIf I unzipping the org.eclipse.wst.ws.explorer_1.0.305.v200710012116.jar into a org.eclipse.wst.ws.explorer_1.0.305.v200710012116 directory, then the WSE would run OK.\n\nSince we need the final code for WTP 3.0 M2 check in by EOD today, I have reverted the wst-ws-ui.map file to the previous tag for the WSE plugin (i.e. v200710012105 without the change for turning the WSE into a single JAR).  Unless you can find the solution for this immediately, we\u0027ll have to leave the explorer plugin as a directory in WTP 3.0 M2 and revisit this after M2 is declared.\n\nAs for the source zip, I checked the org.eclipse.wst.ws_ui.feature.source plugin and now the explorer src is properly in zipped up form.",
    "I\u0027ve reverted the code that change the explorer plugin to single JAR.   Here are the versions of the files containing the changes to change the explorer plugin to single JAR:\n\n- Version 1.34 -  feature.xml in org.eclipse.wst.ws_ui.feature (adding unpack\u003dfalse)\n- Version 1.43 - manifest.mf in org.eclipse.wst.ws.explorer (removing bundle.classpath)\n- Version 1.23 - build.properties in org.eclipse.wst.ws.explorer (changing to source.. and bin..)\n\nThe above versions can be used as a starting point for continuing this investigation for post WTP 3.0 M2.",
    "I just checked the wtp-sdk-S-3.0M2-20071002141531 build and the wst.ws.explorer is now back to packaged as a directory.  It\u0027s back functional again.  The source directory is still in a zipped file.  So we\u0027re OK for WTP 3.0 M2.  \n\nHere\u0027s the stack trace when launching the WSE in a driver when the explorer plugin is in a JAR (e.g. in S-3.0M2-20071001213732):\n\nOct 2, 2007 1:24:34 PM org.mortbay.jetty.servlet.ServletHandler handle\nWARNING: EXCEPTION\norg.apache.jasper.JasperException: Exception in JSP: /wsexplorer/wsexplorer.jsp:64\n\n61:     }\n62:\n63:     // controller.init()\n64:     controller.init(sessionId,application,request.getContextPath());\n65:     %\u003e\n66:   \u003c/jsp:useBean\u003e\n67:   \u003c%\n\n\nStacktrace:\n        at org.apache.jasper.servlet.JspServletWrapper.handleJspException(JspServletWrapper.java:504\n)\n        at org.apache.jasper.servlet.JspServletWrapper.service(JspServletWrapper.java:393)\n        at org.apache.jasper.servlet.JspServlet.serviceJspFile(JspServlet.java:314)\n        at org.apache.jasper.servlet.JspServlet.service(JspServlet.java:264)\n        at javax.servlet.http.HttpServlet.service(HttpServlet.java:689)\n        at org.eclipse.equinox.jsp.jasper.JspServlet.service(JspServlet.java:107)\n        at javax.servlet.http.HttpServlet.service(HttpServlet.java:689)\n        at org.eclipse.equinox.http.registry.internal.ServletManager$ServletWrapper.service(ServletM\nanager.java:180)\n        at org.eclipse.equinox.http.servlet.internal.ServletRegistration.handleRequest(ServletRegist\nration.java:90)\n        at org.eclipse.equinox.http.servlet.internal.ProxyServlet.processAlias(ProxyServlet.java:111\n)\n        at org.eclipse.equinox.http.servlet.internal.ProxyServlet.service(ProxyServlet.java:75)\n        at javax.servlet.http.HttpServlet.service(HttpServlet.java:689)\n        at org.eclipse.equinox.http.jetty.internal.HttpServerManager$InternalHttpServiceServlet.serv\nice(HttpServerManager.java:270)\n        at org.mortbay.jetty.servlet.ServletHolder.handle(ServletHolder.java:428)\n        at org.mortbay.jetty.servlet.ServletHandler.dispatch(ServletHandler.java:677)\n        at org.mortbay.jetty.servlet.ServletHandler.handle(ServletHandler.java:568)\n        at org.mortbay.http.HttpContext.handle(HttpContext.java:1530)\n        at org.mortbay.http.HttpContext.handle(HttpContext.java:1482)\n        at org.mortbay.http.HttpServer.service(HttpServer.java:909)\n        at org.mortbay.http.HttpConnection.service(HttpConnection.java:820)\n        at org.mortbay.http.HttpConnection.handleNext(HttpConnection.java:986)\n        at org.mortbay.http.HttpConnection.handle(HttpConnection.java:837)\n        at org.mortbay.http.SocketListener.handleConnection(SocketListener.java:245)\n        at org.mortbay.util.ThreadedServer.handle(ThreadedServer.java:357)\n        at org.mortbay.util.ThreadPool$PoolThread.run(ThreadPool.java:534)\nOct 2, 2007 1:24:34 PM org.mortbay.jetty.servlet.ServletHandler handle\nSEVERE: /wse/wsexplorer/wsexplorer.jsp?org.eclipse.wst.ws.explorer\u003d0:\njava.lang.NullPointerException\n        at org.eclipse.wst.ws.internal.explorer.platform.uddi.perspective.OpenRegistryTool.initDefau\nltProperties(OpenRegistryTool.java:42)\n        at org.eclipse.wst.ws.internal.explorer.platform.perspective.FormTool.\u003cinit\u003e(FormTool.java:2\n5)\n        at org.eclipse.wst.ws.internal.explorer.platform.uddi.perspective.OpenRegistryTool.\u003cinit\u003e(Op\nenRegistryTool.java:35)\n        at org.eclipse.wst.ws.internal.explorer.platform.uddi.perspective.UDDIMainNode.initTools(UDD\nIMainNode.java:82)\n        at org.eclipse.wst.ws.internal.explorer.platform.perspective.Node.\u003cinit\u003e(Node.java:51)\n        at org.eclipse.wst.ws.internal.explorer.platform.uddi.perspective.UDDINavigatorNode.\u003cinit\u003e(U\nDDINavigatorNode.java:25)\n        at org.eclipse.wst.ws.internal.explorer.platform.uddi.perspective.UDDIMainNode.\u003cinit\u003e(UDDIMa\ninNode.java:31)\n        at org.eclipse.wst.ws.internal.explorer.platform.uddi.perspective.UDDIPerspective.initPerspe\nctive(UDDIPerspective.java:88)\n        at org.eclipse.wst.ws.internal.explorer.platform.perspective.Controller.init(Controller.java\n:108)\n        at org.apache.jsp.wsexplorer.wsexplorer_jsp._jspService(wsexplorer_jsp.java:118)\n        at org.apache.jasper.runtime.HttpJspBase.service(HttpJspBase.java:97)\n        at javax.servlet.http.HttpServlet.service(HttpServlet.java:689)\n        at org.apache.jasper.servlet.JspServletWrapper.service(JspServletWrapper.java:332)\n        at org.apache.jasper.servlet.JspServlet.serviceJspFile(JspServlet.java:314)\n        at org.apache.jasper.servlet.JspServlet.service(JspServlet.java:264)\n        at javax.servlet.http.HttpServlet.service(HttpServlet.java:689)\n        at org.eclipse.equinox.jsp.jasper.JspServlet.service(JspServlet.java:107)\n        at javax.servlet.http.HttpServlet.service(HttpServlet.java:689)\n        at org.eclipse.equinox.http.registry.internal.ServletManager$ServletWrapper.service(ServletM\nanager.java:180)\n        at org.eclipse.equinox.http.servlet.internal.ServletRegistration.handleRequest(ServletRegist\nration.java:90)\n        at org.eclipse.equinox.http.servlet.internal.ProxyServlet.processAlias(ProxyServlet.java:111\n)\n        at org.eclipse.equinox.http.servlet.internal.ProxyServlet.service(ProxyServlet.java:75)\n        at javax.servlet.http.HttpServlet.service(HttpServlet.java:689)\n        at org.eclipse.equinox.http.jetty.internal.HttpServerManager$InternalHttpServiceServlet.serv\nice(HttpServerManager.java:270)\n        at org.mortbay.jetty.servlet.ServletHolder.handle(ServletHolder.java:428)\n        at org.mortbay.jetty.servlet.ServletHandler.dispatch(ServletHandler.java:677)\n        at org.mortbay.jetty.servlet.ServletHandler.handle(ServletHandler.java:568)\n        at org.mortbay.http.HttpContext.handle(HttpContext.java:1530)\n        at org.mortbay.http.HttpContext.handle(HttpContext.java:1482)\n        at org.mortbay.http.HttpServer.service(HttpServer.java:909)\n        at org.mortbay.http.HttpConnection.service(HttpConnection.java:820)\n        at org.mortbay.http.HttpConnection.handleNext(HttpConnection.java:986)\n        at org.mortbay.http.HttpConnection.handle(HttpConnection.java:837)\n        at org.mortbay.http.SocketListener.handleConnection(SocketListener.java:245)\n        at org.mortbay.util.ThreadedServer.handle(ThreadedServer.java:357)\n        at org.mortbay.util.ThreadPool$PoolThread.run(ThreadPool.java:534)\n\nHere\u0027s the stack trace when the WSE is launched a second time:\n\nWARNING: EXCEPTION\norg.apache.jasper.JasperException: Exception in JSP: /uddi/navigator_toolbar.jsp:49\n\n46:         \u003ctd valign\u003d\"middle\" align\u003d\"center\" width\u003d25 height\u003d25\u003e\u003cimg class\u003d\"normal\" src\u003d\"\u003c%\u003drespon\nse.encodeURL(controller.getPathWithContext(\"images/navigator.gif\"))%\u003e\" width\u003d16 height\u003d16\u003e\u003c/td\u003e\n47: \u003c%\n48:    String doubleClickColumnTitle \u003d null;\n49:    if (uddiPerspective.getPerspectiveContentFramesetCols().startsWith(\"100%\"))\n50:      doubleClickColumnTitle \u003d controller.getMessage(\"ALT_DOUBLE_CLICK_TO_RESTORE\");\n51:    else\n52:      doubleClickColumnTitle \u003d controller.getMessage(\"ALT_DOUBLE_CLICK_TO_MAXIMIZE\");\n\n\nStacktrace:\n        at org.apache.jasper.servlet.JspServletWrapper.handleJspException(JspServletWrapper.java:504\n)\n        at org.apache.jasper.servlet.JspServletWrapper.service(JspServletWrapper.java:393)\n        at org.apache.jasper.servlet.JspServlet.serviceJspFile(JspServlet.java:314)\n        at org.apache.jasper.servlet.JspServlet.service(JspServlet.java:264)\n        at javax.servlet.http.HttpServlet.service(HttpServlet.java:689)\n        at org.eclipse.equinox.jsp.jasper.JspServlet.service(JspServlet.java:107)\n        at javax.servlet.http.HttpServlet.service(HttpServlet.java:689)\n        at org.eclipse.equinox.http.registry.internal.ServletManager$ServletWrapper.service(ServletM\nanager.java:180)\n        at org.eclipse.equinox.http.servlet.internal.ServletRegistration.handleRequest(ServletRegist\nration.java:90)\n        at org.eclipse.equinox.http.servlet.internal.ProxyServlet.processAlias(ProxyServlet.java:111\n)\n        at org.eclipse.equinox.http.servlet.internal.ProxyServlet.service(ProxyServlet.java:75)\n        at javax.servlet.http.HttpServlet.service(HttpServlet.java:689)\n        at org.eclipse.equinox.http.jetty.internal.HttpServerManager$InternalHttpServiceServlet.serv\nice(HttpServerManager.java:270)\n        at org.mortbay.jetty.servlet.ServletHolder.handle(ServletHolder.java:428)\n        at org.mortbay.jetty.servlet.ServletHandler.dispatch(ServletHandler.java:677)\n        at org.mortbay.jetty.servlet.ServletHandler.handle(ServletHandler.java:568)\n        at org.mortbay.http.HttpContext.handle(HttpContext.java:1530)\n        at org.mortbay.http.HttpContext.handle(HttpContext.java:1482)\n        at org.mortbay.http.HttpServer.service(HttpServer.java:909)\n        at org.mortbay.http.HttpConnection.service(HttpConnection.java:820)\n        at org.mortbay.http.HttpConnection.handleNext(HttpConnection.java:986)\n        at org.mortbay.http.HttpConnection.handle(HttpConnection.java:837)\n        at org.mortbay.http.SocketListener.handleConnection(SocketListener.java:245)\n        at org.mortbay.util.ThreadedServer.handle(ThreadedServer.java:357)\n        at org.mortbay.util.ThreadPool$PoolThread.run(ThreadPool.java:534)\nOct 2, 2007 1:27:59 PM org.mortbay.jetty.servlet.ServletHandler handle\nSEVERE: /wse/uddi/navigator_toolbar.jsp:\njava.lang.NullPointerException\n        at org.apache.jsp.uddi.navigator_005ftoolbar_jsp._jspService(navigator_005ftoolbar_jsp.java:\n135)\n        at org.apache.jasper.runtime.HttpJspBase.service(HttpJspBase.java:97)\n        at javax.servlet.http.HttpServlet.service(HttpServlet.java:689)\n        at org.apache.jasper.servlet.JspServletWrapper.service(JspServletWrapper.java:332)\n        at org.apache.jasper.servlet.JspServlet.serviceJspFile(JspServlet.java:314)\n        at org.apache.jasper.servlet.JspServlet.service(JspServlet.java:264)\n        at javax.servlet.http.HttpServlet.service(HttpServlet.java:689)\n        at org.eclipse.equinox.jsp.jasper.JspServlet.service(JspServlet.java:107)\n        at javax.servlet.http.HttpServlet.service(HttpServlet.java:689)\n        at org.eclipse.equinox.http.registry.internal.ServletManager$ServletWrapper.service(ServletM\nanager.java:180)\n        at org.eclipse.equinox.http.servlet.internal.ServletRegistration.handleRequest(ServletRegist\nration.java:90)\n        at org.eclipse.equinox.http.servlet.internal.ProxyServlet.processAlias(ProxyServlet.java:111\n)\n        at org.eclipse.equinox.http.servlet.internal.ProxyServlet.service(ProxyServlet.java:75)\n        at javax.servlet.http.HttpServlet.service(HttpServlet.java:689)\n        at org.eclipse.equinox.http.jetty.internal.HttpServerManager$InternalHttpServiceServlet.serv\nice(HttpServerManager.java:270)\n        at org.mortbay.jetty.servlet.ServletHolder.handle(ServletHolder.java:428)\n        at org.mortbay.jetty.servlet.ServletHandler.dispatch(ServletHandler.java:677)\n        at org.mortbay.jetty.servlet.ServletHandler.handle(ServletHandler.java:568)\n        at org.mortbay.http.HttpContext.handle(HttpContext.java:1530)\n        at org.mortbay.http.HttpContext.handle(HttpContext.java:1482)\n        at org.mortbay.http.HttpServer.service(HttpServer.java:909)\n        at org.mortbay.http.HttpConnection.service(HttpConnection.java:820)\n        at org.mortbay.http.HttpConnection.handleNext(HttpConnection.java:986)\n        at org.mortbay.http.HttpConnection.handle(HttpConnection.java:837)\n        at org.mortbay.http.SocketListener.handleConnection(SocketListener.java:245)\n        at org.mortbay.util.ThreadedServer.handle(ThreadedServer.java:357)\n        at org.mortbay.util.ThreadPool$PoolThread.run(ThreadPool.java:534)",
    "Deferring to M4."
  ],
  "commentCreationDates": [
    "2007-09-25T21:21:46+02:00",
    "2007-09-26T19:34:36+02:00",
    "2007-09-27T19:01:46+02:00",
    "2007-09-28T19:49:50+02:00",
    "2007-09-28T20:25:22+02:00",
    "2007-10-01T17:59:10+02:00",
    "2007-10-02T04:12:56+02:00",
    "2007-10-02T17:12:01+02:00",
    "2007-10-02T19:29:28+02:00",
    "2007-11-14T04:51:41+01:00"
  ],
  "traces": [
    {
      "exceptionType": "org.apache.jasper.JasperException",
      "message": "Exception in JSP: /wsexplorer/wsexplorer.jsp:64  61:     } 62: 63:     // controller.init() 64:     controller.init(sessionId,application,request.getContextPath()); 65:     %\u003e 66:   \u003c/jsp:useBean\u003e 67:   \u003c%   Stacktrace:",
      "elements": [
        {
          "method": "org.apache.jasper.servlet.JspServletWrapper.handleJspException",
          "source": "JspServletWrapper.java:504 "
        },
        {
          "method": "org.apache.jasper.servlet.JspServletWrapper.service",
          "source": "JspServletWrapper.java:393"
        },
        {
          "method": "org.apache.jasper.servlet.JspServlet.serviceJspFile",
          "source": "JspServlet.java:314"
        },
        {
          "method": "org.apache.jasper.servlet.JspServlet.service",
          "source": "JspServlet.java:264"
        },
        {
          "method": "javax.servlet.http.HttpServlet.service",
          "source": "HttpServlet.java:689"
        },
        {
          "method": "org.eclipse.equinox.jsp.jasper.JspServlet.service",
          "source": "JspServlet.java:107"
        },
        {
          "method": "javax.servlet.http.HttpServlet.service",
          "source": "HttpServlet.java:689"
        },
        {
          "method": "org.eclipse.equinox.http.registry.internal.ServletManager$ServletWrapper.service",
          "source": "ServletM anager.java:180"
        },
        {
          "method": "org.eclipse.equinox.http.servlet.internal.ServletRegistration.handleRequest",
          "source": "ServletRegist ration.java:90"
        },
        {
          "method": "org.eclipse.equinox.http.servlet.internal.ProxyServlet.processAlias",
          "source": "ProxyServlet.java:111 "
        },
        {
          "method": "org.eclipse.equinox.http.servlet.internal.ProxyServlet.service",
          "source": "ProxyServlet.java:75"
        },
        {
          "method": "javax.servlet.http.HttpServlet.service",
          "source": "HttpServlet.java:689"
        },
        {
          "method": "org.eclipse.equinox.http.jetty.internal.HttpServerManager$InternalHttpServiceServlet.service",
          "source": "HttpServerManager.java:270"
        },
        {
          "method": "org.mortbay.jetty.servlet.ServletHolder.handle",
          "source": "ServletHolder.java:428"
        },
        {
          "method": "org.mortbay.jetty.servlet.ServletHandler.dispatch",
          "source": "ServletHandler.java:677"
        },
        {
          "method": "org.mortbay.jetty.servlet.ServletHandler.handle",
          "source": "ServletHandler.java:568"
        },
        {
          "method": "org.mortbay.http.HttpContext.handle",
          "source": "HttpContext.java:1530"
        },
        {
          "method": "org.mortbay.http.HttpContext.handle",
          "source": "HttpContext.java:1482"
        },
        {
          "method": "org.mortbay.http.HttpServer.service",
          "source": "HttpServer.java:909"
        },
        {
          "method": "org.mortbay.http.HttpConnection.service",
          "source": "HttpConnection.java:820"
        },
        {
          "method": "org.mortbay.http.HttpConnection.handleNext",
          "source": "HttpConnection.java:986"
        },
        {
          "method": "org.mortbay.http.HttpConnection.handle",
          "source": "HttpConnection.java:837"
        },
        {
          "method": "org.mortbay.http.SocketListener.handleConnection",
          "source": "SocketListener.java:245"
        },
        {
          "method": "org.mortbay.util.ThreadedServer.handle",
          "source": "ThreadedServer.java:357"
        },
        {
          "method": "org.mortbay.util.ThreadPool$PoolThread.run",
          "source": "ThreadPool.java:534"
        }
      ],
      "number": 0,
      "commentIndex": 8,
      "bugId": "204602",
      "date": "2007-10-02T19:29:28+02:00",
      "product": "Web Tools",
      "component": "wst.ws",
      "severity": "major"
    },
    {
      "exceptionType": "java.lang.NullPointerException",
      "elements": [
        {
          "method": "org.eclipse.wst.ws.internal.explorer.platform.uddi.perspective.OpenRegistryTool.initDefaultProperties",
          "source": "OpenRegistryTool.java:42"
        },
        {
          "method": "org.eclipse.wst.ws.internal.explorer.platform.perspective.FormTool.\u003cinit\u003e",
          "source": "FormTool.java:2 5"
        },
        {
          "method": "org.eclipse.wst.ws.internal.explorer.platform.uddi.perspective.OpenRegistryTool.\u003cinit\u003e",
          "source": "Op enRegistryTool.java:35"
        },
        {
          "method": "org.eclipse.wst.ws.internal.explorer.platform.uddi.perspective.UDDIMainNode.initTools",
          "source": "UDD IMainNode.java:82"
        },
        {
          "method": "org.eclipse.wst.ws.internal.explorer.platform.perspective.Node.\u003cinit\u003e",
          "source": "Node.java:51"
        },
        {
          "method": "org.eclipse.wst.ws.internal.explorer.platform.uddi.perspective.UDDINavigatorNode.\u003cinit\u003e",
          "source": "U DDINavigatorNode.java:25"
        },
        {
          "method": "org.eclipse.wst.ws.internal.explorer.platform.uddi.perspective.UDDIMainNode.\u003cinit\u003e",
          "source": "UDDIMa inNode.java:31"
        },
        {
          "method": "org.eclipse.wst.ws.internal.explorer.platform.uddi.perspective.UDDIPerspective.initPerspective",
          "source": "UDDIPerspective.java:88"
        },
        {
          "method": "org.eclipse.wst.ws.internal.explorer.platform.perspective.Controller.init",
          "source": "Controller.java :108"
        },
        {
          "method": "org.apache.jsp.wsexplorer.wsexplorer_jsp._jspService",
          "source": "wsexplorer_jsp.java:118"
        },
        {
          "method": "org.apache.jasper.runtime.HttpJspBase.service",
          "source": "HttpJspBase.java:97"
        },
        {
          "method": "javax.servlet.http.HttpServlet.service",
          "source": "HttpServlet.java:689"
        },
        {
          "method": "org.apache.jasper.servlet.JspServletWrapper.service",
          "source": "JspServletWrapper.java:332"
        },
        {
          "method": "org.apache.jasper.servlet.JspServlet.serviceJspFile",
          "source": "JspServlet.java:314"
        },
        {
          "method": "org.apache.jasper.servlet.JspServlet.service",
          "source": "JspServlet.java:264"
        },
        {
          "method": "javax.servlet.http.HttpServlet.service",
          "source": "HttpServlet.java:689"
        },
        {
          "method": "org.eclipse.equinox.jsp.jasper.JspServlet.service",
          "source": "JspServlet.java:107"
        },
        {
          "method": "javax.servlet.http.HttpServlet.service",
          "source": "HttpServlet.java:689"
        },
        {
          "method": "org.eclipse.equinox.http.registry.internal.ServletManager$ServletWrapper.service",
          "source": "ServletM anager.java:180"
        },
        {
          "method": "org.eclipse.equinox.http.servlet.internal.ServletRegistration.handleRequest",
          "source": "ServletRegist ration.java:90"
        },
        {
          "method": "org.eclipse.equinox.http.servlet.internal.ProxyServlet.processAlias",
          "source": "ProxyServlet.java:111 "
        },
        {
          "method": "org.eclipse.equinox.http.servlet.internal.ProxyServlet.service",
          "source": "ProxyServlet.java:75"
        },
        {
          "method": "javax.servlet.http.HttpServlet.service",
          "source": "HttpServlet.java:689"
        },
        {
          "method": "org.eclipse.equinox.http.jetty.internal.HttpServerManager$InternalHttpServiceServlet.service",
          "source": "HttpServerManager.java:270"
        },
        {
          "method": "org.mortbay.jetty.servlet.ServletHolder.handle",
          "source": "ServletHolder.java:428"
        },
        {
          "method": "org.mortbay.jetty.servlet.ServletHandler.dispatch",
          "source": "ServletHandler.java:677"
        },
        {
          "method": "org.mortbay.jetty.servlet.ServletHandler.handle",
          "source": "ServletHandler.java:568"
        },
        {
          "method": "org.mortbay.http.HttpContext.handle",
          "source": "HttpContext.java:1530"
        },
        {
          "method": "org.mortbay.http.HttpContext.handle",
          "source": "HttpContext.java:1482"
        },
        {
          "method": "org.mortbay.http.HttpServer.service",
          "source": "HttpServer.java:909"
        },
        {
          "method": "org.mortbay.http.HttpConnection.service",
          "source": "HttpConnection.java:820"
        },
        {
          "method": "org.mortbay.http.HttpConnection.handleNext",
          "source": "HttpConnection.java:986"
        },
        {
          "method": "org.mortbay.http.HttpConnection.handle",
          "source": "HttpConnection.java:837"
        },
        {
          "method": "org.mortbay.http.SocketListener.handleConnection",
          "source": "SocketListener.java:245"
        },
        {
          "method": "org.mortbay.util.ThreadedServer.handle",
          "source": "ThreadedServer.java:357"
        },
        {
          "method": "org.mortbay.util.ThreadPool$PoolThread.run",
          "source": "ThreadPool.java:534"
        }
      ],
      "number": 1,
      "commentIndex": 8,
      "bugId": "204602",
      "date": "2007-10-02T19:29:28+02:00",
      "product": "Web Tools",
      "component": "wst.ws",
      "severity": "major"
    },
    {
      "exceptionType": "org.apache.jasper.JasperException",
      "message": "Exception in JSP: /uddi/navigator_toolbar.jsp:49  46:         \u003ctd valign\u003d\"middle\" align\u003d\"center\" width\u003d25 height\u003d25\u003e\u003cimg class\u003d\"normal\" src\u003d\"\u003c%\u003drespon se.encodeURL(controller.getPathWithContext(\"images/navigator.gif\"))%\u003e\" width\u003d16 height\u003d16\u003e\u003c/td\u003e 47: \u003c% 48:    String doubleClickColumnTitle \u003d null; 49:    if (uddiPerspective.getPerspectiveContentFramesetCols().startsWith(\"100%\")) 50:      doubleClickColumnTitle \u003d controller.getMessage(\"ALT_DOUBLE_CLICK_TO_RESTORE\"); 51:    else 52:      doubleClickColumnTitle \u003d controller.getMessage(\"ALT_DOUBLE_CLICK_TO_MAXIMIZE\");   Stacktrace:",
      "elements": [
        {
          "method": "org.apache.jasper.servlet.JspServletWrapper.handleJspException",
          "source": "JspServletWrapper.java:504 "
        },
        {
          "method": "org.apache.jasper.servlet.JspServletWrapper.service",
          "source": "JspServletWrapper.java:393"
        },
        {
          "method": "org.apache.jasper.servlet.JspServlet.serviceJspFile",
          "source": "JspServlet.java:314"
        },
        {
          "method": "org.apache.jasper.servlet.JspServlet.service",
          "source": "JspServlet.java:264"
        },
        {
          "method": "javax.servlet.http.HttpServlet.service",
          "source": "HttpServlet.java:689"
        },
        {
          "method": "org.eclipse.equinox.jsp.jasper.JspServlet.service",
          "source": "JspServlet.java:107"
        },
        {
          "method": "javax.servlet.http.HttpServlet.service",
          "source": "HttpServlet.java:689"
        },
        {
          "method": "org.eclipse.equinox.http.registry.internal.ServletManager$ServletWrapper.service",
          "source": "ServletM anager.java:180"
        },
        {
          "method": "org.eclipse.equinox.http.servlet.internal.ServletRegistration.handleRequest",
          "source": "ServletRegist ration.java:90"
        },
        {
          "method": "org.eclipse.equinox.http.servlet.internal.ProxyServlet.processAlias",
          "source": "ProxyServlet.java:111 "
        },
        {
          "method": "org.eclipse.equinox.http.servlet.internal.ProxyServlet.service",
          "source": "ProxyServlet.java:75"
        },
        {
          "method": "javax.servlet.http.HttpServlet.service",
          "source": "HttpServlet.java:689"
        },
        {
          "method": "org.eclipse.equinox.http.jetty.internal.HttpServerManager$InternalHttpServiceServlet.service",
          "source": "HttpServerManager.java:270"
        },
        {
          "method": "org.mortbay.jetty.servlet.ServletHolder.handle",
          "source": "ServletHolder.java:428"
        },
        {
          "method": "org.mortbay.jetty.servlet.ServletHandler.dispatch",
          "source": "ServletHandler.java:677"
        },
        {
          "method": "org.mortbay.jetty.servlet.ServletHandler.handle",
          "source": "ServletHandler.java:568"
        },
        {
          "method": "org.mortbay.http.HttpContext.handle",
          "source": "HttpContext.java:1530"
        },
        {
          "method": "org.mortbay.http.HttpContext.handle",
          "source": "HttpContext.java:1482"
        },
        {
          "method": "org.mortbay.http.HttpServer.service",
          "source": "HttpServer.java:909"
        },
        {
          "method": "org.mortbay.http.HttpConnection.service",
          "source": "HttpConnection.java:820"
        },
        {
          "method": "org.mortbay.http.HttpConnection.handleNext",
          "source": "HttpConnection.java:986"
        },
        {
          "method": "org.mortbay.http.HttpConnection.handle",
          "source": "HttpConnection.java:837"
        },
        {
          "method": "org.mortbay.http.SocketListener.handleConnection",
          "source": "SocketListener.java:245"
        },
        {
          "method": "org.mortbay.util.ThreadedServer.handle",
          "source": "ThreadedServer.java:357"
        },
        {
          "method": "org.mortbay.util.ThreadPool$PoolThread.run",
          "source": "ThreadPool.java:534"
        }
      ],
      "number": 2,
      "commentIndex": 8,
      "bugId": "204602",
      "date": "2007-10-02T19:29:28+02:00",
      "product": "Web Tools",
      "component": "wst.ws",
      "severity": "major"
    },
    {
      "exceptionType": "java.lang.NullPointerException",
      "elements": [
        {
          "method": "org.apache.jsp.uddi.navigator_005ftoolbar_jsp._jspService",
          "source": "navigator_005ftoolbar_jsp.java: 135"
        },
        {
          "method": "org.apache.jasper.runtime.HttpJspBase.service",
          "source": "HttpJspBase.java:97"
        },
        {
          "method": "javax.servlet.http.HttpServlet.service",
          "source": "HttpServlet.java:689"
        },
        {
          "method": "org.apache.jasper.servlet.JspServletWrapper.service",
          "source": "JspServletWrapper.java:332"
        },
        {
          "method": "org.apache.jasper.servlet.JspServlet.serviceJspFile",
          "source": "JspServlet.java:314"
        },
        {
          "method": "org.apache.jasper.servlet.JspServlet.service",
          "source": "JspServlet.java:264"
        },
        {
          "method": "javax.servlet.http.HttpServlet.service",
          "source": "HttpServlet.java:689"
        },
        {
          "method": "org.eclipse.equinox.jsp.jasper.JspServlet.service",
          "source": "JspServlet.java:107"
        },
        {
          "method": "javax.servlet.http.HttpServlet.service",
          "source": "HttpServlet.java:689"
        },
        {
          "method": "org.eclipse.equinox.http.registry.internal.ServletManager$ServletWrapper.service",
          "source": "ServletM anager.java:180"
        },
        {
          "method": "org.eclipse.equinox.http.servlet.internal.ServletRegistration.handleRequest",
          "source": "ServletRegist ration.java:90"
        },
        {
          "method": "org.eclipse.equinox.http.servlet.internal.ProxyServlet.processAlias",
          "source": "ProxyServlet.java:111 "
        },
        {
          "method": "org.eclipse.equinox.http.servlet.internal.ProxyServlet.service",
          "source": "ProxyServlet.java:75"
        },
        {
          "method": "javax.servlet.http.HttpServlet.service",
          "source": "HttpServlet.java:689"
        },
        {
          "method": "org.eclipse.equinox.http.jetty.internal.HttpServerManager$InternalHttpServiceServlet.service",
          "source": "HttpServerManager.java:270"
        },
        {
          "method": "org.mortbay.jetty.servlet.ServletHolder.handle",
          "source": "ServletHolder.java:428"
        },
        {
          "method": "org.mortbay.jetty.servlet.ServletHandler.dispatch",
          "source": "ServletHandler.java:677"
        },
        {
          "method": "org.mortbay.jetty.servlet.ServletHandler.handle",
          "source": "ServletHandler.java:568"
        },
        {
          "method": "org.mortbay.http.HttpContext.handle",
          "source": "HttpContext.java:1530"
        },
        {
          "method": "org.mortbay.http.HttpContext.handle",
          "source": "HttpContext.java:1482"
        },
        {
          "method": "org.mortbay.http.HttpServer.service",
          "source": "HttpServer.java:909"
        },
        {
          "method": "org.mortbay.http.HttpConnection.service",
          "source": "HttpConnection.java:820"
        },
        {
          "method": "org.mortbay.http.HttpConnection.handleNext",
          "source": "HttpConnection.java:986"
        },
        {
          "method": "org.mortbay.http.HttpConnection.handle",
          "source": "HttpConnection.java:837"
        },
        {
          "method": "org.mortbay.http.SocketListener.handleConnection",
          "source": "SocketListener.java:245"
        },
        {
          "method": "org.mortbay.util.ThreadedServer.handle",
          "source": "ThreadedServer.java:357"
        },
        {
          "method": "org.mortbay.util.ThreadPool$PoolThread.run",
          "source": "ThreadPool.java:534"
        }
      ],
      "number": 3,
      "commentIndex": 8,
      "bugId": "204602",
      "date": "2007-10-02T19:29:28+02:00",
      "product": "Web Tools",
      "component": "wst.ws",
      "severity": "major"
    }
  ],
  "groupId": "204602",
  "bugId": "204602",
  "date": "2007-09-25T21:21:46+02:00",
  "product": "Web Tools",
  "component": "wst.ws",
  "severity": "major"
}