{
  "comments": [
    "Found this NPE in the log. Sorry, didn\u0027t see when it was printed, but since NPEs are often easy to figure out, thought I would log anyway.\n\n!SESSION 2007-10-07 01:04:00.120 -----------------------------------------------\neclipse.buildId\u003dI20070625-1500\njava.version\u003d1.5.0_12\njava.vendor\u003dSun Microsystems Inc.\nBootLoader constants: OS\u003dwin32, ARCH\u003dx86, WS\u003dwin32, NL\u003den_CA\nFramework arguments:  -product org.eclipse.sdk.ide -pdelaunch\nCommand-line arguments:  -product org.eclipse.sdk.ide -data C:\\dev\\abstratt/../runtime-New_configuration -dev file:C:/dev/abstratt/.metadata/.plugins/org.eclipse.pde.core/Full/dev.properties -pdelaunch -os win32 -ws win32 -arch x86 -consolelog -console\n\n!ENTRY org.eclipse.ui 4 0 2007-10-07 01:02:06.595\n!MESSAGE Unhandled event loop exception\n!STACK 0\norg.eclipse.swt.SWTException: Failed to execute runnable (java.lang.NullPointerException)\n\tat org.eclipse.swt.SWT.error(SWT.java:3563)\n\tat org.eclipse.swt.SWT.error(SWT.java:3481)\n\tat org.eclipse.swt.widgets.Synchronizer.runAsyncMessages(Synchronizer.java:126)\n\tat org.eclipse.swt.widgets.Display.runAsyncMessages(Display.java:3659)\n\tat org.eclipse.swt.widgets.Display.readAndDispatch(Display.java:3296)\n\tat org.eclipse.ui.internal.Workbench.runEventLoop(Workbench.java:2389)\n\tat org.eclipse.ui.internal.Workbench.runUI(Workbench.java:2353)\n\tat org.eclipse.ui.internal.Workbench.access$4(Workbench.java:2219)\n\tat org.eclipse.ui.internal.Workbench$4.run(Workbench.java:466)\n\tat org.eclipse.core.databinding.observable.Realm.runWithDefault(Realm.java:289)\n\tat org.eclipse.ui.internal.Workbench.createAndRunWorkbench(Workbench.java:461)\n\tat org.eclipse.ui.PlatformUI.createAndRunWorkbench(PlatformUI.java:149)\n\tat org.eclipse.ui.internal.ide.application.IDEApplication.start(IDEApplication.java:106)\n\tat org.eclipse.equinox.internal.app.EclipseAppHandle.run(EclipseAppHandle.java:153)\n\tat org.eclipse.core.runtime.internal.adaptor.EclipseAppLauncher.runApplication(EclipseAppLauncher.java:106)\n\tat org.eclipse.core.runtime.internal.adaptor.EclipseAppLauncher.start(EclipseAppLauncher.java:76)\n\tat org.eclipse.core.runtime.adaptor.EclipseStarter.run(EclipseStarter.java:363)\n\tat org.eclipse.core.runtime.adaptor.EclipseStarter.run(EclipseStarter.java:176)\n\tat sun.reflect.NativeMethodAccessorImpl.invoke0(Native Method)\n\tat sun.reflect.NativeMethodAccessorImpl.invoke(NativeMethodAccessorImpl.java:39)\n\tat sun.reflect.DelegatingMethodAccessorImpl.invoke(DelegatingMethodAccessorImpl.java:25)\n\tat java.lang.reflect.Method.invoke(Method.java:585)\n\tat org.eclipse.equinox.launcher.Main.invokeFramework(Main.java:504)\n\tat org.eclipse.equinox.launcher.Main.basicRun(Main.java:443)\n\tat org.eclipse.equinox.launcher.Main.run(Main.java:1169)\n\tat org.eclipse.equinox.launcher.Main.main(Main.java:1144)\nCaused by: java.lang.NullPointerException\n\tat org.eclipse.pde.internal.ui.editor.plugin.ManifestEditorMatchingStrategy.matches(ManifestEditorMatchingStrategy.java:32)\n\tat org.eclipse.ui.internal.EditorManager.findEditors(EditorManager.java:485)\n\tat org.eclipse.ui.internal.EditorManager.findEditors(EditorManager.java:431)\n\tat org.eclipse.ui.internal.EditorManager.findEditor(EditorManager.java:394)\n\tat org.eclipse.ui.internal.EditorManager.findEditor(EditorManager.java:376)\n\tat org.eclipse.ui.internal.WorkbenchPage.findEditor(WorkbenchPage.java:1967)\n\tat org.eclipse.ui.NavigationLocation.getEditorPart(NavigationLocation.java:44)\n\tat org.eclipse.ui.NavigationLocation.getText(NavigationLocation.java:60)\n\tat org.eclipse.ui.internal.NavigationHistoryEntry.\u003cinit\u003e(NavigationHistoryEntry.java:49)\n\tat org.eclipse.ui.internal.NavigationHistory.createEntry(NavigationHistory.java:655)\n\tat org.eclipse.ui.internal.NavigationHistory.addEntry(NavigationHistory.java:371)\n\tat org.eclipse.ui.internal.NavigationHistory.access$10(NavigationHistory.java:352)\n\tat org.eclipse.ui.internal.NavigationHistory$2.run(NavigationHistory.java:199)\n\tat org.eclipse.swt.widgets.RunnableLock.run(RunnableLock.java:35)\n\tat org.eclipse.swt.widgets.Synchronizer.runAsyncMessages(Synchronizer.java:123)\n\t... 23 more",
    "Created an attachment (id\u003d80803)\nPatch\n\n",
    "(In reply to comment #0)\n\u003e Found this NPE in the log. Sorry, didn\u0027t see when it was printed, but since\n\u003e NPEs are often easy to figure out, thought I would log anyway.\n\u003e !SESSION 2007-10-07 01:04:00.120\n\u003e -----------------------------------------------\n\u003e eclipse.buildId\u003dI20070625-1500\n\u003e java.version\u003d1.5.0_12\n\u003e java.vendor\u003dSun Microsystems Inc.\n\u003e BootLoader constants: OS\u003dwin32, ARCH\u003dx86, WS\u003dwin32, NL\u003den_CA\n\u003e Framework arguments:  -product org.eclipse.sdk.ide -pdelaunch\n\u003e Command-line arguments:  -product org.eclipse.sdk.ide -data\n\u003e C:\\dev\\abstratt/../runtime-New_configuration -dev\n\u003e file:C:/dev/abstratt/.metadata/.plugins/org.eclipse.pde.core/Full/dev.properties\n\u003e -pdelaunch -os win32 -ws win32 -arch x86 -consolelog -console\n\u003e !ENTRY org.eclipse.ui 4 0 2007-10-07 01:02:06.595\n\u003e !MESSAGE Unhandled event loop exception\n\u003e !STACK 0\n\u003e org.eclipse.swt.SWTException: Failed to execute runnable\n\u003e (java.lang.NullPointerException)\n\u003e         at org.eclipse.swt.SWT.error(SWT.java:3563)\n\u003e         at org.eclipse.swt.SWT.error(SWT.java:3481)\n\u003e         at\n\u003e org.eclipse.swt.widgets.Synchronizer.runAsyncMessages(Synchronizer.java:126)\n\u003e         at org.eclipse.swt.widgets.Display.runAsyncMessages(Display.java:3659)\n\u003e         at org.eclipse.swt.widgets.Display.readAndDispatch(Display.java:3296)\n\u003e         at org.eclipse.ui.internal.Workbench.runEventLoop(Workbench.java:2389)\n\u003e         at org.eclipse.ui.internal.Workbench.runUI(Workbench.java:2353)\n\u003e         at org.eclipse.ui.internal.Workbench.access$4(Workbench.java:2219)\n\u003e         at org.eclipse.ui.internal.Workbench$4.run(Workbench.java:466)\n\u003e         at\n\u003e org.eclipse.core.databinding.observable.Realm.runWithDefault(Realm.java:289)\n\u003e         at\n\u003e org.eclipse.ui.internal.Workbench.createAndRunWorkbench(Workbench.java:461)\n\u003e         at org.eclipse.ui.PlatformUI.createAndRunWorkbench(PlatformUI.java:149)\n\u003e         at\n\u003e org.eclipse.ui.internal.ide.application.IDEApplication.start(IDEApplication.java:106)\n\u003e         at\n\u003e org.eclipse.equinox.internal.app.EclipseAppHandle.run(EclipseAppHandle.java:153)\n\u003e         at\n\u003e org.eclipse.core.runtime.internal.adaptor.EclipseAppLauncher.runApplication(EclipseAppLauncher.java:106)\n\u003e         at\n\u003e org.eclipse.core.runtime.internal.adaptor.EclipseAppLauncher.start(EclipseAppLauncher.java:76)\n\u003e         at\n\u003e org.eclipse.core.runtime.adaptor.EclipseStarter.run(EclipseStarter.java:363)\n\u003e         at\n\u003e org.eclipse.core.runtime.adaptor.EclipseStarter.run(EclipseStarter.java:176)\n\u003e         at sun.reflect.NativeMethodAccessorImpl.invoke0(Native Method)\n\u003e         at\n\u003e sun.reflect.NativeMethodAccessorImpl.invoke(NativeMethodAccessorImpl.java:39)\n\u003e         at\n\u003e sun.reflect.DelegatingMethodAccessorImpl.invoke(DelegatingMethodAccessorImpl.java:25)\n\u003e         at java.lang.reflect.Method.invoke(Method.java:585)\n\u003e         at org.eclipse.equinox.launcher.Main.invokeFramework(Main.java:504)\n\u003e         at org.eclipse.equinox.launcher.Main.basicRun(Main.java:443)\n\u003e         at org.eclipse.equinox.launcher.Main.run(Main.java:1169)\n\u003e         at org.eclipse.equinox.launcher.Main.main(Main.java:1144)\n\u003e Caused by: java.lang.NullPointerException\n\u003e         at\n\u003e org.eclipse.pde.internal.ui.editor.plugin.ManifestEditorMatchingStrategy.matches(ManifestEditorMatchingStrategy.java:32)\n\u003e         at\n\u003e org.eclipse.ui.internal.EditorManager.findEditors(EditorManager.java:485)\n\u003e         at\n\u003e org.eclipse.ui.internal.EditorManager.findEditors(EditorManager.java:431)\n\u003e         at\n\u003e org.eclipse.ui.internal.EditorManager.findEditor(EditorManager.java:394)\n\u003e         at\n\u003e org.eclipse.ui.internal.EditorManager.findEditor(EditorManager.java:376)\n\u003e         at\n\u003e org.eclipse.ui.internal.WorkbenchPage.findEditor(WorkbenchPage.java:1967)\n\u003e         at\n\u003e org.eclipse.ui.NavigationLocation.getEditorPart(NavigationLocation.java:44)\n\u003e         at\n\u003e org.eclipse.ui.NavigationLocation.getText(NavigationLocation.java:60)\n\u003e         at\n\u003e org.eclipse.ui.internal.NavigationHistoryEntry.\u003cinit\u003e(NavigationHistoryEntry.java:49)\n\u003e         at\n\u003e org.eclipse.ui.internal.NavigationHistory.createEntry(NavigationHistory.java:655)\n\u003e         at\n\u003e org.eclipse.ui.internal.NavigationHistory.addEntry(NavigationHistory.java:371)\n\u003e         at\n\u003e org.eclipse.ui.internal.NavigationHistory.access$10(NavigationHistory.java:352)\n\u003e         at\n\u003e org.eclipse.ui.internal.NavigationHistory$2.run(NavigationHistory.java:199)\n\u003e         at org.eclipse.swt.widgets.RunnableLock.run(RunnableLock.java:35)\n\u003e         at\n\u003e org.eclipse.swt.widgets.Synchronizer.runAsyncMessages(Synchronizer.java:123)\n\u003e         ... 23 more\n\nHi. As you said this bug was easy to figure out. The problem was that it did not occur in my environment. I\u0027ve assumed that NPE was triggered when an inputFile variable had been set to null by ResourceUtil.getFile(input) method when an instance of IEditorInput being passed as argument didn\u0027t guarantee that the resource does exist. I attach a patch which simply extends the conditional expression by adding inputFile!\u003dnull when the input is an instance of IFileEditorInput. This is my first bug so please be understanding ;]",
    "I could not reproduce this bug either, but your assumption seems to be correct.  If for some reason that is not the culprit of the NPE, this is definitely a good check that could save us in the future.\n\nJanusz, thanks for your help and your educated guessing ;-)\n\nSend me a photo with a leafy background if you would like to be included on the PDE Contributor page (http://www.eclipse.org/pde/pde-ui/committers/committers.php).  Thanks again for your help!"
  ],
  "commentCreationDates": [
    "2007-10-07T10:09:57+02:00",
    "2007-10-19T22:58:15+02:00",
    "2007-10-19T22:58:51+02:00",
    "2007-10-22T19:31:39+02:00"
  ],
  "traces": [
    {
      "exceptionType": "org.eclipse.swt.SWTException",
      "message": "Failed to execute runnable (java.lang.NullPointerException)",
      "elements": [
        {
          "method": "org.eclipse.swt.SWT.error",
          "source": "SWT.java:3563"
        },
        {
          "method": "org.eclipse.swt.SWT.error",
          "source": "SWT.java:3481"
        },
        {
          "method": "org.eclipse.swt.widgets.Synchronizer.runAsyncMessages",
          "source": "Synchronizer.java:126"
        },
        {
          "method": "org.eclipse.swt.widgets.Display.runAsyncMessages",
          "source": "Display.java:3659"
        },
        {
          "method": "org.eclipse.swt.widgets.Display.readAndDispatch",
          "source": "Display.java:3296"
        },
        {
          "method": "org.eclipse.ui.internal.Workbench.runEventLoop",
          "source": "Workbench.java:2389"
        },
        {
          "method": "org.eclipse.ui.internal.Workbench.runUI",
          "source": "Workbench.java:2353"
        },
        {
          "method": "org.eclipse.ui.internal.Workbench.access$4",
          "source": "Workbench.java:2219"
        },
        {
          "method": "org.eclipse.ui.internal.Workbench$4.run",
          "source": "Workbench.java:466"
        },
        {
          "method": "org.eclipse.core.databinding.observable.Realm.runWithDefault",
          "source": "Realm.java:289"
        },
        {
          "method": "org.eclipse.ui.internal.Workbench.createAndRunWorkbench",
          "source": "Workbench.java:461"
        },
        {
          "method": "org.eclipse.ui.PlatformUI.createAndRunWorkbench",
          "source": "PlatformUI.java:149"
        },
        {
          "method": "org.eclipse.ui.internal.ide.application.IDEApplication.start",
          "source": "IDEApplication.java:106"
        },
        {
          "method": "org.eclipse.equinox.internal.app.EclipseAppHandle.run",
          "source": "EclipseAppHandle.java:153"
        },
        {
          "method": "org.eclipse.core.runtime.internal.adaptor.EclipseAppLauncher.runApplication",
          "source": "EclipseAppLauncher.java:106"
        },
        {
          "method": "org.eclipse.core.runtime.internal.adaptor.EclipseAppLauncher.start",
          "source": "EclipseAppLauncher.java:76"
        },
        {
          "method": "org.eclipse.core.runtime.adaptor.EclipseStarter.run",
          "source": "EclipseStarter.java:363"
        },
        {
          "method": "org.eclipse.core.runtime.adaptor.EclipseStarter.run",
          "source": "EclipseStarter.java:176"
        },
        {
          "method": "sun.reflect.NativeMethodAccessorImpl.invoke0",
          "source": "Native Method"
        },
        {
          "method": "sun.reflect.NativeMethodAccessorImpl.invoke",
          "source": "NativeMethodAccessorImpl.java:39"
        },
        {
          "method": "sun.reflect.DelegatingMethodAccessorImpl.invoke",
          "source": "DelegatingMethodAccessorImpl.java:25"
        },
        {
          "method": "java.lang.reflect.Method.invoke",
          "source": "Method.java:585"
        },
        {
          "method": "org.eclipse.equinox.launcher.Main.invokeFramework",
          "source": "Main.java:504"
        },
        {
          "method": "org.eclipse.equinox.launcher.Main.basicRun",
          "source": "Main.java:443"
        },
        {
          "method": "org.eclipse.equinox.launcher.Main.run",
          "source": "Main.java:1169"
        },
        {
          "method": "org.eclipse.equinox.launcher.Main.main",
          "source": "Main.java:1144"
        }
      ],
      "causedBy": {
        "exceptionType": "java.lang.NullPointerException",
        "elements": [
          {
            "method": "org.eclipse.pde.internal.ui.editor.plugin.ManifestEditorMatchingStrategy.matches",
            "source": "ManifestEditorMatchingStrategy.java:32"
          },
          {
            "method": "org.eclipse.ui.internal.EditorManager.findEditors",
            "source": "EditorManager.java:485"
          },
          {
            "method": "org.eclipse.ui.internal.EditorManager.findEditors",
            "source": "EditorManager.java:431"
          },
          {
            "method": "org.eclipse.ui.internal.EditorManager.findEditor",
            "source": "EditorManager.java:394"
          },
          {
            "method": "org.eclipse.ui.internal.EditorManager.findEditor",
            "source": "EditorManager.java:376"
          },
          {
            "method": "org.eclipse.ui.internal.WorkbenchPage.findEditor",
            "source": "WorkbenchPage.java:1967"
          },
          {
            "method": "org.eclipse.ui.NavigationLocation.getEditorPart",
            "source": "NavigationLocation.java:44"
          },
          {
            "method": "org.eclipse.ui.NavigationLocation.getText",
            "source": "NavigationLocation.java:60"
          },
          {
            "method": "org.eclipse.ui.internal.NavigationHistoryEntry.\u003cinit\u003e",
            "source": "NavigationHistoryEntry.java:49"
          },
          {
            "method": "org.eclipse.ui.internal.NavigationHistory.createEntry",
            "source": "NavigationHistory.java:655"
          },
          {
            "method": "org.eclipse.ui.internal.NavigationHistory.addEntry",
            "source": "NavigationHistory.java:371"
          },
          {
            "method": "org.eclipse.ui.internal.NavigationHistory.access$10",
            "source": "NavigationHistory.java:352"
          },
          {
            "method": "org.eclipse.ui.internal.NavigationHistory$2.run",
            "source": "NavigationHistory.java:199"
          },
          {
            "method": "org.eclipse.swt.widgets.RunnableLock.run",
            "source": "RunnableLock.java:35"
          },
          {
            "method": "org.eclipse.swt.widgets.Synchronizer.runAsyncMessages",
            "source": "Synchronizer.java:123"
          }
        ],
        "number": 0,
        "commentIndex": 0
      },
      "number": 0,
      "commentIndex": 0,
      "bugId": "205655",
      "date": "2007-10-07T10:09:57+02:00",
      "product": "PDE",
      "component": "UI",
      "severity": "normal"
    },
    {
      "exceptionType": "org.eclipse.swt.SWTException",
      "message": "Failed to execute runnable \u003e (java.lang.NullPointerException) \u003e",
      "elements": [
        {
          "method": "org.eclipse.swt.SWT.error",
          "source": "SWT.java:3563"
        }
      ],
      "number": 1,
      "commentIndex": 2,
      "bugId": "205655",
      "date": "2007-10-19T22:58:51+02:00",
      "product": "PDE",
      "component": "UI",
      "severity": "normal"
    }
  ],
  "groupId": "205655",
  "bugId": "205655",
  "date": "2007-10-07T10:09:57+02:00",
  "product": "PDE",
  "component": "UI",
  "severity": "normal"
}