{
  "comments": [
    "I20071009-2225\n\nIn my code, I accidentally used JavaCore.create(handleIdentifier, null), although JavaCore#create(String, WorkingCopyOwner) does not allow the second parameter to be null.\n\nAn ICompilationUnit was created with owner \u003d\u003d null, which later lead to NPEs when it was used, e.g. here:\nException in thread \"Info view input computer\" java.lang.NullPointerException\n\tat org.eclipse.jdt.internal.core.CompilationUnit.equals(CompilationUnit.java:453)\n\tat org.eclipse.jdt.internal.core.JavaElement.equals(JavaElement.java:121)\n\tat org.eclipse.jdt.internal.core.SourceRefElement.equals(SourceRefElement.java:83)\n\tat org.eclipse.jdt.internal.core.SourceType.equals(SourceType.java:158)\n\tat org.eclipse.jdt.internal.ui.infoviews.AbstractInfoView.isIgnoringNewInput(AbstractInfoView.java:376)\n\tat org.eclipse.jdt.internal.ui.infoviews.JavadocView.isIgnoringNewInput(JavadocView.java:633)\n\tat org.eclipse.jdt.internal.ui.infoviews.AbstractInfoView$2.run(AbstractInfoView.java:537)\n\nThe create(..,..) method should either allow null as owner (and replace it with DefaultWorkingCopyOwner.PRIMARY), or it should throw an NPE or an IllegalArgumentException in this case).\n\nFurthermore, the Javadoc is not fully correct:\n\n * @param owner the owner of the returned compilation unit, ignored if the\n *   returned element is not a compilation unit\n\n\u003d\u003e owner is only ignored if the element is not a CU *or an element inside a CU* (my call actually created an IType)."
  ],
  "commentCreationDates": [
    "2007-10-10T15:51:36+02:00"
  ],
  "traces": [
    {
      "exceptionType": "java.lang.NullPointerException",
      "elements": [
        {
          "method": "org.eclipse.jdt.internal.core.CompilationUnit.equals",
          "source": "CompilationUnit.java:453"
        },
        {
          "method": "org.eclipse.jdt.internal.core.JavaElement.equals",
          "source": "JavaElement.java:121"
        },
        {
          "method": "org.eclipse.jdt.internal.core.SourceRefElement.equals",
          "source": "SourceRefElement.java:83"
        },
        {
          "method": "org.eclipse.jdt.internal.core.SourceType.equals",
          "source": "SourceType.java:158"
        },
        {
          "method": "org.eclipse.jdt.internal.ui.infoviews.AbstractInfoView.isIgnoringNewInput",
          "source": "AbstractInfoView.java:376"
        },
        {
          "method": "org.eclipse.jdt.internal.ui.infoviews.JavadocView.isIgnoringNewInput",
          "source": "JavadocView.java:633"
        },
        {
          "method": "org.eclipse.jdt.internal.ui.infoviews.AbstractInfoView$2.run",
          "source": "AbstractInfoView.java:537"
        }
      ],
      "number": 0,
      "commentIndex": 0,
      "bugId": "205917",
      "date": "2007-10-10T15:51:36+02:00",
      "product": "JDT",
      "component": "Core",
      "severity": "normal"
    }
  ],
  "groupId": "205917",
  "bugId": "205917",
  "date": "2007-10-10T15:51:36+02:00",
  "product": "JDT",
  "component": "Core",
  "severity": "normal"
}