{
  "comments": [
    "Build ID: M20070921-1145\n\nSteps To Reproduce:\nI\u0027m using Eclipse v3.3.1 M20070921-1145, Mylyn v2.0.0 200070627-1400, I also have Subclipse installed, but the Subclipse Mylyn Integration is disabled. \n\nI get the above exception in the log every time Eclipse starts.\n\nI\u0027m seeing similar problems to the ones described in bug 205673. This could also be connected to bug 200220.\n\nMore information:\nThis is the exception from the log:\n\n!ENTRY org.eclipse.osgi 2 0 2007-10-12 01:12:15.656\n!MESSAGE While loading class\n\"org.eclipse.mylyn.internal.tasks.ui.ITaskHighlighter\", thread\n\"Thread[Worker-0,5,main]\" timed out waiting (5000ms) for thread\n\"Thread[Worker-1,5,main]\" to finish starting bundle\n\"update@plugins/org.eclipse.mylyn.tasks.ui_2.0.0.v20070627-1400.jar [140]\". To\navoid deadlock, thread \"Thread[Worker-0,5,main]\" is proceeding but\n\"org.eclipse.mylyn.internal.tasks.ui.ITaskHighlighter\" may not be fully\ninitialized.\n!STACK 0\norg.osgi.framework.BundleException: State change in progress for bundle\n\"update@plugins/org.eclipse.mylyn.tasks.ui_2.0.0.v20070627-1400.jar\" by thread\n\"Worker-1\".\n        at\norg.eclipse.osgi.framework.internal.core.AbstractBundle.beginStateChange(AbstractBundle.java:1141)\n        at\norg.eclipse.osgi.framework.internal.core.AbstractBundle.start(AbstractBundle.java:258)\n        at\norg.eclipse.osgi.framework.util.SecureAction.start(SecureAction.java:400)\n        at\norg.eclipse.core.runtime.internal.adaptor.EclipseLazyStarter.postFindLocalClass(EclipseLazyStarter.java:111)\n        at\norg.eclipse.osgi.baseadaptor.loader.ClasspathManager.findLocalClass(ClasspathManager.java:417)\n        at\norg.eclipse.osgi.internal.baseadaptor.DefaultClassLoader.findLocalClass(DefaultClassLoader.java:189)\n        at\norg.eclipse.osgi.framework.internal.core.BundleLoader.findLocalClass(BundleLoader.java:340)\n        at\norg.eclipse.osgi.framework.internal.core.SingleSourcePackage.loadClass(SingleSourcePackage.java:37)\n        at\norg.eclipse.osgi.framework.internal.core.BundleLoader.findClassInternal(BundleLoader.java:405)\n        at\norg.eclipse.osgi.framework.internal.core.BundleLoader.findClass(BundleLoader.java:369)\n        at\norg.eclipse.osgi.framework.internal.core.BundleLoader.findClass(BundleLoader.java:357)\n        at\norg.eclipse.osgi.internal.baseadaptor.DefaultClassLoader.loadClass(DefaultClassLoader.java:83)\n        at java.lang.ClassLoader.loadClass(Unknown Source)\n        at java.lang.ClassLoader.loadClassInternal(Unknown Source)\n        at java.lang.Class.getDeclaredConstructors0(Native Method)\n        at java.lang.Class.privateGetDeclaredConstructors(Unknown Source)\n        at java.lang.Class.getConstructor0(Unknown Source)\n        at java.lang.Class.newInstance0(Unknown Source)\n        at java.lang.Class.newInstance(Unknown Source)\n        at\norg.eclipse.osgi.framework.internal.core.AbstractBundle.loadBundleActivator(AbstractBundle.java:136)\n        at\norg.eclipse.osgi.framework.internal.core.BundleContextImpl.start(BundleContextImpl.java:970)\n        at\norg.eclipse.osgi.framework.internal.core.BundleHost.startWorker(BundleHost.java:346)\n        at\norg.eclipse.osgi.framework.internal.core.AbstractBundle.start(AbstractBundle.java:260)\n        at\norg.eclipse.osgi.framework.util.SecureAction.start(SecureAction.java:400)\n        at\norg.eclipse.core.runtime.internal.adaptor.EclipseLazyStarter.postFindLocalClass(EclipseLazyStarter.java:111)\n        at\norg.eclipse.osgi.baseadaptor.loader.ClasspathManager.findLocalClass(ClasspathManager.java:417)\n        at\norg.eclipse.osgi.internal.baseadaptor.DefaultClassLoader.findLocalClass(DefaultClassLoader.java:189)\n        at\norg.eclipse.osgi.framework.internal.core.BundleLoader.findLocalClass(BundleLoader.java:340)\n        at\norg.eclipse.osgi.framework.internal.core.BundleLoader.findClassInternal(BundleLoader.java:408)\n        at\norg.eclipse.osgi.framework.internal.core.BundleLoader.findClass(BundleLoader.java:369)\n        at\norg.eclipse.osgi.framework.internal.core.BundleLoader.findClass(BundleLoader.java:357)\n        at\norg.eclipse.osgi.internal.baseadaptor.DefaultClassLoader.loadClass(DefaultClassLoader.java:83)\n        at java.lang.ClassLoader.loadClass(Unknown Source)\n        at\norg.eclipse.osgi.framework.internal.core.BundleLoader.loadClass(BundleLoader.java:289)\n        at\norg.eclipse.osgi.framework.internal.core.BundleHost.loadClass(BundleHost.java:227)\n        at\norg.eclipse.osgi.framework.internal.core.AbstractBundle.loadClass(AbstractBundle.java:1269)\n        at\norg.eclipse.core.internal.registry.osgi.RegistryStrategyOSGI.createExecutableExtension(RegistryStrategyOSGI.java:160)\n        at\norg.eclipse.core.internal.registry.ExtensionRegistry.createExecutableExtension(ExtensionRegistry.java:788)\n        at\norg.eclipse.core.internal.registry.ConfigurationElement.createExecutableExtension(ConfigurationElement.java:243)\n        at\norg.eclipse.core.internal.registry.ConfigurationElementHandle.createExecutableExtension(ConfigurationElementHandle.java:51)\n        at\norg.eclipse.ui.internal.WorkbenchPlugin$1.run(WorkbenchPlugin.java:252)\n        at\norg.eclipse.swt.custom.BusyIndicator.showWhile(BusyIndicator.java:49)\n        at\norg.eclipse.ui.internal.WorkbenchPlugin.createExtension(WorkbenchPlugin.java:248)\n        at\norg.eclipse.ui.internal.decorators.LightweightDecoratorDefinition$1.run(LightweightDecoratorDefinition.java:117)\n        at org.eclipse.core.runtime.SafeRunner.run(SafeRunner.java:37)\n        at org.eclipse.core.runtime.Platform.run(Platform.java:857)\n        at\norg.eclipse.ui.internal.decorators.LightweightDecoratorDefinition.internalGetDecorator(LightweightDecoratorDefinition.java:113)\n        at\norg.eclipse.ui.internal.decorators.LightweightDecoratorDefinition.decorate(LightweightDecoratorDefinition.java:241)\n        at\norg.eclipse.ui.internal.decorators.LightweightDecoratorManager$LightweightRunnable.run(LightweightDecoratorManager.java:71)\n        at org.eclipse.core.runtime.SafeRunner.run(SafeRunner.java:37)\n        at org.eclipse.core.runtime.Platform.run(Platform.java:857)\n        at\norg.eclipse.ui.internal.decorators.LightweightDecoratorManager.decorate(LightweightDecoratorManager.java:336)\n        at\norg.eclipse.ui.internal.decorators.LightweightDecoratorManager.getDecorations(LightweightDecoratorManager.java:322)\n        at\norg.eclipse.ui.internal.decorators.DecorationScheduler$1.ensureResultCached(DecorationScheduler.java:369)\n        at\norg.eclipse.ui.internal.decorators.DecorationScheduler$1.run(DecorationScheduler.java:329)\n        at org.eclipse.core.internal.jobs.Worker.run(Worker.java:55)\nCaused by:\norg.eclipse.osgi.framework.internal.core.AbstractBundle$BundleStatusException\n        ... 56 more\nRoot exception:\norg.eclipse.osgi.framework.internal.core.AbstractBundle$BundleStatusException\n        at\norg.eclipse.osgi.framework.internal.core.AbstractBundle.beginStateChange(AbstractBundle.java:1141)\n        at\norg.eclipse.osgi.framework.internal.core.AbstractBundle.start(AbstractBundle.java:258)\n        at\norg.eclipse.osgi.framework.util.SecureAction.start(SecureAction.java:400)\n        at\norg.eclipse.core.runtime.internal.adaptor.EclipseLazyStarter.postFindLocalClass(EclipseLazyStarter.java:111)\n        at\norg.eclipse.osgi.baseadaptor.loader.ClasspathManager.findLocalClass(ClasspathManager.java:417)\n        at\norg.eclipse.osgi.internal.baseadaptor.DefaultClassLoader.findLocalClass(DefaultClassLoader.java:189)\n        at\norg.eclipse.osgi.framework.internal.core.BundleLoader.findLocalClass(BundleLoader.java:340)\n        at\norg.eclipse.osgi.framework.internal.core.SingleSourcePackage.loadClass(SingleSourcePackage.java:37)\n        at\norg.eclipse.osgi.framework.internal.core.BundleLoader.findClassInternal(BundleLoader.java:405)\n        at\norg.eclipse.osgi.framework.internal.core.BundleLoader.findClass(BundleLoader.java:369)\n        at\norg.eclipse.osgi.framework.internal.core.BundleLoader.findClass(BundleLoader.java:357)\n        at\norg.eclipse.osgi.internal.baseadaptor.DefaultClassLoader.loadClass(DefaultClassLoader.java:83)\n        at java.lang.ClassLoader.loadClass(Unknown Source)\n        at java.lang.ClassLoader.loadClassInternal(Unknown Source)\n        at java.lang.Class.getDeclaredConstructors0(Native Method)\n        at java.lang.Class.privateGetDeclaredConstructors(Unknown Source)\n        at java.lang.Class.getConstructor0(Unknown Source)\n        at java.lang.Class.newInstance0(Unknown Source)\n        at java.lang.Class.newInstance(Unknown Source)\n        at\norg.eclipse.osgi.framework.internal.core.AbstractBundle.loadBundleActivator(AbstractBundle.java:136)\n        at\norg.eclipse.osgi.framework.internal.core.BundleContextImpl.start(BundleContextImpl.java:970)\n        at\norg.eclipse.osgi.framework.internal.core.BundleHost.startWorker(BundleHost.java:346)\n        at\norg.eclipse.osgi.framework.internal.core.AbstractBundle.start(AbstractBundle.java:260)\n        at\norg.eclipse.osgi.framework.util.SecureAction.start(SecureAction.java:400)\n        at\norg.eclipse.core.runtime.internal.adaptor.EclipseLazyStarter.postFindLocalClass(EclipseLazyStarter.java:111)\n        at\norg.eclipse.osgi.baseadaptor.loader.ClasspathManager.findLocalClass(ClasspathManager.java:417)\n        at\norg.eclipse.osgi.internal.baseadaptor.DefaultClassLoader.findLocalClass(DefaultClassLoader.java:189)\n        at\norg.eclipse.osgi.framework.internal.core.BundleLoader.findLocalClass(BundleLoader.java:340)\n        at\norg.eclipse.osgi.framework.internal.core.BundleLoader.findClassInternal(BundleLoader.java:408)\n        at\norg.eclipse.osgi.framework.internal.core.BundleLoader.findClass(BundleLoader.java:369)\n        at\norg.eclipse.osgi.framework.internal.core.BundleLoader.findClass(BundleLoader.java:357)\n        at\norg.eclipse.osgi.internal.baseadaptor.DefaultClassLoader.loadClass(DefaultClassLoader.java:83)\n        at java.lang.ClassLoader.loadClass(Unknown Source)\n        at\norg.eclipse.osgi.framework.internal.core.BundleLoader.loadClass(BundleLoader.java:289)\n        at\norg.eclipse.osgi.framework.internal.core.BundleHost.loadClass(BundleHost.java:227)\n        at\norg.eclipse.osgi.framework.internal.core.AbstractBundle.loadClass(AbstractBundle.java:1269)\n        at\norg.eclipse.core.internal.registry.osgi.RegistryStrategyOSGI.createExecutableExtension(RegistryStrategyOSGI.java:160)\n        at\norg.eclipse.core.internal.registry.ExtensionRegistry.createExecutableExtension(ExtensionRegistry.java:788)\n        at\norg.eclipse.core.internal.registry.ConfigurationElement.createExecutableExtension(ConfigurationElement.java:243)\n        at\norg.eclipse.core.internal.registry.ConfigurationElementHandle.createExecutableExtension(ConfigurationElementHandle.java:51)\n        at\norg.eclipse.ui.internal.WorkbenchPlugin$1.run(WorkbenchPlugin.java:252)\n        at\norg.eclipse.swt.custom.BusyIndicator.showWhile(BusyIndicator.java:49)\n        at\norg.eclipse.ui.internal.WorkbenchPlugin.createExtension(WorkbenchPlugin.java:248)\n        at\norg.eclipse.ui.internal.decorators.LightweightDecoratorDefinition$1.run(LightweightDecoratorDefinition.java:117)\n        at org.eclipse.core.runtime.SafeRunner.run(SafeRunner.java:37)\n        at org.eclipse.core.runtime.Platform.run(Platform.java:857)\n        at\norg.eclipse.ui.internal.decorators.LightweightDecoratorDefinition.internalGetDecorator(LightweightDecoratorDefinition.java:113)\n        at\norg.eclipse.ui.internal.decorators.LightweightDecoratorDefinition.decorate(LightweightDecoratorDefinition.java:241)\n        at\norg.eclipse.ui.internal.decorators.LightweightDecoratorManager$LightweightRunnable.run(LightweightDecoratorManager.java:71)\n        at org.eclipse.core.runtime.SafeRunner.run(SafeRunner.java:37)\n        at org.eclipse.core.runtime.Platform.run(Platform.java:857)\n        at\norg.eclipse.ui.internal.decorators.LightweightDecoratorManager.decorate(LightweightDecoratorManager.java:336)\n        at\norg.eclipse.ui.internal.decorators.LightweightDecoratorManager.getDecorations(LightweightDecoratorManager.java:322)\n        at\norg.eclipse.ui.internal.decorators.DecorationScheduler$1.ensureResultCached(DecorationScheduler.java:369)\n        at\norg.eclipse.ui.internal.decorators.DecorationScheduler$1.run(DecorationScheduler.java:329)\n        at org.eclipse.core.internal.jobs.Worker.run(Worker.java:55)",
    "I just wanted to add that the problem started after updating to Eclipse v3.3.1.",
    "Note that these warnings are innocuous as far as we know.  Do you see this on every restart, or just on the first restart?\n\n*** This bug has been marked as a duplicate of bug 188524 ***"
  ],
  "commentCreationDates": [
    "2007-10-12T01:26:44+02:00",
    "2007-10-12T13:36:10+02:00",
    "2007-10-17T06:27:11+02:00"
  ],
  "traces": [
    {
      "exceptionType": "org.osgi.framework.BundleException",
      "message": "State change in progress for bundle \"update@plugins/org.eclipse.mylyn.tasks.ui_2.0.0.v20070627-1400.jar\" by thread \"Worker-1\".",
      "elements": [
        {
          "method": "org.eclipse.osgi.framework.internal.core.AbstractBundle.beginStateChange",
          "source": "AbstractBundle.java:1141"
        },
        {
          "method": "org.eclipse.osgi.framework.internal.core.AbstractBundle.start",
          "source": "AbstractBundle.java:258"
        },
        {
          "method": "org.eclipse.osgi.framework.util.SecureAction.start",
          "source": "SecureAction.java:400"
        },
        {
          "method": "org.eclipse.core.runtime.internal.adaptor.EclipseLazyStarter.postFindLocalClass",
          "source": "EclipseLazyStarter.java:111"
        },
        {
          "method": "org.eclipse.osgi.baseadaptor.loader.ClasspathManager.findLocalClass",
          "source": "ClasspathManager.java:417"
        },
        {
          "method": "org.eclipse.osgi.internal.baseadaptor.DefaultClassLoader.findLocalClass",
          "source": "DefaultClassLoader.java:189"
        },
        {
          "method": "org.eclipse.osgi.framework.internal.core.BundleLoader.findLocalClass",
          "source": "BundleLoader.java:340"
        },
        {
          "method": "org.eclipse.osgi.framework.internal.core.SingleSourcePackage.loadClass",
          "source": "SingleSourcePackage.java:37"
        },
        {
          "method": "org.eclipse.osgi.framework.internal.core.BundleLoader.findClassInternal",
          "source": "BundleLoader.java:405"
        },
        {
          "method": "org.eclipse.osgi.framework.internal.core.BundleLoader.findClass",
          "source": "BundleLoader.java:369"
        },
        {
          "method": "org.eclipse.osgi.framework.internal.core.BundleLoader.findClass",
          "source": "BundleLoader.java:357"
        },
        {
          "method": "org.eclipse.osgi.internal.baseadaptor.DefaultClassLoader.loadClass",
          "source": "DefaultClassLoader.java:83"
        },
        {
          "method": "java.lang.ClassLoader.loadClass",
          "source": "Unknown Source"
        },
        {
          "method": "java.lang.ClassLoader.loadClassInternal",
          "source": "Unknown Source"
        },
        {
          "method": "java.lang.Class.getDeclaredConstructors0",
          "source": "Native Method"
        },
        {
          "method": "java.lang.Class.privateGetDeclaredConstructors",
          "source": "Unknown Source"
        },
        {
          "method": "java.lang.Class.getConstructor0",
          "source": "Unknown Source"
        },
        {
          "method": "java.lang.Class.newInstance0",
          "source": "Unknown Source"
        },
        {
          "method": "java.lang.Class.newInstance",
          "source": "Unknown Source"
        },
        {
          "method": "org.eclipse.osgi.framework.internal.core.AbstractBundle.loadBundleActivator",
          "source": "AbstractBundle.java:136"
        },
        {
          "method": "org.eclipse.osgi.framework.internal.core.BundleContextImpl.start",
          "source": "BundleContextImpl.java:970"
        },
        {
          "method": "org.eclipse.osgi.framework.internal.core.BundleHost.startWorker",
          "source": "BundleHost.java:346"
        },
        {
          "method": "org.eclipse.osgi.framework.internal.core.AbstractBundle.start",
          "source": "AbstractBundle.java:260"
        },
        {
          "method": "org.eclipse.osgi.framework.util.SecureAction.start",
          "source": "SecureAction.java:400"
        },
        {
          "method": "org.eclipse.core.runtime.internal.adaptor.EclipseLazyStarter.postFindLocalClass",
          "source": "EclipseLazyStarter.java:111"
        },
        {
          "method": "org.eclipse.osgi.baseadaptor.loader.ClasspathManager.findLocalClass",
          "source": "ClasspathManager.java:417"
        },
        {
          "method": "org.eclipse.osgi.internal.baseadaptor.DefaultClassLoader.findLocalClass",
          "source": "DefaultClassLoader.java:189"
        },
        {
          "method": "org.eclipse.osgi.framework.internal.core.BundleLoader.findLocalClass",
          "source": "BundleLoader.java:340"
        },
        {
          "method": "org.eclipse.osgi.framework.internal.core.BundleLoader.findClassInternal",
          "source": "BundleLoader.java:408"
        },
        {
          "method": "org.eclipse.osgi.framework.internal.core.BundleLoader.findClass",
          "source": "BundleLoader.java:369"
        },
        {
          "method": "org.eclipse.osgi.framework.internal.core.BundleLoader.findClass",
          "source": "BundleLoader.java:357"
        },
        {
          "method": "org.eclipse.osgi.internal.baseadaptor.DefaultClassLoader.loadClass",
          "source": "DefaultClassLoader.java:83"
        },
        {
          "method": "java.lang.ClassLoader.loadClass",
          "source": "Unknown Source"
        },
        {
          "method": "org.eclipse.osgi.framework.internal.core.BundleLoader.loadClass",
          "source": "BundleLoader.java:289"
        },
        {
          "method": "org.eclipse.osgi.framework.internal.core.BundleHost.loadClass",
          "source": "BundleHost.java:227"
        },
        {
          "method": "org.eclipse.osgi.framework.internal.core.AbstractBundle.loadClass",
          "source": "AbstractBundle.java:1269"
        },
        {
          "method": "org.eclipse.core.internal.registry.osgi.RegistryStrategyOSGI.createExecutableExtension",
          "source": "RegistryStrategyOSGI.java:160"
        },
        {
          "method": "org.eclipse.core.internal.registry.ExtensionRegistry.createExecutableExtension",
          "source": "ExtensionRegistry.java:788"
        },
        {
          "method": "org.eclipse.core.internal.registry.ConfigurationElement.createExecutableExtension",
          "source": "ConfigurationElement.java:243"
        },
        {
          "method": "org.eclipse.core.internal.registry.ConfigurationElementHandle.createExecutableExtension",
          "source": "ConfigurationElementHandle.java:51"
        },
        {
          "method": "org.eclipse.ui.internal.WorkbenchPlugin$1.run",
          "source": "WorkbenchPlugin.java:252"
        },
        {
          "method": "org.eclipse.swt.custom.BusyIndicator.showWhile",
          "source": "BusyIndicator.java:49"
        },
        {
          "method": "org.eclipse.ui.internal.WorkbenchPlugin.createExtension",
          "source": "WorkbenchPlugin.java:248"
        },
        {
          "method": "org.eclipse.ui.internal.decorators.LightweightDecoratorDefinition$1.run",
          "source": "LightweightDecoratorDefinition.java:117"
        },
        {
          "method": "org.eclipse.core.runtime.SafeRunner.run",
          "source": "SafeRunner.java:37"
        },
        {
          "method": "org.eclipse.core.runtime.Platform.run",
          "source": "Platform.java:857"
        },
        {
          "method": "org.eclipse.ui.internal.decorators.LightweightDecoratorDefinition.internalGetDecorator",
          "source": "LightweightDecoratorDefinition.java:113"
        },
        {
          "method": "org.eclipse.ui.internal.decorators.LightweightDecoratorDefinition.decorate",
          "source": "LightweightDecoratorDefinition.java:241"
        },
        {
          "method": "org.eclipse.ui.internal.decorators.LightweightDecoratorManager$LightweightRunnable.run",
          "source": "LightweightDecoratorManager.java:71"
        },
        {
          "method": "org.eclipse.core.runtime.SafeRunner.run",
          "source": "SafeRunner.java:37"
        },
        {
          "method": "org.eclipse.core.runtime.Platform.run",
          "source": "Platform.java:857"
        },
        {
          "method": "org.eclipse.ui.internal.decorators.LightweightDecoratorManager.decorate",
          "source": "LightweightDecoratorManager.java:336"
        },
        {
          "method": "org.eclipse.ui.internal.decorators.LightweightDecoratorManager.getDecorations",
          "source": "LightweightDecoratorManager.java:322"
        },
        {
          "method": "org.eclipse.ui.internal.decorators.DecorationScheduler$1.ensureResultCached",
          "source": "DecorationScheduler.java:369"
        },
        {
          "method": "org.eclipse.ui.internal.decorators.DecorationScheduler$1.run",
          "source": "DecorationScheduler.java:329"
        },
        {
          "method": "org.eclipse.core.internal.jobs.Worker.run",
          "source": "Worker.java:55"
        }
      ],
      "causedBy": {
        "exceptionType": "org.eclipse.osgi.framework.internal.core.AbstractBundle$BundleStatusException",
        "elements": [
          {
            "method": "org.eclipse.osgi.framework.internal.core.AbstractBundle.beginStateChange",
            "source": "AbstractBundle.java:1141"
          },
          {
            "method": "org.eclipse.osgi.framework.internal.core.AbstractBundle.start",
            "source": "AbstractBundle.java:258"
          },
          {
            "method": "org.eclipse.osgi.framework.util.SecureAction.start",
            "source": "SecureAction.java:400"
          },
          {
            "method": "org.eclipse.core.runtime.internal.adaptor.EclipseLazyStarter.postFindLocalClass",
            "source": "EclipseLazyStarter.java:111"
          },
          {
            "method": "org.eclipse.osgi.baseadaptor.loader.ClasspathManager.findLocalClass",
            "source": "ClasspathManager.java:417"
          },
          {
            "method": "org.eclipse.osgi.internal.baseadaptor.DefaultClassLoader.findLocalClass",
            "source": "DefaultClassLoader.java:189"
          },
          {
            "method": "org.eclipse.osgi.framework.internal.core.BundleLoader.findLocalClass",
            "source": "BundleLoader.java:340"
          },
          {
            "method": "org.eclipse.osgi.framework.internal.core.SingleSourcePackage.loadClass",
            "source": "SingleSourcePackage.java:37"
          },
          {
            "method": "org.eclipse.osgi.framework.internal.core.BundleLoader.findClassInternal",
            "source": "BundleLoader.java:405"
          },
          {
            "method": "org.eclipse.osgi.framework.internal.core.BundleLoader.findClass",
            "source": "BundleLoader.java:369"
          },
          {
            "method": "org.eclipse.osgi.framework.internal.core.BundleLoader.findClass",
            "source": "BundleLoader.java:357"
          },
          {
            "method": "org.eclipse.osgi.internal.baseadaptor.DefaultClassLoader.loadClass",
            "source": "DefaultClassLoader.java:83"
          },
          {
            "method": "java.lang.ClassLoader.loadClass",
            "source": "Unknown Source"
          },
          {
            "method": "java.lang.ClassLoader.loadClassInternal",
            "source": "Unknown Source"
          },
          {
            "method": "java.lang.Class.getDeclaredConstructors0",
            "source": "Native Method"
          },
          {
            "method": "java.lang.Class.privateGetDeclaredConstructors",
            "source": "Unknown Source"
          },
          {
            "method": "java.lang.Class.getConstructor0",
            "source": "Unknown Source"
          },
          {
            "method": "java.lang.Class.newInstance0",
            "source": "Unknown Source"
          },
          {
            "method": "java.lang.Class.newInstance",
            "source": "Unknown Source"
          },
          {
            "method": "org.eclipse.osgi.framework.internal.core.AbstractBundle.loadBundleActivator",
            "source": "AbstractBundle.java:136"
          },
          {
            "method": "org.eclipse.osgi.framework.internal.core.BundleContextImpl.start",
            "source": "BundleContextImpl.java:970"
          },
          {
            "method": "org.eclipse.osgi.framework.internal.core.BundleHost.startWorker",
            "source": "BundleHost.java:346"
          },
          {
            "method": "org.eclipse.osgi.framework.internal.core.AbstractBundle.start",
            "source": "AbstractBundle.java:260"
          },
          {
            "method": "org.eclipse.osgi.framework.util.SecureAction.start",
            "source": "SecureAction.java:400"
          },
          {
            "method": "org.eclipse.core.runtime.internal.adaptor.EclipseLazyStarter.postFindLocalClass",
            "source": "EclipseLazyStarter.java:111"
          },
          {
            "method": "org.eclipse.osgi.baseadaptor.loader.ClasspathManager.findLocalClass",
            "source": "ClasspathManager.java:417"
          },
          {
            "method": "org.eclipse.osgi.internal.baseadaptor.DefaultClassLoader.findLocalClass",
            "source": "DefaultClassLoader.java:189"
          },
          {
            "method": "org.eclipse.osgi.framework.internal.core.BundleLoader.findLocalClass",
            "source": "BundleLoader.java:340"
          },
          {
            "method": "org.eclipse.osgi.framework.internal.core.BundleLoader.findClassInternal",
            "source": "BundleLoader.java:408"
          },
          {
            "method": "org.eclipse.osgi.framework.internal.core.BundleLoader.findClass",
            "source": "BundleLoader.java:369"
          },
          {
            "method": "org.eclipse.osgi.framework.internal.core.BundleLoader.findClass",
            "source": "BundleLoader.java:357"
          },
          {
            "method": "org.eclipse.osgi.internal.baseadaptor.DefaultClassLoader.loadClass",
            "source": "DefaultClassLoader.java:83"
          },
          {
            "method": "java.lang.ClassLoader.loadClass",
            "source": "Unknown Source"
          },
          {
            "method": "org.eclipse.osgi.framework.internal.core.BundleLoader.loadClass",
            "source": "BundleLoader.java:289"
          },
          {
            "method": "org.eclipse.osgi.framework.internal.core.BundleHost.loadClass",
            "source": "BundleHost.java:227"
          },
          {
            "method": "org.eclipse.osgi.framework.internal.core.AbstractBundle.loadClass",
            "source": "AbstractBundle.java:1269"
          },
          {
            "method": "org.eclipse.core.internal.registry.osgi.RegistryStrategyOSGI.createExecutableExtension",
            "source": "RegistryStrategyOSGI.java:160"
          },
          {
            "method": "org.eclipse.core.internal.registry.ExtensionRegistry.createExecutableExtension",
            "source": "ExtensionRegistry.java:788"
          },
          {
            "method": "org.eclipse.core.internal.registry.ConfigurationElement.createExecutableExtension",
            "source": "ConfigurationElement.java:243"
          },
          {
            "method": "org.eclipse.core.internal.registry.ConfigurationElementHandle.createExecutableExtension",
            "source": "ConfigurationElementHandle.java:51"
          },
          {
            "method": "org.eclipse.ui.internal.WorkbenchPlugin$1.run",
            "source": "WorkbenchPlugin.java:252"
          },
          {
            "method": "org.eclipse.swt.custom.BusyIndicator.showWhile",
            "source": "BusyIndicator.java:49"
          },
          {
            "method": "org.eclipse.ui.internal.WorkbenchPlugin.createExtension",
            "source": "WorkbenchPlugin.java:248"
          },
          {
            "method": "org.eclipse.ui.internal.decorators.LightweightDecoratorDefinition$1.run",
            "source": "LightweightDecoratorDefinition.java:117"
          },
          {
            "method": "org.eclipse.core.runtime.SafeRunner.run",
            "source": "SafeRunner.java:37"
          },
          {
            "method": "org.eclipse.core.runtime.Platform.run",
            "source": "Platform.java:857"
          },
          {
            "method": "org.eclipse.ui.internal.decorators.LightweightDecoratorDefinition.internalGetDecorator",
            "source": "LightweightDecoratorDefinition.java:113"
          },
          {
            "method": "org.eclipse.ui.internal.decorators.LightweightDecoratorDefinition.decorate",
            "source": "LightweightDecoratorDefinition.java:241"
          },
          {
            "method": "org.eclipse.ui.internal.decorators.LightweightDecoratorManager$LightweightRunnable.run",
            "source": "LightweightDecoratorManager.java:71"
          },
          {
            "method": "org.eclipse.core.runtime.SafeRunner.run",
            "source": "SafeRunner.java:37"
          },
          {
            "method": "org.eclipse.core.runtime.Platform.run",
            "source": "Platform.java:857"
          },
          {
            "method": "org.eclipse.ui.internal.decorators.LightweightDecoratorManager.decorate",
            "source": "LightweightDecoratorManager.java:336"
          },
          {
            "method": "org.eclipse.ui.internal.decorators.LightweightDecoratorManager.getDecorations",
            "source": "LightweightDecoratorManager.java:322"
          },
          {
            "method": "org.eclipse.ui.internal.decorators.DecorationScheduler$1.ensureResultCached",
            "source": "DecorationScheduler.java:369"
          },
          {
            "method": "org.eclipse.ui.internal.decorators.DecorationScheduler$1.run",
            "source": "DecorationScheduler.java:329"
          },
          {
            "method": "org.eclipse.core.internal.jobs.Worker.run",
            "source": "Worker.java:55"
          }
        ],
        "number": 0,
        "commentIndex": 0
      },
      "number": 0,
      "commentIndex": 0,
      "bugId": "206097",
      "duplicateId": "188524",
      "date": "2007-10-12T01:26:44+02:00",
      "product": "Mylyn",
      "component": "Tasks",
      "severity": "normal"
    }
  ],
  "groupId": "188524",
  "bugId": "206097",
  "duplicateId": "188524",
  "date": "2007-10-12T01:26:44+02:00",
  "product": "Mylyn",
  "component": "Tasks",
  "severity": "normal"
}