{
  "comments": [
    "Created an attachment (id\u003d80128)\nConfig snapshot and workbanch log files\n\nDuring Eclipse 3.3.1 Europa Fall startup the following error is seen in the workspace log file:\n--------------------------------------------------\nENTRY org.eclipse.osgi 2 0 2007-10-11 11:18:28.737\n!MESSAGE While loading class \"org.eclipse.mylyn.internal.tasks.ui.ITaskHighlighter\", thread \"Thread[Worker-2,5,main]\" timed out waiting (5000ms) for thread \"Thread[Worker-0,5,main]\" to finish starting bundle \"update@plugins/org.eclipse.mylyn.tasks.ui_2.1.0.v20070927-0900.jar [77]\". To avoid deadlock, thread \"Thread[Worker-2,5,main]\" is proceeding but \"org.eclipse.mylyn.internal.tasks.ui.ITaskHighlighter\" may not be fully initialized.\n!STACK 0\norg.osgi.framework.BundleException: State change in progress for bundle \"update@plugins/org.eclipse.mylyn.tasks.ui_2.1.0.v20070927-0900.jar\" by thread \"Worker-0\".\n        at org.eclipse.osgi.framework.internal.core.AbstractBundle.beginStateChange(AbstractBundle.java:1141)\n        at org.eclipse.osgi.framework.internal.core.AbstractBundle.start(AbstractBundle.java:258)\n        at org.eclipse.osgi.framework.util.SecureAction.start(SecureAction.java:400)\n        at org.eclipse.core.runtime.internal.adaptor.EclipseLazyStarter.postFindLocalClass(EclipseLazyStarter.java:111)\n        at org.eclipse.osgi.baseadaptor.loader.ClasspathManager.findLocalClass(ClasspathManager.java:417)\n        at org.eclipse.osgi.internal.baseadaptor.DefaultClassLoader.findLocalClass(DefaultClassLoader.java:189)\n        at org.eclipse.osgi.framework.internal.core.BundleLoader.findLocalClass(BundleLoader.java:340)\n        at org.eclipse.osgi.framework.internal.core.SingleSourcePackage.loadClass(SingleSourcePackage.java:37)\n        at org.eclipse.osgi.framework.internal.core.BundleLoader.findClassInternal(BundleLoader.java:405)\n        at org.eclipse.osgi.framework.internal.core.BundleLoader.findClass(BundleLoader.java:369)\n        at org.eclipse.osgi.framework.internal.core.BundleLoader.findClass(BundleLoader.java:357)\n        at org.eclipse.osgi.internal.baseadaptor.DefaultClassLoader.loadClass(DefaultClassLoader.java:83)\n...\n-------------------------------------------\n\nDetailed exception stack trace can be found in the attached workspace log file.\nAlso the configuration snapshot is attached.\n\nI saw the same error(s) in the Eclipse Europa 3.3 release under both Linux (Fedora 6) and Windows XP OSes.",
    "This is a duplicate of bug 188524 and should have no bad behavior.  The message in the log should be a warning and not an error (yellow icon instead of red).  If either of those statements is not true please let us know.\n\n*** This bug has been marked as a duplicate of bug 188524 ***"
  ],
  "commentCreationDates": [
    "2007-10-11T11:23:45+02:00",
    "2007-10-12T00:39:44+02:00"
  ],
  "traces": [
    {
      "exceptionType": "org.osgi.framework.BundleException",
      "message": "State change in progress for bundle \"update@plugins/org.eclipse.mylyn.tasks.ui_2.1.0.v20070927-0900.jar\" by thread \"Worker-0\".",
      "elements": [
        {
          "method": "org.eclipse.osgi.framework.internal.core.AbstractBundle.beginStateChange",
          "source": "AbstractBundle.java:1141"
        },
        {
          "method": "org.eclipse.osgi.framework.internal.core.AbstractBundle.start",
          "source": "AbstractBundle.java:258"
        },
        {
          "method": "org.eclipse.osgi.framework.util.SecureAction.start",
          "source": "SecureAction.java:400"
        },
        {
          "method": "org.eclipse.core.runtime.internal.adaptor.EclipseLazyStarter.postFindLocalClass",
          "source": "EclipseLazyStarter.java:111"
        },
        {
          "method": "org.eclipse.osgi.baseadaptor.loader.ClasspathManager.findLocalClass",
          "source": "ClasspathManager.java:417"
        },
        {
          "method": "org.eclipse.osgi.internal.baseadaptor.DefaultClassLoader.findLocalClass",
          "source": "DefaultClassLoader.java:189"
        },
        {
          "method": "org.eclipse.osgi.framework.internal.core.BundleLoader.findLocalClass",
          "source": "BundleLoader.java:340"
        },
        {
          "method": "org.eclipse.osgi.framework.internal.core.SingleSourcePackage.loadClass",
          "source": "SingleSourcePackage.java:37"
        },
        {
          "method": "org.eclipse.osgi.framework.internal.core.BundleLoader.findClassInternal",
          "source": "BundleLoader.java:405"
        },
        {
          "method": "org.eclipse.osgi.framework.internal.core.BundleLoader.findClass",
          "source": "BundleLoader.java:369"
        },
        {
          "method": "org.eclipse.osgi.framework.internal.core.BundleLoader.findClass",
          "source": "BundleLoader.java:357"
        },
        {
          "method": "org.eclipse.osgi.internal.baseadaptor.DefaultClassLoader.loadClass",
          "source": "DefaultClassLoader.java:83"
        }
      ],
      "number": 0,
      "commentIndex": 0,
      "bugId": "206014",
      "duplicateId": "188524",
      "date": "2007-10-11T11:23:45+02:00",
      "product": "Mylyn",
      "component": "UI",
      "severity": "normal"
    }
  ],
  "groupId": "188524",
  "bugId": "206014",
  "duplicateId": "188524",
  "date": "2007-10-11T11:23:45+02:00",
  "product": "Mylyn",
  "component": "UI",
  "severity": "normal"
}