{
  "comments": [
    "20020618\n\nFound the following exception in the log. I can remember that I tried to \nsuspend a thread but I didn\u0027t get the stack expanded in the UI. But I was able\nto click on resume.\n\n\n!ENTRY org.eclipse.jdt.debug 4 100 Jun 19, 2002 12:24:48.15\n!MESSAGE com.sun.jdi.IncompatibleThreadStateException: Thread was not suspended\noccurred retrieving stack frames.\n!STACK 0\ncom.sun.jdi.IncompatibleThreadStateException: Thread was not suspended\n        at org.eclipse.jdi.internal.ThreadReferenceImpl.frames(ThreadReferenceIm\npl.java:180)\n        at org.eclipse.jdi.internal.ThreadReferenceImpl.frames(ThreadReferenceIm\npl.java:159)\n        at org.eclipse.jdt.internal.debug.core.model.JDIThread.getUnderlyingFram\nes(JDIThread.java:483)\n        at org.eclipse.jdt.internal.debug.core.model.JDIThread.createAllStackFra\nmes(JDIThread.java:460)\n        at org.eclipse.jdt.internal.debug.core.model.JDIThread.computeStackFrame\ns(JDIThread.java:352)\n        at org.eclipse.jdt.internal.debug.core.model.JDIThread.computeStackFrame\ns(JDIThread.java:432)\n        at org.eclipse.jdt.internal.debug.core.model.JDIThread.getStackFrames(JD\nIThread.java:336)\n        at org.eclipse.debug.internal.ui.views.launch.LaunchViewEventHandler.doH\nandleSuspendThreadEvent(LaunchViewEventHandler.java:210)\n        at org.eclipse.debug.internal.ui.views.launch.LaunchViewEventHandler.doH\nandleSuspendEvent(LaunchViewEventHandler.java:187)\n        at org.eclipse.debug.internal.ui.views.launch.LaunchViewEventHandler.doH\nandleDebugEvents(LaunchViewEventHandler.java:104)\n        at org.eclipse.debug.internal.ui.views.AbstractDebugEventHandler$1.run(A\nbstractDebugEventHandler.java:49)\n        at org.eclipse.swt.widgets.RunnableLock.run(RunnableLock.java:29)\n        at org.eclipse.swt.widgets.Synchronizer.runAsyncMessages(Synchronizer.ja\nva:93)\n        at org.eclipse.swt.widgets.Display.runAsyncMessages(Display.java:1504)\n        at org.eclipse.swt.widgets.Display.readAndDispatch(Display.java:1292)\n        at org.eclipse.ui.internal.Workbench.runEventLoop(Workbench.java:1177)\n        at org.eclipse.ui.internal.Workbench.run(Workbench.java:1160)\n        at org.eclipse.core.internal.boot.InternalBootLoader.run(InternalBootLoa\nder.java:775)\n        at org.eclipse.core.boot.BootLoader.run(BootLoader.java:462)\n        at java.lang.reflect.Method.invoke(Native Method)\n        at org.eclipse.core.launcher.Main.basicRun(Main.java:248)\n        at org.eclipse.core.launcher.Main.run(Main.java:698)\n        at org.eclipse.core.launcher.Main.main(Main.java:534)",
    "Dirk, which VM?\nCould be dup of bug 17081.",
    "Target VM is JDK 1.4.1 beta",
    "\n\n*** This bug has been marked as a duplicate of 17081 ***"
  ],
  "commentCreationDates": [
    "2002-06-19T15:25:11+02:00",
    "2002-06-19T15:45:29+02:00",
    "2002-06-19T15:53:32+02:00",
    "2002-06-19T16:44:18+02:00"
  ],
  "traces": [
    {
      "exceptionType": "com.sun.jdi.IncompatibleThreadStateException",
      "message": "Thread was not suspended",
      "elements": [
        {
          "method": "org.eclipse.jdi.internal.ThreadReferenceImpl.frames",
          "source": "ThreadReferenceIm pl.java:180"
        },
        {
          "method": "org.eclipse.jdi.internal.ThreadReferenceImpl.frames",
          "source": "ThreadReferenceIm pl.java:159"
        },
        {
          "method": "org.eclipse.jdt.internal.debug.core.model.JDIThread.getUnderlyingFrames",
          "source": "JDIThread.java:483"
        },
        {
          "method": "org.eclipse.jdt.internal.debug.core.model.JDIThread.createAllStackFrames",
          "source": "JDIThread.java:460"
        },
        {
          "method": "org.eclipse.jdt.internal.debug.core.model.JDIThread.computeStackFrames",
          "source": "JDIThread.java:352"
        },
        {
          "method": "org.eclipse.jdt.internal.debug.core.model.JDIThread.computeStackFrames",
          "source": "JDIThread.java:432"
        },
        {
          "method": "org.eclipse.jdt.internal.debug.core.model.JDIThread.getStackFrames",
          "source": "JD IThread.java:336"
        },
        {
          "method": "org.eclipse.debug.internal.ui.views.launch.LaunchViewEventHandler.doHandleSuspendThreadEvent",
          "source": "LaunchViewEventHandler.java:210"
        },
        {
          "method": "org.eclipse.debug.internal.ui.views.launch.LaunchViewEventHandler.doHandleSuspendEvent",
          "source": "LaunchViewEventHandler.java:187"
        },
        {
          "method": "org.eclipse.debug.internal.ui.views.launch.LaunchViewEventHandler.doHandleDebugEvents",
          "source": "LaunchViewEventHandler.java:104"
        },
        {
          "method": "org.eclipse.debug.internal.ui.views.AbstractDebugEventHandler$1.run",
          "source": "A bstractDebugEventHandler.java:49"
        },
        {
          "method": "org.eclipse.swt.widgets.RunnableLock.run",
          "source": "RunnableLock.java:29"
        },
        {
          "method": "org.eclipse.swt.widgets.Synchronizer.runAsyncMessages",
          "source": "Synchronizer.ja va:93"
        },
        {
          "method": "org.eclipse.swt.widgets.Display.runAsyncMessages",
          "source": "Display.java:1504"
        },
        {
          "method": "org.eclipse.swt.widgets.Display.readAndDispatch",
          "source": "Display.java:1292"
        },
        {
          "method": "org.eclipse.ui.internal.Workbench.runEventLoop",
          "source": "Workbench.java:1177"
        },
        {
          "method": "org.eclipse.ui.internal.Workbench.run",
          "source": "Workbench.java:1160"
        },
        {
          "method": "org.eclipse.core.internal.boot.InternalBootLoader.run",
          "source": "InternalBootLoa der.java:775"
        },
        {
          "method": "org.eclipse.core.boot.BootLoader.run",
          "source": "BootLoader.java:462"
        },
        {
          "method": "java.lang.reflect.Method.invoke",
          "source": "Native Method"
        },
        {
          "method": "org.eclipse.core.launcher.Main.basicRun",
          "source": "Main.java:248"
        },
        {
          "method": "org.eclipse.core.launcher.Main.run",
          "source": "Main.java:698"
        },
        {
          "method": "org.eclipse.core.launcher.Main.main",
          "source": "Main.java:534"
        }
      ],
      "number": 0,
      "commentIndex": 0,
      "bugId": "20639",
      "duplicateId": "17081",
      "date": "2002-06-19T15:25:11+02:00",
      "product": "JDT",
      "component": "Debug",
      "severity": "normal"
    }
  ],
  "groupId": "17081",
  "bugId": "20639",
  "duplicateId": "17081",
  "date": "2002-06-19T15:25:11+02:00",
  "product": "JDT",
  "component": "Debug",
  "severity": "normal"
}