{
  "comments": [
    "Error when creating UI usage Report. I thought it been reported before, but duplicate search don\u0027t find anything by this stack trace.\n\n-- Error Log --\nDate: Mon Oct 15 13:49:19 EDT 2007\nMessage: Mylyn monitor log rollover failed\n\nSeverity: Error\nPlugin ID: org.eclipse.mylyn\nStack Trace:\njava.io.IOException: The system cannot find the path specified\n\tat java.io.WinNTFileSystem.createFileExclusively(Native Method)\n\tat java.io.File.createNewFile(File.java:883)\n\tat org.eclipse.mylyn.internal.monitor.usage.MonitorFileRolloverJob.run(MonitorFileRolloverJob.java:144)\n\tat org.eclipse.core.internal.jobs.Worker.run(Worker.java:55)",
    "It would be helpful if you could try to search for duplicates using at least one or two of the most obvious search terms, since we haven\u0027t yet been to put time towards improving duplicate detection. \n\n*** This bug has been marked as a duplicate of bug 195889 ***",
    "Sorry, it somehow didn\u0027t cross my mind at that time."
  ],
  "commentCreationDates": [
    "2007-10-15T19:59:34+02:00",
    "2007-10-17T05:29:47+02:00",
    "2007-10-17T17:34:09+02:00"
  ],
  "traces": [
    {
      "exceptionType": "java.io.IOException",
      "message": "The system cannot find the path specified",
      "elements": [
        {
          "method": "java.io.WinNTFileSystem.createFileExclusively",
          "source": "Native Method"
        },
        {
          "method": "java.io.File.createNewFile",
          "source": "File.java:883"
        },
        {
          "method": "org.eclipse.mylyn.internal.monitor.usage.MonitorFileRolloverJob.run",
          "source": "MonitorFileRolloverJob.java:144"
        },
        {
          "method": "org.eclipse.core.internal.jobs.Worker.run",
          "source": "Worker.java:55"
        }
      ],
      "number": 0,
      "commentIndex": 0,
      "bugId": "206360",
      "duplicateId": "195889",
      "date": "2007-10-15T19:59:34+02:00",
      "product": "Mylyn",
      "component": "Monitor",
      "severity": "normal"
    }
  ],
  "groupId": "211526",
  "bugId": "206360",
  "duplicateId": "195889",
  "date": "2007-10-15T19:59:34+02:00",
  "product": "Mylyn",
  "component": "Monitor",
  "severity": "normal"
}