{
  "comments": [
    "I have reproduced this with Eclipse 3.2.2 and 3.3.1\nConfiguration:\nUbuntu Linux 7.04 with all patches. Sun JVM 1.5.0.1\nAMD Athlon X2, 2GB RAM\n(also jrockit-R27.3.1-jre1.5.0_11) See conversation in #eclipse at http://echelog.matzon.dk/logs/browse/eclipse/1191369005 between \u003cjseghers_\u003e and others for context.\n\nUsing Windows XP Pro with RealVNC to communicate with Linux box. Followed instructions at http://ubuntuforums.org/showthread.php?t\u003d45565 to install x11vnc and autocutsel to get clipboard sharing to work.\n\n1) Open a VNC session to the Linux box\n\n2) With an empty workspace, Eclipse will run. Add an existing CDT project, and open a file.\n\n3) Let Linux system idle for a period of time. I don\u0027t believe any interaction with the Windows system is needed during this time, other than have the VNC connection open.  I also don\u0027t know if even the VNC connection is necessary.\n\n4) return to the Linux session and click in the Project Explorer or the Navigator.  An OutOfMemory error like the one below will be generated.\n\n5) Exit Eclipse and attempt to load the same workspace.  Sometimes it will load, more often it will fail to load giving similar exceptions.\n\n6) reboot Linux and load same workspace.  This will act as steps 1-4 above.\n\nThe delay needed for step 4 can be anything from a few minutes to a few hours, but seems to grow shorter the longer the situation persists. Immediately after reinstalling Linux I was able to work with the system for a couple of days before running into the problem again.\n\nAfter removing autocutsel and x11vnc from the session autorun, I no longer experience this problem, but I also have lost the capability of cut/paste across VNC.\n\n\n\n!ENTRY org.eclipse.ui.navigator 4 0 2007-10-10 14:08:17.419\n!MESSAGE Requested array size exceeds VM limit\n!STACK 0\njava.lang.OutOfMemoryError: Requested array size exceeds VM limit\n\n!ENTRY org.eclipse.ui 4 0 2007-10-10 14:08:17.493\n!MESSAGE Unhandled event loop exception\n!STACK 0\norg.eclipse.swt.SWTException: Failed to execute runnable (java.lang.OutOfMemoryError: Requested array size exceeds VM limit)\n\tat org.eclipse.swt.SWT.error(SWT.java:3563)\n\tat org.eclipse.swt.SWT.error(SWT.java:3481)\n\tat org.eclipse.swt.widgets.Synchronizer.runAsyncMessages(Synchronizer.java:126)\n\tat org.eclipse.swt.widgets.Display.runAsyncMessages(Display.java:3296)\n\tat org.eclipse.swt.widgets.Display.readAndDispatch(Display.java:2974)\n\tat org.eclipse.ui.internal.Workbench.runEventLoop(Workbench.java:2389)\n\tat org.eclipse.ui.internal.Workbench.runUI(Workbench.java:2353)\n\tat org.eclipse.ui.internal.Workbench.access$4(Workbench.java:2219)\n\tat org.eclipse.ui.internal.Workbench$4.run(Workbench.java:466)\n\tat org.eclipse.core.databinding.observable.Realm.runWithDefault(Realm.java:289)\n\tat org.eclipse.ui.internal.Workbench.createAndRunWorkbench(Workbench.java:461)\n\tat org.eclipse.ui.PlatformUI.createAndRunWorkbench(PlatformUI.java:149)\n\tat org.eclipse.ui.internal.ide.application.IDEApplication.start(IDEApplication.java:106)\n\tat org.eclipse.equinox.internal.app.EclipseAppHandle.run(EclipseAppHandle.java:169)\n\tat org.eclipse.core.runtime.internal.adaptor.EclipseAppLauncher.runApplication(EclipseAppLauncher.java:106)\n\tat org.eclipse.core.runtime.internal.adaptor.EclipseAppLauncher.start(EclipseAppLauncher.java:76)\n\tat org.eclipse.core.runtime.adaptor.EclipseStarter.run(EclipseStarter.java:363)\n\tat org.eclipse.core.runtime.adaptor.EclipseStarter.run(EclipseStarter.java:176)\n\tat sun.reflect.NativeMethodAccessorImpl.invoke0(Native Method)\n\tat sun.reflect.NativeMethodAccessorImpl.invoke(NativeMethodAccessorImpl.java:39)\n\tat sun.reflect.DelegatingMethodAccessorImpl.invoke(DelegatingMethodAccessorImpl.java:25)\n\tat java.lang.reflect.Method.invoke(Method.java:585)\n\tat org.eclipse.equinox.launcher.Main.invokeFramework(Main.java:508)\n\tat org.eclipse.equinox.launcher.Main.basicRun(Main.java:447)\n\tat org.eclipse.equinox.launcher.Main.run(Main.java:1173)\nCaused by: java.lang.OutOfMemoryError: Requested array size exceeds VM limit",
    "Sounds similar to bug 205678.\nCould you attach the .log file from the \u003cworkspace\u003e/.metadata directory? Thanks.",
    "Created an attachment (id\u003d80574)\n.metadata/.log file\n\nI concur that this looks like the same as but 205678.  I\u0027d searched for autocutsel, but not x11vnc.\n",
    "Anyway, I don\u0027t think CDT can do something about it. Moving to Platform/SWT.",
    "\n\n*** This bug has been marked as a duplicate of bug 205678 ***",
    "(In reply to comment #2)\n\u003e I concur that this looks like the same as but 205678.  I\u0027d searched for\n\u003e autocutsel, but not x11vnc.\n\nI misinterpreted \"I concur\" as \"I object\". Sorry."
  ],
  "commentCreationDates": [
    "2007-10-17T02:16:40+02:00",
    "2007-10-17T12:00:02+02:00",
    "2007-10-17T17:42:17+02:00",
    "2007-10-18T16:58:43+02:00",
    "2007-10-18T20:22:02+02:00",
    "2007-10-19T09:57:58+02:00"
  ],
  "traces": [
    {
      "exceptionType": "java.lang.OutOfMemoryError",
      "message": "Requested array size exceeds VM limit)",
      "elements": [
        {
          "method": "org.eclipse.swt.SWT.error",
          "source": "SWT.java:3563"
        },
        {
          "method": "org.eclipse.swt.SWT.error",
          "source": "SWT.java:3481"
        },
        {
          "method": "org.eclipse.swt.widgets.Synchronizer.runAsyncMessages",
          "source": "Synchronizer.java:126"
        },
        {
          "method": "org.eclipse.swt.widgets.Display.runAsyncMessages",
          "source": "Display.java:3296"
        },
        {
          "method": "org.eclipse.swt.widgets.Display.readAndDispatch",
          "source": "Display.java:2974"
        },
        {
          "method": "org.eclipse.ui.internal.Workbench.runEventLoop",
          "source": "Workbench.java:2389"
        },
        {
          "method": "org.eclipse.ui.internal.Workbench.runUI",
          "source": "Workbench.java:2353"
        },
        {
          "method": "org.eclipse.ui.internal.Workbench.access$4",
          "source": "Workbench.java:2219"
        },
        {
          "method": "org.eclipse.ui.internal.Workbench$4.run",
          "source": "Workbench.java:466"
        },
        {
          "method": "org.eclipse.core.databinding.observable.Realm.runWithDefault",
          "source": "Realm.java:289"
        },
        {
          "method": "org.eclipse.ui.internal.Workbench.createAndRunWorkbench",
          "source": "Workbench.java:461"
        },
        {
          "method": "org.eclipse.ui.PlatformUI.createAndRunWorkbench",
          "source": "PlatformUI.java:149"
        },
        {
          "method": "org.eclipse.ui.internal.ide.application.IDEApplication.start",
          "source": "IDEApplication.java:106"
        },
        {
          "method": "org.eclipse.equinox.internal.app.EclipseAppHandle.run",
          "source": "EclipseAppHandle.java:169"
        },
        {
          "method": "org.eclipse.core.runtime.internal.adaptor.EclipseAppLauncher.runApplication",
          "source": "EclipseAppLauncher.java:106"
        },
        {
          "method": "org.eclipse.core.runtime.internal.adaptor.EclipseAppLauncher.start",
          "source": "EclipseAppLauncher.java:76"
        },
        {
          "method": "org.eclipse.core.runtime.adaptor.EclipseStarter.run",
          "source": "EclipseStarter.java:363"
        },
        {
          "method": "org.eclipse.core.runtime.adaptor.EclipseStarter.run",
          "source": "EclipseStarter.java:176"
        },
        {
          "method": "sun.reflect.NativeMethodAccessorImpl.invoke0",
          "source": "Native Method"
        },
        {
          "method": "sun.reflect.NativeMethodAccessorImpl.invoke",
          "source": "NativeMethodAccessorImpl.java:39"
        },
        {
          "method": "sun.reflect.DelegatingMethodAccessorImpl.invoke",
          "source": "DelegatingMethodAccessorImpl.java:25"
        },
        {
          "method": "java.lang.reflect.Method.invoke",
          "source": "Method.java:585"
        },
        {
          "method": "org.eclipse.equinox.launcher.Main.invokeFramework",
          "source": "Main.java:508"
        },
        {
          "method": "org.eclipse.equinox.launcher.Main.basicRun",
          "source": "Main.java:447"
        },
        {
          "method": "org.eclipse.equinox.launcher.Main.run",
          "source": "Main.java:1173"
        }
      ],
      "number": 0,
      "commentIndex": 0,
      "bugId": "206552",
      "duplicateId": "205678",
      "date": "2007-10-17T02:16:40+02:00",
      "product": "Platform",
      "component": "SWT",
      "severity": "normal"
    }
  ],
  "groupId": "205678",
  "bugId": "206552",
  "duplicateId": "205678",
  "date": "2007-10-17T02:16:40+02:00",
  "product": "Platform",
  "component": "SWT",
  "severity": "normal"
}