{
  "comments": [
    "Created an attachment (id\u003d80620)\nSourcefile that causes crash...\n\nBuild ID: I20070621-1340\n\nSteps To Reproduce:\n1. Open or paste the java source from http://fisheye5.cenqua.com/browse/~raw,r\u003d1.5/xom/src/nu/xom/UnicodeUtil.java \n2. Pop up error message \u0027An internal error occurred during \u0027Requesting java AST from selection\u0027\n3. ..followed by an \u0027Internal Error occurred while showing an internal error\u0027\n\n\nMore information:\nUsing standard Eclipse Europa on Linux x86 (Fedora 7).",
    "This sounds like a duplicate of https://bugs.eclipse.org/bugs/show_bug.cgi?id\u003d154047 However this time the problem occurs on Linux rather than Mac OS X.",
    "The \u0027crash\u0027 is in fact a StackOverflowError:\n\njava.lang.StackOverflowError\n        at org.eclipse.jdt.internal.compiler.parser.Scanner.getNextToken(Scanner.java:1660)\n        at org.eclipse.jdt.core.dom.ASTConverter.retrieveEndOfElementTypeNamePosition(ASTConverter.java:4053)\n        at org.eclipse.jdt.core.dom.ASTConverter.convertType(ASTConverter.java:3086)\n        at org.eclipse.jdt.core.dom.ASTConverter.convert(ASTConverter.java:1172)\n        at org.eclipse.jdt.core.dom.ASTConverter.convert(ASTConverter.java:1529)\n        at org.eclipse.jdt.core.dom.ASTConverter.convert(ASTConverter.java:1999)\n        at org.eclipse.jdt.core.dom.ASTConverter.convert(ASTConverter.java:1620)\n        at org.eclipse.jdt.core.dom.ASTConverter.convert(ASTConverter.java:2478)\n        at org.eclipse.jdt.core.dom.ASTConverter.convert(ASTConverter.java:1130)\n        at org.eclipse.jdt.core.dom.ASTConverter.convert(ASTConverter.java:2382)\n        at org.eclipse.jdt.core.dom.ASTConverter.convert(ASTConverter.java:1784)\n        at org.eclipse.jdt.core.dom.ASTConverter.convert(ASTConverter.java:2406)\n        at org.eclipse.jdt.core.dom.ASTConverter.convert(ASTConverter.java:1789)\n        at org.eclipse.jdt.core.dom.ASTConverter.convert(ASTConverter.java:2406)\n        at org.eclipse.jdt.core.dom.ASTConverter.convert(ASTConverter.java:1789)\n        at org.eclipse.jdt.core.dom.ASTConverter.convert(ASTConverter.java:2406)\n        at org.eclipse.jdt.core.dom.ASTConverter.convert(ASTConverter.java:1789)\n        at org.eclipse.jdt.core.dom.ASTConverter.convert(ASTConverter.java:2406)\n        at org.eclipse.jdt.core.dom.ASTConverter.convert(ASTConverter.java:1789)\n        at org.eclipse.jdt.core.dom.ASTConverter.convert(ASTConverter.java:2406)\n        at org.eclipse.jdt.core.dom.ASTConverter.convert(ASTConverter.java:1789)\n        at org.eclipse.jdt.core.dom.ASTConverter.convert(ASTConverter.java:2406)\n        at org.eclipse.jdt.core.dom.ASTConverter.convert(ASTConverter.java:1789)\n        at org.eclipse.jdt.core.dom.ASTConverter.convert(ASTConverter.java:2406)\n        at org.eclipse.jdt.core.dom.ASTConverter.convert(ASTConverter.java:1789)\n        at org.eclipse.jdt.core.dom.ASTConverter.convert(ASTConverter.java:2406)\n        at org.eclipse.jdt.core.dom.ASTConverter.convert(ASTConverter.java:1789)\n        at org.eclipse.jdt.core.dom.ASTConverter.convert(ASTConverter.java:2406)\n        at org.eclipse.jdt.core.dom.ASTConverter.convert(ASTConverter.java:1789)\n        at org.eclipse.jdt.core.dom.ASTConverter.convert(ASTConverter.java:2406)\n        at org.eclipse.jdt.core.dom.ASTConverter.convert(ASTConverter.java:1789)\n        at org.eclipse.jdt.core.dom.ASTConverter.convert(ASTConverter.java:2406)",
    "This is not a dup of bug 154047 (since the StackOverflow happens in another part of the code). However the workaround described in this bug will work (ie. increasing the stack size will allow this test case to pass).\n\nTo fix this, the ASTConverter would need to be rewritten to not use recursion. That is not an obvious change.",
    "What VM are you running on?\nWhat is the stack size ?",
    "(In reply to comment #4)\n\u003e What VM are you running on?\njava version \"1.6.0_01\"\nJava(TM) SE Runtime Environment (build 1.6.0_01-b06)\nJava HotSpot(TM) Client VM (build 1.6.0_01-b06, mixed mode, sharing)\n\n\u003e What is the stack size ?\neclipse.ini: (standard 3.3.0 unchanged...)\n-showsplash\norg.eclipse.platform\n--launcher.XXMaxPermSize\n128M\n-vmargs\n-Xms40m\n-Xmx256m\n-Dosgi.bundlefile.limit\u003d100\n\nAdding e.g an -Xss2m parameter does indeed \u0027solve\u0027 this issue. However, there should really be a more friendly way of reporting errors with (and configuring) memory usage within Eclipse...\n"
  ],
  "commentCreationDates": [
    "2007-10-18T00:45:23+02:00",
    "2007-10-18T12:16:33+02:00",
    "2007-10-18T12:52:33+02:00",
    "2007-10-18T12:54:54+02:00",
    "2007-10-20T04:51:41+02:00",
    "2007-10-20T05:21:48+02:00"
  ],
  "traces": [
    {
      "exceptionType": "java.lang.StackOverflowError",
      "elements": [
        {
          "method": "org.eclipse.jdt.internal.compiler.parser.Scanner.getNextToken",
          "source": "Scanner.java:1660"
        },
        {
          "method": "org.eclipse.jdt.core.dom.ASTConverter.retrieveEndOfElementTypeNamePosition",
          "source": "ASTConverter.java:4053"
        },
        {
          "method": "org.eclipse.jdt.core.dom.ASTConverter.convertType",
          "source": "ASTConverter.java:3086"
        },
        {
          "method": "org.eclipse.jdt.core.dom.ASTConverter.convert",
          "source": "ASTConverter.java:1172"
        },
        {
          "method": "org.eclipse.jdt.core.dom.ASTConverter.convert",
          "source": "ASTConverter.java:1529"
        },
        {
          "method": "org.eclipse.jdt.core.dom.ASTConverter.convert",
          "source": "ASTConverter.java:1999"
        },
        {
          "method": "org.eclipse.jdt.core.dom.ASTConverter.convert",
          "source": "ASTConverter.java:1620"
        },
        {
          "method": "org.eclipse.jdt.core.dom.ASTConverter.convert",
          "source": "ASTConverter.java:2478"
        },
        {
          "method": "org.eclipse.jdt.core.dom.ASTConverter.convert",
          "source": "ASTConverter.java:1130"
        },
        {
          "method": "org.eclipse.jdt.core.dom.ASTConverter.convert",
          "source": "ASTConverter.java:2382"
        },
        {
          "method": "org.eclipse.jdt.core.dom.ASTConverter.convert",
          "source": "ASTConverter.java:1784"
        },
        {
          "method": "org.eclipse.jdt.core.dom.ASTConverter.convert",
          "source": "ASTConverter.java:2406"
        },
        {
          "method": "org.eclipse.jdt.core.dom.ASTConverter.convert",
          "source": "ASTConverter.java:1789"
        },
        {
          "method": "org.eclipse.jdt.core.dom.ASTConverter.convert",
          "source": "ASTConverter.java:2406"
        },
        {
          "method": "org.eclipse.jdt.core.dom.ASTConverter.convert",
          "source": "ASTConverter.java:1789"
        },
        {
          "method": "org.eclipse.jdt.core.dom.ASTConverter.convert",
          "source": "ASTConverter.java:2406"
        },
        {
          "method": "org.eclipse.jdt.core.dom.ASTConverter.convert",
          "source": "ASTConverter.java:1789"
        },
        {
          "method": "org.eclipse.jdt.core.dom.ASTConverter.convert",
          "source": "ASTConverter.java:2406"
        },
        {
          "method": "org.eclipse.jdt.core.dom.ASTConverter.convert",
          "source": "ASTConverter.java:1789"
        },
        {
          "method": "org.eclipse.jdt.core.dom.ASTConverter.convert",
          "source": "ASTConverter.java:2406"
        },
        {
          "method": "org.eclipse.jdt.core.dom.ASTConverter.convert",
          "source": "ASTConverter.java:1789"
        },
        {
          "method": "org.eclipse.jdt.core.dom.ASTConverter.convert",
          "source": "ASTConverter.java:2406"
        },
        {
          "method": "org.eclipse.jdt.core.dom.ASTConverter.convert",
          "source": "ASTConverter.java:1789"
        },
        {
          "method": "org.eclipse.jdt.core.dom.ASTConverter.convert",
          "source": "ASTConverter.java:2406"
        },
        {
          "method": "org.eclipse.jdt.core.dom.ASTConverter.convert",
          "source": "ASTConverter.java:1789"
        },
        {
          "method": "org.eclipse.jdt.core.dom.ASTConverter.convert",
          "source": "ASTConverter.java:2406"
        },
        {
          "method": "org.eclipse.jdt.core.dom.ASTConverter.convert",
          "source": "ASTConverter.java:1789"
        },
        {
          "method": "org.eclipse.jdt.core.dom.ASTConverter.convert",
          "source": "ASTConverter.java:2406"
        },
        {
          "method": "org.eclipse.jdt.core.dom.ASTConverter.convert",
          "source": "ASTConverter.java:1789"
        },
        {
          "method": "org.eclipse.jdt.core.dom.ASTConverter.convert",
          "source": "ASTConverter.java:2406"
        },
        {
          "method": "org.eclipse.jdt.core.dom.ASTConverter.convert",
          "source": "ASTConverter.java:1789"
        },
        {
          "method": "org.eclipse.jdt.core.dom.ASTConverter.convert",
          "source": "ASTConverter.java:2406"
        }
      ],
      "number": 0,
      "commentIndex": 2,
      "bugId": "206697",
      "date": "2007-10-18T12:52:33+02:00",
      "product": "JDT",
      "component": "Core",
      "severity": "normal"
    }
  ],
  "groupId": "206697",
  "bugId": "206697",
  "date": "2007-10-18T00:45:23+02:00",
  "product": "JDT",
  "component": "Core",
  "severity": "normal"
}