{
  "comments": [
    "This bug is reproducable on Linux-GTK only (not on Windows) and only with the \nexact steps given. The issue is trivial since the NPE is only logged, and only under very specific conditions, user experience is otherwise not affected.\n\n1. Launch Eclipse\n2. Window \u003e Show View \u003e Other \u003e PDE Runtime \u003e PDE Error Log\n3. Window \u003e Customize Perspective \u003e Submenus:Show View\n   --\u003e Add \"Terminal\" as a Show View Shortcut\n4. Window \u003e Show View \u003e Terminal\n5. Close the Terminal by pressing the View\u0027s X button\n6. Press the \"Add fastview\" buttom on the bottom left of the Eclipse screen\n7. Choose the Terminal\n8. Click into any other location in the screen, e.g. caption of the error log\n\n--\u003e Observe following NPE reported as \"Unhandled event loop exception\".\nThis might be an Eclipse problem, because it looks like \"focusLost()\" is called on the Terminal\u0027s focus handler before it receives \"focusGained()\". The bug might actually be that when a view is restored as FastView from a View Shortcut, focusGained() is never called.\n\njava.lang.NullPointerException\n\tat\norg.eclipse.ui.internal.contexts.ContextService.deactivateContext(ContextService.java:139)\n\tat\norg.eclipse.tm.internal.terminal.emulator.VT100TerminalControl$TerminalFocusListener.focusLost(VT100TerminalControl.java:639)\n\tat\norg.eclipse.swt.widgets.TypedListener.handleEvent(TypedListener.java:136)\n\tat org.eclipse.swt.widgets.EventTable.sendEvent(EventTable.java:66)\n\tat org.eclipse.swt.widgets.Widget.sendEvent(Widget.java:1101)\n\tat org.eclipse.swt.widgets.Widget.sendEvent(Widget.java:1125)\n\tat org.eclipse.swt.widgets.Widget.sendEvent(Widget.java:1106)\n\t...\n\n\n-----------Enter bugs above this line-----------\ninstallation : eclipse-SDK-3.3.1-linux-gtk, Terminal M20071018-0500\njava.runtime : Sun 1.6.0_01\nos.name:     : Linux RHEL4\n------------------------------------------------"
  ],
  "commentCreationDates": [
    "2007-10-18T16:36:28+02:00"
  ],
  "traces": [
    {
      "exceptionType": "java.lang.NullPointerException",
      "elements": [
        {
          "method": "org.eclipse.ui.internal.contexts.ContextService.deactivateContext",
          "source": "ContextService.java:139"
        },
        {
          "method": "org.eclipse.tm.internal.terminal.emulator.VT100TerminalControl$TerminalFocusListener.focusLost",
          "source": "VT100TerminalControl.java:639"
        },
        {
          "method": "org.eclipse.swt.widgets.TypedListener.handleEvent",
          "source": "TypedListener.java:136"
        },
        {
          "method": "org.eclipse.swt.widgets.EventTable.sendEvent",
          "source": "EventTable.java:66"
        },
        {
          "method": "org.eclipse.swt.widgets.Widget.sendEvent",
          "source": "Widget.java:1101"
        },
        {
          "method": "org.eclipse.swt.widgets.Widget.sendEvent",
          "source": "Widget.java:1125"
        },
        {
          "method": "org.eclipse.swt.widgets.Widget.sendEvent",
          "source": "Widget.java:1106"
        }
      ],
      "number": 0,
      "commentIndex": 0,
      "bugId": "206764",
      "date": "2007-10-18T16:36:28+02:00",
      "product": "Target Management",
      "component": "Terminal",
      "severity": "trivial"
    }
  ],
  "groupId": "206764",
  "bugId": "206764",
  "date": "2007-10-18T16:36:28+02:00",
  "product": "Target Management",
  "component": "Terminal",
  "severity": "trivial"
}