{
  "comments": [
    "Debian (Sid) Eclipse F3 doesn\u0027t start, both GTK and Motif version.\nI installed in /opt/eclipse and ran ldconfig.\nPrevious version F2 and M3 I tried only GTK) work fine.\n\nNow I get splash screen, next something like window appeared for a moment\nand I got next dialog window \"Problems during startup. Check the \u0027.log\u0027 \nfile...\"\nIn .log file I found:\n!SESSION \n----------------------------------------------------------------------\n!ENTRY org.eclipse.core.launcher 4 0 cze 19, 2002 22:42:33.819\n!MESSAGE Exception launching the Eclipse Platform:\n!STACK\njava.lang.ExceptionInInitializerError\n        at \norg.eclipse.core.internal.plugins.RegistryLoader.processManifestFile(RegistryLoader.java:89)\n        at \norg.eclipse.core.internal.plugins.RegistryLoader.processPluginPathFile(RegistryLoader.java:136)\n        at \norg.eclipse.core.internal.plugins.RegistryLoader.processPluginPathEntry(RegistryLoader.java:127)\n        at \norg.eclipse.core.internal.plugins.RegistryLoader.processManifestFiles(RegistryLoader.java:104)\n        at \norg.eclipse.core.internal.plugins.RegistryLoader.parseRegistry(RegistryLoader.java:63)\n        at \norg.eclipse.core.internal.plugins.RegistryLoader.parseRegistry(RegistryLoader.java:71)\n        at \norg.eclipse.core.internal.runtime.InternalPlatform.parsePlugins(InternalPlatform.java:716)\n        at \norg.eclipse.core.internal.runtime.InternalPlatform.loadRegistry(InternalPlatform.java:665)\n\n\n        at \norg.eclipse.core.internal.runtime.InternalPlatform.loaderStartup(InternalPlatform.java:561)\n        at sun.reflect.NativeMethodAccessorImpl.invoke0(Native Method)\n        at \nsun.reflect.NativeMethodAccessorImpl.invoke(NativeMethodAccessorImpl.java:39)\n        at \nsun.reflect.DelegatingMethodAccessorImpl.invoke(DelegatingMethodAccessorImpl.java:25)\n        at java.lang.reflect.Method.invoke(Method.java:324)\n        at \norg.eclipse.core.internal.boot.InternalBootLoader.startup(InternalBootLoader.java:873)\n        at \norg.eclipse.core.internal.boot.InternalBootLoader.run(InternalBootLoader.java:732)\n        at org.eclipse.core.boot.BootLoader.run(BootLoader.java:462)\n        at sun.reflect.NativeMethodAccessorImpl.invoke0(Native Method)\n        at \nsun.reflect.NativeMethodAccessorImpl.invoke(NativeMethodAccessorImpl.java:39)\n        at \nsun.reflect.DelegatingMethodAccessorImpl.invoke(DelegatingMethodAccessorImpl.java:25)\n        at java.lang.reflect.Method.invoke(Method.java:324)\n        at org.eclipse.core.launcher.Main.basicRun(Main.java:248)\nat org.eclipse.core.launcher.Main.run(Main.java:697)\n        at org.eclipse.core.launcher.Main.main(Main.java:530)\nCaused by: java.lang.ClassCastException: \norg.apache.xerces.parsers.StandardParserConfiguration\n        at org.apache.xerces.parsers.SAXParser.\u003cinit\u003e(SAXParser.java:95)\n        at \norg.eclipse.core.internal.plugins.PluginParser.initializeParser(PluginParser.java:78)\n        at \norg.eclipse.core.internal.plugins.PluginParser.\u003cclinit\u003e(PluginParser.java:43)\n        ... 23 more\n\nThe same message with motif version.\nJDK 1.4 from Sun.\nNothig were changed except Eclipse version from F2 to F3 (by removing \nprevious).\n\nI tried run it with -ws gtk option and -Djava.library.path\u003dpath do .so files\n(I found this on eclipse.tools newsgroup).",
    "A new implementation of xerces was shipped with F3.  Is it possible you have an \nincompatible version of xerces somewhere on your classpath?  There have also \nbeen reports of Sun J2SE 1.4 including an incompatible version of xerces.  What \nVM are you using?",
    "I forgot. I use KDE 2.0.\n",
    "The same I got with Gnome and Window Maker.\nAnd the same with F2 when I tried to return to it...\nSo probably my last Debian upgrade spoilt some libararies.\n",
    "Please followup again if you find out what caused this.  The answer might be \nhelpful to others in this situation...",
    "From bug #19252:\n\n------- Additional Comments From Timothy Folks 2002-06-17 04:01 -------\n\nThe problem is \nthat, contrary to what Sun\u0027s JAXP pluggability FAQ tells you,\nmust place both xercesImpl.jar \nand xmlParserAPIs.jar into the jre\\lib\\endorsed\ndirectory. This is not an Eclipse bug, but a \nSun documentation bug.\n\n--\nI have forgotten about copying xerces libraries into jre/ext \ndirectory.\nWhen I removed its from /jre/ext directory Eclipse runs without problems.\n\n*** This bug has been marked as a duplicate of 19252 ***"
  ],
  "commentCreationDates": [
    "2002-06-19T22:55:02+02:00",
    "2002-06-19T23:39:46+02:00",
    "2002-06-20T09:09:14+02:00",
    "2002-06-21T09:47:29+02:00",
    "2002-06-25T20:31:45+02:00",
    "2002-06-26T11:52:16+02:00"
  ],
  "traces": [
    {
      "exceptionType": "java.lang.ExceptionInInitializerError",
      "elements": [
        {
          "method": "org.eclipse.core.internal.plugins.RegistryLoader.processManifestFile",
          "source": "RegistryLoader.java:89"
        },
        {
          "method": "org.eclipse.core.internal.plugins.RegistryLoader.processPluginPathFile",
          "source": "RegistryLoader.java:136"
        },
        {
          "method": "org.eclipse.core.internal.plugins.RegistryLoader.processPluginPathEntry",
          "source": "RegistryLoader.java:127"
        },
        {
          "method": "org.eclipse.core.internal.plugins.RegistryLoader.processManifestFiles",
          "source": "RegistryLoader.java:104"
        },
        {
          "method": "org.eclipse.core.internal.plugins.RegistryLoader.parseRegistry",
          "source": "RegistryLoader.java:63"
        },
        {
          "method": "org.eclipse.core.internal.plugins.RegistryLoader.parseRegistry",
          "source": "RegistryLoader.java:71"
        },
        {
          "method": "org.eclipse.core.internal.runtime.InternalPlatform.parsePlugins",
          "source": "InternalPlatform.java:716"
        },
        {
          "method": "org.eclipse.core.internal.runtime.InternalPlatform.loadRegistry",
          "source": "InternalPlatform.java:665"
        },
        {
          "method": "org.eclipse.core.internal.runtime.InternalPlatform.loaderStartup",
          "source": "InternalPlatform.java:561"
        },
        {
          "method": "sun.reflect.NativeMethodAccessorImpl.invoke0",
          "source": "Native Method"
        },
        {
          "method": "sun.reflect.NativeMethodAccessorImpl.invoke",
          "source": "NativeMethodAccessorImpl.java:39"
        },
        {
          "method": "sun.reflect.DelegatingMethodAccessorImpl.invoke",
          "source": "DelegatingMethodAccessorImpl.java:25"
        },
        {
          "method": "java.lang.reflect.Method.invoke",
          "source": "Method.java:324"
        },
        {
          "method": "org.eclipse.core.internal.boot.InternalBootLoader.startup",
          "source": "InternalBootLoader.java:873"
        },
        {
          "method": "org.eclipse.core.internal.boot.InternalBootLoader.run",
          "source": "InternalBootLoader.java:732"
        },
        {
          "method": "org.eclipse.core.boot.BootLoader.run",
          "source": "BootLoader.java:462"
        },
        {
          "method": "sun.reflect.NativeMethodAccessorImpl.invoke0",
          "source": "Native Method"
        },
        {
          "method": "sun.reflect.NativeMethodAccessorImpl.invoke",
          "source": "NativeMethodAccessorImpl.java:39"
        },
        {
          "method": "sun.reflect.DelegatingMethodAccessorImpl.invoke",
          "source": "DelegatingMethodAccessorImpl.java:25"
        },
        {
          "method": "java.lang.reflect.Method.invoke",
          "source": "Method.java:324"
        },
        {
          "method": "org.eclipse.core.launcher.Main.basicRun",
          "source": "Main.java:248"
        },
        {
          "method": "org.eclipse.core.launcher.Main.run",
          "source": "Main.java:697"
        },
        {
          "method": "org.eclipse.core.launcher.Main.main",
          "source": "Main.java:530"
        }
      ],
      "causedBy": {
        "exceptionType": "java.lang.ClassCastException",
        "message": "org.apache.xerces.parsers.StandardParserConfiguration",
        "elements": [
          {
            "method": "org.apache.xerces.parsers.SAXParser.\u003cinit\u003e",
            "source": "SAXParser.java:95"
          },
          {
            "method": "org.eclipse.core.internal.plugins.PluginParser.initializeParser",
            "source": "PluginParser.java:78"
          },
          {
            "method": "org.eclipse.core.internal.plugins.PluginParser.\u003cclinit\u003e",
            "source": "PluginParser.java:43"
          }
        ],
        "number": 0,
        "commentIndex": 0
      },
      "number": 0,
      "commentIndex": 0,
      "bugId": "20687",
      "duplicateId": "19252",
      "date": "2002-06-19T22:55:02+02:00",
      "product": "Platform",
      "component": "Resources",
      "severity": "major"
    }
  ],
  "groupId": "19252",
  "bugId": "20687",
  "duplicateId": "19252",
  "date": "2002-06-19T22:55:02+02:00",
  "product": "Platform",
  "component": "Resources",
  "severity": "major"
}