{
  "comments": [
    "I20071029-0010\n\npublic class D {\n\tpublic static void main(String[] args) {\n\t\tnew D();\n\t}\n}\n\n- run D as Java Application\n- search for references to D\n- disable Preferences \u003e General \u003e Search \u003e Reuse editors to show matches\n- doubleclick the launch configuration match in the Search view\n\n\u003d\u003e error dialog and 2 log entries:\n\n!ENTRY org.eclipse.search 4 2 2007-10-29 11:11:47.484\n!MESSAGE Problems occurred when invoking code from plug-in: \"org.eclipse.search\".\n!STACK 1\norg.eclipse.ui.PartInitException: Could not get an editor input for the given element\n        at org.eclipse.jdt.internal.ui.javaeditor.EditorUtility.throwPartInitException(EditorUtility.java:335)\n        at org.eclipse.jdt.internal.ui.javaeditor.EditorUtility.openInEditor(EditorUtility.java:189)\n        at org.eclipse.jdt.internal.ui.search.JavaSearchEditorOpener.showWithoutReuse(JavaSearchEditorOpener.java:72)\n        at org.eclipse.jdt.internal.ui.search.JavaSearchEditorOpener.openElement(JavaSearchEditorOpener.java:54)\n        at org.eclipse.jdt.internal.ui.search.JavaSearchEditorOpener.openMatch(JavaSearchEditorOpener.java:64)\n        at org.eclipse.jdt.internal.ui.search.JavaSearchResultPage.showMatch(JavaSearchResultPage.java:183)\n        at org.eclipse.search.ui.text.AbstractTextSearchViewPage$7.run(AbstractTextSearchViewPage.java:854)\n        at org.eclipse.core.runtime.SafeRunner.run(SafeRunner.java:37)\n        at org.eclipse.search.ui.text.AbstractTextSearchViewPage.showMatch(AbstractTextSearchViewPage.java:857)\n        at org.eclipse.search.ui.text.AbstractTextSearchViewPage.showCurrentMatch(AbstractTextSearchViewPage.java:922)\n        at org.eclipse.search.ui.text.AbstractTextSearchViewPage.gotoNextMatch(AbstractTextSearchViewPage.java:887)\n        at org.eclipse.search.ui.text.AbstractTextSearchViewPage.handleOpen(AbstractTextSearchViewPage.java:1357)\n        at org.eclipse.jdt.internal.ui.search.JavaSearchResultPage.handleOpen(JavaSearchResultPage.java:549)\n        at org.eclipse.search.ui.text.AbstractTextSearchViewPage$5.open(AbstractTextSearchViewPage.java:676)\n        at org.eclipse.jface.viewers.StructuredViewer$2.run(StructuredViewer.java:820)\n        at org.eclipse.core.runtime.SafeRunner.run(SafeRunner.java:37)\n        at org.eclipse.core.runtime.Platform.run(Platform.java:857)\n        at org.eclipse.ui.internal.JFaceUtil$1.run(JFaceUtil.java:46)\n        at org.eclipse.jface.util.SafeRunnable.run(SafeRunnable.java:199)\n        at org.eclipse.jface.viewers.StructuredViewer.fireOpen(StructuredViewer.java:818)\n        at org.eclipse.jface.viewers.StructuredViewer.handleOpen(StructuredViewer.java:1079)\n        at org.eclipse.jface.viewers.StructuredViewer$6.handleOpen(StructuredViewer.java:1183)\n        at org.eclipse.jface.util.OpenStrategy.fireOpenEvent(OpenStrategy.java:263)\n        at org.eclipse.jface.util.OpenStrategy.access$2(OpenStrategy.java:257)\n        at org.eclipse.jface.util.OpenStrategy$1.handleEvent(OpenStrategy.java:297)\n        at org.eclipse.swt.widgets.EventTable.sendEvent(EventTable.java:66)\n        at org.eclipse.swt.widgets.Widget.sendEvent(Widget.java:947)\n        at org.eclipse.swt.widgets.Display.runDeferredEvents(Display.java:3744)\n        at org.eclipse.swt.widgets.Display.readAndDispatch(Display.java:3355)\n        at org.eclipse.ui.internal.Workbench.runEventLoop(Workbench.java:2395)\n        at org.eclipse.ui.internal.Workbench.runUI(Workbench.java:2359)\n        at org.eclipse.ui.internal.Workbench.access$4(Workbench.java:2225)\n        at org.eclipse.ui.internal.Workbench$4.run(Workbench.java:468)\n        at org.eclipse.core.databinding.observable.Realm.runWithDefault(Realm.java:288)\n        at org.eclipse.ui.internal.Workbench.createAndRunWorkbench(Workbench.java:463)\n        at org.eclipse.ui.PlatformUI.createAndRunWorkbench(PlatformUI.java:149)\n        at org.eclipse.ui.internal.ide.application.IDEApplication.start(IDEApplication.java:106)\n        at org.eclipse.equinox.internal.app.EclipseAppHandle.run(EclipseAppHandle.java:193)\n        at org.eclipse.core.runtime.internal.adaptor.EclipseAppLauncher.runApplication(EclipseAppLauncher.java:106)\n        at org.eclipse.core.runtime.internal.adaptor.EclipseAppLauncher.start(EclipseAppLauncher.java:76)\n        at org.eclipse.core.runtime.adaptor.EclipseStarter.run(EclipseStarter.java:362)\n        at org.eclipse.core.runtime.adaptor.EclipseStarter.run(EclipseStarter.java:175)\n        at sun.reflect.NativeMethodAccessorImpl.invoke0(Native Method)\n        at sun.reflect.NativeMethodAccessorImpl.invoke(NativeMethodAccessorImpl.java:39)\n        at sun.reflect.DelegatingMethodAccessorImpl.invoke(DelegatingMethodAccessorImpl.java:25)\n        at java.lang.reflect.Method.invoke(Method.java:597)\n        at org.eclipse.equinox.launcher.Main.invokeFramework(Main.java:515)\n        at org.eclipse.equinox.launcher.Main.basicRun(Main.java:455)\n        at org.eclipse.equinox.launcher.Main.run(Main.java:1193)\n        at org.eclipse.equinox.launcher.Main.main(Main.java:1169)\n!SUBENTRY 1 org.eclipse.jdt.ui 4 0 2007-10-29 11:11:47.484\n!MESSAGE Could not get an editor input for the given element\n!SUBENTRY 1 org.eclipse.jdt.ui 4 0 2007-10-29 11:11:47.484\n!MESSAGE Could not get an editor input for the given element\n\nThe problem is that org.eclipse.jdt.internal.ui.javaeditor.EditorUtility.openInEditor(Object, boolean) throws a PIE when no editor could be found:\n * @throws PartInitException if the editor could not be opened or\n * the input element is not valid\n\nCallers cannot distinguish between the two conditions leading to a PIE.\n\n- Quick workaround: add a check for\nEditorUtility.getEditorInput(element) \u003d\u003d null in\nJavaSearchEditorOpener.showWithoutReuse(Object) and don\u0027t try to open if true\n\n- Long-term solution:\nThrow another exception in EditorUtility.openInEditor(..) or at least set a specific status code",
    "fixed \u003e 20071029",
    "Does not work for me in HEAD nor in M3:\n\norg.eclipse.ui.PartInitException: Could not get an editor input for the given element\n\tat org.eclipse.jdt.internal.ui.javaeditor.EditorUtility.throwPartInitException(EditorUtility.java:338)\n\tat org.eclipse.jdt.internal.ui.javaeditor.EditorUtility.throwPartInitException(EditorUtility.java:342)\n\tat org.eclipse.jdt.internal.ui.javaeditor.EditorUtility.openInEditor(EditorUtility.java:192)\n\tat org.eclipse.jdt.internal.ui.search.JavaSearchEditorOpener.showWithoutReuse(JavaSearchEditorOpener.java:61)\n\tat org.eclipse.jdt.internal.ui.search.JavaSearchEditorOpener.openElement(JavaSearchEditorOpener.java:42)\n\tat org.eclipse.jdt.internal.ui.search.JavaSearchEditorOpener.openMatch(JavaSearchEditorOpener.java:52)\n\tat org.eclipse.jdt.internal.ui.search.JavaSearchResultPage.showMatch(JavaSearchResultPage.java:181)\n\tat org.eclipse.search.ui.text.AbstractTextSearchViewPage$7.run(AbstractTextSearchViewPage.java:869)\n\tat org.eclipse.core.runtime.SafeRunner.run(SafeRunner.java:37)\n\tat org.eclipse.search.ui.text.AbstractTextSearchViewPage.showMatch(AbstractTextSearchViewPage.java:872)\n\tat org.eclipse.search.ui.text.AbstractTextSearchViewPage.showCurrentMatch(AbstractTextSearchViewPage.java:937)\n\tat org.eclipse.search.ui.text.AbstractTextSearchViewPage.gotoNextMatch(AbstractTextSearchViewPage.java:902)\n\tat org.eclipse.search.ui.text.AbstractTextSearchViewPage.handleOpen(AbstractTextSearchViewPage.java:1367)\n\tat org.eclipse.jdt.internal.ui.search.JavaSearchResultPage.handleOpen(JavaSearchResultPage.java:542)\n\tat org.eclipse.search.ui.text.AbstractTextSearchViewPage$5.open(AbstractTextSearchViewPage.java:691)\n\tat org.eclipse.jface.viewers.StructuredViewer$2.run(StructuredViewer.java:820)\n\tat org.eclipse.core.runtime.SafeRunner.run(SafeRunner.java:37)\n\tat org.eclipse.core.runtime.Platform.run(Platform.java:857)\n\tat org.eclipse.ui.internal.JFaceUtil$1.run(JFaceUtil.java:46)\n\tat org.eclipse.jface.util.SafeRunnable.run(SafeRunnable.java:199)\n\tat org.eclipse.jface.viewers.StructuredViewer.fireOpen(StructuredViewer.java:818)\n\tat org.eclipse.jface.viewers.StructuredViewer.handleOpen(StructuredViewer.java:1079)\n\tat org.eclipse.jface.viewers.StructuredViewer$6.handleOpen(StructuredViewer.java:1183)\n\tat org.eclipse.jface.util.OpenStrategy.fireOpenEvent(OpenStrategy.java:263)\n\tat org.eclipse.jface.util.OpenStrategy.access$2(OpenStrategy.java:257)\n\tat org.eclipse.jface.util.OpenStrategy$1.handleEvent(OpenStrategy.java:297)\n\tat org.eclipse.swt.widgets.EventTable.sendEvent(EventTable.java:66)\n\tat org.eclipse.swt.widgets.Widget.sendEvent(Widget.java:947)\n\tat org.eclipse.swt.widgets.Display.runDeferredEvents(Display.java:3744)\n\tat org.eclipse.swt.widgets.Display.readAndDispatch(Display.java:3355)\n\tat org.eclipse.ui.internal.Workbench.runEventLoop(Workbench.java:2395)\n\tat org.eclipse.ui.internal.Workbench.runUI(Workbench.java:2359)\n\tat org.eclipse.ui.internal.Workbench.access$4(Workbench.java:2225)\n\tat org.eclipse.ui.internal.Workbench$4.run(Workbench.java:468)\n\tat org.eclipse.core.databinding.observable.Realm.runWithDefault(Realm.java:288)\n\tat org.eclipse.ui.internal.Workbench.createAndRunWorkbench(Workbench.java:463)\n\tat org.eclipse.ui.PlatformUI.createAndRunWorkbench(PlatformUI.java:149)\n\tat org.eclipse.ui.internal.ide.application.IDEApplication.start(IDEApplication.java:106)\n\tat org.eclipse.equinox.internal.app.EclipseAppHandle.run(EclipseAppHandle.java:193)\n\tat org.eclipse.core.runtime.internal.adaptor.EclipseAppLauncher.runApplication(EclipseAppLauncher.java:106)\n\tat org.eclipse.core.runtime.internal.adaptor.EclipseAppLauncher.start(EclipseAppLauncher.java:76)\n\tat org.eclipse.core.runtime.adaptor.EclipseStarter.run(EclipseStarter.java:362)\n\tat org.eclipse.core.runtime.adaptor.EclipseStarter.run(EclipseStarter.java:175)\n\tat sun.reflect.NativeMethodAccessorImpl.invoke0(Native Method)\n\tat sun.reflect.NativeMethodAccessorImpl.invoke(NativeMethodAccessorImpl.java:39)\n\tat sun.reflect.DelegatingMethodAccessorImpl.invoke(DelegatingMethodAccessorImpl.java:25)\n\tat java.lang.reflect.Method.invoke(Method.java:597)\n\tat org.eclipse.equinox.launcher.Main.invokeFramework(Main.java:515)\n\tat org.eclipse.equinox.launcher.Main.basicRun(Main.java:455)\n\tat org.eclipse.equinox.launcher.Main.run(Main.java:1193)\n\tat org.eclipse.equinox.launcher.Main.main(Main.java:1169)",
    "now it is fixed! \u003e 20071112"
  ],
  "commentCreationDates": [
    "2007-10-29T11:50:25+01:00",
    "2007-10-29T13:10:24+01:00",
    "2007-11-12T11:25:34+01:00",
    "2007-11-12T12:15:02+01:00"
  ],
  "traces": [
    {
      "exceptionType": "org.eclipse.ui.PartInitException",
      "message": "Could not get an editor input for the given element",
      "elements": [
        {
          "method": "org.eclipse.jdt.internal.ui.javaeditor.EditorUtility.throwPartInitException",
          "source": "EditorUtility.java:335"
        },
        {
          "method": "org.eclipse.jdt.internal.ui.javaeditor.EditorUtility.openInEditor",
          "source": "EditorUtility.java:189"
        },
        {
          "method": "org.eclipse.jdt.internal.ui.search.JavaSearchEditorOpener.showWithoutReuse",
          "source": "JavaSearchEditorOpener.java:72"
        },
        {
          "method": "org.eclipse.jdt.internal.ui.search.JavaSearchEditorOpener.openElement",
          "source": "JavaSearchEditorOpener.java:54"
        },
        {
          "method": "org.eclipse.jdt.internal.ui.search.JavaSearchEditorOpener.openMatch",
          "source": "JavaSearchEditorOpener.java:64"
        },
        {
          "method": "org.eclipse.jdt.internal.ui.search.JavaSearchResultPage.showMatch",
          "source": "JavaSearchResultPage.java:183"
        },
        {
          "method": "org.eclipse.search.ui.text.AbstractTextSearchViewPage$7.run",
          "source": "AbstractTextSearchViewPage.java:854"
        },
        {
          "method": "org.eclipse.core.runtime.SafeRunner.run",
          "source": "SafeRunner.java:37"
        },
        {
          "method": "org.eclipse.search.ui.text.AbstractTextSearchViewPage.showMatch",
          "source": "AbstractTextSearchViewPage.java:857"
        },
        {
          "method": "org.eclipse.search.ui.text.AbstractTextSearchViewPage.showCurrentMatch",
          "source": "AbstractTextSearchViewPage.java:922"
        },
        {
          "method": "org.eclipse.search.ui.text.AbstractTextSearchViewPage.gotoNextMatch",
          "source": "AbstractTextSearchViewPage.java:887"
        },
        {
          "method": "org.eclipse.search.ui.text.AbstractTextSearchViewPage.handleOpen",
          "source": "AbstractTextSearchViewPage.java:1357"
        },
        {
          "method": "org.eclipse.jdt.internal.ui.search.JavaSearchResultPage.handleOpen",
          "source": "JavaSearchResultPage.java:549"
        },
        {
          "method": "org.eclipse.search.ui.text.AbstractTextSearchViewPage$5.open",
          "source": "AbstractTextSearchViewPage.java:676"
        },
        {
          "method": "org.eclipse.jface.viewers.StructuredViewer$2.run",
          "source": "StructuredViewer.java:820"
        },
        {
          "method": "org.eclipse.core.runtime.SafeRunner.run",
          "source": "SafeRunner.java:37"
        },
        {
          "method": "org.eclipse.core.runtime.Platform.run",
          "source": "Platform.java:857"
        },
        {
          "method": "org.eclipse.ui.internal.JFaceUtil$1.run",
          "source": "JFaceUtil.java:46"
        },
        {
          "method": "org.eclipse.jface.util.SafeRunnable.run",
          "source": "SafeRunnable.java:199"
        },
        {
          "method": "org.eclipse.jface.viewers.StructuredViewer.fireOpen",
          "source": "StructuredViewer.java:818"
        },
        {
          "method": "org.eclipse.jface.viewers.StructuredViewer.handleOpen",
          "source": "StructuredViewer.java:1079"
        },
        {
          "method": "org.eclipse.jface.viewers.StructuredViewer$6.handleOpen",
          "source": "StructuredViewer.java:1183"
        },
        {
          "method": "org.eclipse.jface.util.OpenStrategy.fireOpenEvent",
          "source": "OpenStrategy.java:263"
        },
        {
          "method": "org.eclipse.jface.util.OpenStrategy.access$2",
          "source": "OpenStrategy.java:257"
        },
        {
          "method": "org.eclipse.jface.util.OpenStrategy$1.handleEvent",
          "source": "OpenStrategy.java:297"
        },
        {
          "method": "org.eclipse.swt.widgets.EventTable.sendEvent",
          "source": "EventTable.java:66"
        },
        {
          "method": "org.eclipse.swt.widgets.Widget.sendEvent",
          "source": "Widget.java:947"
        },
        {
          "method": "org.eclipse.swt.widgets.Display.runDeferredEvents",
          "source": "Display.java:3744"
        },
        {
          "method": "org.eclipse.swt.widgets.Display.readAndDispatch",
          "source": "Display.java:3355"
        },
        {
          "method": "org.eclipse.ui.internal.Workbench.runEventLoop",
          "source": "Workbench.java:2395"
        },
        {
          "method": "org.eclipse.ui.internal.Workbench.runUI",
          "source": "Workbench.java:2359"
        },
        {
          "method": "org.eclipse.ui.internal.Workbench.access$4",
          "source": "Workbench.java:2225"
        },
        {
          "method": "org.eclipse.ui.internal.Workbench$4.run",
          "source": "Workbench.java:468"
        },
        {
          "method": "org.eclipse.core.databinding.observable.Realm.runWithDefault",
          "source": "Realm.java:288"
        },
        {
          "method": "org.eclipse.ui.internal.Workbench.createAndRunWorkbench",
          "source": "Workbench.java:463"
        },
        {
          "method": "org.eclipse.ui.PlatformUI.createAndRunWorkbench",
          "source": "PlatformUI.java:149"
        },
        {
          "method": "org.eclipse.ui.internal.ide.application.IDEApplication.start",
          "source": "IDEApplication.java:106"
        },
        {
          "method": "org.eclipse.equinox.internal.app.EclipseAppHandle.run",
          "source": "EclipseAppHandle.java:193"
        },
        {
          "method": "org.eclipse.core.runtime.internal.adaptor.EclipseAppLauncher.runApplication",
          "source": "EclipseAppLauncher.java:106"
        },
        {
          "method": "org.eclipse.core.runtime.internal.adaptor.EclipseAppLauncher.start",
          "source": "EclipseAppLauncher.java:76"
        },
        {
          "method": "org.eclipse.core.runtime.adaptor.EclipseStarter.run",
          "source": "EclipseStarter.java:362"
        },
        {
          "method": "org.eclipse.core.runtime.adaptor.EclipseStarter.run",
          "source": "EclipseStarter.java:175"
        },
        {
          "method": "sun.reflect.NativeMethodAccessorImpl.invoke0",
          "source": "Native Method"
        },
        {
          "method": "sun.reflect.NativeMethodAccessorImpl.invoke",
          "source": "NativeMethodAccessorImpl.java:39"
        },
        {
          "method": "sun.reflect.DelegatingMethodAccessorImpl.invoke",
          "source": "DelegatingMethodAccessorImpl.java:25"
        },
        {
          "method": "java.lang.reflect.Method.invoke",
          "source": "Method.java:597"
        },
        {
          "method": "org.eclipse.equinox.launcher.Main.invokeFramework",
          "source": "Main.java:515"
        },
        {
          "method": "org.eclipse.equinox.launcher.Main.basicRun",
          "source": "Main.java:455"
        },
        {
          "method": "org.eclipse.equinox.launcher.Main.run",
          "source": "Main.java:1193"
        },
        {
          "method": "org.eclipse.equinox.launcher.Main.main",
          "source": "Main.java:1169"
        }
      ],
      "number": 0,
      "commentIndex": 0,
      "bugId": "207752",
      "date": "2007-10-29T11:50:25+01:00",
      "product": "JDT",
      "component": "UI",
      "severity": "normal"
    },
    {
      "exceptionType": "org.eclipse.ui.PartInitException",
      "message": "Could not get an editor input for the given element",
      "elements": [
        {
          "method": "org.eclipse.jdt.internal.ui.javaeditor.EditorUtility.throwPartInitException",
          "source": "EditorUtility.java:338"
        },
        {
          "method": "org.eclipse.jdt.internal.ui.javaeditor.EditorUtility.throwPartInitException",
          "source": "EditorUtility.java:342"
        },
        {
          "method": "org.eclipse.jdt.internal.ui.javaeditor.EditorUtility.openInEditor",
          "source": "EditorUtility.java:192"
        },
        {
          "method": "org.eclipse.jdt.internal.ui.search.JavaSearchEditorOpener.showWithoutReuse",
          "source": "JavaSearchEditorOpener.java:61"
        },
        {
          "method": "org.eclipse.jdt.internal.ui.search.JavaSearchEditorOpener.openElement",
          "source": "JavaSearchEditorOpener.java:42"
        },
        {
          "method": "org.eclipse.jdt.internal.ui.search.JavaSearchEditorOpener.openMatch",
          "source": "JavaSearchEditorOpener.java:52"
        },
        {
          "method": "org.eclipse.jdt.internal.ui.search.JavaSearchResultPage.showMatch",
          "source": "JavaSearchResultPage.java:181"
        },
        {
          "method": "org.eclipse.search.ui.text.AbstractTextSearchViewPage$7.run",
          "source": "AbstractTextSearchViewPage.java:869"
        },
        {
          "method": "org.eclipse.core.runtime.SafeRunner.run",
          "source": "SafeRunner.java:37"
        },
        {
          "method": "org.eclipse.search.ui.text.AbstractTextSearchViewPage.showMatch",
          "source": "AbstractTextSearchViewPage.java:872"
        },
        {
          "method": "org.eclipse.search.ui.text.AbstractTextSearchViewPage.showCurrentMatch",
          "source": "AbstractTextSearchViewPage.java:937"
        },
        {
          "method": "org.eclipse.search.ui.text.AbstractTextSearchViewPage.gotoNextMatch",
          "source": "AbstractTextSearchViewPage.java:902"
        },
        {
          "method": "org.eclipse.search.ui.text.AbstractTextSearchViewPage.handleOpen",
          "source": "AbstractTextSearchViewPage.java:1367"
        },
        {
          "method": "org.eclipse.jdt.internal.ui.search.JavaSearchResultPage.handleOpen",
          "source": "JavaSearchResultPage.java:542"
        },
        {
          "method": "org.eclipse.search.ui.text.AbstractTextSearchViewPage$5.open",
          "source": "AbstractTextSearchViewPage.java:691"
        },
        {
          "method": "org.eclipse.jface.viewers.StructuredViewer$2.run",
          "source": "StructuredViewer.java:820"
        },
        {
          "method": "org.eclipse.core.runtime.SafeRunner.run",
          "source": "SafeRunner.java:37"
        },
        {
          "method": "org.eclipse.core.runtime.Platform.run",
          "source": "Platform.java:857"
        },
        {
          "method": "org.eclipse.ui.internal.JFaceUtil$1.run",
          "source": "JFaceUtil.java:46"
        },
        {
          "method": "org.eclipse.jface.util.SafeRunnable.run",
          "source": "SafeRunnable.java:199"
        },
        {
          "method": "org.eclipse.jface.viewers.StructuredViewer.fireOpen",
          "source": "StructuredViewer.java:818"
        },
        {
          "method": "org.eclipse.jface.viewers.StructuredViewer.handleOpen",
          "source": "StructuredViewer.java:1079"
        },
        {
          "method": "org.eclipse.jface.viewers.StructuredViewer$6.handleOpen",
          "source": "StructuredViewer.java:1183"
        },
        {
          "method": "org.eclipse.jface.util.OpenStrategy.fireOpenEvent",
          "source": "OpenStrategy.java:263"
        },
        {
          "method": "org.eclipse.jface.util.OpenStrategy.access$2",
          "source": "OpenStrategy.java:257"
        },
        {
          "method": "org.eclipse.jface.util.OpenStrategy$1.handleEvent",
          "source": "OpenStrategy.java:297"
        },
        {
          "method": "org.eclipse.swt.widgets.EventTable.sendEvent",
          "source": "EventTable.java:66"
        },
        {
          "method": "org.eclipse.swt.widgets.Widget.sendEvent",
          "source": "Widget.java:947"
        },
        {
          "method": "org.eclipse.swt.widgets.Display.runDeferredEvents",
          "source": "Display.java:3744"
        },
        {
          "method": "org.eclipse.swt.widgets.Display.readAndDispatch",
          "source": "Display.java:3355"
        },
        {
          "method": "org.eclipse.ui.internal.Workbench.runEventLoop",
          "source": "Workbench.java:2395"
        },
        {
          "method": "org.eclipse.ui.internal.Workbench.runUI",
          "source": "Workbench.java:2359"
        },
        {
          "method": "org.eclipse.ui.internal.Workbench.access$4",
          "source": "Workbench.java:2225"
        },
        {
          "method": "org.eclipse.ui.internal.Workbench$4.run",
          "source": "Workbench.java:468"
        },
        {
          "method": "org.eclipse.core.databinding.observable.Realm.runWithDefault",
          "source": "Realm.java:288"
        },
        {
          "method": "org.eclipse.ui.internal.Workbench.createAndRunWorkbench",
          "source": "Workbench.java:463"
        },
        {
          "method": "org.eclipse.ui.PlatformUI.createAndRunWorkbench",
          "source": "PlatformUI.java:149"
        },
        {
          "method": "org.eclipse.ui.internal.ide.application.IDEApplication.start",
          "source": "IDEApplication.java:106"
        },
        {
          "method": "org.eclipse.equinox.internal.app.EclipseAppHandle.run",
          "source": "EclipseAppHandle.java:193"
        },
        {
          "method": "org.eclipse.core.runtime.internal.adaptor.EclipseAppLauncher.runApplication",
          "source": "EclipseAppLauncher.java:106"
        },
        {
          "method": "org.eclipse.core.runtime.internal.adaptor.EclipseAppLauncher.start",
          "source": "EclipseAppLauncher.java:76"
        },
        {
          "method": "org.eclipse.core.runtime.adaptor.EclipseStarter.run",
          "source": "EclipseStarter.java:362"
        },
        {
          "method": "org.eclipse.core.runtime.adaptor.EclipseStarter.run",
          "source": "EclipseStarter.java:175"
        },
        {
          "method": "sun.reflect.NativeMethodAccessorImpl.invoke0",
          "source": "Native Method"
        },
        {
          "method": "sun.reflect.NativeMethodAccessorImpl.invoke",
          "source": "NativeMethodAccessorImpl.java:39"
        },
        {
          "method": "sun.reflect.DelegatingMethodAccessorImpl.invoke",
          "source": "DelegatingMethodAccessorImpl.java:25"
        },
        {
          "method": "java.lang.reflect.Method.invoke",
          "source": "Method.java:597"
        },
        {
          "method": "org.eclipse.equinox.launcher.Main.invokeFramework",
          "source": "Main.java:515"
        },
        {
          "method": "org.eclipse.equinox.launcher.Main.basicRun",
          "source": "Main.java:455"
        },
        {
          "method": "org.eclipse.equinox.launcher.Main.run",
          "source": "Main.java:1193"
        },
        {
          "method": "org.eclipse.equinox.launcher.Main.main",
          "source": "Main.java:1169"
        }
      ],
      "number": 1,
      "commentIndex": 2,
      "bugId": "207752",
      "date": "2007-11-12T11:25:34+01:00",
      "product": "JDT",
      "component": "UI",
      "severity": "normal"
    }
  ],
  "groupId": "207752",
  "bugId": "207752",
  "date": "2007-10-29T11:50:25+01:00",
  "product": "JDT",
  "component": "UI",
  "severity": "normal"
}