{
  "comments": [
    "build I20071030-0010\n\nI had an OSGi launch configuration (from a while ago) that was set up to run with a foundation 1.0 VM. When I try and launch it, I get the following NPE. If I switch the VM to be the default (1.4.2) then all works ok.\n\n!ENTRY org.eclipse.core.jobs 4 2 2007-10-31 13:13:52.572\n!MESSAGE An internal error occurred during: \"Launching ProvAdminUI\".\n!STACK 0\njava.lang.NullPointerException\n        at org.eclipse.jdt.internal.launching.StandardVMDebugger.getJavaVersion(StandardVMDebugger.java:441)\n        at org.eclipse.jdt.internal.launching.StandardVMDebugger.run(StandardVMDebugger.java:176)\n        at org.eclipse.pde.ui.launcher.AbstractPDELaunchConfiguration.launch(AbstractPDELaunchConfiguration.java:94)\n        at org.eclipse.pde.ui.launcher.OSGiLaunchConfigurationDelegate.launch(OSGiLaunchConfigurationDelegate.java:48)\n        at org.eclipse.debug.internal.core.LaunchConfiguration.launch(LaunchConfiguration.java:757)\n        at org.eclipse.debug.internal.core.LaunchConfiguration.launch(LaunchConfiguration.java:607)\n        at org.eclipse.debug.internal.ui.DebugUIPlugin.buildAndLaunch(DebugUIPlugin.java:826)\n        at org.eclipse.debug.internal.ui.DebugUIPlugin$7.run(DebugUIPlugin.java:1029)\n        at org.eclipse.core.internal.jobs.Worker.run(Worker.java:55)",
    "If you defined the JRE a while ago, please try re-creating it from the ee file (delete/add). We added a new JRE type for EE\u0027s and I think the JRE you have is an old one.",
    "Yes. I believe this was the problem."
  ],
  "commentCreationDates": [
    "2007-10-31T18:21:35+01:00",
    "2007-10-31T19:21:16+01:00",
    "2007-11-06T13:26:35+01:00"
  ],
  "traces": [
    {
      "exceptionType": "java.lang.NullPointerException",
      "elements": [
        {
          "method": "org.eclipse.jdt.internal.launching.StandardVMDebugger.getJavaVersion",
          "source": "StandardVMDebugger.java:441"
        },
        {
          "method": "org.eclipse.jdt.internal.launching.StandardVMDebugger.run",
          "source": "StandardVMDebugger.java:176"
        },
        {
          "method": "org.eclipse.pde.ui.launcher.AbstractPDELaunchConfiguration.launch",
          "source": "AbstractPDELaunchConfiguration.java:94"
        },
        {
          "method": "org.eclipse.pde.ui.launcher.OSGiLaunchConfigurationDelegate.launch",
          "source": "OSGiLaunchConfigurationDelegate.java:48"
        },
        {
          "method": "org.eclipse.debug.internal.core.LaunchConfiguration.launch",
          "source": "LaunchConfiguration.java:757"
        },
        {
          "method": "org.eclipse.debug.internal.core.LaunchConfiguration.launch",
          "source": "LaunchConfiguration.java:607"
        },
        {
          "method": "org.eclipse.debug.internal.ui.DebugUIPlugin.buildAndLaunch",
          "source": "DebugUIPlugin.java:826"
        },
        {
          "method": "org.eclipse.debug.internal.ui.DebugUIPlugin$7.run",
          "source": "DebugUIPlugin.java:1029"
        },
        {
          "method": "org.eclipse.core.internal.jobs.Worker.run",
          "source": "Worker.java:55"
        }
      ],
      "number": 0,
      "commentIndex": 0,
      "bugId": "208289",
      "date": "2007-10-31T18:21:35+01:00",
      "product": "JDT",
      "component": "Debug",
      "severity": "normal"
    }
  ],
  "groupId": "208289",
  "bugId": "208289",
  "date": "2007-10-31T18:21:35+01:00",
  "product": "JDT",
  "component": "Debug",
  "severity": "normal"
}