{
  "comments": [
    "Problem: Analysis context menu is not updated after changing the name of an Analysis Configuration in the Analysis dialog box, exception when selecting it (option with the old name) from the context menu\n\nExpected Result: Menu should be updated after changing the Analysis configuration name in the Analysis dialog box\n\nSteps:\n- Created a UML project, created a Class diagram\n- Added two Classes and an Interface to the Class diagram from the Palette\n- Connected these elements using Associations\n- Added Attributes and Operations to Classes\n- Saved all\n- Right-clicked on the model in PE and selected Analysis --\u003e Open Analysis Dialog\n- Created a new Analysis Configuration (called it archdisc01)\n- Ran the Analysis\n- Changed the Class diagram by adding another Class\n- Opened the Analysis Dialog again and this time changed the name of the already created Analysis Configuration to NewAnalysis and clicked on Apply\n- closed the Analysis dialog box\n- Right-clicked on the model again and selected Analysis\n- clicked on the name displayed in the context menu (which is still the old name for the Analysis Configuration)\n\nResult:\n- Analysis does not run and the following exception is generated:\n\nNote1: closing and re-opening the application will update the context menu\nNote2: This problem is a regression\n\nStack trace:\n--------------------------------------------------------------------------------------------------\n\n\n!ENTRY org.eclipse.tptp.platform.analysis.core 4 4 2007-10-25 14:45:32.673\n!MESSAGE Error loading launch configuration\n!STACK 1\norg.eclipse.debug.core.DebugException: Launch configuration archdisc01 at C:\\Documents and Settings\\Administrator\\IBM\\rationalsdp7.0.5\\workspace_new1022\\.metadata\\.plugins\\org.eclipse.debug.core\\.launches\\archdisc01.launch does not exist.\n\tat org.eclipse.debug.internal.core.LaunchManager.createDebugException(Unknown Source)\n\tat org.eclipse.debug.internal.core.LaunchManager.getInfo(Unknown Source)\n\tat org.eclipse.debug.internal.core.LaunchConfiguration.getInfo(Unknown Source)\n\tat org.eclipse.debug.internal.core.LaunchConfigurationWorkingCopy.copyFrom(Unknown Source)\n\tat org.eclipse.debug.internal.core.LaunchConfigurationWorkingCopy.\u003cinit\u003e(Unknown Source)\n\tat org.eclipse.debug.internal.core.LaunchConfiguration.getWorkingCopy(Unknown Source)\n\tat org.eclipse.tptp.platform.analysis.core.ui.internal.actions.MultiAnalysisActionDelegate$2.run(Unknown Source)\n\tat org.eclipse.core.internal.jobs.Worker.run(Unknown Source)\n!SUBENTRY 1 org.eclipse.debug.core 4 5012 2007-10-25 14:45:32.673\n!MESSAGE Launch configuration archdisc01 at C:\\Documents and Settings\\Administrator\\IBM\\rationalsdp7.0.5\\workspace_new1022\\.metadata\\.plugins\\org.eclipse.debug.core\\.launches\\archdisc01.launch does not exist."
  ],
  "commentCreationDates": [
    "2007-11-01T15:14:26+01:00"
  ],
  "traces": [
    {
      "exceptionType": "org.eclipse.debug.core.DebugException",
      "message": "Launch configuration archdisc01 at C:\\Documents and Settings\\Administrator\\IBM\\rationalsdp7.0.5\\workspace_new1022\\.metadata\\.plugins\\org.eclipse.debug.core\\.launches\\archdisc01.launch does not exist.",
      "elements": [
        {
          "method": "org.eclipse.debug.internal.core.LaunchManager.createDebugException",
          "source": "Unknown Source"
        },
        {
          "method": "org.eclipse.debug.internal.core.LaunchManager.getInfo",
          "source": "Unknown Source"
        },
        {
          "method": "org.eclipse.debug.internal.core.LaunchConfiguration.getInfo",
          "source": "Unknown Source"
        },
        {
          "method": "org.eclipse.debug.internal.core.LaunchConfigurationWorkingCopy.copyFrom",
          "source": "Unknown Source"
        },
        {
          "method": "org.eclipse.debug.internal.core.LaunchConfigurationWorkingCopy.\u003cinit\u003e",
          "source": "Unknown Source"
        },
        {
          "method": "org.eclipse.debug.internal.core.LaunchConfiguration.getWorkingCopy",
          "source": "Unknown Source"
        },
        {
          "method": "org.eclipse.tptp.platform.analysis.core.ui.internal.actions.MultiAnalysisActionDelegate$2.run",
          "source": "Unknown Source"
        },
        {
          "method": "org.eclipse.core.internal.jobs.Worker.run",
          "source": "Unknown Source"
        }
      ],
      "number": 0,
      "commentIndex": 0,
      "bugId": "208411",
      "date": "2007-11-01T15:14:26+01:00",
      "product": "TPTP Static Analysis",
      "component": "Platform.Analysis",
      "severity": "normal"
    }
  ],
  "groupId": "208411",
  "bugId": "208411",
  "date": "2007-11-01T15:14:26+01:00",
  "product": "TPTP Static Analysis",
  "component": "Platform.Analysis",
  "severity": "normal"
}