{
  "comments": [
    "OS:AIX5.3\nJava 1.5\nJ2EE server: WAS CE 2.0(Apache Geronimo).\nI have successfully deployed birt.war, but when trying to open test report in browser it gives \"Cant startup the OSGI framework\" message. Log contains following stack trace:\n\norg.eclipse.birt.core.exception.BirtException: Cant startup the OSGI framework\n        at org.eclipse.birt.core.framework.Platform.startup(Platform.java:90)\n        at org.eclipse.birt.report.service.ReportEngineService.setEngineContext(Unknown Source)\n        at org.eclipse.birt.report.service.BirtViewerReportService.setContext(Unknown Source)\n        at org.eclipse.birt.report.servlet.ViewerServlet.__getContext(Unknown Source)\n        at org.eclipse.birt.report.servlet.BirtSoapMessageDispatcherServlet.doGet(Unknown Source)\n        at javax.servlet.http.HttpServlet.service(HttpServlet.java:693)\n        at org.apache.axis.transport.http.AxisServletBase.service(AxisServletBase.java:327)\n        at javax.servlet.http.HttpServlet.service(HttpServlet.java:806)\n        at org.apache.catalina.core.ApplicationFilterChain.internalDoFilter(ApplicationFilterChain.java:290)\n        at org.apache.catalina.core.ApplicationFilterChain.doFilter(ApplicationFilterChain.java:206)\n        at org.eclipse.birt.report.filter.ViewerFilter.doFilter(Unknown Source)\n        at org.apache.catalina.core.ApplicationFilterChain.internalDoFilter(ApplicationFilterChain.java:235)\n        at org.apache.catalina.core.ApplicationFilterChain.doFilter(ApplicationFilterChain.java:206)\n        at org.apache.catalina.core.StandardWrapperValve.invoke(StandardWrapperValve.java:230)\n        at org.apache.catalina.core.StandardContextValve.invoke(StandardContextValve.java:175)\n        at org.apache.geronimo.tomcat.valve.DefaultSubjectValve.invoke(DefaultSubjectValve.java:56)\n        at org.apache.geronimo.tomcat.GeronimoStandardContext$SystemMethodValve.invoke(GeronimoStandardContext.java:351)\n        at org.apache.geronimo.tomcat.valve.GeronimoBeforeAfterValve.invoke(GeronimoBeforeAfterValve.java:47)\n        at org.apache.catalina.core.StandardHostValve.invoke(StandardHostValve.java:128)\n        at org.apache.catalina.valves.ErrorReportValve.invoke(ErrorReportValve.java:104)\n        at org.apache.catalina.core.StandardEngineValve.invoke(StandardEngineValve.java:109)\n        at org.apache.catalina.valves.AccessLogValve.invoke(AccessLogValve.java:563)\n        at org.apache.catalina.connector.CoyoteAdapter.service(CoyoteAdapter.java:261)\n        at org.apache.coyote.http11.Http11Processor.process(Http11Processor.java:844)\n        at org.apache.coyote.http11.Http11Protocol$Http11ConnectionHandler.process(Http11Protocol.java:581)\n        at org.apache.tomcat.util.net.JIoEndpoint$Worker.run(JIoEndpoint.java:447)\n        at java.lang.Thread.run(Thread.java:801)\nCaused by: org.eclipse.birt.core.exception.BirtException: Can not start up OSGI - null\n        at org.eclipse.birt.core.framework.osgi.OSGILauncher.startup(OSGILauncher.java:169)\n        at org.eclipse.birt.core.framework.Platform.startup(Platform.java:78)\n        ... 26 more",
    "Reassign to engine for further research."
  ],
  "commentCreationDates": [
    "2007-11-02T13:35:16+01:00",
    "2007-11-06T03:28:48+01:00"
  ],
  "traces": [
    {
      "exceptionType": "org.eclipse.birt.core.exception.BirtException",
      "message": "Cant startup the OSGI framework",
      "elements": [
        {
          "method": "org.eclipse.birt.core.framework.Platform.startup",
          "source": "Platform.java:90"
        },
        {
          "method": "org.eclipse.birt.report.service.ReportEngineService.setEngineContext",
          "source": "Unknown Source"
        },
        {
          "method": "org.eclipse.birt.report.service.BirtViewerReportService.setContext",
          "source": "Unknown Source"
        },
        {
          "method": "org.eclipse.birt.report.servlet.ViewerServlet.__getContext",
          "source": "Unknown Source"
        },
        {
          "method": "org.eclipse.birt.report.servlet.BirtSoapMessageDispatcherServlet.doGet",
          "source": "Unknown Source"
        },
        {
          "method": "javax.servlet.http.HttpServlet.service",
          "source": "HttpServlet.java:693"
        },
        {
          "method": "org.apache.axis.transport.http.AxisServletBase.service",
          "source": "AxisServletBase.java:327"
        },
        {
          "method": "javax.servlet.http.HttpServlet.service",
          "source": "HttpServlet.java:806"
        },
        {
          "method": "org.apache.catalina.core.ApplicationFilterChain.internalDoFilter",
          "source": "ApplicationFilterChain.java:290"
        },
        {
          "method": "org.apache.catalina.core.ApplicationFilterChain.doFilter",
          "source": "ApplicationFilterChain.java:206"
        },
        {
          "method": "org.eclipse.birt.report.filter.ViewerFilter.doFilter",
          "source": "Unknown Source"
        },
        {
          "method": "org.apache.catalina.core.ApplicationFilterChain.internalDoFilter",
          "source": "ApplicationFilterChain.java:235"
        },
        {
          "method": "org.apache.catalina.core.ApplicationFilterChain.doFilter",
          "source": "ApplicationFilterChain.java:206"
        },
        {
          "method": "org.apache.catalina.core.StandardWrapperValve.invoke",
          "source": "StandardWrapperValve.java:230"
        },
        {
          "method": "org.apache.catalina.core.StandardContextValve.invoke",
          "source": "StandardContextValve.java:175"
        },
        {
          "method": "org.apache.geronimo.tomcat.valve.DefaultSubjectValve.invoke",
          "source": "DefaultSubjectValve.java:56"
        },
        {
          "method": "org.apache.geronimo.tomcat.GeronimoStandardContext$SystemMethodValve.invoke",
          "source": "GeronimoStandardContext.java:351"
        },
        {
          "method": "org.apache.geronimo.tomcat.valve.GeronimoBeforeAfterValve.invoke",
          "source": "GeronimoBeforeAfterValve.java:47"
        },
        {
          "method": "org.apache.catalina.core.StandardHostValve.invoke",
          "source": "StandardHostValve.java:128"
        },
        {
          "method": "org.apache.catalina.valves.ErrorReportValve.invoke",
          "source": "ErrorReportValve.java:104"
        },
        {
          "method": "org.apache.catalina.core.StandardEngineValve.invoke",
          "source": "StandardEngineValve.java:109"
        },
        {
          "method": "org.apache.catalina.valves.AccessLogValve.invoke",
          "source": "AccessLogValve.java:563"
        },
        {
          "method": "org.apache.catalina.connector.CoyoteAdapter.service",
          "source": "CoyoteAdapter.java:261"
        },
        {
          "method": "org.apache.coyote.http11.Http11Processor.process",
          "source": "Http11Processor.java:844"
        },
        {
          "method": "org.apache.coyote.http11.Http11Protocol$Http11ConnectionHandler.process",
          "source": "Http11Protocol.java:581"
        },
        {
          "method": "org.apache.tomcat.util.net.JIoEndpoint$Worker.run",
          "source": "JIoEndpoint.java:447"
        },
        {
          "method": "java.lang.Thread.run",
          "source": "Thread.java:801"
        }
      ],
      "causedBy": {
        "exceptionType": "org.eclipse.birt.core.exception.BirtException",
        "message": "Can not start up OSGI - null",
        "elements": [
          {
            "method": "org.eclipse.birt.core.framework.osgi.OSGILauncher.startup",
            "source": "OSGILauncher.java:169"
          },
          {
            "method": "org.eclipse.birt.core.framework.Platform.startup",
            "source": "Platform.java:78"
          }
        ],
        "number": 0,
        "commentIndex": 0
      },
      "number": 0,
      "commentIndex": 0,
      "bugId": "208552",
      "date": "2007-11-02T13:35:16+01:00",
      "product": "BIRT",
      "component": "Report Engine",
      "severity": "critical"
    }
  ],
  "groupId": "208552",
  "bugId": "208552",
  "date": "2007-11-02T13:35:16+01:00",
  "product": "BIRT",
  "component": "Report Engine",
  "severity": "critical"
}