{
  "comments": [
    "When I generate a report the DC runtime component throws the following exceptions:\n\n\nCaused by: org.eclipse.cosmos.dc.runtime.RetryException: COSMOS Runtime Host not\n initialized\n        at org.eclipse.cosmos.dc.birt.helper.LocalHelper.verifyRuntimeHost(Local\nHelper.java:49)\n        at org.eclipse.cosmos.dc.birt.helper.LocalHelper.getLatestDatasetForSour\nceKeyset(LocalHelper.java:80)\n        at sun.reflect.NativeMethodAccessorImpl.invoke0(Native Method)\n        at sun.reflect.NativeMethodAccessorImpl.invoke(NativeMethodAccessorImpl.\njava:64)\n        at sun.reflect.DelegatingMethodAccessorImpl.invoke(DelegatingMethodAcces\nsorImpl.java:43)\n        at java.lang.reflect.Method.invoke(Method.java:615)\n        at org.mozilla.javascript.MemberBox.invoke(MemberBox.java:174)\n        ... 112 more\n\n\nSteps to reproduce the problem\n\u003d\u003d\u003d\u003d\u003d\u003d\u003d\u003d\u003d\u003d\u003d\u003d\u003d\u003d\u003d\u003d\u003d\u003d\u003d\u003d\u003d\u003d\u003d\u003d\u003d\u003d\u003d\u003d\u003d\u003d\u003d\n1. To reproduce the problem download the latest driver.  I used: http://www.eclipse.org/downloads/download.php?file\u003d/technology/cosmos/1.0.0/COSMOS-1.0.0-200711051600/cosmos-dr-incubation-COSMOS-1.0.0-200711051600.zip\n\n2. Unzip the driver in the tomcat/webapps directory.\n\n3. Start tomcat.  Note that you have to change the catalina.properties file to point to the derby database.   The catalina.properties file should contain the following entry.\n  derby.system.home\u003dC://apache-tomcat-5.5.20/webapps/database\n\n\n4. Open a browser and point to  http://dev.eclipse.org/viewcvs/index.cgi/org.eclipse.cosmos/tests/data-reporting/org.eclipse.cosmos.dr.tests/WebContent/org/eclipse/cosmos/dr/gvs/report/viewer/LogReport.html?root\u003dTechnology_Project\u0026view\u003dco\n\n5. Click the submit button.  This should open another window with the generated report.  If you look at the tomcat console it will show the COSMOS exception",
    "This problem is related to the BIRT driver.\n\nRefer to Bug #209708"
  ],
  "commentCreationDates": [
    "2007-11-12T21:05:34+01:00",
    "2007-11-15T18:28:59+01:00"
  ],
  "traces": [
    {
      "exceptionType": "org.eclipse.cosmos.dc.runtime.RetryException",
      "message": "COSMOS Runtime Host not  initialized",
      "elements": [
        {
          "method": "org.eclipse.cosmos.dc.birt.helper.LocalHelper.verifyRuntimeHost",
          "source": "Local Helper.java:49"
        },
        {
          "method": "org.eclipse.cosmos.dc.birt.helper.LocalHelper.getLatestDatasetForSourceKeyset",
          "source": "LocalHelper.java:80"
        },
        {
          "method": "sun.reflect.NativeMethodAccessorImpl.invoke0",
          "source": "Native Method"
        },
        {
          "method": "sun.reflect.NativeMethodAccessorImpl.invoke",
          "source": "NativeMethodAccessorImpl. java:64"
        },
        {
          "method": "sun.reflect.DelegatingMethodAccessorImpl.invoke",
          "source": "DelegatingMethodAcces sorImpl.java:43"
        },
        {
          "method": "java.lang.reflect.Method.invoke",
          "source": "Method.java:615"
        },
        {
          "method": "org.mozilla.javascript.MemberBox.invoke",
          "source": "MemberBox.java:174"
        }
      ],
      "number": 0,
      "commentIndex": 0,
      "bugId": "209548",
      "date": "2007-11-12T21:05:34+01:00",
      "product": "Cosmos",
      "component": "DataCollection",
      "severity": "blocker"
    }
  ],
  "groupId": "209548",
  "bugId": "209548",
  "date": "2007-11-12T21:05:34+01:00",
  "product": "Cosmos",
  "component": "DataCollection",
  "severity": "blocker"
}