{
  "comments": [
    "When I update the web service the following exception is thrown:\n\njavax.xml.soap.SOAPException: org.apache.axis2.AxisFault: Two services can not have same name, a service with TestService already exists in the system\n\n        at org.eclipse.corona.internal.soa.provider.axis2.AdminServiceImpl.deployRPCService(AdminServiceImpl.java:167)\n        at org.eclipse.corona.internal.soa.provider.axis2.AdminServiceImpl.deployService(AdminServiceImpl.java:178)\n        at org.eclipse.corona.internal.soa.webservice.WebServiceDeployer.deployWebService(WebServiceDeployer.java:123)\n        at org.eclipse.corona.internal.soa.webservice.WebServiceDeployer.serviceChanged(WebServiceDeployer.java:91)\n        at org.eclipse.osgi.framework.internal.core.FilteredServiceListener.serviceChanged(FilteredServiceListener.java:94)\n        at org.eclipse.osgi.framework.internal.core.BundleContextImpl.dispatchEvent(BundleContextImpl.java:1224)\n        at org.eclipse.osgi.framework.eventmgr.EventManager.dispatchEvent(EventManager.java:195)\n        at org.eclipse.osgi.framework.eventmgr.ListenerQueue.dispatchEventSynchronous(ListenerQueue.java:141)\n        at org.eclipse.osgi.framework.internal.core.Framework.publishServiceEventPrivileged(Framework.java:1603)\n        at org.eclipse.osgi.framework.internal.core.Framework.publishServiceEvent(Framework.java:1578)\n        at org.eclipse.osgi.framework.internal.core.ServiceRegistrationImpl.\u003cinit\u003e(ServiceRegistrationImpl.java:103)\n        at org.eclipse.osgi.framework.internal.core.BundleContextImpl.createServiceRegistration(BundleContextImpl.java:657)\n        at org.eclipse.osgi.framework.internal.core.BundleContextImpl.registerService(BundleContextImpl.java:609)\n        at org.eclipse.osgi.framework.internal.core.BundleContextImpl.registerService(BundleContextImpl.java:675)\n        at com.prosyst.service.register.RegisterActivator.start(RegisterActivator.java:21)\n        at org.eclipse.osgi.framework.internal.core.BundleContextImpl$2.run(BundleContextImpl.java:999)\n        at java.security.AccessController.doPrivileged(Native Method)\n        at org.eclipse.osgi.framework.internal.core.BundleContextImpl.startActivator(BundleContextImpl.java:993)\n        at org.eclipse.osgi.framework.internal.core.BundleContextImpl.start(BundleContextImpl.java:974)\n        at org.eclipse.osgi.framework.internal.core.BundleHost.startWorker(BundleHost.java:346)\n        at org.eclipse.osgi.framework.internal.core.AbstractBundle.start(AbstractBundle.java:260)\n        at org.eclipse.osgi.framework.internal.core.AbstractBundle.start(AbstractBundle.java:252)\n        at org.eclipse.osgi.framework.internal.core.FrameworkCommandProvider._start(FrameworkCommandProvider.java:260)\n        at sun.reflect.NativeMethodAccessorImpl.invoke0(Native Method)\n        at sun.reflect.NativeMethodAccessorImpl.invoke(NativeMethodAccessorImpl.java:39)\n        at sun.reflect.DelegatingMethodAccessorImpl.invoke(DelegatingMethodAccessorImpl.java:25)\n        at java.lang.reflect.Method.invoke(Method.java:585)\n        at org.eclipse.osgi.framework.internal.core.FrameworkCommandInterpreter.execute(FrameworkCommandInterpreter.java:150)\n        at org.eclipse.osgi.framework.internal.core.FrameworkConsole.docommand(FrameworkConsole.java:291)\n        at org.eclipse.osgi.framework.internal.core.FrameworkConsole.console(FrameworkConsole.java:276)\n        at org.eclipse.osgi.framework.internal.core.FrameworkConsole.run(FrameworkConsole.java:218)\n        at java.lang.Thread.run(Thread.java:595)\nCaused by: org.apache.axis2.AxisFault: Two services can not have same name, a service with TestService already exists in the system\n        at org.apache.axis2.engine.AxisConfiguration.addServiceGroup(AxisConfiguration.java:254)\n        at org.apache.axis2.engine.AxisConfiguration.addService(AxisConfiguration.java:206)\n        at org.eclipse.corona.internal.soa.provider.axis2.AdminServiceImpl.deployRPCService(AdminServiceImpl.java:165)\n        ... 31 more"
  ],
  "commentCreationDates": [
    "2007-11-15T07:33:51+01:00"
  ],
  "traces": [
    {
      "exceptionType": "javax.xml.soap.SOAPException",
      "message": "org.apache.axis2.AxisFault: Two services can not have same name, a service with TestService already exists in the system",
      "elements": [
        {
          "method": "org.eclipse.corona.internal.soa.provider.axis2.AdminServiceImpl.deployRPCService",
          "source": "AdminServiceImpl.java:167"
        },
        {
          "method": "org.eclipse.corona.internal.soa.provider.axis2.AdminServiceImpl.deployService",
          "source": "AdminServiceImpl.java:178"
        },
        {
          "method": "org.eclipse.corona.internal.soa.webservice.WebServiceDeployer.deployWebService",
          "source": "WebServiceDeployer.java:123"
        },
        {
          "method": "org.eclipse.corona.internal.soa.webservice.WebServiceDeployer.serviceChanged",
          "source": "WebServiceDeployer.java:91"
        },
        {
          "method": "org.eclipse.osgi.framework.internal.core.FilteredServiceListener.serviceChanged",
          "source": "FilteredServiceListener.java:94"
        },
        {
          "method": "org.eclipse.osgi.framework.internal.core.BundleContextImpl.dispatchEvent",
          "source": "BundleContextImpl.java:1224"
        },
        {
          "method": "org.eclipse.osgi.framework.eventmgr.EventManager.dispatchEvent",
          "source": "EventManager.java:195"
        },
        {
          "method": "org.eclipse.osgi.framework.eventmgr.ListenerQueue.dispatchEventSynchronous",
          "source": "ListenerQueue.java:141"
        },
        {
          "method": "org.eclipse.osgi.framework.internal.core.Framework.publishServiceEventPrivileged",
          "source": "Framework.java:1603"
        },
        {
          "method": "org.eclipse.osgi.framework.internal.core.Framework.publishServiceEvent",
          "source": "Framework.java:1578"
        },
        {
          "method": "org.eclipse.osgi.framework.internal.core.ServiceRegistrationImpl.\u003cinit\u003e",
          "source": "ServiceRegistrationImpl.java:103"
        },
        {
          "method": "org.eclipse.osgi.framework.internal.core.BundleContextImpl.createServiceRegistration",
          "source": "BundleContextImpl.java:657"
        },
        {
          "method": "org.eclipse.osgi.framework.internal.core.BundleContextImpl.registerService",
          "source": "BundleContextImpl.java:609"
        },
        {
          "method": "org.eclipse.osgi.framework.internal.core.BundleContextImpl.registerService",
          "source": "BundleContextImpl.java:675"
        },
        {
          "method": "com.prosyst.service.register.RegisterActivator.start",
          "source": "RegisterActivator.java:21"
        },
        {
          "method": "org.eclipse.osgi.framework.internal.core.BundleContextImpl$2.run",
          "source": "BundleContextImpl.java:999"
        },
        {
          "method": "java.security.AccessController.doPrivileged",
          "source": "Native Method"
        },
        {
          "method": "org.eclipse.osgi.framework.internal.core.BundleContextImpl.startActivator",
          "source": "BundleContextImpl.java:993"
        },
        {
          "method": "org.eclipse.osgi.framework.internal.core.BundleContextImpl.start",
          "source": "BundleContextImpl.java:974"
        },
        {
          "method": "org.eclipse.osgi.framework.internal.core.BundleHost.startWorker",
          "source": "BundleHost.java:346"
        },
        {
          "method": "org.eclipse.osgi.framework.internal.core.AbstractBundle.start",
          "source": "AbstractBundle.java:260"
        },
        {
          "method": "org.eclipse.osgi.framework.internal.core.AbstractBundle.start",
          "source": "AbstractBundle.java:252"
        },
        {
          "method": "org.eclipse.osgi.framework.internal.core.FrameworkCommandProvider._start",
          "source": "FrameworkCommandProvider.java:260"
        },
        {
          "method": "sun.reflect.NativeMethodAccessorImpl.invoke0",
          "source": "Native Method"
        },
        {
          "method": "sun.reflect.NativeMethodAccessorImpl.invoke",
          "source": "NativeMethodAccessorImpl.java:39"
        },
        {
          "method": "sun.reflect.DelegatingMethodAccessorImpl.invoke",
          "source": "DelegatingMethodAccessorImpl.java:25"
        },
        {
          "method": "java.lang.reflect.Method.invoke",
          "source": "Method.java:585"
        },
        {
          "method": "org.eclipse.osgi.framework.internal.core.FrameworkCommandInterpreter.execute",
          "source": "FrameworkCommandInterpreter.java:150"
        },
        {
          "method": "org.eclipse.osgi.framework.internal.core.FrameworkConsole.docommand",
          "source": "FrameworkConsole.java:291"
        },
        {
          "method": "org.eclipse.osgi.framework.internal.core.FrameworkConsole.console",
          "source": "FrameworkConsole.java:276"
        },
        {
          "method": "org.eclipse.osgi.framework.internal.core.FrameworkConsole.run",
          "source": "FrameworkConsole.java:218"
        },
        {
          "method": "java.lang.Thread.run",
          "source": "Thread.java:595"
        }
      ],
      "number": 0,
      "commentIndex": 0,
      "bugId": "209904",
      "date": "2007-11-15T07:33:51+01:00",
      "product": "Corona",
      "component": "soa",
      "severity": "major"
    }
  ],
  "groupId": "209904",
  "bugId": "209904",
  "date": "2007-11-15T07:33:51+01:00",
  "product": "Corona",
  "component": "soa",
  "severity": "major"
}