{
  "comments": [
    "I created an FTP connection in the RSE explorer view.\nWhen I click symbolic link icon (looks like a special folder)\nI get the following exception:\njava.lang.ClassCastException: org.eclipse.rse.core.filters.SystemFilterReference \n      at org.eclipse.rse.internal.files.ui.view.SystemViewRemoteFileAdapter.internalGetChildren(SystemViewRemoteFileAdapter.java:558) \n      at org.eclipse.rse.internal.files.ui.view.SystemViewRemoteFileAdapter.getChildren(SystemViewRemoteFileAdapter.java:552) \n      at org.eclipse.rse.internal.ui.view.SystemView$CheckExistenceJob.run(SystemView.java:5772) \n      at org.eclipse.core.internal.jobs.Worker.run(Worker.java:55) \n\nSee screenshot attached.\nYaron",
    "Created an attachment (id\u003d83966)\nerror_screenshot\n\n"
  ],
  "commentCreationDates": [
    "2007-11-28T11:18:39+01:00",
    "2007-11-28T11:35:46+01:00"
  ],
  "traces": [
    {
      "exceptionType": "java.lang.ClassCastException",
      "message": "org.eclipse.rse.core.filters.SystemFilterReference",
      "elements": [
        {
          "method": "org.eclipse.rse.internal.files.ui.view.SystemViewRemoteFileAdapter.internalGetChildren",
          "source": "SystemViewRemoteFileAdapter.java:558"
        },
        {
          "method": "org.eclipse.rse.internal.files.ui.view.SystemViewRemoteFileAdapter.getChildren",
          "source": "SystemViewRemoteFileAdapter.java:552"
        },
        {
          "method": "org.eclipse.rse.internal.ui.view.SystemView$CheckExistenceJob.run",
          "source": "SystemView.java:5772"
        },
        {
          "method": "org.eclipse.core.internal.jobs.Worker.run",
          "source": "Worker.java:55"
        }
      ],
      "number": 0,
      "commentIndex": 0,
      "bugId": "211198",
      "date": "2007-11-28T11:18:39+01:00",
      "product": "Target Management",
      "component": "RSE",
      "severity": "normal"
    }
  ],
  "groupId": "211198",
  "bugId": "211198",
  "date": "2007-11-28T11:18:39+01:00",
  "product": "Target Management",
  "component": "RSE",
  "severity": "normal"
}