{
  "comments": [
    "Running Snapshot based simulation with the option to create a new mof files failed with \njava.io.FileNotFoundException: conf\\remove_override.txt (The system cannot find\nthe file specified)\n        at java.io.FileInputStream.open(Native Method)\n        at java.io.FileInputStream.\u003cinit\u003e(Unknown Source)\n        at java.io.FileInputStream.\u003cinit\u003e(Unknown Source)\n        at org.eclipse.aperi.simulator.cimom.sblim.util.MOFGenerator.doAdditiona\nlChanges(MOFGenerator.java:265)\n        at org.eclipse.aperi.simulator.cimom.sblim.util.MOFGenerator.printData(M\nOFGenerator.java:166)\n        at org.eclipse.aperi.simulator.cimom.sblim.util.MOFGenerator.generateDat\naForNameSpace(MOFGenerator.java:128)\n        at org.eclipse.aperi.simulator.cimom.sblim.util.MOFGenerator.generateDat\na(MOFGenerator.java:596)\n        at org.eclipse.aperi.simulator.cimom.common.base.BaseMOFGenerator.genera\nteMOFData(BaseMOFGenerator.java:116)\n        at org.eclipse.aperi.simulator.cimom.common.GenericMOFGenerator.startMOF\nGenerator(GenericMOFGenerator.java:99)\n        at org.eclipse.aperi.simulator.ui.GenerateMof.generate(GenerateMof.java:\n63)\n        at org.eclipse.aperi.simulator.ui.SetupProcess.SetupSANSimulator(SetupPr\nocess.java:96)\n        at org.eclipse.aperi.simulator.ui.SetupProcess.run(SetupProcess.java:55)\n\nThe simulation code is Simulator-Aperi-incubation-R04-071127-140700.zip",
    "the build of  Simulator-Aperi-incubation-R04-071130-115054.zip fixed the problem."
  ],
  "commentCreationDates": [
    "2007-11-30T18:03:57+01:00",
    "2007-12-01T22:26:26+01:00"
  ],
  "traces": [
    {
      "exceptionType": "java.io.FileNotFoundException",
      "message": "conf\\remove_override.txt (The system cannot find the file specified)",
      "elements": [
        {
          "method": "java.io.FileInputStream.open",
          "source": "Native Method"
        },
        {
          "method": "java.io.FileInputStream.\u003cinit\u003e",
          "source": "Unknown Source"
        },
        {
          "method": "java.io.FileInputStream.\u003cinit\u003e",
          "source": "Unknown Source"
        },
        {
          "method": "org.eclipse.aperi.simulator.cimom.sblim.util.MOFGenerator.doAdditionalChanges",
          "source": "MOFGenerator.java:265"
        },
        {
          "method": "org.eclipse.aperi.simulator.cimom.sblim.util.MOFGenerator.printData",
          "source": "M OFGenerator.java:166"
        },
        {
          "method": "org.eclipse.aperi.simulator.cimom.sblim.util.MOFGenerator.generateDataForNameSpace",
          "source": "MOFGenerator.java:128"
        },
        {
          "method": "org.eclipse.aperi.simulator.cimom.sblim.util.MOFGenerator.generateData",
          "source": "MOFGenerator.java:596"
        },
        {
          "method": "org.eclipse.aperi.simulator.cimom.common.base.BaseMOFGenerator.generateMOFData",
          "source": "BaseMOFGenerator.java:116"
        },
        {
          "method": "org.eclipse.aperi.simulator.cimom.common.GenericMOFGenerator.startMOFGenerator",
          "source": "GenericMOFGenerator.java:99"
        },
        {
          "method": "org.eclipse.aperi.simulator.ui.GenerateMof.generate",
          "source": "GenerateMof.java: 63"
        },
        {
          "method": "org.eclipse.aperi.simulator.ui.SetupProcess.SetupSANSimulator",
          "source": "SetupPr ocess.java:96"
        },
        {
          "method": "org.eclipse.aperi.simulator.ui.SetupProcess.run",
          "source": "SetupProcess.java:55"
        }
      ],
      "number": 0,
      "commentIndex": 0,
      "bugId": "211618",
      "date": "2007-11-30T18:03:57+01:00",
      "product": "Aperi",
      "component": "san.simulator",
      "severity": "major"
    }
  ],
  "groupId": "211618",
  "bugId": "211618",
  "date": "2007-11-30T18:03:57+01:00",
  "product": "Aperi",
  "component": "san.simulator",
  "severity": "major"
}