{
  "comments": [
    "Build ID: N/A\n\nSteps To Reproduce:\n1. I am using BIRT 2.2.2 on Oracle9i, P4-dual 3MHz\n2. I am running concurrency test to evaluate BIRT. To do the test, I run same report in different threads, using shared IReportRunnable instance (it is said to be thread-safe). See bug #211475 (which prevents using BIRT 2.2.1), it is the same scenario, but with more threads involved. Report contains a table with simple JDBC dataset and a line chart. \n\nWhen running with more than 200 threads, I start getting following exceptions:\n\njava.util.ConcurrentModificationException\n\tat org.eclipse.emf.common.util.BasicEList$EIterator.checkModCount(BasicEList.java:1327)\n\tat org.eclipse.emf.common.util.BasicEList$EIterator.next(BasicEList.java:1275)\n\tat org.eclipse.emf.ecore.util.EcoreUtil$Copier.copyAll(EcoreUtil.java:426)\n\tat org.eclipse.emf.ecore.util.EcoreUtil$Copier.copyContainment(EcoreUtil.java:534)\n\tat org.eclipse.emf.ecore.util.EcoreUtil$Copier.copy(EcoreUtil.java:455)\n\tat org.eclipse.emf.ecore.util.EcoreUtil$Copier.copyAll(EcoreUtil.java:426)\n\tat org.eclipse.emf.ecore.util.EcoreUtil$Copier.copyContainment(EcoreUtil.java:534)\n\tat org.eclipse.emf.ecore.util.EcoreUtil$Copier.copy(EcoreUtil.java:455)\n\tat org.eclipse.emf.ecore.util.EcoreUtil$Copier.copyAll(EcoreUtil.java:426)\n\tat org.eclipse.emf.ecore.util.EcoreUtil$Copier.copyContainment(EcoreUtil.java:534)\n\tat org.eclipse.emf.ecore.util.EcoreUtil$Copier.copy(EcoreUtil.java:455)\n\tat org.eclipse.emf.ecore.util.EcoreUtil$Copier.copyAll(EcoreUtil.java:426)\n\tat org.eclipse.emf.ecore.util.EcoreUtil$Copier.copyContainment(EcoreUtil.java:534)\n\tat org.eclipse.emf.ecore.util.EcoreUtil$Copier.copy(EcoreUtil.java:455)\n\tat org.eclipse.emf.ecore.util.EcoreUtil.copy(EcoreUtil.java:355)\n\tat org.eclipse.birt.chart.factory.Generator.prepare(Generator.java:627)\n\tat org.eclipse.birt.chart.reportitem.ChartReportItemGenerationImpl.onRowSets(ChartReportItemGenerationImpl.java:142)\n\tat org.eclipse.birt.report.engine.executor.ExtendedGenerateExecutor.generateContent(ExtendedGenerateExecutor.java:113)\n\tat org.eclipse.birt.report.engine.executor.ExtendedGenerateExecutor.execute(ExtendedGenerateExecutor.java:72)\n\tat org.eclipse.birt.report.engine.executor.ExtendedItemExecutor.execute(ExtendedItemExecutor.java:60)\n\tat org.eclipse.birt.report.engine.internal.executor.dup.SuppressDuplicateItemExecutor.execute(SuppressDuplicateItemExecutor.java:42)\n\tat org.eclipse.birt.report.engine.internal.executor.wrap.WrappedReportItemExecutor.execute(WrappedReportItemExecutor.java:45)\n\tat org.eclipse.birt.report.engine.internal.executor.l18n.LocalizedReportItemExecutor.execute(LocalizedReportItemExecutor.java:33)\n\tat org.eclipse.birt.report.engine.layout.html.HTMLBlockStackingLM.layoutNodes(HTMLBlockStackingLM.java:63)\n\tat org.eclipse.birt.report.engine.layout.html.HTMLPageLM.layout(HTMLPageLM.java:85)\n\tat org.eclipse.birt.report.engine.layout.html.HTMLReportLayoutEngine.layout(HTMLReportLayoutEngine.java:106)\n\tat org.eclipse.birt.report.engine.api.impl.RunAndRenderTask.doRun(RunAndRenderTask.java:140)\n\tat org.eclipse.birt.report.engine.api.impl.RunAndRenderTask.run(RunAndRenderTask.java:68)\n\tat com.epeople.reporting.test.BirtRunOnlyBenchmarkUnitFactory$BIRTRunOnlyBenchmarkUnit.run(BirtRunOnlyBenchmarkUnitFactory.java:60)\n\tat java.util.concurrent.ThreadPoolExecutor$Worker.runTask(ThreadPoolExecutor.java:650)\n\tat java.util.concurrent.ThreadPoolExecutor$Worker.run(ThreadPoolExecutor.java:675)\n\tat java.lang.Thread.run(Thread.java:595)\norg.eclipse.birt.report.engine.api.EngineException: Error happened while running the report\n\tat org.eclipse.birt.report.engine.api.impl.RunAndRenderTask.doRun(RunAndRenderTask.java:155)\n\tat org.eclipse.birt.report.engine.api.impl.RunAndRenderTask.run(RunAndRenderTask.java:68)\n\tat com.epeople.reporting.test.BirtRunOnlyBenchmarkUnitFactory$BIRTRunOnlyBenchmarkUnit.run(BirtRunOnlyBenchmarkUnitFactory.java:60)\n\tat java.util.concurrent.ThreadPoolExecutor$Worker.runTask(ThreadPoolExecutor.java:650)\n\tat java.util.concurrent.ThreadPoolExecutor$Worker.run(ThreadPoolExecutor.java:675)\n\tat java.lang.Thread.run(Thread.java:595)\nCaused by: java.util.ConcurrentModificationException\n\tat org.eclipse.emf.common.util.BasicEList$EIterator.checkModCount(BasicEList.java:1327)\n\tat org.eclipse.emf.common.util.BasicEList$EIterator.next(BasicEList.java:1275)\n\tat org.eclipse.emf.ecore.util.EcoreUtil$Copier.copyAll(EcoreUtil.java:426)\n\tat org.eclipse.emf.ecore.util.EcoreUtil$Copier.copyContainment(EcoreUtil.java:534)\n\tat org.eclipse.emf.ecore.util.EcoreUtil$Copier.copy(EcoreUtil.java:455)\n\tat org.eclipse.emf.ecore.util.EcoreUtil$Copier.copyAll(EcoreUtil.java:426)\n\tat org.eclipse.emf.ecore.util.EcoreUtil$Copier.copyContainment(EcoreUtil.java:534)\n\tat org.eclipse.emf.ecore.util.EcoreUtil$Copier.copy(EcoreUtil.java:455)\n\tat org.eclipse.emf.ecore.util.EcoreUtil$Copier.copyAll(EcoreUtil.java:426)\n\tat org.eclipse.emf.ecore.util.EcoreUtil$Copier.copyContainment(EcoreUtil.java:534)\n\tat org.eclipse.emf.ecore.util.EcoreUtil$Copier.copy(EcoreUtil.java:455)\n\tat org.eclipse.emf.ecore.util.EcoreUtil$Copier.copyAll(EcoreUtil.java:426)\n\tat org.eclipse.emf.ecore.util.EcoreUtil$Copier.copyContainment(EcoreUtil.java:534)\n\tat org.eclipse.emf.ecore.util.EcoreUtil$Copier.copy(EcoreUtil.java:455)\n\tat org.eclipse.emf.ecore.util.EcoreUtil.copy(EcoreUtil.java:355)\n\tat org.eclipse.birt.chart.factory.Generator.prepare(Generator.java:627)\n\tat org.eclipse.birt.chart.reportitem.ChartReportItemGenerationImpl.onRowSets(ChartReportItemGenerationImpl.java:142)\n\tat org.eclipse.birt.report.engine.executor.ExtendedGenerateExecutor.generateContent(ExtendedGenerateExecutor.java:113)\n\tat org.eclipse.birt.report.engine.executor.ExtendedGenerateExecutor.execute(ExtendedGenerateExecutor.java:72)\n\tat org.eclipse.birt.report.engine.executor.ExtendedItemExecutor.execute(ExtendedItemExecutor.java:60)\n\tat org.eclipse.birt.report.engine.internal.executor.dup.SuppressDuplicateItemExecutor.execute(SuppressDuplicateItemExecutor.java:42)\n\tat org.eclipse.birt.report.engine.internal.executor.wrap.WrappedReportItemExecutor.execute(WrappedReportItemExecutor.java:45)\n\tat org.eclipse.birt.report.engine.internal.executor.l18n.LocalizedReportItemExecutor.execute(LocalizedReportItemExecutor.java:33)\n\tat org.eclipse.birt.report.engine.layout.html.HTMLBlockStackingLM.layoutNodes(HTMLBlockStackingLM.java:63)\n\tat org.eclipse.birt.report.engine.layout.html.HTMLPageLM.layout(HTMLPageLM.java:85)\n\tat org.eclipse.birt.report.engine.layout.html.HTMLReportLayoutEngine.layout(HTMLReportLayoutEngine.java:106)\n\tat org.eclipse.birt.report.engine.api.impl.RunAndRenderTask.doRun(RunAndRenderTask.java:140)\n\t... 5 more\nDec 5, 2007 12:47:18 PM org.eclipse.birt.data.engine.odaconsumer.PreparedStatement close\nSEVERE: Cannot close statement.\norg.eclipse.birt.report.data.oda.jdbc.JDBCException: Cannot close preparedStatement.\nSQL error #1: Io exception: Socket closed\n ;\n    java.sql.SQLException: Io exception: Socket closed\n\tat org.eclipse.birt.report.data.oda.jdbc.Statement.close(Statement.java:209)\n\tat org.eclipse.datatools.connectivity.oda.consumer.helper.OdaQuery.close(OdaQuery.java:257)\n\tat org.eclipse.birt.data.engine.odaconsumer.PreparedStatement.close(PreparedStatement.java:855)\n\tat org.eclipse.birt.data.engine.executor.DataSource.close(DataSource.java:262)\n\tat org.eclipse.birt.data.engine.executor.DataSource.finalize(DataSource.java:304)\n\tat java.lang.ref.Finalizer.invokeFinalizeMethod(Native Method)\n\tat java.lang.ref.Finalizer.runFinalizer(Finalizer.java:83)\n\tat java.lang.ref.Finalizer.access$100(Finalizer.java:14)\n\tat java.lang.ref.Finalizer$FinalizerThread.run(Finalizer.java:160)\nCaused by: java.sql.SQLException: Io exception: Socket closed\n\tat oracle.jdbc.dbaccess.DBError.throwSqlException(DBError.java:134)\n\tat oracle.jdbc.dbaccess.DBError.throwSqlException(DBError.java:179)\n\tat oracle.jdbc.dbaccess.DBError.throwSqlException(DBError.java:334)\n\tat oracle.jdbc.ttc7.TTC7Protocol.handleIOException(TTC7Protocol.java:3678)\n\tat oracle.jdbc.ttc7.TTC7Protocol.close(TTC7Protocol.java:726)\n\tat oracle.jdbc.driver.OracleStatement.close(OracleStatement.java:720)\n\tat oracle.jdbc.driver.OraclePreparedStatement.privateClose(OraclePreparedStatement.java:490)\n\tat oracle.jdbc.driver.OraclePreparedStatement.close(OraclePreparedStatement.java:398)\n\tat org.eclipse.birt.report.data.oda.jdbc.Statement.close(Statement.java:204)\n\t... 8 more\n\n\n3. Here is a test case code:\n\nMore information:\nCode for test case (composed from various tutorials on BIRT all over the net):\n\nimport org.eclipse.birt.report.engine.api.IReportEngine;\nimport org.eclipse.birt.report.engine.api.EngineConfig;\nimport org.eclipse.birt.report.engine.api.IReportEngineFactory;\nimport org.eclipse.birt.report.engine.api.IRunAndRenderTask;\nimport org.eclipse.birt.report.engine.api.HTMLRenderContext;\nimport org.eclipse.birt.report.engine.api.EngineConstants;\nimport org.eclipse.birt.report.engine.api.HTMLRenderOption;\nimport org.eclipse.birt.report.engine.api.IReportRunnable;\nimport org.eclipse.birt.core.framework.Platform;\n\nimport java.util.logging.Level;\nimport java.util.concurrent.BlockingQueue;\nimport java.util.concurrent.ArrayBlockingQueue;\nimport java.util.concurrent.ThreadPoolExecutor;\nimport java.util.concurrent.TimeUnit;\nimport java.util.ArrayList;\nimport java.util.HashMap;\nimport java.io.ByteArrayOutputStream;\n\npublic class BugTest {\n\n    private IReportEngine engine;\n    private IReportRunnable design;\n\n    public BugTest(IReportEngine engine, IReportRunnable design) {\n        this.engine \u003d engine;\n        this.design \u003d design;\n    }\n\n    public void runTest(int unitCount, int threadCount) {\n        BlockingQueue\u003cRunnable\u003e queue \u003d new\nArrayBlockingQueue\u003cRunnable\u003e(unitCount);\n\n        ArrayList\u003cThreadTestUnit\u003e units \u003d new\nArrayList\u003cThreadTestUnit\u003e(unitCount);\n        for (int i \u003d 0; i \u003c unitCount; i++) {\n            ThreadTestUnit unit \u003d new ThreadTestUnit();\n            units.add(unit);\n        }\n\n        ThreadPoolExecutor executor \u003d new ThreadPoolExecutor(threadCount,\nthreadCount, Integer.MAX_VALUE, TimeUnit.SECONDS, queue);\n\n        for (ThreadTestUnit unit : units) {\n            executor.execute(unit);\n        }\n\n        executor.shutdown();\n        try {\n            executor.awaitTermination(Long.MAX_VALUE, TimeUnit.SECONDS);\n        } catch (InterruptedException e1) {\n            throw new RuntimeException(e1);\n        }\n    }\n\n\n    public static void main(String[] args) {\n\n        String birtRuntimeDir \u003d \"F:/birt-runtime-2_2_2/ReportEngine\";\n        String logDir \u003d \"f:/temp\";\n        String reportSrc \u003d \"F:/birt/new_report_2.rptdesign\";\n\n        IReportEngine engine;\n        IReportRunnable design;\n\n        try {\n            EngineConfig config \u003d new EngineConfig();\n            config.setEngineHome(birtRuntimeDir);\n            config.setLogConfig(logDir, Level.FINE);\n            Platform.startup(config);\n            IReportEngineFactory factory \u003d (IReportEngineFactory) Platform\n                   \n.createFactoryObject(IReportEngineFactory.EXTENSION_REPORT_ENGINE_FACTORY);\n            engine \u003d factory.createReportEngine(config);\n            engine.changeLogLevel(Level.WARNING);\n            design \u003d engine.openReportDesign(reportSrc);\n        } catch (Exception e) {\n            throw new RuntimeException(e);\n        }\n\n        new BugTest(engine, design).runTest(600, 600);\n\n        engine.shutdown();\n        Platform.shutdown();\n    }\n\n    private class ThreadTestUnit implements Runnable {\n\n        public void run() {\n            try {\n                IRunAndRenderTask task \u003d engine.createRunAndRenderTask(design);\n                HTMLRenderContext renderContext \u003d new HTMLRenderContext();\n                renderContext.setImageDirectory(\"image\");\n                HashMap contextMap \u003d new HashMap();\n                contextMap.put( EngineConstants.APPCONTEXT_HTML_RENDER_CONTEXT,\nrenderContext );\n                task.setAppContext( contextMap );\n                HTMLRenderOption options \u003d new HTMLRenderOption();\n                ByteArrayOutputStream str \u003d new ByteArrayOutputStream();\n                options.setOutputStream(str);\n                options.setOutputFormat(\"html\");\n                task.setRenderOption(options);\n                task.run();\n                task.close();\n            } catch (Exception e) {\n                throw new RuntimeException(e);\n            }\n        }\n    }\n}\n\n\n\nMore information:",
    "Looks like the exception is coming from EMF, need to check if chart engine\u0027s usage of EMF."
  ],
  "commentCreationDates": [
    "2007-12-05T10:09:29+01:00",
    "2007-12-12T01:36:32+01:00"
  ],
  "traces": [
    {
      "exceptionType": "java.util.ConcurrentModificationException",
      "elements": [
        {
          "method": "org.eclipse.emf.common.util.BasicEList$EIterator.checkModCount",
          "source": "BasicEList.java:1327"
        },
        {
          "method": "org.eclipse.emf.common.util.BasicEList$EIterator.next",
          "source": "BasicEList.java:1275"
        },
        {
          "method": "org.eclipse.emf.ecore.util.EcoreUtil$Copier.copyAll",
          "source": "EcoreUtil.java:426"
        },
        {
          "method": "org.eclipse.emf.ecore.util.EcoreUtil$Copier.copyContainment",
          "source": "EcoreUtil.java:534"
        },
        {
          "method": "org.eclipse.emf.ecore.util.EcoreUtil$Copier.copy",
          "source": "EcoreUtil.java:455"
        },
        {
          "method": "org.eclipse.emf.ecore.util.EcoreUtil$Copier.copyAll",
          "source": "EcoreUtil.java:426"
        },
        {
          "method": "org.eclipse.emf.ecore.util.EcoreUtil$Copier.copyContainment",
          "source": "EcoreUtil.java:534"
        },
        {
          "method": "org.eclipse.emf.ecore.util.EcoreUtil$Copier.copy",
          "source": "EcoreUtil.java:455"
        },
        {
          "method": "org.eclipse.emf.ecore.util.EcoreUtil$Copier.copyAll",
          "source": "EcoreUtil.java:426"
        },
        {
          "method": "org.eclipse.emf.ecore.util.EcoreUtil$Copier.copyContainment",
          "source": "EcoreUtil.java:534"
        },
        {
          "method": "org.eclipse.emf.ecore.util.EcoreUtil$Copier.copy",
          "source": "EcoreUtil.java:455"
        },
        {
          "method": "org.eclipse.emf.ecore.util.EcoreUtil$Copier.copyAll",
          "source": "EcoreUtil.java:426"
        },
        {
          "method": "org.eclipse.emf.ecore.util.EcoreUtil$Copier.copyContainment",
          "source": "EcoreUtil.java:534"
        },
        {
          "method": "org.eclipse.emf.ecore.util.EcoreUtil$Copier.copy",
          "source": "EcoreUtil.java:455"
        },
        {
          "method": "org.eclipse.emf.ecore.util.EcoreUtil.copy",
          "source": "EcoreUtil.java:355"
        },
        {
          "method": "org.eclipse.birt.chart.factory.Generator.prepare",
          "source": "Generator.java:627"
        },
        {
          "method": "org.eclipse.birt.chart.reportitem.ChartReportItemGenerationImpl.onRowSets",
          "source": "ChartReportItemGenerationImpl.java:142"
        },
        {
          "method": "org.eclipse.birt.report.engine.executor.ExtendedGenerateExecutor.generateContent",
          "source": "ExtendedGenerateExecutor.java:113"
        },
        {
          "method": "org.eclipse.birt.report.engine.executor.ExtendedGenerateExecutor.execute",
          "source": "ExtendedGenerateExecutor.java:72"
        },
        {
          "method": "org.eclipse.birt.report.engine.executor.ExtendedItemExecutor.execute",
          "source": "ExtendedItemExecutor.java:60"
        },
        {
          "method": "org.eclipse.birt.report.engine.internal.executor.dup.SuppressDuplicateItemExecutor.execute",
          "source": "SuppressDuplicateItemExecutor.java:42"
        },
        {
          "method": "org.eclipse.birt.report.engine.internal.executor.wrap.WrappedReportItemExecutor.execute",
          "source": "WrappedReportItemExecutor.java:45"
        },
        {
          "method": "org.eclipse.birt.report.engine.internal.executor.l18n.LocalizedReportItemExecutor.execute",
          "source": "LocalizedReportItemExecutor.java:33"
        },
        {
          "method": "org.eclipse.birt.report.engine.layout.html.HTMLBlockStackingLM.layoutNodes",
          "source": "HTMLBlockStackingLM.java:63"
        },
        {
          "method": "org.eclipse.birt.report.engine.layout.html.HTMLPageLM.layout",
          "source": "HTMLPageLM.java:85"
        },
        {
          "method": "org.eclipse.birt.report.engine.layout.html.HTMLReportLayoutEngine.layout",
          "source": "HTMLReportLayoutEngine.java:106"
        },
        {
          "method": "org.eclipse.birt.report.engine.api.impl.RunAndRenderTask.doRun",
          "source": "RunAndRenderTask.java:140"
        },
        {
          "method": "org.eclipse.birt.report.engine.api.impl.RunAndRenderTask.run",
          "source": "RunAndRenderTask.java:68"
        },
        {
          "method": "com.epeople.reporting.test.BirtRunOnlyBenchmarkUnitFactory$BIRTRunOnlyBenchmarkUnit.run",
          "source": "BirtRunOnlyBenchmarkUnitFactory.java:60"
        },
        {
          "method": "java.util.concurrent.ThreadPoolExecutor$Worker.runTask",
          "source": "ThreadPoolExecutor.java:650"
        },
        {
          "method": "java.util.concurrent.ThreadPoolExecutor$Worker.run",
          "source": "ThreadPoolExecutor.java:675"
        },
        {
          "method": "java.lang.Thread.run",
          "source": "Thread.java:595"
        }
      ],
      "number": 0,
      "commentIndex": 0,
      "bugId": "211976",
      "date": "2007-12-05T10:09:29+01:00",
      "product": "BIRT",
      "component": "Chart",
      "severity": "normal"
    },
    {
      "exceptionType": "org.eclipse.birt.report.engine.api.EngineException",
      "message": "Error happened while running the report",
      "elements": [
        {
          "method": "org.eclipse.birt.report.engine.api.impl.RunAndRenderTask.doRun",
          "source": "RunAndRenderTask.java:155"
        },
        {
          "method": "org.eclipse.birt.report.engine.api.impl.RunAndRenderTask.run",
          "source": "RunAndRenderTask.java:68"
        },
        {
          "method": "com.epeople.reporting.test.BirtRunOnlyBenchmarkUnitFactory$BIRTRunOnlyBenchmarkUnit.run",
          "source": "BirtRunOnlyBenchmarkUnitFactory.java:60"
        },
        {
          "method": "java.util.concurrent.ThreadPoolExecutor$Worker.runTask",
          "source": "ThreadPoolExecutor.java:650"
        },
        {
          "method": "java.util.concurrent.ThreadPoolExecutor$Worker.run",
          "source": "ThreadPoolExecutor.java:675"
        },
        {
          "method": "java.lang.Thread.run",
          "source": "Thread.java:595"
        }
      ],
      "causedBy": {
        "exceptionType": "java.util.ConcurrentModificationException",
        "elements": [
          {
            "method": "org.eclipse.emf.common.util.BasicEList$EIterator.checkModCount",
            "source": "BasicEList.java:1327"
          },
          {
            "method": "org.eclipse.emf.common.util.BasicEList$EIterator.next",
            "source": "BasicEList.java:1275"
          },
          {
            "method": "org.eclipse.emf.ecore.util.EcoreUtil$Copier.copyAll",
            "source": "EcoreUtil.java:426"
          },
          {
            "method": "org.eclipse.emf.ecore.util.EcoreUtil$Copier.copyContainment",
            "source": "EcoreUtil.java:534"
          },
          {
            "method": "org.eclipse.emf.ecore.util.EcoreUtil$Copier.copy",
            "source": "EcoreUtil.java:455"
          },
          {
            "method": "org.eclipse.emf.ecore.util.EcoreUtil$Copier.copyAll",
            "source": "EcoreUtil.java:426"
          },
          {
            "method": "org.eclipse.emf.ecore.util.EcoreUtil$Copier.copyContainment",
            "source": "EcoreUtil.java:534"
          },
          {
            "method": "org.eclipse.emf.ecore.util.EcoreUtil$Copier.copy",
            "source": "EcoreUtil.java:455"
          },
          {
            "method": "org.eclipse.emf.ecore.util.EcoreUtil$Copier.copyAll",
            "source": "EcoreUtil.java:426"
          },
          {
            "method": "org.eclipse.emf.ecore.util.EcoreUtil$Copier.copyContainment",
            "source": "EcoreUtil.java:534"
          },
          {
            "method": "org.eclipse.emf.ecore.util.EcoreUtil$Copier.copy",
            "source": "EcoreUtil.java:455"
          },
          {
            "method": "org.eclipse.emf.ecore.util.EcoreUtil$Copier.copyAll",
            "source": "EcoreUtil.java:426"
          },
          {
            "method": "org.eclipse.emf.ecore.util.EcoreUtil$Copier.copyContainment",
            "source": "EcoreUtil.java:534"
          },
          {
            "method": "org.eclipse.emf.ecore.util.EcoreUtil$Copier.copy",
            "source": "EcoreUtil.java:455"
          },
          {
            "method": "org.eclipse.emf.ecore.util.EcoreUtil.copy",
            "source": "EcoreUtil.java:355"
          },
          {
            "method": "org.eclipse.birt.chart.factory.Generator.prepare",
            "source": "Generator.java:627"
          },
          {
            "method": "org.eclipse.birt.chart.reportitem.ChartReportItemGenerationImpl.onRowSets",
            "source": "ChartReportItemGenerationImpl.java:142"
          },
          {
            "method": "org.eclipse.birt.report.engine.executor.ExtendedGenerateExecutor.generateContent",
            "source": "ExtendedGenerateExecutor.java:113"
          },
          {
            "method": "org.eclipse.birt.report.engine.executor.ExtendedGenerateExecutor.execute",
            "source": "ExtendedGenerateExecutor.java:72"
          },
          {
            "method": "org.eclipse.birt.report.engine.executor.ExtendedItemExecutor.execute",
            "source": "ExtendedItemExecutor.java:60"
          },
          {
            "method": "org.eclipse.birt.report.engine.internal.executor.dup.SuppressDuplicateItemExecutor.execute",
            "source": "SuppressDuplicateItemExecutor.java:42"
          },
          {
            "method": "org.eclipse.birt.report.engine.internal.executor.wrap.WrappedReportItemExecutor.execute",
            "source": "WrappedReportItemExecutor.java:45"
          },
          {
            "method": "org.eclipse.birt.report.engine.internal.executor.l18n.LocalizedReportItemExecutor.execute",
            "source": "LocalizedReportItemExecutor.java:33"
          },
          {
            "method": "org.eclipse.birt.report.engine.layout.html.HTMLBlockStackingLM.layoutNodes",
            "source": "HTMLBlockStackingLM.java:63"
          },
          {
            "method": "org.eclipse.birt.report.engine.layout.html.HTMLPageLM.layout",
            "source": "HTMLPageLM.java:85"
          },
          {
            "method": "org.eclipse.birt.report.engine.layout.html.HTMLReportLayoutEngine.layout",
            "source": "HTMLReportLayoutEngine.java:106"
          },
          {
            "method": "org.eclipse.birt.report.engine.api.impl.RunAndRenderTask.doRun",
            "source": "RunAndRenderTask.java:140"
          }
        ],
        "number": 0,
        "commentIndex": 0
      },
      "number": 1,
      "commentIndex": 0,
      "bugId": "211976",
      "date": "2007-12-05T10:09:29+01:00",
      "product": "BIRT",
      "component": "Chart",
      "severity": "normal"
    },
    {
      "exceptionType": "java.sql.SQLException",
      "message": "Io exception: Socket closed",
      "elements": [
        {
          "method": "org.eclipse.birt.report.data.oda.jdbc.Statement.close",
          "source": "Statement.java:209"
        },
        {
          "method": "org.eclipse.datatools.connectivity.oda.consumer.helper.OdaQuery.close",
          "source": "OdaQuery.java:257"
        },
        {
          "method": "org.eclipse.birt.data.engine.odaconsumer.PreparedStatement.close",
          "source": "PreparedStatement.java:855"
        },
        {
          "method": "org.eclipse.birt.data.engine.executor.DataSource.close",
          "source": "DataSource.java:262"
        },
        {
          "method": "org.eclipse.birt.data.engine.executor.DataSource.finalize",
          "source": "DataSource.java:304"
        },
        {
          "method": "java.lang.ref.Finalizer.invokeFinalizeMethod",
          "source": "Native Method"
        },
        {
          "method": "java.lang.ref.Finalizer.runFinalizer",
          "source": "Finalizer.java:83"
        },
        {
          "method": "java.lang.ref.Finalizer.access$100",
          "source": "Finalizer.java:14"
        },
        {
          "method": "java.lang.ref.Finalizer$FinalizerThread.run",
          "source": "Finalizer.java:160"
        }
      ],
      "causedBy": {
        "exceptionType": "java.sql.SQLException",
        "message": "Io exception: Socket closed",
        "elements": [
          {
            "method": "oracle.jdbc.dbaccess.DBError.throwSqlException",
            "source": "DBError.java:134"
          },
          {
            "method": "oracle.jdbc.dbaccess.DBError.throwSqlException",
            "source": "DBError.java:179"
          },
          {
            "method": "oracle.jdbc.dbaccess.DBError.throwSqlException",
            "source": "DBError.java:334"
          },
          {
            "method": "oracle.jdbc.ttc7.TTC7Protocol.handleIOException",
            "source": "TTC7Protocol.java:3678"
          },
          {
            "method": "oracle.jdbc.ttc7.TTC7Protocol.close",
            "source": "TTC7Protocol.java:726"
          },
          {
            "method": "oracle.jdbc.driver.OracleStatement.close",
            "source": "OracleStatement.java:720"
          },
          {
            "method": "oracle.jdbc.driver.OraclePreparedStatement.privateClose",
            "source": "OraclePreparedStatement.java:490"
          },
          {
            "method": "oracle.jdbc.driver.OraclePreparedStatement.close",
            "source": "OraclePreparedStatement.java:398"
          },
          {
            "method": "org.eclipse.birt.report.data.oda.jdbc.Statement.close",
            "source": "Statement.java:204"
          }
        ],
        "number": 0,
        "commentIndex": 0
      },
      "number": 2,
      "commentIndex": 0,
      "bugId": "211976",
      "date": "2007-12-05T10:09:29+01:00",
      "product": "BIRT",
      "component": "Chart",
      "severity": "normal"
    }
  ],
  "groupId": "211976",
  "bugId": "211976",
  "date": "2007-12-05T10:09:29+01:00",
  "product": "BIRT",
  "component": "Chart",
  "severity": "normal"
}