{
  "comments": [
    "Created an attachment (id\u003d84811)\nText to paste into a plug-in project\n\nI20071204-1547\n\n- new workspace\n- new Plug-in project, accept all defaults\n- Prefs \u003e Java \u003e Compiler \u003e Errors/Warnings \u003e Code Style:\n    set \"Non-externalized...\" to Warning\n- copy contents of attached file to clipboard\n- select source folder and paste\n- Ctrl+A\n\n\u003d\u003e log:\n!ENTRY org.eclipse.ui.ide 4 4 2007-12-09 15:30:18.921\n!MESSAGE Error accessing marker type\n\n!ENTRY org.eclipse.core.resources 4 376 2007-12-09 15:30:18.921\n!MESSAGE Marker id 2 not found.\n\nComplete stacktrace (swallowed by bug 212340):\n\n!ENTRY org.eclipse.core.resources 4 376 2007-12-09 15:32:33.234\n!MESSAGE Marker id 2 not found.\norg.eclipse.core.internal.resources.ResourceException: Marker id 2 not found.\n        at org.eclipse.core.internal.resources.Marker.checkInfo(Marker.java:56)\n        at org.eclipse.core.internal.resources.Marker.getType(Marker.java:194)\n        at org.eclipse.core.internal.resources.Marker.isSubtypeOf(Marker.java:215)\n        at org.eclipse.ui.views.markers.MarkerViewUtil.getViewId(MarkerViewUtil.java:63)\n        at org.eclipse.ui.views.markers.MarkerViewUtil.showMarker(MarkerViewUtil.java:94)\n        at org.eclipse.ui.texteditor.AbstractDecoratedTextEditor.updateMarkerViews(AbstractDecoratedTextEditor.java:1865)\n        at org.eclipse.jdt.internal.ui.javaeditor.JavaEditor.updateMarkerViews(JavaEditor.java:2697)\n        at org.eclipse.jdt.internal.ui.javaeditor.JavaEditor.updateStatusLine(JavaEditor.java:3116)\n        at org.eclipse.jdt.internal.ui.javaeditor.JavaEditor.selectionChanged(JavaEditor.java:1872)\n        at org.eclipse.jdt.internal.ui.javaeditor.JavaEditor$EditorSelectionChangedListener.selectionChanged(JavaEditor.java:285)\n        at org.eclipse.jface.text.TextViewer.firePostSelectionChanged(TextViewer.java:2560)\n        at org.eclipse.jface.text.TextViewer.firePostSelectionChanged(TextViewer.java:2512)\n        at org.eclipse.jface.text.TextViewer$5.run(TextViewer.java:2491)\n        at org.eclipse.swt.widgets.Display.runTimer(Display.java:3813)\n        at org.eclipse.swt.widgets.Display.messageProc(Display.java:3031)\n        at org.eclipse.swt.internal.win32.OS.$$YJP$$DispatchMessageW(Native Method)\n        at org.eclipse.swt.internal.win32.OS.DispatchMessageW(OS.java)\n        at org.eclipse.swt.internal.win32.OS.DispatchMessage(OS.java:2327)\n        at org.eclipse.swt.widgets.Display.readAndDispatch(Display.java:3359)\n        at org.eclipse.ui.internal.Workbench.runEventLoop(Workbench.java:2381)\n        at org.eclipse.ui.internal.Workbench.runUI(Workbench.java:2345)\n        at org.eclipse.ui.internal.Workbench.access$4(Workbench.java:2211)\n        at org.eclipse.ui.internal.Workbench$4.run(Workbench.java:473)\n        at org.eclipse.core.databinding.observable.Realm.runWithDefault(Realm.java:288)\n        at org.eclipse.ui.internal.Workbench.createAndRunWorkbench(Workbench.java:468)\n        at org.eclipse.ui.PlatformUI.createAndRunWorkbench(PlatformUI.java:149)\n        at org.eclipse.ui.internal.ide.application.IDEApplication.start(IDEApplication.java:106)\n        at org.eclipse.equinox.internal.app.EclipseAppHandle.run(EclipseAppHandle.java:193)\n        at org.eclipse.core.runtime.internal.adaptor.EclipseAppLauncher.runApplication(EclipseAppLauncher.java:106)\n        at org.eclipse.core.runtime.internal.adaptor.EclipseAppLauncher.start(EclipseAppLauncher.java:76)\n        at org.eclipse.core.runtime.adaptor.EclipseStarter.run(EclipseStarter.java:362)\n        at org.eclipse.core.runtime.adaptor.EclipseStarter.run(EclipseStarter.java:175)\n        at sun.reflect.NativeMethodAccessorImpl.invoke0(Native Method)\n        at sun.reflect.NativeMethodAccessorImpl.invoke(NativeMethodAccessorImpl.java:39)\n        at sun.reflect.DelegatingMethodAccessorImpl.invoke(DelegatingMethodAccessorImpl.java:25)\n        at java.lang.reflect.Method.invoke(Method.java:597)\n        at org.eclipse.equinox.launcher.Main.invokeFramework(Main.java:561)\n        at org.eclipse.equinox.launcher.Main.basicRun(Main.java:501)\n        at org.eclipse.equinox.launcher.Main.run(Main.java:1239)\n        at org.eclipse.equinox.launcher.Main.main(Main.java:1215)",
    "This is an issue with a stale markers being sent to the problems view to be opened - likely they were removed in a build during this (I can\u0027t replicate but I can see what happened using code inspection).\n\nAre you running with auto build on? \n\nEither way we have a couple of options\n\n1) We abort the operation for stale markers (current behaviour)\n2) We open the problems view with no selection\n3) We see what we can figure out and try and select on afterwards\n\nI think 2) makes the most sense as the marker is inconsistent and will likely be a mismatch anyways.",
    "Looking at the code again I think it actually makes more sense to do 1) - we failed to open on the marker and so are returning false.\n\nI have updated the core exception logging using the pattern prescibed by CoreException and I think that is all we want to do.",
    "Verified in Version: 3.4.0\nBuild id: I20071212-0010"
  ],
  "commentCreationDates": [
    "2007-12-09T14:40:25+01:00",
    "2007-12-10T15:03:29+01:00",
    "2007-12-10T15:14:52+01:00",
    "2007-12-12T20:18:34+01:00"
  ],
  "traces": [
    {
      "exceptionType": "org.eclipse.core.internal.resources.ResourceException",
      "message": "Marker id 2 not found.",
      "elements": [
        {
          "method": "org.eclipse.core.internal.resources.Marker.checkInfo",
          "source": "Marker.java:56"
        },
        {
          "method": "org.eclipse.core.internal.resources.Marker.getType",
          "source": "Marker.java:194"
        },
        {
          "method": "org.eclipse.core.internal.resources.Marker.isSubtypeOf",
          "source": "Marker.java:215"
        },
        {
          "method": "org.eclipse.ui.views.markers.MarkerViewUtil.getViewId",
          "source": "MarkerViewUtil.java:63"
        },
        {
          "method": "org.eclipse.ui.views.markers.MarkerViewUtil.showMarker",
          "source": "MarkerViewUtil.java:94"
        },
        {
          "method": "org.eclipse.ui.texteditor.AbstractDecoratedTextEditor.updateMarkerViews",
          "source": "AbstractDecoratedTextEditor.java:1865"
        },
        {
          "method": "org.eclipse.jdt.internal.ui.javaeditor.JavaEditor.updateMarkerViews",
          "source": "JavaEditor.java:2697"
        },
        {
          "method": "org.eclipse.jdt.internal.ui.javaeditor.JavaEditor.updateStatusLine",
          "source": "JavaEditor.java:3116"
        },
        {
          "method": "org.eclipse.jdt.internal.ui.javaeditor.JavaEditor.selectionChanged",
          "source": "JavaEditor.java:1872"
        },
        {
          "method": "org.eclipse.jdt.internal.ui.javaeditor.JavaEditor$EditorSelectionChangedListener.selectionChanged",
          "source": "JavaEditor.java:285"
        },
        {
          "method": "org.eclipse.jface.text.TextViewer.firePostSelectionChanged",
          "source": "TextViewer.java:2560"
        },
        {
          "method": "org.eclipse.jface.text.TextViewer.firePostSelectionChanged",
          "source": "TextViewer.java:2512"
        },
        {
          "method": "org.eclipse.jface.text.TextViewer$5.run",
          "source": "TextViewer.java:2491"
        },
        {
          "method": "org.eclipse.swt.widgets.Display.runTimer",
          "source": "Display.java:3813"
        },
        {
          "method": "org.eclipse.swt.widgets.Display.messageProc",
          "source": "Display.java:3031"
        },
        {
          "method": "org.eclipse.swt.internal.win32.OS.$$YJP$$DispatchMessageW",
          "source": "Native Method"
        },
        {
          "method": "org.eclipse.swt.internal.win32.OS.DispatchMessageW",
          "source": "OS.java"
        },
        {
          "method": "org.eclipse.swt.internal.win32.OS.DispatchMessage",
          "source": "OS.java:2327"
        },
        {
          "method": "org.eclipse.swt.widgets.Display.readAndDispatch",
          "source": "Display.java:3359"
        },
        {
          "method": "org.eclipse.ui.internal.Workbench.runEventLoop",
          "source": "Workbench.java:2381"
        },
        {
          "method": "org.eclipse.ui.internal.Workbench.runUI",
          "source": "Workbench.java:2345"
        },
        {
          "method": "org.eclipse.ui.internal.Workbench.access$4",
          "source": "Workbench.java:2211"
        },
        {
          "method": "org.eclipse.ui.internal.Workbench$4.run",
          "source": "Workbench.java:473"
        },
        {
          "method": "org.eclipse.core.databinding.observable.Realm.runWithDefault",
          "source": "Realm.java:288"
        },
        {
          "method": "org.eclipse.ui.internal.Workbench.createAndRunWorkbench",
          "source": "Workbench.java:468"
        },
        {
          "method": "org.eclipse.ui.PlatformUI.createAndRunWorkbench",
          "source": "PlatformUI.java:149"
        },
        {
          "method": "org.eclipse.ui.internal.ide.application.IDEApplication.start",
          "source": "IDEApplication.java:106"
        },
        {
          "method": "org.eclipse.equinox.internal.app.EclipseAppHandle.run",
          "source": "EclipseAppHandle.java:193"
        },
        {
          "method": "org.eclipse.core.runtime.internal.adaptor.EclipseAppLauncher.runApplication",
          "source": "EclipseAppLauncher.java:106"
        },
        {
          "method": "org.eclipse.core.runtime.internal.adaptor.EclipseAppLauncher.start",
          "source": "EclipseAppLauncher.java:76"
        },
        {
          "method": "org.eclipse.core.runtime.adaptor.EclipseStarter.run",
          "source": "EclipseStarter.java:362"
        },
        {
          "method": "org.eclipse.core.runtime.adaptor.EclipseStarter.run",
          "source": "EclipseStarter.java:175"
        },
        {
          "method": "sun.reflect.NativeMethodAccessorImpl.invoke0",
          "source": "Native Method"
        },
        {
          "method": "sun.reflect.NativeMethodAccessorImpl.invoke",
          "source": "NativeMethodAccessorImpl.java:39"
        },
        {
          "method": "sun.reflect.DelegatingMethodAccessorImpl.invoke",
          "source": "DelegatingMethodAccessorImpl.java:25"
        },
        {
          "method": "java.lang.reflect.Method.invoke",
          "source": "Method.java:597"
        },
        {
          "method": "org.eclipse.equinox.launcher.Main.invokeFramework",
          "source": "Main.java:561"
        },
        {
          "method": "org.eclipse.equinox.launcher.Main.basicRun",
          "source": "Main.java:501"
        },
        {
          "method": "org.eclipse.equinox.launcher.Main.run",
          "source": "Main.java:1239"
        },
        {
          "method": "org.eclipse.equinox.launcher.Main.main",
          "source": "Main.java:1215"
        }
      ],
      "number": 0,
      "commentIndex": 0,
      "bugId": "212341",
      "date": "2007-12-09T14:40:25+01:00",
      "product": "Platform",
      "component": "UI",
      "severity": "major"
    }
  ],
  "groupId": "212341",
  "bugId": "212341",
  "date": "2007-12-09T14:40:25+01:00",
  "product": "Platform",
  "component": "UI",
  "severity": "major"
}