{
  "comments": [
    "Exception in thread \"DLTK indexing\" java.lang.IllegalStateException: Workspace is closed.\n        at org.eclipse.core.resources.ResourcesPlugin.getWorkspace(ResourcesPlugin.java:326)\n        at org.eclipse.dltk.core.search.indexing.SourceIndexer.indexDocument(SourceIndexer.java:53)\n        at org.eclipse.dltk.core.search.DLTKSearchParticipant.indexDocument(DLTKSearchParticipant.java:68)\n        at org.eclipse.dltk.core.search.indexing.IndexManager.indexDocument(IndexManager.java:576)\n        at org.eclipse.dltk.core.search.indexing.IndexManager$1.execute(IndexManager.java:1020)\n        at org.eclipse.dltk.internal.core.search.processing.JobManager.run(JobManager.java:374)\n        at java.lang.Thread.run(Thread.java:619)"
  ],
  "commentCreationDates": [
    "2007-12-11T13:06:11+01:00"
  ],
  "traces": [
    {
      "exceptionType": "java.lang.IllegalStateException",
      "message": "Workspace is closed.",
      "elements": [
        {
          "method": "org.eclipse.core.resources.ResourcesPlugin.getWorkspace",
          "source": "ResourcesPlugin.java:326"
        },
        {
          "method": "org.eclipse.dltk.core.search.indexing.SourceIndexer.indexDocument",
          "source": "SourceIndexer.java:53"
        },
        {
          "method": "org.eclipse.dltk.core.search.DLTKSearchParticipant.indexDocument",
          "source": "DLTKSearchParticipant.java:68"
        },
        {
          "method": "org.eclipse.dltk.core.search.indexing.IndexManager.indexDocument",
          "source": "IndexManager.java:576"
        },
        {
          "method": "org.eclipse.dltk.core.search.indexing.IndexManager$1.execute",
          "source": "IndexManager.java:1020"
        },
        {
          "method": "org.eclipse.dltk.internal.core.search.processing.JobManager.run",
          "source": "JobManager.java:374"
        },
        {
          "method": "java.lang.Thread.run",
          "source": "Thread.java:619"
        }
      ],
      "number": 0,
      "commentIndex": 0,
      "bugId": "212536",
      "date": "2007-12-11T13:06:11+01:00",
      "product": "DLTK",
      "component": "Common",
      "severity": "minor"
    }
  ],
  "groupId": "212536",
  "bugId": "212536",
  "date": "2007-12-11T13:06:11+01:00",
  "product": "DLTK",
  "component": "Common",
  "severity": "minor"
}