{
  "comments": [
    "Build ID: CDT 4.0.2.200711280800\n\nSteps To Reproduce:\n1. Create a debug session using the attach type\n2. Debug\n3. Pick the executing GCC app from the process list\n\n\nMore information:\nYou will see part of the log below. Note that I get the NPE on each thread it tries to stack walk. Note that the GDB works fine (I can attach and debug via command line).\nThe console shows:\nattach 3144\n[Switching to thread 3144.0xb30]\n\nThe log subset is:\n\n!ENTRY org.eclipse.core.jobs 4 2 2007-12-07 16:09:52.660\n!MESSAGE An internal error occurred during: \"Label Job\".\n!STACK 0\njava.lang.NullPointerException\n        at\norg.eclipse.cdt.debug.internal.core.model.CStackFrame.getAddress(CStackFrame.java:578)\n        at\norg.eclipse.cdt.debug.internal.ui.CDebugModelPresentation.getStackFrameText(CDebugModelPresentation.java:703)\n        at\norg.eclipse.cdt.debug.internal.ui.CDebugModelPresentation.getBaseText(CDebugModelPresentation.java:374)\n        at\norg.eclipse.cdt.debug.internal.ui.CDebugModelPresentation.getText(CDebugModelPresentation.java:340)\n        at\norg.eclipse.debug.internal.ui.LazyModelPresentation.getText(LazyModelPresentation.java:163)\n        at\norg.eclipse.debug.internal.ui.DelegatingModelPresentation.getText(DelegatingModelPresentation.java:162)\n        at\norg.eclipse.debug.internal.ui.model.elements.DebugElementLabelProvider.getLabel(DebugElementLabelProvider.java:31)\n        at\norg.eclipse.debug.internal.ui.model.elements.ElementLabelProvider.retrieveLabel(ElementLabelProvider.java:201)\n        at\norg.eclipse.debug.internal.ui.model.elements.ElementLabelProvider$LabelUpdater.run(ElementLabelProvider.java:151)\n        at\norg.eclipse.debug.internal.ui.model.elements.ElementLabelProvider$LabelJob.run(ElementLabelProvider.java:70)\n        at org.eclipse.core.internal.jobs.Worker.run(Worker.java:55)\n\n!ENTRY org.eclipse.debug.core 4 120 2007-12-07 16:10:35.311\n!MESSAGE Error logged from Debug Core: \n!STACK 0\njava.io.IOException: Write end dead\n        at java.io.PipedInputStream.read(Unknown Source)\n        at java.io.PipedInputStream.read(Unknown Source)\n        at java.io.BufferedInputStream.read1(Unknown Source)\n        at java.io.BufferedInputStream.read(Unknown Source)\n        at java.io.FilterInputStream.read(Unknown Source)\n        at\norg.eclipse.debug.internal.core.OutputStreamMonitor.read(OutputStreamMonitor.java:144)\n        at\norg.eclipse.debug.internal.core.OutputStreamMonitor.access$1(OutputStreamMonitor.java:134)\n        at\norg.eclipse.debug.internal.core.OutputStreamMonitor$1.run(OutputStreamMonitor.java:207)\n        at java.lang.Thread.run(Unknown Source)\n\n!ENTRY org.eclipse.core.jobs 4 2 2007-12-07 16:10:35.651\n!MESSAGE An internal error occurred during: \"Label Job\".\n!STACK 0\njava.lang.NullPointerException\n        at\norg.eclipse.cdt.debug.internal.core.model.CStackFrame.getAddress(CStackFrame.java:578)\n        at\norg.eclipse.cdt.debug.internal.ui.CDebugModelPresentation.getStackFrameText(CDebugModelPresentation.java:703)\n        at\norg.eclipse.cdt.debug.internal.ui.CDebugModelPresentation.getBaseText(CDebugModelPresentation.java:374)\n        at\norg.eclipse.cdt.debug.internal.ui.CDebugModelPresentation.getText(CDebugModelPresentation.java:340)\n        at\norg.eclipse.debug.internal.ui.LazyModelPresentation.getText(LazyModelPresentation.java:163)\n        at\norg.eclipse.debug.internal.ui.DelegatingModelPresentation.getText(DelegatingModelPresentation.java:162)\n        at\norg.eclipse.debug.internal.ui.model.elements.DebugElementLabelProvider.getLabel(DebugElementLabelProvider.java:31)\n        at\norg.eclipse.debug.internal.ui.model.elements.ElementLabelProvider.retrieveLabel(ElementLabelProvider.java:201)\n        at\norg.eclipse.debug.internal.ui.model.elements.ElementLabelProvider$LabelUpdater.run(ElementLabelProvider.java:151)\n        at\norg.eclipse.debug.internal.ui.model.elements.ElementLabelProvider$LabelJob.run(ElementLabelProvider.java:70)\n        at org.eclipse.core.internal.jobs.Worker.run(Worker.java:55)\n\n!ENTRY org.eclipse.core.jobs 4 2 2007-12-07 16:10:36.182\n!MESSAGE An internal error occurred during: \"Label Job\".\n!STACK 0\njava.lang.NullPointerException\n        at\norg.eclipse.cdt.debug.internal.core.model.CStackFrame.getAddress(CStackFrame.java:578)\n        at\norg.eclipse.cdt.debug.internal.ui.CDebugModelPresentation.getStackFrameText(CDebugModelPresentation.java:703)\n        at\norg.eclipse.cdt.debug.internal.ui.CDebugModelPresentation.getBaseText(CDebugModelPresentation.java:374)\n        at\norg.eclipse.cdt.debug.internal.ui.CDebugModelPresentation.getText(CDebugModelPresentation.java:340)\n        at\norg.eclipse.debug.internal.ui.LazyModelPresentation.getText(LazyModelPresentation.java:163)\n        at\norg.eclipse.debug.internal.ui.DelegatingModelPresentation.getText(DelegatingModelPresentation.java:162)\n        at\norg.eclipse.debug.internal.ui.model.elements.DebugElementLabelProvider.getLabel(DebugElementLabelProvider.java:31)\n        at\norg.eclipse.debug.internal.ui.model.elements.ElementLabelProvider.retrieveLabel(ElementLabelProvider.java:201)\n        at\norg.eclipse.debug.internal.ui.model.elements.ElementLabelProvider$LabelUpdater.run(ElementLabelProvider.java:151)\n        at\norg.eclipse.debug.internal.ui.model.elements.ElementLabelProvider$LabelJob.run(ElementLabelProvider.java:70)\n        at org.eclipse.core.internal.jobs.Worker.run(Worker.java:55)\n\n!ENTRY org.eclipse.core.jobs 4 2 2007-12-07 16:10:36.222\n!MESSAGE An internal error occurred during: \"Label Job\".\n!STACK 0\njava.lang.NullPointerException\n        at\norg.eclipse.cdt.debug.internal.core.model.CStackFrame.getAddress(CStackFrame.java:578)\n        at\norg.eclipse.cdt.debug.internal.ui.CDebugModelPresentation.getStackFrameText(CDebugModelPresentation.java:703)\n        at\norg.eclipse.cdt.debug.internal.ui.CDebugModelPresentation.getBaseText(CDebugModelPresentation.java:374)\n        at\norg.eclipse.cdt.debug.internal.ui.CDebugModelPresentation.getText(CDebugModelPresentation.java:340)\n        at\norg.eclipse.debug.internal.ui.LazyModelPresentation.getText(LazyModelPresentation.java:163)\n        at\norg.eclipse.debug.internal.ui.DelegatingModelPresentation.getText(DelegatingModelPresentation.java:162)\n        at\norg.eclipse.debug.internal.ui.model.elements.DebugElementLabelProvider.getLabel(DebugElementLabelProvider.java:31)\n        at\norg.eclipse.debug.internal.ui.model.elements.ElementLabelProvider.retrieveLabel(ElementLabelProvider.java:201)\n        at\norg.eclipse.debug.internal.ui.model.elements.ElementLabelProvider$LabelUpdater.run(ElementLabelProvider.java:151)\n        at\norg.eclipse.debug.internal.ui.model.elements.ElementLabelProvider$LabelJob.run(ElementLabelProvider.java:70)\n        at org.eclipse.core.internal.jobs.Worker.run(Worker.java:55)",
    "I get the exceptions only if I leave the C/C++ Application field in the launch config empty.\nI think you need to enter the path to your executable.",
    "(In reply to comment #1)\n\u003e I get the exceptions only if I leave the C/C++ Application field in the launch\n\u003e config empty.\n\u003e I think you need to enter the path to your executable.\n\nOK, the problem is that it does this if the path is absolute (using the browse button). If I use the project relative path, it seems OK.\n\nNote that it makes no effort to fill this in if I try to create a new one. For the local case, it at least shows it as an error (no program). For attach case, it says nothing about it. In the previous version, I believe, it would fill it in or pop a dialog to ask which one.\n\n"
  ],
  "commentCreationDates": [
    "2007-12-11T18:04:42+01:00",
    "2007-12-12T11:23:59+01:00",
    "2007-12-14T00:02:17+01:00"
  ],
  "traces": [
    {
      "exceptionType": "java.lang.NullPointerException",
      "elements": [
        {
          "method": "org.eclipse.cdt.debug.internal.core.model.CStackFrame.getAddress",
          "source": "CStackFrame.java:578"
        },
        {
          "method": "org.eclipse.cdt.debug.internal.ui.CDebugModelPresentation.getStackFrameText",
          "source": "CDebugModelPresentation.java:703"
        },
        {
          "method": "org.eclipse.cdt.debug.internal.ui.CDebugModelPresentation.getBaseText",
          "source": "CDebugModelPresentation.java:374"
        },
        {
          "method": "org.eclipse.cdt.debug.internal.ui.CDebugModelPresentation.getText",
          "source": "CDebugModelPresentation.java:340"
        },
        {
          "method": "org.eclipse.debug.internal.ui.LazyModelPresentation.getText",
          "source": "LazyModelPresentation.java:163"
        },
        {
          "method": "org.eclipse.debug.internal.ui.DelegatingModelPresentation.getText",
          "source": "DelegatingModelPresentation.java:162"
        },
        {
          "method": "org.eclipse.debug.internal.ui.model.elements.DebugElementLabelProvider.getLabel",
          "source": "DebugElementLabelProvider.java:31"
        },
        {
          "method": "org.eclipse.debug.internal.ui.model.elements.ElementLabelProvider.retrieveLabel",
          "source": "ElementLabelProvider.java:201"
        },
        {
          "method": "org.eclipse.debug.internal.ui.model.elements.ElementLabelProvider$LabelUpdater.run",
          "source": "ElementLabelProvider.java:151"
        },
        {
          "method": "org.eclipse.debug.internal.ui.model.elements.ElementLabelProvider$LabelJob.run",
          "source": "ElementLabelProvider.java:70"
        },
        {
          "method": "org.eclipse.core.internal.jobs.Worker.run",
          "source": "Worker.java:55"
        }
      ],
      "number": 0,
      "commentIndex": 0,
      "bugId": "212632",
      "date": "2007-12-11T18:04:42+01:00",
      "product": "CDT",
      "component": "cdt-debug",
      "severity": "critical"
    },
    {
      "exceptionType": "java.io.IOException",
      "message": "Write end dead",
      "elements": [
        {
          "method": "java.io.PipedInputStream.read",
          "source": "Unknown Source"
        },
        {
          "method": "java.io.PipedInputStream.read",
          "source": "Unknown Source"
        },
        {
          "method": "java.io.BufferedInputStream.read1",
          "source": "Unknown Source"
        },
        {
          "method": "java.io.BufferedInputStream.read",
          "source": "Unknown Source"
        },
        {
          "method": "java.io.FilterInputStream.read",
          "source": "Unknown Source"
        },
        {
          "method": "org.eclipse.debug.internal.core.OutputStreamMonitor.read",
          "source": "OutputStreamMonitor.java:144"
        },
        {
          "method": "org.eclipse.debug.internal.core.OutputStreamMonitor.access$1",
          "source": "OutputStreamMonitor.java:134"
        },
        {
          "method": "org.eclipse.debug.internal.core.OutputStreamMonitor$1.run",
          "source": "OutputStreamMonitor.java:207"
        },
        {
          "method": "java.lang.Thread.run",
          "source": "Unknown Source"
        }
      ],
      "number": 1,
      "commentIndex": 0,
      "bugId": "212632",
      "date": "2007-12-11T18:04:42+01:00",
      "product": "CDT",
      "component": "cdt-debug",
      "severity": "critical"
    },
    {
      "exceptionType": "java.lang.NullPointerException",
      "elements": [
        {
          "method": "org.eclipse.cdt.debug.internal.core.model.CStackFrame.getAddress",
          "source": "CStackFrame.java:578"
        },
        {
          "method": "org.eclipse.cdt.debug.internal.ui.CDebugModelPresentation.getStackFrameText",
          "source": "CDebugModelPresentation.java:703"
        },
        {
          "method": "org.eclipse.cdt.debug.internal.ui.CDebugModelPresentation.getBaseText",
          "source": "CDebugModelPresentation.java:374"
        },
        {
          "method": "org.eclipse.cdt.debug.internal.ui.CDebugModelPresentation.getText",
          "source": "CDebugModelPresentation.java:340"
        },
        {
          "method": "org.eclipse.debug.internal.ui.LazyModelPresentation.getText",
          "source": "LazyModelPresentation.java:163"
        },
        {
          "method": "org.eclipse.debug.internal.ui.DelegatingModelPresentation.getText",
          "source": "DelegatingModelPresentation.java:162"
        },
        {
          "method": "org.eclipse.debug.internal.ui.model.elements.DebugElementLabelProvider.getLabel",
          "source": "DebugElementLabelProvider.java:31"
        },
        {
          "method": "org.eclipse.debug.internal.ui.model.elements.ElementLabelProvider.retrieveLabel",
          "source": "ElementLabelProvider.java:201"
        },
        {
          "method": "org.eclipse.debug.internal.ui.model.elements.ElementLabelProvider$LabelUpdater.run",
          "source": "ElementLabelProvider.java:151"
        },
        {
          "method": "org.eclipse.debug.internal.ui.model.elements.ElementLabelProvider$LabelJob.run",
          "source": "ElementLabelProvider.java:70"
        },
        {
          "method": "org.eclipse.core.internal.jobs.Worker.run",
          "source": "Worker.java:55"
        }
      ],
      "number": 2,
      "commentIndex": 0,
      "bugId": "212632",
      "date": "2007-12-11T18:04:42+01:00",
      "product": "CDT",
      "component": "cdt-debug",
      "severity": "critical"
    },
    {
      "exceptionType": "java.lang.NullPointerException",
      "elements": [
        {
          "method": "org.eclipse.cdt.debug.internal.core.model.CStackFrame.getAddress",
          "source": "CStackFrame.java:578"
        },
        {
          "method": "org.eclipse.cdt.debug.internal.ui.CDebugModelPresentation.getStackFrameText",
          "source": "CDebugModelPresentation.java:703"
        },
        {
          "method": "org.eclipse.cdt.debug.internal.ui.CDebugModelPresentation.getBaseText",
          "source": "CDebugModelPresentation.java:374"
        },
        {
          "method": "org.eclipse.cdt.debug.internal.ui.CDebugModelPresentation.getText",
          "source": "CDebugModelPresentation.java:340"
        },
        {
          "method": "org.eclipse.debug.internal.ui.LazyModelPresentation.getText",
          "source": "LazyModelPresentation.java:163"
        },
        {
          "method": "org.eclipse.debug.internal.ui.DelegatingModelPresentation.getText",
          "source": "DelegatingModelPresentation.java:162"
        },
        {
          "method": "org.eclipse.debug.internal.ui.model.elements.DebugElementLabelProvider.getLabel",
          "source": "DebugElementLabelProvider.java:31"
        },
        {
          "method": "org.eclipse.debug.internal.ui.model.elements.ElementLabelProvider.retrieveLabel",
          "source": "ElementLabelProvider.java:201"
        },
        {
          "method": "org.eclipse.debug.internal.ui.model.elements.ElementLabelProvider$LabelUpdater.run",
          "source": "ElementLabelProvider.java:151"
        },
        {
          "method": "org.eclipse.debug.internal.ui.model.elements.ElementLabelProvider$LabelJob.run",
          "source": "ElementLabelProvider.java:70"
        },
        {
          "method": "org.eclipse.core.internal.jobs.Worker.run",
          "source": "Worker.java:55"
        }
      ],
      "number": 3,
      "commentIndex": 0,
      "bugId": "212632",
      "date": "2007-12-11T18:04:42+01:00",
      "product": "CDT",
      "component": "cdt-debug",
      "severity": "critical"
    },
    {
      "exceptionType": "java.lang.NullPointerException",
      "elements": [
        {
          "method": "org.eclipse.cdt.debug.internal.core.model.CStackFrame.getAddress",
          "source": "CStackFrame.java:578"
        },
        {
          "method": "org.eclipse.cdt.debug.internal.ui.CDebugModelPresentation.getStackFrameText",
          "source": "CDebugModelPresentation.java:703"
        },
        {
          "method": "org.eclipse.cdt.debug.internal.ui.CDebugModelPresentation.getBaseText",
          "source": "CDebugModelPresentation.java:374"
        },
        {
          "method": "org.eclipse.cdt.debug.internal.ui.CDebugModelPresentation.getText",
          "source": "CDebugModelPresentation.java:340"
        },
        {
          "method": "org.eclipse.debug.internal.ui.LazyModelPresentation.getText",
          "source": "LazyModelPresentation.java:163"
        },
        {
          "method": "org.eclipse.debug.internal.ui.DelegatingModelPresentation.getText",
          "source": "DelegatingModelPresentation.java:162"
        },
        {
          "method": "org.eclipse.debug.internal.ui.model.elements.DebugElementLabelProvider.getLabel",
          "source": "DebugElementLabelProvider.java:31"
        },
        {
          "method": "org.eclipse.debug.internal.ui.model.elements.ElementLabelProvider.retrieveLabel",
          "source": "ElementLabelProvider.java:201"
        },
        {
          "method": "org.eclipse.debug.internal.ui.model.elements.ElementLabelProvider$LabelUpdater.run",
          "source": "ElementLabelProvider.java:151"
        },
        {
          "method": "org.eclipse.debug.internal.ui.model.elements.ElementLabelProvider$LabelJob.run",
          "source": "ElementLabelProvider.java:70"
        },
        {
          "method": "org.eclipse.core.internal.jobs.Worker.run",
          "source": "Worker.java:55"
        }
      ],
      "number": 4,
      "commentIndex": 0,
      "bugId": "212632",
      "date": "2007-12-11T18:04:42+01:00",
      "product": "CDT",
      "component": "cdt-debug",
      "severity": "critical"
    }
  ],
  "groupId": "212632",
  "bugId": "212632",
  "date": "2007-12-11T18:04:42+01:00",
  "product": "CDT",
  "component": "cdt-debug",
  "severity": "critical"
}