{
  "comments": [
    "Sometimes I get the following exception that hangs eclipse - I have to do a force quit. I cannot tell you under what circumstances this happens but it tends to happen when I switch a perspective.\n\n!ENTRY org.eclipse.ui 4 4 Jul 07, 2002 19:42:43.844\n!MESSAGE Unhandled exception caught in event loop.\n!ENTRY org.eclipse.ui 4 0 Jul 07, 2002 19:42:43.862\n!MESSAGE Widget is disposed\n!STACK 0\norg.eclipse.swt.SWTException: Widget is disposed\n        at org.eclipse.swt.SWT.error(SWT.java:2119)\n        at org.eclipse.swt.SWT.error(SWT.java:2051)\n        at org.eclipse.swt.widgets.Widget.error(Widget.java:311)\n        at org.eclipse.swt.widgets.Menu.getDisplay(Menu.java:338)\n        at org.eclipse.swt.widgets.Widget.isValidThread(Widget.java:470)\n        at org.eclipse.swt.widgets.Widget.checkWidget(Widget.java:237)\n        at org.eclipse.swt.widgets.Menu.getItems(Menu.java:427)\n        at org.eclipse.swt.widgets.Menu.releaseWidget(Menu.java:694)\n        at org.eclipse.swt.widgets.MenuItem.releaseWidget(MenuItem.java:368)\n        at org.eclipse.swt.widgets.Menu.releaseWidget(Menu.java:697)\n        at org.eclipse.swt.widgets.Widget.dispose(Widget.java:297)\n        at org.eclipse.swt.widgets.MenuItem.releaseChild(MenuItem.java:361)\n        at org.eclipse.swt.widgets.Widget.dispose(Widget.java:296)\n        at org.eclipse.jface.action.MenuManager.update(MenuManager.java:502)\n        at org.eclipse.jface.action.MenuManager.updateAll(MenuManager.java:577)\n        at org.eclipse.ui.internal.WorkbenchWindow.updateActionBars(WorkbenchWindow.java:1402)\n        at org.eclipse.ui.internal.WorkbenchWindow.updateActionSets(WorkbenchWindow.java:1420)\n        at org.eclipse.ui.internal.WorkbenchPage.setPerspective(WorkbenchPage.java:2135)\n        at org.eclipse.ui.internal.WorkbenchPage.busySetPerspective(WorkbenchPage.java:531)\n        at org.eclipse.ui.internal.WorkbenchPage.access$6(WorkbenchPage.java:519)\n        at org.eclipse.ui.internal.WorkbenchPage$10.run(WorkbenchPage.java:2179)\n        at org.eclipse.swt.custom.BusyIndicator.showWhile(BusyIndicator.java:66)\n        at org.eclipse.ui.internal.WorkbenchPage.setPerspective(WorkbenchPage.java:2177)\n        at org.eclipse.ui.internal.SetPagePerspectiveAction.run(SetPagePerspectiveAction.java:66)\n        at org.eclipse.jface.action.Action.runWithEvent(Action.java:749)\n        at org.eclipse.jface.action.ActionContributionItem.handleWidgetSelection(ActionContributionItem.java:407)\n        at org.eclipse.jface.action.ActionContributionItem.handleWidgetEvent(ActionContributionItem.java:361)\n        at org.eclipse.jface.action.ActionContributionItem.access$0(ActionContributionItem.java:352)\n        at org.eclipse.jface.action.ActionContributionItem$ActionListener.handleEvent(ActionContributionItem.java:47)\n        at org.eclipse.swt.widgets.EventTable.sendEvent(EventTable.java:77)\n        at org.eclipse.swt.widgets.Widget.notifyListeners(Widget.java:519)\n        at org.eclipse.swt.widgets.Display.runDeferredEvents(Display.java:1351)\n        at org.eclipse.swt.widgets.Display.readAndDispatch(Display.java:1189)\n        at org.eclipse.ui.internal.Workbench.runEventLoop(Workbench.java:1177)\n        at org.eclipse.ui.internal.Workbench.run(Workbench.java:1160)\n        at org.eclipse.core.internal.boot.InternalBootLoader.run(InternalBootLoader.java:775)\n        at org.eclipse.core.boot.BootLoader.run(BootLoader.java:462)\n        at java.lang.reflect.Method.invoke(Native Method)\n        at org.eclipse.core.launcher.Main.basicRun(Main.java:248)\n        at org.eclipse.core.launcher.Main.run(Main.java:698)\n        at org.eclipse.core.launcher.Main.main(Main.java:534)\n        at java.lang.reflect.Method.invoke(Native Method)\n        at com.apple.buckyball.app.LaunchRunner.run(LaunchRunner.java:82)\n        at com.apple.buckyball.app.LaunchRunner.callMain(LaunchRunner.java:44)\n        at com.apple.buckyball.app.CarbonLibApp.main(CarbonLibApp.java:76)",
    "ok, it seems that doing just about anything in the resource perspective causes this bug. I have tried closing views, resizing columns in the task view, expanding/collapsing nodes in the Navigator tree - all result in the exception.\n\nI tried closing the perspective and adding it back again but it didn\u0027t help.\n\nThis bug only surfaced after using Eclipse for a few days so it wasn\u0027t something that manifested itself immediately.",
    "I cannot reproduce this problem in the latest builds. Can you?",
    "Hi Andre,\nI haven\u0027t had much opportunity to try the latest build in earnest but so far I haven\u0027t seen it. Perhaps its fixed?\n\nChanning",
    "I haven\u0027t had a repeat of this bug so I believe it must be fixed.",
    "Closed."
  ],
  "commentCreationDates": [
    "2002-07-07T20:38:33+02:00",
    "2002-07-07T21:04:35+02:00",
    "2002-08-05T13:02:47+02:00",
    "2002-08-07T00:49:43+02:00",
    "2002-09-25T07:45:20+02:00",
    "2002-09-25T09:47:38+02:00"
  ],
  "traces": [
    {
      "exceptionType": "org.eclipse.swt.SWTException",
      "message": "Widget is disposed",
      "elements": [
        {
          "method": "org.eclipse.swt.SWT.error",
          "source": "SWT.java:2119"
        },
        {
          "method": "org.eclipse.swt.SWT.error",
          "source": "SWT.java:2051"
        },
        {
          "method": "org.eclipse.swt.widgets.Widget.error",
          "source": "Widget.java:311"
        },
        {
          "method": "org.eclipse.swt.widgets.Menu.getDisplay",
          "source": "Menu.java:338"
        },
        {
          "method": "org.eclipse.swt.widgets.Widget.isValidThread",
          "source": "Widget.java:470"
        },
        {
          "method": "org.eclipse.swt.widgets.Widget.checkWidget",
          "source": "Widget.java:237"
        },
        {
          "method": "org.eclipse.swt.widgets.Menu.getItems",
          "source": "Menu.java:427"
        },
        {
          "method": "org.eclipse.swt.widgets.Menu.releaseWidget",
          "source": "Menu.java:694"
        },
        {
          "method": "org.eclipse.swt.widgets.MenuItem.releaseWidget",
          "source": "MenuItem.java:368"
        },
        {
          "method": "org.eclipse.swt.widgets.Menu.releaseWidget",
          "source": "Menu.java:697"
        },
        {
          "method": "org.eclipse.swt.widgets.Widget.dispose",
          "source": "Widget.java:297"
        },
        {
          "method": "org.eclipse.swt.widgets.MenuItem.releaseChild",
          "source": "MenuItem.java:361"
        },
        {
          "method": "org.eclipse.swt.widgets.Widget.dispose",
          "source": "Widget.java:296"
        },
        {
          "method": "org.eclipse.jface.action.MenuManager.update",
          "source": "MenuManager.java:502"
        },
        {
          "method": "org.eclipse.jface.action.MenuManager.updateAll",
          "source": "MenuManager.java:577"
        },
        {
          "method": "org.eclipse.ui.internal.WorkbenchWindow.updateActionBars",
          "source": "WorkbenchWindow.java:1402"
        },
        {
          "method": "org.eclipse.ui.internal.WorkbenchWindow.updateActionSets",
          "source": "WorkbenchWindow.java:1420"
        },
        {
          "method": "org.eclipse.ui.internal.WorkbenchPage.setPerspective",
          "source": "WorkbenchPage.java:2135"
        },
        {
          "method": "org.eclipse.ui.internal.WorkbenchPage.busySetPerspective",
          "source": "WorkbenchPage.java:531"
        },
        {
          "method": "org.eclipse.ui.internal.WorkbenchPage.access$6",
          "source": "WorkbenchPage.java:519"
        },
        {
          "method": "org.eclipse.ui.internal.WorkbenchPage$10.run",
          "source": "WorkbenchPage.java:2179"
        },
        {
          "method": "org.eclipse.swt.custom.BusyIndicator.showWhile",
          "source": "BusyIndicator.java:66"
        },
        {
          "method": "org.eclipse.ui.internal.WorkbenchPage.setPerspective",
          "source": "WorkbenchPage.java:2177"
        },
        {
          "method": "org.eclipse.ui.internal.SetPagePerspectiveAction.run",
          "source": "SetPagePerspectiveAction.java:66"
        },
        {
          "method": "org.eclipse.jface.action.Action.runWithEvent",
          "source": "Action.java:749"
        },
        {
          "method": "org.eclipse.jface.action.ActionContributionItem.handleWidgetSelection",
          "source": "ActionContributionItem.java:407"
        },
        {
          "method": "org.eclipse.jface.action.ActionContributionItem.handleWidgetEvent",
          "source": "ActionContributionItem.java:361"
        },
        {
          "method": "org.eclipse.jface.action.ActionContributionItem.access$0",
          "source": "ActionContributionItem.java:352"
        },
        {
          "method": "org.eclipse.jface.action.ActionContributionItem$ActionListener.handleEvent",
          "source": "ActionContributionItem.java:47"
        },
        {
          "method": "org.eclipse.swt.widgets.EventTable.sendEvent",
          "source": "EventTable.java:77"
        },
        {
          "method": "org.eclipse.swt.widgets.Widget.notifyListeners",
          "source": "Widget.java:519"
        },
        {
          "method": "org.eclipse.swt.widgets.Display.runDeferredEvents",
          "source": "Display.java:1351"
        },
        {
          "method": "org.eclipse.swt.widgets.Display.readAndDispatch",
          "source": "Display.java:1189"
        },
        {
          "method": "org.eclipse.ui.internal.Workbench.runEventLoop",
          "source": "Workbench.java:1177"
        },
        {
          "method": "org.eclipse.ui.internal.Workbench.run",
          "source": "Workbench.java:1160"
        },
        {
          "method": "org.eclipse.core.internal.boot.InternalBootLoader.run",
          "source": "InternalBootLoader.java:775"
        },
        {
          "method": "org.eclipse.core.boot.BootLoader.run",
          "source": "BootLoader.java:462"
        },
        {
          "method": "java.lang.reflect.Method.invoke",
          "source": "Native Method"
        },
        {
          "method": "org.eclipse.core.launcher.Main.basicRun",
          "source": "Main.java:248"
        },
        {
          "method": "org.eclipse.core.launcher.Main.run",
          "source": "Main.java:698"
        },
        {
          "method": "org.eclipse.core.launcher.Main.main",
          "source": "Main.java:534"
        },
        {
          "method": "java.lang.reflect.Method.invoke",
          "source": "Native Method"
        },
        {
          "method": "com.apple.buckyball.app.LaunchRunner.run",
          "source": "LaunchRunner.java:82"
        },
        {
          "method": "com.apple.buckyball.app.LaunchRunner.callMain",
          "source": "LaunchRunner.java:44"
        },
        {
          "method": "com.apple.buckyball.app.CarbonLibApp.main",
          "source": "CarbonLibApp.java:76"
        }
      ],
      "number": 0,
      "commentIndex": 0,
      "bugId": "21287",
      "date": "2002-07-07T20:38:33+02:00",
      "product": "Platform",
      "component": "SWT",
      "severity": "critical"
    }
  ],
  "groupId": "21287",
  "bugId": "21287",
  "date": "2002-07-07T20:38:33+02:00",
  "product": "Platform",
  "component": "SWT",
  "severity": "critical"
}