{
  "comments": [
    "If I create the following code:\n\nimport junit.framework.TestCase;\n\npublic class JUnitInnerClassIssue \n{\n    public static class InnerTestCase extends TestCase \n    {\t\t\n        public static void main(String[] args)\n        {\n            junit.swingui.TestRunner.run( InnerTestCase.class );\t\n        }\n\t\t\t\n        public InnerTestCase(String name) \n        {\n            super(name);\n        }\n\t\t\n        public void testFail() \n        {\n            fail();\n        }\n    }\n}\n\nI can use the standalone JUnit test runner to run the test by setting up a Java\nApplication configuration with Main Class set to\n\"JUnitInnerClassIssue$InnerTestCase\".\n\nHowever, if I try to run the same class under a JUnit configuration (setting\nTest Class to \"JUnitInnerClassIssue$InnerTestCase\") I get an error from Eclipse\nstating: \"Test type does not exist\"\n\nThe error from the log looks as follows:\n\n!SESSION Jul 24, 2002 10:16:42.379 ---------------------------------------------\njava.version\u003d1.4.0_01\njava.vendor\u003dSun Microsystems Inc.\nBootLoader constants: OS\u003dwin32, ARCH\u003dx86, WS\u003dwin32, NL\u003den_GB\nCommand-line arguments: -os win32 -ws win32 -arch x86 -install file:D:/eclipse/\n!ENTRY org.eclipse.debug.ui 4 120 Jul 24, 2002 10:16:42.379\n!MESSAGE Error logged from Debug UI: \n!STACK 1\norg.eclipse.core.runtime.CoreException: Test type does not exist\n\tat\norg.eclipse.jdt.internal.junit.launcher.JUnitBaseLaunchConfiguration.abort(JUnitBaseLaunchConfiguration.java:128)\n\tat\norg.eclipse.jdt.internal.junit.launcher.JUnitBaseLaunchConfiguration.getTestType(JUnitBaseLaunchConfiguration.java:113)\n\tat\norg.eclipse.jdt.internal.junit.launcher.JUnitBaseLaunchConfiguration.launch(JUnitBaseLaunchConfiguration.java:60)\n\tat\norg.eclipse.debug.internal.core.LaunchConfiguration.launch(LaunchConfiguration.java:136)\n\tat\norg.eclipse.debug.internal.ui.launchConfigurations.LaunchConfigurationDialog$10.run(LaunchConfigurationDialog.java:2299)\n\tat\norg.eclipse.jface.operation.ModalContext$ModalContextThread.run(ModalContext.java:98)\n!ENTRY org.eclipse.jdt.junit 4 101 Jul 24, 2002 10:16:42.395\n!MESSAGE Test type does not exist\n\nThanks, let me know if you need any more info.",
    "I encountered the same problem.\n\nThis is a duplicate of bug http://dev.eclipse.org/bugs/show_bug.cgi?id\u003d11035\n",
    "tried to reproduce in 200210171646 but it works for me.\n\n11035 is a different problem and is still open\n\n",
    "I also tried and now it works (with M2)."
  ],
  "commentCreationDates": [
    "2002-07-24T11:09:05+02:00",
    "2002-10-19T05:22:58+02:00",
    "2002-10-19T21:13:53+02:00",
    "2002-10-20T01:41:07+02:00"
  ],
  "traces": [
    {
      "exceptionType": "org.eclipse.core.runtime.CoreException",
      "message": "Test type does not exist",
      "elements": [
        {
          "method": "org.eclipse.jdt.internal.junit.launcher.JUnitBaseLaunchConfiguration.abort",
          "source": "JUnitBaseLaunchConfiguration.java:128"
        },
        {
          "method": "org.eclipse.jdt.internal.junit.launcher.JUnitBaseLaunchConfiguration.getTestType",
          "source": "JUnitBaseLaunchConfiguration.java:113"
        },
        {
          "method": "org.eclipse.jdt.internal.junit.launcher.JUnitBaseLaunchConfiguration.launch",
          "source": "JUnitBaseLaunchConfiguration.java:60"
        },
        {
          "method": "org.eclipse.debug.internal.core.LaunchConfiguration.launch",
          "source": "LaunchConfiguration.java:136"
        },
        {
          "method": "org.eclipse.debug.internal.ui.launchConfigurations.LaunchConfigurationDialog$10.run",
          "source": "LaunchConfigurationDialog.java:2299"
        },
        {
          "method": "org.eclipse.jface.operation.ModalContext$ModalContextThread.run",
          "source": "ModalContext.java:98"
        }
      ],
      "number": 0,
      "commentIndex": 0,
      "bugId": "21844",
      "date": "2002-07-24T11:09:05+02:00",
      "product": "JDT",
      "component": "UI",
      "severity": "normal"
    }
  ],
  "groupId": "21844",
  "bugId": "21844",
  "date": "2002-07-24T11:09:05+02:00",
  "product": "JDT",
  "component": "UI",
  "severity": "normal"
}