{
  "comments": [
    "\u003e After updating to the latest gtk packages from gtk.org I got a link error\n\u003e concerning the XFree Xft library. Eclipse 2.0 release also stopped\n\u003e working...",
    "I believe I have seen this and I don\u0027t think it is our problem. Try going\nback to an older version of the pango library (pango 1.0.1-1gtk).",
    "Just to give a little extra info, this is the result of trying to start the\nlatest integration build against a new pango (pango-1.0.3):\n\n[wouter@om eclipse-SDK-I20020806-linux-gtk]$ ./eclipse \njava.lang.UnsatisfiedLinkError:\n/home/wouter/opt/eclipse-SDK-I20020806-linux-gtk/plugins/org.eclipse.swt.gtk_2.0.0/os/linux/x86/libswt-pi-gtk-2103.so:\n/usr/lib/libpangoxft-1.0.so.0: undefined symbol: FT_Seek_Stream\n        at java.lang.ClassLoader$NativeLibrary.load(Native Method)\n        at java.lang.ClassLoader.loadLibrary0(ClassLoader.java:1473)\n        at java.lang.ClassLoader.loadLibrary(ClassLoader.java:1381)\n        at java.lang.Runtime.loadLibrary0(Runtime.java:788)\n        at java.lang.System.loadLibrary(System.java:832)\n        at org.eclipse.swt.internal.Library.loadLibrary(Library.java:104)\n        at org.eclipse.swt.internal.gtk.OS.\u003cclinit\u003e(OS.java:19)\n        at org.eclipse.swt.widgets.Display.createDisplay(Display.java:404)\n        at org.eclipse.swt.widgets.Display.create(Display.java:398)\n        at org.eclipse.swt.graphics.Device.\u003cinit\u003e(Device.java:103)\n        at org.eclipse.swt.widgets.Display.\u003cinit\u003e(Display.java:284)\n        at org.eclipse.swt.widgets.Display.\u003cinit\u003e(Display.java:280)\n        at org.eclipse.ui.internal.Workbench.run(Workbench.java:1220)\n        at\norg.eclipse.core.internal.boot.InternalBootLoader.run(InternalBootLoader.java:775)\n        at org.eclipse.core.boot.BootLoader.run(BootLoader.java:462)\n        at sun.reflect.NativeMethodAccessorImpl.invoke0(Native Method)\n        at\nsun.reflect.NativeMethodAccessorImpl.invoke(NativeMethodAccessorImpl.java:39)\n        at\nsun.reflect.DelegatingMethodAccessorImpl.invoke(DelegatingMethodAccessorImpl.java:25)\n        at java.lang.reflect.Method.invoke(Method.java:324)\n        at org.eclipse.core.launcher.Main.basicRun(Main.java:248)\n        at org.eclipse.core.launcher.Main.run(Main.java:698)\n        at org.eclipse.core.launcher.Main.main(Main.java:534)\n[wouter@om eclipse-SDK-I20020806-linux-gtk]$ ",
    "If you want to use pango greater than 1.0.1, you need to upgrade\nyour freetype library as well. See Bug#23178 for more information.",
    "\n\n*** This bug has been marked as a duplicate of 23178 ***",
    "*** Bug 48346 has been marked as a duplicate of this bug. ***",
    "*** Bug 40809 has been marked as a duplicate of this bug. ***"
  ],
  "commentCreationDates": [
    "2002-07-31T15:31:39+02:00",
    "2002-07-31T16:44:50+02:00",
    "2002-08-07T11:52:09+02:00",
    "2002-09-06T00:06:33+02:00",
    "2002-09-06T00:07:01+02:00",
    "2003-12-09T19:31:28+01:00",
    "2004-05-25T22:13:53+02:00"
  ],
  "traces": [
    {
      "exceptionType": "java.lang.UnsatisfiedLinkError",
      "message": "/home/wouter/opt/eclipse-SDK-I20020806-linux-gtk/plugins/org.eclipse.swt.gtk_2.0.0/os/linux/x86/libswt-pi-gtk-2103.so: /usr/lib/libpangoxft-1.0.so.0: undefined symbol: FT_Seek_Stream",
      "elements": [
        {
          "method": "java.lang.ClassLoader$NativeLibrary.load",
          "source": "Native Method"
        },
        {
          "method": "java.lang.ClassLoader.loadLibrary0",
          "source": "ClassLoader.java:1473"
        },
        {
          "method": "java.lang.ClassLoader.loadLibrary",
          "source": "ClassLoader.java:1381"
        },
        {
          "method": "java.lang.Runtime.loadLibrary0",
          "source": "Runtime.java:788"
        },
        {
          "method": "java.lang.System.loadLibrary",
          "source": "System.java:832"
        },
        {
          "method": "org.eclipse.swt.internal.Library.loadLibrary",
          "source": "Library.java:104"
        },
        {
          "method": "org.eclipse.swt.internal.gtk.OS.\u003cclinit\u003e",
          "source": "OS.java:19"
        },
        {
          "method": "org.eclipse.swt.widgets.Display.createDisplay",
          "source": "Display.java:404"
        },
        {
          "method": "org.eclipse.swt.widgets.Display.create",
          "source": "Display.java:398"
        },
        {
          "method": "org.eclipse.swt.graphics.Device.\u003cinit\u003e",
          "source": "Device.java:103"
        },
        {
          "method": "org.eclipse.swt.widgets.Display.\u003cinit\u003e",
          "source": "Display.java:284"
        },
        {
          "method": "org.eclipse.swt.widgets.Display.\u003cinit\u003e",
          "source": "Display.java:280"
        },
        {
          "method": "org.eclipse.ui.internal.Workbench.run",
          "source": "Workbench.java:1220"
        },
        {
          "method": "org.eclipse.core.internal.boot.InternalBootLoader.run",
          "source": "InternalBootLoader.java:775"
        },
        {
          "method": "org.eclipse.core.boot.BootLoader.run",
          "source": "BootLoader.java:462"
        },
        {
          "method": "sun.reflect.NativeMethodAccessorImpl.invoke0",
          "source": "Native Method"
        },
        {
          "method": "sun.reflect.NativeMethodAccessorImpl.invoke",
          "source": "NativeMethodAccessorImpl.java:39"
        },
        {
          "method": "sun.reflect.DelegatingMethodAccessorImpl.invoke",
          "source": "DelegatingMethodAccessorImpl.java:25"
        },
        {
          "method": "java.lang.reflect.Method.invoke",
          "source": "Method.java:324"
        },
        {
          "method": "org.eclipse.core.launcher.Main.basicRun",
          "source": "Main.java:248"
        },
        {
          "method": "org.eclipse.core.launcher.Main.run",
          "source": "Main.java:698"
        },
        {
          "method": "org.eclipse.core.launcher.Main.main",
          "source": "Main.java:534"
        }
      ],
      "number": 0,
      "commentIndex": 2,
      "bugId": "22074",
      "duplicateId": "23178",
      "date": "2002-08-07T11:52:09+02:00",
      "product": "Platform",
      "component": "SWT",
      "severity": "normal"
    }
  ],
  "groupId": "23178",
  "bugId": "22074",
  "duplicateId": "23178",
  "date": "2002-07-31T15:31:39+02:00",
  "product": "Platform",
  "component": "SWT",
  "severity": "normal"
}