{
  "comments": [
    "!ENTRY org.eclipse.core.runtime 4 2 Aug 07, 2002 10:15:32.810\n!MESSAGE Problems occurred when invoking code from plug-in:\n\"org.eclipse.core.runtime\".\n!STACK 0\njava.lang.ClassCastException: org.apache.xerces.jaxp.DocumentBuilderFactoryImpl\n        at\njavax.xml.parsers.DocumentBuilderFactory.newInstance(DocumentBuilderFactory.java:139)\n        at\norg.eclipse.core.internal.resources.ModelObjectReader.read(ModelObjectReader.java:85)\n        at\norg.eclipse.core.internal.resources.ModelObjectReader.read(ModelObjectReader.java:107)\n        at\norg.eclipse.core.internal.resources.LocalMetaArea.readWorkspace(LocalMetaArea.java:241)\n        at org.eclipse.core.internal.resources.Workspace.open(Workspace.java:1263)\n        at\norg.eclipse.core.resources.ResourcesPlugin.startup(ResourcesPlugin.java:201)\n        at\norg.eclipse.core.internal.plugins.PluginDescriptor$1.run(PluginDescriptor.java:694)\n        at\norg.eclipse.core.internal.runtime.InternalPlatform.run(InternalPlatform.java:831)\n        at\norg.eclipse.core.internal.plugins.PluginDescriptor.internalDoPluginActivation(PluginDescriptor.java:706)\n        at\norg.eclipse.core.internal.plugins.PluginDescriptor.doPluginActivation(PluginDescriptor.java:186)\n        at\norg.eclipse.core.internal.plugins.PluginClassLoader.activatePlugin(PluginClassLoader.java:58)\n        at\norg.eclipse.core.internal.plugins.PluginClassLoader.findClassParentsSelf(PluginClassLoader.java:136)\n        at\norg.eclipse.core.internal.boot.DelegatingURLClassLoader.loadClass(DelegatingURLClassLoader.java:750)\n        at\norg.eclipse.core.internal.boot.DelegatingURLClassLoader.access$0(DelegatingURLClassLoader.java:744)\n        at\norg.eclipse.core.internal.boot.DelegatingURLClassLoader$DelegateLoader.loadClass(DelegatingURLClassLoader.java:70)\n        at\norg.eclipse.core.internal.boot.DelegatingURLClassLoader.findClassPrerequisites(DelegatingURLClassLoader.java:429)\n        at\norg.eclipse.core.internal.boot.DelegatingURLClassLoader.loadClass(DelegatingURLClassLoader.java:758)\n        at\norg.eclipse.core.internal.boot.DelegatingURLClassLoader.loadClass(DelegatingURLClassLoader.java:730)\n        at java.lang.ClassLoader.loadClass(ClassLoader.java:250)\n        at java.lang.ClassLoader.loadClassInternal(ClassLoader.java:310)\n        at java.lang.Class.newInstance0(Native Method)\n        at java.lang.Class.newInstance(Class.java:232)\n        at\norg.eclipse.core.internal.plugins.PluginDescriptor.createExecutableExtension(PluginDescriptor.java:138)\n        at\norg.eclipse.core.internal.plugins.PluginDescriptor.createExecutableExtension(PluginDescriptor.java:167)\n        at\norg.eclipse.core.internal.plugins.ConfigurationElement.createExecutableExtension(ConfigurationElement.java:102)\n        at\norg.eclipse.core.internal.runtime.InternalPlatform.loaderGetRunnable(InternalPlatform.java:463)\n        at java.lang.reflect.Method.invoke(Native Method)\n        at\norg.eclipse.core.internal.boot.InternalBootLoader.getRunnable(InternalBootLoader.java:440)\n        at\norg.eclipse.core.internal.boot.InternalBootLoader.run(InternalBootLoader.java:771)\n        at org.eclipse.core.boot.BootLoader.run(BootLoader.java:462)\n        at java.lang.reflect.Method.invoke(Native Method)\n        at org.eclipse.core.launcher.Main.basicRun(Main.java:248)\n        at org.eclipse.core.launcher.Main.run(Main.java:698)\n        at org.eclipse.core.launcher.Main.main(Main.java:534)\n!ENTRY org.eclipse.core.runtime 4 2 Aug 07, 2002 10:15:32.823\n!MESSAGE Plug-in \"org.eclipse.ui\" was unable to instantiate class\n\"org.eclipse.ui.internal.Workbench\".\n!STACK 0",
    "\n\n*** This bug has been marked as a duplicate of 21744 ***",
    "*** Bug 24777 has been marked as a duplicate of this bug. ***"
  ],
  "commentCreationDates": [
    "2002-08-07T10:42:31+02:00",
    "2002-08-07T14:34:45+02:00",
    "2002-10-15T15:47:20+02:00"
  ],
  "traces": [
    {
      "exceptionType": "java.lang.ClassCastException",
      "message": "org.apache.xerces.jaxp.DocumentBuilderFactoryImpl",
      "elements": [
        {
          "method": "javax.xml.parsers.DocumentBuilderFactory.newInstance",
          "source": "DocumentBuilderFactory.java:139"
        },
        {
          "method": "org.eclipse.core.internal.resources.ModelObjectReader.read",
          "source": "ModelObjectReader.java:85"
        },
        {
          "method": "org.eclipse.core.internal.resources.ModelObjectReader.read",
          "source": "ModelObjectReader.java:107"
        },
        {
          "method": "org.eclipse.core.internal.resources.LocalMetaArea.readWorkspace",
          "source": "LocalMetaArea.java:241"
        },
        {
          "method": "org.eclipse.core.internal.resources.Workspace.open",
          "source": "Workspace.java:1263"
        },
        {
          "method": "org.eclipse.core.resources.ResourcesPlugin.startup",
          "source": "ResourcesPlugin.java:201"
        },
        {
          "method": "org.eclipse.core.internal.plugins.PluginDescriptor$1.run",
          "source": "PluginDescriptor.java:694"
        },
        {
          "method": "org.eclipse.core.internal.runtime.InternalPlatform.run",
          "source": "InternalPlatform.java:831"
        },
        {
          "method": "org.eclipse.core.internal.plugins.PluginDescriptor.internalDoPluginActivation",
          "source": "PluginDescriptor.java:706"
        },
        {
          "method": "org.eclipse.core.internal.plugins.PluginDescriptor.doPluginActivation",
          "source": "PluginDescriptor.java:186"
        },
        {
          "method": "org.eclipse.core.internal.plugins.PluginClassLoader.activatePlugin",
          "source": "PluginClassLoader.java:58"
        },
        {
          "method": "org.eclipse.core.internal.plugins.PluginClassLoader.findClassParentsSelf",
          "source": "PluginClassLoader.java:136"
        },
        {
          "method": "org.eclipse.core.internal.boot.DelegatingURLClassLoader.loadClass",
          "source": "DelegatingURLClassLoader.java:750"
        },
        {
          "method": "org.eclipse.core.internal.boot.DelegatingURLClassLoader.access$0",
          "source": "DelegatingURLClassLoader.java:744"
        },
        {
          "method": "org.eclipse.core.internal.boot.DelegatingURLClassLoader$DelegateLoader.loadClass",
          "source": "DelegatingURLClassLoader.java:70"
        },
        {
          "method": "org.eclipse.core.internal.boot.DelegatingURLClassLoader.findClassPrerequisites",
          "source": "DelegatingURLClassLoader.java:429"
        },
        {
          "method": "org.eclipse.core.internal.boot.DelegatingURLClassLoader.loadClass",
          "source": "DelegatingURLClassLoader.java:758"
        },
        {
          "method": "org.eclipse.core.internal.boot.DelegatingURLClassLoader.loadClass",
          "source": "DelegatingURLClassLoader.java:730"
        },
        {
          "method": "java.lang.ClassLoader.loadClass",
          "source": "ClassLoader.java:250"
        },
        {
          "method": "java.lang.ClassLoader.loadClassInternal",
          "source": "ClassLoader.java:310"
        },
        {
          "method": "java.lang.Class.newInstance0",
          "source": "Native Method"
        },
        {
          "method": "java.lang.Class.newInstance",
          "source": "Class.java:232"
        },
        {
          "method": "org.eclipse.core.internal.plugins.PluginDescriptor.createExecutableExtension",
          "source": "PluginDescriptor.java:138"
        },
        {
          "method": "org.eclipse.core.internal.plugins.PluginDescriptor.createExecutableExtension",
          "source": "PluginDescriptor.java:167"
        },
        {
          "method": "org.eclipse.core.internal.plugins.ConfigurationElement.createExecutableExtension",
          "source": "ConfigurationElement.java:102"
        },
        {
          "method": "org.eclipse.core.internal.runtime.InternalPlatform.loaderGetRunnable",
          "source": "InternalPlatform.java:463"
        },
        {
          "method": "java.lang.reflect.Method.invoke",
          "source": "Native Method"
        },
        {
          "method": "org.eclipse.core.internal.boot.InternalBootLoader.getRunnable",
          "source": "InternalBootLoader.java:440"
        },
        {
          "method": "org.eclipse.core.internal.boot.InternalBootLoader.run",
          "source": "InternalBootLoader.java:771"
        },
        {
          "method": "org.eclipse.core.boot.BootLoader.run",
          "source": "BootLoader.java:462"
        },
        {
          "method": "java.lang.reflect.Method.invoke",
          "source": "Native Method"
        },
        {
          "method": "org.eclipse.core.launcher.Main.basicRun",
          "source": "Main.java:248"
        },
        {
          "method": "org.eclipse.core.launcher.Main.run",
          "source": "Main.java:698"
        },
        {
          "method": "org.eclipse.core.launcher.Main.main",
          "source": "Main.java:534"
        }
      ],
      "number": 0,
      "commentIndex": 0,
      "bugId": "22225",
      "duplicateId": "21744",
      "date": "2002-08-07T10:42:31+02:00",
      "product": "Platform",
      "component": "Resources",
      "severity": "blocker"
    }
  ],
  "groupId": "21262",
  "bugId": "22225",
  "duplicateId": "21744",
  "date": "2002-08-07T10:42:31+02:00",
  "product": "Platform",
  "component": "Resources",
  "severity": "blocker"
}