{
  "comments": [
    "Build: 0826-2.0.1\n\nI got the following walkback during a debug session.  I have not been able to \nreproduce the problem.\n\njava.lang.NullPointerException\n        at \norg.eclipse.jdi.internal.ReferenceTypeImpl.fields(ReferenceTypeImpl.java:541)\n        at \norg.eclipse.jdi.internal.ReferenceTypeImpl.allFields(ReferenceTypeImpl.java:403)\n        \nat \norg.eclipse.jdi.internal.ReferenceTypeImpl.allFields(ReferenceTypeImpl.java:417)\n        \nat \norg.eclipse.jdt.internal.debug.core.model.JDIValue.getVariables0(JDIValue.java:204)\n \n       at \norg.eclipse.jdt.internal.debug.core.model.JDIStackFrame.findVariable(JDIStackFrame.java:574)\n \n       at \norg.eclipse.jdt.internal.debug.core.model.JDIThread.findVariable(JDIThread.java:1401)\n \n       at \norg.eclipse.jdt.internal.debug.core.model.JDIDebugTarget.findVariable(JDIDebugTarget.java:1363)\n \n       at \norg.eclipse.jdt.internal.debug.ui.JavaDebugHover.getHoverInfo(JavaDebugHover.java:91)\n \n       at \norg.eclipse.jdt.internal.ui.text.java.hover.JavaTextHover.getHoverInfo(JavaTextHover.java:304)\n \n       at \norg.eclipse.jface.text.TextViewerHoverManager$2.runTextViewerHoverManager.java:107)",
    "\n\n*** This bug has been marked as a duplicate of 19433 ***"
  ],
  "commentCreationDates": [
    "2002-08-28T20:05:16+02:00",
    "2002-08-28T20:13:08+02:00"
  ],
  "traces": [
    {
      "exceptionType": "java.lang.NullPointerException",
      "elements": [
        {
          "method": "org.eclipse.jdi.internal.ReferenceTypeImpl.fields",
          "source": "ReferenceTypeImpl.java:541"
        },
        {
          "method": "org.eclipse.jdi.internal.ReferenceTypeImpl.allFields",
          "source": "ReferenceTypeImpl.java:403"
        },
        {
          "method": "org.eclipse.jdi.internal.ReferenceTypeImpl.allFields",
          "source": "ReferenceTypeImpl.java:417"
        },
        {
          "method": "org.eclipse.jdt.internal.debug.core.model.JDIValue.getVariables0",
          "source": "JDIValue.java:204"
        },
        {
          "method": "org.eclipse.jdt.internal.debug.core.model.JDIStackFrame.findVariable",
          "source": "JDIStackFrame.java:574"
        },
        {
          "method": "org.eclipse.jdt.internal.debug.core.model.JDIThread.findVariable",
          "source": "JDIThread.java:1401"
        },
        {
          "method": "org.eclipse.jdt.internal.debug.core.model.JDIDebugTarget.findVariable",
          "source": "JDIDebugTarget.java:1363"
        },
        {
          "method": "org.eclipse.jdt.internal.debug.ui.JavaDebugHover.getHoverInfo",
          "source": "JavaDebugHover.java:91"
        },
        {
          "method": "org.eclipse.jdt.internal.ui.text.java.hover.JavaTextHover.getHoverInfo",
          "source": "JavaTextHover.java:304"
        }
      ],
      "number": 0,
      "commentIndex": 0,
      "bugId": "22955",
      "duplicateId": "19433",
      "date": "2002-08-28T20:05:16+02:00",
      "product": "JDT",
      "component": "Debug",
      "severity": "normal"
    }
  ],
  "groupId": "21622",
  "bugId": "22955",
  "duplicateId": "19433",
  "date": "2002-08-28T20:05:16+02:00",
  "product": "JDT",
  "component": "Debug",
  "severity": "normal"
}