{
  "comments": [
    "Scrapbook and Xerces/Jaxp to not work.  The same code works in a Junit test or \nin a class file.\n\nI am trying to use the Xerces with JAXP in a Scrapbook.   My environment is \nj2sdk1.4.0_01/Eclipse 2.0.\n\nUsing Xerces/Jaxp gives a FactoryConfigurationError Exception.  I have tried \nvarious combinations of import statements and various Java Build Path \ncombinations.\nTwo examples follow.  First the default crimson compiler is used.  Then I \nchange it to use Xerces.\n\nIf there is a workaround for this, please post.\n\n\n---------------------------------------------------------------------------\nThis works fine - (using default crimson parser)\n Scrapbook Code:\n   System.setProperty(\"jaxp.debug\", \"true\");\n   System.out.println(\"DocumentBuilderFactory \u003d \" + System.getProperty\n(\"javax.xml.parsers.DocumentBuilderFactory\"));\n   DocumentBuilderFactory dbf \u003d DocumentBuilderFactory.newInstance();\n   return dbf;\n\n\n   Console output:\n       DocumentBuilderFactory \u003d null\n       JAXP: loaded from fallback value: \norg.apache.crimson.jaxp.DocumentBuilderFactoryImpl\n\n---------------------------------------------------------------------------\nThis does not work.  Here I have changed it to use the Xerces parser.\n  Scrapbook Code:\n\tSystem.setProperty(\"jaxp.debug\", \"true\");\n\tSystem.setProperty\n( \"javax.xml.parsers.DocumentBuilderFactory\",\"org.apache.xerces.jaxp.DocumentBui\nlderFactoryImpl\" );\n\tSystem.out.println(\"DocumentBuilderFactory \u003d \" + System.getProperty\n(\"javax.xml.parsers.DocumentBuilderFactory\"));\n\tDocumentBuilderFactory dbf \u003d DocumentBuilderFactory.newInstance();\n\treturn dbf;\n\n\n   Console Output:\nDocumentBuilderFactory \u003d org.apache.xerces.jaxp.DocumentBuilderFactoryImpl\nJAXP: found system propertyorg.apache.xerces.jaxp.DocumentBuilderFactoryImpl\njavax.xml.parsers.FactoryConfigurationError: Provider \norg.apache.xerces.jaxp.DocumentBuilderFactoryImpl not found\n\tat javax.xml.parsers.DocumentBuilderFactory.newInstance\n(DocumentBuilderFactory.java:109)\n\tat CodeSnippet_7.run(CodeSnippet_7.java:8)\n\tat org.eclipse.jdt.internal.debug.ui.snippeteditor.ScrapbookMain1.eval\n(ScrapbookMain1.java:14)\n\tat sun.reflect.NativeMethodAccessorImpl.invoke0(Native Method)\n\tat sun.reflect.NativeMethodAccessorImpl.invoke\n(NativeMethodAccessorImpl.java:39)\n\tat sun.reflect.DelegatingMethodAccessorImpl.invoke\n(DelegatingMethodAccessorImpl.java:25)\n\tat java.lang.reflect.Method.invoke(Method.java:324)\n\tat \norg.eclipse.jdt.internal.debug.ui.snippeteditor.ScrapbookMain.evalLoop\n(ScrapbookMain.java:48)\n\tat org.eclipse.jdt.internal.debug.ui.snippeteditor.ScrapbookMain.main\n(ScrapbookMain.java:29)",
    "This works for me. I created a scrapbook page, in a project \"A\" which \nhas \"org.apache.xerces\" as required project (build path). I then added an \nimport to the snippet page for the \ntype \"javax.xml.parsers.DocumentBuilderFactory\". The snippet ran with no errors \n(running on IBM 1.3.1):\n\nThe display result was:\n\n(org.apache.xerces.jaxp.DocumentBuilderFactoryImpl) \norg.apache.xerces.jaxp.DocumentBuilderFactoryImpl@36c1e0c4"
  ],
  "commentCreationDates": [
    "2002-09-05T16:18:39+02:00",
    "2002-10-08T15:14:40+02:00"
  ],
  "traces": [
    {
      "exceptionType": "javax.xml.parsers.FactoryConfigurationError",
      "message": "Provider  org.apache.xerces.jaxp.DocumentBuilderFactoryImpl not found",
      "elements": [
        {
          "method": "javax.xml.parsers.DocumentBuilderFactory.newInstance",
          "source": "DocumentBuilderFactory.java:109"
        },
        {
          "method": "CodeSnippet_7.run",
          "source": "CodeSnippet_7.java:8"
        },
        {
          "method": "org.eclipse.jdt.internal.debug.ui.snippeteditor.ScrapbookMain1.eval",
          "source": "ScrapbookMain1.java:14"
        },
        {
          "method": "sun.reflect.NativeMethodAccessorImpl.invoke0",
          "source": "Native Method"
        },
        {
          "method": "sun.reflect.NativeMethodAccessorImpl.invoke",
          "source": "NativeMethodAccessorImpl.java:39"
        },
        {
          "method": "sun.reflect.DelegatingMethodAccessorImpl.invoke",
          "source": "DelegatingMethodAccessorImpl.java:25"
        },
        {
          "method": "java.lang.reflect.Method.invoke",
          "source": "Method.java:324"
        },
        {
          "method": "org.eclipse.jdt.internal.debug.ui.snippeteditor.ScrapbookMain.evalLoop",
          "source": "ScrapbookMain.java:48"
        },
        {
          "method": "org.eclipse.jdt.internal.debug.ui.snippeteditor.ScrapbookMain.main",
          "source": "ScrapbookMain.java:29"
        }
      ],
      "number": 0,
      "commentIndex": 0,
      "bugId": "23221",
      "date": "2002-09-05T16:18:39+02:00",
      "product": "JDT",
      "component": "Debug",
      "severity": "normal"
    }
  ],
  "groupId": "23221",
  "bugId": "23221",
  "date": "2002-09-05T16:18:39+02:00",
  "product": "JDT",
  "component": "Debug",
  "severity": "normal"
}