{
  "comments": [
    "I think the following exception should not be logged unless it represents a bug.\nIn this case I think that not even the message \"Thread not suspended, ....\" \nshould be logged.\n\norg.eclipse.debug.core.DebugException: Thread not suspended, stack frame unavail\nable.\n        at org.eclipse.jdt.internal.debug.core.model.JDIDebugElement.throwDebugE\nxception(JDIDebugElement.java:277)\n        at org.eclipse.jdt.internal.debug.core.model.JDIDebugElement.requestFail\ned(JDIDebugElement.java:235)\n        at org.eclipse.jdt.internal.debug.core.model.JDIStackFrame.getUnderlying\nStackFrame(JDIStackFrame.java:922)\n        at org.eclipse.jdt.internal.debug.core.model.JDIStackFrame.getUnderlying\nMethod(JDIStackFrame.java:191)\n        at org.eclipse.jdt.internal.debug.core.model.JDIStackFrame.getDeclaringT\nypeName(JDIStackFrame.java:663)\n        at org.eclipse.jdt.debug.ui.JavaUISourceLocator$1.run(JavaUISourceLocato\nr.java:141)\n        at org.eclipse.swt.widgets.Synchronizer.syncExec(Synchronizer.java:123)\n        at org.eclipse.ui.internal.UISynchronizer.syncExec(UISynchronizer.java:1\n8)\n        at org.eclipse.swt.widgets.Display.syncExec(Display.java:1906)\n        at org.eclipse.jdt.debug.ui.JavaUISourceLocator.showDebugSourcePage(Java\nUISourceLocator.java:149)\n        at org.eclipse.jdt.debug.ui.JavaUISourceLocator.getSourceElement(JavaUIS\nourceLocator.java:121)\n        at org.eclipse.debug.internal.ui.views.launch.LaunchView.lookupEditorInp\nut(LaunchView.java:489)\n        at org.eclipse.debug.internal.ui.views.launch.LaunchView.showMarkerForCu\nrrentSelection(LaunchView.java:445)\n        at org.eclipse.debug.internal.ui.views.launch.LaunchView.selectionChange\nd(LaunchView.java:324)\n        at org.eclipse.jface.viewers.Viewer.fireSelectionChanged(Viewer.java(Com\npiled Code))\n        at org.eclipse.jface.viewers.StructuredViewer.updateSelection(Structured\nViewer.java:1155)\n        at org.eclipse.jface.viewers.StructuredViewer.handleSelect(StructuredVie\nwer.java:544)\n        at org.eclipse.jface.viewers.StructuredViewer$1.widgetSelected(Structure\ndViewer.java:568)\n        at org.eclipse.jface.util.OpenStrategy.fireSelectionEvent(OpenStrategy.j\nava:173)\n        at org.eclipse.jface.util.OpenStrategy.access$3(OpenStrategy.java:168)\n        at org.eclipse.jface.util.OpenStrategy$1.handleEvent(OpenStrategy.java:3\n03)\n        at org.eclipse.swt.widgets.EventTable.sendEvent(EventTable.java(Compiled\n Code))\n        at org.eclipse.swt.widgets.Widget.sendEvent(Widget.java(Compiled Code))\n        at org.eclipse.swt.widgets.Display.runDeferredEvents(Display.java(Compil\ned Code))\n        at org.eclipse.swt.widgets.Display.readAndDispatch(Display.java(Compiled\n Code))\n        at org.eclipse.ui.internal.Workbench.runEventLoop(Workbench.java(Compile\nd Code))\n        at org.eclipse.ui.internal.Workbench.run(Workbench.java:1239)\n        at org.eclipse.core.internal.boot.InternalBootLoader.run(InternalBootLoa\nder.java:775)\n        at org.eclipse.core.boot.BootLoader.run(BootLoader.java:462)\n        at java.lang.reflect.Method.invoke(Native Method)\n        at org.eclipse.core.launcher.Main.basicRun(Main.java:247)\n        at org.eclipse.core.launcher.Main.run(Main.java:703)\n        at org.eclipse.core.launcher.Main.main(Main.java:539)\n!ENTRY org.eclipse.jdt.debug 4 100 Sep 16, 2002 10:58:44.540\n!MESSAGE Thread not suspended, stack frame unavailable.",
    "Fixed in JavaUISourceLocator.",
    "Please verify, Darin S.",
    "Verified code change."
  ],
  "commentCreationDates": [
    "2002-09-16T16:43:20+02:00",
    "2002-11-27T16:15:49+01:00",
    "2002-11-27T16:16:08+01:00",
    "2002-11-27T19:16:19+01:00"
  ],
  "traces": [
    {
      "exceptionType": "org.eclipse.debug.core.DebugException",
      "message": "Thread not suspended, stack frame unavail able.",
      "elements": [
        {
          "method": "org.eclipse.jdt.internal.debug.core.model.JDIDebugElement.throwDebugException",
          "source": "JDIDebugElement.java:277"
        },
        {
          "method": "org.eclipse.jdt.internal.debug.core.model.JDIDebugElement.requestFailed",
          "source": "JDIDebugElement.java:235"
        },
        {
          "method": "org.eclipse.jdt.internal.debug.core.model.JDIStackFrame.getUnderlyingStackFrame",
          "source": "JDIStackFrame.java:922"
        },
        {
          "method": "org.eclipse.jdt.internal.debug.core.model.JDIStackFrame.getUnderlyingMethod",
          "source": "JDIStackFrame.java:191"
        },
        {
          "method": "org.eclipse.jdt.internal.debug.core.model.JDIStackFrame.getDeclaringTypeName",
          "source": "JDIStackFrame.java:663"
        },
        {
          "method": "org.eclipse.jdt.debug.ui.JavaUISourceLocator$1.run",
          "source": "JavaUISourceLocato r.java:141"
        },
        {
          "method": "org.eclipse.swt.widgets.Synchronizer.syncExec",
          "source": "Synchronizer.java:123"
        },
        {
          "method": "org.eclipse.ui.internal.UISynchronizer.syncExec",
          "source": "UISynchronizer.java:1 8"
        },
        {
          "method": "org.eclipse.swt.widgets.Display.syncExec",
          "source": "Display.java:1906"
        },
        {
          "method": "org.eclipse.jdt.debug.ui.JavaUISourceLocator.showDebugSourcePage",
          "source": "Java UISourceLocator.java:149"
        },
        {
          "method": "org.eclipse.jdt.debug.ui.JavaUISourceLocator.getSourceElement",
          "source": "JavaUIS ourceLocator.java:121"
        },
        {
          "method": "org.eclipse.debug.internal.ui.views.launch.LaunchView.lookupEditorInput",
          "source": "LaunchView.java:489"
        },
        {
          "method": "org.eclipse.debug.internal.ui.views.launch.LaunchView.showMarkerForCurrentSelection",
          "source": "LaunchView.java:445"
        },
        {
          "method": "org.eclipse.debug.internal.ui.views.launch.LaunchView.selectionChanged",
          "source": "LaunchView.java:324"
        },
        {
          "method": "org.eclipse.jface.viewers.Viewer.fireSelectionChanged",
          "source": "Viewer.java(Com piled Code)"
        },
        {
          "method": "org.eclipse.jface.viewers.StructuredViewer.updateSelection",
          "source": "Structured Viewer.java:1155"
        },
        {
          "method": "org.eclipse.jface.viewers.StructuredViewer.handleSelect",
          "source": "StructuredVie wer.java:544"
        },
        {
          "method": "org.eclipse.jface.viewers.StructuredViewer$1.widgetSelected",
          "source": "Structure dViewer.java:568"
        },
        {
          "method": "org.eclipse.jface.util.OpenStrategy.fireSelectionEvent",
          "source": "OpenStrategy.j ava:173"
        },
        {
          "method": "org.eclipse.jface.util.OpenStrategy.access$3",
          "source": "OpenStrategy.java:168"
        },
        {
          "method": "org.eclipse.jface.util.OpenStrategy$1.handleEvent",
          "source": "OpenStrategy.java:3 03"
        },
        {
          "method": "org.eclipse.swt.widgets.EventTable.sendEvent",
          "source": "EventTable.java(Compiled  Code)"
        },
        {
          "method": "org.eclipse.swt.widgets.Widget.sendEvent",
          "source": "Widget.java(Compiled Code)"
        },
        {
          "method": "org.eclipse.swt.widgets.Display.runDeferredEvents",
          "source": "Display.java(Compil ed Code)"
        },
        {
          "method": "org.eclipse.swt.widgets.Display.readAndDispatch",
          "source": "Display.java(Compiled  Code)"
        },
        {
          "method": "org.eclipse.ui.internal.Workbench.runEventLoop",
          "source": "Workbench.java(Compile d Code)"
        },
        {
          "method": "org.eclipse.ui.internal.Workbench.run",
          "source": "Workbench.java:1239"
        },
        {
          "method": "org.eclipse.core.internal.boot.InternalBootLoader.run",
          "source": "InternalBootLoa der.java:775"
        },
        {
          "method": "org.eclipse.core.boot.BootLoader.run",
          "source": "BootLoader.java:462"
        },
        {
          "method": "java.lang.reflect.Method.invoke",
          "source": "Native Method"
        },
        {
          "method": "org.eclipse.core.launcher.Main.basicRun",
          "source": "Main.java:247"
        },
        {
          "method": "org.eclipse.core.launcher.Main.run",
          "source": "Main.java:703"
        },
        {
          "method": "org.eclipse.core.launcher.Main.main",
          "source": "Main.java:539"
        }
      ],
      "number": 0,
      "commentIndex": 0,
      "bugId": "23607",
      "date": "2002-09-16T16:43:20+02:00",
      "product": "JDT",
      "component": "Debug",
      "severity": "normal"
    }
  ],
  "groupId": "23607",
  "bugId": "23607",
  "date": "2002-09-16T16:43:20+02:00",
  "product": "JDT",
  "component": "Debug",
  "severity": "normal"
}