{
  "comments": [
    "MA (6/7/01 12:21:50 PM)\n\tWhile closing the workbench\n\tThis walkback was printed to the console on shutdown of eclipse (not to the log)\n\norg.eclipse.swt.SWTError: No more handles\n        at org.eclipse.swt.SWT.error(SWT.java:1732)\n        at org.eclipse.swt.SWT.error(SWT.java:1642)\n        at org.eclipse.swt.graphics.Image.init(Image.java(Compiled Code))\n        at org.eclipse.swt.graphics.Image.\u003cinit\u003e(Image.java(Compiled Code))\n        at org.eclipse.jface.resource.ImageDescriptor.createImage(ImageDescriptor.java(Compiled Code))\n        at org.eclipse.jface.resource.ImageDescriptor.createImage(ImageDescriptor.java(Compiled Code))\n        at org.eclipse.ui.actions.PerspectiveMenu.createMenuItem(PerspectiveMenu.java(Compiled Code))\n        at org.eclipse.ui.actions.PerspectiveMenu.fill(PerspectiveMenu.java(Compiled Code))\n        at org.eclipse.jface.action.MenuManager.update(MenuManager.java(Compiled Code))\n        at org.eclipse.jface.action.MenuManager.updateAll(MenuManager.java(Compiled Code))\n        at org.eclipse.jface.action.MenuManager.update(MenuManager.java(Compiled Code))\n        at org.eclipse.jface.action.MenuManager.updateAll(MenuManager.java(Compiled Code))\n        at org.eclipse.jface.action.MenuManager.update(MenuManager.java(Compiled Code))\n        at org.eclipse.jface.action.MenuManager.updateAll(MenuManager.java(Compiled Code))\n        at org.eclipse.ui.internal.WorkbenchWindow.updateActionBars(WorkbenchWindow.java:939)\n        at org.eclipse.ui.internal.WorkbenchWindow.updateActionSets(WorkbenchWindow.java:953)\n        at org.eclipse.ui.internal.WorkbenchWindow$5.run(WorkbenchWindow.java:881)\n        at org.eclipse.swt.custom.BusyIndicator.showWhile(BusyIndicator.java(Compiled Code))\n        at org.eclipse.ui.internal.WorkbenchWindow.setActivePage(WorkbenchWindow.java:860)\n        at org.eclipse.ui.internal.WorkbenchWindow.closeAllPages(WorkbenchWindow.java:303)\n        at org.eclipse.ui.internal.WorkbenchWindow.hardClose(WorkbenchWindow.java:608)\n        at org.eclipse.ui.internal.WorkbenchWindow.busyClose(WorkbenchWindow.java:261)\n        at org.eclipse.ui.internal.WorkbenchWindow.access$3(WorkbenchWindow.java:252)\n        at org.eclipse.ui.internal.WorkbenchWindow$1.run(WorkbenchWindow.java:292)\n        at org.eclipse.swt.custom.BusyIndicator.showWhile(BusyIndicator.java(Compiled Code))\n        at org.eclipse.ui.internal.WorkbenchWindow.close(WorkbenchWindow.java:290)\n        at org.eclipse.jface.window.WindowManager.close(WindowManager.java:103)\n        at org.eclipse.ui.internal.Workbench$2.run(Workbench.java:99)\n        at org.eclipse.core.internal.runtime.InternalPlatform.run(InternalPlatform.java(Compiled Code))\n        at org.eclipse.core.runtime.Platform.run(Platform.java(Compiled Code))\n        at org.eclipse.ui.internal.Workbench.busyClose(Workbench.java:97)\n        at org.eclipse.ui.internal.Workbench.access$4(Workbench.java:75)\n        at org.eclipse.ui.internal.Workbench$3.run(Workbench.java:156)\n        at org.eclipse.swt.custom.BusyIndicator.showWhile(BusyIndicator.java(Compiled Code))\n        at org.eclipse.ui.internal.Workbench.close(Workbench.java:154)\n        at org.eclipse.ui.internal.QuitAction.run(QuitAction.java:30)\n        at org.eclipse.jface.action.ActionContributionItem.handleWidgetSelection(ActionContributionItem.java:408)\n        at org.eclipse.jface.action.ActionContributionItem.handleWidgetEvent(ActionContributionItem.java(Compiled Code))\n        at org.eclipse.jface.action.ActionContributionItem$ActionListener.handleEvent(ActionContributionItem.java(Compiled Code))\n        at org.eclipse.jface.action.ActionContributionItem$ActionListener.handleEvent(ActionContributionItem.java(Compiled Code))\n        at org.eclipse.swt.widgets.Widget.notifyListeners(Widget.java(Compiled Code))\n        at org.eclipse.swt.widgets.Widget.notifyListeners(Widget.java(Compiled Code))\n        at org.eclipse.swt.widgets.Display.runDeferredEvents(Display.java(Compiled Code))\n        at org.eclipse.swt.widgets.Display.readAndDispatch(Display.java(Compiled Code))\n        at org.eclipse.ui.internal.Workbench.runEventLoop(Workbench.java(Compiled Code))\n        at org.eclipse.ui.internal.Workbench.run(Workbench.java:620)\n        at org.eclipse.core.internal.boot.InternalBootLoader.run(InternalBootLoader.java:815)\n        at org.eclipse.core.boot.BootLoader.run(BootLoader.java:285)\n        at java.lang.reflect.Method.invoke(Native Method)\n        at org.eclipse.core.launcher.Main.basicRun(Main.java:69)\n        at org.eclipse.core.launcher.Main.run(Main.java:311)\n        at org.eclipse.core.launcher.UIMain.main(UIMain.java:43)\n\n\nNOTES:\nEG (6/7/2001 1:11:44 AM)\n\tmoving on layer down to ITPUI.\n\nDS (6/7/01 3:30:10 PM)\n\tWe print exceptions in 5 places in the workbench ui ..\n\n\t\texecute(IProgressMonitor) :: WorkspaceModifyDelegatingOperation\n\t\thandleExceptionInEventLoop(Throwable) :: Workbench ( only if debug )\n\t\tinit(String []) :: Workbench\n\t\tjavaToNative(Object, TransferData) :: PluginTransfer\n\t\tnativeToJava(TransferData) :: PluginTransfer\n\n\tand 3 places in core boot ..\n\n\t\tDelegatingURLClassLoader\n\t\tloadOptions() :: InternalBootLoader\n\t\trun(String, URL, String, String []) :: InternalBootLoader\n\n\tAfter we release all of these should be modified to log rather than print.\n\nKH (9/14/2001 12:04:58 PM)\n\tI am more concerned about the fact that there was an exception not where it was logged.",
    "PRODUCT VERSION:\n\t0.119\n\n",
    "Pls note the priority of this defect report\n\nThere are a couple issues: \n  - Where exeptions are being displayed\n  - What is written to the log (e.g. exceptions in async execs do not contain \nany usefull information)\n  - The fact that we ran out of handles\n\n",
    "- handleExceptionInEventLoop has being changed to try to log any exception \nindependent if it is a fatal error or not but if exception happen when handling \nfatal errors then we print them to the console (nothing else to do since there \nis no more memory or handles, etc).\n- exception wrapped by SWTException or SWTError are printed now; \n- we are not updating the menus (which would create images) on shutdown anymore.\n"
  ],
  "commentCreationDates": [
    "2001-10-11T04:35:35+02:00",
    "2001-10-29T23:25:12+01:00",
    "2002-01-23T22:13:08+01:00",
    "2002-02-05T19:38:21+01:00"
  ],
  "traces": [
    {
      "exceptionType": "org.eclipse.swt.SWTError",
      "message": "No more handles",
      "elements": [
        {
          "method": "org.eclipse.swt.SWT.error",
          "source": "SWT.java:1732"
        },
        {
          "method": "org.eclipse.swt.SWT.error",
          "source": "SWT.java:1642"
        },
        {
          "method": "org.eclipse.swt.graphics.Image.init",
          "source": "Image.java(Compiled Code)"
        },
        {
          "method": "org.eclipse.swt.graphics.Image.\u003cinit\u003e",
          "source": "Image.java(Compiled Code)"
        },
        {
          "method": "org.eclipse.jface.resource.ImageDescriptor.createImage",
          "source": "ImageDescriptor.java(Compiled Code)"
        },
        {
          "method": "org.eclipse.jface.resource.ImageDescriptor.createImage",
          "source": "ImageDescriptor.java(Compiled Code)"
        },
        {
          "method": "org.eclipse.ui.actions.PerspectiveMenu.createMenuItem",
          "source": "PerspectiveMenu.java(Compiled Code)"
        },
        {
          "method": "org.eclipse.ui.actions.PerspectiveMenu.fill",
          "source": "PerspectiveMenu.java(Compiled Code)"
        },
        {
          "method": "org.eclipse.jface.action.MenuManager.update",
          "source": "MenuManager.java(Compiled Code)"
        },
        {
          "method": "org.eclipse.jface.action.MenuManager.updateAll",
          "source": "MenuManager.java(Compiled Code)"
        },
        {
          "method": "org.eclipse.jface.action.MenuManager.update",
          "source": "MenuManager.java(Compiled Code)"
        },
        {
          "method": "org.eclipse.jface.action.MenuManager.updateAll",
          "source": "MenuManager.java(Compiled Code)"
        },
        {
          "method": "org.eclipse.jface.action.MenuManager.update",
          "source": "MenuManager.java(Compiled Code)"
        },
        {
          "method": "org.eclipse.jface.action.MenuManager.updateAll",
          "source": "MenuManager.java(Compiled Code)"
        },
        {
          "method": "org.eclipse.ui.internal.WorkbenchWindow.updateActionBars",
          "source": "WorkbenchWindow.java:939"
        },
        {
          "method": "org.eclipse.ui.internal.WorkbenchWindow.updateActionSets",
          "source": "WorkbenchWindow.java:953"
        },
        {
          "method": "org.eclipse.ui.internal.WorkbenchWindow$5.run",
          "source": "WorkbenchWindow.java:881"
        },
        {
          "method": "org.eclipse.swt.custom.BusyIndicator.showWhile",
          "source": "BusyIndicator.java(Compiled Code)"
        },
        {
          "method": "org.eclipse.ui.internal.WorkbenchWindow.setActivePage",
          "source": "WorkbenchWindow.java:860"
        },
        {
          "method": "org.eclipse.ui.internal.WorkbenchWindow.closeAllPages",
          "source": "WorkbenchWindow.java:303"
        },
        {
          "method": "org.eclipse.ui.internal.WorkbenchWindow.hardClose",
          "source": "WorkbenchWindow.java:608"
        },
        {
          "method": "org.eclipse.ui.internal.WorkbenchWindow.busyClose",
          "source": "WorkbenchWindow.java:261"
        },
        {
          "method": "org.eclipse.ui.internal.WorkbenchWindow.access$3",
          "source": "WorkbenchWindow.java:252"
        },
        {
          "method": "org.eclipse.ui.internal.WorkbenchWindow$1.run",
          "source": "WorkbenchWindow.java:292"
        },
        {
          "method": "org.eclipse.swt.custom.BusyIndicator.showWhile",
          "source": "BusyIndicator.java(Compiled Code)"
        },
        {
          "method": "org.eclipse.ui.internal.WorkbenchWindow.close",
          "source": "WorkbenchWindow.java:290"
        },
        {
          "method": "org.eclipse.jface.window.WindowManager.close",
          "source": "WindowManager.java:103"
        },
        {
          "method": "org.eclipse.ui.internal.Workbench$2.run",
          "source": "Workbench.java:99"
        },
        {
          "method": "org.eclipse.core.internal.runtime.InternalPlatform.run",
          "source": "InternalPlatform.java(Compiled Code)"
        },
        {
          "method": "org.eclipse.core.runtime.Platform.run",
          "source": "Platform.java(Compiled Code)"
        },
        {
          "method": "org.eclipse.ui.internal.Workbench.busyClose",
          "source": "Workbench.java:97"
        },
        {
          "method": "org.eclipse.ui.internal.Workbench.access$4",
          "source": "Workbench.java:75"
        },
        {
          "method": "org.eclipse.ui.internal.Workbench$3.run",
          "source": "Workbench.java:156"
        },
        {
          "method": "org.eclipse.swt.custom.BusyIndicator.showWhile",
          "source": "BusyIndicator.java(Compiled Code)"
        },
        {
          "method": "org.eclipse.ui.internal.Workbench.close",
          "source": "Workbench.java:154"
        },
        {
          "method": "org.eclipse.ui.internal.QuitAction.run",
          "source": "QuitAction.java:30"
        },
        {
          "method": "org.eclipse.jface.action.ActionContributionItem.handleWidgetSelection",
          "source": "ActionContributionItem.java:408"
        },
        {
          "method": "org.eclipse.jface.action.ActionContributionItem.handleWidgetEvent",
          "source": "ActionContributionItem.java(Compiled Code)"
        },
        {
          "method": "org.eclipse.jface.action.ActionContributionItem$ActionListener.handleEvent",
          "source": "ActionContributionItem.java(Compiled Code)"
        },
        {
          "method": "org.eclipse.jface.action.ActionContributionItem$ActionListener.handleEvent",
          "source": "ActionContributionItem.java(Compiled Code)"
        },
        {
          "method": "org.eclipse.swt.widgets.Widget.notifyListeners",
          "source": "Widget.java(Compiled Code)"
        },
        {
          "method": "org.eclipse.swt.widgets.Widget.notifyListeners",
          "source": "Widget.java(Compiled Code)"
        },
        {
          "method": "org.eclipse.swt.widgets.Display.runDeferredEvents",
          "source": "Display.java(Compiled Code)"
        },
        {
          "method": "org.eclipse.swt.widgets.Display.readAndDispatch",
          "source": "Display.java(Compiled Code)"
        },
        {
          "method": "org.eclipse.ui.internal.Workbench.runEventLoop",
          "source": "Workbench.java(Compiled Code)"
        },
        {
          "method": "org.eclipse.ui.internal.Workbench.run",
          "source": "Workbench.java:620"
        },
        {
          "method": "org.eclipse.core.internal.boot.InternalBootLoader.run",
          "source": "InternalBootLoader.java:815"
        },
        {
          "method": "org.eclipse.core.boot.BootLoader.run",
          "source": "BootLoader.java:285"
        },
        {
          "method": "java.lang.reflect.Method.invoke",
          "source": "Native Method"
        },
        {
          "method": "org.eclipse.core.launcher.Main.basicRun",
          "source": "Main.java:69"
        },
        {
          "method": "org.eclipse.core.launcher.Main.run",
          "source": "Main.java:311"
        },
        {
          "method": "org.eclipse.core.launcher.UIMain.main",
          "source": "UIMain.java:43"
        }
      ],
      "number": 0,
      "commentIndex": 0,
      "bugId": "2394",
      "date": "2001-10-11T04:35:35+02:00",
      "product": "Platform",
      "component": "UI",
      "severity": "normal"
    }
  ],
  "groupId": "2394",
  "bugId": "2394",
  "date": "2001-10-11T04:35:35+02:00",
  "product": "Platform",
  "component": "UI",
  "severity": "normal"
}