{
  "comments": [
    "After a major change to CVS project struture and references, one in our team \ncouldn\u0027t run her JUnit test class any more. All attempts at running that class -\n and also at getting the Run/Run...-window (Launch configurations) resulted in \na NPE. After several failed attempts at clearing the classpath and launch \nhistory, we noticed that one of the old history launches was able to run. After \nthat, everything worked OK.\n\nThis is the relevant part of the log file.\n\n!SESSION sep 25, 2002 10:38:42.734 ---------------------------------------------\njava.version\u003d1.3.1_03\njava.vendor\u003dSun Microsystems Inc.\nBootLoader constants: OS\u003dwin32, ARCH\u003dx86, WS\u003dwin32, NL\u003dsv_SE\nCommand-line arguments: -os win32 -ws win32 -arch x86 -install file:C:/Program \nFiles/eclipse/eclipse/\n!ENTRY org.eclipse.core.resources 2 1 sep 25, 2002 10:38:42.734\n!MESSAGE Skipping builder \ncom.telesynthesis.tools.eclipse.checkstyle.CheckStyleBuilder for project \nToolsConsoleTestUtils. Either the builder is missing from the install, or it \nbelongs to a project nature that is missing or disabled.\n!ENTRY org.eclipse.core.resources 2 1 sep 25, 2002 10:38:42.781\n!MESSAGE Skipping builder \ncom.telesynthesis.tools.eclipse.checkstyle.CheckStyleBuilder for project \nToolsCommon. Either the builder is missing from the install, or it belongs to a \nproject nature that is missing or disabled.\n!ENTRY org.eclipse.core.resources 2 1 sep 25, 2002 10:38:42.781\n!MESSAGE Skipping builder \ncom.telesynthesis.tools.eclipse.checkstyle.CheckStyleBuilder for project \nManagementAPI. Either the builder is missing from the install, or it belongs to \na project nature that is missing or disabled.\n!ENTRY org.eclipse.core.resources 2 1 sep 25, 2002 10:38:42.781\n!MESSAGE Skipping builder \ncom.telesynthesis.tools.eclipse.checkstyle.CheckStyleBuilder for project \nToolsJRockitSide. Either the builder is missing from the install, or it belongs \nto a project nature that is missing or disabled.\n!ENTRY org.eclipse.core.resources 2 1 sep 25, 2002 10:38:42.781\n!MESSAGE Skipping builder \ncom.telesynthesis.tools.eclipse.checkstyle.CheckStyleBuilder for project \nToolsConsole. Either the builder is missing from the install, or it belongs to \na project nature that is missing or disabled.\n!ENTRY org.eclipse.core.resources 2 1 sep 25, 2002 10:38:42.796\n!MESSAGE Skipping builder \ncom.telesynthesis.tools.eclipse.checkstyle.CheckStyleBuilder for project \nToolsConsoleTest. Either the builder is missing from the install, or it belongs \nto a project nature that is missing or disabled.\n!ENTRY org.eclipse.ui 4 4 sep 25, 2002 10:38:59.328\n!MESSAGE Unhandled exception caught in event loop.\n!ENTRY org.eclipse.ui 4 0 sep 25, 2002 10:38:59.343\n!MESSAGE java.lang.NullPointerException\n!STACK 0\njava.lang.NullPointerException\n        at org.eclipse.jdt.internal.launching.RuntimeClasspathEntry.\u003cinit\u003e\n(RuntimeClasspathEntry.java:168)\n        at org.eclipse.jdt.launching.JavaRuntime.newRuntimeClasspathEntry\n(JavaRuntime.java:504)\n        at \norg.eclipse.jdt.launching.StandardClasspathProvider.recoverRuntimePath\n(StandardClasspathProvider.java:96)\n        at \norg.eclipse.jdt.launching.StandardClasspathProvider.computeUnresolvedClasspath\n(StandardClasspathProvider.java:61)\n        at \norg.eclipse.jdt.launching.JavaRuntime.computeUnresolvedRuntimeClasspath\n(JavaRuntime.java:763)\n        at \norg.eclipse.jdt.debug.ui.launchConfigurations.JavaClasspathTab.initializeFrom\n(JavaClasspathTab.java:224)\n        at \norg.eclipse.debug.ui.AbstractLaunchConfigurationTabGroup.initializeFrom\n(AbstractLaunchConfigurationTabGroup.java:78)\n        at \norg.eclipse.debug.internal.ui.launchConfigurations.LaunchConfigurationDialog.set\nLaunchConfiguration(LaunchConfigurationDialog.java:1453)\n        at \norg.eclipse.debug.internal.ui.launchConfigurations.LaunchConfigurationDialog.sel\nectionChanged(LaunchConfigurationDialog.java:1382)\n        at org.eclipse.jface.viewers.Viewer.fireSelectionChanged\n(Viewer.java:147)\n        at org.eclipse.jface.viewers.StructuredViewer.updateSelection\n(StructuredViewer.java:1155)\n        at org.eclipse.jface.viewers.StructuredViewer.setSelection\n(StructuredViewer.java:904)\n        at org.eclipse.jface.viewers.Viewer.setSelection(Viewer.java:342)\n        at \norg.eclipse.debug.internal.ui.launchConfigurations.LaunchConfigurationDialog.doI\nnitialTreeSelection(LaunchConfigurationDialog.java:537)\n        at \norg.eclipse.debug.internal.ui.launchConfigurations.LaunchConfigurationDialog.cre\nateContents(LaunchConfigurationDialog.java:456)\n        at org.eclipse.jface.window.Window.create(Window.java:277)\n        at org.eclipse.jface.window.Window.open(Window.java:526)\n        at \norg.eclipse.debug.internal.ui.launchConfigurations.LaunchConfigurationDialog.doL\nastLaunchedConfig(LaunchConfigurationDialog.java:617)\n        at \norg.eclipse.debug.internal.ui.launchConfigurations.LaunchConfigurationDialog.ope\nn(LaunchConfigurationDialog.java:578)\n        at \norg.eclipse.debug.internal.ui.actions.OpenLaunchConfigurationsAction.run\n(OpenLaunchConfigurationsAction.java:132)\n        at org.eclipse.jface.action.Action.runWithEvent(Action.java:749)\n        at org.eclipse.jface.action.ActionContributionItem.handleWidgetSelection\n(ActionContributionItem.java:407)\n        at org.eclipse.jface.action.ActionContributionItem.handleWidgetEvent\n(ActionContributionItem.java:361)\n        at org.eclipse.jface.action.ActionContributionItem.access$0\n(ActionContributionItem.java:352)\n        at \norg.eclipse.jface.action.ActionContributionItem$ActionListener.handleEvent\n(ActionContributionItem.java:47)\n        at org.eclipse.swt.widgets.EventTable.sendEvent(EventTable.java:77)\n        at org.eclipse.swt.widgets.Widget.sendEvent(Widget.java:827)\n        at org.eclipse.swt.widgets.Display.runDeferredEvents(Display.java:1529)\n        at org.eclipse.swt.widgets.Display.readAndDispatch(Display.java:1291)\n        at org.eclipse.ui.internal.Workbench.runEventLoop(Workbench.java:1177)\n        at org.eclipse.ui.internal.Workbench.run(Workbench.java:1160)\n        at org.eclipse.core.internal.boot.InternalBootLoader.run\n(InternalBootLoader.java:775)\n        at org.eclipse.core.boot.BootLoader.run(BootLoader.java:462)\n        at java.lang.reflect.Method.invoke(Native Method)\n        at org.eclipse.core.launcher.Main.basicRun(Main.java:248)\n        at org.eclipse.core.launcher.Main.run(Main.java:698)\n        at org.eclipse.core.launcher.Main.main(Main.java:534)\n!ENTRY org.eclipse.ui 4 4 sep 25, 2002 10:40:02.234\n!MESSAGE Unhandled exception caught in event loop.\n!ENTRY org.eclipse.ui 4 0 sep 25, 2002 10:40:02.234\n!MESSAGE java.lang.NullPointerException\n!STACK 0\njava.lang.NullPointerException\n        at org.eclipse.jdt.internal.launching.RuntimeClasspathEntry.\u003cinit\u003e\n(RuntimeClasspathEntry.java:168)\n        at org.eclipse.jdt.launching.JavaRuntime.newRuntimeClasspathEntry\n(JavaRuntime.java:504)\n        at \norg.eclipse.jdt.launching.StandardClasspathProvider.recoverRuntimePath\n(StandardClasspathProvider.java:96)\n        at \norg.eclipse.jdt.launching.StandardClasspathProvider.computeUnresolvedClasspath\n(StandardClasspathProvider.java:61)\n        at \norg.eclipse.jdt.launching.JavaRuntime.computeUnresolvedRuntimeClasspath\n(JavaRuntime.java:763)\n        at \norg.eclipse.jdt.debug.ui.launchConfigurations.JavaClasspathTab.initializeFrom\n(JavaClasspathTab.java:224)\n        at \norg.eclipse.debug.ui.AbstractLaunchConfigurationTabGroup.initializeFrom\n(AbstractLaunchConfigurationTabGroup.java:78)\n        at \norg.eclipse.debug.internal.ui.launchConfigurations.LaunchConfigurationDialog.set\nLaunchConfiguration(LaunchConfigurationDialog.java:1453)\n        at \norg.eclipse.debug.internal.ui.launchConfigurations.LaunchConfigurationDialog.sel\nectionChanged(LaunchConfigurationDialog.java:1382)\n        at org.eclipse.jface.viewers.Viewer.fireSelectionChanged\n(Viewer.java:147)\n        at org.eclipse.jface.viewers.StructuredViewer.updateSelection\n(StructuredViewer.java:1155)\n        at org.eclipse.jface.viewers.StructuredViewer.setSelection\n(StructuredViewer.java:904)\n        at org.eclipse.jface.viewers.Viewer.setSelection(Viewer.java:342)\n        at \norg.eclipse.debug.internal.ui.launchConfigurations.LaunchConfigurationDialog.doI\nnitialTreeSelection(LaunchConfigurationDialog.java:537)\n        at \norg.eclipse.debug.internal.ui.launchConfigurations.LaunchConfigurationDialog.cre\nateContents(LaunchConfigurationDialog.java:456)\n        at org.eclipse.jface.window.Window.create(Window.java:277)\n        at org.eclipse.jface.window.Window.open(Window.java:526)\n        at \norg.eclipse.debug.internal.ui.launchConfigurations.LaunchConfigurationDialog.doL\nastLaunchedConfig(LaunchConfigurationDialog.java:617)\n        at \norg.eclipse.debug.internal.ui.launchConfigurations.LaunchConfigurationDialog.ope\nn(LaunchConfigurationDialog.java:578)\n        at \norg.eclipse.debug.internal.ui.actions.OpenLaunchConfigurationsAction.run\n(OpenLaunchConfigurationsAction.java:132)\n        at org.eclipse.jface.action.Action.runWithEvent(Action.java:749)\n        at org.eclipse.jface.action.ActionContributionItem.handleWidgetSelection\n(ActionContributionItem.java:407)\n        at org.eclipse.jface.action.ActionContributionItem.handleWidgetEvent\n(ActionContributionItem.java:361)\n        at org.eclipse.jface.action.ActionContributionItem.access$0\n(ActionContributionItem.java:352)\n        at \norg.eclipse.jface.action.ActionContributionItem$ActionListener.handleEvent\n(ActionContributionItem.java:47)\n        at org.eclipse.swt.widgets.EventTable.sendEvent(EventTable.java:77)\n        at org.eclipse.swt.widgets.Widget.sendEvent(Widget.java:827)\n        at org.eclipse.swt.widgets.Display.runDeferredEvents(Display.java:1529)\n        at org.eclipse.swt.widgets.Display.readAndDispatch(Display.java:1291)\n        at org.eclipse.ui.internal.Workbench.runEventLoop(Workbench.java:1177)\n        at org.eclipse.ui.internal.Workbench.run(Workbench.java:1160)\n        at org.eclipse.core.internal.boot.InternalBootLoader.run\n(InternalBootLoader.java:775)\n        at org.eclipse.core.boot.BootLoader.run(BootLoader.java:462)\n        at java.lang.reflect.Method.invoke(Native Method)\n        at org.eclipse.core.launcher.Main.basicRun(Main.java:248)\n        at org.eclipse.core.launcher.Main.run(Main.java:698)\n        at org.eclipse.core.launcher.Main.main(Main.java:534)",
    "Fixed in 2.0.1\n\n*** This bug has been marked as a duplicate of 21170 ***"
  ],
  "commentCreationDates": [
    "2002-09-25T10:42:31+02:00",
    "2002-09-26T15:57:54+02:00"
  ],
  "traces": [
    {
      "exceptionType": "java.lang.NullPointerException",
      "elements": [
        {
          "method": "org.eclipse.jdt.internal.launching.RuntimeClasspathEntry.\u003cinit\u003e",
          "source": "RuntimeClasspathEntry.java:168"
        },
        {
          "method": "org.eclipse.jdt.launching.JavaRuntime.newRuntimeClasspathEntry",
          "source": "JavaRuntime.java:504"
        },
        {
          "method": "org.eclipse.jdt.launching.StandardClasspathProvider.recoverRuntimePath",
          "source": "StandardClasspathProvider.java:96"
        },
        {
          "method": "org.eclipse.jdt.launching.StandardClasspathProvider.computeUnresolvedClasspath",
          "source": "StandardClasspathProvider.java:61"
        },
        {
          "method": "org.eclipse.jdt.launching.JavaRuntime.computeUnresolvedRuntimeClasspath",
          "source": "JavaRuntime.java:763"
        },
        {
          "method": "org.eclipse.jdt.debug.ui.launchConfigurations.JavaClasspathTab.initializeFrom",
          "source": "JavaClasspathTab.java:224"
        },
        {
          "method": "org.eclipse.debug.ui.AbstractLaunchConfigurationTabGroup.initializeFrom",
          "source": "AbstractLaunchConfigurationTabGroup.java:78"
        },
        {
          "method": "org.eclipse.debug.internal.ui.launchConfigurations.LaunchConfigurationDialog.setLaunchConfiguration",
          "source": "LaunchConfigurationDialog.java:1453"
        },
        {
          "method": "org.eclipse.debug.internal.ui.launchConfigurations.LaunchConfigurationDialog.selectionChanged",
          "source": "LaunchConfigurationDialog.java:1382"
        },
        {
          "method": "org.eclipse.jface.viewers.Viewer.fireSelectionChanged",
          "source": "Viewer.java:147"
        },
        {
          "method": "org.eclipse.jface.viewers.StructuredViewer.updateSelection",
          "source": "StructuredViewer.java:1155"
        },
        {
          "method": "org.eclipse.jface.viewers.StructuredViewer.setSelection",
          "source": "StructuredViewer.java:904"
        },
        {
          "method": "org.eclipse.jface.viewers.Viewer.setSelection",
          "source": "Viewer.java:342"
        },
        {
          "method": "org.eclipse.debug.internal.ui.launchConfigurations.LaunchConfigurationDialog.doInitialTreeSelection",
          "source": "LaunchConfigurationDialog.java:537"
        },
        {
          "method": "org.eclipse.debug.internal.ui.launchConfigurations.LaunchConfigurationDialog.createContents",
          "source": "LaunchConfigurationDialog.java:456"
        },
        {
          "method": "org.eclipse.jface.window.Window.create",
          "source": "Window.java:277"
        },
        {
          "method": "org.eclipse.jface.window.Window.open",
          "source": "Window.java:526"
        },
        {
          "method": "org.eclipse.debug.internal.ui.launchConfigurations.LaunchConfigurationDialog.doLastLaunchedConfig",
          "source": "LaunchConfigurationDialog.java:617"
        },
        {
          "method": "org.eclipse.debug.internal.ui.launchConfigurations.LaunchConfigurationDialog.open",
          "source": "LaunchConfigurationDialog.java:578"
        },
        {
          "method": "org.eclipse.debug.internal.ui.actions.OpenLaunchConfigurationsAction.run",
          "source": "OpenLaunchConfigurationsAction.java:132"
        },
        {
          "method": "org.eclipse.jface.action.Action.runWithEvent",
          "source": "Action.java:749"
        },
        {
          "method": "org.eclipse.jface.action.ActionContributionItem.handleWidgetSelection",
          "source": "ActionContributionItem.java:407"
        },
        {
          "method": "org.eclipse.jface.action.ActionContributionItem.handleWidgetEvent",
          "source": "ActionContributionItem.java:361"
        },
        {
          "method": "org.eclipse.jface.action.ActionContributionItem.access$0",
          "source": "ActionContributionItem.java:352"
        },
        {
          "method": "org.eclipse.jface.action.ActionContributionItem$ActionListener.handleEvent",
          "source": "ActionContributionItem.java:47"
        },
        {
          "method": "org.eclipse.swt.widgets.EventTable.sendEvent",
          "source": "EventTable.java:77"
        },
        {
          "method": "org.eclipse.swt.widgets.Widget.sendEvent",
          "source": "Widget.java:827"
        },
        {
          "method": "org.eclipse.swt.widgets.Display.runDeferredEvents",
          "source": "Display.java:1529"
        },
        {
          "method": "org.eclipse.swt.widgets.Display.readAndDispatch",
          "source": "Display.java:1291"
        },
        {
          "method": "org.eclipse.ui.internal.Workbench.runEventLoop",
          "source": "Workbench.java:1177"
        },
        {
          "method": "org.eclipse.ui.internal.Workbench.run",
          "source": "Workbench.java:1160"
        },
        {
          "method": "org.eclipse.core.internal.boot.InternalBootLoader.run",
          "source": "InternalBootLoader.java:775"
        },
        {
          "method": "org.eclipse.core.boot.BootLoader.run",
          "source": "BootLoader.java:462"
        },
        {
          "method": "java.lang.reflect.Method.invoke",
          "source": "Native Method"
        },
        {
          "method": "org.eclipse.core.launcher.Main.basicRun",
          "source": "Main.java:248"
        },
        {
          "method": "org.eclipse.core.launcher.Main.run",
          "source": "Main.java:698"
        },
        {
          "method": "org.eclipse.core.launcher.Main.main",
          "source": "Main.java:534"
        }
      ],
      "number": 0,
      "commentIndex": 0,
      "bugId": "24069",
      "duplicateId": "21170",
      "date": "2002-09-25T10:42:31+02:00",
      "product": "JDT",
      "component": "Debug",
      "severity": "normal"
    },
    {
      "exceptionType": "java.lang.NullPointerException",
      "elements": [
        {
          "method": "org.eclipse.jdt.internal.launching.RuntimeClasspathEntry.\u003cinit\u003e",
          "source": "RuntimeClasspathEntry.java:168"
        },
        {
          "method": "org.eclipse.jdt.launching.JavaRuntime.newRuntimeClasspathEntry",
          "source": "JavaRuntime.java:504"
        },
        {
          "method": "org.eclipse.jdt.launching.StandardClasspathProvider.recoverRuntimePath",
          "source": "StandardClasspathProvider.java:96"
        },
        {
          "method": "org.eclipse.jdt.launching.StandardClasspathProvider.computeUnresolvedClasspath",
          "source": "StandardClasspathProvider.java:61"
        },
        {
          "method": "org.eclipse.jdt.launching.JavaRuntime.computeUnresolvedRuntimeClasspath",
          "source": "JavaRuntime.java:763"
        },
        {
          "method": "org.eclipse.jdt.debug.ui.launchConfigurations.JavaClasspathTab.initializeFrom",
          "source": "JavaClasspathTab.java:224"
        },
        {
          "method": "org.eclipse.debug.ui.AbstractLaunchConfigurationTabGroup.initializeFrom",
          "source": "AbstractLaunchConfigurationTabGroup.java:78"
        },
        {
          "method": "org.eclipse.debug.internal.ui.launchConfigurations.LaunchConfigurationDialog.setLaunchConfiguration",
          "source": "LaunchConfigurationDialog.java:1453"
        },
        {
          "method": "org.eclipse.debug.internal.ui.launchConfigurations.LaunchConfigurationDialog.selectionChanged",
          "source": "LaunchConfigurationDialog.java:1382"
        },
        {
          "method": "org.eclipse.jface.viewers.Viewer.fireSelectionChanged",
          "source": "Viewer.java:147"
        },
        {
          "method": "org.eclipse.jface.viewers.StructuredViewer.updateSelection",
          "source": "StructuredViewer.java:1155"
        },
        {
          "method": "org.eclipse.jface.viewers.StructuredViewer.setSelection",
          "source": "StructuredViewer.java:904"
        },
        {
          "method": "org.eclipse.jface.viewers.Viewer.setSelection",
          "source": "Viewer.java:342"
        },
        {
          "method": "org.eclipse.debug.internal.ui.launchConfigurations.LaunchConfigurationDialog.doInitialTreeSelection",
          "source": "LaunchConfigurationDialog.java:537"
        },
        {
          "method": "org.eclipse.debug.internal.ui.launchConfigurations.LaunchConfigurationDialog.createContents",
          "source": "LaunchConfigurationDialog.java:456"
        },
        {
          "method": "org.eclipse.jface.window.Window.create",
          "source": "Window.java:277"
        },
        {
          "method": "org.eclipse.jface.window.Window.open",
          "source": "Window.java:526"
        },
        {
          "method": "org.eclipse.debug.internal.ui.launchConfigurations.LaunchConfigurationDialog.doLastLaunchedConfig",
          "source": "LaunchConfigurationDialog.java:617"
        },
        {
          "method": "org.eclipse.debug.internal.ui.launchConfigurations.LaunchConfigurationDialog.open",
          "source": "LaunchConfigurationDialog.java:578"
        },
        {
          "method": "org.eclipse.debug.internal.ui.actions.OpenLaunchConfigurationsAction.run",
          "source": "OpenLaunchConfigurationsAction.java:132"
        },
        {
          "method": "org.eclipse.jface.action.Action.runWithEvent",
          "source": "Action.java:749"
        },
        {
          "method": "org.eclipse.jface.action.ActionContributionItem.handleWidgetSelection",
          "source": "ActionContributionItem.java:407"
        },
        {
          "method": "org.eclipse.jface.action.ActionContributionItem.handleWidgetEvent",
          "source": "ActionContributionItem.java:361"
        },
        {
          "method": "org.eclipse.jface.action.ActionContributionItem.access$0",
          "source": "ActionContributionItem.java:352"
        },
        {
          "method": "org.eclipse.jface.action.ActionContributionItem$ActionListener.handleEvent",
          "source": "ActionContributionItem.java:47"
        },
        {
          "method": "org.eclipse.swt.widgets.EventTable.sendEvent",
          "source": "EventTable.java:77"
        },
        {
          "method": "org.eclipse.swt.widgets.Widget.sendEvent",
          "source": "Widget.java:827"
        },
        {
          "method": "org.eclipse.swt.widgets.Display.runDeferredEvents",
          "source": "Display.java:1529"
        },
        {
          "method": "org.eclipse.swt.widgets.Display.readAndDispatch",
          "source": "Display.java:1291"
        },
        {
          "method": "org.eclipse.ui.internal.Workbench.runEventLoop",
          "source": "Workbench.java:1177"
        },
        {
          "method": "org.eclipse.ui.internal.Workbench.run",
          "source": "Workbench.java:1160"
        },
        {
          "method": "org.eclipse.core.internal.boot.InternalBootLoader.run",
          "source": "InternalBootLoader.java:775"
        },
        {
          "method": "org.eclipse.core.boot.BootLoader.run",
          "source": "BootLoader.java:462"
        },
        {
          "method": "java.lang.reflect.Method.invoke",
          "source": "Native Method"
        },
        {
          "method": "org.eclipse.core.launcher.Main.basicRun",
          "source": "Main.java:248"
        },
        {
          "method": "org.eclipse.core.launcher.Main.run",
          "source": "Main.java:698"
        },
        {
          "method": "org.eclipse.core.launcher.Main.main",
          "source": "Main.java:534"
        }
      ],
      "number": 1,
      "commentIndex": 0,
      "bugId": "24069",
      "duplicateId": "21170",
      "date": "2002-09-25T10:42:31+02:00",
      "product": "JDT",
      "component": "Debug",
      "severity": "normal"
    }
  ],
  "groupId": "21170",
  "bugId": "24069",
  "duplicateId": "21170",
  "date": "2002-09-25T10:42:31+02:00",
  "product": "JDT",
  "component": "Debug",
  "severity": "normal"
}