{
  "comments": [
    "20020924\n\n\n!ENTRY org.eclipse.core.resources 4 2 Sep 25, 2002 15:27:29.25\n!MESSAGE Problems occurred when invoking code from plug-\nin: \"org.eclipse.core.resources\".\n!STACK 0\njava.lang.NullPointerException\n        at org.eclipse.jdt.internal.core.JavaProject.loadPreferences\n(JavaProject.java:1757)\n        at org.eclipse.jdt.internal.core.JavaProject.getPreferences\n(JavaProject.java:1366)\n        at org.eclipse.jdt.internal.core.JavaProject.getOption\n(JavaProject.java:1092)\n        at org.eclipse.jdt.internal.core.JavaProject.getResolvedClasspath\n(JavaProject.java:1483)\n        at org.eclipse.jdt.internal.core.JavaProject.getResolvedClasspath\n(JavaProject.java:1450)\n        at org.eclipse.jdt.internal.core.DeltaProcessor.updateClasspathMarkers\n(DeltaProcessor.java:1661)\n        at org.eclipse.jdt.internal.core.DeltaProcessor.resourceChanged\n(DeltaProcessor.java:1426)\n        at org.eclipse.core.internal.events.NotificationManager$1.run\n(NotificationManager.java:128)\n        at org.eclipse.core.internal.runtime.InternalPlatform.run\n(InternalPlatform.java:839)\n        at org.eclipse.core.runtime.Platform.run(Platform.java:413)\n        at org.eclipse.core.internal.events.NotificationManager.notify\n(NotificationManager.java:143)\n        at org.eclipse.core.internal.events.NotificationManager.broadcastChanges\n(NotificationManager.java:67)\n        at org.eclipse.core.internal.resources.Workspace.broadcastChanges\n(Workspace.java:133)\n        at org.eclipse.core.internal.resources.Workspace.endOperation\n(Workspace.java:742)\n        at org.eclipse.core.internal.resources.Workspace.run\n(Workspace.java:1383)\n        at org.eclipse.ui.actions.WorkspaceModifyOperation.run\n(WorkspaceModifyOperation.java:78)\n        at org.eclipse.jface.operation.ModalContext$ModalContextThread.run\n(ModalContext.java:98)",
    "Fixed, got burned by deleted projects.",
    "*** Bug 24210 has been marked as a duplicate of this bug. ***",
    "Verified."
  ],
  "commentCreationDates": [
    "2002-09-25T16:03:20+02:00",
    "2002-09-25T17:47:52+02:00",
    "2002-09-30T10:42:12+02:00",
    "2002-10-17T16:22:32+02:00"
  ],
  "traces": [
    {
      "exceptionType": "java.lang.NullPointerException",
      "elements": [
        {
          "method": "org.eclipse.jdt.internal.core.JavaProject.loadPreferences",
          "source": "JavaProject.java:1757"
        },
        {
          "method": "org.eclipse.jdt.internal.core.JavaProject.getPreferences",
          "source": "JavaProject.java:1366"
        },
        {
          "method": "org.eclipse.jdt.internal.core.JavaProject.getOption",
          "source": "JavaProject.java:1092"
        },
        {
          "method": "org.eclipse.jdt.internal.core.JavaProject.getResolvedClasspath",
          "source": "JavaProject.java:1483"
        },
        {
          "method": "org.eclipse.jdt.internal.core.JavaProject.getResolvedClasspath",
          "source": "JavaProject.java:1450"
        },
        {
          "method": "org.eclipse.jdt.internal.core.DeltaProcessor.updateClasspathMarkers",
          "source": "DeltaProcessor.java:1661"
        },
        {
          "method": "org.eclipse.jdt.internal.core.DeltaProcessor.resourceChanged",
          "source": "DeltaProcessor.java:1426"
        },
        {
          "method": "org.eclipse.core.internal.events.NotificationManager$1.run",
          "source": "NotificationManager.java:128"
        },
        {
          "method": "org.eclipse.core.internal.runtime.InternalPlatform.run",
          "source": "InternalPlatform.java:839"
        },
        {
          "method": "org.eclipse.core.runtime.Platform.run",
          "source": "Platform.java:413"
        },
        {
          "method": "org.eclipse.core.internal.events.NotificationManager.notify",
          "source": "NotificationManager.java:143"
        },
        {
          "method": "org.eclipse.core.internal.events.NotificationManager.broadcastChanges",
          "source": "NotificationManager.java:67"
        },
        {
          "method": "org.eclipse.core.internal.resources.Workspace.broadcastChanges",
          "source": "Workspace.java:133"
        },
        {
          "method": "org.eclipse.core.internal.resources.Workspace.endOperation",
          "source": "Workspace.java:742"
        },
        {
          "method": "org.eclipse.core.internal.resources.Workspace.run",
          "source": "Workspace.java:1383"
        },
        {
          "method": "org.eclipse.ui.actions.WorkspaceModifyOperation.run",
          "source": "WorkspaceModifyOperation.java:78"
        },
        {
          "method": "org.eclipse.jface.operation.ModalContext$ModalContextThread.run",
          "source": "ModalContext.java:98"
        }
      ],
      "number": 0,
      "commentIndex": 0,
      "bugId": "24083",
      "date": "2002-09-25T16:03:20+02:00",
      "product": "JDT",
      "component": "Core",
      "severity": "normal"
    }
  ],
  "groupId": "24083",
  "bugId": "24083",
  "date": "2002-09-25T16:03:20+02:00",
  "product": "JDT",
  "component": "Core",
  "severity": "normal"
}