{
  "comments": [
    "I can not start eclipse. It will only bounce a couple of times and then disapear. The \nworkspace-folder are created.\n\nI am running Jaguar and have tried to log in as a different user and remove everything \nfrom /Library/Java/Extensions. Nothing helps\n\nin workspace/.metadata/.log:\n\n!SESSION ----------------------------------------------------------------------\n!ENTRY org.eclipse.core.launcher 4 0 Sep 25, 2002 23:44:48.597\n!MESSAGE Exception launching the Eclipse Platform:\n!STACK\njava.lang.ExceptionInInitializerError: java.lang.ClassCastException: \norg.apache.xerces.parsers.StandardParserConfiguration\n        at org.apache.xerces.parsers.SAXParser.\u003cinit\u003e(SAXParser.java:95)\n        at \norg.eclipse.core.internal.plugins.PluginParser.initializeParser(PluginParser.java:78)\n        at org.eclipse.core.internal.plugins.PluginParser.\u003cclinit\u003e(PluginParser.java:43)\n        at \norg.eclipse.core.internal.plugins.RegistryLoader.processManifestFile(RegistryLoader.jav\na:89)\n        at \norg.eclipse.core.internal.plugins.RegistryLoader.processPluginPathFile(RegistryLoader.j\nava:136)\n        at \norg.eclipse.core.internal.plugins.RegistryLoader.processPluginPathEntry(RegistryLoade\nr.java:127)\n        at \norg.eclipse.core.internal.plugins.RegistryLoader.processManifestFiles(RegistryLoader.ja\nva:104)\n        at \norg.eclipse.core.internal.plugins.RegistryLoader.parseRegistry(RegistryLoader.java:63)\n        at \norg.eclipse.core.internal.plugins.RegistryLoader.parseRegistry(RegistryLoader.java:71)\n        at \norg.eclipse.core.internal.runtime.InternalPlatform.parsePlugins(InternalPlatform.java:742\n)\n        at \norg.eclipse.core.internal.runtime.InternalPlatform.loadRegistry(InternalPlatform.java:686)\n        at \norg.eclipse.core.internal.runtime.InternalPlatform.loaderStartup(InternalPlatform.java:562\n)\n        at java.lang.reflect.Method.invoke(Native Method)\n        at \norg.eclipse.core.internal.boot.InternalBootLoader.startup(InternalBootLoader.java:909)\n        at \norg.eclipse.core.internal.boot.InternalBootLoader.run(InternalBootLoader.java:768)\n        at org.eclipse.core.boot.BootLoader.run(BootLoader.java:462)\n        at java.lang.reflect.Method.invoke(Native Method)\n        at org.eclipse.core.launcher.Main.basicRun(Main.java:247)\n        at org.eclipse.core.launcher.Main.run(Main.java:703)\n        at org.eclipse.core.launcher.Main.main(Main.java:539)\n        at java.lang.reflect.Method.invoke(Native Method)\n        at com.apple.buckyball.app.LaunchRunner.run(LaunchRunner.java:82)\n        at com.apple.buckyball.app.LaunchRunner.callMain(LaunchRunner.java:44)\n        at com.apple.buckyball.app.CarbonLibApp.launch(CarbonLibApp.java:67)",
    "Please make sure not to have any other (incompatible) xerces or lucene jar files on your \nclasspath. Check in:\n  /Library/Java/Home/lib/ext\n  /Library/Java/Extensions\n  ~/Library/Java/Extensions\nAnd throw away the workspace before restarting Eclipse.\nLet me know if this fixes your problem.",
    "I have tried to remove all jars from those locations, but it dit not help. I have WebObjects \n5.1.4 installed and I think it has xerces in its XML-framework. Other people are using WO \nand eclipse side by side without problems.\n\nI have altso tried to log in as a different user on the same machine. Does not help.\n\nHave tried with SDK-N20020925-macosx and 0926. They all had the same problem on \nmy iMac.",
    "\n\n*** This bug has been marked as a duplicate of 21214 ***"
  ],
  "commentCreationDates": [
    "2002-09-25T23:34:28+02:00",
    "2002-09-26T15:54:49+02:00",
    "2002-09-26T22:40:57+02:00",
    "2002-10-02T19:18:08+02:00"
  ],
  "traces": [
    {
      "exceptionType": "java.lang.ClassCastException",
      "message": "org.apache.xerces.parsers.StandardParserConfiguration",
      "elements": [
        {
          "method": "org.apache.xerces.parsers.SAXParser.\u003cinit\u003e",
          "source": "SAXParser.java:95"
        },
        {
          "method": "org.eclipse.core.internal.plugins.PluginParser.initializeParser",
          "source": "PluginParser.java:78"
        },
        {
          "method": "org.eclipse.core.internal.plugins.PluginParser.\u003cclinit\u003e",
          "source": "PluginParser.java:43"
        },
        {
          "method": "org.eclipse.core.internal.plugins.RegistryLoader.processManifestFile",
          "source": "RegistryLoader.jav a:89"
        },
        {
          "method": "org.eclipse.core.internal.plugins.RegistryLoader.processPluginPathFile",
          "source": "RegistryLoader.j ava:136"
        },
        {
          "method": "org.eclipse.core.internal.plugins.RegistryLoader.processPluginPathEntry",
          "source": "RegistryLoade r.java:127"
        },
        {
          "method": "org.eclipse.core.internal.plugins.RegistryLoader.processManifestFiles",
          "source": "RegistryLoader.ja va:104"
        },
        {
          "method": "org.eclipse.core.internal.plugins.RegistryLoader.parseRegistry",
          "source": "RegistryLoader.java:63"
        },
        {
          "method": "org.eclipse.core.internal.plugins.RegistryLoader.parseRegistry",
          "source": "RegistryLoader.java:71"
        },
        {
          "method": "org.eclipse.core.internal.runtime.InternalPlatform.parsePlugins",
          "source": "InternalPlatform.java:742 "
        },
        {
          "method": "org.eclipse.core.internal.runtime.InternalPlatform.loadRegistry",
          "source": "InternalPlatform.java:686"
        },
        {
          "method": "org.eclipse.core.internal.runtime.InternalPlatform.loaderStartup",
          "source": "InternalPlatform.java:562 "
        },
        {
          "method": "java.lang.reflect.Method.invoke",
          "source": "Native Method"
        },
        {
          "method": "org.eclipse.core.internal.boot.InternalBootLoader.startup",
          "source": "InternalBootLoader.java:909"
        },
        {
          "method": "org.eclipse.core.internal.boot.InternalBootLoader.run",
          "source": "InternalBootLoader.java:768"
        },
        {
          "method": "org.eclipse.core.boot.BootLoader.run",
          "source": "BootLoader.java:462"
        },
        {
          "method": "java.lang.reflect.Method.invoke",
          "source": "Native Method"
        },
        {
          "method": "org.eclipse.core.launcher.Main.basicRun",
          "source": "Main.java:247"
        },
        {
          "method": "org.eclipse.core.launcher.Main.run",
          "source": "Main.java:703"
        },
        {
          "method": "org.eclipse.core.launcher.Main.main",
          "source": "Main.java:539"
        },
        {
          "method": "java.lang.reflect.Method.invoke",
          "source": "Native Method"
        },
        {
          "method": "com.apple.buckyball.app.LaunchRunner.run",
          "source": "LaunchRunner.java:82"
        },
        {
          "method": "com.apple.buckyball.app.LaunchRunner.callMain",
          "source": "LaunchRunner.java:44"
        },
        {
          "method": "com.apple.buckyball.app.CarbonLibApp.launch",
          "source": "CarbonLibApp.java:67"
        }
      ],
      "number": 0,
      "commentIndex": 0,
      "bugId": "24107",
      "duplicateId": "21214",
      "date": "2002-09-25T23:34:28+02:00",
      "product": "Platform",
      "component": "Resources",
      "severity": "blocker"
    }
  ],
  "groupId": "19252",
  "bugId": "24107",
  "duplicateId": "21214",
  "date": "2002-09-25T23:34:28+02:00",
  "product": "Platform",
  "component": "Resources",
  "severity": "blocker"
}