{
  "comments": [
    "This problem occurs on both the 2.0.1 release and the stable M1 build. I am running Red Hat 7.2 retrofitted with the gtk2-2.0.2, atk-1.0.1 and pango-1.0.1 RPMs from Red Hat 7.3. Yes, glib2-2.0.1 is also installed. Starting eclipse for the first time results in the following error (M1 build). Note that there is no information on what symbol is actually missing: it\u0027s a blank here, sometimes it is some random character.\n\njava.lang.UnsatisfiedLinkError: /usr/local/eclipse/plugins/org.eclipse.swt.gtk_2.1.0/os/linux/x86/libswt-pi-gtk-2108.so: : shared object not open\n        at java.lang.ClassLoader$NativeLibrary.load(Native Method)\n        at java.lang.ClassLoader.loadLibrary0(ClassLoader.java:1480)\n        at java.lang.ClassLoader.loadLibrary(ClassLoader.java:1388)\n        at java.lang.Runtime.loadLibrary0(Runtime.java:772)\n        at java.lang.System.loadLibrary(System.java:832)\n        at org.eclipse.swt.internal.Library.loadLibrary(Library.java:104)\n        at org.eclipse.swt.internal.gtk.OS.\u003cclinit\u003e(OS.java:19)\n        at org.eclipse.swt.widgets.Display.createDisplay(Display.java:404)\n        at org.eclipse.swt.widgets.Display.create(Display.java:398)\n        at org.eclipse.swt.graphics.Device.\u003cinit\u003e(Device.java:103)\n        at org.eclipse.swt.widgets.Display.\u003cinit\u003e(Display.java:284)\n        at org.eclipse.swt.widgets.Display.\u003cinit\u003e(Display.java:280)\n        at org.eclipse.ui.internal.Workbench.run(Workbench.java:1221)\n        at org.eclipse.core.internal.boot.InternalBootLoader.run(InternalBootLoader.java:775)\n        at org.eclipse.core.boot.BootLoader.run(BootLoader.java:462)\n        at sun.reflect.NativeMethodAccessorImpl.invoke0(Native Method)\n        at sun.reflect.NativeMethodAccessorImpl.invoke(NativeMethodAccessorImpl.java:39)\n        at sun.reflect.DelegatingMethodAccessorImpl.invoke(DelegatingMethodAccessorImpl.java:25)\n        at java.lang.reflect.Method.invoke(Method.java:324)\n        at org.eclipse.core.launcher.Main.basicRun(Main.java:247)\n        at org.eclipse.core.launcher.Main.run(Main.java:703)\n        at org.eclipse.core.launcher.Main.main(Main.java:539)",
    "GG to investigate and adivse.  Running SWT on Linux GTK is a bit of a black \nart.  Can we make a FAQ describing DLL versions etc.?",
    "Chris, Have you been able to run the GTK demo that you can download from the \ngtk web site? (From web site: \"You can test your GTK+ installation by running \nthe gtk-demo program that GTK+ installs\").\n\nIt definitely sounds like the installation of GTK2 did not succeed.",
    "No, it is not a gtk installation problem. The gtk2 RPM comes with  gtk-demo, which runs fine (I just tested it). ",
    "I noticed on the newsgroup that this is now working (changed versions of pango \nand freetype).  So changing status of report to WORKSFORME since there were no \nrequired changes on this end.\n"
  ],
  "commentCreationDates": [
    "2002-10-16T22:25:30+02:00",
    "2002-10-18T15:52:06+02:00",
    "2002-10-23T15:29:34+02:00",
    "2002-10-23T16:01:33+02:00",
    "2002-10-24T14:01:22+02:00"
  ],
  "traces": [
    {
      "exceptionType": "java.lang.UnsatisfiedLinkError",
      "message": "/usr/local/eclipse/plugins/org.eclipse.swt.gtk_2.1.0/os/linux/x86/libswt-pi-gtk-2108.so: : shared object not open",
      "elements": [
        {
          "method": "java.lang.ClassLoader$NativeLibrary.load",
          "source": "Native Method"
        },
        {
          "method": "java.lang.ClassLoader.loadLibrary0",
          "source": "ClassLoader.java:1480"
        },
        {
          "method": "java.lang.ClassLoader.loadLibrary",
          "source": "ClassLoader.java:1388"
        },
        {
          "method": "java.lang.Runtime.loadLibrary0",
          "source": "Runtime.java:772"
        },
        {
          "method": "java.lang.System.loadLibrary",
          "source": "System.java:832"
        },
        {
          "method": "org.eclipse.swt.internal.Library.loadLibrary",
          "source": "Library.java:104"
        },
        {
          "method": "org.eclipse.swt.internal.gtk.OS.\u003cclinit\u003e",
          "source": "OS.java:19"
        },
        {
          "method": "org.eclipse.swt.widgets.Display.createDisplay",
          "source": "Display.java:404"
        },
        {
          "method": "org.eclipse.swt.widgets.Display.create",
          "source": "Display.java:398"
        },
        {
          "method": "org.eclipse.swt.graphics.Device.\u003cinit\u003e",
          "source": "Device.java:103"
        },
        {
          "method": "org.eclipse.swt.widgets.Display.\u003cinit\u003e",
          "source": "Display.java:284"
        },
        {
          "method": "org.eclipse.swt.widgets.Display.\u003cinit\u003e",
          "source": "Display.java:280"
        },
        {
          "method": "org.eclipse.ui.internal.Workbench.run",
          "source": "Workbench.java:1221"
        },
        {
          "method": "org.eclipse.core.internal.boot.InternalBootLoader.run",
          "source": "InternalBootLoader.java:775"
        },
        {
          "method": "org.eclipse.core.boot.BootLoader.run",
          "source": "BootLoader.java:462"
        },
        {
          "method": "sun.reflect.NativeMethodAccessorImpl.invoke0",
          "source": "Native Method"
        },
        {
          "method": "sun.reflect.NativeMethodAccessorImpl.invoke",
          "source": "NativeMethodAccessorImpl.java:39"
        },
        {
          "method": "sun.reflect.DelegatingMethodAccessorImpl.invoke",
          "source": "DelegatingMethodAccessorImpl.java:25"
        },
        {
          "method": "java.lang.reflect.Method.invoke",
          "source": "Method.java:324"
        },
        {
          "method": "org.eclipse.core.launcher.Main.basicRun",
          "source": "Main.java:247"
        },
        {
          "method": "org.eclipse.core.launcher.Main.run",
          "source": "Main.java:703"
        },
        {
          "method": "org.eclipse.core.launcher.Main.main",
          "source": "Main.java:539"
        }
      ],
      "number": 0,
      "commentIndex": 0,
      "bugId": "24867",
      "date": "2002-10-16T22:25:30+02:00",
      "product": "Platform",
      "component": "SWT",
      "severity": "critical"
    }
  ],
  "groupId": "24867",
  "bugId": "24867",
  "date": "2002-10-16T22:25:30+02:00",
  "product": "Platform",
  "component": "SWT",
  "severity": "critical"
}