{
  "comments": [
    "Build 20021016\nLinux-GTK\n\nIt\u0027s the second time I get this problem. After a while, the pop-up menu stop\nworking, every time I right click on an element, I get an internal error dialog:\n\"A SWT error has occured [...] Exit workspace?\"\n\nI get the following message on the consol:\n\nbind fail, no free callback slot ******* \nUnhandled exception caught in event loop.\nReason:\nNo more callbacks\n\nand the following trace in the log file:\n\n!ENTRY org.eclipse.ui 4 4 Oct 17, 2002 13:38:38.31\n!MESSAGE Unhandled exception caught in event loop.\n!ENTRY org.eclipse.ui 4 0 Oct 17, 2002 13:38:38.35\n!MESSAGE No more callbacks\n!STACK 0\norg.eclipse.swt.SWTError: No more callbacks\n        at org.eclipse.swt.SWT.error(SWT.java:2164)\n        at org.eclipse.swt.SWT.error(SWT.java:2071)\n        at org.eclipse.swt.widgets.Widget.error(Widget.java:294)\n        at org.eclipse.swt.widgets.Menu.setVisible(Menu.java:784)\n        at org.eclipse.swt.widgets.Control.processMouseDown(Control.java:1778)\n        at org.eclipse.swt.widgets.Composite.processMouseDown(Composite.java:448)\n        at org.eclipse.swt.widgets.Table.processMouseDown(Table.java:910)\n        at org.eclipse.swt.widgets.Widget.processEvent(Widget.java:589)\n        at org.eclipse.swt.widgets.Table.processEvent(Table.java:863)\n        at org.eclipse.swt.widgets.Display.windowProc(Display.java:1774)\n        at org.eclipse.swt.internal.gtk.OS.gtk_main_iteration(Native Method)\n        at org.eclipse.swt.widgets.Display.readAndDispatch(Display.java:1242)\n        at org.eclipse.ui.internal.Workbench.runEventLoop(Workbench.java:1420)\n        at org.eclipse.ui.internal.Workbench.run(Workbench.java:1403)\n        at\norg.eclipse.core.internal.boot.InternalBootLoader.run(InternalBootLoader.java:775)\n        at org.eclipse.core.boot.BootLoader.run(BootLoader.java:462)\n        at sun.reflect.NativeMethodAccessorImpl.invoke0(Native Method)\n        at\nsun.reflect.NativeMethodAccessorImpl.invoke(NativeMethodAccessorImpl.java:39)\n        at\nsun.reflect.DelegatingMethodAccessorImpl.invoke(DelegatingMethodAccessorImpl.java:25)\n        at java.lang.reflect.Method.invoke(Method.java:324)\n        at org.eclipse.core.launcher.Main.basicRun(Main.java:247)\n        at org.eclipse.core.launcher.Main.run(Main.java:703)\n        at org.eclipse.core.launcher.Main.main(Main.java:539)",
    "\n\n*** This bug has been marked as a duplicate of 25017 ***"
  ],
  "commentCreationDates": [
    "2002-10-17T20:20:43+02:00",
    "2002-10-18T15:49:00+02:00"
  ],
  "traces": [
    {
      "exceptionType": "org.eclipse.swt.SWTError",
      "message": "No more callbacks",
      "elements": [
        {
          "method": "org.eclipse.swt.SWT.error",
          "source": "SWT.java:2164"
        },
        {
          "method": "org.eclipse.swt.SWT.error",
          "source": "SWT.java:2071"
        },
        {
          "method": "org.eclipse.swt.widgets.Widget.error",
          "source": "Widget.java:294"
        },
        {
          "method": "org.eclipse.swt.widgets.Menu.setVisible",
          "source": "Menu.java:784"
        },
        {
          "method": "org.eclipse.swt.widgets.Control.processMouseDown",
          "source": "Control.java:1778"
        },
        {
          "method": "org.eclipse.swt.widgets.Composite.processMouseDown",
          "source": "Composite.java:448"
        },
        {
          "method": "org.eclipse.swt.widgets.Table.processMouseDown",
          "source": "Table.java:910"
        },
        {
          "method": "org.eclipse.swt.widgets.Widget.processEvent",
          "source": "Widget.java:589"
        },
        {
          "method": "org.eclipse.swt.widgets.Table.processEvent",
          "source": "Table.java:863"
        },
        {
          "method": "org.eclipse.swt.widgets.Display.windowProc",
          "source": "Display.java:1774"
        },
        {
          "method": "org.eclipse.swt.internal.gtk.OS.gtk_main_iteration",
          "source": "Native Method"
        },
        {
          "method": "org.eclipse.swt.widgets.Display.readAndDispatch",
          "source": "Display.java:1242"
        },
        {
          "method": "org.eclipse.ui.internal.Workbench.runEventLoop",
          "source": "Workbench.java:1420"
        },
        {
          "method": "org.eclipse.ui.internal.Workbench.run",
          "source": "Workbench.java:1403"
        },
        {
          "method": "org.eclipse.core.internal.boot.InternalBootLoader.run",
          "source": "InternalBootLoader.java:775"
        },
        {
          "method": "org.eclipse.core.boot.BootLoader.run",
          "source": "BootLoader.java:462"
        },
        {
          "method": "sun.reflect.NativeMethodAccessorImpl.invoke0",
          "source": "Native Method"
        },
        {
          "method": "sun.reflect.NativeMethodAccessorImpl.invoke",
          "source": "NativeMethodAccessorImpl.java:39"
        },
        {
          "method": "sun.reflect.DelegatingMethodAccessorImpl.invoke",
          "source": "DelegatingMethodAccessorImpl.java:25"
        },
        {
          "method": "java.lang.reflect.Method.invoke",
          "source": "Method.java:324"
        },
        {
          "method": "org.eclipse.core.launcher.Main.basicRun",
          "source": "Main.java:247"
        },
        {
          "method": "org.eclipse.core.launcher.Main.run",
          "source": "Main.java:703"
        },
        {
          "method": "org.eclipse.core.launcher.Main.main",
          "source": "Main.java:539"
        }
      ],
      "number": 0,
      "commentIndex": 0,
      "bugId": "25011",
      "duplicateId": "25017",
      "date": "2002-10-17T20:20:43+02:00",
      "product": "Platform",
      "component": "SWT",
      "severity": "normal"
    }
  ],
  "groupId": "24055",
  "bugId": "25011",
  "duplicateId": "25017",
  "date": "2002-10-17T20:20:43+02:00",
  "product": "Platform",
  "component": "SWT",
  "severity": "normal"
}