{
  "comments": [
    "Build 20021022\n\n1. Replace ClasspathTests with the attached version\n2. Position the cursor in testDeleteProjectSetCPAnotherProject() where \nindicated.\n3. Ctrl-Space\nObserve: You get the following NPE:\njava.lang.NullPointerException\n        at \norg.eclipse.jdt.internal.codeassist.complete.CompletionParser.buildMoreCompletio\nnContext(CompletionParser.java:207)\n        at \norg.eclipse.jdt.internal.codeassist.complete.CompletionParser.attachOrphanComple\ntionNode(CompletionParser.java:167)\n        at \norg.eclipse.jdt.internal.codeassist.complete.CompletionParser.updateRecoveryStat\ne(CompletionParser.java:1555)\n        at org.eclipse.jdt.internal.compiler.parser.Parser.resumeOnSyntaxError\n(Parser.java:7440)\n        at org.eclipse.jdt.internal.compiler.parser.Parser.parse\n(Parser.java:6793)\n        at \norg.eclipse.jdt.internal.codeassist.impl.AssistParser.parseBlockStatements\n(AssistParser.java:853)\n        at \norg.eclipse.jdt.internal.codeassist.impl.AssistParser.parseBlockStatements\n(AssistParser.java:767)\n        at org.eclipse.jdt.internal.codeassist.impl.Engine.parseMethod\n(Engine.java:166)\n        at org.eclipse.jdt.internal.codeassist.impl.Engine.parseMethod\n(Engine.java:135)\n        at org.eclipse.jdt.internal.codeassist.CompletionEngine.complete\n(CompletionEngine.java:813)\n        at org.eclipse.jdt.internal.core.Openable.codeComplete\n(Openable.java:124)\n        at org.eclipse.jdt.internal.core.CompilationUnit.codeComplete\n(CompilationUnit.java:101)\n        at \norg.eclipse.jdt.internal.ui.text.java.JavaCompletionProcessor.internalComputeCom\npletionProposals(JavaCompletionProcessor.java:342)\n        at \norg.eclipse.jdt.internal.ui.text.java.JavaCompletionProcessor.computeCompletionP\nroposals(JavaCompletionProcessor.java:300)\n        at \norg.eclipse.jface.text.contentassist.ContentAssistant.computeCompletionProposals\n(ContentAssistant.java:1279)\n        at \norg.eclipse.jface.text.contentassist.CompletionProposalPopup.computeProposals\n(CompletionProposalPopup.java:177)\n        at org.eclipse.jface.text.contentassist.CompletionProposalPopup.access$7\n(CompletionProposalPopup.java:176)\n        at org.eclipse.jface.text.contentassist.CompletionProposalPopup$3.run\n(CompletionProposalPopup.java:138)\n        at org.eclipse.swt.custom.BusyIndicator.showWhile(BusyIndicator.java:66)\n        at \norg.eclipse.jface.text.contentassist.CompletionProposalPopup.showProposals\n(CompletionProposalPopup.java:133)\n        at \norg.eclipse.jface.text.contentassist.ContentAssistant.showPossibleCompletions\n(ContentAssistant.java:1199)\n        at \norg.eclipse.jdt.internal.ui.javaeditor.CompilationUnitEditor$AdaptedSourceViewer\n.doOperation(CompilationUnitEditor.java:226)\n        at org.eclipse.ui.texteditor.ContentAssistAction$1.run\n(ContentAssistAction.java:84)\n        at org.eclipse.swt.custom.BusyIndicator.showWhile(BusyIndicator.java:66)\n        at org.eclipse.ui.texteditor.ContentAssistAction.run\n(ContentAssistAction.java:82)\n        at org.eclipse.ui.internal.WWinKeyBindingService.invoke\n(WWinKeyBindingService.java:134)\n        at org.eclipse.ui.internal.WWinKeyBindingService.pressed\n(WWinKeyBindingService.java:109)\n        at org.eclipse.ui.internal.WWinKeyBindingService$5.widgetSelected\n(WWinKeyBindingService.java:325)\n        at org.eclipse.ui.internal.AcceleratorMenu$2.handleEvent\n(AcceleratorMenu.java:53)\n        at org.eclipse.swt.widgets.EventTable.sendEvent(EventTable.java:77)\n        at org.eclipse.swt.widgets.Widget.sendEvent(Widget.java:833)\n        at org.eclipse.swt.widgets.Display.runDeferredEvents(Display.java:1622)\n        at org.eclipse.swt.widgets.Display.readAndDispatch(Display.java:1368)\n        at org.eclipse.ui.internal.Workbench.runEventLoop(Workbench.java:1420)\n        at org.eclipse.ui.internal.Workbench.run(Workbench.java:1403)\n        at org.eclipse.core.internal.boot.InternalBootLoader.run\n(InternalBootLoader.java:775)\n        at org.eclipse.core.boot.BootLoader.run(BootLoader.java:462)\n        at sun.reflect.NativeMethodAccessorImpl.invoke0(Native Method)\n        at sun.reflect.NativeMethodAccessorImpl.invoke\n(NativeMethodAccessorImpl.java:39)\n        at sun.reflect.DelegatingMethodAccessorImpl.invoke\n(DelegatingMethodAccessorImpl.java:25)\n        at java.lang.reflect.Method.invoke(Method.java:324)\n        at org.eclipse.core.launcher.Main.basicRun(Main.java:247)\n        at org.eclipse.core.launcher.Main.run(Main.java:703)\n        at org.eclipse.core.launcher.Main.main(Main.java:539)",
    "Created an attachment (id\u003d2255)\nClasspathTest.java\n",
    "Null check added\n\nFixed.",
    "Verified."
  ],
  "commentCreationDates": [
    "2002-10-23T12:20:32+02:00",
    "2002-10-23T12:21:49+02:00",
    "2002-10-23T17:29:55+02:00",
    "2002-11-13T09:45:57+01:00"
  ],
  "traces": [
    {
      "exceptionType": "java.lang.NullPointerException",
      "elements": [
        {
          "method": "org.eclipse.jdt.internal.codeassist.complete.CompletionParser.buildMoreCompletionContext",
          "source": "CompletionParser.java:207"
        },
        {
          "method": "org.eclipse.jdt.internal.codeassist.complete.CompletionParser.attachOrphanCompletionNode",
          "source": "CompletionParser.java:167"
        },
        {
          "method": "org.eclipse.jdt.internal.codeassist.complete.CompletionParser.updateRecoveryState",
          "source": "CompletionParser.java:1555"
        },
        {
          "method": "org.eclipse.jdt.internal.compiler.parser.Parser.resumeOnSyntaxError",
          "source": "Parser.java:7440"
        },
        {
          "method": "org.eclipse.jdt.internal.compiler.parser.Parser.parse",
          "source": "Parser.java:6793"
        },
        {
          "method": "org.eclipse.jdt.internal.codeassist.impl.AssistParser.parseBlockStatements",
          "source": "AssistParser.java:853"
        },
        {
          "method": "org.eclipse.jdt.internal.codeassist.impl.AssistParser.parseBlockStatements",
          "source": "AssistParser.java:767"
        },
        {
          "method": "org.eclipse.jdt.internal.codeassist.impl.Engine.parseMethod",
          "source": "Engine.java:166"
        },
        {
          "method": "org.eclipse.jdt.internal.codeassist.impl.Engine.parseMethod",
          "source": "Engine.java:135"
        },
        {
          "method": "org.eclipse.jdt.internal.codeassist.CompletionEngine.complete",
          "source": "CompletionEngine.java:813"
        },
        {
          "method": "org.eclipse.jdt.internal.core.Openable.codeComplete",
          "source": "Openable.java:124"
        },
        {
          "method": "org.eclipse.jdt.internal.core.CompilationUnit.codeComplete",
          "source": "CompilationUnit.java:101"
        },
        {
          "method": "org.eclipse.jdt.internal.ui.text.java.JavaCompletionProcessor.internalComputeCompletionProposals",
          "source": "JavaCompletionProcessor.java:342"
        },
        {
          "method": "org.eclipse.jdt.internal.ui.text.java.JavaCompletionProcessor.computeCompletionProposals",
          "source": "JavaCompletionProcessor.java:300"
        },
        {
          "method": "org.eclipse.jface.text.contentassist.ContentAssistant.computeCompletionProposals",
          "source": "ContentAssistant.java:1279"
        },
        {
          "method": "org.eclipse.jface.text.contentassist.CompletionProposalPopup.computeProposals",
          "source": "CompletionProposalPopup.java:177"
        },
        {
          "method": "org.eclipse.jface.text.contentassist.CompletionProposalPopup.access$7",
          "source": "CompletionProposalPopup.java:176"
        },
        {
          "method": "org.eclipse.jface.text.contentassist.CompletionProposalPopup$3.run",
          "source": "CompletionProposalPopup.java:138"
        },
        {
          "method": "org.eclipse.swt.custom.BusyIndicator.showWhile",
          "source": "BusyIndicator.java:66"
        },
        {
          "method": "org.eclipse.jface.text.contentassist.CompletionProposalPopup.showProposals",
          "source": "CompletionProposalPopup.java:133"
        },
        {
          "method": "org.eclipse.jface.text.contentassist.ContentAssistant.showPossibleCompletions",
          "source": "ContentAssistant.java:1199"
        },
        {
          "method": "org.eclipse.jdt.internal.ui.javaeditor.CompilationUnitEditor$AdaptedSourceViewer.doOperation",
          "source": "CompilationUnitEditor.java:226"
        },
        {
          "method": "org.eclipse.ui.texteditor.ContentAssistAction$1.run",
          "source": "ContentAssistAction.java:84"
        },
        {
          "method": "org.eclipse.swt.custom.BusyIndicator.showWhile",
          "source": "BusyIndicator.java:66"
        },
        {
          "method": "org.eclipse.ui.texteditor.ContentAssistAction.run",
          "source": "ContentAssistAction.java:82"
        },
        {
          "method": "org.eclipse.ui.internal.WWinKeyBindingService.invoke",
          "source": "WWinKeyBindingService.java:134"
        },
        {
          "method": "org.eclipse.ui.internal.WWinKeyBindingService.pressed",
          "source": "WWinKeyBindingService.java:109"
        },
        {
          "method": "org.eclipse.ui.internal.WWinKeyBindingService$5.widgetSelected",
          "source": "WWinKeyBindingService.java:325"
        },
        {
          "method": "org.eclipse.ui.internal.AcceleratorMenu$2.handleEvent",
          "source": "AcceleratorMenu.java:53"
        },
        {
          "method": "org.eclipse.swt.widgets.EventTable.sendEvent",
          "source": "EventTable.java:77"
        },
        {
          "method": "org.eclipse.swt.widgets.Widget.sendEvent",
          "source": "Widget.java:833"
        },
        {
          "method": "org.eclipse.swt.widgets.Display.runDeferredEvents",
          "source": "Display.java:1622"
        },
        {
          "method": "org.eclipse.swt.widgets.Display.readAndDispatch",
          "source": "Display.java:1368"
        },
        {
          "method": "org.eclipse.ui.internal.Workbench.runEventLoop",
          "source": "Workbench.java:1420"
        },
        {
          "method": "org.eclipse.ui.internal.Workbench.run",
          "source": "Workbench.java:1403"
        },
        {
          "method": "org.eclipse.core.internal.boot.InternalBootLoader.run",
          "source": "InternalBootLoader.java:775"
        },
        {
          "method": "org.eclipse.core.boot.BootLoader.run",
          "source": "BootLoader.java:462"
        },
        {
          "method": "sun.reflect.NativeMethodAccessorImpl.invoke0",
          "source": "Native Method"
        },
        {
          "method": "sun.reflect.NativeMethodAccessorImpl.invoke",
          "source": "NativeMethodAccessorImpl.java:39"
        },
        {
          "method": "sun.reflect.DelegatingMethodAccessorImpl.invoke",
          "source": "DelegatingMethodAccessorImpl.java:25"
        },
        {
          "method": "java.lang.reflect.Method.invoke",
          "source": "Method.java:324"
        },
        {
          "method": "org.eclipse.core.launcher.Main.basicRun",
          "source": "Main.java:247"
        },
        {
          "method": "org.eclipse.core.launcher.Main.run",
          "source": "Main.java:703"
        },
        {
          "method": "org.eclipse.core.launcher.Main.main",
          "source": "Main.java:539"
        }
      ],
      "number": 0,
      "commentIndex": 0,
      "bugId": "25233",
      "date": "2002-10-23T12:20:32+02:00",
      "product": "JDT",
      "component": "Core",
      "severity": "major"
    }
  ],
  "groupId": "25233",
  "bugId": "25233",
  "date": "2002-10-23T12:20:32+02:00",
  "product": "JDT",
  "component": "Core",
  "severity": "major"
}