{
  "comments": [
    "I am trying to run Eclipse on a Linux box (RedHat 7.3) using a Windows machine \nrunning X-Win32 as a display (it\u0027s a X-Server emulator we use rather \nsuccessfully for any other X11 application).\n\nEclipse crashes with the following message:\n\njava.lang.ArrayIndexOutOfBoundsException\n        at org.eclipse.swt.graphics.ImageData.blit(ImageData.java:2318)\n        at org.eclipse.swt.graphics.Image.putImage(Image.java:1200)\n        at org.eclipse.swt.graphics.Image.init(Image.java:988)\n        at org.eclipse.swt.graphics.Image.\u003cinit\u003e(Image.java:446)\n        at\norg.eclipse.jface.action.ActionContributionItem$ImageCache.getGrayImage(\nActionContributionItem.java:105)\n        at\norg.eclipse.jface.action.ActionContributionItem.updateImages(ActionContr\nibutionItem.java:602)\n        at\norg.eclipse.jface.action.ActionContributionItem.update(ActionContributio\nnItem.java:468)\n        at\norg.eclipse.jface.action.ActionContributionItem.fill(ActionContributionI\ntem.java:287)\n        at\norg.eclipse.jface.action.ToolBarManager.update(ToolBarManager.java:230)\n        at\norg.eclipse.ui.internal.WorkbenchWindow.addPerspectiveShortcut(Workbench\nWindow.java:295)\n        at\norg.eclipse.ui.internal.WorkbenchPage.onActivate(WorkbenchPage.java:1519\n)\n        at\norg.eclipse.ui.internal.WorkbenchWindow$7.run(WorkbenchWindow.java:1235)\n        at\norg.eclipse.swt.custom.BusyIndicator.showWhile(BusyIndicator.java:66)\n        at\norg.eclipse.ui.internal.WorkbenchWindow.setActivePage(WorkbenchWindow.ja\nva:1222)\n        at\norg.eclipse.ui.internal.WorkbenchWindow.busyOpenPage(WorkbenchWindow.jav\na:345)\n        at\norg.eclipse.ui.internal.WorkbenchWindow$6.run(WorkbenchWindow.java:932)\n        at\norg.eclipse.swt.custom.BusyIndicator.showWhile(BusyIndicator.java:66)\n        at\norg.eclipse.ui.internal.WorkbenchWindow.openPage(WorkbenchWindow.java:92\n9)\n        at\norg.eclipse.ui.internal.Workbench.openFirstTimeWindow(Workbench.java:745\n)\n        at org.eclipse.ui.internal.Workbench.init(Workbench.java:581)\n        at org.eclipse.ui.internal.Workbench.run(Workbench.java:1232)\n        at\norg.eclipse.core.internal.boot.InternalBootLoader.run(InternalBootLoader\n.java:775)\n        at org.eclipse.core.boot.BootLoader.run(BootLoader.java:462)\n        at sun.reflect.NativeMethodAccessorImpl.invoke0(Native Method)\n        at\nsun.reflect.NativeMethodAccessorImpl.invoke(NativeMethodAccessorImpl.jav\na:39)\n        at\nsun.reflect.DelegatingMethodAccessorImpl.invoke(DelegatingMethodAccessor\nImpl.java:25)\n        at java.lang.reflect.Method.invoke(Method.java:324)\n        at org.eclipse.core.launcher.Main.basicRun(Main.java:247)\n        at org.eclipse.core.launcher.Main.run(Main.java:703)\n        at org.eclipse.core.launcher.Main.main(Main.java:539)\n\n\nXwin32 version 5.3\nThis bug is very critical for us, since all our desktops are Windows.\n\nNotice: the problem also occurs when the platform is Solaris.",
    "GG to investigate and advise.  Consult with Chrix about the graphics blit code.",
    "Michele, which version of Eclipse (build?) are you using ?\nThis sounds familiar to PR7435.",
    "\u003e Michele, which version of Eclipse (build?) are you using ?\n\nBuild is 200208291828\n\n\u003e\n\u003e This sounds familiar to PR7435.\n\u003e\n\nindeed, sorry I hadn\u0027t seen it before.\n\n\nI add also my xdpyinfo output, just for completeness,\nthanks.\n\nM.\n\n\n\nname of display:    PC004651.ads.eso.org:0.0\nversion number:    11.0\nvendor string:    StarNet Communications Corp.\nvendor release number:    5306\nmaximum request size:  262140 bytes\nmotion buffer size:  256\nbitmap unit, bit order, padding:    8, MSBFirst, 16\nimage byte order:    MSBFirst\nnumber of supported pixmap formats:    7\nsupported pixmap formats:\n    depth 1, bits_per_pixel 1, scanline_pad 16\n    depth 4, bits_per_pixel 4, scanline_pad 32\n    depth 8, bits_per_pixel 8, scanline_pad 32\n    depth 15, bits_per_pixel 16, scanline_pad 32\n    depth 16, bits_per_pixel 16, scanline_pad 32\n    depth 24, bits_per_pixel 32, scanline_pad 32\n    depth 32, bits_per_pixel 32, scanline_pad 32\nkeycode range:    minimum 8, maximum 122\nfocus:  window 0xc0000e, revert to PointerRoot\nnumber of extensions:    5\n    GLX\n    LBX\n    SGI-GLX\n    SHAPE\n    XTEST\ndefault screen number:    0\nnumber of screens:    1\n\nscreen #0:\n  dimensions:    1280x996 pixels (320x233 millimeters)\n  resolution:    102x109 dots per inch\n  depths (3):    1, 24, 8\n  root window id:    0x24\n  depth of root window:    24 planes\n  number of colormaps:    minimum 0, maximum 128\n  default colormap:    0x22\n  default number of colormap cells:    256\n  preallocated pixels:    black 0, white 16777215\n  options:    backing-store NO, save-unders YES\n  largest cursor:    32x32\n  current input event mask:    0x584030\n    EnterWindowMask          LeaveWindowMask          KeymapStateMask\n    SubstructureNotifyMask   SubstructureRedirectMask PropertyChangeMask\n  number of visuals:    2\n  default visual id:  0x20\n  visual:\n    visual id:    0x20\n    class:    TrueColor\n    depth:    24 planes\n    available colormap entries:    256 per subfield\n    red, green, blue masks:    0xff, 0xff00, 0xff0000\n    significant bits in color specification:    8 bits\n  visual:\n    visual id:    0x21\n    class:    PseudoColor\n    depth:    8 planes\n    available colormap entries:    256\n    red, green, blue masks:    0x0, 0x0, 0x0\n    significant bits in color specification:    8 bits\n\n\n",
    "This is fixed in the M2 build ( \nhttp://eclipsedrops.ott.oti.com/downloads/master/downloads/drops/S-M2-\n200210181211/index.php ).\n\n\n\n*** This bug has been marked as a duplicate of 7435 ***",
    "Sorry Grant,\n\nI downloaded M2 for Linux, but it doesn\u0027t seem to solve the problem.\nCan you please double check ?\nFile was eclipse-SDK-I20021018-linux-motif.zip\n\njava.lang.ArrayIndexOutOfBoundsException\n        at org.eclipse.swt.graphics.ImageData.blit(ImageData.java:2321)\n        at org.eclipse.swt.graphics.Image.putImage(Image.java:1200)\n        at org.eclipse.swt.graphics.Image.init(Image.java:988)\n        at org.eclipse.swt.graphics.Image.\u003cinit\u003e(Image.java:446)\n        at org.eclipse.jface.action.ActionContributionItem$ImageCache.getGrayIma\nge(ActionContributionItem.java:105)\n        at org.eclipse.jface.action.ActionContributionItem.updateImages(ActionCo\nntributionItem.java:602)\n        at org.eclipse.jface.action.ActionContributionItem.update(ActionContribu\ntionItem.java:468)\n        at org.eclipse.jface.action.ActionContributionItem.fill(ActionContributi\nonItem.java:287)\n        at org.eclipse.jface.action.ToolBarManager.update(ToolBarManager.java:23\n0)\n        at org.eclipse.ui.internal.WorkbenchWindow.addPerspectiveShortcut(Workbe\nnchWindow.java:331)\n        at org.eclipse.ui.internal.WorkbenchPage.onActivate(WorkbenchPage.java:1\n568)\n        at org.eclipse.ui.internal.WorkbenchWindow$7.run(WorkbenchWindow.java:13\n03)\n        at org.eclipse.swt.custom.BusyIndicator.showWhile(BusyIndicator.java:66)\n        at org.eclipse.ui.internal.WorkbenchWindow.setActivePage(WorkbenchWindow\n.java:1290)\n        at org.eclipse.ui.internal.WorkbenchWindow.busyOpenPage(WorkbenchWindow.\njava:381)\n        at org.eclipse.ui.internal.WorkbenchWindow$6.run(WorkbenchWindow.java:99\n5)\n        at org.eclipse.swt.custom.BusyIndicator.showWhile(BusyIndicator.java:66)\n        at org.eclipse.ui.internal.WorkbenchWindow.openPage(WorkbenchWindow.java\n:992)\n        at org.eclipse.ui.internal.Workbench.openFirstTimeWindow(Workbench.java:\n822)\n        at org.eclipse.ui.internal.Workbench.init(Workbench.java:653)\n        at org.eclipse.ui.internal.Workbench.run(Workbench.java:1396)\n        at org.eclipse.core.internal.boot.InternalBootLoader.run(InternalBootLoa\nder.java:775)\n        at org.eclipse.core.boot.BootLoader.run(BootLoader.java:462)\n        at sun.reflect.NativeMethodAccessorImpl.invoke0(Native Method)\n        at sun.reflect.NativeMethodAccessorImpl.invoke(NativeMethodAccessorImpl.\njava:39)\n        at sun.reflect.DelegatingMethodAccessorImpl.invoke(DelegatingMethodAcces\nsorImpl.java:25)\n        at java.lang.reflect.Method.invoke(Method.java:324)\n        at org.eclipse.core.launcher.Main.basicRun(Main.java:247)\n        at org.eclipse.core.launcher.Main.run(Main.java:703)\n        at org.eclipse.core.launcher.Main.main(Main.java:539)\n",
    "My mistake, I glanced at your stack trace a bit too quickly.  Your problem is \nnot fixed yet, but has been reported.  See bug 21695.\n\n\n*** This bug has been marked as a duplicate of 21695 ***"
  ],
  "commentCreationDates": [
    "2002-10-24T09:55:15+02:00",
    "2002-10-25T14:08:26+02:00",
    "2002-10-25T14:57:56+02:00",
    "2002-10-25T15:20:25+02:00",
    "2002-10-25T15:54:52+02:00",
    "2002-10-28T12:47:50+01:00",
    "2002-10-28T19:45:02+01:00"
  ],
  "traces": [
    {
      "exceptionType": "java.lang.ArrayIndexOutOfBoundsException",
      "elements": [
        {
          "method": "org.eclipse.swt.graphics.ImageData.blit",
          "source": "ImageData.java:2318"
        },
        {
          "method": "org.eclipse.swt.graphics.Image.putImage",
          "source": "Image.java:1200"
        },
        {
          "method": "org.eclipse.swt.graphics.Image.init",
          "source": "Image.java:988"
        },
        {
          "method": "org.eclipse.swt.graphics.Image.\u003cinit\u003e",
          "source": "Image.java:446"
        },
        {
          "method": "org.eclipse.jface.action.ActionContributionItem$ImageCache.getGrayImage",
          "source": " ActionContributionItem.java:105"
        },
        {
          "method": "org.eclipse.jface.action.ActionContributionItem.updateImages",
          "source": "ActionContr ibutionItem.java:602"
        },
        {
          "method": "org.eclipse.jface.action.ActionContributionItem.update",
          "source": "ActionContributio nItem.java:468"
        },
        {
          "method": "org.eclipse.jface.action.ActionContributionItem.fill",
          "source": "ActionContributionI tem.java:287"
        },
        {
          "method": "org.eclipse.jface.action.ToolBarManager.update",
          "source": "ToolBarManager.java:230"
        },
        {
          "method": "org.eclipse.ui.internal.WorkbenchWindow.addPerspectiveShortcut",
          "source": "Workbench Window.java:295"
        },
        {
          "method": "org.eclipse.ui.internal.WorkbenchPage.onActivate",
          "source": "WorkbenchPage.java:1519 "
        },
        {
          "method": "org.eclipse.ui.internal.WorkbenchWindow$7.run",
          "source": "WorkbenchWindow.java:1235"
        },
        {
          "method": "org.eclipse.swt.custom.BusyIndicator.showWhile",
          "source": "BusyIndicator.java:66"
        },
        {
          "method": "org.eclipse.ui.internal.WorkbenchWindow.setActivePage",
          "source": "WorkbenchWindow.ja va:1222"
        },
        {
          "method": "org.eclipse.ui.internal.WorkbenchWindow.busyOpenPage",
          "source": "WorkbenchWindow.jav a:345"
        },
        {
          "method": "org.eclipse.ui.internal.WorkbenchWindow$6.run",
          "source": "WorkbenchWindow.java:932"
        },
        {
          "method": "org.eclipse.swt.custom.BusyIndicator.showWhile",
          "source": "BusyIndicator.java:66"
        },
        {
          "method": "org.eclipse.ui.internal.WorkbenchWindow.openPage",
          "source": "WorkbenchWindow.java:92 9"
        },
        {
          "method": "org.eclipse.ui.internal.Workbench.openFirstTimeWindow",
          "source": "Workbench.java:745 "
        },
        {
          "method": "org.eclipse.ui.internal.Workbench.init",
          "source": "Workbench.java:581"
        },
        {
          "method": "org.eclipse.ui.internal.Workbench.run",
          "source": "Workbench.java:1232"
        },
        {
          "method": "org.eclipse.core.internal.boot.InternalBootLoader.run",
          "source": "InternalBootLoader .java:775"
        },
        {
          "method": "org.eclipse.core.boot.BootLoader.run",
          "source": "BootLoader.java:462"
        },
        {
          "method": "sun.reflect.NativeMethodAccessorImpl.invoke0",
          "source": "Native Method"
        },
        {
          "method": "sun.reflect.NativeMethodAccessorImpl.invoke",
          "source": "NativeMethodAccessorImpl.jav a:39"
        },
        {
          "method": "sun.reflect.DelegatingMethodAccessorImpl.invoke",
          "source": "DelegatingMethodAccessor Impl.java:25"
        },
        {
          "method": "java.lang.reflect.Method.invoke",
          "source": "Method.java:324"
        },
        {
          "method": "org.eclipse.core.launcher.Main.basicRun",
          "source": "Main.java:247"
        },
        {
          "method": "org.eclipse.core.launcher.Main.run",
          "source": "Main.java:703"
        },
        {
          "method": "org.eclipse.core.launcher.Main.main",
          "source": "Main.java:539"
        }
      ],
      "number": 0,
      "commentIndex": 0,
      "bugId": "25296",
      "duplicateId": "21695",
      "date": "2002-10-24T09:55:15+02:00",
      "product": "Platform",
      "component": "SWT",
      "severity": "blocker"
    },
    {
      "exceptionType": "java.lang.ArrayIndexOutOfBoundsException",
      "elements": [
        {
          "method": "org.eclipse.swt.graphics.ImageData.blit",
          "source": "ImageData.java:2321"
        },
        {
          "method": "org.eclipse.swt.graphics.Image.putImage",
          "source": "Image.java:1200"
        },
        {
          "method": "org.eclipse.swt.graphics.Image.init",
          "source": "Image.java:988"
        },
        {
          "method": "org.eclipse.swt.graphics.Image.\u003cinit\u003e",
          "source": "Image.java:446"
        },
        {
          "method": "org.eclipse.jface.action.ActionContributionItem$ImageCache.getGrayImage",
          "source": "ActionContributionItem.java:105"
        },
        {
          "method": "org.eclipse.jface.action.ActionContributionItem.updateImages",
          "source": "ActionCo ntributionItem.java:602"
        },
        {
          "method": "org.eclipse.jface.action.ActionContributionItem.update",
          "source": "ActionContribu tionItem.java:468"
        },
        {
          "method": "org.eclipse.jface.action.ActionContributionItem.fill",
          "source": "ActionContributi onItem.java:287"
        },
        {
          "method": "org.eclipse.jface.action.ToolBarManager.update",
          "source": "ToolBarManager.java:23 0"
        },
        {
          "method": "org.eclipse.ui.internal.WorkbenchWindow.addPerspectiveShortcut",
          "source": "Workbe nchWindow.java:331"
        },
        {
          "method": "org.eclipse.ui.internal.WorkbenchPage.onActivate",
          "source": "WorkbenchPage.java:1 568"
        },
        {
          "method": "org.eclipse.ui.internal.WorkbenchWindow$7.run",
          "source": "WorkbenchWindow.java:13 03"
        },
        {
          "method": "org.eclipse.swt.custom.BusyIndicator.showWhile",
          "source": "BusyIndicator.java:66"
        },
        {
          "method": "org.eclipse.ui.internal.WorkbenchWindow.setActivePage",
          "source": "WorkbenchWindow .java:1290"
        },
        {
          "method": "org.eclipse.ui.internal.WorkbenchWindow.busyOpenPage",
          "source": "WorkbenchWindow. java:381"
        },
        {
          "method": "org.eclipse.ui.internal.WorkbenchWindow$6.run",
          "source": "WorkbenchWindow.java:99 5"
        },
        {
          "method": "org.eclipse.swt.custom.BusyIndicator.showWhile",
          "source": "BusyIndicator.java:66"
        },
        {
          "method": "org.eclipse.ui.internal.WorkbenchWindow.openPage",
          "source": "WorkbenchWindow.java :992"
        },
        {
          "method": "org.eclipse.ui.internal.Workbench.openFirstTimeWindow",
          "source": "Workbench.java: 822"
        },
        {
          "method": "org.eclipse.ui.internal.Workbench.init",
          "source": "Workbench.java:653"
        },
        {
          "method": "org.eclipse.ui.internal.Workbench.run",
          "source": "Workbench.java:1396"
        },
        {
          "method": "org.eclipse.core.internal.boot.InternalBootLoader.run",
          "source": "InternalBootLoa der.java:775"
        },
        {
          "method": "org.eclipse.core.boot.BootLoader.run",
          "source": "BootLoader.java:462"
        },
        {
          "method": "sun.reflect.NativeMethodAccessorImpl.invoke0",
          "source": "Native Method"
        },
        {
          "method": "sun.reflect.NativeMethodAccessorImpl.invoke",
          "source": "NativeMethodAccessorImpl. java:39"
        },
        {
          "method": "sun.reflect.DelegatingMethodAccessorImpl.invoke",
          "source": "DelegatingMethodAcces sorImpl.java:25"
        },
        {
          "method": "java.lang.reflect.Method.invoke",
          "source": "Method.java:324"
        },
        {
          "method": "org.eclipse.core.launcher.Main.basicRun",
          "source": "Main.java:247"
        },
        {
          "method": "org.eclipse.core.launcher.Main.run",
          "source": "Main.java:703"
        },
        {
          "method": "org.eclipse.core.launcher.Main.main",
          "source": "Main.java:539"
        }
      ],
      "number": 1,
      "commentIndex": 5,
      "bugId": "25296",
      "duplicateId": "21695",
      "date": "2002-10-28T12:47:50+01:00",
      "product": "Platform",
      "component": "SWT",
      "severity": "blocker"
    }
  ],
  "groupId": "21695",
  "bugId": "25296",
  "duplicateId": "21695",
  "date": "2002-10-24T09:55:15+02:00",
  "product": "Platform",
  "component": "SWT",
  "severity": "blocker"
}