{
  "comments": [
    "Using a fresh SuSE 8.0 install, downloaded and installed GTK: lib versions: pango-1.0.3-2gtk atk-1.0.3-1 glib2-2.0.4-1gtk gtk2-2.0.5-1gtk  Eclipse does not start but throws an Exception. I have tried earlier versions of pango but they throw a similar link exception as well. The motif build starts okay but when I try to open a Java Editor an error message pops up saying: \"Could not create part\". So I can not use Eclipse on Linux at the moment. This is extremely annoying. Can fix this very quickly please?   oglueck@gimli:~/bin/eclipse-gtk\u003e ./eclipse java.lang.UnsatisfiedLinkError: /home/oglueck/bin/eclipse-gtk/plugins/org.eclipse.swt.gtk_2.1.0/os/linux/x86/libswt-pi-gtk-2112.so: /usr/lib/libpangoxft-1.0.so.0: undefined symbol: FT_Stream_GetShort         at java.lang.ClassLoader$NativeLibrary.load(Native Method)         at java.lang.ClassLoader.loadLibrary0(ClassLoader.java:1419)         at java.lang.ClassLoader.loadLibrary(ClassLoader.java:1327)         at java.lang.Runtime.loadLibrary0(Runtime.java:749)         at java.lang.System.loadLibrary(System.java:820)         at org.eclipse.swt.internal.Library.loadLibrary(Library.java:104)         at org.eclipse.swt.internal.gtk.OS.\u003cclinit\u003e(OS.java:19)         at org.eclipse.swt.widgets.Display.createDisplay(Display.java:404)         at org.eclipse.swt.widgets.Display.create(Display.java:398)         at org.eclipse.swt.graphics.Device.\u003cinit\u003e(Device.java:103)         at org.eclipse.swt.widgets.Display.\u003cinit\u003e(Display.java:284)         at org.eclipse.swt.widgets.Display.\u003cinit\u003e(Display.java:280)         at org.eclipse.ui.internal.Workbench.run(Workbench.java:1385)         at org.eclipse.core.internal.boot.InternalBootLoader.run(InternalBootLoader.java:775)         at org.eclipse.core.boot.BootLoader.run(BootLoader.java:462)         at java.lang.reflect.Method.invoke(Native Method)         at org.eclipse.core.launcher.Main.basicRun(Main.java:247)         at org.eclipse.core.launcher.Main.run(Main.java:703)         at org.eclipse.core.launcher.Main.main(Main.java:539)",
    "(oops something happend to the line breaks, so again:)\n\nUsing a fresh SuSE 8.0 install, downloaded and installed GTK:\nlib versions:\npango-1.0.3-2gtk\natk-1.0.3-1\nglib2-2.0.4-1gtk\ngtk2-2.0.5-1gtk\n\nEclipse does not start but throws an Exception. I have tried earlier versions of\npango but they throw a similar link exception as well. The motif build starts\nokay but when I try to open a Java Editor an error message pops up saying:\n\"Could not create part\".\n\nSo I can not use Eclipse on Linux at the moment. This is extremely annoying. Can\nfix this very quickly please?\n\noglueck@gimli:~/bin/eclipse-gtk\u003e ./eclipse java.lang.UnsatisfiedLinkError: \n/home/oglueck/bin/eclipse-gtk/plugins/org.eclipse.swt.gtk_2.1.0/os/linux/x86/libswt-pi-gtk-2112.so:\n/usr/lib/libpangoxft-1.0.so.0: undefined symbol: FT_Stream_GetShort         at \njava.lang.ClassLoader$NativeLibrary.load(Native Method)         at \njava.lang.ClassLoader.loadLibrary0(ClassLoader.java:1419)         at \njava.lang.ClassLoader.loadLibrary(ClassLoader.java:1327)         at \njava.lang.Runtime.loadLibrary0(Runtime.java:749)         at \njava.lang.System.loadLibrary(System.java:820)         at \norg.eclipse.swt.internal.Library.loadLibrary(Library.java:104)         at \norg.eclipse.swt.internal.gtk.OS.\u003cclinit\u003e(OS.java:19)         at \norg.eclipse.swt.widgets.Display.createDisplay(Display.java:404)         at \norg.eclipse.swt.widgets.Display.create(Display.java:398)         at \norg.eclipse.swt.graphics.Device.\u003cinit\u003e(Device.java:103)         at \norg.eclipse.swt.widgets.Display.\u003cinit\u003e(Display.java:284)         at \norg.eclipse.swt.widgets.Display.\u003cinit\u003e(Display.java:280)         at \norg.eclipse.ui.internal.Workbench.run(Workbench.java:1385)         at \norg.eclipse.core.internal.boot.InternalBootLoader.run(InternalBootLoader.java:775)\n       \n at org.eclipse.core.boot.BootLoader.run(BootLoader.java:462)         at \njava.lang.reflect.Method.invoke(Native Method)         at \norg.eclipse.core.launcher.Main.basicRun(Main.java:247)         at \norg.eclipse.core.launcher.Main.run(Main.java:703)         at \norg.eclipse.core.launcher.Main.main(Main.java:539)",
    "This again.  GG, can you make a FAQ and post a link to it?  Not being able to \nrun on Linux due to DLL hell (Motif - our DLL, GTK - our DLL and theirs) is a \nhuge problem.  We need a section on our web page for this.  VI?",
    "At least all the dependencies should be listed with exact versions (and maybe a\nlink to a download location). Thanks.",
    "The FAQ lists the GTK dependencies:\n\nhttp://dev.eclipse.org/viewcvs/index.cgi/%7Echeckout%7E/platform-swt-\nhome/faq.html#gtkstartup\n\nThere is also an FAQ about the dll hell on linux motif which I have a link to \nfrom the SWT FAQ page:\nhttp://mmoebius.gmxhome.de/eclipse/downloads/mini-HOWTO.html\n\nI could make our own section on the linux motif library issues.",
    "I think you\u0027re missing the required version of Freetype.  I\u0027ve just duplicated \nthe FT_Stream_GetShort problem and then fixed it by upgrading my Freetype from \n2.0.9-2 to 2.1.2-7, using Eclipse 2.0.1.\n\nIf doing this on your end fixes your problem then please add a comment here.  \nThanks.\n",
    "Assuming that this is a setup problem, changing to WORKSFORME.  If this is not \nthe case then please reopen the report.\n",
    "*** Bug 69790 has been marked as a duplicate of this bug. ***"
  ],
  "commentCreationDates": [
    "2002-10-25T10:32:31+02:00",
    "2002-10-25T10:37:38+02:00",
    "2002-10-25T14:28:00+02:00",
    "2002-10-25T14:37:16+02:00",
    "2002-10-25T16:50:35+02:00",
    "2002-10-25T17:10:47+02:00",
    "2002-11-05T21:49:55+01:00",
    "2004-07-12T23:58:22+02:00"
  ],
  "traces": [
    {
      "exceptionType": "java.lang.UnsatisfiedLinkError",
      "message": "/home/oglueck/bin/eclipse-gtk/plugins/org.eclipse.swt.gtk_2.1.0/os/linux/x86/libswt-pi-gtk-2112.so: /usr/lib/libpangoxft-1.0.so.0: undefined symbol: FT_Stream_GetShort",
      "elements": [
        {
          "method": "java.lang.ClassLoader$NativeLibrary.load",
          "source": "Native Method"
        },
        {
          "method": "java.lang.ClassLoader.loadLibrary0",
          "source": "ClassLoader.java:1419"
        },
        {
          "method": "java.lang.ClassLoader.loadLibrary",
          "source": "ClassLoader.java:1327"
        },
        {
          "method": "java.lang.Runtime.loadLibrary0",
          "source": "Runtime.java:749"
        },
        {
          "method": "java.lang.System.loadLibrary",
          "source": "System.java:820"
        },
        {
          "method": "org.eclipse.swt.internal.Library.loadLibrary",
          "source": "Library.java:104"
        },
        {
          "method": "org.eclipse.swt.internal.gtk.OS.\u003cclinit\u003e",
          "source": "OS.java:19"
        },
        {
          "method": "org.eclipse.swt.widgets.Display.createDisplay",
          "source": "Display.java:404"
        },
        {
          "method": "org.eclipse.swt.widgets.Display.create",
          "source": "Display.java:398"
        },
        {
          "method": "org.eclipse.swt.graphics.Device.\u003cinit\u003e",
          "source": "Device.java:103"
        },
        {
          "method": "org.eclipse.swt.widgets.Display.\u003cinit\u003e",
          "source": "Display.java:284"
        },
        {
          "method": "org.eclipse.swt.widgets.Display.\u003cinit\u003e",
          "source": "Display.java:280"
        },
        {
          "method": "org.eclipse.ui.internal.Workbench.run",
          "source": "Workbench.java:1385"
        },
        {
          "method": "org.eclipse.core.internal.boot.InternalBootLoader.run",
          "source": "InternalBootLoader.java:775"
        },
        {
          "method": "org.eclipse.core.boot.BootLoader.run",
          "source": "BootLoader.java:462"
        },
        {
          "method": "java.lang.reflect.Method.invoke",
          "source": "Native Method"
        },
        {
          "method": "org.eclipse.core.launcher.Main.basicRun",
          "source": "Main.java:247"
        },
        {
          "method": "org.eclipse.core.launcher.Main.run",
          "source": "Main.java:703"
        },
        {
          "method": "org.eclipse.core.launcher.Main.main",
          "source": "Main.java:539"
        }
      ],
      "number": 0,
      "commentIndex": 0,
      "bugId": "25367",
      "date": "2002-10-25T10:32:31+02:00",
      "product": "Platform",
      "component": "SWT",
      "severity": "major"
    },
    {
      "exceptionType": "java.lang.UnsatisfiedLinkError",
      "message": "/home/oglueck/bin/eclipse-gtk/plugins/org.eclipse.swt.gtk_2.1.0/os/linux/x86/libswt-pi-gtk-2112.so: /usr/lib/libpangoxft-1.0.so.0: undefined symbol: FT_Stream_GetShort",
      "elements": [
        {
          "method": "java.lang.ClassLoader$NativeLibrary.load",
          "source": "Native Method"
        },
        {
          "method": "java.lang.ClassLoader.loadLibrary0",
          "source": "ClassLoader.java:1419"
        },
        {
          "method": "java.lang.ClassLoader.loadLibrary",
          "source": "ClassLoader.java:1327"
        },
        {
          "method": "java.lang.Runtime.loadLibrary0",
          "source": "Runtime.java:749"
        },
        {
          "method": "java.lang.System.loadLibrary",
          "source": "System.java:820"
        },
        {
          "method": "org.eclipse.swt.internal.Library.loadLibrary",
          "source": "Library.java:104"
        },
        {
          "method": "org.eclipse.swt.internal.gtk.OS.\u003cclinit\u003e",
          "source": "OS.java:19"
        },
        {
          "method": "org.eclipse.swt.widgets.Display.createDisplay",
          "source": "Display.java:404"
        },
        {
          "method": "org.eclipse.swt.widgets.Display.create",
          "source": "Display.java:398"
        },
        {
          "method": "org.eclipse.swt.graphics.Device.\u003cinit\u003e",
          "source": "Device.java:103"
        },
        {
          "method": "org.eclipse.swt.widgets.Display.\u003cinit\u003e",
          "source": "Display.java:284"
        },
        {
          "method": "org.eclipse.swt.widgets.Display.\u003cinit\u003e",
          "source": "Display.java:280"
        },
        {
          "method": "org.eclipse.ui.internal.Workbench.run",
          "source": "Workbench.java:1385"
        },
        {
          "method": "org.eclipse.core.internal.boot.InternalBootLoader.run",
          "source": "InternalBootLoader.java:775"
        },
        {
          "method": "org.eclipse.core.boot.BootLoader.run",
          "source": "BootLoader.java:462"
        },
        {
          "method": "java.lang.reflect.Method.invoke",
          "source": "Native Method"
        },
        {
          "method": "org.eclipse.core.launcher.Main.basicRun",
          "source": "Main.java:247"
        },
        {
          "method": "org.eclipse.core.launcher.Main.run",
          "source": "Main.java:703"
        },
        {
          "method": "org.eclipse.core.launcher.Main.main",
          "source": "Main.java:539"
        }
      ],
      "number": 1,
      "commentIndex": 1,
      "bugId": "25367",
      "date": "2002-10-25T10:37:38+02:00",
      "product": "Platform",
      "component": "SWT",
      "severity": "major"
    }
  ],
  "groupId": "25367",
  "bugId": "25367",
  "date": "2002-10-25T10:32:31+02:00",
  "product": "Platform",
  "component": "SWT",
  "severity": "major"
}