{
  "comments": [
    "Build 20021022\nLinux-GTK\n\nI get a NPE when I try to import (override/update) org.apache.xerces :\n\njava.lang.NullPointerException\n        at\norg.eclipse.jdt.internal.core.SetClasspathOperation.generateClasspathChangeDeltas(SetClasspathOperation.java:260)\n        at\norg.eclipse.jdt.internal.core.SetClasspathOperation.updateClasspath(SetClasspathOperation.java:508)\n        at\norg.eclipse.jdt.internal.core.SetClasspathOperation.executeOperation(SetClasspathOperation.java:216)\n        at\norg.eclipse.jdt.internal.core.JavaModelOperation.execute(JavaModelOperation.java:321)\n        at\norg.eclipse.jdt.internal.core.JavaModelOperation.run(JavaModelOperation.java:621)\n        at org.eclipse.core.internal.resources.Workspace.run(Workspace.java:1378)\n        at\norg.eclipse.jdt.internal.core.JavaElement.runOperation(JavaElement.java:563)\n        at\norg.eclipse.jdt.internal.core.JavaProject.setRawClasspath(JavaProject.java:2251)\n        at\norg.eclipse.jdt.internal.core.SetClasspathOperation.updateAffectedProjects(SetClasspathOperation.java:544)\n        at\norg.eclipse.jdt.internal.core.SetClasspathOperation.generateClasspathChangeDeltas(SetClasspathOperation.java:409)\n        at\norg.eclipse.jdt.internal.core.SetClasspathOperation.updateClasspath(SetClasspathOperation.java:508)\n        at\norg.eclipse.jdt.internal.core.SetClasspathOperation.executeOperation(SetClasspathOperation.java:216)\n        at\norg.eclipse.jdt.internal.core.JavaModelOperation.execute(JavaModelOperation.java:321)\n        at\norg.eclipse.jdt.internal.core.JavaModelOperation.run(JavaModelOperation.java:621)\n        at org.eclipse.core.internal.resources.Workspace.run(Workspace.java:1378)\n        at\norg.eclipse.jdt.internal.core.JavaElement.runOperation(JavaElement.java:563)\n        at\norg.eclipse.jdt.internal.core.JavaProject.setRawClasspath(JavaProject.java:2251)\n        at\norg.eclipse.jdt.internal.core.JavaProject.setRawClasspath(JavaProject.java:2267)\n        at\norg.eclipse.pde.internal.ui.wizards.imports.PluginImportOperation.createProject(PluginImportOperation.java:235)\n        at\norg.eclipse.pde.internal.ui.wizards.imports.PluginImportOperation.run(PluginImportOperation.java:149)\n        at org.eclipse.core.internal.resources.Workspace.run(Workspace.java:1378)\n        at\norg.eclipse.pde.internal.ui.wizards.imports.PluginImportWizard$2.run(PluginImportWizard.java:136)\n        at\norg.eclipse.jface.operation.ModalContext$ModalContextThread.run(ModalContext.java:98)\n\nThe result is the classpath of the project is not set.",
    "There were some import related problems im 20021022. They were fixed in \n20021023. Can you try it out? I can\u0027t really use 20021023 because of some SWT-\nGTK problems (I\u0027m still on 20021018).",
    "\n\n*** This bug has been marked as a duplicate of 25197 ***",
    "Forgot to assign",
    "\n\n*** This bug has been marked as a duplicate of 25197 ***"
  ],
  "commentCreationDates": [
    "2002-10-28T20:02:37+01:00",
    "2002-10-29T08:40:51+01:00",
    "2002-10-29T09:57:46+01:00",
    "2002-10-29T09:58:09+01:00",
    "2002-10-29T09:58:41+01:00"
  ],
  "traces": [
    {
      "exceptionType": "java.lang.NullPointerException",
      "elements": [
        {
          "method": "org.eclipse.jdt.internal.core.SetClasspathOperation.generateClasspathChangeDeltas",
          "source": "SetClasspathOperation.java:260"
        },
        {
          "method": "org.eclipse.jdt.internal.core.SetClasspathOperation.updateClasspath",
          "source": "SetClasspathOperation.java:508"
        },
        {
          "method": "org.eclipse.jdt.internal.core.SetClasspathOperation.executeOperation",
          "source": "SetClasspathOperation.java:216"
        },
        {
          "method": "org.eclipse.jdt.internal.core.JavaModelOperation.execute",
          "source": "JavaModelOperation.java:321"
        },
        {
          "method": "org.eclipse.jdt.internal.core.JavaModelOperation.run",
          "source": "JavaModelOperation.java:621"
        },
        {
          "method": "org.eclipse.core.internal.resources.Workspace.run",
          "source": "Workspace.java:1378"
        },
        {
          "method": "org.eclipse.jdt.internal.core.JavaElement.runOperation",
          "source": "JavaElement.java:563"
        },
        {
          "method": "org.eclipse.jdt.internal.core.JavaProject.setRawClasspath",
          "source": "JavaProject.java:2251"
        },
        {
          "method": "org.eclipse.jdt.internal.core.SetClasspathOperation.updateAffectedProjects",
          "source": "SetClasspathOperation.java:544"
        },
        {
          "method": "org.eclipse.jdt.internal.core.SetClasspathOperation.generateClasspathChangeDeltas",
          "source": "SetClasspathOperation.java:409"
        },
        {
          "method": "org.eclipse.jdt.internal.core.SetClasspathOperation.updateClasspath",
          "source": "SetClasspathOperation.java:508"
        },
        {
          "method": "org.eclipse.jdt.internal.core.SetClasspathOperation.executeOperation",
          "source": "SetClasspathOperation.java:216"
        },
        {
          "method": "org.eclipse.jdt.internal.core.JavaModelOperation.execute",
          "source": "JavaModelOperation.java:321"
        },
        {
          "method": "org.eclipse.jdt.internal.core.JavaModelOperation.run",
          "source": "JavaModelOperation.java:621"
        },
        {
          "method": "org.eclipse.core.internal.resources.Workspace.run",
          "source": "Workspace.java:1378"
        },
        {
          "method": "org.eclipse.jdt.internal.core.JavaElement.runOperation",
          "source": "JavaElement.java:563"
        },
        {
          "method": "org.eclipse.jdt.internal.core.JavaProject.setRawClasspath",
          "source": "JavaProject.java:2251"
        },
        {
          "method": "org.eclipse.jdt.internal.core.JavaProject.setRawClasspath",
          "source": "JavaProject.java:2267"
        },
        {
          "method": "org.eclipse.pde.internal.ui.wizards.imports.PluginImportOperation.createProject",
          "source": "PluginImportOperation.java:235"
        },
        {
          "method": "org.eclipse.pde.internal.ui.wizards.imports.PluginImportOperation.run",
          "source": "PluginImportOperation.java:149"
        },
        {
          "method": "org.eclipse.core.internal.resources.Workspace.run",
          "source": "Workspace.java:1378"
        },
        {
          "method": "org.eclipse.pde.internal.ui.wizards.imports.PluginImportWizard$2.run",
          "source": "PluginImportWizard.java:136"
        },
        {
          "method": "org.eclipse.jface.operation.ModalContext$ModalContextThread.run",
          "source": "ModalContext.java:98"
        }
      ],
      "number": 0,
      "commentIndex": 0,
      "bugId": "25464",
      "duplicateId": "25197",
      "date": "2002-10-28T20:02:37+01:00",
      "product": "JDT",
      "component": "Core",
      "severity": "normal"
    }
  ],
  "groupId": "25197",
  "bugId": "25464",
  "duplicateId": "25197",
  "date": "2002-10-28T20:02:37+01:00",
  "product": "JDT",
  "component": "Core",
  "severity": "normal"
}