{
  "comments": [
    "Build 20021030\n\n1. create the following compilation unit:\n\npublic class TestCompletion {\n  public String aString() {\n    return \"test\";\n  }\n}\n\n2. go in window\u003epreference\u003ejava\u003edebug\u003edetail formatters\n3. create/edit the detail formatter for TestCompletion\n4. type \"return aStr\" in the text area.\n5. hit [CTRL+SPACE] for activate the code completion.\nNo proposals are displayed.\nthe log file contains:\n\n!ENTRY org.eclipse.ui 4 4 Oct 31, 2002 09:18:17.314\n!MESSAGE Unhandled exception caught in event loop.\n!ENTRY org.eclipse.ui 4 0 Oct 31, 2002 09:18:17.317\n!MESSAGE java.lang.ClassCastException\n!STACK 0\njava.lang.ClassCastException\n        at\norg.eclipse.jdt.internal.codeassist.CompletionEngine.computeExpectedTypes(CompletionEngine.java:2626)\n        at\norg.eclipse.jdt.internal.codeassist.CompletionEngine.complete(CompletionEngine.java:349)\n        at\norg.eclipse.jdt.internal.codeassist.CompletionEngine.complete(CompletionEngine.java:714)\n        at org.eclipse.jdt.internal.core.SourceType.codeComplete(SourceType.java:74)\n        at\norg.eclipse.jdt.internal.debug.ui.DetailFormatterCompletionProcessor.computeCompletionProposals(DetailFormatterCompletionProcessor.java:49)\n        at\norg.eclipse.jface.text.contentassist.ContentAssistant.computeCompletionProposals(ContentAssistant.java:1279)\n        at\norg.eclipse.jface.text.contentassist.CompletionProposalPopup.computeProposals(CompletionProposalPopup.java:177)\n        at\norg.eclipse.jface.text.contentassist.CompletionProposalPopup.access$7(CompletionProposalPopup.java:176)\n        at\norg.eclipse.jface.text.contentassist.CompletionProposalPopup$3.run(CompletionProposalPopup.java:138)\n        at org.eclipse.swt.custom.BusyIndicator.showWhile(BusyIndicator.java:65)\n        at\norg.eclipse.jface.text.contentassist.CompletionProposalPopup.showProposals(CompletionProposalPopup.java:133)\n        at\norg.eclipse.jface.text.contentassist.ContentAssistant.showPossibleCompletions(ContentAssistant.java:1199)\n        at\norg.eclipse.jface.text.source.SourceViewer.doOperation(SourceViewer.java:413)\n        at\norg.eclipse.jdt.internal.debug.ui.DetailFormatterDialog$4.verifyKey(DetailFormatterDialog.java:214)\n        at\norg.eclipse.swt.custom.StyledTextListener.handleEvent(StyledTextListener.java:51)\n        at org.eclipse.swt.widgets.EventTable.sendEvent(EventTable.java:77)\n        at org.eclipse.swt.widgets.Widget.sendEvent(Widget.java:839)\n        at org.eclipse.swt.widgets.Widget.sendEvent(Widget.java:864)\n        at org.eclipse.swt.widgets.Widget.sendEvent(Widget.java:848)\n        at org.eclipse.swt.widgets.Widget.notifyListeners(Widget.java:551)\n        at org.eclipse.swt.custom.StyledText.handleKeyDown(StyledText.java:4859)\n        at org.eclipse.swt.custom.StyledText$8.handleEvent(StyledText.java:4634)\n        at org.eclipse.swt.widgets.EventTable.sendEvent(EventTable.java:77)\n        at org.eclipse.swt.widgets.Widget.sendEvent(Widget.java:839)\n        at org.eclipse.swt.widgets.Display.runDeferredEvents(Display.java:1464)\n        at org.eclipse.swt.widgets.Display.readAndDispatch(Display.java:1284)\n        at org.eclipse.jface.window.Window.runEventLoop(Window.java:561)\n        at org.eclipse.jface.window.Window.open(Window.java:541)\n        at\norg.eclipse.jdt.internal.debug.ui.JavaDetailFormattersPreferencePage.addType(JavaDetailFormattersPreferencePage.java:254)\n        at\norg.eclipse.jdt.internal.debug.ui.JavaDetailFormattersPreferencePage$4.handleEvent(JavaDetailFormattersPreferencePage.java:168)\n        at org.eclipse.swt.widgets.EventTable.sendEvent(EventTable.java:77)\n        at org.eclipse.swt.widgets.Widget.sendEvent(Widget.java:839)\n        at org.eclipse.swt.widgets.Display.runDeferredEvents(Display.java:1464)\n        at org.eclipse.swt.widgets.Display.readAndDispatch(Display.java:1284)\n        at org.eclipse.jface.window.Window.runEventLoop(Window.java:561)\n        at org.eclipse.jface.window.Window.open(Window.java:541)\n        at\norg.eclipse.ui.internal.OpenPreferencesAction.run(OpenPreferencesAction.java:47)\n        at org.eclipse.jface.action.Action.runWithEvent(Action.java:769)\n        at\norg.eclipse.jface.action.ActionContributionItem.handleWidgetSelection(ActionContributionItem.java:408)\n        at\norg.eclipse.jface.action.ActionContributionItem.handleWidgetEvent(ActionContributionItem.java:362)\n        at\norg.eclipse.jface.action.ActionContributionItem.access$0(ActionContributionItem.java:353)\n        at\norg.eclipse.jface.action.ActionContributionItem$ActionListener.handleEvent(ActionContributionItem.java:48)\n        at org.eclipse.swt.widgets.EventTable.sendEvent(EventTable.java:77)\n        at org.eclipse.swt.widgets.Widget.sendEvent(Widget.java:839)\n        at org.eclipse.swt.widgets.Display.runDeferredEvents(Display.java:1464)\n        at org.eclipse.swt.widgets.Display.readAndDispatch(Display.java:1284)\n        at org.eclipse.ui.internal.Workbench.runEventLoop(Workbench.java:1419)\n        at org.eclipse.ui.internal.Workbench.run(Workbench.java:1402)\n        at\norg.eclipse.core.internal.boot.InternalBootLoader.run(InternalBootLoader.java:831)\n        at org.eclipse.core.boot.BootLoader.run(BootLoader.java:462)\n        at sun.reflect.NativeMethodAccessorImpl.invoke0(Native Method)\n        at\nsun.reflect.NativeMethodAccessorImpl.invoke(NativeMethodAccessorImpl.java:39)\n        at\nsun.reflect.DelegatingMethodAccessorImpl.invoke(DelegatingMethodAccessorImpl.java:25)\n        at java.lang.reflect.Method.invoke(Method.java:324)\n        at org.eclipse.core.launcher.Main.basicRun(Main.java:247)\n        at org.eclipse.core.launcher.Main.run(Main.java:703)\n        at org.eclipse.core.launcher.Main.main(Main.java:539)",
    "Protection added.\n\nFixed.",
    "Verified."
  ],
  "commentCreationDates": [
    "2002-10-31T15:24:03+01:00",
    "2002-10-31T16:27:05+01:00",
    "2002-11-13T10:20:24+01:00"
  ],
  "traces": [
    {
      "exceptionType": "java.lang.ClassCastException",
      "elements": [
        {
          "method": "org.eclipse.jdt.internal.codeassist.CompletionEngine.computeExpectedTypes",
          "source": "CompletionEngine.java:2626"
        },
        {
          "method": "org.eclipse.jdt.internal.codeassist.CompletionEngine.complete",
          "source": "CompletionEngine.java:349"
        },
        {
          "method": "org.eclipse.jdt.internal.codeassist.CompletionEngine.complete",
          "source": "CompletionEngine.java:714"
        },
        {
          "method": "org.eclipse.jdt.internal.core.SourceType.codeComplete",
          "source": "SourceType.java:74"
        },
        {
          "method": "org.eclipse.jdt.internal.debug.ui.DetailFormatterCompletionProcessor.computeCompletionProposals",
          "source": "DetailFormatterCompletionProcessor.java:49"
        },
        {
          "method": "org.eclipse.jface.text.contentassist.ContentAssistant.computeCompletionProposals",
          "source": "ContentAssistant.java:1279"
        },
        {
          "method": "org.eclipse.jface.text.contentassist.CompletionProposalPopup.computeProposals",
          "source": "CompletionProposalPopup.java:177"
        },
        {
          "method": "org.eclipse.jface.text.contentassist.CompletionProposalPopup.access$7",
          "source": "CompletionProposalPopup.java:176"
        },
        {
          "method": "org.eclipse.jface.text.contentassist.CompletionProposalPopup$3.run",
          "source": "CompletionProposalPopup.java:138"
        },
        {
          "method": "org.eclipse.swt.custom.BusyIndicator.showWhile",
          "source": "BusyIndicator.java:65"
        },
        {
          "method": "org.eclipse.jface.text.contentassist.CompletionProposalPopup.showProposals",
          "source": "CompletionProposalPopup.java:133"
        },
        {
          "method": "org.eclipse.jface.text.contentassist.ContentAssistant.showPossibleCompletions",
          "source": "ContentAssistant.java:1199"
        },
        {
          "method": "org.eclipse.jface.text.source.SourceViewer.doOperation",
          "source": "SourceViewer.java:413"
        },
        {
          "method": "org.eclipse.jdt.internal.debug.ui.DetailFormatterDialog$4.verifyKey",
          "source": "DetailFormatterDialog.java:214"
        },
        {
          "method": "org.eclipse.swt.custom.StyledTextListener.handleEvent",
          "source": "StyledTextListener.java:51"
        },
        {
          "method": "org.eclipse.swt.widgets.EventTable.sendEvent",
          "source": "EventTable.java:77"
        },
        {
          "method": "org.eclipse.swt.widgets.Widget.sendEvent",
          "source": "Widget.java:839"
        },
        {
          "method": "org.eclipse.swt.widgets.Widget.sendEvent",
          "source": "Widget.java:864"
        },
        {
          "method": "org.eclipse.swt.widgets.Widget.sendEvent",
          "source": "Widget.java:848"
        },
        {
          "method": "org.eclipse.swt.widgets.Widget.notifyListeners",
          "source": "Widget.java:551"
        },
        {
          "method": "org.eclipse.swt.custom.StyledText.handleKeyDown",
          "source": "StyledText.java:4859"
        },
        {
          "method": "org.eclipse.swt.custom.StyledText$8.handleEvent",
          "source": "StyledText.java:4634"
        },
        {
          "method": "org.eclipse.swt.widgets.EventTable.sendEvent",
          "source": "EventTable.java:77"
        },
        {
          "method": "org.eclipse.swt.widgets.Widget.sendEvent",
          "source": "Widget.java:839"
        },
        {
          "method": "org.eclipse.swt.widgets.Display.runDeferredEvents",
          "source": "Display.java:1464"
        },
        {
          "method": "org.eclipse.swt.widgets.Display.readAndDispatch",
          "source": "Display.java:1284"
        },
        {
          "method": "org.eclipse.jface.window.Window.runEventLoop",
          "source": "Window.java:561"
        },
        {
          "method": "org.eclipse.jface.window.Window.open",
          "source": "Window.java:541"
        },
        {
          "method": "org.eclipse.jdt.internal.debug.ui.JavaDetailFormattersPreferencePage.addType",
          "source": "JavaDetailFormattersPreferencePage.java:254"
        },
        {
          "method": "org.eclipse.jdt.internal.debug.ui.JavaDetailFormattersPreferencePage$4.handleEvent",
          "source": "JavaDetailFormattersPreferencePage.java:168"
        },
        {
          "method": "org.eclipse.swt.widgets.EventTable.sendEvent",
          "source": "EventTable.java:77"
        },
        {
          "method": "org.eclipse.swt.widgets.Widget.sendEvent",
          "source": "Widget.java:839"
        },
        {
          "method": "org.eclipse.swt.widgets.Display.runDeferredEvents",
          "source": "Display.java:1464"
        },
        {
          "method": "org.eclipse.swt.widgets.Display.readAndDispatch",
          "source": "Display.java:1284"
        },
        {
          "method": "org.eclipse.jface.window.Window.runEventLoop",
          "source": "Window.java:561"
        },
        {
          "method": "org.eclipse.jface.window.Window.open",
          "source": "Window.java:541"
        },
        {
          "method": "org.eclipse.ui.internal.OpenPreferencesAction.run",
          "source": "OpenPreferencesAction.java:47"
        },
        {
          "method": "org.eclipse.jface.action.Action.runWithEvent",
          "source": "Action.java:769"
        },
        {
          "method": "org.eclipse.jface.action.ActionContributionItem.handleWidgetSelection",
          "source": "ActionContributionItem.java:408"
        },
        {
          "method": "org.eclipse.jface.action.ActionContributionItem.handleWidgetEvent",
          "source": "ActionContributionItem.java:362"
        },
        {
          "method": "org.eclipse.jface.action.ActionContributionItem.access$0",
          "source": "ActionContributionItem.java:353"
        },
        {
          "method": "org.eclipse.jface.action.ActionContributionItem$ActionListener.handleEvent",
          "source": "ActionContributionItem.java:48"
        },
        {
          "method": "org.eclipse.swt.widgets.EventTable.sendEvent",
          "source": "EventTable.java:77"
        },
        {
          "method": "org.eclipse.swt.widgets.Widget.sendEvent",
          "source": "Widget.java:839"
        },
        {
          "method": "org.eclipse.swt.widgets.Display.runDeferredEvents",
          "source": "Display.java:1464"
        },
        {
          "method": "org.eclipse.swt.widgets.Display.readAndDispatch",
          "source": "Display.java:1284"
        },
        {
          "method": "org.eclipse.ui.internal.Workbench.runEventLoop",
          "source": "Workbench.java:1419"
        },
        {
          "method": "org.eclipse.ui.internal.Workbench.run",
          "source": "Workbench.java:1402"
        },
        {
          "method": "org.eclipse.core.internal.boot.InternalBootLoader.run",
          "source": "InternalBootLoader.java:831"
        },
        {
          "method": "org.eclipse.core.boot.BootLoader.run",
          "source": "BootLoader.java:462"
        },
        {
          "method": "sun.reflect.NativeMethodAccessorImpl.invoke0",
          "source": "Native Method"
        },
        {
          "method": "sun.reflect.NativeMethodAccessorImpl.invoke",
          "source": "NativeMethodAccessorImpl.java:39"
        },
        {
          "method": "sun.reflect.DelegatingMethodAccessorImpl.invoke",
          "source": "DelegatingMethodAccessorImpl.java:25"
        },
        {
          "method": "java.lang.reflect.Method.invoke",
          "source": "Method.java:324"
        },
        {
          "method": "org.eclipse.core.launcher.Main.basicRun",
          "source": "Main.java:247"
        },
        {
          "method": "org.eclipse.core.launcher.Main.run",
          "source": "Main.java:703"
        },
        {
          "method": "org.eclipse.core.launcher.Main.main",
          "source": "Main.java:539"
        }
      ],
      "number": 0,
      "commentIndex": 0,
      "bugId": "25591",
      "date": "2002-10-31T15:24:03+01:00",
      "product": "JDT",
      "component": "Core",
      "severity": "normal"
    }
  ],
  "groupId": "25591",
  "bugId": "25591",
  "date": "2002-10-31T15:24:03+01:00",
  "product": "JDT",
  "component": "Core",
  "severity": "normal"
}