{
  "comments": [
    "Build 20021105\n\nI noticed the following exception in the log, I do not have steps unfortunately.\n\n!ENTRY org.eclipse.ui 4 0 Nov 07, 2002 11:44:06.467\n!MESSAGE Index out of bounds\n!STACK 0\njava.lang.IllegalArgumentException: Index out of bounds\n        at org.eclipse.swt.SWT.error(SWT.java:2166)\n        at org.eclipse.swt.SWT.error(SWT.java:2110)\n        at org.eclipse.swt.custom.StyledText.redrawRange(StyledText.java:6087)\n        at org.eclipse.jdt.internal.ui.javaeditor.ProblemPainter.draw\n(ProblemPainter.java:331)\n        at \norg.eclipse.jdt.internal.ui.javaeditor.ProblemPainter.handleDrawRequest\n(ProblemPainter.java:268)\n        at org.eclipse.jdt.internal.ui.javaeditor.ProblemPainter.disablePainting\n(ProblemPainter.java:95)\n        at org.eclipse.jdt.internal.ui.javaeditor.ProblemPainter.updatePainting\n(ProblemPainter.java:143)\n        at org.eclipse.jdt.internal.ui.javaeditor.ProblemPainter.access$1\n(ProblemPainter.java:142)\n        at org.eclipse.jdt.internal.ui.javaeditor.ProblemPainter$1.run\n(ProblemPainter.java:162)\n        at org.eclipse.swt.widgets.RunnableLock.run(RunnableLock.java:31)\n        at org.eclipse.swt.widgets.Synchronizer.runAsyncMessages\n(Synchronizer.java:94)\n        at org.eclipse.swt.widgets.Display.runAsyncMessages(Display.java:1669)\n        at org.eclipse.swt.widgets.Display.readAndDispatch(Display.java:1414)\n        at org.eclipse.ui.internal.Workbench.runEventLoop(Workbench.java:1419)\n        at org.eclipse.ui.internal.Workbench.run(Workbench.java:1402)\n        at org.eclipse.core.internal.boot.InternalBootLoader.run\n(InternalBootLoader.java:831)\n        at org.eclipse.core.boot.BootLoader.run(BootLoader.java:462)\n        at sun.reflect.NativeMethodAccessorImpl.invoke0(Native Method)\n        at sun.reflect.NativeMethodAccessorImpl.invoke\n(NativeMethodAccessorImpl.java:39)\n        at sun.reflect.DelegatingMethodAccessorImpl.invoke\n(DelegatingMethodAccessorImpl.java:25)\n        at java.lang.reflect.Method.invoke(Method.java:324)\n        at org.eclipse.core.launcher.Main.basicRun(Main.java:247)\n        at org.eclipse.core.launcher.Main.run(Main.java:703)\n        at org.eclipse.core.launcher.Main.main(Main.java:539)\nIndex out of bounds",
    "*** Bug 25881 has been marked as a duplicate of this bug. ***",
    "I suppose this bug is caused by the NPE in bug 25900.\n\n\n*** This bug has been marked as a duplicate of 25900 ***",
    "*** Bug 25987 has been marked as a duplicate of this bug. ***",
    "*** Bug 26031 has been marked as a duplicate of this bug. ***",
    "*** Bug 27178 has been marked as a duplicate of this bug. ***"
  ],
  "commentCreationDates": [
    "2002-11-07T11:56:54+01:00",
    "2002-11-08T13:24:35+01:00",
    "2002-11-11T15:05:27+01:00",
    "2002-11-12T12:04:10+01:00",
    "2002-11-13T07:56:03+01:00",
    "2003-07-16T18:17:08+02:00"
  ],
  "traces": [
    {
      "exceptionType": "java.lang.IllegalArgumentException",
      "message": "Index out of bounds",
      "elements": [
        {
          "method": "org.eclipse.swt.SWT.error",
          "source": "SWT.java:2166"
        },
        {
          "method": "org.eclipse.swt.SWT.error",
          "source": "SWT.java:2110"
        },
        {
          "method": "org.eclipse.swt.custom.StyledText.redrawRange",
          "source": "StyledText.java:6087"
        },
        {
          "method": "org.eclipse.jdt.internal.ui.javaeditor.ProblemPainter.draw",
          "source": "ProblemPainter.java:331"
        },
        {
          "method": "org.eclipse.jdt.internal.ui.javaeditor.ProblemPainter.handleDrawRequest",
          "source": "ProblemPainter.java:268"
        },
        {
          "method": "org.eclipse.jdt.internal.ui.javaeditor.ProblemPainter.disablePainting",
          "source": "ProblemPainter.java:95"
        },
        {
          "method": "org.eclipse.jdt.internal.ui.javaeditor.ProblemPainter.updatePainting",
          "source": "ProblemPainter.java:143"
        },
        {
          "method": "org.eclipse.jdt.internal.ui.javaeditor.ProblemPainter.access$1",
          "source": "ProblemPainter.java:142"
        },
        {
          "method": "org.eclipse.jdt.internal.ui.javaeditor.ProblemPainter$1.run",
          "source": "ProblemPainter.java:162"
        },
        {
          "method": "org.eclipse.swt.widgets.RunnableLock.run",
          "source": "RunnableLock.java:31"
        },
        {
          "method": "org.eclipse.swt.widgets.Synchronizer.runAsyncMessages",
          "source": "Synchronizer.java:94"
        },
        {
          "method": "org.eclipse.swt.widgets.Display.runAsyncMessages",
          "source": "Display.java:1669"
        },
        {
          "method": "org.eclipse.swt.widgets.Display.readAndDispatch",
          "source": "Display.java:1414"
        },
        {
          "method": "org.eclipse.ui.internal.Workbench.runEventLoop",
          "source": "Workbench.java:1419"
        },
        {
          "method": "org.eclipse.ui.internal.Workbench.run",
          "source": "Workbench.java:1402"
        },
        {
          "method": "org.eclipse.core.internal.boot.InternalBootLoader.run",
          "source": "InternalBootLoader.java:831"
        },
        {
          "method": "org.eclipse.core.boot.BootLoader.run",
          "source": "BootLoader.java:462"
        },
        {
          "method": "sun.reflect.NativeMethodAccessorImpl.invoke0",
          "source": "Native Method"
        },
        {
          "method": "sun.reflect.NativeMethodAccessorImpl.invoke",
          "source": "NativeMethodAccessorImpl.java:39"
        },
        {
          "method": "sun.reflect.DelegatingMethodAccessorImpl.invoke",
          "source": "DelegatingMethodAccessorImpl.java:25"
        },
        {
          "method": "java.lang.reflect.Method.invoke",
          "source": "Method.java:324"
        },
        {
          "method": "org.eclipse.core.launcher.Main.basicRun",
          "source": "Main.java:247"
        },
        {
          "method": "org.eclipse.core.launcher.Main.run",
          "source": "Main.java:703"
        },
        {
          "method": "org.eclipse.core.launcher.Main.main",
          "source": "Main.java:539"
        }
      ],
      "number": 0,
      "commentIndex": 0,
      "bugId": "25812",
      "duplicateId": "25900",
      "date": "2002-11-07T11:56:54+01:00",
      "product": "JDT",
      "component": "Text",
      "severity": "major"
    }
  ],
  "groupId": "25900",
  "bugId": "25812",
  "duplicateId": "25900",
  "date": "2002-11-07T11:56:54+01:00",
  "product": "JDT",
  "component": "Text",
  "severity": "major"
}