{
  "comments": [
    "Build 20021105\n\nNoticed the following during startup (I hadn\u0027t experienced any problem on \nprevious shutdown):\n\n!ENTRY org.eclipse.core.resources 4 567 Nov 07, 2002 13:50:01.428\n!MESSAGE Problems occurred while restoring the workspace.\n!SUBENTRY 1 org.eclipse.core.resources 4 567 Nov 07, 2002 13:50:01.428\n!MESSAGE Could not read metadata for: \nD:/eclipse/workspaces/dev2.0/plugins/.metadata/.plugins/org.eclipse.core.resourc\nes/.projects/org.eclipse.jdt/.markers.\n!STACK 0\njava.io.EOFException\n        at java.io.DataInputStream.readInt(DataInputStream.java:397)\n        at org.eclipse.core.internal.resources.MarkerReader.readVersionNumber\n(MarkerReader.java:50)\n        at org.eclipse.core.internal.resources.MarkerReader.read\n(MarkerReader.java:45)\n        at org.eclipse.core.internal.resources.MarkerManager.restoreFromSave\n(MarkerManager.java:438)\n        at org.eclipse.core.internal.resources.MarkerManager.restore\n(MarkerManager.java:428)\n        at org.eclipse.core.internal.resources.SaveManager.restoreMarkers\n(SaveManager.java:508)\n        at org.eclipse.core.internal.resources.SaveManager.restore\n(SaveManager.java:468)\n        at org.eclipse.core.internal.resources.SaveManager.startup\n(SaveManager.java:947)\n        at org.eclipse.core.internal.resources.Workspace.startup\n(Workspace.java:1565)\n        at org.eclipse.core.internal.resources.Workspace.open\n(Workspace.java:1357)\n        at org.eclipse.core.resources.ResourcesPlugin.startup\n(ResourcesPlugin.java:207)\n        at org.eclipse.core.internal.plugins.PluginDescriptor$1.run\n(PluginDescriptor.java:697)\n        at org.eclipse.core.internal.runtime.InternalPlatform.run\n(InternalPlatform.java:839)\n        at \norg.eclipse.core.internal.plugins.PluginDescriptor.internalDoPluginActivation\n(PluginDescriptor.java:709)\n        at org.eclipse.core.internal.plugins.PluginDescriptor.doPluginActivation\n(PluginDescriptor.java:184)\n        at org.eclipse.core.internal.plugins.PluginClassLoader.activatePlugin\n(PluginClassLoader.java:60)\n        at \norg.eclipse.core.internal.plugins.PluginClassLoader.internalFindClassParentsSelf\n(PluginClassLoader.java:138)\n        at \norg.eclipse.core.internal.boot.DelegatingURLClassLoader.findClassParentsSelf\n(DelegatingURLClassLoader.java:473)\n        at org.eclipse.core.internal.boot.DelegatingURLClassLoader.loadClass\n(DelegatingURLClassLoader.java:863)\n        at org.eclipse.core.internal.boot.DelegatingURLClassLoader.access$0\n(DelegatingURLClassLoader.java:857)\n        at \norg.eclipse.core.internal.boot.DelegatingURLClassLoader$DelegateLoader.loadClass\n(DelegatingURLClassLoader.java:80)\n        at \norg.eclipse.core.internal.boot.DelegatingURLClassLoader.findClassPrerequisites\n(DelegatingURLClassLoader.java:537)\n        at org.eclipse.core.internal.boot.DelegatingURLClassLoader.loadClass\n(DelegatingURLClassLoader.java:871)\n        at org.eclipse.core.internal.boot.DelegatingURLClassLoader.loadClass\n(DelegatingURLClassLoader.java:843)\n        at java.lang.ClassLoader.loadClass(ClassLoader.java:255)\n        at java.lang.ClassLoader.loadClassInternal(ClassLoader.java:315)\n        at java.lang.Class.getDeclaredConstructors0(Native Method)\n        at java.lang.Class.privateGetDeclaredConstructors(Class.java:1590)\n        at java.lang.Class.getConstructor0(Class.java:1762)\n        at java.lang.Class.newInstance0(Class.java:276)\n        at java.lang.Class.newInstance(Class.java:259)\n        at \norg.eclipse.core.internal.plugins.PluginDescriptor.createExecutableExtension\n(PluginDescriptor.java:136)\n        at \norg.eclipse.core.internal.plugins.PluginDescriptor.createExecutableExtension\n(PluginDescriptor.java:165)\n        at \norg.eclipse.core.internal.plugins.ConfigurationElement.createExecutableExtension\n(ConfigurationElement.java:102)\n        at org.eclipse.core.internal.runtime.InternalPlatform.loaderGetRunnable\n(InternalPlatform.java:461)\n        at sun.reflect.NativeMethodAccessorImpl.invoke0(Native Method)\n        at sun.reflect.NativeMethodAccessorImpl.invoke\n(NativeMethodAccessorImpl.java:39)\n        at sun.reflect.DelegatingMethodAccessorImpl.invoke\n(DelegatingMethodAccessorImpl.java:25)\n        at java.lang.reflect.Method.invoke(Method.java:324)\n        at org.eclipse.core.internal.boot.InternalBootLoader.getRunnable\n(InternalBootLoader.java:457)\n        at org.eclipse.core.internal.boot.InternalBootLoader.run\n(InternalBootLoader.java:827)\n        at org.eclipse.core.boot.BootLoader.run(BootLoader.java:462)\n        at sun.reflect.NativeMethodAccessorImpl.invoke0(Native Method)\n        at sun.reflect.NativeMethodAccessorImpl.invoke\n(NativeMethodAccessorImpl.java:39)\n        at sun.reflect.DelegatingMethodAccessorImpl.invoke\n(DelegatingMethodAccessorImpl.java:25)\n        at java.lang.reflect.Method.invoke(Method.java:324)\n        at org.eclipse.core.launcher.Main.basicRun(Main.java:247)\n        at org.eclipse.core.launcher.Main.run(Main.java:703)\n        at org.eclipse.core.launcher.Main.main(Main.java:539)\n!SUBENTRY 1 org.eclipse.core.resources 4 567 Nov 07, 2002 13:50:01.444\n!MESSAGE Could not read metadata for: \nD:/eclipse/workspaces/dev2.0/plugins/.metadata/.plugins/org.eclipse.core.resourc\nes/.projects/org.eclipse.jdt/.syncinfo.\n!STACK 0\njava.io.EOFException\n        at java.io.DataInputStream.readInt(DataInputStream.java:397)\n        at org.eclipse.core.internal.resources.SyncInfoReader.readVersionNumber\n(SyncInfoReader.java:68)\n        at org.eclipse.core.internal.resources.SyncInfoReader.readSyncInfo\n(SyncInfoReader.java:63)\n        at org.eclipse.core.internal.resources.Synchronizer.restoreFromSave\n(Synchronizer.java:145)\n        at org.eclipse.core.internal.resources.Synchronizer.restore\n(Synchronizer.java:135)\n        at org.eclipse.core.internal.resources.SaveManager.restoreSyncInfo\n(SaveManager.java:649)\n        at org.eclipse.core.internal.resources.SaveManager.restore\n(SaveManager.java:473)\n        at org.eclipse.core.internal.resources.SaveManager.startup\n(SaveManager.java:947)\n        at org.eclipse.core.internal.resources.Workspace.startup\n(Workspace.java:1565)\n        at org.eclipse.core.internal.resources.Workspace.open\n(Workspace.java:1357)\n        at org.eclipse.core.resources.ResourcesPlugin.startup\n(ResourcesPlugin.java:207)\n        at org.eclipse.core.internal.plugins.PluginDescriptor$1.run\n(PluginDescriptor.java:697)\n        at org.eclipse.core.internal.runtime.InternalPlatform.run\n(InternalPlatform.java:839)\n        at \norg.eclipse.core.internal.plugins.PluginDescriptor.internalDoPluginActivation\n(PluginDescriptor.java:709)\n        at org.eclipse.core.internal.plugins.PluginDescriptor.doPluginActivation\n(PluginDescriptor.java:184)\n        at org.eclipse.core.internal.plugins.PluginClassLoader.activatePlugin\n(PluginClassLoader.java:60)\n        at \norg.eclipse.core.internal.plugins.PluginClassLoader.internalFindClassParentsSelf\n(PluginClassLoader.java:138)\n        at \norg.eclipse.core.internal.boot.DelegatingURLClassLoader.findClassParentsSelf\n(DelegatingURLClassLoader.java:473)\n        at org.eclipse.core.internal.boot.DelegatingURLClassLoader.loadClass\n(DelegatingURLClassLoader.java:863)\n        at org.eclipse.core.internal.boot.DelegatingURLClassLoader.access$0\n(DelegatingURLClassLoader.java:857)\n        at \norg.eclipse.core.internal.boot.DelegatingURLClassLoader$DelegateLoader.loadClass\n(DelegatingURLClassLoader.java:80)\n        at \norg.eclipse.core.internal.boot.DelegatingURLClassLoader.findClassPrerequisites\n(DelegatingURLClassLoader.java:537)\n        at org.eclipse.core.internal.boot.DelegatingURLClassLoader.loadClass\n(DelegatingURLClassLoader.java:871)\n        at org.eclipse.core.internal.boot.DelegatingURLClassLoader.loadClass\n(DelegatingURLClassLoader.java:843)\n        at java.lang.ClassLoader.loadClass(ClassLoader.java:255)\n        at java.lang.ClassLoader.loadClassInternal(ClassLoader.java:315)\n        at java.lang.Class.getDeclaredConstructors0(Native Method)\n        at java.lang.Class.privateGetDeclaredConstructors(Class.java:1590)\n        at java.lang.Class.getConstructor0(Class.java:1762)\n        at java.lang.Class.newInstance0(Class.java:276)\n        at java.lang.Class.newInstance(Class.java:259)\n        at \norg.eclipse.core.internal.plugins.PluginDescriptor.createExecutableExtension\n(PluginDescriptor.java:136)\n        at \norg.eclipse.core.internal.plugins.PluginDescriptor.createExecutableExtension\n(PluginDescriptor.java:165)\n        at \norg.eclipse.core.internal.plugins.ConfigurationElement.createExecutableExtension\n(ConfigurationElement.java:102)\n        at org.eclipse.core.internal.runtime.InternalPlatform.loaderGetRunnable\n(InternalPlatform.java:461)\n        at sun.reflect.NativeMethodAccessorImpl.invoke0(Native Method)\n        at sun.reflect.NativeMethodAccessorImpl.invoke\n(NativeMethodAccessorImpl.java:39)\n        at sun.reflect.DelegatingMethodAccessorImpl.invoke\n(DelegatingMethodAccessorImpl.java:25)\n        at java.lang.reflect.Method.invoke(Method.java:324)\n        at org.eclipse.core.internal.boot.InternalBootLoader.getRunnable\n(InternalBootLoader.java:457)\n        at org.eclipse.core.internal.boot.InternalBootLoader.run\n(InternalBootLoader.java:827)\n        at org.eclipse.core.boot.BootLoader.run(BootLoader.java:462)\n        at sun.reflect.NativeMethodAccessorImpl.invoke0(Native Method)\n        at sun.reflect.NativeMethodAccessorImpl.invoke\n(NativeMethodAccessorImpl.java:39)\n        at sun.reflect.DelegatingMethodAccessorImpl.invoke\n(DelegatingMethodAccessorImpl.java:25)\n        at java.lang.reflect.Method.invoke(Method.java:324)\n        at org.eclipse.core.launcher.Main.basicRun(Main.java:247)\n        at org.eclipse.core.launcher.Main.run(Main.java:703)\n        at org.eclipse.core.launcher.Main.main(Main.java:539)",
    "Did this prevent startup or is this just a message that you happened to notice \nin the log file?\n",
    "Just a message in the log. The workbench opened nicely.",
    "There are two issues here.\n\n1). Message is silently logged but the description in the log file does not \nindicate to the user whether or not it is ok. Duplicate of bug 25353.\n\n2). Why did we have an empty markers save file in the first place? Investigate \nSaveManager code for potential answers.",
    "Closing old bug.  Never reproduced."
  ],
  "commentCreationDates": [
    "2002-11-07T12:46:54+01:00",
    "2002-11-07T15:20:04+01:00",
    "2002-11-08T14:17:28+01:00",
    "2002-11-08T21:57:30+01:00",
    "2005-01-12T18:47:34+01:00"
  ],
  "traces": [
    {
      "exceptionType": "java.io.EOFException",
      "elements": [
        {
          "method": "java.io.DataInputStream.readInt",
          "source": "DataInputStream.java:397"
        },
        {
          "method": "org.eclipse.core.internal.resources.MarkerReader.readVersionNumber",
          "source": "MarkerReader.java:50"
        },
        {
          "method": "org.eclipse.core.internal.resources.MarkerReader.read",
          "source": "MarkerReader.java:45"
        },
        {
          "method": "org.eclipse.core.internal.resources.MarkerManager.restoreFromSave",
          "source": "MarkerManager.java:438"
        },
        {
          "method": "org.eclipse.core.internal.resources.MarkerManager.restore",
          "source": "MarkerManager.java:428"
        },
        {
          "method": "org.eclipse.core.internal.resources.SaveManager.restoreMarkers",
          "source": "SaveManager.java:508"
        },
        {
          "method": "org.eclipse.core.internal.resources.SaveManager.restore",
          "source": "SaveManager.java:468"
        },
        {
          "method": "org.eclipse.core.internal.resources.SaveManager.startup",
          "source": "SaveManager.java:947"
        },
        {
          "method": "org.eclipse.core.internal.resources.Workspace.startup",
          "source": "Workspace.java:1565"
        },
        {
          "method": "org.eclipse.core.internal.resources.Workspace.open",
          "source": "Workspace.java:1357"
        },
        {
          "method": "org.eclipse.core.resources.ResourcesPlugin.startup",
          "source": "ResourcesPlugin.java:207"
        },
        {
          "method": "org.eclipse.core.internal.plugins.PluginDescriptor$1.run",
          "source": "PluginDescriptor.java:697"
        },
        {
          "method": "org.eclipse.core.internal.runtime.InternalPlatform.run",
          "source": "InternalPlatform.java:839"
        },
        {
          "method": "org.eclipse.core.internal.plugins.PluginDescriptor.internalDoPluginActivation",
          "source": "PluginDescriptor.java:709"
        },
        {
          "method": "org.eclipse.core.internal.plugins.PluginDescriptor.doPluginActivation",
          "source": "PluginDescriptor.java:184"
        },
        {
          "method": "org.eclipse.core.internal.plugins.PluginClassLoader.activatePlugin",
          "source": "PluginClassLoader.java:60"
        },
        {
          "method": "org.eclipse.core.internal.plugins.PluginClassLoader.internalFindClassParentsSelf",
          "source": "PluginClassLoader.java:138"
        },
        {
          "method": "org.eclipse.core.internal.boot.DelegatingURLClassLoader.findClassParentsSelf",
          "source": "DelegatingURLClassLoader.java:473"
        },
        {
          "method": "org.eclipse.core.internal.boot.DelegatingURLClassLoader.loadClass",
          "source": "DelegatingURLClassLoader.java:863"
        },
        {
          "method": "org.eclipse.core.internal.boot.DelegatingURLClassLoader.access$0",
          "source": "DelegatingURLClassLoader.java:857"
        },
        {
          "method": "org.eclipse.core.internal.boot.DelegatingURLClassLoader$DelegateLoader.loadClass",
          "source": "DelegatingURLClassLoader.java:80"
        },
        {
          "method": "org.eclipse.core.internal.boot.DelegatingURLClassLoader.findClassPrerequisites",
          "source": "DelegatingURLClassLoader.java:537"
        },
        {
          "method": "org.eclipse.core.internal.boot.DelegatingURLClassLoader.loadClass",
          "source": "DelegatingURLClassLoader.java:871"
        },
        {
          "method": "org.eclipse.core.internal.boot.DelegatingURLClassLoader.loadClass",
          "source": "DelegatingURLClassLoader.java:843"
        },
        {
          "method": "java.lang.ClassLoader.loadClass",
          "source": "ClassLoader.java:255"
        },
        {
          "method": "java.lang.ClassLoader.loadClassInternal",
          "source": "ClassLoader.java:315"
        },
        {
          "method": "java.lang.Class.getDeclaredConstructors0",
          "source": "Native Method"
        },
        {
          "method": "java.lang.Class.privateGetDeclaredConstructors",
          "source": "Class.java:1590"
        },
        {
          "method": "java.lang.Class.getConstructor0",
          "source": "Class.java:1762"
        },
        {
          "method": "java.lang.Class.newInstance0",
          "source": "Class.java:276"
        },
        {
          "method": "java.lang.Class.newInstance",
          "source": "Class.java:259"
        },
        {
          "method": "org.eclipse.core.internal.plugins.PluginDescriptor.createExecutableExtension",
          "source": "PluginDescriptor.java:136"
        },
        {
          "method": "org.eclipse.core.internal.plugins.PluginDescriptor.createExecutableExtension",
          "source": "PluginDescriptor.java:165"
        },
        {
          "method": "org.eclipse.core.internal.plugins.ConfigurationElement.createExecutableExtension",
          "source": "ConfigurationElement.java:102"
        },
        {
          "method": "org.eclipse.core.internal.runtime.InternalPlatform.loaderGetRunnable",
          "source": "InternalPlatform.java:461"
        },
        {
          "method": "sun.reflect.NativeMethodAccessorImpl.invoke0",
          "source": "Native Method"
        },
        {
          "method": "sun.reflect.NativeMethodAccessorImpl.invoke",
          "source": "NativeMethodAccessorImpl.java:39"
        },
        {
          "method": "sun.reflect.DelegatingMethodAccessorImpl.invoke",
          "source": "DelegatingMethodAccessorImpl.java:25"
        },
        {
          "method": "java.lang.reflect.Method.invoke",
          "source": "Method.java:324"
        },
        {
          "method": "org.eclipse.core.internal.boot.InternalBootLoader.getRunnable",
          "source": "InternalBootLoader.java:457"
        },
        {
          "method": "org.eclipse.core.internal.boot.InternalBootLoader.run",
          "source": "InternalBootLoader.java:827"
        },
        {
          "method": "org.eclipse.core.boot.BootLoader.run",
          "source": "BootLoader.java:462"
        },
        {
          "method": "sun.reflect.NativeMethodAccessorImpl.invoke0",
          "source": "Native Method"
        },
        {
          "method": "sun.reflect.NativeMethodAccessorImpl.invoke",
          "source": "NativeMethodAccessorImpl.java:39"
        },
        {
          "method": "sun.reflect.DelegatingMethodAccessorImpl.invoke",
          "source": "DelegatingMethodAccessorImpl.java:25"
        },
        {
          "method": "java.lang.reflect.Method.invoke",
          "source": "Method.java:324"
        },
        {
          "method": "org.eclipse.core.launcher.Main.basicRun",
          "source": "Main.java:247"
        },
        {
          "method": "org.eclipse.core.launcher.Main.run",
          "source": "Main.java:703"
        },
        {
          "method": "org.eclipse.core.launcher.Main.main",
          "source": "Main.java:539"
        }
      ],
      "number": 0,
      "commentIndex": 0,
      "bugId": "25813",
      "date": "2002-11-07T12:46:54+01:00",
      "product": "Platform",
      "component": "Resources",
      "severity": "normal"
    },
    {
      "exceptionType": "java.io.EOFException",
      "elements": [
        {
          "method": "java.io.DataInputStream.readInt",
          "source": "DataInputStream.java:397"
        },
        {
          "method": "org.eclipse.core.internal.resources.SyncInfoReader.readVersionNumber",
          "source": "SyncInfoReader.java:68"
        },
        {
          "method": "org.eclipse.core.internal.resources.SyncInfoReader.readSyncInfo",
          "source": "SyncInfoReader.java:63"
        },
        {
          "method": "org.eclipse.core.internal.resources.Synchronizer.restoreFromSave",
          "source": "Synchronizer.java:145"
        },
        {
          "method": "org.eclipse.core.internal.resources.Synchronizer.restore",
          "source": "Synchronizer.java:135"
        },
        {
          "method": "org.eclipse.core.internal.resources.SaveManager.restoreSyncInfo",
          "source": "SaveManager.java:649"
        },
        {
          "method": "org.eclipse.core.internal.resources.SaveManager.restore",
          "source": "SaveManager.java:473"
        },
        {
          "method": "org.eclipse.core.internal.resources.SaveManager.startup",
          "source": "SaveManager.java:947"
        },
        {
          "method": "org.eclipse.core.internal.resources.Workspace.startup",
          "source": "Workspace.java:1565"
        },
        {
          "method": "org.eclipse.core.internal.resources.Workspace.open",
          "source": "Workspace.java:1357"
        },
        {
          "method": "org.eclipse.core.resources.ResourcesPlugin.startup",
          "source": "ResourcesPlugin.java:207"
        },
        {
          "method": "org.eclipse.core.internal.plugins.PluginDescriptor$1.run",
          "source": "PluginDescriptor.java:697"
        },
        {
          "method": "org.eclipse.core.internal.runtime.InternalPlatform.run",
          "source": "InternalPlatform.java:839"
        },
        {
          "method": "org.eclipse.core.internal.plugins.PluginDescriptor.internalDoPluginActivation",
          "source": "PluginDescriptor.java:709"
        },
        {
          "method": "org.eclipse.core.internal.plugins.PluginDescriptor.doPluginActivation",
          "source": "PluginDescriptor.java:184"
        },
        {
          "method": "org.eclipse.core.internal.plugins.PluginClassLoader.activatePlugin",
          "source": "PluginClassLoader.java:60"
        },
        {
          "method": "org.eclipse.core.internal.plugins.PluginClassLoader.internalFindClassParentsSelf",
          "source": "PluginClassLoader.java:138"
        },
        {
          "method": "org.eclipse.core.internal.boot.DelegatingURLClassLoader.findClassParentsSelf",
          "source": "DelegatingURLClassLoader.java:473"
        },
        {
          "method": "org.eclipse.core.internal.boot.DelegatingURLClassLoader.loadClass",
          "source": "DelegatingURLClassLoader.java:863"
        },
        {
          "method": "org.eclipse.core.internal.boot.DelegatingURLClassLoader.access$0",
          "source": "DelegatingURLClassLoader.java:857"
        },
        {
          "method": "org.eclipse.core.internal.boot.DelegatingURLClassLoader$DelegateLoader.loadClass",
          "source": "DelegatingURLClassLoader.java:80"
        },
        {
          "method": "org.eclipse.core.internal.boot.DelegatingURLClassLoader.findClassPrerequisites",
          "source": "DelegatingURLClassLoader.java:537"
        },
        {
          "method": "org.eclipse.core.internal.boot.DelegatingURLClassLoader.loadClass",
          "source": "DelegatingURLClassLoader.java:871"
        },
        {
          "method": "org.eclipse.core.internal.boot.DelegatingURLClassLoader.loadClass",
          "source": "DelegatingURLClassLoader.java:843"
        },
        {
          "method": "java.lang.ClassLoader.loadClass",
          "source": "ClassLoader.java:255"
        },
        {
          "method": "java.lang.ClassLoader.loadClassInternal",
          "source": "ClassLoader.java:315"
        },
        {
          "method": "java.lang.Class.getDeclaredConstructors0",
          "source": "Native Method"
        },
        {
          "method": "java.lang.Class.privateGetDeclaredConstructors",
          "source": "Class.java:1590"
        },
        {
          "method": "java.lang.Class.getConstructor0",
          "source": "Class.java:1762"
        },
        {
          "method": "java.lang.Class.newInstance0",
          "source": "Class.java:276"
        },
        {
          "method": "java.lang.Class.newInstance",
          "source": "Class.java:259"
        },
        {
          "method": "org.eclipse.core.internal.plugins.PluginDescriptor.createExecutableExtension",
          "source": "PluginDescriptor.java:136"
        },
        {
          "method": "org.eclipse.core.internal.plugins.PluginDescriptor.createExecutableExtension",
          "source": "PluginDescriptor.java:165"
        },
        {
          "method": "org.eclipse.core.internal.plugins.ConfigurationElement.createExecutableExtension",
          "source": "ConfigurationElement.java:102"
        },
        {
          "method": "org.eclipse.core.internal.runtime.InternalPlatform.loaderGetRunnable",
          "source": "InternalPlatform.java:461"
        },
        {
          "method": "sun.reflect.NativeMethodAccessorImpl.invoke0",
          "source": "Native Method"
        },
        {
          "method": "sun.reflect.NativeMethodAccessorImpl.invoke",
          "source": "NativeMethodAccessorImpl.java:39"
        },
        {
          "method": "sun.reflect.DelegatingMethodAccessorImpl.invoke",
          "source": "DelegatingMethodAccessorImpl.java:25"
        },
        {
          "method": "java.lang.reflect.Method.invoke",
          "source": "Method.java:324"
        },
        {
          "method": "org.eclipse.core.internal.boot.InternalBootLoader.getRunnable",
          "source": "InternalBootLoader.java:457"
        },
        {
          "method": "org.eclipse.core.internal.boot.InternalBootLoader.run",
          "source": "InternalBootLoader.java:827"
        },
        {
          "method": "org.eclipse.core.boot.BootLoader.run",
          "source": "BootLoader.java:462"
        },
        {
          "method": "sun.reflect.NativeMethodAccessorImpl.invoke0",
          "source": "Native Method"
        },
        {
          "method": "sun.reflect.NativeMethodAccessorImpl.invoke",
          "source": "NativeMethodAccessorImpl.java:39"
        },
        {
          "method": "sun.reflect.DelegatingMethodAccessorImpl.invoke",
          "source": "DelegatingMethodAccessorImpl.java:25"
        },
        {
          "method": "java.lang.reflect.Method.invoke",
          "source": "Method.java:324"
        },
        {
          "method": "org.eclipse.core.launcher.Main.basicRun",
          "source": "Main.java:247"
        },
        {
          "method": "org.eclipse.core.launcher.Main.run",
          "source": "Main.java:703"
        },
        {
          "method": "org.eclipse.core.launcher.Main.main",
          "source": "Main.java:539"
        }
      ],
      "number": 1,
      "commentIndex": 0,
      "bugId": "25813",
      "date": "2002-11-07T12:46:54+01:00",
      "product": "Platform",
      "component": "Resources",
      "severity": "normal"
    }
  ],
  "groupId": "25813",
  "bugId": "25813",
  "date": "2002-11-07T12:46:54+01:00",
  "product": "Platform",
  "component": "Resources",
  "severity": "normal"
}