{
  "comments": [
    "I200211120800\nTry to save a Java file that I have been editing.\nGet error dialog saying:\nSave could not be completed.  Errors during build.\n\nThere is also a log entry:\n\n!ENTRY org.eclipse.core.resources 4 2 Nov 12, 2002 17:08:31.130\n!MESSAGE Problems occurred when invoking code from plug-in: \n\"org.eclipse.core.resources\".\n!STACK 0\njava.lang.IllegalArgumentException: Path must include project and resource name.\n        at org.eclipse.core.internal.utils.Assert.isLegal(Assert.java:55)\n        at \norg.eclipse.core.internal.resources.Workspace.newResource(Workspace.java:1413)\n        at org.eclipse.core.internal.resources.Container.getFolder(Container.java:131)\n        at \norg.eclipse.jdt.internal.core.builder.NameEnvironment.computeClasspathLocations(Nam\neEnviro\nnment.java:102)\n        at org.eclipse.jdt.internal.core.builder.NameEnvironment.\u003cinit\u003e\n(NameEnvironment.java:36)\n        at \norg.eclipse.jdt.internal.core.builder.JavaBuilder.initializeBuilder(JavaBuilder.java:417)\n        at org.eclipse.jdt.internal.core.builder.JavaBuilder.build(JavaBuilder.java:97)\n        at org.eclipse.core.internal.events.BuildManager$2.run(BuildManager.java:393)\n        at org.eclipse.core.internal.runtime.InternalPlatform.run(InternalPlatform.java:839)\n        at org.eclipse.core.runtime.Platform.run(Platform.java:413)\n        at \norg.eclipse.core.internal.events.BuildManager.basicBuild(BuildManager.java:120)\n        at \norg.eclipse.core.internal.events.BuildManager.basicBuild(BuildManager.java:176)\n        at \norg.eclipse.core.internal.events.BuildManager.basicBuild(BuildManager.java:186)\n        at org.eclipse.core.internal.events.BuildManager$1.run(BuildManager.java:146)\n        at org.eclipse.core.internal.runtime.InternalPlatform.run(InternalPlatform.java:839)\n        at org.eclipse.core.runtime.Platform.run(Platform.java:413)\n        at \norg.eclipse.core.internal.events.BuildManager.basicBuild(BuildManager.java:160)\n        at org.eclipse.core.internal.events.BuildManager.build(BuildManager.java:211)\n        at \norg.eclipse.core.internal.resources.Workspace.endOperation(Workspace.java:863)\n        at org.eclipse.core.internal.resources.Workspace.run(Workspace.java:1571)\n        at \norg.eclipse.ui.actions.WorkspaceModifyOperation.run(WorkspaceModifyOperation.java:7\n9)\n        at \norg.eclipse.ui.texteditor.AbstractTextEditor.performSaveOperation(AbstractTextEditor.jav\na:\n2596)\n        at \norg.eclipse.jdt.internal.ui.javaeditor.CompilationUnitEditor.performSaveOperation(Compi\nlat\nionUnitEditor.java:797)\n        at \norg.eclipse.jdt.internal.ui.javaeditor.CompilationUnitEditor.doSave(CompilationUnitEdito\nr.\njava:847)\n        at org.eclipse.ui.internal.EditorManager$11.run(EditorManager.java:1015)\n        at org.eclipse.ui.internal.EditorManager$8.run(EditorManager.java:884)\n        at \norg.eclipse.jface.operation.ModalContext.runInCurrentThread(ModalContext.java:296)\n        at org.eclipse.jface.operation.ModalContext.run(ModalContext.java:246)\n        at org.eclipse.jface.window.ApplicationWindow$1.run(ApplicationWindow.java:391)\n        at org.eclipse.swt.custom.BusyIndicator.showWhile(BusyIndicator.java:65)\n        at org.eclipse.jface.window.ApplicationWindow.run(ApplicationWindow.java:388)\n        at org.eclipse.ui.internal.WorkbenchWindow.run(WorkbenchWindow.java:1147)\n        at \norg.eclipse.ui.internal.EditorManager.runProgressMonitorOperation(EditorManager.java:\n890)\n        at org.eclipse.ui.internal.EditorManager.saveEditor(EditorManager.java:1020)\n        at org.eclipse.ui.internal.WorkbenchPage.saveEditor(WorkbenchPage.java:2051)\n        at org.eclipse.ui.internal.SaveAction.run(SaveAction.java:30)\n        at org.eclipse.jface.action.Action.runWithEvent(Action.java:769)\n        at \norg.eclipse.ui.internal.WWinKeyBindingService.invoke(WWinKeyBindingService.java:13\n9)\n        at \norg.eclipse.ui.internal.WWinKeyBindingService.pressed(WWinKeyBindingService.java:1\n20)\n        at \norg.eclipse.ui.internal.WWinKeyBindingService$5.widgetSelected(WWinKeyBindingServ\nice.java:\n367)\n        at org.eclipse.ui.internal.AcceleratorMenu$2.handleEvent(AcceleratorMenu.java:53)\n        at org.eclipse.swt.widgets.EventTable.sendEvent(EventTable.java:77)\n        at org.eclipse.swt.widgets.Widget.notifyListeners(Widget.java:485)\n        at org.eclipse.swt.widgets.Display.runDeferredEvents(Display.java:1272)\n        at org.eclipse.swt.widgets.Display.readAndDispatch(Display.java:1120)\n        at org.eclipse.ui.internal.Workbench.runEventLoop(Workbench.java:1435)\n        at org.eclipse.ui.internal.Workbench.run(Workbench.java:1418)\n        at \norg.eclipse.core.internal.boot.InternalBootLoader.run(InternalBootLoader.java:831)\n        at org.eclipse.core.boot.BootLoader.run(BootLoader.java:462)\n        at java.lang.reflect.Method.invoke(Native Method)\n        at org.eclipse.core.launcher.Main.basicRun(Main.java:247)\n        at org.eclipse.core.launcher.Main.run(Main.java:703)\n        at org.eclipse.core.launcher.Main.main(Main.java:539)\n        at java.lang.reflect.Method.invoke(Native Method)\n        at com.apple.buckyball.app.LaunchRunner.run(LaunchRunner.java:82)\n        at com.apple.buckyball.app.LaunchRunner.callMain(LaunchRunner.java:44)\n        at com.apple.buckyball.app.CarbonLibApp.launch(CarbonLibApp.java:67)",
    "This may be duplicate of 26053.  Moving to JDT Core for comment.",
    "Indeed this is a duplicate",
    "\n\n*** This bug has been marked as a duplicate of 26053 ***"
  ],
  "commentCreationDates": [
    "2002-11-12T22:08:48+01:00",
    "2002-11-13T13:42:55+01:00",
    "2002-11-13T13:46:49+01:00",
    "2002-11-13T13:47:06+01:00"
  ],
  "traces": [
    {
      "exceptionType": "java.lang.IllegalArgumentException",
      "message": "Path must include project and resource name.",
      "elements": [
        {
          "method": "org.eclipse.core.internal.utils.Assert.isLegal",
          "source": "Assert.java:55"
        },
        {
          "method": "org.eclipse.core.internal.resources.Workspace.newResource",
          "source": "Workspace.java:1413"
        },
        {
          "method": "org.eclipse.core.internal.resources.Container.getFolder",
          "source": "Container.java:131"
        },
        {
          "method": "org.eclipse.jdt.internal.core.builder.NameEnvironment.computeClasspathLocations",
          "source": "Nam eEnviro nment.java:102"
        },
        {
          "method": "org.eclipse.jdt.internal.core.builder.NameEnvironment.\u003cinit\u003e",
          "source": "NameEnvironment.java:36"
        },
        {
          "method": "org.eclipse.jdt.internal.core.builder.JavaBuilder.initializeBuilder",
          "source": "JavaBuilder.java:417"
        },
        {
          "method": "org.eclipse.jdt.internal.core.builder.JavaBuilder.build",
          "source": "JavaBuilder.java:97"
        },
        {
          "method": "org.eclipse.core.internal.events.BuildManager$2.run",
          "source": "BuildManager.java:393"
        },
        {
          "method": "org.eclipse.core.internal.runtime.InternalPlatform.run",
          "source": "InternalPlatform.java:839"
        },
        {
          "method": "org.eclipse.core.runtime.Platform.run",
          "source": "Platform.java:413"
        },
        {
          "method": "org.eclipse.core.internal.events.BuildManager.basicBuild",
          "source": "BuildManager.java:120"
        },
        {
          "method": "org.eclipse.core.internal.events.BuildManager.basicBuild",
          "source": "BuildManager.java:176"
        },
        {
          "method": "org.eclipse.core.internal.events.BuildManager.basicBuild",
          "source": "BuildManager.java:186"
        },
        {
          "method": "org.eclipse.core.internal.events.BuildManager$1.run",
          "source": "BuildManager.java:146"
        },
        {
          "method": "org.eclipse.core.internal.runtime.InternalPlatform.run",
          "source": "InternalPlatform.java:839"
        },
        {
          "method": "org.eclipse.core.runtime.Platform.run",
          "source": "Platform.java:413"
        },
        {
          "method": "org.eclipse.core.internal.events.BuildManager.basicBuild",
          "source": "BuildManager.java:160"
        },
        {
          "method": "org.eclipse.core.internal.events.BuildManager.build",
          "source": "BuildManager.java:211"
        },
        {
          "method": "org.eclipse.core.internal.resources.Workspace.endOperation",
          "source": "Workspace.java:863"
        },
        {
          "method": "org.eclipse.core.internal.resources.Workspace.run",
          "source": "Workspace.java:1571"
        },
        {
          "method": "org.eclipse.ui.actions.WorkspaceModifyOperation.run",
          "source": "WorkspaceModifyOperation.java:7 9"
        },
        {
          "method": "org.eclipse.ui.texteditor.AbstractTextEditor.performSaveOperation",
          "source": "AbstractTextEditor.jav a: 2596"
        },
        {
          "method": "org.eclipse.jdt.internal.ui.javaeditor.CompilationUnitEditor.performSaveOperation",
          "source": "Compi lat ionUnitEditor.java:797"
        },
        {
          "method": "org.eclipse.jdt.internal.ui.javaeditor.CompilationUnitEditor.doSave",
          "source": "CompilationUnitEdito r. java:847"
        },
        {
          "method": "org.eclipse.ui.internal.EditorManager$11.run",
          "source": "EditorManager.java:1015"
        },
        {
          "method": "org.eclipse.ui.internal.EditorManager$8.run",
          "source": "EditorManager.java:884"
        },
        {
          "method": "org.eclipse.jface.operation.ModalContext.runInCurrentThread",
          "source": "ModalContext.java:296"
        },
        {
          "method": "org.eclipse.jface.operation.ModalContext.run",
          "source": "ModalContext.java:246"
        },
        {
          "method": "org.eclipse.jface.window.ApplicationWindow$1.run",
          "source": "ApplicationWindow.java:391"
        },
        {
          "method": "org.eclipse.swt.custom.BusyIndicator.showWhile",
          "source": "BusyIndicator.java:65"
        },
        {
          "method": "org.eclipse.jface.window.ApplicationWindow.run",
          "source": "ApplicationWindow.java:388"
        },
        {
          "method": "org.eclipse.ui.internal.WorkbenchWindow.run",
          "source": "WorkbenchWindow.java:1147"
        },
        {
          "method": "org.eclipse.ui.internal.EditorManager.runProgressMonitorOperation",
          "source": "EditorManager.java: 890"
        },
        {
          "method": "org.eclipse.ui.internal.EditorManager.saveEditor",
          "source": "EditorManager.java:1020"
        },
        {
          "method": "org.eclipse.ui.internal.WorkbenchPage.saveEditor",
          "source": "WorkbenchPage.java:2051"
        },
        {
          "method": "org.eclipse.ui.internal.SaveAction.run",
          "source": "SaveAction.java:30"
        },
        {
          "method": "org.eclipse.jface.action.Action.runWithEvent",
          "source": "Action.java:769"
        },
        {
          "method": "org.eclipse.ui.internal.WWinKeyBindingService.invoke",
          "source": "WWinKeyBindingService.java:13 9"
        },
        {
          "method": "org.eclipse.ui.internal.WWinKeyBindingService.pressed",
          "source": "WWinKeyBindingService.java:1 20"
        },
        {
          "method": "org.eclipse.ui.internal.WWinKeyBindingService$5.widgetSelected",
          "source": "WWinKeyBindingServ ice.java: 367"
        },
        {
          "method": "org.eclipse.ui.internal.AcceleratorMenu$2.handleEvent",
          "source": "AcceleratorMenu.java:53"
        },
        {
          "method": "org.eclipse.swt.widgets.EventTable.sendEvent",
          "source": "EventTable.java:77"
        },
        {
          "method": "org.eclipse.swt.widgets.Widget.notifyListeners",
          "source": "Widget.java:485"
        },
        {
          "method": "org.eclipse.swt.widgets.Display.runDeferredEvents",
          "source": "Display.java:1272"
        },
        {
          "method": "org.eclipse.swt.widgets.Display.readAndDispatch",
          "source": "Display.java:1120"
        },
        {
          "method": "org.eclipse.ui.internal.Workbench.runEventLoop",
          "source": "Workbench.java:1435"
        },
        {
          "method": "org.eclipse.ui.internal.Workbench.run",
          "source": "Workbench.java:1418"
        },
        {
          "method": "org.eclipse.core.internal.boot.InternalBootLoader.run",
          "source": "InternalBootLoader.java:831"
        },
        {
          "method": "org.eclipse.core.boot.BootLoader.run",
          "source": "BootLoader.java:462"
        },
        {
          "method": "java.lang.reflect.Method.invoke",
          "source": "Native Method"
        },
        {
          "method": "org.eclipse.core.launcher.Main.basicRun",
          "source": "Main.java:247"
        },
        {
          "method": "org.eclipse.core.launcher.Main.run",
          "source": "Main.java:703"
        },
        {
          "method": "org.eclipse.core.launcher.Main.main",
          "source": "Main.java:539"
        },
        {
          "method": "java.lang.reflect.Method.invoke",
          "source": "Native Method"
        },
        {
          "method": "com.apple.buckyball.app.LaunchRunner.run",
          "source": "LaunchRunner.java:82"
        },
        {
          "method": "com.apple.buckyball.app.LaunchRunner.callMain",
          "source": "LaunchRunner.java:44"
        },
        {
          "method": "com.apple.buckyball.app.CarbonLibApp.launch",
          "source": "CarbonLibApp.java:67"
        }
      ],
      "number": 0,
      "commentIndex": 0,
      "bugId": "26063",
      "duplicateId": "26053",
      "date": "2002-11-12T22:08:48+01:00",
      "product": "JDT",
      "component": "Core",
      "severity": "normal"
    }
  ],
  "groupId": "26053",
  "bugId": "26063",
  "duplicateId": "26053",
  "date": "2002-11-12T22:08:48+01:00",
  "product": "JDT",
  "component": "Core",
  "severity": "normal"
}