{
  "comments": [
    "Build 20021115\n\n0. Autobuild on\n1. Create Java project Test1 (with prj\u003dsrc\u003dbin)\n2. Create Java project Test2 (with prj\u003dsrc\u003dbin) and add Test1 as a prerequesite\n3. Add class X in Test1\n4. Add class Y (a subclass of X) in Test2\n5. Exit and restart workspace\n6. Add a method foo() to Y \n\nObserve: You get the following exception:\n\njava.lang.IllegalArgumentException: Path must include project and resource name.\n        at org.eclipse.core.internal.utils.Assert.isLegal(Assert.java:55)\n        at org.eclipse.core.internal.resources.Workspace.newResource\n(Workspace.java:1427)\n        at org.eclipse.core.internal.resources.Container.getFolder\n(Container.java:131)\n        at org.eclipse.jdt.internal.core.builder.State.read(State.java:212)\n        at org.eclipse.jdt.internal.core.builder.JavaBuilder.readState\n(JavaBuilder.java:75)\n        at org.eclipse.jdt.internal.core.JavaModelManager.readState\n(JavaModelManager.java:1172)\n        at org.eclipse.jdt.internal.core.JavaModelManager.getLastBuiltState\n(JavaModelManager.java:892)\n        at org.eclipse.jdt.internal.core.builder.JavaBuilder.getLastState\n(JavaBuilder.java:287)\n        at org.eclipse.jdt.internal.core.builder.JavaBuilder.build\n(JavaBuilder.java:103)\n        at org.eclipse.core.internal.events.BuildManager$2.run\n(BuildManager.java:393)\n        at org.eclipse.core.internal.runtime.InternalPlatform.run\n(InternalPlatform.java:839)\n        at org.eclipse.core.runtime.Platform.run(Platform.java:413)\n        at org.eclipse.core.internal.events.BuildManager.basicBuild\n(BuildManager.java:120)\n        at org.eclipse.core.internal.events.BuildManager.basicBuild\n(BuildManager.java:176)\n        at org.eclipse.core.internal.events.BuildManager.basicBuild\n(BuildManager.java:186)\n        at org.eclipse.core.internal.events.BuildManager$1.run\n(BuildManager.java:146)\n        at org.eclipse.core.internal.runtime.InternalPlatform.run\n(InternalPlatform.java:839)\n        at org.eclipse.core.runtime.Platform.run(Platform.java:413)\n        at org.eclipse.core.internal.events.BuildManager.basicBuild\n(BuildManager.java:160)\n        at org.eclipse.core.internal.events.BuildManager.build\n(BuildManager.java:211)\n        at org.eclipse.core.internal.resources.Workspace.endOperation\n(Workspace.java:876)\n        at org.eclipse.core.internal.resources.Workspace.run\n(Workspace.java:1585)\n        at org.eclipse.ui.actions.WorkspaceModifyOperation.run\n(WorkspaceModifyOperation.java:79)\n        at org.eclipse.ui.texteditor.AbstractTextEditor.performSaveOperation\n(AbstractTextEditor.java:2596)\n        at \norg.eclipse.jdt.internal.ui.javaeditor.CompilationUnitEditor.performSaveOperatio\nn(CompilationUnitEditor.java:799)\n        at org.eclipse.jdt.internal.ui.javaeditor.CompilationUnitEditor.doSave\n(CompilationUnitEditor.java:849)\n        at org.eclipse.ui.internal.EditorManager$11.run(EditorManager.java:1015)\n        at org.eclipse.ui.internal.EditorManager$8.run(EditorManager.java:884)\n        at org.eclipse.jface.operation.ModalContext.runInCurrentThread\n(ModalContext.java:296)\n        at org.eclipse.jface.operation.ModalContext.run(ModalContext.java:246)\n        at org.eclipse.jface.window.ApplicationWindow$1.run\n(ApplicationWindow.java:391)\n        at org.eclipse.swt.custom.BusyIndicator.showWhile(BusyIndicator.java:65)\n        at org.eclipse.jface.window.ApplicationWindow.run\n(ApplicationWindow.java:388)\n        at org.eclipse.ui.internal.WorkbenchWindow.run\n(WorkbenchWindow.java:1146)\n        at org.eclipse.ui.internal.EditorManager.runProgressMonitorOperation\n(EditorManager.java:890)\n        at org.eclipse.ui.internal.EditorManager.saveEditor\n(EditorManager.java:1020)\n        at org.eclipse.ui.internal.WorkbenchPage.saveEditor\n(WorkbenchPage.java:2050)\n        at org.eclipse.ui.internal.SaveAction.run(SaveAction.java:30)\n        at org.eclipse.jface.action.Action.runWithEvent(Action.java:769)\n        at org.eclipse.ui.internal.WWinKeyBindingService.invoke\n(WWinKeyBindingService.java:138)\n        at org.eclipse.ui.internal.WWinKeyBindingService.pressed\n(WWinKeyBindingService.java:119)\n        at org.eclipse.ui.internal.WWinKeyBindingService$5.widgetSelected\n(WWinKeyBindingService.java:366)\n        at org.eclipse.ui.internal.AcceleratorMenu$2.handleEvent\n(AcceleratorMenu.java:55)\n        at org.eclipse.swt.widgets.EventTable.sendEvent(EventTable.java:77)\n        at org.eclipse.swt.widgets.Widget.sendEvent(Widget.java:825)\n        at org.eclipse.swt.widgets.Display.runDeferredEvents(Display.java:1692)\n        at org.eclipse.swt.widgets.Display.readAndDispatch(Display.java:1410)\n        at org.eclipse.ui.internal.Workbench.runEventLoop(Workbench.java:1435)\n        at org.eclipse.ui.internal.Workbench.run(Workbench.java:1418)\n        at org.eclipse.core.internal.boot.InternalBootLoader.run\n(InternalBootLoader.java:831)\n        at org.eclipse.core.boot.BootLoader.run(BootLoader.java:462)\n        at sun.reflect.NativeMethodAccessorImpl.invoke0(Native Method)\n        at sun.reflect.NativeMethodAccessorImpl.invoke\n(NativeMethodAccessorImpl.java:39)\n        at sun.reflect.DelegatingMethodAccessorImpl.invoke\n(DelegatingMethodAccessorImpl.java:25)\n        at java.lang.reflect.Method.invoke(Method.java:324)\n        at org.eclipse.core.launcher.Main.basicRun(Main.java:247)\n        at org.eclipse.core.launcher.Main.run(Main.java:703)\n        at org.eclipse.core.launcher.Main.main(Main.java:539)\norg.eclipse.core.runtime.CoreException[2]: java.lang.IllegalArgumentException: \nPath must include project and resource name.\n        at org.eclipse.core.internal.utils.Assert.isLegal(Assert.java:55)\n        at org.eclipse.core.internal.resources.Workspace.newResource\n(Workspace.java:1427)\n        at org.eclipse.core.internal.resources.Container.getFolder\n(Container.java:131)\n        at org.eclipse.jdt.internal.core.builder.State.read(State.java:212)\n        at org.eclipse.jdt.internal.core.builder.JavaBuilder.readState\n(JavaBuilder.java:75)\n        at org.eclipse.jdt.internal.core.JavaModelManager.readState\n(JavaModelManager.java:1172)\n        at org.eclipse.jdt.internal.core.JavaModelManager.getLastBuiltState\n(JavaModelManager.java:892)\n        at org.eclipse.jdt.internal.core.builder.JavaBuilder.getLastState\n(JavaBuilder.java:287)\n        at org.eclipse.jdt.internal.core.builder.JavaBuilder.build\n(JavaBuilder.java:103)\n        at org.eclipse.core.internal.events.BuildManager$2.run\n(BuildManager.java:393)\n        at org.eclipse.core.internal.runtime.InternalPlatform.run\n(InternalPlatform.java:839)\n        at org.eclipse.core.runtime.Platform.run(Platform.java:413)\n        at org.eclipse.core.internal.events.BuildManager.basicBuild\n(BuildManager.java:120)\n        at org.eclipse.core.internal.events.BuildManager.basicBuild\n(BuildManager.java:176)\n        at org.eclipse.core.internal.events.BuildManager.basicBuild\n(BuildManager.java:186)\n        at org.eclipse.core.internal.events.BuildManager$1.run\n(BuildManager.java:146)\n        at org.eclipse.core.internal.runtime.InternalPlatform.run\n(InternalPlatform.java:839)\n        at org.eclipse.core.runtime.Platform.run(Platform.java:413)\n        at org.eclipse.core.internal.events.BuildManager.basicBuild\n(BuildManager.java:160)\n        at org.eclipse.core.internal.events.BuildManager.build\n(BuildManager.java:211)\n        at org.eclipse.core.internal.resources.Workspace.endOperation\n(Workspace.java:876)\n        at org.eclipse.core.internal.resources.Workspace.run\n(Workspace.java:1585)\n        at org.eclipse.ui.actions.WorkspaceModifyOperation.run\n(WorkspaceModifyOperation.java:79)\n        at org.eclipse.ui.texteditor.AbstractTextEditor.performSaveOperation\n(AbstractTextEditor.java:2596)\n        at \norg.eclipse.jdt.internal.ui.javaeditor.CompilationUnitEditor.performSaveOperatio\nn(CompilationUnitEditor.java:799)\n        at org.eclipse.jdt.internal.ui.javaeditor.CompilationUnitEditor.doSave\n(CompilationUnitEditor.java:849)\n        at org.eclipse.ui.internal.EditorManager$11.run(EditorManager.java:1015)\n        at org.eclipse.ui.internal.EditorManager$8.run(EditorManager.java:884)\n        at org.eclipse.jface.operation.ModalContext.runInCurrentThread\n(ModalContext.java:296)\n        at org.eclipse.jface.operation.ModalContext.run(ModalContext.java:246)\n        at org.eclipse.jface.window.ApplicationWindow$1.run\n(ApplicationWindow.java:391)\n        at org.eclipse.swt.custom.BusyIndicator.showWhile(BusyIndicator.java:65)\n        at org.eclipse.jface.window.ApplicationWindow.run\n(ApplicationWindow.java:388)\n        at org.eclipse.ui.internal.WorkbenchWindow.run\n(WorkbenchWindow.java:1146)\n        at org.eclipse.ui.internal.EditorManager.runProgressMonitorOperation\n(EditorManager.java:890)\n        at org.eclipse.ui.internal.EditorManager.saveEditor\n(EditorManager.java:1020)\n        at org.eclipse.ui.internal.WorkbenchPage.saveEditor\n(WorkbenchPage.java:2050)\n        at org.eclipse.ui.internal.SaveAction.run(SaveAction.java:30)\n        at org.eclipse.jface.action.Action.runWithEvent(Action.java:769)\n        at org.eclipse.ui.internal.WWinKeyBindingService.invoke\n(WWinKeyBindingService.java:138)\n        at org.eclipse.ui.internal.WWinKeyBindingService.pressed\n(WWinKeyBindingService.java:119)\n        at org.eclipse.ui.internal.WWinKeyBindingService$5.widgetSelected\n(WWinKeyBindingService.java:366)\n        at org.eclipse.ui.internal.AcceleratorMenu$2.handleEvent\n(AcceleratorMenu.java:55)\n        at org.eclipse.swt.widgets.EventTable.sendEvent(EventTable.java:77)\n        at org.eclipse.swt.widgets.Widget.sendEvent(Widget.java:825)\n        at org.eclipse.swt.widgets.Display.runDeferredEvents(Display.java:1692)\n        at org.eclipse.swt.widgets.Display.readAndDispatch(Display.java:1410)\n        at org.eclipse.ui.internal.Workbench.runEventLoop(Workbench.java:1435)\n        at org.eclipse.ui.internal.Workbench.run(Workbench.java:1418)\n        at org.eclipse.core.internal.boot.InternalBootLoader.run\n(InternalBootLoader.java:831)\n        at org.eclipse.core.boot.BootLoader.run(BootLoader.java:462)\n        at sun.reflect.NativeMethodAccessorImpl.invoke0(Native Method)\n        at sun.reflect.NativeMethodAccessorImpl.invoke\n(NativeMethodAccessorImpl.java:39)\n        at sun.reflect.DelegatingMethodAccessorImpl.invoke\n(DelegatingMethodAccessorImpl.java:25)\n        at java.lang.reflect.Method.invoke(Method.java:324)\n        at org.eclipse.core.launcher.Main.basicRun(Main.java:247)\n        at org.eclipse.core.launcher.Main.run(Main.java:703)\n        at org.eclipse.core.launcher.Main.main(Main.java:539)",
    "Fixed.\n\nOccurs whenever a project is dependent on a simple project (project \u003d\u003d src \u003d\u003d \nbin) .",
    "Verified."
  ],
  "commentCreationDates": [
    "2002-11-20T10:42:33+01:00",
    "2002-11-20T19:41:10+01:00",
    "2002-12-17T11:41:46+01:00"
  ],
  "traces": [
    {
      "exceptionType": "java.lang.IllegalArgumentException",
      "message": "Path must include project and resource name.",
      "elements": [
        {
          "method": "org.eclipse.core.internal.utils.Assert.isLegal",
          "source": "Assert.java:55"
        },
        {
          "method": "org.eclipse.core.internal.resources.Workspace.newResource",
          "source": "Workspace.java:1427"
        },
        {
          "method": "org.eclipse.core.internal.resources.Container.getFolder",
          "source": "Container.java:131"
        },
        {
          "method": "org.eclipse.jdt.internal.core.builder.State.read",
          "source": "State.java:212"
        },
        {
          "method": "org.eclipse.jdt.internal.core.builder.JavaBuilder.readState",
          "source": "JavaBuilder.java:75"
        },
        {
          "method": "org.eclipse.jdt.internal.core.JavaModelManager.readState",
          "source": "JavaModelManager.java:1172"
        },
        {
          "method": "org.eclipse.jdt.internal.core.JavaModelManager.getLastBuiltState",
          "source": "JavaModelManager.java:892"
        },
        {
          "method": "org.eclipse.jdt.internal.core.builder.JavaBuilder.getLastState",
          "source": "JavaBuilder.java:287"
        },
        {
          "method": "org.eclipse.jdt.internal.core.builder.JavaBuilder.build",
          "source": "JavaBuilder.java:103"
        },
        {
          "method": "org.eclipse.core.internal.events.BuildManager$2.run",
          "source": "BuildManager.java:393"
        },
        {
          "method": "org.eclipse.core.internal.runtime.InternalPlatform.run",
          "source": "InternalPlatform.java:839"
        },
        {
          "method": "org.eclipse.core.runtime.Platform.run",
          "source": "Platform.java:413"
        },
        {
          "method": "org.eclipse.core.internal.events.BuildManager.basicBuild",
          "source": "BuildManager.java:120"
        },
        {
          "method": "org.eclipse.core.internal.events.BuildManager.basicBuild",
          "source": "BuildManager.java:176"
        },
        {
          "method": "org.eclipse.core.internal.events.BuildManager.basicBuild",
          "source": "BuildManager.java:186"
        },
        {
          "method": "org.eclipse.core.internal.events.BuildManager$1.run",
          "source": "BuildManager.java:146"
        },
        {
          "method": "org.eclipse.core.internal.runtime.InternalPlatform.run",
          "source": "InternalPlatform.java:839"
        },
        {
          "method": "org.eclipse.core.runtime.Platform.run",
          "source": "Platform.java:413"
        },
        {
          "method": "org.eclipse.core.internal.events.BuildManager.basicBuild",
          "source": "BuildManager.java:160"
        },
        {
          "method": "org.eclipse.core.internal.events.BuildManager.build",
          "source": "BuildManager.java:211"
        },
        {
          "method": "org.eclipse.core.internal.resources.Workspace.endOperation",
          "source": "Workspace.java:876"
        },
        {
          "method": "org.eclipse.core.internal.resources.Workspace.run",
          "source": "Workspace.java:1585"
        },
        {
          "method": "org.eclipse.ui.actions.WorkspaceModifyOperation.run",
          "source": "WorkspaceModifyOperation.java:79"
        },
        {
          "method": "org.eclipse.ui.texteditor.AbstractTextEditor.performSaveOperation",
          "source": "AbstractTextEditor.java:2596"
        },
        {
          "method": "org.eclipse.jdt.internal.ui.javaeditor.CompilationUnitEditor.performSaveOperation",
          "source": "CompilationUnitEditor.java:799"
        },
        {
          "method": "org.eclipse.jdt.internal.ui.javaeditor.CompilationUnitEditor.doSave",
          "source": "CompilationUnitEditor.java:849"
        },
        {
          "method": "org.eclipse.ui.internal.EditorManager$11.run",
          "source": "EditorManager.java:1015"
        },
        {
          "method": "org.eclipse.ui.internal.EditorManager$8.run",
          "source": "EditorManager.java:884"
        },
        {
          "method": "org.eclipse.jface.operation.ModalContext.runInCurrentThread",
          "source": "ModalContext.java:296"
        },
        {
          "method": "org.eclipse.jface.operation.ModalContext.run",
          "source": "ModalContext.java:246"
        },
        {
          "method": "org.eclipse.jface.window.ApplicationWindow$1.run",
          "source": "ApplicationWindow.java:391"
        },
        {
          "method": "org.eclipse.swt.custom.BusyIndicator.showWhile",
          "source": "BusyIndicator.java:65"
        },
        {
          "method": "org.eclipse.jface.window.ApplicationWindow.run",
          "source": "ApplicationWindow.java:388"
        },
        {
          "method": "org.eclipse.ui.internal.WorkbenchWindow.run",
          "source": "WorkbenchWindow.java:1146"
        },
        {
          "method": "org.eclipse.ui.internal.EditorManager.runProgressMonitorOperation",
          "source": "EditorManager.java:890"
        },
        {
          "method": "org.eclipse.ui.internal.EditorManager.saveEditor",
          "source": "EditorManager.java:1020"
        },
        {
          "method": "org.eclipse.ui.internal.WorkbenchPage.saveEditor",
          "source": "WorkbenchPage.java:2050"
        },
        {
          "method": "org.eclipse.ui.internal.SaveAction.run",
          "source": "SaveAction.java:30"
        },
        {
          "method": "org.eclipse.jface.action.Action.runWithEvent",
          "source": "Action.java:769"
        },
        {
          "method": "org.eclipse.ui.internal.WWinKeyBindingService.invoke",
          "source": "WWinKeyBindingService.java:138"
        },
        {
          "method": "org.eclipse.ui.internal.WWinKeyBindingService.pressed",
          "source": "WWinKeyBindingService.java:119"
        },
        {
          "method": "org.eclipse.ui.internal.WWinKeyBindingService$5.widgetSelected",
          "source": "WWinKeyBindingService.java:366"
        },
        {
          "method": "org.eclipse.ui.internal.AcceleratorMenu$2.handleEvent",
          "source": "AcceleratorMenu.java:55"
        },
        {
          "method": "org.eclipse.swt.widgets.EventTable.sendEvent",
          "source": "EventTable.java:77"
        },
        {
          "method": "org.eclipse.swt.widgets.Widget.sendEvent",
          "source": "Widget.java:825"
        },
        {
          "method": "org.eclipse.swt.widgets.Display.runDeferredEvents",
          "source": "Display.java:1692"
        },
        {
          "method": "org.eclipse.swt.widgets.Display.readAndDispatch",
          "source": "Display.java:1410"
        },
        {
          "method": "org.eclipse.ui.internal.Workbench.runEventLoop",
          "source": "Workbench.java:1435"
        },
        {
          "method": "org.eclipse.ui.internal.Workbench.run",
          "source": "Workbench.java:1418"
        },
        {
          "method": "org.eclipse.core.internal.boot.InternalBootLoader.run",
          "source": "InternalBootLoader.java:831"
        },
        {
          "method": "org.eclipse.core.boot.BootLoader.run",
          "source": "BootLoader.java:462"
        },
        {
          "method": "sun.reflect.NativeMethodAccessorImpl.invoke0",
          "source": "Native Method"
        },
        {
          "method": "sun.reflect.NativeMethodAccessorImpl.invoke",
          "source": "NativeMethodAccessorImpl.java:39"
        },
        {
          "method": "sun.reflect.DelegatingMethodAccessorImpl.invoke",
          "source": "DelegatingMethodAccessorImpl.java:25"
        },
        {
          "method": "java.lang.reflect.Method.invoke",
          "source": "Method.java:324"
        },
        {
          "method": "org.eclipse.core.launcher.Main.basicRun",
          "source": "Main.java:247"
        },
        {
          "method": "org.eclipse.core.launcher.Main.run",
          "source": "Main.java:703"
        },
        {
          "method": "org.eclipse.core.launcher.Main.main",
          "source": "Main.java:539"
        }
      ],
      "number": 0,
      "commentIndex": 0,
      "bugId": "26747",
      "date": "2002-11-20T10:42:33+01:00",
      "product": "JDT",
      "component": "Core",
      "severity": "critical"
    },
    {
      "exceptionType": "java.lang.IllegalArgumentException",
      "message": "Path must include project and resource name.",
      "elements": [
        {
          "method": "org.eclipse.core.internal.utils.Assert.isLegal",
          "source": "Assert.java:55"
        },
        {
          "method": "org.eclipse.core.internal.resources.Workspace.newResource",
          "source": "Workspace.java:1427"
        },
        {
          "method": "org.eclipse.core.internal.resources.Container.getFolder",
          "source": "Container.java:131"
        },
        {
          "method": "org.eclipse.jdt.internal.core.builder.State.read",
          "source": "State.java:212"
        },
        {
          "method": "org.eclipse.jdt.internal.core.builder.JavaBuilder.readState",
          "source": "JavaBuilder.java:75"
        },
        {
          "method": "org.eclipse.jdt.internal.core.JavaModelManager.readState",
          "source": "JavaModelManager.java:1172"
        },
        {
          "method": "org.eclipse.jdt.internal.core.JavaModelManager.getLastBuiltState",
          "source": "JavaModelManager.java:892"
        },
        {
          "method": "org.eclipse.jdt.internal.core.builder.JavaBuilder.getLastState",
          "source": "JavaBuilder.java:287"
        },
        {
          "method": "org.eclipse.jdt.internal.core.builder.JavaBuilder.build",
          "source": "JavaBuilder.java:103"
        },
        {
          "method": "org.eclipse.core.internal.events.BuildManager$2.run",
          "source": "BuildManager.java:393"
        },
        {
          "method": "org.eclipse.core.internal.runtime.InternalPlatform.run",
          "source": "InternalPlatform.java:839"
        },
        {
          "method": "org.eclipse.core.runtime.Platform.run",
          "source": "Platform.java:413"
        },
        {
          "method": "org.eclipse.core.internal.events.BuildManager.basicBuild",
          "source": "BuildManager.java:120"
        },
        {
          "method": "org.eclipse.core.internal.events.BuildManager.basicBuild",
          "source": "BuildManager.java:176"
        },
        {
          "method": "org.eclipse.core.internal.events.BuildManager.basicBuild",
          "source": "BuildManager.java:186"
        },
        {
          "method": "org.eclipse.core.internal.events.BuildManager$1.run",
          "source": "BuildManager.java:146"
        },
        {
          "method": "org.eclipse.core.internal.runtime.InternalPlatform.run",
          "source": "InternalPlatform.java:839"
        },
        {
          "method": "org.eclipse.core.runtime.Platform.run",
          "source": "Platform.java:413"
        },
        {
          "method": "org.eclipse.core.internal.events.BuildManager.basicBuild",
          "source": "BuildManager.java:160"
        },
        {
          "method": "org.eclipse.core.internal.events.BuildManager.build",
          "source": "BuildManager.java:211"
        },
        {
          "method": "org.eclipse.core.internal.resources.Workspace.endOperation",
          "source": "Workspace.java:876"
        },
        {
          "method": "org.eclipse.core.internal.resources.Workspace.run",
          "source": "Workspace.java:1585"
        },
        {
          "method": "org.eclipse.ui.actions.WorkspaceModifyOperation.run",
          "source": "WorkspaceModifyOperation.java:79"
        },
        {
          "method": "org.eclipse.ui.texteditor.AbstractTextEditor.performSaveOperation",
          "source": "AbstractTextEditor.java:2596"
        },
        {
          "method": "org.eclipse.jdt.internal.ui.javaeditor.CompilationUnitEditor.performSaveOperation",
          "source": "CompilationUnitEditor.java:799"
        },
        {
          "method": "org.eclipse.jdt.internal.ui.javaeditor.CompilationUnitEditor.doSave",
          "source": "CompilationUnitEditor.java:849"
        },
        {
          "method": "org.eclipse.ui.internal.EditorManager$11.run",
          "source": "EditorManager.java:1015"
        },
        {
          "method": "org.eclipse.ui.internal.EditorManager$8.run",
          "source": "EditorManager.java:884"
        },
        {
          "method": "org.eclipse.jface.operation.ModalContext.runInCurrentThread",
          "source": "ModalContext.java:296"
        },
        {
          "method": "org.eclipse.jface.operation.ModalContext.run",
          "source": "ModalContext.java:246"
        },
        {
          "method": "org.eclipse.jface.window.ApplicationWindow$1.run",
          "source": "ApplicationWindow.java:391"
        },
        {
          "method": "org.eclipse.swt.custom.BusyIndicator.showWhile",
          "source": "BusyIndicator.java:65"
        },
        {
          "method": "org.eclipse.jface.window.ApplicationWindow.run",
          "source": "ApplicationWindow.java:388"
        },
        {
          "method": "org.eclipse.ui.internal.WorkbenchWindow.run",
          "source": "WorkbenchWindow.java:1146"
        },
        {
          "method": "org.eclipse.ui.internal.EditorManager.runProgressMonitorOperation",
          "source": "EditorManager.java:890"
        },
        {
          "method": "org.eclipse.ui.internal.EditorManager.saveEditor",
          "source": "EditorManager.java:1020"
        },
        {
          "method": "org.eclipse.ui.internal.WorkbenchPage.saveEditor",
          "source": "WorkbenchPage.java:2050"
        },
        {
          "method": "org.eclipse.ui.internal.SaveAction.run",
          "source": "SaveAction.java:30"
        },
        {
          "method": "org.eclipse.jface.action.Action.runWithEvent",
          "source": "Action.java:769"
        },
        {
          "method": "org.eclipse.ui.internal.WWinKeyBindingService.invoke",
          "source": "WWinKeyBindingService.java:138"
        },
        {
          "method": "org.eclipse.ui.internal.WWinKeyBindingService.pressed",
          "source": "WWinKeyBindingService.java:119"
        },
        {
          "method": "org.eclipse.ui.internal.WWinKeyBindingService$5.widgetSelected",
          "source": "WWinKeyBindingService.java:366"
        },
        {
          "method": "org.eclipse.ui.internal.AcceleratorMenu$2.handleEvent",
          "source": "AcceleratorMenu.java:55"
        },
        {
          "method": "org.eclipse.swt.widgets.EventTable.sendEvent",
          "source": "EventTable.java:77"
        },
        {
          "method": "org.eclipse.swt.widgets.Widget.sendEvent",
          "source": "Widget.java:825"
        },
        {
          "method": "org.eclipse.swt.widgets.Display.runDeferredEvents",
          "source": "Display.java:1692"
        },
        {
          "method": "org.eclipse.swt.widgets.Display.readAndDispatch",
          "source": "Display.java:1410"
        },
        {
          "method": "org.eclipse.ui.internal.Workbench.runEventLoop",
          "source": "Workbench.java:1435"
        },
        {
          "method": "org.eclipse.ui.internal.Workbench.run",
          "source": "Workbench.java:1418"
        },
        {
          "method": "org.eclipse.core.internal.boot.InternalBootLoader.run",
          "source": "InternalBootLoader.java:831"
        },
        {
          "method": "org.eclipse.core.boot.BootLoader.run",
          "source": "BootLoader.java:462"
        },
        {
          "method": "sun.reflect.NativeMethodAccessorImpl.invoke0",
          "source": "Native Method"
        },
        {
          "method": "sun.reflect.NativeMethodAccessorImpl.invoke",
          "source": "NativeMethodAccessorImpl.java:39"
        },
        {
          "method": "sun.reflect.DelegatingMethodAccessorImpl.invoke",
          "source": "DelegatingMethodAccessorImpl.java:25"
        },
        {
          "method": "java.lang.reflect.Method.invoke",
          "source": "Method.java:324"
        },
        {
          "method": "org.eclipse.core.launcher.Main.basicRun",
          "source": "Main.java:247"
        },
        {
          "method": "org.eclipse.core.launcher.Main.run",
          "source": "Main.java:703"
        },
        {
          "method": "org.eclipse.core.launcher.Main.main",
          "source": "Main.java:539"
        }
      ],
      "number": 1,
      "commentIndex": 0,
      "bugId": "26747",
      "date": "2002-11-20T10:42:33+01:00",
      "product": "JDT",
      "component": "Core",
      "severity": "critical"
    }
  ],
  "groupId": "26747",
  "bugId": "26747",
  "date": "2002-11-20T10:42:33+01:00",
  "product": "JDT",
  "component": "Core",
  "severity": "critical"
}