{
  "comments": [
    "Build 2.1 M3\n\nMaybe a consequence of bug 26748.\n\nAfter bug 26748 occurred, I have closed/reopened my Java perspective, and open \none file in editor. As soon as I typed in the editor, I saw an error dialog \nopen, and noticed the following dump into the .log (likely what tagging the \neditor as dirty).\n\n!ENTRY org.eclipse.ui.workbench 4 2 Nov 20, 2002 12:09:18.555\n!MESSAGE Problems occurred when invoking code from plug-\nin: \"org.eclipse.ui.workbench\".\n!STACK 0\norg.eclipse.swt.SWTException: Widget is disposed\n        at org.eclipse.swt.SWT.error(SWT.java:2180)\n        at org.eclipse.swt.SWT.error(SWT.java:2110)\n        at org.eclipse.swt.custom.CTabItem.getDisplay(CTabItem.java:142)\n        at org.eclipse.swt.widgets.Widget.isValidThread(Widget.java:578)\n        at org.eclipse.swt.widgets.Widget.checkWidget(Widget.java:300)\n        at org.eclipse.swt.custom.CTabItem.setText(CTabItem.java:502)\n        at org.eclipse.ui.internal.EditorWorkbook.updateEditorTab\n(EditorWorkbook.java:853)\n        at org.eclipse.ui.internal.EditorWorkbook.updateEditorTab\n(EditorWorkbook.java:827)\n        at org.eclipse.ui.internal.EditorWorkbook.propertyChanged\n(EditorWorkbook.java:512)\n        at org.eclipse.ui.part.WorkbenchPart$1.run(WorkbenchPart.java:95)\n        at org.eclipse.core.internal.runtime.InternalPlatform.run\n(InternalPlatform.java:839)\n        at org.eclipse.core.runtime.Platform.run(Platform.java:413)\n        at org.eclipse.ui.part.WorkbenchPart.firePropertyChange\n(WorkbenchPart.java:93)\n        at org.eclipse.ui.texteditor.AbstractTextEditor.firePropertyChange\n(AbstractTextEditor.java:3606)\n        at \norg.eclipse.ui.texteditor.AbstractTextEditor$ElementStateListener.elementDirtySt\nateChanged(AbstractTextEditor.java:257)\n        at \norg.eclipse.ui.texteditor.AbstractDocumentProvider.fireElementDirtyStateChanged\n(AbstractDocumentProvider.java:508)\n        at \norg.eclipse.ui.texteditor.AbstractDocumentProvider$ElementInfo.documentChanged\n(AbstractDocumentProvider.java:118)\n        at org.eclipse.jface.text.AbstractDocument.fireDocumentChanged\n(AbstractDocument.java:547)\n        at org.eclipse.jface.text.AbstractDocument.replace\n(AbstractDocument.java:839)\n        at \norg.eclipse.jdt.internal.ui.javaeditor.CompilationUnitDocumentProvider$Partially\nSynchronizedDocument.replace(CompilationUnitDocumentProvider.java:748)\n        at org.eclipse.jface.text.DocumentAdapter.replaceTextRange\n(DocumentAdapter.java:162)\n        at org.eclipse.swt.custom.StyledText.modifyContent(StyledText.java:5621)\n        at org.eclipse.swt.custom.StyledText.sendKeyEvent(StyledText.java:6545)\n        at org.eclipse.swt.custom.StyledText.doContent(StyledText.java:2652)\n        at org.eclipse.swt.custom.StyledText.handleKey(StyledText.java:5007)\n        at org.eclipse.swt.custom.StyledText.handleKeyDown(StyledText.java:5030)\n        at org.eclipse.swt.custom.StyledText$8.handleEvent(StyledText.java:4800)\n        at org.eclipse.swt.widgets.EventTable.sendEvent(EventTable.java:77)\n        at org.eclipse.swt.widgets.Widget.sendEvent(Widget.java:825)\n        at org.eclipse.swt.widgets.Display.runDeferredEvents(Display.java:1692)\n        at org.eclipse.swt.widgets.Display.readAndDispatch(Display.java:1410)\n        at org.eclipse.ui.internal.Workbench.runEventLoop(Workbench.java:1435)\n        at org.eclipse.ui.internal.Workbench.run(Workbench.java:1418)\n        at org.eclipse.core.internal.boot.InternalBootLoader.run\n(InternalBootLoader.java:831)\n        at org.eclipse.core.boot.BootLoader.run(BootLoader.java:462)\n        at sun.reflect.NativeMethodAccessorImpl.invoke0(Native Method)\n        at sun.reflect.NativeMethodAccessorImpl.invoke\n(NativeMethodAccessorImpl.java:39)\n        at sun.reflect.DelegatingMethodAccessorImpl.invoke\n(DelegatingMethodAccessorImpl.java:25)\n        at java.lang.reflect.Method.invoke(Method.java:324)\n        at org.eclipse.core.launcher.Main.basicRun(Main.java:247)\n        at org.eclipse.core.launcher.Main.run(Main.java:703)\n        at org.eclipse.core.launcher.Main.main(Main.java:539)",
    "Happened after PR26748, during same session. Assumed to be a consequence of \nPR26748.\n\n*** This bug has been marked as a duplicate of 26748 ***"
  ],
  "commentCreationDates": [
    "2002-11-20T11:04:32+01:00",
    "2002-11-20T15:11:12+01:00"
  ],
  "traces": [
    {
      "exceptionType": "org.eclipse.swt.SWTException",
      "message": "Widget is disposed",
      "elements": [
        {
          "method": "org.eclipse.swt.SWT.error",
          "source": "SWT.java:2180"
        },
        {
          "method": "org.eclipse.swt.SWT.error",
          "source": "SWT.java:2110"
        },
        {
          "method": "org.eclipse.swt.custom.CTabItem.getDisplay",
          "source": "CTabItem.java:142"
        },
        {
          "method": "org.eclipse.swt.widgets.Widget.isValidThread",
          "source": "Widget.java:578"
        },
        {
          "method": "org.eclipse.swt.widgets.Widget.checkWidget",
          "source": "Widget.java:300"
        },
        {
          "method": "org.eclipse.swt.custom.CTabItem.setText",
          "source": "CTabItem.java:502"
        },
        {
          "method": "org.eclipse.ui.internal.EditorWorkbook.updateEditorTab",
          "source": "EditorWorkbook.java:853"
        },
        {
          "method": "org.eclipse.ui.internal.EditorWorkbook.updateEditorTab",
          "source": "EditorWorkbook.java:827"
        },
        {
          "method": "org.eclipse.ui.internal.EditorWorkbook.propertyChanged",
          "source": "EditorWorkbook.java:512"
        },
        {
          "method": "org.eclipse.ui.part.WorkbenchPart$1.run",
          "source": "WorkbenchPart.java:95"
        },
        {
          "method": "org.eclipse.core.internal.runtime.InternalPlatform.run",
          "source": "InternalPlatform.java:839"
        },
        {
          "method": "org.eclipse.core.runtime.Platform.run",
          "source": "Platform.java:413"
        },
        {
          "method": "org.eclipse.ui.part.WorkbenchPart.firePropertyChange",
          "source": "WorkbenchPart.java:93"
        },
        {
          "method": "org.eclipse.ui.texteditor.AbstractTextEditor.firePropertyChange",
          "source": "AbstractTextEditor.java:3606"
        },
        {
          "method": "org.eclipse.ui.texteditor.AbstractTextEditor$ElementStateListener.elementDirtyStateChanged",
          "source": "AbstractTextEditor.java:257"
        },
        {
          "method": "org.eclipse.ui.texteditor.AbstractDocumentProvider.fireElementDirtyStateChanged",
          "source": "AbstractDocumentProvider.java:508"
        },
        {
          "method": "org.eclipse.ui.texteditor.AbstractDocumentProvider$ElementInfo.documentChanged",
          "source": "AbstractDocumentProvider.java:118"
        },
        {
          "method": "org.eclipse.jface.text.AbstractDocument.fireDocumentChanged",
          "source": "AbstractDocument.java:547"
        },
        {
          "method": "org.eclipse.jface.text.AbstractDocument.replace",
          "source": "AbstractDocument.java:839"
        },
        {
          "method": "org.eclipse.jdt.internal.ui.javaeditor.CompilationUnitDocumentProvider$PartiallySynchronizedDocument.replace",
          "source": "CompilationUnitDocumentProvider.java:748"
        },
        {
          "method": "org.eclipse.jface.text.DocumentAdapter.replaceTextRange",
          "source": "DocumentAdapter.java:162"
        },
        {
          "method": "org.eclipse.swt.custom.StyledText.modifyContent",
          "source": "StyledText.java:5621"
        },
        {
          "method": "org.eclipse.swt.custom.StyledText.sendKeyEvent",
          "source": "StyledText.java:6545"
        },
        {
          "method": "org.eclipse.swt.custom.StyledText.doContent",
          "source": "StyledText.java:2652"
        },
        {
          "method": "org.eclipse.swt.custom.StyledText.handleKey",
          "source": "StyledText.java:5007"
        },
        {
          "method": "org.eclipse.swt.custom.StyledText.handleKeyDown",
          "source": "StyledText.java:5030"
        },
        {
          "method": "org.eclipse.swt.custom.StyledText$8.handleEvent",
          "source": "StyledText.java:4800"
        },
        {
          "method": "org.eclipse.swt.widgets.EventTable.sendEvent",
          "source": "EventTable.java:77"
        },
        {
          "method": "org.eclipse.swt.widgets.Widget.sendEvent",
          "source": "Widget.java:825"
        },
        {
          "method": "org.eclipse.swt.widgets.Display.runDeferredEvents",
          "source": "Display.java:1692"
        },
        {
          "method": "org.eclipse.swt.widgets.Display.readAndDispatch",
          "source": "Display.java:1410"
        },
        {
          "method": "org.eclipse.ui.internal.Workbench.runEventLoop",
          "source": "Workbench.java:1435"
        },
        {
          "method": "org.eclipse.ui.internal.Workbench.run",
          "source": "Workbench.java:1418"
        },
        {
          "method": "org.eclipse.core.internal.boot.InternalBootLoader.run",
          "source": "InternalBootLoader.java:831"
        },
        {
          "method": "org.eclipse.core.boot.BootLoader.run",
          "source": "BootLoader.java:462"
        },
        {
          "method": "sun.reflect.NativeMethodAccessorImpl.invoke0",
          "source": "Native Method"
        },
        {
          "method": "sun.reflect.NativeMethodAccessorImpl.invoke",
          "source": "NativeMethodAccessorImpl.java:39"
        },
        {
          "method": "sun.reflect.DelegatingMethodAccessorImpl.invoke",
          "source": "DelegatingMethodAccessorImpl.java:25"
        },
        {
          "method": "java.lang.reflect.Method.invoke",
          "source": "Method.java:324"
        },
        {
          "method": "org.eclipse.core.launcher.Main.basicRun",
          "source": "Main.java:247"
        },
        {
          "method": "org.eclipse.core.launcher.Main.run",
          "source": "Main.java:703"
        },
        {
          "method": "org.eclipse.core.launcher.Main.main",
          "source": "Main.java:539"
        }
      ],
      "number": 0,
      "commentIndex": 0,
      "bugId": "26749",
      "duplicateId": "26748",
      "date": "2002-11-20T11:04:32+01:00",
      "product": "Platform",
      "component": "SWT",
      "severity": "normal"
    }
  ],
  "groupId": "25892",
  "bugId": "26749",
  "duplicateId": "26748",
  "date": "2002-11-20T11:04:32+01:00",
  "product": "Platform",
  "component": "SWT",
  "severity": "normal"
}