{
  "comments": [
    "When calling project.build() for a project with external builders the class\norg.eclipse.ui.externaltools.internal.model.VariableContextManager is instantiated.\n\nThe constructor of this class has the lines:\n\nIWorkbench workbench \u003d PlatformUI.getWorkbench();\nworkbench.addWindowListener(this);\n\nwhich cause a NPE in headless mode (since workbench will be null)\n\nHere is a partial stack trace:\n\njava.lang.NullPointerException\n        at\norg.eclipse.ui.externaltools.internal.model.VariableContextManager.\u003cinit\u003e(VariableContextManager.java:45)\n        at\norg.eclipse.ui.externaltools.internal.model.VariableContextManager.getDefault(VariableContextManager.java:59)\n        at\norg.eclipse.ui.externaltools.internal.model.ExternalToolsPlugin.startup(ExternalToolsPlugin.java:231)\n        at\norg.eclipse.core.internal.plugins.PluginDescriptor$1.run(PluginDescriptor.java:697)\n        at\norg.eclipse.core.internal.runtime.InternalPlatform.run(InternalPlatform.java:839)\n        at\norg.eclipse.core.internal.plugins.PluginDescriptor.internalDoPluginActivation(PluginDescriptor.java:709)\n        at\norg.eclipse.core.internal.plugins.PluginDescriptor.doPluginActivation(PluginDescriptor.java:184)\n        at\norg.eclipse.core.internal.plugins.PluginClassLoader.activatePlugin(PluginClassLoader.java:60)\n        at\norg.eclipse.core.internal.plugins.PluginClassLoader.internalFindClassParentsSelf(PluginClassLoader.java:138)\n        at\norg.eclipse.core.internal.boot.DelegatingURLClassLoader.findClassParentsSelf(DelegatingURLClassLoader.java:473)\n        at\norg.eclipse.core.internal.boot.DelegatingURLClassLoader.loadClass(DelegatingURLClassLoader.java:863)\n        at\norg.eclipse.core.internal.boot.DelegatingURLClassLoader.loadClass(DelegatingURLClassLoader.java:843)\n        at java.lang.ClassLoader.loadClass(ClassLoader.java:255)\n        at\norg.eclipse.core.internal.plugins.PluginDescriptor.createExecutableExtension(PluginDescriptor.java:128)\n        at\norg.eclipse.core.internal.plugins.PluginDescriptor.createExecutableExtension(PluginDescriptor.java:165)\n        at\norg.eclipse.core.internal.plugins.ConfigurationElement.createExecutableExtension(ConfigurationElement.java:102)\n        at\norg.eclipse.core.internal.events.BuildManager.instantiateBuilder(BuildManager.java:489)\n        at\norg.eclipse.core.internal.events.BuildManager.initializeBuilder(BuildManager.java:443)\n        at\norg.eclipse.core.internal.events.BuildManager.getBuilder(BuildManager.java:328)\n        at\norg.eclipse.core.internal.events.BuildManager.basicBuild(BuildManager.java:165)\n        at\norg.eclipse.core.internal.events.BuildManager.basicBuild(BuildManager.java:186)\n        at\norg.eclipse.core.internal.events.BuildManager$1.run(BuildManager.java:146)\n        at\norg.eclipse.core.internal.runtime.InternalPlatform.run(InternalPlatform.java:839)\n        at org.eclipse.core.runtime.Platform.run(Platform.java:413)\n        at\norg.eclipse.core.internal.events.BuildManager.basicBuild(BuildManager.java:160)\n        at\norg.eclipse.core.internal.events.BuildManager.build(BuildManager.java:232)\n        at org.eclipse.core.internal.resources.Project.build(Project.java:85)",
    "Im using Eclipse-2.1-M3 on Linux-GTK",
    "Fixed.\nplease verify changes to VariableContextManager (Luc).",
    "Verified.\nPlease update the build notes (DarinS)"
  ],
  "commentCreationDates": [
    "2002-11-22T00:40:30+01:00",
    "2002-11-22T00:41:42+01:00",
    "2002-11-25T22:50:35+01:00",
    "2002-11-26T22:02:21+01:00"
  ],
  "traces": [
    {
      "exceptionType": "java.lang.NullPointerException",
      "elements": [
        {
          "method": "org.eclipse.ui.externaltools.internal.model.VariableContextManager.\u003cinit\u003e",
          "source": "VariableContextManager.java:45"
        },
        {
          "method": "org.eclipse.ui.externaltools.internal.model.VariableContextManager.getDefault",
          "source": "VariableContextManager.java:59"
        },
        {
          "method": "org.eclipse.ui.externaltools.internal.model.ExternalToolsPlugin.startup",
          "source": "ExternalToolsPlugin.java:231"
        },
        {
          "method": "org.eclipse.core.internal.plugins.PluginDescriptor$1.run",
          "source": "PluginDescriptor.java:697"
        },
        {
          "method": "org.eclipse.core.internal.runtime.InternalPlatform.run",
          "source": "InternalPlatform.java:839"
        },
        {
          "method": "org.eclipse.core.internal.plugins.PluginDescriptor.internalDoPluginActivation",
          "source": "PluginDescriptor.java:709"
        },
        {
          "method": "org.eclipse.core.internal.plugins.PluginDescriptor.doPluginActivation",
          "source": "PluginDescriptor.java:184"
        },
        {
          "method": "org.eclipse.core.internal.plugins.PluginClassLoader.activatePlugin",
          "source": "PluginClassLoader.java:60"
        },
        {
          "method": "org.eclipse.core.internal.plugins.PluginClassLoader.internalFindClassParentsSelf",
          "source": "PluginClassLoader.java:138"
        },
        {
          "method": "org.eclipse.core.internal.boot.DelegatingURLClassLoader.findClassParentsSelf",
          "source": "DelegatingURLClassLoader.java:473"
        },
        {
          "method": "org.eclipse.core.internal.boot.DelegatingURLClassLoader.loadClass",
          "source": "DelegatingURLClassLoader.java:863"
        },
        {
          "method": "org.eclipse.core.internal.boot.DelegatingURLClassLoader.loadClass",
          "source": "DelegatingURLClassLoader.java:843"
        },
        {
          "method": "java.lang.ClassLoader.loadClass",
          "source": "ClassLoader.java:255"
        },
        {
          "method": "org.eclipse.core.internal.plugins.PluginDescriptor.createExecutableExtension",
          "source": "PluginDescriptor.java:128"
        },
        {
          "method": "org.eclipse.core.internal.plugins.PluginDescriptor.createExecutableExtension",
          "source": "PluginDescriptor.java:165"
        },
        {
          "method": "org.eclipse.core.internal.plugins.ConfigurationElement.createExecutableExtension",
          "source": "ConfigurationElement.java:102"
        },
        {
          "method": "org.eclipse.core.internal.events.BuildManager.instantiateBuilder",
          "source": "BuildManager.java:489"
        },
        {
          "method": "org.eclipse.core.internal.events.BuildManager.initializeBuilder",
          "source": "BuildManager.java:443"
        },
        {
          "method": "org.eclipse.core.internal.events.BuildManager.getBuilder",
          "source": "BuildManager.java:328"
        },
        {
          "method": "org.eclipse.core.internal.events.BuildManager.basicBuild",
          "source": "BuildManager.java:165"
        },
        {
          "method": "org.eclipse.core.internal.events.BuildManager.basicBuild",
          "source": "BuildManager.java:186"
        },
        {
          "method": "org.eclipse.core.internal.events.BuildManager$1.run",
          "source": "BuildManager.java:146"
        },
        {
          "method": "org.eclipse.core.internal.runtime.InternalPlatform.run",
          "source": "InternalPlatform.java:839"
        },
        {
          "method": "org.eclipse.core.runtime.Platform.run",
          "source": "Platform.java:413"
        },
        {
          "method": "org.eclipse.core.internal.events.BuildManager.basicBuild",
          "source": "BuildManager.java:160"
        },
        {
          "method": "org.eclipse.core.internal.events.BuildManager.build",
          "source": "BuildManager.java:232"
        },
        {
          "method": "org.eclipse.core.internal.resources.Project.build",
          "source": "Project.java:85"
        }
      ],
      "number": 0,
      "commentIndex": 0,
      "bugId": "26918",
      "date": "2002-11-22T00:40:30+01:00",
      "product": "Platform",
      "component": "Ant",
      "severity": "normal"
    }
  ],
  "groupId": "26918",
  "bugId": "26918",
  "date": "2002-11-22T00:40:30+01:00",
  "product": "Platform",
  "component": "Ant",
  "severity": "normal"
}