{
  "comments": [
    "Eclipse recently developed an intermittent problem with editor tabs.  It has\nhappened when starting, using, and exiting eclipse.  I see the problem most\noften when switching an editor tab - and lately, it seems to happen to a\nparticular editor tab.  I believe it happens no more than once per session.  The\nproblem has never caused any negative side-effects such as loss of data.  When\nthe error occurs, a message window pops up and points to the error log.  Here is\nthe latest of several identical messages from the error log:\n\n!SESSION Nov 22, 2002 17:25:52.78 ----------------------------------------------\njava.version\u003d1.4.1\njava.vendor\u003dSun Microsystems Inc.\nBootLoader constants: OS\u003dlinux, ARCH\u003dx86, WS\u003dmotif, NL\u003den_US\nCommand-line arguments: -os linux -ws motif -arch x86 -install\nfile:/usr/src/eclipse-2.0.2/\n!ENTRY org.eclipse.ui 4 2 Nov 22, 2002 17:25:52.80\n!MESSAGE Problems occurred when invoking code from plug-in: \"org.eclipse.ui\".\n!STACK 0\norg.eclipse.swt.SWTException: Widget is disposed\n        at org.eclipse.swt.SWT.error(SWT.java:2119)\n        at org.eclipse.swt.SWT.error(SWT.java:2051)\n        at org.eclipse.swt.widgets.Widget.error(Widget.java:296)\n        at org.eclipse.swt.widgets.Menu.getDisplay(Menu.java:291)\n        at org.eclipse.swt.widgets.Widget.isValidThread(Widget.java:455)\n        at org.eclipse.swt.widgets.Widget.checkWidget(Widget.java:234)\n        at org.eclipse.swt.widgets.Menu.getParentItem(Menu.java:446)\n        at\norg.eclipse.ui.internal.WorkbenchWindow$5.getText(WorkbenchWindow.java:580)\n        at\norg.eclipse.ui.internal.EditorMenuManager$Overrides.getText(EditorMenuManager.java:62)\n        at org.eclipse.jface.action.MenuManager.update(MenuManager.java:452)\n        at\norg.eclipse.jface.action.SubContributionItem.update(SubContributionItem.java:115)\n        at org.eclipse.jface.action.MenuManager.update(MenuManager.java:449)\n        at\norg.eclipse.ui.internal.WWinKeyBindingService.update(WWinKeyBindingService.java:203)\n        at\norg.eclipse.ui.internal.WWinKeyBindingService.access$0(WWinKeyBindingService.java:176)\n        at\norg.eclipse.ui.internal.WWinKeyBindingService$1.partActivated(WWinKeyBindingService.java:54)\n        at org.eclipse.ui.internal.PartListenerList$1.run(PartListenerList.java:39)\n        at\norg.eclipse.core.internal.runtime.InternalPlatform.run(InternalPlatform.java:839)\n        at org.eclipse.core.runtime.Platform.run(Platform.java:416)\n        at\norg.eclipse.ui.internal.PartListenerList.firePartActivated(PartListenerList.java:37)\n        at\norg.eclipse.ui.internal.WorkbenchPage.firePartActivated(WorkbenchPage.java:1044)\n        at\norg.eclipse.ui.internal.WorkbenchPage.setActivePart(WorkbenchPage.java:2122)\n        at\norg.eclipse.ui.internal.WorkbenchPage.requestActivation(WorkbenchPage.java:1864)\n        at org.eclipse.ui.internal.PartPane.requestActivation(PartPane.java:332)\n        at org.eclipse.ui.internal.EditorPane.requestActivation(EditorPane.java:129)\n        at org.eclipse.ui.internal.PartPane.setFocus(PartPane.java:350)\n        at\norg.eclipse.ui.internal.EditorWorkbook$2.widgetSelected(EditorWorkbook.java:140)\n        at org.eclipse.swt.widgets.TypedListener.handleEvent(TypedListener.java:87)\n        at org.eclipse.swt.widgets.EventTable.sendEvent(EventTable.java:77)\n        at org.eclipse.swt.widgets.Widget.sendEvent(Widget.java:845)\n        at org.eclipse.swt.widgets.Widget.notifyListeners(Widget.java:498)\n        at org.eclipse.swt.custom.CTabFolder.setSelection(CTabFolder.java:1687)\n        at org.eclipse.swt.custom.CTabFolder.onMouseDown(CTabFolder.java:1804)\n        at org.eclipse.swt.custom.CTabFolder.access$4(CTabFolder.java:1801)\n        at org.eclipse.swt.custom.CTabFolder$1.handleEvent(CTabFolder.java:200)\n        at org.eclipse.swt.widgets.EventTable.sendEvent(EventTable.java:77)\n        at org.eclipse.swt.widgets.Widget.sendEvent(Widget.java:853)\n        at org.eclipse.swt.widgets.Display.runDeferredEvents(Display.java:1708)\n        at org.eclipse.swt.widgets.Display.readAndDispatch(Display.java:1531)\n        at org.eclipse.ui.internal.Workbench.runEventLoop(Workbench.java:1343)\n        at org.eclipse.ui.internal.Workbench.run(Workbench.java:1326)\n        at\norg.eclipse.core.internal.boot.InternalBootLoader.run(InternalBootLoader.java:831)\n        at org.eclipse.core.boot.BootLoader.run(BootLoader.java:462)\n        at sun.reflect.NativeMethodAccessorImpl.invoke0(Native Method)\n        at\nsun.reflect.NativeMethodAccessorImpl.invoke(NativeMethodAccessorImpl.java:39)\n        at\nsun.reflect.DelegatingMethodAccessorImpl.invoke(DelegatingMethodAccessorImpl.java:25)\n        at java.lang.reflect.Method.invoke(Method.java:324)\n        at org.eclipse.core.launcher.Main.basicRun(Main.java:247)\n        at org.eclipse.core.launcher.Main.run(Main.java:703)\n        at org.eclipse.core.launcher.Main.main(Main.java:539)",
    "\n\n*** This bug has been marked as a duplicate of 25892 ***"
  ],
  "commentCreationDates": [
    "2002-11-23T04:40:14+01:00",
    "2002-11-25T16:02:55+01:00"
  ],
  "traces": [
    {
      "exceptionType": "org.eclipse.swt.SWTException",
      "message": "Widget is disposed",
      "elements": [
        {
          "method": "org.eclipse.swt.SWT.error",
          "source": "SWT.java:2119"
        },
        {
          "method": "org.eclipse.swt.SWT.error",
          "source": "SWT.java:2051"
        },
        {
          "method": "org.eclipse.swt.widgets.Widget.error",
          "source": "Widget.java:296"
        },
        {
          "method": "org.eclipse.swt.widgets.Menu.getDisplay",
          "source": "Menu.java:291"
        },
        {
          "method": "org.eclipse.swt.widgets.Widget.isValidThread",
          "source": "Widget.java:455"
        },
        {
          "method": "org.eclipse.swt.widgets.Widget.checkWidget",
          "source": "Widget.java:234"
        },
        {
          "method": "org.eclipse.swt.widgets.Menu.getParentItem",
          "source": "Menu.java:446"
        },
        {
          "method": "org.eclipse.ui.internal.WorkbenchWindow$5.getText",
          "source": "WorkbenchWindow.java:580"
        },
        {
          "method": "org.eclipse.ui.internal.EditorMenuManager$Overrides.getText",
          "source": "EditorMenuManager.java:62"
        },
        {
          "method": "org.eclipse.jface.action.MenuManager.update",
          "source": "MenuManager.java:452"
        },
        {
          "method": "org.eclipse.jface.action.SubContributionItem.update",
          "source": "SubContributionItem.java:115"
        },
        {
          "method": "org.eclipse.jface.action.MenuManager.update",
          "source": "MenuManager.java:449"
        },
        {
          "method": "org.eclipse.ui.internal.WWinKeyBindingService.update",
          "source": "WWinKeyBindingService.java:203"
        },
        {
          "method": "org.eclipse.ui.internal.WWinKeyBindingService.access$0",
          "source": "WWinKeyBindingService.java:176"
        },
        {
          "method": "org.eclipse.ui.internal.WWinKeyBindingService$1.partActivated",
          "source": "WWinKeyBindingService.java:54"
        },
        {
          "method": "org.eclipse.ui.internal.PartListenerList$1.run",
          "source": "PartListenerList.java:39"
        },
        {
          "method": "org.eclipse.core.internal.runtime.InternalPlatform.run",
          "source": "InternalPlatform.java:839"
        },
        {
          "method": "org.eclipse.core.runtime.Platform.run",
          "source": "Platform.java:416"
        },
        {
          "method": "org.eclipse.ui.internal.PartListenerList.firePartActivated",
          "source": "PartListenerList.java:37"
        },
        {
          "method": "org.eclipse.ui.internal.WorkbenchPage.firePartActivated",
          "source": "WorkbenchPage.java:1044"
        },
        {
          "method": "org.eclipse.ui.internal.WorkbenchPage.setActivePart",
          "source": "WorkbenchPage.java:2122"
        },
        {
          "method": "org.eclipse.ui.internal.WorkbenchPage.requestActivation",
          "source": "WorkbenchPage.java:1864"
        },
        {
          "method": "org.eclipse.ui.internal.PartPane.requestActivation",
          "source": "PartPane.java:332"
        },
        {
          "method": "org.eclipse.ui.internal.EditorPane.requestActivation",
          "source": "EditorPane.java:129"
        },
        {
          "method": "org.eclipse.ui.internal.PartPane.setFocus",
          "source": "PartPane.java:350"
        },
        {
          "method": "org.eclipse.ui.internal.EditorWorkbook$2.widgetSelected",
          "source": "EditorWorkbook.java:140"
        },
        {
          "method": "org.eclipse.swt.widgets.TypedListener.handleEvent",
          "source": "TypedListener.java:87"
        },
        {
          "method": "org.eclipse.swt.widgets.EventTable.sendEvent",
          "source": "EventTable.java:77"
        },
        {
          "method": "org.eclipse.swt.widgets.Widget.sendEvent",
          "source": "Widget.java:845"
        },
        {
          "method": "org.eclipse.swt.widgets.Widget.notifyListeners",
          "source": "Widget.java:498"
        },
        {
          "method": "org.eclipse.swt.custom.CTabFolder.setSelection",
          "source": "CTabFolder.java:1687"
        },
        {
          "method": "org.eclipse.swt.custom.CTabFolder.onMouseDown",
          "source": "CTabFolder.java:1804"
        },
        {
          "method": "org.eclipse.swt.custom.CTabFolder.access$4",
          "source": "CTabFolder.java:1801"
        },
        {
          "method": "org.eclipse.swt.custom.CTabFolder$1.handleEvent",
          "source": "CTabFolder.java:200"
        },
        {
          "method": "org.eclipse.swt.widgets.EventTable.sendEvent",
          "source": "EventTable.java:77"
        },
        {
          "method": "org.eclipse.swt.widgets.Widget.sendEvent",
          "source": "Widget.java:853"
        },
        {
          "method": "org.eclipse.swt.widgets.Display.runDeferredEvents",
          "source": "Display.java:1708"
        },
        {
          "method": "org.eclipse.swt.widgets.Display.readAndDispatch",
          "source": "Display.java:1531"
        },
        {
          "method": "org.eclipse.ui.internal.Workbench.runEventLoop",
          "source": "Workbench.java:1343"
        },
        {
          "method": "org.eclipse.ui.internal.Workbench.run",
          "source": "Workbench.java:1326"
        },
        {
          "method": "org.eclipse.core.internal.boot.InternalBootLoader.run",
          "source": "InternalBootLoader.java:831"
        },
        {
          "method": "org.eclipse.core.boot.BootLoader.run",
          "source": "BootLoader.java:462"
        },
        {
          "method": "sun.reflect.NativeMethodAccessorImpl.invoke0",
          "source": "Native Method"
        },
        {
          "method": "sun.reflect.NativeMethodAccessorImpl.invoke",
          "source": "NativeMethodAccessorImpl.java:39"
        },
        {
          "method": "sun.reflect.DelegatingMethodAccessorImpl.invoke",
          "source": "DelegatingMethodAccessorImpl.java:25"
        },
        {
          "method": "java.lang.reflect.Method.invoke",
          "source": "Method.java:324"
        },
        {
          "method": "org.eclipse.core.launcher.Main.basicRun",
          "source": "Main.java:247"
        },
        {
          "method": "org.eclipse.core.launcher.Main.run",
          "source": "Main.java:703"
        },
        {
          "method": "org.eclipse.core.launcher.Main.main",
          "source": "Main.java:539"
        }
      ],
      "number": 0,
      "commentIndex": 0,
      "bugId": "27017",
      "duplicateId": "25892",
      "date": "2002-11-23T04:40:14+01:00",
      "product": "Platform",
      "component": "UI",
      "severity": "normal"
    }
  ],
  "groupId": "25892",
  "bugId": "27017",
  "duplicateId": "25892",
  "date": "2002-11-23T04:40:14+01:00",
  "product": "Platform",
  "component": "UI",
  "severity": "normal"
}