{
  "comments": [
    "Eclipse crashed when a mouse drag select was attempted in\na java source file. This was in Plugin Package Perspective,\nin Package Explorer, with a java source file selected and\ndisplayed in an edit window.\n\nFollowing are the logs for \n\tcrashreporter, and\n\t.metadata/\n\nThis was on Mac OS 10.2.2\n\n\n\u003d\u003d\u003d\u003d\u003d\u003d\u003d\u003d\u003d\u003d\u003d\u003d\u003d\u003d\u003d\u003d\u003d\u003d\u003d\u003d\u003d\u003d\u003d\u003d\u003d\u003d\u003d\u003d\u003d\u003d\u003d\u003d\u003d\u003d\u003d\u003d\u003d\u003d\u003d\u003d\u003d\u003d\u003d\u003d\u003d\u003d\u003d\u003d\u003d\u003d\u003d\u003d\u003d\u003d\u003d\u003d\u003d\u003d\n\nDate/Time:  2002-11-26 13:39:02 -0700\nOS Version: 10.2.2 (Build 6F21)\nHost:       Alan-Hawrelaks-Computer.local.\n\nCommand:    Eclipse\nPID:        505\n\nException:  EXC_BAD_ACCESS (0x0001)\nCodes:      KERN_PROTECTION_FAILURE (0x0002) at 0x00000008\n\nThread 0:\n #0   0x90074168 in mach_msg_trap\n #1   0x900064b0 in mach_msg\n #2   0x9283ddf4 in JVM_NewInstance\n #3   0x9285eb40 in JVM_FillInStackTrace\n #4   0x92874f80 in JVM_GetCPClassNameUTF\n #5   0x9287076c in JVM_IHashCode\n #6   0x92886c68 in JVM_SetThreadPriority\n #7   0x9287ac9c in JVM_GetCPMethodModifiers\n #8   0x928817a8 in JVM_DefineClass\n #9   0x021015b8 in 0x21015b8\n #10  0x0239b24c in 0x239b24c\n #11  0x0234f738 in 0x234f738\n #12  0x021005cc in 0x21005cc\n #13  0xa2843c38 in typeinfo name for std::bad_exception\n #14  0x92838bdc in JVM_CurrentTimeMillis\n #15  0x92872ed4 in JVM_GetCPClassNameUTF\n #16  0x9287a3b8 in JVM_GetCPMethodModifiers\n #17  0x92993a20 in jio_vsnprintf\n #18  0x01e08f9c in callback\n #19  0x01e036a8 in fn6_2\n #20  0x92c11d04 in DrawOurControl(UserPaneGlobals*)\n #21  0x92bd42b8 in UserPaneCDEF\n #22  0x92baf700 in DispatchMessage(HIView*, short, long, unsigned char, unsigned char)\n #23  0x92bca9b4 in Draw(HIView*, OpaqueEventRef*)\n #24  0x92bb681c in ClassicCDEFAdapter::EventHandler(OpaqueEventHandlerCallRef*, OpaqueEventRef*, void*)\n #25  0x92ba25b4 in DispatchEventToHandlers\n #26  0x92ba291c in SendEventToEventTargetInternal\n #27  0x92ba5d28 in SendEventToEventTargetWithOptions\n #28  0x92bb2e20 in SendControlDefDraw(HIView*, short, OpaqueGrafPtr*, OpaqueRgnHandle*, CGContext*)\n #29  0x92baea3c in HIView::DrawInternal(short, OpaqueGrafPtr*, OpaqueRgnHandle*, unsigned char, unsigned char, unsigned char, HIView*, CGContext*)\n #30  0x92baeb58 in HIView::DrawInternal(short, OpaqueGrafPtr*, OpaqueRgnHandle*, unsigned char, unsigned char, unsigned char, HIView*, CGContext*)\n #31  0x92baeb58 in HIView::DrawInternal(short, OpaqueGrafPtr*, OpaqueRgnHandle*, unsigned char, unsigned char, unsigned char, HIView*, CGContext*)\n #32  0x92baeb58 in HIView::DrawInternal(short, OpaqueGrafPtr*, OpaqueRgnHandle*, unsigned char, unsigned char, unsigned char, HIView*, CGContext*)\n #33  0x92baeb58 in HIView::DrawInternal(short, OpaqueGrafPtr*, OpaqueRgnHandle*, unsigned char, unsigned char, unsigned char, HIView*, CGContext*)\n #34  0x92baeb58 in HIView::DrawInternal(short, OpaqueGrafPtr*, OpaqueRgnHandle*, unsigned char, unsigned char, unsigned char, HIView*, CGContext*)\n #35  0x92baeb58 in HIView::DrawInternal(short, OpaqueGrafPtr*, OpaqueRgnHandle*, unsigned char, unsigned char, unsigned char, HIView*, CGContext*)\n #36  0x92baeb58 in HIView::DrawInternal(short, OpaqueGrafPtr*, OpaqueRgnHandle*, unsigned char, unsigned char, unsigned char, HIView*, CGContext*)\n #37  0x92baeb58 in HIView::DrawInternal(short, OpaqueGrafPtr*, OpaqueRgnHandle*, unsigned char, unsigned char, unsigned char, HIView*, CGContext*)\n #38  0x92bb02f0 in HIView::Draw(short, OpaqueGrafPtr*, OpaqueRgnHandle*, unsigned long, HIView*, CGContext*)\n #39  0x92c07b34 in ActivateControl\n #40  0x92bdc75c in HandleWindowEvent\n #41  0x92bed6c4 in StandardWindowEventHandler\n #42  0x92ba25b4 in DispatchEventToHandlers\n #43  0x92ba291c in SendEventToEventTargetInternal\n #44  0x92ba5d28 in SendEventToEventTargetWithOptions\n #45  0x92bf1f70 in PostActivateEvent\n #46  0x92beab44 in HiliteAndActivateWindow\n #47  0x92c09c80 in AdjustToNewWindowActivation(WindowData*, WindowContext*, OpaqueWindowPtr*, WindowData*)\n #48  0x92c2d298 in PotentiallyAdjustToNewWindowActivation(WindowData*, WindowData*, WindowContext*, OpaqueWindowPtr*, WindowData*)\n #49  0x92c27e38 in SelectWindowInGroup(WindowData*, WindowContext*, OpaqueWindowGroupRef*)\n #50  0x92c4c138 in SelectWindow\n #51  0x92c37560 in HandleAppActivated(unsigned char, OpaqueWindowPtr*)\n #52  0x92bb0dd4 in CompatibilityEventObserver(unsigned long, OpaqueEventRef*, void*)\n #53  0x92ba2370 in _NotifyEventLoopObservers\n #54  0x92bb47e8 in AcquireEventFromQueue\n #55  0x92bb328c in ReceiveNextEventCommon\n #56  0x92c0499c in ReceiveNextEventInMode\n #57  0x01df6fa0 in Java_org_eclipse_swt_internal_carbon_OS_ReceiveNextEvent\n #58  0x02102668 in 0x2102668\n #59  0x021005cc in 0x21005cc\n #60  0x021005cc in 0x21005cc\n #61  0x0210068c in 0x210068c\n #62  0x021007ac in 0x21007ac\n #63  0x021005cc in 0x21005cc\n #64  0xa2843c38 in typeinfo name for std::bad_exception\n #65  0x92838bdc in JVM_CurrentTimeMillis\n #66  0x92872ed4 in JVM_GetCPClassNameUTF\n #67  0x92907430 in JVM_InvokeMethod\n #68  0x92906a90 in JVM_InvokeMethod\n #69  0x92906738 in JVM_InvokeMethod\n #70  0x02102668 in 0x2102668\n #71  0x021005cc in 0x21005cc\n #72  0x021005cc in 0x21005cc\n #73  0x021005cc in 0x21005cc\n #74  0xa2843c38 in typeinfo name for std::bad_exception\n #75  0x92838bdc in JVM_CurrentTimeMillis\n #76  0x92872ed4 in JVM_GetCPClassNameUTF\n #77  0x92907430 in JVM_InvokeMethod\n #78  0x92906a90 in JVM_InvokeMethod\n #79  0x92906738 in JVM_InvokeMethod\n #80  0x02102668 in 0x2102668\n #81  0x021005cc in 0x21005cc\n #82  0x0210068c in 0x210068c\n #83  0x0210068c in 0x210068c\n #84  0xa2843c38 in typeinfo name for std::bad_exception\n #85  0x92838bdc in JVM_CurrentTimeMillis\n #86  0x92872ed4 in JVM_GetCPClassNameUTF\n #87  0x9287a3b8 in JVM_GetCPMethodModifiers\n #88  0x92904790 in JVM_IsSupportedJNIVersion\n #89  0x92b22174 in JNIEnv_::CallStaticVoidMethod(_jclass*, _jmethodID*, ...)\n #90  0x92b111c0 in CallCarbonLibAppLaunch(JNIEnv_*, __CFDictionary const*, __CFArray const*)\n #91  0x92b12ce8 in launchJavaApplication\n #92  0x00001c54 in 0x1c54\n #93  0x00001ad4 in 0x1ad4\n\nThread 1:\n #0   0x90074168 in mach_msg_trap\n #1   0x900064b0 in mach_msg\n #2   0x928ec28c in JNI_CreateJavaVM_Impl\n #3   0x928ec224 in JNI_CreateJavaVM_Impl\n #4   0x928a51fc in JVM_GetClassMethodsCount\n #5   0x90021268 in _pthread_body\n\nThread 2:\n #0   0x90074168 in mach_msg_trap\n #1   0x900064b0 in mach_msg\n #2   0x9283de9c in JVM_NewInstance\n #3   0x9285eae4 in JVM_FillInStackTrace\n #4   0x928647a0 in JVM_Send\n #5   0x9290114c in JNI_CreateJavaVM_Impl\n #6   0x928a51fc in JVM_GetClassMethodsCount\n #7   0x90021268 in _pthread_body\n\nThread 3:\n #0   0x90074168 in mach_msg_trap\n #1   0x900064b0 in mach_msg\n #2   0x9283ddf4 in JVM_NewInstance\n #3   0x92845d80 in JVM_ArrayCopy\n #4   0x9285d620 in JVM_MonitorNotify\n #5   0x9285e2f8 in JVM_MonitorWait\n #6   0x02102668 in 0x2102668\n #7   0x0210068c in 0x210068c\n #8   0x0210068c in 0x210068c\n #9   0xa2843c38 in typeinfo name for std::bad_exception\n #10  0x92838bdc in JVM_CurrentTimeMillis\n #11  0x92878c28 in JVM_FindClassFromClass\n #12  0x92892c90 in JVM_IsSameClassPackage\n #13  0x9288cf70 in JVM_GetMethodIxExceptionTableEntry\n #14  0x928787a0 in JVM_FindClassFromClass\n #15  0x928a51fc in JVM_GetClassMethodsCount\n #16  0x90021268 in _pthread_body\n\nThread 4:\n #0   0x90074168 in mach_msg_trap\n #1   0x900064b0 in mach_msg\n #2   0x9283ddf4 in JVM_NewInstance\n #3   0x92845d80 in JVM_ArrayCopy\n #4   0x9285d620 in JVM_MonitorNotify\n #5   0x9285e2f8 in JVM_MonitorWait\n #6   0x02102668 in 0x2102668\n #7   0x0210068c in 0x210068c\n #8   0x021005cc in 0x21005cc\n #9   0x021005cc in 0x21005cc\n #10  0xa2843c38 in typeinfo name for std::bad_exception\n #11  0x92838bdc in JVM_CurrentTimeMillis\n #12  0x92878c28 in JVM_FindClassFromClass\n #13  0x92892c90 in JVM_IsSameClassPackage\n #14  0x9288cf70 in JVM_GetMethodIxExceptionTableEntry\n #15  0x928787a0 in JVM_FindClassFromClass\n #16  0x928a51fc in JVM_GetClassMethodsCount\n #17  0x90021268 in _pthread_body\n\nThread 5:\n #0   0x90074168 in mach_msg_trap\n #1   0x900064b0 in mach_msg\n #2   0x9283de9c in JVM_NewInstance\n #3   0x92844e18 in JVM_GetClassLoader\n #4   0x92844ba4 in JVM_GetClassLoader\n #5   0x928a51fc in JVM_GetClassMethodsCount\n #6   0x90021268 in _pthread_body\n\nThread 6:\n #0   0x90074168 in mach_msg_trap\n #1   0x900064b0 in mach_msg\n #2   0x9283ddf4 in JVM_NewInstance\n #3   0x9285eb40 in JVM_FillInStackTrace\n #4   0x92903300 in JVM_InitProperties\n #5   0x92903138 in JVM_InitProperties\n #6   0x928787a0 in JVM_FindClassFromClass\n #7   0x928a51fc in JVM_GetClassMethodsCount\n #8   0x90021268 in _pthread_body\n\nThread 7 Crashed:\n #0   0x92856914 in JVM_GetMethodIxLocalsCount\n #1   0x92848a18 in __moddi3\n #2   0x92859434 in JVM_GetCPMethodNameUTF\n #3   0x92976dd8 in JVM_UnloadLibrary\n #4   0x92863a1c in JVM_Send\n #5   0x92862a80 in JVM_Send\n #6   0x9284cfd0 in JVM_GetCPMethodClassNameUTF\n #7   0x9283ff08 in JVM_Read\n #8   0x9287316c in JVM_GetCPClassNameUTF\n #9   0x928731bc in JVM_GetCPClassNameUTF\n #10  0x928731bc in JVM_GetCPClassNameUTF\n #11  0x92858134 in JVM_GetCPMethodNameUTF\n #12  0x9286e520 in JVM_IHashCode\n #13  0x92866b28 in JVM_DoPrivileged\n #14  0x92871e6c in JVM_GetCPClassNameUTF\n #15  0x92847988 in __moddi3\n #16  0x9283ff18 in JVM_Read\n #17  0x9287316c in JVM_GetCPClassNameUTF\n #18  0x928731bc in JVM_GetCPClassNameUTF\n #19  0x928731bc in JVM_GetCPClassNameUTF\n #20  0x928731bc in JVM_GetCPClassNameUTF\n #21  0x928731bc in JVM_GetCPClassNameUTF\n #22  0x928731bc in JVM_GetCPClassNameUTF\n #23  0x928731bc in JVM_GetCPClassNameUTF\n #24  0x928731bc in JVM_GetCPClassNameUTF\n #25  0x928731bc in JVM_GetCPClassNameUTF\n #26  0x928731bc in JVM_GetCPClassNameUTF\n #27  0x928731bc in JVM_GetCPClassNameUTF\n #28  0x928731bc in JVM_GetCPClassNameUTF\n #29  0x928731bc in JVM_GetCPClassNameUTF\n #30  0x928731bc in JVM_GetCPClassNameUTF\n #31  0x928837dc in JVM_DefineClass\n #32  0x9283eac8 in JVM_Read\n #33  0x9287316c in JVM_GetCPClassNameUTF\n #34  0x928731bc in JVM_GetCPClassNameUTF\n #35  0x928731bc in JVM_GetCPClassNameUTF\n #36  0x928731bc in JVM_GetCPClassNameUTF\n #37  0x928731bc in JVM_GetCPClassNameUTF\n #38  0x928731bc in JVM_GetCPClassNameUTF\n #39  0x928731bc in JVM_GetCPClassNameUTF\n #40  0x928731bc in JVM_GetCPClassNameUTF\n #41  0x928731bc in JVM_GetCPClassNameUTF\n #42  0x928731bc in JVM_GetCPClassNameUTF\n #43  0x928731bc in JVM_GetCPClassNameUTF\n #44  0x928731bc in JVM_GetCPClassNameUTF\n #45  0x928731bc in JVM_GetCPClassNameUTF\n #46  0x928731bc in JVM_GetCPClassNameUTF\n #47  0x928731bc in JVM_GetCPClassNameUTF\n #48  0x928731bc in JVM_GetCPClassNameUTF\n #49  0x928731bc in JVM_GetCPClassNameUTF\n #50  0x928731bc in JVM_GetCPClassNameUTF\n #51  0x928731bc in JVM_GetCPClassNameUTF\n #52  0x928731bc in JVM_GetCPClassNameUTF\n #53  0x928731bc in JVM_GetCPClassNameUTF\n #54  0x928731bc in JVM_GetCPClassNameUTF\n #55  0x928731bc in JVM_GetCPClassNameUTF\n #56  0x928731bc in JVM_GetCPClassNameUTF\n #57  0x928731bc in JVM_GetCPClassNameUTF\n #58  0x928731bc in JVM_GetCPClassNameUTF\n #59  0x92858134 in JVM_GetCPMethodNameUTF\n #60  0x9286e520 in JVM_IHashCode\n #61  0x928840a0 in JVM_DefineClass\n #62  0x92881894 in JVM_DefineClass\n #63  0x9287bef4 in JVM_GetCPMethodModifiers\n #64  0x9287e9dc in JVM_GetMethodIxExceptionIndexes\n #65  0x9287e380 in JVM_RawMonitorExit\n #66  0x92863608 in JVM_Send\n #67  0x92876c68 in JVM_FindLoadedClass\n #68  0x928787a0 in JVM_FindClassFromClass\n #69  0x928a51fc in JVM_GetClassMethodsCount\n #70  0x90021268 in _pthread_body\n\nThread 8:\n #0   0x90074168 in mach_msg_trap\n #1   0x900064b0 in mach_msg\n #2   0xc00076cc in __ape_internal\n #3   0xc0000dd0 in __ape_agent\n #4   0x90021268 in _pthread_body\n\nThread 9:\n #0   0x90074168 in mach_msg_trap\n #1   0x900064b0 in mach_msg\n #2   0x9283ddf4 in JVM_NewInstance\n #3   0x92845d80 in JVM_ArrayCopy\n #4   0x9285d620 in JVM_MonitorNotify\n #5   0x9285e2f8 in JVM_MonitorWait\n #6   0x02102668 in 0x2102668\n #7   0x0210068c in 0x210068c\n #8   0x0210068c in 0x210068c\n #9   0x0210086c in 0x210086c\n #10  0xa2843c38 in typeinfo name for std::bad_exception\n #11  0x92838bdc in JVM_CurrentTimeMillis\n #12  0x92878c28 in JVM_FindClassFromClass\n #13  0x92892c90 in JVM_IsSameClassPackage\n #14  0x9288cf70 in JVM_GetMethodIxExceptionTableEntry\n #15  0x928787a0 in JVM_FindClassFromClass\n #16  0x928a51fc in JVM_GetClassMethodsCount\n #17  0x90021268 in _pthread_body\n\nThread 10:\n #0   0x90074168 in mach_msg_trap\n #1   0x900064b0 in mach_msg\n #2   0x9283de9c in JVM_NewInstance\n #3   0x92844d34 in JVM_GetClassLoader\n #4   0x9290a3a4 in JVM_Sleep\n #5   0x02102668 in 0x2102668\n #6   0x0210068c in 0x210068c\n #7   0x0210086c in 0x210086c\n #8   0xa2843c38 in typeinfo name for std::bad_exception\n #9   0x92838bdc in JVM_CurrentTimeMillis\n #10  0x92878c28 in JVM_FindClassFromClass\n #11  0x92892c90 in JVM_IsSameClassPackage\n #12  0x9288cf70 in JVM_GetMethodIxExceptionTableEntry\n #13  0x928787a0 in JVM_FindClassFromClass\n #14  0x928a51fc in JVM_GetClassMethodsCount\n #15  0x90021268 in _pthread_body\n\nThread 11:\n #0   0x90074168 in mach_msg_trap\n #1   0x900064b0 in mach_msg\n #2   0x9283de9c in JVM_NewInstance\n #3   0x92845d80 in JVM_ArrayCopy\n #4   0x9285d620 in JVM_MonitorNotify\n #5   0x9285e2f8 in JVM_MonitorWait\n #6   0x02102668 in 0x2102668\n #7   0x0210068c in 0x210068c\n #8   0xa2843c38 in typeinfo name for std::bad_exception\n #9   0x92838bdc in JVM_CurrentTimeMillis\n #10  0x92878c28 in JVM_FindClassFromClass\n #11  0x92892c90 in JVM_IsSameClassPackage\n #12  0x9288cf70 in JVM_GetMethodIxExceptionTableEntry\n #13  0x928787a0 in JVM_FindClassFromClass\n #14  0x928a51fc in JVM_GetClassMethodsCount\n #15  0x90021268 in _pthread_body\n\nThread 12:\n #0   0x90074168 in mach_msg_trap\n #1   0x900064b0 in mach_msg\n #2   0x9283de9c in JVM_NewInstance\n #3   0x92845d80 in JVM_ArrayCopy\n #4   0x9285d620 in JVM_MonitorNotify\n #5   0x9285e2f8 in JVM_MonitorWait\n #6   0x02102668 in 0x2102668\n #7   0x0210068c in 0x210068c\n #8   0xa2843c38 in typeinfo name for std::bad_exception\n #9   0x92838bdc in JVM_CurrentTimeMillis\n #10  0x92878c28 in JVM_FindClassFromClass\n #11  0x92892c90 in JVM_IsSameClassPackage\n #12  0x9288cf70 in JVM_GetMethodIxExceptionTableEntry\n #13  0x928787a0 in JVM_FindClassFromClass\n #14  0x928a51fc in JVM_GetClassMethodsCount\n #15  0x90021268 in _pthread_body\n\nThread 13:\n #0   0x90074168 in mach_msg_trap\n #1   0x900064b0 in mach_msg\n #2   0x9283de9c in JVM_NewInstance\n #3   0x92845d80 in JVM_ArrayCopy\n #4   0x9285d620 in JVM_MonitorNotify\n #5   0x9285e2f8 in JVM_MonitorWait\n #6   0x02102668 in 0x2102668\n #7   0x0210068c in 0x210068c\n #8   0xa2843c38 in typeinfo name for std::bad_exception\n #9   0x92838bdc in JVM_CurrentTimeMillis\n #10  0x92878c28 in JVM_FindClassFromClass\n #11  0x92892c90 in JVM_IsSameClassPackage\n #12  0x9288cf70 in JVM_GetMethodIxExceptionTableEntry\n #13  0x928787a0 in JVM_FindClassFromClass\n #14  0x928a51fc in JVM_GetClassMethodsCount\n #15  0x90021268 in _pthread_body\n\nPPC Thread State:\n  srr0: 0x92856914 srr1: 0x0000d030                vrsave: 0x00000000\n   xer: 0x00000000   lr: 0x92856858  ctr: 0x90001400   mq: 0x00000000\n    r0: 0x03ce4585   r1: 0xf0385240   r2: 0x0001bb5f   r3: 0x62e56460\n    r4: 0x000376be   r5: 0xa28367dc   r6: 0x00000001   r7: 0x00000000\n    r8: 0x6c9bba40   r9: 0x0000017b  r10: 0x000382a4  r11: 0x03ce0000\n   r12: 0x000000e4  r13: 0x00000000  r14: 0x00000000  r15: 0x00000000\n   r16: 0xa2832704  r17: 0xa28322c8  r18: 0x929b9500  r19: 0x929b9518\n   r20: 0xa283b1a0  r21: 0x9283fefc  r22: 0x05801068  r23: 0x058030cc\n   r24: 0x05801068  r25: 0x00108bcc  r26: 0x00108bd0  r27: 0x6c262a18\n   r28: 0x62e56460  r29: 0x0001c8c0  r30: 0x04aee500  r31: 0x928567dc\n\n\u003d\u003d\u003d\u003d\u003d\u003d\u003d\u003d\u003d\u003d\u003d\u003d\u003d\u003d\u003d\u003d\u003d\u003d\u003d\u003d\u003d\u003d\u003d\u003d\u003d\u003d\u003d\u003d\u003d\u003d\u003d\u003d\u003d\u003d\u003d\u003d\u003d\u003d\u003d\u003d\u003d\u003d\u003d\u003d\u003d\u003d\u003d\u003d\u003d\u003d\u003d\u003d\u003d\u003d\u003d\u003d\u003d\u003d\n\n\n!SESSION Nov 18, 2002 17:12:49.377 ---------------------------------------------\njava.version\u003d1.3.1\njava.vendor\u003dApple Computer, Inc.\nBootLoader constants: OS\u003dmacosx, ARCH\u003dppc, WS\u003dcarbon, NL\u003den_US\nCommand-line arguments: -noupdate -consoleLog -showlocation -os macosx -ws carbon -install file:/Volumes/Mac9.2/eclipse_Nov15/Eclipse_2.0.app/Contents/Resources/Java/\n!ENTRY org.eclipse.ui.workbench 4 2 Nov 18, 2002 17:12:49.379\n!MESSAGE Problems occurred when invoking code from plug-in: \"org.eclipse.ui.workbench\".\n!STACK 0\norg.eclipse.swt.SWTException: Widget is disposed\n\tat org.eclipse.swt.SWT.error(SWT.java:2180)\n\tat org.eclipse.swt.SWT.error(SWT.java:2110)\n\tat org.eclipse.swt.widgets.Widget.error(Widget.java:299)\n\tat org.eclipse.swt.widgets.Menu.getDisplay(Menu.java:335)\n\tat org.eclipse.swt.widgets.Widget.isValidThread(Widget.java:458)\n\tat org.eclipse.swt.widgets.Widget.checkWidget(Widget.java:229)\n\tat org.eclipse.swt.widgets.Menu.getItems(Menu.java:415)\n\tat org.eclipse.swt.widgets.Menu.releaseWidget(Menu.java:688)\n\tat org.eclipse.swt.widgets.MenuItem.releaseWidget(MenuItem.java:402)\n\tat org.eclipse.swt.widgets.Menu.releaseWidget(Menu.java:692)\n\tat org.eclipse.swt.widgets.MenuItem.releaseWidget(MenuItem.java:402)\n\tat org.eclipse.swt.widgets.Menu.releaseWidget(Menu.java:692)\n\tat org.eclipse.swt.widgets.Decorations.releaseWidget(Decorations.java:393)\n\tat org.eclipse.swt.widgets.Shell.releaseWidget(Shell.java:1213)\n\tat org.eclipse.swt.widgets.Widget.dispose(Widget.java:289)\n\tat org.eclipse.swt.widgets.Shell.dispose(Shell.java:725)\n\tat org.eclipse.jface.window.Window.close(Window.java:223)\n\tat org.eclipse.jface.window.ApplicationWindow.close(ApplicationWindow.java:186)\n\tat org.eclipse.ui.internal.WorkbenchWindow.hardClose(WorkbenchWindow.java:908)\n\tat org.eclipse.ui.internal.WorkbenchWindow.busyClose(WorkbenchWindow.java:337)\n\tat org.eclipse.ui.internal.WorkbenchWindow.access$3(WorkbenchWindow.java:326)\n\tat org.eclipse.ui.internal.WorkbenchWindow$2.run(WorkbenchWindow.java:382)\n\tat org.eclipse.swt.custom.BusyIndicator.showWhile(BusyIndicator.java:65)\n\tat org.eclipse.ui.internal.WorkbenchWindow.close(WorkbenchWindow.java:380)\n\tat org.eclipse.jface.window.WindowManager.close(WindowManager.java:102)\n\tat org.eclipse.ui.internal.Workbench$3.run(Workbench.java:253)\n\tat org.eclipse.core.internal.runtime.InternalPlatform.run(InternalPlatform.java:839)\n\tat org.eclipse.core.runtime.Platform.run(Platform.java:413)\n\tat org.eclipse.ui.internal.Workbench.busyClose(Workbench.java:250)\n\tat org.eclipse.ui.internal.Workbench.access$5(Workbench.java:207)\n\tat org.eclipse.ui.internal.Workbench$5.run(Workbench.java:383)\n\tat org.eclipse.swt.custom.BusyIndicator.showWhile(BusyIndicator.java:65)\n\tat org.eclipse.ui.internal.Workbench.close(Workbench.java:381)\n\tat org.eclipse.ui.internal.Workbench.close(Workbench.java:373)\n\tat org.eclipse.ui.internal.Workbench.close(Workbench.java:367)\n\tat org.eclipse.ui.internal.Workbench$13.handleEvent(Workbench.java:1405)\n\tat org.eclipse.swt.widgets.EventTable.sendEvent(EventTable.java:77)\n\tat org.eclipse.swt.widgets.Display.sendEvent(Display.java:1301)\n\tat org.eclipse.swt.widgets.Display.close(Display.java:338)\n\tat org.eclipse.swt.widgets.Display.handleApplicationCallback(Display.java:2065)\n\tat org.eclipse.swt.internal.carbon.OS.SendEventToEventTarget(Native Method)\n\tat org.eclipse.swt.widgets.Display.readAndDispatch(Display.java:1118)\n\tat org.eclipse.ui.internal.Workbench.runEventLoop(Workbench.java:1435)\n\tat org.eclipse.ui.internal.Workbench.run(Workbench.java:1418)\n\tat org.eclipse.core.internal.boot.InternalBootLoader.run(InternalBootLoader.java:831)\n\tat org.eclipse.core.boot.BootLoader.run(BootLoader.java:462)\n\tat java.lang.reflect.Method.invoke(Native Method)\n\tat org.eclipse.core.launcher.Main.basicRun(Main.java:247)\n\tat org.eclipse.core.launcher.Main.run(Main.java:703)\n\tat org.eclipse.core.launcher.Main.main(Main.java:539)\n\tat java.lang.reflect.Method.invoke(Native Method)\n\tat com.apple.buckyball.app.LaunchRunner.run(LaunchRunner.java:82)\n\tat com.apple.buckyball.app.LaunchRunner.callMain(LaunchRunner.java:44)\n\tat com.apple.buckyball.app.CarbonLibApp.launch(CarbonLibApp.java:67)\n!SESSION Nov 19, 2002 17:01:40.853 ---------------------------------------------\njava.version\u003d1.3.1\njava.vendor\u003dApple Computer, Inc.\nBootLoader constants: OS\u003dmacosx, ARCH\u003dppc, WS\u003dcarbon, NL\u003den_US\nCommand-line arguments: -noupdate -consoleLog -showlocation -os macosx -ws carbon -install file:/Volumes/Mac9.2/eclipse_Nov15/Eclipse_2.0.app/Contents/Resources/Java/\n!ENTRY org.eclipse.core.resources 1 1 Nov 19, 2002 17:01:40.856\n!MESSAGE Could not load library: libcore_2_0_5.jnilib.  This library provides platform-specific optimizations for certain file-system operations.  This library is not present on all platforms, so this may not be an error.  The resources plugin will safely fall back to using java.io.File functionality.\n!SESSION Nov 21, 2002 16:25:10.562 ---------------------------------------------\njava.version\u003d1.3.1\njava.vendor\u003dApple Computer, Inc.\nBootLoader constants: OS\u003dmacosx, ARCH\u003dppc, WS\u003dcarbon, NL\u003den_US\nCommand-line arguments: -noupdate -consoleLog -showlocation -os macosx -ws carbon -install file:/Volumes/Mac9.2/eclipse_Nov15/Eclipse_2.0.app/Contents/Resources/Java/\n!ENTRY org.eclipse.core.resources 1 1 Nov 21, 2002 16:25:10.564\n!MESSAGE Could not load library: libcore_2_0_5.jnilib.  This library provides platform-specific optimizations for certain file-system operations.  This library is not present on all platforms, so this may not be an error.  The resources plugin will safely fall back to using java.io.File functionality.\n!SESSION Nov 21, 2002 16:27:33.503 ---------------------------------------------\njava.version\u003d1.3.1\njava.vendor\u003dApple Computer, Inc.\nBootLoader constants: OS\u003dmacosx, ARCH\u003dppc, WS\u003dcarbon, NL\u003den_US\nCommand-line arguments: -noupdate -consoleLog -showlocation -os macosx -ws carbon -install file:/Volumes/Mac9.2/eclipse_Nov15/Eclipse_2.0.app/Contents/Resources/Java/\n!ENTRY org.eclipse.core.resources 1 1 Nov 21, 2002 16:27:33.507\n!MESSAGE Could not load library: libcore_2_0_5.jnilib.  This library provides platform-specific optimizations for certain file-system operations.  This library is not present on all platforms, so this may not be an error.  The resources plugin will safely fall back to using java.io.File functionality.\n!SESSION Nov 21, 2002 16:32:53.29 ----------------------------------------------\njava.version\u003d1.3.1\njava.vendor\u003dApple Computer, Inc.\nBootLoader constants: OS\u003dmacosx, ARCH\u003dppc, WS\u003dcarbon, NL\u003den_US\nCommand-line arguments: -noupdate -consoleLog -showlocation -os macosx -ws carbon -install file:/Volumes/Mac9.2/eclipse_Nov15/Eclipse_2.0.app/Contents/Resources/Java/\n!ENTRY org.eclipse.core.resources 1 1 Nov 21, 2002 16:32:53.32\n!MESSAGE Could not load library: libcore_2_0_5.jnilib.  This library provides platform-specific optimizations for certain file-system operations.  This library is not present on all platforms, so this may not be an error.  The resources plugin will safely fall back to using java.io.File functionality.\n!SESSION Nov 26, 2002 09:57:31.977 ---------------------------------------------\njava.version\u003d1.3.1\njava.vendor\u003dApple Computer, Inc.\nBootLoader constants: OS\u003dmacosx, ARCH\u003dppc, WS\u003dcarbon, NL\u003den_US\nCommand-line arguments: -noupdate -consoleLog -showlocation -os macosx -ws carbon -install file:/Volumes/Mac9.2/eclipse_Nov15/Eclipse_2.0.app/Contents/Resources/Java/\n!ENTRY org.eclipse.core.resources 1 1 Nov 26, 2002 09:57:31.983\n!MESSAGE Could not load library: libcore_2_0_5.jnilib.  This library provides platform-specific optimizations for certain file-system operations.  This library is not present on all platforms, so this may not be an error.  The resources plugin will safely fall back to using java.io.File functionality.\n!SESSION Nov 26, 2002 10:02:15.186 ---------------------------------------------\njava.version\u003d1.3.1\njava.vendor\u003dApple Computer, Inc.\nBootLoader constants: OS\u003dmacosx, ARCH\u003dppc, WS\u003dcarbon, NL\u003den_US\nCommand-line arguments: -noupdate -consoleLog -showlocation -os macosx -ws carbon -install file:/Volumes/Mac9.2/eclipse_Nov15/Eclipse_2.0.app/Contents/Resources/Java/\n!ENTRY org.eclipse.core.resources 1 1 Nov 26, 2002 10:02:15.198\n!MESSAGE Could not load library: libcore_2_0_5.jnilib.  This library provides platform-specific optimizations for certain file-system operations.  This library is not present on all platforms, so this may not be an error.  The resources plugin will safely fall back to using java.io.File functionality.\n!SESSION Nov 26, 2002 11:06:22.587 ---------------------------------------------\njava.version\u003d1.3.1\njava.vendor\u003dApple Computer, Inc.\nBootLoader constants: OS\u003dmacosx, ARCH\u003dppc, WS\u003dcarbon, NL\u003den_US\nCommand-line arguments: -noupdate -consoleLog -showlocation -os macosx -ws carbon -install file:/Volumes/Mac9.2/eclipse_Nov15/Eclipse_2.0.app/Contents/Resources/Java/\n!ENTRY org.eclipse.core.resources 1 1 Nov 26, 2002 11:06:22.592\n!MESSAGE Could not load library: libcore_2_0_5.jnilib.  This library provides platform-specific optimizations for certain file-system operations.  This library is not present on all platforms, so this may not be an error.  The resources plugin will safely fall back to using java.io.File functionality.\n!SESSION Nov 26, 2002 12:20:55.50 ----------------------------------------------\njava.version\u003d1.3.1\njava.vendor\u003dApple Computer, Inc.\nBootLoader constants: OS\u003dmacosx, ARCH\u003dppc, WS\u003dcarbon, NL\u003den_US\nCommand-line arguments: -noupdate -consoleLog -showlocation -os macosx -ws carbon -install file:/Volumes/Mac9.2/eclipse_Nov15/Eclipse_2.0.app/Contents/Resources/Java/\n!ENTRY org.eclipse.core.resources 1 1 Nov 26, 2002 12:20:55.55\n!MESSAGE Could not load library: libcore_2_0_5.jnilib.  This library provides platform-specific optimizations for certain file-system operations.  This library is not present on all platforms, so this may not be an error.  The resources plugin will safely fall back to using java.io.File functionality.\n!SESSION Nov 26, 2002 13:41:04.376 ---------------------------------------------\njava.version\u003d1.3.1\njava.vendor\u003dApple Computer, Inc.\nBootLoader constants: OS\u003dmacosx, ARCH\u003dppc, WS\u003dcarbon, NL\u003den_US\nCommand-line arguments: -noupdate -consoleLog -showlocation -os macosx -ws carbon -install file:/Volumes/Mac9.2/eclipse_Nov15/Eclipse_2.0.app/Contents/Resources/Java/\n!ENTRY org.eclipse.core.resources 1 1 Nov 26, 2002 13:41:04.379\n!MESSAGE Could not load library: libcore_2_0_5.jnilib.  This library provides platform-specific optimizations for certain file-system operations.  This library is not present on all platforms, so this may not be an error.  The resources plugin will safely fall back to using java.io.File functionality.\n\n\u003d\u003d\u003d\u003d\u003d\u003d\u003d\u003d\u003d\u003d\u003d\u003d\u003d\u003d\u003d\u003d\u003d\u003d\u003d\u003d\u003d\u003d\u003d\u003d\u003d\u003d\u003d\u003d\u003d\u003d\u003d\u003d\u003d\u003d\u003d\u003d\u003d\u003d\u003d\u003d\u003d\u003d\u003d\u003d\u003d\u003d\u003d\u003d\u003d\u003d\u003d\u003d\u003d\u003d\u003d\u003d\u003d\u003d",
    "Veronika to investigate and advise\n\nNote. The stack trace is similar to the one posted on PR27176.\n\nAlan, is the crash reproduceable? Which build are you using?\n\n",
    "This was with a Nov 15 build of Eclipse: v. 2.1; build id: 200211151436",
    "I will try this in the carbon_work stream.",
    "Not completely clear, but this bug may be due to a shortage of memory (too little disc space for virtual memory to operate properly) on the testing machine.",
    "Works in I20030128"
  ],
  "commentCreationDates": [
    "2002-11-26T20:40:15+01:00",
    "2002-11-27T15:13:26+01:00",
    "2002-11-27T18:52:48+01:00",
    "2002-11-27T19:53:34+01:00",
    "2002-11-28T18:13:05+01:00",
    "2003-01-28T20:03:15+01:00"
  ],
  "traces": [
    {
      "exceptionType": "org.eclipse.swt.SWTException",
      "message": "Widget is disposed",
      "elements": [
        {
          "method": "org.eclipse.swt.SWT.error",
          "source": "SWT.java:2180"
        },
        {
          "method": "org.eclipse.swt.SWT.error",
          "source": "SWT.java:2110"
        },
        {
          "method": "org.eclipse.swt.widgets.Widget.error",
          "source": "Widget.java:299"
        },
        {
          "method": "org.eclipse.swt.widgets.Menu.getDisplay",
          "source": "Menu.java:335"
        },
        {
          "method": "org.eclipse.swt.widgets.Widget.isValidThread",
          "source": "Widget.java:458"
        },
        {
          "method": "org.eclipse.swt.widgets.Widget.checkWidget",
          "source": "Widget.java:229"
        },
        {
          "method": "org.eclipse.swt.widgets.Menu.getItems",
          "source": "Menu.java:415"
        },
        {
          "method": "org.eclipse.swt.widgets.Menu.releaseWidget",
          "source": "Menu.java:688"
        },
        {
          "method": "org.eclipse.swt.widgets.MenuItem.releaseWidget",
          "source": "MenuItem.java:402"
        },
        {
          "method": "org.eclipse.swt.widgets.Menu.releaseWidget",
          "source": "Menu.java:692"
        },
        {
          "method": "org.eclipse.swt.widgets.MenuItem.releaseWidget",
          "source": "MenuItem.java:402"
        },
        {
          "method": "org.eclipse.swt.widgets.Menu.releaseWidget",
          "source": "Menu.java:692"
        },
        {
          "method": "org.eclipse.swt.widgets.Decorations.releaseWidget",
          "source": "Decorations.java:393"
        },
        {
          "method": "org.eclipse.swt.widgets.Shell.releaseWidget",
          "source": "Shell.java:1213"
        },
        {
          "method": "org.eclipse.swt.widgets.Widget.dispose",
          "source": "Widget.java:289"
        },
        {
          "method": "org.eclipse.swt.widgets.Shell.dispose",
          "source": "Shell.java:725"
        },
        {
          "method": "org.eclipse.jface.window.Window.close",
          "source": "Window.java:223"
        },
        {
          "method": "org.eclipse.jface.window.ApplicationWindow.close",
          "source": "ApplicationWindow.java:186"
        },
        {
          "method": "org.eclipse.ui.internal.WorkbenchWindow.hardClose",
          "source": "WorkbenchWindow.java:908"
        },
        {
          "method": "org.eclipse.ui.internal.WorkbenchWindow.busyClose",
          "source": "WorkbenchWindow.java:337"
        },
        {
          "method": "org.eclipse.ui.internal.WorkbenchWindow.access$3",
          "source": "WorkbenchWindow.java:326"
        },
        {
          "method": "org.eclipse.ui.internal.WorkbenchWindow$2.run",
          "source": "WorkbenchWindow.java:382"
        },
        {
          "method": "org.eclipse.swt.custom.BusyIndicator.showWhile",
          "source": "BusyIndicator.java:65"
        },
        {
          "method": "org.eclipse.ui.internal.WorkbenchWindow.close",
          "source": "WorkbenchWindow.java:380"
        },
        {
          "method": "org.eclipse.jface.window.WindowManager.close",
          "source": "WindowManager.java:102"
        },
        {
          "method": "org.eclipse.ui.internal.Workbench$3.run",
          "source": "Workbench.java:253"
        },
        {
          "method": "org.eclipse.core.internal.runtime.InternalPlatform.run",
          "source": "InternalPlatform.java:839"
        },
        {
          "method": "org.eclipse.core.runtime.Platform.run",
          "source": "Platform.java:413"
        },
        {
          "method": "org.eclipse.ui.internal.Workbench.busyClose",
          "source": "Workbench.java:250"
        },
        {
          "method": "org.eclipse.ui.internal.Workbench.access$5",
          "source": "Workbench.java:207"
        },
        {
          "method": "org.eclipse.ui.internal.Workbench$5.run",
          "source": "Workbench.java:383"
        },
        {
          "method": "org.eclipse.swt.custom.BusyIndicator.showWhile",
          "source": "BusyIndicator.java:65"
        },
        {
          "method": "org.eclipse.ui.internal.Workbench.close",
          "source": "Workbench.java:381"
        },
        {
          "method": "org.eclipse.ui.internal.Workbench.close",
          "source": "Workbench.java:373"
        },
        {
          "method": "org.eclipse.ui.internal.Workbench.close",
          "source": "Workbench.java:367"
        },
        {
          "method": "org.eclipse.ui.internal.Workbench$13.handleEvent",
          "source": "Workbench.java:1405"
        },
        {
          "method": "org.eclipse.swt.widgets.EventTable.sendEvent",
          "source": "EventTable.java:77"
        },
        {
          "method": "org.eclipse.swt.widgets.Display.sendEvent",
          "source": "Display.java:1301"
        },
        {
          "method": "org.eclipse.swt.widgets.Display.close",
          "source": "Display.java:338"
        },
        {
          "method": "org.eclipse.swt.widgets.Display.handleApplicationCallback",
          "source": "Display.java:2065"
        },
        {
          "method": "org.eclipse.swt.internal.carbon.OS.SendEventToEventTarget",
          "source": "Native Method"
        },
        {
          "method": "org.eclipse.swt.widgets.Display.readAndDispatch",
          "source": "Display.java:1118"
        },
        {
          "method": "org.eclipse.ui.internal.Workbench.runEventLoop",
          "source": "Workbench.java:1435"
        },
        {
          "method": "org.eclipse.ui.internal.Workbench.run",
          "source": "Workbench.java:1418"
        },
        {
          "method": "org.eclipse.core.internal.boot.InternalBootLoader.run",
          "source": "InternalBootLoader.java:831"
        },
        {
          "method": "org.eclipse.core.boot.BootLoader.run",
          "source": "BootLoader.java:462"
        },
        {
          "method": "java.lang.reflect.Method.invoke",
          "source": "Native Method"
        },
        {
          "method": "org.eclipse.core.launcher.Main.basicRun",
          "source": "Main.java:247"
        },
        {
          "method": "org.eclipse.core.launcher.Main.run",
          "source": "Main.java:703"
        },
        {
          "method": "org.eclipse.core.launcher.Main.main",
          "source": "Main.java:539"
        },
        {
          "method": "java.lang.reflect.Method.invoke",
          "source": "Native Method"
        },
        {
          "method": "com.apple.buckyball.app.LaunchRunner.run",
          "source": "LaunchRunner.java:82"
        },
        {
          "method": "com.apple.buckyball.app.LaunchRunner.callMain",
          "source": "LaunchRunner.java:44"
        },
        {
          "method": "com.apple.buckyball.app.CarbonLibApp.launch",
          "source": "CarbonLibApp.java:67"
        }
      ],
      "number": 0,
      "commentIndex": 0,
      "bugId": "27183",
      "date": "2002-11-26T20:40:15+01:00",
      "product": "Platform",
      "component": "SWT",
      "severity": "normal"
    }
  ],
  "groupId": "27183",
  "bugId": "27183",
  "date": "2002-11-26T20:40:15+01:00",
  "product": "Platform",
  "component": "SWT",
  "severity": "normal"
}