{
  "comments": [
    "Build 20021126 + jdtcore patch\n\nPerforming a code assist at line 560 column 67 in the attached cu gave me the \nfollowing ClassCastException:\njava.lang.ClassCastException: \norg.eclipse.jdt.internal.compiler.ast.EqualExpression\n        at org.eclipse.jdt.internal.compiler.ast.Assignment.\u003cinit\u003e\n(Assignment.java:28)\n        at \norg.eclipse.jdt.internal.codeassist.complete.CompletionParser.buildMoreCompletio\nnContext(CompletionParser.java:375)\n        at \norg.eclipse.jdt.internal.codeassist.complete.CompletionParser.attachOrphanComple\ntionNode(CompletionParser.java:171)\n        at \norg.eclipse.jdt.internal.codeassist.complete.CompletionParser.updateRecoveryStat\ne(CompletionParser.java:1672)\n        at org.eclipse.jdt.internal.compiler.parser.Parser.resumeOnSyntaxError\n(Parser.java:7469)\n        at org.eclipse.jdt.internal.compiler.parser.Parser.parse\n(Parser.java:6806)\n        at \norg.eclipse.jdt.internal.codeassist.impl.AssistParser.parseBlockStatements\n(AssistParser.java:856)\n        at \norg.eclipse.jdt.internal.codeassist.impl.AssistParser.parseBlockStatements\n(AssistParser.java:770)\n        at org.eclipse.jdt.internal.codeassist.impl.Engine.parseMethod\n(Engine.java:166)\n        at org.eclipse.jdt.internal.codeassist.impl.Engine.parseMethod\n(Engine.java:135)\n        at org.eclipse.jdt.internal.codeassist.CompletionEngine.complete\n(CompletionEngine.java:839)\n        at org.eclipse.jdt.internal.core.Openable.codeComplete\n(Openable.java:124)\n        at org.eclipse.jdt.internal.core.CompilationUnit.codeComplete\n(CompilationUnit.java:104)\n        at \norg.eclipse.jdt.internal.ui.text.java.JavaCompletionProcessor.internalComputeCom\npletionProposals(JavaCompletionProcessor.java:342)\n        at \norg.eclipse.jdt.internal.ui.text.java.JavaCompletionProcessor.computeCompletionP\nroposals(JavaCompletionProcessor.java:300)\n        at \norg.eclipse.jface.text.contentassist.ContentAssistant.computeCompletionProposals\n(ContentAssistant.java:1279)\n        at \norg.eclipse.jface.text.contentassist.CompletionProposalPopup.computeProposals\n(CompletionProposalPopup.java:178)\n        at org.eclipse.jface.text.contentassist.CompletionProposalPopup.access$7\n(CompletionProposalPopup.java:177)\n        at org.eclipse.jface.text.contentassist.CompletionProposalPopup$3.run\n(CompletionProposalPopup.java:139)\n        at org.eclipse.swt.custom.BusyIndicator.showWhile(BusyIndicator.java:65)\n        at \norg.eclipse.jface.text.contentassist.CompletionProposalPopup.showProposals\n(CompletionProposalPopup.java:134)\n        at \norg.eclipse.jface.text.contentassist.ContentAssistant.showPossibleCompletions\n(ContentAssistant.java:1199)\n        at \norg.eclipse.jdt.internal.ui.javaeditor.CompilationUnitEditor$AdaptedSourceViewer\n.doOperation(CompilationUnitEditor.java:277)\n        at org.eclipse.ui.texteditor.ContentAssistAction$1.run\n(ContentAssistAction.java:84)\n        at org.eclipse.swt.custom.BusyIndicator.showWhile(BusyIndicator.java:65)\n        at org.eclipse.ui.texteditor.ContentAssistAction.run\n(ContentAssistAction.java:82)\n        at org.eclipse.jface.action.Action.runWithEvent(Action.java:769)\n        at org.eclipse.ui.internal.WWinKeyBindingService.invoke\n(WWinKeyBindingService.java:139)\n        at org.eclipse.ui.internal.WWinKeyBindingService.pressed\n(WWinKeyBindingService.java:120)\n        at org.eclipse.ui.internal.WWinKeyBindingService$6.widgetSelected\n(WWinKeyBindingService.java:376)\n        at org.eclipse.ui.internal.AcceleratorMenu$2.handleEvent\n(AcceleratorMenu.java:55)\n        at org.eclipse.swt.widgets.EventTable.sendEvent(EventTable.java:77)\n        at org.eclipse.swt.widgets.Widget.sendEvent(Widget.java:825)\n        at org.eclipse.swt.widgets.Display.runDeferredEvents(Display.java:1692)\n        at org.eclipse.swt.widgets.Display.readAndDispatch(Display.java:1410)\n        at org.eclipse.ui.internal.Workbench.runEventLoop(Workbench.java:1370)\n        at org.eclipse.ui.internal.Workbench.run(Workbench.java:1353)\n        at org.eclipse.core.internal.boot.InternalBootLoader.run\n(InternalBootLoader.java:841)\n        at org.eclipse.core.boot.BootLoader.run(BootLoader.java:462)\n        at sun.reflect.NativeMethodAccessorImpl.invoke0(Native Method)\n        at sun.reflect.NativeMethodAccessorImpl.invoke\n(NativeMethodAccessorImpl.java:39)\n        at sun.reflect.DelegatingMethodAccessorImpl.invoke\n(DelegatingMethodAccessorImpl.java:25)\n        at java.lang.reflect.Method.invoke(Method.java:324)\n        at org.eclipse.core.launcher.Main.basicRun(Main.java:247)\n        at org.eclipse.core.launcher.Main.run(Main.java:703)\n        at org.eclipse.core.launcher.Main.main(Main.java:539)\norg.eclipse.jdt.internal.compiler.ast.EqualExpression",
    "Created an attachment (id\u003d2566)\nDeltaProcessor.java\n",
    "Simple test case\n\n1) Create X.java\npublic class X {\n   void foo() {\n      boolean a, b, c;\n      c \u003d a \u003d\u003d b ? zzz\u003ccursor\u003e\n   }\n}\n2) Do ctrl + space at cursor location",
    "Fixed.",
    "Verified."
  ],
  "commentCreationDates": [
    "2002-11-28T15:12:05+01:00",
    "2002-11-28T15:12:55+01:00",
    "2002-11-29T10:21:18+01:00",
    "2002-11-29T12:33:03+01:00",
    "2002-12-17T12:13:12+01:00"
  ],
  "traces": [
    {
      "exceptionType": "java.lang.ClassCastException",
      "message": "org.eclipse.jdt.internal.compiler.ast.EqualExpression",
      "elements": [
        {
          "method": "org.eclipse.jdt.internal.compiler.ast.Assignment.\u003cinit\u003e",
          "source": "Assignment.java:28"
        },
        {
          "method": "org.eclipse.jdt.internal.codeassist.complete.CompletionParser.buildMoreCompletionContext",
          "source": "CompletionParser.java:375"
        },
        {
          "method": "org.eclipse.jdt.internal.codeassist.complete.CompletionParser.attachOrphanCompletionNode",
          "source": "CompletionParser.java:171"
        },
        {
          "method": "org.eclipse.jdt.internal.codeassist.complete.CompletionParser.updateRecoveryState",
          "source": "CompletionParser.java:1672"
        },
        {
          "method": "org.eclipse.jdt.internal.compiler.parser.Parser.resumeOnSyntaxError",
          "source": "Parser.java:7469"
        },
        {
          "method": "org.eclipse.jdt.internal.compiler.parser.Parser.parse",
          "source": "Parser.java:6806"
        },
        {
          "method": "org.eclipse.jdt.internal.codeassist.impl.AssistParser.parseBlockStatements",
          "source": "AssistParser.java:856"
        },
        {
          "method": "org.eclipse.jdt.internal.codeassist.impl.AssistParser.parseBlockStatements",
          "source": "AssistParser.java:770"
        },
        {
          "method": "org.eclipse.jdt.internal.codeassist.impl.Engine.parseMethod",
          "source": "Engine.java:166"
        },
        {
          "method": "org.eclipse.jdt.internal.codeassist.impl.Engine.parseMethod",
          "source": "Engine.java:135"
        },
        {
          "method": "org.eclipse.jdt.internal.codeassist.CompletionEngine.complete",
          "source": "CompletionEngine.java:839"
        },
        {
          "method": "org.eclipse.jdt.internal.core.Openable.codeComplete",
          "source": "Openable.java:124"
        },
        {
          "method": "org.eclipse.jdt.internal.core.CompilationUnit.codeComplete",
          "source": "CompilationUnit.java:104"
        },
        {
          "method": "org.eclipse.jdt.internal.ui.text.java.JavaCompletionProcessor.internalComputeCompletionProposals",
          "source": "JavaCompletionProcessor.java:342"
        },
        {
          "method": "org.eclipse.jdt.internal.ui.text.java.JavaCompletionProcessor.computeCompletionProposals",
          "source": "JavaCompletionProcessor.java:300"
        },
        {
          "method": "org.eclipse.jface.text.contentassist.ContentAssistant.computeCompletionProposals",
          "source": "ContentAssistant.java:1279"
        },
        {
          "method": "org.eclipse.jface.text.contentassist.CompletionProposalPopup.computeProposals",
          "source": "CompletionProposalPopup.java:178"
        },
        {
          "method": "org.eclipse.jface.text.contentassist.CompletionProposalPopup.access$7",
          "source": "CompletionProposalPopup.java:177"
        },
        {
          "method": "org.eclipse.jface.text.contentassist.CompletionProposalPopup$3.run",
          "source": "CompletionProposalPopup.java:139"
        },
        {
          "method": "org.eclipse.swt.custom.BusyIndicator.showWhile",
          "source": "BusyIndicator.java:65"
        },
        {
          "method": "org.eclipse.jface.text.contentassist.CompletionProposalPopup.showProposals",
          "source": "CompletionProposalPopup.java:134"
        },
        {
          "method": "org.eclipse.jface.text.contentassist.ContentAssistant.showPossibleCompletions",
          "source": "ContentAssistant.java:1199"
        },
        {
          "method": "org.eclipse.jdt.internal.ui.javaeditor.CompilationUnitEditor$AdaptedSourceViewer.doOperation",
          "source": "CompilationUnitEditor.java:277"
        },
        {
          "method": "org.eclipse.ui.texteditor.ContentAssistAction$1.run",
          "source": "ContentAssistAction.java:84"
        },
        {
          "method": "org.eclipse.swt.custom.BusyIndicator.showWhile",
          "source": "BusyIndicator.java:65"
        },
        {
          "method": "org.eclipse.ui.texteditor.ContentAssistAction.run",
          "source": "ContentAssistAction.java:82"
        },
        {
          "method": "org.eclipse.jface.action.Action.runWithEvent",
          "source": "Action.java:769"
        },
        {
          "method": "org.eclipse.ui.internal.WWinKeyBindingService.invoke",
          "source": "WWinKeyBindingService.java:139"
        },
        {
          "method": "org.eclipse.ui.internal.WWinKeyBindingService.pressed",
          "source": "WWinKeyBindingService.java:120"
        },
        {
          "method": "org.eclipse.ui.internal.WWinKeyBindingService$6.widgetSelected",
          "source": "WWinKeyBindingService.java:376"
        },
        {
          "method": "org.eclipse.ui.internal.AcceleratorMenu$2.handleEvent",
          "source": "AcceleratorMenu.java:55"
        },
        {
          "method": "org.eclipse.swt.widgets.EventTable.sendEvent",
          "source": "EventTable.java:77"
        },
        {
          "method": "org.eclipse.swt.widgets.Widget.sendEvent",
          "source": "Widget.java:825"
        },
        {
          "method": "org.eclipse.swt.widgets.Display.runDeferredEvents",
          "source": "Display.java:1692"
        },
        {
          "method": "org.eclipse.swt.widgets.Display.readAndDispatch",
          "source": "Display.java:1410"
        },
        {
          "method": "org.eclipse.ui.internal.Workbench.runEventLoop",
          "source": "Workbench.java:1370"
        },
        {
          "method": "org.eclipse.ui.internal.Workbench.run",
          "source": "Workbench.java:1353"
        },
        {
          "method": "org.eclipse.core.internal.boot.InternalBootLoader.run",
          "source": "InternalBootLoader.java:841"
        },
        {
          "method": "org.eclipse.core.boot.BootLoader.run",
          "source": "BootLoader.java:462"
        },
        {
          "method": "sun.reflect.NativeMethodAccessorImpl.invoke0",
          "source": "Native Method"
        },
        {
          "method": "sun.reflect.NativeMethodAccessorImpl.invoke",
          "source": "NativeMethodAccessorImpl.java:39"
        },
        {
          "method": "sun.reflect.DelegatingMethodAccessorImpl.invoke",
          "source": "DelegatingMethodAccessorImpl.java:25"
        },
        {
          "method": "java.lang.reflect.Method.invoke",
          "source": "Method.java:324"
        },
        {
          "method": "org.eclipse.core.launcher.Main.basicRun",
          "source": "Main.java:247"
        },
        {
          "method": "org.eclipse.core.launcher.Main.run",
          "source": "Main.java:703"
        },
        {
          "method": "org.eclipse.core.launcher.Main.main",
          "source": "Main.java:539"
        }
      ],
      "number": 0,
      "commentIndex": 0,
      "bugId": "27322",
      "date": "2002-11-28T15:12:05+01:00",
      "product": "JDT",
      "component": "Core",
      "severity": "major"
    }
  ],
  "groupId": "27322",
  "bugId": "27322",
  "date": "2002-11-28T15:12:05+01:00",
  "product": "JDT",
  "component": "Core",
  "severity": "major"
}