{
  "comments": [
    "Build 20021204\nLinux\n\nI launched eclipse, opened some files, closed them and launched a runtime workbench.\n\nAfter that, I had this stack trace in the console\n\njava.lang.ClassCastException: org.eclipse.core.internal.resources.ResourceInfo\n        at\norg.eclipse.core.internal.resources.Project.internalGetDescription(Project.java:504)\n        at\norg.eclipse.core.internal.localstore.FileSystemResourceManager.locationFor(FileSystemResourceManager.java:349)\n        at\norg.eclipse.core.internal.resources.Resource.getLocation(Resource.java:726)\n        at\norg.eclipse.core.internal.localstore.UnifiedTree.setRoot(UnifiedTree.java:328)\n        at\norg.eclipse.core.internal.localstore.UnifiedTree.\u003cinit\u003e(UnifiedTree.java:54)\n        at\norg.eclipse.core.internal.localstore.FileSystemResourceManager.refreshResource(FileSystemResourceManager.java:499)\n        at\norg.eclipse.core.internal.localstore.FileSystemResourceManager.refresh(FileSystemResourceManager.java:488)\n        at\norg.eclipse.core.internal.resources.Resource.refreshLocal(Resource.java:1082)\n        at\ncom.example.autorefresh.internal.RefreshManager.refreshDepthOneResources(RefreshManager.java:367)\n        at\ncom.example.autorefresh.internal.RefreshManager.refresh0(RefreshManager.java:270)\n        at\ncom.example.autorefresh.internal.RefreshManager.access$1(RefreshManager.java:262)\n        at\ncom.example.autorefresh.internal.RefreshManager$2.run(RefreshManager.java:237)\n        at org.eclipse.core.internal.resources.Workspace.run(Workspace.java:1578)\n        at\ncom.example.autorefresh.internal.RefreshManager.refresh(RefreshManager.java:248)\n        at\ncom.example.autorefresh.internal.RefreshManager.refresh(RefreshManager.java:205)\n        at\ncom.example.autorefresh.internal.RefreshManager.run(RefreshManager.java:181)\n        at java.lang.Thread.run(Thread.java:536)",
    "I have not been able to reproduce this bug.",
    "*** Bug 27145 has been marked as a duplicate of this bug. ***"
  ],
  "commentCreationDates": [
    "2002-12-06T16:31:40+01:00",
    "2003-02-07T22:43:40+01:00",
    "2003-05-15T19:39:59+02:00"
  ],
  "traces": [
    {
      "exceptionType": "java.lang.ClassCastException",
      "message": "org.eclipse.core.internal.resources.ResourceInfo",
      "elements": [
        {
          "method": "org.eclipse.core.internal.resources.Project.internalGetDescription",
          "source": "Project.java:504"
        },
        {
          "method": "org.eclipse.core.internal.localstore.FileSystemResourceManager.locationFor",
          "source": "FileSystemResourceManager.java:349"
        },
        {
          "method": "org.eclipse.core.internal.resources.Resource.getLocation",
          "source": "Resource.java:726"
        },
        {
          "method": "org.eclipse.core.internal.localstore.UnifiedTree.setRoot",
          "source": "UnifiedTree.java:328"
        },
        {
          "method": "org.eclipse.core.internal.localstore.UnifiedTree.\u003cinit\u003e",
          "source": "UnifiedTree.java:54"
        },
        {
          "method": "org.eclipse.core.internal.localstore.FileSystemResourceManager.refreshResource",
          "source": "FileSystemResourceManager.java:499"
        },
        {
          "method": "org.eclipse.core.internal.localstore.FileSystemResourceManager.refresh",
          "source": "FileSystemResourceManager.java:488"
        },
        {
          "method": "org.eclipse.core.internal.resources.Resource.refreshLocal",
          "source": "Resource.java:1082"
        },
        {
          "method": "com.example.autorefresh.internal.RefreshManager.refreshDepthOneResources",
          "source": "RefreshManager.java:367"
        },
        {
          "method": "com.example.autorefresh.internal.RefreshManager.refresh0",
          "source": "RefreshManager.java:270"
        },
        {
          "method": "com.example.autorefresh.internal.RefreshManager.access$1",
          "source": "RefreshManager.java:262"
        },
        {
          "method": "com.example.autorefresh.internal.RefreshManager$2.run",
          "source": "RefreshManager.java:237"
        },
        {
          "method": "org.eclipse.core.internal.resources.Workspace.run",
          "source": "Workspace.java:1578"
        },
        {
          "method": "com.example.autorefresh.internal.RefreshManager.refresh",
          "source": "RefreshManager.java:248"
        },
        {
          "method": "com.example.autorefresh.internal.RefreshManager.refresh",
          "source": "RefreshManager.java:205"
        },
        {
          "method": "com.example.autorefresh.internal.RefreshManager.run",
          "source": "RefreshManager.java:181"
        },
        {
          "method": "java.lang.Thread.run",
          "source": "Thread.java:536"
        }
      ],
      "number": 0,
      "commentIndex": 0,
      "bugId": "27844",
      "date": "2002-12-06T16:31:40+01:00",
      "product": "Platform",
      "component": "Resources",
      "severity": "normal"
    }
  ],
  "groupId": "27844",
  "bugId": "27844",
  "date": "2002-12-06T16:31:40+01:00",
  "product": "Platform",
  "component": "Resources",
  "severity": "normal"
}