{
  "comments": [
    "Tried the autorefresh on our Japanese box, and got the following error when I \ntried to create a simple project with the name eclipse \u0026#12408;\u0026#12398;\u0026#12471;\u0026#12519;\u0026#12540;\u0026#12488;\u0026#12459;\u0026#12483;\u0026#12488;\n\nStartup: using configuration file:c:\\AutorefreshTest\\.metadata\\.config\\platform.\ncfg\nBoot URL: file:C:/eclipse20021210/eclipse/plugins/org.eclipse.core.boot_2.1.0/bo\not.jar\nStartup: splash path \u003d C:\\eclipse20021210\\eclipse\\plugins\\org.eclipse.platform_2\n.1.0\\splash.bmp\nWorkspace location:\n   c:\\AutorefreshTest\nDebug-Options:\n    file:C:/eclipse20021210/eclipse/.options\nInstall URL:\n    file:C:/eclipse20021210/eclipse/\nStartup Monitor Manager\nStarting Refresh Manager\nRefreshed at 1039743998420\nRefreshed at 1039744008424\nRefreshed at 1039744018428\nRefreshed at 1039744028433\nWin32 Monitor (21403224): creating handle for c:\\AutorefreshTest\\eclipse ?\u0026#9555;?\u0026#9568;?V?\n??[?g?J?b?g\nRefreshed at 1039744038437\nAn error occured:\nWin32 Monitor (21403224): could not create handle for \"c:\\AutorefreshTest\\eclips\ne ?\u0026#9555;?\u0026#9568;?V???[?g?J?b?g\".  Error: 2\njava.lang.Exception\n        at com.example.autorefresh.win32.internal.Win32Monitor.addPath(Win32Moni\ntor.java:108)\n        at com.example.autorefresh.win32.internal.MonitorFactory.createMonitor(M\nonitorFactory.java:36)\n        at com.example.autorefresh.internal.MonitorManager.monitor(MonitorManage\nr.java:63)\n        at com.example.autorefresh.internal.MonitorManager.access$0(MonitorManag\ner.java:54)\n        at com.example.autorefresh.internal.MonitorManager$2.visit(MonitorManage\nr.java:199)\n        at org.eclipse.core.internal.events.ResourceDelta.accept(ResourceDelta.j\nava:71)\n        at org.eclipse.core.internal.events.ResourceDelta.accept(ResourceDelta.j\nava:79)\n        at org.eclipse.core.internal.events.ResourceDelta.accept(ResourceDelta.j\nava:52)\n        at com.example.autorefresh.internal.MonitorManager$1.resourceChanged(Mon\nitorManager.java:233)\n        at org.eclipse.core.internal.events.NotificationManager$1.run(Notificati\nonManager.java:129)\n        at org.eclipse.core.internal.runtime.InternalPlatform.run(InternalPlatfo\nrm.java:850)\n        at org.eclipse.core.runtime.Platform.run(Platform.java:413)\n        at org.eclipse.core.internal.events.NotificationManager.notify(Notificat\nionManager.java:144)\n        at org.eclipse.core.internal.events.NotificationManager.broadcastChanges\n(NotificationManager.java:67)\n        at org.eclipse.core.internal.resources.Workspace.broadcastChanges(Worksp\nace.java:141)\n        at org.eclipse.core.internal.resources.Workspace.endOperation(Workspace.\njava:882)\n        at org.eclipse.core.internal.resources.Workspace.run(Workspace.java:1593\n)\n        at org.eclipse.ui.actions.WorkspaceModifyOperation.run(WorkspaceModifyOp\neration.java:79)\n        at org.eclipse.jface.operation.ModalContext$ModalContextThread.run(Modal\nContext.java:95)\nAdded monitor (com.example.autorefresh.internal.PollingMonitor@89dd) for P/eclip\nse ?\u0026#9555;?\u0026#9568;?V???[?g?J?b?g\nStarted polling thread.",
    "New support has exposed a bug in the core refresh support.",
    "Can this be closed with the new win32 dll that was released in M5?",
    "Just finished verifying this today."
  ],
  "commentCreationDates": [
    "2002-12-13T01:33:01+01:00",
    "2003-01-15T22:41:45+01:00",
    "2003-02-07T22:23:08+01:00",
    "2003-02-07T22:32:55+01:00"
  ],
  "traces": [
    {
      "exceptionType": "java.lang.Exception",
      "elements": [
        {
          "method": "com.example.autorefresh.win32.internal.Win32Monitor.addPath",
          "source": "Win32Moni tor.java:108"
        },
        {
          "method": "com.example.autorefresh.win32.internal.MonitorFactory.createMonitor",
          "source": "M onitorFactory.java:36"
        },
        {
          "method": "com.example.autorefresh.internal.MonitorManager.monitor",
          "source": "MonitorManage r.java:63"
        },
        {
          "method": "com.example.autorefresh.internal.MonitorManager.access$0",
          "source": "MonitorManag er.java:54"
        },
        {
          "method": "com.example.autorefresh.internal.MonitorManager$2.visit",
          "source": "MonitorManage r.java:199"
        },
        {
          "method": "org.eclipse.core.internal.events.ResourceDelta.accept",
          "source": "ResourceDelta.j ava:71"
        },
        {
          "method": "org.eclipse.core.internal.events.ResourceDelta.accept",
          "source": "ResourceDelta.j ava:79"
        },
        {
          "method": "org.eclipse.core.internal.events.ResourceDelta.accept",
          "source": "ResourceDelta.j ava:52"
        },
        {
          "method": "com.example.autorefresh.internal.MonitorManager$1.resourceChanged",
          "source": "Mon itorManager.java:233"
        },
        {
          "method": "org.eclipse.core.internal.events.NotificationManager$1.run",
          "source": "Notificati onManager.java:129"
        },
        {
          "method": "org.eclipse.core.internal.runtime.InternalPlatform.run",
          "source": "InternalPlatfo rm.java:850"
        },
        {
          "method": "org.eclipse.core.runtime.Platform.run",
          "source": "Platform.java:413"
        },
        {
          "method": "org.eclipse.core.internal.events.NotificationManager.notify",
          "source": "Notificat ionManager.java:144"
        },
        {
          "method": "org.eclipse.core.internal.events.NotificationManager.broadcastChanges",
          "source": "NotificationManager.java:67"
        },
        {
          "method": "org.eclipse.core.internal.resources.Workspace.broadcastChanges",
          "source": "Worksp ace.java:141"
        },
        {
          "method": "org.eclipse.core.internal.resources.Workspace.endOperation",
          "source": "Workspace. java:882"
        },
        {
          "method": "org.eclipse.core.internal.resources.Workspace.run",
          "source": "Workspace.java:1593 "
        },
        {
          "method": "org.eclipse.ui.actions.WorkspaceModifyOperation.run",
          "source": "WorkspaceModifyOp eration.java:79"
        },
        {
          "method": "org.eclipse.jface.operation.ModalContext$ModalContextThread.run",
          "source": "Modal Context.java:95"
        }
      ],
      "number": 0,
      "commentIndex": 0,
      "bugId": "28233",
      "date": "2002-12-13T01:33:01+01:00",
      "product": "Platform",
      "component": "Resources",
      "severity": "normal"
    }
  ],
  "groupId": "28233",
  "bugId": "28233",
  "date": "2002-12-13T01:33:01+01:00",
  "product": "Platform",
  "component": "Resources",
  "severity": "normal"
}