{
  "comments": [
    "Build 20021210 + org.eclipse.pde.junit_2.1.1\n\nI got the following NPE launching a JUnit test under Debug from the Java \nperspective. Note that I have a separate Debug window that was minimized.\n\nIf I restore the Debug window, the NPE doesn\u0027t occur.\n\n!ENTRY org.eclipse.ui 4 4 Dec 13, 2002 15:20:00.228\n!MESSAGE Unhandled exception caught in event loop.\nUnhandled exception caught in event loop.\nReason:\n!ENTRY org.eclipse.ui 4 0 Dec 13, 2002 15:20:00.244\n!MESSAGE Failed to execute runnable (java.lang.NullPointerException)\n!STACK 0\norg.eclipse.swt.SWTException: Failed to execute runnable \n(java.lang.NullPointerException)\n        at org.eclipse.swt.SWT.error(SWT.java:2180)\n        at org.eclipse.swt.widgets.Synchronizer.runAsyncMessages\n(Synchronizer.java:97)\n        at org.eclipse.swt.widgets.Display.runAsyncMessages(Display.java:1669)\n        at org.eclipse.swt.widgets.Display.readAndDispatch(Display.java:1414)\n        at org.eclipse.jface.operation.ModalContext$ModalContextThread.block\n(ModalContext.java:130)\n        at org.eclipse.jface.operation.ModalContext.run(ModalContext.java:255)\n        at org.eclipse.jface.dialogs.ProgressMonitorDialog.run\n(ProgressMonitorDialog.java:351)\n        at org.eclipse.debug.ui.DebugUITools.launch(DebugUITools.java:387)\n        at org.eclipse.debug.ui.actions.LaunchAction.run(LaunchAction.java:57)\n        at org.eclipse.jface.action.Action.runWithEvent(Action.java:769)\n        at org.eclipse.jface.action.ActionContributionItem.handleWidgetSelection\n(ActionContributionItem.java:411)\n        at org.eclipse.jface.action.ActionContributionItem.handleWidgetEvent\n(ActionContributionItem.java:365)\n        at org.eclipse.jface.action.ActionContributionItem.access$0\n(ActionContributionItem.java:356)\n        at \norg.eclipse.jface.action.ActionContributionItem$ActionListener.handleEvent\n(ActionContributionItem.java:48)\n        at org.eclipse.swt.widgets.EventTable.sendEvent(EventTable.java:77)\n        at org.eclipse.swt.widgets.Widget.sendEvent(Widget.java:825)\n        at org.eclipse.swt.widgets.Display.runDeferredEvents(Display.java:1692)\n        at org.eclipse.swt.widgets.Display.readAndDispatch(Display.java:1410)\n        at org.eclipse.ui.internal.Workbench.runEventLoop(Workbench.java:1403)\n        at org.eclipse.ui.internal.Workbench.run(Workbench.java:1386)\n        at org.eclipse.core.internal.boot.InternalBootLoader.run\n(InternalBootLoader.java:845)\n        at org.eclipse.core.boot.BootLoader.run(BootLoader.java:462)\n        at sun.reflect.NativeMethodAccessorImpl.invoke0(Native Method)\n        at sun.reflect.NativeMethodAccessorImpl.invoke\n(NativeMethodAccessorImpl.java:39)\n        at sun.reflect.DelegatingMethodAccessorImpl.invoke\n(DelegatingMethodAccessorImpl.java:25)\n        at java.lang.reflect.Method.invoke(Method.java:324)\n        at org.eclipse.core.launcher.Main.basicRun(Main.java:247)\n        at org.eclipse.core.launcher.Main.run(Main.java:703)\n        at org.eclipse.core.launcher.Main.main(Main.java:539)\nFailed to execute runnable (java.lang.NullPointerException)\n!ENTRY org.eclipse.ui 4 4 Dec 13, 2002 15:20:00.259\n!MESSAGE\n*** Stack trace of contained exception ***\n\n*** Stack trace of contained exception ***\nReason:\n!ENTRY org.eclipse.ui 4 0 Dec 13, 2002 15:20:00.275\n!MESSAGE java.lang.NullPointerException\n!STACK 0\njava.lang.NullPointerException\n        at org.eclipse.jdt.internal.junit.ui.TestRunnerViewPart.isDisposed\n(TestRunnerViewPart.java:832)\n        at org.eclipse.jdt.internal.junit.ui.TestRunnerViewPart.postSyncRunnable\n(TestRunnerViewPart.java:518)\n        at org.eclipse.jdt.internal.junit.ui.TestRunnerViewPart.showInformation\n(TestRunnerViewPart.java:636)\n        at org.eclipse.jdt.internal.junit.ui.TestRunnerViewPart.aboutToLaunch\n(TestRunnerViewPart.java:475)\n        at \norg.eclipse.jdt.internal.junit.ui.TestRunnerViewPart.startTestRunListening\n(TestRunnerViewPart.java:456)\n        at org.eclipse.jdt.internal.junit.ui.JUnitPlugin.connectTestRunner\n(JUnitPlugin.java:170)\n        at org.eclipse.jdt.internal.junit.ui.JUnitPlugin$1.run\n(JUnitPlugin.java:200)\n        at org.eclipse.swt.widgets.RunnableLock.run(RunnableLock.java:31)\n        at org.eclipse.swt.widgets.Synchronizer.runAsyncMessages\n(Synchronizer.java:94)\n        at org.eclipse.swt.widgets.Display.runAsyncMessages(Display.java:1669)\n        at org.eclipse.swt.widgets.Display.readAndDispatch(Display.java:1414)\n        at org.eclipse.jface.operation.ModalContext$ModalContextThread.block\n(ModalContext.java:130)\n        at org.eclipse.jface.operation.ModalContext.run(ModalContext.java:255)\n        at org.eclipse.jface.dialogs.ProgressMonitorDialog.run\n(ProgressMonitorDialog.java:351)\n        at org.eclipse.debug.ui.DebugUITools.launch(DebugUITools.java:387)\n        at org.eclipse.debug.ui.actions.LaunchAction.run(LaunchAction.java:57)\n        at org.eclipse.jface.action.Action.runWithEvent(Action.java:769)\n        at org.eclipse.jface.action.ActionContributionItem.handleWidgetSelection\n(ActionContributionItem.java:411)\n        at org.eclipse.jface.action.ActionContributionItem.handleWidgetEvent\n(ActionContributionItem.java:365)\n        at org.eclipse.jface.action.ActionContributionItem.access$0\n(ActionContributionItem.java:356)\n        at \norg.eclipse.jface.action.ActionContributionItem$ActionListener.handleEvent\n(ActionContributionItem.java:48)\n        at org.eclipse.swt.widgets.EventTable.sendEvent(EventTable.java:77)\n        at org.eclipse.swt.widgets.Widget.sendEvent(Widget.java:825)\n        at org.eclipse.swt.widgets.Display.runDeferredEvents(Display.java:1692)\n        at org.eclipse.swt.widgets.Display.readAndDispatch(Display.java:1410)\n        at org.eclipse.ui.internal.Workbench.runEventLoop(Workbench.java:1403)\n        at org.eclipse.ui.internal.Workbench.run(Workbench.java:1386)\n        at org.eclipse.core.internal.boot.InternalBootLoader.run\n(InternalBootLoader.java:845)\n        at org.eclipse.core.boot.BootLoader.run(BootLoader.java:462)\n        at sun.reflect.NativeMethodAccessorImpl.invoke0(Native Method)\n        at sun.reflect.NativeMethodAccessorImpl.invoke\n(NativeMethodAccessorImpl.java:39)\n        at sun.reflect.DelegatingMethodAccessorImpl.invoke\n(DelegatingMethodAccessorImpl.java:25)\n        at java.lang.reflect.Method.invoke(Method.java:324)\n        at org.eclipse.core.launcher.Main.basicRun(Main.java:247)\n        at org.eclipse.core.launcher.Main.run(Main.java:703)\n        at org.eclipse.core.launcher.Main.main(Main.java:539)",
    "this is a consequence of the lazy view creation. This is not pde.junit related.\nThe problem is fixed in the latest integration build."
  ],
  "commentCreationDates": [
    "2002-12-13T14:12:11+01:00",
    "2002-12-13T14:58:55+01:00"
  ],
  "traces": [
    {
      "exceptionType": "org.eclipse.swt.SWTException",
      "message": "Failed to execute runnable  (java.lang.NullPointerException)",
      "elements": [
        {
          "method": "org.eclipse.swt.SWT.error",
          "source": "SWT.java:2180"
        },
        {
          "method": "org.eclipse.swt.widgets.Synchronizer.runAsyncMessages",
          "source": "Synchronizer.java:97"
        },
        {
          "method": "org.eclipse.swt.widgets.Display.runAsyncMessages",
          "source": "Display.java:1669"
        },
        {
          "method": "org.eclipse.swt.widgets.Display.readAndDispatch",
          "source": "Display.java:1414"
        },
        {
          "method": "org.eclipse.jface.operation.ModalContext$ModalContextThread.block",
          "source": "ModalContext.java:130"
        },
        {
          "method": "org.eclipse.jface.operation.ModalContext.run",
          "source": "ModalContext.java:255"
        },
        {
          "method": "org.eclipse.jface.dialogs.ProgressMonitorDialog.run",
          "source": "ProgressMonitorDialog.java:351"
        },
        {
          "method": "org.eclipse.debug.ui.DebugUITools.launch",
          "source": "DebugUITools.java:387"
        },
        {
          "method": "org.eclipse.debug.ui.actions.LaunchAction.run",
          "source": "LaunchAction.java:57"
        },
        {
          "method": "org.eclipse.jface.action.Action.runWithEvent",
          "source": "Action.java:769"
        },
        {
          "method": "org.eclipse.jface.action.ActionContributionItem.handleWidgetSelection",
          "source": "ActionContributionItem.java:411"
        },
        {
          "method": "org.eclipse.jface.action.ActionContributionItem.handleWidgetEvent",
          "source": "ActionContributionItem.java:365"
        },
        {
          "method": "org.eclipse.jface.action.ActionContributionItem.access$0",
          "source": "ActionContributionItem.java:356"
        },
        {
          "method": "org.eclipse.jface.action.ActionContributionItem$ActionListener.handleEvent",
          "source": "ActionContributionItem.java:48"
        },
        {
          "method": "org.eclipse.swt.widgets.EventTable.sendEvent",
          "source": "EventTable.java:77"
        },
        {
          "method": "org.eclipse.swt.widgets.Widget.sendEvent",
          "source": "Widget.java:825"
        },
        {
          "method": "org.eclipse.swt.widgets.Display.runDeferredEvents",
          "source": "Display.java:1692"
        },
        {
          "method": "org.eclipse.swt.widgets.Display.readAndDispatch",
          "source": "Display.java:1410"
        },
        {
          "method": "org.eclipse.ui.internal.Workbench.runEventLoop",
          "source": "Workbench.java:1403"
        },
        {
          "method": "org.eclipse.ui.internal.Workbench.run",
          "source": "Workbench.java:1386"
        },
        {
          "method": "org.eclipse.core.internal.boot.InternalBootLoader.run",
          "source": "InternalBootLoader.java:845"
        },
        {
          "method": "org.eclipse.core.boot.BootLoader.run",
          "source": "BootLoader.java:462"
        },
        {
          "method": "sun.reflect.NativeMethodAccessorImpl.invoke0",
          "source": "Native Method"
        },
        {
          "method": "sun.reflect.NativeMethodAccessorImpl.invoke",
          "source": "NativeMethodAccessorImpl.java:39"
        },
        {
          "method": "sun.reflect.DelegatingMethodAccessorImpl.invoke",
          "source": "DelegatingMethodAccessorImpl.java:25"
        },
        {
          "method": "java.lang.reflect.Method.invoke",
          "source": "Method.java:324"
        },
        {
          "method": "org.eclipse.core.launcher.Main.basicRun",
          "source": "Main.java:247"
        },
        {
          "method": "org.eclipse.core.launcher.Main.run",
          "source": "Main.java:703"
        },
        {
          "method": "org.eclipse.core.launcher.Main.main",
          "source": "Main.java:539"
        }
      ],
      "number": 0,
      "commentIndex": 0,
      "bugId": "28262",
      "date": "2002-12-13T14:12:11+01:00",
      "product": "JDT",
      "component": "UI",
      "severity": "normal"
    },
    {
      "exceptionType": "java.lang.NullPointerException",
      "elements": [
        {
          "method": "org.eclipse.jdt.internal.junit.ui.TestRunnerViewPart.isDisposed",
          "source": "TestRunnerViewPart.java:832"
        },
        {
          "method": "org.eclipse.jdt.internal.junit.ui.TestRunnerViewPart.postSyncRunnable",
          "source": "TestRunnerViewPart.java:518"
        },
        {
          "method": "org.eclipse.jdt.internal.junit.ui.TestRunnerViewPart.showInformation",
          "source": "TestRunnerViewPart.java:636"
        },
        {
          "method": "org.eclipse.jdt.internal.junit.ui.TestRunnerViewPart.aboutToLaunch",
          "source": "TestRunnerViewPart.java:475"
        },
        {
          "method": "org.eclipse.jdt.internal.junit.ui.TestRunnerViewPart.startTestRunListening",
          "source": "TestRunnerViewPart.java:456"
        },
        {
          "method": "org.eclipse.jdt.internal.junit.ui.JUnitPlugin.connectTestRunner",
          "source": "JUnitPlugin.java:170"
        },
        {
          "method": "org.eclipse.jdt.internal.junit.ui.JUnitPlugin$1.run",
          "source": "JUnitPlugin.java:200"
        },
        {
          "method": "org.eclipse.swt.widgets.RunnableLock.run",
          "source": "RunnableLock.java:31"
        },
        {
          "method": "org.eclipse.swt.widgets.Synchronizer.runAsyncMessages",
          "source": "Synchronizer.java:94"
        },
        {
          "method": "org.eclipse.swt.widgets.Display.runAsyncMessages",
          "source": "Display.java:1669"
        },
        {
          "method": "org.eclipse.swt.widgets.Display.readAndDispatch",
          "source": "Display.java:1414"
        },
        {
          "method": "org.eclipse.jface.operation.ModalContext$ModalContextThread.block",
          "source": "ModalContext.java:130"
        },
        {
          "method": "org.eclipse.jface.operation.ModalContext.run",
          "source": "ModalContext.java:255"
        },
        {
          "method": "org.eclipse.jface.dialogs.ProgressMonitorDialog.run",
          "source": "ProgressMonitorDialog.java:351"
        },
        {
          "method": "org.eclipse.debug.ui.DebugUITools.launch",
          "source": "DebugUITools.java:387"
        },
        {
          "method": "org.eclipse.debug.ui.actions.LaunchAction.run",
          "source": "LaunchAction.java:57"
        },
        {
          "method": "org.eclipse.jface.action.Action.runWithEvent",
          "source": "Action.java:769"
        },
        {
          "method": "org.eclipse.jface.action.ActionContributionItem.handleWidgetSelection",
          "source": "ActionContributionItem.java:411"
        },
        {
          "method": "org.eclipse.jface.action.ActionContributionItem.handleWidgetEvent",
          "source": "ActionContributionItem.java:365"
        },
        {
          "method": "org.eclipse.jface.action.ActionContributionItem.access$0",
          "source": "ActionContributionItem.java:356"
        },
        {
          "method": "org.eclipse.jface.action.ActionContributionItem$ActionListener.handleEvent",
          "source": "ActionContributionItem.java:48"
        },
        {
          "method": "org.eclipse.swt.widgets.EventTable.sendEvent",
          "source": "EventTable.java:77"
        },
        {
          "method": "org.eclipse.swt.widgets.Widget.sendEvent",
          "source": "Widget.java:825"
        },
        {
          "method": "org.eclipse.swt.widgets.Display.runDeferredEvents",
          "source": "Display.java:1692"
        },
        {
          "method": "org.eclipse.swt.widgets.Display.readAndDispatch",
          "source": "Display.java:1410"
        },
        {
          "method": "org.eclipse.ui.internal.Workbench.runEventLoop",
          "source": "Workbench.java:1403"
        },
        {
          "method": "org.eclipse.ui.internal.Workbench.run",
          "source": "Workbench.java:1386"
        },
        {
          "method": "org.eclipse.core.internal.boot.InternalBootLoader.run",
          "source": "InternalBootLoader.java:845"
        },
        {
          "method": "org.eclipse.core.boot.BootLoader.run",
          "source": "BootLoader.java:462"
        },
        {
          "method": "sun.reflect.NativeMethodAccessorImpl.invoke0",
          "source": "Native Method"
        },
        {
          "method": "sun.reflect.NativeMethodAccessorImpl.invoke",
          "source": "NativeMethodAccessorImpl.java:39"
        },
        {
          "method": "sun.reflect.DelegatingMethodAccessorImpl.invoke",
          "source": "DelegatingMethodAccessorImpl.java:25"
        },
        {
          "method": "java.lang.reflect.Method.invoke",
          "source": "Method.java:324"
        },
        {
          "method": "org.eclipse.core.launcher.Main.basicRun",
          "source": "Main.java:247"
        },
        {
          "method": "org.eclipse.core.launcher.Main.run",
          "source": "Main.java:703"
        },
        {
          "method": "org.eclipse.core.launcher.Main.main",
          "source": "Main.java:539"
        }
      ],
      "number": 1,
      "commentIndex": 0,
      "bugId": "28262",
      "date": "2002-12-13T14:12:11+01:00",
      "product": "JDT",
      "component": "UI",
      "severity": "normal"
    }
  ],
  "groupId": "28262",
  "bugId": "28262",
  "date": "2002-12-13T14:12:11+01:00",
  "product": "JDT",
  "component": "UI",
  "severity": "normal"
}