{
  "comments": [
    "Build 20021216\n\nI add an exception breakpoint that was disabled. I started a runtime workbench \nunder debug. I had the main thread suspended at a breakpoint. I tried to enable \nthe exception breakpoint and got the following NPE:\n\njava.lang.NullPointerException\n        at \norg.eclipse.jdt.internal.debug.core.model.JDIDebugElement.getEventRequestManager\n(JDIDebugElement.java:342)\n        at \norg.eclipse.jdt.internal.debug.core.model.JDIDebugTarget.createClassPrepareReque\nst(JDIDebugTarget.java:915)\n        at \norg.eclipse.jdt.internal.debug.core.model.JDIDebugTarget.createClassPrepareReque\nst(JDIDebugTarget.java:894)\n        at \norg.eclipse.jdt.internal.debug.core.breakpoints.JavaBreakpoint.createRequests\n(JavaBreakpoint.java:457)\n        at \norg.eclipse.jdt.internal.debug.core.breakpoints.JavaBreakpoint.recreate\n(JavaBreakpoint.java:1068)\n        at \norg.eclipse.jdt.internal.debug.core.breakpoints.JavaBreakpoint.recreate\n(JavaBreakpoint.java:1052)\n        at \norg.eclipse.jdt.internal.debug.core.breakpoints.JavaBreakpoint.setEnabled\n(JavaBreakpoint.java:1076)\n        at \norg.eclipse.jdt.internal.debug.core.breakpoints.JavaExceptionBreakpoint.setEnabl\ned(JavaExceptionBreakpoint.java:178)\n        at org.eclipse.debug.internal.ui.actions.EnableBreakpointsAction.run\n(EnableBreakpointsAction.java:87)\n        at org.eclipse.ui.internal.PluginAction.runWithEvent\n(PluginAction.java:250)\n        at org.eclipse.jface.action.ActionContributionItem.handleWidgetSelection\n(ActionContributionItem.java:411)\n        at org.eclipse.jface.action.ActionContributionItem.handleWidgetEvent\n(ActionContributionItem.java:365)\n        at org.eclipse.jface.action.ActionContributionItem.access$0\n(ActionContributionItem.java:356)\n        at \norg.eclipse.jface.action.ActionContributionItem$ActionListener.handleEvent\n(ActionContributionItem.java:48)\n        at org.eclipse.swt.widgets.EventTable.sendEvent(EventTable.java:77)\n        at org.eclipse.swt.widgets.Widget.sendEvent(Widget.java:825)\n        at org.eclipse.swt.widgets.Display.runDeferredEvents(Display.java:1692)\n        at org.eclipse.swt.widgets.Display.readAndDispatch(Display.java:1410)\n        at org.eclipse.ui.internal.Workbench.runEventLoop(Workbench.java:1403)\n        at org.eclipse.ui.internal.Workbench.run(Workbench.java:1386)\n        at org.eclipse.core.internal.boot.InternalBootLoader.run\n(InternalBootLoader.java:845)\n        at org.eclipse.core.boot.BootLoader.run(BootLoader.java:462)\n        at sun.reflect.NativeMethodAccessorImpl.invoke0(Native Method)\n        at sun.reflect.NativeMethodAccessorImpl.invoke\n(NativeMethodAccessorImpl.java:39)\n        at sun.reflect.DelegatingMethodAccessorImpl.invoke\n(DelegatingMethodAccessorImpl.java:25)\n        at java.lang.reflect.Method.invoke(Method.java:324)\n        at org.eclipse.core.launcher.Main.basicRun(Main.java:247)\n        at org.eclipse.core.launcher.Main.run(Main.java:703)\n        at org.eclipse.core.launcher.Main.main(Main.java:539)",
    "\n\n*** This bug has been marked as a duplicate of 27857 ***"
  ],
  "commentCreationDates": [
    "2002-12-17T14:35:49+01:00",
    "2002-12-17T14:53:52+01:00"
  ],
  "traces": [
    {
      "exceptionType": "java.lang.NullPointerException",
      "elements": [
        {
          "method": "org.eclipse.jdt.internal.debug.core.model.JDIDebugElement.getEventRequestManager",
          "source": "JDIDebugElement.java:342"
        },
        {
          "method": "org.eclipse.jdt.internal.debug.core.model.JDIDebugTarget.createClassPrepareRequest",
          "source": "JDIDebugTarget.java:915"
        },
        {
          "method": "org.eclipse.jdt.internal.debug.core.model.JDIDebugTarget.createClassPrepareRequest",
          "source": "JDIDebugTarget.java:894"
        },
        {
          "method": "org.eclipse.jdt.internal.debug.core.breakpoints.JavaBreakpoint.createRequests",
          "source": "JavaBreakpoint.java:457"
        },
        {
          "method": "org.eclipse.jdt.internal.debug.core.breakpoints.JavaBreakpoint.recreate",
          "source": "JavaBreakpoint.java:1068"
        },
        {
          "method": "org.eclipse.jdt.internal.debug.core.breakpoints.JavaBreakpoint.recreate",
          "source": "JavaBreakpoint.java:1052"
        },
        {
          "method": "org.eclipse.jdt.internal.debug.core.breakpoints.JavaBreakpoint.setEnabled",
          "source": "JavaBreakpoint.java:1076"
        },
        {
          "method": "org.eclipse.jdt.internal.debug.core.breakpoints.JavaExceptionBreakpoint.setEnabled",
          "source": "JavaExceptionBreakpoint.java:178"
        },
        {
          "method": "org.eclipse.debug.internal.ui.actions.EnableBreakpointsAction.run",
          "source": "EnableBreakpointsAction.java:87"
        },
        {
          "method": "org.eclipse.ui.internal.PluginAction.runWithEvent",
          "source": "PluginAction.java:250"
        },
        {
          "method": "org.eclipse.jface.action.ActionContributionItem.handleWidgetSelection",
          "source": "ActionContributionItem.java:411"
        },
        {
          "method": "org.eclipse.jface.action.ActionContributionItem.handleWidgetEvent",
          "source": "ActionContributionItem.java:365"
        },
        {
          "method": "org.eclipse.jface.action.ActionContributionItem.access$0",
          "source": "ActionContributionItem.java:356"
        },
        {
          "method": "org.eclipse.jface.action.ActionContributionItem$ActionListener.handleEvent",
          "source": "ActionContributionItem.java:48"
        },
        {
          "method": "org.eclipse.swt.widgets.EventTable.sendEvent",
          "source": "EventTable.java:77"
        },
        {
          "method": "org.eclipse.swt.widgets.Widget.sendEvent",
          "source": "Widget.java:825"
        },
        {
          "method": "org.eclipse.swt.widgets.Display.runDeferredEvents",
          "source": "Display.java:1692"
        },
        {
          "method": "org.eclipse.swt.widgets.Display.readAndDispatch",
          "source": "Display.java:1410"
        },
        {
          "method": "org.eclipse.ui.internal.Workbench.runEventLoop",
          "source": "Workbench.java:1403"
        },
        {
          "method": "org.eclipse.ui.internal.Workbench.run",
          "source": "Workbench.java:1386"
        },
        {
          "method": "org.eclipse.core.internal.boot.InternalBootLoader.run",
          "source": "InternalBootLoader.java:845"
        },
        {
          "method": "org.eclipse.core.boot.BootLoader.run",
          "source": "BootLoader.java:462"
        },
        {
          "method": "sun.reflect.NativeMethodAccessorImpl.invoke0",
          "source": "Native Method"
        },
        {
          "method": "sun.reflect.NativeMethodAccessorImpl.invoke",
          "source": "NativeMethodAccessorImpl.java:39"
        },
        {
          "method": "sun.reflect.DelegatingMethodAccessorImpl.invoke",
          "source": "DelegatingMethodAccessorImpl.java:25"
        },
        {
          "method": "java.lang.reflect.Method.invoke",
          "source": "Method.java:324"
        },
        {
          "method": "org.eclipse.core.launcher.Main.basicRun",
          "source": "Main.java:247"
        },
        {
          "method": "org.eclipse.core.launcher.Main.run",
          "source": "Main.java:703"
        },
        {
          "method": "org.eclipse.core.launcher.Main.main",
          "source": "Main.java:539"
        }
      ],
      "number": 0,
      "commentIndex": 0,
      "bugId": "28506",
      "duplicateId": "27857",
      "date": "2002-12-17T14:35:49+01:00",
      "product": "JDT",
      "component": "Debug",
      "severity": "normal"
    }
  ],
  "groupId": "29617",
  "bugId": "28506",
  "duplicateId": "27857",
  "date": "2002-12-17T14:35:49+01:00",
  "product": "JDT",
  "component": "Debug",
  "severity": "normal"
}