{
  "comments": [
    "Build 20021218 (M4)\n\nHad a self-hosted workspace, with breakpoints defined in the code. \nPerformed a PDE import, which refreshed some resources, JavaModel update is \ntriggered (POST_CHANGE) and debugger kicks in trying to modify resources.\n\n!ENTRY org.eclipse.debug.core 4 120 Dec 19, 2002 11:46:08.18\n!MESSAGE Error logged from Debug Core:\n!STACK 1\norg.eclipse.core.internal.resources.ResourceException: The resource tree is \nlocked for modifications.\n        at org.eclipse.core.internal.resources.Workspace.beginOperation\n(Workspace.java:136)\n        at org.eclipse.core.internal.resources.Workspace.run\n(Workspace.java:1563)\n        at org.eclipse.debug.internal.core.BreakpointManager.addBreakpoints\n(BreakpointManager.java:402)\n        at org.eclipse.debug.internal.core.BreakpointManager.loadBreakpoints\n(BreakpointManager.java:139)\n        at \norg.eclipse.debug.internal.core.BreakpointManager.initializeBreakpoints\n(BreakpointManager.java:266)\n        at org.eclipse.debug.internal.core.BreakpointManager.getBreakpoints0\n(BreakpointManager.java:237)\n        at org.eclipse.debug.internal.core.BreakpointManager.getBreakpoints\n(BreakpointManager.java:246)\n        at org.eclipse.jdt.internal.debug.ui.JavaModelListener.elementChanged\n(JavaModelListener.java:51)\n        at org.eclipse.jdt.internal.core.JavaModelManager$3.run\n(JavaModelManager.java:776)\n        at org.eclipse.core.internal.runtime.InternalPlatform.run\n(InternalPlatform.java:852)\n        at org.eclipse.core.runtime.Platform.run(Platform.java:413)\n        at org.eclipse.jdt.internal.core.JavaModelManager.fire\n(JavaModelManager.java:771)\n        at org.eclipse.jdt.internal.core.DeltaProcessor.resourceChanged\n(DeltaProcessor.java:1624)\n        at org.eclipse.core.internal.events.NotificationManager$1.run\n(NotificationManager.java:137)\n        at org.eclipse.core.internal.runtime.InternalPlatform.run\n(InternalPlatform.java:852)\n        at org.eclipse.core.runtime.Platform.run(Platform.java:413)\n        at org.eclipse.core.internal.events.NotificationManager.notify\n(NotificationManager.java:152)\n        at org.eclipse.core.internal.events.NotificationManager.broadcastChanges\n(NotificationManager.java:67)\n        at org.eclipse.core.internal.resources.Workspace.broadcastChanges\n(Workspace.java:153)\n        at org.eclipse.core.internal.resources.Workspace.endOperation\n(Workspace.java:869)\n        at org.eclipse.core.internal.resources.Workspace.run\n(Workspace.java:1569)\n        at org.eclipse.pde.internal.ui.wizards.imports.PluginImportWizard$2.run\n(PluginImportWizard.java:152)\n        at org.eclipse.jface.operation.ModalContext$ModalContextThread.run\n(ModalContext.java:95)\n!ENTRY org.eclipse.core.resources 1 4 Dec 19, 2002 11:46:08.18",
    "This is a duplicate. One solution would be new support from JCORE that provided \nelement deltas while the resource tree is not locked :-)\n\n*** This bug has been marked as a duplicate of 24903 ***",
    "This is unlikely to occur until we get a mechanism from platform/core so as to \navoid processing the same delta more than once (if listening for deltas at \ndifferent stages). Currently all rsc delta processing is done once we have them \nall - post-change.\n\nIf we did update and process the model each time we listen to deltas to notify \nour clients, we would likely do the same amount of work 4 times, since there is \nno way to distinguish whether we did react already to a delta (i.e. is it the \nsame delta, or did the resource change again since then?).\n\nUnlikely that we would evolve without first the platform provide such an \nenhancement (timestamps with deltas would do it).\n\nFor now, you should avoid performing resource modifying operations in reaction \nto our deltas during post-change."
  ],
  "commentCreationDates": [
    "2002-12-19T10:35:16+01:00",
    "2002-12-19T13:58:34+01:00",
    "2002-12-19T15:09:36+01:00"
  ],
  "traces": [
    {
      "exceptionType": "org.eclipse.core.internal.resources.ResourceException",
      "message": "The resource tree is  locked for modifications.",
      "elements": [
        {
          "method": "org.eclipse.core.internal.resources.Workspace.beginOperation",
          "source": "Workspace.java:136"
        },
        {
          "method": "org.eclipse.core.internal.resources.Workspace.run",
          "source": "Workspace.java:1563"
        },
        {
          "method": "org.eclipse.debug.internal.core.BreakpointManager.addBreakpoints",
          "source": "BreakpointManager.java:402"
        },
        {
          "method": "org.eclipse.debug.internal.core.BreakpointManager.loadBreakpoints",
          "source": "BreakpointManager.java:139"
        },
        {
          "method": "org.eclipse.debug.internal.core.BreakpointManager.initializeBreakpoints",
          "source": "BreakpointManager.java:266"
        },
        {
          "method": "org.eclipse.debug.internal.core.BreakpointManager.getBreakpoints0",
          "source": "BreakpointManager.java:237"
        },
        {
          "method": "org.eclipse.debug.internal.core.BreakpointManager.getBreakpoints",
          "source": "BreakpointManager.java:246"
        },
        {
          "method": "org.eclipse.jdt.internal.debug.ui.JavaModelListener.elementChanged",
          "source": "JavaModelListener.java:51"
        },
        {
          "method": "org.eclipse.jdt.internal.core.JavaModelManager$3.run",
          "source": "JavaModelManager.java:776"
        },
        {
          "method": "org.eclipse.core.internal.runtime.InternalPlatform.run",
          "source": "InternalPlatform.java:852"
        },
        {
          "method": "org.eclipse.core.runtime.Platform.run",
          "source": "Platform.java:413"
        },
        {
          "method": "org.eclipse.jdt.internal.core.JavaModelManager.fire",
          "source": "JavaModelManager.java:771"
        },
        {
          "method": "org.eclipse.jdt.internal.core.DeltaProcessor.resourceChanged",
          "source": "DeltaProcessor.java:1624"
        },
        {
          "method": "org.eclipse.core.internal.events.NotificationManager$1.run",
          "source": "NotificationManager.java:137"
        },
        {
          "method": "org.eclipse.core.internal.runtime.InternalPlatform.run",
          "source": "InternalPlatform.java:852"
        },
        {
          "method": "org.eclipse.core.runtime.Platform.run",
          "source": "Platform.java:413"
        },
        {
          "method": "org.eclipse.core.internal.events.NotificationManager.notify",
          "source": "NotificationManager.java:152"
        },
        {
          "method": "org.eclipse.core.internal.events.NotificationManager.broadcastChanges",
          "source": "NotificationManager.java:67"
        },
        {
          "method": "org.eclipse.core.internal.resources.Workspace.broadcastChanges",
          "source": "Workspace.java:153"
        },
        {
          "method": "org.eclipse.core.internal.resources.Workspace.endOperation",
          "source": "Workspace.java:869"
        },
        {
          "method": "org.eclipse.core.internal.resources.Workspace.run",
          "source": "Workspace.java:1569"
        },
        {
          "method": "org.eclipse.pde.internal.ui.wizards.imports.PluginImportWizard$2.run",
          "source": "PluginImportWizard.java:152"
        },
        {
          "method": "org.eclipse.jface.operation.ModalContext$ModalContextThread.run",
          "source": "ModalContext.java:95"
        }
      ],
      "number": 0,
      "commentIndex": 0,
      "bugId": "28661",
      "duplicateId": "24903",
      "date": "2002-12-19T10:35:16+01:00",
      "product": "JDT",
      "component": "Debug",
      "severity": "normal"
    }
  ],
  "groupId": "24903",
  "bugId": "28661",
  "duplicateId": "24903",
  "date": "2002-12-19T10:35:16+01:00",
  "product": "JDT",
  "component": "Debug",
  "severity": "normal"
}