{
  "comments": [
    "Build 20021218\n\n- had a Java editor opened on unit with following contents:\n[\npublic class A { \\n\"+\n\tprivate static void doSomething(String showThis) {\\n\"+\n\t\tSystem.out.print(showThis)\t\t\\n\"+\n\t\treturn;\t\t\t\\n\"+\n\t}\t\\n\"+\n\tclass B {\t\\n\"+\n\t\tvoid aMethod () {\t\\n\"+\n\t\t\tp1.A.doSomething(\\\"SUCC\\\");\t\\n\"+\n\t\t\tA.doSomething(\\\"ES\\\");\t\t\\n\"+\n\t\t\tdoSomething(\\\"S\\\");\t\\n\"+\n\t\t}\t\\n\"+\t\t\n\t}\t\t\\n\"+\n\tpublic static void main (String argv[]) {\t\t\\n\"+\n\t\tB foo \u003d new A().new B();\t\t\\n\"+\n\t\tfoo.aMethod();\t\t\t\t\\n\"+\n\t}\t\t\t\\n\"+\n]\n\n- selected \u0027\\n\"+\u0027, pressed ctrl-F and hit replace all\n- nothing occurs (exception in the .log)\n\nUnhandled exception caught in event loop.\nReason:\n!ENTRY org.eclipse.ui 4 0 Dec 19, 2002 13:16:32.183\n!MESSAGE Invalid range argument\n!STACK 0\njava.lang.IllegalArgumentException: Invalid range argument\n        at org.eclipse.jface.text.TextViewer.internalRevealRange\n(TextViewer.java:2246)\n        at org.eclipse.jface.text.TextViewer.revealRange(TextViewer.java:2152)\n        at org.eclipse.jface.text.TextViewer.enabledRedrawing\n(TextViewer.java:3595)\n        at org.eclipse.jface.text.TextViewer.setRedraw(TextViewer.java:3632)\n        at org.eclipse.jface.text.TextViewer$FindReplaceTarget.setReplaceAllMode\n(TextViewer.java:858)\n        at org.eclipse.ui.texteditor.FindReplaceDialog.replaceAll\n(FindReplaceDialog.java:1149)\n        at org.eclipse.ui.texteditor.FindReplaceDialog.access$29\n(FindReplaceDialog.java:1117)\n        at org.eclipse.ui.texteditor.FindReplaceDialog$1$ReplaceAllRunnable.run\n(FindReplaceDialog.java:1043)\n        at org.eclipse.swt.custom.BusyIndicator.showWhile(BusyIndicator.java:65)\n        at org.eclipse.ui.texteditor.FindReplaceDialog.performReplaceAll\n(FindReplaceDialog.java:1048)\n        at org.eclipse.ui.texteditor.FindReplaceDialog.access$25\n(FindReplaceDialog.java:1032)\n        at org.eclipse.ui.texteditor.FindReplaceDialog$4.widgetSelected\n(FindReplaceDialog.java:290)\n        at org.eclipse.swt.widgets.TypedListener.handleEvent\n(TypedListener.java:87)\n        at org.eclipse.swt.widgets.EventTable.sendEvent(EventTable.java:77)\n        at org.eclipse.swt.widgets.Widget.sendEvent(Widget.java:825)\n        at org.eclipse.swt.widgets.Display.runDeferredEvents(Display.java:1692)\n        at org.eclipse.swt.widgets.Display.readAndDispatch(Display.java:1410)\n        at org.eclipse.ui.internal.Workbench.runEventLoop(Workbench.java:1446)\n        at org.eclipse.ui.internal.Workbench.run(Workbench.java:1429)\n        at org.eclipse.core.internal.boot.InternalBootLoader.run\n(InternalBootLoader.java:845)\n        at org.eclipse.core.boot.BootLoader.run(BootLoader.java:462)\n        at sun.reflect.NativeMethodAccessorImpl.invoke0(Native Method)\n        at sun.reflect.NativeMethodAccessorImpl.invoke\n(NativeMethodAccessorImpl.java:39)\n        at sun.reflect.DelegatingMethodAccessorImpl.invoke\n(DelegatingMethodAccessorImpl.java:25)\n        at java.lang.reflect.Method.invoke(Method.java:324)\n        at org.eclipse.core.launcher.Main.basicRun(Main.java:247)\n        at org.eclipse.core.launcher.Main.run(Main.java:703)\n        at org.eclipse.core.launcher.Main.main(Main.java:539)\nInvalid range argument",
    "*** Bug 29237 has been marked as a duplicate of this bug. ***",
    "Build I20030206.",
    "start verifying"
  ],
  "commentCreationDates": [
    "2002-12-19T12:01:28+01:00",
    "2003-02-05T17:27:36+01:00",
    "2003-02-05T17:30:16+01:00",
    "2003-02-27T15:37:22+01:00"
  ],
  "traces": [
    {
      "exceptionType": "java.lang.IllegalArgumentException",
      "message": "Invalid range argument",
      "elements": [
        {
          "method": "org.eclipse.jface.text.TextViewer.internalRevealRange",
          "source": "TextViewer.java:2246"
        },
        {
          "method": "org.eclipse.jface.text.TextViewer.revealRange",
          "source": "TextViewer.java:2152"
        },
        {
          "method": "org.eclipse.jface.text.TextViewer.enabledRedrawing",
          "source": "TextViewer.java:3595"
        },
        {
          "method": "org.eclipse.jface.text.TextViewer.setRedraw",
          "source": "TextViewer.java:3632"
        },
        {
          "method": "org.eclipse.jface.text.TextViewer$FindReplaceTarget.setReplaceAllMode",
          "source": "TextViewer.java:858"
        },
        {
          "method": "org.eclipse.ui.texteditor.FindReplaceDialog.replaceAll",
          "source": "FindReplaceDialog.java:1149"
        },
        {
          "method": "org.eclipse.ui.texteditor.FindReplaceDialog.access$29",
          "source": "FindReplaceDialog.java:1117"
        },
        {
          "method": "org.eclipse.ui.texteditor.FindReplaceDialog$1$ReplaceAllRunnable.run",
          "source": "FindReplaceDialog.java:1043"
        },
        {
          "method": "org.eclipse.swt.custom.BusyIndicator.showWhile",
          "source": "BusyIndicator.java:65"
        },
        {
          "method": "org.eclipse.ui.texteditor.FindReplaceDialog.performReplaceAll",
          "source": "FindReplaceDialog.java:1048"
        },
        {
          "method": "org.eclipse.ui.texteditor.FindReplaceDialog.access$25",
          "source": "FindReplaceDialog.java:1032"
        },
        {
          "method": "org.eclipse.ui.texteditor.FindReplaceDialog$4.widgetSelected",
          "source": "FindReplaceDialog.java:290"
        },
        {
          "method": "org.eclipse.swt.widgets.TypedListener.handleEvent",
          "source": "TypedListener.java:87"
        },
        {
          "method": "org.eclipse.swt.widgets.EventTable.sendEvent",
          "source": "EventTable.java:77"
        },
        {
          "method": "org.eclipse.swt.widgets.Widget.sendEvent",
          "source": "Widget.java:825"
        },
        {
          "method": "org.eclipse.swt.widgets.Display.runDeferredEvents",
          "source": "Display.java:1692"
        },
        {
          "method": "org.eclipse.swt.widgets.Display.readAndDispatch",
          "source": "Display.java:1410"
        },
        {
          "method": "org.eclipse.ui.internal.Workbench.runEventLoop",
          "source": "Workbench.java:1446"
        },
        {
          "method": "org.eclipse.ui.internal.Workbench.run",
          "source": "Workbench.java:1429"
        },
        {
          "method": "org.eclipse.core.internal.boot.InternalBootLoader.run",
          "source": "InternalBootLoader.java:845"
        },
        {
          "method": "org.eclipse.core.boot.BootLoader.run",
          "source": "BootLoader.java:462"
        },
        {
          "method": "sun.reflect.NativeMethodAccessorImpl.invoke0",
          "source": "Native Method"
        },
        {
          "method": "sun.reflect.NativeMethodAccessorImpl.invoke",
          "source": "NativeMethodAccessorImpl.java:39"
        },
        {
          "method": "sun.reflect.DelegatingMethodAccessorImpl.invoke",
          "source": "DelegatingMethodAccessorImpl.java:25"
        },
        {
          "method": "java.lang.reflect.Method.invoke",
          "source": "Method.java:324"
        },
        {
          "method": "org.eclipse.core.launcher.Main.basicRun",
          "source": "Main.java:247"
        },
        {
          "method": "org.eclipse.core.launcher.Main.run",
          "source": "Main.java:703"
        },
        {
          "method": "org.eclipse.core.launcher.Main.main",
          "source": "Main.java:539"
        }
      ],
      "number": 0,
      "commentIndex": 0,
      "bugId": "28665",
      "date": "2002-12-19T12:01:28+01:00",
      "product": "Platform",
      "component": "Text",
      "severity": "normal"
    }
  ],
  "groupId": "28665",
  "bugId": "28665",
  "date": "2002-12-19T12:01:28+01:00",
  "product": "Platform",
  "component": "Text",
  "severity": "normal"
}