{
  "comments": [
    "This is the simplest use case I could think of, but I started out advising calls\nto println, so I know it\u0027s not the empty class and aspect that causes this.\n\ndirectory structure:\nbugs/\n  incremental/\n    BasicAspect.java\n    Basic.java\n\nBasicAspect.java:\n---\npackage incremental;\npublic aspect BasicAspect{}\n---\n\nBasic.java:\n---\npackage incremental;\npublic class Basic{}\n\n\nSteps to reproduce:\n[...]/bugs% ajc -incremental -sourceroots .\n    press enter to recompile (q to quit):\n[... from another shell:...]/bugs% touch incremental/BasicAspect.java\n[... in first window hit enter ...]\n\njava.lang.NullPointerException\n        at org.aspectj.weaver.CrosscuttingMembers.replaceWith(Unknown Source)\n        at org.aspectj.weaver.CrosscuttingMembersSet.addOrReplaceAspect(Unknown\nSource)\n        at\norg.aspectj.ajdt.internal.compiler.ast.AspectDeclaration.buildInterTypeAndPerClause(Unknown\nSource)\n        at\norg.aspectj.ajdt.internal.compiler.lookup.AjLookupEnvironment.buildInterTypeAndPerClause(Unknown\nSource)\n        at\norg.aspectj.ajdt.internal.compiler.lookup.AjLookupEnvironment.completeTypeBindings(Unknown\nSource)\n        at org.eclipse.jdt.internal.compiler.Compiler.beginToCompile(Unknown Source)\n        at org.eclipse.jdt.internal.compiler.Compiler.compile(Unknown Source)\n        at\norg.eclipse.jdt.internal.core.builder.AbstractImageBuilder.compile(Unknown Source)\n        at\norg.eclipse.jdt.internal.core.builder.AbstractImageBuilder.compile(Unknown Source)\n        at\norg.eclipse.jdt.internal.core.builder.IncrementalImageBuilder.build(Unknown Source)\n        at\norg.aspectj.ajdt.internal.core.builder.AjBuildManager$IncrementalBuilder.build(Unknown\nSource)\n        at\norg.aspectj.ajdt.internal.core.builder.AjBuildManager.incrementalBuild(Unknown\nSource)\n        at org.aspectj.ajdt.ajc.AjdtCommand.repeatCommand(Unknown Source)\n        at org.aspectj.tools.ajc.Main.run(Unknown Source)\n        at org.aspectj.tools.ajc.Main.runMain(Unknown Source)\n        at org.aspectj.tools.ajc.Main.main(Unknown Source)\n/Users/nick/aspectj1.1/bugs/./incremental/BasicAspect.java:0: Internal compiler\nerror\njava.lang.NullPointerException\n        at org.aspectj.weaver.CrosscuttingMembers.replaceWith(Unknown Source)\n        at org.aspectj.weaver.CrosscuttingMembersSet.addOrReplaceAspect(Unknown\nSource)\n        at\norg.aspectj.ajdt.internal.compiler.ast.AspectDeclaration.buildInterTypeAndPerClause(Unknown\nSource)\n        at\norg.aspectj.ajdt.internal.compiler.lookup.AjLookupEnvironment.buildInterTypeAndPerClause(Unknown\nSource)\n        at\norg.aspectj.ajdt.internal.compiler.lookup.AjLookupEnvironment.completeTypeBindings(Unknown\nSource)\n        at org.eclipse.jdt.internal.compiler.Compiler.beginToCompile(Unknown Source)\n        at org.eclipse.jdt.internal.compiler.Compiler.compile(Unknown Source)\n        at\norg.eclipse.jdt.internal.core.builder.AbstractImageBuilder.compile(Unknown Source)\n        at\norg.eclipse.jdt.internal.core.builder.AbstractImageBuilder.compile(Unknown Source)\n        at\norg.eclipse.jdt.internal.core.builder.IncrementalImageBuilder.build(Unknown Source)\n        at\norg.aspectj.ajdt.internal.core.builder.AjBuildManager$IncrementalBuilder.build(Unknown\nSource)\n        at\norg.aspectj.ajdt.internal.core.builder.AjBuildManager.incrementalBuild(Unknown\nSource)\n        at org.aspectj.ajdt.ajc.AjdtCommand.repeatCommand(Unknown Source)\n        at org.aspectj.tools.ajc.Main.run(Unknown Source)\n        at org.aspectj.tools.ajc.Main.runMain(Unknown Source)\n        at org.aspectj.tools.ajc.Main.main(Unknown Source)\n\n\n!! no source information available !!\nException thrown from AspectJ 1.1b2\n\nThis might be logged as a bug already -- see the bug database at\n  http://dev.eclipse.org (product: AspectJ, component: compiler)\n\nBugs for exceptions thrown have titles File:line from the top stack, \ne.g., \"SomeFile.java:243\"\n\nIf you don\u0027t find the exception below in a bug, please add a new bug\nTo make the bug a priority, please include a test program\nthat can reproduce this exception.\nnull\njava.lang.NullPointerException\n        at org.aspectj.weaver.CrosscuttingMembers.replaceWith(Unknown Source)\n        at org.aspectj.weaver.CrosscuttingMembersSet.addOrReplaceAspect(Unknown\nSource)\n        at\norg.aspectj.ajdt.internal.compiler.ast.AspectDeclaration.buildInterTypeAndPerClause(Unknown\nSource)\n        at\norg.aspectj.ajdt.internal.compiler.lookup.AjLookupEnvironment.buildInterTypeAndPerClause(Unknown\nSource)\n        at\norg.aspectj.ajdt.internal.compiler.lookup.AjLookupEnvironment.completeTypeBindings(Unknown\nSource)\n        at org.eclipse.jdt.internal.compiler.Compiler.beginToCompile(Unknown Source)\n        at org.eclipse.jdt.internal.compiler.Compiler.compile(Unknown Source)\n        at\norg.eclipse.jdt.internal.core.builder.AbstractImageBuilder.compile(Unknown Source)\n        at\norg.eclipse.jdt.internal.core.builder.AbstractImageBuilder.compile(Unknown Source)\n        at\norg.eclipse.jdt.internal.core.builder.IncrementalImageBuilder.build(Unknown Source)\n        at\norg.aspectj.ajdt.internal.core.builder.AjBuildManager$IncrementalBuilder.build(Unknown\nSource)\n        at\norg.aspectj.ajdt.internal.core.builder.AjBuildManager.incrementalBuild(Unknown\nSource)\n        at org.aspectj.ajdt.ajc.AjdtCommand.repeatCommand(Unknown Source)\n        at org.aspectj.tools.ajc.Main.run(Unknown Source)\n        at org.aspectj.tools.ajc.Main.runMain(Unknown Source)\n        at org.aspectj.tools.ajc.Main.main(Unknown Source)\n\n\n1 fail|abort, 1 error",
    "fixed in current cvs tree, some minimal incremental tests are now in \ntests/scripts/incr.py"
  ],
  "commentCreationDates": [
    "2002-12-22T20:34:00+01:00",
    "2003-01-14T22:07:53+01:00"
  ],
  "traces": [
    {
      "exceptionType": "java.lang.NullPointerException",
      "elements": [
        {
          "method": "org.aspectj.weaver.CrosscuttingMembers.replaceWith",
          "source": "Unknown Source"
        },
        {
          "method": "org.aspectj.weaver.CrosscuttingMembersSet.addOrReplaceAspect",
          "source": "Unknown Source"
        },
        {
          "method": "org.aspectj.ajdt.internal.compiler.ast.AspectDeclaration.buildInterTypeAndPerClause",
          "source": "Unknown Source"
        },
        {
          "method": "org.aspectj.ajdt.internal.compiler.lookup.AjLookupEnvironment.buildInterTypeAndPerClause",
          "source": "Unknown Source"
        },
        {
          "method": "org.aspectj.ajdt.internal.compiler.lookup.AjLookupEnvironment.completeTypeBindings",
          "source": "Unknown Source"
        },
        {
          "method": "org.eclipse.jdt.internal.compiler.Compiler.beginToCompile",
          "source": "Unknown Source"
        },
        {
          "method": "org.eclipse.jdt.internal.compiler.Compiler.compile",
          "source": "Unknown Source"
        },
        {
          "method": "org.eclipse.jdt.internal.core.builder.AbstractImageBuilder.compile",
          "source": "Unknown Source"
        },
        {
          "method": "org.eclipse.jdt.internal.core.builder.AbstractImageBuilder.compile",
          "source": "Unknown Source"
        },
        {
          "method": "org.eclipse.jdt.internal.core.builder.IncrementalImageBuilder.build",
          "source": "Unknown Source"
        },
        {
          "method": "org.aspectj.ajdt.internal.core.builder.AjBuildManager$IncrementalBuilder.build",
          "source": "Unknown Source"
        },
        {
          "method": "org.aspectj.ajdt.internal.core.builder.AjBuildManager.incrementalBuild",
          "source": "Unknown Source"
        },
        {
          "method": "org.aspectj.ajdt.ajc.AjdtCommand.repeatCommand",
          "source": "Unknown Source"
        },
        {
          "method": "org.aspectj.tools.ajc.Main.run",
          "source": "Unknown Source"
        },
        {
          "method": "org.aspectj.tools.ajc.Main.runMain",
          "source": "Unknown Source"
        },
        {
          "method": "org.aspectj.tools.ajc.Main.main",
          "source": "Unknown Source"
        }
      ],
      "number": 0,
      "commentIndex": 0,
      "bugId": "28807",
      "date": "2002-12-22T20:34:00+01:00",
      "product": "AspectJ",
      "component": "Compiler",
      "severity": "major"
    },
    {
      "exceptionType": "java.lang.NullPointerException",
      "elements": [
        {
          "method": "org.aspectj.weaver.CrosscuttingMembers.replaceWith",
          "source": "Unknown Source"
        },
        {
          "method": "org.aspectj.weaver.CrosscuttingMembersSet.addOrReplaceAspect",
          "source": "Unknown Source"
        },
        {
          "method": "org.aspectj.ajdt.internal.compiler.ast.AspectDeclaration.buildInterTypeAndPerClause",
          "source": "Unknown Source"
        },
        {
          "method": "org.aspectj.ajdt.internal.compiler.lookup.AjLookupEnvironment.buildInterTypeAndPerClause",
          "source": "Unknown Source"
        },
        {
          "method": "org.aspectj.ajdt.internal.compiler.lookup.AjLookupEnvironment.completeTypeBindings",
          "source": "Unknown Source"
        },
        {
          "method": "org.eclipse.jdt.internal.compiler.Compiler.beginToCompile",
          "source": "Unknown Source"
        },
        {
          "method": "org.eclipse.jdt.internal.compiler.Compiler.compile",
          "source": "Unknown Source"
        },
        {
          "method": "org.eclipse.jdt.internal.core.builder.AbstractImageBuilder.compile",
          "source": "Unknown Source"
        },
        {
          "method": "org.eclipse.jdt.internal.core.builder.AbstractImageBuilder.compile",
          "source": "Unknown Source"
        },
        {
          "method": "org.eclipse.jdt.internal.core.builder.IncrementalImageBuilder.build",
          "source": "Unknown Source"
        },
        {
          "method": "org.aspectj.ajdt.internal.core.builder.AjBuildManager$IncrementalBuilder.build",
          "source": "Unknown Source"
        },
        {
          "method": "org.aspectj.ajdt.internal.core.builder.AjBuildManager.incrementalBuild",
          "source": "Unknown Source"
        },
        {
          "method": "org.aspectj.ajdt.ajc.AjdtCommand.repeatCommand",
          "source": "Unknown Source"
        },
        {
          "method": "org.aspectj.tools.ajc.Main.run",
          "source": "Unknown Source"
        },
        {
          "method": "org.aspectj.tools.ajc.Main.runMain",
          "source": "Unknown Source"
        },
        {
          "method": "org.aspectj.tools.ajc.Main.main",
          "source": "Unknown Source"
        }
      ],
      "number": 1,
      "commentIndex": 0,
      "bugId": "28807",
      "date": "2002-12-22T20:34:00+01:00",
      "product": "AspectJ",
      "component": "Compiler",
      "severity": "major"
    },
    {
      "exceptionType": "java.lang.NullPointerException",
      "elements": [
        {
          "method": "org.aspectj.weaver.CrosscuttingMembers.replaceWith",
          "source": "Unknown Source"
        },
        {
          "method": "org.aspectj.weaver.CrosscuttingMembersSet.addOrReplaceAspect",
          "source": "Unknown Source"
        },
        {
          "method": "org.aspectj.ajdt.internal.compiler.ast.AspectDeclaration.buildInterTypeAndPerClause",
          "source": "Unknown Source"
        },
        {
          "method": "org.aspectj.ajdt.internal.compiler.lookup.AjLookupEnvironment.buildInterTypeAndPerClause",
          "source": "Unknown Source"
        },
        {
          "method": "org.aspectj.ajdt.internal.compiler.lookup.AjLookupEnvironment.completeTypeBindings",
          "source": "Unknown Source"
        },
        {
          "method": "org.eclipse.jdt.internal.compiler.Compiler.beginToCompile",
          "source": "Unknown Source"
        },
        {
          "method": "org.eclipse.jdt.internal.compiler.Compiler.compile",
          "source": "Unknown Source"
        },
        {
          "method": "org.eclipse.jdt.internal.core.builder.AbstractImageBuilder.compile",
          "source": "Unknown Source"
        },
        {
          "method": "org.eclipse.jdt.internal.core.builder.AbstractImageBuilder.compile",
          "source": "Unknown Source"
        },
        {
          "method": "org.eclipse.jdt.internal.core.builder.IncrementalImageBuilder.build",
          "source": "Unknown Source"
        },
        {
          "method": "org.aspectj.ajdt.internal.core.builder.AjBuildManager$IncrementalBuilder.build",
          "source": "Unknown Source"
        },
        {
          "method": "org.aspectj.ajdt.internal.core.builder.AjBuildManager.incrementalBuild",
          "source": "Unknown Source"
        },
        {
          "method": "org.aspectj.ajdt.ajc.AjdtCommand.repeatCommand",
          "source": "Unknown Source"
        },
        {
          "method": "org.aspectj.tools.ajc.Main.run",
          "source": "Unknown Source"
        },
        {
          "method": "org.aspectj.tools.ajc.Main.runMain",
          "source": "Unknown Source"
        },
        {
          "method": "org.aspectj.tools.ajc.Main.main",
          "source": "Unknown Source"
        }
      ],
      "number": 2,
      "commentIndex": 0,
      "bugId": "28807",
      "date": "2002-12-22T20:34:00+01:00",
      "product": "AspectJ",
      "component": "Compiler",
      "severity": "major"
    }
  ],
  "groupId": "28807",
  "bugId": "28807",
  "date": "2002-12-22T20:34:00+01:00",
  "product": "AspectJ",
  "component": "Compiler",
  "severity": "major"
}