{
  "comments": [
    "Installed eclipse on my win2k system (win2k professional).  Did not try to do \nsource build or anything like that.  Eclipse will not start, the following \nmessage appears in the log.\n\n!SESSION ----------------------------------------------------------------------\n!ENTRY org.eclipse.core.launcher 4 0 Dec 22, 2002 20:33:02.670\n!MESSAGE Exception launching the Eclipse Platform:\n!STACK\njava.lang.RuntimeException: Could not find bootstrap code. Check location of \nboot plug-in or specify -boot.\n\tat org.eclipse.core.launcher.Main.searchForBoot(Main.java:425)\n\tat org.eclipse.core.launcher.Main.getBootPath(Main.java:395)\n\tat org.eclipse.core.launcher.Main.basicRun(Main.java:238)\n\tat org.eclipse.core.launcher.Main.run(Main.java:698)\n\tat org.eclipse.core.launcher.Main.main(Main.java:534)\n\nSymptoms seem similar to 19046 but I noticed no strangely cased file names,\nall file names are in all lower case.\n\nAlso of course the system is not Win98.\n\n\nspecifying the startup command as eclipse c:\\eclipse does not help.\n\nIs the problem that it for whatever reason cannot find boot.jar and startup.jar\n\nThe jdk is 1.3.1, found in c:\\jdk1.3.1, JAVA_HOME is set up and does point\nto this place.",
    "Is your eclipse installation contained is a folder containing non-alphanumeric \ncharacters?  If yes, this is a duplicate of bug 28036.\n\n",
    "No further information from  originator, closing.  Please reopen if you have \nmore information on this bug."
  ],
  "commentCreationDates": [
    "2002-12-23T02:15:24+01:00",
    "2003-01-02T15:30:38+01:00",
    "2003-01-09T14:12:17+01:00"
  ],
  "traces": [
    {
      "exceptionType": "java.lang.RuntimeException",
      "message": "Could not find bootstrap code. Check location of  boot plug-in or specify -boot.",
      "elements": [
        {
          "method": "org.eclipse.core.launcher.Main.searchForBoot",
          "source": "Main.java:425"
        },
        {
          "method": "org.eclipse.core.launcher.Main.getBootPath",
          "source": "Main.java:395"
        },
        {
          "method": "org.eclipse.core.launcher.Main.basicRun",
          "source": "Main.java:238"
        },
        {
          "method": "org.eclipse.core.launcher.Main.run",
          "source": "Main.java:698"
        },
        {
          "method": "org.eclipse.core.launcher.Main.main",
          "source": "Main.java:534"
        }
      ],
      "number": 0,
      "commentIndex": 0,
      "bugId": "28813",
      "date": "2002-12-23T02:15:24+01:00",
      "product": "Platform",
      "component": "Resources",
      "severity": "normal"
    }
  ],
  "groupId": "28813",
  "bugId": "28813",
  "date": "2002-12-23T02:15:24+01:00",
  "product": "Platform",
  "component": "Resources",
  "severity": "normal"
}