{
  "comments": [
    "When trying to build a class I get the following stack trace.\n\n!ENTRY org.eclipse.core.resources 4 2 dec 23, 2002 08:52:54.939\n!MESSAGE Problems occurred when invoking code from plug-in: \"org.eclipse.core.re\nsources\".\n!STACK 0\njava.lang.NullPointerException\n        at org.eclipse.jdt.internal.compiler.ClassFile.addFieldInfo\n(ClassFile.java:434)\n        at org.eclipse.jdt.internal.compiler.ClassFile.addFieldInfos\n(ClassFile.java:579)\n        at org.eclipse.jdt.internal.compiler.ast.TypeDeclaration.generateCode\n(TypeDeclaration.java:694)\n        at org.eclipse.jdt.internal.compiler.ast.TypeDeclaration.generateCode\n(TypeDeclaration.java:762)\n        at org.eclipse.jdt.internal.compiler.ast.TypeDeclaration.generateCode\n(TypeDeclaration.java:709)\n        at org.eclipse.jdt.internal.compiler.ast.TypeDeclaration.generateCode\n(TypeDeclaration.java:770)\n        at  \norg.eclipse.jdt.internal.compiler.ast.CompilationUnitDeclaration.generateCode\n(CompilationUnitDeclaration.java:158)\n        at org.eclipse.jdt.internal.compiler.Compiler.process(Compiler.java:543)\n        at org.eclipse.jdt.internal.compiler.Compiler.compile(Compiler.java:337)\n\n        at org.eclipse.jdt.internal.core.builder.AbstractImageBuilder.compile(Ab\nstractImageBuilder.java:194)\n        at org.eclipse.jdt.internal.core.builder.AbstractImageBuilder.compile(Ab\nstractImageBuilder.java:144)\n        at org.eclipse.jdt.internal.core.builder.BatchImageBuilder.build(BatchIm\nageBuilder.java:49)\n        at org.eclipse.jdt.internal.core.builder.JavaBuilder.buildAll(JavaBuilde\nr.java:179)\n        at org.eclipse.jdt.internal.core.builder.JavaBuilder.build(JavaBuilder.j\nava:102)\n        at org.eclipse.core.internal.events.BuildManager$2.run(BuildManager.java\n:384)\n        at org.eclipse.core.internal.runtime.InternalPlatform.run(InternalPlatfo\nrm.java:852)\n        at org.eclipse.core.runtime.Platform.run(Platform.java:413)\n        at org.eclipse.core.internal.events.BuildManager.basicBuild(BuildManager\n.java:120)\n        at org.eclipse.core.internal.events.BuildManager.basicBuild(BuildManager\n.java:176)\n        at org.eclipse.core.internal.events.BuildManager.basicBuild(BuildManager\n.java:186)\n        at org.eclipse.core.internal.events.BuildManager$1.run(BuildManager.java\n:146)\n        at org.eclipse.core.internal.runtime.InternalPlatform.run(InternalPlatfo\nrm.java:852)\n        at org.eclipse.core.runtime.Platform.run(Platform.java:413)\n        at org.eclipse.core.internal.events.BuildManager.basicBuild(BuildManager\n.java:160)\n        at org.eclipse.core.internal.events.BuildManager.build(BuildManager.java\n:232)\n        at org.eclipse.core.internal.resources.Project.build(Project.java:87)\n        at org.eclipse.ui.actions.BuildAction.invokeOperation(BuildAction.java:1\n56)\n        at org.eclipse.ui.actions.WorkspaceAction.execute(WorkspaceAction.java:1\n11)\n        at org.eclipse.ui.actions.WorkspaceAction$1.execute(WorkspaceAction.java\n:268)\n        at org.eclipse.ui.actions.WorkspaceModifyOperation$1.run(WorkspaceModify\nOperation.java:65)\n        at org.eclipse.core.internal.resources.Workspace.run(Workspace.java:1564\n)\n        at org.eclipse.ui.actions.WorkspaceModifyOperation.run(WorkspaceModifyOp\neration.java:79)\n        at org.eclipse.jface.operation.ModalContext$ModalContextThread.run(Modal\nContext.java:95)",
    "\n\n*** This bug has been marked as a duplicate of 28750 ***"
  ],
  "commentCreationDates": [
    "2002-12-23T07:38:36+01:00",
    "2002-12-24T14:59:54+01:00"
  ],
  "traces": [
    {
      "exceptionType": "java.lang.NullPointerException",
      "elements": [
        {
          "method": "org.eclipse.jdt.internal.compiler.ClassFile.addFieldInfo",
          "source": "ClassFile.java:434"
        },
        {
          "method": "org.eclipse.jdt.internal.compiler.ClassFile.addFieldInfos",
          "source": "ClassFile.java:579"
        },
        {
          "method": "org.eclipse.jdt.internal.compiler.ast.TypeDeclaration.generateCode",
          "source": "TypeDeclaration.java:694"
        },
        {
          "method": "org.eclipse.jdt.internal.compiler.ast.TypeDeclaration.generateCode",
          "source": "TypeDeclaration.java:762"
        },
        {
          "method": "org.eclipse.jdt.internal.compiler.ast.TypeDeclaration.generateCode",
          "source": "TypeDeclaration.java:709"
        },
        {
          "method": "org.eclipse.jdt.internal.compiler.ast.TypeDeclaration.generateCode",
          "source": "TypeDeclaration.java:770"
        },
        {
          "method": "org.eclipse.jdt.internal.compiler.ast.CompilationUnitDeclaration.generateCode",
          "source": "CompilationUnitDeclaration.java:158"
        },
        {
          "method": "org.eclipse.jdt.internal.compiler.Compiler.process",
          "source": "Compiler.java:543"
        },
        {
          "method": "org.eclipse.jdt.internal.compiler.Compiler.compile",
          "source": "Compiler.java:337"
        },
        {
          "method": "org.eclipse.jdt.internal.core.builder.AbstractImageBuilder.compile",
          "source": "Ab stractImageBuilder.java:194"
        },
        {
          "method": "org.eclipse.jdt.internal.core.builder.AbstractImageBuilder.compile",
          "source": "Ab stractImageBuilder.java:144"
        },
        {
          "method": "org.eclipse.jdt.internal.core.builder.BatchImageBuilder.build",
          "source": "BatchIm ageBuilder.java:49"
        },
        {
          "method": "org.eclipse.jdt.internal.core.builder.JavaBuilder.buildAll",
          "source": "JavaBuilde r.java:179"
        },
        {
          "method": "org.eclipse.jdt.internal.core.builder.JavaBuilder.build",
          "source": "JavaBuilder.j ava:102"
        },
        {
          "method": "org.eclipse.core.internal.events.BuildManager$2.run",
          "source": "BuildManager.java :384"
        },
        {
          "method": "org.eclipse.core.internal.runtime.InternalPlatform.run",
          "source": "InternalPlatfo rm.java:852"
        },
        {
          "method": "org.eclipse.core.runtime.Platform.run",
          "source": "Platform.java:413"
        },
        {
          "method": "org.eclipse.core.internal.events.BuildManager.basicBuild",
          "source": "BuildManager .java:120"
        },
        {
          "method": "org.eclipse.core.internal.events.BuildManager.basicBuild",
          "source": "BuildManager .java:176"
        },
        {
          "method": "org.eclipse.core.internal.events.BuildManager.basicBuild",
          "source": "BuildManager .java:186"
        },
        {
          "method": "org.eclipse.core.internal.events.BuildManager$1.run",
          "source": "BuildManager.java :146"
        },
        {
          "method": "org.eclipse.core.internal.runtime.InternalPlatform.run",
          "source": "InternalPlatfo rm.java:852"
        },
        {
          "method": "org.eclipse.core.runtime.Platform.run",
          "source": "Platform.java:413"
        },
        {
          "method": "org.eclipse.core.internal.events.BuildManager.basicBuild",
          "source": "BuildManager .java:160"
        },
        {
          "method": "org.eclipse.core.internal.events.BuildManager.build",
          "source": "BuildManager.java :232"
        },
        {
          "method": "org.eclipse.core.internal.resources.Project.build",
          "source": "Project.java:87"
        },
        {
          "method": "org.eclipse.ui.actions.BuildAction.invokeOperation",
          "source": "BuildAction.java:1 56"
        },
        {
          "method": "org.eclipse.ui.actions.WorkspaceAction.execute",
          "source": "WorkspaceAction.java:1 11"
        },
        {
          "method": "org.eclipse.ui.actions.WorkspaceAction$1.execute",
          "source": "WorkspaceAction.java :268"
        },
        {
          "method": "org.eclipse.ui.actions.WorkspaceModifyOperation$1.run",
          "source": "WorkspaceModify Operation.java:65"
        },
        {
          "method": "org.eclipse.core.internal.resources.Workspace.run",
          "source": "Workspace.java:1564 "
        },
        {
          "method": "org.eclipse.ui.actions.WorkspaceModifyOperation.run",
          "source": "WorkspaceModifyOp eration.java:79"
        },
        {
          "method": "org.eclipse.jface.operation.ModalContext$ModalContextThread.run",
          "source": "Modal Context.java:95"
        }
      ],
      "number": 0,
      "commentIndex": 0,
      "bugId": "28819",
      "duplicateId": "28750",
      "date": "2002-12-23T07:38:36+01:00",
      "product": "JDT",
      "component": "Core",
      "severity": "major"
    }
  ],
  "groupId": "28750",
  "bugId": "28819",
  "duplicateId": "28750",
  "date": "2002-12-23T07:38:36+01:00",
  "product": "JDT",
  "component": "Core",
  "severity": "major"
}