{
  "comments": [
    "If you don\u0027t find the exception below in a bug, please add a new bug\nTo make the bug a priority, please include a test program\nthat can reproduce this exception.\nbad non-abstract method with no code: private native int \nnativeMessagePumpInitialize() on public class \nplc.comm.pvi.PviCom$LinkEventHandlerImpl\nbad non-abstract method with no code: private native int \nnativeMessagePumpInitialize() on public class \nplc.comm.pvi.PviCom$LinkEventHandlerImpl\njava.lang.RuntimeException: bad non-abstract method with no code: private \nnative int nativeMessagePumpInitialize() on public class \nplc.comm.pvi.PviCom$LinkEventHandlerImpl\n        at org.aspectj.weaver.bcel.LazyMethodGen.\u003cinit\u003e(Unknown Source)\n        at org.aspectj.weaver.bcel.LazyClassGen.\u003cinit\u003e(Unknown Source)\n        at org.aspectj.weaver.bcel.BcelObjectType.getLazyClassGen(Unknown \nSource)\n        at org.aspectj.weaver.bcel.BcelWeaver.weave(Unknown Source)\n        at org.aspectj.weaver.bcel.BcelWeaver.weave(Unknown Source)\n        at \norg.aspectj.ajdt.internal.core.builder.AjBuildManager.weaveAndGenerateClassFiles\n(Unknown Source)\n        at org.aspectj.ajdt.internal.core.builder.AjBuildManager.batchBuild\n(Unknown Source)\n        at org.aspectj.ajdt.ajc.AjdtCommand.runCommand(Unknown Source)\n        at org.aspectj.tools.ajc.Main.run(Unknown Source)\n        at org.aspectj.tools.ajc.Main.runMain(Unknown Source)\n        at org.aspectj.tools.ajc.Main.main(Unknown Source)",
    "The problem was an over-eager debugging guard that throws an exception when\ngiven seriously malformed classfiles.  Seriously malformed, in this particular\ncase, being non-abstract with no code.  This has now been properly relaxed to\nnon-(abstract or native) with no code."
  ],
  "commentCreationDates": [
    "2002-12-30T21:40:03+01:00",
    "2003-01-14T20:06:20+01:00"
  ],
  "traces": [
    {
      "exceptionType": "java.lang.RuntimeException",
      "message": "bad non-abstract method with no code: private  native int nativeMessagePumpInitialize() on public class  plc.comm.pvi.PviCom$LinkEventHandlerImpl",
      "elements": [
        {
          "method": "org.aspectj.weaver.bcel.LazyMethodGen.\u003cinit\u003e",
          "source": "Unknown Source"
        },
        {
          "method": "org.aspectj.weaver.bcel.LazyClassGen.\u003cinit\u003e",
          "source": "Unknown Source"
        },
        {
          "method": "org.aspectj.weaver.bcel.BcelObjectType.getLazyClassGen",
          "source": "Unknown  Source"
        },
        {
          "method": "org.aspectj.weaver.bcel.BcelWeaver.weave",
          "source": "Unknown Source"
        },
        {
          "method": "org.aspectj.weaver.bcel.BcelWeaver.weave",
          "source": "Unknown Source"
        },
        {
          "method": "org.aspectj.ajdt.internal.core.builder.AjBuildManager.weaveAndGenerateClassFiles",
          "source": "Unknown Source"
        },
        {
          "method": "org.aspectj.ajdt.internal.core.builder.AjBuildManager.batchBuild",
          "source": "Unknown Source"
        },
        {
          "method": "org.aspectj.ajdt.ajc.AjdtCommand.runCommand",
          "source": "Unknown Source"
        },
        {
          "method": "org.aspectj.tools.ajc.Main.run",
          "source": "Unknown Source"
        },
        {
          "method": "org.aspectj.tools.ajc.Main.runMain",
          "source": "Unknown Source"
        },
        {
          "method": "org.aspectj.tools.ajc.Main.main",
          "source": "Unknown Source"
        }
      ],
      "number": 0,
      "commentIndex": 0,
      "bugId": "28919",
      "date": "2002-12-30T21:40:03+01:00",
      "product": "AspectJ",
      "component": "Compiler",
      "severity": "critical"
    }
  ],
  "groupId": "28919",
  "bugId": "28919",
  "date": "2002-12-30T21:40:03+01:00",
  "product": "AspectJ",
  "component": "Compiler",
  "severity": "critical"
}