{
  "comments": [
    "I have got this problem in trying to compile one of my projects with M4. The\nsame code has been correctly compiled with 2.0.2 on windows. I was not able to \nisolate the class that causes the problem, the same source file put in a\ndifferent project does not cause problem.\nHope you have enough info to isolate the bug...\n\njava.version\u003d1.4.1\njava.vendor\u003dBlackdown Java-Linux Team\nBootLoader constants: OS\u003dlinux, ARCH\u003dx86, WS\u003dgtk, NL\u003den_US\nCommand-line arguments: -os linux -ws gtk -arch x86 -data\n/home/cozzi/eclipse/workspace -install file:\n/home/cozzi/eclipse/\n!ENTRY org.eclipse.core.resources 4 2 Dec 23, 2002 15:31:18.824\n!MESSAGE Problems occurred when invoking code from plug-in:\n\"org.eclipse.core.resources\".\n!STACK 0\njava.lang.NullPointerException\n        at\norg.eclipse.jdt.internal.compiler.ClassFile.addFieldInfo(ClassFile.java:434)\n        at\norg.eclipse.jdt.internal.compiler.ClassFile.addFieldInfos(ClassFile.java:579)\n        at\norg.eclipse.jdt.internal.compiler.ast.TypeDeclaration.generateCode(TypeDeclaration.java:694\n)\n        at\norg.eclipse.jdt.internal.compiler.ast.TypeDeclaration.generateCode(TypeDeclaration.java:762\n)\n        at\norg.eclipse.jdt.internal.compiler.ast.TypeDeclaration.generateCode(TypeDeclaration.java:709\n)\n        at\norg.eclipse.jdt.internal.compiler.ast.TypeDeclaration.generateCode(TypeDeclaration.java:770\n)\n        at\norg.eclipse.jdt.internal.compiler.ast.CompilationUnitDeclaration.generateCode(CompilationUn\nitDeclaration.java:158)\n        at org.eclipse.jdt.internal.compiler.Compiler.process(Compiler.java:543)\n        at org.eclipse.jdt.internal.compiler.Compiler.compile(Compiler.java:337)\n        at\norg.eclipse.jdt.internal.core.builder.AbstractImageBuilder.compile(AbstractImageBuilder.jav\na:194)\n        at\norg.eclipse.jdt.internal.core.builder.AbstractImageBuilder.compile(AbstractImageBuilder.jav\na:144)\n        at\norg.eclipse.jdt.internal.core.builder.IncrementalImageBuilder.build(IncrementalImageBuilder\n.java:106)\n        at\norg.eclipse.jdt.internal.core.builder.JavaBuilder.buildDeltas(JavaBuilder.java:190)\n        at\norg.eclipse.jdt.internal.core.builder.JavaBuilder.build(JavaBuilder.java:118)\n        at\norg.eclipse.core.internal.events.BuildManager$2.run(BuildManager.java:384)\n        at\norg.eclipse.core.internal.runtime.InternalPlatform.run(InternalPlatform.java:852)\n        at org.eclipse.core.runtime.Platform.run(Platform.java:413)\n        at\norg.eclipse.core.internal.events.BuildManager.basicBuild(BuildManager.java:120)\n        at\norg.eclipse.core.internal.events.BuildManager.basicBuild(BuildManager.java:176)\n        at\norg.eclipse.core.internal.events.BuildManager.basicBuild(BuildManager.java:186)\n        at\norg.eclipse.core.internal.events.BuildManager$1.run(BuildManager.java:146)\n        at\norg.eclipse.core.internal.runtime.InternalPlatform.run(InternalPlatform.java:852)\n        at org.eclipse.core.runtime.Platform.run(Platform.java:413)\n        at\norg.eclipse.core.internal.events.BuildManager.basicBuild(BuildManager.java:160)\n        at\norg.eclipse.core.internal.events.BuildManager.build(BuildManager.java:211)\n        at\norg.eclipse.core.internal.resources.Workspace.endOperation(Workspace.java:861)\n        at org.eclipse.core.internal.resources.Workspace.run(Workspace.java:1569)\n   at\norg.eclipse.ui.actions.WorkspaceModifyOperation.run(WorkspaceModifyOperation.java:79)\n        at\norg.eclipse.jface.operation.ModalContext$ModalContextThread.run(ModalContext.java:95)",
    "\n\n*** This bug has been marked as a duplicate of 28801 ***"
  ],
  "commentCreationDates": [
    "2002-12-30T23:06:51+01:00",
    "2003-01-02T17:19:59+01:00"
  ],
  "traces": [
    {
      "exceptionType": "java.lang.NullPointerException",
      "elements": [
        {
          "method": "org.eclipse.jdt.internal.compiler.ClassFile.addFieldInfo",
          "source": "ClassFile.java:434"
        },
        {
          "method": "org.eclipse.jdt.internal.compiler.ClassFile.addFieldInfos",
          "source": "ClassFile.java:579"
        },
        {
          "method": "org.eclipse.jdt.internal.compiler.ast.TypeDeclaration.generateCode",
          "source": "TypeDeclaration.java:694 "
        },
        {
          "method": "org.eclipse.jdt.internal.compiler.ast.TypeDeclaration.generateCode",
          "source": "TypeDeclaration.java:762 "
        },
        {
          "method": "org.eclipse.jdt.internal.compiler.ast.TypeDeclaration.generateCode",
          "source": "TypeDeclaration.java:709 "
        },
        {
          "method": "org.eclipse.jdt.internal.compiler.ast.TypeDeclaration.generateCode",
          "source": "TypeDeclaration.java:770 "
        },
        {
          "method": "org.eclipse.jdt.internal.compiler.ast.CompilationUnitDeclaration.generateCode",
          "source": "CompilationUn itDeclaration.java:158"
        },
        {
          "method": "org.eclipse.jdt.internal.compiler.Compiler.process",
          "source": "Compiler.java:543"
        },
        {
          "method": "org.eclipse.jdt.internal.compiler.Compiler.compile",
          "source": "Compiler.java:337"
        },
        {
          "method": "org.eclipse.jdt.internal.core.builder.AbstractImageBuilder.compile",
          "source": "AbstractImageBuilder.jav a:194"
        },
        {
          "method": "org.eclipse.jdt.internal.core.builder.AbstractImageBuilder.compile",
          "source": "AbstractImageBuilder.jav a:144"
        },
        {
          "method": "org.eclipse.jdt.internal.core.builder.IncrementalImageBuilder.build",
          "source": "IncrementalImageBuilder .java:106"
        },
        {
          "method": "org.eclipse.jdt.internal.core.builder.JavaBuilder.buildDeltas",
          "source": "JavaBuilder.java:190"
        },
        {
          "method": "org.eclipse.jdt.internal.core.builder.JavaBuilder.build",
          "source": "JavaBuilder.java:118"
        },
        {
          "method": "org.eclipse.core.internal.events.BuildManager$2.run",
          "source": "BuildManager.java:384"
        },
        {
          "method": "org.eclipse.core.internal.runtime.InternalPlatform.run",
          "source": "InternalPlatform.java:852"
        },
        {
          "method": "org.eclipse.core.runtime.Platform.run",
          "source": "Platform.java:413"
        },
        {
          "method": "org.eclipse.core.internal.events.BuildManager.basicBuild",
          "source": "BuildManager.java:120"
        },
        {
          "method": "org.eclipse.core.internal.events.BuildManager.basicBuild",
          "source": "BuildManager.java:176"
        },
        {
          "method": "org.eclipse.core.internal.events.BuildManager.basicBuild",
          "source": "BuildManager.java:186"
        },
        {
          "method": "org.eclipse.core.internal.events.BuildManager$1.run",
          "source": "BuildManager.java:146"
        },
        {
          "method": "org.eclipse.core.internal.runtime.InternalPlatform.run",
          "source": "InternalPlatform.java:852"
        },
        {
          "method": "org.eclipse.core.runtime.Platform.run",
          "source": "Platform.java:413"
        },
        {
          "method": "org.eclipse.core.internal.events.BuildManager.basicBuild",
          "source": "BuildManager.java:160"
        },
        {
          "method": "org.eclipse.core.internal.events.BuildManager.build",
          "source": "BuildManager.java:211"
        },
        {
          "method": "org.eclipse.core.internal.resources.Workspace.endOperation",
          "source": "Workspace.java:861"
        },
        {
          "method": "org.eclipse.core.internal.resources.Workspace.run",
          "source": "Workspace.java:1569"
        },
        {
          "method": "org.eclipse.ui.actions.WorkspaceModifyOperation.run",
          "source": "WorkspaceModifyOperation.java:79"
        },
        {
          "method": "org.eclipse.jface.operation.ModalContext$ModalContextThread.run",
          "source": "ModalContext.java:95"
        }
      ],
      "number": 0,
      "commentIndex": 0,
      "bugId": "28920",
      "duplicateId": "28801",
      "date": "2002-12-30T23:06:51+01:00",
      "product": "JDT",
      "component": "Core",
      "severity": "normal"
    }
  ],
  "groupId": "28750",
  "bugId": "28920",
  "duplicateId": "28801",
  "date": "2002-12-30T23:06:51+01:00",
  "product": "JDT",
  "component": "Core",
  "severity": "normal"
}