{
  "comments": [
    "I do not reproduceable steps, sorry.\n\n\n!ENTRY org.eclipse.ui 4 0 Jan 09, 2003 16:47:46.170\n!MESSAGE Invalid range argument\n!STACK 0\njava.lang.IllegalArgumentException: Invalid range argument\n        at org.eclipse.jface.text.TextViewer.internalRevealRange(TextViewer.java\n:2246)\n        at org.eclipse.jface.text.TextViewer.revealRange(TextViewer.java:2152)\n        at org.eclipse.jface.text.source.SourceViewer.setRangeIndication(SourceV\niewer.java:489)\n        at org.eclipse.ui.texteditor.AbstractTextEditor.setHighlightRange(Abstra\nctTextEditor.java:3738)\n        at org.eclipse.jdt.internal.ui.javaeditor.JavaEditor.adjustHighlightRang\ne(JavaEditor.java:1319)\n        at org.eclipse.ui.texteditor.AbstractTextEditor.selectAndReveal(Abstract\nTextEditor.java:3801)\n        at org.eclipse.jdt.internal.ui.javaeditor.CompilationUnitEditor.restoreS\nelection(CompilationUnitEditor.java:2105)\n        at org.eclipse.ui.texteditor.AbstractTextEditor$ElementStateListener.ele\nmentContentReplaced(AbstractTextEditor.java:275)\n        at org.eclipse.ui.texteditor.AbstractDocumentProvider.fireElementContent\nReplaced(AbstractDocumentProvider.java:543)\n        at org.eclipse.jdt.internal.ui.javaeditor.CompilationUnitDocumentProvide\nr.resetDocument(CompilationUnitDocumentProvider.java:1050)\n        at org.eclipse.ui.texteditor.AbstractTextEditor.doRevertToSaved(Abstract\nTextEditor.java:2964)\n        at org.eclipse.ui.texteditor.StatusTextEditor.doRevertToSaved(StatusText\nEditor.java:170)\n        at org.eclipse.ui.editors.text.DefaultEncodingSupport$2.run(DefaultEncod\ningSupport.java:122)\n        at org.eclipse.swt.custom.BusyIndicator.showWhile(BusyIndicator.java:65)\n\n        at org.eclipse.ui.editors.text.DefaultEncodingSupport.setEncoding(Defaul\ntEncodingSupport.java:128)\n        at org.eclipse.ui.editors.text.DefaultEncodingSupport.setEncoding(Defaul\ntEncodingSupport.java:141)\n        at org.eclipse.ui.editors.text.EncodingActionGroup$PredefinedEncodingAct\nion.run(EncodingActionGroup.java:103)\n        at org.eclipse.ui.texteditor.RetargetTextEditorAction.run(RetargetTextEd\nitorAction.java:137)\n        at org.eclipse.jface.action.Action.runWithEvent(Action.java:769)\n        at org.eclipse.jface.action.ActionContributionItem.handleWidgetSelection\n(ActionContributionItem.java:411)\n        at org.eclipse.jface.action.ActionContributionItem.handleWidgetEvent(Act\nionContributionItem.java:365)\n        at org.eclipse.jface.action.ActionContributionItem.access$0(ActionContri\nbutionItem.java:356)\n        at org.eclipse.jface.action.ActionContributionItem$ActionListener.handle\nEvent(ActionContributionItem.java:48)\n        at org.eclipse.swt.widgets.EventTable.sendEvent(EventTable.java:77)\n        at org.eclipse.swt.widgets.Widget.sendEvent(Widget.java:825)\n        at org.eclipse.swt.widgets.Display.runDeferredEvents(Display.java:1692)\n        at org.eclipse.swt.widgets.Display.readAndDispatch(Display.java:1410)\n        at org.eclipse.ui.internal.Workbench.runEventLoop(Workbench.java:1467)\n        at org.eclipse.ui.internal.Workbench.run(Workbench.java:1450)\n        at org.eclipse.core.internal.boot.InternalBootLoader.run(InternalBootLoa\nder.java:845)\n        at org.eclipse.core.boot.BootLoader.run(BootLoader.java:462)\n        at sun.reflect.NativeMethodAccessorImpl.invoke0(Native Method)\n        at sun.reflect.NativeMethodAccessorImpl.invoke(NativeMethodAccessorImpl.\njava:39)\n        at sun.reflect.DelegatingMethodAccessorImpl.invoke(DelegatingMethodAcces\nsorImpl.java:25)\n        at java.lang.reflect.Method.invoke(Method.java:324)\n        at org.eclipse.core.launcher.Main.basicRun(Main.java:247)\n        at org.eclipse.core.launcher.Main.run(Main.java:703)\n        at org.eclipse.core.launcher.Main.main(Main.java:539)\nInvalid range argument",
    "Build I20030206.",
    "start verifying"
  ],
  "commentCreationDates": [
    "2003-01-09T18:00:57+01:00",
    "2003-02-05T18:51:36+01:00",
    "2003-02-27T12:58:54+01:00"
  ],
  "traces": [
    {
      "exceptionType": "java.lang.IllegalArgumentException",
      "message": "Invalid range argument",
      "elements": [
        {
          "method": "org.eclipse.jface.text.TextViewer.internalRevealRange",
          "source": "TextViewer.java :2246"
        },
        {
          "method": "org.eclipse.jface.text.TextViewer.revealRange",
          "source": "TextViewer.java:2152"
        },
        {
          "method": "org.eclipse.jface.text.source.SourceViewer.setRangeIndication",
          "source": "SourceV iewer.java:489"
        },
        {
          "method": "org.eclipse.ui.texteditor.AbstractTextEditor.setHighlightRange",
          "source": "Abstra ctTextEditor.java:3738"
        },
        {
          "method": "org.eclipse.jdt.internal.ui.javaeditor.JavaEditor.adjustHighlightRange",
          "source": "JavaEditor.java:1319"
        },
        {
          "method": "org.eclipse.ui.texteditor.AbstractTextEditor.selectAndReveal",
          "source": "Abstract TextEditor.java:3801"
        },
        {
          "method": "org.eclipse.jdt.internal.ui.javaeditor.CompilationUnitEditor.restoreSelection",
          "source": "CompilationUnitEditor.java:2105"
        },
        {
          "method": "org.eclipse.ui.texteditor.AbstractTextEditor$ElementStateListener.elementContentReplaced",
          "source": "AbstractTextEditor.java:275"
        },
        {
          "method": "org.eclipse.ui.texteditor.AbstractDocumentProvider.fireElementContentReplaced",
          "source": "AbstractDocumentProvider.java:543"
        },
        {
          "method": "org.eclipse.jdt.internal.ui.javaeditor.CompilationUnitDocumentProvider.resetDocument",
          "source": "CompilationUnitDocumentProvider.java:1050"
        },
        {
          "method": "org.eclipse.ui.texteditor.AbstractTextEditor.doRevertToSaved",
          "source": "Abstract TextEditor.java:2964"
        },
        {
          "method": "org.eclipse.ui.texteditor.StatusTextEditor.doRevertToSaved",
          "source": "StatusText Editor.java:170"
        },
        {
          "method": "org.eclipse.ui.editors.text.DefaultEncodingSupport$2.run",
          "source": "DefaultEncod ingSupport.java:122"
        },
        {
          "method": "org.eclipse.swt.custom.BusyIndicator.showWhile",
          "source": "BusyIndicator.java:65"
        },
        {
          "method": "org.eclipse.ui.editors.text.DefaultEncodingSupport.setEncoding",
          "source": "Defaul tEncodingSupport.java:128"
        },
        {
          "method": "org.eclipse.ui.editors.text.DefaultEncodingSupport.setEncoding",
          "source": "Defaul tEncodingSupport.java:141"
        },
        {
          "method": "org.eclipse.ui.editors.text.EncodingActionGroup$PredefinedEncodingAction.run",
          "source": "EncodingActionGroup.java:103"
        },
        {
          "method": "org.eclipse.ui.texteditor.RetargetTextEditorAction.run",
          "source": "RetargetTextEd itorAction.java:137"
        },
        {
          "method": "org.eclipse.jface.action.Action.runWithEvent",
          "source": "Action.java:769"
        },
        {
          "method": "org.eclipse.jface.action.ActionContributionItem.handleWidgetSelection",
          "source": "ActionContributionItem.java:411"
        },
        {
          "method": "org.eclipse.jface.action.ActionContributionItem.handleWidgetEvent",
          "source": "Act ionContributionItem.java:365"
        },
        {
          "method": "org.eclipse.jface.action.ActionContributionItem.access$0",
          "source": "ActionContri butionItem.java:356"
        },
        {
          "method": "org.eclipse.jface.action.ActionContributionItem$ActionListener.handleEvent",
          "source": "ActionContributionItem.java:48"
        },
        {
          "method": "org.eclipse.swt.widgets.EventTable.sendEvent",
          "source": "EventTable.java:77"
        },
        {
          "method": "org.eclipse.swt.widgets.Widget.sendEvent",
          "source": "Widget.java:825"
        },
        {
          "method": "org.eclipse.swt.widgets.Display.runDeferredEvents",
          "source": "Display.java:1692"
        },
        {
          "method": "org.eclipse.swt.widgets.Display.readAndDispatch",
          "source": "Display.java:1410"
        },
        {
          "method": "org.eclipse.ui.internal.Workbench.runEventLoop",
          "source": "Workbench.java:1467"
        },
        {
          "method": "org.eclipse.ui.internal.Workbench.run",
          "source": "Workbench.java:1450"
        },
        {
          "method": "org.eclipse.core.internal.boot.InternalBootLoader.run",
          "source": "InternalBootLoa der.java:845"
        },
        {
          "method": "org.eclipse.core.boot.BootLoader.run",
          "source": "BootLoader.java:462"
        },
        {
          "method": "sun.reflect.NativeMethodAccessorImpl.invoke0",
          "source": "Native Method"
        },
        {
          "method": "sun.reflect.NativeMethodAccessorImpl.invoke",
          "source": "NativeMethodAccessorImpl. java:39"
        },
        {
          "method": "sun.reflect.DelegatingMethodAccessorImpl.invoke",
          "source": "DelegatingMethodAcces sorImpl.java:25"
        },
        {
          "method": "java.lang.reflect.Method.invoke",
          "source": "Method.java:324"
        },
        {
          "method": "org.eclipse.core.launcher.Main.basicRun",
          "source": "Main.java:247"
        },
        {
          "method": "org.eclipse.core.launcher.Main.run",
          "source": "Main.java:703"
        },
        {
          "method": "org.eclipse.core.launcher.Main.main",
          "source": "Main.java:539"
        }
      ],
      "number": 0,
      "commentIndex": 0,
      "bugId": "29238",
      "date": "2003-01-09T18:00:57+01:00",
      "product": "JDT",
      "component": "Text",
      "severity": "normal"
    }
  ],
  "groupId": "29238",
  "bugId": "29238",
  "date": "2003-01-09T18:00:57+01:00",
  "product": "JDT",
  "component": "Text",
  "severity": "normal"
}