{
  "comments": [
    "In build 20030107 I get the following exception when running an Ant script.\n\n!ENTRY org.eclipse.core.runtime 4 2 Jan 13, 2003 10:39:11.317\n!MESSAGE Plug-in org.eclipse.ui.externaltools was unable to load class org.eclip\nse.ui.externaltools.internal.ant.logger.TaskLineTracker.\n!STACK 0\njava.lang.ClassNotFoundException: org.eclipse.ui.externaltools.internal.ant.logg\ner.TaskLineTracker\n        at org.eclipse.core.internal.boot.DelegatingURLClassLoader.loadClass(Del\negatingURLClassLoader.java:875)\n        at java.lang.ClassLoader.loadClass(ClassLoader.java:255)\n        at org.eclipse.core.internal.plugins.PluginDescriptor.createExecutableEx\ntension(PluginDescriptor.java:130)\n        at org.eclipse.core.internal.plugins.PluginDescriptor.createExecutableEx\ntension(PluginDescriptor.java:167)\n        at org.eclipse.core.internal.plugins.ConfigurationElement.createExecutab\nleExtension(ConfigurationElement.java:103)\n        at org.eclipse.debug.internal.ui.views.console.ConsoleDocumentManager.ne\nwLineNotifier(ConsoleDocumentManager.java:372)\n        at org.eclipse.debug.internal.ui.views.console.ConsoleDocumentProvider.g\netLineNotifier(ConsoleDocumentProvider.java:100)\n        at org.eclipse.debug.internal.ui.views.console.ConsoleDocumentProvider.c\nreateDocument(ConsoleDocumentProvider.java:35)\n        at org.eclipse.ui.texteditor.AbstractDocumentProvider.createElementInfo(\nAbstractDocumentProvider.java:236)\n        at org.eclipse.ui.texteditor.AbstractDocumentProvider.connect(AbstractDo\ncumentProvider.java:302)\n        at org.eclipse.debug.internal.ui.views.console.ConsoleDocumentManager$2.\nrun(ConsoleDocumentManager.java:128)\n        at org.eclipse.swt.widgets.RunnableLock.run(RunnableLock.java:31)\n        at org.eclipse.swt.widgets.Synchronizer.runAsyncMessages(Synchronizer.ja\nva:94)\n        at org.eclipse.swt.widgets.Display.runAsyncMessages(Display.java:1669)\n        at org.eclipse.swt.widgets.Display.readAndDispatch(Display.java:1414)\n        at org.eclipse.jface.operation.ModalContext$ModalContextThread.block(Mod\nalContext.java:130)\n        at org.eclipse.jface.operation.ModalContext.run(ModalContext.java:255)\n        at org.eclipse.debug.internal.ui.launchConfigurations.LaunchConfiguratio\nnsDialog.run(LaunchConfigurationsDialog.java:1294)\n        at org.eclipse.debug.internal.ui.launchConfigurations.LaunchConfiguratio\nnsDialog.launchWithProgress(LaunchConfigurationsDialog.java:1248)\n        at org.eclipse.debug.internal.ui.launchConfigurations.LaunchConfiguratio\nnsDialog.doLaunch(LaunchConfigurationsDialog.java:1215)\n        at org.eclipse.debug.internal.ui.launchConfigurations.LaunchConfiguratio\nnsDialog.handleLaunchPressed(LaunchConfigurationsDialog.java:1185)\n        at org.eclipse.debug.internal.ui.launchConfigurations.LaunchConfiguratio\nnsDialog.buttonPressed(LaunchConfigurationsDialog.java:323)\n        at org.eclipse.jface.dialogs.Dialog$1.widgetSelected(Dialog.java:398)\n        at org.eclipse.swt.widgets.TypedListener.handleEvent(TypedListener.java:\n87)\n        at org.eclipse.swt.widgets.EventTable.sendEvent(EventTable.java:77)\n        at org.eclipse.swt.widgets.Widget.sendEvent(Widget.java:825)\n        at org.eclipse.swt.widgets.Display.runDeferredEvents(Display.java:1692)\n        at org.eclipse.swt.widgets.Display.readAndDispatch(Display.java:1410)\n        at org.eclipse.jface.window.Window.runEventLoop(Window.java:561)\n        at org.eclipse.jface.window.Window.open(Window.java:541)\n        at org.eclipse.debug.internal.ui.launchConfigurations.LaunchConfiguratio\nnsDialog.openDialogOnSelection(LaunchConfigurationsDialog.java:541)\n        at org.eclipse.debug.internal.ui.launchConfigurations.LaunchConfiguratio\nnsDialog.open(LaunchConfigurationsDialog.java:495)\n        at org.eclipse.debug.ui.DebugUITools$1.run(DebugUITools.java:324)\n        at org.eclipse.swt.custom.BusyIndicator.showWhile(BusyIndicator.java:65)\n\n        at org.eclipse.debug.ui.DebugUITools.openLaunchConfigurationDialogOnGrou\np(DebugUITools.java:328)\n        at org.eclipse.ui.externaltools.internal.ant.launchConfigurations.AntLau\nnchShortcut.launch(AntLaunchShortcut.java:122)\n        at org.eclipse.ui.externaltools.internal.ant.launchConfigurations.AntLau\nnchShortcut.launch(AntLaunchShortcut.java:72)\n        at org.eclipse.ui.externaltools.internal.ant.launchConfigurations.AntRun\nActionDelegate.run(AntRunActionDelegate.java:35)\n        at org.eclipse.ui.internal.PluginAction.runWithEvent(PluginAction.java:2\n50)\n        at org.eclipse.jface.action.ActionContributionItem.handleWidgetSelection\n(ActionContributionItem.java:411)\n        at org.eclipse.jface.action.ActionContributionItem.handleWidgetEvent(Act\nionContributionItem.java:365)\n        at org.eclipse.jface.action.ActionContributionItem.access$0(ActionContri\nbutionItem.java:356)\n        at org.eclipse.jface.action.ActionContributionItem$ActionListener.handle\nEvent(ActionContributionItem.java:48)\n        at org.eclipse.swt.widgets.EventTable.sendEvent(EventTable.java:77)\n        at org.eclipse.swt.widgets.Widget.sendEvent(Widget.java:825)\n        at org.eclipse.swt.widgets.Display.runDeferredEvents(Display.java:1692)\n        at org.eclipse.swt.widgets.Display.readAndDispatch(Display.java:1410)\n        at org.eclipse.ui.internal.Workbench.runEventLoop(Workbench.java:1467)\n        at org.eclipse.ui.internal.Workbench.run(Workbench.java:1450)\n        at org.eclipse.core.internal.boot.InternalBootLoader.run(InternalBootLoa\nder.java:845)\n        at org.eclipse.core.boot.BootLoader.run(BootLoader.java:462)\n        at sun.reflect.NativeMethodAccessorImpl.invoke0(Native Method)\n        at sun.reflect.NativeMethodAccessorImpl.invoke(NativeMethodAccessorImpl.\njava:39)\n        at sun.reflect.DelegatingMethodAccessorImpl.invoke(DelegatingMethodAcces\nsorImpl.java:25)\n        at java.lang.reflect.Method.invoke(Method.java:324)\n        at org.eclipse.core.launcher.Main.basicRun(Main.java:247)\n        at org.eclipse.core.launcher.Main.run(Main.java:703)\n        at org.eclipse.core.launcher.Main.main(Main.java:539)",
    "\n\n*** This bug has been marked as a duplicate of 29269 ***"
  ],
  "commentCreationDates": [
    "2003-01-13T09:17:39+01:00",
    "2003-01-13T12:56:48+01:00"
  ],
  "traces": [
    {
      "exceptionType": "java.lang.ClassNotFoundException",
      "message": "org.eclipse.ui.externaltools.internal.ant.logg er.TaskLineTracker",
      "elements": [
        {
          "method": "org.eclipse.core.internal.boot.DelegatingURLClassLoader.loadClass",
          "source": "Del egatingURLClassLoader.java:875"
        },
        {
          "method": "java.lang.ClassLoader.loadClass",
          "source": "ClassLoader.java:255"
        },
        {
          "method": "org.eclipse.core.internal.plugins.PluginDescriptor.createExecutableExtension",
          "source": "PluginDescriptor.java:130"
        },
        {
          "method": "org.eclipse.core.internal.plugins.PluginDescriptor.createExecutableExtension",
          "source": "PluginDescriptor.java:167"
        },
        {
          "method": "org.eclipse.core.internal.plugins.ConfigurationElement.createExecutableExtension",
          "source": "ConfigurationElement.java:103"
        },
        {
          "method": "org.eclipse.debug.internal.ui.views.console.ConsoleDocumentManager.newLineNotifier",
          "source": "ConsoleDocumentManager.java:372"
        },
        {
          "method": "org.eclipse.debug.internal.ui.views.console.ConsoleDocumentProvider.getLineNotifier",
          "source": "ConsoleDocumentProvider.java:100"
        },
        {
          "method": "org.eclipse.debug.internal.ui.views.console.ConsoleDocumentProvider.createDocument",
          "source": "ConsoleDocumentProvider.java:35"
        },
        {
          "method": "org.eclipse.ui.texteditor.AbstractDocumentProvider.createElementInfo",
          "source": " AbstractDocumentProvider.java:236"
        },
        {
          "method": "org.eclipse.ui.texteditor.AbstractDocumentProvider.connect",
          "source": "AbstractDo cumentProvider.java:302"
        },
        {
          "method": "org.eclipse.debug.internal.ui.views.console.ConsoleDocumentManager$2.run",
          "source": "ConsoleDocumentManager.java:128"
        },
        {
          "method": "org.eclipse.swt.widgets.RunnableLock.run",
          "source": "RunnableLock.java:31"
        },
        {
          "method": "org.eclipse.swt.widgets.Synchronizer.runAsyncMessages",
          "source": "Synchronizer.ja va:94"
        },
        {
          "method": "org.eclipse.swt.widgets.Display.runAsyncMessages",
          "source": "Display.java:1669"
        },
        {
          "method": "org.eclipse.swt.widgets.Display.readAndDispatch",
          "source": "Display.java:1414"
        },
        {
          "method": "org.eclipse.jface.operation.ModalContext$ModalContextThread.block",
          "source": "Mod alContext.java:130"
        },
        {
          "method": "org.eclipse.jface.operation.ModalContext.run",
          "source": "ModalContext.java:255"
        },
        {
          "method": "org.eclipse.debug.internal.ui.launchConfigurations.LaunchConfigurationsDialog.run",
          "source": "LaunchConfigurationsDialog.java:1294"
        },
        {
          "method": "org.eclipse.debug.internal.ui.launchConfigurations.LaunchConfigurationsDialog.launchWithProgress",
          "source": "LaunchConfigurationsDialog.java:1248"
        },
        {
          "method": "org.eclipse.debug.internal.ui.launchConfigurations.LaunchConfigurationsDialog.doLaunch",
          "source": "LaunchConfigurationsDialog.java:1215"
        },
        {
          "method": "org.eclipse.debug.internal.ui.launchConfigurations.LaunchConfigurationsDialog.handleLaunchPressed",
          "source": "LaunchConfigurationsDialog.java:1185"
        },
        {
          "method": "org.eclipse.debug.internal.ui.launchConfigurations.LaunchConfigurationsDialog.buttonPressed",
          "source": "LaunchConfigurationsDialog.java:323"
        },
        {
          "method": "org.eclipse.jface.dialogs.Dialog$1.widgetSelected",
          "source": "Dialog.java:398"
        },
        {
          "method": "org.eclipse.swt.widgets.TypedListener.handleEvent",
          "source": "TypedListener.java: 87"
        },
        {
          "method": "org.eclipse.swt.widgets.EventTable.sendEvent",
          "source": "EventTable.java:77"
        },
        {
          "method": "org.eclipse.swt.widgets.Widget.sendEvent",
          "source": "Widget.java:825"
        },
        {
          "method": "org.eclipse.swt.widgets.Display.runDeferredEvents",
          "source": "Display.java:1692"
        },
        {
          "method": "org.eclipse.swt.widgets.Display.readAndDispatch",
          "source": "Display.java:1410"
        },
        {
          "method": "org.eclipse.jface.window.Window.runEventLoop",
          "source": "Window.java:561"
        },
        {
          "method": "org.eclipse.jface.window.Window.open",
          "source": "Window.java:541"
        },
        {
          "method": "org.eclipse.debug.internal.ui.launchConfigurations.LaunchConfigurationsDialog.openDialogOnSelection",
          "source": "LaunchConfigurationsDialog.java:541"
        },
        {
          "method": "org.eclipse.debug.internal.ui.launchConfigurations.LaunchConfigurationsDialog.open",
          "source": "LaunchConfigurationsDialog.java:495"
        },
        {
          "method": "org.eclipse.debug.ui.DebugUITools$1.run",
          "source": "DebugUITools.java:324"
        },
        {
          "method": "org.eclipse.swt.custom.BusyIndicator.showWhile",
          "source": "BusyIndicator.java:65"
        },
        {
          "method": "org.eclipse.debug.ui.DebugUITools.openLaunchConfigurationDialogOnGroup",
          "source": "DebugUITools.java:328"
        },
        {
          "method": "org.eclipse.ui.externaltools.internal.ant.launchConfigurations.AntLaunchShortcut.launch",
          "source": "AntLaunchShortcut.java:122"
        },
        {
          "method": "org.eclipse.ui.externaltools.internal.ant.launchConfigurations.AntLaunchShortcut.launch",
          "source": "AntLaunchShortcut.java:72"
        },
        {
          "method": "org.eclipse.ui.externaltools.internal.ant.launchConfigurations.AntRunActionDelegate.run",
          "source": "AntRunActionDelegate.java:35"
        },
        {
          "method": "org.eclipse.ui.internal.PluginAction.runWithEvent",
          "source": "PluginAction.java:2 50"
        },
        {
          "method": "org.eclipse.jface.action.ActionContributionItem.handleWidgetSelection",
          "source": "ActionContributionItem.java:411"
        },
        {
          "method": "org.eclipse.jface.action.ActionContributionItem.handleWidgetEvent",
          "source": "Act ionContributionItem.java:365"
        },
        {
          "method": "org.eclipse.jface.action.ActionContributionItem.access$0",
          "source": "ActionContri butionItem.java:356"
        },
        {
          "method": "org.eclipse.jface.action.ActionContributionItem$ActionListener.handleEvent",
          "source": "ActionContributionItem.java:48"
        },
        {
          "method": "org.eclipse.swt.widgets.EventTable.sendEvent",
          "source": "EventTable.java:77"
        },
        {
          "method": "org.eclipse.swt.widgets.Widget.sendEvent",
          "source": "Widget.java:825"
        },
        {
          "method": "org.eclipse.swt.widgets.Display.runDeferredEvents",
          "source": "Display.java:1692"
        },
        {
          "method": "org.eclipse.swt.widgets.Display.readAndDispatch",
          "source": "Display.java:1410"
        },
        {
          "method": "org.eclipse.ui.internal.Workbench.runEventLoop",
          "source": "Workbench.java:1467"
        },
        {
          "method": "org.eclipse.ui.internal.Workbench.run",
          "source": "Workbench.java:1450"
        },
        {
          "method": "org.eclipse.core.internal.boot.InternalBootLoader.run",
          "source": "InternalBootLoa der.java:845"
        },
        {
          "method": "org.eclipse.core.boot.BootLoader.run",
          "source": "BootLoader.java:462"
        },
        {
          "method": "sun.reflect.NativeMethodAccessorImpl.invoke0",
          "source": "Native Method"
        },
        {
          "method": "sun.reflect.NativeMethodAccessorImpl.invoke",
          "source": "NativeMethodAccessorImpl. java:39"
        },
        {
          "method": "sun.reflect.DelegatingMethodAccessorImpl.invoke",
          "source": "DelegatingMethodAcces sorImpl.java:25"
        },
        {
          "method": "java.lang.reflect.Method.invoke",
          "source": "Method.java:324"
        },
        {
          "method": "org.eclipse.core.launcher.Main.basicRun",
          "source": "Main.java:247"
        },
        {
          "method": "org.eclipse.core.launcher.Main.run",
          "source": "Main.java:703"
        },
        {
          "method": "org.eclipse.core.launcher.Main.main",
          "source": "Main.java:539"
        }
      ],
      "number": 0,
      "commentIndex": 0,
      "bugId": "29357",
      "duplicateId": "29269",
      "date": "2003-01-13T09:17:39+01:00",
      "product": "Platform",
      "component": "Ant",
      "severity": "normal"
    }
  ],
  "groupId": "29269",
  "bugId": "29357",
  "duplicateId": "29269",
  "date": "2003-01-13T09:17:39+01:00",
  "product": "Platform",
  "component": "Ant",
  "severity": "normal"
}