{
  "comments": [
    "Build 20030114\n\nGot the following CVSException in the log while building:\norg.eclipse.team.internal.ccvs.core.CVSException: The resource tree is locked \nfor modifications.\n        at org.eclipse.team.internal.ccvs.core.CVSException.wrapException\n(CVSException.java:92)\n        at \norg.eclipse.team.internal.ccvs.core.resources.SynchronizerSyncInfoCache.setCache\ndSyncBytes(SynchronizerSyncInfoCache.java:276)\n        at \norg.eclipse.team.internal.ccvs.core.resources.EclipseSynchronizer.cacheResourceS\nyncForChildren(EclipseSynchronizer.java:623)\n        at \norg.eclipse.team.internal.ccvs.core.resources.EclipseSynchronizer.getSyncBytes\n(EclipseSynchronizer.java:229)\n        at \norg.eclipse.team.internal.ccvs.core.resources.EclipseResource.getSyncBytes\n(EclipseResource.java:222)\n        at \norg.eclipse.team.internal.ccvs.core.resources.EclipseResource.isManaged\n(EclipseResource.java:181)\n        at \norg.eclipse.team.internal.ccvs.core.resources.EclipseResource.isIgnored\n(EclipseResource.java:115)\n        at \norg.eclipse.team.internal.ccvs.core.resources.EclipseFile.handleModification\n(EclipseFile.java:494)\n        at \norg.eclipse.team.internal.ccvs.core.resources.FileModificationManager.contentsCh\nanged(FileModificationManager.java:161)\n        at \norg.eclipse.team.internal.ccvs.core.resources.FileModificationManager$1.visit\n(FileModificationManager.java:77)\n        at org.eclipse.core.internal.events.ResourceDelta.accept\n(ResourceDelta.java:71)\n        at org.eclipse.core.internal.events.ResourceDelta.accept\n(ResourceDelta.java:79)\n        at org.eclipse.core.internal.events.ResourceDelta.accept\n(ResourceDelta.java:79)\n        at org.eclipse.core.internal.events.ResourceDelta.accept\n(ResourceDelta.java:79)\n        at org.eclipse.core.internal.events.ResourceDelta.accept\n(ResourceDelta.java:79)\n        at org.eclipse.core.internal.events.ResourceDelta.accept\n(ResourceDelta.java:79)\n        at org.eclipse.core.internal.events.ResourceDelta.accept\n(ResourceDelta.java:79)\n        at org.eclipse.core.internal.events.ResourceDelta.accept\n(ResourceDelta.java:79)\n        at org.eclipse.core.internal.events.ResourceDelta.accept\n(ResourceDelta.java:79)\n        at org.eclipse.core.internal.events.ResourceDelta.accept\n(ResourceDelta.java:52)\n        at \norg.eclipse.team.internal.ccvs.core.resources.FileModificationManager.resourceCh\nanged(FileModificationManager.java:62)\n        at org.eclipse.core.internal.events.NotificationManager$1.run\n(NotificationManager.java:137)\n        at org.eclipse.core.internal.runtime.InternalPlatform.run\n(InternalPlatform.java:852)\n        at org.eclipse.core.runtime.Platform.run(Platform.java:413)\n        at org.eclipse.core.internal.events.NotificationManager.notify\n(NotificationManager.java:152)\n        at org.eclipse.core.internal.events.NotificationManager.broadcastChanges\n(NotificationManager.java:67)\n        at org.eclipse.core.internal.resources.Workspace.broadcastChanges\n(Workspace.java:154)\n        at org.eclipse.core.internal.resources.Workspace.endOperation\n(Workspace.java:885)\n        at org.eclipse.core.internal.resources.Workspace.build\n(Workspace.java:180)\n        at org.eclipse.debug.internal.ui.DebugUIPlugin$3.run\n(DebugUIPlugin.java:491)\n        at org.eclipse.jface.operation.ModalContext$ModalContextThread.run\n(ModalContext.java:95)",
    "Were there any other exceptions in the log? Is this reproducable for you? If \nso, can you give me the steps to reproduce.",
    "The only exception was the one reported above. I cannot reproduce the problem.",
    "I have modified the code path so it will not fail but instead dump a more \ndetailed message to the log."
  ],
  "commentCreationDates": [
    "2003-01-15T10:16:28+01:00",
    "2003-01-15T20:10:38+01:00",
    "2003-01-16T09:14:28+01:00",
    "2003-01-20T17:55:13+01:00"
  ],
  "traces": [
    {
      "exceptionType": "org.eclipse.team.internal.ccvs.core.CVSException",
      "message": "The resource tree is locked  for modifications.",
      "elements": [
        {
          "method": "org.eclipse.team.internal.ccvs.core.CVSException.wrapException",
          "source": "CVSException.java:92"
        },
        {
          "method": "org.eclipse.team.internal.ccvs.core.resources.SynchronizerSyncInfoCache.setCachedSyncBytes",
          "source": "SynchronizerSyncInfoCache.java:276"
        },
        {
          "method": "org.eclipse.team.internal.ccvs.core.resources.EclipseSynchronizer.cacheResourceSyncForChildren",
          "source": "EclipseSynchronizer.java:623"
        },
        {
          "method": "org.eclipse.team.internal.ccvs.core.resources.EclipseSynchronizer.getSyncBytes",
          "source": "EclipseSynchronizer.java:229"
        },
        {
          "method": "org.eclipse.team.internal.ccvs.core.resources.EclipseResource.getSyncBytes",
          "source": "EclipseResource.java:222"
        },
        {
          "method": "org.eclipse.team.internal.ccvs.core.resources.EclipseResource.isManaged",
          "source": "EclipseResource.java:181"
        },
        {
          "method": "org.eclipse.team.internal.ccvs.core.resources.EclipseResource.isIgnored",
          "source": "EclipseResource.java:115"
        },
        {
          "method": "org.eclipse.team.internal.ccvs.core.resources.EclipseFile.handleModification",
          "source": "EclipseFile.java:494"
        },
        {
          "method": "org.eclipse.team.internal.ccvs.core.resources.FileModificationManager.contentsChanged",
          "source": "FileModificationManager.java:161"
        },
        {
          "method": "org.eclipse.team.internal.ccvs.core.resources.FileModificationManager$1.visit",
          "source": "FileModificationManager.java:77"
        },
        {
          "method": "org.eclipse.core.internal.events.ResourceDelta.accept",
          "source": "ResourceDelta.java:71"
        },
        {
          "method": "org.eclipse.core.internal.events.ResourceDelta.accept",
          "source": "ResourceDelta.java:79"
        },
        {
          "method": "org.eclipse.core.internal.events.ResourceDelta.accept",
          "source": "ResourceDelta.java:79"
        },
        {
          "method": "org.eclipse.core.internal.events.ResourceDelta.accept",
          "source": "ResourceDelta.java:79"
        },
        {
          "method": "org.eclipse.core.internal.events.ResourceDelta.accept",
          "source": "ResourceDelta.java:79"
        },
        {
          "method": "org.eclipse.core.internal.events.ResourceDelta.accept",
          "source": "ResourceDelta.java:79"
        },
        {
          "method": "org.eclipse.core.internal.events.ResourceDelta.accept",
          "source": "ResourceDelta.java:79"
        },
        {
          "method": "org.eclipse.core.internal.events.ResourceDelta.accept",
          "source": "ResourceDelta.java:79"
        },
        {
          "method": "org.eclipse.core.internal.events.ResourceDelta.accept",
          "source": "ResourceDelta.java:79"
        },
        {
          "method": "org.eclipse.core.internal.events.ResourceDelta.accept",
          "source": "ResourceDelta.java:52"
        },
        {
          "method": "org.eclipse.team.internal.ccvs.core.resources.FileModificationManager.resourceChanged",
          "source": "FileModificationManager.java:62"
        },
        {
          "method": "org.eclipse.core.internal.events.NotificationManager$1.run",
          "source": "NotificationManager.java:137"
        },
        {
          "method": "org.eclipse.core.internal.runtime.InternalPlatform.run",
          "source": "InternalPlatform.java:852"
        },
        {
          "method": "org.eclipse.core.runtime.Platform.run",
          "source": "Platform.java:413"
        },
        {
          "method": "org.eclipse.core.internal.events.NotificationManager.notify",
          "source": "NotificationManager.java:152"
        },
        {
          "method": "org.eclipse.core.internal.events.NotificationManager.broadcastChanges",
          "source": "NotificationManager.java:67"
        },
        {
          "method": "org.eclipse.core.internal.resources.Workspace.broadcastChanges",
          "source": "Workspace.java:154"
        },
        {
          "method": "org.eclipse.core.internal.resources.Workspace.endOperation",
          "source": "Workspace.java:885"
        },
        {
          "method": "org.eclipse.core.internal.resources.Workspace.build",
          "source": "Workspace.java:180"
        },
        {
          "method": "org.eclipse.debug.internal.ui.DebugUIPlugin$3.run",
          "source": "DebugUIPlugin.java:491"
        },
        {
          "method": "org.eclipse.jface.operation.ModalContext$ModalContextThread.run",
          "source": "ModalContext.java:95"
        }
      ],
      "number": 0,
      "commentIndex": 0,
      "bugId": "29521",
      "date": "2003-01-15T10:16:28+01:00",
      "product": "Platform",
      "component": "Team",
      "severity": "major"
    }
  ],
  "groupId": "29521",
  "bugId": "29521",
  "date": "2003-01-15T10:16:28+01:00",
  "product": "Platform",
  "component": "Team",
  "severity": "major"
}