{
  "comments": [
    "20030115\n\nUnsure of test case.\n\njava.util.ConcurrentModificationException\n        at java.util.AbstractList$Itr.checkForComodification(AbstractList.java:4\n44)\n        at java.util.AbstractList$Itr.next(AbstractList.java:417)\n        at org.eclipse.jdt.internal.debug.core.model.JDIThread.findVariable(JDIT\nhread.java:1464)\n        at org.eclipse.jdt.internal.debug.core.model.JDIDebugTarget.findVariable\n(JDIDebugTarget.java:1288)\n        at org.eclipse.jdt.internal.debug.ui.JavaDebugHover.getHoverInfo(JavaDeb\nugHover.java:91)\n        at org.eclipse.jdt.internal.ui.text.java.hover.BestMatchHover.getHoverIn\nfo(BestMatchHover.java:131)\n        at org.eclipse.jdt.internal.ui.text.java.hover.JavaEditorTextHoverProxy.\ngetHoverInfo(JavaEditorTextHoverProxy.java:132)\n        at org.eclipse.jface.text.TextViewerHoverManager$2.run(TextViewerHoverMa\nnager.java:108)",
    "Fixed in JDIThread and JDIStackFrame. The implementations used the internal \nlist data structures, rather than copies. The fix is to use the API methods \n(#getStackFrames(), #getVariables()) rather than the internal lists. Less \nefficient, but safe.",
    "Please verify, Darin (S).",
    "Verified."
  ],
  "commentCreationDates": [
    "2003-01-15T23:27:14+01:00",
    "2003-02-15T16:43:46+01:00",
    "2003-02-15T16:44:03+01:00",
    "2003-02-15T20:45:11+01:00"
  ],
  "traces": [
    {
      "exceptionType": "java.util.ConcurrentModificationException",
      "elements": [
        {
          "method": "java.util.AbstractList$Itr.checkForComodification",
          "source": "AbstractList.java:4 44"
        },
        {
          "method": "java.util.AbstractList$Itr.next",
          "source": "AbstractList.java:417"
        },
        {
          "method": "org.eclipse.jdt.internal.debug.core.model.JDIThread.findVariable",
          "source": "JDIT hread.java:1464"
        },
        {
          "method": "org.eclipse.jdt.internal.debug.core.model.JDIDebugTarget.findVariable",
          "source": "JDIDebugTarget.java:1288"
        },
        {
          "method": "org.eclipse.jdt.internal.debug.ui.JavaDebugHover.getHoverInfo",
          "source": "JavaDeb ugHover.java:91"
        },
        {
          "method": "org.eclipse.jdt.internal.ui.text.java.hover.BestMatchHover.getHoverInfo",
          "source": "BestMatchHover.java:131"
        },
        {
          "method": "org.eclipse.jdt.internal.ui.text.java.hover.JavaEditorTextHoverProxy.getHoverInfo",
          "source": "JavaEditorTextHoverProxy.java:132"
        },
        {
          "method": "org.eclipse.jface.text.TextViewerHoverManager$2.run",
          "source": "TextViewerHoverMa nager.java:108"
        }
      ],
      "number": 0,
      "commentIndex": 0,
      "bugId": "29587",
      "date": "2003-01-15T23:27:14+01:00",
      "product": "JDT",
      "component": "Debug",
      "severity": "normal"
    }
  ],
  "groupId": "29587",
  "bugId": "29587",
  "date": "2003-01-15T23:27:14+01:00",
  "product": "JDT",
  "component": "Debug",
  "severity": "normal"
}