{
  "comments": [
    "Build 20030115\n\nGot the following NPE attempting to modify a watchpoint (i.e. trying to make it \na read watchpoint):\njava.lang.NullPointerException\n        at \norg.eclipse.jdt.internal.debug.core.model.JDIDebugElement.getEventRequestManager\n(JDIDebugElement.java:342)\n        at \norg.eclipse.jdt.internal.debug.core.model.JDIDebugTarget.createClassPrepareReque\nst(JDIDebugTarget.java:919)\n        at \norg.eclipse.jdt.internal.debug.core.model.JDIDebugTarget.createClassPrepareReque\nst(JDIDebugTarget.java:898)\n        at \norg.eclipse.jdt.internal.debug.core.breakpoints.JavaBreakpoint.createRequests\n(JavaBreakpoint.java:457)\n        at \norg.eclipse.jdt.internal.debug.core.breakpoints.JavaBreakpoint.recreate\n(JavaBreakpoint.java:1072)\n        at \norg.eclipse.jdt.internal.debug.core.breakpoints.JavaBreakpoint.removeThreadFilte\nr(JavaBreakpoint.java:974)\n        at org.eclipse.jdt.internal.debug.ui.actions.ThreadFilterViewer.doStore\n(ThreadFilterViewer.java:180)\n        at org.eclipse.jface.preference.FieldEditor.store(FieldEditor.java:580)\n        at org.eclipse.jface.preference.FieldEditorPreferencePage.performOk\n(FieldEditorPreferencePage.java:308)\n        at \norg.eclipse.jdt.internal.debug.ui.actions.JavaBreakpointPropertiesDialog.okPress\ned(JavaBreakpointPropertiesDialog.java:153)\n        at org.eclipse.jface.dialogs.Dialog.buttonPressed(Dialog.java:240)\n        at org.eclipse.jface.dialogs.Dialog$1.widgetSelected(Dialog.java:398)\n        at org.eclipse.swt.widgets.TypedListener.handleEvent\n(TypedListener.java:87)\n        at org.eclipse.swt.widgets.EventTable.sendEvent(EventTable.java:77)\n        at org.eclipse.swt.widgets.Widget.sendEvent(Widget.java:836)\n        at org.eclipse.swt.widgets.Display.runDeferredEvents(Display.java:1692)\n        at org.eclipse.swt.widgets.Display.readAndDispatch(Display.java:1410)\n        at org.eclipse.jface.window.Window.runEventLoop(Window.java:561)\n        at org.eclipse.jface.window.Window.open(Window.java:541)\n        at \norg.eclipse.jdt.internal.debug.ui.actions.JavaBreakpointPropertiesRulerAction.ru\nn(JavaBreakpointPropertiesRulerAction.java:42)\n        at org.eclipse.ui.texteditor.AbstractRulerActionDelegate.run\n(AbstractRulerActionDelegate.java:98)\n        at org.eclipse.ui.internal.PluginAction.runWithEvent\n(PluginAction.java:250)\n        at org.eclipse.jface.action.ActionContributionItem.handleWidgetSelection\n(ActionContributionItem.java:422)\n        at org.eclipse.jface.action.ActionContributionItem.handleWidgetEvent\n(ActionContributionItem.java:374)\n        at org.eclipse.jface.action.ActionContributionItem.access$0\n(ActionContributionItem.java:368)\n        at \norg.eclipse.jface.action.ActionContributionItem$ActionListener.handleEvent\n(ActionContributionItem.java:69)\n        at org.eclipse.swt.widgets.EventTable.sendEvent(EventTable.java:77)\n        at org.eclipse.swt.widgets.Widget.sendEvent(Widget.java:836)\n        at org.eclipse.swt.widgets.Display.runDeferredEvents(Display.java:1692)\n        at org.eclipse.swt.widgets.Display.readAndDispatch(Display.java:1410)\n        at org.eclipse.ui.internal.Workbench.runEventLoop(Workbench.java:1467)\n        at org.eclipse.ui.internal.Workbench.run(Workbench.java:1450)\n        at org.eclipse.core.internal.boot.InternalBootLoader.run\n(InternalBootLoader.java:845)\n        at org.eclipse.core.boot.BootLoader.run(BootLoader.java:462)\n        at sun.reflect.NativeMethodAccessorImpl.invoke0(Native Method)\n        at sun.reflect.NativeMethodAccessorImpl.invoke\n(NativeMethodAccessorImpl.java:39)\n        at sun.reflect.DelegatingMethodAccessorImpl.invoke\n(DelegatingMethodAccessorImpl.java:25)\n        at java.lang.reflect.Method.invoke(Method.java:324)\n        at org.eclipse.core.launcher.Main.basicRun(Main.java:247)\n        at org.eclipse.core.launcher.Main.run(Main.java:703)\n        at org.eclipse.core.launcher.Main.main(Main.java:539)\n\nI cannot reproduce the problem.",
    "Both this and bug 27278 appear to be getting the NPE when calling getVM().\nAll of our code assumes that this will not be null but this is not the case if \nthe timing is bad or if a \"zombie\" target is left around.",
    "And bug 28195.",
    "*** Bug 27857 has been marked as a duplicate of this bug. ***",
    "Fixed in JavaBreakpoint.\nplease verify (DarinW).",
    "Verified."
  ],
  "commentCreationDates": [
    "2003-01-16T12:34:34+01:00",
    "2003-01-17T01:36:09+01:00",
    "2003-01-17T20:10:41+01:00",
    "2003-01-20T19:18:12+01:00",
    "2003-01-20T19:20:05+01:00",
    "2003-01-20T19:58:06+01:00"
  ],
  "traces": [
    {
      "exceptionType": "java.lang.NullPointerException",
      "elements": [
        {
          "method": "org.eclipse.jdt.internal.debug.core.model.JDIDebugElement.getEventRequestManager",
          "source": "JDIDebugElement.java:342"
        },
        {
          "method": "org.eclipse.jdt.internal.debug.core.model.JDIDebugTarget.createClassPrepareRequest",
          "source": "JDIDebugTarget.java:919"
        },
        {
          "method": "org.eclipse.jdt.internal.debug.core.model.JDIDebugTarget.createClassPrepareRequest",
          "source": "JDIDebugTarget.java:898"
        },
        {
          "method": "org.eclipse.jdt.internal.debug.core.breakpoints.JavaBreakpoint.createRequests",
          "source": "JavaBreakpoint.java:457"
        },
        {
          "method": "org.eclipse.jdt.internal.debug.core.breakpoints.JavaBreakpoint.recreate",
          "source": "JavaBreakpoint.java:1072"
        },
        {
          "method": "org.eclipse.jdt.internal.debug.core.breakpoints.JavaBreakpoint.removeThreadFilter",
          "source": "JavaBreakpoint.java:974"
        },
        {
          "method": "org.eclipse.jdt.internal.debug.ui.actions.ThreadFilterViewer.doStore",
          "source": "ThreadFilterViewer.java:180"
        },
        {
          "method": "org.eclipse.jface.preference.FieldEditor.store",
          "source": "FieldEditor.java:580"
        },
        {
          "method": "org.eclipse.jface.preference.FieldEditorPreferencePage.performOk",
          "source": "FieldEditorPreferencePage.java:308"
        },
        {
          "method": "org.eclipse.jdt.internal.debug.ui.actions.JavaBreakpointPropertiesDialog.okPressed",
          "source": "JavaBreakpointPropertiesDialog.java:153"
        },
        {
          "method": "org.eclipse.jface.dialogs.Dialog.buttonPressed",
          "source": "Dialog.java:240"
        },
        {
          "method": "org.eclipse.jface.dialogs.Dialog$1.widgetSelected",
          "source": "Dialog.java:398"
        },
        {
          "method": "org.eclipse.swt.widgets.TypedListener.handleEvent",
          "source": "TypedListener.java:87"
        },
        {
          "method": "org.eclipse.swt.widgets.EventTable.sendEvent",
          "source": "EventTable.java:77"
        },
        {
          "method": "org.eclipse.swt.widgets.Widget.sendEvent",
          "source": "Widget.java:836"
        },
        {
          "method": "org.eclipse.swt.widgets.Display.runDeferredEvents",
          "source": "Display.java:1692"
        },
        {
          "method": "org.eclipse.swt.widgets.Display.readAndDispatch",
          "source": "Display.java:1410"
        },
        {
          "method": "org.eclipse.jface.window.Window.runEventLoop",
          "source": "Window.java:561"
        },
        {
          "method": "org.eclipse.jface.window.Window.open",
          "source": "Window.java:541"
        },
        {
          "method": "org.eclipse.jdt.internal.debug.ui.actions.JavaBreakpointPropertiesRulerAction.run",
          "source": "JavaBreakpointPropertiesRulerAction.java:42"
        },
        {
          "method": "org.eclipse.ui.texteditor.AbstractRulerActionDelegate.run",
          "source": "AbstractRulerActionDelegate.java:98"
        },
        {
          "method": "org.eclipse.ui.internal.PluginAction.runWithEvent",
          "source": "PluginAction.java:250"
        },
        {
          "method": "org.eclipse.jface.action.ActionContributionItem.handleWidgetSelection",
          "source": "ActionContributionItem.java:422"
        },
        {
          "method": "org.eclipse.jface.action.ActionContributionItem.handleWidgetEvent",
          "source": "ActionContributionItem.java:374"
        },
        {
          "method": "org.eclipse.jface.action.ActionContributionItem.access$0",
          "source": "ActionContributionItem.java:368"
        },
        {
          "method": "org.eclipse.jface.action.ActionContributionItem$ActionListener.handleEvent",
          "source": "ActionContributionItem.java:69"
        },
        {
          "method": "org.eclipse.swt.widgets.EventTable.sendEvent",
          "source": "EventTable.java:77"
        },
        {
          "method": "org.eclipse.swt.widgets.Widget.sendEvent",
          "source": "Widget.java:836"
        },
        {
          "method": "org.eclipse.swt.widgets.Display.runDeferredEvents",
          "source": "Display.java:1692"
        },
        {
          "method": "org.eclipse.swt.widgets.Display.readAndDispatch",
          "source": "Display.java:1410"
        },
        {
          "method": "org.eclipse.ui.internal.Workbench.runEventLoop",
          "source": "Workbench.java:1467"
        },
        {
          "method": "org.eclipse.ui.internal.Workbench.run",
          "source": "Workbench.java:1450"
        },
        {
          "method": "org.eclipse.core.internal.boot.InternalBootLoader.run",
          "source": "InternalBootLoader.java:845"
        },
        {
          "method": "org.eclipse.core.boot.BootLoader.run",
          "source": "BootLoader.java:462"
        },
        {
          "method": "sun.reflect.NativeMethodAccessorImpl.invoke0",
          "source": "Native Method"
        },
        {
          "method": "sun.reflect.NativeMethodAccessorImpl.invoke",
          "source": "NativeMethodAccessorImpl.java:39"
        },
        {
          "method": "sun.reflect.DelegatingMethodAccessorImpl.invoke",
          "source": "DelegatingMethodAccessorImpl.java:25"
        },
        {
          "method": "java.lang.reflect.Method.invoke",
          "source": "Method.java:324"
        },
        {
          "method": "org.eclipse.core.launcher.Main.basicRun",
          "source": "Main.java:247"
        },
        {
          "method": "org.eclipse.core.launcher.Main.run",
          "source": "Main.java:703"
        },
        {
          "method": "org.eclipse.core.launcher.Main.main",
          "source": "Main.java:539"
        }
      ],
      "number": 0,
      "commentIndex": 0,
      "bugId": "29617",
      "date": "2003-01-16T12:34:34+01:00",
      "product": "JDT",
      "component": "Debug",
      "severity": "normal"
    }
  ],
  "groupId": "29617",
  "bugId": "29617",
  "date": "2003-01-16T12:34:34+01:00",
  "product": "JDT",
  "component": "Debug",
  "severity": "normal"
}