{
  "comments": [
    "I\u0027m able to run eclipse on J9-sidecar-1.3.1 for linux, but when I try to launch\na runtime-workbench from eclipse, I get the following exception in the .log file :\n\n!SESSION ----------------------------------------------------------------------\n!ENTRY org.eclipse.core.launcher 4 0 Jan 17, 2003 16:18:46.580\n!MESSAGE Exception launching the Eclipse Platform:\n!STACK\njava.lang.NoSuchMethodError:\ncom/ibm/oti/vm/VM.setClassPathImpl(Ljava/lang/ClassLoader;Ljava/lang/String;)V\n        at java.lang.Throwable.\u003cinit\u003e(Throwable.java:54)\n        at java.lang.Throwable.\u003cinit\u003e(Throwable.java:68)\n        at java.lang.NoSuchMethodError.\u003cinit\u003e(NoSuchMethodError.java:56)\n        at\norg.eclipse.core.internal.boot.DelegatingURLClassLoader.setHotSwapPath(DelegatingURLClassLoader.java:924)\n        at\norg.eclipse.core.internal.boot.DelegatingURLClassLoader.\u003cinit\u003e(DelegatingURLClassLoader.java:279)\n        at\norg.eclipse.core.internal.boot.PlatformClassLoader.\u003cinit\u003e(PlatformClassLoader.java:26)\n        at\norg.eclipse.core.internal.boot.InternalBootLoader.configurePlatformLoader(InternalBootLoader.java:158)\n        at\norg.eclipse.core.internal.boot.InternalBootLoader.initialize(InternalBootLoader.java:585)\n        at\norg.eclipse.core.internal.boot.InternalBootLoader.startup(InternalBootLoader.java:989)\n        at\norg.eclipse.core.internal.boot.InternalBootLoader.run(InternalBootLoader.java:838)\n        at org.eclipse.core.boot.BootLoader.run(BootLoader.java:462)\n        at java.lang.reflect.AccessibleObject.invokeL(AccessibleObject.java:203)\n        at java.lang.reflect.Method.invoke(Method.java:271)\n        at org.eclipse.core.launcher.Main.basicRun(Main.java:247)\n        at org.eclipse.core.launcher.Main.run(Main.java:703)\n        at org.eclipse.core.launcher.Main.main(Main.java:539)",
    "DJ, we fixed this, right?",
    "Yep, fixed and released for M5."
  ],
  "commentCreationDates": [
    "2003-01-17T20:57:58+01:00",
    "2003-02-11T17:37:56+01:00",
    "2003-02-11T23:10:52+01:00"
  ],
  "traces": [
    {
      "exceptionType": "java.lang.NoSuchMethodError",
      "message": "com/ibm/oti/vm/VM.setClassPathImpl(Ljava/lang/ClassLoader;Ljava/lang/String;)V",
      "elements": [
        {
          "method": "java.lang.Throwable.\u003cinit\u003e",
          "source": "Throwable.java:54"
        },
        {
          "method": "java.lang.Throwable.\u003cinit\u003e",
          "source": "Throwable.java:68"
        },
        {
          "method": "java.lang.NoSuchMethodError.\u003cinit\u003e",
          "source": "NoSuchMethodError.java:56"
        },
        {
          "method": "org.eclipse.core.internal.boot.DelegatingURLClassLoader.setHotSwapPath",
          "source": "DelegatingURLClassLoader.java:924"
        },
        {
          "method": "org.eclipse.core.internal.boot.DelegatingURLClassLoader.\u003cinit\u003e",
          "source": "DelegatingURLClassLoader.java:279"
        },
        {
          "method": "org.eclipse.core.internal.boot.PlatformClassLoader.\u003cinit\u003e",
          "source": "PlatformClassLoader.java:26"
        },
        {
          "method": "org.eclipse.core.internal.boot.InternalBootLoader.configurePlatformLoader",
          "source": "InternalBootLoader.java:158"
        },
        {
          "method": "org.eclipse.core.internal.boot.InternalBootLoader.initialize",
          "source": "InternalBootLoader.java:585"
        },
        {
          "method": "org.eclipse.core.internal.boot.InternalBootLoader.startup",
          "source": "InternalBootLoader.java:989"
        },
        {
          "method": "org.eclipse.core.internal.boot.InternalBootLoader.run",
          "source": "InternalBootLoader.java:838"
        },
        {
          "method": "org.eclipse.core.boot.BootLoader.run",
          "source": "BootLoader.java:462"
        },
        {
          "method": "java.lang.reflect.AccessibleObject.invokeL",
          "source": "AccessibleObject.java:203"
        },
        {
          "method": "java.lang.reflect.Method.invoke",
          "source": "Method.java:271"
        },
        {
          "method": "org.eclipse.core.launcher.Main.basicRun",
          "source": "Main.java:247"
        },
        {
          "method": "org.eclipse.core.launcher.Main.run",
          "source": "Main.java:703"
        },
        {
          "method": "org.eclipse.core.launcher.Main.main",
          "source": "Main.java:539"
        }
      ],
      "number": 0,
      "commentIndex": 0,
      "bugId": "29748",
      "date": "2003-01-17T20:57:58+01:00",
      "product": "Platform",
      "component": "Resources",
      "severity": "normal"
    }
  ],
  "groupId": "29748",
  "bugId": "29748",
  "date": "2003-01-17T20:57:58+01:00",
  "product": "Platform",
  "component": "Resources",
  "severity": "normal"
}