{
  "comments": [
    "It\u0027s not possible to start Eclipse build I20030115 on an NT 4.0 worstation with \nlatest SP.\n\nEven with a fresh installation and fresh workspace it is not possible. The \nEclipse launcher is started and starts the VM. In the VM console window I can \nsee a SWT exception \"no more handles\" but I can\u0027t view it because the console \ndisappears really fast after the stack trace.\n\nThanks, Gunnar",
    "got the stack trace:\n\norg.eclipse.swt.SWTError: No more handles\n        at org.eclipse.swt.SWT.error(SWT.java:2257)\n        at org.eclipse.swt.SWT.error(SWT.java:2161)\n        at org.eclipse.swt.widgets.Widget.error(Widget.java:381)\n        at org.eclipse.swt.widgets.Control.createHandle(Control.java:465)\n        at org.eclipse.swt.widgets.Composite.createHandle(Composite.java:167)\n        at org.eclipse.swt.widgets.Decorations.createHandle\n(Decorations.java:330)\n        at org.eclipse.swt.widgets.Shell.createHandle(Shell.java:429)\n        at org.eclipse.swt.widgets.Control.createWidget(Control.java:480)\n        at org.eclipse.swt.widgets.Scrollable.createWidget(Scrollable.java:121)\n        at org.eclipse.swt.widgets.Decorations.createWidget\n(Decorations.java:337)\n        at org.eclipse.swt.widgets.Shell.\u003cinit\u003e(Shell.java:248)\n        at org.eclipse.swt.widgets.Shell.\u003cinit\u003e(Shell.java:233)\n        at org.eclipse.swt.widgets.Shell.\u003cinit\u003e(Shell.java:186)\n        at org.eclipse.swt.widgets.Shell.\u003cinit\u003e(Shell.java:124)\n        at org.eclipse.ui.internal.ExceptionHandler.\u003cinit\u003e\n(ExceptionHandler.java:30)\n        at org.eclipse.ui.internal.Workbench.run(Workbench.java:1441)\n        at org.eclipse.core.internal.boot.InternalBootLoader.run\n(InternalBootLoader.java:845)\n        at org.eclipse.core.boot.BootLoader.run(BootLoader.java:462)\n        at java.lang.reflect.Method.invoke(Native Method)\n        at org.eclipse.core.launcher.Main.basicRun(Main.java:247)\n        at org.eclipse.core.launcher.Main.run(Main.java:703)\n        at org.eclipse.core.launcher.Main.main(Main.java:539)\n\n\n\nSystem:\nMicrosoft Windows NT\n4.00.1381\nIE 5 6.0.2600.0000",
    "This has been fixed already.  Please retest in the latest and reopen this PR if \nI am a liar."
  ],
  "commentCreationDates": [
    "2003-01-22T13:42:47+01:00",
    "2003-01-22T13:52:46+01:00",
    "2003-01-22T16:42:15+01:00"
  ],
  "traces": [
    {
      "exceptionType": "org.eclipse.swt.SWTError",
      "message": "No more handles",
      "elements": [
        {
          "method": "org.eclipse.swt.SWT.error",
          "source": "SWT.java:2257"
        },
        {
          "method": "org.eclipse.swt.SWT.error",
          "source": "SWT.java:2161"
        },
        {
          "method": "org.eclipse.swt.widgets.Widget.error",
          "source": "Widget.java:381"
        },
        {
          "method": "org.eclipse.swt.widgets.Control.createHandle",
          "source": "Control.java:465"
        },
        {
          "method": "org.eclipse.swt.widgets.Composite.createHandle",
          "source": "Composite.java:167"
        },
        {
          "method": "org.eclipse.swt.widgets.Decorations.createHandle",
          "source": "Decorations.java:330"
        },
        {
          "method": "org.eclipse.swt.widgets.Shell.createHandle",
          "source": "Shell.java:429"
        },
        {
          "method": "org.eclipse.swt.widgets.Control.createWidget",
          "source": "Control.java:480"
        },
        {
          "method": "org.eclipse.swt.widgets.Scrollable.createWidget",
          "source": "Scrollable.java:121"
        },
        {
          "method": "org.eclipse.swt.widgets.Decorations.createWidget",
          "source": "Decorations.java:337"
        },
        {
          "method": "org.eclipse.swt.widgets.Shell.\u003cinit\u003e",
          "source": "Shell.java:248"
        },
        {
          "method": "org.eclipse.swt.widgets.Shell.\u003cinit\u003e",
          "source": "Shell.java:233"
        },
        {
          "method": "org.eclipse.swt.widgets.Shell.\u003cinit\u003e",
          "source": "Shell.java:186"
        },
        {
          "method": "org.eclipse.swt.widgets.Shell.\u003cinit\u003e",
          "source": "Shell.java:124"
        },
        {
          "method": "org.eclipse.ui.internal.ExceptionHandler.\u003cinit\u003e",
          "source": "ExceptionHandler.java:30"
        },
        {
          "method": "org.eclipse.ui.internal.Workbench.run",
          "source": "Workbench.java:1441"
        },
        {
          "method": "org.eclipse.core.internal.boot.InternalBootLoader.run",
          "source": "InternalBootLoader.java:845"
        },
        {
          "method": "org.eclipse.core.boot.BootLoader.run",
          "source": "BootLoader.java:462"
        },
        {
          "method": "java.lang.reflect.Method.invoke",
          "source": "Native Method"
        },
        {
          "method": "org.eclipse.core.launcher.Main.basicRun",
          "source": "Main.java:247"
        },
        {
          "method": "org.eclipse.core.launcher.Main.run",
          "source": "Main.java:703"
        },
        {
          "method": "org.eclipse.core.launcher.Main.main",
          "source": "Main.java:539"
        }
      ],
      "number": 0,
      "commentIndex": 1,
      "bugId": "29966",
      "date": "2003-01-22T13:52:46+01:00",
      "product": "Platform",
      "component": "SWT",
      "severity": "blocker"
    }
  ],
  "groupId": "29966",
  "bugId": "29966",
  "date": "2003-01-22T13:42:47+01:00",
  "product": "Platform",
  "component": "SWT",
  "severity": "blocker"
}