{
  "comments": [
    "DW (6/7/00 5:17:06 PM)\n\tWhile releasing \u003e 1000 resources to a server, I received \"Problems\" dialog with the message:\n\t\t\"Problems occurred synchronizing the selected resources\".\n\n\tWhen I looked at the \"details\", the message was: \"SeverException.\"\n\n\tTo create the workspace:\n\t1) Start a new empty workbench\n\t2) Turn auto-build off\n\t3) Create projects \u0026 solutions by importing from file system into\n\t\tthe following project structure (available on \"ftp.min.oti.com\", outgoing/eBAF/1FW747src.zip)\n\t\t(Created each project as a Java Project, with a server property of \"mercury\")\n\t\t\tTp1NLS\n\t\t\t\tTp1Compiler\n\t\t\t\tTp1Core\n\t\t\t\tTp1DAV4J\n\t\t\t\tTp1JavaModel\n\t\t\t\tTp1WebDAV\n\t\t\t\tTp1XML\n\n\t4) Select the solution and release to the server.\n\t5) Received error message\n\nDJH (6/8/00 9:31:37 AM)\n\tWas able to release solution OK to machine here in Ottawa. Some questions:\n\t- did you get a single error message or multiple ones with the same \"ServerException\" message?\n\t- were some of the projects already on the server when you went to release them?\n\t\t\t\t\nDW (6/8/00 8:45:13 AM)\n\tI received a single error message.\n\tI tried several times, with new project names each time - thus the projects were not\n\talready on the server.\n\nPCD (6/8/00 2:01:46 PM)\n\tCould reproduce the bug in the JDK version (0.21) but not inside VAJ.\n\nDJH (6/8/00 4:25:03 PM)\n\tWas able to release onto gold using both VAJ and JDK. A local/remote server thing maybe?\n\nDJH (6/8/00 6:10:16 PM)\n\tWas able to release to hydrogen on JDK. Weird.\n\nDW (6/9/00 10:18:49 AM)\n\tI caught this exception by instrumenting code - I found that a DAV4JSystemException was being\n\tthrown, and I added a printStackTrace() to:\n\n\tpublic DAV4JSystemException(Exception e) {\n\t\tsuper();\n\t\te.printStackTrace();\n\t\tfWrappedException \u003d e;\n\t}\n\n\tI got this in the console:\n\n\n\tC:\\vajar\\itp\u003ejre\\bin\\java -verify -cp startup.jar;. com.ibm.itp.core.startup.App\nlication\njava.net.BindException: Address in use: no further information\n        at java.net.PlainSocketImpl.socketConnect(Native Method)\n        at java.net.PlainSocketImpl.doConnect(PlainSocketImpl.java:328)\n        at java.net.PlainSocketImpl.connectToAddress(PlainSocketImpl.java:126)\n        at java.net.PlainSocketImpl.connect(PlainSocketImpl.java:122)\n        at java.net.Socket.\u003cinit\u003e(Socket.java:246)\n        at java.net.Socket.\u003cinit\u003e(Socket.java:97)\n        at sun.net.NetworkClient.doConnect(NetworkClient.java:56)\n        at sun.net.www.http.HttpClient.openServer(HttpClient.java:321)\n        at sun.net.www.http.HttpClient.openServer(HttpClient.java:469)\n        at sun.net.www.http.HttpClient.\u003cinit\u003e(HttpClient.java:238)\n        at sun.net.www.http.HttpClient.\u003cinit\u003e(HttpClient.java:270)\n        at sun.net.www.http.HttpClient.New(HttpClient.java:290)\n        at sun.net.www.protocol.http.HttpURLConnection.connect(HttpURLConnection.java:366)\n        at sun.net.www.protocol.http.HttpURLConnection.getOutputStream(HttpURLConnection.java:435)\n        at com.ibm.dav4j.client.comms.WebDAVURLConnection.getOutputStream(WebDAVURLConnection.java:182)\n        at com.ibm.dav4j.client.comms.CommunicationsHandler.putBody(CommunicationsHandler.java:118)\n        at com.ibm.dav4j.client.comms.CommunicationsHandler.invoke(CommunicationsHandler.java:77)\n        at com.ibm.dav4j.client.RemoteServerProxy.proppatch(RemoteServerProxy.java:364)\n        at com.ibm.dav4j.client.AbstractResourceHandle.setProperties(AbstractResourceHandle.java)\n        at com.ibm.itp.core.serverstore.DavStore.setProperties(DavStore.java:495)\n        at com.ibm.itp.core.serverstore.DavResourceManager.updateSyncProperty(DavResourceManager.java:933)\n        at com.ibm.itp.core.serverstore.DavResourceManager.write(DavResourceManager.java:978)\n        at com.ibm.itp.core.serverstore.Synchronizer.internalPushContentFile(Synchronizer.java:625)\n        at com.ibm.itp.core.serverstore.Synchronizer.internalPush(Synchronizer.java:555)\n        at com.ibm.itp.core.serverstore.Synchronizer.push(Synchronizer.java:819)\n        at com.ibm.itp.core.serverstore.Synchronizer.push(Synchronizer.java:819)\n        at com.ibm.itp.core.serverstore.Synchronizer.push(Synchronizer.java:819)\n        at com.ibm.itp.core.serverstore.Synchronizer.push(Synchronizer.java:819)\n        at com.ibm.itp.core.serverstore.Synchronizer.push(Synchronizer.java:819)\n        at com.ibm.itp.core.serverstore.Synchronizer.push(Synchronizer.java:819)\n        at com.ibm.itp.core.serverstore.Synchronizer.push(Synchronizer.java:819)\n        at com.ibm.itp.core.serverstore.Synchronizer.push(Synchronizer.java:819)\n        at com.ibm.itp.core.serverstore.Synchronizer.push(Synchronizer.java:819)\n        at com.ibm.itp.core.serverstore.Synchronizer.push(Synchronizer.java:884)\n        at com.ibm.itp.core.serverstore.Synchronizer.release(Synchronizer.java:960)\n        at com.ibm.itp.core.serverstore.Synchronizer.release(Synchronizer.java:932)\n        at com.ibm.itp.ui.dialogs.ServerSynchronizationDialog.performRelease(ServerSynchronizationDialog.java)\n        at com.ibm.itp.ui.dialogs.ServerSynchronizationDialog$3.execute(ServerSynchronizationDialog.java)\n        at com.ibm.itp.ui.support.operations.WorkbenchModifyOperation.run(WorkbenchModifyOperation.java:56)\n        at com.ibm.itp.core.resources.Workbench.run(Workbench.java:1225)\n        at com.ibm.itp.ui.support.operations.WorkbenchModifyOperation.internalStart(WorkbenchModifyOperation.java:34)\n        at com.ibm.jface.util.ModalContext.run(ModalContext.java:227)\n\njava.net.BindException: Address in use: no further information\n        at java.net.PlainSocketImpl.socketConnect(Native Method)\n        at java.net.PlainSocketImpl.doConnect(PlainSocketImpl.java:328)\n        at java.net.PlainSocketImpl.connectToAddress(PlainSocketImpl.java:126)\n        at java.net.PlainSocketImpl.connect(PlainSocketImpl.java:122)\n        at java.net.Socket.\u003cinit\u003e(Socket.java:246)\n        at java.net.Socket.\u003cinit\u003e(Socket.java:97)\n        at sun.net.NetworkClient.doConnect(NetworkClient.java:56)\n        at sun.net.www.http.HttpClient.openServer(HttpClient.java:321)\n        at sun.net.www.http.HttpClient.openServer(HttpClient.java:469)\n        at sun.net.www.http.HttpClient.\u003cinit\u003e(HttpClient.java:238)\n        at sun.net.www.http.HttpClient.\u003cinit\u003e(HttpClient.java:270)\n        at sun.net.www.http.HttpClient.New(HttpClient.java:290)\n        at sun.net.www.protocol.http.HttpURLConnection.connect(HttpURLConnection.java:366)\n        at sun.net.www.protocol.http.HttpURLConnection.getOutputStream(HttpURLConnection.java:435)\n        at com.ibm.dav4j.client.comms.WebDAVURLConnection.getOutputStream(WebDAVURLConnection.java:182)\n        at com.ibm.dav4j.client.comms.CommunicationsHandler.putBody(CommunicationsHandler.java:118)\n        at com.ibm.dav4j.client.comms.CommunicationsHandler.invoke(CommunicationsHandler.java:77)\n        at com.ibm.dav4j.client.RemoteServerProxy.propfind(RemoteServerProxy.java:350)\n        at com.ibm.dav4j.client.AbstractResourceHandle.getProperties(AbstractResourceHandle.java)\n        at com.ibm.itp.core.serverstore.DavStore.getProperties(DavStore.java:394)\n        at com.ibm.itp.core.resources.ServerMetaArea.exists(ServerMetaArea.java:187)\n        at com.ibm.itp.core.resources.ServerMetaArea.exists(ServerMetaArea.java:161)\n        at com.ibm.itp.core.resources.ServerMetaArea.createFolder(ServerMetaArea.java:108)\n        at com.ibm.itp.core.resources.ServerMetaArea.createContentArea(ServerMetaArea.java:93)\n        at com.ibm.itp.core.serverstore.Synchronizer.ensureMetaAreasExist(Synchronizer.java:167)\n        at com.ibm.itp.core.serverstore.Synchronizer.internalPush(Synchronizer.java:555)\n        at com.ibm.itp.core.serverstore.Synchronizer.push(Synchronizer.java:819)\n        at com.ibm.itp.core.serverstore.Synchronizer.push(Synchronizer.java:819)\n        at com.ibm.itp.core.serverstore.Synchronizer.push(Synchronizer.java:819)\n        at com.ibm.itp.core.serverstore.Synchronizer.push(Synchronizer.java:819)\n        at com.ibm.itp.core.serverstore.Synchronizer.push(Synchronizer.java:819)\n        at com.ibm.itp.core.serverstore.Synchronizer.push(Synchronizer.java:819)\n        at com.ibm.itp.core.serverstore.Synchronizer.push(Synchronizer.java:819)\n        at com.ibm.itp.core.serverstore.Synchronizer.push(Synchronizer.java:819)\n        at com.ibm.itp.core.serverstore.Synchronizer.push(Synchronizer.java:819)\n        at com.ibm.itp.core.serverstore.Synchronizer.push(Synchronizer.java:884)\n        at com.ibm.itp.core.serverstore.Synchronizer.release(Synchronizer.java:960)\n        at com.ibm.itp.core.serverstore.Synchronizer.release(Synchronizer.java:932)\n        at com.ibm.itp.ui.dialogs.ServerSynchronizationDialog.performRelease(ServerSynchronizationDialog.java)\n        at com.ibm.itp.ui.dialogs.ServerSynchronizationDialog$3.execute(ServerSynchronizationDialog.java)\n        at com.ibm.itp.ui.support.operations.WorkbenchModifyOperation.run(WorkbenchModifyOperation.java:56)\n        at com.ibm.itp.core.resources.Workbench.run(Workbench.java:1225)\n        at com.ibm.itp.ui.support.operations.WorkbenchModifyOperation.internalStart(WorkbenchModifyOperation.java:34)\n        at com.ibm.jface.util.ModalContext.run(ModalContext.java:227)\n\nDW (6/9/00 10:49:52 AM)\n\tFound that the failure occurrs on WIN NT \u0026 Win 2000, but not on Win 98\n\nDJH (6/12/00 4:03:38 PM)\n\tSee also:\n\t\t1FW76SX: IWT:WINNT - release of large imported jar takes several tries\n\nJM (6/22/2000 11:18:51 AM)\n\tREADME with JEP\u0027s notes\n\nJM (6/22/2000 2:10:36 PM)\n\tREADME from JEP \n\tIn some cases, users may experience problems when releasing a large number of \n\tresources (\u003e1000) while running the WebSphere Studio Workbench Java 1.2.2 Edition.\n\n\tThe problem occurs during a release and is made known to the user through a \"Problems\" \n\tdialog with the message: \"Problems occurred synchronizing the selected resources\".  \n\tThe \"details\" of the problem indicates that a \"SeverException\" has occured.  In general\n\tthis problem is not fatal in that released and unreleased resources are consistent in\n\tboth the server and the workbench.  Re-releasing the resources which did not get released\n\tresolves this problem.\n\n\tUnfortunately, the cause of the problem is related to the a subtlety in the TCP implementation\n\tin Windows NT (Win98 users will not experience this problem) which prevents sockets \n\tfrom being reused effectively.  As such, immediately retrying the release operation will \n\tnot always work.  Users may have to wait until the TCP stack clears some unused sockets \n\tbefore attempting to release the resources.  This may take a number (1-4) of minutes.\n\nJM (6/22/2000 2:56:40 PM)\n\tAdded to readme\n\nJM (01/02/2001 12:15:24 PM)\n\tThis is a severe problem for which we need to find a fix/workaround.\n\tMoving to candidates",
    "Additional work on target management is not a committed item in the 2.0 plan. \nChanging resolution to LATER.\n",
    "Reopening to close.",
    "Target management is now provided by Platform/VCM and is based on a totally \ndifferent implementation.\nClosing."
  ],
  "commentCreationDates": [
    "2001-10-11T04:47:31+02:00",
    "2002-01-08T18:26:23+01:00",
    "2002-09-10T19:21:40+02:00",
    "2002-09-10T19:22:10+02:00"
  ],
  "traces": [
    {
      "exceptionType": "java.net.BindException",
      "message": "Address in use: no further information",
      "elements": [
        {
          "method": "java.net.PlainSocketImpl.socketConnect",
          "source": "Native Method"
        },
        {
          "method": "java.net.PlainSocketImpl.doConnect",
          "source": "PlainSocketImpl.java:328"
        },
        {
          "method": "java.net.PlainSocketImpl.connectToAddress",
          "source": "PlainSocketImpl.java:126"
        },
        {
          "method": "java.net.PlainSocketImpl.connect",
          "source": "PlainSocketImpl.java:122"
        },
        {
          "method": "java.net.Socket.\u003cinit\u003e",
          "source": "Socket.java:246"
        },
        {
          "method": "java.net.Socket.\u003cinit\u003e",
          "source": "Socket.java:97"
        },
        {
          "method": "sun.net.NetworkClient.doConnect",
          "source": "NetworkClient.java:56"
        },
        {
          "method": "sun.net.www.http.HttpClient.openServer",
          "source": "HttpClient.java:321"
        },
        {
          "method": "sun.net.www.http.HttpClient.openServer",
          "source": "HttpClient.java:469"
        },
        {
          "method": "sun.net.www.http.HttpClient.\u003cinit\u003e",
          "source": "HttpClient.java:238"
        },
        {
          "method": "sun.net.www.http.HttpClient.\u003cinit\u003e",
          "source": "HttpClient.java:270"
        },
        {
          "method": "sun.net.www.http.HttpClient.New",
          "source": "HttpClient.java:290"
        },
        {
          "method": "sun.net.www.protocol.http.HttpURLConnection.connect",
          "source": "HttpURLConnection.java:366"
        },
        {
          "method": "sun.net.www.protocol.http.HttpURLConnection.getOutputStream",
          "source": "HttpURLConnection.java:435"
        },
        {
          "method": "com.ibm.dav4j.client.comms.WebDAVURLConnection.getOutputStream",
          "source": "WebDAVURLConnection.java:182"
        },
        {
          "method": "com.ibm.dav4j.client.comms.CommunicationsHandler.putBody",
          "source": "CommunicationsHandler.java:118"
        },
        {
          "method": "com.ibm.dav4j.client.comms.CommunicationsHandler.invoke",
          "source": "CommunicationsHandler.java:77"
        },
        {
          "method": "com.ibm.dav4j.client.RemoteServerProxy.proppatch",
          "source": "RemoteServerProxy.java:364"
        },
        {
          "method": "com.ibm.dav4j.client.AbstractResourceHandle.setProperties",
          "source": "AbstractResourceHandle.java"
        },
        {
          "method": "com.ibm.itp.core.serverstore.DavStore.setProperties",
          "source": "DavStore.java:495"
        },
        {
          "method": "com.ibm.itp.core.serverstore.DavResourceManager.updateSyncProperty",
          "source": "DavResourceManager.java:933"
        },
        {
          "method": "com.ibm.itp.core.serverstore.DavResourceManager.write",
          "source": "DavResourceManager.java:978"
        },
        {
          "method": "com.ibm.itp.core.serverstore.Synchronizer.internalPushContentFile",
          "source": "Synchronizer.java:625"
        },
        {
          "method": "com.ibm.itp.core.serverstore.Synchronizer.internalPush",
          "source": "Synchronizer.java:555"
        },
        {
          "method": "com.ibm.itp.core.serverstore.Synchronizer.push",
          "source": "Synchronizer.java:819"
        },
        {
          "method": "com.ibm.itp.core.serverstore.Synchronizer.push",
          "source": "Synchronizer.java:819"
        },
        {
          "method": "com.ibm.itp.core.serverstore.Synchronizer.push",
          "source": "Synchronizer.java:819"
        },
        {
          "method": "com.ibm.itp.core.serverstore.Synchronizer.push",
          "source": "Synchronizer.java:819"
        },
        {
          "method": "com.ibm.itp.core.serverstore.Synchronizer.push",
          "source": "Synchronizer.java:819"
        },
        {
          "method": "com.ibm.itp.core.serverstore.Synchronizer.push",
          "source": "Synchronizer.java:819"
        },
        {
          "method": "com.ibm.itp.core.serverstore.Synchronizer.push",
          "source": "Synchronizer.java:819"
        },
        {
          "method": "com.ibm.itp.core.serverstore.Synchronizer.push",
          "source": "Synchronizer.java:819"
        },
        {
          "method": "com.ibm.itp.core.serverstore.Synchronizer.push",
          "source": "Synchronizer.java:819"
        },
        {
          "method": "com.ibm.itp.core.serverstore.Synchronizer.push",
          "source": "Synchronizer.java:884"
        },
        {
          "method": "com.ibm.itp.core.serverstore.Synchronizer.release",
          "source": "Synchronizer.java:960"
        },
        {
          "method": "com.ibm.itp.core.serverstore.Synchronizer.release",
          "source": "Synchronizer.java:932"
        },
        {
          "method": "com.ibm.itp.ui.dialogs.ServerSynchronizationDialog.performRelease",
          "source": "ServerSynchronizationDialog.java"
        },
        {
          "method": "com.ibm.itp.ui.dialogs.ServerSynchronizationDialog$3.execute",
          "source": "ServerSynchronizationDialog.java"
        },
        {
          "method": "com.ibm.itp.ui.support.operations.WorkbenchModifyOperation.run",
          "source": "WorkbenchModifyOperation.java:56"
        },
        {
          "method": "com.ibm.itp.core.resources.Workbench.run",
          "source": "Workbench.java:1225"
        },
        {
          "method": "com.ibm.itp.ui.support.operations.WorkbenchModifyOperation.internalStart",
          "source": "WorkbenchModifyOperation.java:34"
        },
        {
          "method": "com.ibm.jface.util.ModalContext.run",
          "source": "ModalContext.java:227"
        }
      ],
      "number": 0,
      "commentIndex": 0,
      "bugId": "2998",
      "date": "2001-10-11T04:47:31+02:00",
      "product": "Platform",
      "component": "Resources",
      "severity": "normal"
    },
    {
      "exceptionType": "java.net.BindException",
      "message": "Address in use: no further information",
      "elements": [
        {
          "method": "java.net.PlainSocketImpl.socketConnect",
          "source": "Native Method"
        },
        {
          "method": "java.net.PlainSocketImpl.doConnect",
          "source": "PlainSocketImpl.java:328"
        },
        {
          "method": "java.net.PlainSocketImpl.connectToAddress",
          "source": "PlainSocketImpl.java:126"
        },
        {
          "method": "java.net.PlainSocketImpl.connect",
          "source": "PlainSocketImpl.java:122"
        },
        {
          "method": "java.net.Socket.\u003cinit\u003e",
          "source": "Socket.java:246"
        },
        {
          "method": "java.net.Socket.\u003cinit\u003e",
          "source": "Socket.java:97"
        },
        {
          "method": "sun.net.NetworkClient.doConnect",
          "source": "NetworkClient.java:56"
        },
        {
          "method": "sun.net.www.http.HttpClient.openServer",
          "source": "HttpClient.java:321"
        },
        {
          "method": "sun.net.www.http.HttpClient.openServer",
          "source": "HttpClient.java:469"
        },
        {
          "method": "sun.net.www.http.HttpClient.\u003cinit\u003e",
          "source": "HttpClient.java:238"
        },
        {
          "method": "sun.net.www.http.HttpClient.\u003cinit\u003e",
          "source": "HttpClient.java:270"
        },
        {
          "method": "sun.net.www.http.HttpClient.New",
          "source": "HttpClient.java:290"
        },
        {
          "method": "sun.net.www.protocol.http.HttpURLConnection.connect",
          "source": "HttpURLConnection.java:366"
        },
        {
          "method": "sun.net.www.protocol.http.HttpURLConnection.getOutputStream",
          "source": "HttpURLConnection.java:435"
        },
        {
          "method": "com.ibm.dav4j.client.comms.WebDAVURLConnection.getOutputStream",
          "source": "WebDAVURLConnection.java:182"
        },
        {
          "method": "com.ibm.dav4j.client.comms.CommunicationsHandler.putBody",
          "source": "CommunicationsHandler.java:118"
        },
        {
          "method": "com.ibm.dav4j.client.comms.CommunicationsHandler.invoke",
          "source": "CommunicationsHandler.java:77"
        },
        {
          "method": "com.ibm.dav4j.client.RemoteServerProxy.propfind",
          "source": "RemoteServerProxy.java:350"
        },
        {
          "method": "com.ibm.dav4j.client.AbstractResourceHandle.getProperties",
          "source": "AbstractResourceHandle.java"
        },
        {
          "method": "com.ibm.itp.core.serverstore.DavStore.getProperties",
          "source": "DavStore.java:394"
        },
        {
          "method": "com.ibm.itp.core.resources.ServerMetaArea.exists",
          "source": "ServerMetaArea.java:187"
        },
        {
          "method": "com.ibm.itp.core.resources.ServerMetaArea.exists",
          "source": "ServerMetaArea.java:161"
        },
        {
          "method": "com.ibm.itp.core.resources.ServerMetaArea.createFolder",
          "source": "ServerMetaArea.java:108"
        },
        {
          "method": "com.ibm.itp.core.resources.ServerMetaArea.createContentArea",
          "source": "ServerMetaArea.java:93"
        },
        {
          "method": "com.ibm.itp.core.serverstore.Synchronizer.ensureMetaAreasExist",
          "source": "Synchronizer.java:167"
        },
        {
          "method": "com.ibm.itp.core.serverstore.Synchronizer.internalPush",
          "source": "Synchronizer.java:555"
        },
        {
          "method": "com.ibm.itp.core.serverstore.Synchronizer.push",
          "source": "Synchronizer.java:819"
        },
        {
          "method": "com.ibm.itp.core.serverstore.Synchronizer.push",
          "source": "Synchronizer.java:819"
        },
        {
          "method": "com.ibm.itp.core.serverstore.Synchronizer.push",
          "source": "Synchronizer.java:819"
        },
        {
          "method": "com.ibm.itp.core.serverstore.Synchronizer.push",
          "source": "Synchronizer.java:819"
        },
        {
          "method": "com.ibm.itp.core.serverstore.Synchronizer.push",
          "source": "Synchronizer.java:819"
        },
        {
          "method": "com.ibm.itp.core.serverstore.Synchronizer.push",
          "source": "Synchronizer.java:819"
        },
        {
          "method": "com.ibm.itp.core.serverstore.Synchronizer.push",
          "source": "Synchronizer.java:819"
        },
        {
          "method": "com.ibm.itp.core.serverstore.Synchronizer.push",
          "source": "Synchronizer.java:819"
        },
        {
          "method": "com.ibm.itp.core.serverstore.Synchronizer.push",
          "source": "Synchronizer.java:819"
        },
        {
          "method": "com.ibm.itp.core.serverstore.Synchronizer.push",
          "source": "Synchronizer.java:884"
        },
        {
          "method": "com.ibm.itp.core.serverstore.Synchronizer.release",
          "source": "Synchronizer.java:960"
        },
        {
          "method": "com.ibm.itp.core.serverstore.Synchronizer.release",
          "source": "Synchronizer.java:932"
        },
        {
          "method": "com.ibm.itp.ui.dialogs.ServerSynchronizationDialog.performRelease",
          "source": "ServerSynchronizationDialog.java"
        },
        {
          "method": "com.ibm.itp.ui.dialogs.ServerSynchronizationDialog$3.execute",
          "source": "ServerSynchronizationDialog.java"
        },
        {
          "method": "com.ibm.itp.ui.support.operations.WorkbenchModifyOperation.run",
          "source": "WorkbenchModifyOperation.java:56"
        },
        {
          "method": "com.ibm.itp.core.resources.Workbench.run",
          "source": "Workbench.java:1225"
        },
        {
          "method": "com.ibm.itp.ui.support.operations.WorkbenchModifyOperation.internalStart",
          "source": "WorkbenchModifyOperation.java:34"
        },
        {
          "method": "com.ibm.jface.util.ModalContext.run",
          "source": "ModalContext.java:227"
        }
      ],
      "number": 1,
      "commentIndex": 0,
      "bugId": "2998",
      "date": "2001-10-11T04:47:31+02:00",
      "product": "Platform",
      "component": "Resources",
      "severity": "normal"
    }
  ],
  "groupId": "2998",
  "bugId": "2998",
  "date": "2001-10-11T04:47:31+02:00",
  "product": "Platform",
  "component": "Resources",
  "severity": "normal"
}