{
  "comments": [
    "Build I20030121\n\nIn my workspace, I have\na test.sh file\na test program\n\n- Edit the runtime config file of a java app\n- select some text from the file test.sh (something like -Djava.library.path ...)\n- In the VM arguments text entry of the runtime config file, paste the selection. The \nfollowing stack trace occasionally comes up. From there, Eclipse is in a bizarre state and \nneeds to be restarted.\nThis may be a problem at a lower level with drag and drop - does this problem ring a \nbell?\n\n!ENTRY org.eclipse.debug.ui 4 120 Jan 24, 2003 16:51:27.267\n!MESSAGE Error logged from Debug UI: \n!STACK 1\norg.eclipse.debug.core.DebugException[5012]: org.xml.sax.SAXParseException: \nCharacter reference \"\u0026#0\" is an invalid XML character.\n        at org.apache.xerces.parsers.DOMParser.parse(DOMParser.java:235)\n        at \norg.apache.xerces.jaxp.DocumentBuilderImpl.parse(DocumentBuilderImpl.java:209)\n        at \norg.eclipse.debug.internal.core.LaunchManager.createInfoFromXML(LaunchManager.ja\nva:423)\n        at \norg.eclipse.debug.internal.core.LaunchManager.getInfo(LaunchManager.java:473)\n        at \norg.eclipse.debug.internal.core.LaunchConfiguration.getInfo(LaunchConfiguration.java:\n348)\n        at \norg.eclipse.debug.internal.core.LaunchConfiguration.getType(LaunchConfiguration.java\n:271)\n        at \norg.eclipse.debug.internal.ui.launchConfigurations.LaunchConfigurationTreeContentPro\nvider.getParent(LaunchConfigurationTreeContentProvider.java:89)\n        at \norg.eclipse.jface.viewers.AbstractTreeViewer.internalExpand(AbstractTreeViewer.java:7\n78)\n        at \norg.eclipse.jface.viewers.AbstractTreeViewer.setSelectionToWidget(AbstractTreeViewer.\njava:1190)\n        at \norg.eclipse.jface.viewers.StructuredViewer.setSelectionToWidget(StructuredViewer.java:\n993)\n        at \norg.eclipse.jface.viewers.StructuredViewer.preservingSelection(StructuredViewer.java:7\n48)\n        at \norg.eclipse.jface.viewers.AbstractTreeViewer.remove(AbstractTreeViewer.java:1021)\n        at \norg.eclipse.jface.viewers.AbstractTreeViewer.remove(AbstractTreeViewer.java:1041)\n        at \norg.eclipse.debug.internal.ui.launchConfigurations.LaunchConfigurationView.launchCo\nnfigurationRemoved(LaunchConfigurationView.java:201)\n        at \norg.eclipse.debug.internal.core.LaunchManager.launchConfigurationDeleted(LaunchMa\nnager.java:655)\n        at \norg.eclipse.debug.internal.core.LaunchManager.launchConfigurationChanged(Launch\nManager.java:703)\n        at \norg.eclipse.debug.internal.core.LaunchConfigurationWorkingCopy.writeNewFile(Launch\nConfigurationWorkingCopy.java:201)\n        at \norg.eclipse.debug.internal.core.LaunchConfigurationWorkingCopy$1.run(LaunchConfig\nurationWorkingCopy.java:149)\n        at org.eclipse.core.internal.resources.Workspace.run(Workspace.java:1580)\n        at \norg.eclipse.debug.internal.core.LaunchConfigurationWorkingCopy.doSave(LaunchConfi\ngurationWorkingCopy.java:159)\n        at \norg.eclipse.debug.internal.ui.launchConfigurations.LaunchConfigurationTabGroupView\ner.handleApplyPressed(LaunchConfigurationTabGroupViewer.java:1004)\n        at \norg.eclipse.debug.internal.ui.launchConfigurations.LaunchConfigurationTabGroupView\ner$3.widgetSelected(LaunchConfigurationTabGroupViewer.java:253)\n        at org.eclipse.swt.widgets.TypedListener.handleEvent(TypedListener.java:87)\n        at org.eclipse.swt.widgets.EventTable.sendEvent(EventTable.java:77)\n        at org.eclipse.swt.widgets.Widget.notifyListeners(Widget.java:634)\n        at org.eclipse.swt.widgets.Display.runDeferredEvents(Display.java:1252)\n        at org.eclipse.swt.widgets.Display.readAndDispatch(Display.java:1009)\n        at org.eclipse.jface.window.Window.runEventLoop(Window.java:561)\n        at org.eclipse.jface.window.Window.open(Window.java:541)\n        at \norg.eclipse.debug.internal.ui.launchConfigurations.LaunchConfigurationsDialog.openDi\nalogOnSelection(LaunchConfigurationsDialog.java:515)\n        at \norg.eclipse.debug.internal.ui.launchConfigurations.LaunchConfigurationsDialog.open(L\naunchConfigurationsDialog.java:469)\n        at org.eclipse.debug.ui.DebugUITools$1.run(DebugUITools.java:368)\n        at org.eclipse.swt.custom.BusyIndicator.showWhile(BusyIndicator.java:65)\n        at \norg.eclipse.debug.ui.DebugUITools.openLaunchConfigurationDialogOnGroup(DebugUI\nTools.java:372)\n        at \norg.eclipse.debug.ui.DebugUITools.openLaunchConfigurationDialogOnGroup(DebugUI\nTools.java:314)\n        at \norg.eclipse.debug.ui.actions.OpenLaunchDialogAction.run(OpenLaunchDialogAction.ja\nva:66)\n        at org.eclipse.jface.action.Action.runWithEvent(Action.java:804)\n        at \norg.eclipse.jface.action.ActionContributionItem.handleWidgetSelection(ActionContributio\nnItem.java:422)\n        at \norg.eclipse.jface.action.ActionContributionItem.handleWidgetEvent(ActionContributionIte\nm.java:374)\n        at \norg.eclipse.jface.action.ActionContributionItem.access$0(ActionContributionItem.java:36\n8)\n        at \norg.eclipse.jface.action.ActionContributionItem$ActionListener.handleEvent(ActionContri\nbutionItem.java:69)\n        at org.eclipse.swt.widgets.EventTable.sendEvent(EventTable.java:77)\n        at org.eclipse.swt.widgets.Widget.notifyListeners(Widget.java:634)\n        at org.eclipse.swt.widgets.Display.runDeferredEvents(Display.java:1252)\n        at org.eclipse.swt.widgets.Display.readAndDispatch(Display.java:1009)\n        at org.eclipse.ui.internal.Workbench.runEventLoop(Workbench.java:1525)\n        at org.eclipse.ui.internal.Workbench.run(Workbench.java:1508)\n        at \norg.eclipse.core.internal.boot.InternalBootLoader.run(InternalBootLoader.java:845)\n        at org.eclipse.core.boot.BootLoader.run(BootLoader.java:462)\n        at java.lang.reflect.Method.invoke(Native Method)\n        at org.eclipse.core.launcher.Main.basicRun(Main.java:247)\n        at org.eclipse.core.launcher.Main.run(Main.java:703)\n        at org.eclipse.core.launcher.Main.main(Main.java:539)\n        at java.lang.reflect.Method.invoke(Native Method)\n        at com.apple.buckyball.app.LaunchRunner.run(LaunchRunner.java:82)\n        at com.apple.buckyball.app.LaunchRunner.callMain(LaunchRunner.java:44)\n        at com.apple.buckyball.app.CarbonLibApp.launch(CarbonLibApp.java:67)\n!ENTRY org.eclipse.debug.core 4 5012 Jan 24, 2003 16:51:27.272\n!MESSAGE Exception occurred while reading launch configuration file: \norg.xml.sax.SAXParseException: Character reference \"\u0026#0\" is an invalid XML character..\n!STACK 0\norg.xml.sax.SAXParseException: Character reference \"\u0026#0\" is an invalid XML character.\n        at org.apache.xerces.parsers.DOMParser.parse(DOMParser.java:235)\n        at \norg.apache.xerces.jaxp.DocumentBuilderImpl.parse(DocumentBuilderImpl.java:209)\n        at \norg.eclipse.debug.internal.core.LaunchManager.createInfoFromXML(LaunchManager.ja\nva:423)\n        at \norg.eclipse.debug.internal.core.LaunchManager.getInfo(LaunchManager.java:473)\n        at \norg.eclipse.debug.internal.core.LaunchConfiguration.getInfo(LaunchConfiguration.java:\n348)\n        at \norg.eclipse.debug.internal.core.LaunchConfiguration.getType(LaunchConfiguration.java\n:271)\n        at \norg.eclipse.debug.internal.ui.launchConfigurations.LaunchConfigurationTreeContentPro\nvider.getParent(LaunchConfigurationTreeContentProvider.java:89)\n        at \norg.eclipse.jface.viewers.AbstractTreeViewer.internalExpand(AbstractTreeViewer.java:7\n78)\n        at \norg.eclipse.jface.viewers.AbstractTreeViewer.setSelectionToWidget(AbstractTreeViewer.\njava:1190)\n        at \norg.eclipse.jface.viewers.StructuredViewer.setSelectionToWidget(StructuredViewer.java:\n993)\n        at \norg.eclipse.jface.viewers.StructuredViewer.preservingSelection(StructuredViewer.java:7\n48)\n        at \norg.eclipse.jface.viewers.AbstractTreeViewer.remove(AbstractTreeViewer.java:1021)\n        at \norg.eclipse.jface.viewers.AbstractTreeViewer.remove(AbstractTreeViewer.java:1041)\n        at \norg.eclipse.debug.internal.ui.launchConfigurations.LaunchConfigurationView.launchCo\nnfigurationRemoved(LaunchConfigurationView.java:201)\n        at \norg.eclipse.debug.internal.core.LaunchManager.launchConfigurationDeleted(LaunchMa\nnager.java:655)\n        at \norg.eclipse.debug.internal.core.LaunchManager.launchConfigurationChanged(Launch\nManager.java:703)\n        at \norg.eclipse.debug.internal.core.LaunchConfigurationWorkingCopy.writeNewFile(Launch\nConfigurationWorkingCopy.java:201)\n        at \norg.eclipse.debug.internal.core.LaunchConfigurationWorkingCopy$1.run(LaunchConfig\nurationWorkingCopy.java:149)\n        at org.eclipse.core.internal.resources.Workspace.run(Workspace.java:1580)\n        at \norg.eclipse.debug.internal.core.LaunchConfigurationWorkingCopy.doSave(LaunchConfi\ngurationWorkingCopy.java:159)\n        at \norg.eclipse.debug.internal.ui.launchConfigurations.LaunchConfigurationTabGroupView\ner.handleApplyPressed(LaunchConfigurationTabGroupViewer.java:1004)\n        at \norg.eclipse.debug.internal.ui.launchConfigurations.LaunchConfigurationTabGroupView\ner$3.widgetSelected(LaunchConfigurationTabGroupViewer.java:253)\n        at org.eclipse.swt.widgets.TypedListener.handleEvent(TypedListener.java:87)\n        at org.eclipse.swt.widgets.EventTable.sendEvent(EventTable.java:77)\n        at org.eclipse.swt.widgets.Widget.notifyListeners(Widget.java:634)\n        at org.eclipse.swt.widgets.Display.runDeferredEvents(Display.java:1252)\n        at org.eclipse.swt.widgets.Display.readAndDispatch(Display.java:1009)\n        at org.eclipse.jface.window.Window.runEventLoop(Window.java:561)\n        at org.eclipse.jface.window.Window.open(Window.java:541)\n        at \norg.eclipse.debug.internal.ui.launchConfigurations.LaunchConfigurationsDialog.openDi\nalogOnSelection(LaunchConfigurationsDialog.java:515)\n        at \norg.eclipse.debug.internal.ui.launchConfigurations.LaunchConfigurationsDialog.open(L\naunchConfigurationsDialog.java:469)\n        at org.eclipse.debug.ui.DebugUITools$1.run(DebugUITools.java:368)\n        at org.eclipse.swt.custom.BusyIndicator.showWhile(BusyIndicator.java:65)\n        at \norg.eclipse.debug.ui.DebugUITools.openLaunchConfigurationDialogOnGroup(DebugUI\nTools.java:372)\n        at \norg.eclipse.debug.ui.DebugUITools.openLaunchConfigurationDialogOnGroup(DebugUI\nTools.java:314)\n        at \norg.eclipse.debug.ui.actions.OpenLaunchDialogAction.run(OpenLaunchDialogAction.ja\nva:66)\n        at org.eclipse.jface.action.Action.runWithEvent(Action.java:804)\n        at \norg.eclipse.jface.action.ActionContributionItem.handleWidgetSelection(ActionContributio\nnItem.java:422)\n        at \norg.eclipse.jface.action.ActionContributionItem.handleWidgetEvent(ActionContributionIte\nm.java:374)\n        at \norg.eclipse.jface.action.ActionContributionItem.access$0(ActionContributionItem.java:36\n8)\n        at \norg.eclipse.jface.action.ActionContributionItem$ActionListener.handleEvent(ActionContri\nbutionItem.java:69)\n        at org.eclipse.swt.widgets.EventTable.sendEvent(EventTable.java:77)\n        at org.eclipse.swt.widgets.Widget.notifyListeners(Widget.java:634)\n        at org.eclipse.swt.widgets.Display.runDeferredEvents(Display.java:1252)\n        at org.eclipse.swt.widgets.Display.readAndDispatch(Display.java:1009)\n        at org.eclipse.ui.internal.Workbench.runEventLoop(Workbench.java:1525)\n        at org.eclipse.ui.internal.Workbench.run(Workbench.java:1508)\n        at \norg.eclipse.core.internal.boot.InternalBootLoader.run(InternalBootLoader.java:845)\n        at org.eclipse.core.boot.BootLoader.run(BootLoader.java:462)\n        at java.lang.reflect.Method.invoke(Native Method)\n        at org.eclipse.core.launcher.Main.basicRun(Main.java:247)\n        at org.eclipse.core.launcher.Main.run(Main.java:703)\n        at org.eclipse.core.launcher.Main.main(Main.java:539)\n        at java.lang.reflect.Method.invoke(Native Method)\n        at com.apple.buckyball.app.LaunchRunner.run(LaunchRunner.java:82)\n        at com.apple.buckyball.app.LaunchRunner.callMain(LaunchRunner.java:44)\n        at com.apple.buckyball.app.CarbonLibApp.launch(CarbonLibApp.java:67)\n[Fatal Error] :6:202: Character reference \"\u0026#0\" is an invalid XML character.\n[Fatal Error] :6:202: Character reference \"\u0026#0\" is an invalid XML character.",
    "Needs investigation.",
    "Note that if I\u0027m the only one who reported this kind of problem, it\u0027s possibly \na Mac specific issue. You can reassign it to SWT. It\u0027s possible that copying \ntext from a shell script on this platform has some issues.",
    "It could be SWT-related, but the stack trace shows a problem with XML parsing. \nIt could be realted (i.e. a corrput paste makes the config corrupt). Does it \nmatter what you paste into the field?",
    "Yes. It had to be copied from a shell script.",
    "Please attach the shell script to this bug report.",
    "Created an attachment (id\u003d3593)\nshell script\n\nThe stack trace was caused on the Mac with I20030121 by:\n- opening the shell script with a standard editor in Eclipse\n- copy this part:\n-Djava.library.path\u003d/Users/stephennorthover/Desktop/CHRIX_I20030121/eclipse/workspace/org.eclipse.swt.carbon/os/macosx/ppc/\n\n- past it into the VM arguments dialog\n- Apply changes\n\nNote that I tried again on the same config and I can\u0027t reproduce the problem\nanymore.",
    "Joe, please verify that this no longer causes trouble on the Mac.",
    "I cannot duplicate this on build 20030220.  However, I\u0027m using Apple-C and Apple-V to \ncopy and paste.  The first description of the problem mentions drag and drop.  \nChristophe, is it possible to copy \u0026 paste text using drag and drop on OSX?  If so, how?",
    "You did correctly what I did by using Apple C and Apple V.",
    "Marking as WORKSFORME.\n"
  ],
  "commentCreationDates": [
    "2003-01-24T21:32:56+01:00",
    "2003-01-25T14:53:20+01:00",
    "2003-02-19T22:30:49+01:00",
    "2003-02-19T22:46:48+01:00",
    "2003-02-19T23:12:18+01:00",
    "2003-02-20T01:06:56+01:00",
    "2003-02-20T14:26:22+01:00",
    "2003-02-20T15:24:49+01:00",
    "2003-02-20T22:25:20+01:00",
    "2003-02-21T14:08:58+01:00",
    "2003-02-21T17:49:18+01:00"
  ],
  "traces": [
    {
      "exceptionType": "org.xml.sax.SAXParseException",
      "message": "Character reference \"\u0026#0\" is an invalid XML character.",
      "elements": [
        {
          "method": "org.apache.xerces.parsers.DOMParser.parse",
          "source": "DOMParser.java:235"
        },
        {
          "method": "org.apache.xerces.jaxp.DocumentBuilderImpl.parse",
          "source": "DocumentBuilderImpl.java:209"
        },
        {
          "method": "org.eclipse.debug.internal.core.LaunchManager.createInfoFromXML",
          "source": "LaunchManager.ja va:423"
        },
        {
          "method": "org.eclipse.debug.internal.core.LaunchManager.getInfo",
          "source": "LaunchManager.java:473"
        },
        {
          "method": "org.eclipse.debug.internal.core.LaunchConfiguration.getInfo",
          "source": "LaunchConfiguration.java: 348"
        },
        {
          "method": "org.eclipse.debug.internal.core.LaunchConfiguration.getType",
          "source": "LaunchConfiguration.java :271"
        },
        {
          "method": "org.eclipse.debug.internal.ui.launchConfigurations.LaunchConfigurationTreeContentProvider.getParent",
          "source": "LaunchConfigurationTreeContentProvider.java:89"
        },
        {
          "method": "org.eclipse.jface.viewers.AbstractTreeViewer.internalExpand",
          "source": "AbstractTreeViewer.java:7 78"
        },
        {
          "method": "org.eclipse.jface.viewers.AbstractTreeViewer.setSelectionToWidget",
          "source": "AbstractTreeViewer. java:1190"
        },
        {
          "method": "org.eclipse.jface.viewers.StructuredViewer.setSelectionToWidget",
          "source": "StructuredViewer.java: 993"
        },
        {
          "method": "org.eclipse.jface.viewers.StructuredViewer.preservingSelection",
          "source": "StructuredViewer.java:7 48"
        },
        {
          "method": "org.eclipse.jface.viewers.AbstractTreeViewer.remove",
          "source": "AbstractTreeViewer.java:1021"
        },
        {
          "method": "org.eclipse.jface.viewers.AbstractTreeViewer.remove",
          "source": "AbstractTreeViewer.java:1041"
        },
        {
          "method": "org.eclipse.debug.internal.ui.launchConfigurations.LaunchConfigurationView.launchConfigurationRemoved",
          "source": "LaunchConfigurationView.java:201"
        },
        {
          "method": "org.eclipse.debug.internal.core.LaunchManager.launchConfigurationDeleted",
          "source": "LaunchMa nager.java:655"
        },
        {
          "method": "org.eclipse.debug.internal.core.LaunchManager.launchConfigurationChanged",
          "source": "Launch Manager.java:703"
        },
        {
          "method": "org.eclipse.debug.internal.core.LaunchConfigurationWorkingCopy.writeNewFile",
          "source": "Launch ConfigurationWorkingCopy.java:201"
        },
        {
          "method": "org.eclipse.debug.internal.core.LaunchConfigurationWorkingCopy$1.run",
          "source": "LaunchConfig urationWorkingCopy.java:149"
        },
        {
          "method": "org.eclipse.core.internal.resources.Workspace.run",
          "source": "Workspace.java:1580"
        },
        {
          "method": "org.eclipse.debug.internal.core.LaunchConfigurationWorkingCopy.doSave",
          "source": "LaunchConfi gurationWorkingCopy.java:159"
        },
        {
          "method": "org.eclipse.debug.internal.ui.launchConfigurations.LaunchConfigurationTabGroupViewer.handleApplyPressed",
          "source": "LaunchConfigurationTabGroupViewer.java:1004"
        },
        {
          "method": "org.eclipse.debug.internal.ui.launchConfigurations.LaunchConfigurationTabGroupViewer$3.widgetSelected",
          "source": "LaunchConfigurationTabGroupViewer.java:253"
        },
        {
          "method": "org.eclipse.swt.widgets.TypedListener.handleEvent",
          "source": "TypedListener.java:87"
        },
        {
          "method": "org.eclipse.swt.widgets.EventTable.sendEvent",
          "source": "EventTable.java:77"
        },
        {
          "method": "org.eclipse.swt.widgets.Widget.notifyListeners",
          "source": "Widget.java:634"
        },
        {
          "method": "org.eclipse.swt.widgets.Display.runDeferredEvents",
          "source": "Display.java:1252"
        },
        {
          "method": "org.eclipse.swt.widgets.Display.readAndDispatch",
          "source": "Display.java:1009"
        },
        {
          "method": "org.eclipse.jface.window.Window.runEventLoop",
          "source": "Window.java:561"
        },
        {
          "method": "org.eclipse.jface.window.Window.open",
          "source": "Window.java:541"
        },
        {
          "method": "org.eclipse.debug.internal.ui.launchConfigurations.LaunchConfigurationsDialog.openDialogOnSelection",
          "source": "LaunchConfigurationsDialog.java:515"
        },
        {
          "method": "org.eclipse.debug.internal.ui.launchConfigurations.LaunchConfigurationsDialog.open",
          "source": "L aunchConfigurationsDialog.java:469"
        },
        {
          "method": "org.eclipse.debug.ui.DebugUITools$1.run",
          "source": "DebugUITools.java:368"
        },
        {
          "method": "org.eclipse.swt.custom.BusyIndicator.showWhile",
          "source": "BusyIndicator.java:65"
        },
        {
          "method": "org.eclipse.debug.ui.DebugUITools.openLaunchConfigurationDialogOnGroup",
          "source": "DebugUI Tools.java:372"
        },
        {
          "method": "org.eclipse.debug.ui.DebugUITools.openLaunchConfigurationDialogOnGroup",
          "source": "DebugUI Tools.java:314"
        },
        {
          "method": "org.eclipse.debug.ui.actions.OpenLaunchDialogAction.run",
          "source": "OpenLaunchDialogAction.ja va:66"
        },
        {
          "method": "org.eclipse.jface.action.Action.runWithEvent",
          "source": "Action.java:804"
        },
        {
          "method": "org.eclipse.jface.action.ActionContributionItem.handleWidgetSelection",
          "source": "ActionContributio nItem.java:422"
        },
        {
          "method": "org.eclipse.jface.action.ActionContributionItem.handleWidgetEvent",
          "source": "ActionContributionIte m.java:374"
        },
        {
          "method": "org.eclipse.jface.action.ActionContributionItem.access$0",
          "source": "ActionContributionItem.java:36 8"
        },
        {
          "method": "org.eclipse.jface.action.ActionContributionItem$ActionListener.handleEvent",
          "source": "ActionContri butionItem.java:69"
        },
        {
          "method": "org.eclipse.swt.widgets.EventTable.sendEvent",
          "source": "EventTable.java:77"
        },
        {
          "method": "org.eclipse.swt.widgets.Widget.notifyListeners",
          "source": "Widget.java:634"
        },
        {
          "method": "org.eclipse.swt.widgets.Display.runDeferredEvents",
          "source": "Display.java:1252"
        },
        {
          "method": "org.eclipse.swt.widgets.Display.readAndDispatch",
          "source": "Display.java:1009"
        },
        {
          "method": "org.eclipse.ui.internal.Workbench.runEventLoop",
          "source": "Workbench.java:1525"
        },
        {
          "method": "org.eclipse.ui.internal.Workbench.run",
          "source": "Workbench.java:1508"
        },
        {
          "method": "org.eclipse.core.internal.boot.InternalBootLoader.run",
          "source": "InternalBootLoader.java:845"
        },
        {
          "method": "org.eclipse.core.boot.BootLoader.run",
          "source": "BootLoader.java:462"
        },
        {
          "method": "java.lang.reflect.Method.invoke",
          "source": "Native Method"
        },
        {
          "method": "org.eclipse.core.launcher.Main.basicRun",
          "source": "Main.java:247"
        },
        {
          "method": "org.eclipse.core.launcher.Main.run",
          "source": "Main.java:703"
        },
        {
          "method": "org.eclipse.core.launcher.Main.main",
          "source": "Main.java:539"
        },
        {
          "method": "java.lang.reflect.Method.invoke",
          "source": "Native Method"
        },
        {
          "method": "com.apple.buckyball.app.LaunchRunner.run",
          "source": "LaunchRunner.java:82"
        },
        {
          "method": "com.apple.buckyball.app.LaunchRunner.callMain",
          "source": "LaunchRunner.java:44"
        },
        {
          "method": "com.apple.buckyball.app.CarbonLibApp.launch",
          "source": "CarbonLibApp.java:67"
        }
      ],
      "number": 0,
      "commentIndex": 0,
      "bugId": "30211",
      "date": "2003-01-24T21:32:56+01:00",
      "product": "Platform",
      "component": "Debug",
      "severity": "normal"
    },
    {
      "exceptionType": "org.xml.sax.SAXParseException",
      "message": "Character reference \"\u0026#0\" is an invalid XML character.",
      "elements": [
        {
          "method": "org.apache.xerces.parsers.DOMParser.parse",
          "source": "DOMParser.java:235"
        },
        {
          "method": "org.apache.xerces.jaxp.DocumentBuilderImpl.parse",
          "source": "DocumentBuilderImpl.java:209"
        },
        {
          "method": "org.eclipse.debug.internal.core.LaunchManager.createInfoFromXML",
          "source": "LaunchManager.ja va:423"
        },
        {
          "method": "org.eclipse.debug.internal.core.LaunchManager.getInfo",
          "source": "LaunchManager.java:473"
        },
        {
          "method": "org.eclipse.debug.internal.core.LaunchConfiguration.getInfo",
          "source": "LaunchConfiguration.java: 348"
        },
        {
          "method": "org.eclipse.debug.internal.core.LaunchConfiguration.getType",
          "source": "LaunchConfiguration.java :271"
        },
        {
          "method": "org.eclipse.debug.internal.ui.launchConfigurations.LaunchConfigurationTreeContentProvider.getParent",
          "source": "LaunchConfigurationTreeContentProvider.java:89"
        },
        {
          "method": "org.eclipse.jface.viewers.AbstractTreeViewer.internalExpand",
          "source": "AbstractTreeViewer.java:7 78"
        },
        {
          "method": "org.eclipse.jface.viewers.AbstractTreeViewer.setSelectionToWidget",
          "source": "AbstractTreeViewer. java:1190"
        },
        {
          "method": "org.eclipse.jface.viewers.StructuredViewer.setSelectionToWidget",
          "source": "StructuredViewer.java: 993"
        },
        {
          "method": "org.eclipse.jface.viewers.StructuredViewer.preservingSelection",
          "source": "StructuredViewer.java:7 48"
        },
        {
          "method": "org.eclipse.jface.viewers.AbstractTreeViewer.remove",
          "source": "AbstractTreeViewer.java:1021"
        },
        {
          "method": "org.eclipse.jface.viewers.AbstractTreeViewer.remove",
          "source": "AbstractTreeViewer.java:1041"
        },
        {
          "method": "org.eclipse.debug.internal.ui.launchConfigurations.LaunchConfigurationView.launchConfigurationRemoved",
          "source": "LaunchConfigurationView.java:201"
        },
        {
          "method": "org.eclipse.debug.internal.core.LaunchManager.launchConfigurationDeleted",
          "source": "LaunchMa nager.java:655"
        },
        {
          "method": "org.eclipse.debug.internal.core.LaunchManager.launchConfigurationChanged",
          "source": "Launch Manager.java:703"
        },
        {
          "method": "org.eclipse.debug.internal.core.LaunchConfigurationWorkingCopy.writeNewFile",
          "source": "Launch ConfigurationWorkingCopy.java:201"
        },
        {
          "method": "org.eclipse.debug.internal.core.LaunchConfigurationWorkingCopy$1.run",
          "source": "LaunchConfig urationWorkingCopy.java:149"
        },
        {
          "method": "org.eclipse.core.internal.resources.Workspace.run",
          "source": "Workspace.java:1580"
        },
        {
          "method": "org.eclipse.debug.internal.core.LaunchConfigurationWorkingCopy.doSave",
          "source": "LaunchConfi gurationWorkingCopy.java:159"
        },
        {
          "method": "org.eclipse.debug.internal.ui.launchConfigurations.LaunchConfigurationTabGroupViewer.handleApplyPressed",
          "source": "LaunchConfigurationTabGroupViewer.java:1004"
        },
        {
          "method": "org.eclipse.debug.internal.ui.launchConfigurations.LaunchConfigurationTabGroupViewer$3.widgetSelected",
          "source": "LaunchConfigurationTabGroupViewer.java:253"
        },
        {
          "method": "org.eclipse.swt.widgets.TypedListener.handleEvent",
          "source": "TypedListener.java:87"
        },
        {
          "method": "org.eclipse.swt.widgets.EventTable.sendEvent",
          "source": "EventTable.java:77"
        },
        {
          "method": "org.eclipse.swt.widgets.Widget.notifyListeners",
          "source": "Widget.java:634"
        },
        {
          "method": "org.eclipse.swt.widgets.Display.runDeferredEvents",
          "source": "Display.java:1252"
        },
        {
          "method": "org.eclipse.swt.widgets.Display.readAndDispatch",
          "source": "Display.java:1009"
        },
        {
          "method": "org.eclipse.jface.window.Window.runEventLoop",
          "source": "Window.java:561"
        },
        {
          "method": "org.eclipse.jface.window.Window.open",
          "source": "Window.java:541"
        },
        {
          "method": "org.eclipse.debug.internal.ui.launchConfigurations.LaunchConfigurationsDialog.openDialogOnSelection",
          "source": "LaunchConfigurationsDialog.java:515"
        },
        {
          "method": "org.eclipse.debug.internal.ui.launchConfigurations.LaunchConfigurationsDialog.open",
          "source": "L aunchConfigurationsDialog.java:469"
        },
        {
          "method": "org.eclipse.debug.ui.DebugUITools$1.run",
          "source": "DebugUITools.java:368"
        },
        {
          "method": "org.eclipse.swt.custom.BusyIndicator.showWhile",
          "source": "BusyIndicator.java:65"
        },
        {
          "method": "org.eclipse.debug.ui.DebugUITools.openLaunchConfigurationDialogOnGroup",
          "source": "DebugUI Tools.java:372"
        },
        {
          "method": "org.eclipse.debug.ui.DebugUITools.openLaunchConfigurationDialogOnGroup",
          "source": "DebugUI Tools.java:314"
        },
        {
          "method": "org.eclipse.debug.ui.actions.OpenLaunchDialogAction.run",
          "source": "OpenLaunchDialogAction.ja va:66"
        },
        {
          "method": "org.eclipse.jface.action.Action.runWithEvent",
          "source": "Action.java:804"
        },
        {
          "method": "org.eclipse.jface.action.ActionContributionItem.handleWidgetSelection",
          "source": "ActionContributio nItem.java:422"
        },
        {
          "method": "org.eclipse.jface.action.ActionContributionItem.handleWidgetEvent",
          "source": "ActionContributionIte m.java:374"
        },
        {
          "method": "org.eclipse.jface.action.ActionContributionItem.access$0",
          "source": "ActionContributionItem.java:36 8"
        },
        {
          "method": "org.eclipse.jface.action.ActionContributionItem$ActionListener.handleEvent",
          "source": "ActionContri butionItem.java:69"
        },
        {
          "method": "org.eclipse.swt.widgets.EventTable.sendEvent",
          "source": "EventTable.java:77"
        },
        {
          "method": "org.eclipse.swt.widgets.Widget.notifyListeners",
          "source": "Widget.java:634"
        },
        {
          "method": "org.eclipse.swt.widgets.Display.runDeferredEvents",
          "source": "Display.java:1252"
        },
        {
          "method": "org.eclipse.swt.widgets.Display.readAndDispatch",
          "source": "Display.java:1009"
        },
        {
          "method": "org.eclipse.ui.internal.Workbench.runEventLoop",
          "source": "Workbench.java:1525"
        },
        {
          "method": "org.eclipse.ui.internal.Workbench.run",
          "source": "Workbench.java:1508"
        },
        {
          "method": "org.eclipse.core.internal.boot.InternalBootLoader.run",
          "source": "InternalBootLoader.java:845"
        },
        {
          "method": "org.eclipse.core.boot.BootLoader.run",
          "source": "BootLoader.java:462"
        },
        {
          "method": "java.lang.reflect.Method.invoke",
          "source": "Native Method"
        },
        {
          "method": "org.eclipse.core.launcher.Main.basicRun",
          "source": "Main.java:247"
        },
        {
          "method": "org.eclipse.core.launcher.Main.run",
          "source": "Main.java:703"
        },
        {
          "method": "org.eclipse.core.launcher.Main.main",
          "source": "Main.java:539"
        },
        {
          "method": "java.lang.reflect.Method.invoke",
          "source": "Native Method"
        },
        {
          "method": "com.apple.buckyball.app.LaunchRunner.run",
          "source": "LaunchRunner.java:82"
        },
        {
          "method": "com.apple.buckyball.app.LaunchRunner.callMain",
          "source": "LaunchRunner.java:44"
        },
        {
          "method": "com.apple.buckyball.app.CarbonLibApp.launch",
          "source": "CarbonLibApp.java:67"
        }
      ],
      "number": 1,
      "commentIndex": 0,
      "bugId": "30211",
      "date": "2003-01-24T21:32:56+01:00",
      "product": "Platform",
      "component": "Debug",
      "severity": "normal"
    }
  ],
  "groupId": "30211",
  "bugId": "30211",
  "date": "2003-01-24T21:32:56+01:00",
  "product": "Platform",
  "component": "Debug",
  "severity": "normal"
}