{
  "comments": [
    "It would be nice if you could expand the exception node in the failure trace portion of the JUnit view to see the root cause of the exception.  Not being able to see the \"cause chain\" limits the usefulness of this view and requires developers to put extra try/catch blocks in the tests.  Thanks!",
    "Postpone \u003e 2.1",
    "Using these two classes:\n\n@@ Z.java @@\n\npublic class Z {\n\tpublic void test() {\n\t\ttry {\n\t\t\ttest2();\n\t\t} catch (Exception e) {\n\t\t\tthrow new RuntimeException(\"outer\", e);\n\t\t}\n\t}\n\n\tpublic void test2() {\n\t\ttry {\n\t\t\ttest3();\n\t\t} catch (Exception e) {\n\t\t\tthrow new RuntimeException(\"middle\", e);\n\t\t}\n\t}\n\n\tpublic void test3() {\n\t\tthrow new IllegalArgumentException(\"inner\");\n\t}\n}\n\n@@ ZTest.java @@\n\nimport junit.framework.TestCase;\n\npublic class ZTest extends TestCase {\n\n\tpublic void test() {\n\t\tnew Z().test();\n\t}\n}\n\nI will get the following Trace:\n\njava.lang.RuntimeException: outer\n\tat c.F.test(ZTest.java:16)\n\tat c.ZTest.test(ZTest.java:36)\n\tat sun.reflect.NativeMethodAccessorImpl.invoke0(Native Method)\n\tat sun.reflect.NativeMethodAccessorImpl.invoke(NativeMethodAccessorImpl.java:39)\n\tat\nsun.reflect.DelegatingMethodAccessorImpl.invoke(DelegatingMethodAccessorImpl.java:25)\n\tat java.lang.reflect.Method.invoke(Method.java:324)\n\tat junit.framework.TestCase.runTest(TestCase.java:154)\n\tat junit.framework.TestCase.runBare(TestCase.java:127)\n\tat junit.framework.TestResult$1.protect(TestResult.java:106)\n\tat junit.framework.TestResult.runProtected(TestResult.java:124)\n\tat junit.framework.TestResult.run(TestResult.java:109)\n\tat junit.framework.TestCase.run(TestCase.java:118)\n\tat junit.framework.TestSuite.runTest(TestSuite.java:208)\n\tat junit.framework.TestSuite.run(TestSuite.java:203)\n\tat\norg.eclipse.jdt.internal.junit.runner.RemoteTestRunner.runTests(RemoteTestRunner.java:393)\n\tat\norg.eclipse.jdt.internal.junit.runner.RemoteTestRunner.run(RemoteTestRunner.java:277)\n\tat\norg.eclipse.jdt.internal.junit.runner.RemoteTestRunner.main(RemoteTestRunner.java:168)\nCaused by: java.lang.RuntimeException: middle\n\tat c.F.test2(ZTest.java:24)\n\tat c.F.test(ZTest.java:14)\n\t... 16 more\nCaused by: java.lang.IllegalArgumentException: inner\n\tat c.F.test3(ZTest.java:29)\n\tat c.F.test2(ZTest.java:22)\n\t... 17 more\n\n@@@@\n\nClicking on the line right below the last Exception in the Failure Trace will\nshow you the root cause."
  ],
  "commentCreationDates": [
    "2003-01-24T22:30:40+01:00",
    "2003-01-27T09:31:50+01:00",
    "2003-05-07T17:44:28+02:00"
  ],
  "traces": [
    {
      "exceptionType": "java.lang.RuntimeException",
      "message": "outer",
      "elements": [
        {
          "method": "c.F.test",
          "source": "ZTest.java:16"
        },
        {
          "method": "c.ZTest.test",
          "source": "ZTest.java:36"
        },
        {
          "method": "sun.reflect.NativeMethodAccessorImpl.invoke0",
          "source": "Native Method"
        },
        {
          "method": "sun.reflect.NativeMethodAccessorImpl.invoke",
          "source": "NativeMethodAccessorImpl.java:39"
        },
        {
          "method": "sun.reflect.DelegatingMethodAccessorImpl.invoke",
          "source": "DelegatingMethodAccessorImpl.java:25"
        },
        {
          "method": "java.lang.reflect.Method.invoke",
          "source": "Method.java:324"
        },
        {
          "method": "junit.framework.TestCase.runTest",
          "source": "TestCase.java:154"
        },
        {
          "method": "junit.framework.TestCase.runBare",
          "source": "TestCase.java:127"
        },
        {
          "method": "junit.framework.TestResult$1.protect",
          "source": "TestResult.java:106"
        },
        {
          "method": "junit.framework.TestResult.runProtected",
          "source": "TestResult.java:124"
        },
        {
          "method": "junit.framework.TestResult.run",
          "source": "TestResult.java:109"
        },
        {
          "method": "junit.framework.TestCase.run",
          "source": "TestCase.java:118"
        },
        {
          "method": "junit.framework.TestSuite.runTest",
          "source": "TestSuite.java:208"
        },
        {
          "method": "junit.framework.TestSuite.run",
          "source": "TestSuite.java:203"
        },
        {
          "method": "org.eclipse.jdt.internal.junit.runner.RemoteTestRunner.runTests",
          "source": "RemoteTestRunner.java:393"
        },
        {
          "method": "org.eclipse.jdt.internal.junit.runner.RemoteTestRunner.run",
          "source": "RemoteTestRunner.java:277"
        },
        {
          "method": "org.eclipse.jdt.internal.junit.runner.RemoteTestRunner.main",
          "source": "RemoteTestRunner.java:168"
        }
      ],
      "causedBy": {
        "exceptionType": "java.lang.RuntimeException",
        "message": "middle",
        "elements": [
          {
            "method": "c.F.test2",
            "source": "ZTest.java:24"
          },
          {
            "method": "c.F.test",
            "source": "ZTest.java:14"
          }
        ],
        "causedBy": {
          "exceptionType": "java.lang.IllegalArgumentException",
          "message": "inner",
          "elements": [
            {
              "method": "c.F.test3",
              "source": "ZTest.java:29"
            },
            {
              "method": "c.F.test2",
              "source": "ZTest.java:22"
            }
          ],
          "number": 0,
          "commentIndex": 0
        },
        "number": 0,
        "commentIndex": 0
      },
      "number": 0,
      "commentIndex": 2,
      "bugId": "30213",
      "date": "2003-05-07T17:44:28+02:00",
      "product": "JDT",
      "component": "UI",
      "severity": "enhancement"
    }
  ],
  "groupId": "30213",
  "bugId": "30213",
  "date": "2003-01-24T22:30:40+01:00",
  "product": "JDT",
  "component": "UI",
  "severity": "enhancement"
}