{
  "comments": [
    "Build 20030122\n\nWhen exiting a workbench, I had just restarted, I got the following exception:\n\njava.lang.ArrayIndexOutOfBoundsException: 1\n        at org.eclipse.jdt.internal.core.SearchableEnvironment.find\n(SearchableEnvironment.java:95)\n        at org.eclipse.jdt.internal.core.SearchableEnvironment.findType\n(SearchableEnvironment.java:143)\n        at org.eclipse.jdt.internal.compiler.lookup.LookupEnvironment.askForType\n(LookupEnvironment.java:94)\n        at org.eclipse.jdt.internal.compiler.lookup.PackageBinding.getType\n(PackageBinding.java:116)\n        at org.eclipse.jdt.internal.compiler.lookup.Scope.findType\n(Scope.java:721)\n        at org.eclipse.jdt.internal.compiler.lookup.Scope.getTypeOrPackage\n(Scope.java:1118)\n        at org.eclipse.jdt.internal.compiler.lookup.ClassScope.findSupertype\n(ClassScope.java:789)\n        at \norg.eclipse.jdt.internal.compiler.lookup.ClassScope.connectSuperInterfaces\n(ClassScope.java:627)\n        at \norg.eclipse.jdt.internal.compiler.lookup.ClassScope.connectTypeHierarchy\n(ClassScope.java:676)\n        at \norg.eclipse.jdt.internal.compiler.lookup.CompilationUnitScope.connectTypeHierarc\nhy(CompilationUnitScope.java:249)\n        at \norg.eclipse.jdt.internal.compiler.lookup.LookupEnvironment.completeTypeBindings\n(LookupEnvironment.java:221)\n        at org.eclipse.jdt.internal.core.CompilationUnitProblemFinder.accept\n(CompilationUnitProblemFinder.java:105)\n        at org.eclipse.jdt.internal.compiler.lookup.LookupEnvironment.askForType\n(LookupEnvironment.java:106)\n        at org.eclipse.jdt.internal.compiler.lookup.PackageBinding.getType\n(PackageBinding.java:116)\n        at org.eclipse.jdt.internal.compiler.lookup.Scope.findType\n(Scope.java:721)\n        at org.eclipse.jdt.internal.compiler.lookup.Scope.getTypeOrPackage\n(Scope.java:1106)\n        at org.eclipse.jdt.internal.compiler.lookup.ClassScope.findSupertype\n(ClassScope.java:789)\n        at org.eclipse.jdt.internal.compiler.lookup.ClassScope.connectSuperclass\n(ClassScope.java:582)\n        at \norg.eclipse.jdt.internal.compiler.lookup.ClassScope.connectTypeHierarchy\n(ClassScope.java:675)\n        at \norg.eclipse.jdt.internal.compiler.lookup.CompilationUnitScope.connectTypeHierarc\nhy(CompilationUnitScope.java:249)\n        at \norg.eclipse.jdt.internal.compiler.lookup.LookupEnvironment.completeTypeBindings\n(LookupEnvironment.java:221)\n        at org.eclipse.jdt.internal.core.CompilationUnitProblemFinder.accept\n(CompilationUnitProblemFinder.java:105)\n        at org.eclipse.jdt.internal.compiler.lookup.LookupEnvironment.askForType\n(LookupEnvironment.java:106)\n        at org.eclipse.jdt.internal.compiler.lookup.PackageBinding.getType\n(PackageBinding.java:116)\n        at org.eclipse.jdt.internal.compiler.lookup.Scope.findType\n(Scope.java:721)\n        at org.eclipse.jdt.internal.compiler.lookup.Scope.getTypeOrPackage\n(Scope.java:1106)\n        at org.eclipse.jdt.internal.compiler.lookup.ClassScope.findSupertype\n(ClassScope.java:789)\n        at org.eclipse.jdt.internal.compiler.lookup.ClassScope.connectSuperclass\n(ClassScope.java:582)\n        at \norg.eclipse.jdt.internal.compiler.lookup.ClassScope.connectTypeHierarchy\n(ClassScope.java:675)\n        at \norg.eclipse.jdt.internal.compiler.lookup.CompilationUnitScope.connectTypeHierarc\nhy(CompilationUnitScope.java:249)\n        at \norg.eclipse.jdt.internal.compiler.lookup.LookupEnvironment.completeTypeBindings\n(LookupEnvironment.java:221)\n        at org.eclipse.jdt.internal.core.CompilationUnitProblemFinder.accept\n(CompilationUnitProblemFinder.java:105)\n        at org.eclipse.jdt.internal.compiler.lookup.LookupEnvironment.askForType\n(LookupEnvironment.java:106)\n        at org.eclipse.jdt.internal.compiler.lookup.PackageBinding.getType\n(PackageBinding.java:116)\n        at org.eclipse.jdt.internal.compiler.lookup.Scope.findType\n(Scope.java:721)\n        at org.eclipse.jdt.internal.compiler.lookup.Scope.getTypeOrPackage\n(Scope.java:1118)\n        at org.eclipse.jdt.internal.compiler.lookup.Scope.getType\n(Scope.java:965)\n        at \norg.eclipse.jdt.internal.compiler.ast.SingleTypeReference.getTypeBinding\n(SingleTypeReference.java:39)\n        at org.eclipse.jdt.internal.compiler.ast.FieldDeclaration.getTypeBinding\n(FieldDeclaration.java:121)\n        at \norg.eclipse.jdt.internal.compiler.lookup.SourceTypeBinding.resolveTypeFor\n(SourceTypeBinding.java:768)\n        at org.eclipse.jdt.internal.compiler.lookup.SourceTypeBinding.fields\n(SourceTypeBinding.java:357)\n        at \norg.eclipse.jdt.internal.compiler.lookup.SourceTypeBinding.faultInTypesForFields\nAndMethods(SourceTypeBinding.java:344)\n        at \norg.eclipse.jdt.internal.compiler.lookup.CompilationUnitScope.faultInTypes\n(CompilationUnitScope.java:341)\n        at org.eclipse.jdt.internal.compiler.Compiler.resolve(Compiler.java:579)\n        at org.eclipse.jdt.internal.core.CompilationUnitProblemFinder.process\n(CompilationUnitProblemFinder.java:204)\n        at org.eclipse.jdt.internal.core.WorkingCopy.reconcile\n(WorkingCopy.java:453)\n        at \norg.eclipse.jdt.internal.ui.text.java.JavaReconcilingStrategy.reconcile\n(JavaReconcilingStrategy.java:73)\n        at \norg.eclipse.jdt.internal.ui.text.java.JavaReconcilingStrategy.initialReconcile\n(JavaReconcilingStrategy.java:127)\n        at org.eclipse.jface.text.reconciler.MonoReconciler.initialProcess\n(MonoReconciler.java:104)\n        at \norg.eclipse.jface.text.reconciler.AbstractReconciler$BackgroundThread.run\n(AbstractReconciler.java:155)\njava.lang.ArrayIndexOutOfBoundsException: 1\n        at org.eclipse.jdt.internal.core.SearchableEnvironment.find\n(SearchableEnvironment.java:95)\n        at org.eclipse.jdt.internal.core.SearchableEnvironment.findType\n(SearchableEnvironment.java:143)\n        at org.eclipse.jdt.internal.compiler.lookup.LookupEnvironment.askForType\n(LookupEnvironment.java:94)\n        at org.eclipse.jdt.internal.compiler.lookup.PackageBinding.getType\n(PackageBinding.java:116)\n        at org.eclipse.jdt.internal.compiler.lookup.Scope.findType\n(Scope.java:721)\n        at org.eclipse.jdt.internal.compiler.lookup.Scope.getTypeOrPackage\n(Scope.java:1118)\n        at org.eclipse.jdt.internal.compiler.lookup.ClassScope.findSupertype\n(ClassScope.java:789)\n        at \norg.eclipse.jdt.internal.compiler.lookup.ClassScope.connectSuperInterfaces\n(ClassScope.java:627)\n        at \norg.eclipse.jdt.internal.compiler.lookup.ClassScope.connectTypeHierarchy\n(ClassScope.java:676)\n        at \norg.eclipse.jdt.internal.compiler.lookup.CompilationUnitScope.connectTypeHierarc\nhy(CompilationUnitScope.java:249)\n        at \norg.eclipse.jdt.internal.compiler.lookup.LookupEnvironment.completeTypeBindings\n(LookupEnvironment.java:221)\n        at org.eclipse.jdt.internal.core.CompilationUnitProblemFinder.accept\n(CompilationUnitProblemFinder.java:105)\n        at org.eclipse.jdt.internal.compiler.lookup.LookupEnvironment.askForType\n(LookupEnvironment.java:106)\n        at org.eclipse.jdt.internal.compiler.lookup.PackageBinding.getType\n(PackageBinding.java:116)\n        at org.eclipse.jdt.internal.compiler.lookup.Scope.findType\n(Scope.java:721)\n        at org.eclipse.jdt.internal.compiler.lookup.Scope.getTypeOrPackage\n(Scope.java:1106)\n        at org.eclipse.jdt.internal.compiler.lookup.ClassScope.findSupertype\n(ClassScope.java:789)\n        at org.eclipse.jdt.internal.compiler.lookup.ClassScope.connectSuperclass\n(ClassScope.java:582)\n        at \norg.eclipse.jdt.internal.compiler.lookup.ClassScope.connectTypeHierarchy\n(ClassScope.java:675)\n        at \norg.eclipse.jdt.internal.compiler.lookup.CompilationUnitScope.connectTypeHierarc\nhy(CompilationUnitScope.java:249)\n        at \norg.eclipse.jdt.internal.compiler.lookup.LookupEnvironment.completeTypeBindings\n(LookupEnvironment.java:221)\n        at org.eclipse.jdt.internal.core.CompilationUnitProblemFinder.accept\n(CompilationUnitProblemFinder.java:105)\n        at org.eclipse.jdt.internal.compiler.lookup.LookupEnvironment.askForType\n(LookupEnvironment.java:106)\n        at org.eclipse.jdt.internal.compiler.lookup.PackageBinding.getType\n(PackageBinding.java:116)\n        at org.eclipse.jdt.internal.compiler.lookup.Scope.findType\n(Scope.java:721)\n        at org.eclipse.jdt.internal.compiler.lookup.Scope.getTypeOrPackage\n(Scope.java:1106)\n        at org.eclipse.jdt.internal.compiler.lookup.ClassScope.findSupertype\n(ClassScope.java:789)\n        at org.eclipse.jdt.internal.compiler.lookup.ClassScope.connectSuperclass\n(ClassScope.java:582)\n        at \norg.eclipse.jdt.internal.compiler.lookup.ClassScope.connectTypeHierarchy\n(ClassScope.java:675)\n        at \norg.eclipse.jdt.internal.compiler.lookup.CompilationUnitScope.connectTypeHierarc\nhy(CompilationUnitScope.java:249)\n        at \norg.eclipse.jdt.internal.compiler.lookup.LookupEnvironment.completeTypeBindings\n(LookupEnvironment.java:221)\n        at org.eclipse.jdt.internal.core.CompilationUnitProblemFinder.accept\n(CompilationUnitProblemFinder.java:105)\n        at org.eclipse.jdt.internal.compiler.lookup.LookupEnvironment.askForType\n(LookupEnvironment.java:106)\n        at org.eclipse.jdt.internal.compiler.lookup.PackageBinding.getType\n(PackageBinding.java:116)\n        at org.eclipse.jdt.internal.compiler.lookup.Scope.findType\n(Scope.java:721)\n        at org.eclipse.jdt.internal.compiler.lookup.Scope.getTypeOrPackage\n(Scope.java:1118)\n        at org.eclipse.jdt.internal.compiler.lookup.Scope.getType\n(Scope.java:965)\n        at \norg.eclipse.jdt.internal.compiler.ast.SingleTypeReference.getTypeBinding\n(SingleTypeReference.java:39)\n        at org.eclipse.jdt.internal.compiler.ast.FieldDeclaration.getTypeBinding\n(FieldDeclaration.java:121)\n        at \norg.eclipse.jdt.internal.compiler.lookup.SourceTypeBinding.resolveTypeFor\n(SourceTypeBinding.java:768)\n        at org.eclipse.jdt.internal.compiler.lookup.SourceTypeBinding.fields\n(SourceTypeBinding.java:357)\n        at \norg.eclipse.jdt.internal.compiler.lookup.SourceTypeBinding.faultInTypesForFields\nAndMethods(SourceTypeBinding.java:344)\n        at \norg.eclipse.jdt.internal.compiler.lookup.CompilationUnitScope.faultInTypes\n(CompilationUnitScope.java:341)\n        at org.eclipse.jdt.internal.compiler.Compiler.resolve(Compiler.java:579)\n        at org.eclipse.jdt.internal.core.CompilationUnitProblemFinder.process\n(CompilationUnitProblemFinder.java:204)\n        at org.eclipse.jdt.internal.core.WorkingCopy.reconcile\n(WorkingCopy.java:453)\n        at \norg.eclipse.jdt.internal.ui.text.java.JavaReconcilingStrategy.reconcile\n(JavaReconcilingStrategy.java:73)\n        at \norg.eclipse.jdt.internal.ui.text.java.JavaReconcilingStrategy.initialReconcile\n(JavaReconcilingStrategy.java:127)\n        at org.eclipse.jface.text.reconciler.MonoReconciler.initialProcess\n(MonoReconciler.java:104)\n        at \norg.eclipse.jface.text.reconciler.AbstractReconciler$BackgroundThread.run\n(AbstractReconciler.java:155)",
    "Cannot reproduce."
  ],
  "commentCreationDates": [
    "2003-01-29T12:07:24+01:00",
    "2003-02-13T11:46:03+01:00"
  ],
  "traces": [
    {
      "exceptionType": "java.lang.ArrayIndexOutOfBoundsException",
      "message": "1",
      "elements": [
        {
          "method": "org.eclipse.jdt.internal.core.SearchableEnvironment.find",
          "source": "SearchableEnvironment.java:95"
        },
        {
          "method": "org.eclipse.jdt.internal.core.SearchableEnvironment.findType",
          "source": "SearchableEnvironment.java:143"
        },
        {
          "method": "org.eclipse.jdt.internal.compiler.lookup.LookupEnvironment.askForType",
          "source": "LookupEnvironment.java:94"
        },
        {
          "method": "org.eclipse.jdt.internal.compiler.lookup.PackageBinding.getType",
          "source": "PackageBinding.java:116"
        },
        {
          "method": "org.eclipse.jdt.internal.compiler.lookup.Scope.findType",
          "source": "Scope.java:721"
        },
        {
          "method": "org.eclipse.jdt.internal.compiler.lookup.Scope.getTypeOrPackage",
          "source": "Scope.java:1118"
        },
        {
          "method": "org.eclipse.jdt.internal.compiler.lookup.ClassScope.findSupertype",
          "source": "ClassScope.java:789"
        },
        {
          "method": "org.eclipse.jdt.internal.compiler.lookup.ClassScope.connectSuperInterfaces",
          "source": "ClassScope.java:627"
        },
        {
          "method": "org.eclipse.jdt.internal.compiler.lookup.ClassScope.connectTypeHierarchy",
          "source": "ClassScope.java:676"
        },
        {
          "method": "org.eclipse.jdt.internal.compiler.lookup.CompilationUnitScope.connectTypeHierarchy",
          "source": "CompilationUnitScope.java:249"
        },
        {
          "method": "org.eclipse.jdt.internal.compiler.lookup.LookupEnvironment.completeTypeBindings",
          "source": "LookupEnvironment.java:221"
        },
        {
          "method": "org.eclipse.jdt.internal.core.CompilationUnitProblemFinder.accept",
          "source": "CompilationUnitProblemFinder.java:105"
        },
        {
          "method": "org.eclipse.jdt.internal.compiler.lookup.LookupEnvironment.askForType",
          "source": "LookupEnvironment.java:106"
        },
        {
          "method": "org.eclipse.jdt.internal.compiler.lookup.PackageBinding.getType",
          "source": "PackageBinding.java:116"
        },
        {
          "method": "org.eclipse.jdt.internal.compiler.lookup.Scope.findType",
          "source": "Scope.java:721"
        },
        {
          "method": "org.eclipse.jdt.internal.compiler.lookup.Scope.getTypeOrPackage",
          "source": "Scope.java:1106"
        },
        {
          "method": "org.eclipse.jdt.internal.compiler.lookup.ClassScope.findSupertype",
          "source": "ClassScope.java:789"
        },
        {
          "method": "org.eclipse.jdt.internal.compiler.lookup.ClassScope.connectSuperclass",
          "source": "ClassScope.java:582"
        },
        {
          "method": "org.eclipse.jdt.internal.compiler.lookup.ClassScope.connectTypeHierarchy",
          "source": "ClassScope.java:675"
        },
        {
          "method": "org.eclipse.jdt.internal.compiler.lookup.CompilationUnitScope.connectTypeHierarchy",
          "source": "CompilationUnitScope.java:249"
        },
        {
          "method": "org.eclipse.jdt.internal.compiler.lookup.LookupEnvironment.completeTypeBindings",
          "source": "LookupEnvironment.java:221"
        },
        {
          "method": "org.eclipse.jdt.internal.core.CompilationUnitProblemFinder.accept",
          "source": "CompilationUnitProblemFinder.java:105"
        },
        {
          "method": "org.eclipse.jdt.internal.compiler.lookup.LookupEnvironment.askForType",
          "source": "LookupEnvironment.java:106"
        },
        {
          "method": "org.eclipse.jdt.internal.compiler.lookup.PackageBinding.getType",
          "source": "PackageBinding.java:116"
        },
        {
          "method": "org.eclipse.jdt.internal.compiler.lookup.Scope.findType",
          "source": "Scope.java:721"
        },
        {
          "method": "org.eclipse.jdt.internal.compiler.lookup.Scope.getTypeOrPackage",
          "source": "Scope.java:1106"
        },
        {
          "method": "org.eclipse.jdt.internal.compiler.lookup.ClassScope.findSupertype",
          "source": "ClassScope.java:789"
        },
        {
          "method": "org.eclipse.jdt.internal.compiler.lookup.ClassScope.connectSuperclass",
          "source": "ClassScope.java:582"
        },
        {
          "method": "org.eclipse.jdt.internal.compiler.lookup.ClassScope.connectTypeHierarchy",
          "source": "ClassScope.java:675"
        },
        {
          "method": "org.eclipse.jdt.internal.compiler.lookup.CompilationUnitScope.connectTypeHierarchy",
          "source": "CompilationUnitScope.java:249"
        },
        {
          "method": "org.eclipse.jdt.internal.compiler.lookup.LookupEnvironment.completeTypeBindings",
          "source": "LookupEnvironment.java:221"
        },
        {
          "method": "org.eclipse.jdt.internal.core.CompilationUnitProblemFinder.accept",
          "source": "CompilationUnitProblemFinder.java:105"
        },
        {
          "method": "org.eclipse.jdt.internal.compiler.lookup.LookupEnvironment.askForType",
          "source": "LookupEnvironment.java:106"
        },
        {
          "method": "org.eclipse.jdt.internal.compiler.lookup.PackageBinding.getType",
          "source": "PackageBinding.java:116"
        },
        {
          "method": "org.eclipse.jdt.internal.compiler.lookup.Scope.findType",
          "source": "Scope.java:721"
        },
        {
          "method": "org.eclipse.jdt.internal.compiler.lookup.Scope.getTypeOrPackage",
          "source": "Scope.java:1118"
        },
        {
          "method": "org.eclipse.jdt.internal.compiler.lookup.Scope.getType",
          "source": "Scope.java:965"
        },
        {
          "method": "org.eclipse.jdt.internal.compiler.ast.SingleTypeReference.getTypeBinding",
          "source": "SingleTypeReference.java:39"
        },
        {
          "method": "org.eclipse.jdt.internal.compiler.ast.FieldDeclaration.getTypeBinding",
          "source": "FieldDeclaration.java:121"
        },
        {
          "method": "org.eclipse.jdt.internal.compiler.lookup.SourceTypeBinding.resolveTypeFor",
          "source": "SourceTypeBinding.java:768"
        },
        {
          "method": "org.eclipse.jdt.internal.compiler.lookup.SourceTypeBinding.fields",
          "source": "SourceTypeBinding.java:357"
        },
        {
          "method": "org.eclipse.jdt.internal.compiler.lookup.SourceTypeBinding.faultInTypesForFieldsAndMethods",
          "source": "SourceTypeBinding.java:344"
        },
        {
          "method": "org.eclipse.jdt.internal.compiler.lookup.CompilationUnitScope.faultInTypes",
          "source": "CompilationUnitScope.java:341"
        },
        {
          "method": "org.eclipse.jdt.internal.compiler.Compiler.resolve",
          "source": "Compiler.java:579"
        },
        {
          "method": "org.eclipse.jdt.internal.core.CompilationUnitProblemFinder.process",
          "source": "CompilationUnitProblemFinder.java:204"
        },
        {
          "method": "org.eclipse.jdt.internal.core.WorkingCopy.reconcile",
          "source": "WorkingCopy.java:453"
        },
        {
          "method": "org.eclipse.jdt.internal.ui.text.java.JavaReconcilingStrategy.reconcile",
          "source": "JavaReconcilingStrategy.java:73"
        },
        {
          "method": "org.eclipse.jdt.internal.ui.text.java.JavaReconcilingStrategy.initialReconcile",
          "source": "JavaReconcilingStrategy.java:127"
        },
        {
          "method": "org.eclipse.jface.text.reconciler.MonoReconciler.initialProcess",
          "source": "MonoReconciler.java:104"
        },
        {
          "method": "org.eclipse.jface.text.reconciler.AbstractReconciler$BackgroundThread.run",
          "source": "AbstractReconciler.java:155"
        }
      ],
      "number": 0,
      "commentIndex": 0,
      "bugId": "30485",
      "date": "2003-01-29T12:07:24+01:00",
      "product": "JDT",
      "component": "Core",
      "severity": "normal"
    },
    {
      "exceptionType": "java.lang.ArrayIndexOutOfBoundsException",
      "message": "1",
      "elements": [
        {
          "method": "org.eclipse.jdt.internal.core.SearchableEnvironment.find",
          "source": "SearchableEnvironment.java:95"
        },
        {
          "method": "org.eclipse.jdt.internal.core.SearchableEnvironment.findType",
          "source": "SearchableEnvironment.java:143"
        },
        {
          "method": "org.eclipse.jdt.internal.compiler.lookup.LookupEnvironment.askForType",
          "source": "LookupEnvironment.java:94"
        },
        {
          "method": "org.eclipse.jdt.internal.compiler.lookup.PackageBinding.getType",
          "source": "PackageBinding.java:116"
        },
        {
          "method": "org.eclipse.jdt.internal.compiler.lookup.Scope.findType",
          "source": "Scope.java:721"
        },
        {
          "method": "org.eclipse.jdt.internal.compiler.lookup.Scope.getTypeOrPackage",
          "source": "Scope.java:1118"
        },
        {
          "method": "org.eclipse.jdt.internal.compiler.lookup.ClassScope.findSupertype",
          "source": "ClassScope.java:789"
        },
        {
          "method": "org.eclipse.jdt.internal.compiler.lookup.ClassScope.connectSuperInterfaces",
          "source": "ClassScope.java:627"
        },
        {
          "method": "org.eclipse.jdt.internal.compiler.lookup.ClassScope.connectTypeHierarchy",
          "source": "ClassScope.java:676"
        },
        {
          "method": "org.eclipse.jdt.internal.compiler.lookup.CompilationUnitScope.connectTypeHierarchy",
          "source": "CompilationUnitScope.java:249"
        },
        {
          "method": "org.eclipse.jdt.internal.compiler.lookup.LookupEnvironment.completeTypeBindings",
          "source": "LookupEnvironment.java:221"
        },
        {
          "method": "org.eclipse.jdt.internal.core.CompilationUnitProblemFinder.accept",
          "source": "CompilationUnitProblemFinder.java:105"
        },
        {
          "method": "org.eclipse.jdt.internal.compiler.lookup.LookupEnvironment.askForType",
          "source": "LookupEnvironment.java:106"
        },
        {
          "method": "org.eclipse.jdt.internal.compiler.lookup.PackageBinding.getType",
          "source": "PackageBinding.java:116"
        },
        {
          "method": "org.eclipse.jdt.internal.compiler.lookup.Scope.findType",
          "source": "Scope.java:721"
        },
        {
          "method": "org.eclipse.jdt.internal.compiler.lookup.Scope.getTypeOrPackage",
          "source": "Scope.java:1106"
        },
        {
          "method": "org.eclipse.jdt.internal.compiler.lookup.ClassScope.findSupertype",
          "source": "ClassScope.java:789"
        },
        {
          "method": "org.eclipse.jdt.internal.compiler.lookup.ClassScope.connectSuperclass",
          "source": "ClassScope.java:582"
        },
        {
          "method": "org.eclipse.jdt.internal.compiler.lookup.ClassScope.connectTypeHierarchy",
          "source": "ClassScope.java:675"
        },
        {
          "method": "org.eclipse.jdt.internal.compiler.lookup.CompilationUnitScope.connectTypeHierarchy",
          "source": "CompilationUnitScope.java:249"
        },
        {
          "method": "org.eclipse.jdt.internal.compiler.lookup.LookupEnvironment.completeTypeBindings",
          "source": "LookupEnvironment.java:221"
        },
        {
          "method": "org.eclipse.jdt.internal.core.CompilationUnitProblemFinder.accept",
          "source": "CompilationUnitProblemFinder.java:105"
        },
        {
          "method": "org.eclipse.jdt.internal.compiler.lookup.LookupEnvironment.askForType",
          "source": "LookupEnvironment.java:106"
        },
        {
          "method": "org.eclipse.jdt.internal.compiler.lookup.PackageBinding.getType",
          "source": "PackageBinding.java:116"
        },
        {
          "method": "org.eclipse.jdt.internal.compiler.lookup.Scope.findType",
          "source": "Scope.java:721"
        },
        {
          "method": "org.eclipse.jdt.internal.compiler.lookup.Scope.getTypeOrPackage",
          "source": "Scope.java:1106"
        },
        {
          "method": "org.eclipse.jdt.internal.compiler.lookup.ClassScope.findSupertype",
          "source": "ClassScope.java:789"
        },
        {
          "method": "org.eclipse.jdt.internal.compiler.lookup.ClassScope.connectSuperclass",
          "source": "ClassScope.java:582"
        },
        {
          "method": "org.eclipse.jdt.internal.compiler.lookup.ClassScope.connectTypeHierarchy",
          "source": "ClassScope.java:675"
        },
        {
          "method": "org.eclipse.jdt.internal.compiler.lookup.CompilationUnitScope.connectTypeHierarchy",
          "source": "CompilationUnitScope.java:249"
        },
        {
          "method": "org.eclipse.jdt.internal.compiler.lookup.LookupEnvironment.completeTypeBindings",
          "source": "LookupEnvironment.java:221"
        },
        {
          "method": "org.eclipse.jdt.internal.core.CompilationUnitProblemFinder.accept",
          "source": "CompilationUnitProblemFinder.java:105"
        },
        {
          "method": "org.eclipse.jdt.internal.compiler.lookup.LookupEnvironment.askForType",
          "source": "LookupEnvironment.java:106"
        },
        {
          "method": "org.eclipse.jdt.internal.compiler.lookup.PackageBinding.getType",
          "source": "PackageBinding.java:116"
        },
        {
          "method": "org.eclipse.jdt.internal.compiler.lookup.Scope.findType",
          "source": "Scope.java:721"
        },
        {
          "method": "org.eclipse.jdt.internal.compiler.lookup.Scope.getTypeOrPackage",
          "source": "Scope.java:1118"
        },
        {
          "method": "org.eclipse.jdt.internal.compiler.lookup.Scope.getType",
          "source": "Scope.java:965"
        },
        {
          "method": "org.eclipse.jdt.internal.compiler.ast.SingleTypeReference.getTypeBinding",
          "source": "SingleTypeReference.java:39"
        },
        {
          "method": "org.eclipse.jdt.internal.compiler.ast.FieldDeclaration.getTypeBinding",
          "source": "FieldDeclaration.java:121"
        },
        {
          "method": "org.eclipse.jdt.internal.compiler.lookup.SourceTypeBinding.resolveTypeFor",
          "source": "SourceTypeBinding.java:768"
        },
        {
          "method": "org.eclipse.jdt.internal.compiler.lookup.SourceTypeBinding.fields",
          "source": "SourceTypeBinding.java:357"
        },
        {
          "method": "org.eclipse.jdt.internal.compiler.lookup.SourceTypeBinding.faultInTypesForFieldsAndMethods",
          "source": "SourceTypeBinding.java:344"
        },
        {
          "method": "org.eclipse.jdt.internal.compiler.lookup.CompilationUnitScope.faultInTypes",
          "source": "CompilationUnitScope.java:341"
        },
        {
          "method": "org.eclipse.jdt.internal.compiler.Compiler.resolve",
          "source": "Compiler.java:579"
        },
        {
          "method": "org.eclipse.jdt.internal.core.CompilationUnitProblemFinder.process",
          "source": "CompilationUnitProblemFinder.java:204"
        },
        {
          "method": "org.eclipse.jdt.internal.core.WorkingCopy.reconcile",
          "source": "WorkingCopy.java:453"
        },
        {
          "method": "org.eclipse.jdt.internal.ui.text.java.JavaReconcilingStrategy.reconcile",
          "source": "JavaReconcilingStrategy.java:73"
        },
        {
          "method": "org.eclipse.jdt.internal.ui.text.java.JavaReconcilingStrategy.initialReconcile",
          "source": "JavaReconcilingStrategy.java:127"
        },
        {
          "method": "org.eclipse.jface.text.reconciler.MonoReconciler.initialProcess",
          "source": "MonoReconciler.java:104"
        },
        {
          "method": "org.eclipse.jface.text.reconciler.AbstractReconciler$BackgroundThread.run",
          "source": "AbstractReconciler.java:155"
        }
      ],
      "number": 1,
      "commentIndex": 0,
      "bugId": "30485",
      "date": "2003-01-29T12:07:24+01:00",
      "product": "JDT",
      "component": "Core",
      "severity": "normal"
    }
  ],
  "groupId": "30485",
  "bugId": "30485",
  "date": "2003-01-29T12:07:24+01:00",
  "product": "JDT",
  "component": "Core",
  "severity": "normal"
}