{
  "comments": [
    "Build 20030122\n\nDuring quick shutdown (right after restarting workspace), the following error \noccurred on exit:\n\njava.lang.NullPointerException\n        at org.eclipse.jdt.internal.core.JavaProject.canonicalizedPath\n(JavaProject.java:117)\n        at org.eclipse.jdt.core.JavaCore.newLibraryEntry(JavaCore.java:2316)\n        at org.eclipse.jdt.core.JavaCore.newLibraryEntry(JavaCore.java:2272)\n        at org.eclipse.jdt.internal.launching.JREContainer.getClasspathEntries\n(JREContainer.java:61)\n        at \norg.eclipse.jdt.internal.core.PackageFragmentRoot.getRawClasspathEntry\n(PackageFragmentRoot.java:506)\n        at \norg.eclipse.jdt.internal.core.PackageFragmentRoot.fullExclusionPatternChars\n(PackageFragmentRoot.java:404)\n        at org.eclipse.jdt.internal.core.PackageFragmentRoot.computeChildren\n(PackageFragmentRoot.java:197)\n        at org.eclipse.jdt.internal.core.PackageFragmentRoot.generateInfos\n(PackageFragmentRoot.java:421)\n        at org.eclipse.jdt.internal.core.Openable.buildStructure\n(Openable.java:71)\n        at org.eclipse.jdt.internal.core.Openable.openWhenClosed\n(Openable.java:394)\n        at org.eclipse.jdt.internal.core.PackageFragmentRoot.openWhenClosed\n(PackageFragmentRoot.java:724)\n        at org.eclipse.jdt.internal.core.JavaElement.openHierarchy\n(JavaElement.java:509)\n        at org.eclipse.jdt.internal.core.JavaElement.getElementInfo\n(JavaElement.java:296)\n        at org.eclipse.jdt.internal.core.JavaElement.getChildren\n(JavaElement.java:252)\n        at org.eclipse.jdt.internal.core.NameLookup.seekPackageFragments\n(NameLookup.java:509)\n        at org.eclipse.jdt.internal.core.NameLookup.findType\n(NameLookup.java:361)\n        at org.eclipse.jdt.internal.core.SearchableEnvironment.find\n(SearchableEnvironment.java:64)\n        at org.eclipse.jdt.internal.core.SearchableEnvironment.findType\n(SearchableEnvironment.java:143)\n        at org.eclipse.jdt.internal.compiler.lookup.LookupEnvironment.askForType\n(LookupEnvironment.java:94)\n        at org.eclipse.jdt.internal.compiler.lookup.PackageBinding.getType\n(PackageBinding.java:116)\n        at org.eclipse.jdt.internal.compiler.lookup.Scope.findType\n(Scope.java:721)\n        at org.eclipse.jdt.internal.compiler.lookup.Scope.getTypeOrPackage\n(Scope.java:1118)\n        at org.eclipse.jdt.internal.compiler.lookup.ClassScope.findSupertype\n(ClassScope.java:789)\n        at \norg.eclipse.jdt.internal.compiler.lookup.ClassScope.connectSuperInterfaces\n(ClassScope.java:627)\n        at \norg.eclipse.jdt.internal.compiler.lookup.ClassScope.connectTypeHierarchy\n(ClassScope.java:676)",
    "Truncated stack trace, but could be a reconciling thread still busy resolving.\nAdded protection to JavaProject.canonicalizedPath\n",
    "Fixed",
    "Verified."
  ],
  "commentCreationDates": [
    "2003-01-29T12:16:06+01:00",
    "2003-01-29T12:17:22+01:00",
    "2003-01-29T12:20:09+01:00",
    "2003-02-10T17:51:22+01:00"
  ],
  "traces": [
    {
      "exceptionType": "java.lang.NullPointerException",
      "elements": [
        {
          "method": "org.eclipse.jdt.internal.core.JavaProject.canonicalizedPath",
          "source": "JavaProject.java:117"
        },
        {
          "method": "org.eclipse.jdt.core.JavaCore.newLibraryEntry",
          "source": "JavaCore.java:2316"
        },
        {
          "method": "org.eclipse.jdt.core.JavaCore.newLibraryEntry",
          "source": "JavaCore.java:2272"
        },
        {
          "method": "org.eclipse.jdt.internal.launching.JREContainer.getClasspathEntries",
          "source": "JREContainer.java:61"
        },
        {
          "method": "org.eclipse.jdt.internal.core.PackageFragmentRoot.getRawClasspathEntry",
          "source": "PackageFragmentRoot.java:506"
        },
        {
          "method": "org.eclipse.jdt.internal.core.PackageFragmentRoot.fullExclusionPatternChars",
          "source": "PackageFragmentRoot.java:404"
        },
        {
          "method": "org.eclipse.jdt.internal.core.PackageFragmentRoot.computeChildren",
          "source": "PackageFragmentRoot.java:197"
        },
        {
          "method": "org.eclipse.jdt.internal.core.PackageFragmentRoot.generateInfos",
          "source": "PackageFragmentRoot.java:421"
        },
        {
          "method": "org.eclipse.jdt.internal.core.Openable.buildStructure",
          "source": "Openable.java:71"
        },
        {
          "method": "org.eclipse.jdt.internal.core.Openable.openWhenClosed",
          "source": "Openable.java:394"
        },
        {
          "method": "org.eclipse.jdt.internal.core.PackageFragmentRoot.openWhenClosed",
          "source": "PackageFragmentRoot.java:724"
        },
        {
          "method": "org.eclipse.jdt.internal.core.JavaElement.openHierarchy",
          "source": "JavaElement.java:509"
        },
        {
          "method": "org.eclipse.jdt.internal.core.JavaElement.getElementInfo",
          "source": "JavaElement.java:296"
        },
        {
          "method": "org.eclipse.jdt.internal.core.JavaElement.getChildren",
          "source": "JavaElement.java:252"
        },
        {
          "method": "org.eclipse.jdt.internal.core.NameLookup.seekPackageFragments",
          "source": "NameLookup.java:509"
        },
        {
          "method": "org.eclipse.jdt.internal.core.NameLookup.findType",
          "source": "NameLookup.java:361"
        },
        {
          "method": "org.eclipse.jdt.internal.core.SearchableEnvironment.find",
          "source": "SearchableEnvironment.java:64"
        },
        {
          "method": "org.eclipse.jdt.internal.core.SearchableEnvironment.findType",
          "source": "SearchableEnvironment.java:143"
        },
        {
          "method": "org.eclipse.jdt.internal.compiler.lookup.LookupEnvironment.askForType",
          "source": "LookupEnvironment.java:94"
        },
        {
          "method": "org.eclipse.jdt.internal.compiler.lookup.PackageBinding.getType",
          "source": "PackageBinding.java:116"
        },
        {
          "method": "org.eclipse.jdt.internal.compiler.lookup.Scope.findType",
          "source": "Scope.java:721"
        },
        {
          "method": "org.eclipse.jdt.internal.compiler.lookup.Scope.getTypeOrPackage",
          "source": "Scope.java:1118"
        },
        {
          "method": "org.eclipse.jdt.internal.compiler.lookup.ClassScope.findSupertype",
          "source": "ClassScope.java:789"
        },
        {
          "method": "org.eclipse.jdt.internal.compiler.lookup.ClassScope.connectSuperInterfaces",
          "source": "ClassScope.java:627"
        },
        {
          "method": "org.eclipse.jdt.internal.compiler.lookup.ClassScope.connectTypeHierarchy",
          "source": "ClassScope.java:676"
        }
      ],
      "number": 0,
      "commentIndex": 0,
      "bugId": "30487",
      "date": "2003-01-29T12:16:06+01:00",
      "product": "JDT",
      "component": "Core",
      "severity": "normal"
    }
  ],
  "groupId": "30487",
  "bugId": "30487",
  "date": "2003-01-29T12:16:06+01:00",
  "product": "JDT",
  "component": "Core",
  "severity": "normal"
}