{
  "comments": [
    "Build 20030122\n\nI observed this exception during shutdown. The only particular thing with this \nsession is that I started and exited almost instantaneously.\n\n!ENTRY org.eclipse.ui.workbench 4 2 Jan 29, 2003 13:35:27.800\n!MESSAGE Problems occurred when invoking code from plug-\nin: \"org.eclipse.ui.workbench\".\n!STACK 0\njava.lang.ClassCastException\n        at org.eclipse.team.core.RepositoryProvider.newProvider\n(RepositoryProvider.java:503)\n        at org.eclipse.team.core.RepositoryProvider.mapNewProvider\n(RepositoryProvider.java:135)\n        at org.eclipse.team.core.RepositoryProvider.getProvider\n(RepositoryProvider.java:411)\n        at \norg.eclipse.team.internal.ccvs.ui.CVSLightweightDecorator.getCVSProviderFor\n(CVSLightweightDecorator.java:130)\n        at org.eclipse.team.internal.ccvs.ui.CVSLightweightDecorator.decorate\n(CVSLightweightDecorator.java:165)\n        at \norg.eclipse.ui.internal.decorators.LightweightDecoratorDefinition.decorate\n(LightweightDecoratorDefinition.java:153)\n        at \norg.eclipse.ui.internal.decorators.LightweightDecoratorManager$LightweightRunnab\nle.run(LightweightDecoratorManager.java:60)\n        at org.eclipse.core.internal.runtime.InternalPlatform.run\n(InternalPlatform.java:852)\n        at org.eclipse.core.runtime.Platform.run(Platform.java:413)\n        at \norg.eclipse.ui.internal.decorators.LightweightDecoratorManager.decorate\n(LightweightDecoratorManager.java:220)\n        at \norg.eclipse.ui.internal.decorators.LightweightDecoratorManager.getDecorations\n(LightweightDecoratorManager.java:191)\n        at org.eclipse.ui.internal.decorators.DecorationScheduler$3.run\n(DecorationScheduler.java:286)\n        at java.lang.Thread.run(Thread.java:536)",
    "I don\u0027t know how this would have happened but we should be catching this \nexception anyway to ensure that classes registered with the repository provider \nextension point are the proper class.",
    "Fix releaed to HEAD",
    "Alternatively, an instanceof check is not to bad."
  ],
  "commentCreationDates": [
    "2003-01-29T12:09:52+01:00",
    "2003-01-29T14:24:59+01:00",
    "2003-01-29T14:25:15+01:00",
    "2003-01-29T16:25:26+01:00"
  ],
  "traces": [
    {
      "exceptionType": "java.lang.ClassCastException",
      "elements": [
        {
          "method": "org.eclipse.team.core.RepositoryProvider.newProvider",
          "source": "RepositoryProvider.java:503"
        },
        {
          "method": "org.eclipse.team.core.RepositoryProvider.mapNewProvider",
          "source": "RepositoryProvider.java:135"
        },
        {
          "method": "org.eclipse.team.core.RepositoryProvider.getProvider",
          "source": "RepositoryProvider.java:411"
        },
        {
          "method": "org.eclipse.team.internal.ccvs.ui.CVSLightweightDecorator.getCVSProviderFor",
          "source": "CVSLightweightDecorator.java:130"
        },
        {
          "method": "org.eclipse.team.internal.ccvs.ui.CVSLightweightDecorator.decorate",
          "source": "CVSLightweightDecorator.java:165"
        },
        {
          "method": "org.eclipse.ui.internal.decorators.LightweightDecoratorDefinition.decorate",
          "source": "LightweightDecoratorDefinition.java:153"
        },
        {
          "method": "org.eclipse.ui.internal.decorators.LightweightDecoratorManager$LightweightRunnable.run",
          "source": "LightweightDecoratorManager.java:60"
        },
        {
          "method": "org.eclipse.core.internal.runtime.InternalPlatform.run",
          "source": "InternalPlatform.java:852"
        },
        {
          "method": "org.eclipse.core.runtime.Platform.run",
          "source": "Platform.java:413"
        },
        {
          "method": "org.eclipse.ui.internal.decorators.LightweightDecoratorManager.decorate",
          "source": "LightweightDecoratorManager.java:220"
        },
        {
          "method": "org.eclipse.ui.internal.decorators.LightweightDecoratorManager.getDecorations",
          "source": "LightweightDecoratorManager.java:191"
        },
        {
          "method": "org.eclipse.ui.internal.decorators.DecorationScheduler$3.run",
          "source": "DecorationScheduler.java:286"
        },
        {
          "method": "java.lang.Thread.run",
          "source": "Thread.java:536"
        }
      ],
      "number": 0,
      "commentIndex": 0,
      "bugId": "30486",
      "date": "2003-01-29T12:09:52+01:00",
      "product": "Platform",
      "component": "Team",
      "severity": "normal"
    }
  ],
  "groupId": "30486",
  "bugId": "30486",
  "date": "2003-01-29T12:09:52+01:00",
  "product": "Platform",
  "component": "Team",
  "severity": "normal"
}