{
  "comments": [
    "build i2003-01-28 (1500), win2k, running sidecar VM (launching debug session of \na runtime workbench with J9 VM)\n\nI set a breakpoint and tried to launch a debug session of a runtime workbench \n(using J9). My breakpoint was hit but when I click on the file to open it, I \nget the stack trace below. Note that I can still use F6, etc to continue \nexecution but I don\u0027t know where I am in the file. (high-lighting doesn\u0027t work \nif I open the right editor manually).\n\n!ENTRY org.eclipse.ui 4 4 Jan 29, 2003 16:42:15.211\n!MESSAGE Unhandled exception caught in event loop.\nUnhandled exception caught in event loop.\nReason:\n!ENTRY org.eclipse.ui 4 0 Jan 29, 2003 16:42:15.321\n!MESSAGE java.lang.NullPointerException\n!STACK 0\njava.lang.NullPointerException\n        at java.lang.Throwable.\u003cinit\u003e(Throwable.java)\n        at java.lang.Throwable.\u003cinit\u003e(Throwable.java)\n        at java.lang.NullPointerException.\u003cinit\u003e(NullPointerException.java:63)\n        at org.eclipse.jdt.internal.debug.ui.actions.OpenTypeAction.getSourceEle\nment(OpenTypeAction.java:151)\n        at org.eclipse.jdt.internal.debug.ui.actions.OpenDeclaringTypeAction.doA\nction(OpenDeclaringTypeAction.java:21)\n        at org.eclipse.jdt.internal.debug.ui.actions.OpenTypeAction.run(OpenType\nAction.java:53)\n        at org.eclipse.ui.internal.PluginAction.runWithEvent(PluginAction.java:2\n50)\n        at org.eclipse.jface.action.ActionContributionItem.handleWidgetSelection\n(ActionContributionItem.java:450)\n        at org.eclipse.jface.action.ActionContributionItem.handleWidgetEvent(Act\nionContributionItem.java)\n        at org.eclipse.jface.action.ActionContributionItem.access$0(ActionContri\nbutionItem.java)\n        at org.eclipse.jface.action.ActionContributionItem$ActionListener.handle\nEvent(ActionContributionItem.java)\n        at org.eclipse.swt.widgets.EventTable.sendEvent(EventTable.java)\n        at org.eclipse.swt.widgets.Widget.sendEvent(Widget.java)\n        at org.eclipse.swt.widgets.Display.runDeferredEvents(Display.java)\n        at org.eclipse.swt.widgets.Display.readAndDispatch(Display.java)\n        at org.eclipse.ui.internal.Workbench.runEventLoop(Workbench.java:1240)\n        at org.eclipse.ui.internal.Workbench.run(Workbench.java:1223)\n        at org.eclipse.core.internal.boot.InternalBootLoader.run(InternalBootLoa\nder.java:845)\n        at org.eclipse.core.boot.BootLoader.run(BootLoader.java:462)\n        at java.lang.reflect.AccessibleObject.invokeL(AccessibleObject.java:203)\n\n        at java.lang.reflect.Method.invoke(Method.java:271)\n        at org.eclipse.core.launcher.Main.basicRun(Main.java:247)\n        at org.eclipse.core.launcher.Main.run(Main.java:703)\n        at org.eclipse.core.launcher.Main.main(Main.java:539)\njava.lang.NullPointerException",
    "Note that nothing is showing up in my variables view too. Perhaps I\u0027m in some \nweird state?",
    "\n\n*** This bug has been marked as a duplicate of 30385 ***"
  ],
  "commentCreationDates": [
    "2003-01-29T21:14:06+01:00",
    "2003-01-29T21:16:26+01:00",
    "2003-01-29T21:17:49+01:00"
  ],
  "traces": [
    {
      "exceptionType": "java.lang.NullPointerException",
      "elements": [
        {
          "method": "java.lang.Throwable.\u003cinit\u003e",
          "source": "Throwable.java"
        },
        {
          "method": "java.lang.Throwable.\u003cinit\u003e",
          "source": "Throwable.java"
        },
        {
          "method": "java.lang.NullPointerException.\u003cinit\u003e",
          "source": "NullPointerException.java:63"
        },
        {
          "method": "org.eclipse.jdt.internal.debug.ui.actions.OpenTypeAction.getSourceElement",
          "source": "OpenTypeAction.java:151"
        },
        {
          "method": "org.eclipse.jdt.internal.debug.ui.actions.OpenDeclaringTypeAction.doAction",
          "source": "OpenDeclaringTypeAction.java:21"
        },
        {
          "method": "org.eclipse.jdt.internal.debug.ui.actions.OpenTypeAction.run",
          "source": "OpenType Action.java:53"
        },
        {
          "method": "org.eclipse.ui.internal.PluginAction.runWithEvent",
          "source": "PluginAction.java:2 50"
        },
        {
          "method": "org.eclipse.jface.action.ActionContributionItem.handleWidgetSelection",
          "source": "ActionContributionItem.java:450"
        },
        {
          "method": "org.eclipse.jface.action.ActionContributionItem.handleWidgetEvent",
          "source": "Act ionContributionItem.java"
        },
        {
          "method": "org.eclipse.jface.action.ActionContributionItem.access$0",
          "source": "ActionContri butionItem.java"
        },
        {
          "method": "org.eclipse.jface.action.ActionContributionItem$ActionListener.handleEvent",
          "source": "ActionContributionItem.java"
        },
        {
          "method": "org.eclipse.swt.widgets.EventTable.sendEvent",
          "source": "EventTable.java"
        },
        {
          "method": "org.eclipse.swt.widgets.Widget.sendEvent",
          "source": "Widget.java"
        },
        {
          "method": "org.eclipse.swt.widgets.Display.runDeferredEvents",
          "source": "Display.java"
        },
        {
          "method": "org.eclipse.swt.widgets.Display.readAndDispatch",
          "source": "Display.java"
        },
        {
          "method": "org.eclipse.ui.internal.Workbench.runEventLoop",
          "source": "Workbench.java:1240"
        },
        {
          "method": "org.eclipse.ui.internal.Workbench.run",
          "source": "Workbench.java:1223"
        },
        {
          "method": "org.eclipse.core.internal.boot.InternalBootLoader.run",
          "source": "InternalBootLoa der.java:845"
        },
        {
          "method": "org.eclipse.core.boot.BootLoader.run",
          "source": "BootLoader.java:462"
        },
        {
          "method": "java.lang.reflect.AccessibleObject.invokeL",
          "source": "AccessibleObject.java:203"
        },
        {
          "method": "java.lang.reflect.Method.invoke",
          "source": "Method.java:271"
        },
        {
          "method": "org.eclipse.core.launcher.Main.basicRun",
          "source": "Main.java:247"
        },
        {
          "method": "org.eclipse.core.launcher.Main.run",
          "source": "Main.java:703"
        },
        {
          "method": "org.eclipse.core.launcher.Main.main",
          "source": "Main.java:539"
        }
      ],
      "number": 0,
      "commentIndex": 0,
      "bugId": "30542",
      "duplicateId": "30385",
      "date": "2003-01-29T21:14:06+01:00",
      "product": "JDT",
      "component": "Debug",
      "severity": "normal"
    }
  ],
  "groupId": "30385",
  "bugId": "30542",
  "duplicateId": "30385",
  "date": "2003-01-29T21:14:06+01:00",
  "product": "JDT",
  "component": "Debug",
  "severity": "normal"
}