{
  "comments": [
    "Saw this exception in the log file. Did not see any error in the UI. Not sure \nwhat happened.\n\nBuild id: 200301291650\n\n!ENTRY org.eclipse.ui 4 0 Feb 04, 2003 11:32:59.628\n!MESSAGE Failed to execute runnable (java.util.ConcurrentModificationException)\n!STACK 0\norg.eclipse.swt.SWTException: Failed to execute runnable \n(java.util.ConcurrentModificationException)\n        at org.eclipse.swt.SWT.error(SWT.java:2292)\n        at org.eclipse.swt.widgets.Synchronizer.runAsyncMessages\n(Synchronizer.java:97)\n        at org.eclipse.swt.widgets.Display.runAsyncMessages(Display.java:1669)\n        at org.eclipse.swt.widgets.Display.readAndDispatch(Display.java:1414)\n        at org.eclipse.jface.operation.ModalContext$ModalContextThread.block\n(ModalContext.java:130)\n        at org.eclipse.jface.operation.ModalContext.run(ModalContext.java:255)\n        at org.eclipse.jface.dialogs.ProgressMonitorDialog.run\n(ProgressMonitorDialog.java:351)\n        at org.eclipse.jdt.ui.actions.FindAction.run(FindAction.java:287)\n        at org.eclipse.jdt.ui.actions.FindReferencesAction.run\n(FindReferencesAction.java:79)\n        at org.eclipse.jdt.ui.actions.FindAction.run(FindAction.java:237)\n        at org.eclipse.jdt.ui.actions.SelectionDispatchAction.dispatchRun\n(SelectionDispatchAction.java:193)\n        at org.eclipse.jdt.ui.actions.SelectionDispatchAction.run\n(SelectionDispatchAction.java:169)\n        at org.eclipse.jface.action.Action.runWithEvent(Action.java:804)\n        at \norg.eclipse.jface.action.ActionContributionItem.handleWidgetSelection\n(ActionContributionItem.java:450)\n        at org.eclipse.jface.action.ActionContributionItem.handleWidgetEvent\n(ActionContributionItem.java:398)\n        at org.eclipse.jface.action.ActionContributionItem.access$0\n(ActionContributionItem.java:392)\n        at \norg.eclipse.jface.action.ActionContributionItem$ActionListener.handleEvent\n(ActionContributionItem.java:72)\n        at org.eclipse.swt.widgets.EventTable.sendEvent(EventTable.java:77)\n        at org.eclipse.swt.widgets.Widget.sendEvent(Widget.java:836)\n        at org.eclipse.swt.widgets.Display.runDeferredEvents(Display.java:1692)\n        at org.eclipse.swt.widgets.Display.readAndDispatch(Display.java:1410)\n        at org.eclipse.ui.internal.Workbench.runEventLoop(Workbench.java:1240)\n        at org.eclipse.ui.internal.Workbench.run(Workbench.java:1223)\n        at org.eclipse.core.internal.boot.InternalBootLoader.run\n(InternalBootLoader.java:845)\n        at org.eclipse.core.boot.BootLoader.run(BootLoader.java:462)\n        at java.lang.reflect.Method.invoke(Native Method)\n        at org.eclipse.core.launcher.Main.basicRun(Main.java:247)\n        at org.eclipse.core.launcher.Main.run(Main.java:703)\n        at org.eclipse.core.launcher.Main.main(Main.java:539)\nFailed to execute runnable (java.util.ConcurrentModificationException)\n!ENTRY org.eclipse.ui 4 4 Feb 04, 2003 11:32:59.628\n!MESSAGE\n*** Stack trace of contained exception ***\n\n*** Stack trace of contained exception ***\nReason:\n!ENTRY org.eclipse.ui 4 0 Feb 04, 2003 11:32:59.628\n!MESSAGE java.util.ConcurrentModificationException\n!STACK 0\njava.util.ConcurrentModificationException\n        at java.util.HashMap$HashIterator.next(HashMap.java:731)\n        at org.eclipse.search.internal.ui.SearchManager.handleNewSearchResult\n(SearchManager.java:416)\n        at \norg.eclipse.search.internal.ui.SearchManager.handleSearchMarkersChanged\n(SearchManager.java:353)\n        at org.eclipse.search.internal.ui.SearchManager.access$2\n(SearchManager.java:350)\n        at org.eclipse.search.internal.ui.SearchManager$7.run\n(SearchManager.java:493)\n        at org.eclipse.ui.internal.UIWorkspaceLock.doPendingWork\n(UIWorkspaceLock.java:53)\n        at org.eclipse.ui.internal.UISynchronizer$1.run(UISynchronizer.java:23)\n        at org.eclipse.swt.widgets.RunnableLock.run(RunnableLock.java:31)\n        at org.eclipse.swt.widgets.Synchronizer.runAsyncMessages\n(Synchronizer.java:94)\n        at org.eclipse.swt.widgets.Display.runAsyncMessages(Display.java:1669)\n        at org.eclipse.swt.widgets.Display.readAndDispatch(Display.java:1414)\n        at org.eclipse.jface.operation.ModalContext$ModalContextThread.block\n(ModalContext.java:130)\n        at org.eclipse.jface.operation.ModalContext.run(ModalContext.java:255)\n        at org.eclipse.jface.dialogs.ProgressMonitorDialog.run\n(ProgressMonitorDialog.java:351)\n        at org.eclipse.jdt.ui.actions.FindAction.run(FindAction.java:287)\n        at org.eclipse.jdt.ui.actions.FindReferencesAction.run\n(FindReferencesAction.java:79)\n        at org.eclipse.jdt.ui.actions.FindAction.run(FindAction.java:237)\n        at org.eclipse.jdt.ui.actions.SelectionDispatchAction.dispatchRun\n(SelectionDispatchAction.java:193)\n        at org.eclipse.jdt.ui.actions.SelectionDispatchAction.run\n(SelectionDispatchAction.java:169)\n        at org.eclipse.jface.action.Action.runWithEvent(Action.java:804)\n        at \norg.eclipse.jface.action.ActionContributionItem.handleWidgetSelection\n(ActionContributionItem.java:450)\n        at org.eclipse.jface.action.ActionContributionItem.handleWidgetEvent\n(ActionContributionItem.java:398)\n        at org.eclipse.jface.action.ActionContributionItem.access$0\n(ActionContributionItem.java:392)\n        at \norg.eclipse.jface.action.ActionContributionItem$ActionListener.handleEvent\n(ActionContributionItem.java:72)\n        at org.eclipse.swt.widgets.EventTable.sendEvent(EventTable.java:77)\n        at org.eclipse.swt.widgets.Widget.sendEvent(Widget.java:836)\n        at org.eclipse.swt.widgets.Display.runDeferredEvents(Display.java:1692)\n        at org.eclipse.swt.widgets.Display.readAndDispatch(Display.java:1410)\n        at org.eclipse.ui.internal.Workbench.runEventLoop(Workbench.java:1240)\n        at org.eclipse.ui.internal.Workbench.run(Workbench.java:1223)\n        at org.eclipse.core.internal.boot.InternalBootLoader.run\n(InternalBootLoader.java:845)\n        at org.eclipse.core.boot.BootLoader.run(BootLoader.java:462)\n        at java.lang.reflect.Method.invoke(Native Method)\n        at org.eclipse.core.launcher.Main.basicRun(Main.java:247)\n        at org.eclipse.core.launcher.Main.run(Main.java:703)\n        at org.eclipse.core.launcher.Main.main(Main.java:539)\njava.util.ConcurrentModificationException",
    "This should not happen. It looks like somehow  a Search view is added or removed\nwhile a (previous?) Search is going on (or the other way around).\n\nDo you experiment with some background threading?\n\nAny hint on how to reproduce?\n\nNote: I now protected the code but I think the error happens somewhere else.\n\n",
    "Removed the protection code again there must be some other issue here.\nDid your workbench crash or run out of memory?\n",
    "No. I was working (I use -consoleLog) and I saw this exception in the console  \nbut I did not see any problem in the UI.",
    "Please reopen if you see this again.\n"
  ],
  "commentCreationDates": [
    "2003-02-04T21:14:58+01:00",
    "2003-02-05T09:17:44+01:00",
    "2003-02-05T09:27:26+01:00",
    "2003-02-05T15:52:25+01:00",
    "2003-02-18T07:55:35+01:00"
  ],
  "traces": [
    {
      "exceptionType": "org.eclipse.swt.SWTException",
      "message": "Failed to execute runnable  (java.util.ConcurrentModificationException)",
      "elements": [
        {
          "method": "org.eclipse.swt.SWT.error",
          "source": "SWT.java:2292"
        },
        {
          "method": "org.eclipse.swt.widgets.Synchronizer.runAsyncMessages",
          "source": "Synchronizer.java:97"
        },
        {
          "method": "org.eclipse.swt.widgets.Display.runAsyncMessages",
          "source": "Display.java:1669"
        },
        {
          "method": "org.eclipse.swt.widgets.Display.readAndDispatch",
          "source": "Display.java:1414"
        },
        {
          "method": "org.eclipse.jface.operation.ModalContext$ModalContextThread.block",
          "source": "ModalContext.java:130"
        },
        {
          "method": "org.eclipse.jface.operation.ModalContext.run",
          "source": "ModalContext.java:255"
        },
        {
          "method": "org.eclipse.jface.dialogs.ProgressMonitorDialog.run",
          "source": "ProgressMonitorDialog.java:351"
        },
        {
          "method": "org.eclipse.jdt.ui.actions.FindAction.run",
          "source": "FindAction.java:287"
        },
        {
          "method": "org.eclipse.jdt.ui.actions.FindReferencesAction.run",
          "source": "FindReferencesAction.java:79"
        },
        {
          "method": "org.eclipse.jdt.ui.actions.FindAction.run",
          "source": "FindAction.java:237"
        },
        {
          "method": "org.eclipse.jdt.ui.actions.SelectionDispatchAction.dispatchRun",
          "source": "SelectionDispatchAction.java:193"
        },
        {
          "method": "org.eclipse.jdt.ui.actions.SelectionDispatchAction.run",
          "source": "SelectionDispatchAction.java:169"
        },
        {
          "method": "org.eclipse.jface.action.Action.runWithEvent",
          "source": "Action.java:804"
        },
        {
          "method": "org.eclipse.jface.action.ActionContributionItem.handleWidgetSelection",
          "source": "ActionContributionItem.java:450"
        },
        {
          "method": "org.eclipse.jface.action.ActionContributionItem.handleWidgetEvent",
          "source": "ActionContributionItem.java:398"
        },
        {
          "method": "org.eclipse.jface.action.ActionContributionItem.access$0",
          "source": "ActionContributionItem.java:392"
        },
        {
          "method": "org.eclipse.jface.action.ActionContributionItem$ActionListener.handleEvent",
          "source": "ActionContributionItem.java:72"
        },
        {
          "method": "org.eclipse.swt.widgets.EventTable.sendEvent",
          "source": "EventTable.java:77"
        },
        {
          "method": "org.eclipse.swt.widgets.Widget.sendEvent",
          "source": "Widget.java:836"
        },
        {
          "method": "org.eclipse.swt.widgets.Display.runDeferredEvents",
          "source": "Display.java:1692"
        },
        {
          "method": "org.eclipse.swt.widgets.Display.readAndDispatch",
          "source": "Display.java:1410"
        },
        {
          "method": "org.eclipse.ui.internal.Workbench.runEventLoop",
          "source": "Workbench.java:1240"
        },
        {
          "method": "org.eclipse.ui.internal.Workbench.run",
          "source": "Workbench.java:1223"
        },
        {
          "method": "org.eclipse.core.internal.boot.InternalBootLoader.run",
          "source": "InternalBootLoader.java:845"
        },
        {
          "method": "org.eclipse.core.boot.BootLoader.run",
          "source": "BootLoader.java:462"
        },
        {
          "method": "java.lang.reflect.Method.invoke",
          "source": "Native Method"
        },
        {
          "method": "org.eclipse.core.launcher.Main.basicRun",
          "source": "Main.java:247"
        },
        {
          "method": "org.eclipse.core.launcher.Main.run",
          "source": "Main.java:703"
        },
        {
          "method": "org.eclipse.core.launcher.Main.main",
          "source": "Main.java:539"
        }
      ],
      "number": 0,
      "commentIndex": 0,
      "bugId": "30908",
      "date": "2003-02-04T21:14:58+01:00",
      "product": "Platform",
      "component": "Search",
      "severity": "normal"
    },
    {
      "exceptionType": "java.util.ConcurrentModificationException",
      "elements": [
        {
          "method": "java.util.HashMap$HashIterator.next",
          "source": "HashMap.java:731"
        },
        {
          "method": "org.eclipse.search.internal.ui.SearchManager.handleNewSearchResult",
          "source": "SearchManager.java:416"
        },
        {
          "method": "org.eclipse.search.internal.ui.SearchManager.handleSearchMarkersChanged",
          "source": "SearchManager.java:353"
        },
        {
          "method": "org.eclipse.search.internal.ui.SearchManager.access$2",
          "source": "SearchManager.java:350"
        },
        {
          "method": "org.eclipse.search.internal.ui.SearchManager$7.run",
          "source": "SearchManager.java:493"
        },
        {
          "method": "org.eclipse.ui.internal.UIWorkspaceLock.doPendingWork",
          "source": "UIWorkspaceLock.java:53"
        },
        {
          "method": "org.eclipse.ui.internal.UISynchronizer$1.run",
          "source": "UISynchronizer.java:23"
        },
        {
          "method": "org.eclipse.swt.widgets.RunnableLock.run",
          "source": "RunnableLock.java:31"
        },
        {
          "method": "org.eclipse.swt.widgets.Synchronizer.runAsyncMessages",
          "source": "Synchronizer.java:94"
        },
        {
          "method": "org.eclipse.swt.widgets.Display.runAsyncMessages",
          "source": "Display.java:1669"
        },
        {
          "method": "org.eclipse.swt.widgets.Display.readAndDispatch",
          "source": "Display.java:1414"
        },
        {
          "method": "org.eclipse.jface.operation.ModalContext$ModalContextThread.block",
          "source": "ModalContext.java:130"
        },
        {
          "method": "org.eclipse.jface.operation.ModalContext.run",
          "source": "ModalContext.java:255"
        },
        {
          "method": "org.eclipse.jface.dialogs.ProgressMonitorDialog.run",
          "source": "ProgressMonitorDialog.java:351"
        },
        {
          "method": "org.eclipse.jdt.ui.actions.FindAction.run",
          "source": "FindAction.java:287"
        },
        {
          "method": "org.eclipse.jdt.ui.actions.FindReferencesAction.run",
          "source": "FindReferencesAction.java:79"
        },
        {
          "method": "org.eclipse.jdt.ui.actions.FindAction.run",
          "source": "FindAction.java:237"
        },
        {
          "method": "org.eclipse.jdt.ui.actions.SelectionDispatchAction.dispatchRun",
          "source": "SelectionDispatchAction.java:193"
        },
        {
          "method": "org.eclipse.jdt.ui.actions.SelectionDispatchAction.run",
          "source": "SelectionDispatchAction.java:169"
        },
        {
          "method": "org.eclipse.jface.action.Action.runWithEvent",
          "source": "Action.java:804"
        },
        {
          "method": "org.eclipse.jface.action.ActionContributionItem.handleWidgetSelection",
          "source": "ActionContributionItem.java:450"
        },
        {
          "method": "org.eclipse.jface.action.ActionContributionItem.handleWidgetEvent",
          "source": "ActionContributionItem.java:398"
        },
        {
          "method": "org.eclipse.jface.action.ActionContributionItem.access$0",
          "source": "ActionContributionItem.java:392"
        },
        {
          "method": "org.eclipse.jface.action.ActionContributionItem$ActionListener.handleEvent",
          "source": "ActionContributionItem.java:72"
        },
        {
          "method": "org.eclipse.swt.widgets.EventTable.sendEvent",
          "source": "EventTable.java:77"
        },
        {
          "method": "org.eclipse.swt.widgets.Widget.sendEvent",
          "source": "Widget.java:836"
        },
        {
          "method": "org.eclipse.swt.widgets.Display.runDeferredEvents",
          "source": "Display.java:1692"
        },
        {
          "method": "org.eclipse.swt.widgets.Display.readAndDispatch",
          "source": "Display.java:1410"
        },
        {
          "method": "org.eclipse.ui.internal.Workbench.runEventLoop",
          "source": "Workbench.java:1240"
        },
        {
          "method": "org.eclipse.ui.internal.Workbench.run",
          "source": "Workbench.java:1223"
        },
        {
          "method": "org.eclipse.core.internal.boot.InternalBootLoader.run",
          "source": "InternalBootLoader.java:845"
        },
        {
          "method": "org.eclipse.core.boot.BootLoader.run",
          "source": "BootLoader.java:462"
        },
        {
          "method": "java.lang.reflect.Method.invoke",
          "source": "Native Method"
        },
        {
          "method": "org.eclipse.core.launcher.Main.basicRun",
          "source": "Main.java:247"
        },
        {
          "method": "org.eclipse.core.launcher.Main.run",
          "source": "Main.java:703"
        },
        {
          "method": "org.eclipse.core.launcher.Main.main",
          "source": "Main.java:539"
        }
      ],
      "number": 1,
      "commentIndex": 0,
      "bugId": "30908",
      "date": "2003-02-04T21:14:58+01:00",
      "product": "Platform",
      "component": "Search",
      "severity": "normal"
    }
  ],
  "groupId": "30908",
  "bugId": "30908",
  "date": "2003-02-04T21:14:58+01:00",
  "product": "Platform",
  "component": "Search",
  "severity": "normal"
}