{
  "comments": [
    "Build id: 200302050800\n\nGot this excecption in the log. After clicking in an item in the search view.\nEclipse was not responding for 30 seconds.\n\n\n!ENTRY org.eclipse.jdt.ui 4 10001 Feb 05, 2003 15:25:09.893\n!MESSAGE Internal Error\n!STACK 1\norg.eclipse.core.internal.resources.ResourceException: Marker id: 92868 not \nfound.\n        at org.eclipse.core.internal.resources.Marker.checkInfo(Marker.java:53)\n        at org.eclipse.core.internal.resources.Marker.getType(Marker.java:176)\n        at org.eclipse.core.internal.resources.Marker.isSubtypeOf\n(Marker.java:194)\n        at \norg.eclipse.jdt.internal.ui.text.correction.JavaCorrectionProcessor.hasCorrecti\nons(JavaCorrectionProcessor.java:107)\n        at \norg.eclipse.jdt.internal.ui.javaeditor.JavaMarkerAnnotation.mustShowQuickFixIco\nn(JavaMarkerAnnotation.java:132)\n        at org.eclipse.jdt.internal.ui.javaeditor.JavaMarkerAnnotation.getImage\n(JavaMarkerAnnotation.java:232)\n        at org.eclipse.ui.texteditor.MarkerAnnotation.paint\n(MarkerAnnotation.java:196)\n        at org.eclipse.jface.text.source.AnnotationRulerColumn.doPaint\n(AnnotationRulerColumn.java:350)\n        at \norg.eclipse.jface.text.source.AnnotationRulerColumn.doubleBufferPaint\n(AnnotationRulerColumn.java:241)\n        at org.eclipse.jface.text.source.AnnotationRulerColumn.access$3\n(AnnotationRulerColumn.java:216)\n        at org.eclipse.jface.text.source.AnnotationRulerColumn$1.paintControl\n(AnnotationRulerColumn.java:155)\n        at org.eclipse.swt.widgets.TypedListener.handleEvent\n(TypedListener.java:80)\n        at org.eclipse.swt.widgets.EventTable.sendEvent(EventTable.java:77)\n        at org.eclipse.swt.widgets.Widget.sendEvent(Widget.java:836)\n        at org.eclipse.swt.widgets.Widget.sendEvent(Widget.java:861)\n        at org.eclipse.swt.widgets.Widget.sendEvent(Widget.java:845)\n        at org.eclipse.swt.widgets.Composite.WM_PAINT(Composite.java:726)\n        at org.eclipse.swt.widgets.Control.windowProc(Control.java:2804)\n        at org.eclipse.swt.widgets.Display.windowProc(Display.java:2198)\n        at org.eclipse.swt.internal.win32.OS.DispatchMessageW(Native Method)\n        at org.eclipse.swt.internal.win32.OS.DispatchMessage(OS.java:1292)\n        at org.eclipse.swt.widgets.Display.readAndDispatch(Display.java:1408)\n        at org.eclipse.jface.operation.ModalContext$ModalContextThread.block\n(ModalContext.java:130)\n        at org.eclipse.jface.operation.ModalContext.run(ModalContext.java:255)\n        at org.eclipse.jface.dialogs.ProgressMonitorDialog.run\n(ProgressMonitorDialog.java:351)\n        at org.eclipse.jdt.ui.actions.FindAction.run(FindAction.java:289)\n        at org.eclipse.jdt.ui.actions.FindReferencesAction.run\n(FindReferencesAction.java:79)\n        at org.eclipse.jdt.ui.actions.WorkingSetFindAction.run\n(WorkingSetFindAction.java:66)\n        at org.eclipse.jdt.ui.actions.FindAction.run(FindAction.java:239)\n        at org.eclipse.jdt.ui.actions.SelectionDispatchAction.dispatchRun\n(SelectionDispatchAction.java:193)\n        at org.eclipse.jdt.ui.actions.SelectionDispatchAction.run\n(SelectionDispatchAction.java:169)\n        at org.eclipse.jface.action.Action.runWithEvent(Action.java:804)\n        at \norg.eclipse.jface.action.ActionContributionItem.handleWidgetSelection\n(ActionContributionItem.java:450)\n        at org.eclipse.jface.action.ActionContributionItem.handleWidgetEvent\n(ActionContributionItem.java:398)\n        at org.eclipse.jface.action.ActionContributionItem.access$0\n(ActionContributionItem.java:392)\n        at \norg.eclipse.jface.action.ActionContributionItem$ActionListener.handleEvent\n(ActionContributionItem.java:72)\n        at org.eclipse.swt.widgets.EventTable.sendEvent(EventTable.java:77)\n        at org.eclipse.swt.widgets.Widget.sendEvent(Widget.java:836)\n        at org.eclipse.swt.widgets.Display.runDeferredEvents(Display.java:1692)\n        at org.eclipse.swt.widgets.Display.readAndDispatch(Display.java:1410)\n        at org.eclipse.ui.internal.Workbench.runEventLoop(Workbench.java:1289)\n        at org.eclipse.ui.internal.Workbench.run(Workbench.java:1272)\n        at org.eclipse.core.internal.boot.InternalBootLoader.run\n(InternalBootLoader.java:845)\n        at org.eclipse.core.boot.BootLoader.run(BootLoader.java:461)\n        at java.lang.reflect.Method.invoke(Native Method)\n        at org.eclipse.core.launcher.Main.basicRun(Main.java:247)\n        at org.eclipse.core.launcher.Main.run(Main.java:703)\n        at org.eclipse.core.launcher.Main.main(Main.java:539)\n!ENTRY org.eclipse.core.resources 4 376 Feb 05, 2003 15:25:09.909\n!MESSAGE Marker id: 92868 not found.",
    "Daniel, any idea ?",
    "I used existing methods from the processor which don\u0027t seem to be thread safe.\nWill look into it. ",
    "Fixed the utility method. It now checks if the marker exists.\nAvailable in builds \u003e\u003d I20030206\n"
  ],
  "commentCreationDates": [
    "2003-02-05T20:41:06+01:00",
    "2003-02-05T20:59:18+01:00",
    "2003-02-06T07:30:35+01:00",
    "2003-02-06T09:35:56+01:00"
  ],
  "traces": [
    {
      "exceptionType": "org.eclipse.core.internal.resources.ResourceException",
      "message": "Marker id: 92868 not  found.",
      "elements": [
        {
          "method": "org.eclipse.core.internal.resources.Marker.checkInfo",
          "source": "Marker.java:53"
        },
        {
          "method": "org.eclipse.core.internal.resources.Marker.getType",
          "source": "Marker.java:176"
        },
        {
          "method": "org.eclipse.core.internal.resources.Marker.isSubtypeOf",
          "source": "Marker.java:194"
        },
        {
          "method": "org.eclipse.jdt.internal.ui.text.correction.JavaCorrectionProcessor.hasCorrections",
          "source": "JavaCorrectionProcessor.java:107"
        },
        {
          "method": "org.eclipse.jdt.internal.ui.javaeditor.JavaMarkerAnnotation.mustShowQuickFixIcon",
          "source": "JavaMarkerAnnotation.java:132"
        },
        {
          "method": "org.eclipse.jdt.internal.ui.javaeditor.JavaMarkerAnnotation.getImage",
          "source": "JavaMarkerAnnotation.java:232"
        },
        {
          "method": "org.eclipse.ui.texteditor.MarkerAnnotation.paint",
          "source": "MarkerAnnotation.java:196"
        },
        {
          "method": "org.eclipse.jface.text.source.AnnotationRulerColumn.doPaint",
          "source": "AnnotationRulerColumn.java:350"
        },
        {
          "method": "org.eclipse.jface.text.source.AnnotationRulerColumn.doubleBufferPaint",
          "source": "AnnotationRulerColumn.java:241"
        },
        {
          "method": "org.eclipse.jface.text.source.AnnotationRulerColumn.access$3",
          "source": "AnnotationRulerColumn.java:216"
        },
        {
          "method": "org.eclipse.jface.text.source.AnnotationRulerColumn$1.paintControl",
          "source": "AnnotationRulerColumn.java:155"
        },
        {
          "method": "org.eclipse.swt.widgets.TypedListener.handleEvent",
          "source": "TypedListener.java:80"
        },
        {
          "method": "org.eclipse.swt.widgets.EventTable.sendEvent",
          "source": "EventTable.java:77"
        },
        {
          "method": "org.eclipse.swt.widgets.Widget.sendEvent",
          "source": "Widget.java:836"
        },
        {
          "method": "org.eclipse.swt.widgets.Widget.sendEvent",
          "source": "Widget.java:861"
        },
        {
          "method": "org.eclipse.swt.widgets.Widget.sendEvent",
          "source": "Widget.java:845"
        },
        {
          "method": "org.eclipse.swt.widgets.Composite.WM_PAINT",
          "source": "Composite.java:726"
        },
        {
          "method": "org.eclipse.swt.widgets.Control.windowProc",
          "source": "Control.java:2804"
        },
        {
          "method": "org.eclipse.swt.widgets.Display.windowProc",
          "source": "Display.java:2198"
        },
        {
          "method": "org.eclipse.swt.internal.win32.OS.DispatchMessageW",
          "source": "Native Method"
        },
        {
          "method": "org.eclipse.swt.internal.win32.OS.DispatchMessage",
          "source": "OS.java:1292"
        },
        {
          "method": "org.eclipse.swt.widgets.Display.readAndDispatch",
          "source": "Display.java:1408"
        },
        {
          "method": "org.eclipse.jface.operation.ModalContext$ModalContextThread.block",
          "source": "ModalContext.java:130"
        },
        {
          "method": "org.eclipse.jface.operation.ModalContext.run",
          "source": "ModalContext.java:255"
        },
        {
          "method": "org.eclipse.jface.dialogs.ProgressMonitorDialog.run",
          "source": "ProgressMonitorDialog.java:351"
        },
        {
          "method": "org.eclipse.jdt.ui.actions.FindAction.run",
          "source": "FindAction.java:289"
        },
        {
          "method": "org.eclipse.jdt.ui.actions.FindReferencesAction.run",
          "source": "FindReferencesAction.java:79"
        },
        {
          "method": "org.eclipse.jdt.ui.actions.WorkingSetFindAction.run",
          "source": "WorkingSetFindAction.java:66"
        },
        {
          "method": "org.eclipse.jdt.ui.actions.FindAction.run",
          "source": "FindAction.java:239"
        },
        {
          "method": "org.eclipse.jdt.ui.actions.SelectionDispatchAction.dispatchRun",
          "source": "SelectionDispatchAction.java:193"
        },
        {
          "method": "org.eclipse.jdt.ui.actions.SelectionDispatchAction.run",
          "source": "SelectionDispatchAction.java:169"
        },
        {
          "method": "org.eclipse.jface.action.Action.runWithEvent",
          "source": "Action.java:804"
        },
        {
          "method": "org.eclipse.jface.action.ActionContributionItem.handleWidgetSelection",
          "source": "ActionContributionItem.java:450"
        },
        {
          "method": "org.eclipse.jface.action.ActionContributionItem.handleWidgetEvent",
          "source": "ActionContributionItem.java:398"
        },
        {
          "method": "org.eclipse.jface.action.ActionContributionItem.access$0",
          "source": "ActionContributionItem.java:392"
        },
        {
          "method": "org.eclipse.jface.action.ActionContributionItem$ActionListener.handleEvent",
          "source": "ActionContributionItem.java:72"
        },
        {
          "method": "org.eclipse.swt.widgets.EventTable.sendEvent",
          "source": "EventTable.java:77"
        },
        {
          "method": "org.eclipse.swt.widgets.Widget.sendEvent",
          "source": "Widget.java:836"
        },
        {
          "method": "org.eclipse.swt.widgets.Display.runDeferredEvents",
          "source": "Display.java:1692"
        },
        {
          "method": "org.eclipse.swt.widgets.Display.readAndDispatch",
          "source": "Display.java:1410"
        },
        {
          "method": "org.eclipse.ui.internal.Workbench.runEventLoop",
          "source": "Workbench.java:1289"
        },
        {
          "method": "org.eclipse.ui.internal.Workbench.run",
          "source": "Workbench.java:1272"
        },
        {
          "method": "org.eclipse.core.internal.boot.InternalBootLoader.run",
          "source": "InternalBootLoader.java:845"
        },
        {
          "method": "org.eclipse.core.boot.BootLoader.run",
          "source": "BootLoader.java:461"
        },
        {
          "method": "java.lang.reflect.Method.invoke",
          "source": "Native Method"
        },
        {
          "method": "org.eclipse.core.launcher.Main.basicRun",
          "source": "Main.java:247"
        },
        {
          "method": "org.eclipse.core.launcher.Main.run",
          "source": "Main.java:703"
        },
        {
          "method": "org.eclipse.core.launcher.Main.main",
          "source": "Main.java:539"
        }
      ],
      "number": 0,
      "commentIndex": 0,
      "bugId": "31027",
      "date": "2003-02-05T20:41:06+01:00",
      "product": "JDT",
      "component": "UI",
      "severity": "major"
    }
  ],
  "groupId": "31027",
  "bugId": "31027",
  "date": "2003-02-05T20:41:06+01:00",
  "product": "JDT",
  "component": "UI",
  "severity": "major"
}