{
  "comments": [
    "build i0206 (1700), win2k, j9sc20030205\n\nI: \n- created Java project aaa\n- created Java project bbb\n- right-click properties on aaa and changed the Java Build Path to reference \nproject bbb\n- hit ok\n- right-click properties on bbb and changed the Java Build Path to reference \nproject aaa\n- hit ok\n\nGot a message saying that an error occurred and got the following in my log \nfile.\n\n!ENTRY org.eclipse.jdt.ui 4 10001 Feb 07, 2003 17:24:53.959\n!MESSAGE Internal Error\n!STACK 0\njava.lang.reflect.InvocationTargetException: java.lang.NullPointerException\n        at java.lang.Throwable.\u003cinit\u003e(Throwable.java)\n        at java.lang.Throwable.\u003cinit\u003e(Throwable.java)\n        at java.lang.NullPointerException.\u003cinit\u003e(NullPointerException.java:63)\n        at org.eclipse.jdt.internal.core.SetClasspathOperation$2.run(SetClasspat\nhOperation.java)\n        at org.eclipse.jdt.internal.core.JavaModelOperation.runPostActions(JavaM\nodelOperation.java)\n        at org.eclipse.jdt.internal.core.JavaModelOperation.run(JavaModelOperati\non.java)\n        at org.eclipse.core.internal.resources.Workspace.run(Workspace.java)\n        at org.eclipse.jdt.internal.core.JavaElement.runOperation(JavaElement.ja\nva)\n        at org.eclipse.jdt.internal.core.JavaProject.setRawClasspath(JavaProject\n.java:2078)\n        at org.eclipse.jdt.internal.core.JavaProject.setRawClasspath(JavaProject\n.java:2042)\n        at org.eclipse.jdt.internal.ui.wizards.buildpaths.BuildPathsBlock.intern\nalConfigureJavaProject(BuildPathsBlock.java:653)\n        at org.eclipse.jdt.internal.ui.wizards.buildpaths.BuildPathsBlock.config\nureJavaProject(BuildPathsBlock.java:588)\n        at org.eclipse.jdt.internal.ui.preferences.BuildPathsPropertyPage$1.run(\nBuildPathsPropertyPage.java:145)\n        at org.eclipse.ui.actions.WorkspaceModifyDelegatingOperation.execute(Wor\nkspaceModifyDelegatingOperation.java:39)\n        at org.eclipse.ui.actions.WorkspaceModifyOperation$1.run(WorkspaceModify\nOperation.java:65)\n        at org.eclipse.core.internal.resources.Workspace.run(Workspace.java)\n        at org.eclipse.ui.actions.WorkspaceModifyOperation.run(WorkspaceModifyOp\neration.java:79)\n        at org.eclipse.jface.operation.ModalContext.runInCurrentThread(ModalCont\next.java:296)\n        at org.eclipse.jface.operation.ModalContext.run(ModalContext.java:246)\n        at org.eclipse.jface.dialogs.ProgressMonitorDialog.run(ProgressMonitorDi\nalog.java:351)\n        at org.eclipse.jdt.internal.ui.preferences.BuildPathsPropertyPage.perfor\nmOk(BuildPathsPropertyPage.java:153)\n        at org.eclipse.jface.preference.PreferenceDialog.okPressed(PreferenceDia\nlog.java:629)\n        at org.eclipse.jface.preference.PreferenceDialog.buttonPressed(Preferenc\neDialog.java:184)\n        at org.eclipse.jface.dialogs.Dialog$1.widgetSelected(Dialog.java:417)\n        at org.eclipse.swt.widgets.TypedListener.handleEvent(TypedListener.java)\n\n        at org.eclipse.swt.widgets.EventTable.sendEvent(EventTable.java)\n        at org.eclipse.swt.widgets.Widget.sendEvent(Widget.java)\n        at org.eclipse.swt.widgets.Display.runDeferredEvents(Display.java)\n        at org.eclipse.swt.widgets.Display.readAndDispatch(Display.java)\n        at org.eclipse.jface.window.Window.runEventLoop(Window.java)\n        at org.eclipse.jface.window.Window.open(Window.java:541)\n        at org.eclipse.ui.dialogs.PropertyDialogAction.run(PropertyDialogAction.\njava:158)\n        at org.eclipse.jface.action.Action.runWithEvent(Action.java:804)\n        at org.eclipse.jface.action.ActionContributionItem.handleWidgetSelection\n(ActionContributionItem.java:450)\n        at org.eclipse.jface.action.ActionContributionItem.handleWidgetEvent(Act\nionContributionItem.java)\n        at org.eclipse.jface.action.ActionContributionItem.access$0(ActionContri\nbutionItem.java)\n        at org.eclipse.jface.action.ActionContributionItem$ActionListener.handle\nEvent(ActionContributionItem.java)\n        at org.eclipse.swt.widgets.EventTable.sendEvent(EventTable.java)\n        at org.eclipse.swt.widgets.Widget.sendEvent(Widget.java)\n        at org.eclipse.swt.widgets.Display.runDeferredEvents(Display.java)\n        at org.eclipse.swt.widgets.Display.readAndDispatch(Display.java)\n        at org.eclipse.ui.internal.Workbench.runEventLoop(Workbench.java:1289)\n        at org.eclipse.ui.internal.Workbench.run(Workbench.java:1272)\n        at org.eclipse.core.internal.boot.InternalBootLoader.run(InternalBootLoa\nder.java:845)\n        at org.eclipse.core.boot.BootLoader.run(BootLoader.java:461)\n        at java.lang.reflect.AccessibleObject.invokeL(AccessibleObject.java:203)\n\n        at java.lang.reflect.Method.invoke(Method.java:271)\n        at org.eclipse.core.launcher.Main.basicRun(Main.java:247)\n        at org.eclipse.core.launcher.Main.run(Main.java:703)\n        at org.eclipse.core.launcher.Main.main(Main.java:539)",
    "Increasing severity as this is easily reproducable. (not marking as critical \nsince projects with cyclic build orders aren\u0027t common)\n\nOn a side note, it looks like it prevents people from creating projects with \ncyclic dependancies so perhaps we can remove the new project build cycle \nsupport? :-)\n",
    "Some cycles are working (we have regression tests for these), will investigate.",
    "Cannot reproduce on jdk1.4.1_01. Could you give it a try on a different JRE ?\nIf not reproduceable, then we should show your test case to j9 folks.",
    "Works ok for me on IBM JRE 1.3.1 build cn131-20020403.\n",
    "Closing as VM issue."
  ],
  "commentCreationDates": [
    "2003-02-07T22:31:47+01:00",
    "2003-02-07T22:43:12+01:00",
    "2003-02-08T09:21:10+01:00",
    "2003-02-08T12:25:02+01:00",
    "2003-02-10T00:54:30+01:00",
    "2003-02-13T13:20:33+01:00"
  ],
  "traces": [
    {
      "exceptionType": "java.lang.NullPointerException",
      "elements": [
        {
          "method": "java.lang.Throwable.\u003cinit\u003e",
          "source": "Throwable.java"
        },
        {
          "method": "java.lang.Throwable.\u003cinit\u003e",
          "source": "Throwable.java"
        },
        {
          "method": "java.lang.NullPointerException.\u003cinit\u003e",
          "source": "NullPointerException.java:63"
        },
        {
          "method": "org.eclipse.jdt.internal.core.SetClasspathOperation$2.run",
          "source": "SetClasspat hOperation.java"
        },
        {
          "method": "org.eclipse.jdt.internal.core.JavaModelOperation.runPostActions",
          "source": "JavaM odelOperation.java"
        },
        {
          "method": "org.eclipse.jdt.internal.core.JavaModelOperation.run",
          "source": "JavaModelOperati on.java"
        },
        {
          "method": "org.eclipse.core.internal.resources.Workspace.run",
          "source": "Workspace.java"
        },
        {
          "method": "org.eclipse.jdt.internal.core.JavaElement.runOperation",
          "source": "JavaElement.ja va"
        },
        {
          "method": "org.eclipse.jdt.internal.core.JavaProject.setRawClasspath",
          "source": "JavaProject .java:2078"
        },
        {
          "method": "org.eclipse.jdt.internal.core.JavaProject.setRawClasspath",
          "source": "JavaProject .java:2042"
        },
        {
          "method": "org.eclipse.jdt.internal.ui.wizards.buildpaths.BuildPathsBlock.internalConfigureJavaProject",
          "source": "BuildPathsBlock.java:653"
        },
        {
          "method": "org.eclipse.jdt.internal.ui.wizards.buildpaths.BuildPathsBlock.configureJavaProject",
          "source": "BuildPathsBlock.java:588"
        },
        {
          "method": "org.eclipse.jdt.internal.ui.preferences.BuildPathsPropertyPage$1.run",
          "source": " BuildPathsPropertyPage.java:145"
        },
        {
          "method": "org.eclipse.ui.actions.WorkspaceModifyDelegatingOperation.execute",
          "source": "Wor kspaceModifyDelegatingOperation.java:39"
        },
        {
          "method": "org.eclipse.ui.actions.WorkspaceModifyOperation$1.run",
          "source": "WorkspaceModify Operation.java:65"
        },
        {
          "method": "org.eclipse.core.internal.resources.Workspace.run",
          "source": "Workspace.java"
        },
        {
          "method": "org.eclipse.ui.actions.WorkspaceModifyOperation.run",
          "source": "WorkspaceModifyOp eration.java:79"
        },
        {
          "method": "org.eclipse.jface.operation.ModalContext.runInCurrentThread",
          "source": "ModalCont ext.java:296"
        },
        {
          "method": "org.eclipse.jface.operation.ModalContext.run",
          "source": "ModalContext.java:246"
        },
        {
          "method": "org.eclipse.jface.dialogs.ProgressMonitorDialog.run",
          "source": "ProgressMonitorDi alog.java:351"
        },
        {
          "method": "org.eclipse.jdt.internal.ui.preferences.BuildPathsPropertyPage.performOk",
          "source": "BuildPathsPropertyPage.java:153"
        },
        {
          "method": "org.eclipse.jface.preference.PreferenceDialog.okPressed",
          "source": "PreferenceDia log.java:629"
        },
        {
          "method": "org.eclipse.jface.preference.PreferenceDialog.buttonPressed",
          "source": "Preferenc eDialog.java:184"
        },
        {
          "method": "org.eclipse.jface.dialogs.Dialog$1.widgetSelected",
          "source": "Dialog.java:417"
        },
        {
          "method": "org.eclipse.swt.widgets.TypedListener.handleEvent",
          "source": "TypedListener.java"
        },
        {
          "method": "org.eclipse.swt.widgets.EventTable.sendEvent",
          "source": "EventTable.java"
        },
        {
          "method": "org.eclipse.swt.widgets.Widget.sendEvent",
          "source": "Widget.java"
        },
        {
          "method": "org.eclipse.swt.widgets.Display.runDeferredEvents",
          "source": "Display.java"
        },
        {
          "method": "org.eclipse.swt.widgets.Display.readAndDispatch",
          "source": "Display.java"
        },
        {
          "method": "org.eclipse.jface.window.Window.runEventLoop",
          "source": "Window.java"
        },
        {
          "method": "org.eclipse.jface.window.Window.open",
          "source": "Window.java:541"
        },
        {
          "method": "org.eclipse.ui.dialogs.PropertyDialogAction.run",
          "source": "PropertyDialogAction. java:158"
        },
        {
          "method": "org.eclipse.jface.action.Action.runWithEvent",
          "source": "Action.java:804"
        },
        {
          "method": "org.eclipse.jface.action.ActionContributionItem.handleWidgetSelection",
          "source": "ActionContributionItem.java:450"
        },
        {
          "method": "org.eclipse.jface.action.ActionContributionItem.handleWidgetEvent",
          "source": "Act ionContributionItem.java"
        },
        {
          "method": "org.eclipse.jface.action.ActionContributionItem.access$0",
          "source": "ActionContri butionItem.java"
        },
        {
          "method": "org.eclipse.jface.action.ActionContributionItem$ActionListener.handleEvent",
          "source": "ActionContributionItem.java"
        },
        {
          "method": "org.eclipse.swt.widgets.EventTable.sendEvent",
          "source": "EventTable.java"
        },
        {
          "method": "org.eclipse.swt.widgets.Widget.sendEvent",
          "source": "Widget.java"
        },
        {
          "method": "org.eclipse.swt.widgets.Display.runDeferredEvents",
          "source": "Display.java"
        },
        {
          "method": "org.eclipse.swt.widgets.Display.readAndDispatch",
          "source": "Display.java"
        },
        {
          "method": "org.eclipse.ui.internal.Workbench.runEventLoop",
          "source": "Workbench.java:1289"
        },
        {
          "method": "org.eclipse.ui.internal.Workbench.run",
          "source": "Workbench.java:1272"
        },
        {
          "method": "org.eclipse.core.internal.boot.InternalBootLoader.run",
          "source": "InternalBootLoa der.java:845"
        },
        {
          "method": "org.eclipse.core.boot.BootLoader.run",
          "source": "BootLoader.java:461"
        },
        {
          "method": "java.lang.reflect.AccessibleObject.invokeL",
          "source": "AccessibleObject.java:203"
        },
        {
          "method": "java.lang.reflect.Method.invoke",
          "source": "Method.java:271"
        },
        {
          "method": "org.eclipse.core.launcher.Main.basicRun",
          "source": "Main.java:247"
        },
        {
          "method": "org.eclipse.core.launcher.Main.run",
          "source": "Main.java:703"
        },
        {
          "method": "org.eclipse.core.launcher.Main.main",
          "source": "Main.java:539"
        }
      ],
      "number": 0,
      "commentIndex": 0,
      "bugId": "31380",
      "date": "2003-02-07T22:31:47+01:00",
      "product": "JDT",
      "component": "Core",
      "severity": "major"
    }
  ],
  "groupId": "31380",
  "bugId": "31380",
  "date": "2003-02-07T22:31:47+01:00",
  "product": "JDT",
  "component": "Core",
  "severity": "major"
}