{
  "comments": [
    "when starting eclipse, I receive this dialog:\n\nProblems during startup: check the .log file in the .metadata directory.\n\nThis is what I find in the .log file:\n\n!SESSION Feb 09, 2003 12:18:56.372\n---------------------------------------------java.version\u003d1.4.1_01\njava.vendor\u003dSun Microsystems Inc.\nBootLoader constants: OS\u003dlinux, ARCH\u003dx86, WS\u003dgtk, NL\u003den_US\nCommand-line arguments: -os linux -ws gtk -arch x86 -data\n/home3/eclipse-user/wsp2 -install file:/home3/eclipse/\n!ENTRY org.eclipse.core.runtime 4 2 Feb 09, 2003 12:18:56.379\n!MESSAGE Problems occurred when invoking code from plug-in:\n\"org.eclipse.core.runtime\".\n!STACK 0\norg.eclipse.core.internal.dtree.ObjectNotFoundException: Tree element\n/wspublisher2/build/url.properties not found.\n        at\norg.eclipse.core.internal.dtree.AbstractDataTree.handleNotFound(AbstractDataTree.java:243)\n        at\norg.eclipse.core.internal.dtree.DeltaDataTree.getData(DeltaDataTree.java:611)\n        at\norg.eclipse.core.internal.dtree.DataDeltaNode.asBackwardDelta(DataDeltaNode.java:54)\n        at\norg.eclipse.core.internal.dtree.NoDataDeltaNode.asBackwardDelta(NoDataDeltaNode.java:57)\n        at\norg.eclipse.core.internal.dtree.NoDataDeltaNode.asBackwardDelta(NoDataDeltaNode.java:57)\n        at\norg.eclipse.core.internal.dtree.DataDeltaNode.asBackwardDelta(DataDeltaNode.java:51)\n        at\norg.eclipse.core.internal.dtree.DeltaDataTree.asBackwardDelta(DeltaDataTree.java:96)\n        at\norg.eclipse.core.internal.dtree.DeltaDataTree.reroot(DeltaDataTree.java:818)\n        at\norg.eclipse.core.internal.dtree.DeltaDataTree.reroot(DeltaDataTree.java:817)\n        at\norg.eclipse.core.internal.dtree.DeltaDataTree.reroot(DeltaDataTree.java:817)\n        at\norg.eclipse.core.internal.dtree.DeltaDataTree.reroot(DeltaDataTree.java:817)\n        at\norg.eclipse.core.internal.dtree.DeltaDataTree.reroot(DeltaDataTree.java:817)\n        at\norg.eclipse.core.internal.dtree.DeltaDataTree.reroot(DeltaDataTree.java:817)\n        at\norg.eclipse.core.internal.dtree.DeltaDataTree.reroot(DeltaDataTree.java:817)\n        at\norg.eclipse.core.internal.dtree.DeltaDataTree.reroot(DeltaDataTree.java:817)\n        at\norg.eclipse.core.internal.dtree.DeltaDataTree.reroot(DeltaDataTree.java:817)\n        at\norg.eclipse.core.internal.dtree.DeltaDataTree.reroot(DeltaDataTree.java:793)\n        at\norg.eclipse.core.internal.watson.ElementTree.immutable(ElementTree.java:696)\n        at\norg.eclipse.core.internal.resources.SaveManager.restore(SaveManager.java:485)\n        at\norg.eclipse.core.internal.resources.SaveManager.startup(SaveManager.java:946)\n        at\norg.eclipse.core.internal.resources.Workspace.startup(Workspace.java:1504)\n        at org.eclipse.core.internal.resources.Workspace.open(Workspace.java:1296)\n        at\norg.eclipse.core.resources.ResourcesPlugin.startup(ResourcesPlugin.java:201)\n        at\norg.eclipse.core.internal.plugins.PluginDescriptor$1.run(PluginDescriptor.java:697)\n        at\norg.eclipse.core.internal.runtime.InternalPlatform.run(InternalPlatform.java:839)\n        at\norg.eclipse.core.internal.plugins.PluginDescriptor.internalDoPluginActivation(PluginDescriptor.java:709)\n        at\norg.eclipse.core.internal.plugins.PluginDescriptor.doPluginActivation(PluginDescriptor.java:184)\n        at\norg.eclipse.core.internal.plugins.PluginClassLoader.activatePlugin(PluginClassLoader.java:60)\n        at\norg.eclipse.core.internal.plugins.PluginClassLoader.internalFindClassParentsSelf(PluginClassLoader.java:138)\n        at\norg.eclipse.core.internal.boot.DelegatingURLClassLoader.findClassParentsSelf(DelegatingURLClassLoader.java:473)\n        at\norg.eclipse.core.internal.boot.DelegatingURLClassLoader.loadClass(DelegatingURLClassLoader.java:863)\n        at\norg.eclipse.core.internal.boot.DelegatingURLClassLoader.access$0(DelegatingURLClassLoader.java:857)\n        at\norg.eclipse.core.internal.boot.DelegatingURLClassLoader$DelegateLoader.loadClass(DelegatingURLClassLoader.java:80)\n        at\norg.eclipse.core.internal.boot.DelegatingURLClassLoader.findClassPrerequisites(DelegatingURLClassLoader.java:537)\n        at\norg.eclipse.core.internal.boot.DelegatingURLClassLoader.loadClass(DelegatingURLClassLoader.java:871)\n        at\norg.eclipse.core.internal.boot.DelegatingURLClassLoader.loadClass(DelegatingURLClassLoader.java:843)\n        at java.lang.ClassLoader.loadClass(ClassLoader.java:255)\n        at java.lang.ClassLoader.loadClassInternal(ClassLoader.java:315)\n        at java.lang.Class.getDeclaredConstructors0(Native Method)\n        at java.lang.Class.privateGetDeclaredConstructors(Class.java:1590)\n        at java.lang.Class.getConstructor0(Class.java:1762)\n        at java.lang.Class.newInstance0(Class.java:276)\n        at java.lang.Class.newInstance(Class.java:259)\n        at\norg.eclipse.core.internal.plugins.PluginDescriptor.createExecutableExtension(PluginDescriptor.java:136)\n        at\norg.eclipse.core.internal.plugins.PluginDescriptor.createExecutableExtension(PluginDescriptor.java:165)\n        at\norg.eclipse.core.internal.plugins.ConfigurationElement.createExecutableExtension(ConfigurationElement.java:102)\n        at\norg.eclipse.core.internal.runtime.InternalPlatform.loaderGetRunnable(InternalPlatform.java:461)\n        at sun.reflect.NativeMethodAccessorImpl.invoke0(Native Method)\n        at\nsun.reflect.NativeMethodAccessorImpl.invoke(NativeMethodAccessorImpl.java:39)\n        at\nsun.reflect.DelegatingMethodAccessorImpl.invoke(DelegatingMethodAccessorImpl.java:25)\n        at java.lang.reflect.Method.invoke(Method.java:324)\n        at\norg.eclipse.core.internal.boot.InternalBootLoader.getRunnable(InternalBootLoader.java:457)\n        at\norg.eclipse.core.internal.boot.InternalBootLoader.run(InternalBootLoader.java:827)\n        at org.eclipse.core.boot.BootLoader.run(BootLoader.java:462)\n        at sun.reflect.NativeMethodAccessorImpl.invoke0(Native Method)\n        at\nsun.reflect.NativeMethodAccessorImpl.invoke(NativeMethodAccessorImpl.java:39)\n        at\nsun.reflect.DelegatingMethodAccessorImpl.invoke(DelegatingMethodAccessorImpl.java:25)\n        at java.lang.reflect.Method.invoke(Method.java:324)\n        at org.eclipse.core.launcher.Main.basicRun(Main.java:247)\n        at org.eclipse.core.launcher.Main.run(Main.java:703)\n        at org.eclipse.core.launcher.Main.main(Main.java:539)\n!ENTRY org.eclipse.core.runtime 4 2 Feb 09, 2003 12:18:57.07\n!MESSAGE Plug-in \"org.eclipse.ui\" was unable to instantiate class\n\"org.eclipse.ui.internal.Workbench\".\n!STACK 0\norg.eclipse.core.internal.boot.DelegatingLoaderException:\norg.eclipse.core.runtime.CoreException: Problems encountered starting up\nplug-in: \"org.eclipse.core.resources\".\n        at\norg.eclipse.core.internal.plugins.PluginDescriptor.internalDoPluginActivation(PluginDescriptor.java:715)\n        at\norg.eclipse.core.internal.plugins.PluginDescriptor.doPluginActivation(PluginDescriptor.java:184)\n        at\norg.eclipse.core.internal.plugins.PluginClassLoader.activatePlugin(PluginClassLoader.java:60)\n        at\norg.eclipse.core.internal.plugins.PluginClassLoader.internalFindClassParentsSelf(PluginClassLoader.java:138)\n        at\norg.eclipse.core.internal.boot.DelegatingURLClassLoader.findClassParentsSelf(DelegatingURLClassLoader.java:473)\n        at\norg.eclipse.core.internal.boot.DelegatingURLClassLoader.loadClass(DelegatingURLClassLoader.java:863)\n        at\norg.eclipse.core.internal.boot.DelegatingURLClassLoader.access$0(DelegatingURLClassLoader.java:857)\n        at\norg.eclipse.core.internal.boot.DelegatingURLClassLoader$DelegateLoader.loadClass(DelegatingURLClassLoader.java:80)\n        at\norg.eclipse.core.internal.boot.DelegatingURLClassLoader.findClassPrerequisites(DelegatingURLClassLoader.java:537)\n        at\norg.eclipse.core.internal.boot.DelegatingURLClassLoader.loadClass(DelegatingURLClassLoader.java:871)\n        at\norg.eclipse.core.internal.boot.DelegatingURLClassLoader.loadClass(DelegatingURLClassLoader.java:843)\n        at java.lang.ClassLoader.loadClass(ClassLoader.java:255)\n        at java.lang.ClassLoader.loadClassInternal(ClassLoader.java:315)\n        at java.lang.Class.getDeclaredConstructors0(Native Method)\n        at java.lang.Class.privateGetDeclaredConstructors(Class.java:1590)\n        at java.lang.Class.getConstructor0(Class.java:1762)\n        at java.lang.Class.newInstance0(Class.java:276)\n        at java.lang.Class.newInstance(Class.java:259)\n        at\norg.eclipse.core.internal.plugins.PluginDescriptor.createExecutableExtension(PluginDescriptor.java:136)\n        at\norg.eclipse.core.internal.plugins.PluginDescriptor.createExecutableExtension(PluginDescriptor.java:165)\n        at\norg.eclipse.core.internal.plugins.ConfigurationElement.createExecutableExtension(ConfigurationElement.java:102)\n        at\norg.eclipse.core.internal.runtime.InternalPlatform.loaderGetRunnable(InternalPlatform.java:461)\n        at sun.reflect.NativeMethodAccessorImpl.invoke0(Native Method)\n        at\nsun.reflect.NativeMethodAccessorImpl.invoke(NativeMethodAccessorImpl.java:39)\n        at\nsun.reflect.DelegatingMethodAccessorImpl.invoke(DelegatingMethodAccessorImpl.java:25)\n        at java.lang.reflect.Method.invoke(Method.java:324)\n        at\norg.eclipse.core.internal.boot.InternalBootLoader.getRunnable(InternalBootLoader.java:457)\n        at\norg.eclipse.core.internal.boot.InternalBootLoader.run(InternalBootLoader.java:827)\n        at org.eclipse.core.boot.BootLoader.run(BootLoader.java:462)\n        at sun.reflect.NativeMethodAccessorImpl.invoke0(Native Method)\n        at\nsun.reflect.NativeMethodAccessorImpl.invoke(NativeMethodAccessorImpl.java:39)\n        at\nsun.reflect.DelegatingMethodAccessorImpl.invoke(DelegatingMethodAccessorImpl.java:25)\n        at java.lang.reflect.Method.invoke(Method.java:324)\n        at org.eclipse.core.launcher.Main.basicRun(Main.java:247)\n        at org.eclipse.core.launcher.Main.run(Main.java:703)\n        at org.eclipse.core.launcher.Main.main(Main.java:539)\n!ENTRY org.eclipse.core.runtime 4 2 Feb 09, 2003 12:18:57.11\n!MESSAGE Plug-in \"org.eclipse.ui\" was unable to instantiate class\n\"org.eclipse.ui.internal.Workbench\".\n!STACK 0\norg.eclipse.core.internal.boot.DelegatingLoaderException:\norg.eclipse.core.runtime.CoreException: Problems encountered starting up\nplug-in: \"org.eclipse.core.resources\".\n        at\norg.eclipse.core.internal.plugins.PluginDescriptor.internalDoPluginActivation(PluginDescriptor.java:715)\n        at\norg.eclipse.core.internal.plugins.PluginDescriptor.doPluginActivation(PluginDescriptor.java:184)\n        at\norg.eclipse.core.internal.plugins.PluginClassLoader.activatePlugin(PluginClassLoader.java:60)\n        at\norg.eclipse.core.internal.plugins.PluginClassLoader.internalFindClassParentsSelf(PluginClassLoader.java:138)\n        at\norg.eclipse.core.internal.boot.DelegatingURLClassLoader.findClassParentsSelf(DelegatingURLClassLoader.java:473)\n        at\norg.eclipse.core.internal.boot.DelegatingURLClassLoader.loadClass(DelegatingURLClassLoader.java:863)\n        at\norg.eclipse.core.internal.boot.DelegatingURLClassLoader.access$0(DelegatingURLClassLoader.java:857)\n        at\norg.eclipse.core.internal.boot.DelegatingURLClassLoader$DelegateLoader.loadClass(DelegatingURLClassLoader.java:80)\n        at\norg.eclipse.core.internal.boot.DelegatingURLClassLoader.findClassPrerequisites(DelegatingURLClassLoader.java:537)\n        at\norg.eclipse.core.internal.boot.DelegatingURLClassLoader.loadClass(DelegatingURLClassLoader.java:871)\n        at\norg.eclipse.core.internal.boot.DelegatingURLClassLoader.loadClass(DelegatingURLClassLoader.java:843)\n        at java.lang.ClassLoader.loadClass(ClassLoader.java:255)\n        at java.lang.ClassLoader.loadClassInternal(ClassLoader.java:315)\n        at java.lang.Class.getDeclaredConstructors0(Native Method)\n        at java.lang.Class.privateGetDeclaredConstructors(Class.java:1590)\n        at java.lang.Class.getConstructor0(Class.java:1762)\n        at java.lang.Class.newInstance0(Class.java:276)\n        at java.lang.Class.newInstance(Class.java:259)\n        at\norg.eclipse.core.internal.plugins.PluginDescriptor.createExecutableExtension(PluginDescriptor.java:136)\n        at\norg.eclipse.core.internal.plugins.PluginDescriptor.createExecutableExtension(PluginDescriptor.java:165)\n        at\norg.eclipse.core.internal.plugins.ConfigurationElement.createExecutableExtension(ConfigurationElement.java:102)\n        at\norg.eclipse.core.internal.runtime.InternalPlatform.loaderGetRunnable(InternalPlatform.java:461)\n        at sun.reflect.NativeMethodAccessorImpl.invoke0(Native Method)\n        at\nsun.reflect.NativeMethodAccessorImpl.invoke(NativeMethodAccessorImpl.java:39)\n        at\nsun.reflect.DelegatingMethodAccessorImpl.invoke(DelegatingMethodAccessorImpl.java:25)\n        at java.lang.reflect.Method.invoke(Method.java:324)\n        at\norg.eclipse.core.internal.boot.InternalBootLoader.getRunnable(InternalBootLoader.java:457)\n        at\norg.eclipse.core.internal.boot.InternalBootLoader.run(InternalBootLoader.java:827)\n        at org.eclipse.core.boot.BootLoader.run(BootLoader.java:462)\n        at sun.reflect.NativeMethodAccessorImpl.invoke0(Native Method)\n        at\nsun.reflect.NativeMethodAccessorImpl.invoke(NativeMethodAccessorImpl.java:39)\n        at\nsun.reflect.DelegatingMethodAccessorImpl.invoke(DelegatingMethodAccessorImpl.java:25)\n        at java.lang.reflect.Method.invoke(Method.java:324)\n        at org.eclipse.core.launcher.Main.basicRun(Main.java:247)\n        at org.eclipse.core.launcher.Main.run(Main.java:703)\n        at org.eclipse.core.launcher.Main.main(Main.java:539)\n!SESSION ----------------------------------------------------------------------\n!ENTRY org.eclipse.core.launcher 4 0 Feb 09, 2003 12:18:57.100\n!MESSAGE Exception launching the Eclipse Platform:\n!STACK\njava.lang.reflect.InvocationTargetException\n        at sun.reflect.NativeMethodAccessorImpl.invoke0(Native Method)\n        at\nsun.reflect.NativeMethodAccessorImpl.invoke(NativeMethodAccessorImpl.java:39)\n        at\nsun.reflect.DelegatingMethodAccessorImpl.invoke(DelegatingMethodAccessorImpl.java:25)\n        at java.lang.reflect.Method.invoke(Method.java:324)\n        at org.eclipse.core.launcher.Main.basicRun(Main.java:247)\n        at org.eclipse.core.launcher.Main.run(Main.java:703)\n        at org.eclipse.core.launcher.Main.main(Main.java:539)\nCaused by: java.lang.IllegalArgumentException: Application not found:\norg.eclipse.ui.workbench.\n        at\norg.eclipse.core.internal.boot.InternalBootLoader.run(InternalBootLoader.java:829)\n        at org.eclipse.core.boot.BootLoader.run(BootLoader.java:462)\n        ... 7 more\n\nThe file it is complaining about does, in fact and seems fine.  The only around\nthis problem is create a new workspace entirely or delete the metadata directory\nand try to re-import the projects.  Either of these is very inconvenient.  This\nis not the first time I have seen this problem.",
    "Did you crash at some point or are you getting these messages when starting\nafter shutting down cleanly?",
    "\n\n*** This bug has been marked as a duplicate of 12575 ***"
  ],
  "commentCreationDates": [
    "2003-02-09T17:29:58+01:00",
    "2003-02-10T19:06:50+01:00",
    "2003-02-10T19:10:19+01:00"
  ],
  "traces": [
    {
      "exceptionType": "org.eclipse.core.internal.dtree.ObjectNotFoundException",
      "message": "Tree element /wspublisher2/build/url.properties not found.",
      "elements": [
        {
          "method": "org.eclipse.core.internal.dtree.AbstractDataTree.handleNotFound",
          "source": "AbstractDataTree.java:243"
        },
        {
          "method": "org.eclipse.core.internal.dtree.DeltaDataTree.getData",
          "source": "DeltaDataTree.java:611"
        },
        {
          "method": "org.eclipse.core.internal.dtree.DataDeltaNode.asBackwardDelta",
          "source": "DataDeltaNode.java:54"
        },
        {
          "method": "org.eclipse.core.internal.dtree.NoDataDeltaNode.asBackwardDelta",
          "source": "NoDataDeltaNode.java:57"
        },
        {
          "method": "org.eclipse.core.internal.dtree.NoDataDeltaNode.asBackwardDelta",
          "source": "NoDataDeltaNode.java:57"
        },
        {
          "method": "org.eclipse.core.internal.dtree.DataDeltaNode.asBackwardDelta",
          "source": "DataDeltaNode.java:51"
        },
        {
          "method": "org.eclipse.core.internal.dtree.DeltaDataTree.asBackwardDelta",
          "source": "DeltaDataTree.java:96"
        },
        {
          "method": "org.eclipse.core.internal.dtree.DeltaDataTree.reroot",
          "source": "DeltaDataTree.java:818"
        },
        {
          "method": "org.eclipse.core.internal.dtree.DeltaDataTree.reroot",
          "source": "DeltaDataTree.java:817"
        },
        {
          "method": "org.eclipse.core.internal.dtree.DeltaDataTree.reroot",
          "source": "DeltaDataTree.java:817"
        },
        {
          "method": "org.eclipse.core.internal.dtree.DeltaDataTree.reroot",
          "source": "DeltaDataTree.java:817"
        },
        {
          "method": "org.eclipse.core.internal.dtree.DeltaDataTree.reroot",
          "source": "DeltaDataTree.java:817"
        },
        {
          "method": "org.eclipse.core.internal.dtree.DeltaDataTree.reroot",
          "source": "DeltaDataTree.java:817"
        },
        {
          "method": "org.eclipse.core.internal.dtree.DeltaDataTree.reroot",
          "source": "DeltaDataTree.java:817"
        },
        {
          "method": "org.eclipse.core.internal.dtree.DeltaDataTree.reroot",
          "source": "DeltaDataTree.java:817"
        },
        {
          "method": "org.eclipse.core.internal.dtree.DeltaDataTree.reroot",
          "source": "DeltaDataTree.java:817"
        },
        {
          "method": "org.eclipse.core.internal.dtree.DeltaDataTree.reroot",
          "source": "DeltaDataTree.java:793"
        },
        {
          "method": "org.eclipse.core.internal.watson.ElementTree.immutable",
          "source": "ElementTree.java:696"
        },
        {
          "method": "org.eclipse.core.internal.resources.SaveManager.restore",
          "source": "SaveManager.java:485"
        },
        {
          "method": "org.eclipse.core.internal.resources.SaveManager.startup",
          "source": "SaveManager.java:946"
        },
        {
          "method": "org.eclipse.core.internal.resources.Workspace.startup",
          "source": "Workspace.java:1504"
        },
        {
          "method": "org.eclipse.core.internal.resources.Workspace.open",
          "source": "Workspace.java:1296"
        },
        {
          "method": "org.eclipse.core.resources.ResourcesPlugin.startup",
          "source": "ResourcesPlugin.java:201"
        },
        {
          "method": "org.eclipse.core.internal.plugins.PluginDescriptor$1.run",
          "source": "PluginDescriptor.java:697"
        },
        {
          "method": "org.eclipse.core.internal.runtime.InternalPlatform.run",
          "source": "InternalPlatform.java:839"
        },
        {
          "method": "org.eclipse.core.internal.plugins.PluginDescriptor.internalDoPluginActivation",
          "source": "PluginDescriptor.java:709"
        },
        {
          "method": "org.eclipse.core.internal.plugins.PluginDescriptor.doPluginActivation",
          "source": "PluginDescriptor.java:184"
        },
        {
          "method": "org.eclipse.core.internal.plugins.PluginClassLoader.activatePlugin",
          "source": "PluginClassLoader.java:60"
        },
        {
          "method": "org.eclipse.core.internal.plugins.PluginClassLoader.internalFindClassParentsSelf",
          "source": "PluginClassLoader.java:138"
        },
        {
          "method": "org.eclipse.core.internal.boot.DelegatingURLClassLoader.findClassParentsSelf",
          "source": "DelegatingURLClassLoader.java:473"
        },
        {
          "method": "org.eclipse.core.internal.boot.DelegatingURLClassLoader.loadClass",
          "source": "DelegatingURLClassLoader.java:863"
        },
        {
          "method": "org.eclipse.core.internal.boot.DelegatingURLClassLoader.access$0",
          "source": "DelegatingURLClassLoader.java:857"
        },
        {
          "method": "org.eclipse.core.internal.boot.DelegatingURLClassLoader$DelegateLoader.loadClass",
          "source": "DelegatingURLClassLoader.java:80"
        },
        {
          "method": "org.eclipse.core.internal.boot.DelegatingURLClassLoader.findClassPrerequisites",
          "source": "DelegatingURLClassLoader.java:537"
        },
        {
          "method": "org.eclipse.core.internal.boot.DelegatingURLClassLoader.loadClass",
          "source": "DelegatingURLClassLoader.java:871"
        },
        {
          "method": "org.eclipse.core.internal.boot.DelegatingURLClassLoader.loadClass",
          "source": "DelegatingURLClassLoader.java:843"
        },
        {
          "method": "java.lang.ClassLoader.loadClass",
          "source": "ClassLoader.java:255"
        },
        {
          "method": "java.lang.ClassLoader.loadClassInternal",
          "source": "ClassLoader.java:315"
        },
        {
          "method": "java.lang.Class.getDeclaredConstructors0",
          "source": "Native Method"
        },
        {
          "method": "java.lang.Class.privateGetDeclaredConstructors",
          "source": "Class.java:1590"
        },
        {
          "method": "java.lang.Class.getConstructor0",
          "source": "Class.java:1762"
        },
        {
          "method": "java.lang.Class.newInstance0",
          "source": "Class.java:276"
        },
        {
          "method": "java.lang.Class.newInstance",
          "source": "Class.java:259"
        },
        {
          "method": "org.eclipse.core.internal.plugins.PluginDescriptor.createExecutableExtension",
          "source": "PluginDescriptor.java:136"
        },
        {
          "method": "org.eclipse.core.internal.plugins.PluginDescriptor.createExecutableExtension",
          "source": "PluginDescriptor.java:165"
        },
        {
          "method": "org.eclipse.core.internal.plugins.ConfigurationElement.createExecutableExtension",
          "source": "ConfigurationElement.java:102"
        },
        {
          "method": "org.eclipse.core.internal.runtime.InternalPlatform.loaderGetRunnable",
          "source": "InternalPlatform.java:461"
        },
        {
          "method": "sun.reflect.NativeMethodAccessorImpl.invoke0",
          "source": "Native Method"
        },
        {
          "method": "sun.reflect.NativeMethodAccessorImpl.invoke",
          "source": "NativeMethodAccessorImpl.java:39"
        },
        {
          "method": "sun.reflect.DelegatingMethodAccessorImpl.invoke",
          "source": "DelegatingMethodAccessorImpl.java:25"
        },
        {
          "method": "java.lang.reflect.Method.invoke",
          "source": "Method.java:324"
        },
        {
          "method": "org.eclipse.core.internal.boot.InternalBootLoader.getRunnable",
          "source": "InternalBootLoader.java:457"
        },
        {
          "method": "org.eclipse.core.internal.boot.InternalBootLoader.run",
          "source": "InternalBootLoader.java:827"
        },
        {
          "method": "org.eclipse.core.boot.BootLoader.run",
          "source": "BootLoader.java:462"
        },
        {
          "method": "sun.reflect.NativeMethodAccessorImpl.invoke0",
          "source": "Native Method"
        },
        {
          "method": "sun.reflect.NativeMethodAccessorImpl.invoke",
          "source": "NativeMethodAccessorImpl.java:39"
        },
        {
          "method": "sun.reflect.DelegatingMethodAccessorImpl.invoke",
          "source": "DelegatingMethodAccessorImpl.java:25"
        },
        {
          "method": "java.lang.reflect.Method.invoke",
          "source": "Method.java:324"
        },
        {
          "method": "org.eclipse.core.launcher.Main.basicRun",
          "source": "Main.java:247"
        },
        {
          "method": "org.eclipse.core.launcher.Main.run",
          "source": "Main.java:703"
        },
        {
          "method": "org.eclipse.core.launcher.Main.main",
          "source": "Main.java:539"
        }
      ],
      "number": 0,
      "commentIndex": 0,
      "bugId": "31424",
      "duplicateId": "12575",
      "date": "2003-02-09T17:29:58+01:00",
      "product": "Platform",
      "component": "Resources",
      "severity": "blocker"
    },
    {
      "exceptionType": "org.eclipse.core.runtime.CoreException",
      "message": "Problems encountered starting up plug-in: \"org.eclipse.core.resources\".",
      "elements": [
        {
          "method": "org.eclipse.core.internal.plugins.PluginDescriptor.internalDoPluginActivation",
          "source": "PluginDescriptor.java:715"
        },
        {
          "method": "org.eclipse.core.internal.plugins.PluginDescriptor.doPluginActivation",
          "source": "PluginDescriptor.java:184"
        },
        {
          "method": "org.eclipse.core.internal.plugins.PluginClassLoader.activatePlugin",
          "source": "PluginClassLoader.java:60"
        },
        {
          "method": "org.eclipse.core.internal.plugins.PluginClassLoader.internalFindClassParentsSelf",
          "source": "PluginClassLoader.java:138"
        },
        {
          "method": "org.eclipse.core.internal.boot.DelegatingURLClassLoader.findClassParentsSelf",
          "source": "DelegatingURLClassLoader.java:473"
        },
        {
          "method": "org.eclipse.core.internal.boot.DelegatingURLClassLoader.loadClass",
          "source": "DelegatingURLClassLoader.java:863"
        },
        {
          "method": "org.eclipse.core.internal.boot.DelegatingURLClassLoader.access$0",
          "source": "DelegatingURLClassLoader.java:857"
        },
        {
          "method": "org.eclipse.core.internal.boot.DelegatingURLClassLoader$DelegateLoader.loadClass",
          "source": "DelegatingURLClassLoader.java:80"
        },
        {
          "method": "org.eclipse.core.internal.boot.DelegatingURLClassLoader.findClassPrerequisites",
          "source": "DelegatingURLClassLoader.java:537"
        },
        {
          "method": "org.eclipse.core.internal.boot.DelegatingURLClassLoader.loadClass",
          "source": "DelegatingURLClassLoader.java:871"
        },
        {
          "method": "org.eclipse.core.internal.boot.DelegatingURLClassLoader.loadClass",
          "source": "DelegatingURLClassLoader.java:843"
        },
        {
          "method": "java.lang.ClassLoader.loadClass",
          "source": "ClassLoader.java:255"
        },
        {
          "method": "java.lang.ClassLoader.loadClassInternal",
          "source": "ClassLoader.java:315"
        },
        {
          "method": "java.lang.Class.getDeclaredConstructors0",
          "source": "Native Method"
        },
        {
          "method": "java.lang.Class.privateGetDeclaredConstructors",
          "source": "Class.java:1590"
        },
        {
          "method": "java.lang.Class.getConstructor0",
          "source": "Class.java:1762"
        },
        {
          "method": "java.lang.Class.newInstance0",
          "source": "Class.java:276"
        },
        {
          "method": "java.lang.Class.newInstance",
          "source": "Class.java:259"
        },
        {
          "method": "org.eclipse.core.internal.plugins.PluginDescriptor.createExecutableExtension",
          "source": "PluginDescriptor.java:136"
        },
        {
          "method": "org.eclipse.core.internal.plugins.PluginDescriptor.createExecutableExtension",
          "source": "PluginDescriptor.java:165"
        },
        {
          "method": "org.eclipse.core.internal.plugins.ConfigurationElement.createExecutableExtension",
          "source": "ConfigurationElement.java:102"
        },
        {
          "method": "org.eclipse.core.internal.runtime.InternalPlatform.loaderGetRunnable",
          "source": "InternalPlatform.java:461"
        },
        {
          "method": "sun.reflect.NativeMethodAccessorImpl.invoke0",
          "source": "Native Method"
        },
        {
          "method": "sun.reflect.NativeMethodAccessorImpl.invoke",
          "source": "NativeMethodAccessorImpl.java:39"
        },
        {
          "method": "sun.reflect.DelegatingMethodAccessorImpl.invoke",
          "source": "DelegatingMethodAccessorImpl.java:25"
        },
        {
          "method": "java.lang.reflect.Method.invoke",
          "source": "Method.java:324"
        },
        {
          "method": "org.eclipse.core.internal.boot.InternalBootLoader.getRunnable",
          "source": "InternalBootLoader.java:457"
        },
        {
          "method": "org.eclipse.core.internal.boot.InternalBootLoader.run",
          "source": "InternalBootLoader.java:827"
        },
        {
          "method": "org.eclipse.core.boot.BootLoader.run",
          "source": "BootLoader.java:462"
        },
        {
          "method": "sun.reflect.NativeMethodAccessorImpl.invoke0",
          "source": "Native Method"
        },
        {
          "method": "sun.reflect.NativeMethodAccessorImpl.invoke",
          "source": "NativeMethodAccessorImpl.java:39"
        },
        {
          "method": "sun.reflect.DelegatingMethodAccessorImpl.invoke",
          "source": "DelegatingMethodAccessorImpl.java:25"
        },
        {
          "method": "java.lang.reflect.Method.invoke",
          "source": "Method.java:324"
        },
        {
          "method": "org.eclipse.core.launcher.Main.basicRun",
          "source": "Main.java:247"
        },
        {
          "method": "org.eclipse.core.launcher.Main.run",
          "source": "Main.java:703"
        },
        {
          "method": "org.eclipse.core.launcher.Main.main",
          "source": "Main.java:539"
        }
      ],
      "number": 1,
      "commentIndex": 0,
      "bugId": "31424",
      "duplicateId": "12575",
      "date": "2003-02-09T17:29:58+01:00",
      "product": "Platform",
      "component": "Resources",
      "severity": "blocker"
    },
    {
      "exceptionType": "org.eclipse.core.runtime.CoreException",
      "message": "Problems encountered starting up plug-in: \"org.eclipse.core.resources\".",
      "elements": [
        {
          "method": "org.eclipse.core.internal.plugins.PluginDescriptor.internalDoPluginActivation",
          "source": "PluginDescriptor.java:715"
        },
        {
          "method": "org.eclipse.core.internal.plugins.PluginDescriptor.doPluginActivation",
          "source": "PluginDescriptor.java:184"
        },
        {
          "method": "org.eclipse.core.internal.plugins.PluginClassLoader.activatePlugin",
          "source": "PluginClassLoader.java:60"
        },
        {
          "method": "org.eclipse.core.internal.plugins.PluginClassLoader.internalFindClassParentsSelf",
          "source": "PluginClassLoader.java:138"
        },
        {
          "method": "org.eclipse.core.internal.boot.DelegatingURLClassLoader.findClassParentsSelf",
          "source": "DelegatingURLClassLoader.java:473"
        },
        {
          "method": "org.eclipse.core.internal.boot.DelegatingURLClassLoader.loadClass",
          "source": "DelegatingURLClassLoader.java:863"
        },
        {
          "method": "org.eclipse.core.internal.boot.DelegatingURLClassLoader.access$0",
          "source": "DelegatingURLClassLoader.java:857"
        },
        {
          "method": "org.eclipse.core.internal.boot.DelegatingURLClassLoader$DelegateLoader.loadClass",
          "source": "DelegatingURLClassLoader.java:80"
        },
        {
          "method": "org.eclipse.core.internal.boot.DelegatingURLClassLoader.findClassPrerequisites",
          "source": "DelegatingURLClassLoader.java:537"
        },
        {
          "method": "org.eclipse.core.internal.boot.DelegatingURLClassLoader.loadClass",
          "source": "DelegatingURLClassLoader.java:871"
        },
        {
          "method": "org.eclipse.core.internal.boot.DelegatingURLClassLoader.loadClass",
          "source": "DelegatingURLClassLoader.java:843"
        },
        {
          "method": "java.lang.ClassLoader.loadClass",
          "source": "ClassLoader.java:255"
        },
        {
          "method": "java.lang.ClassLoader.loadClassInternal",
          "source": "ClassLoader.java:315"
        },
        {
          "method": "java.lang.Class.getDeclaredConstructors0",
          "source": "Native Method"
        },
        {
          "method": "java.lang.Class.privateGetDeclaredConstructors",
          "source": "Class.java:1590"
        },
        {
          "method": "java.lang.Class.getConstructor0",
          "source": "Class.java:1762"
        },
        {
          "method": "java.lang.Class.newInstance0",
          "source": "Class.java:276"
        },
        {
          "method": "java.lang.Class.newInstance",
          "source": "Class.java:259"
        },
        {
          "method": "org.eclipse.core.internal.plugins.PluginDescriptor.createExecutableExtension",
          "source": "PluginDescriptor.java:136"
        },
        {
          "method": "org.eclipse.core.internal.plugins.PluginDescriptor.createExecutableExtension",
          "source": "PluginDescriptor.java:165"
        },
        {
          "method": "org.eclipse.core.internal.plugins.ConfigurationElement.createExecutableExtension",
          "source": "ConfigurationElement.java:102"
        },
        {
          "method": "org.eclipse.core.internal.runtime.InternalPlatform.loaderGetRunnable",
          "source": "InternalPlatform.java:461"
        },
        {
          "method": "sun.reflect.NativeMethodAccessorImpl.invoke0",
          "source": "Native Method"
        },
        {
          "method": "sun.reflect.NativeMethodAccessorImpl.invoke",
          "source": "NativeMethodAccessorImpl.java:39"
        },
        {
          "method": "sun.reflect.DelegatingMethodAccessorImpl.invoke",
          "source": "DelegatingMethodAccessorImpl.java:25"
        },
        {
          "method": "java.lang.reflect.Method.invoke",
          "source": "Method.java:324"
        },
        {
          "method": "org.eclipse.core.internal.boot.InternalBootLoader.getRunnable",
          "source": "InternalBootLoader.java:457"
        },
        {
          "method": "org.eclipse.core.internal.boot.InternalBootLoader.run",
          "source": "InternalBootLoader.java:827"
        },
        {
          "method": "org.eclipse.core.boot.BootLoader.run",
          "source": "BootLoader.java:462"
        },
        {
          "method": "sun.reflect.NativeMethodAccessorImpl.invoke0",
          "source": "Native Method"
        },
        {
          "method": "sun.reflect.NativeMethodAccessorImpl.invoke",
          "source": "NativeMethodAccessorImpl.java:39"
        },
        {
          "method": "sun.reflect.DelegatingMethodAccessorImpl.invoke",
          "source": "DelegatingMethodAccessorImpl.java:25"
        },
        {
          "method": "java.lang.reflect.Method.invoke",
          "source": "Method.java:324"
        },
        {
          "method": "org.eclipse.core.launcher.Main.basicRun",
          "source": "Main.java:247"
        },
        {
          "method": "org.eclipse.core.launcher.Main.run",
          "source": "Main.java:703"
        },
        {
          "method": "org.eclipse.core.launcher.Main.main",
          "source": "Main.java:539"
        }
      ],
      "number": 2,
      "commentIndex": 0,
      "bugId": "31424",
      "duplicateId": "12575",
      "date": "2003-02-09T17:29:58+01:00",
      "product": "Platform",
      "component": "Resources",
      "severity": "blocker"
    },
    {
      "exceptionType": "java.lang.reflect.InvocationTargetException",
      "elements": [
        {
          "method": "sun.reflect.NativeMethodAccessorImpl.invoke0",
          "source": "Native Method"
        },
        {
          "method": "sun.reflect.NativeMethodAccessorImpl.invoke",
          "source": "NativeMethodAccessorImpl.java:39"
        },
        {
          "method": "sun.reflect.DelegatingMethodAccessorImpl.invoke",
          "source": "DelegatingMethodAccessorImpl.java:25"
        },
        {
          "method": "java.lang.reflect.Method.invoke",
          "source": "Method.java:324"
        },
        {
          "method": "org.eclipse.core.launcher.Main.basicRun",
          "source": "Main.java:247"
        },
        {
          "method": "org.eclipse.core.launcher.Main.run",
          "source": "Main.java:703"
        },
        {
          "method": "org.eclipse.core.launcher.Main.main",
          "source": "Main.java:539"
        }
      ],
      "causedBy": {
        "exceptionType": "java.lang.IllegalArgumentException",
        "message": "Application not found: org.eclipse.ui.workbench.",
        "elements": [
          {
            "method": "org.eclipse.core.internal.boot.InternalBootLoader.run",
            "source": "InternalBootLoader.java:829"
          },
          {
            "method": "org.eclipse.core.boot.BootLoader.run",
            "source": "BootLoader.java:462"
          }
        ],
        "number": 0,
        "commentIndex": 0
      },
      "number": 3,
      "commentIndex": 0,
      "bugId": "31424",
      "duplicateId": "12575",
      "date": "2003-02-09T17:29:58+01:00",
      "product": "Platform",
      "component": "Resources",
      "severity": "blocker"
    }
  ],
  "groupId": "12575",
  "bugId": "31424",
  "duplicateId": "12575",
  "date": "2003-02-09T17:29:58+01:00",
  "product": "Platform",
  "component": "Resources",
  "severity": "blocker"
}