{
  "comments": [
    "!SESSION ---------------------------------------------------------------------- \n!ENTRY org.eclipse.core.launcher 4 0 Feb 10, 2003 09:39:13.920 \n!MESSAGE Exception launching the Eclipse Platform: \n!STACK \njava.lang.reflect.InvocationTargetException \n        at sun.reflect.NativeMethodAccessorImpl.invoke0(Native Method) \n        at sun.reflect.NativeMethodAccessorImpl.invoke(NativeMethodAccessorImpl.java:39) \n        at \nsun.reflect.DelegatingMethodAccessorImpl.invoke(DelegatingMethodAccessorImpl.java:25) \n        at java.lang.reflect.Method.invoke(Method.java:324) \n        at org.eclipse.core.launcher.Main.basicRun(Main.java:247) \n        at org.eclipse.core.launcher.Main.run(Main.java:703) \n        at org.eclipse.core.launcher.Main.main(Main.java:539) \nCaused by: java.lang.RuntimeException: Fatal Error: Unable to locate matching \norg.eclipse.core.runtime plugin. \n        at \norg.eclipse.core.internal.boot.PlatformConfiguration.locateDefaultPlugins(PlatformConfiguration.java:2254) \n        at \norg.eclipse.core.internal.boot.PlatformConfiguration.\u003cinit\u003e(PlatformConfiguration.java:903) \n        at \norg.eclipse.core.internal.boot.PlatformConfiguration.startup(PlatformConfiguration.java:1368) \n        at org.eclipse.core.internal.boot.InternalBootLoader.initialize(InternalBootLoader.java:582) \n        at org.eclipse.core.internal.boot.InternalBootLoader.startup(InternalBootLoader.java:989) \n        at org.eclipse.core.internal.boot.InternalBootLoader.run(InternalBootLoader.java:838) \n        at org.eclipse.core.boot.BootLoader.run(BootLoader.java:462) \n        ... 7 more \n \nEclipse M3 build worked fine for me allong with all the other versions, however this version \ncrashes with the above error.  I am running Mandrake Linux 9.0 with kde 3.1. I have tested it also  \non a mandrake 9 system with kde3.0 . Unfortunately I dont have any other linux versions to test it \non.",
    "\n\n*** This bug has been marked as a duplicate of 31437 ***"
  ],
  "commentCreationDates": [
    "2003-02-10T09:55:11+01:00",
    "2003-02-10T15:22:25+01:00"
  ],
  "traces": [
    {
      "exceptionType": "java.lang.reflect.InvocationTargetException",
      "elements": [
        {
          "method": "sun.reflect.NativeMethodAccessorImpl.invoke0",
          "source": "Native Method"
        },
        {
          "method": "sun.reflect.NativeMethodAccessorImpl.invoke",
          "source": "NativeMethodAccessorImpl.java:39"
        },
        {
          "method": "sun.reflect.DelegatingMethodAccessorImpl.invoke",
          "source": "DelegatingMethodAccessorImpl.java:25"
        },
        {
          "method": "java.lang.reflect.Method.invoke",
          "source": "Method.java:324"
        },
        {
          "method": "org.eclipse.core.launcher.Main.basicRun",
          "source": "Main.java:247"
        },
        {
          "method": "org.eclipse.core.launcher.Main.run",
          "source": "Main.java:703"
        },
        {
          "method": "org.eclipse.core.launcher.Main.main",
          "source": "Main.java:539"
        }
      ],
      "causedBy": {
        "exceptionType": "java.lang.RuntimeException",
        "message": "Fatal Error: Unable to locate matching  org.eclipse.core.runtime plugin.",
        "elements": [
          {
            "method": "org.eclipse.core.internal.boot.PlatformConfiguration.locateDefaultPlugins",
            "source": "PlatformConfiguration.java:2254"
          },
          {
            "method": "org.eclipse.core.internal.boot.PlatformConfiguration.\u003cinit\u003e",
            "source": "PlatformConfiguration.java:903"
          },
          {
            "method": "org.eclipse.core.internal.boot.PlatformConfiguration.startup",
            "source": "PlatformConfiguration.java:1368"
          },
          {
            "method": "org.eclipse.core.internal.boot.InternalBootLoader.initialize",
            "source": "InternalBootLoader.java:582"
          },
          {
            "method": "org.eclipse.core.internal.boot.InternalBootLoader.startup",
            "source": "InternalBootLoader.java:989"
          },
          {
            "method": "org.eclipse.core.internal.boot.InternalBootLoader.run",
            "source": "InternalBootLoader.java:838"
          },
          {
            "method": "org.eclipse.core.boot.BootLoader.run",
            "source": "BootLoader.java:462"
          }
        ],
        "number": 0,
        "commentIndex": 0
      },
      "number": 0,
      "commentIndex": 0,
      "bugId": "31438",
      "duplicateId": "31437",
      "date": "2003-02-10T09:55:11+01:00",
      "product": "Platform",
      "component": "Resources",
      "severity": "blocker"
    }
  ],
  "groupId": "31437",
  "bugId": "31438",
  "duplicateId": "31437",
  "date": "2003-02-10T09:55:11+01:00",
  "product": "Platform",
  "component": "Resources",
  "severity": "blocker"
}