{
  "comments": [
    "Build: I20030211 (1320)\n\nAn error occurred while synchronizing (error in resource visitor code).  As a\nresult, the CVS synchronize operation attempted to open an ErrorDialog. \nHowever, this was happening in a non-UI thread, so it failed to open the dialog.\n Below is the stack trace:\n\norg.eclipse.swt.SWTException: Invalid thread access\n        at org.eclipse.swt.SWT.error(SWT.java:2316)\n        at org.eclipse.swt.SWT.error(SWT.java:2246)\n        at org.eclipse.swt.widgets.Widget.error(Widget.java:359)\n        at org.eclipse.swt.widgets.Shell.\u003cinit\u003e(Shell.java:231)\n        at org.eclipse.swt.widgets.Shell.\u003cinit\u003e(Shell.java:308)\n        at org.eclipse.jface.window.Window.createShell(Window.java:314)\n        at org.eclipse.jface.window.Window.create(Window.java:280)\n        at org.eclipse.jface.window.Window.open(Window.java:530)\n        at org.eclipse.jface.dialogs.ErrorDialog.open(ErrorDialog.java:291)\n        at org.eclipse.jface.dialogs.ErrorDialog.openError(ErrorDialog.java:354)\n        at org.eclipse.jface.dialogs.ErrorDialog.openError(ErrorDialog.java:317)\n        at\norg.eclipse.team.internal.ccvs.ui.CVSUIPlugin$3.open(CVSUIPlugin.java:403)\n        at org.eclipse.team.internal.ccvs.ui.CVSUIPlugin$4.run(CVSUIPlugin.java:452)\n        at\norg.eclipse.team.internal.ccvs.ui.CVSUIPlugin.openDialog(CVSUIPlugin.java:472)\n        at\norg.eclipse.team.internal.ccvs.ui.CVSUIPlugin.openError(CVSUIPlugin.java:407)\n        at\norg.eclipse.team.internal.ccvs.ui.sync.CVSSyncCompareInput.createSyncElements(CVSSyncCompareInput.java:245)\n        at\norg.eclipse.team.internal.ui.sync.SyncCompareInput.prepareInput(SyncCompareInput.java:208)\n        at\norg.eclipse.team.internal.ccvs.ui.sync.CVSSyncCompareInput.access$3(CVSSyncCompareInput.java:1)\n        at\norg.eclipse.team.internal.ccvs.ui.sync.CVSSyncCompareInput$6.run(CVSSyncCompareInput.java:390)\n        at\norg.eclipse.team.internal.ccvs.ui.CVSUIPlugin.runWithRefresh(CVSUIPlugin.java:159)\n        at\norg.eclipse.team.internal.ccvs.ui.sync.CVSSyncCompareInput$5.run(CVSSyncCompareInput.java:388)\n        at org.eclipse.team.internal.ccvs.core.client.Session.run(Session.java:167)\n        at\norg.eclipse.team.internal.ccvs.ui.sync.CVSSyncCompareInput.prepareInput(CVSSyncCompareInput.java:385)\n        at org.eclipse.compare.CompareEditorInput.run(CompareEditorInput.java:310)\n        at\norg.eclipse.jface.operation.ModalContext$ModalContextThread.run(ModalContext.java:95)",
    "This code no longer invokes UI (due to an independant refactoring)"
  ],
  "commentCreationDates": [
    "2003-02-13T19:42:53+01:00",
    "2003-03-24T20:33:48+01:00"
  ],
  "traces": [
    {
      "exceptionType": "org.eclipse.swt.SWTException",
      "message": "Invalid thread access",
      "elements": [
        {
          "method": "org.eclipse.swt.SWT.error",
          "source": "SWT.java:2316"
        },
        {
          "method": "org.eclipse.swt.SWT.error",
          "source": "SWT.java:2246"
        },
        {
          "method": "org.eclipse.swt.widgets.Widget.error",
          "source": "Widget.java:359"
        },
        {
          "method": "org.eclipse.swt.widgets.Shell.\u003cinit\u003e",
          "source": "Shell.java:231"
        },
        {
          "method": "org.eclipse.swt.widgets.Shell.\u003cinit\u003e",
          "source": "Shell.java:308"
        },
        {
          "method": "org.eclipse.jface.window.Window.createShell",
          "source": "Window.java:314"
        },
        {
          "method": "org.eclipse.jface.window.Window.create",
          "source": "Window.java:280"
        },
        {
          "method": "org.eclipse.jface.window.Window.open",
          "source": "Window.java:530"
        },
        {
          "method": "org.eclipse.jface.dialogs.ErrorDialog.open",
          "source": "ErrorDialog.java:291"
        },
        {
          "method": "org.eclipse.jface.dialogs.ErrorDialog.openError",
          "source": "ErrorDialog.java:354"
        },
        {
          "method": "org.eclipse.jface.dialogs.ErrorDialog.openError",
          "source": "ErrorDialog.java:317"
        },
        {
          "method": "org.eclipse.team.internal.ccvs.ui.CVSUIPlugin$3.open",
          "source": "CVSUIPlugin.java:403"
        },
        {
          "method": "org.eclipse.team.internal.ccvs.ui.CVSUIPlugin$4.run",
          "source": "CVSUIPlugin.java:452"
        },
        {
          "method": "org.eclipse.team.internal.ccvs.ui.CVSUIPlugin.openDialog",
          "source": "CVSUIPlugin.java:472"
        },
        {
          "method": "org.eclipse.team.internal.ccvs.ui.CVSUIPlugin.openError",
          "source": "CVSUIPlugin.java:407"
        },
        {
          "method": "org.eclipse.team.internal.ccvs.ui.sync.CVSSyncCompareInput.createSyncElements",
          "source": "CVSSyncCompareInput.java:245"
        },
        {
          "method": "org.eclipse.team.internal.ui.sync.SyncCompareInput.prepareInput",
          "source": "SyncCompareInput.java:208"
        },
        {
          "method": "org.eclipse.team.internal.ccvs.ui.sync.CVSSyncCompareInput.access$3",
          "source": "CVSSyncCompareInput.java:1"
        },
        {
          "method": "org.eclipse.team.internal.ccvs.ui.sync.CVSSyncCompareInput$6.run",
          "source": "CVSSyncCompareInput.java:390"
        },
        {
          "method": "org.eclipse.team.internal.ccvs.ui.CVSUIPlugin.runWithRefresh",
          "source": "CVSUIPlugin.java:159"
        },
        {
          "method": "org.eclipse.team.internal.ccvs.ui.sync.CVSSyncCompareInput$5.run",
          "source": "CVSSyncCompareInput.java:388"
        },
        {
          "method": "org.eclipse.team.internal.ccvs.core.client.Session.run",
          "source": "Session.java:167"
        },
        {
          "method": "org.eclipse.team.internal.ccvs.ui.sync.CVSSyncCompareInput.prepareInput",
          "source": "CVSSyncCompareInput.java:385"
        },
        {
          "method": "org.eclipse.compare.CompareEditorInput.run",
          "source": "CompareEditorInput.java:310"
        },
        {
          "method": "org.eclipse.jface.operation.ModalContext$ModalContextThread.run",
          "source": "ModalContext.java:95"
        }
      ],
      "number": 0,
      "commentIndex": 0,
      "bugId": "31810",
      "date": "2003-02-13T19:42:53+01:00",
      "product": "Platform",
      "component": "Team",
      "severity": "normal"
    }
  ],
  "groupId": "31810",
  "bugId": "31810",
  "date": "2003-02-13T19:42:53+01:00",
  "product": "Platform",
  "component": "Team",
  "severity": "normal"
}