{
  "comments": [
    "Build 20030214\n\nSearching for type reference to \u0027Throwable\u0027 in jdt.core with in case \ninsensitive mode throws the following NPE:\n\nCaused by: java.lang.NullPointerException\n        at \norg.eclipse.jdt.internal.compiler.lookup.SourceTypeBinding.resolveTypeFor\n(SourceTypeBinding.java:763)\n        at org.eclipse.jdt.internal.compiler.lookup.SourceTypeBinding.getField\n(SourceTypeBinding.java:491)\n        at org.eclipse.jdt.internal.compiler.lookup.Scope.findField\n(Scope.java:196)\n        at org.eclipse.jdt.internal.compiler.lookup.MethodScope.findField\n(MethodScope.java:331)\n        at org.eclipse.jdt.internal.compiler.lookup.BlockScope.getBinding\n(BlockScope.java:445)\n        at \norg.eclipse.jdt.internal.compiler.ast.QualifiedNameReference.resolveType\n(QualifiedNameReference.java:720)\n        at org.eclipse.jdt.internal.compiler.ast.ExplicitConstructorCall.resolve\n(ExplicitConstructorCall.java:245)\n        at \norg.eclipse.jdt.internal.compiler.ast.ConstructorDeclaration.resolveStatements\n(ConstructorDeclaration.java:392)\n        at \norg.eclipse.jdt.internal.compiler.ast.AbstractMethodDeclaration.resolve\n(AbstractMethodDeclaration.java:309)\n        at org.eclipse.jdt.internal.compiler.ast.TypeDeclaration.resolve\n(TypeDeclaration.java:789)\n        at org.eclipse.jdt.internal.compiler.ast.TypeDeclaration.resolve\n(TypeDeclaration.java:830)\n        at \norg.eclipse.jdt.internal.compiler.ast.CompilationUnitDeclaration.resolve\n(CompilationUnitDeclaration.java:259)\n        at org.eclipse.jdt.internal.core.search.matching.MatchLocator2.process\n(MatchLocator2.java:950)\n        at \norg.eclipse.jdt.internal.core.search.matching.MatchLocator2.locateMatches\n(MatchLocator2.java:663)\n        at \norg.eclipse.jdt.internal.core.search.matching.MatchLocator2.locateMatches\n(MatchLocator2.java:835)\n        at org.eclipse.jdt.core.search.SearchEngine.search\n(SearchEngine.java:470)\n        at org.eclipse.jdt.internal.ui.search.JavaSearchOperation.execute\n(JavaSearchOperation.java:86)\n        at org.eclipse.ui.actions.WorkspaceModifyOperation$1.run\n(WorkspaceModifyOperation.java:65)\n        at org.eclipse.core.internal.resources.Workspace.run\n(Workspace.java:1588)\n        at org.eclipse.ui.actions.WorkspaceModifyOperation.run\n(WorkspaceModifyOperation.java:79)\n        at org.eclipse.jface.operation.ModalContext$ModalContextThread.run\n(ModalContext.java:95)",
    "Did it work with MatchLocator (1) ?",
    "Yes, it used to work with MatchLocator (1)",
    "It is failing because the cu being processed needs to be resolved (because of a \nsingle name reference which is a potential match), but it needs a cu that was \ninitialy in the queue but that didn\u0027t need resolve.\n\nNow marking type reference pattern and field reference pattern as always \nneeding resolve.\n\nAdded regression test JavaSearchTests.testTypeReference3()",
    "Verified."
  ],
  "commentCreationDates": [
    "2003-02-17T10:18:19+01:00",
    "2003-02-17T10:52:26+01:00",
    "2003-02-17T11:56:18+01:00",
    "2003-02-17T16:15:33+01:00",
    "2003-02-25T11:29:24+01:00"
  ],
  "traces": [
    {
      "exceptionType": "java.lang.NullPointerException",
      "elements": [
        {
          "method": "org.eclipse.jdt.internal.compiler.lookup.SourceTypeBinding.resolveTypeFor",
          "source": "SourceTypeBinding.java:763"
        },
        {
          "method": "org.eclipse.jdt.internal.compiler.lookup.SourceTypeBinding.getField",
          "source": "SourceTypeBinding.java:491"
        },
        {
          "method": "org.eclipse.jdt.internal.compiler.lookup.Scope.findField",
          "source": "Scope.java:196"
        },
        {
          "method": "org.eclipse.jdt.internal.compiler.lookup.MethodScope.findField",
          "source": "MethodScope.java:331"
        },
        {
          "method": "org.eclipse.jdt.internal.compiler.lookup.BlockScope.getBinding",
          "source": "BlockScope.java:445"
        },
        {
          "method": "org.eclipse.jdt.internal.compiler.ast.QualifiedNameReference.resolveType",
          "source": "QualifiedNameReference.java:720"
        },
        {
          "method": "org.eclipse.jdt.internal.compiler.ast.ExplicitConstructorCall.resolve",
          "source": "ExplicitConstructorCall.java:245"
        },
        {
          "method": "org.eclipse.jdt.internal.compiler.ast.ConstructorDeclaration.resolveStatements",
          "source": "ConstructorDeclaration.java:392"
        },
        {
          "method": "org.eclipse.jdt.internal.compiler.ast.AbstractMethodDeclaration.resolve",
          "source": "AbstractMethodDeclaration.java:309"
        },
        {
          "method": "org.eclipse.jdt.internal.compiler.ast.TypeDeclaration.resolve",
          "source": "TypeDeclaration.java:789"
        },
        {
          "method": "org.eclipse.jdt.internal.compiler.ast.TypeDeclaration.resolve",
          "source": "TypeDeclaration.java:830"
        },
        {
          "method": "org.eclipse.jdt.internal.compiler.ast.CompilationUnitDeclaration.resolve",
          "source": "CompilationUnitDeclaration.java:259"
        },
        {
          "method": "org.eclipse.jdt.internal.core.search.matching.MatchLocator2.process",
          "source": "MatchLocator2.java:950"
        },
        {
          "method": "org.eclipse.jdt.internal.core.search.matching.MatchLocator2.locateMatches",
          "source": "MatchLocator2.java:663"
        },
        {
          "method": "org.eclipse.jdt.internal.core.search.matching.MatchLocator2.locateMatches",
          "source": "MatchLocator2.java:835"
        },
        {
          "method": "org.eclipse.jdt.core.search.SearchEngine.search",
          "source": "SearchEngine.java:470"
        },
        {
          "method": "org.eclipse.jdt.internal.ui.search.JavaSearchOperation.execute",
          "source": "JavaSearchOperation.java:86"
        },
        {
          "method": "org.eclipse.ui.actions.WorkspaceModifyOperation$1.run",
          "source": "WorkspaceModifyOperation.java:65"
        },
        {
          "method": "org.eclipse.core.internal.resources.Workspace.run",
          "source": "Workspace.java:1588"
        },
        {
          "method": "org.eclipse.ui.actions.WorkspaceModifyOperation.run",
          "source": "WorkspaceModifyOperation.java:79"
        },
        {
          "method": "org.eclipse.jface.operation.ModalContext$ModalContextThread.run",
          "source": "ModalContext.java:95"
        }
      ],
      "number": 0,
      "commentIndex": 0,
      "bugId": "31985",
      "date": "2003-02-17T10:18:19+01:00",
      "product": "JDT",
      "component": "Core",
      "severity": "normal"
    }
  ],
  "groupId": "31985",
  "bugId": "31985",
  "date": "2003-02-17T10:18:19+01:00",
  "product": "JDT",
  "component": "Core",
  "severity": "normal"
}