{
  "comments": [
    "Build 20030218\n\nIn a self-hosted workspace, I imported all source plugins, had some editors \nopened on jdt.core sources (which I did not refresh in the process). Then I \ndecided to override org.apache.ant and org.eclipse.tomcat with their binary \nforms. All open editors did close all the sudden, and following stack trace got \ndumped to the .log.\n\n!ENTRY org.eclipse.core.resources 4 2 Feb 19, 2003 12:52:54.83\n!MESSAGE Problems occurred when invoking code from plug-\nin: \"org.eclipse.core.resources\".\n!STACK 0\njava.lang.NullPointerException\n        at \norg.eclipse.jdt.internal.ui.javaeditor.CompilationUnitDocumentProvider$Compilati\nonUnitAnnotationModel.update(CompilationUnitDocumentProvider.java:390)\n        at \norg.eclipse.ui.texteditor.ResourceMarkerAnnotationModel$ResourceDeltaVisitor.vis\nit(ResourceMarkerAnnotationModel.java:68)\n        at org.eclipse.core.internal.events.ResourceDelta.accept\n(ResourceDelta.java:71)\n        at org.eclipse.core.internal.events.ResourceDelta.accept\n(ResourceDelta.java:79)\n        at org.eclipse.core.internal.events.ResourceDelta.accept\n(ResourceDelta.java:79)\n        at org.eclipse.core.internal.events.ResourceDelta.accept\n(ResourceDelta.java:79)\n        at org.eclipse.core.internal.events.ResourceDelta.accept\n(ResourceDelta.java:79)\n        at org.eclipse.core.internal.events.ResourceDelta.accept\n(ResourceDelta.java:79)\n        at org.eclipse.core.internal.events.ResourceDelta.accept\n(ResourceDelta.java:79)\n        at org.eclipse.core.internal.events.ResourceDelta.accept\n(ResourceDelta.java:79)\n        at org.eclipse.core.internal.events.ResourceDelta.accept\n(ResourceDelta.java:52)\n        at \norg.eclipse.ui.texteditor.ResourceMarkerAnnotationModel$ResourceChangeListener.r\nesourceChanged(ResourceMarkerAnnotationModel.java:52)\n        at org.eclipse.core.internal.events.NotificationManager$1.run\n(NotificationManager.java:137)\n        at org.eclipse.core.internal.runtime.InternalPlatform.run\n(InternalPlatform.java:867)\n        at org.eclipse.core.runtime.Platform.run(Platform.java:413)\n        at org.eclipse.core.internal.events.NotificationManager.notify\n(NotificationManager.java:152)\n        at org.eclipse.core.internal.events.NotificationManager.broadcastChanges\n(NotificationManager.java:67)\n        at org.eclipse.core.internal.resources.Workspace.broadcastChanges\n(Workspace.java:161)\n        at org.eclipse.core.internal.resources.Workspace.endOperation\n(Workspace.java:892)\n        at org.eclipse.core.internal.resources.Workspace.run\n(Workspace.java:1593)\n        at org.eclipse.pde.internal.ui.wizards.imports.PluginImportWizard$2.run\n(PluginImportWizard.java:179)\n        at org.eclipse.jface.operation.ModalContext$ModalContextThread.run\n(ModalContext.java:95)",
    "Available in builds \u003e N20030219",
    "*** Bug 32307 has been marked as a duplicate of this bug. ***"
  ],
  "commentCreationDates": [
    "2003-02-19T11:56:01+01:00",
    "2003-02-20T08:48:15+01:00",
    "2003-02-20T16:08:33+01:00"
  ],
  "traces": [
    {
      "exceptionType": "java.lang.NullPointerException",
      "elements": [
        {
          "method": "org.eclipse.jdt.internal.ui.javaeditor.CompilationUnitDocumentProvider$CompilationUnitAnnotationModel.update",
          "source": "CompilationUnitDocumentProvider.java:390"
        },
        {
          "method": "org.eclipse.ui.texteditor.ResourceMarkerAnnotationModel$ResourceDeltaVisitor.visit",
          "source": "ResourceMarkerAnnotationModel.java:68"
        },
        {
          "method": "org.eclipse.core.internal.events.ResourceDelta.accept",
          "source": "ResourceDelta.java:71"
        },
        {
          "method": "org.eclipse.core.internal.events.ResourceDelta.accept",
          "source": "ResourceDelta.java:79"
        },
        {
          "method": "org.eclipse.core.internal.events.ResourceDelta.accept",
          "source": "ResourceDelta.java:79"
        },
        {
          "method": "org.eclipse.core.internal.events.ResourceDelta.accept",
          "source": "ResourceDelta.java:79"
        },
        {
          "method": "org.eclipse.core.internal.events.ResourceDelta.accept",
          "source": "ResourceDelta.java:79"
        },
        {
          "method": "org.eclipse.core.internal.events.ResourceDelta.accept",
          "source": "ResourceDelta.java:79"
        },
        {
          "method": "org.eclipse.core.internal.events.ResourceDelta.accept",
          "source": "ResourceDelta.java:79"
        },
        {
          "method": "org.eclipse.core.internal.events.ResourceDelta.accept",
          "source": "ResourceDelta.java:79"
        },
        {
          "method": "org.eclipse.core.internal.events.ResourceDelta.accept",
          "source": "ResourceDelta.java:52"
        },
        {
          "method": "org.eclipse.ui.texteditor.ResourceMarkerAnnotationModel$ResourceChangeListener.resourceChanged",
          "source": "ResourceMarkerAnnotationModel.java:52"
        },
        {
          "method": "org.eclipse.core.internal.events.NotificationManager$1.run",
          "source": "NotificationManager.java:137"
        },
        {
          "method": "org.eclipse.core.internal.runtime.InternalPlatform.run",
          "source": "InternalPlatform.java:867"
        },
        {
          "method": "org.eclipse.core.runtime.Platform.run",
          "source": "Platform.java:413"
        },
        {
          "method": "org.eclipse.core.internal.events.NotificationManager.notify",
          "source": "NotificationManager.java:152"
        },
        {
          "method": "org.eclipse.core.internal.events.NotificationManager.broadcastChanges",
          "source": "NotificationManager.java:67"
        },
        {
          "method": "org.eclipse.core.internal.resources.Workspace.broadcastChanges",
          "source": "Workspace.java:161"
        },
        {
          "method": "org.eclipse.core.internal.resources.Workspace.endOperation",
          "source": "Workspace.java:892"
        },
        {
          "method": "org.eclipse.core.internal.resources.Workspace.run",
          "source": "Workspace.java:1593"
        },
        {
          "method": "org.eclipse.pde.internal.ui.wizards.imports.PluginImportWizard$2.run",
          "source": "PluginImportWizard.java:179"
        },
        {
          "method": "org.eclipse.jface.operation.ModalContext$ModalContextThread.run",
          "source": "ModalContext.java:95"
        }
      ],
      "number": 0,
      "commentIndex": 0,
      "bugId": "32223",
      "date": "2003-02-19T11:56:01+01:00",
      "product": "JDT",
      "component": "Text",
      "severity": "normal"
    }
  ],
  "groupId": "32223",
  "bugId": "32223",
  "date": "2003-02-19T11:56:01+01:00",
  "product": "JDT",
  "component": "Text",
  "severity": "normal"
}