{
  "comments": [
    "Build id: 200302141436\n\nI get these kind of exceptions in my log now and then. Is this a bug? I looks \nlike jdi exception that are handled and are not bugs. Should they be printed \nto the log?\n\nPS: It seems strange to have a class called com.sun.* in a org.eclipse.* \nplugin.\n\n!ENTRY org.eclipse.jdt.debug.ui 4 150 Feb 17, 2003 14:35:47.936\n!MESSAGE Internal Error\n!STACK 1\norg.eclipse.debug.core.DebugException[5010]: \ncom.sun.jdi.ObjectCollectedException\n        at org.eclipse.jdi.internal.MirrorImpl.defaultReplyErrorHandler\n(MirrorImpl.java:234)\n        at org.eclipse.jdi.internal.ThreadReferenceImpl.name\n(ThreadReferenceImpl.java:269)\n        at org.eclipse.jdt.internal.debug.core.model.JDIThread.getName\n(JDIThread.java:908)\n        at org.eclipse.jdt.internal.debug.ui.JDIModelPresentation.getThreadText\n(JDIModelPresentation.java:293)\n        at org.eclipse.jdt.internal.debug.ui.JDIModelPresentation.getText\n(JDIModelPresentation.java:219)\n        at org.eclipse.debug.internal.ui.LazyModelPresentation.getText\n(LazyModelPresentation.java:68)\n        at org.eclipse.debug.internal.ui.DelegatingModelPresentation.getText\n(DelegatingModelPresentation.java:121)\n        at org.eclipse.jface.viewers.TreeViewer.doUpdateItem\n(TreeViewer.java:96)\n        at \norg.eclipse.jface.viewers.AbstractTreeViewer$UpdateItemSafeRunnable.run\n(AbstractTreeViewer.java:85)\n        at org.eclipse.core.internal.runtime.InternalPlatform.run\n(InternalPlatform.java:867)\n        at org.eclipse.core.runtime.Platform.run(Platform.java:413)\n        at org.eclipse.jface.viewers.AbstractTreeViewer.doUpdateItem\n(AbstractTreeViewer.java:397)\n        at \norg.eclipse.jface.viewers.StructuredViewer$UpdateItemSafeRunnable.run\n(StructuredViewer.java:119)\n        at org.eclipse.core.internal.runtime.InternalPlatform.run\n(InternalPlatform.java:867)\n        at org.eclipse.core.runtime.Platform.run(Platform.java:413)\n        at org.eclipse.jface.viewers.StructuredViewer.updateItem\n(StructuredViewer.java:1266)\n        at org.eclipse.jface.viewers.AbstractTreeViewer.createTreeItem\n(AbstractTreeViewer.java:299)\n        at org.eclipse.jface.viewers.AbstractTreeViewer.add\n(AbstractTreeViewer.java:170)\n        at org.eclipse.jface.viewers.AbstractTreeViewer.add\n(AbstractTreeViewer.java:203)\n        at org.eclipse.debug.internal.ui.views.AbstractDebugEventHandler.insert\n(AbstractDebugEventHandler.java:99)\n        at \norg.eclipse.debug.internal.ui.views.launch.LaunchViewEventHandler.doHandleDebug\nEvents(LaunchViewEventHand\n        at org.eclipse.debug.internal.ui.views.AbstractDebugEventHandler$1.run\n(AbstractDebugEventHandler.java:65)\n        at org.eclipse.swt.widgets.RunnableLock.run(RunnableLock.java:31)\n        at org.eclipse.swt.widgets.Synchronizer.runAsyncMessages\n(Synchronizer.java:94)\n        at org.eclipse.swt.widgets.Display.runAsyncMessages(Display.java:1669)\n        at org.eclipse.swt.widgets.Display.readAndDispatch(Display.java:1414)\n        at org.eclipse.ui.internal.Workbench.runEventLoop(Workbench.java:1288)\n        at org.eclipse.ui.internal.Workbench.run(Workbench.java:1271)\n        at org.eclipse.core.internal.boot.InternalBootLoader.run\n(InternalBootLoader.java:845)\n        at org.eclipse.core.boot.BootLoader.run(BootLoader.java:461)\n        at java.lang.reflect.Method.invoke(Native Method)\n        at org.eclipse.core.launcher.Main.basicRun(Main.java:247)\n        at org.eclipse.core.launcher.Main.run(Main.java:703)\n        at org.eclipse.core.launcher.Main.main(Main.java:539)\n!ENTRY org.eclipse.jdt.debug 4 5010 Feb 17, 2003 14:35:47.936\n!MESSAGE com.sun.jdi.ObjectCollectedException occurred retrieving thread name.\n!STACK 0\ncom.sun.jdi.ObjectCollectedException\n        at org.eclipse.jdi.internal.MirrorImpl.defaultReplyErrorHandler\n(MirrorImpl.java:234)\n        at org.eclipse.jdi.internal.ThreadReferenceImpl.name\n(ThreadReferenceImpl.java:269)\n        at org.eclipse.jdt.internal.debug.core.model.JDIThread.getName\n(JDIThread.java:908)\n        at org.eclipse.jdt.internal.debug.ui.JDIModelPresentation.getThreadText\n(JDIModelPresentation.java:293)\n        at org.eclipse.jdt.internal.debug.ui.JDIModelPresentation.getText\n(JDIModelPresentation.java:219)\n        at org.eclipse.debug.internal.ui.LazyModelPresentation.getText\n(LazyModelPresentation.java:68)\n        at org.eclipse.debug.internal.ui.DelegatingModelPresentation.getText\n(DelegatingModelPresentation.java:121)\n        at org.eclipse.jface.viewers.TreeViewer.doUpdateItem\n(TreeViewer.java:96)\n        at \norg.eclipse.jface.viewers.AbstractTreeViewer$UpdateItemSafeRunnable.run\n(AbstractTreeViewer.java:85)\n        at org.eclipse.core.internal.runtime.InternalPlatform.run\n(InternalPlatform.java:867)\n        at org.eclipse.core.runtime.Platform.run(Platform.java:413)\n        at org.eclipse.jface.viewers.AbstractTreeViewer.doUpdateItem\n(AbstractTreeViewer.java:397)\n        at \norg.eclipse.jface.viewers.StructuredViewer$UpdateItemSafeRunnable.run\n(StructuredViewer.java:119)\n        at org.eclipse.core.internal.runtime.InternalPlatform.run\n(InternalPlatform.java:867)\n        at org.eclipse.core.runtime.Platform.run(Platform.java:413)\n        at org.eclipse.jface.viewers.StructuredViewer.updateItem\n(StructuredViewer.java:1266)\n        at org.eclipse.jface.viewers.AbstractTreeViewer.createTreeItem\n(AbstractTreeViewer.java:299)\n        at org.eclipse.jface.viewers.AbstractTreeViewer.add\n(AbstractTreeViewer.java:170)\n        at org.eclipse.jface.viewers.AbstractTreeViewer.add\n(AbstractTreeViewer.java:203)\n        at org.eclipse.debug.internal.ui.views.AbstractDebugEventHandler.insert\n(AbstractDebugEventHandler.java:99)\n        at \norg.eclipse.debug.internal.ui.views.launch.LaunchViewEventHandler.doHandleDebug\nEvents(LaunchViewEventHand\n        at org.eclipse.debug.internal.ui.views.AbstractDebugEventHandler$1.run\n(AbstractDebugEventHandler.java:65)\n        at org.eclipse.swt.widgets.RunnableLock.run(RunnableLock.java:31)\n        at org.eclipse.swt.widgets.Synchronizer.runAsyncMessages\n(Synchronizer.java:94)\n        at org.eclipse.swt.widgets.Display.runAsyncMessages(Display.java:1669)\n        at org.eclipse.swt.widgets.Display.readAndDispatch(Display.java:1414)\n        at org.eclipse.ui.internal.Workbench.runEventLoop(Workbench.java:1288)\n        at org.eclipse.ui.internal.Workbench.run(Workbench.java:1271)\n        at org.eclipse.core.internal.boot.InternalBootLoader.run\n(InternalBootLoader.java:845)\n        at org.eclipse.core.boot.BootLoader.run(BootLoader.java:461)\n        at java.lang.reflect.Method.invoke(Native Method)\n        at org.eclipse.core.launcher.Main.basicRun(Main.java:247)\n        at org.eclipse.core.launcher.Main.run(Main.java:703)\n        at org.eclipse.core.launcher.Main.main(Main.java:539)\n!ENTRY org.eclipse.jdt.debug.ui 4 150 Feb 17, 2003 15:31:19.00\n!MESSAGE Internal Error\n!STACK 1\norg.eclipse.debug.core.DebugException[5010]: \ncom.sun.jdi.ObjectCollectedException\n        at org.eclipse.jdi.internal.MirrorImpl.defaultReplyErrorHandler\n(MirrorImpl.java:234)\n        at org.eclipse.jdi.internal.ThreadReferenceImpl.name\n(ThreadReferenceImpl.java:269)\n        at org.eclipse.jdt.internal.debug.core.model.JDIThread.getName\n(JDIThread.java:908)\n        at org.eclipse.jdt.internal.debug.ui.JDIModelPresentation.getThreadText\n(JDIModelPresentation.java:293)\n        at org.eclipse.jdt.internal.debug.ui.JDIModelPresentation.getText\n(JDIModelPresentation.java:219)\n        at org.eclipse.debug.internal.ui.LazyModelPresentation.getText\n(LazyModelPresentation.java:68)\n        at org.eclipse.debug.internal.ui.DelegatingModelPresentation.getText\n(DelegatingModelPresentation.java:121)\n        at org.eclipse.jface.viewers.TreeViewer.doUpdateItem\n(TreeViewer.java:96)\n        at \norg.eclipse.jface.viewers.AbstractTreeViewer$UpdateItemSafeRunnable.run\n(AbstractTreeViewer.java:85)\n        at org.eclipse.core.internal.runtime.InternalPlatform.run\n(InternalPlatform.java:867)\n        at org.eclipse.core.runtime.Platform.run(Platform.java:413)\n        at org.eclipse.jface.viewers.AbstractTreeViewer.doUpdateItem\n(AbstractTreeViewer.java:397)\n        at \norg.eclipse.jface.viewers.StructuredViewer$UpdateItemSafeRunnable.run\n(StructuredViewer.java:119)\n        at org.eclipse.core.internal.runtime.InternalPlatform.run\n(InternalPlatform.java:867)\n        at org.eclipse.core.runtime.Platform.run(Platform.java:413)\n        at org.eclipse.jface.viewers.StructuredViewer.updateItem\n(StructuredViewer.java:1266)\n        at org.eclipse.jface.viewers.AbstractTreeViewer.createTreeItem\n(AbstractTreeViewer.java:299)\n        at org.eclipse.jface.viewers.AbstractTreeViewer.add\n(AbstractTreeViewer.java:170)\n        at org.eclipse.jface.viewers.AbstractTreeViewer.add\n(AbstractTreeViewer.java:203)\n        at org.eclipse.debug.internal.ui.views.AbstractDebugEventHandler.insert\n(AbstractDebugEventHandler.java:99)\n        at \norg.eclipse.debug.internal.ui.views.launch.LaunchViewEventHandler.doHandleDebug\nEvents(LaunchViewEventHand\n        at org.eclipse.debug.internal.ui.views.AbstractDebugEventHandler$1.run\n(AbstractDebugEventHandler.java:65)\n        at org.eclipse.swt.widgets.RunnableLock.run(RunnableLock.java:31)\n        at org.eclipse.swt.widgets.Synchronizer.runAsyncMessages\n(Synchronizer.java:94)\n        at org.eclipse.swt.widgets.Display.runAsyncMessages(Display.java:1669)\n        at org.eclipse.swt.widgets.Display.readAndDispatch(Display.java:1414)\n        at org.eclipse.ui.internal.Workbench.runEventLoop(Workbench.java:1288)\n        at org.eclipse.ui.internal.Workbench.run(Workbench.java:1271)\n        at org.eclipse.core.internal.boot.InternalBootLoader.run\n(InternalBootLoader.java:845)\n        at org.eclipse.core.boot.BootLoader.run(BootLoader.java:461)\n        at java.lang.reflect.Method.invoke(Native Method)\n        at org.eclipse.core.launcher.Main.basicRun(Main.java:247)\n        at org.eclipse.core.launcher.Main.run(Main.java:703)\n        at org.eclipse.core.launcher.Main.main(Main.java:539)\n!ENTRY org.eclipse.jdt.debug 4 5010 Feb 17, 2003 15:31:19.00\n!MESSAGE com.sun.jdi.ObjectCollectedException occurred retrieving thread name.\n!STACK 0\ncom.sun.jdi.ObjectCollectedException\n        at org.eclipse.jdi.internal.MirrorImpl.defaultReplyErrorHandler\n(MirrorImpl.java:234)\n        at org.eclipse.jdi.internal.ThreadReferenceImpl.name\n(ThreadReferenceImpl.java:269)\n        at org.eclipse.jdt.internal.debug.core.model.JDIThread.getName\n(JDIThread.java:908)\n        at org.eclipse.jdt.internal.debug.ui.JDIModelPresentation.getThreadText\n(JDIModelPresentation.java:293)\n        at org.eclipse.jdt.internal.debug.ui.JDIModelPresentation.getText\n(JDIModelPresentation.java:219)\n        at org.eclipse.debug.internal.ui.LazyModelPresentation.getText\n(LazyModelPresentation.java:68)\n        at org.eclipse.debug.internal.ui.DelegatingModelPresentation.getText\n(DelegatingModelPresentation.java:121)\n        at org.eclipse.jface.viewers.TreeViewer.doUpdateItem\n(TreeViewer.java:96)\n        at \norg.eclipse.jface.viewers.AbstractTreeViewer$UpdateItemSafeRunnable.run\n(AbstractTreeViewer.java:85)\n        at org.eclipse.core.internal.runtime.InternalPlatform.run\n(InternalPlatform.java:867)\n        at org.eclipse.core.runtime.Platform.run(Platform.java:413)\n        at org.eclipse.jface.viewers.AbstractTreeViewer.doUpdateItem\n(AbstractTreeViewer.java:397)\n        at \norg.eclipse.jface.viewers.StructuredViewer$UpdateItemSafeRunnable.run\n(StructuredViewer.java:119)\n        at org.eclipse.core.internal.runtime.InternalPlatform.run\n(InternalPlatform.java:867)\n        at org.eclipse.core.runtime.Platform.run(Platform.java:413)\n        at org.eclipse.jface.viewers.StructuredViewer.updateItem\n(StructuredViewer.java:1266)\n        at org.eclipse.jface.viewers.AbstractTreeViewer.createTreeItem\n(AbstractTreeViewer.java:299)\n        at org.eclipse.jface.viewers.AbstractTreeViewer.add\n(AbstractTreeViewer.java:170)\n        at org.eclipse.jface.viewers.AbstractTreeViewer.add\n(AbstractTreeViewer.java:203)\n        at org.eclipse.debug.internal.ui.views.AbstractDebugEventHandler.insert\n(AbstractDebugEventHandler.java:99)\n        at \norg.eclipse.debug.internal.ui.views.launch.LaunchViewEventHandler.doHandleDebug\nEvents(LaunchViewEventHand\n        at org.eclipse.debug.internal.ui.views.AbstractDebugEventHandler$1.run\n(AbstractDebugEventHandler.java:65)\n        at org.eclipse.swt.widgets.RunnableLock.run(RunnableLock.java:31)\n        at org.eclipse.swt.widgets.Synchronizer.runAsyncMessages\n(Synchronizer.java:94)\n        at org.eclipse.swt.widgets.Display.runAsyncMessages(Display.java:1669)\n        at org.eclipse.swt.widgets.Display.readAndDispatch(Display.java:1414)\n        at org.eclipse.ui.internal.Workbench.runEventLoop(Workbench.java:1288)\n        at org.eclipse.ui.internal.Workbench.run(Workbench.java:1271)\n        at org.eclipse.core.internal.boot.InternalBootLoader.run\n(InternalBootLoader.java:845)\n        at org.eclipse.core.boot.BootLoader.run(BootLoader.java:461)\n        at java.lang.reflect.Method.invoke(Native Method)\n        at org.eclipse.core.launcher.Main.basicRun(Main.java:247)\n        at org.eclipse.core.launcher.Main.run(Main.java:703)\n        at org.eclipse.core.launcher.Main.main(Main.java:539)\n!ENTRY org.eclipse.pde.ui 4 0 Feb 19, 2003 15:01:34.557\n!MESSAGE Problems detected while importing plug-ins",
    "\n\n*** This bug has been marked as a duplicate of 32407 ***"
  ],
  "commentCreationDates": [
    "2003-02-20T21:20:13+01:00",
    "2003-02-20T21:26:38+01:00"
  ],
  "traces": [
    {
      "exceptionType": "com.sun.jdi.ObjectCollectedException",
      "elements": [
        {
          "method": "org.eclipse.jdi.internal.MirrorImpl.defaultReplyErrorHandler",
          "source": "MirrorImpl.java:234"
        },
        {
          "method": "org.eclipse.jdi.internal.ThreadReferenceImpl.name",
          "source": "ThreadReferenceImpl.java:269"
        },
        {
          "method": "org.eclipse.jdt.internal.debug.core.model.JDIThread.getName",
          "source": "JDIThread.java:908"
        },
        {
          "method": "org.eclipse.jdt.internal.debug.ui.JDIModelPresentation.getThreadText",
          "source": "JDIModelPresentation.java:293"
        },
        {
          "method": "org.eclipse.jdt.internal.debug.ui.JDIModelPresentation.getText",
          "source": "JDIModelPresentation.java:219"
        },
        {
          "method": "org.eclipse.debug.internal.ui.LazyModelPresentation.getText",
          "source": "LazyModelPresentation.java:68"
        },
        {
          "method": "org.eclipse.debug.internal.ui.DelegatingModelPresentation.getText",
          "source": "DelegatingModelPresentation.java:121"
        },
        {
          "method": "org.eclipse.jface.viewers.TreeViewer.doUpdateItem",
          "source": "TreeViewer.java:96"
        },
        {
          "method": "org.eclipse.jface.viewers.AbstractTreeViewer$UpdateItemSafeRunnable.run",
          "source": "AbstractTreeViewer.java:85"
        },
        {
          "method": "org.eclipse.core.internal.runtime.InternalPlatform.run",
          "source": "InternalPlatform.java:867"
        },
        {
          "method": "org.eclipse.core.runtime.Platform.run",
          "source": "Platform.java:413"
        },
        {
          "method": "org.eclipse.jface.viewers.AbstractTreeViewer.doUpdateItem",
          "source": "AbstractTreeViewer.java:397"
        },
        {
          "method": "org.eclipse.jface.viewers.StructuredViewer$UpdateItemSafeRunnable.run",
          "source": "StructuredViewer.java:119"
        },
        {
          "method": "org.eclipse.core.internal.runtime.InternalPlatform.run",
          "source": "InternalPlatform.java:867"
        },
        {
          "method": "org.eclipse.core.runtime.Platform.run",
          "source": "Platform.java:413"
        },
        {
          "method": "org.eclipse.jface.viewers.StructuredViewer.updateItem",
          "source": "StructuredViewer.java:1266"
        },
        {
          "method": "org.eclipse.jface.viewers.AbstractTreeViewer.createTreeItem",
          "source": "AbstractTreeViewer.java:299"
        },
        {
          "method": "org.eclipse.jface.viewers.AbstractTreeViewer.add",
          "source": "AbstractTreeViewer.java:170"
        },
        {
          "method": "org.eclipse.jface.viewers.AbstractTreeViewer.add",
          "source": "AbstractTreeViewer.java:203"
        },
        {
          "method": "org.eclipse.debug.internal.ui.views.AbstractDebugEventHandler.insert",
          "source": "AbstractDebugEventHandler.java:99"
        }
      ],
      "number": 0,
      "commentIndex": 0,
      "bugId": "32410",
      "duplicateId": "32407",
      "date": "2003-02-20T21:20:13+01:00",
      "product": "Platform",
      "component": "Debug",
      "severity": "normal"
    },
    {
      "exceptionType": "com.sun.jdi.ObjectCollectedException",
      "elements": [
        {
          "method": "org.eclipse.jdi.internal.MirrorImpl.defaultReplyErrorHandler",
          "source": "MirrorImpl.java:234"
        },
        {
          "method": "org.eclipse.jdi.internal.ThreadReferenceImpl.name",
          "source": "ThreadReferenceImpl.java:269"
        },
        {
          "method": "org.eclipse.jdt.internal.debug.core.model.JDIThread.getName",
          "source": "JDIThread.java:908"
        },
        {
          "method": "org.eclipse.jdt.internal.debug.ui.JDIModelPresentation.getThreadText",
          "source": "JDIModelPresentation.java:293"
        },
        {
          "method": "org.eclipse.jdt.internal.debug.ui.JDIModelPresentation.getText",
          "source": "JDIModelPresentation.java:219"
        },
        {
          "method": "org.eclipse.debug.internal.ui.LazyModelPresentation.getText",
          "source": "LazyModelPresentation.java:68"
        },
        {
          "method": "org.eclipse.debug.internal.ui.DelegatingModelPresentation.getText",
          "source": "DelegatingModelPresentation.java:121"
        },
        {
          "method": "org.eclipse.jface.viewers.TreeViewer.doUpdateItem",
          "source": "TreeViewer.java:96"
        },
        {
          "method": "org.eclipse.jface.viewers.AbstractTreeViewer$UpdateItemSafeRunnable.run",
          "source": "AbstractTreeViewer.java:85"
        },
        {
          "method": "org.eclipse.core.internal.runtime.InternalPlatform.run",
          "source": "InternalPlatform.java:867"
        },
        {
          "method": "org.eclipse.core.runtime.Platform.run",
          "source": "Platform.java:413"
        },
        {
          "method": "org.eclipse.jface.viewers.AbstractTreeViewer.doUpdateItem",
          "source": "AbstractTreeViewer.java:397"
        },
        {
          "method": "org.eclipse.jface.viewers.StructuredViewer$UpdateItemSafeRunnable.run",
          "source": "StructuredViewer.java:119"
        },
        {
          "method": "org.eclipse.core.internal.runtime.InternalPlatform.run",
          "source": "InternalPlatform.java:867"
        },
        {
          "method": "org.eclipse.core.runtime.Platform.run",
          "source": "Platform.java:413"
        },
        {
          "method": "org.eclipse.jface.viewers.StructuredViewer.updateItem",
          "source": "StructuredViewer.java:1266"
        },
        {
          "method": "org.eclipse.jface.viewers.AbstractTreeViewer.createTreeItem",
          "source": "AbstractTreeViewer.java:299"
        },
        {
          "method": "org.eclipse.jface.viewers.AbstractTreeViewer.add",
          "source": "AbstractTreeViewer.java:170"
        },
        {
          "method": "org.eclipse.jface.viewers.AbstractTreeViewer.add",
          "source": "AbstractTreeViewer.java:203"
        },
        {
          "method": "org.eclipse.debug.internal.ui.views.AbstractDebugEventHandler.insert",
          "source": "AbstractDebugEventHandler.java:99"
        }
      ],
      "number": 1,
      "commentIndex": 0,
      "bugId": "32410",
      "duplicateId": "32407",
      "date": "2003-02-20T21:20:13+01:00",
      "product": "Platform",
      "component": "Debug",
      "severity": "normal"
    },
    {
      "exceptionType": "com.sun.jdi.ObjectCollectedException",
      "elements": [
        {
          "method": "org.eclipse.jdi.internal.MirrorImpl.defaultReplyErrorHandler",
          "source": "MirrorImpl.java:234"
        },
        {
          "method": "org.eclipse.jdi.internal.ThreadReferenceImpl.name",
          "source": "ThreadReferenceImpl.java:269"
        },
        {
          "method": "org.eclipse.jdt.internal.debug.core.model.JDIThread.getName",
          "source": "JDIThread.java:908"
        },
        {
          "method": "org.eclipse.jdt.internal.debug.ui.JDIModelPresentation.getThreadText",
          "source": "JDIModelPresentation.java:293"
        },
        {
          "method": "org.eclipse.jdt.internal.debug.ui.JDIModelPresentation.getText",
          "source": "JDIModelPresentation.java:219"
        },
        {
          "method": "org.eclipse.debug.internal.ui.LazyModelPresentation.getText",
          "source": "LazyModelPresentation.java:68"
        },
        {
          "method": "org.eclipse.debug.internal.ui.DelegatingModelPresentation.getText",
          "source": "DelegatingModelPresentation.java:121"
        },
        {
          "method": "org.eclipse.jface.viewers.TreeViewer.doUpdateItem",
          "source": "TreeViewer.java:96"
        },
        {
          "method": "org.eclipse.jface.viewers.AbstractTreeViewer$UpdateItemSafeRunnable.run",
          "source": "AbstractTreeViewer.java:85"
        },
        {
          "method": "org.eclipse.core.internal.runtime.InternalPlatform.run",
          "source": "InternalPlatform.java:867"
        },
        {
          "method": "org.eclipse.core.runtime.Platform.run",
          "source": "Platform.java:413"
        },
        {
          "method": "org.eclipse.jface.viewers.AbstractTreeViewer.doUpdateItem",
          "source": "AbstractTreeViewer.java:397"
        },
        {
          "method": "org.eclipse.jface.viewers.StructuredViewer$UpdateItemSafeRunnable.run",
          "source": "StructuredViewer.java:119"
        },
        {
          "method": "org.eclipse.core.internal.runtime.InternalPlatform.run",
          "source": "InternalPlatform.java:867"
        },
        {
          "method": "org.eclipse.core.runtime.Platform.run",
          "source": "Platform.java:413"
        },
        {
          "method": "org.eclipse.jface.viewers.StructuredViewer.updateItem",
          "source": "StructuredViewer.java:1266"
        },
        {
          "method": "org.eclipse.jface.viewers.AbstractTreeViewer.createTreeItem",
          "source": "AbstractTreeViewer.java:299"
        },
        {
          "method": "org.eclipse.jface.viewers.AbstractTreeViewer.add",
          "source": "AbstractTreeViewer.java:170"
        },
        {
          "method": "org.eclipse.jface.viewers.AbstractTreeViewer.add",
          "source": "AbstractTreeViewer.java:203"
        },
        {
          "method": "org.eclipse.debug.internal.ui.views.AbstractDebugEventHandler.insert",
          "source": "AbstractDebugEventHandler.java:99"
        }
      ],
      "number": 2,
      "commentIndex": 0,
      "bugId": "32410",
      "duplicateId": "32407",
      "date": "2003-02-20T21:20:13+01:00",
      "product": "Platform",
      "component": "Debug",
      "severity": "normal"
    },
    {
      "exceptionType": "com.sun.jdi.ObjectCollectedException",
      "elements": [
        {
          "method": "org.eclipse.jdi.internal.MirrorImpl.defaultReplyErrorHandler",
          "source": "MirrorImpl.java:234"
        },
        {
          "method": "org.eclipse.jdi.internal.ThreadReferenceImpl.name",
          "source": "ThreadReferenceImpl.java:269"
        },
        {
          "method": "org.eclipse.jdt.internal.debug.core.model.JDIThread.getName",
          "source": "JDIThread.java:908"
        },
        {
          "method": "org.eclipse.jdt.internal.debug.ui.JDIModelPresentation.getThreadText",
          "source": "JDIModelPresentation.java:293"
        },
        {
          "method": "org.eclipse.jdt.internal.debug.ui.JDIModelPresentation.getText",
          "source": "JDIModelPresentation.java:219"
        },
        {
          "method": "org.eclipse.debug.internal.ui.LazyModelPresentation.getText",
          "source": "LazyModelPresentation.java:68"
        },
        {
          "method": "org.eclipse.debug.internal.ui.DelegatingModelPresentation.getText",
          "source": "DelegatingModelPresentation.java:121"
        },
        {
          "method": "org.eclipse.jface.viewers.TreeViewer.doUpdateItem",
          "source": "TreeViewer.java:96"
        },
        {
          "method": "org.eclipse.jface.viewers.AbstractTreeViewer$UpdateItemSafeRunnable.run",
          "source": "AbstractTreeViewer.java:85"
        },
        {
          "method": "org.eclipse.core.internal.runtime.InternalPlatform.run",
          "source": "InternalPlatform.java:867"
        },
        {
          "method": "org.eclipse.core.runtime.Platform.run",
          "source": "Platform.java:413"
        },
        {
          "method": "org.eclipse.jface.viewers.AbstractTreeViewer.doUpdateItem",
          "source": "AbstractTreeViewer.java:397"
        },
        {
          "method": "org.eclipse.jface.viewers.StructuredViewer$UpdateItemSafeRunnable.run",
          "source": "StructuredViewer.java:119"
        },
        {
          "method": "org.eclipse.core.internal.runtime.InternalPlatform.run",
          "source": "InternalPlatform.java:867"
        },
        {
          "method": "org.eclipse.core.runtime.Platform.run",
          "source": "Platform.java:413"
        },
        {
          "method": "org.eclipse.jface.viewers.StructuredViewer.updateItem",
          "source": "StructuredViewer.java:1266"
        },
        {
          "method": "org.eclipse.jface.viewers.AbstractTreeViewer.createTreeItem",
          "source": "AbstractTreeViewer.java:299"
        },
        {
          "method": "org.eclipse.jface.viewers.AbstractTreeViewer.add",
          "source": "AbstractTreeViewer.java:170"
        },
        {
          "method": "org.eclipse.jface.viewers.AbstractTreeViewer.add",
          "source": "AbstractTreeViewer.java:203"
        },
        {
          "method": "org.eclipse.debug.internal.ui.views.AbstractDebugEventHandler.insert",
          "source": "AbstractDebugEventHandler.java:99"
        }
      ],
      "number": 3,
      "commentIndex": 0,
      "bugId": "32410",
      "duplicateId": "32407",
      "date": "2003-02-20T21:20:13+01:00",
      "product": "Platform",
      "component": "Debug",
      "severity": "normal"
    }
  ],
  "groupId": "30758",
  "bugId": "32410",
  "duplicateId": "32407",
  "date": "2003-02-20T21:20:13+01:00",
  "product": "Platform",
  "component": "Debug",
  "severity": "normal"
}