{
  "comments": [
    "I ran the FileViewer example on my Macintosh, clicked around for a while, then\nexited. I do not believe it was still filling in the list of items in the\ncurrent folder when I quit, but it might have been. The following walkback was\ndisplayed in the console:\n\norg.eclipse.swt.SWTException: Device is disposed\n\tat org.eclipse.swt.SWT.error(SWT.java:2316)\n\tat org.eclipse.swt.SWT.error(SWT.java:2246)\n\tat org.eclipse.swt.widgets.Display.error(Display.java:474)\n\tat org.eclipse.swt.widgets.Display.wake(Display.java:1641)\n\tat org.eclipse.swt.examples.fileviewer.FileViewer$1.run(FileViewer.java:1502)\n\tat java.lang.Thread.run(Thread.java:554)"
  ],
  "commentCreationDates": [
    "2003-02-24T15:21:30+01:00"
  ],
  "traces": [
    {
      "exceptionType": "org.eclipse.swt.SWTException",
      "message": "Device is disposed",
      "elements": [
        {
          "method": "org.eclipse.swt.SWT.error",
          "source": "SWT.java:2316"
        },
        {
          "method": "org.eclipse.swt.SWT.error",
          "source": "SWT.java:2246"
        },
        {
          "method": "org.eclipse.swt.widgets.Display.error",
          "source": "Display.java:474"
        },
        {
          "method": "org.eclipse.swt.widgets.Display.wake",
          "source": "Display.java:1641"
        },
        {
          "method": "org.eclipse.swt.examples.fileviewer.FileViewer$1.run",
          "source": "FileViewer.java:1502"
        },
        {
          "method": "java.lang.Thread.run",
          "source": "Thread.java:554"
        }
      ],
      "number": 0,
      "commentIndex": 0,
      "bugId": "32672",
      "date": "2003-02-24T15:21:30+01:00",
      "product": "Platform",
      "component": "SWT",
      "severity": "minor"
    }
  ],
  "groupId": "32672",
  "bugId": "32672",
  "date": "2003-02-24T15:21:30+01:00",
  "product": "Platform",
  "component": "SWT",
  "severity": "minor"
}