{
  "comments": [
    "Using RC1...\nI am using a home grown CMVC task which is performing an extract.  With RC1, I \nam now getting a Widget is disposed whenever I run that task against any file.\nThe entire stack looks like:\n\norg.eclipse.swt.SWTException: Widget is disposed\n        at org.eclipse.swt.SWT.error(SWT.java:2316)\n        at org.eclipse.swt.SWT.error(SWT.java(Inlined Compiled Code))\n        at org.eclipse.swt.widgets.Widget.error(Widget.java(Inlined Compiled \nCode))\n        at org.eclipse.swt.widgets.Control.getDisplay(Control.java(Compiled \nCode))\n        at org.eclipse.swt.widgets.Widget.isValidThread(Widget.java(Inlined \nCompiled Code))\n        at org.eclipse.swt.widgets.Widget.checkWidget(Widget.java(Compiled \nCode))\n        at org.eclipse.swt.widgets.Control.setEnabled(Control.java:1888)\n        at \norg.eclipse.jface.dialogs.ProgressMonitorDialog.setOperationCancelButtonEnabled\n(ProgressMonitorDialog.java:377)\n        at org.eclipse.jface.dialogs.ProgressMonitorDialog.access$5\n(ProgressMonitorDialog.java:375)\n        at org.eclipse.jface.dialogs.ProgressMonitorDialog$1.run\n(ProgressMonitorDialog.java:225)\n        at org.eclipse.swt.widgets.RunnableLock.run(RunnableLock.java(Inlined \nCompiled Code))\n        at org.eclipse.swt.widgets.Synchronizer.runAsyncMessages\n(Synchronizer.java(Compiled Code))\n        at org.eclipse.swt.widgets.Display.runAsyncMessages(Display.java\n(Inlined Compiled Code))\n        at org.eclipse.swt.widgets.Display.readAndDispatch(Display.java\n(Compiled Code))\n        at org.eclipse.ui.internal.Workbench.runEventLoop(Workbench.java\n(Compiled Code))\n        at org.eclipse.ui.internal.Workbench.run(Workbench.java:1254)\n        at org.eclipse.core.internal.boot.InternalBootLoader.run\n(InternalBootLoader.java:845)\n        at org.eclipse.core.boot.BootLoader.run(BootLoader.java:461)\n        at java.lang.reflect.Method.invoke(Native Method)\n        at org.eclipse.core.launcher.Main.basicRun(Main.java:247)\n        at org.eclipse.core.launcher.Main.run(Main.java:703)\n        at org.eclipse.core.launcher.Main.main(Main.java:539)",
    "You are trying to enable a widget that has been dispsoed.  The exception is \nvalid in this case.\n\nPlease check your code to see why you are referencing a disposed widget.  This \nis not a defect in SWT."
  ],
  "commentCreationDates": [
    "2003-02-24T19:48:06+01:00",
    "2003-02-25T15:17:19+01:00"
  ],
  "traces": [
    {
      "exceptionType": "org.eclipse.swt.SWTException",
      "message": "Widget is disposed",
      "elements": [
        {
          "method": "org.eclipse.swt.SWT.error",
          "source": "SWT.java:2316"
        },
        {
          "method": "org.eclipse.swt.SWT.error",
          "source": "SWT.java(Inlined Compiled Code)"
        },
        {
          "method": "org.eclipse.swt.widgets.Widget.error",
          "source": "Widget.java(Inlined Compiled  Code)"
        },
        {
          "method": "org.eclipse.swt.widgets.Control.getDisplay",
          "source": "Control.java(Compiled  Code)"
        },
        {
          "method": "org.eclipse.swt.widgets.Widget.isValidThread",
          "source": "Widget.java(Inlined  Compiled Code)"
        },
        {
          "method": "org.eclipse.swt.widgets.Widget.checkWidget",
          "source": "Widget.java(Compiled  Code)"
        },
        {
          "method": "org.eclipse.swt.widgets.Control.setEnabled",
          "source": "Control.java:1888"
        },
        {
          "method": "org.eclipse.jface.dialogs.ProgressMonitorDialog.setOperationCancelButtonEnabled",
          "source": "ProgressMonitorDialog.java:377"
        },
        {
          "method": "org.eclipse.jface.dialogs.ProgressMonitorDialog.access$5",
          "source": "ProgressMonitorDialog.java:375"
        },
        {
          "method": "org.eclipse.jface.dialogs.ProgressMonitorDialog$1.run",
          "source": "ProgressMonitorDialog.java:225"
        },
        {
          "method": "org.eclipse.swt.widgets.RunnableLock.run",
          "source": "RunnableLock.java(Inlined  Compiled Code)"
        },
        {
          "method": "org.eclipse.swt.widgets.Synchronizer.runAsyncMessages",
          "source": "Synchronizer.java(Compiled Code)"
        },
        {
          "method": "org.eclipse.swt.widgets.Display.runAsyncMessages",
          "source": "Display.java (Inlined Compiled Code)"
        },
        {
          "method": "org.eclipse.swt.widgets.Display.readAndDispatch",
          "source": "Display.java (Compiled Code)"
        },
        {
          "method": "org.eclipse.ui.internal.Workbench.runEventLoop",
          "source": "Workbench.java (Compiled Code)"
        },
        {
          "method": "org.eclipse.ui.internal.Workbench.run",
          "source": "Workbench.java:1254"
        },
        {
          "method": "org.eclipse.core.internal.boot.InternalBootLoader.run",
          "source": "InternalBootLoader.java:845"
        },
        {
          "method": "org.eclipse.core.boot.BootLoader.run",
          "source": "BootLoader.java:461"
        },
        {
          "method": "java.lang.reflect.Method.invoke",
          "source": "Native Method"
        },
        {
          "method": "org.eclipse.core.launcher.Main.basicRun",
          "source": "Main.java:247"
        },
        {
          "method": "org.eclipse.core.launcher.Main.run",
          "source": "Main.java:703"
        },
        {
          "method": "org.eclipse.core.launcher.Main.main",
          "source": "Main.java:539"
        }
      ],
      "number": 0,
      "commentIndex": 0,
      "bugId": "32774",
      "date": "2003-02-24T19:48:06+01:00",
      "product": "Platform",
      "component": "SWT",
      "severity": "normal"
    }
  ],
  "groupId": "32774",
  "bugId": "32774",
  "date": "2003-02-24T19:48:06+01:00",
  "product": "Platform",
  "component": "SWT",
  "severity": "normal"
}