{
  "comments": [
    "Found following trace in .log\n\n!ENTRY org.eclipse.jdt.debug 4 120 Feb 24, 2003 11:41:50.830\n!MESSAGE Internal error logged from JDI Debug: \n!STACK 0\njava.lang.ClassCastException: org.eclipse.jdi.internal.request.BreakpointRequestImpl\n        at \norg.eclipse.jdt.internal.debug.core.breakpoints.JavaMethodBreakpoint.setRequestThrea\ndFilter(JavaMethodBreakpoint.java:297)\n        at \norg.eclipse.jdt.internal.debug.core.breakpoints.JavaBreakpoint.configureRequestThread\nFilter(JavaBreakpoint.java:390)\n        at \norg.eclipse.jdt.internal.debug.core.breakpoints.JavaBreakpoint.configureRequest(JavaB\nreakpoint.java:366)\n        at \norg.eclipse.jdt.internal.debug.core.breakpoints.JavaMethodBreakpoint.createMethodRe\nquest(JavaMethodBreakpoint.java:278)\n        at \norg.eclipse.jdt.internal.debug.core.breakpoints.JavaMethodBreakpoint.createMethodEntr\nyRequest(JavaMethodBreakpoint.java:214)\n        at \norg.eclipse.jdt.internal.debug.core.breakpoints.JavaMethodBreakpoint.createRequest(Ja\nvaMethodBreakpoint.java:636)\n        at \norg.eclipse.jdt.internal.debug.core.breakpoints.JavaBreakpoint.createRequests(JavaBre\nakpoint.java:476)\n        at \norg.eclipse.jdt.internal.debug.core.breakpoints.JavaBreakpoint.recreate(JavaBreakpoint.\njava:1070)\n        at \norg.eclipse.jdt.internal.debug.core.breakpoints.JavaBreakpoint.setThreadFilter(JavaBrea\nkpoint.java:890)\n        at \norg.eclipse.jdt.internal.debug.ui.actions.ThreadFilterViewer.doStore(ThreadFilterViewer.j\nava:175)\n        at org.eclipse.jface.preference.FieldEditor.store(FieldEditor.java:580)\n        at \norg.eclipse.jface.preference.FieldEditorPreferencePage.performOk(FieldEditorPreferenc\nePage.java:308)\n        at \norg.eclipse.jdt.internal.debug.ui.actions.JavaBreakpointPropertiesDialog.okPressed(Jav\naBreakpointPropertiesDialog.java:153)\n        at org.eclipse.jface.dialogs.Dialog.buttonPressed(Dialog.java:250)\n        at org.eclipse.jface.dialogs.Dialog$1.widgetSelected(Dialog.java:417)\n        at org.eclipse.swt.widgets.TypedListener.handleEvent(TypedListener.java:87)\n        at org.eclipse.swt.widgets.EventTable.sendEvent(EventTable.java:77)\n        at org.eclipse.swt.widgets.Widget.notifyListeners(Widget.java:695)\n        at org.eclipse.swt.widgets.Display.runDeferredEvents(Display.java:1293)\n        at org.eclipse.swt.widgets.Display.readAndDispatch(Display.java:1046)\n        at org.eclipse.jface.window.Window.runEventLoop(Window.java:577)\n        at org.eclipse.jface.window.Window.open(Window.java:557)\n        at \norg.eclipse.jdt.internal.debug.ui.actions.JavaBreakpointPropertiesAction.run(JavaBreakp\nointPropertiesAction.java:31)\n        at org.eclipse.ui.internal.PluginAction.runWithEvent(PluginAction.java:250)\n        at \norg.eclipse.jface.action.ActionContributionItem.handleWidgetSelection(ActionContributio\nnItem.java:456)\n        at \norg.eclipse.jface.action.ActionContributionItem.handleWidgetEvent(ActionContributionIte\nm.java:403)\n        at \norg.eclipse.jface.action.ActionContributionItem.access$0(ActionContributionItem.java:39\n7)\n        at \norg.eclipse.jface.action.ActionContributionItem$ActionListener.handleEvent(ActionContri\nbutionItem.java:72)\n        at org.eclipse.swt.widgets.EventTable.sendEvent(EventTable.java:77)\n        at org.eclipse.swt.widgets.Widget.notifyListeners(Widget.java:695)\n        at org.eclipse.swt.widgets.Display.runDeferredEvents(Display.java:1293)\n        at org.eclipse.swt.widgets.Display.readAndDispatch(Display.java:1046)\n        at org.eclipse.ui.internal.Workbench.runEventLoop(Workbench.java:1271)\n        at org.eclipse.ui.internal.Workbench.run(Workbench.java:1254)\n        at \norg.eclipse.core.internal.boot.InternalBootLoader.run(InternalBootLoader.java:845)\n        at org.eclipse.core.boot.BootLoader.run(BootLoader.java:461)\n        at java.lang.reflect.Method.invoke(Native Method)\n        at org.eclipse.core.launcher.Main.basicRun(Main.java:247)\n        at org.eclipse.core.launcher.Main.run(Main.java:703)\n        at org.eclipse.core.launcher.Main.main(Main.java:539)\n        at java.lang.reflect.Method.invoke(Native Method)\n        at com.apple.buckyball.app.LaunchRunner.run(LaunchRunner.java:82)\n        at com.apple.buckyball.app.LaunchRunner.callMain(LaunchRunner.java:44)\n        at com.apple.buckyball.app.CarbonLibApp.launch(CarbonLibApp.java:67)",
    "A method breakpoint can have a line breakpoint request in the case that its \nsignature can be resolved exactly (which is more efficient than using a method \nentry request). This looks like a problem on all platforms.",
    "*** Bug 32723 has been marked as a duplicate of this bug. ***",
    "Fixed in JavaMethodBreakpoint.",
    "Please verify, Joe (S).",
    "Added two JUnit tests to MethodBreakpointTests\n\n* testThreadFilterInclusive\n* testThreadFilterExclusive",
    "Verified code.\n"
  ],
  "commentCreationDates": [
    "2003-02-24T22:39:05+01:00",
    "2003-02-26T20:47:22+01:00",
    "2003-02-26T20:48:48+01:00",
    "2003-02-27T21:26:09+01:00",
    "2003-02-27T21:26:25+01:00",
    "2003-02-27T21:52:03+01:00",
    "2003-03-03T22:42:01+01:00"
  ],
  "traces": [
    {
      "exceptionType": "java.lang.ClassCastException",
      "message": "org.eclipse.jdi.internal.request.BreakpointRequestImpl",
      "elements": [
        {
          "method": "org.eclipse.jdt.internal.debug.core.breakpoints.JavaMethodBreakpoint.setRequestThreadFilter",
          "source": "JavaMethodBreakpoint.java:297"
        },
        {
          "method": "org.eclipse.jdt.internal.debug.core.breakpoints.JavaBreakpoint.configureRequestThreadFilter",
          "source": "JavaBreakpoint.java:390"
        },
        {
          "method": "org.eclipse.jdt.internal.debug.core.breakpoints.JavaBreakpoint.configureRequest",
          "source": "JavaB reakpoint.java:366"
        },
        {
          "method": "org.eclipse.jdt.internal.debug.core.breakpoints.JavaMethodBreakpoint.createMethodRequest",
          "source": "JavaMethodBreakpoint.java:278"
        },
        {
          "method": "org.eclipse.jdt.internal.debug.core.breakpoints.JavaMethodBreakpoint.createMethodEntryRequest",
          "source": "JavaMethodBreakpoint.java:214"
        },
        {
          "method": "org.eclipse.jdt.internal.debug.core.breakpoints.JavaMethodBreakpoint.createRequest",
          "source": "Ja vaMethodBreakpoint.java:636"
        },
        {
          "method": "org.eclipse.jdt.internal.debug.core.breakpoints.JavaBreakpoint.createRequests",
          "source": "JavaBre akpoint.java:476"
        },
        {
          "method": "org.eclipse.jdt.internal.debug.core.breakpoints.JavaBreakpoint.recreate",
          "source": "JavaBreakpoint. java:1070"
        },
        {
          "method": "org.eclipse.jdt.internal.debug.core.breakpoints.JavaBreakpoint.setThreadFilter",
          "source": "JavaBrea kpoint.java:890"
        },
        {
          "method": "org.eclipse.jdt.internal.debug.ui.actions.ThreadFilterViewer.doStore",
          "source": "ThreadFilterViewer.j ava:175"
        },
        {
          "method": "org.eclipse.jface.preference.FieldEditor.store",
          "source": "FieldEditor.java:580"
        },
        {
          "method": "org.eclipse.jface.preference.FieldEditorPreferencePage.performOk",
          "source": "FieldEditorPreferenc ePage.java:308"
        },
        {
          "method": "org.eclipse.jdt.internal.debug.ui.actions.JavaBreakpointPropertiesDialog.okPressed",
          "source": "Jav aBreakpointPropertiesDialog.java:153"
        },
        {
          "method": "org.eclipse.jface.dialogs.Dialog.buttonPressed",
          "source": "Dialog.java:250"
        },
        {
          "method": "org.eclipse.jface.dialogs.Dialog$1.widgetSelected",
          "source": "Dialog.java:417"
        },
        {
          "method": "org.eclipse.swt.widgets.TypedListener.handleEvent",
          "source": "TypedListener.java:87"
        },
        {
          "method": "org.eclipse.swt.widgets.EventTable.sendEvent",
          "source": "EventTable.java:77"
        },
        {
          "method": "org.eclipse.swt.widgets.Widget.notifyListeners",
          "source": "Widget.java:695"
        },
        {
          "method": "org.eclipse.swt.widgets.Display.runDeferredEvents",
          "source": "Display.java:1293"
        },
        {
          "method": "org.eclipse.swt.widgets.Display.readAndDispatch",
          "source": "Display.java:1046"
        },
        {
          "method": "org.eclipse.jface.window.Window.runEventLoop",
          "source": "Window.java:577"
        },
        {
          "method": "org.eclipse.jface.window.Window.open",
          "source": "Window.java:557"
        },
        {
          "method": "org.eclipse.jdt.internal.debug.ui.actions.JavaBreakpointPropertiesAction.run",
          "source": "JavaBreakp ointPropertiesAction.java:31"
        },
        {
          "method": "org.eclipse.ui.internal.PluginAction.runWithEvent",
          "source": "PluginAction.java:250"
        },
        {
          "method": "org.eclipse.jface.action.ActionContributionItem.handleWidgetSelection",
          "source": "ActionContributio nItem.java:456"
        },
        {
          "method": "org.eclipse.jface.action.ActionContributionItem.handleWidgetEvent",
          "source": "ActionContributionIte m.java:403"
        },
        {
          "method": "org.eclipse.jface.action.ActionContributionItem.access$0",
          "source": "ActionContributionItem.java:39 7"
        },
        {
          "method": "org.eclipse.jface.action.ActionContributionItem$ActionListener.handleEvent",
          "source": "ActionContri butionItem.java:72"
        },
        {
          "method": "org.eclipse.swt.widgets.EventTable.sendEvent",
          "source": "EventTable.java:77"
        },
        {
          "method": "org.eclipse.swt.widgets.Widget.notifyListeners",
          "source": "Widget.java:695"
        },
        {
          "method": "org.eclipse.swt.widgets.Display.runDeferredEvents",
          "source": "Display.java:1293"
        },
        {
          "method": "org.eclipse.swt.widgets.Display.readAndDispatch",
          "source": "Display.java:1046"
        },
        {
          "method": "org.eclipse.ui.internal.Workbench.runEventLoop",
          "source": "Workbench.java:1271"
        },
        {
          "method": "org.eclipse.ui.internal.Workbench.run",
          "source": "Workbench.java:1254"
        },
        {
          "method": "org.eclipse.core.internal.boot.InternalBootLoader.run",
          "source": "InternalBootLoader.java:845"
        },
        {
          "method": "org.eclipse.core.boot.BootLoader.run",
          "source": "BootLoader.java:461"
        },
        {
          "method": "java.lang.reflect.Method.invoke",
          "source": "Native Method"
        },
        {
          "method": "org.eclipse.core.launcher.Main.basicRun",
          "source": "Main.java:247"
        },
        {
          "method": "org.eclipse.core.launcher.Main.run",
          "source": "Main.java:703"
        },
        {
          "method": "org.eclipse.core.launcher.Main.main",
          "source": "Main.java:539"
        },
        {
          "method": "java.lang.reflect.Method.invoke",
          "source": "Native Method"
        },
        {
          "method": "com.apple.buckyball.app.LaunchRunner.run",
          "source": "LaunchRunner.java:82"
        },
        {
          "method": "com.apple.buckyball.app.LaunchRunner.callMain",
          "source": "LaunchRunner.java:44"
        },
        {
          "method": "com.apple.buckyball.app.CarbonLibApp.launch",
          "source": "CarbonLibApp.java:67"
        }
      ],
      "number": 0,
      "commentIndex": 0,
      "bugId": "32841",
      "date": "2003-02-24T22:39:05+01:00",
      "product": "JDT",
      "component": "Debug",
      "severity": "normal"
    }
  ],
  "groupId": "32841",
  "bugId": "32841",
  "date": "2003-02-24T22:39:05+01:00",
  "product": "JDT",
  "component": "Debug",
  "severity": "normal"
}