{
  "comments": [
    "1. In the project properties dialog, create an external tool builder on a project. Click OK.\n2. Delete the launch configuration manually from the navigator.\n3. Try to open the project properties dialog. The following exception occurs:\n\n!ENTRY org.eclipse.ui 4 4 Feb 24, 2003 16:43:30.538\n!MESSAGE Unhandled exception caught in event loop.\n!ENTRY org.eclipse.ui 4 0 Feb 24, 2003 16:43:30.539\n!MESSAGE Widget is disposed\n!STACK 0\norg.eclipse.swt.SWTException: Widget is disposed\n        at org.eclipse.swt.SWT.error(SWT.java:2316)\n        at org.eclipse.swt.SWT.error(SWT.java:2246)\n        at org.eclipse.swt.widgets.Widget.error(Widget.java:334)\n        at org.eclipse.swt.widgets.Control.getDisplay(Control.java:310)\n        at org.eclipse.swt.widgets.Widget.isValidThread(Widget.java:492)\n        at org.eclipse.swt.widgets.Widget.checkWidget(Widget.java:113)\n        at org.eclipse.swt.widgets.Control.setLayoutData(Control.java:1090)\n        at \norg.eclipse.jface.preference.PreferencePage.createControl(PreferencePage.java:212)\n        at \norg.eclipse.ui.externaltools.internal.ui.BuilderPropertyPage.createControl(BuilderPropert\nyPage.java:1018)\n        at \norg.eclipse.jface.preference.PreferenceDialog.showPage(PreferenceDialog.java:1015)\n        at \norg.eclipse.jface.preference.PreferenceDialog.selectSavedItem(PreferenceDialog.java:7\n00)\n        at org.eclipse.jface.preference.PreferenceDialog$4.run(PreferenceDialog.java:341)\n        at org.eclipse.swt.custom.BusyIndicator.showWhile(BusyIndicator.java:65)\n        at \norg.eclipse.jface.preference.PreferenceDialog.createContents(PreferenceDialog.java:33\n6)\n        at org.eclipse.jface.window.Window.create(Window.java:296)\n        at org.eclipse.ui.dialogs.PropertyDialogAction.run(PropertyDialogAction.java:155)\n        at org.eclipse.jface.action.Action.runWithEvent(Action.java:841)\n        at \norg.eclipse.jface.action.ActionContributionItem.handleWidgetSelection(ActionContributio\nnItem.java:456)\n        at \norg.eclipse.jface.action.ActionContributionItem.handleWidgetEvent(ActionContributionIte\nm.java:403)\n        at \norg.eclipse.jface.action.ActionContributionItem.access$0(ActionContributionItem.java:39\n7)\n        at \norg.eclipse.jface.action.ActionContributionItem$ActionListener.handleEvent(ActionContri\nbutionItem.java:72)\n        at org.eclipse.swt.widgets.EventTable.sendEvent(EventTable.java:77)\n        at org.eclipse.swt.widgets.Widget.notifyListeners(Widget.java:695)\n        at org.eclipse.swt.widgets.Display.runDeferredEvents(Display.java:1293)\n        at org.eclipse.swt.widgets.Display.readAndDispatch(Display.java:1046)\n        at org.eclipse.jface.window.Window.runEventLoop(Window.java:577)\n        at org.eclipse.jface.window.Window.open(Window.java:557)\n        at org.eclipse.jface.dialogs.ErrorDialog.open(ErrorDialog.java:291)\n        at org.eclipse.jface.dialogs.ErrorDialog.openError(ErrorDialog.java:354)\n        at org.eclipse.jface.dialogs.ErrorDialog.openError(ErrorDialog.java:317)\n        at \norg.eclipse.ui.externaltools.internal.ui.BuilderPropertyPage.addBuildersToTable(Builder\nPropertyPage.java:189)\n        at \norg.eclipse.ui.externaltools.internal.ui.BuilderPropertyPage.createContents(BuilderProp\nertyPage.java:388)\n        at \norg.eclipse.jface.preference.PreferencePage.createControl(PreferencePage.java:209)\n        at \norg.eclipse.ui.externaltools.internal.ui.BuilderPropertyPage.createControl(BuilderPropert\nyPage.java:1018)\n        at \norg.eclipse.jface.preference.PreferenceDialog.showPage(PreferenceDialog.java:1015)\n        at \norg.eclipse.jface.preference.PreferenceDialog.selectSavedItem(PreferenceDialog.java:7\n00)\n        at org.eclipse.jface.preference.PreferenceDialog$4.run(PreferenceDialog.java:341)\n        at org.eclipse.swt.custom.BusyIndicator.showWhile(BusyIndicator.java:65)\n        at \norg.eclipse.jface.preference.PreferenceDialog.createContents(PreferenceDialog.java:33\n6)\n        at org.eclipse.jface.window.Window.create(Window.java:296)\n        at org.eclipse.ui.dialogs.PropertyDialogAction.run(PropertyDialogAction.java:155)\n        at org.eclipse.jface.action.Action.runWithEvent(Action.java:841)\n        at \norg.eclipse.jface.action.ActionContributionItem.handleWidgetSelection(ActionContributio\nnItem.java:456)\n        at \norg.eclipse.jface.action.ActionContributionItem.handleWidgetEvent(ActionContributionIte\nm.java:403)\n        at \norg.eclipse.jface.action.ActionContributionItem.access$0(ActionContributionItem.java:39\n7)\n        at \norg.eclipse.jface.action.ActionContributionItem$ActionListener.handleEvent(ActionContri\nbutionItem.java:72)\n        at org.eclipse.swt.widgets.EventTable.sendEvent(EventTable.java:77)\n        at org.eclipse.swt.widgets.Widget.notifyListeners(Widget.java:695)\n        at org.eclipse.swt.widgets.Display.runDeferredEvents(Display.java:1293)\n        at org.eclipse.swt.widgets.Display.readAndDispatch(Display.java:1046)\n        at org.eclipse.jface.window.Window.runEventLoop(Window.java:577)\n        at org.eclipse.jface.window.Window.open(Window.java:557)\n        at org.eclipse.jface.dialogs.ErrorDialog.open(ErrorDialog.java:291)\n        at org.eclipse.jface.dialogs.ErrorDialog.openError(ErrorDialog.java:354)\n        at org.eclipse.jface.dialogs.ErrorDialog.openError(ErrorDialog.java:317)\n        at \norg.eclipse.ui.externaltools.internal.ui.BuilderPropertyPage.addBuildersToTable(Builder\nPropertyPage.java:189)\n        at \norg.eclipse.ui.externaltools.internal.ui.BuilderPropertyPage.createContents(BuilderProp\nertyPage.java:388)\n        at \norg.eclipse.jface.preference.PreferencePage.createControl(PreferencePage.java:209)\n        at \norg.eclipse.ui.externaltools.internal.ui.BuilderPropertyPage.createControl(BuilderPropert\nyPage.java:1018)\n        at \norg.eclipse.jface.preference.PreferenceDialog.showPage(PreferenceDialog.java:1015)\n        at \norg.eclipse.jface.preference.PreferenceDialog.selectSavedItem(PreferenceDialog.java:7\n00)\n        at org.eclipse.jface.preference.PreferenceDialog$4.run(PreferenceDialog.java:341)\n        at org.eclipse.swt.custom.BusyIndicator.showWhile(BusyIndicator.java:65)\n        at \norg.eclipse.jface.preference.PreferenceDialog.createContents(PreferenceDialog.java:33\n6)\n        at org.eclipse.jface.window.Window.create(Window.java:296)\n        at org.eclipse.ui.dialogs.PropertyDialogAction.run(PropertyDialogAction.java:155)\n        at org.eclipse.jface.action.Action.runWithEvent(Action.java:841)\n        at \norg.eclipse.jface.action.ActionContributionItem.handleWidgetSelection(ActionContributio\nnItem.java:456)\n        at \norg.eclipse.jface.action.ActionContributionItem.handleWidgetEvent(ActionContributionIte\nm.java:403)\n        at \norg.eclipse.jface.action.ActionContributionItem.access$0(ActionContributionItem.java:39\n7)\n        at \norg.eclipse.jface.action.ActionContributionItem$ActionListener.handleEvent(ActionContri\nbutionItem.java:72)\n        at org.eclipse.swt.widgets.EventTable.sendEvent(EventTable.java:77)\n        at org.eclipse.swt.widgets.Widget.notifyListeners(Widget.java:695)\n        at org.eclipse.swt.widgets.Display.runDeferredEvents(Display.java:1293)\n        at org.eclipse.swt.widgets.Display.readAndDispatch(Display.java:1046)\n        at org.eclipse.ui.internal.Workbench.runEventLoop(Workbench.java:1271)\n        at org.eclipse.ui.internal.Workbench.run(Workbench.java:1254)\n        at \norg.eclipse.core.internal.boot.InternalBootLoader.run(InternalBootLoader.java:845)\n        at org.eclipse.core.boot.BootLoader.run(BootLoader.java:461)\n        at java.lang.reflect.Method.invoke(Native Method)\n        at org.eclipse.core.launcher.Main.basicRun(Main.java:247)\n        at org.eclipse.core.launcher.Main.run(Main.java:703)\n        at org.eclipse.core.launcher.Main.main(Main.java:539)\n        at java.lang.reflect.Method.invoke(Native Method)\n        at com.apple.buckyball.app.LaunchRunner.run(LaunchRunner.java:82)\n        at com.apple.buckyball.app.LaunchRunner.callMain(LaunchRunner.java:44)\n        at com.apple.buckyball.app.CarbonLibApp.launch(CarbonLibApp.java:67)",
    "I cannot reproduce this problem Joe.\nI get no exceptions and an error dialog indicating the missing launch config.\nI don\u0027t see how removing .launch files could result in a widget is diposed \nerror anyway? \nCan you see if this is just a MAC phenomenon?",
    "The stack trace baffles me. If you follow it from the bottom up, it looks like\nduring the page initialization we tried to open the error dialog (expected)\nbut opening the error dialog somehow got back into initializing the page, which\ngot *back* into the error dialog and then back into the page... All in one\nstack trace? I don\u0027t understand. Could it be that the Mac didn\u0027t open the\nerror dialog on top and make it modal, allowing you to click in the property\npage?",
    "Doesn\u0027t happen on Linux or Win32. Somehow it looks like the Window code is\nreally getting into the circular path shown in the stack trace.",
    "Andre, can you please take a look at this problem and advise?",
    "Veronika, can you please take a look at this problem? Thanks.",
    "The problem only appears on Mac. Works fine on Windows and Linux-GTK\n(20030312)(an error dialog is displayed).\n\nMoving to Platform/SWT.",
    "I cannot reproduce this in the latest. I believe this is the same problem as Bug#34166 .\nI will close this bug. Please reopen it if you can reproduce it in builds \u003e 20030317."
  ],
  "commentCreationDates": [
    "2003-02-24T22:55:57+01:00",
    "2003-02-28T20:44:24+01:00",
    "2003-03-01T17:39:39+01:00",
    "2003-03-04T23:04:15+01:00",
    "2003-03-05T19:22:39+01:00",
    "2003-03-12T19:12:21+01:00",
    "2003-03-13T22:01:27+01:00",
    "2003-03-17T23:49:25+01:00"
  ],
  "traces": [
    {
      "exceptionType": "org.eclipse.swt.SWTException",
      "message": "Widget is disposed",
      "elements": [
        {
          "method": "org.eclipse.swt.SWT.error",
          "source": "SWT.java:2316"
        },
        {
          "method": "org.eclipse.swt.SWT.error",
          "source": "SWT.java:2246"
        },
        {
          "method": "org.eclipse.swt.widgets.Widget.error",
          "source": "Widget.java:334"
        },
        {
          "method": "org.eclipse.swt.widgets.Control.getDisplay",
          "source": "Control.java:310"
        },
        {
          "method": "org.eclipse.swt.widgets.Widget.isValidThread",
          "source": "Widget.java:492"
        },
        {
          "method": "org.eclipse.swt.widgets.Widget.checkWidget",
          "source": "Widget.java:113"
        },
        {
          "method": "org.eclipse.swt.widgets.Control.setLayoutData",
          "source": "Control.java:1090"
        },
        {
          "method": "org.eclipse.jface.preference.PreferencePage.createControl",
          "source": "PreferencePage.java:212"
        },
        {
          "method": "org.eclipse.ui.externaltools.internal.ui.BuilderPropertyPage.createControl",
          "source": "BuilderPropert yPage.java:1018"
        },
        {
          "method": "org.eclipse.jface.preference.PreferenceDialog.showPage",
          "source": "PreferenceDialog.java:1015"
        },
        {
          "method": "org.eclipse.jface.preference.PreferenceDialog.selectSavedItem",
          "source": "PreferenceDialog.java:7 00"
        },
        {
          "method": "org.eclipse.jface.preference.PreferenceDialog$4.run",
          "source": "PreferenceDialog.java:341"
        },
        {
          "method": "org.eclipse.swt.custom.BusyIndicator.showWhile",
          "source": "BusyIndicator.java:65"
        },
        {
          "method": "org.eclipse.jface.preference.PreferenceDialog.createContents",
          "source": "PreferenceDialog.java:33 6"
        },
        {
          "method": "org.eclipse.jface.window.Window.create",
          "source": "Window.java:296"
        },
        {
          "method": "org.eclipse.ui.dialogs.PropertyDialogAction.run",
          "source": "PropertyDialogAction.java:155"
        },
        {
          "method": "org.eclipse.jface.action.Action.runWithEvent",
          "source": "Action.java:841"
        },
        {
          "method": "org.eclipse.jface.action.ActionContributionItem.handleWidgetSelection",
          "source": "ActionContributio nItem.java:456"
        },
        {
          "method": "org.eclipse.jface.action.ActionContributionItem.handleWidgetEvent",
          "source": "ActionContributionIte m.java:403"
        },
        {
          "method": "org.eclipse.jface.action.ActionContributionItem.access$0",
          "source": "ActionContributionItem.java:39 7"
        },
        {
          "method": "org.eclipse.jface.action.ActionContributionItem$ActionListener.handleEvent",
          "source": "ActionContri butionItem.java:72"
        },
        {
          "method": "org.eclipse.swt.widgets.EventTable.sendEvent",
          "source": "EventTable.java:77"
        },
        {
          "method": "org.eclipse.swt.widgets.Widget.notifyListeners",
          "source": "Widget.java:695"
        },
        {
          "method": "org.eclipse.swt.widgets.Display.runDeferredEvents",
          "source": "Display.java:1293"
        },
        {
          "method": "org.eclipse.swt.widgets.Display.readAndDispatch",
          "source": "Display.java:1046"
        },
        {
          "method": "org.eclipse.jface.window.Window.runEventLoop",
          "source": "Window.java:577"
        },
        {
          "method": "org.eclipse.jface.window.Window.open",
          "source": "Window.java:557"
        },
        {
          "method": "org.eclipse.jface.dialogs.ErrorDialog.open",
          "source": "ErrorDialog.java:291"
        },
        {
          "method": "org.eclipse.jface.dialogs.ErrorDialog.openError",
          "source": "ErrorDialog.java:354"
        },
        {
          "method": "org.eclipse.jface.dialogs.ErrorDialog.openError",
          "source": "ErrorDialog.java:317"
        },
        {
          "method": "org.eclipse.ui.externaltools.internal.ui.BuilderPropertyPage.addBuildersToTable",
          "source": "Builder PropertyPage.java:189"
        },
        {
          "method": "org.eclipse.ui.externaltools.internal.ui.BuilderPropertyPage.createContents",
          "source": "BuilderProp ertyPage.java:388"
        },
        {
          "method": "org.eclipse.jface.preference.PreferencePage.createControl",
          "source": "PreferencePage.java:209"
        },
        {
          "method": "org.eclipse.ui.externaltools.internal.ui.BuilderPropertyPage.createControl",
          "source": "BuilderPropert yPage.java:1018"
        },
        {
          "method": "org.eclipse.jface.preference.PreferenceDialog.showPage",
          "source": "PreferenceDialog.java:1015"
        },
        {
          "method": "org.eclipse.jface.preference.PreferenceDialog.selectSavedItem",
          "source": "PreferenceDialog.java:7 00"
        },
        {
          "method": "org.eclipse.jface.preference.PreferenceDialog$4.run",
          "source": "PreferenceDialog.java:341"
        },
        {
          "method": "org.eclipse.swt.custom.BusyIndicator.showWhile",
          "source": "BusyIndicator.java:65"
        },
        {
          "method": "org.eclipse.jface.preference.PreferenceDialog.createContents",
          "source": "PreferenceDialog.java:33 6"
        },
        {
          "method": "org.eclipse.jface.window.Window.create",
          "source": "Window.java:296"
        },
        {
          "method": "org.eclipse.ui.dialogs.PropertyDialogAction.run",
          "source": "PropertyDialogAction.java:155"
        },
        {
          "method": "org.eclipse.jface.action.Action.runWithEvent",
          "source": "Action.java:841"
        },
        {
          "method": "org.eclipse.jface.action.ActionContributionItem.handleWidgetSelection",
          "source": "ActionContributio nItem.java:456"
        },
        {
          "method": "org.eclipse.jface.action.ActionContributionItem.handleWidgetEvent",
          "source": "ActionContributionIte m.java:403"
        },
        {
          "method": "org.eclipse.jface.action.ActionContributionItem.access$0",
          "source": "ActionContributionItem.java:39 7"
        },
        {
          "method": "org.eclipse.jface.action.ActionContributionItem$ActionListener.handleEvent",
          "source": "ActionContri butionItem.java:72"
        },
        {
          "method": "org.eclipse.swt.widgets.EventTable.sendEvent",
          "source": "EventTable.java:77"
        },
        {
          "method": "org.eclipse.swt.widgets.Widget.notifyListeners",
          "source": "Widget.java:695"
        },
        {
          "method": "org.eclipse.swt.widgets.Display.runDeferredEvents",
          "source": "Display.java:1293"
        },
        {
          "method": "org.eclipse.swt.widgets.Display.readAndDispatch",
          "source": "Display.java:1046"
        },
        {
          "method": "org.eclipse.jface.window.Window.runEventLoop",
          "source": "Window.java:577"
        },
        {
          "method": "org.eclipse.jface.window.Window.open",
          "source": "Window.java:557"
        },
        {
          "method": "org.eclipse.jface.dialogs.ErrorDialog.open",
          "source": "ErrorDialog.java:291"
        },
        {
          "method": "org.eclipse.jface.dialogs.ErrorDialog.openError",
          "source": "ErrorDialog.java:354"
        },
        {
          "method": "org.eclipse.jface.dialogs.ErrorDialog.openError",
          "source": "ErrorDialog.java:317"
        },
        {
          "method": "org.eclipse.ui.externaltools.internal.ui.BuilderPropertyPage.addBuildersToTable",
          "source": "Builder PropertyPage.java:189"
        },
        {
          "method": "org.eclipse.ui.externaltools.internal.ui.BuilderPropertyPage.createContents",
          "source": "BuilderProp ertyPage.java:388"
        },
        {
          "method": "org.eclipse.jface.preference.PreferencePage.createControl",
          "source": "PreferencePage.java:209"
        },
        {
          "method": "org.eclipse.ui.externaltools.internal.ui.BuilderPropertyPage.createControl",
          "source": "BuilderPropert yPage.java:1018"
        },
        {
          "method": "org.eclipse.jface.preference.PreferenceDialog.showPage",
          "source": "PreferenceDialog.java:1015"
        },
        {
          "method": "org.eclipse.jface.preference.PreferenceDialog.selectSavedItem",
          "source": "PreferenceDialog.java:7 00"
        },
        {
          "method": "org.eclipse.jface.preference.PreferenceDialog$4.run",
          "source": "PreferenceDialog.java:341"
        },
        {
          "method": "org.eclipse.swt.custom.BusyIndicator.showWhile",
          "source": "BusyIndicator.java:65"
        },
        {
          "method": "org.eclipse.jface.preference.PreferenceDialog.createContents",
          "source": "PreferenceDialog.java:33 6"
        },
        {
          "method": "org.eclipse.jface.window.Window.create",
          "source": "Window.java:296"
        },
        {
          "method": "org.eclipse.ui.dialogs.PropertyDialogAction.run",
          "source": "PropertyDialogAction.java:155"
        },
        {
          "method": "org.eclipse.jface.action.Action.runWithEvent",
          "source": "Action.java:841"
        },
        {
          "method": "org.eclipse.jface.action.ActionContributionItem.handleWidgetSelection",
          "source": "ActionContributio nItem.java:456"
        },
        {
          "method": "org.eclipse.jface.action.ActionContributionItem.handleWidgetEvent",
          "source": "ActionContributionIte m.java:403"
        },
        {
          "method": "org.eclipse.jface.action.ActionContributionItem.access$0",
          "source": "ActionContributionItem.java:39 7"
        },
        {
          "method": "org.eclipse.jface.action.ActionContributionItem$ActionListener.handleEvent",
          "source": "ActionContri butionItem.java:72"
        },
        {
          "method": "org.eclipse.swt.widgets.EventTable.sendEvent",
          "source": "EventTable.java:77"
        },
        {
          "method": "org.eclipse.swt.widgets.Widget.notifyListeners",
          "source": "Widget.java:695"
        },
        {
          "method": "org.eclipse.swt.widgets.Display.runDeferredEvents",
          "source": "Display.java:1293"
        },
        {
          "method": "org.eclipse.swt.widgets.Display.readAndDispatch",
          "source": "Display.java:1046"
        },
        {
          "method": "org.eclipse.ui.internal.Workbench.runEventLoop",
          "source": "Workbench.java:1271"
        },
        {
          "method": "org.eclipse.ui.internal.Workbench.run",
          "source": "Workbench.java:1254"
        },
        {
          "method": "org.eclipse.core.internal.boot.InternalBootLoader.run",
          "source": "InternalBootLoader.java:845"
        },
        {
          "method": "org.eclipse.core.boot.BootLoader.run",
          "source": "BootLoader.java:461"
        },
        {
          "method": "java.lang.reflect.Method.invoke",
          "source": "Native Method"
        },
        {
          "method": "org.eclipse.core.launcher.Main.basicRun",
          "source": "Main.java:247"
        },
        {
          "method": "org.eclipse.core.launcher.Main.run",
          "source": "Main.java:703"
        },
        {
          "method": "org.eclipse.core.launcher.Main.main",
          "source": "Main.java:539"
        },
        {
          "method": "java.lang.reflect.Method.invoke",
          "source": "Native Method"
        },
        {
          "method": "com.apple.buckyball.app.LaunchRunner.run",
          "source": "LaunchRunner.java:82"
        },
        {
          "method": "com.apple.buckyball.app.LaunchRunner.callMain",
          "source": "LaunchRunner.java:44"
        },
        {
          "method": "com.apple.buckyball.app.CarbonLibApp.launch",
          "source": "CarbonLibApp.java:67"
        }
      ],
      "number": 0,
      "commentIndex": 0,
      "bugId": "32851",
      "date": "2003-02-24T22:55:57+01:00",
      "product": "Platform",
      "component": "SWT",
      "severity": "normal"
    }
  ],
  "groupId": "32851",
  "bugId": "32851",
  "date": "2003-02-24T22:55:57+01:00",
  "product": "Platform",
  "component": "SWT",
  "severity": "normal"
}