{
  "comments": [
    "Choosing preview from the feature editor pop up menu caused and error: \"Unable \nto instantiate view: org.eclipse.update.ui.DetailsView\".\n\nThe log contains:\n\n!ENTRY org.eclipse.core.runtime 4 2 Feb 25, 2003 11:25:49.04\n!MESSAGE Plug-in org.eclipse.update.ui was unable to load class org.eclipse.upda\nte.internal.ui.views.DetailsView.\n!STACK 0\norg.eclipse.core.internal.boot.DelegatingLoaderException: org.eclipse.core.runti\nme.CoreException: Problems encountered starting up plug-in: \"org.eclipse.update.\nui\".\n        at org.eclipse.core.internal.plugins.PluginDescriptor.internalDoPluginAc\ntivation(PluginDescriptor.java(Compiled Code))\n        at org.eclipse.core.internal.plugins.PluginDescriptor.doPluginActivation\n(PluginDescriptor.java(Compiled Code))\n        at org.eclipse.core.internal.plugins.PluginClassLoader.activatePlugin(Pl\nuginClassLoader.java(Compiled Code))\n        at org.eclipse.core.internal.plugins.PluginClassLoader.internalFindClass\nParentsSelf(PluginClassLoader.java(Compiled Code))\n        at org.eclipse.core.internal.boot.DelegatingURLClassLoader.findClassPare\nntsSelf(DelegatingURLClassLoader.java(Compiled Code))\n        at org.eclipse.core.internal.boot.DelegatingURLClassLoader.loadClass(Del\negatingURLClassLoader.java(Compiled Code))\n        at org.eclipse.core.internal.boot.DelegatingURLClassLoader.loadClass(Del\negatingURLClassLoader.java(Compiled Code))\n        at org.eclipse.core.internal.plugins.PluginDescriptor.createExecutableEx\ntension(PluginDescriptor.java(Compiled Code))\n        at org.eclipse.core.internal.plugins.PluginDescriptor.createExecutableEx\ntension(PluginDescriptor.java(Compiled Code))\n        at org.eclipse.core.internal.plugins.PluginDescriptor.createExecutableEx\ntension(PluginDescriptor.java(Compiled Code))\n        at org.eclipse.core.internal.plugins.ConfigurationElement.createExecutab\nleExtension(ConfigurationElement.java(Compiled Code))\n        at org.eclipse.ui.internal.WorkbenchPlugin$1.run(WorkbenchPlugin.java:15\n8)\n        at org.eclipse.swt.custom.BusyIndicator.showWhile(BusyIndicator.java(Com\npiled Code))\n        at org.eclipse.ui.internal.WorkbenchPlugin.createExtension(WorkbenchPlug\nin.java(Compiled Code))\n        at org.eclipse.ui.internal.registry.ViewDescriptor.createView(ViewDescri\nptor.java:45)\n        at org.eclipse.ui.internal.ViewFactory$2.run(ViewFactory.java:109)\n        at org.eclipse.core.runtime.Platform.run(Platform.java(Compiled Code))\n        at org.eclipse.core.runtime.Platform.run(Platform.java(Compiled Code))\n        at org.eclipse.ui.internal.ViewFactory.busyRestoreView(ViewFactory.java:\n92)\n        at org.eclipse.ui.internal.ViewFactory$1.run(ViewFactory.java:76)\n        at org.eclipse.swt.custom.BusyIndicator.showWhile(BusyIndicator.java(Com\npiled Code))\n        at org.eclipse.ui.internal.ViewFactory.restoreView(ViewFactory.java:72)\n        at org.eclipse.ui.internal.Perspective.showView(Perspective.java:1454)\n        at org.eclipse.ui.internal.WorkbenchPage.busyShowView(WorkbenchPage.java\n:652)\n        at org.eclipse.ui.internal.WorkbenchPage.access$9(WorkbenchPage.java:631\n)\n        at org.eclipse.ui.internal.WorkbenchPage$12.run(WorkbenchPage.java:2742)\n        at org.eclipse.swt.custom.BusyIndicator.showWhile(BusyIndicator.java(Com\npiled Code))\n        at org.eclipse.ui.internal.WorkbenchPage.showView(WorkbenchPage.java:273\n9)\n        at org.eclipse.ui.internal.WorkbenchPage.showView(WorkbenchPage.java:272\n9)\n        at org.eclipse.pde.internal.ui.editor.feature.PreviewAction.run(PreviewA\nction.java:53)\n        at org.eclipse.jface.action.Action.runWithEvent(Action.java:841)\n        at org.eclipse.jface.action.ActionContributionItem.handleWidgetSelection\n(ActionContributionItem.java:450)\n        at org.eclipse.jface.action.ActionContributionItem.handleWidgetEvent(Act\nionContributionItem.java:398)\n        at org.eclipse.jface.action.ActionContributionItem.access$0(ActionContri\nbutionItem.java:392)\n        at org.eclipse.jface.action.ActionContributionItem$ActionListener.handle\nEvent(ActionContributionItem.java:72)\n        at org.eclipse.swt.widgets.EventTable.sendEvent(EventTable.java(Compiled\n Code))\n        at org.eclipse.swt.widgets.Display.runDeferredEvents(Display.java(Compil\ned Code))\n        at org.eclipse.swt.widgets.Display.runDeferredEvents(Display.java(Compil\ned Code))\n        at org.eclipse.swt.widgets.Display.readAndDispatch(Display.java(Compiled\n Code))\n        at org.eclipse.ui.internal.Workbench.runEventLoop(Workbench.java:1271)\n        at org.eclipse.ui.internal.Workbench.run(Workbench.java:1254)\n        at org.eclipse.core.internal.boot.InternalBootLoader.run(InternalBootLoa\nder.java:845)\n        at org.eclipse.core.boot.BootLoader.run(BootLoader.java:461)\n        at java.lang.reflect.Method.invoke(Native Method)\n        at org.eclipse.core.launcher.Main.basicRun(Main.java:247)\n        at org.eclipse.core.launcher.Main.run(Main.java:703)\n        at org.eclipse.core.launcher.Main.main(Main.java:539)",
    "The DetailsView is no longer in the 3.0 M1 driver."
  ],
  "commentCreationDates": [
    "2003-02-25T16:32:22+01:00",
    "2003-06-11T21:56:32+02:00"
  ],
  "traces": [
    {
      "exceptionType": "me.CoreException",
      "message": "Problems encountered starting up plug-in: \"org.eclipse.update. ui\".",
      "elements": [
        {
          "method": "org.eclipse.core.internal.plugins.PluginDescriptor.internalDoPluginActivation",
          "source": "PluginDescriptor.java(Compiled Code)"
        },
        {
          "method": "org.eclipse.core.internal.plugins.PluginDescriptor.doPluginActivation",
          "source": "PluginDescriptor.java(Compiled Code)"
        },
        {
          "method": "org.eclipse.core.internal.plugins.PluginClassLoader.activatePlugin",
          "source": "Pl uginClassLoader.java(Compiled Code)"
        },
        {
          "method": "org.eclipse.core.internal.plugins.PluginClassLoader.internalFindClassParentsSelf",
          "source": "PluginClassLoader.java(Compiled Code)"
        },
        {
          "method": "org.eclipse.core.internal.boot.DelegatingURLClassLoader.findClassParentsSelf",
          "source": "DelegatingURLClassLoader.java(Compiled Code)"
        },
        {
          "method": "org.eclipse.core.internal.boot.DelegatingURLClassLoader.loadClass",
          "source": "Del egatingURLClassLoader.java(Compiled Code)"
        },
        {
          "method": "org.eclipse.core.internal.boot.DelegatingURLClassLoader.loadClass",
          "source": "Del egatingURLClassLoader.java(Compiled Code)"
        },
        {
          "method": "org.eclipse.core.internal.plugins.PluginDescriptor.createExecutableExtension",
          "source": "PluginDescriptor.java(Compiled Code)"
        },
        {
          "method": "org.eclipse.core.internal.plugins.PluginDescriptor.createExecutableExtension",
          "source": "PluginDescriptor.java(Compiled Code)"
        },
        {
          "method": "org.eclipse.core.internal.plugins.PluginDescriptor.createExecutableExtension",
          "source": "PluginDescriptor.java(Compiled Code)"
        },
        {
          "method": "org.eclipse.core.internal.plugins.ConfigurationElement.createExecutableExtension",
          "source": "ConfigurationElement.java(Compiled Code)"
        },
        {
          "method": "org.eclipse.ui.internal.WorkbenchPlugin$1.run",
          "source": "WorkbenchPlugin.java:15 8"
        },
        {
          "method": "org.eclipse.swt.custom.BusyIndicator.showWhile",
          "source": "BusyIndicator.java(Com piled Code)"
        },
        {
          "method": "org.eclipse.ui.internal.WorkbenchPlugin.createExtension",
          "source": "WorkbenchPlug in.java(Compiled Code)"
        },
        {
          "method": "org.eclipse.ui.internal.registry.ViewDescriptor.createView",
          "source": "ViewDescri ptor.java:45"
        },
        {
          "method": "org.eclipse.ui.internal.ViewFactory$2.run",
          "source": "ViewFactory.java:109"
        },
        {
          "method": "org.eclipse.core.runtime.Platform.run",
          "source": "Platform.java(Compiled Code)"
        },
        {
          "method": "org.eclipse.core.runtime.Platform.run",
          "source": "Platform.java(Compiled Code)"
        },
        {
          "method": "org.eclipse.ui.internal.ViewFactory.busyRestoreView",
          "source": "ViewFactory.java: 92"
        },
        {
          "method": "org.eclipse.ui.internal.ViewFactory$1.run",
          "source": "ViewFactory.java:76"
        },
        {
          "method": "org.eclipse.swt.custom.BusyIndicator.showWhile",
          "source": "BusyIndicator.java(Com piled Code)"
        },
        {
          "method": "org.eclipse.ui.internal.ViewFactory.restoreView",
          "source": "ViewFactory.java:72"
        },
        {
          "method": "org.eclipse.ui.internal.Perspective.showView",
          "source": "Perspective.java:1454"
        },
        {
          "method": "org.eclipse.ui.internal.WorkbenchPage.busyShowView",
          "source": "WorkbenchPage.java :652"
        },
        {
          "method": "org.eclipse.ui.internal.WorkbenchPage.access$9",
          "source": "WorkbenchPage.java:631 "
        },
        {
          "method": "org.eclipse.ui.internal.WorkbenchPage$12.run",
          "source": "WorkbenchPage.java:2742"
        },
        {
          "method": "org.eclipse.swt.custom.BusyIndicator.showWhile",
          "source": "BusyIndicator.java(Com piled Code)"
        },
        {
          "method": "org.eclipse.ui.internal.WorkbenchPage.showView",
          "source": "WorkbenchPage.java:273 9"
        },
        {
          "method": "org.eclipse.ui.internal.WorkbenchPage.showView",
          "source": "WorkbenchPage.java:272 9"
        },
        {
          "method": "org.eclipse.pde.internal.ui.editor.feature.PreviewAction.run",
          "source": "PreviewA ction.java:53"
        },
        {
          "method": "org.eclipse.jface.action.Action.runWithEvent",
          "source": "Action.java:841"
        },
        {
          "method": "org.eclipse.jface.action.ActionContributionItem.handleWidgetSelection",
          "source": "ActionContributionItem.java:450"
        },
        {
          "method": "org.eclipse.jface.action.ActionContributionItem.handleWidgetEvent",
          "source": "Act ionContributionItem.java:398"
        },
        {
          "method": "org.eclipse.jface.action.ActionContributionItem.access$0",
          "source": "ActionContri butionItem.java:392"
        },
        {
          "method": "org.eclipse.jface.action.ActionContributionItem$ActionListener.handleEvent",
          "source": "ActionContributionItem.java:72"
        },
        {
          "method": "org.eclipse.swt.widgets.EventTable.sendEvent",
          "source": "EventTable.java(Compiled  Code)"
        },
        {
          "method": "org.eclipse.swt.widgets.Display.runDeferredEvents",
          "source": "Display.java(Compil ed Code)"
        },
        {
          "method": "org.eclipse.swt.widgets.Display.runDeferredEvents",
          "source": "Display.java(Compil ed Code)"
        },
        {
          "method": "org.eclipse.swt.widgets.Display.readAndDispatch",
          "source": "Display.java(Compiled  Code)"
        },
        {
          "method": "org.eclipse.ui.internal.Workbench.runEventLoop",
          "source": "Workbench.java:1271"
        },
        {
          "method": "org.eclipse.ui.internal.Workbench.run",
          "source": "Workbench.java:1254"
        },
        {
          "method": "org.eclipse.core.internal.boot.InternalBootLoader.run",
          "source": "InternalBootLoa der.java:845"
        },
        {
          "method": "org.eclipse.core.boot.BootLoader.run",
          "source": "BootLoader.java:461"
        },
        {
          "method": "java.lang.reflect.Method.invoke",
          "source": "Native Method"
        },
        {
          "method": "org.eclipse.core.launcher.Main.basicRun",
          "source": "Main.java:247"
        },
        {
          "method": "org.eclipse.core.launcher.Main.run",
          "source": "Main.java:703"
        },
        {
          "method": "org.eclipse.core.launcher.Main.main",
          "source": "Main.java:539"
        }
      ],
      "number": 0,
      "commentIndex": 0,
      "bugId": "33004",
      "date": "2003-02-25T16:32:22+01:00",
      "product": "Platform",
      "component": "Update",
      "severity": "normal"
    }
  ],
  "groupId": "33004",
  "bugId": "33004",
  "date": "2003-02-25T16:32:22+01:00",
  "product": "Platform",
  "component": "Update",
  "severity": "normal"
}