{
  "comments": [
    "In a nutshell, installing Eclipse using a UNC path, or trying to run Eclipse \nafterwards using a UNC path will just not work. There are several steps \ninvolved in the Eclipse startup sequence:\n\n1. The launcher (eclipse.exe) takes its executable path and looks for \nthe \"startup.jar\" file which contains the Java platform launching code. This \nlogic appears to support UNC paths since the launcher finds the startup.jar \nfile and the JVM is launched.\n\n2. The platform launching code (in startup.jar) uses its class path (specified \nby the launcher) to find the config file in the workspace and to create the \nboot URL. If the location of the startup.jar file is \n\u003cinstallDir\u003e/eclipse/startup.jar, then the boot URL created is:\n    file:\u003cinstallDir\u003e/eclipse/plugins/org.eclipse.core.boot_2.0.2/boot.jar\n\nIf the config file is not found, a new one is created but if the boot.jar file \ncannot be found, Eclipse does not run (see the first exception below).\n\n3. If the boot.jar file can be found, the core.boot plug-in starts the \nworkbench assuming the core.runtime plug-ins are in sibling directories. If \nalso uses the install directory to add several plug-in subdirectories to the \nlibrary path so that DLLs can be loaded via System.loadLibrary().\n\n4. As part of starting up the workbench, features and plug-ins defined in \nEclipse extensions are logically added to the list of default plug-ins (e.g., \n\u003cinstallDir\u003e/eclipse/plugins). These extensions are found by parsing all of the \nfiles in the \u003cinstallDir\u003e/eclipse/links directory. The format of the extension \nlocations in these link files does not support UNC paths (I tried).\n\nI installed Eclipse on the file system and then attempted to run Eclipse where \neclipse.exe was referenced using a UNC path. The error message in the .log file \nwas:\n\njava.lang.RuntimeException: Could not find bootstrap code. Check location of \nboot plug-in or specify -boot.\n\tat org.eclipse.core.launcher.Main.searchForBoot(Main.java:424)\n\tat org.eclipse.core.launcher.Main.getBootPath(Main.java:394)\n\tat org.eclipse.core.launcher.Main.basicRun(Main.java:237)\n\tat org.eclipse.core.launcher.Main.run(Main.java:703)\n\tat org.eclipse.core.launcher.Main.main(Main.java:539)\n\nThis implies that the default logic in the Java launcher code does not support \nUNC paths. However, I tried adding the ?boot switch specifying the boot.jar \nfile using the URL syntax with a UNC path and then the following error occurred:\n\njava.lang.ClassNotFoundException: org.eclipse.core.boot.BootLoader\n\tat java.net.URLClassLoader$1.run(URLClassLoader.java:198)\n\tat java.security.AccessController.doPrivileged(Native Method)\n\tat java.net.URLClassLoader.findClass(URLClassLoader.java:186)\n\tat java.lang.ClassLoader.loadClass(ClassLoader.java:306)\n\tat java.lang.ClassLoader.loadClass(ClassLoader.java:262)\n\tat org.eclipse.core.launcher.Main.getBootLoader(Main.java:338)\n\tat org.eclipse.core.launcher.Main.basicRun(Main.java:244)\n\tat org.eclipse.core.launcher.Main.run(Main.java:703)\n\tat org.eclipse.core.launcher.Main.main(Main.java:539)\n\nThis error seems to indicate the mechanism used by Eclipse to extend the class \npath does not appear to support UNC paths. The boot.jar file was found but when \nadded to the class path, classes in that jar file could not be found.\n\nThe next step was to modify the ?boot switch specifying the boot.jar file so \nthat the URL syntax did not use a UNC path and the following error occurred:\n\njava.lang.reflect.InvocationTargetException\n\tat sun.reflect.NativeMethodAccessorImpl.invoke0(Native Method)\n\tat sun.reflect.NativeMethodAccessorImpl.invoke\n(NativeMethodAccessorImpl.java:39)\nat sun.reflect.DelegatingMethodAccessorImpl.invoke\n(DelegatingMethodAccessorImpl.java:25)\n\tat java.lang.reflect.Method.invoke(Method.java:324)\n\tat org.eclipse.core.launcher.Main.basicRun(Main.java:247)\n\tat org.eclipse.core.launcher.Main.run(Main.java:703)\n\tat org.eclipse.core.launcher.Main.main(Main.java:539)\n\nCaused by: java.lang.RuntimeException: Fatal Error: Unable to locate matching \norg.eclipse.core.runtime plugin.\nat org.eclipse.core.internal.boot.PlatformConfiguration.locateDefaultPlugins\n(PlatformConfiguration.java:2212)\nat org.eclipse.core.internal.boot.PlatformConfiguration.\u003cinit\u003e\n(PlatformConfiguration.java:879)\nat org.eclipse.core.internal.boot.PlatformConfiguration.startup\n(PlatformConfiguration.java:1343)\nat org.eclipse.core.internal.boot.InternalBootLoader.initialize\n(InternalBootLoader.java:568)\nat org.eclipse.core.internal.boot.InternalBootLoader.startup\n(InternalBootLoader.java:960)\nat org.eclipse.core.internal.boot.InternalBootLoader.run\n(InternalBootLoader.java:824)\n\tat org.eclipse.core.boot.BootLoader.run(BootLoader.java:462)\n\t... 7 more\n\nWhen Eclipse extends the class path for other plug-ins (e.g.,\norg.eclipse.core.runtime), the same problem appears to occur since the install \npath still contains the UNC format.\n\nConclusion: UNC paths are not supported by Eclipse.",
    "\n\n*** This bug has been marked as a duplicate of 28656 ***"
  ],
  "commentCreationDates": [
    "2003-02-26T14:53:29+01:00",
    "2003-02-26T16:02:13+01:00"
  ],
  "traces": [
    {
      "exceptionType": "java.lang.RuntimeException",
      "message": "Could not find bootstrap code. Check location of  boot plug-in or specify -boot.",
      "elements": [
        {
          "method": "org.eclipse.core.launcher.Main.searchForBoot",
          "source": "Main.java:424"
        },
        {
          "method": "org.eclipse.core.launcher.Main.getBootPath",
          "source": "Main.java:394"
        },
        {
          "method": "org.eclipse.core.launcher.Main.basicRun",
          "source": "Main.java:237"
        },
        {
          "method": "org.eclipse.core.launcher.Main.run",
          "source": "Main.java:703"
        },
        {
          "method": "org.eclipse.core.launcher.Main.main",
          "source": "Main.java:539"
        }
      ],
      "number": 0,
      "commentIndex": 0,
      "bugId": "33265",
      "duplicateId": "28656",
      "date": "2003-02-26T14:53:29+01:00",
      "product": "Platform",
      "component": "Resources",
      "severity": "minor"
    },
    {
      "exceptionType": "java.lang.ClassNotFoundException",
      "message": "org.eclipse.core.boot.BootLoader",
      "elements": [
        {
          "method": "java.net.URLClassLoader$1.run",
          "source": "URLClassLoader.java:198"
        },
        {
          "method": "java.security.AccessController.doPrivileged",
          "source": "Native Method"
        },
        {
          "method": "java.net.URLClassLoader.findClass",
          "source": "URLClassLoader.java:186"
        },
        {
          "method": "java.lang.ClassLoader.loadClass",
          "source": "ClassLoader.java:306"
        },
        {
          "method": "java.lang.ClassLoader.loadClass",
          "source": "ClassLoader.java:262"
        },
        {
          "method": "org.eclipse.core.launcher.Main.getBootLoader",
          "source": "Main.java:338"
        },
        {
          "method": "org.eclipse.core.launcher.Main.basicRun",
          "source": "Main.java:244"
        },
        {
          "method": "org.eclipse.core.launcher.Main.run",
          "source": "Main.java:703"
        },
        {
          "method": "org.eclipse.core.launcher.Main.main",
          "source": "Main.java:539"
        }
      ],
      "number": 1,
      "commentIndex": 0,
      "bugId": "33265",
      "duplicateId": "28656",
      "date": "2003-02-26T14:53:29+01:00",
      "product": "Platform",
      "component": "Resources",
      "severity": "minor"
    },
    {
      "exceptionType": "java.lang.reflect.InvocationTargetException",
      "elements": [
        {
          "method": "sun.reflect.NativeMethodAccessorImpl.invoke0",
          "source": "Native Method"
        },
        {
          "method": "sun.reflect.NativeMethodAccessorImpl.invoke",
          "source": "NativeMethodAccessorImpl.java:39"
        },
        {
          "method": "sun.reflect.DelegatingMethodAccessorImpl.invoke",
          "source": "DelegatingMethodAccessorImpl.java:25"
        },
        {
          "method": "java.lang.reflect.Method.invoke",
          "source": "Method.java:324"
        },
        {
          "method": "org.eclipse.core.launcher.Main.basicRun",
          "source": "Main.java:247"
        },
        {
          "method": "org.eclipse.core.launcher.Main.run",
          "source": "Main.java:703"
        },
        {
          "method": "org.eclipse.core.launcher.Main.main",
          "source": "Main.java:539"
        }
      ],
      "causedBy": {
        "exceptionType": "java.lang.RuntimeException",
        "message": "Fatal Error: Unable to locate matching  org.eclipse.core.runtime plugin.",
        "elements": [
          {
            "method": "org.eclipse.core.internal.boot.PlatformConfiguration.locateDefaultPlugins",
            "source": "PlatformConfiguration.java:2212"
          },
          {
            "method": "org.eclipse.core.internal.boot.PlatformConfiguration.\u003cinit\u003e",
            "source": "PlatformConfiguration.java:879"
          },
          {
            "method": "org.eclipse.core.internal.boot.PlatformConfiguration.startup",
            "source": "PlatformConfiguration.java:1343"
          },
          {
            "method": "org.eclipse.core.internal.boot.InternalBootLoader.initialize",
            "source": "InternalBootLoader.java:568"
          },
          {
            "method": "org.eclipse.core.internal.boot.InternalBootLoader.startup",
            "source": "InternalBootLoader.java:960"
          },
          {
            "method": "org.eclipse.core.internal.boot.InternalBootLoader.run",
            "source": "InternalBootLoader.java:824"
          },
          {
            "method": "org.eclipse.core.boot.BootLoader.run",
            "source": "BootLoader.java:462"
          }
        ],
        "number": 0,
        "commentIndex": 0
      },
      "number": 2,
      "commentIndex": 0,
      "bugId": "33265",
      "duplicateId": "28656",
      "date": "2003-02-26T14:53:29+01:00",
      "product": "Platform",
      "component": "Resources",
      "severity": "minor"
    }
  ],
  "groupId": "28656",
  "bugId": "33265",
  "duplicateId": "28656",
  "date": "2003-02-26T14:53:29+01:00",
  "product": "Platform",
  "component": "Resources",
  "severity": "minor"
}