{
  "comments": [
    "After 2J tests I have found following in the log.\n\n!ENTRY org.eclipse.ui 4 0 Feb 26, 2003 13:51:21.246\n!MESSAGE String index out of range: 44\n!STACK 0\njava.lang.StringIndexOutOfBoundsException: String index out of range: 44\n        at java.lang.String.substring(String.java:1517)\n        at java.net.URLDecoder.decode(URLDecoder.java:52)\n        at \norg.eclipse.update.internal.ui.wizards.NewSiteBookmarkWizardPage.validatePage\n(NewSiteBookmarkWizardPage.java:106)\n        at \norg.eclipse.update.internal.ui.wizards.NewSiteBookmarkWizardPage$1.modifyText\n(NewSiteBookmarkWizardPage.java:71)\n        at org.eclipse.swt.widgets.TypedListener.handleEvent\n(TypedListener.java:181)\n        at org.eclipse.swt.widgets.EventTable.sendEvent(EventTable.java:77)\n        at org.eclipse.swt.widgets.Widget.sendEvent(Widget.java:807)\n        at org.eclipse.swt.widgets.Widget.sendEvent(Widget.java:829)\n        at org.eclipse.swt.widgets.Widget.sendEvent(Widget.java:811)\n        at org.eclipse.swt.widgets.Text.XmNvalueChangedCallback(Text.java:1518)\n        at org.eclipse.swt.widgets.Widget.windowProc(Widget.java:1017)\n        at org.eclipse.swt.widgets.Display.windowProc(Display.java:2296)\n        at org.eclipse.swt.internal.motif.OS.XtDispatchEvent(Native Method)\n        at org.eclipse.swt.widgets.Display.readAndDispatch(Display.java:1618)\n        at org.eclipse.jface.window.Window.runEventLoop(Window.java:577)\n        at org.eclipse.jface.window.Window.open(Window.java:557)\n        at org.eclipse.update.internal.ui.views.UpdatesView.performNewBookmark\n(UpdatesView.java:791)\n        at org.eclipse.update.internal.ui.views.UpdatesView.access$10\n(UpdatesView.java:779)\n        at org.eclipse.update.internal.ui.views.UpdatesView$1.run\n(UpdatesView.java:485)\n        at org.eclipse.jface.action.Action.runWithEvent(Action.java:841)\n        at org.eclipse.jface.action.ActionContributionItem.handleWidgetSelection\n(ActionContributionItem.java:456)\n        at org.eclipse.jface.action.ActionContributionItem.handleWidgetEvent\n(ActionContributionItem.java:403)\n        at org.eclipse.jface.action.ActionContributionItem.access$0\n(ActionContributionItem.java:397)\n        at \norg.eclipse.jface.action.ActionContributionItem$ActionListener.handleEvent\n(ActionContributionItem.java:72)\n        at org.eclipse.swt.widgets.EventTable.sendEvent(EventTable.java:77)\n        at org.eclipse.swt.widgets.Widget.sendEvent(Widget.java:807)\n        at org.eclipse.swt.widgets.Display.runDeferredEvents(Display.java:1829)\n        at org.eclipse.swt.widgets.Display.readAndDispatch(Display.java:1620)\n        at org.eclipse.ui.internal.Workbench.runEventLoop(Workbench.java:1271)\n        at org.eclipse.ui.internal.Workbench.run(Workbench.java:1254)\n        at org.eclipse.core.internal.boot.InternalBootLoader.run\n(InternalBootLoader.java:845)\n        at org.eclipse.core.boot.BootLoader.run(BootLoader.java:461)\n        at java.lang.reflect.Method.invoke(Native Method)\n        at org.eclipse.core.launcher.Main.basicRun(Main.java:247)\n        at org.eclipse.core.launcher.Main.run(Main.java:703)\n        at org.eclipse.core.launcher.Main.main(Main.java:539)\n!ENTRY org.eclipse.ui 4 4 Feb 26, 2003 13:51:25.464\n!MESSAGE Unhandled exception caught in event loop.\n!ENTRY org.eclipse.ui 4 0 Feb 26, 2003 13:51:25.481\n!MESSAGE String index out of range: 55\n!STACK 0\njava.lang.StringIndexOutOfBoundsException: String index out of range: 55\n        at java.lang.String.substring(String.java:1517)\n        at java.net.URLDecoder.decode(URLDecoder.java:52)\n        at \norg.eclipse.update.internal.ui.wizards.NewSiteBookmarkWizardPage.validatePage\n(NewSiteBookmarkWizardPage.java:106)\n        at \norg.eclipse.update.internal.ui.wizards.NewSiteBookmarkWizardPage$1.modifyText\n(NewSiteBookmarkWizardPage.java:71)\n        at org.eclipse.swt.widgets.TypedListener.handleEvent\n(TypedListener.java:181)\n        at org.eclipse.swt.widgets.EventTable.sendEvent(EventTable.java:77)\n        at org.eclipse.swt.widgets.Widget.sendEvent(Widget.java:807)\n        at org.eclipse.swt.widgets.Widget.sendEvent(Widget.java:829)\n        at org.eclipse.swt.widgets.Widget.sendEvent(Widget.java:811)\n        at org.eclipse.swt.widgets.Text.XmNvalueChangedCallback(Text.java:1518)\n        at org.eclipse.swt.widgets.Widget.windowProc(Widget.java:1017)\n        at org.eclipse.swt.widgets.Display.windowProc(Display.java:2296)\n        at org.eclipse.swt.internal.motif.OS.XtDispatchEvent(Native Method)\n        at org.eclipse.swt.widgets.Display.readAndDispatch(Display.java:1618)\n        at org.eclipse.jface.window.Window.runEventLoop(Window.java:577)\n        at org.eclipse.jface.window.Window.open(Window.java:557)\n        at org.eclipse.update.internal.ui.views.UpdatesView.performNewBookmark\n(UpdatesView.java:791)\n        at org.eclipse.update.internal.ui.views.UpdatesView.access$10\n(UpdatesView.java:779)\n        at org.eclipse.update.internal.ui.views.UpdatesView$1.run\n(UpdatesView.java:485)\n        at org.eclipse.jface.action.Action.runWithEvent(Action.java:841)\n        at org.eclipse.jface.action.ActionContributionItem.handleWidgetSelection\n(ActionContributionItem.java:456)\n        at org.eclipse.jface.action.ActionContributionItem.handleWidgetEvent\n(ActionContributionItem.java:403)\n        at org.eclipse.jface.action.ActionContributionItem.access$0\n(ActionContributionItem.java:397)\n        at \norg.eclipse.jface.action.ActionContributionItem$ActionListener.handleEvent\n(ActionContributionItem.java:72)\n        at org.eclipse.swt.widgets.EventTable.sendEvent(EventTable.java:77)\n        at org.eclipse.swt.widgets.Widget.sendEvent(Widget.java:807)\n        at org.eclipse.swt.widgets.Display.runDeferredEvents(Display.java:1829)\n        at org.eclipse.swt.widgets.Display.readAndDispatch(Display.java:1620)\n        at org.eclipse.ui.internal.Workbench.runEventLoop(Workbench.java:1271)\n        at org.eclipse.ui.internal.Workbench.run(Workbench.java:1254)\n        at org.eclipse.core.internal.boot.InternalBootLoader.run\n(InternalBootLoader.java:845)\n        at org.eclipse.core.boot.BootLoader.run(BootLoader.java:461)\n        at java.lang.reflect.Method.invoke(Native Method)\n        at org.eclipse.core.launcher.Main.basicRun(Main.java:247)\n        at org.eclipse.core.launcher.Main.run(Main.java:703)\n        at org.eclipse.core.launcher.Main.main(Main.java:539)\n!ENTRY org.eclipse.ui 4 4 Feb 26, 2003 13:51:26.436\n!MESSAGE Unhandled exception caught in event loop.",
    "\n\n*** This bug has been marked as a duplicate of 33159 ***"
  ],
  "commentCreationDates": [
    "2003-02-26T19:59:01+01:00",
    "2003-03-02T00:24:24+01:00"
  ],
  "traces": [
    {
      "exceptionType": "java.lang.StringIndexOutOfBoundsException",
      "message": "String index out of range: 44",
      "elements": [
        {
          "method": "java.lang.String.substring",
          "source": "String.java:1517"
        },
        {
          "method": "java.net.URLDecoder.decode",
          "source": "URLDecoder.java:52"
        },
        {
          "method": "org.eclipse.update.internal.ui.wizards.NewSiteBookmarkWizardPage.validatePage",
          "source": "NewSiteBookmarkWizardPage.java:106"
        },
        {
          "method": "org.eclipse.update.internal.ui.wizards.NewSiteBookmarkWizardPage$1.modifyText",
          "source": "NewSiteBookmarkWizardPage.java:71"
        },
        {
          "method": "org.eclipse.swt.widgets.TypedListener.handleEvent",
          "source": "TypedListener.java:181"
        },
        {
          "method": "org.eclipse.swt.widgets.EventTable.sendEvent",
          "source": "EventTable.java:77"
        },
        {
          "method": "org.eclipse.swt.widgets.Widget.sendEvent",
          "source": "Widget.java:807"
        },
        {
          "method": "org.eclipse.swt.widgets.Widget.sendEvent",
          "source": "Widget.java:829"
        },
        {
          "method": "org.eclipse.swt.widgets.Widget.sendEvent",
          "source": "Widget.java:811"
        },
        {
          "method": "org.eclipse.swt.widgets.Text.XmNvalueChangedCallback",
          "source": "Text.java:1518"
        },
        {
          "method": "org.eclipse.swt.widgets.Widget.windowProc",
          "source": "Widget.java:1017"
        },
        {
          "method": "org.eclipse.swt.widgets.Display.windowProc",
          "source": "Display.java:2296"
        },
        {
          "method": "org.eclipse.swt.internal.motif.OS.XtDispatchEvent",
          "source": "Native Method"
        },
        {
          "method": "org.eclipse.swt.widgets.Display.readAndDispatch",
          "source": "Display.java:1618"
        },
        {
          "method": "org.eclipse.jface.window.Window.runEventLoop",
          "source": "Window.java:577"
        },
        {
          "method": "org.eclipse.jface.window.Window.open",
          "source": "Window.java:557"
        },
        {
          "method": "org.eclipse.update.internal.ui.views.UpdatesView.performNewBookmark",
          "source": "UpdatesView.java:791"
        },
        {
          "method": "org.eclipse.update.internal.ui.views.UpdatesView.access$10",
          "source": "UpdatesView.java:779"
        },
        {
          "method": "org.eclipse.update.internal.ui.views.UpdatesView$1.run",
          "source": "UpdatesView.java:485"
        },
        {
          "method": "org.eclipse.jface.action.Action.runWithEvent",
          "source": "Action.java:841"
        },
        {
          "method": "org.eclipse.jface.action.ActionContributionItem.handleWidgetSelection",
          "source": "ActionContributionItem.java:456"
        },
        {
          "method": "org.eclipse.jface.action.ActionContributionItem.handleWidgetEvent",
          "source": "ActionContributionItem.java:403"
        },
        {
          "method": "org.eclipse.jface.action.ActionContributionItem.access$0",
          "source": "ActionContributionItem.java:397"
        },
        {
          "method": "org.eclipse.jface.action.ActionContributionItem$ActionListener.handleEvent",
          "source": "ActionContributionItem.java:72"
        },
        {
          "method": "org.eclipse.swt.widgets.EventTable.sendEvent",
          "source": "EventTable.java:77"
        },
        {
          "method": "org.eclipse.swt.widgets.Widget.sendEvent",
          "source": "Widget.java:807"
        },
        {
          "method": "org.eclipse.swt.widgets.Display.runDeferredEvents",
          "source": "Display.java:1829"
        },
        {
          "method": "org.eclipse.swt.widgets.Display.readAndDispatch",
          "source": "Display.java:1620"
        },
        {
          "method": "org.eclipse.ui.internal.Workbench.runEventLoop",
          "source": "Workbench.java:1271"
        },
        {
          "method": "org.eclipse.ui.internal.Workbench.run",
          "source": "Workbench.java:1254"
        },
        {
          "method": "org.eclipse.core.internal.boot.InternalBootLoader.run",
          "source": "InternalBootLoader.java:845"
        },
        {
          "method": "org.eclipse.core.boot.BootLoader.run",
          "source": "BootLoader.java:461"
        },
        {
          "method": "java.lang.reflect.Method.invoke",
          "source": "Native Method"
        },
        {
          "method": "org.eclipse.core.launcher.Main.basicRun",
          "source": "Main.java:247"
        },
        {
          "method": "org.eclipse.core.launcher.Main.run",
          "source": "Main.java:703"
        },
        {
          "method": "org.eclipse.core.launcher.Main.main",
          "source": "Main.java:539"
        }
      ],
      "number": 0,
      "commentIndex": 0,
      "bugId": "33342",
      "duplicateId": "33159",
      "date": "2003-02-26T19:59:01+01:00",
      "product": "Platform",
      "component": "Update",
      "severity": "normal"
    },
    {
      "exceptionType": "java.lang.StringIndexOutOfBoundsException",
      "message": "String index out of range: 55",
      "elements": [
        {
          "method": "java.lang.String.substring",
          "source": "String.java:1517"
        },
        {
          "method": "java.net.URLDecoder.decode",
          "source": "URLDecoder.java:52"
        },
        {
          "method": "org.eclipse.update.internal.ui.wizards.NewSiteBookmarkWizardPage.validatePage",
          "source": "NewSiteBookmarkWizardPage.java:106"
        },
        {
          "method": "org.eclipse.update.internal.ui.wizards.NewSiteBookmarkWizardPage$1.modifyText",
          "source": "NewSiteBookmarkWizardPage.java:71"
        },
        {
          "method": "org.eclipse.swt.widgets.TypedListener.handleEvent",
          "source": "TypedListener.java:181"
        },
        {
          "method": "org.eclipse.swt.widgets.EventTable.sendEvent",
          "source": "EventTable.java:77"
        },
        {
          "method": "org.eclipse.swt.widgets.Widget.sendEvent",
          "source": "Widget.java:807"
        },
        {
          "method": "org.eclipse.swt.widgets.Widget.sendEvent",
          "source": "Widget.java:829"
        },
        {
          "method": "org.eclipse.swt.widgets.Widget.sendEvent",
          "source": "Widget.java:811"
        },
        {
          "method": "org.eclipse.swt.widgets.Text.XmNvalueChangedCallback",
          "source": "Text.java:1518"
        },
        {
          "method": "org.eclipse.swt.widgets.Widget.windowProc",
          "source": "Widget.java:1017"
        },
        {
          "method": "org.eclipse.swt.widgets.Display.windowProc",
          "source": "Display.java:2296"
        },
        {
          "method": "org.eclipse.swt.internal.motif.OS.XtDispatchEvent",
          "source": "Native Method"
        },
        {
          "method": "org.eclipse.swt.widgets.Display.readAndDispatch",
          "source": "Display.java:1618"
        },
        {
          "method": "org.eclipse.jface.window.Window.runEventLoop",
          "source": "Window.java:577"
        },
        {
          "method": "org.eclipse.jface.window.Window.open",
          "source": "Window.java:557"
        },
        {
          "method": "org.eclipse.update.internal.ui.views.UpdatesView.performNewBookmark",
          "source": "UpdatesView.java:791"
        },
        {
          "method": "org.eclipse.update.internal.ui.views.UpdatesView.access$10",
          "source": "UpdatesView.java:779"
        },
        {
          "method": "org.eclipse.update.internal.ui.views.UpdatesView$1.run",
          "source": "UpdatesView.java:485"
        },
        {
          "method": "org.eclipse.jface.action.Action.runWithEvent",
          "source": "Action.java:841"
        },
        {
          "method": "org.eclipse.jface.action.ActionContributionItem.handleWidgetSelection",
          "source": "ActionContributionItem.java:456"
        },
        {
          "method": "org.eclipse.jface.action.ActionContributionItem.handleWidgetEvent",
          "source": "ActionContributionItem.java:403"
        },
        {
          "method": "org.eclipse.jface.action.ActionContributionItem.access$0",
          "source": "ActionContributionItem.java:397"
        },
        {
          "method": "org.eclipse.jface.action.ActionContributionItem$ActionListener.handleEvent",
          "source": "ActionContributionItem.java:72"
        },
        {
          "method": "org.eclipse.swt.widgets.EventTable.sendEvent",
          "source": "EventTable.java:77"
        },
        {
          "method": "org.eclipse.swt.widgets.Widget.sendEvent",
          "source": "Widget.java:807"
        },
        {
          "method": "org.eclipse.swt.widgets.Display.runDeferredEvents",
          "source": "Display.java:1829"
        },
        {
          "method": "org.eclipse.swt.widgets.Display.readAndDispatch",
          "source": "Display.java:1620"
        },
        {
          "method": "org.eclipse.ui.internal.Workbench.runEventLoop",
          "source": "Workbench.java:1271"
        },
        {
          "method": "org.eclipse.ui.internal.Workbench.run",
          "source": "Workbench.java:1254"
        },
        {
          "method": "org.eclipse.core.internal.boot.InternalBootLoader.run",
          "source": "InternalBootLoader.java:845"
        },
        {
          "method": "org.eclipse.core.boot.BootLoader.run",
          "source": "BootLoader.java:461"
        },
        {
          "method": "java.lang.reflect.Method.invoke",
          "source": "Native Method"
        },
        {
          "method": "org.eclipse.core.launcher.Main.basicRun",
          "source": "Main.java:247"
        },
        {
          "method": "org.eclipse.core.launcher.Main.run",
          "source": "Main.java:703"
        },
        {
          "method": "org.eclipse.core.launcher.Main.main",
          "source": "Main.java:539"
        }
      ],
      "number": 1,
      "commentIndex": 0,
      "bugId": "33342",
      "duplicateId": "33159",
      "date": "2003-02-26T19:59:01+01:00",
      "product": "Platform",
      "component": "Update",
      "severity": "normal"
    }
  ],
  "groupId": "33159",
  "bugId": "33342",
  "duplicateId": "33159",
  "date": "2003-02-26T19:59:01+01:00",
  "product": "Platform",
  "component": "Update",
  "severity": "normal"
}