{
  "comments": [
    "There appears to be a problem when trying to preview a refactoring operation on\none or more files which contain a file that has a CVS edit open on it. The\npreview craps out saying there was an exception, with no details available\n(sorry, it is gone now. You can then abort or go ahead. If you go ahead, you get\na message:\n  \"The resource has already editors. Do you want to edit?\"\nand when you say ok, the refactor seems to happen ok (although I should add that\npreviously I had a big blowup on a group of files which I think was due to the\nsame thing, which I said to back out of, and Eclipse was not actually able to\nback out of).\n\nHere is the console log which shows the exception that I think happens in the\npreview operation:\n\n!ENTRY org.eclipse.core.resources 4 2 Mar 03, 2003 18:34:44.910\n!MESSAGE Problems occurred when invoking code from plug-in: \"org.eclipse.core.re\nsources\".\n!STACK 0\norg.eclipse.swt.SWTException: Invalid thread access\n        at org.eclipse.swt.SWT.error(SWT.java:2316)\n        at org.eclipse.swt.SWT.error(SWT.java:2246)\n        at org.eclipse.swt.widgets.Widget.error(Widget.java:381)\n        at org.eclipse.swt.widgets.Shell.\u003cinit\u003e(Shell.java:242)\n        at org.eclipse.swt.widgets.Shell.\u003cinit\u003e(Shell.java:320)\n        at org.eclipse.jface.window.Window.createShell(Window.java:329)\n        at org.eclipse.jface.window.Window.create(Window.java:295)\n        at org.eclipse.jface.window.Window.open(Window.java:546)\n        at org.eclipse.team.internal.ccvs.ui.actions.EditorsAction.promptToEdit(\nEditorsAction.java:74)\n        at org.eclipse.team.internal.ccvs.ui.FileModificationValidator.promptToE\nditFiles(FileModificationValidator.java:160)\n        at org.eclipse.team.internal.ccvs.ui.FileModificationValidator.edit(File\nModificationValidator.java:124)\n        at org.eclipse.team.internal.ccvs.ui.FileModificationValidator.validateE\ndit(FileModificationValidator.java:51)\n        at org.eclipse.team.internal.core.FileModificationValidatorManager.valid\nateEdit(FileModificationValidatorManager.java:64)\n        at org.eclipse.core.internal.resources.Workspace$4.run(Workspace.java:17\n81)\n        at org.eclipse.core.internal.runtime.InternalPlatform.run(InternalPlatfo\nrm.java:867)\n        at org.eclipse.core.runtime.Platform.run(Platform.java:413)\n        at org.eclipse.core.internal.resources.Workspace.validateEdit(Workspace.\njava:1787)\n        at org.eclipse.jdt.internal.corext.util.Resources.makeCommittable(Resour\nces.java:114)\n        at org.eclipse.jdt.internal.corext.refactoring.Checks.validateModifiesFi\nles(Checks.java:535)\n        at org.eclipse.jdt.internal.corext.refactoring.reorg.MoveRefactoring.val\nidateModifiesFiles(MoveRefactoring.java:288)\n        at org.eclipse.jdt.internal.corext.refactoring.reorg.MoveRefactoring.che\nckInput(MoveRefactoring.java:162)\n        at org.eclipse.jdt.internal.ui.refactoring.CheckConditionsOperation.run(\nCheckConditionsOperation.java:59)\n        at org.eclipse.jdt.internal.ui.refactoring.CreateChangeOperation.run(Cre\nateChangeOperation.java:94)\n        at org.eclipse.jface.operation.ModalContext$ModalContextThread.run(Modal\nContext.java:95)",
    "I am not sure if this is related or not, but I want to add that when I now do an\nupdate, the directory which I refactored to move the files out of now comes up\nwith a message:\n\nCVS Synchronization information could not be found for the folder\n\u0027/emulator/src/java/main/com/tira/emulator\u0027. \n\n",
    "I have released the fix for the exception to HEAD.\n\nThe second problem you mentioned has already been fixed.",
    "You might want to fix the grammar on the message about the editors, too :-)\n   \"The resource has already editors. Do you want to edit?\"\n"
  ],
  "commentCreationDates": [
    "2003-03-03T23:47:54+01:00",
    "2003-03-03T23:57:31+01:00",
    "2003-03-04T14:39:31+01:00",
    "2003-03-04T14:45:43+01:00"
  ],
  "traces": [
    {
      "exceptionType": "org.eclipse.swt.SWTException",
      "message": "Invalid thread access",
      "elements": [
        {
          "method": "org.eclipse.swt.SWT.error",
          "source": "SWT.java:2316"
        },
        {
          "method": "org.eclipse.swt.SWT.error",
          "source": "SWT.java:2246"
        },
        {
          "method": "org.eclipse.swt.widgets.Widget.error",
          "source": "Widget.java:381"
        },
        {
          "method": "org.eclipse.swt.widgets.Shell.\u003cinit\u003e",
          "source": "Shell.java:242"
        },
        {
          "method": "org.eclipse.swt.widgets.Shell.\u003cinit\u003e",
          "source": "Shell.java:320"
        },
        {
          "method": "org.eclipse.jface.window.Window.createShell",
          "source": "Window.java:329"
        },
        {
          "method": "org.eclipse.jface.window.Window.create",
          "source": "Window.java:295"
        },
        {
          "method": "org.eclipse.jface.window.Window.open",
          "source": "Window.java:546"
        },
        {
          "method": "org.eclipse.team.internal.ccvs.ui.actions.EditorsAction.promptToEdit",
          "source": " EditorsAction.java:74"
        },
        {
          "method": "org.eclipse.team.internal.ccvs.ui.FileModificationValidator.promptToEditFiles",
          "source": "FileModificationValidator.java:160"
        },
        {
          "method": "org.eclipse.team.internal.ccvs.ui.FileModificationValidator.edit",
          "source": "File ModificationValidator.java:124"
        },
        {
          "method": "org.eclipse.team.internal.ccvs.ui.FileModificationValidator.validateEdit",
          "source": "FileModificationValidator.java:51"
        },
        {
          "method": "org.eclipse.team.internal.core.FileModificationValidatorManager.validateEdit",
          "source": "FileModificationValidatorManager.java:64"
        },
        {
          "method": "org.eclipse.core.internal.resources.Workspace$4.run",
          "source": "Workspace.java:17 81"
        },
        {
          "method": "org.eclipse.core.internal.runtime.InternalPlatform.run",
          "source": "InternalPlatfo rm.java:867"
        },
        {
          "method": "org.eclipse.core.runtime.Platform.run",
          "source": "Platform.java:413"
        },
        {
          "method": "org.eclipse.core.internal.resources.Workspace.validateEdit",
          "source": "Workspace. java:1787"
        },
        {
          "method": "org.eclipse.jdt.internal.corext.util.Resources.makeCommittable",
          "source": "Resour ces.java:114"
        },
        {
          "method": "org.eclipse.jdt.internal.corext.refactoring.Checks.validateModifiesFiles",
          "source": "Checks.java:535"
        },
        {
          "method": "org.eclipse.jdt.internal.corext.refactoring.reorg.MoveRefactoring.validateModifiesFiles",
          "source": "MoveRefactoring.java:288"
        },
        {
          "method": "org.eclipse.jdt.internal.corext.refactoring.reorg.MoveRefactoring.checkInput",
          "source": "MoveRefactoring.java:162"
        },
        {
          "method": "org.eclipse.jdt.internal.ui.refactoring.CheckConditionsOperation.run",
          "source": " CheckConditionsOperation.java:59"
        },
        {
          "method": "org.eclipse.jdt.internal.ui.refactoring.CreateChangeOperation.run",
          "source": "Cre ateChangeOperation.java:94"
        },
        {
          "method": "org.eclipse.jface.operation.ModalContext$ModalContextThread.run",
          "source": "Modal Context.java:95"
        }
      ],
      "number": 0,
      "commentIndex": 0,
      "bugId": "33715",
      "date": "2003-03-03T23:47:54+01:00",
      "product": "Platform",
      "component": "Team",
      "severity": "normal"
    }
  ],
  "groupId": "33715",
  "bugId": "33715",
  "date": "2003-03-03T23:47:54+01:00",
  "product": "Platform",
  "component": "Team",
  "severity": "normal"
}