{
  "comments": [
    "Build 20030304\n\nIn a self-hosting workspace, I deleted shared projects jdt/core (+tests), then \nadded them back from repository, and discarded on of them (again). I noticed \nthe following dump in the .log.\n\n!ENTRY org.eclipse.debug.core 4 2 Mar 06, 2003 17:54:55.545\n!MESSAGE Problems occurred when invoking code from plug-\nin: \"org.eclipse.debug.core\".\n!STACK 0\njava.lang.NullPointerException\n        at org.eclipse.debug.internal.core.LaunchConfiguration.getMemento\n(LaunchConfiguration.java:388)\n        at \norg.eclipse.debug.internal.ui.launchConfigurations.LaunchConfigurationManager.cr\neateEntry(LaunchConfigurationManager.java:251)\n        at \norg.eclipse.debug.internal.ui.launchConfigurations.LaunchConfigurationManager.ge\ntHistoryAsXML(LaunchConfigurationManager.java:234)\n        at \norg.eclipse.debug.internal.ui.launchConfigurations.LaunchConfigurationManager.pe\nrsistLaunchHistory(LaunchConfigurationManager.java:271)\n        at org.eclipse.debug.internal.ui.launchConfigurations.LaunchHistory.save\n(LaunchHistory.java:113)\n        at \norg.eclipse.debug.internal.ui.launchConfigurations.LaunchHistory.launchConfigura\ntionRemoved(LaunchHistory.java:412)\n        at \norg.eclipse.debug.internal.core.LaunchManager$ConfigurationNotifier.run\n(LaunchManager.java:1378)\n        at org.eclipse.core.internal.runtime.InternalPlatform.run\n(InternalPlatform.java:867)\n        at org.eclipse.core.runtime.Platform.run(Platform.java:413)\n        at \norg.eclipse.debug.internal.core.LaunchManager$ConfigurationNotifier.notify\n(LaunchManager.java:1399)\n        at \norg.eclipse.debug.internal.core.LaunchManager.launchConfigurationDeleted\n(LaunchManager.java:628)\n        at \norg.eclipse.debug.internal.core.LaunchManager$LaunchManagerVisitor.visit\n(LaunchManager.java:961)\n        at org.eclipse.core.internal.events.ResourceDelta.accept\n(ResourceDelta.java:71)\n        at org.eclipse.core.internal.events.ResourceDelta.accept\n(ResourceDelta.java:79)\n        at org.eclipse.core.internal.events.ResourceDelta.accept\n(ResourceDelta.java:79)\n        at org.eclipse.core.internal.events.ResourceDelta.accept\n(ResourceDelta.java:79)\n        at org.eclipse.core.internal.events.ResourceDelta.accept\n(ResourceDelta.java:79)\n        at org.eclipse.core.internal.events.ResourceDelta.accept\n(ResourceDelta.java:52)\n        at org.eclipse.debug.internal.core.LaunchManager.resourceChanged\n(LaunchManager.java:830)\n        at org.eclipse.core.internal.events.NotificationManager$1.run\n(NotificationManager.java:137)\n        at org.eclipse.core.internal.runtime.InternalPlatform.run\n(InternalPlatform.java:867)\n        at org.eclipse.core.runtime.Platform.run(Platform.java:413)\n        at org.eclipse.core.internal.events.NotificationManager.notify\n(NotificationManager.java:152)\n        at org.eclipse.core.internal.events.NotificationManager.broadcastChanges\n(NotificationManager.java:67)\n        at org.eclipse.core.internal.resources.Workspace.broadcastChanges\n(Workspace.java:161)\n        at org.eclipse.core.internal.resources.Workspace.endOperation\n(Workspace.java:892)\n        at org.eclipse.core.internal.resources.Workspace.run\n(Workspace.java:1596)\n        at org.eclipse.ui.actions.WorkspaceModifyOperation.run\n(WorkspaceModifyOperation.java:79)\n        at org.eclipse.jface.operation.ModalContext$ModalContextThread.run\n(ModalContext.java:95)\n!ENTRY org.eclipse.debug.core 4 120 Mar 06, 2003 17:54:55.635\n!MESSAGE An exception occurred during launch configuration change notification.\n!STACK 0\njava.lang.NullPointerException\n        at org.eclipse.debug.internal.core.LaunchConfiguration.getMemento\n(LaunchConfiguration.java:388)\n        at \norg.eclipse.debug.internal.ui.launchConfigurations.LaunchConfigurationManager.cr\neateEntry(LaunchConfigurationManager.java:251)\n        at \norg.eclipse.debug.internal.ui.launchConfigurations.LaunchConfigurationManager.ge\ntHistoryAsXML(LaunchConfigurationManager.java:234)\n        at \norg.eclipse.debug.internal.ui.launchConfigurations.LaunchConfigurationManager.pe\nrsistLaunchHistory(LaunchConfigurationManager.java:271)\n        at org.eclipse.debug.internal.ui.launchConfigurations.LaunchHistory.save\n(LaunchHistory.java:113)\n        at \norg.eclipse.debug.internal.ui.launchConfigurations.LaunchHistory.launchConfigura\ntionRemoved(LaunchHistory.java:412)\n        at \norg.eclipse.debug.internal.core.LaunchManager$ConfigurationNotifier.run\n(LaunchManager.java:1378)\n        at org.eclipse.core.internal.runtime.InternalPlatform.run\n(InternalPlatform.java:867)\n        at org.eclipse.core.runtime.Platform.run(Platform.java:413)\n        at \norg.eclipse.debug.internal.core.LaunchManager$ConfigurationNotifier.notify\n(LaunchManager.java:1399)\n        at \norg.eclipse.debug.internal.core.LaunchManager.launchConfigurationDeleted\n(LaunchManager.java:628)\n        at \norg.eclipse.debug.internal.core.LaunchManager$LaunchManagerVisitor.visit\n(LaunchManager.java:961)\n        at org.eclipse.core.internal.events.ResourceDelta.accept\n(ResourceDelta.java:71)\n        at org.eclipse.core.internal.events.ResourceDelta.accept\n(ResourceDelta.java:79)\n        at org.eclipse.core.internal.events.ResourceDelta.accept\n(ResourceDelta.java:79)\n        at org.eclipse.core.internal.events.ResourceDelta.accept\n(ResourceDelta.java:79)\n        at org.eclipse.core.internal.events.ResourceDelta.accept\n(ResourceDelta.java:79)\n        at org.eclipse.core.internal.events.ResourceDelta.accept\n(ResourceDelta.java:52)\n        at org.eclipse.debug.internal.core.LaunchManager.resourceChanged\n(LaunchManager.java:830)\n        at org.eclipse.core.internal.events.NotificationManager$1.run\n(NotificationManager.java:137)\n        at org.eclipse.core.internal.runtime.InternalPlatform.run\n(InternalPlatform.java:867)\n        at org.eclipse.core.runtime.Platform.run(Platform.java:413)\n        at org.eclipse.core.internal.events.NotificationManager.notify\n(NotificationManager.java:152)\n        at org.eclipse.core.internal.events.NotificationManager.broadcastChanges\n(NotificationManager.java:67)\n        at org.eclipse.core.internal.resources.Workspace.broadcastChanges\n(Workspace.java:161)\n        at org.eclipse.core.internal.resources.Workspace.endOperation\n(Workspace.java:892)\n        at org.eclipse.core.internal.resources.Workspace.run\n(Workspace.java:1596)\n        at org.eclipse.ui.actions.WorkspaceModifyOperation.run\n(WorkspaceModifyOperation.java:79)\n        at org.eclipse.jface.operation.ModalContext$ModalContextThread.run\n(ModalContext.java:95)",
    "Looks like the underlying IFile was gone.",
    "I can reproduce this by having more than one shared config in the launch \nhistory and then delete the project containing the configs. The problem is that \nwe receive notifications one by one as configs are removed, so we try to \nretrieve a memento for a deleted config, which fails.",
    "Fixed. Check for null file in LaunchConfiguration#getMemento (and throw an \nexception). Updated launch history manager to check that a config exists before \nsaving it into the history.",
    "Please verify, Joe.",
    "Verified.\n"
  ],
  "commentCreationDates": [
    "2003-03-06T17:04:47+01:00",
    "2003-03-06T17:10:55+01:00",
    "2003-03-06T17:25:32+01:00",
    "2003-03-06T17:54:32+01:00",
    "2003-03-06T17:54:52+01:00",
    "2003-03-06T18:10:13+01:00"
  ],
  "traces": [
    {
      "exceptionType": "java.lang.NullPointerException",
      "elements": [
        {
          "method": "org.eclipse.debug.internal.core.LaunchConfiguration.getMemento",
          "source": "LaunchConfiguration.java:388"
        },
        {
          "method": "org.eclipse.debug.internal.ui.launchConfigurations.LaunchConfigurationManager.createEntry",
          "source": "LaunchConfigurationManager.java:251"
        },
        {
          "method": "org.eclipse.debug.internal.ui.launchConfigurations.LaunchConfigurationManager.getHistoryAsXML",
          "source": "LaunchConfigurationManager.java:234"
        },
        {
          "method": "org.eclipse.debug.internal.ui.launchConfigurations.LaunchConfigurationManager.persistLaunchHistory",
          "source": "LaunchConfigurationManager.java:271"
        },
        {
          "method": "org.eclipse.debug.internal.ui.launchConfigurations.LaunchHistory.save",
          "source": "LaunchHistory.java:113"
        },
        {
          "method": "org.eclipse.debug.internal.ui.launchConfigurations.LaunchHistory.launchConfigurationRemoved",
          "source": "LaunchHistory.java:412"
        },
        {
          "method": "org.eclipse.debug.internal.core.LaunchManager$ConfigurationNotifier.run",
          "source": "LaunchManager.java:1378"
        },
        {
          "method": "org.eclipse.core.internal.runtime.InternalPlatform.run",
          "source": "InternalPlatform.java:867"
        },
        {
          "method": "org.eclipse.core.runtime.Platform.run",
          "source": "Platform.java:413"
        },
        {
          "method": "org.eclipse.debug.internal.core.LaunchManager$ConfigurationNotifier.notify",
          "source": "LaunchManager.java:1399"
        },
        {
          "method": "org.eclipse.debug.internal.core.LaunchManager.launchConfigurationDeleted",
          "source": "LaunchManager.java:628"
        },
        {
          "method": "org.eclipse.debug.internal.core.LaunchManager$LaunchManagerVisitor.visit",
          "source": "LaunchManager.java:961"
        },
        {
          "method": "org.eclipse.core.internal.events.ResourceDelta.accept",
          "source": "ResourceDelta.java:71"
        },
        {
          "method": "org.eclipse.core.internal.events.ResourceDelta.accept",
          "source": "ResourceDelta.java:79"
        },
        {
          "method": "org.eclipse.core.internal.events.ResourceDelta.accept",
          "source": "ResourceDelta.java:79"
        },
        {
          "method": "org.eclipse.core.internal.events.ResourceDelta.accept",
          "source": "ResourceDelta.java:79"
        },
        {
          "method": "org.eclipse.core.internal.events.ResourceDelta.accept",
          "source": "ResourceDelta.java:79"
        },
        {
          "method": "org.eclipse.core.internal.events.ResourceDelta.accept",
          "source": "ResourceDelta.java:52"
        },
        {
          "method": "org.eclipse.debug.internal.core.LaunchManager.resourceChanged",
          "source": "LaunchManager.java:830"
        },
        {
          "method": "org.eclipse.core.internal.events.NotificationManager$1.run",
          "source": "NotificationManager.java:137"
        },
        {
          "method": "org.eclipse.core.internal.runtime.InternalPlatform.run",
          "source": "InternalPlatform.java:867"
        },
        {
          "method": "org.eclipse.core.runtime.Platform.run",
          "source": "Platform.java:413"
        },
        {
          "method": "org.eclipse.core.internal.events.NotificationManager.notify",
          "source": "NotificationManager.java:152"
        },
        {
          "method": "org.eclipse.core.internal.events.NotificationManager.broadcastChanges",
          "source": "NotificationManager.java:67"
        },
        {
          "method": "org.eclipse.core.internal.resources.Workspace.broadcastChanges",
          "source": "Workspace.java:161"
        },
        {
          "method": "org.eclipse.core.internal.resources.Workspace.endOperation",
          "source": "Workspace.java:892"
        },
        {
          "method": "org.eclipse.core.internal.resources.Workspace.run",
          "source": "Workspace.java:1596"
        },
        {
          "method": "org.eclipse.ui.actions.WorkspaceModifyOperation.run",
          "source": "WorkspaceModifyOperation.java:79"
        },
        {
          "method": "org.eclipse.jface.operation.ModalContext$ModalContextThread.run",
          "source": "ModalContext.java:95"
        }
      ],
      "number": 0,
      "commentIndex": 0,
      "bugId": "33993",
      "date": "2003-03-06T17:04:47+01:00",
      "product": "JDT",
      "component": "Debug",
      "severity": "normal"
    },
    {
      "exceptionType": "java.lang.NullPointerException",
      "elements": [
        {
          "method": "org.eclipse.debug.internal.core.LaunchConfiguration.getMemento",
          "source": "LaunchConfiguration.java:388"
        },
        {
          "method": "org.eclipse.debug.internal.ui.launchConfigurations.LaunchConfigurationManager.createEntry",
          "source": "LaunchConfigurationManager.java:251"
        },
        {
          "method": "org.eclipse.debug.internal.ui.launchConfigurations.LaunchConfigurationManager.getHistoryAsXML",
          "source": "LaunchConfigurationManager.java:234"
        },
        {
          "method": "org.eclipse.debug.internal.ui.launchConfigurations.LaunchConfigurationManager.persistLaunchHistory",
          "source": "LaunchConfigurationManager.java:271"
        },
        {
          "method": "org.eclipse.debug.internal.ui.launchConfigurations.LaunchHistory.save",
          "source": "LaunchHistory.java:113"
        },
        {
          "method": "org.eclipse.debug.internal.ui.launchConfigurations.LaunchHistory.launchConfigurationRemoved",
          "source": "LaunchHistory.java:412"
        },
        {
          "method": "org.eclipse.debug.internal.core.LaunchManager$ConfigurationNotifier.run",
          "source": "LaunchManager.java:1378"
        },
        {
          "method": "org.eclipse.core.internal.runtime.InternalPlatform.run",
          "source": "InternalPlatform.java:867"
        },
        {
          "method": "org.eclipse.core.runtime.Platform.run",
          "source": "Platform.java:413"
        },
        {
          "method": "org.eclipse.debug.internal.core.LaunchManager$ConfigurationNotifier.notify",
          "source": "LaunchManager.java:1399"
        },
        {
          "method": "org.eclipse.debug.internal.core.LaunchManager.launchConfigurationDeleted",
          "source": "LaunchManager.java:628"
        },
        {
          "method": "org.eclipse.debug.internal.core.LaunchManager$LaunchManagerVisitor.visit",
          "source": "LaunchManager.java:961"
        },
        {
          "method": "org.eclipse.core.internal.events.ResourceDelta.accept",
          "source": "ResourceDelta.java:71"
        },
        {
          "method": "org.eclipse.core.internal.events.ResourceDelta.accept",
          "source": "ResourceDelta.java:79"
        },
        {
          "method": "org.eclipse.core.internal.events.ResourceDelta.accept",
          "source": "ResourceDelta.java:79"
        },
        {
          "method": "org.eclipse.core.internal.events.ResourceDelta.accept",
          "source": "ResourceDelta.java:79"
        },
        {
          "method": "org.eclipse.core.internal.events.ResourceDelta.accept",
          "source": "ResourceDelta.java:79"
        },
        {
          "method": "org.eclipse.core.internal.events.ResourceDelta.accept",
          "source": "ResourceDelta.java:52"
        },
        {
          "method": "org.eclipse.debug.internal.core.LaunchManager.resourceChanged",
          "source": "LaunchManager.java:830"
        },
        {
          "method": "org.eclipse.core.internal.events.NotificationManager$1.run",
          "source": "NotificationManager.java:137"
        },
        {
          "method": "org.eclipse.core.internal.runtime.InternalPlatform.run",
          "source": "InternalPlatform.java:867"
        },
        {
          "method": "org.eclipse.core.runtime.Platform.run",
          "source": "Platform.java:413"
        },
        {
          "method": "org.eclipse.core.internal.events.NotificationManager.notify",
          "source": "NotificationManager.java:152"
        },
        {
          "method": "org.eclipse.core.internal.events.NotificationManager.broadcastChanges",
          "source": "NotificationManager.java:67"
        },
        {
          "method": "org.eclipse.core.internal.resources.Workspace.broadcastChanges",
          "source": "Workspace.java:161"
        },
        {
          "method": "org.eclipse.core.internal.resources.Workspace.endOperation",
          "source": "Workspace.java:892"
        },
        {
          "method": "org.eclipse.core.internal.resources.Workspace.run",
          "source": "Workspace.java:1596"
        },
        {
          "method": "org.eclipse.ui.actions.WorkspaceModifyOperation.run",
          "source": "WorkspaceModifyOperation.java:79"
        },
        {
          "method": "org.eclipse.jface.operation.ModalContext$ModalContextThread.run",
          "source": "ModalContext.java:95"
        }
      ],
      "number": 1,
      "commentIndex": 0,
      "bugId": "33993",
      "date": "2003-03-06T17:04:47+01:00",
      "product": "JDT",
      "component": "Debug",
      "severity": "normal"
    }
  ],
  "groupId": "33993",
  "bugId": "33993",
  "date": "2003-03-06T17:04:47+01:00",
  "product": "JDT",
  "component": "Debug",
  "severity": "normal"
}