{
  "comments": [
    "Eclipse N200303060010\nRH 8.0, IBM JDK 1.3.1\n\nI install eclipse and launch a new workspace.  See bug #33987 for the first log\ngenerated prior to importing any projects.\n\nTurn off automatic compile\nImport all projects as source required for the plugin org.eclipse.ui, except for\norg.eclipse.swt and org.eclipse.swt.gtk, which are imported as binary.\nTurn on compile\n\nNow open the class PropertySheetViewer.  The following log is displayed to the\nconsole, no log is genereated.\n\njava.lang.Error: Unresolved compilation problem:\n        Unreachable catch block\n\n        at java.lang.reflect.Constructor.newInstance(Native Method)\n        at\norg.eclipse.jdt.internal.ui.javaeditor.CompilationUnitDocumentProvider$CompilationUnitAnnotationModel.beginReporting(CompilationUnitDocumentProvider.java:409)\n        at\norg.eclipse.jdt.internal.core.ReconcileWorkingCopyOperation.executeOperation(ReconcileWorkingCopyOperation.java:61)\n        at\norg.eclipse.jdt.internal.core.JavaModelOperation.execute(JavaModelOperation.java:365)\n        at\norg.eclipse.jdt.internal.core.JavaModelOperation.run(JavaModelOperation.java:681)\n        at\norg.eclipse.jdt.internal.core.JavaElement.runOperation(JavaElement.java:538)\n        at org.eclipse.jdt.internal.core.WorkingCopy.reconcile(WorkingCopy.java:438)\n        at\norg.eclipse.jdt.internal.ui.text.java.JavaReconcilingStrategy.reconcile(JavaReconcilingStrategy.java:72)\n        at\norg.eclipse.jdt.internal.ui.text.java.JavaReconcilingStrategy.initialReconcile(JavaReconcilingStrategy.java:126)\n        at\norg.eclipse.jface.text.reconciler.MonoReconciler.initialProcess(MonoReconciler.java:104)\n       at\norg.eclipse.jface.text.reconciler.AbstractReconciler$BackgroundThread.run(AbstractReconciler.java:155)",
    "This is a consequence of JDT/UI not having reacted to a change into JDT/Core, \nwhich caused the nightly build to have compile errors.\n\nWhat you saw is the expected behavior when running code which had compile \nerrors, and exception is thrown to remind of this issue.\n\n(one can turn this compiler feature, i.e. if error detected then no classfile \nis produced)",
    "Got addressed for RC2.",
    "I20030318"
  ],
  "commentCreationDates": [
    "2003-03-06T16:57:04+01:00",
    "2003-03-06T17:10:38+01:00",
    "2003-03-06T17:15:25+01:00",
    "2003-03-19T15:46:12+01:00"
  ],
  "traces": [
    {
      "exceptionType": "java.lang.Error",
      "message": "Unresolved compilation problem:         Unreachable catch block",
      "elements": [
        {
          "method": "java.lang.reflect.Constructor.newInstance",
          "source": "Native Method"
        },
        {
          "method": "org.eclipse.jdt.internal.ui.javaeditor.CompilationUnitDocumentProvider$CompilationUnitAnnotationModel.beginReporting",
          "source": "CompilationUnitDocumentProvider.java:409"
        },
        {
          "method": "org.eclipse.jdt.internal.core.ReconcileWorkingCopyOperation.executeOperation",
          "source": "ReconcileWorkingCopyOperation.java:61"
        },
        {
          "method": "org.eclipse.jdt.internal.core.JavaModelOperation.execute",
          "source": "JavaModelOperation.java:365"
        },
        {
          "method": "org.eclipse.jdt.internal.core.JavaModelOperation.run",
          "source": "JavaModelOperation.java:681"
        },
        {
          "method": "org.eclipse.jdt.internal.core.JavaElement.runOperation",
          "source": "JavaElement.java:538"
        },
        {
          "method": "org.eclipse.jdt.internal.core.WorkingCopy.reconcile",
          "source": "WorkingCopy.java:438"
        },
        {
          "method": "org.eclipse.jdt.internal.ui.text.java.JavaReconcilingStrategy.reconcile",
          "source": "JavaReconcilingStrategy.java:72"
        },
        {
          "method": "org.eclipse.jdt.internal.ui.text.java.JavaReconcilingStrategy.initialReconcile",
          "source": "JavaReconcilingStrategy.java:126"
        },
        {
          "method": "org.eclipse.jface.text.reconciler.MonoReconciler.initialProcess",
          "source": "MonoReconciler.java:104"
        },
        {
          "method": "org.eclipse.jface.text.reconciler.AbstractReconciler$BackgroundThread.run",
          "source": "AbstractReconciler.java:155"
        }
      ],
      "number": 0,
      "commentIndex": 0,
      "bugId": "33991",
      "date": "2003-03-06T16:57:04+01:00",
      "product": "JDT",
      "component": "UI",
      "severity": "critical"
    }
  ],
  "groupId": "33991",
  "bugId": "33991",
  "date": "2003-03-06T16:57:04+01:00",
  "product": "JDT",
  "component": "UI",
  "severity": "critical"
}