{
  "comments": [
    "Eclipse 200303062359\nRH 8.0\n\nSee also bug #34128 for slightly different setup.\n\nLaunch eclipse with a new workspace.\nTurn off automatic compile\nFrom CVS load platform-core, platform-ui, platform-ui-examples, org.eclipse.swt\nand org.eclipse.swt.gtk\nCopy the .classpath_gtk in org.eclipse.swt to .classpath.\nImport all required plug-ins as source\nImport org.eclipse.apache as binary (you can\u0027t bring this in as source due to\nanother bug).\n\nAt no time was I prompted as I was in bug #34128 to alter classpaths etc.\nNow turn on compile.\n\nEverything compiles.\nNow launch a debug session.\n\nThe following log is generated:\n\n!ENTRY org.eclipse.debug.ui 4 120 Mar 07, 2003 13:50:35.685\n!MESSAGE Error logged from Debug UI:\n!STACK 1\norg.eclipse.core.runtime.CoreException: Launching failed. Required Library\n\"startup.jar\" is missing from the target platform.\n        at\norg.eclipse.pde.internal.ui.launcher.WorkbenchLaunchConfigurationDelegate.createWorkspaceRunnerConfiguration(WorkbenchLaunchConfigurationDeleg\nate.java:162)\n        at\norg.eclipse.pde.internal.ui.launcher.WorkbenchLaunchConfigurationDelegate.launch(WorkbenchLaunchConfigurationDelegate.java:74)\n        at\norg.eclipse.debug.internal.core.LaunchConfiguration.launch(LaunchConfiguration.java:152)\n        at\norg.eclipse.debug.internal.ui.DebugUIPlugin.buildAndLaunch(DebugUIPlugin.java:672)\n        at org.eclipse.debug.ui.DebugUITools.buildAndLaunch(DebugUITools.java:537)\n        at org.eclipse.debug.ui.DebugUITools$2.run(DebugUITools.java:486)\n        at\norg.eclipse.jface.operation.ModalContext$ModalContextThread.run(ModalContext.java:95)\n\nWhat am I missing?\nI tried setting the non-workspace plug-ins via the PDE preference page target\nplatform, selecting all, but that made no difference.",
    "Followed all the steps verbatim using I-20030307 and was able to launch without\nany problems.",
    "Agree, I was just updating the text myself.  This might have been related to a \nCVS bug that was fixed between 200303062369 and 200303071024\n\nAnother interesting bug that was fixed as a result of the CVS corruption is bug \n#34137 in which motif would not launch debug due to a corrupt .gif file.  \nThe .gif file was missing one byte, the line-feed.\n\nSorry about that.  I will now go verify bug #34128"
  ],
  "commentCreationDates": [
    "2003-03-07T19:40:59+01:00",
    "2003-03-07T22:38:01+01:00",
    "2003-03-07T22:55:14+01:00"
  ],
  "traces": [
    {
      "exceptionType": "org.eclipse.core.runtime.CoreException",
      "message": "Launching failed. Required Library \"startup.jar\" is missing from the target platform.",
      "elements": [
        {
          "method": "org.eclipse.pde.internal.ui.launcher.WorkbenchLaunchConfigurationDelegate.createWorkspaceRunnerConfiguration",
          "source": "WorkbenchLaunchConfigurationDeleg ate.java:162"
        },
        {
          "method": "org.eclipse.pde.internal.ui.launcher.WorkbenchLaunchConfigurationDelegate.launch",
          "source": "WorkbenchLaunchConfigurationDelegate.java:74"
        },
        {
          "method": "org.eclipse.debug.internal.core.LaunchConfiguration.launch",
          "source": "LaunchConfiguration.java:152"
        },
        {
          "method": "org.eclipse.debug.internal.ui.DebugUIPlugin.buildAndLaunch",
          "source": "DebugUIPlugin.java:672"
        },
        {
          "method": "org.eclipse.debug.ui.DebugUITools.buildAndLaunch",
          "source": "DebugUITools.java:537"
        },
        {
          "method": "org.eclipse.debug.ui.DebugUITools$2.run",
          "source": "DebugUITools.java:486"
        },
        {
          "method": "org.eclipse.jface.operation.ModalContext$ModalContextThread.run",
          "source": "ModalContext.java:95"
        }
      ],
      "number": 0,
      "commentIndex": 0,
      "bugId": "34133",
      "date": "2003-03-07T19:40:59+01:00",
      "product": "PDE",
      "component": "UI",
      "severity": "normal"
    }
  ],
  "groupId": "34133",
  "bugId": "34133",
  "date": "2003-03-07T19:40:59+01:00",
  "product": "PDE",
  "component": "UI",
  "severity": "normal"
}