{
  "comments": [
    "RC2\nJDT SmokeTest\nhttp://www.zrh.oti.com/webprojects/jabiru2000/smoketest/smoke.htm\nGoing through the Java Resource Compare list\nFrom the resource view, I copied a folder and renamed it.\nI switched to the java perspective and got a dialog \u0027error occured in this\nview\u0027. The log file contains a few of these exceptions.\n\n!ENTRY org.eclipse.ui 4 4 Mar 10, 2003 15:03:14.514\n!MESSAGE Unhandled exception caught in event loop.\n!ENTRY org.eclipse.ui 4 0 Mar 10, 2003 15:03:14.542\n!MESSAGE Widget is disposed\n!STACK 0\norg.eclipse.swt.SWTException: Widget is disposed\n        at org.eclipse.swt.SWT.error(SWT.java:2316)\n        at org.eclipse.swt.SWT.error(SWT.java:2246)\n        at org.eclipse.swt.widgets.Widget.error(Widget.java:334)\n        at org.eclipse.swt.widgets.SelectableItem.getDisplay(SelectableItem.java\n:142)\n        at org.eclipse.swt.widgets.TreeItem.getDisplay(TreeItem.java:1250)\n        at org.eclipse.swt.widgets.Widget.isValidThread(Widget.java:495)\n        at org.eclipse.swt.widgets.Widget.checkWidget(Widget.java:272)\n        at org.eclipse.swt.widgets.TreeItem.getParentItem(TreeItem.java:750)\n        at org.eclipse.swt.widgets.TreeItem.isRoot(TreeItem.java:956)\n        at org.eclipse.swt.widgets.TreeItem.getVisibleIndex(TreeItem.java:845)\n        at org.eclipse.swt.widgets.Tree.getVisibleIndex(Tree.java:761)\n        at org.eclipse.swt.widgets.SelectableItemWidget.getRedrawY(SelectableIte\nmWidget.java:1023)\n        at org.eclipse.swt.widgets.Tree.getVisibleRedrawY(Tree.java:794)\n        at org.eclipse.swt.widgets.SelectableItemWidget.redrawSelection(Selectab\nleItemWidget.java:1425)\n        at org.eclipse.swt.widgets.SelectableItemWidget.focusOut(SelectableItemW\nidget.java:832)\n        at org.eclipse.swt.widgets.SelectableItemWidget.handleEvents(SelectableI\ntemWidget.java:1155)\n        at org.eclipse.swt.widgets.Tree.handleEvents(Tree.java:816)\n        at org.eclipse.swt.widgets.SelectableItemWidget$1.handleEvent(Selectable\nItemWidget.java:1192)\n        at org.eclipse.swt.widgets.EventTable.sendEvent(EventTable.java:77)\n        at org.eclipse.swt.widgets.Widget.sendEvent(Widget.java:805)\n        at org.eclipse.swt.widgets.Display.runDeferredEvents(Display.java:1912)\n        at org.eclipse.swt.widgets.Display.readAndDispatch(Display.java:1679)\n        at org.eclipse.ui.internal.Workbench.runEventLoop(Workbench.java:1400)\n        at org.eclipse.ui.internal.Workbench.run(Workbench.java:1383)\n        at org.eclipse.core.internal.boot.InternalBootLoader.run(InternalBootLoa\nder.java:845)\n        at org.eclipse.core.boot.BootLoader.run(BootLoader.java:461)\n        at java.lang.reflect.Method.invoke(Native Method)\n        at org.eclipse.core.launcher.Main.basicRun(Main.java:247)\n        at org.eclipse.core.launcher.Main.run(Main.java:703)\n        at org.eclipse.core.launcher.Main.main(Main.java:539)",
    "The exact message dialog is:\nAn error has occured when activating this view",
    "Cannot reproduce with either a new workspace or with chris\u0027 workspace that had \nthis problem.  Will revisit this during next test pass, time permitting.\n",
    "I suspect that this is the same problem as bug 35774 and bug 35244 (though \nthese bugs appear as GP\u0027s on Solaris, they were disposed widget errors on \nhpux).  If so then this is now fixed, but I can\u0027t prove it since I couldn\u0027t \nreproduce it.  Will keep report open for now.\n",
    "Closing since I haven\u0027t seen/heard about this since.  It seems like a bug that \nwould have been fixed by the introduction of the focus proxy."
  ],
  "commentCreationDates": [
    "2003-03-10T20:18:42+01:00",
    "2003-03-10T20:20:22+01:00",
    "2003-03-12T14:40:07+01:00",
    "2003-04-10T18:08:33+02:00",
    "2003-07-16T16:02:00+02:00"
  ],
  "traces": [
    {
      "exceptionType": "org.eclipse.swt.SWTException",
      "message": "Widget is disposed",
      "elements": [
        {
          "method": "org.eclipse.swt.SWT.error",
          "source": "SWT.java:2316"
        },
        {
          "method": "org.eclipse.swt.SWT.error",
          "source": "SWT.java:2246"
        },
        {
          "method": "org.eclipse.swt.widgets.Widget.error",
          "source": "Widget.java:334"
        },
        {
          "method": "org.eclipse.swt.widgets.SelectableItem.getDisplay",
          "source": "SelectableItem.java :142"
        },
        {
          "method": "org.eclipse.swt.widgets.TreeItem.getDisplay",
          "source": "TreeItem.java:1250"
        },
        {
          "method": "org.eclipse.swt.widgets.Widget.isValidThread",
          "source": "Widget.java:495"
        },
        {
          "method": "org.eclipse.swt.widgets.Widget.checkWidget",
          "source": "Widget.java:272"
        },
        {
          "method": "org.eclipse.swt.widgets.TreeItem.getParentItem",
          "source": "TreeItem.java:750"
        },
        {
          "method": "org.eclipse.swt.widgets.TreeItem.isRoot",
          "source": "TreeItem.java:956"
        },
        {
          "method": "org.eclipse.swt.widgets.TreeItem.getVisibleIndex",
          "source": "TreeItem.java:845"
        },
        {
          "method": "org.eclipse.swt.widgets.Tree.getVisibleIndex",
          "source": "Tree.java:761"
        },
        {
          "method": "org.eclipse.swt.widgets.SelectableItemWidget.getRedrawY",
          "source": "SelectableIte mWidget.java:1023"
        },
        {
          "method": "org.eclipse.swt.widgets.Tree.getVisibleRedrawY",
          "source": "Tree.java:794"
        },
        {
          "method": "org.eclipse.swt.widgets.SelectableItemWidget.redrawSelection",
          "source": "Selectab leItemWidget.java:1425"
        },
        {
          "method": "org.eclipse.swt.widgets.SelectableItemWidget.focusOut",
          "source": "SelectableItemW idget.java:832"
        },
        {
          "method": "org.eclipse.swt.widgets.SelectableItemWidget.handleEvents",
          "source": "SelectableI temWidget.java:1155"
        },
        {
          "method": "org.eclipse.swt.widgets.Tree.handleEvents",
          "source": "Tree.java:816"
        },
        {
          "method": "org.eclipse.swt.widgets.SelectableItemWidget$1.handleEvent",
          "source": "Selectable ItemWidget.java:1192"
        },
        {
          "method": "org.eclipse.swt.widgets.EventTable.sendEvent",
          "source": "EventTable.java:77"
        },
        {
          "method": "org.eclipse.swt.widgets.Widget.sendEvent",
          "source": "Widget.java:805"
        },
        {
          "method": "org.eclipse.swt.widgets.Display.runDeferredEvents",
          "source": "Display.java:1912"
        },
        {
          "method": "org.eclipse.swt.widgets.Display.readAndDispatch",
          "source": "Display.java:1679"
        },
        {
          "method": "org.eclipse.ui.internal.Workbench.runEventLoop",
          "source": "Workbench.java:1400"
        },
        {
          "method": "org.eclipse.ui.internal.Workbench.run",
          "source": "Workbench.java:1383"
        },
        {
          "method": "org.eclipse.core.internal.boot.InternalBootLoader.run",
          "source": "InternalBootLoa der.java:845"
        },
        {
          "method": "org.eclipse.core.boot.BootLoader.run",
          "source": "BootLoader.java:461"
        },
        {
          "method": "java.lang.reflect.Method.invoke",
          "source": "Native Method"
        },
        {
          "method": "org.eclipse.core.launcher.Main.basicRun",
          "source": "Main.java:247"
        },
        {
          "method": "org.eclipse.core.launcher.Main.run",
          "source": "Main.java:703"
        },
        {
          "method": "org.eclipse.core.launcher.Main.main",
          "source": "Main.java:539"
        }
      ],
      "number": 0,
      "commentIndex": 0,
      "bugId": "34436",
      "date": "2003-03-10T20:18:42+01:00",
      "product": "Platform",
      "component": "SWT",
      "severity": "major"
    }
  ],
  "groupId": "34436",
  "bugId": "34436",
  "date": "2003-03-10T20:18:42+01:00",
  "product": "Platform",
  "component": "SWT",
  "severity": "major"
}