{
  "comments": [
    "Build RC2\n\nI have several launches in the Debug view. The last but one is still active. \nAll others are terminated. When I hover in a Java editor, I get the following \nstack trace:\n\n!ENTRY org.eclipse.jdt.debug 4 5010 Mar 11, 2003 15:13:39.204\n!MESSAGE com.sun.jdi.VMDisconnectedException: Got IOException from Virtual \nMachine occurred retrieving stack frames.\n!STACK 0\ncom.sun.jdi.VMDisconnectedException: Got IOException from Virtual Machine\n        at org.eclipse.jdi.internal.connect.PacketSendManager.sendPacket\n(PacketSendManager.java:75)\n        at org.eclipse.jdi.internal.MirrorImpl.requestVM(MirrorImpl.java:163)\n        at org.eclipse.jdi.internal.MirrorImpl.requestVM(MirrorImpl.java:185)\n        at org.eclipse.jdi.internal.ThreadReferenceImpl.frames\n(ThreadReferenceImpl.java:181)\n        at org.eclipse.jdi.internal.ThreadReferenceImpl.frames\n(ThreadReferenceImpl.java:165)\n        at \norg.eclipse.jdt.internal.debug.core.model.JDIThread.getUnderlyingFrames\n(JDIThread.java:537)\n        at \norg.eclipse.jdt.internal.debug.core.model.JDIThread.createAllStackFrames\n(JDIThread.java:514)\n        at \norg.eclipse.jdt.internal.debug.core.model.JDIThread.computeStackFrames\n(JDIThread.java:390)\n        at \norg.eclipse.jdt.internal.debug.core.model.JDIThread.computeStackFrames\n(JDIThread.java:486)\n        at org.eclipse.jdt.internal.debug.core.model.JDIThread.getStackFrames\n(JDIThread.java:374)\n        at org.eclipse.jdt.internal.debug.core.model.JDIThread.findVariable\n(JDIThread.java:1572)\n        at org.eclipse.jdt.internal.debug.core.model.JDIDebugTarget.findVariable\n(JDIDebugTarget.java:1288)\n        at org.eclipse.jdt.internal.debug.ui.JavaDebugHover.getHoverInfo\n(JavaDebugHover.java:91)\n        at \norg.eclipse.jdt.internal.ui.text.java.hover.BestMatchHover.getHoverInfo\n(BestMatchHover.java:131)\n        at \norg.eclipse.jdt.internal.ui.text.java.hover.JavaEditorTextHoverProxy.getHoverInf\no(JavaEditorTextHoverProxy.java:72)\n        at org.eclipse.jface.text.TextViewerHoverManager$2.run\n(TextViewerHoverManager.java:110)",
    "More info: I have another \u0027unterminated\u0027 launch. Its \u0027javaw.exe\u0027 process is \nmarked as \u003cterminated\u003e, but the VM is marked as suspended. It has several \nthreads that are marked as \u003cnot responding\u003e. I verified with the Windows Task \nManager that the corresponding process is not running.\n\nI cannot remove this launch (the Remove All Terminated Launches button is \ngreyed out).",
    "You should be able to use \"terminate and remove\" from the context menu when a \nVM gets into a \"broken\" state.",
    "This menu item was disabled as well.",
    "Deferred",
    "Closing."
  ],
  "commentCreationDates": [
    "2003-03-11T14:23:06+01:00",
    "2003-03-11T15:15:30+01:00",
    "2003-03-12T03:27:30+01:00",
    "2003-03-12T08:33:45+01:00",
    "2003-03-19T16:40:34+01:00",
    "2004-11-09T19:46:13+01:00"
  ],
  "traces": [
    {
      "exceptionType": "com.sun.jdi.VMDisconnectedException",
      "message": "Got IOException from Virtual Machine",
      "elements": [
        {
          "method": "org.eclipse.jdi.internal.connect.PacketSendManager.sendPacket",
          "source": "PacketSendManager.java:75"
        },
        {
          "method": "org.eclipse.jdi.internal.MirrorImpl.requestVM",
          "source": "MirrorImpl.java:163"
        },
        {
          "method": "org.eclipse.jdi.internal.MirrorImpl.requestVM",
          "source": "MirrorImpl.java:185"
        },
        {
          "method": "org.eclipse.jdi.internal.ThreadReferenceImpl.frames",
          "source": "ThreadReferenceImpl.java:181"
        },
        {
          "method": "org.eclipse.jdi.internal.ThreadReferenceImpl.frames",
          "source": "ThreadReferenceImpl.java:165"
        },
        {
          "method": "org.eclipse.jdt.internal.debug.core.model.JDIThread.getUnderlyingFrames",
          "source": "JDIThread.java:537"
        },
        {
          "method": "org.eclipse.jdt.internal.debug.core.model.JDIThread.createAllStackFrames",
          "source": "JDIThread.java:514"
        },
        {
          "method": "org.eclipse.jdt.internal.debug.core.model.JDIThread.computeStackFrames",
          "source": "JDIThread.java:390"
        },
        {
          "method": "org.eclipse.jdt.internal.debug.core.model.JDIThread.computeStackFrames",
          "source": "JDIThread.java:486"
        },
        {
          "method": "org.eclipse.jdt.internal.debug.core.model.JDIThread.getStackFrames",
          "source": "JDIThread.java:374"
        },
        {
          "method": "org.eclipse.jdt.internal.debug.core.model.JDIThread.findVariable",
          "source": "JDIThread.java:1572"
        },
        {
          "method": "org.eclipse.jdt.internal.debug.core.model.JDIDebugTarget.findVariable",
          "source": "JDIDebugTarget.java:1288"
        },
        {
          "method": "org.eclipse.jdt.internal.debug.ui.JavaDebugHover.getHoverInfo",
          "source": "JavaDebugHover.java:91"
        },
        {
          "method": "org.eclipse.jdt.internal.ui.text.java.hover.BestMatchHover.getHoverInfo",
          "source": "BestMatchHover.java:131"
        },
        {
          "method": "org.eclipse.jdt.internal.ui.text.java.hover.JavaEditorTextHoverProxy.getHoverInfo",
          "source": "JavaEditorTextHoverProxy.java:72"
        },
        {
          "method": "org.eclipse.jface.text.TextViewerHoverManager$2.run",
          "source": "TextViewerHoverManager.java:110"
        }
      ],
      "number": 0,
      "commentIndex": 0,
      "bugId": "34601",
      "date": "2003-03-11T14:23:06+01:00",
      "product": "JDT",
      "component": "Debug",
      "severity": "normal"
    }
  ],
  "groupId": "34601",
  "bugId": "34601",
  "date": "2003-03-11T14:23:06+01:00",
  "product": "JDT",
  "component": "Debug",
  "severity": "normal"
}