{
  "comments": [
    "build RC2\n\nI set up disk quotas on my machine so that they would be exceeded while saving a\nfile. The file save seemed to work, I did not get an error message.\nWhen I shutdown the workbench I got an internal error inidcating a problem\nwriting a workspace state file.\nA stack trace was dumped to the console.\nWhen I tried to restart I got another stack dump to the console and the\n\"Problems during startup\" dialog. The dialog refers me to the .log file. The log\nfile is empty because I have exceeded my disk quota.",
    "Do we handle \"out of disk space\" during startup? If so we should probably treat\nthe IOException: Disk quota exceeded like a regular out of disk space.\n\nAn exception occurred while writing to the platform log:\njava.io.IOException: Disk quota exceeded\n        at java.io.FileOutputStream.writeBytes(Native Method)\n        at java.io.FileOutputStream.write(FileOutputStream.java:257)\n        at sun.nio.cs.StreamEncoder$CharsetSE.writeBytes(StreamEncoder.java:334)\n        at\nsun.nio.cs.StreamEncoder$CharsetSE.implFlushBuffer(StreamEncoder.java:402)\n        at sun.nio.cs.StreamEncoder$CharsetSE.implFlush(StreamEncoder.java:406)\n        at sun.nio.cs.StreamEncoder.flush(StreamEncoder.java:150)\n        at java.io.OutputStreamWriter.flush(OutputStreamWriter.java:213)\n        at java.io.BufferedWriter.flush(BufferedWriter.java:230)\n        at org.eclipse.core.launcher.Main.closeLogFile(Main.java:1372)\n        at org.eclipse.core.launcher.Main.log(Main.java:1233)\n        at org.eclipse.core.launcher.Main.main(Main.java:543)\nLogging to the console instead.\n!ENTRY org.eclipse.core.launcher 4 0 Mar 11, 2003 13:47:22.383\n!MESSAGE Exception launching the Eclipse Platform:\nAn exception occurred while writing to the platform log:\njava.io.IOException: Disk quota exceeded\n        at java.io.FileOutputStream.writeBytes(Native Method)\n        at java.io.FileOutputStream.write(FileOutputStream.java:257)\n        at sun.nio.cs.StreamEncoder$CharsetSE.writeBytes(StreamEncoder.java:334)\n        at\nsun.nio.cs.StreamEncoder$CharsetSE.implFlushBuffer(StreamEncoder.java:402)\n        at sun.nio.cs.StreamEncoder$CharsetSE.implFlush(StreamEncoder.java:406)\n        at sun.nio.cs.StreamEncoder.flush(StreamEncoder.java:150)\n        at java.io.OutputStreamWriter.flush(OutputStreamWriter.java:213)\n        at java.io.BufferedWriter.flush(BufferedWriter.java:230)\n        at org.eclipse.core.launcher.Main.closeLogFile(Main.java:1372)\n        at org.eclipse.core.launcher.Main.log(Main.java:1233)\n        at org.eclipse.core.launcher.Main.main(Main.java:544)\nLogging to the console instead.\n!STACK\njava.lang.reflect.InvocationTargetException\n        at sun.reflect.NativeMethodAccessorImpl.invoke0(Native Method)\n        at\nsun.reflect.NativeMethodAccessorImpl.invoke(NativeMethodAccessorImpl.java:39)\n        at\nsun.reflect.DelegatingMethodAccessorImpl.invoke(DelegatingMethodAccessorImpl.java:25)\n        at java.lang.reflect.Method.invoke(Method.java:324)\n        at org.eclipse.core.launcher.Main.basicRun(Main.java:247)\n        at org.eclipse.core.launcher.Main.run(Main.java:703)\n        at org.eclipse.core.launcher.Main.main(Main.java:539)\nCaused by: java.lang.reflect.InvocationTargetException\n        at sun.reflect.NativeMethodAccessorImpl.invoke0(Native Method)\n        at\nsun.reflect.NativeMethodAccessorImpl.invoke(NativeMethodAccessorImpl.java:39)\n        at\nsun.reflect.DelegatingMethodAccessorImpl.invoke(DelegatingMethodAccessorImpl.java:25)\n        at java.lang.reflect.Method.invoke(Method.java:324)\n        at\norg.eclipse.core.internal.boot.InternalBootLoader.startup(InternalBootLoader.java:1011)\n        at\norg.eclipse.core.internal.boot.InternalBootLoader.run(InternalBootLoader.java:838)\n        at org.eclipse.core.boot.BootLoader.run(BootLoader.java:461)\n        ... 7 more\nCaused by: org.eclipse.core.runtime.CoreException: Unable to create platform\nlock file: /home/knutr/eclipse/workspaces/testpass2/.metadata/.lock.\n        at\norg.eclipse.core.internal.runtime.InternalPlatform.createLockFile(InternalPlatform.java:220)\n        at\norg.eclipse.core.internal.runtime.InternalPlatform.loaderStartup(InternalPlatform.java:567)\n        ... 14 more\n",
    "Defer",
    "There is no plan to work on this at this time."
  ],
  "commentCreationDates": [
    "2003-03-11T18:51:30+01:00",
    "2003-03-11T18:53:49+01:00",
    "2003-03-12T06:26:58+01:00",
    "2004-10-22T16:05:14+02:00"
  ],
  "traces": [
    {
      "exceptionType": "java.io.IOException",
      "message": "Disk quota exceeded",
      "elements": [
        {
          "method": "java.io.FileOutputStream.writeBytes",
          "source": "Native Method"
        },
        {
          "method": "java.io.FileOutputStream.write",
          "source": "FileOutputStream.java:257"
        },
        {
          "method": "sun.nio.cs.StreamEncoder$CharsetSE.writeBytes",
          "source": "StreamEncoder.java:334"
        },
        {
          "method": "sun.nio.cs.StreamEncoder$CharsetSE.implFlushBuffer",
          "source": "StreamEncoder.java:402"
        },
        {
          "method": "sun.nio.cs.StreamEncoder$CharsetSE.implFlush",
          "source": "StreamEncoder.java:406"
        },
        {
          "method": "sun.nio.cs.StreamEncoder.flush",
          "source": "StreamEncoder.java:150"
        },
        {
          "method": "java.io.OutputStreamWriter.flush",
          "source": "OutputStreamWriter.java:213"
        },
        {
          "method": "java.io.BufferedWriter.flush",
          "source": "BufferedWriter.java:230"
        },
        {
          "method": "org.eclipse.core.launcher.Main.closeLogFile",
          "source": "Main.java:1372"
        },
        {
          "method": "org.eclipse.core.launcher.Main.log",
          "source": "Main.java:1233"
        },
        {
          "method": "org.eclipse.core.launcher.Main.main",
          "source": "Main.java:543"
        }
      ],
      "number": 0,
      "commentIndex": 1,
      "bugId": "34693",
      "date": "2003-03-11T18:53:49+01:00",
      "product": "Platform",
      "component": "UI",
      "severity": "major"
    },
    {
      "exceptionType": "java.io.IOException",
      "message": "Disk quota exceeded",
      "elements": [
        {
          "method": "java.io.FileOutputStream.writeBytes",
          "source": "Native Method"
        },
        {
          "method": "java.io.FileOutputStream.write",
          "source": "FileOutputStream.java:257"
        },
        {
          "method": "sun.nio.cs.StreamEncoder$CharsetSE.writeBytes",
          "source": "StreamEncoder.java:334"
        },
        {
          "method": "sun.nio.cs.StreamEncoder$CharsetSE.implFlushBuffer",
          "source": "StreamEncoder.java:402"
        },
        {
          "method": "sun.nio.cs.StreamEncoder$CharsetSE.implFlush",
          "source": "StreamEncoder.java:406"
        },
        {
          "method": "sun.nio.cs.StreamEncoder.flush",
          "source": "StreamEncoder.java:150"
        },
        {
          "method": "java.io.OutputStreamWriter.flush",
          "source": "OutputStreamWriter.java:213"
        },
        {
          "method": "java.io.BufferedWriter.flush",
          "source": "BufferedWriter.java:230"
        },
        {
          "method": "org.eclipse.core.launcher.Main.closeLogFile",
          "source": "Main.java:1372"
        },
        {
          "method": "org.eclipse.core.launcher.Main.log",
          "source": "Main.java:1233"
        },
        {
          "method": "org.eclipse.core.launcher.Main.main",
          "source": "Main.java:544"
        }
      ],
      "number": 1,
      "commentIndex": 1,
      "bugId": "34693",
      "date": "2003-03-11T18:53:49+01:00",
      "product": "Platform",
      "component": "UI",
      "severity": "major"
    },
    {
      "exceptionType": "java.lang.reflect.InvocationTargetException",
      "elements": [
        {
          "method": "sun.reflect.NativeMethodAccessorImpl.invoke0",
          "source": "Native Method"
        },
        {
          "method": "sun.reflect.NativeMethodAccessorImpl.invoke",
          "source": "NativeMethodAccessorImpl.java:39"
        },
        {
          "method": "sun.reflect.DelegatingMethodAccessorImpl.invoke",
          "source": "DelegatingMethodAccessorImpl.java:25"
        },
        {
          "method": "java.lang.reflect.Method.invoke",
          "source": "Method.java:324"
        },
        {
          "method": "org.eclipse.core.launcher.Main.basicRun",
          "source": "Main.java:247"
        },
        {
          "method": "org.eclipse.core.launcher.Main.run",
          "source": "Main.java:703"
        },
        {
          "method": "org.eclipse.core.launcher.Main.main",
          "source": "Main.java:539"
        }
      ],
      "causedBy": {
        "exceptionType": "java.lang.reflect.InvocationTargetException",
        "elements": [
          {
            "method": "sun.reflect.NativeMethodAccessorImpl.invoke0",
            "source": "Native Method"
          },
          {
            "method": "sun.reflect.NativeMethodAccessorImpl.invoke",
            "source": "NativeMethodAccessorImpl.java:39"
          },
          {
            "method": "sun.reflect.DelegatingMethodAccessorImpl.invoke",
            "source": "DelegatingMethodAccessorImpl.java:25"
          },
          {
            "method": "java.lang.reflect.Method.invoke",
            "source": "Method.java:324"
          },
          {
            "method": "org.eclipse.core.internal.boot.InternalBootLoader.startup",
            "source": "InternalBootLoader.java:1011"
          },
          {
            "method": "org.eclipse.core.internal.boot.InternalBootLoader.run",
            "source": "InternalBootLoader.java:838"
          },
          {
            "method": "org.eclipse.core.boot.BootLoader.run",
            "source": "BootLoader.java:461"
          }
        ],
        "causedBy": {
          "exceptionType": "org.eclipse.core.runtime.CoreException",
          "message": "Unable to create platform lock file: /home/knutr/eclipse/workspaces/testpass2/.metadata/.lock.",
          "elements": [
            {
              "method": "org.eclipse.core.internal.runtime.InternalPlatform.createLockFile",
              "source": "InternalPlatform.java:220"
            },
            {
              "method": "org.eclipse.core.internal.runtime.InternalPlatform.loaderStartup",
              "source": "InternalPlatform.java:567"
            }
          ],
          "number": 0,
          "commentIndex": 0
        },
        "number": 0,
        "commentIndex": 0
      },
      "number": 2,
      "commentIndex": 1,
      "bugId": "34693",
      "date": "2003-03-11T18:53:49+01:00",
      "product": "Platform",
      "component": "UI",
      "severity": "major"
    }
  ],
  "groupId": "34693",
  "bugId": "34693",
  "date": "2003-03-11T18:51:30+01:00",
  "product": "Platform",
  "component": "UI",
  "severity": "major"
}