{
  "comments": [
    "When I\u0027m trying to save a file sometimes I receive this error \"Save failed:null\".\nI\u0027m using Eclipse 2.1 RC2 GTK version on Redhat Linux 8.0.\nThis is a snippet from .log in .metadata folder:\n\n!SESSION Mar 14, 2003 10:58:13.595 ---------------------------------------------\njava.version\u003d1.4.0_02\njava.vendor\u003dSun Microsystems Inc.\nBootLoader constants: OS\u003dlinux, ARCH\u003dx86, WS\u003dgtk, NL\u003den_US\nCommand-line arguments: -os linux -ws gtk -arch x86 -install\nfile:/home/adi/apps/eclipse-RC2/\n!ENTRY org.eclipse.ui 4 4 Mar 14, 2003 10:58:13.597\n!MESSAGE Save Failed\n!ENTRY org.eclipse.ui 2 0 Mar 14, 2003 10:58:13.599\n!MESSAGE Save Failed\n!STACK 0\njava.lang.NegativeArraySizeException\n        at\norg.eclipse.jdt.internal.compiler.parser.Scanner.checkTaskTag(Scanner.java:284)\n        at\norg.eclipse.jdt.internal.compiler.parser.Parser.checkAndReportBracketAnomalies(Parser.java:869)\n        at\norg.eclipse.jdt.internal.compiler.parser.Parser.reportSyntaxError(Parser.java:7482)\n        at\norg.eclipse.jdt.internal.compiler.SourceElementParser.reportSyntaxError(SourceElementParser.java:1254)\n        at org.eclipse.jdt.internal.compiler.parser.Parser.parse(Parser.java:6850)\n        at org.eclipse.jdt.internal.compiler.parser.Parser.parse(Parser.java:7116)\n        at\norg.eclipse.jdt.internal.compiler.SourceElementParser.parseCompilationUnit(SourceElementParser.java:1051)\n        at\norg.eclipse.jdt.internal.core.CompilationUnit.generateInfos(CompilationUnit.java:313)\n        at\norg.eclipse.jdt.internal.core.CompilationUnit.buildStructure(CompilationUnit.java:77)\n        at\norg.eclipse.jdt.internal.core.CompilationUnit.makeConsistent(CompilationUnit.java:636)\n        at\norg.eclipse.jdt.internal.core.WorkingCopy.makeConsistent(WorkingCopy.java:340)\n        at\norg.eclipse.jdt.internal.core.ReconcileWorkingCopyOperation.executeOperation(ReconcileWorkingCopyOperation.java:48)\n        at\norg.eclipse.jdt.internal.core.JavaModelOperation.execute(JavaModelOperation.java:365)\n        at\norg.eclipse.jdt.internal.core.JavaModelOperation.run(JavaModelOperation.java:681)\n        at\norg.eclipse.jdt.internal.core.JavaElement.runOperation(JavaElement.java:540)\n        at org.eclipse.jdt.internal.core.WorkingCopy.reconcile(WorkingCopy.java:438)\n        at org.eclipse.jdt.internal.core.WorkingCopy.reconcile(WorkingCopy.java:429)\n        at\norg.eclipse.jdt.internal.ui.javaeditor.CompilationUnitDocumentProvider.doSaveDocument(CompilationUnitDocumentProvider.java:906)\n        at\norg.eclipse.ui.texteditor.AbstractDocumentProvider.saveDocument(AbstractDocumentProvider.java:455)\n        at\norg.eclipse.ui.texteditor.AbstractTextEditor$11.execute(AbstractTextEditor.java:2906)\n        at\norg.eclipse.ui.actions.WorkspaceModifyOperation$1.run(WorkspaceModifyOperation.java:65)\n        at org.eclipse.core.internal.resources.Workspace.run(Workspace.java:1591)\n        at\norg.eclipse.ui.actions.WorkspaceModifyOperation.run(WorkspaceModifyOperation.java:79)\n        at\norg.eclipse.ui.texteditor.AbstractTextEditor.performSaveOperation(AbstractTextEditor.java:2926)\n        at\norg.eclipse.jdt.internal.ui.javaeditor.CompilationUnitEditor.performSaveOperation(CompilationUnitEditor.java:742)\n        at\norg.eclipse.jdt.internal.ui.javaeditor.CompilationUnitEditor.doSave(CompilationUnitEditor.java:806)\n        at org.eclipse.ui.internal.EditorManager$11.run(EditorManager.java:1083)\n        at org.eclipse.ui.internal.EditorManager$8.run(EditorManager.java:954)\n        at\norg.eclipse.jface.operation.ModalContext.runInCurrentThread(ModalContext.java:296)\n        at org.eclipse.jface.operation.ModalContext.run(ModalContext.java:246)\n        at\norg.eclipse.jface.window.ApplicationWindow$1.run(ApplicationWindow.java:431)\n        at org.eclipse.swt.custom.BusyIndicator.showWhile(BusyIndicator.java:65)\n        at\norg.eclipse.jface.window.ApplicationWindow.run(ApplicationWindow.java:428)\n        at org.eclipse.ui.internal.WorkbenchWindow.run(WorkbenchWindow.java:1385)\n        at\norg.eclipse.ui.internal.EditorManager.runProgressMonitorOperation(EditorManager.java:960)\n        at org.eclipse.ui.internal.EditorManager.savePart(EditorManager.java:1088)\n        at org.eclipse.ui.internal.WorkbenchPage.savePart(WorkbenchPage.java:2350)\n        at org.eclipse.ui.internal.WorkbenchPage.saveEditor(WorkbenchPage.java:2362)\n        at org.eclipse.ui.internal.SaveAction.run(SaveAction.java:57)\n        at org.eclipse.jface.action.Action.runWithEvent(Action.java:842)\n        at\norg.eclipse.ui.internal.WWinKeyBindingService.pressed(WWinKeyBindingService.java:214)\n        at\norg.eclipse.ui.internal.WWinKeyBindingService$5.widgetSelected(WWinKeyBindingService.java:328)\n        at\norg.eclipse.ui.internal.AcceleratorMenu$2.handleEvent(AcceleratorMenu.java:55)\n        at org.eclipse.swt.widgets.EventTable.sendEvent(EventTable.java:77)\n        at org.eclipse.swt.widgets.Widget.sendEvent(Widget.java:902)\n        at org.eclipse.swt.widgets.Display.runDeferredEvents(Display.java:1590)\n        at org.eclipse.swt.widgets.Display.readAndDispatch(Display.java:1383)\n        at org.eclipse.ui.internal.Workbench.runEventLoop(Workbench.java:1400)\n        at org.eclipse.ui.internal.Workbench.run(Workbench.java:1383)\n        at\norg.eclipse.core.internal.boot.InternalBootLoader.run(InternalBootLoader.java:845)\n        at org.eclipse.core.boot.BootLoader.run(BootLoader.java:461)\n        at sun.reflect.NativeMethodAccessorImpl.invoke0(Native Method)\n        at\nsun.reflect.NativeMethodAccessorImpl.invoke(NativeMethodAccessorImpl.java:39)\n        at\nsun.reflect.DelegatingMethodAccessorImpl.invoke(DelegatingMethodAccessorImpl.java:25)\n        at java.lang.reflect.Method.invoke(Method.        \nat org.eclipse.core.launcher.Main.basicRun(Main.java:247)\n        at org.eclipse.core.launcher.Main.run(Main.java:703)\n        at org.eclipse.core.launcher.Main.main(Main.java:539)\njava:324)",
    "Could you attach the source of the unit which fails to save ?\nThe bug seems located in the scanner, when attempting to discover some TODO \ntasks.",
    "Actually, was able to reproduce on last TODO task (immediately followed by a \nEOF)\n\npublic class X {\t\n}//TODO",
    "Created an attachment (id\u003d4259)\nPatch for Scanner\n\nwould also need to be applied to public scanner class",
    "Fix is available and is quite simple.",
    "Not really critical.",
    "Created an attachment (id\u003d4286)\nPatch for the Public scanner class\n\nIdentical patch for the public scanner class.",
    "Adrian - do you confirm my testcase is what you also had ?",
    "I guess so. Is it fix in the latest version of eclipse(RC3b)?",
    "No, the patch is not included in the latest integration build.",
    "Given we are really close to the 2.1 release, this fix will not make it into \nthis release, unless it would be a stop ship issue (which it doesn\u0027t qualify \nfor). It is likely going to be released just after 2.1, and should be part of \nany patch past it.",
    "Defer",
    "Reopening\n",
    "Fixed",
    "Backported to 2.1 maintenance stream.",
    "Fixed in 2.2 stream as well.",
    "Verified.",
    "Verified. for 3.0M1."
  ],
  "commentCreationDates": [
    "2003-03-20T09:03:05+01:00",
    "2003-03-20T09:53:40+01:00",
    "2003-03-20T11:03:31+01:00",
    "2003-03-20T13:43:35+01:00",
    "2003-03-20T17:58:18+01:00",
    "2003-03-21T14:40:46+01:00",
    "2003-03-21T15:46:06+01:00",
    "2003-03-24T10:26:19+01:00",
    "2003-03-24T16:24:25+01:00",
    "2003-03-24T16:34:12+01:00",
    "2003-03-24T18:18:09+01:00",
    "2003-03-27T10:06:40+01:00",
    "2003-04-01T11:02:47+02:00",
    "2003-04-01T11:03:21+02:00",
    "2003-04-08T13:29:05+02:00",
    "2003-04-15T16:45:32+02:00",
    "2003-06-02T12:54:39+02:00",
    "2003-06-10T16:22:20+02:00"
  ],
  "traces": [
    {
      "exceptionType": "java.lang.NegativeArraySizeException",
      "elements": [
        {
          "method": "org.eclipse.jdt.internal.compiler.parser.Scanner.checkTaskTag",
          "source": "Scanner.java:284"
        },
        {
          "method": "org.eclipse.jdt.internal.compiler.parser.Parser.checkAndReportBracketAnomalies",
          "source": "Parser.java:869"
        },
        {
          "method": "org.eclipse.jdt.internal.compiler.parser.Parser.reportSyntaxError",
          "source": "Parser.java:7482"
        },
        {
          "method": "org.eclipse.jdt.internal.compiler.SourceElementParser.reportSyntaxError",
          "source": "SourceElementParser.java:1254"
        },
        {
          "method": "org.eclipse.jdt.internal.compiler.parser.Parser.parse",
          "source": "Parser.java:6850"
        },
        {
          "method": "org.eclipse.jdt.internal.compiler.parser.Parser.parse",
          "source": "Parser.java:7116"
        },
        {
          "method": "org.eclipse.jdt.internal.compiler.SourceElementParser.parseCompilationUnit",
          "source": "SourceElementParser.java:1051"
        },
        {
          "method": "org.eclipse.jdt.internal.core.CompilationUnit.generateInfos",
          "source": "CompilationUnit.java:313"
        },
        {
          "method": "org.eclipse.jdt.internal.core.CompilationUnit.buildStructure",
          "source": "CompilationUnit.java:77"
        },
        {
          "method": "org.eclipse.jdt.internal.core.CompilationUnit.makeConsistent",
          "source": "CompilationUnit.java:636"
        },
        {
          "method": "org.eclipse.jdt.internal.core.WorkingCopy.makeConsistent",
          "source": "WorkingCopy.java:340"
        },
        {
          "method": "org.eclipse.jdt.internal.core.ReconcileWorkingCopyOperation.executeOperation",
          "source": "ReconcileWorkingCopyOperation.java:48"
        },
        {
          "method": "org.eclipse.jdt.internal.core.JavaModelOperation.execute",
          "source": "JavaModelOperation.java:365"
        },
        {
          "method": "org.eclipse.jdt.internal.core.JavaModelOperation.run",
          "source": "JavaModelOperation.java:681"
        },
        {
          "method": "org.eclipse.jdt.internal.core.JavaElement.runOperation",
          "source": "JavaElement.java:540"
        },
        {
          "method": "org.eclipse.jdt.internal.core.WorkingCopy.reconcile",
          "source": "WorkingCopy.java:438"
        },
        {
          "method": "org.eclipse.jdt.internal.core.WorkingCopy.reconcile",
          "source": "WorkingCopy.java:429"
        },
        {
          "method": "org.eclipse.jdt.internal.ui.javaeditor.CompilationUnitDocumentProvider.doSaveDocument",
          "source": "CompilationUnitDocumentProvider.java:906"
        },
        {
          "method": "org.eclipse.ui.texteditor.AbstractDocumentProvider.saveDocument",
          "source": "AbstractDocumentProvider.java:455"
        },
        {
          "method": "org.eclipse.ui.texteditor.AbstractTextEditor$11.execute",
          "source": "AbstractTextEditor.java:2906"
        },
        {
          "method": "org.eclipse.ui.actions.WorkspaceModifyOperation$1.run",
          "source": "WorkspaceModifyOperation.java:65"
        },
        {
          "method": "org.eclipse.core.internal.resources.Workspace.run",
          "source": "Workspace.java:1591"
        },
        {
          "method": "org.eclipse.ui.actions.WorkspaceModifyOperation.run",
          "source": "WorkspaceModifyOperation.java:79"
        },
        {
          "method": "org.eclipse.ui.texteditor.AbstractTextEditor.performSaveOperation",
          "source": "AbstractTextEditor.java:2926"
        },
        {
          "method": "org.eclipse.jdt.internal.ui.javaeditor.CompilationUnitEditor.performSaveOperation",
          "source": "CompilationUnitEditor.java:742"
        },
        {
          "method": "org.eclipse.jdt.internal.ui.javaeditor.CompilationUnitEditor.doSave",
          "source": "CompilationUnitEditor.java:806"
        },
        {
          "method": "org.eclipse.ui.internal.EditorManager$11.run",
          "source": "EditorManager.java:1083"
        },
        {
          "method": "org.eclipse.ui.internal.EditorManager$8.run",
          "source": "EditorManager.java:954"
        },
        {
          "method": "org.eclipse.jface.operation.ModalContext.runInCurrentThread",
          "source": "ModalContext.java:296"
        },
        {
          "method": "org.eclipse.jface.operation.ModalContext.run",
          "source": "ModalContext.java:246"
        },
        {
          "method": "org.eclipse.jface.window.ApplicationWindow$1.run",
          "source": "ApplicationWindow.java:431"
        },
        {
          "method": "org.eclipse.swt.custom.BusyIndicator.showWhile",
          "source": "BusyIndicator.java:65"
        },
        {
          "method": "org.eclipse.jface.window.ApplicationWindow.run",
          "source": "ApplicationWindow.java:428"
        },
        {
          "method": "org.eclipse.ui.internal.WorkbenchWindow.run",
          "source": "WorkbenchWindow.java:1385"
        },
        {
          "method": "org.eclipse.ui.internal.EditorManager.runProgressMonitorOperation",
          "source": "EditorManager.java:960"
        },
        {
          "method": "org.eclipse.ui.internal.EditorManager.savePart",
          "source": "EditorManager.java:1088"
        },
        {
          "method": "org.eclipse.ui.internal.WorkbenchPage.savePart",
          "source": "WorkbenchPage.java:2350"
        },
        {
          "method": "org.eclipse.ui.internal.WorkbenchPage.saveEditor",
          "source": "WorkbenchPage.java:2362"
        },
        {
          "method": "org.eclipse.ui.internal.SaveAction.run",
          "source": "SaveAction.java:57"
        },
        {
          "method": "org.eclipse.jface.action.Action.runWithEvent",
          "source": "Action.java:842"
        },
        {
          "method": "org.eclipse.ui.internal.WWinKeyBindingService.pressed",
          "source": "WWinKeyBindingService.java:214"
        },
        {
          "method": "org.eclipse.ui.internal.WWinKeyBindingService$5.widgetSelected",
          "source": "WWinKeyBindingService.java:328"
        },
        {
          "method": "org.eclipse.ui.internal.AcceleratorMenu$2.handleEvent",
          "source": "AcceleratorMenu.java:55"
        },
        {
          "method": "org.eclipse.swt.widgets.EventTable.sendEvent",
          "source": "EventTable.java:77"
        },
        {
          "method": "org.eclipse.swt.widgets.Widget.sendEvent",
          "source": "Widget.java:902"
        },
        {
          "method": "org.eclipse.swt.widgets.Display.runDeferredEvents",
          "source": "Display.java:1590"
        },
        {
          "method": "org.eclipse.swt.widgets.Display.readAndDispatch",
          "source": "Display.java:1383"
        },
        {
          "method": "org.eclipse.ui.internal.Workbench.runEventLoop",
          "source": "Workbench.java:1400"
        },
        {
          "method": "org.eclipse.ui.internal.Workbench.run",
          "source": "Workbench.java:1383"
        },
        {
          "method": "org.eclipse.core.internal.boot.InternalBootLoader.run",
          "source": "InternalBootLoader.java:845"
        },
        {
          "method": "org.eclipse.core.boot.BootLoader.run",
          "source": "BootLoader.java:461"
        },
        {
          "method": "sun.reflect.NativeMethodAccessorImpl.invoke0",
          "source": "Native Method"
        },
        {
          "method": "sun.reflect.NativeMethodAccessorImpl.invoke",
          "source": "NativeMethodAccessorImpl.java:39"
        },
        {
          "method": "sun.reflect.DelegatingMethodAccessorImpl.invoke",
          "source": "DelegatingMethodAccessorImpl.java:25"
        }
      ],
      "number": 0,
      "commentIndex": 0,
      "bugId": "35338",
      "date": "2003-03-20T09:03:05+01:00",
      "product": "JDT",
      "component": "Core",
      "severity": "normal"
    }
  ],
  "groupId": "35338",
  "bugId": "35338",
  "date": "2003-03-20T09:03:05+01:00",
  "product": "JDT",
  "component": "Core",
  "severity": "normal"
}