{
  "comments": [
    "Build RC3a\n\nWhen upgrading a self-hosting binary workspace using PDE import, I got the \nfollowing failures in the log:\n\n!ENTRY org.eclipse.ui 4 4 Mar 21, 2003 13:29:43.543\n!MESSAGE Unhandled exception caught in event loop.\nUnhandled exception caught in event loop.\nReason:\n!ENTRY org.eclipse.ui 4 0 Mar 21, 2003 13:29:43.593\n!MESSAGE Failed to execute runnable (java.lang.NullPointerException)\n!STACK 0\norg.eclipse.swt.SWTException: Failed to execute runnable \n(java.lang.NullPointerException)\n        at org.eclipse.swt.SWT.error(SWT.java:2320)\n        at org.eclipse.swt.widgets.Synchronizer.runAsyncMessages\n(Synchronizer.java:101)\n        at org.eclipse.swt.widgets.Display.runAsyncMessages(Display.java:1819)\n        at org.eclipse.swt.widgets.Display.readAndDispatch(Display.java:1553)\n        at org.eclipse.jface.window.Window.runEventLoop(Window.java:583)\n        at org.eclipse.jface.window.Window.open(Window.java:563)\n        at org.eclipse.jface.dialogs.ErrorDialog.open(ErrorDialog.java:292)\n        at org.eclipse.jface.dialogs.ErrorDialog.openError(ErrorDialog.java:355)\n        at org.eclipse.jface.dialogs.ErrorDialog.openError(ErrorDialog.java:318)\n        at org.eclipse.ui.texteditor.AbstractTextEditor.setInput\n(AbstractTextEditor.java:2343)\n        at org.eclipse.jdt.internal.ui.javaeditor.ClassFileEditor$4.run\n(ClassFileEditor.java:617)\n        at org.eclipse.swt.widgets.RunnableLock.run(RunnableLock.java:35)\n        at org.eclipse.swt.widgets.Synchronizer.runAsyncMessages\n(Synchronizer.java:98)\n        at org.eclipse.swt.widgets.Display.runAsyncMessages(Display.java:1819)\n        at org.eclipse.swt.widgets.Display.readAndDispatch(Display.java:1553)\n        at org.eclipse.jface.operation.ModalContext$ModalContextThread.block\n(ModalContext.java:136)\n        at org.eclipse.jface.operation.ModalContext.run(ModalContext.java:261)\n        at org.eclipse.jface.wizard.WizardDialog.run(WizardDialog.java:758)\n        at \norg.eclipse.pde.internal.ui.wizards.imports.PluginImportWizard.performFinish\n(PluginImportWizard.java:145)\n        at org.eclipse.jface.wizard.WizardDialog.finishPressed\n(WizardDialog.java:608)\n        at org.eclipse.jface.wizard.WizardDialog.buttonPressed\n(WizardDialog.java:321)\n        at org.eclipse.jface.dialogs.Dialog$1.widgetSelected(Dialog.java:423)\n        at org.eclipse.swt.widgets.TypedListener.handleEvent\n(TypedListener.java:91)\n        at org.eclipse.swt.widgets.EventTable.sendEvent(EventTable.java:81)\n        at org.eclipse.swt.widgets.Widget.sendEvent(Widget.java:840)\n        at org.eclipse.swt.widgets.Display.runDeferredEvents(Display.java:1842)\n        at org.eclipse.swt.widgets.Display.readAndDispatch(Display.java:1549)\n        at org.eclipse.jface.window.Window.runEventLoop(Window.java:583)\n        at org.eclipse.jface.window.Window.open(Window.java:563)\n        at org.eclipse.ui.actions.ImportResourcesAction.run\n(ImportResourcesAction.java:96)\n        at org.eclipse.jface.action.Action.runWithEvent(Action.java:842)\n        at org.eclipse.jface.action.ActionContributionItem.handleWidgetSelection\n(ActionContributionItem.java:456)\n        at org.eclipse.jface.action.ActionContributionItem.handleWidgetEvent\n(ActionContributionItem.java:403)\n        at org.eclipse.jface.action.ActionContributionItem.access$0\n(ActionContributionItem.java:397)\n        at \norg.eclipse.jface.action.ActionContributionItem$ActionListener.handleEvent\n(ActionContributionItem.java:72)\n        at org.eclipse.swt.widgets.EventTable.sendEvent(EventTable.java:81)\n        at org.eclipse.swt.widgets.Widget.sendEvent(Widget.java:840)\n        at org.eclipse.swt.widgets.Display.runDeferredEvents(Display.java:1842)\n        at org.eclipse.swt.widgets.Display.readAndDispatch(Display.java:1549)\n        at org.eclipse.ui.internal.Workbench.runEventLoop(Workbench.java:1402)\n        at org.eclipse.ui.internal.Workbench.run(Workbench.java:1385)\n        at org.eclipse.core.internal.boot.InternalBootLoader.run\n(InternalBootLoader.java:845)\n        at org.eclipse.core.boot.BootLoader.run(BootLoader.java:461)\n        at sun.reflect.NativeMethodAccessorImpl.invoke0(Native Method)\n        at sun.reflect.NativeMethodAccessorImpl.invoke\n(NativeMethodAccessorImpl.java:39)\n        at sun.reflect.DelegatingMethodAccessorImpl.invoke\n(DelegatingMethodAccessorImpl.java:25)\n        at java.lang.reflect.Method.invoke(Method.java:324)\n        at org.eclipse.core.launcher.Main.basicRun(Main.java:291)\n        at org.eclipse.core.launcher.Main.run(Main.java:747)\n        at org.eclipse.core.launcher.Main.main(Main.java:583)\nFailed to execute runnable (java.lang.NullPointerException)\n!ENTRY org.eclipse.ui 4 4 Mar 21, 2003 13:29:43.984\n!MESSAGE\n*** Stack trace of contained exception ***\n\n*** Stack trace of contained exception ***\nReason:\n!ENTRY org.eclipse.ui 4 0 Mar 21, 2003 13:29:44.04\n!MESSAGE java.lang.NullPointerException\n!STACK 0\njava.lang.NullPointerException\n        at org.eclipse.ui.texteditor.AbstractTextEditor.doSetInput\n(AbstractTextEditor.java:2308)\n        at org.eclipse.ui.texteditor.StatusTextEditor.doSetInput\n(StatusTextEditor.java:160)\n        at org.eclipse.jdt.internal.ui.javaeditor.JavaEditor.doSetInput\n(JavaEditor.java:1560)\n        at org.eclipse.jdt.internal.ui.javaeditor.ClassFileEditor.doSetInput\n(ClassFileEditor.java:518)\n        at org.eclipse.ui.texteditor.AbstractTextEditor.setInput\n(AbstractTextEditor.java:2337)\n        at org.eclipse.jdt.internal.ui.javaeditor.ClassFileEditor$4.run\n(ClassFileEditor.java:617)\n        at org.eclipse.swt.widgets.RunnableLock.run(RunnableLock.java:35)\n        at org.eclipse.swt.widgets.Synchronizer.runAsyncMessages\n(Synchronizer.java:98)\n        at org.eclipse.swt.widgets.Display.runAsyncMessages(Display.java:1819)\n        at org.eclipse.swt.widgets.Display.readAndDispatch(Display.java:1553)\n        at org.eclipse.jface.window.Window.runEventLoop(Window.java:583)\n        at org.eclipse.jface.window.Window.open(Window.java:563)\n        at org.eclipse.jface.dialogs.ErrorDialog.open(ErrorDialog.java:292)\n        at org.eclipse.jface.dialogs.ErrorDialog.openError(ErrorDialog.java:355)\n        at org.eclipse.jface.dialogs.ErrorDialog.openError(ErrorDialog.java:318)\n        at org.eclipse.ui.texteditor.AbstractTextEditor.setInput\n(AbstractTextEditor.java:2343)\n        at org.eclipse.jdt.internal.ui.javaeditor.ClassFileEditor$4.run\n(ClassFileEditor.java:617)\n        at org.eclipse.swt.widgets.RunnableLock.run(RunnableLock.java:35)\n        at org.eclipse.swt.widgets.Synchronizer.runAsyncMessages\n(Synchronizer.java:98)\n        at org.eclipse.swt.widgets.Display.runAsyncMessages(Display.java:1819)\n        at org.eclipse.swt.widgets.Display.readAndDispatch(Display.java:1553)\n        at org.eclipse.jface.operation.ModalContext$ModalContextThread.block\n(ModalContext.java:136)\n        at org.eclipse.jface.operation.ModalContext.run(ModalContext.java:261)\n        at org.eclipse.jface.wizard.WizardDialog.run(WizardDialog.java:758)\n        at \norg.eclipse.pde.internal.ui.wizards.imports.PluginImportWizard.performFinish\n(PluginImportWizard.java:145)\n        at org.eclipse.jface.wizard.WizardDialog.finishPressed\n(WizardDialog.java:608)\n        at org.eclipse.jface.wizard.WizardDialog.buttonPressed\n(WizardDialog.java:321)\n        at org.eclipse.jface.dialogs.Dialog$1.widgetSelected(Dialog.java:423)\n        at org.eclipse.swt.widgets.TypedListener.handleEvent\n(TypedListener.java:91)\n        at org.eclipse.swt.widgets.EventTable.sendEvent(EventTable.java:81)\n        at org.eclipse.swt.widgets.Widget.sendEvent(Widget.java:840)\n        at org.eclipse.swt.widgets.Display.runDeferredEvents(Display.java:1842)\n        at org.eclipse.swt.widgets.Display.readAndDispatch(Display.java:1549)\n        at org.eclipse.jface.window.Window.runEventLoop(Window.java:583)\n        at org.eclipse.jface.window.Window.open(Window.java:563)\n        at org.eclipse.ui.actions.ImportResourcesAction.run\n(ImportResourcesAction.java:96)\n        at org.eclipse.jface.action.Action.runWithEvent(Action.java:842)\n        at org.eclipse.jface.action.ActionContributionItem.handleWidgetSelection\n(ActionContributionItem.java:456)\n        at org.eclipse.jface.action.ActionContributionItem.handleWidgetEvent\n(ActionContributionItem.java:403)\n        at org.eclipse.jface.action.ActionContributionItem.access$0\n(ActionContributionItem.java:397)\n        at \norg.eclipse.jface.action.ActionContributionItem$ActionListener.handleEvent\n(ActionContributionItem.java:72)\n        at org.eclipse.swt.widgets.EventTable.sendEvent(EventTable.java:81)\n        at org.eclipse.swt.widgets.Widget.sendEvent(Widget.java:840)\n        at org.eclipse.swt.widgets.Display.runDeferredEvents(Display.java:1842)\n        at org.eclipse.swt.widgets.Display.readAndDispatch(Display.java:1549)\n        at org.eclipse.ui.internal.Workbench.runEventLoop(Workbench.java:1402)\n        at org.eclipse.ui.internal.Workbench.run(Workbench.java:1385)\n        at org.eclipse.core.internal.boot.InternalBootLoader.run\n(InternalBootLoader.java:845)\n        at org.eclipse.core.boot.BootLoader.run(BootLoader.java:461)\n        at sun.reflect.NativeMethodAccessorImpl.invoke0(Native Method)\n        at sun.reflect.NativeMethodAccessorImpl.invoke\n(NativeMethodAccessorImpl.java:39)\n        at sun.reflect.DelegatingMethodAccessorImpl.invoke\n(DelegatingMethodAccessorImpl.java:25)\n        at java.lang.reflect.Method.invoke(Method.java:324)\n        at org.eclipse.core.launcher.Main.basicRun(Main.java:291)\n        at org.eclipse.core.launcher.Main.run(Main.java:747)\n        at org.eclipse.core.launcher.Main.main(Main.java:583)\njava.lang.NullPointerException\n!ENTRY org.eclipse.ui 4 4 Mar 21, 2003 13:29:44.134\n!MESSAGE Unhandled exception caught in event loop.\nUnhandled exception caught in event loop.\nReason:\n!ENTRY org.eclipse.ui 4 0 Mar 21, 2003 13:29:44.144\n!MESSAGE Failed to execute runnable (java.lang.NullPointerException)\n!STACK 0\norg.eclipse.swt.SWTException: Failed to execute runnable \n(java.lang.NullPointerException)\n        at org.eclipse.swt.SWT.error(SWT.java:2320)\n        at org.eclipse.swt.widgets.Synchronizer.runAsyncMessages\n(Synchronizer.java:101)\n        at org.eclipse.swt.widgets.Display.runAsyncMessages(Display.java:1819)\n        at org.eclipse.swt.widgets.Display.readAndDispatch(Display.java:1553)\n        at org.eclipse.jface.window.Window.runEventLoop(Window.java:583)\n        at org.eclipse.jface.window.Window.open(Window.java:563)\n        at org.eclipse.jface.dialogs.ErrorDialog.open(ErrorDialog.java:292)\n        at org.eclipse.jface.dialogs.ErrorDialog.openError(ErrorDialog.java:355)\n        at org.eclipse.jface.dialogs.ErrorDialog.openError(ErrorDialog.java:318)\n        at org.eclipse.ui.texteditor.AbstractTextEditor.setInput\n(AbstractTextEditor.java:2343)\n        at org.eclipse.jdt.internal.ui.javaeditor.ClassFileEditor$4.run\n(ClassFileEditor.java:617)\n        at org.eclipse.swt.widgets.RunnableLock.run(RunnableLock.java:35)\n        at org.eclipse.swt.widgets.Synchronizer.runAsyncMessages\n(Synchronizer.java:98)\n        at org.eclipse.swt.widgets.Display.runAsyncMessages(Display.java:1819)\n        at org.eclipse.swt.widgets.Display.readAndDispatch(Display.java:1553)\n        at org.eclipse.jface.operation.ModalContext$ModalContextThread.block\n(ModalContext.java:136)\n        at org.eclipse.jface.operation.ModalContext.run(ModalContext.java:261)\n        at org.eclipse.jface.wizard.WizardDialog.run(WizardDialog.java:758)\n        at \norg.eclipse.pde.internal.ui.wizards.imports.PluginImportWizard.performFinish\n(PluginImportWizard.java:145)\n        at org.eclipse.jface.wizard.WizardDialog.finishPressed\n(WizardDialog.java:608)\n        at org.eclipse.jface.wizard.WizardDialog.buttonPressed\n(WizardDialog.java:321)\n        at org.eclipse.jface.dialogs.Dialog$1.widgetSelected(Dialog.java:423)\n        at org.eclipse.swt.widgets.TypedListener.handleEvent\n(TypedListener.java:91)\n        at org.eclipse.swt.widgets.EventTable.sendEvent(EventTable.java:81)\n        at org.eclipse.swt.widgets.Widget.sendEvent(Widget.java:840)\n        at org.eclipse.swt.widgets.Display.runDeferredEvents(Display.java:1842)\n        at org.eclipse.swt.widgets.Display.readAndDispatch(Display.java:1549)\n        at org.eclipse.jface.window.Window.runEventLoop(Window.java:583)\n        at org.eclipse.jface.window.Window.open(Window.java:563)\n        at org.eclipse.ui.actions.ImportResourcesAction.run\n(ImportResourcesAction.java:96)\n        at org.eclipse.jface.action.Action.runWithEvent(Action.java:842)\n        at org.eclipse.jface.action.ActionContributionItem.handleWidgetSelection\n(ActionContributionItem.java:456)\n        at org.eclipse.jface.action.ActionContributionItem.handleWidgetEvent\n(ActionContributionItem.java:403)\n        at org.eclipse.jface.action.ActionContributionItem.access$0\n(ActionContributionItem.java:397)\n        at \norg.eclipse.jface.action.ActionContributionItem$ActionListener.handleEvent\n(ActionContributionItem.java:72)\n        at org.eclipse.swt.widgets.EventTable.sendEvent(EventTable.java:81)\n        at org.eclipse.swt.widgets.Widget.sendEvent(Widget.java:840)\n        at org.eclipse.swt.widgets.Display.runDeferredEvents(Display.java:1842)\n        at org.eclipse.swt.widgets.Display.readAndDispatch(Display.java:1549)\n        at org.eclipse.ui.internal.Workbench.runEventLoop(Workbench.java:1402)\n        at org.eclipse.ui.internal.Workbench.run(Workbench.java:1385)\n        at org.eclipse.core.internal.boot.InternalBootLoader.run\n(InternalBootLoader.java:845)\n        at org.eclipse.core.boot.BootLoader.run(BootLoader.java:461)\n        at sun.reflect.NativeMethodAccessorImpl.invoke0(Native Method)\n        at sun.reflect.NativeMethodAccessorImpl.invoke\n(NativeMethodAccessorImpl.java:39)\n        at sun.reflect.DelegatingMethodAccessorImpl.invoke\n(DelegatingMethodAccessorImpl.java:25)\n        at java.lang.reflect.Method.invoke(Method.java:324)\n        at org.eclipse.core.launcher.Main.basicRun(Main.java:291)\n        at org.eclipse.core.launcher.Main.run(Main.java:747)\n        at org.eclipse.core.launcher.Main.main(Main.java:583)\nFailed to execute runnable (java.lang.NullPointerException)\n!ENTRY org.eclipse.ui 4 4 Mar 21, 2003 13:29:44.224\n!MESSAGE\n*** Stack trace of contained exception ***\n\n*** Stack trace of contained exception ***\nReason:\n!ENTRY org.eclipse.ui 4 0 Mar 21, 2003 13:29:44.224\n!MESSAGE java.lang.NullPointerException\n!STACK 0\njava.lang.NullPointerException\n        at org.eclipse.ui.texteditor.AbstractTextEditor.doSetInput\n(AbstractTextEditor.java:2308)\n        at org.eclipse.ui.texteditor.StatusTextEditor.doSetInput\n(StatusTextEditor.java:160)\n        at org.eclipse.jdt.internal.ui.javaeditor.JavaEditor.doSetInput\n(JavaEditor.java:1560)\n        at org.eclipse.jdt.internal.ui.javaeditor.ClassFileEditor.doSetInput\n(ClassFileEditor.java:518)\n        at org.eclipse.ui.texteditor.AbstractTextEditor.setInput\n(AbstractTextEditor.java:2337)\n        at org.eclipse.jdt.internal.ui.javaeditor.ClassFileEditor$4.run\n(ClassFileEditor.java:617)\n        at org.eclipse.swt.widgets.RunnableLock.run(RunnableLock.java:35)\n        at org.eclipse.swt.widgets.Synchronizer.runAsyncMessages\n(Synchronizer.java:98)\n        at org.eclipse.swt.widgets.Display.runAsyncMessages(Display.java:1819)\n        at org.eclipse.swt.widgets.Display.readAndDispatch(Display.java:1553)\n        at org.eclipse.jface.window.Window.runEventLoop(Window.java:583)\n        at org.eclipse.jface.window.Window.open(Window.java:563)\n        at org.eclipse.jface.dialogs.ErrorDialog.open(ErrorDialog.java:292)\n        at org.eclipse.jface.dialogs.ErrorDialog.openError(ErrorDialog.java:355)\n        at org.eclipse.jface.dialogs.ErrorDialog.openError(ErrorDialog.java:318)\n        at org.eclipse.ui.texteditor.AbstractTextEditor.setInput\n(AbstractTextEditor.java:2343)\n        at org.eclipse.jdt.internal.ui.javaeditor.ClassFileEditor$4.run\n(ClassFileEditor.java:617)\n        at org.eclipse.swt.widgets.RunnableLock.run(RunnableLock.java:35)\n        at org.eclipse.swt.widgets.Synchronizer.runAsyncMessages\n(Synchronizer.java:98)\n        at org.eclipse.swt.widgets.Display.runAsyncMessages(Display.java:1819)\n        at org.eclipse.swt.widgets.Display.readAndDispatch(Display.java:1553)\n        at org.eclipse.jface.operation.ModalContext$ModalContextThread.block\n(ModalContext.java:136)\n        at org.eclipse.jface.operation.ModalContext.run(ModalContext.java:261)\n        at org.eclipse.jface.wizard.WizardDialog.run(WizardDialog.java:758)\n        at \norg.eclipse.pde.internal.ui.wizards.imports.PluginImportWizard.performFinish\n(PluginImportWizard.java:145)\n        at org.eclipse.jface.wizard.WizardDialog.finishPressed\n(WizardDialog.java:608)\n        at org.eclipse.jface.wizard.WizardDialog.buttonPressed\n(WizardDialog.java:321)\n        at org.eclipse.jface.dialogs.Dialog$1.widgetSelected(Dialog.java:423)\n        at org.eclipse.swt.widgets.TypedListener.handleEvent\n(TypedListener.java:91)\n        at org.eclipse.swt.widgets.EventTable.sendEvent(EventTable.java:81)\n        at org.eclipse.swt.widgets.Widget.sendEvent(Widget.java:840)\n        at org.eclipse.swt.widgets.Display.runDeferredEvents(Display.java:1842)\n        at org.eclipse.swt.widgets.Display.readAndDispatch(Display.java:1549)\n        at org.eclipse.jface.window.Window.runEventLoop(Window.java:583)\n        at org.eclipse.jface.window.Window.open(Window.java:563)\n        at org.eclipse.ui.actions.ImportResourcesAction.run\n(ImportResourcesAction.java:96)\n        at org.eclipse.jface.action.Action.runWithEvent(Action.java:842)\n        at org.eclipse.jface.action.ActionContributionItem.handleWidgetSelection\n(ActionContributionItem.java:456)\n        at org.eclipse.jface.action.ActionContributionItem.handleWidgetEvent\n(ActionContributionItem.java:403)\n        at org.eclipse.jface.action.ActionContributionItem.access$0\n(ActionContributionItem.java:397)\n        at \norg.eclipse.jface.action.ActionContributionItem$ActionListener.handleEvent\n(ActionContributionItem.java:72)\n        at org.eclipse.swt.widgets.EventTable.sendEvent(EventTable.java:81)\n        at org.eclipse.swt.widgets.Widget.sendEvent(Widget.java:840)\n        at org.eclipse.swt.widgets.Display.runDeferredEvents(Display.java:1842)\n        at org.eclipse.swt.widgets.Display.readAndDispatch(Display.java:1549)\n        at org.eclipse.ui.internal.Workbench.runEventLoop(Workbench.java:1402)\n        at org.eclipse.ui.internal.Workbench.run(Workbench.java:1385)\n        at org.eclipse.core.internal.boot.InternalBootLoader.run\n(InternalBootLoader.java:845)\n        at org.eclipse.core.boot.BootLoader.run(BootLoader.java:461)\n        at sun.reflect.NativeMethodAccessorImpl.invoke0(Native Method)\n        at sun.reflect.NativeMethodAccessorImpl.invoke\n(NativeMethodAccessorImpl.java:39)\n        at sun.reflect.DelegatingMethodAccessorImpl.invoke\n(DelegatingMethodAccessorImpl.java:25)\n        at java.lang.reflect.Method.invoke(Method.java:324)\n        at org.eclipse.core.launcher.Main.basicRun(Main.java:291)\n        at org.eclipse.core.launcher.Main.run(Main.java:747)\n        at org.eclipse.core.launcher.Main.main(Main.java:583)\njava.lang.NullPointerException\n!ENTRY org.eclipse.ui 4 4 Mar 21, 2003 13:29:44.234\n!MESSAGE Unhandled exception caught in event loop.\nUnhandled exception caught in event loop.\nReason:\n!ENTRY org.eclipse.ui 4 0 Mar 21, 2003 13:29:44.234\n!MESSAGE Failed to execute runnable (java.lang.NullPointerException)\n!STACK 0\norg.eclipse.swt.SWTException: Failed to execute runnable \n(java.lang.NullPointerException)\n        at org.eclipse.swt.SWT.error(SWT.java:2320)\n        at org.eclipse.swt.widgets.Synchronizer.runAsyncMessages\n(Synchronizer.java:101)\n        at org.eclipse.swt.widgets.Display.runAsyncMessages(Display.java:1819)\n        at org.eclipse.swt.widgets.Display.readAndDispatch(Display.java:1553)\n        at org.eclipse.jface.window.Window.runEventLoop(Window.java:583)\n        at org.eclipse.jface.window.Window.open(Window.java:563)\n        at org.eclipse.jface.dialogs.ErrorDialog.open(ErrorDialog.java:292)\n        at org.eclipse.jface.dialogs.ErrorDialog.openError(ErrorDialog.java:355)\n        at org.eclipse.jface.dialogs.ErrorDialog.openError(ErrorDialog.java:318)\n        at org.eclipse.ui.texteditor.AbstractTextEditor.setInput\n(AbstractTextEditor.java:2343)\n        at org.eclipse.jdt.internal.ui.javaeditor.ClassFileEditor$4.run\n(ClassFileEditor.java:617)\n        at org.eclipse.swt.widgets.RunnableLock.run(RunnableLock.java:35)\n        at org.eclipse.swt.widgets.Synchronizer.runAsyncMessages\n(Synchronizer.java:98)\n        at org.eclipse.swt.widgets.Display.runAsyncMessages(Display.java:1819)\n        at org.eclipse.swt.widgets.Display.readAndDispatch(Display.java:1553)\n        at org.eclipse.jface.operation.ModalContext$ModalContextThread.block\n(ModalContext.java:136)\n        at org.eclipse.jface.operation.ModalContext.run(ModalContext.java:261)\n        at org.eclipse.jface.wizard.WizardDialog.run(WizardDialog.java:758)\n        at \norg.eclipse.pde.internal.ui.wizards.imports.PluginImportWizard.performFinish\n(PluginImportWizard.java:145)\n        at org.eclipse.jface.wizard.WizardDialog.finishPressed\n(WizardDialog.java:608)\n        at org.eclipse.jface.wizard.WizardDialog.buttonPressed\n(WizardDialog.java:321)\n        at org.eclipse.jface.dialogs.Dialog$1.widgetSelected(Dialog.java:423)\n        at org.eclipse.swt.widgets.TypedListener.handleEvent\n(TypedListener.java:91)\n        at org.eclipse.swt.widgets.EventTable.sendEvent(EventTable.java:81)\n        at org.eclipse.swt.widgets.Widget.sendEvent(Widget.java:840)\n        at org.eclipse.swt.widgets.Display.runDeferredEvents(Display.java:1842)\n        at org.eclipse.swt.widgets.Display.readAndDispatch(Display.java:1549)\n        at org.eclipse.jface.window.Window.runEventLoop(Window.java:583)\n        at org.eclipse.jface.window.Window.open(Window.java:563)\n        at org.eclipse.ui.actions.ImportResourcesAction.run\n(ImportResourcesAction.java:96)\n        at org.eclipse.jface.action.Action.runWithEvent(Action.java:842)\n        at org.eclipse.jface.action.ActionContributionItem.handleWidgetSelection\n(ActionContributionItem.java:456)\n        at org.eclipse.jface.action.ActionContributionItem.handleWidgetEvent\n(ActionContributionItem.java:403)\n        at org.eclipse.jface.action.ActionContributionItem.access$0\n(ActionContributionItem.java:397)\n        at \norg.eclipse.jface.action.ActionContributionItem$ActionListener.handleEvent\n(ActionContributionItem.java:72)\n        at org.eclipse.swt.widgets.EventTable.sendEvent(EventTable.java:81)\n        at org.eclipse.swt.widgets.Widget.sendEvent(Widget.java:840)\n        at org.eclipse.swt.widgets.Display.runDeferredEvents(Display.java:1842)\n        at org.eclipse.swt.widgets.Display.readAndDispatch(Display.java:1549)\n        at org.eclipse.ui.internal.Workbench.runEventLoop(Workbench.java:1402)\n        at org.eclipse.ui.internal.Workbench.run(Workbench.java:1385)\n        at org.eclipse.core.internal.boot.InternalBootLoader.run\n(InternalBootLoader.java:845)\n        at org.eclipse.core.boot.BootLoader.run(BootLoader.java:461)\n        at sun.reflect.NativeMethodAccessorImpl.invoke0(Native Method)\n        at sun.reflect.NativeMethodAccessorImpl.invoke\n(NativeMethodAccessorImpl.java:39)\n        at sun.reflect.DelegatingMethodAccessorImpl.invoke\n(DelegatingMethodAccessorImpl.java:25)\n        at java.lang.reflect.Method.invoke(Method.java:324)\n        at org.eclipse.core.launcher.Main.basicRun(Main.java:291)\n        at org.eclipse.core.launcher.Main.run(Main.java:747)\n        at org.eclipse.core.launcher.Main.main(Main.java:583)\nFailed to execute runnable (java.lang.NullPointerException)\n!ENTRY org.eclipse.ui 4 4 Mar 21, 2003 13:29:44.244\n!MESSAGE\n*** Stack trace of contained exception ***\n\n*** Stack trace of contained exception ***\nReason:\n!ENTRY org.eclipse.ui 4 0 Mar 21, 2003 13:29:44.254\n!MESSAGE java.lang.NullPointerException\n!STACK 0\njava.lang.NullPointerException\n        at org.eclipse.ui.texteditor.AbstractTextEditor.doSetInput\n(AbstractTextEditor.java:2308)\n        at org.eclipse.ui.texteditor.StatusTextEditor.doSetInput\n(StatusTextEditor.java:160)\n        at org.eclipse.jdt.internal.ui.javaeditor.JavaEditor.doSetInput\n(JavaEditor.java:1560)\n        at org.eclipse.jdt.internal.ui.javaeditor.ClassFileEditor.doSetInput\n(ClassFileEditor.java:518)\n        at org.eclipse.ui.texteditor.AbstractTextEditor.setInput\n(AbstractTextEditor.java:2337)\n        at org.eclipse.jdt.internal.ui.javaeditor.ClassFileEditor$4.run\n(ClassFileEditor.java:617)\n        at org.eclipse.swt.widgets.RunnableLock.run(RunnableLock.java:35)\n        at org.eclipse.swt.widgets.Synchronizer.runAsyncMessages\n(Synchronizer.java:98)\n        at org.eclipse.swt.widgets.Display.runAsyncMessages(Display.java:1819)\n        at org.eclipse.swt.widgets.Display.readAndDispatch(Display.java:1553)\n        at org.eclipse.jface.window.Window.runEventLoop(Window.java:583)\n        at org.eclipse.jface.window.Window.open(Window.java:563)\n        at org.eclipse.jface.dialogs.ErrorDialog.open(ErrorDialog.java:292)\n        at org.eclipse.jface.dialogs.ErrorDialog.openError(ErrorDialog.java:355)\n        at org.eclipse.jface.dialogs.ErrorDialog.openError(ErrorDialog.java:318)\n        at org.eclipse.ui.texteditor.AbstractTextEditor.setInput\n(AbstractTextEditor.java:2343)\n        at org.eclipse.jdt.internal.ui.javaeditor.ClassFileEditor$4.run\n(ClassFileEditor.java:617)\n        at org.eclipse.swt.widgets.RunnableLock.run(RunnableLock.java:35)\n        at org.eclipse.swt.widgets.Synchronizer.runAsyncMessages\n(Synchronizer.java:98)\n        at org.eclipse.swt.widgets.Display.runAsyncMessages(Display.java:1819)\n        at org.eclipse.swt.widgets.Display.readAndDispatch(Display.java:1553)\n        at org.eclipse.jface.operation.ModalContext$ModalContextThread.block\n(ModalContext.java:136)\n        at org.eclipse.jface.operation.ModalContext.run(ModalContext.java:261)\n        at org.eclipse.jface.wizard.WizardDialog.run(WizardDialog.java:758)\n        at \norg.eclipse.pde.internal.ui.wizards.imports.PluginImportWizard.performFinish\n(PluginImportWizard.java:145)\n        at org.eclipse.jface.wizard.WizardDialog.finishPressed\n(WizardDialog.java:608)\n        at org.eclipse.jface.wizard.WizardDialog.buttonPressed\n(WizardDialog.java:321)\n        at org.eclipse.jface.dialogs.Dialog$1.widgetSelected(Dialog.java:423)\n        at org.eclipse.swt.widgets.TypedListener.handleEvent\n(TypedListener.java:91)\n        at org.eclipse.swt.widgets.EventTable.sendEvent(EventTable.java:81)\n        at org.eclipse.swt.widgets.Widget.sendEvent(Widget.java:840)\n        at org.eclipse.swt.widgets.Display.runDeferredEvents(Display.java:1842)\n        at org.eclipse.swt.widgets.Display.readAndDispatch(Display.java:1549)\n        at org.eclipse.jface.window.Window.runEventLoop(Window.java:583)\n        at org.eclipse.jface.window.Window.open(Window.java:563)\n        at org.eclipse.ui.actions.ImportResourcesAction.run\n(ImportResourcesAction.java:96)\n        at org.eclipse.jface.action.Action.runWithEvent(Action.java:842)\n        at org.eclipse.jface.action.ActionContributionItem.handleWidgetSelection\n(ActionContributionItem.java:456)\n        at org.eclipse.jface.action.ActionContributionItem.handleWidgetEvent\n(ActionContributionItem.java:403)\n        at org.eclipse.jface.action.ActionContributionItem.access$0\n(ActionContributionItem.java:397)\n        at \norg.eclipse.jface.action.ActionContributionItem$ActionListener.handleEvent\n(ActionContributionItem.java:72)\n        at org.eclipse.swt.widgets.EventTable.sendEvent(EventTable.java:81)\n        at org.eclipse.swt.widgets.Widget.sendEvent(Widget.java:840)\n        at org.eclipse.swt.widgets.Display.runDeferredEvents(Display.java:1842)\n        at org.eclipse.swt.widgets.Display.readAndDispatch(Display.java:1549)\n        at org.eclipse.ui.internal.Workbench.runEventLoop(Workbench.java:1402)\n        at org.eclipse.ui.internal.Workbench.run(Workbench.java:1385)\n        at org.eclipse.core.internal.boot.InternalBootLoader.run\n(InternalBootLoader.java:845)\n        at org.eclipse.core.boot.BootLoader.run(BootLoader.java:461)\n        at sun.reflect.NativeMethodAccessorImpl.invoke0(Native Method)\n        at sun.reflect.NativeMethodAccessorImpl.invoke\n(NativeMethodAccessorImpl.java:39)\n        at sun.reflect.DelegatingMethodAccessorImpl.invoke\n(DelegatingMethodAccessorImpl.java:25)\n        at java.lang.reflect.Method.invoke(Method.java:324)\n        at org.eclipse.core.launcher.Main.basicRun(Main.java:291)\n        at org.eclipse.core.launcher.Main.run(Main.java:747)\n        at org.eclipse.core.launcher.Main.main(Main.java:583)\njava.lang.NullPointerException\n!ENTRY org.eclipse.ui 4 4 Mar 21, 2003 13:29:44.254\n!MESSAGE Unhandled exception caught in event loop.\nUnhandled exception caught in event loop.\nReason:\n!ENTRY org.eclipse.ui 4 0 Mar 21, 2003 13:29:44.264\n!MESSAGE Failed to execute runnable (java.lang.NullPointerException)\n!STACK 0\norg.eclipse.swt.SWTException: Failed to execute runnable \n(java.lang.NullPointerException)\n        at org.eclipse.swt.SWT.error(SWT.java:2320)\n        at org.eclipse.swt.widgets.Synchronizer.runAsyncMessages\n(Synchronizer.java:101)\n        at org.eclipse.swt.widgets.Display.runAsyncMessages(Display.java:1819)\n        at org.eclipse.swt.widgets.Display.readAndDispatch(Display.java:1553)\n        at org.eclipse.jface.window.Window.runEventLoop(Window.java:583)\n        at org.eclipse.jface.window.Window.open(Window.java:563)\n        at org.eclipse.jface.dialogs.ErrorDialog.open(ErrorDialog.java:292)\n        at org.eclipse.jface.dialogs.ErrorDialog.openError(ErrorDialog.java:355)\n        at org.eclipse.jface.dialogs.ErrorDialog.openError(ErrorDialog.java:318)\n        at org.eclipse.ui.texteditor.AbstractTextEditor.setInput\n(AbstractTextEditor.java:2343)\n        at org.eclipse.jdt.internal.ui.javaeditor.ClassFileEditor$4.run\n(ClassFileEditor.java:617)\n        at org.eclipse.swt.widgets.RunnableLock.run(RunnableLock.java:35)\n        at org.eclipse.swt.widgets.Synchronizer.runAsyncMessages\n(Synchronizer.java:98)\n        at org.eclipse.swt.widgets.Display.runAsyncMessages(Display.java:1819)\n        at org.eclipse.swt.widgets.Display.readAndDispatch(Display.java:1553)\n        at org.eclipse.jface.operation.ModalContext$ModalContextThread.block\n(ModalContext.java:136)\n        at org.eclipse.jface.operation.ModalContext.run(ModalContext.java:261)\n        at org.eclipse.jface.wizard.WizardDialog.run(WizardDialog.java:758)\n        at \norg.eclipse.pde.internal.ui.wizards.imports.PluginImportWizard.performFinish\n(PluginImportWizard.java:145)\n        at org.eclipse.jface.wizard.WizardDialog.finishPressed\n(WizardDialog.java:608)\n        at org.eclipse.jface.wizard.WizardDialog.buttonPressed\n(WizardDialog.java:321)\n        at org.eclipse.jface.dialogs.Dialog$1.widgetSelected(Dialog.java:423)\n        at org.eclipse.swt.widgets.TypedListener.handleEvent\n(TypedListener.java:91)\n        at org.eclipse.swt.widgets.EventTable.sendEvent(EventTable.java:81)\n        at org.eclipse.swt.widgets.Widget.sendEvent(Widget.java:840)\n        at org.eclipse.swt.widgets.Display.runDeferredEvents(Display.java:1842)\n        at org.eclipse.swt.widgets.Display.readAndDispatch(Display.java:1549)\n        at org.eclipse.jface.window.Window.runEventLoop(Window.java:583)\n        at org.eclipse.jface.window.Window.open(Window.java:563)\n        at org.eclipse.ui.actions.ImportResourcesAction.run\n(ImportResourcesAction.java:96)\n        at org.eclipse.jface.action.Action.runWithEvent(Action.java:842)\n        at org.eclipse.jface.action.ActionContributionItem.handleWidgetSelection\n(ActionContributionItem.java:456)\n        at org.eclipse.jface.action.ActionContributionItem.handleWidgetEvent\n(ActionContributionItem.java:403)\n        at org.eclipse.jface.action.ActionContributionItem.access$0\n(ActionContributionItem.java:397)\n        at \norg.eclipse.jface.action.ActionContributionItem$ActionListener.handleEvent\n(ActionContributionItem.java:72)\n        at org.eclipse.swt.widgets.EventTable.sendEvent(EventTable.java:81)\n        at org.eclipse.swt.widgets.Widget.sendEvent(Widget.java:840)\n        at org.eclipse.swt.widgets.Display.runDeferredEvents(Display.java:1842)\n        at org.eclipse.swt.widgets.Display.readAndDispatch(Display.java:1549)\n        at org.eclipse.ui.internal.Workbench.runEventLoop(Workbench.java:1402)\n        at org.eclipse.ui.internal.Workbench.run(Workbench.java:1385)\n        at org.eclipse.core.internal.boot.InternalBootLoader.run\n(InternalBootLoader.java:845)\n        at org.eclipse.core.boot.BootLoader.run(BootLoader.java:461)\n        at sun.reflect.NativeMethodAccessorImpl.invoke0(Native Method)\n        at sun.reflect.NativeMethodAccessorImpl.invoke\n(NativeMethodAccessorImpl.java:39)\n        at sun.reflect.DelegatingMethodAccessorImpl.invoke\n(DelegatingMethodAccessorImpl.java:25)\n        at java.lang.reflect.Method.invoke(Method.java:324)\n        at org.eclipse.core.launcher.Main.basicRun(Main.java:291)\n        at org.eclipse.core.launcher.Main.run(Main.java:747)\n        at org.eclipse.core.launcher.Main.main(Main.java:583)\nFailed to execute runnable (java.lang.NullPointerException)\n!ENTRY org.eclipse.ui 4 4 Mar 21, 2003 13:29:44.294\n!MESSAGE\n*** Stack trace of contained exception ***\n\n*** Stack trace of contained exception ***\nReason:\n!ENTRY org.eclipse.ui 4 0 Mar 21, 2003 13:29:44.304\n!MESSAGE java.lang.NullPointerException\n!STACK 0\njava.lang.NullPointerException\n        at org.eclipse.ui.texteditor.AbstractTextEditor.doSetInput\n(AbstractTextEditor.java:2308)\n        at org.eclipse.ui.texteditor.StatusTextEditor.doSetInput\n(StatusTextEditor.java:160)\n        at org.eclipse.jdt.internal.ui.javaeditor.JavaEditor.doSetInput\n(JavaEditor.java:1560)\n        at org.eclipse.jdt.internal.ui.javaeditor.ClassFileEditor.doSetInput\n(ClassFileEditor.java:518)\n        at org.eclipse.ui.texteditor.AbstractTextEditor.setInput\n(AbstractTextEditor.java:2337)\n        at org.eclipse.jdt.internal.ui.javaeditor.ClassFileEditor$4.run\n(ClassFileEditor.java:617)\n        at org.eclipse.swt.widgets.RunnableLock.run(RunnableLock.java:35)\n        at org.eclipse.swt.widgets.Synchronizer.runAsyncMessages\n(Synchronizer.java:98)\n        at org.eclipse.swt.widgets.Display.runAsyncMessages(Display.java:1819)\n        at org.eclipse.swt.widgets.Display.readAndDispatch(Display.java:1553)\n        at org.eclipse.jface.window.Window.runEventLoop(Window.java:583)\n        at org.eclipse.jface.window.Window.open(Window.java:563)\n        at org.eclipse.jface.dialogs.ErrorDialog.open(ErrorDialog.java:292)\n        at org.eclipse.jface.dialogs.ErrorDialog.openError(ErrorDialog.java:355)\n        at org.eclipse.jface.dialogs.ErrorDialog.openError(ErrorDialog.java:318)\n        at org.eclipse.ui.texteditor.AbstractTextEditor.setInput\n(AbstractTextEditor.java:2343)\n        at org.eclipse.jdt.internal.ui.javaeditor.ClassFileEditor$4.run\n(ClassFileEditor.java:617)\n        at org.eclipse.swt.widgets.RunnableLock.run(RunnableLock.java:35)\n        at org.eclipse.swt.widgets.Synchronizer.runAsyncMessages\n(Synchronizer.java:98)\n        at org.eclipse.swt.widgets.Display.runAsyncMessages(Display.java:1819)\n        at org.eclipse.swt.widgets.Display.readAndDispatch(Display.java:1553)\n        at org.eclipse.jface.operation.ModalContext$ModalContextThread.block\n(ModalContext.java:136)\n        at org.eclipse.jface.operation.ModalContext.run(ModalContext.java:261)\n        at org.eclipse.jface.wizard.WizardDialog.run(WizardDialog.java:758)\n        at \norg.eclipse.pde.internal.ui.wizards.imports.PluginImportWizard.performFinish\n(PluginImportWizard.java:145)\n        at org.eclipse.jface.wizard.WizardDialog.finishPressed\n(WizardDialog.java:608)\n        at org.eclipse.jface.wizard.WizardDialog.buttonPressed\n(WizardDialog.java:321)\n        at org.eclipse.jface.dialogs.Dialog$1.widgetSelected(Dialog.java:423)\n        at org.eclipse.swt.widgets.TypedListener.handleEvent\n(TypedListener.java:91)\n        at org.eclipse.swt.widgets.EventTable.sendEvent(EventTable.java:81)\n        at org.eclipse.swt.widgets.Widget.sendEvent(Widget.java:840)\n        at org.eclipse.swt.widgets.Display.runDeferredEvents(Display.java:1842)\n        at org.eclipse.swt.widgets.Display.readAndDispatch(Display.java:1549)\n        at org.eclipse.jface.window.Window.runEventLoop(Window.java:583)\n        at org.eclipse.jface.window.Window.open(Window.java:563)\n        at org.eclipse.ui.actions.ImportResourcesAction.run\n(ImportResourcesAction.java:96)\n        at org.eclipse.jface.action.Action.runWithEvent(Action.java:842)\n        at org.eclipse.jface.action.ActionContributionItem.handleWidgetSelection\n(ActionContributionItem.java:456)\n        at org.eclipse.jface.action.ActionContributionItem.handleWidgetEvent\n(ActionContributionItem.java:403)\n        at org.eclipse.jface.action.ActionContributionItem.access$0\n(ActionContributionItem.java:397)\n        at \norg.eclipse.jface.action.ActionContributionItem$ActionListener.handleEvent\n(ActionContributionItem.java:72)\n        at org.eclipse.swt.widgets.EventTable.sendEvent(EventTable.java:81)\n        at org.eclipse.swt.widgets.Widget.sendEvent(Widget.java:840)\n        at org.eclipse.swt.widgets.Display.runDeferredEvents(Display.java:1842)\n        at org.eclipse.swt.widgets.Display.readAndDispatch(Display.java:1549)\n        at org.eclipse.ui.internal.Workbench.runEventLoop(Workbench.java:1402)\n        at org.eclipse.ui.internal.Workbench.run(Workbench.java:1385)\n        at org.eclipse.core.internal.boot.InternalBootLoader.run\n(InternalBootLoader.java:845)\n        at org.eclipse.core.boot.BootLoader.run(BootLoader.java:461)\n        at sun.reflect.NativeMethodAccessorImpl.invoke0(Native Method)\n        at sun.reflect.NativeMethodAccessorImpl.invoke\n(NativeMethodAccessorImpl.java:39)\n        at sun.reflect.DelegatingMethodAccessorImpl.invoke\n(DelegatingMethodAccessorImpl.java:25)\n        at java.lang.reflect.Method.invoke(Method.java:324)\n        at org.eclipse.core.launcher.Main.basicRun(Main.java:291)\n        at org.eclipse.core.launcher.Main.run(Main.java:747)\n        at org.eclipse.core.launcher.Main.main(Main.java:583)\njava.lang.NullPointerException\n!ENTRY org.eclipse.ui 4 4 Mar 21, 2003 13:29:44.354\n!MESSAGE Unhandled exception caught in event loop.\nUnhandled exception caught in event loop.\nReason:\n!ENTRY org.eclipse.ui 4 0 Mar 21, 2003 13:29:44.354\n!MESSAGE Failed to execute runnable (java.lang.NullPointerException)\n!STACK 0\norg.eclipse.swt.SWTException: Failed to execute runnable \n(java.lang.NullPointerException)\n        at org.eclipse.swt.SWT.error(SWT.java:2320)\n        at org.eclipse.swt.widgets.Synchronizer.runAsyncMessages\n(Synchronizer.java:101)\n        at org.eclipse.swt.widgets.Display.runAsyncMessages(Display.java:1819)\n        at org.eclipse.swt.widgets.Display.readAndDispatch(Display.java:1553)\n        at org.eclipse.jface.window.Window.runEventLoop(Window.java:583)\n        at org.eclipse.jface.window.Window.open(Window.java:563)\n        at org.eclipse.jface.dialogs.ErrorDialog.open(ErrorDialog.java:292)\n        at org.eclipse.jface.dialogs.ErrorDialog.openError(ErrorDialog.java:355)\n        at org.eclipse.jface.dialogs.ErrorDialog.openError(ErrorDialog.java:318)\n        at org.eclipse.ui.texteditor.AbstractTextEditor.setInput\n(AbstractTextEditor.java:2343)\n        at org.eclipse.jdt.internal.ui.javaeditor.ClassFileEditor$4.run\n(ClassFileEditor.java:617)\n        at org.eclipse.swt.widgets.RunnableLock.run(RunnableLock.java:35)\n        at org.eclipse.swt.widgets.Synchronizer.runAsyncMessages\n(Synchronizer.java:98)\n        at org.eclipse.swt.widgets.Display.runAsyncMessages(Display.java:1819)\n        at org.eclipse.swt.widgets.Display.readAndDispatch(Display.java:1553)\n        at org.eclipse.jface.operation.ModalContext$ModalContextThread.block\n(ModalContext.java:136)\n        at org.eclipse.jface.operation.ModalContext.run(ModalContext.java:261)\n        at org.eclipse.jface.wizard.WizardDialog.run(WizardDialog.java:758)\n        at \norg.eclipse.pde.internal.ui.wizards.imports.PluginImportWizard.performFinish\n(PluginImportWizard.java:145)\n        at org.eclipse.jface.wizard.WizardDialog.finishPressed\n(WizardDialog.java:608)\n        at org.eclipse.jface.wizard.WizardDialog.buttonPressed\n(WizardDialog.java:321)\n        at org.eclipse.jface.dialogs.Dialog$1.widgetSelected(Dialog.java:423)\n        at org.eclipse.swt.widgets.TypedListener.handleEvent\n(TypedListener.java:91)\n        at org.eclipse.swt.widgets.EventTable.sendEvent(EventTable.java:81)\n        at org.eclipse.swt.widgets.Widget.sendEvent(Widget.java:840)\n        at org.eclipse.swt.widgets.Display.runDeferredEvents(Display.java:1842)\n        at org.eclipse.swt.widgets.Display.readAndDispatch(Display.java:1549)\n        at org.eclipse.jface.window.Window.runEventLoop(Window.java:583)\n        at org.eclipse.jface.window.Window.open(Window.java:563)\n        at org.eclipse.ui.actions.ImportResourcesAction.run\n(ImportResourcesAction.java:96)\n        at org.eclipse.jface.action.Action.runWithEvent(Action.java:842)\n        at org.eclipse.jface.action.ActionContributionItem.handleWidgetSelection\n(ActionContributionItem.java:456)\n        at org.eclipse.jface.action.ActionContributionItem.handleWidgetEvent\n(ActionContributionItem.java:403)\n        at org.eclipse.jface.action.ActionContributionItem.access$0\n(ActionContributionItem.java:397)\n        at \norg.eclipse.jface.action.ActionContributionItem$ActionListener.handleEvent\n(ActionContributionItem.java:72)\n        at org.eclipse.swt.widgets.EventTable.sendEvent(EventTable.java:81)\n        at org.eclipse.swt.widgets.Widget.sendEvent(Widget.java:840)\n        at org.eclipse.swt.widgets.Display.runDeferredEvents(Display.java:1842)\n        at org.eclipse.swt.widgets.Display.readAndDispatch(Display.java:1549)\n        at org.eclipse.ui.internal.Workbench.runEventLoop(Workbench.java:1402)\n        at org.eclipse.ui.internal.Workbench.run(Workbench.java:1385)\n        at org.eclipse.core.internal.boot.InternalBootLoader.run\n(InternalBootLoader.java:845)\n        at org.eclipse.core.boot.BootLoader.run(BootLoader.java:461)\n        at sun.reflect.NativeMethodAccessorImpl.invoke0(Native Method)\n        at sun.reflect.NativeMethodAccessorImpl.invoke\n(NativeMethodAccessorImpl.java:39)\n        at sun.reflect.DelegatingMethodAccessorImpl.invoke\n(DelegatingMethodAccessorImpl.java:25)\n        at java.lang.reflect.Method.invoke(Method.java:324)\n        at org.eclipse.core.launcher.Main.basicRun(Main.java:291)\n        at org.eclipse.core.launcher.Main.run(Main.java:747)\n        at org.eclipse.core.launcher.Main.main(Main.java:583)\nFailed to execute runnable (java.lang.NullPointerException)\n!ENTRY org.eclipse.ui 4 4 Mar 21, 2003 13:29:44.364\n!MESSAGE\n*** Stack trace of contained exception ***\n\n*** Stack trace of contained exception ***\nReason:\n!ENTRY org.eclipse.ui 4 0 Mar 21, 2003 13:29:44.374\n!MESSAGE java.lang.NullPointerException\n!STACK 0\njava.lang.NullPointerException\n        at org.eclipse.ui.texteditor.AbstractTextEditor.doSetInput\n(AbstractTextEditor.java:2308)\n        at org.eclipse.ui.texteditor.StatusTextEditor.doSetInput\n(StatusTextEditor.java:160)\n        at org.eclipse.jdt.internal.ui.javaeditor.JavaEditor.doSetInput\n(JavaEditor.java:1560)\n        at org.eclipse.jdt.internal.ui.javaeditor.ClassFileEditor.doSetInput\n(ClassFileEditor.java:518)\n        at org.eclipse.ui.texteditor.AbstractTextEditor.setInput\n(AbstractTextEditor.java:2337)\n        at org.eclipse.jdt.internal.ui.javaeditor.ClassFileEditor$4.run\n(ClassFileEditor.java:617)\n        at org.eclipse.swt.widgets.RunnableLock.run(RunnableLock.java:35)\n        at org.eclipse.swt.widgets.Synchronizer.runAsyncMessages\n(Synchronizer.java:98)\n        at org.eclipse.swt.widgets.Display.runAsyncMessages(Display.java:1819)\n        at org.eclipse.swt.widgets.Display.readAndDispatch(Display.java:1553)\n        at org.eclipse.jface.window.Window.runEventLoop(Window.java:583)\n        at org.eclipse.jface.window.Window.open(Window.java:563)\n        at org.eclipse.jface.dialogs.ErrorDialog.open(ErrorDialog.java:292)\n        at org.eclipse.jface.dialogs.ErrorDialog.openError(ErrorDialog.java:355)\n        at org.eclipse.jface.dialogs.ErrorDialog.openError(ErrorDialog.java:318)\n        at org.eclipse.ui.texteditor.AbstractTextEditor.setInput\n(AbstractTextEditor.java:2343)\n        at org.eclipse.jdt.internal.ui.javaeditor.ClassFileEditor$4.run\n(ClassFileEditor.java:617)\n        at org.eclipse.swt.widgets.RunnableLock.run(RunnableLock.java:35)\n        at org.eclipse.swt.widgets.Synchronizer.runAsyncMessages\n(Synchronizer.java:98)\n        at org.eclipse.swt.widgets.Display.runAsyncMessages(Display.java:1819)\n        at org.eclipse.swt.widgets.Display.readAndDispatch(Display.java:1553)\n        at org.eclipse.jface.operation.ModalContext$ModalContextThread.block\n(ModalContext.java:136)\n        at org.eclipse.jface.operation.ModalContext.run(ModalContext.java:261)\n        at org.eclipse.jface.wizard.WizardDialog.run(WizardDialog.java:758)\n        at \norg.eclipse.pde.internal.ui.wizards.imports.PluginImportWizard.performFinish\n(PluginImportWizard.java:145)\n        at org.eclipse.jface.wizard.WizardDialog.finishPressed\n(WizardDialog.java:608)\n        at org.eclipse.jface.wizard.WizardDialog.buttonPressed\n(WizardDialog.java:321)\n        at org.eclipse.jface.dialogs.Dialog$1.widgetSelected(Dialog.java:423)\n        at org.eclipse.swt.widgets.TypedListener.handleEvent\n(TypedListener.java:91)\n        at org.eclipse.swt.widgets.EventTable.sendEvent(EventTable.java:81)\n        at org.eclipse.swt.widgets.Widget.sendEvent(Widget.java:840)\n        at org.eclipse.swt.widgets.Display.runDeferredEvents(Display.java:1842)\n        at org.eclipse.swt.widgets.Display.readAndDispatch(Display.java:1549)\n        at org.eclipse.jface.window.Window.runEventLoop(Window.java:583)\n        at org.eclipse.jface.window.Window.open(Window.java:563)\n        at org.eclipse.ui.actions.ImportResourcesAction.run\n(ImportResourcesAction.java:96)\n        at org.eclipse.jface.action.Action.runWithEvent(Action.java:842)\n        at org.eclipse.jface.action.ActionContributionItem.handleWidgetSelection\n(ActionContributionItem.java:456)\n        at org.eclipse.jface.action.ActionContributionItem.handleWidgetEvent\n(ActionContributionItem.java:403)\n        at org.eclipse.jface.action.ActionContributionItem.access$0\n(ActionContributionItem.java:397)\n        at \norg.eclipse.jface.action.ActionContributionItem$ActionListener.handleEvent\n(ActionContributionItem.java:72)\n        at org.eclipse.swt.widgets.EventTable.sendEvent(EventTable.java:81)\n        at org.eclipse.swt.widgets.Widget.sendEvent(Widget.java:840)\n        at org.eclipse.swt.widgets.Display.runDeferredEvents(Display.java:1842)\n        at org.eclipse.swt.widgets.Display.readAndDispatch(Display.java:1549)\n        at org.eclipse.ui.internal.Workbench.runEventLoop(Workbench.java:1402)\n        at org.eclipse.ui.internal.Workbench.run(Workbench.java:1385)\n        at org.eclipse.core.internal.boot.InternalBootLoader.run\n(InternalBootLoader.java:845)\n        at org.eclipse.core.boot.BootLoader.run(BootLoader.java:461)\n        at sun.reflect.NativeMethodAccessorImpl.invoke0(Native Method)\n        at sun.reflect.NativeMethodAccessorImpl.invoke\n(NativeMethodAccessorImpl.java:39)\n        at sun.reflect.DelegatingMethodAccessorImpl.invoke\n(DelegatingMethodAccessorImpl.java:25)\n        at java.lang.reflect.Method.invoke(Method.java:324)\n        at org.eclipse.core.launcher.Main.basicRun(Main.java:291)\n        at org.eclipse.core.launcher.Main.run(Main.java:747)\n        at org.eclipse.core.launcher.Main.main(Main.java:583)\njava.lang.NullPointerException",
    "This is also caused by reacting to the mass of change notifications send out \nby core.\n\n*** This bug has been marked as a duplicate of 35236 ***"
  ],
  "commentCreationDates": [
    "2003-03-21T12:44:47+01:00",
    "2003-03-24T13:47:53+01:00"
  ],
  "traces": [
    {
      "exceptionType": "org.eclipse.swt.SWTException",
      "message": "Failed to execute runnable  (java.lang.NullPointerException)",
      "elements": [
        {
          "method": "org.eclipse.swt.SWT.error",
          "source": "SWT.java:2320"
        },
        {
          "method": "org.eclipse.swt.widgets.Synchronizer.runAsyncMessages",
          "source": "Synchronizer.java:101"
        },
        {
          "method": "org.eclipse.swt.widgets.Display.runAsyncMessages",
          "source": "Display.java:1819"
        },
        {
          "method": "org.eclipse.swt.widgets.Display.readAndDispatch",
          "source": "Display.java:1553"
        },
        {
          "method": "org.eclipse.jface.window.Window.runEventLoop",
          "source": "Window.java:583"
        },
        {
          "method": "org.eclipse.jface.window.Window.open",
          "source": "Window.java:563"
        },
        {
          "method": "org.eclipse.jface.dialogs.ErrorDialog.open",
          "source": "ErrorDialog.java:292"
        },
        {
          "method": "org.eclipse.jface.dialogs.ErrorDialog.openError",
          "source": "ErrorDialog.java:355"
        },
        {
          "method": "org.eclipse.jface.dialogs.ErrorDialog.openError",
          "source": "ErrorDialog.java:318"
        },
        {
          "method": "org.eclipse.ui.texteditor.AbstractTextEditor.setInput",
          "source": "AbstractTextEditor.java:2343"
        },
        {
          "method": "org.eclipse.jdt.internal.ui.javaeditor.ClassFileEditor$4.run",
          "source": "ClassFileEditor.java:617"
        },
        {
          "method": "org.eclipse.swt.widgets.RunnableLock.run",
          "source": "RunnableLock.java:35"
        },
        {
          "method": "org.eclipse.swt.widgets.Synchronizer.runAsyncMessages",
          "source": "Synchronizer.java:98"
        },
        {
          "method": "org.eclipse.swt.widgets.Display.runAsyncMessages",
          "source": "Display.java:1819"
        },
        {
          "method": "org.eclipse.swt.widgets.Display.readAndDispatch",
          "source": "Display.java:1553"
        },
        {
          "method": "org.eclipse.jface.operation.ModalContext$ModalContextThread.block",
          "source": "ModalContext.java:136"
        },
        {
          "method": "org.eclipse.jface.operation.ModalContext.run",
          "source": "ModalContext.java:261"
        },
        {
          "method": "org.eclipse.jface.wizard.WizardDialog.run",
          "source": "WizardDialog.java:758"
        },
        {
          "method": "org.eclipse.pde.internal.ui.wizards.imports.PluginImportWizard.performFinish",
          "source": "PluginImportWizard.java:145"
        },
        {
          "method": "org.eclipse.jface.wizard.WizardDialog.finishPressed",
          "source": "WizardDialog.java:608"
        },
        {
          "method": "org.eclipse.jface.wizard.WizardDialog.buttonPressed",
          "source": "WizardDialog.java:321"
        },
        {
          "method": "org.eclipse.jface.dialogs.Dialog$1.widgetSelected",
          "source": "Dialog.java:423"
        },
        {
          "method": "org.eclipse.swt.widgets.TypedListener.handleEvent",
          "source": "TypedListener.java:91"
        },
        {
          "method": "org.eclipse.swt.widgets.EventTable.sendEvent",
          "source": "EventTable.java:81"
        },
        {
          "method": "org.eclipse.swt.widgets.Widget.sendEvent",
          "source": "Widget.java:840"
        },
        {
          "method": "org.eclipse.swt.widgets.Display.runDeferredEvents",
          "source": "Display.java:1842"
        },
        {
          "method": "org.eclipse.swt.widgets.Display.readAndDispatch",
          "source": "Display.java:1549"
        },
        {
          "method": "org.eclipse.jface.window.Window.runEventLoop",
          "source": "Window.java:583"
        },
        {
          "method": "org.eclipse.jface.window.Window.open",
          "source": "Window.java:563"
        },
        {
          "method": "org.eclipse.ui.actions.ImportResourcesAction.run",
          "source": "ImportResourcesAction.java:96"
        },
        {
          "method": "org.eclipse.jface.action.Action.runWithEvent",
          "source": "Action.java:842"
        },
        {
          "method": "org.eclipse.jface.action.ActionContributionItem.handleWidgetSelection",
          "source": "ActionContributionItem.java:456"
        },
        {
          "method": "org.eclipse.jface.action.ActionContributionItem.handleWidgetEvent",
          "source": "ActionContributionItem.java:403"
        },
        {
          "method": "org.eclipse.jface.action.ActionContributionItem.access$0",
          "source": "ActionContributionItem.java:397"
        },
        {
          "method": "org.eclipse.jface.action.ActionContributionItem$ActionListener.handleEvent",
          "source": "ActionContributionItem.java:72"
        },
        {
          "method": "org.eclipse.swt.widgets.EventTable.sendEvent",
          "source": "EventTable.java:81"
        },
        {
          "method": "org.eclipse.swt.widgets.Widget.sendEvent",
          "source": "Widget.java:840"
        },
        {
          "method": "org.eclipse.swt.widgets.Display.runDeferredEvents",
          "source": "Display.java:1842"
        },
        {
          "method": "org.eclipse.swt.widgets.Display.readAndDispatch",
          "source": "Display.java:1549"
        },
        {
          "method": "org.eclipse.ui.internal.Workbench.runEventLoop",
          "source": "Workbench.java:1402"
        },
        {
          "method": "org.eclipse.ui.internal.Workbench.run",
          "source": "Workbench.java:1385"
        },
        {
          "method": "org.eclipse.core.internal.boot.InternalBootLoader.run",
          "source": "InternalBootLoader.java:845"
        },
        {
          "method": "org.eclipse.core.boot.BootLoader.run",
          "source": "BootLoader.java:461"
        },
        {
          "method": "sun.reflect.NativeMethodAccessorImpl.invoke0",
          "source": "Native Method"
        },
        {
          "method": "sun.reflect.NativeMethodAccessorImpl.invoke",
          "source": "NativeMethodAccessorImpl.java:39"
        },
        {
          "method": "sun.reflect.DelegatingMethodAccessorImpl.invoke",
          "source": "DelegatingMethodAccessorImpl.java:25"
        },
        {
          "method": "java.lang.reflect.Method.invoke",
          "source": "Method.java:324"
        },
        {
          "method": "org.eclipse.core.launcher.Main.basicRun",
          "source": "Main.java:291"
        },
        {
          "method": "org.eclipse.core.launcher.Main.run",
          "source": "Main.java:747"
        },
        {
          "method": "org.eclipse.core.launcher.Main.main",
          "source": "Main.java:583"
        }
      ],
      "number": 0,
      "commentIndex": 0,
      "bugId": "35455",
      "duplicateId": "35236",
      "date": "2003-03-21T12:44:47+01:00",
      "product": "JDT",
      "component": "Text",
      "severity": "normal"
    },
    {
      "exceptionType": "java.lang.NullPointerException",
      "elements": [
        {
          "method": "org.eclipse.ui.texteditor.AbstractTextEditor.doSetInput",
          "source": "AbstractTextEditor.java:2308"
        },
        {
          "method": "org.eclipse.ui.texteditor.StatusTextEditor.doSetInput",
          "source": "StatusTextEditor.java:160"
        },
        {
          "method": "org.eclipse.jdt.internal.ui.javaeditor.JavaEditor.doSetInput",
          "source": "JavaEditor.java:1560"
        },
        {
          "method": "org.eclipse.jdt.internal.ui.javaeditor.ClassFileEditor.doSetInput",
          "source": "ClassFileEditor.java:518"
        },
        {
          "method": "org.eclipse.ui.texteditor.AbstractTextEditor.setInput",
          "source": "AbstractTextEditor.java:2337"
        },
        {
          "method": "org.eclipse.jdt.internal.ui.javaeditor.ClassFileEditor$4.run",
          "source": "ClassFileEditor.java:617"
        },
        {
          "method": "org.eclipse.swt.widgets.RunnableLock.run",
          "source": "RunnableLock.java:35"
        },
        {
          "method": "org.eclipse.swt.widgets.Synchronizer.runAsyncMessages",
          "source": "Synchronizer.java:98"
        },
        {
          "method": "org.eclipse.swt.widgets.Display.runAsyncMessages",
          "source": "Display.java:1819"
        },
        {
          "method": "org.eclipse.swt.widgets.Display.readAndDispatch",
          "source": "Display.java:1553"
        },
        {
          "method": "org.eclipse.jface.window.Window.runEventLoop",
          "source": "Window.java:583"
        },
        {
          "method": "org.eclipse.jface.window.Window.open",
          "source": "Window.java:563"
        },
        {
          "method": "org.eclipse.jface.dialogs.ErrorDialog.open",
          "source": "ErrorDialog.java:292"
        },
        {
          "method": "org.eclipse.jface.dialogs.ErrorDialog.openError",
          "source": "ErrorDialog.java:355"
        },
        {
          "method": "org.eclipse.jface.dialogs.ErrorDialog.openError",
          "source": "ErrorDialog.java:318"
        },
        {
          "method": "org.eclipse.ui.texteditor.AbstractTextEditor.setInput",
          "source": "AbstractTextEditor.java:2343"
        },
        {
          "method": "org.eclipse.jdt.internal.ui.javaeditor.ClassFileEditor$4.run",
          "source": "ClassFileEditor.java:617"
        },
        {
          "method": "org.eclipse.swt.widgets.RunnableLock.run",
          "source": "RunnableLock.java:35"
        },
        {
          "method": "org.eclipse.swt.widgets.Synchronizer.runAsyncMessages",
          "source": "Synchronizer.java:98"
        },
        {
          "method": "org.eclipse.swt.widgets.Display.runAsyncMessages",
          "source": "Display.java:1819"
        },
        {
          "method": "org.eclipse.swt.widgets.Display.readAndDispatch",
          "source": "Display.java:1553"
        },
        {
          "method": "org.eclipse.jface.operation.ModalContext$ModalContextThread.block",
          "source": "ModalContext.java:136"
        },
        {
          "method": "org.eclipse.jface.operation.ModalContext.run",
          "source": "ModalContext.java:261"
        },
        {
          "method": "org.eclipse.jface.wizard.WizardDialog.run",
          "source": "WizardDialog.java:758"
        },
        {
          "method": "org.eclipse.pde.internal.ui.wizards.imports.PluginImportWizard.performFinish",
          "source": "PluginImportWizard.java:145"
        },
        {
          "method": "org.eclipse.jface.wizard.WizardDialog.finishPressed",
          "source": "WizardDialog.java:608"
        },
        {
          "method": "org.eclipse.jface.wizard.WizardDialog.buttonPressed",
          "source": "WizardDialog.java:321"
        },
        {
          "method": "org.eclipse.jface.dialogs.Dialog$1.widgetSelected",
          "source": "Dialog.java:423"
        },
        {
          "method": "org.eclipse.swt.widgets.TypedListener.handleEvent",
          "source": "TypedListener.java:91"
        },
        {
          "method": "org.eclipse.swt.widgets.EventTable.sendEvent",
          "source": "EventTable.java:81"
        },
        {
          "method": "org.eclipse.swt.widgets.Widget.sendEvent",
          "source": "Widget.java:840"
        },
        {
          "method": "org.eclipse.swt.widgets.Display.runDeferredEvents",
          "source": "Display.java:1842"
        },
        {
          "method": "org.eclipse.swt.widgets.Display.readAndDispatch",
          "source": "Display.java:1549"
        },
        {
          "method": "org.eclipse.jface.window.Window.runEventLoop",
          "source": "Window.java:583"
        },
        {
          "method": "org.eclipse.jface.window.Window.open",
          "source": "Window.java:563"
        },
        {
          "method": "org.eclipse.ui.actions.ImportResourcesAction.run",
          "source": "ImportResourcesAction.java:96"
        },
        {
          "method": "org.eclipse.jface.action.Action.runWithEvent",
          "source": "Action.java:842"
        },
        {
          "method": "org.eclipse.jface.action.ActionContributionItem.handleWidgetSelection",
          "source": "ActionContributionItem.java:456"
        },
        {
          "method": "org.eclipse.jface.action.ActionContributionItem.handleWidgetEvent",
          "source": "ActionContributionItem.java:403"
        },
        {
          "method": "org.eclipse.jface.action.ActionContributionItem.access$0",
          "source": "ActionContributionItem.java:397"
        },
        {
          "method": "org.eclipse.jface.action.ActionContributionItem$ActionListener.handleEvent",
          "source": "ActionContributionItem.java:72"
        },
        {
          "method": "org.eclipse.swt.widgets.EventTable.sendEvent",
          "source": "EventTable.java:81"
        },
        {
          "method": "org.eclipse.swt.widgets.Widget.sendEvent",
          "source": "Widget.java:840"
        },
        {
          "method": "org.eclipse.swt.widgets.Display.runDeferredEvents",
          "source": "Display.java:1842"
        },
        {
          "method": "org.eclipse.swt.widgets.Display.readAndDispatch",
          "source": "Display.java:1549"
        },
        {
          "method": "org.eclipse.ui.internal.Workbench.runEventLoop",
          "source": "Workbench.java:1402"
        },
        {
          "method": "org.eclipse.ui.internal.Workbench.run",
          "source": "Workbench.java:1385"
        },
        {
          "method": "org.eclipse.core.internal.boot.InternalBootLoader.run",
          "source": "InternalBootLoader.java:845"
        },
        {
          "method": "org.eclipse.core.boot.BootLoader.run",
          "source": "BootLoader.java:461"
        },
        {
          "method": "sun.reflect.NativeMethodAccessorImpl.invoke0",
          "source": "Native Method"
        },
        {
          "method": "sun.reflect.NativeMethodAccessorImpl.invoke",
          "source": "NativeMethodAccessorImpl.java:39"
        },
        {
          "method": "sun.reflect.DelegatingMethodAccessorImpl.invoke",
          "source": "DelegatingMethodAccessorImpl.java:25"
        },
        {
          "method": "java.lang.reflect.Method.invoke",
          "source": "Method.java:324"
        },
        {
          "method": "org.eclipse.core.launcher.Main.basicRun",
          "source": "Main.java:291"
        },
        {
          "method": "org.eclipse.core.launcher.Main.run",
          "source": "Main.java:747"
        },
        {
          "method": "org.eclipse.core.launcher.Main.main",
          "source": "Main.java:583"
        }
      ],
      "number": 1,
      "commentIndex": 0,
      "bugId": "35455",
      "duplicateId": "35236",
      "date": "2003-03-21T12:44:47+01:00",
      "product": "JDT",
      "component": "Text",
      "severity": "normal"
    },
    {
      "exceptionType": "org.eclipse.swt.SWTException",
      "message": "Failed to execute runnable  (java.lang.NullPointerException)",
      "elements": [
        {
          "method": "org.eclipse.swt.SWT.error",
          "source": "SWT.java:2320"
        },
        {
          "method": "org.eclipse.swt.widgets.Synchronizer.runAsyncMessages",
          "source": "Synchronizer.java:101"
        },
        {
          "method": "org.eclipse.swt.widgets.Display.runAsyncMessages",
          "source": "Display.java:1819"
        },
        {
          "method": "org.eclipse.swt.widgets.Display.readAndDispatch",
          "source": "Display.java:1553"
        },
        {
          "method": "org.eclipse.jface.window.Window.runEventLoop",
          "source": "Window.java:583"
        },
        {
          "method": "org.eclipse.jface.window.Window.open",
          "source": "Window.java:563"
        },
        {
          "method": "org.eclipse.jface.dialogs.ErrorDialog.open",
          "source": "ErrorDialog.java:292"
        },
        {
          "method": "org.eclipse.jface.dialogs.ErrorDialog.openError",
          "source": "ErrorDialog.java:355"
        },
        {
          "method": "org.eclipse.jface.dialogs.ErrorDialog.openError",
          "source": "ErrorDialog.java:318"
        },
        {
          "method": "org.eclipse.ui.texteditor.AbstractTextEditor.setInput",
          "source": "AbstractTextEditor.java:2343"
        },
        {
          "method": "org.eclipse.jdt.internal.ui.javaeditor.ClassFileEditor$4.run",
          "source": "ClassFileEditor.java:617"
        },
        {
          "method": "org.eclipse.swt.widgets.RunnableLock.run",
          "source": "RunnableLock.java:35"
        },
        {
          "method": "org.eclipse.swt.widgets.Synchronizer.runAsyncMessages",
          "source": "Synchronizer.java:98"
        },
        {
          "method": "org.eclipse.swt.widgets.Display.runAsyncMessages",
          "source": "Display.java:1819"
        },
        {
          "method": "org.eclipse.swt.widgets.Display.readAndDispatch",
          "source": "Display.java:1553"
        },
        {
          "method": "org.eclipse.jface.operation.ModalContext$ModalContextThread.block",
          "source": "ModalContext.java:136"
        },
        {
          "method": "org.eclipse.jface.operation.ModalContext.run",
          "source": "ModalContext.java:261"
        },
        {
          "method": "org.eclipse.jface.wizard.WizardDialog.run",
          "source": "WizardDialog.java:758"
        },
        {
          "method": "org.eclipse.pde.internal.ui.wizards.imports.PluginImportWizard.performFinish",
          "source": "PluginImportWizard.java:145"
        },
        {
          "method": "org.eclipse.jface.wizard.WizardDialog.finishPressed",
          "source": "WizardDialog.java:608"
        },
        {
          "method": "org.eclipse.jface.wizard.WizardDialog.buttonPressed",
          "source": "WizardDialog.java:321"
        },
        {
          "method": "org.eclipse.jface.dialogs.Dialog$1.widgetSelected",
          "source": "Dialog.java:423"
        },
        {
          "method": "org.eclipse.swt.widgets.TypedListener.handleEvent",
          "source": "TypedListener.java:91"
        },
        {
          "method": "org.eclipse.swt.widgets.EventTable.sendEvent",
          "source": "EventTable.java:81"
        },
        {
          "method": "org.eclipse.swt.widgets.Widget.sendEvent",
          "source": "Widget.java:840"
        },
        {
          "method": "org.eclipse.swt.widgets.Display.runDeferredEvents",
          "source": "Display.java:1842"
        },
        {
          "method": "org.eclipse.swt.widgets.Display.readAndDispatch",
          "source": "Display.java:1549"
        },
        {
          "method": "org.eclipse.jface.window.Window.runEventLoop",
          "source": "Window.java:583"
        },
        {
          "method": "org.eclipse.jface.window.Window.open",
          "source": "Window.java:563"
        },
        {
          "method": "org.eclipse.ui.actions.ImportResourcesAction.run",
          "source": "ImportResourcesAction.java:96"
        },
        {
          "method": "org.eclipse.jface.action.Action.runWithEvent",
          "source": "Action.java:842"
        },
        {
          "method": "org.eclipse.jface.action.ActionContributionItem.handleWidgetSelection",
          "source": "ActionContributionItem.java:456"
        },
        {
          "method": "org.eclipse.jface.action.ActionContributionItem.handleWidgetEvent",
          "source": "ActionContributionItem.java:403"
        },
        {
          "method": "org.eclipse.jface.action.ActionContributionItem.access$0",
          "source": "ActionContributionItem.java:397"
        },
        {
          "method": "org.eclipse.jface.action.ActionContributionItem$ActionListener.handleEvent",
          "source": "ActionContributionItem.java:72"
        },
        {
          "method": "org.eclipse.swt.widgets.EventTable.sendEvent",
          "source": "EventTable.java:81"
        },
        {
          "method": "org.eclipse.swt.widgets.Widget.sendEvent",
          "source": "Widget.java:840"
        },
        {
          "method": "org.eclipse.swt.widgets.Display.runDeferredEvents",
          "source": "Display.java:1842"
        },
        {
          "method": "org.eclipse.swt.widgets.Display.readAndDispatch",
          "source": "Display.java:1549"
        },
        {
          "method": "org.eclipse.ui.internal.Workbench.runEventLoop",
          "source": "Workbench.java:1402"
        },
        {
          "method": "org.eclipse.ui.internal.Workbench.run",
          "source": "Workbench.java:1385"
        },
        {
          "method": "org.eclipse.core.internal.boot.InternalBootLoader.run",
          "source": "InternalBootLoader.java:845"
        },
        {
          "method": "org.eclipse.core.boot.BootLoader.run",
          "source": "BootLoader.java:461"
        },
        {
          "method": "sun.reflect.NativeMethodAccessorImpl.invoke0",
          "source": "Native Method"
        },
        {
          "method": "sun.reflect.NativeMethodAccessorImpl.invoke",
          "source": "NativeMethodAccessorImpl.java:39"
        },
        {
          "method": "sun.reflect.DelegatingMethodAccessorImpl.invoke",
          "source": "DelegatingMethodAccessorImpl.java:25"
        },
        {
          "method": "java.lang.reflect.Method.invoke",
          "source": "Method.java:324"
        },
        {
          "method": "org.eclipse.core.launcher.Main.basicRun",
          "source": "Main.java:291"
        },
        {
          "method": "org.eclipse.core.launcher.Main.run",
          "source": "Main.java:747"
        },
        {
          "method": "org.eclipse.core.launcher.Main.main",
          "source": "Main.java:583"
        }
      ],
      "number": 2,
      "commentIndex": 0,
      "bugId": "35455",
      "duplicateId": "35236",
      "date": "2003-03-21T12:44:47+01:00",
      "product": "JDT",
      "component": "Text",
      "severity": "normal"
    },
    {
      "exceptionType": "java.lang.NullPointerException",
      "elements": [
        {
          "method": "org.eclipse.ui.texteditor.AbstractTextEditor.doSetInput",
          "source": "AbstractTextEditor.java:2308"
        },
        {
          "method": "org.eclipse.ui.texteditor.StatusTextEditor.doSetInput",
          "source": "StatusTextEditor.java:160"
        },
        {
          "method": "org.eclipse.jdt.internal.ui.javaeditor.JavaEditor.doSetInput",
          "source": "JavaEditor.java:1560"
        },
        {
          "method": "org.eclipse.jdt.internal.ui.javaeditor.ClassFileEditor.doSetInput",
          "source": "ClassFileEditor.java:518"
        },
        {
          "method": "org.eclipse.ui.texteditor.AbstractTextEditor.setInput",
          "source": "AbstractTextEditor.java:2337"
        },
        {
          "method": "org.eclipse.jdt.internal.ui.javaeditor.ClassFileEditor$4.run",
          "source": "ClassFileEditor.java:617"
        },
        {
          "method": "org.eclipse.swt.widgets.RunnableLock.run",
          "source": "RunnableLock.java:35"
        },
        {
          "method": "org.eclipse.swt.widgets.Synchronizer.runAsyncMessages",
          "source": "Synchronizer.java:98"
        },
        {
          "method": "org.eclipse.swt.widgets.Display.runAsyncMessages",
          "source": "Display.java:1819"
        },
        {
          "method": "org.eclipse.swt.widgets.Display.readAndDispatch",
          "source": "Display.java:1553"
        },
        {
          "method": "org.eclipse.jface.window.Window.runEventLoop",
          "source": "Window.java:583"
        },
        {
          "method": "org.eclipse.jface.window.Window.open",
          "source": "Window.java:563"
        },
        {
          "method": "org.eclipse.jface.dialogs.ErrorDialog.open",
          "source": "ErrorDialog.java:292"
        },
        {
          "method": "org.eclipse.jface.dialogs.ErrorDialog.openError",
          "source": "ErrorDialog.java:355"
        },
        {
          "method": "org.eclipse.jface.dialogs.ErrorDialog.openError",
          "source": "ErrorDialog.java:318"
        },
        {
          "method": "org.eclipse.ui.texteditor.AbstractTextEditor.setInput",
          "source": "AbstractTextEditor.java:2343"
        },
        {
          "method": "org.eclipse.jdt.internal.ui.javaeditor.ClassFileEditor$4.run",
          "source": "ClassFileEditor.java:617"
        },
        {
          "method": "org.eclipse.swt.widgets.RunnableLock.run",
          "source": "RunnableLock.java:35"
        },
        {
          "method": "org.eclipse.swt.widgets.Synchronizer.runAsyncMessages",
          "source": "Synchronizer.java:98"
        },
        {
          "method": "org.eclipse.swt.widgets.Display.runAsyncMessages",
          "source": "Display.java:1819"
        },
        {
          "method": "org.eclipse.swt.widgets.Display.readAndDispatch",
          "source": "Display.java:1553"
        },
        {
          "method": "org.eclipse.jface.operation.ModalContext$ModalContextThread.block",
          "source": "ModalContext.java:136"
        },
        {
          "method": "org.eclipse.jface.operation.ModalContext.run",
          "source": "ModalContext.java:261"
        },
        {
          "method": "org.eclipse.jface.wizard.WizardDialog.run",
          "source": "WizardDialog.java:758"
        },
        {
          "method": "org.eclipse.pde.internal.ui.wizards.imports.PluginImportWizard.performFinish",
          "source": "PluginImportWizard.java:145"
        },
        {
          "method": "org.eclipse.jface.wizard.WizardDialog.finishPressed",
          "source": "WizardDialog.java:608"
        },
        {
          "method": "org.eclipse.jface.wizard.WizardDialog.buttonPressed",
          "source": "WizardDialog.java:321"
        },
        {
          "method": "org.eclipse.jface.dialogs.Dialog$1.widgetSelected",
          "source": "Dialog.java:423"
        },
        {
          "method": "org.eclipse.swt.widgets.TypedListener.handleEvent",
          "source": "TypedListener.java:91"
        },
        {
          "method": "org.eclipse.swt.widgets.EventTable.sendEvent",
          "source": "EventTable.java:81"
        },
        {
          "method": "org.eclipse.swt.widgets.Widget.sendEvent",
          "source": "Widget.java:840"
        },
        {
          "method": "org.eclipse.swt.widgets.Display.runDeferredEvents",
          "source": "Display.java:1842"
        },
        {
          "method": "org.eclipse.swt.widgets.Display.readAndDispatch",
          "source": "Display.java:1549"
        },
        {
          "method": "org.eclipse.jface.window.Window.runEventLoop",
          "source": "Window.java:583"
        },
        {
          "method": "org.eclipse.jface.window.Window.open",
          "source": "Window.java:563"
        },
        {
          "method": "org.eclipse.ui.actions.ImportResourcesAction.run",
          "source": "ImportResourcesAction.java:96"
        },
        {
          "method": "org.eclipse.jface.action.Action.runWithEvent",
          "source": "Action.java:842"
        },
        {
          "method": "org.eclipse.jface.action.ActionContributionItem.handleWidgetSelection",
          "source": "ActionContributionItem.java:456"
        },
        {
          "method": "org.eclipse.jface.action.ActionContributionItem.handleWidgetEvent",
          "source": "ActionContributionItem.java:403"
        },
        {
          "method": "org.eclipse.jface.action.ActionContributionItem.access$0",
          "source": "ActionContributionItem.java:397"
        },
        {
          "method": "org.eclipse.jface.action.ActionContributionItem$ActionListener.handleEvent",
          "source": "ActionContributionItem.java:72"
        },
        {
          "method": "org.eclipse.swt.widgets.EventTable.sendEvent",
          "source": "EventTable.java:81"
        },
        {
          "method": "org.eclipse.swt.widgets.Widget.sendEvent",
          "source": "Widget.java:840"
        },
        {
          "method": "org.eclipse.swt.widgets.Display.runDeferredEvents",
          "source": "Display.java:1842"
        },
        {
          "method": "org.eclipse.swt.widgets.Display.readAndDispatch",
          "source": "Display.java:1549"
        },
        {
          "method": "org.eclipse.ui.internal.Workbench.runEventLoop",
          "source": "Workbench.java:1402"
        },
        {
          "method": "org.eclipse.ui.internal.Workbench.run",
          "source": "Workbench.java:1385"
        },
        {
          "method": "org.eclipse.core.internal.boot.InternalBootLoader.run",
          "source": "InternalBootLoader.java:845"
        },
        {
          "method": "org.eclipse.core.boot.BootLoader.run",
          "source": "BootLoader.java:461"
        },
        {
          "method": "sun.reflect.NativeMethodAccessorImpl.invoke0",
          "source": "Native Method"
        },
        {
          "method": "sun.reflect.NativeMethodAccessorImpl.invoke",
          "source": "NativeMethodAccessorImpl.java:39"
        },
        {
          "method": "sun.reflect.DelegatingMethodAccessorImpl.invoke",
          "source": "DelegatingMethodAccessorImpl.java:25"
        },
        {
          "method": "java.lang.reflect.Method.invoke",
          "source": "Method.java:324"
        },
        {
          "method": "org.eclipse.core.launcher.Main.basicRun",
          "source": "Main.java:291"
        },
        {
          "method": "org.eclipse.core.launcher.Main.run",
          "source": "Main.java:747"
        },
        {
          "method": "org.eclipse.core.launcher.Main.main",
          "source": "Main.java:583"
        }
      ],
      "number": 3,
      "commentIndex": 0,
      "bugId": "35455",
      "duplicateId": "35236",
      "date": "2003-03-21T12:44:47+01:00",
      "product": "JDT",
      "component": "Text",
      "severity": "normal"
    },
    {
      "exceptionType": "org.eclipse.swt.SWTException",
      "message": "Failed to execute runnable  (java.lang.NullPointerException)",
      "elements": [
        {
          "method": "org.eclipse.swt.SWT.error",
          "source": "SWT.java:2320"
        },
        {
          "method": "org.eclipse.swt.widgets.Synchronizer.runAsyncMessages",
          "source": "Synchronizer.java:101"
        },
        {
          "method": "org.eclipse.swt.widgets.Display.runAsyncMessages",
          "source": "Display.java:1819"
        },
        {
          "method": "org.eclipse.swt.widgets.Display.readAndDispatch",
          "source": "Display.java:1553"
        },
        {
          "method": "org.eclipse.jface.window.Window.runEventLoop",
          "source": "Window.java:583"
        },
        {
          "method": "org.eclipse.jface.window.Window.open",
          "source": "Window.java:563"
        },
        {
          "method": "org.eclipse.jface.dialogs.ErrorDialog.open",
          "source": "ErrorDialog.java:292"
        },
        {
          "method": "org.eclipse.jface.dialogs.ErrorDialog.openError",
          "source": "ErrorDialog.java:355"
        },
        {
          "method": "org.eclipse.jface.dialogs.ErrorDialog.openError",
          "source": "ErrorDialog.java:318"
        },
        {
          "method": "org.eclipse.ui.texteditor.AbstractTextEditor.setInput",
          "source": "AbstractTextEditor.java:2343"
        },
        {
          "method": "org.eclipse.jdt.internal.ui.javaeditor.ClassFileEditor$4.run",
          "source": "ClassFileEditor.java:617"
        },
        {
          "method": "org.eclipse.swt.widgets.RunnableLock.run",
          "source": "RunnableLock.java:35"
        },
        {
          "method": "org.eclipse.swt.widgets.Synchronizer.runAsyncMessages",
          "source": "Synchronizer.java:98"
        },
        {
          "method": "org.eclipse.swt.widgets.Display.runAsyncMessages",
          "source": "Display.java:1819"
        },
        {
          "method": "org.eclipse.swt.widgets.Display.readAndDispatch",
          "source": "Display.java:1553"
        },
        {
          "method": "org.eclipse.jface.operation.ModalContext$ModalContextThread.block",
          "source": "ModalContext.java:136"
        },
        {
          "method": "org.eclipse.jface.operation.ModalContext.run",
          "source": "ModalContext.java:261"
        },
        {
          "method": "org.eclipse.jface.wizard.WizardDialog.run",
          "source": "WizardDialog.java:758"
        },
        {
          "method": "org.eclipse.pde.internal.ui.wizards.imports.PluginImportWizard.performFinish",
          "source": "PluginImportWizard.java:145"
        },
        {
          "method": "org.eclipse.jface.wizard.WizardDialog.finishPressed",
          "source": "WizardDialog.java:608"
        },
        {
          "method": "org.eclipse.jface.wizard.WizardDialog.buttonPressed",
          "source": "WizardDialog.java:321"
        },
        {
          "method": "org.eclipse.jface.dialogs.Dialog$1.widgetSelected",
          "source": "Dialog.java:423"
        },
        {
          "method": "org.eclipse.swt.widgets.TypedListener.handleEvent",
          "source": "TypedListener.java:91"
        },
        {
          "method": "org.eclipse.swt.widgets.EventTable.sendEvent",
          "source": "EventTable.java:81"
        },
        {
          "method": "org.eclipse.swt.widgets.Widget.sendEvent",
          "source": "Widget.java:840"
        },
        {
          "method": "org.eclipse.swt.widgets.Display.runDeferredEvents",
          "source": "Display.java:1842"
        },
        {
          "method": "org.eclipse.swt.widgets.Display.readAndDispatch",
          "source": "Display.java:1549"
        },
        {
          "method": "org.eclipse.jface.window.Window.runEventLoop",
          "source": "Window.java:583"
        },
        {
          "method": "org.eclipse.jface.window.Window.open",
          "source": "Window.java:563"
        },
        {
          "method": "org.eclipse.ui.actions.ImportResourcesAction.run",
          "source": "ImportResourcesAction.java:96"
        },
        {
          "method": "org.eclipse.jface.action.Action.runWithEvent",
          "source": "Action.java:842"
        },
        {
          "method": "org.eclipse.jface.action.ActionContributionItem.handleWidgetSelection",
          "source": "ActionContributionItem.java:456"
        },
        {
          "method": "org.eclipse.jface.action.ActionContributionItem.handleWidgetEvent",
          "source": "ActionContributionItem.java:403"
        },
        {
          "method": "org.eclipse.jface.action.ActionContributionItem.access$0",
          "source": "ActionContributionItem.java:397"
        },
        {
          "method": "org.eclipse.jface.action.ActionContributionItem$ActionListener.handleEvent",
          "source": "ActionContributionItem.java:72"
        },
        {
          "method": "org.eclipse.swt.widgets.EventTable.sendEvent",
          "source": "EventTable.java:81"
        },
        {
          "method": "org.eclipse.swt.widgets.Widget.sendEvent",
          "source": "Widget.java:840"
        },
        {
          "method": "org.eclipse.swt.widgets.Display.runDeferredEvents",
          "source": "Display.java:1842"
        },
        {
          "method": "org.eclipse.swt.widgets.Display.readAndDispatch",
          "source": "Display.java:1549"
        },
        {
          "method": "org.eclipse.ui.internal.Workbench.runEventLoop",
          "source": "Workbench.java:1402"
        },
        {
          "method": "org.eclipse.ui.internal.Workbench.run",
          "source": "Workbench.java:1385"
        },
        {
          "method": "org.eclipse.core.internal.boot.InternalBootLoader.run",
          "source": "InternalBootLoader.java:845"
        },
        {
          "method": "org.eclipse.core.boot.BootLoader.run",
          "source": "BootLoader.java:461"
        },
        {
          "method": "sun.reflect.NativeMethodAccessorImpl.invoke0",
          "source": "Native Method"
        },
        {
          "method": "sun.reflect.NativeMethodAccessorImpl.invoke",
          "source": "NativeMethodAccessorImpl.java:39"
        },
        {
          "method": "sun.reflect.DelegatingMethodAccessorImpl.invoke",
          "source": "DelegatingMethodAccessorImpl.java:25"
        },
        {
          "method": "java.lang.reflect.Method.invoke",
          "source": "Method.java:324"
        },
        {
          "method": "org.eclipse.core.launcher.Main.basicRun",
          "source": "Main.java:291"
        },
        {
          "method": "org.eclipse.core.launcher.Main.run",
          "source": "Main.java:747"
        },
        {
          "method": "org.eclipse.core.launcher.Main.main",
          "source": "Main.java:583"
        }
      ],
      "number": 4,
      "commentIndex": 0,
      "bugId": "35455",
      "duplicateId": "35236",
      "date": "2003-03-21T12:44:47+01:00",
      "product": "JDT",
      "component": "Text",
      "severity": "normal"
    },
    {
      "exceptionType": "java.lang.NullPointerException",
      "elements": [
        {
          "method": "org.eclipse.ui.texteditor.AbstractTextEditor.doSetInput",
          "source": "AbstractTextEditor.java:2308"
        },
        {
          "method": "org.eclipse.ui.texteditor.StatusTextEditor.doSetInput",
          "source": "StatusTextEditor.java:160"
        },
        {
          "method": "org.eclipse.jdt.internal.ui.javaeditor.JavaEditor.doSetInput",
          "source": "JavaEditor.java:1560"
        },
        {
          "method": "org.eclipse.jdt.internal.ui.javaeditor.ClassFileEditor.doSetInput",
          "source": "ClassFileEditor.java:518"
        },
        {
          "method": "org.eclipse.ui.texteditor.AbstractTextEditor.setInput",
          "source": "AbstractTextEditor.java:2337"
        },
        {
          "method": "org.eclipse.jdt.internal.ui.javaeditor.ClassFileEditor$4.run",
          "source": "ClassFileEditor.java:617"
        },
        {
          "method": "org.eclipse.swt.widgets.RunnableLock.run",
          "source": "RunnableLock.java:35"
        },
        {
          "method": "org.eclipse.swt.widgets.Synchronizer.runAsyncMessages",
          "source": "Synchronizer.java:98"
        },
        {
          "method": "org.eclipse.swt.widgets.Display.runAsyncMessages",
          "source": "Display.java:1819"
        },
        {
          "method": "org.eclipse.swt.widgets.Display.readAndDispatch",
          "source": "Display.java:1553"
        },
        {
          "method": "org.eclipse.jface.window.Window.runEventLoop",
          "source": "Window.java:583"
        },
        {
          "method": "org.eclipse.jface.window.Window.open",
          "source": "Window.java:563"
        },
        {
          "method": "org.eclipse.jface.dialogs.ErrorDialog.open",
          "source": "ErrorDialog.java:292"
        },
        {
          "method": "org.eclipse.jface.dialogs.ErrorDialog.openError",
          "source": "ErrorDialog.java:355"
        },
        {
          "method": "org.eclipse.jface.dialogs.ErrorDialog.openError",
          "source": "ErrorDialog.java:318"
        },
        {
          "method": "org.eclipse.ui.texteditor.AbstractTextEditor.setInput",
          "source": "AbstractTextEditor.java:2343"
        },
        {
          "method": "org.eclipse.jdt.internal.ui.javaeditor.ClassFileEditor$4.run",
          "source": "ClassFileEditor.java:617"
        },
        {
          "method": "org.eclipse.swt.widgets.RunnableLock.run",
          "source": "RunnableLock.java:35"
        },
        {
          "method": "org.eclipse.swt.widgets.Synchronizer.runAsyncMessages",
          "source": "Synchronizer.java:98"
        },
        {
          "method": "org.eclipse.swt.widgets.Display.runAsyncMessages",
          "source": "Display.java:1819"
        },
        {
          "method": "org.eclipse.swt.widgets.Display.readAndDispatch",
          "source": "Display.java:1553"
        },
        {
          "method": "org.eclipse.jface.operation.ModalContext$ModalContextThread.block",
          "source": "ModalContext.java:136"
        },
        {
          "method": "org.eclipse.jface.operation.ModalContext.run",
          "source": "ModalContext.java:261"
        },
        {
          "method": "org.eclipse.jface.wizard.WizardDialog.run",
          "source": "WizardDialog.java:758"
        },
        {
          "method": "org.eclipse.pde.internal.ui.wizards.imports.PluginImportWizard.performFinish",
          "source": "PluginImportWizard.java:145"
        },
        {
          "method": "org.eclipse.jface.wizard.WizardDialog.finishPressed",
          "source": "WizardDialog.java:608"
        },
        {
          "method": "org.eclipse.jface.wizard.WizardDialog.buttonPressed",
          "source": "WizardDialog.java:321"
        },
        {
          "method": "org.eclipse.jface.dialogs.Dialog$1.widgetSelected",
          "source": "Dialog.java:423"
        },
        {
          "method": "org.eclipse.swt.widgets.TypedListener.handleEvent",
          "source": "TypedListener.java:91"
        },
        {
          "method": "org.eclipse.swt.widgets.EventTable.sendEvent",
          "source": "EventTable.java:81"
        },
        {
          "method": "org.eclipse.swt.widgets.Widget.sendEvent",
          "source": "Widget.java:840"
        },
        {
          "method": "org.eclipse.swt.widgets.Display.runDeferredEvents",
          "source": "Display.java:1842"
        },
        {
          "method": "org.eclipse.swt.widgets.Display.readAndDispatch",
          "source": "Display.java:1549"
        },
        {
          "method": "org.eclipse.jface.window.Window.runEventLoop",
          "source": "Window.java:583"
        },
        {
          "method": "org.eclipse.jface.window.Window.open",
          "source": "Window.java:563"
        },
        {
          "method": "org.eclipse.ui.actions.ImportResourcesAction.run",
          "source": "ImportResourcesAction.java:96"
        },
        {
          "method": "org.eclipse.jface.action.Action.runWithEvent",
          "source": "Action.java:842"
        },
        {
          "method": "org.eclipse.jface.action.ActionContributionItem.handleWidgetSelection",
          "source": "ActionContributionItem.java:456"
        },
        {
          "method": "org.eclipse.jface.action.ActionContributionItem.handleWidgetEvent",
          "source": "ActionContributionItem.java:403"
        },
        {
          "method": "org.eclipse.jface.action.ActionContributionItem.access$0",
          "source": "ActionContributionItem.java:397"
        },
        {
          "method": "org.eclipse.jface.action.ActionContributionItem$ActionListener.handleEvent",
          "source": "ActionContributionItem.java:72"
        },
        {
          "method": "org.eclipse.swt.widgets.EventTable.sendEvent",
          "source": "EventTable.java:81"
        },
        {
          "method": "org.eclipse.swt.widgets.Widget.sendEvent",
          "source": "Widget.java:840"
        },
        {
          "method": "org.eclipse.swt.widgets.Display.runDeferredEvents",
          "source": "Display.java:1842"
        },
        {
          "method": "org.eclipse.swt.widgets.Display.readAndDispatch",
          "source": "Display.java:1549"
        },
        {
          "method": "org.eclipse.ui.internal.Workbench.runEventLoop",
          "source": "Workbench.java:1402"
        },
        {
          "method": "org.eclipse.ui.internal.Workbench.run",
          "source": "Workbench.java:1385"
        },
        {
          "method": "org.eclipse.core.internal.boot.InternalBootLoader.run",
          "source": "InternalBootLoader.java:845"
        },
        {
          "method": "org.eclipse.core.boot.BootLoader.run",
          "source": "BootLoader.java:461"
        },
        {
          "method": "sun.reflect.NativeMethodAccessorImpl.invoke0",
          "source": "Native Method"
        },
        {
          "method": "sun.reflect.NativeMethodAccessorImpl.invoke",
          "source": "NativeMethodAccessorImpl.java:39"
        },
        {
          "method": "sun.reflect.DelegatingMethodAccessorImpl.invoke",
          "source": "DelegatingMethodAccessorImpl.java:25"
        },
        {
          "method": "java.lang.reflect.Method.invoke",
          "source": "Method.java:324"
        },
        {
          "method": "org.eclipse.core.launcher.Main.basicRun",
          "source": "Main.java:291"
        },
        {
          "method": "org.eclipse.core.launcher.Main.run",
          "source": "Main.java:747"
        },
        {
          "method": "org.eclipse.core.launcher.Main.main",
          "source": "Main.java:583"
        }
      ],
      "number": 5,
      "commentIndex": 0,
      "bugId": "35455",
      "duplicateId": "35236",
      "date": "2003-03-21T12:44:47+01:00",
      "product": "JDT",
      "component": "Text",
      "severity": "normal"
    },
    {
      "exceptionType": "org.eclipse.swt.SWTException",
      "message": "Failed to execute runnable  (java.lang.NullPointerException)",
      "elements": [
        {
          "method": "org.eclipse.swt.SWT.error",
          "source": "SWT.java:2320"
        },
        {
          "method": "org.eclipse.swt.widgets.Synchronizer.runAsyncMessages",
          "source": "Synchronizer.java:101"
        },
        {
          "method": "org.eclipse.swt.widgets.Display.runAsyncMessages",
          "source": "Display.java:1819"
        },
        {
          "method": "org.eclipse.swt.widgets.Display.readAndDispatch",
          "source": "Display.java:1553"
        },
        {
          "method": "org.eclipse.jface.window.Window.runEventLoop",
          "source": "Window.java:583"
        },
        {
          "method": "org.eclipse.jface.window.Window.open",
          "source": "Window.java:563"
        },
        {
          "method": "org.eclipse.jface.dialogs.ErrorDialog.open",
          "source": "ErrorDialog.java:292"
        },
        {
          "method": "org.eclipse.jface.dialogs.ErrorDialog.openError",
          "source": "ErrorDialog.java:355"
        },
        {
          "method": "org.eclipse.jface.dialogs.ErrorDialog.openError",
          "source": "ErrorDialog.java:318"
        },
        {
          "method": "org.eclipse.ui.texteditor.AbstractTextEditor.setInput",
          "source": "AbstractTextEditor.java:2343"
        },
        {
          "method": "org.eclipse.jdt.internal.ui.javaeditor.ClassFileEditor$4.run",
          "source": "ClassFileEditor.java:617"
        },
        {
          "method": "org.eclipse.swt.widgets.RunnableLock.run",
          "source": "RunnableLock.java:35"
        },
        {
          "method": "org.eclipse.swt.widgets.Synchronizer.runAsyncMessages",
          "source": "Synchronizer.java:98"
        },
        {
          "method": "org.eclipse.swt.widgets.Display.runAsyncMessages",
          "source": "Display.java:1819"
        },
        {
          "method": "org.eclipse.swt.widgets.Display.readAndDispatch",
          "source": "Display.java:1553"
        },
        {
          "method": "org.eclipse.jface.operation.ModalContext$ModalContextThread.block",
          "source": "ModalContext.java:136"
        },
        {
          "method": "org.eclipse.jface.operation.ModalContext.run",
          "source": "ModalContext.java:261"
        },
        {
          "method": "org.eclipse.jface.wizard.WizardDialog.run",
          "source": "WizardDialog.java:758"
        },
        {
          "method": "org.eclipse.pde.internal.ui.wizards.imports.PluginImportWizard.performFinish",
          "source": "PluginImportWizard.java:145"
        },
        {
          "method": "org.eclipse.jface.wizard.WizardDialog.finishPressed",
          "source": "WizardDialog.java:608"
        },
        {
          "method": "org.eclipse.jface.wizard.WizardDialog.buttonPressed",
          "source": "WizardDialog.java:321"
        },
        {
          "method": "org.eclipse.jface.dialogs.Dialog$1.widgetSelected",
          "source": "Dialog.java:423"
        },
        {
          "method": "org.eclipse.swt.widgets.TypedListener.handleEvent",
          "source": "TypedListener.java:91"
        },
        {
          "method": "org.eclipse.swt.widgets.EventTable.sendEvent",
          "source": "EventTable.java:81"
        },
        {
          "method": "org.eclipse.swt.widgets.Widget.sendEvent",
          "source": "Widget.java:840"
        },
        {
          "method": "org.eclipse.swt.widgets.Display.runDeferredEvents",
          "source": "Display.java:1842"
        },
        {
          "method": "org.eclipse.swt.widgets.Display.readAndDispatch",
          "source": "Display.java:1549"
        },
        {
          "method": "org.eclipse.jface.window.Window.runEventLoop",
          "source": "Window.java:583"
        },
        {
          "method": "org.eclipse.jface.window.Window.open",
          "source": "Window.java:563"
        },
        {
          "method": "org.eclipse.ui.actions.ImportResourcesAction.run",
          "source": "ImportResourcesAction.java:96"
        },
        {
          "method": "org.eclipse.jface.action.Action.runWithEvent",
          "source": "Action.java:842"
        },
        {
          "method": "org.eclipse.jface.action.ActionContributionItem.handleWidgetSelection",
          "source": "ActionContributionItem.java:456"
        },
        {
          "method": "org.eclipse.jface.action.ActionContributionItem.handleWidgetEvent",
          "source": "ActionContributionItem.java:403"
        },
        {
          "method": "org.eclipse.jface.action.ActionContributionItem.access$0",
          "source": "ActionContributionItem.java:397"
        },
        {
          "method": "org.eclipse.jface.action.ActionContributionItem$ActionListener.handleEvent",
          "source": "ActionContributionItem.java:72"
        },
        {
          "method": "org.eclipse.swt.widgets.EventTable.sendEvent",
          "source": "EventTable.java:81"
        },
        {
          "method": "org.eclipse.swt.widgets.Widget.sendEvent",
          "source": "Widget.java:840"
        },
        {
          "method": "org.eclipse.swt.widgets.Display.runDeferredEvents",
          "source": "Display.java:1842"
        },
        {
          "method": "org.eclipse.swt.widgets.Display.readAndDispatch",
          "source": "Display.java:1549"
        },
        {
          "method": "org.eclipse.ui.internal.Workbench.runEventLoop",
          "source": "Workbench.java:1402"
        },
        {
          "method": "org.eclipse.ui.internal.Workbench.run",
          "source": "Workbench.java:1385"
        },
        {
          "method": "org.eclipse.core.internal.boot.InternalBootLoader.run",
          "source": "InternalBootLoader.java:845"
        },
        {
          "method": "org.eclipse.core.boot.BootLoader.run",
          "source": "BootLoader.java:461"
        },
        {
          "method": "sun.reflect.NativeMethodAccessorImpl.invoke0",
          "source": "Native Method"
        },
        {
          "method": "sun.reflect.NativeMethodAccessorImpl.invoke",
          "source": "NativeMethodAccessorImpl.java:39"
        },
        {
          "method": "sun.reflect.DelegatingMethodAccessorImpl.invoke",
          "source": "DelegatingMethodAccessorImpl.java:25"
        },
        {
          "method": "java.lang.reflect.Method.invoke",
          "source": "Method.java:324"
        },
        {
          "method": "org.eclipse.core.launcher.Main.basicRun",
          "source": "Main.java:291"
        },
        {
          "method": "org.eclipse.core.launcher.Main.run",
          "source": "Main.java:747"
        },
        {
          "method": "org.eclipse.core.launcher.Main.main",
          "source": "Main.java:583"
        }
      ],
      "number": 6,
      "commentIndex": 0,
      "bugId": "35455",
      "duplicateId": "35236",
      "date": "2003-03-21T12:44:47+01:00",
      "product": "JDT",
      "component": "Text",
      "severity": "normal"
    },
    {
      "exceptionType": "java.lang.NullPointerException",
      "elements": [
        {
          "method": "org.eclipse.ui.texteditor.AbstractTextEditor.doSetInput",
          "source": "AbstractTextEditor.java:2308"
        },
        {
          "method": "org.eclipse.ui.texteditor.StatusTextEditor.doSetInput",
          "source": "StatusTextEditor.java:160"
        },
        {
          "method": "org.eclipse.jdt.internal.ui.javaeditor.JavaEditor.doSetInput",
          "source": "JavaEditor.java:1560"
        },
        {
          "method": "org.eclipse.jdt.internal.ui.javaeditor.ClassFileEditor.doSetInput",
          "source": "ClassFileEditor.java:518"
        },
        {
          "method": "org.eclipse.ui.texteditor.AbstractTextEditor.setInput",
          "source": "AbstractTextEditor.java:2337"
        },
        {
          "method": "org.eclipse.jdt.internal.ui.javaeditor.ClassFileEditor$4.run",
          "source": "ClassFileEditor.java:617"
        },
        {
          "method": "org.eclipse.swt.widgets.RunnableLock.run",
          "source": "RunnableLock.java:35"
        },
        {
          "method": "org.eclipse.swt.widgets.Synchronizer.runAsyncMessages",
          "source": "Synchronizer.java:98"
        },
        {
          "method": "org.eclipse.swt.widgets.Display.runAsyncMessages",
          "source": "Display.java:1819"
        },
        {
          "method": "org.eclipse.swt.widgets.Display.readAndDispatch",
          "source": "Display.java:1553"
        },
        {
          "method": "org.eclipse.jface.window.Window.runEventLoop",
          "source": "Window.java:583"
        },
        {
          "method": "org.eclipse.jface.window.Window.open",
          "source": "Window.java:563"
        },
        {
          "method": "org.eclipse.jface.dialogs.ErrorDialog.open",
          "source": "ErrorDialog.java:292"
        },
        {
          "method": "org.eclipse.jface.dialogs.ErrorDialog.openError",
          "source": "ErrorDialog.java:355"
        },
        {
          "method": "org.eclipse.jface.dialogs.ErrorDialog.openError",
          "source": "ErrorDialog.java:318"
        },
        {
          "method": "org.eclipse.ui.texteditor.AbstractTextEditor.setInput",
          "source": "AbstractTextEditor.java:2343"
        },
        {
          "method": "org.eclipse.jdt.internal.ui.javaeditor.ClassFileEditor$4.run",
          "source": "ClassFileEditor.java:617"
        },
        {
          "method": "org.eclipse.swt.widgets.RunnableLock.run",
          "source": "RunnableLock.java:35"
        },
        {
          "method": "org.eclipse.swt.widgets.Synchronizer.runAsyncMessages",
          "source": "Synchronizer.java:98"
        },
        {
          "method": "org.eclipse.swt.widgets.Display.runAsyncMessages",
          "source": "Display.java:1819"
        },
        {
          "method": "org.eclipse.swt.widgets.Display.readAndDispatch",
          "source": "Display.java:1553"
        },
        {
          "method": "org.eclipse.jface.operation.ModalContext$ModalContextThread.block",
          "source": "ModalContext.java:136"
        },
        {
          "method": "org.eclipse.jface.operation.ModalContext.run",
          "source": "ModalContext.java:261"
        },
        {
          "method": "org.eclipse.jface.wizard.WizardDialog.run",
          "source": "WizardDialog.java:758"
        },
        {
          "method": "org.eclipse.pde.internal.ui.wizards.imports.PluginImportWizard.performFinish",
          "source": "PluginImportWizard.java:145"
        },
        {
          "method": "org.eclipse.jface.wizard.WizardDialog.finishPressed",
          "source": "WizardDialog.java:608"
        },
        {
          "method": "org.eclipse.jface.wizard.WizardDialog.buttonPressed",
          "source": "WizardDialog.java:321"
        },
        {
          "method": "org.eclipse.jface.dialogs.Dialog$1.widgetSelected",
          "source": "Dialog.java:423"
        },
        {
          "method": "org.eclipse.swt.widgets.TypedListener.handleEvent",
          "source": "TypedListener.java:91"
        },
        {
          "method": "org.eclipse.swt.widgets.EventTable.sendEvent",
          "source": "EventTable.java:81"
        },
        {
          "method": "org.eclipse.swt.widgets.Widget.sendEvent",
          "source": "Widget.java:840"
        },
        {
          "method": "org.eclipse.swt.widgets.Display.runDeferredEvents",
          "source": "Display.java:1842"
        },
        {
          "method": "org.eclipse.swt.widgets.Display.readAndDispatch",
          "source": "Display.java:1549"
        },
        {
          "method": "org.eclipse.jface.window.Window.runEventLoop",
          "source": "Window.java:583"
        },
        {
          "method": "org.eclipse.jface.window.Window.open",
          "source": "Window.java:563"
        },
        {
          "method": "org.eclipse.ui.actions.ImportResourcesAction.run",
          "source": "ImportResourcesAction.java:96"
        },
        {
          "method": "org.eclipse.jface.action.Action.runWithEvent",
          "source": "Action.java:842"
        },
        {
          "method": "org.eclipse.jface.action.ActionContributionItem.handleWidgetSelection",
          "source": "ActionContributionItem.java:456"
        },
        {
          "method": "org.eclipse.jface.action.ActionContributionItem.handleWidgetEvent",
          "source": "ActionContributionItem.java:403"
        },
        {
          "method": "org.eclipse.jface.action.ActionContributionItem.access$0",
          "source": "ActionContributionItem.java:397"
        },
        {
          "method": "org.eclipse.jface.action.ActionContributionItem$ActionListener.handleEvent",
          "source": "ActionContributionItem.java:72"
        },
        {
          "method": "org.eclipse.swt.widgets.EventTable.sendEvent",
          "source": "EventTable.java:81"
        },
        {
          "method": "org.eclipse.swt.widgets.Widget.sendEvent",
          "source": "Widget.java:840"
        },
        {
          "method": "org.eclipse.swt.widgets.Display.runDeferredEvents",
          "source": "Display.java:1842"
        },
        {
          "method": "org.eclipse.swt.widgets.Display.readAndDispatch",
          "source": "Display.java:1549"
        },
        {
          "method": "org.eclipse.ui.internal.Workbench.runEventLoop",
          "source": "Workbench.java:1402"
        },
        {
          "method": "org.eclipse.ui.internal.Workbench.run",
          "source": "Workbench.java:1385"
        },
        {
          "method": "org.eclipse.core.internal.boot.InternalBootLoader.run",
          "source": "InternalBootLoader.java:845"
        },
        {
          "method": "org.eclipse.core.boot.BootLoader.run",
          "source": "BootLoader.java:461"
        },
        {
          "method": "sun.reflect.NativeMethodAccessorImpl.invoke0",
          "source": "Native Method"
        },
        {
          "method": "sun.reflect.NativeMethodAccessorImpl.invoke",
          "source": "NativeMethodAccessorImpl.java:39"
        },
        {
          "method": "sun.reflect.DelegatingMethodAccessorImpl.invoke",
          "source": "DelegatingMethodAccessorImpl.java:25"
        },
        {
          "method": "java.lang.reflect.Method.invoke",
          "source": "Method.java:324"
        },
        {
          "method": "org.eclipse.core.launcher.Main.basicRun",
          "source": "Main.java:291"
        },
        {
          "method": "org.eclipse.core.launcher.Main.run",
          "source": "Main.java:747"
        },
        {
          "method": "org.eclipse.core.launcher.Main.main",
          "source": "Main.java:583"
        }
      ],
      "number": 7,
      "commentIndex": 0,
      "bugId": "35455",
      "duplicateId": "35236",
      "date": "2003-03-21T12:44:47+01:00",
      "product": "JDT",
      "component": "Text",
      "severity": "normal"
    },
    {
      "exceptionType": "org.eclipse.swt.SWTException",
      "message": "Failed to execute runnable  (java.lang.NullPointerException)",
      "elements": [
        {
          "method": "org.eclipse.swt.SWT.error",
          "source": "SWT.java:2320"
        },
        {
          "method": "org.eclipse.swt.widgets.Synchronizer.runAsyncMessages",
          "source": "Synchronizer.java:101"
        },
        {
          "method": "org.eclipse.swt.widgets.Display.runAsyncMessages",
          "source": "Display.java:1819"
        },
        {
          "method": "org.eclipse.swt.widgets.Display.readAndDispatch",
          "source": "Display.java:1553"
        },
        {
          "method": "org.eclipse.jface.window.Window.runEventLoop",
          "source": "Window.java:583"
        },
        {
          "method": "org.eclipse.jface.window.Window.open",
          "source": "Window.java:563"
        },
        {
          "method": "org.eclipse.jface.dialogs.ErrorDialog.open",
          "source": "ErrorDialog.java:292"
        },
        {
          "method": "org.eclipse.jface.dialogs.ErrorDialog.openError",
          "source": "ErrorDialog.java:355"
        },
        {
          "method": "org.eclipse.jface.dialogs.ErrorDialog.openError",
          "source": "ErrorDialog.java:318"
        },
        {
          "method": "org.eclipse.ui.texteditor.AbstractTextEditor.setInput",
          "source": "AbstractTextEditor.java:2343"
        },
        {
          "method": "org.eclipse.jdt.internal.ui.javaeditor.ClassFileEditor$4.run",
          "source": "ClassFileEditor.java:617"
        },
        {
          "method": "org.eclipse.swt.widgets.RunnableLock.run",
          "source": "RunnableLock.java:35"
        },
        {
          "method": "org.eclipse.swt.widgets.Synchronizer.runAsyncMessages",
          "source": "Synchronizer.java:98"
        },
        {
          "method": "org.eclipse.swt.widgets.Display.runAsyncMessages",
          "source": "Display.java:1819"
        },
        {
          "method": "org.eclipse.swt.widgets.Display.readAndDispatch",
          "source": "Display.java:1553"
        },
        {
          "method": "org.eclipse.jface.operation.ModalContext$ModalContextThread.block",
          "source": "ModalContext.java:136"
        },
        {
          "method": "org.eclipse.jface.operation.ModalContext.run",
          "source": "ModalContext.java:261"
        },
        {
          "method": "org.eclipse.jface.wizard.WizardDialog.run",
          "source": "WizardDialog.java:758"
        },
        {
          "method": "org.eclipse.pde.internal.ui.wizards.imports.PluginImportWizard.performFinish",
          "source": "PluginImportWizard.java:145"
        },
        {
          "method": "org.eclipse.jface.wizard.WizardDialog.finishPressed",
          "source": "WizardDialog.java:608"
        },
        {
          "method": "org.eclipse.jface.wizard.WizardDialog.buttonPressed",
          "source": "WizardDialog.java:321"
        },
        {
          "method": "org.eclipse.jface.dialogs.Dialog$1.widgetSelected",
          "source": "Dialog.java:423"
        },
        {
          "method": "org.eclipse.swt.widgets.TypedListener.handleEvent",
          "source": "TypedListener.java:91"
        },
        {
          "method": "org.eclipse.swt.widgets.EventTable.sendEvent",
          "source": "EventTable.java:81"
        },
        {
          "method": "org.eclipse.swt.widgets.Widget.sendEvent",
          "source": "Widget.java:840"
        },
        {
          "method": "org.eclipse.swt.widgets.Display.runDeferredEvents",
          "source": "Display.java:1842"
        },
        {
          "method": "org.eclipse.swt.widgets.Display.readAndDispatch",
          "source": "Display.java:1549"
        },
        {
          "method": "org.eclipse.jface.window.Window.runEventLoop",
          "source": "Window.java:583"
        },
        {
          "method": "org.eclipse.jface.window.Window.open",
          "source": "Window.java:563"
        },
        {
          "method": "org.eclipse.ui.actions.ImportResourcesAction.run",
          "source": "ImportResourcesAction.java:96"
        },
        {
          "method": "org.eclipse.jface.action.Action.runWithEvent",
          "source": "Action.java:842"
        },
        {
          "method": "org.eclipse.jface.action.ActionContributionItem.handleWidgetSelection",
          "source": "ActionContributionItem.java:456"
        },
        {
          "method": "org.eclipse.jface.action.ActionContributionItem.handleWidgetEvent",
          "source": "ActionContributionItem.java:403"
        },
        {
          "method": "org.eclipse.jface.action.ActionContributionItem.access$0",
          "source": "ActionContributionItem.java:397"
        },
        {
          "method": "org.eclipse.jface.action.ActionContributionItem$ActionListener.handleEvent",
          "source": "ActionContributionItem.java:72"
        },
        {
          "method": "org.eclipse.swt.widgets.EventTable.sendEvent",
          "source": "EventTable.java:81"
        },
        {
          "method": "org.eclipse.swt.widgets.Widget.sendEvent",
          "source": "Widget.java:840"
        },
        {
          "method": "org.eclipse.swt.widgets.Display.runDeferredEvents",
          "source": "Display.java:1842"
        },
        {
          "method": "org.eclipse.swt.widgets.Display.readAndDispatch",
          "source": "Display.java:1549"
        },
        {
          "method": "org.eclipse.ui.internal.Workbench.runEventLoop",
          "source": "Workbench.java:1402"
        },
        {
          "method": "org.eclipse.ui.internal.Workbench.run",
          "source": "Workbench.java:1385"
        },
        {
          "method": "org.eclipse.core.internal.boot.InternalBootLoader.run",
          "source": "InternalBootLoader.java:845"
        },
        {
          "method": "org.eclipse.core.boot.BootLoader.run",
          "source": "BootLoader.java:461"
        },
        {
          "method": "sun.reflect.NativeMethodAccessorImpl.invoke0",
          "source": "Native Method"
        },
        {
          "method": "sun.reflect.NativeMethodAccessorImpl.invoke",
          "source": "NativeMethodAccessorImpl.java:39"
        },
        {
          "method": "sun.reflect.DelegatingMethodAccessorImpl.invoke",
          "source": "DelegatingMethodAccessorImpl.java:25"
        },
        {
          "method": "java.lang.reflect.Method.invoke",
          "source": "Method.java:324"
        },
        {
          "method": "org.eclipse.core.launcher.Main.basicRun",
          "source": "Main.java:291"
        },
        {
          "method": "org.eclipse.core.launcher.Main.run",
          "source": "Main.java:747"
        },
        {
          "method": "org.eclipse.core.launcher.Main.main",
          "source": "Main.java:583"
        }
      ],
      "number": 8,
      "commentIndex": 0,
      "bugId": "35455",
      "duplicateId": "35236",
      "date": "2003-03-21T12:44:47+01:00",
      "product": "JDT",
      "component": "Text",
      "severity": "normal"
    },
    {
      "exceptionType": "java.lang.NullPointerException",
      "elements": [
        {
          "method": "org.eclipse.ui.texteditor.AbstractTextEditor.doSetInput",
          "source": "AbstractTextEditor.java:2308"
        },
        {
          "method": "org.eclipse.ui.texteditor.StatusTextEditor.doSetInput",
          "source": "StatusTextEditor.java:160"
        },
        {
          "method": "org.eclipse.jdt.internal.ui.javaeditor.JavaEditor.doSetInput",
          "source": "JavaEditor.java:1560"
        },
        {
          "method": "org.eclipse.jdt.internal.ui.javaeditor.ClassFileEditor.doSetInput",
          "source": "ClassFileEditor.java:518"
        },
        {
          "method": "org.eclipse.ui.texteditor.AbstractTextEditor.setInput",
          "source": "AbstractTextEditor.java:2337"
        },
        {
          "method": "org.eclipse.jdt.internal.ui.javaeditor.ClassFileEditor$4.run",
          "source": "ClassFileEditor.java:617"
        },
        {
          "method": "org.eclipse.swt.widgets.RunnableLock.run",
          "source": "RunnableLock.java:35"
        },
        {
          "method": "org.eclipse.swt.widgets.Synchronizer.runAsyncMessages",
          "source": "Synchronizer.java:98"
        },
        {
          "method": "org.eclipse.swt.widgets.Display.runAsyncMessages",
          "source": "Display.java:1819"
        },
        {
          "method": "org.eclipse.swt.widgets.Display.readAndDispatch",
          "source": "Display.java:1553"
        },
        {
          "method": "org.eclipse.jface.window.Window.runEventLoop",
          "source": "Window.java:583"
        },
        {
          "method": "org.eclipse.jface.window.Window.open",
          "source": "Window.java:563"
        },
        {
          "method": "org.eclipse.jface.dialogs.ErrorDialog.open",
          "source": "ErrorDialog.java:292"
        },
        {
          "method": "org.eclipse.jface.dialogs.ErrorDialog.openError",
          "source": "ErrorDialog.java:355"
        },
        {
          "method": "org.eclipse.jface.dialogs.ErrorDialog.openError",
          "source": "ErrorDialog.java:318"
        },
        {
          "method": "org.eclipse.ui.texteditor.AbstractTextEditor.setInput",
          "source": "AbstractTextEditor.java:2343"
        },
        {
          "method": "org.eclipse.jdt.internal.ui.javaeditor.ClassFileEditor$4.run",
          "source": "ClassFileEditor.java:617"
        },
        {
          "method": "org.eclipse.swt.widgets.RunnableLock.run",
          "source": "RunnableLock.java:35"
        },
        {
          "method": "org.eclipse.swt.widgets.Synchronizer.runAsyncMessages",
          "source": "Synchronizer.java:98"
        },
        {
          "method": "org.eclipse.swt.widgets.Display.runAsyncMessages",
          "source": "Display.java:1819"
        },
        {
          "method": "org.eclipse.swt.widgets.Display.readAndDispatch",
          "source": "Display.java:1553"
        },
        {
          "method": "org.eclipse.jface.operation.ModalContext$ModalContextThread.block",
          "source": "ModalContext.java:136"
        },
        {
          "method": "org.eclipse.jface.operation.ModalContext.run",
          "source": "ModalContext.java:261"
        },
        {
          "method": "org.eclipse.jface.wizard.WizardDialog.run",
          "source": "WizardDialog.java:758"
        },
        {
          "method": "org.eclipse.pde.internal.ui.wizards.imports.PluginImportWizard.performFinish",
          "source": "PluginImportWizard.java:145"
        },
        {
          "method": "org.eclipse.jface.wizard.WizardDialog.finishPressed",
          "source": "WizardDialog.java:608"
        },
        {
          "method": "org.eclipse.jface.wizard.WizardDialog.buttonPressed",
          "source": "WizardDialog.java:321"
        },
        {
          "method": "org.eclipse.jface.dialogs.Dialog$1.widgetSelected",
          "source": "Dialog.java:423"
        },
        {
          "method": "org.eclipse.swt.widgets.TypedListener.handleEvent",
          "source": "TypedListener.java:91"
        },
        {
          "method": "org.eclipse.swt.widgets.EventTable.sendEvent",
          "source": "EventTable.java:81"
        },
        {
          "method": "org.eclipse.swt.widgets.Widget.sendEvent",
          "source": "Widget.java:840"
        },
        {
          "method": "org.eclipse.swt.widgets.Display.runDeferredEvents",
          "source": "Display.java:1842"
        },
        {
          "method": "org.eclipse.swt.widgets.Display.readAndDispatch",
          "source": "Display.java:1549"
        },
        {
          "method": "org.eclipse.jface.window.Window.runEventLoop",
          "source": "Window.java:583"
        },
        {
          "method": "org.eclipse.jface.window.Window.open",
          "source": "Window.java:563"
        },
        {
          "method": "org.eclipse.ui.actions.ImportResourcesAction.run",
          "source": "ImportResourcesAction.java:96"
        },
        {
          "method": "org.eclipse.jface.action.Action.runWithEvent",
          "source": "Action.java:842"
        },
        {
          "method": "org.eclipse.jface.action.ActionContributionItem.handleWidgetSelection",
          "source": "ActionContributionItem.java:456"
        },
        {
          "method": "org.eclipse.jface.action.ActionContributionItem.handleWidgetEvent",
          "source": "ActionContributionItem.java:403"
        },
        {
          "method": "org.eclipse.jface.action.ActionContributionItem.access$0",
          "source": "ActionContributionItem.java:397"
        },
        {
          "method": "org.eclipse.jface.action.ActionContributionItem$ActionListener.handleEvent",
          "source": "ActionContributionItem.java:72"
        },
        {
          "method": "org.eclipse.swt.widgets.EventTable.sendEvent",
          "source": "EventTable.java:81"
        },
        {
          "method": "org.eclipse.swt.widgets.Widget.sendEvent",
          "source": "Widget.java:840"
        },
        {
          "method": "org.eclipse.swt.widgets.Display.runDeferredEvents",
          "source": "Display.java:1842"
        },
        {
          "method": "org.eclipse.swt.widgets.Display.readAndDispatch",
          "source": "Display.java:1549"
        },
        {
          "method": "org.eclipse.ui.internal.Workbench.runEventLoop",
          "source": "Workbench.java:1402"
        },
        {
          "method": "org.eclipse.ui.internal.Workbench.run",
          "source": "Workbench.java:1385"
        },
        {
          "method": "org.eclipse.core.internal.boot.InternalBootLoader.run",
          "source": "InternalBootLoader.java:845"
        },
        {
          "method": "org.eclipse.core.boot.BootLoader.run",
          "source": "BootLoader.java:461"
        },
        {
          "method": "sun.reflect.NativeMethodAccessorImpl.invoke0",
          "source": "Native Method"
        },
        {
          "method": "sun.reflect.NativeMethodAccessorImpl.invoke",
          "source": "NativeMethodAccessorImpl.java:39"
        },
        {
          "method": "sun.reflect.DelegatingMethodAccessorImpl.invoke",
          "source": "DelegatingMethodAccessorImpl.java:25"
        },
        {
          "method": "java.lang.reflect.Method.invoke",
          "source": "Method.java:324"
        },
        {
          "method": "org.eclipse.core.launcher.Main.basicRun",
          "source": "Main.java:291"
        },
        {
          "method": "org.eclipse.core.launcher.Main.run",
          "source": "Main.java:747"
        },
        {
          "method": "org.eclipse.core.launcher.Main.main",
          "source": "Main.java:583"
        }
      ],
      "number": 9,
      "commentIndex": 0,
      "bugId": "35455",
      "duplicateId": "35236",
      "date": "2003-03-21T12:44:47+01:00",
      "product": "JDT",
      "component": "Text",
      "severity": "normal"
    }
  ],
  "groupId": "35236",
  "bugId": "35455",
  "duplicateId": "35236",
  "date": "2003-03-21T12:44:47+01:00",
  "product": "JDT",
  "component": "Text",
  "severity": "normal"
}