{
  "comments": [
    "Eclipse 2.1 RC3a\n\n1) Fresh Eclipse install\n2) Select the \"show methods only\" toolbar.\n3) Open the attached Java file in Eclipse.\n4) Select the bar method\n5) Position the cursor after the last } of the method\n6) Press HOME\n7) Nothing happens and we get an exception in the console\n\n!ENTRY org.eclipse.ui 4 4 Mar 21, 2003 11:03:20.478\n!MESSAGE Unhandled exception caught in event loop.\nUnhandled exception caught in event loop.\nReason:\n!ENTRY org.eclipse.ui 4 0 Mar 21, 2003 11:03:20.618\n!MESSAGE Index out of bounds\n!STACK 0\njava.lang.IllegalArgumentException: Index out of bounds\n        at org.eclipse.swt.SWT.error(SWT.java:2306)\n        at org.eclipse.swt.SWT.error(SWT.java:2250)\n        at org.eclipse.swt.custom.StyledText.getText(StyledText.java:4561)\n        at org.eclipse.ui.texteditor.AbstractTextEditor$LineStartAction.run\n(AbstractTextEditor.java:967)\n        at \norg.eclipse.ui.texteditor.AbstractTextEditor$ActivationCodeTrigger.verifyKey\n(AbstractTextEditor.java:545)\n        at \norg.eclipse.jface.text.TextViewer$VerifyKeyListenersManager.verifyKey\n(TextViewer.java:368)\n        at org.eclipse.swt.custom.StyledTextListener.handleEvent\n(StyledTextListener.java:55)\n        at org.eclipse.swt.widgets.EventTable.sendEvent(EventTable.java\n(Compiled Code))\n        at org.eclipse.swt.widgets.Widget.sendEvent(Widget.java(Compiled Code))\n        at org.eclipse.swt.widgets.Widget.sendEvent(Widget.java(Compiled Code))\n        at org.eclipse.swt.widgets.Widget.notifyListeners(Widget.java(Compiled \nCode))\n        at org.eclipse.swt.widgets.Widget.notifyListeners(Widget.java(Compiled \nCode))\n        at org.eclipse.swt.custom.StyledText.handleKeyDown\n(StyledText.java:5215)\n        at org.eclipse.swt.custom.StyledText$8.handleEvent\n(StyledText.java:4964)\n        at org.eclipse.swt.widgets.Display.runDeferredEvents(Display.java\n(Compiled Code))\n        at org.eclipse.swt.widgets.Display.runDeferredEvents(Display.java\n(Compiled Code))\n        at org.eclipse.swt.widgets.Display.runDeferredEvents(Display.java\n(Compiled Code))\n        at org.eclipse.swt.widgets.Display.readAndDispatch(Display.java\n(Compiled Code))\n        at org.eclipse.ui.internal.Workbench.runEventLoop(Workbench.java\n(Compiled Code))\n        at org.eclipse.ui.internal.Workbench.run(Workbench.java:1385)\n        at org.eclipse.core.internal.boot.InternalBootLoader.run\n(InternalBootLoader.java:845)\n        at org.eclipse.core.boot.BootLoader.run(BootLoader.java:461)\n        at java.lang.reflect.Method.invoke(Native Method)\n        at org.eclipse.core.launcher.Main.basicRun(Main.java:291)\n        at org.eclipse.core.launcher.Main.run(Main.java:747)\n        at org.eclipse.core.launcher.Main.main(Main.java:583)\nIndex out of bounds",
    "Created an attachment (id\u003d4287)\njava file example\n",
    "The last line of bar has a whitespace behind the closing \u0027}\u0027. This is what is \ncausing the problem with HOME. END suffers from the same problem.",
    "Created an attachment (id\u003d4338)\npatch\n",
    "+1",
    "+1",
    "+1",
    "Reviewed and released to head. Marking as fixed. Will be reopened in case of \nveto within the next 24 hours."
  ],
  "commentCreationDates": [
    "2003-03-21T16:08:42+01:00",
    "2003-03-21T16:09:17+01:00",
    "2003-03-24T14:48:57+01:00",
    "2003-03-25T15:17:38+01:00",
    "2003-03-25T17:18:17+01:00",
    "2003-03-25T17:22:57+01:00",
    "2003-03-25T17:24:44+01:00",
    "2003-03-25T18:47:26+01:00"
  ],
  "traces": [
    {
      "exceptionType": "java.lang.IllegalArgumentException",
      "message": "Index out of bounds",
      "elements": [
        {
          "method": "org.eclipse.swt.SWT.error",
          "source": "SWT.java:2306"
        },
        {
          "method": "org.eclipse.swt.SWT.error",
          "source": "SWT.java:2250"
        },
        {
          "method": "org.eclipse.swt.custom.StyledText.getText",
          "source": "StyledText.java:4561"
        },
        {
          "method": "org.eclipse.ui.texteditor.AbstractTextEditor$LineStartAction.run",
          "source": "AbstractTextEditor.java:967"
        },
        {
          "method": "org.eclipse.ui.texteditor.AbstractTextEditor$ActivationCodeTrigger.verifyKey",
          "source": "AbstractTextEditor.java:545"
        },
        {
          "method": "org.eclipse.jface.text.TextViewer$VerifyKeyListenersManager.verifyKey",
          "source": "TextViewer.java:368"
        },
        {
          "method": "org.eclipse.swt.custom.StyledTextListener.handleEvent",
          "source": "StyledTextListener.java:55"
        },
        {
          "method": "org.eclipse.swt.widgets.EventTable.sendEvent",
          "source": "EventTable.java (Compiled Code)"
        },
        {
          "method": "org.eclipse.swt.widgets.Widget.sendEvent",
          "source": "Widget.java(Compiled Code)"
        },
        {
          "method": "org.eclipse.swt.widgets.Widget.sendEvent",
          "source": "Widget.java(Compiled Code)"
        },
        {
          "method": "org.eclipse.swt.widgets.Widget.notifyListeners",
          "source": "Widget.java(Compiled  Code)"
        },
        {
          "method": "org.eclipse.swt.widgets.Widget.notifyListeners",
          "source": "Widget.java(Compiled  Code)"
        },
        {
          "method": "org.eclipse.swt.custom.StyledText.handleKeyDown",
          "source": "StyledText.java:5215"
        },
        {
          "method": "org.eclipse.swt.custom.StyledText$8.handleEvent",
          "source": "StyledText.java:4964"
        },
        {
          "method": "org.eclipse.swt.widgets.Display.runDeferredEvents",
          "source": "Display.java (Compiled Code)"
        },
        {
          "method": "org.eclipse.swt.widgets.Display.runDeferredEvents",
          "source": "Display.java (Compiled Code)"
        },
        {
          "method": "org.eclipse.swt.widgets.Display.runDeferredEvents",
          "source": "Display.java (Compiled Code)"
        },
        {
          "method": "org.eclipse.swt.widgets.Display.readAndDispatch",
          "source": "Display.java (Compiled Code)"
        },
        {
          "method": "org.eclipse.ui.internal.Workbench.runEventLoop",
          "source": "Workbench.java (Compiled Code)"
        },
        {
          "method": "org.eclipse.ui.internal.Workbench.run",
          "source": "Workbench.java:1385"
        },
        {
          "method": "org.eclipse.core.internal.boot.InternalBootLoader.run",
          "source": "InternalBootLoader.java:845"
        },
        {
          "method": "org.eclipse.core.boot.BootLoader.run",
          "source": "BootLoader.java:461"
        },
        {
          "method": "java.lang.reflect.Method.invoke",
          "source": "Native Method"
        },
        {
          "method": "org.eclipse.core.launcher.Main.basicRun",
          "source": "Main.java:291"
        },
        {
          "method": "org.eclipse.core.launcher.Main.run",
          "source": "Main.java:747"
        },
        {
          "method": "org.eclipse.core.launcher.Main.main",
          "source": "Main.java:583"
        }
      ],
      "number": 0,
      "commentIndex": 0,
      "bugId": "35480",
      "date": "2003-03-21T16:08:42+01:00",
      "product": "Platform",
      "component": "Text",
      "severity": "major"
    }
  ],
  "groupId": "35480",
  "bugId": "35480",
  "date": "2003-03-21T16:08:42+01:00",
  "product": "Platform",
  "component": "Text",
  "severity": "major"
}