{
  "comments": [
    "Overview Description:\nFor any Chinese locale on Sun Solaris 9, Eclipse will crash and throw a null\npointer exception when the user attempts to start Eclipse in that environment.\n\nSteps to Reproduce:\n1) Log into Solaris using any Chinese locale (e.g., zh_TW.BIG5, zh_CN.GB18030, zh).\n2) Open a terminal session and start Eclipse.\n\nActual Results:\nEclipse crashed and threw the following exception:\njava.lang.ExceptionInInitializerError: java.lang.NullPointerException\n        at\norg.eclipse.jface.preference.PreferenceConverter.\u003cclinit\u003e(PreferenceConverter.java:75)\n        at\norg.eclipse.ui.internal.WorkbenchPlugin.initializeDefaultPreferences(WorkbenchPlugin.java:441)\n        at\norg.eclipse.ui.plugin.AbstractUIPlugin.initializeDefaultPluginPreferences(AbstractUIPlugin.java:631)\n        at org.eclipse.core.runtime.Plugin.getPluginPreferences(Plugin.java:347)\n        at\norg.eclipse.ui.plugin.AbstractUIPlugin$CompatibilityPreferenceStore.initialize(AbstractUIPlugin.java:176)\n        at\norg.eclipse.ui.plugin.AbstractUIPlugin.getPreferenceStore(AbstractUIPlugin.java:568)\n        at org.eclipse.ui.internal.Workbench.getPreferenceStore(Workbench.java:701)\n        at org.eclipse.ui.internal.Workbench.init(Workbench.java:844)\n        at org.eclipse.ui.internal.Workbench.run(Workbench.java:1373)\n        at\norg.eclipse.core.internal.boot.InternalBootLoader.run(InternalBootLoader.java:845)\n        at org.eclipse.core.boot.BootLoader.run(BootLoader.java:461)\n        at java.lang.reflect.Method.invoke(Native Method)\n        at org.eclipse.core.launcher.Main.basicRun(Main.java:291)\n        at org.eclipse.core.launcher.Main.run(Main.java:747)\n        at org.eclipse.core.launcher.Main.main(Main.java:583)\n\nExpected Results:\nEclipse should start normally. I have tested this with a Japanese locale\n(ja_JP.eucJP), and Eclipse started normally. Note that no Eclipse language packs\nwere installed, as my intention was only to test the functionality of an English\nversion of Eclipse in a different locale.\n\nBuild Date \u0026 Platform:\nBuild 200303202147 (RC3a) on Sun Solaris 9\n\nAdditional Builds and Platforms:\n- Also Occurs On        \n    Build 200211071448 (2.0.2) on Sun Solaris 9\n\nHowever, on Eclipse 2.0.2, a different exception is thrown, and instead of\ncrashing, Eclipse hangs. Here is the exception:\n\njava.lang.NullPointerException\n        at org.eclipse.swt.graphics.Device.\u003cinit\u003e(Device.java:121)\n        at org.eclipse.swt.widgets.Display.\u003cinit\u003e(Display.java:319)\n        at org.eclipse.swt.widgets.Display.\u003cinit\u003e(Display.java:316)\n        at org.eclipse.ui.internal.Workbench.run(Workbench.java:1308)\n        at\norg.eclipse.core.internal.boot.InternalBootLoader.run(InternalBootLoader.java:831)\n        at org.eclipse.core.boot.BootLoader.run(BootLoader.java:462)\n        at java.lang.reflect.Method.invoke(Native Method)\n        at org.eclipse.core.launcher.Main.basicRun(Main.java:247)\n        at org.eclipse.core.launcher.Main.run(Main.java:703)\n        at org.eclipse.core.launcher.Main.main(Main.java:539)",
    "This also occurs for build 200303192032 (RC3) on Sun Solaris 8.",
    "This type of error is thrown when an unexpected exception occurs during the \nstatic initializer. Moving to Platform/UI for comment.\n",
    "Line 75 of PreferenceConverter is:\n\tFONTDATA_DEFAULT_DEFAULT \u003d FONTDATA_ARRAY_DEFAULT_DEFAULT[0];\nThe array was obtained from:\n\tShell shell \u003d new Shell();\n\tFONTDATA_ARRAY_DEFAULT_DEFAULT \u003d shell.getFont().getFontData();\n\tshell.dispose();\n\ngetFontData() is not spec\u0027ed to return null.\n",
    "Grant and SSQ, this needs to be addressed for 2.1.1.  Thanks.",
    "Grant,\n\nI believe this is the same problem as Bug#25292. Probably, the default font\nname is not a valid XLFD and we fail to parse it.\n\nSilenio",
    "*** Bug 25292 has been marked as a duplicate of this bug. ***",
    "Fixed in 2.1.1 and 3.0 streams with SSQ.\n"
  ],
  "commentCreationDates": [
    "2003-03-25T18:05:25+01:00",
    "2003-03-25T20:48:43+01:00",
    "2003-03-28T16:50:51+01:00",
    "2003-03-28T17:24:16+01:00",
    "2003-05-15T22:46:08+02:00",
    "2003-05-16T01:44:02+02:00",
    "2003-05-20T23:58:42+02:00",
    "2003-05-20T23:59:46+02:00"
  ],
  "traces": [
    {
      "exceptionType": "java.lang.NullPointerException",
      "elements": [
        {
          "method": "org.eclipse.jface.preference.PreferenceConverter.\u003cclinit\u003e",
          "source": "PreferenceConverter.java:75"
        },
        {
          "method": "org.eclipse.ui.internal.WorkbenchPlugin.initializeDefaultPreferences",
          "source": "WorkbenchPlugin.java:441"
        },
        {
          "method": "org.eclipse.ui.plugin.AbstractUIPlugin.initializeDefaultPluginPreferences",
          "source": "AbstractUIPlugin.java:631"
        },
        {
          "method": "org.eclipse.core.runtime.Plugin.getPluginPreferences",
          "source": "Plugin.java:347"
        },
        {
          "method": "org.eclipse.ui.plugin.AbstractUIPlugin$CompatibilityPreferenceStore.initialize",
          "source": "AbstractUIPlugin.java:176"
        },
        {
          "method": "org.eclipse.ui.plugin.AbstractUIPlugin.getPreferenceStore",
          "source": "AbstractUIPlugin.java:568"
        },
        {
          "method": "org.eclipse.ui.internal.Workbench.getPreferenceStore",
          "source": "Workbench.java:701"
        },
        {
          "method": "org.eclipse.ui.internal.Workbench.init",
          "source": "Workbench.java:844"
        },
        {
          "method": "org.eclipse.ui.internal.Workbench.run",
          "source": "Workbench.java:1373"
        },
        {
          "method": "org.eclipse.core.internal.boot.InternalBootLoader.run",
          "source": "InternalBootLoader.java:845"
        },
        {
          "method": "org.eclipse.core.boot.BootLoader.run",
          "source": "BootLoader.java:461"
        },
        {
          "method": "java.lang.reflect.Method.invoke",
          "source": "Native Method"
        },
        {
          "method": "org.eclipse.core.launcher.Main.basicRun",
          "source": "Main.java:291"
        },
        {
          "method": "org.eclipse.core.launcher.Main.run",
          "source": "Main.java:747"
        },
        {
          "method": "org.eclipse.core.launcher.Main.main",
          "source": "Main.java:583"
        }
      ],
      "number": 0,
      "commentIndex": 0,
      "bugId": "35657",
      "date": "2003-03-25T18:05:25+01:00",
      "product": "Platform",
      "component": "SWT",
      "severity": "major"
    },
    {
      "exceptionType": "java.lang.NullPointerException",
      "elements": [
        {
          "method": "org.eclipse.swt.graphics.Device.\u003cinit\u003e",
          "source": "Device.java:121"
        },
        {
          "method": "org.eclipse.swt.widgets.Display.\u003cinit\u003e",
          "source": "Display.java:319"
        },
        {
          "method": "org.eclipse.swt.widgets.Display.\u003cinit\u003e",
          "source": "Display.java:316"
        },
        {
          "method": "org.eclipse.ui.internal.Workbench.run",
          "source": "Workbench.java:1308"
        },
        {
          "method": "org.eclipse.core.internal.boot.InternalBootLoader.run",
          "source": "InternalBootLoader.java:831"
        },
        {
          "method": "org.eclipse.core.boot.BootLoader.run",
          "source": "BootLoader.java:462"
        },
        {
          "method": "java.lang.reflect.Method.invoke",
          "source": "Native Method"
        },
        {
          "method": "org.eclipse.core.launcher.Main.basicRun",
          "source": "Main.java:247"
        },
        {
          "method": "org.eclipse.core.launcher.Main.run",
          "source": "Main.java:703"
        },
        {
          "method": "org.eclipse.core.launcher.Main.main",
          "source": "Main.java:539"
        }
      ],
      "number": 1,
      "commentIndex": 0,
      "bugId": "35657",
      "date": "2003-03-25T18:05:25+01:00",
      "product": "Platform",
      "component": "SWT",
      "severity": "major"
    }
  ],
  "groupId": "35657",
  "bugId": "35657",
  "date": "2003-03-25T18:05:25+01:00",
  "product": "Platform",
  "component": "SWT",
  "severity": "major"
}