{
  "comments": [
    "Greetings.\n\n\n  My code throws a custom RuntimeException, but I found out that it gets lost by\nEclipse\u0027s core platform.  Following is the stack trace I get:\n\norg.eclipse.core.internal.runtime.AssertionFailedException: assertion failed:\nThe application has not been initialized.\n\tat org.eclipse.core.internal.runtime.Assert.isTrue(Assert.java:101)\n\tat\norg.eclipse.core.internal.runtime.InternalPlatform.assertInitialized(InternalPlatform.java:178)\n\tat\norg.eclipse.core.internal.runtime.InternalPlatform.getPluginRegistry(InternalPlatform.java:397)\n\tat\norg.eclipse.core.internal.runtime.InternalPlatform.getRuntimePlugin(InternalPlatform.java:418)\n\tat\norg.eclipse.core.internal.runtime.InternalPlatform.handleException(InternalPlatform.java:429)\n\tat\norg.eclipse.core.internal.runtime.InternalPlatform.run(InternalPlatform.java:869)\n\tat org.eclipse.core.runtime.Platform.run(Platform.java:413)\n\tat org.eclipse.jface.viewers.Viewer.fireSelectionChanged(Viewer.java:151)\n\tat\norg.eclipse.jface.viewers.StructuredViewer.updateSelection(StructuredViewer.java:1285)\n\tat\norg.eclipse.jface.viewers.StructuredViewer.handleSelect(StructuredViewer.java:652)\n\tat\norg.eclipse.jface.viewers.StructuredViewer$4.widgetSelected(StructuredViewer.java:676)\n\tat org.eclipse.jface.util.OpenStrategy.fireSelectionEvent(OpenStrategy.java:172)\n\tat org.eclipse.jface.util.OpenStrategy.access$3(OpenStrategy.java:167)\n\tat org.eclipse.jface.util.OpenStrategy$1.handleEvent(OpenStrategy.java:302)\n\tat org.eclipse.swt.widgets.EventTable.sendEvent(EventTable.java:77)\n\tat org.eclipse.swt.widgets.Widget.sendEvent(Widget.java:836)\n\tat org.eclipse.swt.widgets.Display.runDeferredEvents(Display.java:1692)\n\tat org.eclipse.swt.widgets.Display.readAndDispatch(Display.java:1410)\n\tat org.eclipse.jface.window.Window.runEventLoop(Window.java:561)\n\tat org.eclipse.jface.window.Window.open(Window.java:541)\n\tat biz.deragon.zarionna.client.Main.main(Main.java:81)\n\nThe assertion exception occurs because of another exception of type\nRuntimeException with a message like \"Model passed is null.  Need a valid\nmodel.\" that was thrown by my code.  I found out that my exception is handled in\nthe class InternalPlatform, particularly in the following function:\n\npublic static void run(ISafeRunnable code) {\n\tAssert.isNotNull(code);\n\ttry {\n\t\tcode.run();\n\t} catch (Exception e) {\n\t\thandleException(code, e);\n\t} catch (LinkageError e) {\n\t\thandleException(code, e);\n\t}\n}\n\nNotice that handleException(code, e) is called when my exception is caught. \nSomewhere further down the stack is an assertion that is made and because it\nfails, a new assertion exception is thrown.  The original exception is then lost\nand therefore, the user is not made aware of the real problem.\n\nI believe that if the application throws an exception, it must show up on the\nconsole window for the programmer to see.  My workaround when I get this\nassertion exception is to set a break point in InternalProceess.Run() just\nbefore the call to handleException() so I can inspect the real exception that\noccured and find out what really is wrong with my code.  This happens to me\noften and I beleive that I must not be the only developper suffering from this\nkind of \"exception eating\".",
    "From the stack trace, it looks like you\u0027re trying to use code from Eclipse\nwithout starting the Eclipse platform. Are you writing a plugin, or just linking\nJARs from Eclipse into a stand-alone java program?",
    "I am just linking jars into a standalone appl.",
    "Eclipse platform code is not designed to be run with a stand-alone program.  The\nEclipse platform must be up and running before you can meaningfully use any API.\nI suggest you refactor your program as an Eclipse application (see the doc for\nmore details, the extension point is org.eclipse.core.runtime.application). \nThis is fairly easy to do, and then the Eclipse runtime and plug-in registry\nwill be initialized and our API can be used safely.",
    "Last comment, you wrote:\n\n\u003eI suggest you refactor your program as an Eclipse application \n\u003e(see the doc for more details, the extension point is\n\u003eorg.eclipse.core.runtime.application)\n\nMmm... what doc should I look at?  There is a lot of documents, and I search a\nfew but did not found a \"how to create a standalone application\" chapter.  I\nread the PDE, but I cannot figure out how to convert my project to a plugin and\nget the plugin manifest editor showing up.  Care to provide some help?",
    "Documentation for the extension point can be found here:\n\nPlatform Plug-in Developer Guide -\u003e Reference -\u003e Extension Points Reference -\u003e \nPlatform Runtime -\u003e org.eclipse.core.runtime.applications\n\nThe Platform Plug-in Developer Guide also contains more information about \ncreating a simple plug-in project."
  ],
  "commentCreationDates": [
    "2003-03-26T15:59:53+01:00",
    "2003-03-27T17:35:10+01:00",
    "2003-03-27T22:21:30+01:00",
    "2003-03-28T15:29:20+01:00",
    "2003-04-15T21:41:16+02:00",
    "2003-05-12T21:08:36+02:00"
  ],
  "traces": [
    {
      "exceptionType": "org.eclipse.core.internal.runtime.AssertionFailedException",
      "message": "assertion failed: The application has not been initialized.",
      "elements": [
        {
          "method": "org.eclipse.core.internal.runtime.Assert.isTrue",
          "source": "Assert.java:101"
        },
        {
          "method": "org.eclipse.core.internal.runtime.InternalPlatform.assertInitialized",
          "source": "InternalPlatform.java:178"
        },
        {
          "method": "org.eclipse.core.internal.runtime.InternalPlatform.getPluginRegistry",
          "source": "InternalPlatform.java:397"
        },
        {
          "method": "org.eclipse.core.internal.runtime.InternalPlatform.getRuntimePlugin",
          "source": "InternalPlatform.java:418"
        },
        {
          "method": "org.eclipse.core.internal.runtime.InternalPlatform.handleException",
          "source": "InternalPlatform.java:429"
        },
        {
          "method": "org.eclipse.core.internal.runtime.InternalPlatform.run",
          "source": "InternalPlatform.java:869"
        },
        {
          "method": "org.eclipse.core.runtime.Platform.run",
          "source": "Platform.java:413"
        },
        {
          "method": "org.eclipse.jface.viewers.Viewer.fireSelectionChanged",
          "source": "Viewer.java:151"
        },
        {
          "method": "org.eclipse.jface.viewers.StructuredViewer.updateSelection",
          "source": "StructuredViewer.java:1285"
        },
        {
          "method": "org.eclipse.jface.viewers.StructuredViewer.handleSelect",
          "source": "StructuredViewer.java:652"
        },
        {
          "method": "org.eclipse.jface.viewers.StructuredViewer$4.widgetSelected",
          "source": "StructuredViewer.java:676"
        },
        {
          "method": "org.eclipse.jface.util.OpenStrategy.fireSelectionEvent",
          "source": "OpenStrategy.java:172"
        },
        {
          "method": "org.eclipse.jface.util.OpenStrategy.access$3",
          "source": "OpenStrategy.java:167"
        },
        {
          "method": "org.eclipse.jface.util.OpenStrategy$1.handleEvent",
          "source": "OpenStrategy.java:302"
        },
        {
          "method": "org.eclipse.swt.widgets.EventTable.sendEvent",
          "source": "EventTable.java:77"
        },
        {
          "method": "org.eclipse.swt.widgets.Widget.sendEvent",
          "source": "Widget.java:836"
        },
        {
          "method": "org.eclipse.swt.widgets.Display.runDeferredEvents",
          "source": "Display.java:1692"
        },
        {
          "method": "org.eclipse.swt.widgets.Display.readAndDispatch",
          "source": "Display.java:1410"
        },
        {
          "method": "org.eclipse.jface.window.Window.runEventLoop",
          "source": "Window.java:561"
        },
        {
          "method": "org.eclipse.jface.window.Window.open",
          "source": "Window.java:541"
        },
        {
          "method": "biz.deragon.zarionna.client.Main.main",
          "source": "Main.java:81"
        }
      ],
      "number": 0,
      "commentIndex": 0,
      "bugId": "35715",
      "date": "2003-03-26T15:59:53+01:00",
      "product": "Platform",
      "component": "Resources",
      "severity": "normal"
    }
  ],
  "groupId": "35715",
  "bugId": "35715",
  "date": "2003-03-26T15:59:53+01:00",
  "product": "Platform",
  "component": "Resources",
  "severity": "normal"
}