{
  "comments": [
    "I\u0027m experiencing a long delay 10-20 seconds when opening new editors.  This \ndoesn\u0027t happen though when switching between already open editors.  The strange \npart is that if I open a help browser this delay goes away( but it sometimes \ncomes back ).  It gives me the same delay regardless of the editor used( Java \nor plain text editor ).  I\u0027ve been able to reproduce this with a fresh install, \nand fresh workspace, but with an imported project.",
    "Anything special in your setup? Linked resources?",
    "I can confirm a similar situation on the Linux GTK build 200303272130.  The\ndelay is on double clicking to open a file.  Right clicking exhibits a similar\ndelay before the context menu appears, and the same delay again on selecting\nopen from that menu.  Main menus seem to work as per normal (no delays), but the\nactions initiated from those menus have the same delay.  Eclipse can be closed\nusing the window close box during this delay period (and the close occurs\n\"immediately\"), but an error occurs (dialog box), and the following stack\ntrace(s) are added to the error log.  I cannot confirm the association with the\nhelp browser (haven\u0027t tried). \nDuring the delays, CPU usage is minimal, or rather, eclipse does not appear to\nbe hogging the CPU at all.  \nThe problem is sporadic... it will appear for a while, appears to persist across\nrestarts of eclipse, and will then quietly go away.  (Hence, it\u0027s probably\nenvironmental, perhaps IO contention or something like that?).   However, I seem\nto run into it once or twice a day.  \nI\u0027ll be happy to provide more details if you have any specific testing you wish\nme to perform.\nStack traces on exit during the delay state:\n!ENTRY org.eclipse.jface 4 2 Apr 14, 2003 08:27:16.59\n!MESSAGE Problems occurred when invoking code from plug-in: \"org.eclipse.jface\".\n!STACK 0\njava.lang.NullPointerException\n        at org.eclipse.swt.widgets.Control.gtk_event_after(Control.java:1655)\n        at org.eclipse.swt.widgets.Widget.windowProc(Widget.java:1153)\n        at org.eclipse.swt.widgets.Display.windowProc(Display.java:2080)\n        at org.eclipse.swt.internal.gtk.OS.gtk_main_do_event(Native Method)\n        at org.eclipse.swt.widgets.Display.eventProc(Display.java:631)\n        at\norg.eclipse.swt.internal.gtk.OS.gtk_clipboard_wait_for_contents(Native Method)\n        at org.eclipse.swt.dnd.Clipboard.getContents(Clipboard.java:147)\n        at\norg.eclipse.jdt.internal.ui.reorg.PasteSourceReferencesFromClipboardAction.getContentsToPaste(PasteSourceReferencesFromClipboardAction.java:133)\n        at\norg.eclipse.jdt.internal.ui.reorg.PasteSourceReferencesFromClipboardAction.isAnythingToPaste(PasteSourceReferencesFromClipboardAction.java:111)\n        at\norg.eclipse.jdt.internal.ui.reorg.PasteSourceReferencesFromClipboardAction.canOperateOn(PasteSourceReferencesFromClipboardAction.java:68)\n        at\norg.eclipse.jdt.internal.ui.reorg.PasteSourceReferencesFromClipboardAction.selectionChanged(PasteSourceReferencesFromClipboardAction.java:60)\n        at\norg.eclipse.jdt.ui.actions.SelectionDispatchAction.dispatchSelectionChanged(SelectionDispatchAction.java:181)\n        at\norg.eclipse.jdt.ui.actions.SelectionDispatchAction.selectionChanged(SelectionDispatchAction.java:176)\n        at\norg.eclipse.jdt.internal.ui.reorg.DualReorgAction.selectionChanged(DualReorgAction.java:51)\n        at org.eclipse.jface.viewers.Viewer$2.run(Viewer.java:159)\n        at\norg.eclipse.core.internal.runtime.InternalPlatform.run(InternalPlatform.java:889)\n        at org.eclipse.core.runtime.Platform.run(Platform.java:413)\n        at org.eclipse.jface.viewers.Viewer.fireSelectionChanged(Viewer.java:157)\n        at\norg.eclipse.jface.viewers.StructuredViewer.updateSelection(StructuredViewer.java:1290)\n        at\norg.eclipse.jface.viewers.StructuredViewer.handleSelect(StructuredViewer.java:657)\n        at\norg.eclipse.jface.viewers.StructuredViewer$4.widgetSelected(StructuredViewer.java:681)\n        at\norg.eclipse.jface.util.OpenStrategy.fireSelectionEvent(OpenStrategy.java:178)\n        at org.eclipse.jface.util.OpenStrategy.access$3(OpenStrategy.java:173)\n        at org.eclipse.jface.util.OpenStrategy$1.handleEvent(OpenStrategy.java:308)\n        at org.eclipse.swt.widgets.EventTable.sendEvent(EventTable.java:81)\n        at org.eclipse.swt.widgets.Widget.sendEvent(Widget.java:913)\n        at org.eclipse.swt.widgets.Display.runDeferredEvents(Display.java:1637)\n        at org.eclipse.swt.widgets.Display.readAndDispatch(Display.java:1429)\n        at org.eclipse.ui.internal.Workbench.runEventLoop(Workbench.java:1402)\n        at org.eclipse.ui.internal.Workbench.run(Workbench.java:1385)\n        at\norg.eclipse.core.internal.boot.InternalBootLoader.run(InternalBootLoader.java:845)\n        at org.eclipse.core.boot.BootLoader.run(BootLoader.java:461)\n        at sun.reflect.NativeMethodAccessorImpl.invoke0(Native Method)\n        at\nsun.reflect.NativeMethodAccessorImpl.invoke(NativeMethodAccessorImpl.java:39)\n        at\nsun.reflect.DelegatingMethodAccessorImpl.invoke(DelegatingMethodAccessorImpl.java:25)\n        at java.lang.reflect.Method.invoke(Method.java:324)\n        at org.eclipse.core.launcher.Main.basicRun(Main.java:291)\n        at org.eclipse.core.launcher.Main.run(Main.java:747)\n        at org.eclipse.core.launcher.Main.main(Main.java:583)\n!ENTRY org.eclipse.jface 4 2 Apr 14, 2003 08:27:16.236\n!MESSAGE Problems occurred when invoking code from plug-in: \"org.eclipse.jface\".\n!STACK 0\norg.eclipse.jdt.internal.corext.Assert$AssertionFailedException: null argument;\n        at org.eclipse.jdt.internal.corext.Assert.isNotNull(Assert.java:105)\n        at org.eclipse.jdt.internal.corext.Assert.isNotNull(Assert.java:83)\n        at\norg.eclipse.jdt.internal.ui.reorg.PackageFragmentRootManipulationQuery.\u003cinit\u003e(PackageFragmentRootManipulationQuery.java:53)\n        at\norg.eclipse.jdt.internal.ui.reorg.JdtMoveAction.createUpdateClasspathQuery(JdtMoveAction.java:393)\n        at\norg.eclipse.jdt.internal.ui.reorg.JdtMoveAction.createRefactoring(JdtMoveAction.java:112)\n        at\norg.eclipse.jdt.internal.ui.reorg.ReorgDestinationAction.canOperateOn(ReorgDestinationAction.java:103)\n        at\norg.eclipse.jdt.internal.ui.reorg.ReorgDestinationAction.selectionChanged(ReorgDestinationAction.java:91)\n        at\norg.eclipse.jdt.ui.actions.SelectionDispatchAction.dispatchSelectionChanged(SelectionDispatchAction.java:181)\n        at\norg.eclipse.jdt.ui.actions.SelectionDispatchAction.selectionChanged(SelectionDispatchAction.java:176)\n        at\norg.eclipse.jdt.ui.actions.MoveAction.selectionChanged(MoveAction.java:102)\n        at org.eclipse.jface.viewers.Viewer$2.run(Viewer.java:159)\n        at\norg.eclipse.core.internal.runtime.InternalPlatform.run(InternalPlatform.java:889)\n        at org.eclipse.core.runtime.Platform.run(Platform.java:413)\n        at org.eclipse.jface.viewers.Viewer.fireSelectionChanged(Viewer.java:157)\n        at\norg.eclipse.jface.viewers.StructuredViewer.updateSelection(StructuredViewer.java:1290)\n        at\norg.eclipse.jface.viewers.StructuredViewer.handleSelect(StructuredViewer.java:657)\n        at\norg.eclipse.jface.viewers.StructuredViewer$4.widgetSelected(StructuredViewer.java:681)\n        at\norg.eclipse.jface.util.OpenStrategy.fireSelectionEvent(OpenStrategy.java:178)\n        at org.eclipse.jface.util.OpenStrategy.access$3(OpenStrategy.java:173)\n        at org.eclipse.jface.util.OpenStrategy$1.handleEvent(OpenStrategy.java:308)\n        at org.eclipse.swt.widgets.EventTable.sendEvent(EventTable.java:81)\n        at org.eclipse.swt.widgets.Widget.sendEvent(Widget.java:913)\n        at org.eclipse.swt.widgets.Display.runDeferredEvents(Display.java:1637)\n        at org.eclipse.swt.widgets.Display.readAndDispatch(Display.java:1429)\n        at org.eclipse.ui.internal.Workbench.runEventLoop(Workbench.java:1402)\n        at org.eclipse.ui.internal.Workbench.run(Workbench.java:1385)\n        at\norg.eclipse.core.internal.boot.InternalBootLoader.run(InternalBootLoader.java:845)\n        at org.eclipse.core.boot.BootLoader.run(BootLoader.java:461)\n        at sun.reflect.NativeMethodAccessorImpl.invoke0(Native Method)\n        at\nsun.reflect.NativeMethodAccessorImpl.invoke(NativeMethodAccessorImpl.java:39)\n        at\nsun.reflect.DelegatingMethodAccessorImpl.invoke(DelegatingMethodAccessorImpl.java:25)\n        at java.lang.reflect.Method.invoke(Method.java:324)\n        at org.eclipse.core.launcher.Main.basicRun(Main.java:291)\n        at org.eclipse.core.launcher.Main.run(Main.java:747)\n        at org.eclipse.core.launcher.Main.main(Main.java:583)",
    "\nThis is happening to me also: Eclipse 2.1, Linux (Red Hat 8.0), GTK, Sun JVM\n1.4.1.02. Very annoying. I can provide more information if needed.\n",
    "I think I have found the problem on my system.  It turns when the system is\nhanging it is attempting to open the file /tmp/.X11-pipe/X1.  Since this doesn\u0027t\nexist, because my X11 server is using /tmp/.X11-pipe/X0, it then further\nattempts to connection to the X11 server via TCPIP.  This appears to be the\n\"hang\".  I\u0027m not sure why though it is attempting to connect to the :1 display\nbut I assume it has something to do with printing since the code for printing\ndefaults to looking for Xprt on display :1.  BTW, this problem doesn\u0027t occur\nwhen I use the GTK widgets on Solaris, only Motif.  I\u0027ve included output from\ntruss to show additional information.  Any advice would be appreciated though I\ndo have a workaround now.\n\n/1:     open(\"/tmp/.X11-pipe/X1\", O_RDWR)               Err#2 ENOENT\n/1:     getrlimit(RLIMIT_NOFILE, 0xFFBFBC98)            \u003d 0\n/1:     so_socket(PF_UNIX, SOCK_STREAM, 0, \"\", 1)       \u003d 11\n/1:     connect(11, 0xFFBFBC90, 19, 1)                  Err#2 ENOENT\n/1:     close(11)                                       \u003d 0\n/2:     lwp_suspend(1)                                  \u003d 0 [199]\n/2:     lwp_continue(1)                                 \u003d 0\n/1:     nanosleep(0xFFBFBD68, 0xFFBFBD60)               \u003d 0\n/1:     getrlimit(RLIMIT_NOFILE, 0xFFBFBC98)            \u003d 0\n/1:     so_socket(PF_UNIX, SOCK_STREAM, 0, \"\", 1)       \u003d 11\n/1:     connect(11, 0xFFBFBC90, 19, 1)                  Err#2 ENOENT\n/1:     close(11)                                       \u003d 0\n/1:     nanosleep(0xFFBFBD68, 0xFFBFBD60)               \u003d 0\n/1:     getrlimit(RLIMIT_NOFILE, 0xFFBFBC98)            \u003d 0\n/1:     so_socket(PF_UNIX, SOCK_STREAM, 0, \"\", 1)       \u003d 11\n/1:     connect(11, 0xFFBFBC90, 19, 1)                  Err#2 ENOENT\n/1:     close(11)                                       \u003d 0\n/1:     nanosleep(0xFFBFBD68, 0xFFBFBD60)               \u003d 0\n/1:     getrlimit(RLIMIT_NOFILE, 0xFFBFBC98)            \u003d 0\n/1:     so_socket(PF_UNIX, SOCK_STREAM, 0, \"\", 1)       \u003d 11\n/1:     connect(11, 0xFFBFBC90, 19, 1)                  Err#2 ENOENT\n/1:     close(11)                                       \u003d 0\n/1:     nanosleep(0xFFBFBD68, 0xFFBFBD60) (sleeping...)\n/1:     nanosleep(0xFFBFBD68, 0xFFBFBD60)               \u003d 0\n/1:     getrlimit(RLIMIT_NOFILE, 0xFFBFBC98)            \u003d 0\n/1:     so_socket(PF_UNIX, SOCK_STREAM, 0, \"\", 1)       \u003d 11\n/1:     connect(11, 0xFFBFBC90, 19, 1)                  Err#2 ENOENT\n/1:     close(11)                                       \u003d 0\n/1:     nanosleep(0xFFBFBD68, 0xFFBFBD60)               \u003d 0\n/1:     getrlimit(RLIMIT_NOFILE, 0xFFBFBC98)            \u003d 0\n/1:     so_socket(PF_UNIX, SOCK_STREAM, 0, \"\", 1)       \u003d 11\n/1:     connect(11, 0xFFBFBC90, 19, 1)                  Err#2 ENOENT\n/1:     close(11)                                       \u003d 0\n/1:     nanosleep(0xFFBFBD68, 0xFFBFBD60)               \u003d 0\n/1:     getrlimit(RLIMIT_NOFILE, 0xFFBFBC98)            \u003d 0\n/1:     so_socket(PF_INET6, SOCK_STREAM, IPPROTO_IP, \"\", 1) \u003d 11\n/1:     setsockopt(11, tcp, TCP_NODELAY, 0xFFBFBC94, 4, 1) \u003d 0\n/1:     setsockopt(11, SOL_SOCKET, SO_KEEPALIVE, 0xFFBFBC94, 4, 1) \u003d 0\n/1:     door_info(4, 0xFFBF9740)                        \u003d 0\n/1:     door_call(4, 0xFFBF9728)                        \u003d 0\n/1:     setsockopt(11, SOL_SOCKET, SO_KEEPALIVE, 0xFFBFBB7C, 4, 1) \u003d 0\n/1:     connect(11, 0x002AC988, 32, 1)                  Err#128 ENETUNREACH\n/1:     close(11)                                       \u003d 0\n/1:     nanosleep(0xFFBFBD68, 0xFFBFBD60)               \u003d 0\n/1:     getrlimit(RLIMIT_NOFILE, 0xFFBFBC98)            \u003d 0\n/1:     so_socket(PF_INET6, SOCK_STREAM, IPPROTO_IP, \"\", 1) \u003d 11\n/1:     setsockopt(11, tcp, TCP_NODELAY, 0xFFBFBC94, 4, 1) \u003d 0\n/1:     setsockopt(11, SOL_SOCKET, SO_KEEPALIVE, 0xFFBFBC94, 4, 1) \u003d 0\n/1:     setsockopt(11, SOL_SOCKET, SO_KEEPALIVE, 0xFFBFBB7C, 4, 1) \u003d 0\n/1:     connect(11, 0xFFBFBB80, 32, 1)                  Err#146 ECONNREFUSED\n/1:     close(11)                                       \u003d 0\n/1:     nanosleep(0xFFBFBD68, 0xFFBFBD60)               \u003d 0\n/1:     getrlimit(RLIMIT_NOFILE, 0xFFBFBC98)            \u003d 0\n/1:     so_socket(PF_INET6, SOCK_STREAM, IPPROTO_IP, \"\", 1) \u003d 11\n/1:     setsockopt(11, tcp, TCP_NODELAY, 0xFFBFBC94, 4, 1) \u003d 0\n/1:     setsockopt(11, SOL_SOCKET, SO_KEEPALIVE, 0xFFBFBC94, 4, 1) \u003d 0\n/1:     setsockopt(11, SOL_SOCKET, SO_KEEPALIVE, 0xFFBFBB7C, 4, 1) \u003d 0\n/1:     connect(11, 0x002AC988, 32, 1)                  Err#128 ENETUNREACH\n/1:     close(11)                                       \u003d 0\n/1:     nanosleep(0xFFBFBD68, 0xFFBFBD60) (sleeping...)\n/1:     nanosleep(0xFFBFBD68, 0xFFBFBD60)               \u003d 0\n/1:     getrlimit(RLIMIT_NOFILE, 0xFFBFBC98)            \u003d 0\n/1:     so_socket(PF_INET6, SOCK_STREAM, IPPROTO_IP, \"\", 1) \u003d 11\n/1:     setsockopt(11, tcp, TCP_NODELAY, 0xFFBFBC94, 4, 1) \u003d 0\n/1:     setsockopt(11, SOL_SOCKET, SO_KEEPALIVE, 0xFFBFBC94, 4, 1) \u003d 0\n/1:     setsockopt(11, SOL_SOCKET, SO_KEEPALIVE, 0xFFBFBB7C, 4, 1) \u003d 0\n/1:     connect(11, 0xFFBFBB80, 32, 1)                  Err#146 ECONNREFUSED\n/1:     close(11)                                       \u003d 0\n/1:     nanosleep(0xFFBFBD68, 0xFFBFBD60)               \u003d 0\n/1:     getrlimit(RLIMIT_NOFILE, 0xFFBFBC98)            \u003d 0\n/1:     so_socket(PF_INET6, SOCK_STREAM, IPPROTO_IP, \"\", 1) \u003d 11\n/1:     setsockopt(11, tcp, TCP_NODELAY, 0xFFBFBC94, 4, 1) \u003d 0\n/1:     setsockopt(11, SOL_SOCKET, SO_KEEPALIVE, 0xFFBFBC94, 4, 1) \u003d 0\n/1:     setsockopt(11, SOL_SOCKET, SO_KEEPALIVE, 0xFFBFBB7C, 4, 1) \u003d 0\n/1:     connect(11, 0x002AC988, 32, 1)                  Err#128 ENETUNREACH\n/1:     close(11)                                       \u003d 0\n/1:     nanosleep(0xFFBFBD68, 0xFFBFBD60) (sleeping...)\n/1:     nanosleep(0xFFBFBD68, 0xFFBFBD60)               \u003d 0\n/1:     getrlimit(RLIMIT_NOFILE, 0xFFBFBC98)            \u003d 0\n/1:     so_socket(PF_INET6, SOCK_STREAM, IPPROTO_IP, \"\", 1) \u003d 11\n/1:     setsockopt(11, tcp, TCP_NODELAY, 0xFFBFBC94, 4, 1) \u003d 0\n/1:     setsockopt(11, SOL_SOCKET, SO_KEEPALIVE, 0xFFBFBC94, 4, 1) \u003d 0\n/1:     setsockopt(11, SOL_SOCKET, SO_KEEPALIVE, 0xFFBFBB7C, 4, 1) \u003d 0\n/1:     connect(11, 0xFFBFBB80, 32, 1)                  Err#146 ECONNREFUSED\n/1:     close(11)                                       \u003d 0",
    "moving to SWT for comment on the NPE.\n",
    "The NullPointerException is a duplicate of bug 33028 and is not a motif \nproblem.  Please add comments on NPE to 33028.  This bug report will be used \nto track the original problem reported by Michael.\n\nGrant to investigate the /tmp/.X11-pipe/X1 problem and determine if there is a \nproblem with printing.",
    "Michael do you have Xprint running on your machine by any chance?  If so, can \nyou try the Eclipse 3.0M3 build? (if you aren\u0027t running Xprint then I doubt \nanything will have changed)\n",
    "I think the GTK bug is completely different.  It is the same as bug #44915."
  ],
  "commentCreationDates": [
    "2003-04-03T22:44:51+02:00",
    "2003-04-09T15:59:49+02:00",
    "2003-04-14T21:45:48+02:00",
    "2003-04-30T19:42:01+02:00",
    "2003-06-19T20:25:28+02:00",
    "2003-07-15T18:45:02+02:00",
    "2003-07-15T20:06:31+02:00",
    "2003-10-01T18:06:00+02:00",
    "2004-04-08T19:38:57+02:00"
  ],
  "traces": [
    {
      "exceptionType": "java.lang.NullPointerException",
      "elements": [
        {
          "method": "org.eclipse.swt.widgets.Control.gtk_event_after",
          "source": "Control.java:1655"
        },
        {
          "method": "org.eclipse.swt.widgets.Widget.windowProc",
          "source": "Widget.java:1153"
        },
        {
          "method": "org.eclipse.swt.widgets.Display.windowProc",
          "source": "Display.java:2080"
        },
        {
          "method": "org.eclipse.swt.internal.gtk.OS.gtk_main_do_event",
          "source": "Native Method"
        },
        {
          "method": "org.eclipse.swt.widgets.Display.eventProc",
          "source": "Display.java:631"
        },
        {
          "method": "org.eclipse.swt.internal.gtk.OS.gtk_clipboard_wait_for_contents",
          "source": "Native Method"
        },
        {
          "method": "org.eclipse.swt.dnd.Clipboard.getContents",
          "source": "Clipboard.java:147"
        },
        {
          "method": "org.eclipse.jdt.internal.ui.reorg.PasteSourceReferencesFromClipboardAction.getContentsToPaste",
          "source": "PasteSourceReferencesFromClipboardAction.java:133"
        },
        {
          "method": "org.eclipse.jdt.internal.ui.reorg.PasteSourceReferencesFromClipboardAction.isAnythingToPaste",
          "source": "PasteSourceReferencesFromClipboardAction.java:111"
        },
        {
          "method": "org.eclipse.jdt.internal.ui.reorg.PasteSourceReferencesFromClipboardAction.canOperateOn",
          "source": "PasteSourceReferencesFromClipboardAction.java:68"
        },
        {
          "method": "org.eclipse.jdt.internal.ui.reorg.PasteSourceReferencesFromClipboardAction.selectionChanged",
          "source": "PasteSourceReferencesFromClipboardAction.java:60"
        },
        {
          "method": "org.eclipse.jdt.ui.actions.SelectionDispatchAction.dispatchSelectionChanged",
          "source": "SelectionDispatchAction.java:181"
        },
        {
          "method": "org.eclipse.jdt.ui.actions.SelectionDispatchAction.selectionChanged",
          "source": "SelectionDispatchAction.java:176"
        },
        {
          "method": "org.eclipse.jdt.internal.ui.reorg.DualReorgAction.selectionChanged",
          "source": "DualReorgAction.java:51"
        },
        {
          "method": "org.eclipse.jface.viewers.Viewer$2.run",
          "source": "Viewer.java:159"
        },
        {
          "method": "org.eclipse.core.internal.runtime.InternalPlatform.run",
          "source": "InternalPlatform.java:889"
        },
        {
          "method": "org.eclipse.core.runtime.Platform.run",
          "source": "Platform.java:413"
        },
        {
          "method": "org.eclipse.jface.viewers.Viewer.fireSelectionChanged",
          "source": "Viewer.java:157"
        },
        {
          "method": "org.eclipse.jface.viewers.StructuredViewer.updateSelection",
          "source": "StructuredViewer.java:1290"
        },
        {
          "method": "org.eclipse.jface.viewers.StructuredViewer.handleSelect",
          "source": "StructuredViewer.java:657"
        },
        {
          "method": "org.eclipse.jface.viewers.StructuredViewer$4.widgetSelected",
          "source": "StructuredViewer.java:681"
        },
        {
          "method": "org.eclipse.jface.util.OpenStrategy.fireSelectionEvent",
          "source": "OpenStrategy.java:178"
        },
        {
          "method": "org.eclipse.jface.util.OpenStrategy.access$3",
          "source": "OpenStrategy.java:173"
        },
        {
          "method": "org.eclipse.jface.util.OpenStrategy$1.handleEvent",
          "source": "OpenStrategy.java:308"
        },
        {
          "method": "org.eclipse.swt.widgets.EventTable.sendEvent",
          "source": "EventTable.java:81"
        },
        {
          "method": "org.eclipse.swt.widgets.Widget.sendEvent",
          "source": "Widget.java:913"
        },
        {
          "method": "org.eclipse.swt.widgets.Display.runDeferredEvents",
          "source": "Display.java:1637"
        },
        {
          "method": "org.eclipse.swt.widgets.Display.readAndDispatch",
          "source": "Display.java:1429"
        },
        {
          "method": "org.eclipse.ui.internal.Workbench.runEventLoop",
          "source": "Workbench.java:1402"
        },
        {
          "method": "org.eclipse.ui.internal.Workbench.run",
          "source": "Workbench.java:1385"
        },
        {
          "method": "org.eclipse.core.internal.boot.InternalBootLoader.run",
          "source": "InternalBootLoader.java:845"
        },
        {
          "method": "org.eclipse.core.boot.BootLoader.run",
          "source": "BootLoader.java:461"
        },
        {
          "method": "sun.reflect.NativeMethodAccessorImpl.invoke0",
          "source": "Native Method"
        },
        {
          "method": "sun.reflect.NativeMethodAccessorImpl.invoke",
          "source": "NativeMethodAccessorImpl.java:39"
        },
        {
          "method": "sun.reflect.DelegatingMethodAccessorImpl.invoke",
          "source": "DelegatingMethodAccessorImpl.java:25"
        },
        {
          "method": "java.lang.reflect.Method.invoke",
          "source": "Method.java:324"
        },
        {
          "method": "org.eclipse.core.launcher.Main.basicRun",
          "source": "Main.java:291"
        },
        {
          "method": "org.eclipse.core.launcher.Main.run",
          "source": "Main.java:747"
        },
        {
          "method": "org.eclipse.core.launcher.Main.main",
          "source": "Main.java:583"
        }
      ],
      "number": 0,
      "commentIndex": 2,
      "bugId": "36042",
      "date": "2003-04-14T21:45:48+02:00",
      "product": "Platform",
      "component": "SWT",
      "severity": "major"
    },
    {
      "exceptionType": "org.eclipse.jdt.internal.corext.Assert$AssertionFailedException",
      "message": "null argument;",
      "elements": [
        {
          "method": "org.eclipse.jdt.internal.corext.Assert.isNotNull",
          "source": "Assert.java:105"
        },
        {
          "method": "org.eclipse.jdt.internal.corext.Assert.isNotNull",
          "source": "Assert.java:83"
        },
        {
          "method": "org.eclipse.jdt.internal.ui.reorg.PackageFragmentRootManipulationQuery.\u003cinit\u003e",
          "source": "PackageFragmentRootManipulationQuery.java:53"
        },
        {
          "method": "org.eclipse.jdt.internal.ui.reorg.JdtMoveAction.createUpdateClasspathQuery",
          "source": "JdtMoveAction.java:393"
        },
        {
          "method": "org.eclipse.jdt.internal.ui.reorg.JdtMoveAction.createRefactoring",
          "source": "JdtMoveAction.java:112"
        },
        {
          "method": "org.eclipse.jdt.internal.ui.reorg.ReorgDestinationAction.canOperateOn",
          "source": "ReorgDestinationAction.java:103"
        },
        {
          "method": "org.eclipse.jdt.internal.ui.reorg.ReorgDestinationAction.selectionChanged",
          "source": "ReorgDestinationAction.java:91"
        },
        {
          "method": "org.eclipse.jdt.ui.actions.SelectionDispatchAction.dispatchSelectionChanged",
          "source": "SelectionDispatchAction.java:181"
        },
        {
          "method": "org.eclipse.jdt.ui.actions.SelectionDispatchAction.selectionChanged",
          "source": "SelectionDispatchAction.java:176"
        },
        {
          "method": "org.eclipse.jdt.ui.actions.MoveAction.selectionChanged",
          "source": "MoveAction.java:102"
        },
        {
          "method": "org.eclipse.jface.viewers.Viewer$2.run",
          "source": "Viewer.java:159"
        },
        {
          "method": "org.eclipse.core.internal.runtime.InternalPlatform.run",
          "source": "InternalPlatform.java:889"
        },
        {
          "method": "org.eclipse.core.runtime.Platform.run",
          "source": "Platform.java:413"
        },
        {
          "method": "org.eclipse.jface.viewers.Viewer.fireSelectionChanged",
          "source": "Viewer.java:157"
        },
        {
          "method": "org.eclipse.jface.viewers.StructuredViewer.updateSelection",
          "source": "StructuredViewer.java:1290"
        },
        {
          "method": "org.eclipse.jface.viewers.StructuredViewer.handleSelect",
          "source": "StructuredViewer.java:657"
        },
        {
          "method": "org.eclipse.jface.viewers.StructuredViewer$4.widgetSelected",
          "source": "StructuredViewer.java:681"
        },
        {
          "method": "org.eclipse.jface.util.OpenStrategy.fireSelectionEvent",
          "source": "OpenStrategy.java:178"
        },
        {
          "method": "org.eclipse.jface.util.OpenStrategy.access$3",
          "source": "OpenStrategy.java:173"
        },
        {
          "method": "org.eclipse.jface.util.OpenStrategy$1.handleEvent",
          "source": "OpenStrategy.java:308"
        },
        {
          "method": "org.eclipse.swt.widgets.EventTable.sendEvent",
          "source": "EventTable.java:81"
        },
        {
          "method": "org.eclipse.swt.widgets.Widget.sendEvent",
          "source": "Widget.java:913"
        },
        {
          "method": "org.eclipse.swt.widgets.Display.runDeferredEvents",
          "source": "Display.java:1637"
        },
        {
          "method": "org.eclipse.swt.widgets.Display.readAndDispatch",
          "source": "Display.java:1429"
        },
        {
          "method": "org.eclipse.ui.internal.Workbench.runEventLoop",
          "source": "Workbench.java:1402"
        },
        {
          "method": "org.eclipse.ui.internal.Workbench.run",
          "source": "Workbench.java:1385"
        },
        {
          "method": "org.eclipse.core.internal.boot.InternalBootLoader.run",
          "source": "InternalBootLoader.java:845"
        },
        {
          "method": "org.eclipse.core.boot.BootLoader.run",
          "source": "BootLoader.java:461"
        },
        {
          "method": "sun.reflect.NativeMethodAccessorImpl.invoke0",
          "source": "Native Method"
        },
        {
          "method": "sun.reflect.NativeMethodAccessorImpl.invoke",
          "source": "NativeMethodAccessorImpl.java:39"
        },
        {
          "method": "sun.reflect.DelegatingMethodAccessorImpl.invoke",
          "source": "DelegatingMethodAccessorImpl.java:25"
        },
        {
          "method": "java.lang.reflect.Method.invoke",
          "source": "Method.java:324"
        },
        {
          "method": "org.eclipse.core.launcher.Main.basicRun",
          "source": "Main.java:291"
        },
        {
          "method": "org.eclipse.core.launcher.Main.run",
          "source": "Main.java:747"
        },
        {
          "method": "org.eclipse.core.launcher.Main.main",
          "source": "Main.java:583"
        }
      ],
      "number": 1,
      "commentIndex": 2,
      "bugId": "36042",
      "date": "2003-04-14T21:45:48+02:00",
      "product": "Platform",
      "component": "SWT",
      "severity": "major"
    }
  ],
  "groupId": "36042",
  "bugId": "36042",
  "date": "2003-04-03T22:44:51+02:00",
  "product": "Platform",
  "component": "SWT",
  "severity": "major"
}