{
  "comments": [
    "Not sure if this is the correct component to log this PR under.\n\nIf I create a Java Scrapbook Page in a non-Java project, then try to execute\nsome Java code in the scrapbook page, an exception occurs.  \n\nSTEPS:\nFile-\u003e New-\u003e Other-\u003e Java-\u003e Java Scrapbook Page\nEnter a folder name e.g. /ZZ\n\tNote: The project ZZ does not yet exist, I think the default action is to create\n\t\t\t\ta non-Java project\nEnter file name MyScrap\nFinish\nIn MyScrap type:\n\tSystem.out.println(\"Karice\")\nSelect the line\nCtrl + E\n\n#1\nThe first time you do this the following 4 lines are printed to the (DOS)\nconsole (are these debug messages that will be removed?):\nOperation waiting to be executed... :-/\nOperation started... :-)\nOperation waiting to be executed... :-/\nOperation started... :-)\n\n#2\nThen the following exception occurs: (subsequent executions just give the exception)\norg.eclipse.debug.core.DebugException: Project must be built to perform evaluati\nons\n        at org.eclipse.debug.core.DebugException.\u003cinit\u003e(DebugException.java:75)\n        at org.eclipse.jdt.internal.debug.core.JDIThread.evaluate(JDIThread.java\n:344)\n        at org.eclipse.jdt.internal.debug.core.JDIThread.evaluate(JDIThread.java\n:357)\n        at org.eclipse.jdt.internal.ui.snippeteditor.JavaSnippetEditor.evaluate(\nJavaSnippetEditor.java:247)\n        at org.eclipse.jdt.internal.ui.snippeteditor.JavaSnippetEditor$1.run(Jav\naSnippetEditor.java:240)\n        at org.eclipse.swt.widgets.RunnableLock.run(RunnableLock.java:26)\n        at org.eclipse.swt.widgets.Synchronizer.runAsyncMessages(Synchronizer.ja\nva:85)\n        at org.eclipse.swt.widgets.Display.runAsyncMessages(Display.java:1019)\n        at org.eclipse.swt.widgets.Display.readAndDispatch(Display.java(Compiled\n Code))\n        at org.eclipse.ui.internal.Workbench.runEventLoop(Workbench.java:566)\n        at org.eclipse.ui.internal.Workbench.run(Workbench.java:554)\n        at org.eclipse.core.internal.boot.InternalBootLoader.run(InternalBootLoa\nder.java:800)\n        at org.eclipse.core.boot.BootLoader.run(BootLoader.java:174)\n        at java.lang.reflect.Method.invoke(Native Method)\n        at org.eclipse.core.launcher.Main.basicRun(Main.java:60)\n        at org.eclipse.core.launcher.Main.run(Main.java:222)\n        at org.eclipse.core.launcher.UIMain.main(UIMain.java:43)\n\n\nWhen I execute the Java code snip from a page that is contained by a Java \nproject the exception does not occur.\n\nShould I be allowed to create a Scrapbook page in a non-Java project?\n\nNOTES:\nEG (5/4/2001 2:22:52 AM)\n\t#1 - have seen this need to investigate\n\t#2 - the project has to have build state, need to be smarter\n\t#3 - since a non-Java project can never have build state you should not be\n\t\t\tallowed to create a scrapbook page in a non-Java project\n\nEG (5/17/2001 11:48:14 AM)\n\tDW can pls look into #1\n\nDW (5/18/01 2:27:58 PM)\n\t#1 is not an issue. The messages were core debug messages.\n\t#2 Dup of 1G4PK75: ITPJUI:WINNT - Snippet eval: build project when it isn\u0027t already built\n\nDW (5/18/01 2:29:14 PM)\n\tMoved to JUI for #3.",
    "moved to \u0027active\u0027",
    "PRODUCT VERSION:\n102 JDK\n\n",
    "#3 is fixed in 20020214",
    "yes it is fixed..."
  ],
  "commentCreationDates": [
    "2001-10-11T04:58:12+02:00",
    "2001-10-16T17:16:10+02:00",
    "2001-10-24T13:14:44+02:00",
    "2002-02-27T14:53:49+01:00",
    "2002-02-27T14:54:30+01:00"
  ],
  "traces": [
    {
      "exceptionType": "org.eclipse.debug.core.DebugException",
      "message": "Project must be built to perform evaluati ons",
      "elements": [
        {
          "method": "org.eclipse.debug.core.DebugException.\u003cinit\u003e",
          "source": "DebugException.java:75"
        },
        {
          "method": "org.eclipse.jdt.internal.debug.core.JDIThread.evaluate",
          "source": "JDIThread.java :344"
        },
        {
          "method": "org.eclipse.jdt.internal.debug.core.JDIThread.evaluate",
          "source": "JDIThread.java :357"
        },
        {
          "method": "org.eclipse.jdt.internal.ui.snippeteditor.JavaSnippetEditor.evaluate",
          "source": " JavaSnippetEditor.java:247"
        },
        {
          "method": "org.eclipse.jdt.internal.ui.snippeteditor.JavaSnippetEditor$1.run",
          "source": "Jav aSnippetEditor.java:240"
        },
        {
          "method": "org.eclipse.swt.widgets.RunnableLock.run",
          "source": "RunnableLock.java:26"
        },
        {
          "method": "org.eclipse.swt.widgets.Synchronizer.runAsyncMessages",
          "source": "Synchronizer.ja va:85"
        },
        {
          "method": "org.eclipse.swt.widgets.Display.runAsyncMessages",
          "source": "Display.java:1019"
        },
        {
          "method": "org.eclipse.swt.widgets.Display.readAndDispatch",
          "source": "Display.java(Compiled  Code)"
        },
        {
          "method": "org.eclipse.ui.internal.Workbench.runEventLoop",
          "source": "Workbench.java:566"
        },
        {
          "method": "org.eclipse.ui.internal.Workbench.run",
          "source": "Workbench.java:554"
        },
        {
          "method": "org.eclipse.core.internal.boot.InternalBootLoader.run",
          "source": "InternalBootLoa der.java:800"
        },
        {
          "method": "org.eclipse.core.boot.BootLoader.run",
          "source": "BootLoader.java:174"
        },
        {
          "method": "java.lang.reflect.Method.invoke",
          "source": "Native Method"
        },
        {
          "method": "org.eclipse.core.launcher.Main.basicRun",
          "source": "Main.java:60"
        },
        {
          "method": "org.eclipse.core.launcher.Main.run",
          "source": "Main.java:222"
        },
        {
          "method": "org.eclipse.core.launcher.UIMain.main",
          "source": "UIMain.java:43"
        }
      ],
      "number": 0,
      "commentIndex": 0,
      "bugId": "3626",
      "date": "2001-10-11T04:58:12+02:00",
      "product": "JDT",
      "component": "UI",
      "severity": "normal"
    }
  ],
  "groupId": "3626",
  "bugId": "3626",
  "date": "2001-10-11T04:58:12+02:00",
  "product": "JDT",
  "component": "UI",
  "severity": "normal"
}