{
  "comments": [
    "Eclipse: 2.1.0, 200302211557\nAspectJ: 1.1.1\n\n\nI get the following internal error when using \"thisJoinPoint.getStaticPart()\" \nin around advice at a call joinpoit (source below). Using just \"thisJoinPoint\" \nis fine.\n\njava.lang.NullPointerException\n\tat org.eclipse.jdt.internal.compiler.ast.MessageSend.analyseCode\n(MessageSend.java:40)\n\tat org.eclipse.jdt.internal.compiler.ast.MessageSend.analyseCode\n(MessageSend.java:44)\n\tat \norg.eclipse.jdt.internal.compiler.ast.AbstractMethodDeclaration.analyseCode\n(AbstractMethodDeclaration.java:106)\n\tat org.eclipse.jdt.internal.compiler.ast.TypeDeclaration.analyseCode\n(TypeDeclaration.java:445)\n\tat \norg.eclipse.jdt.internal.compiler.ast.CompilationUnitDeclaration.analyseCode\n(CompilationUnitDeclaration.java:76)\n\tat org.eclipse.jdt.internal.compiler.Compiler.process\n(Compiler.java:539)\n\tat org.aspectj.ajdt.internal.compiler.AjCompiler.process\n(AjCompiler.java:65)\n\tat org.eclipse.jdt.internal.compiler.Compiler.compile\n(Compiler.java:340)\n\tat org.eclipse.jdt.internal.core.builder.AbstractImageBuilder.compile\n(AbstractImageBuilder.java:232)\n\tat org.eclipse.jdt.internal.core.builder.AbstractImageBuilder.compile\n(AbstractImageBuilder.java:171)\n\tat \norg.aspectj.ajdt.internal.core.builder.AjBuildManager$BatchBuilder.run\n(AjBuildManager.java:655)\n\tat org.aspectj.ajdt.internal.core.builder.AjBuildManager.batchBuild\n(AjBuildManager.java:139)\n\tat org.aspectj.ajde.internal.CompilerAdapter.compile\n(CompilerAdapter.java:92)\n\tat org.aspectj.ajde.internal.AspectJBuildManager$CompilerThread.run\n(AspectJBuildManager.java:213)\n\tExceptions.java\tAspectJ Bugs/src/compiler\t\n\nSource:\n\npackage compiler;\n\nimport java.io.*;\n\n/**\n * @author websterm\n *\n * To change this generated comment go to \n * Window\u003ePreferences\u003eJava\u003eCode Generation\u003eCode and Comments\n */\npublic class Test {\n\n\tpublic static void main(String[] args) throws Exception{\n\t\tFileInputStream in \u003d new FileInputStream(\"test\");\n\t}\n}\n\n/*\n * Created on 14-Apr-03\n *\n * To change this generated comment go to \n * Window\u003ePreferences\u003eJava\u003eCode Generation\u003eCode and Comments\n */\npackage compiler;\n\nimport java.io.*;\n\nimport org.aspectj.lang.*;\n\n/**\n * @author websterm\n *\n * To change this generated comment go to \n * Window\u003ePreferences\u003eJava\u003eCode Generation\u003eCode and Comments\n */\npublic aspect Exceptions {\n\t\n\tpointcut exceptionMethods () :\n\t\tcall(* java.io.*.*(..) throws IOException);\n\t\t\n\tObject around () throws IOException : exceptionMethods() \u0026\u0026 !within\n(Exceptions) {\n\t\tObject obj \u003d proceed();\n\t\tSystem.out.println(thisJoinPoint.getStaticPart());\n\t\treturn obj;\t\n\t}\n}",
    "fixed in current tree, test in bugs/tjpStaticPart (test was easily produced \nfrom that provided in the bug report)\n\nThis bug was caused by a failed attempt to optimize thisJoinPoint.getStaticPart\n() to just be thisJoinPointStaticPart so that the dynamic join point object \nwould not have to be created if it wasn\u0027t needed.  The fix was to remove any \nattempt at this particular optimization.\n\nIf you want this performance optimization, you should just use \nthisJoinPointStaticPart directly in your code."
  ],
  "commentCreationDates": [
    "2003-04-16T14:42:21+02:00",
    "2003-04-22T19:55:29+02:00"
  ],
  "traces": [
    {
      "exceptionType": "java.lang.NullPointerException",
      "elements": [
        {
          "method": "org.eclipse.jdt.internal.compiler.ast.MessageSend.analyseCode",
          "source": "MessageSend.java:40"
        },
        {
          "method": "org.eclipse.jdt.internal.compiler.ast.MessageSend.analyseCode",
          "source": "MessageSend.java:44"
        },
        {
          "method": "org.eclipse.jdt.internal.compiler.ast.AbstractMethodDeclaration.analyseCode",
          "source": "AbstractMethodDeclaration.java:106"
        },
        {
          "method": "org.eclipse.jdt.internal.compiler.ast.TypeDeclaration.analyseCode",
          "source": "TypeDeclaration.java:445"
        },
        {
          "method": "org.eclipse.jdt.internal.compiler.ast.CompilationUnitDeclaration.analyseCode",
          "source": "CompilationUnitDeclaration.java:76"
        },
        {
          "method": "org.eclipse.jdt.internal.compiler.Compiler.process",
          "source": "Compiler.java:539"
        },
        {
          "method": "org.aspectj.ajdt.internal.compiler.AjCompiler.process",
          "source": "AjCompiler.java:65"
        },
        {
          "method": "org.eclipse.jdt.internal.compiler.Compiler.compile",
          "source": "Compiler.java:340"
        },
        {
          "method": "org.eclipse.jdt.internal.core.builder.AbstractImageBuilder.compile",
          "source": "AbstractImageBuilder.java:232"
        },
        {
          "method": "org.eclipse.jdt.internal.core.builder.AbstractImageBuilder.compile",
          "source": "AbstractImageBuilder.java:171"
        },
        {
          "method": "org.aspectj.ajdt.internal.core.builder.AjBuildManager$BatchBuilder.run",
          "source": "AjBuildManager.java:655"
        },
        {
          "method": "org.aspectj.ajdt.internal.core.builder.AjBuildManager.batchBuild",
          "source": "AjBuildManager.java:139"
        },
        {
          "method": "org.aspectj.ajde.internal.CompilerAdapter.compile",
          "source": "CompilerAdapter.java:92"
        },
        {
          "method": "org.aspectj.ajde.internal.AspectJBuildManager$CompilerThread.run",
          "source": "AspectJBuildManager.java:213"
        }
      ],
      "number": 0,
      "commentIndex": 0,
      "bugId": "36564",
      "date": "2003-04-16T14:42:21+02:00",
      "product": "AspectJ",
      "component": "Compiler",
      "severity": "normal"
    }
  ],
  "groupId": "36564",
  "bugId": "36564",
  "date": "2003-04-16T14:42:21+02:00",
  "product": "AspectJ",
  "component": "Compiler",
  "severity": "normal"
}