{
  "comments": [
    "Committed a fix for the .log entry.\nPlease close if the changes are satisfactory.\n\n\njava.lang.StringIndexOutOfBoundsException: String index out of range: -1\n        at java.lang.String.charAt(String.java:460)\n        at\norg.eclipse.cdt.debug.internal.core.model.CValue.processCDIValue(CValue.java:226)\n        at\norg.eclipse.cdt.debug.internal.core.model.CValue.getValueString(CValue.java:90)\n        at\norg.eclipse.cdt.debug.internal.ui.CDTDebugModelPresentation.getVariableText(CDTDebugModelPresentation.java:492)\n        at\norg.eclipse.cdt.debug.internal.ui.CDTDebugModelPresentation.getText(CDTDebugModelPresentation.java:288)\n        at\norg.eclipse.debug.internal.ui.LazyModelPresentation.getText(LazyModelPresentation.java:68)\n        at\norg.eclipse.debug.internal.ui.DelegatingModelPresentation.getText(DelegatingModelPresentation.java:121)\n        at\norg.eclipse.debug.internal.ui.VariablesViewModelPresentation.getText(VariablesViewModelPresentation.java:25)\n        at\norg.eclipse.debug.internal.ui.views.variables.VariablesView$VariablesViewLabelProvider.getText(VariablesView.java:129)\n        at org.eclipse.jface.viewers.TreeViewer.doUpdateItem(TreeViewer.java:95)\n        at\norg.eclipse.jface.viewers.AbstractTreeViewer$UpdateItemSafeRunnable.run(AbstractTreeViewer.java:87)\n        at\norg.eclipse.core.internal.runtime.InternalPlatform.run(InternalPlatform.java:867)\n        at org.eclipse.core.runtime.Platform.run(Platform.java:413)\n        at\norg.eclipse.jface.viewers.AbstractTreeViewer.doUpdateItem(AbstractTreeViewer.java:406)\n        at\norg.eclipse.jface.viewers.StructuredViewer$UpdateItemSafeRunnable.run(StructuredViewer.java:119)\n        at\norg.eclipse.core.internal.runtime.InternalPlatform.run(InternalPlatform.java:867)\n        at org.eclipse.core.runtime.Platform.run(Platform.java:413)\n        at\norg.eclipse.jface.viewers.StructuredViewer.updateItem(StructuredViewer.java:1271)\n        at\norg.eclipse.jface.viewers.AbstractTreeViewer.createTreeItem(AbstractTreeViewer.java:320)\n        at\norg.eclipse.jface.viewers.AbstractTreeViewer$1.run(AbstractTreeViewer.java:303)\n        at org.eclipse.swt.custom.BusyIndicator.showWhile(BusyIndicator.java:65)\n        at\norg.eclipse.jface.viewers.AbstractTreeViewer.createChildren(AbstractTreeViewer.java:289)\n        at\norg.eclipse.jface.viewers.AbstractTreeViewer.handleTreeExpand(AbstractTreeViewer.java:697)\n        at\norg.eclipse.jface.viewers.AbstractTreeViewer$4.treeExpanded(AbstractTreeViewer.java:709)\n        at org.eclipse.swt.widgets.TypedListener.handleEvent(TypedListener.java:173)\n        at org.eclipse.swt.widgets.EventTable.sendEvent(EventTable.java:77)\n        at org.eclipse.swt.widgets.Widget.sendEvent(Widget.java:805)\n        at org.eclipse.swt.widgets.Widget.sendEvent(Widget.java:827)\n        at org.eclipse.swt.widgets.Widget.sendEvent(Widget.java:812)\n        at org.eclipse.swt.widgets.Widget.notifyListeners(Widget.java:538)\n        at org.eclipse.swt.widgets.Tree.expand(Tree.java:527)\n        at org.eclipse.swt.widgets.Tree.mouseDown(Tree.java:1030)\n        at org.eclipse.swt.widgets.Tree.handleEvents(Tree.java:810)\n        at\norg.eclipse.swt.widgets.SelectableItemWidget$1.handleEvent(SelectableItemWidget.java:1192)\n        at org.eclipse.swt.widgets.EventTable.sendEvent(EventTable.java:77)\n        at org.eclipse.swt.widgets.Widget.sendEvent(Widget.java:805)\n        at org.eclipse.swt.widgets.Display.runDeferredEvents(Display.java:1912)\n        at org.eclipse.swt.widgets.Display.readAndDispatch(Display.java:1679)\n        at org.eclipse.ui.internal.Workbench.runEventLoop(Workbench.java:1400)\n        at org.eclipse.ui.internal.Workbench.run(Workbench.java:1383)\n        at\norg.eclipse.core.internal.boot.InternalBootLoader.run(InternalBootLoader.java:845)\n        at org.eclipse.core.boot.BootLoader.run(BootLoader.java:461)\n        at sun.reflect.NativeMethodAccessorImpl.invoke0(Native Method)\n        at\nsun.reflect.NativeMethodAccessorImpl.invoke(NativeMethodAccessorImpl.java:39)",
    "Fixed.",
    "Closed."
  ],
  "commentCreationDates": [
    "2003-04-21T01:54:28+02:00",
    "2003-04-21T16:13:45+02:00",
    "2003-04-21T16:14:17+02:00"
  ],
  "traces": [
    {
      "exceptionType": "java.lang.StringIndexOutOfBoundsException",
      "message": "String index out of range: -1",
      "elements": [
        {
          "method": "java.lang.String.charAt",
          "source": "String.java:460"
        },
        {
          "method": "org.eclipse.cdt.debug.internal.core.model.CValue.processCDIValue",
          "source": "CValue.java:226"
        },
        {
          "method": "org.eclipse.cdt.debug.internal.core.model.CValue.getValueString",
          "source": "CValue.java:90"
        },
        {
          "method": "org.eclipse.cdt.debug.internal.ui.CDTDebugModelPresentation.getVariableText",
          "source": "CDTDebugModelPresentation.java:492"
        },
        {
          "method": "org.eclipse.cdt.debug.internal.ui.CDTDebugModelPresentation.getText",
          "source": "CDTDebugModelPresentation.java:288"
        },
        {
          "method": "org.eclipse.debug.internal.ui.LazyModelPresentation.getText",
          "source": "LazyModelPresentation.java:68"
        },
        {
          "method": "org.eclipse.debug.internal.ui.DelegatingModelPresentation.getText",
          "source": "DelegatingModelPresentation.java:121"
        },
        {
          "method": "org.eclipse.debug.internal.ui.VariablesViewModelPresentation.getText",
          "source": "VariablesViewModelPresentation.java:25"
        },
        {
          "method": "org.eclipse.debug.internal.ui.views.variables.VariablesView$VariablesViewLabelProvider.getText",
          "source": "VariablesView.java:129"
        },
        {
          "method": "org.eclipse.jface.viewers.TreeViewer.doUpdateItem",
          "source": "TreeViewer.java:95"
        },
        {
          "method": "org.eclipse.jface.viewers.AbstractTreeViewer$UpdateItemSafeRunnable.run",
          "source": "AbstractTreeViewer.java:87"
        },
        {
          "method": "org.eclipse.core.internal.runtime.InternalPlatform.run",
          "source": "InternalPlatform.java:867"
        },
        {
          "method": "org.eclipse.core.runtime.Platform.run",
          "source": "Platform.java:413"
        },
        {
          "method": "org.eclipse.jface.viewers.AbstractTreeViewer.doUpdateItem",
          "source": "AbstractTreeViewer.java:406"
        },
        {
          "method": "org.eclipse.jface.viewers.StructuredViewer$UpdateItemSafeRunnable.run",
          "source": "StructuredViewer.java:119"
        },
        {
          "method": "org.eclipse.core.internal.runtime.InternalPlatform.run",
          "source": "InternalPlatform.java:867"
        },
        {
          "method": "org.eclipse.core.runtime.Platform.run",
          "source": "Platform.java:413"
        },
        {
          "method": "org.eclipse.jface.viewers.StructuredViewer.updateItem",
          "source": "StructuredViewer.java:1271"
        },
        {
          "method": "org.eclipse.jface.viewers.AbstractTreeViewer.createTreeItem",
          "source": "AbstractTreeViewer.java:320"
        },
        {
          "method": "org.eclipse.jface.viewers.AbstractTreeViewer$1.run",
          "source": "AbstractTreeViewer.java:303"
        },
        {
          "method": "org.eclipse.swt.custom.BusyIndicator.showWhile",
          "source": "BusyIndicator.java:65"
        },
        {
          "method": "org.eclipse.jface.viewers.AbstractTreeViewer.createChildren",
          "source": "AbstractTreeViewer.java:289"
        },
        {
          "method": "org.eclipse.jface.viewers.AbstractTreeViewer.handleTreeExpand",
          "source": "AbstractTreeViewer.java:697"
        },
        {
          "method": "org.eclipse.jface.viewers.AbstractTreeViewer$4.treeExpanded",
          "source": "AbstractTreeViewer.java:709"
        },
        {
          "method": "org.eclipse.swt.widgets.TypedListener.handleEvent",
          "source": "TypedListener.java:173"
        },
        {
          "method": "org.eclipse.swt.widgets.EventTable.sendEvent",
          "source": "EventTable.java:77"
        },
        {
          "method": "org.eclipse.swt.widgets.Widget.sendEvent",
          "source": "Widget.java:805"
        },
        {
          "method": "org.eclipse.swt.widgets.Widget.sendEvent",
          "source": "Widget.java:827"
        },
        {
          "method": "org.eclipse.swt.widgets.Widget.sendEvent",
          "source": "Widget.java:812"
        },
        {
          "method": "org.eclipse.swt.widgets.Widget.notifyListeners",
          "source": "Widget.java:538"
        },
        {
          "method": "org.eclipse.swt.widgets.Tree.expand",
          "source": "Tree.java:527"
        },
        {
          "method": "org.eclipse.swt.widgets.Tree.mouseDown",
          "source": "Tree.java:1030"
        },
        {
          "method": "org.eclipse.swt.widgets.Tree.handleEvents",
          "source": "Tree.java:810"
        },
        {
          "method": "org.eclipse.swt.widgets.SelectableItemWidget$1.handleEvent",
          "source": "SelectableItemWidget.java:1192"
        },
        {
          "method": "org.eclipse.swt.widgets.EventTable.sendEvent",
          "source": "EventTable.java:77"
        },
        {
          "method": "org.eclipse.swt.widgets.Widget.sendEvent",
          "source": "Widget.java:805"
        },
        {
          "method": "org.eclipse.swt.widgets.Display.runDeferredEvents",
          "source": "Display.java:1912"
        },
        {
          "method": "org.eclipse.swt.widgets.Display.readAndDispatch",
          "source": "Display.java:1679"
        },
        {
          "method": "org.eclipse.ui.internal.Workbench.runEventLoop",
          "source": "Workbench.java:1400"
        },
        {
          "method": "org.eclipse.ui.internal.Workbench.run",
          "source": "Workbench.java:1383"
        },
        {
          "method": "org.eclipse.core.internal.boot.InternalBootLoader.run",
          "source": "InternalBootLoader.java:845"
        },
        {
          "method": "org.eclipse.core.boot.BootLoader.run",
          "source": "BootLoader.java:461"
        },
        {
          "method": "sun.reflect.NativeMethodAccessorImpl.invoke0",
          "source": "Native Method"
        },
        {
          "method": "sun.reflect.NativeMethodAccessorImpl.invoke",
          "source": "NativeMethodAccessorImpl.java:39"
        }
      ],
      "number": 0,
      "commentIndex": 0,
      "bugId": "36680",
      "date": "2003-04-21T01:54:28+02:00",
      "product": "CDT",
      "component": "cdt-debug",
      "severity": "normal"
    }
  ],
  "groupId": "36680",
  "bugId": "36680",
  "date": "2003-04-21T01:54:28+02:00",
  "product": "CDT",
  "component": "cdt-debug",
  "severity": "normal"
}