{
  "comments": [
    "Build: i20030422\n\nGot the following stack trace silently output to my console window while I was \nrunning Eclipse. I didn\u0027t notice any problems.\n\njava.lang.NullPointerException\n        at \norg.eclipse.jdt.internal.debug.eval.ast.engine.ASTInstructionCompiler\n.containsALocalType(ASTInstructionCompiler.java:330)\n        at \norg.eclipse.jdt.internal.debug.eval.ast.engine.ASTInstructionCompiler\n.visit(ASTInstructionCompiler.java:2069)\n        at org.eclipse.jdt.core.dom.MethodInvocation.accept0\n(MethodInvocation.ja\nva:90)\n        at org.eclipse.jdt.core.dom.ASTNode.accept(ASTNode.java:1353)\n        at org.eclipse.jdt.core.dom.ASTNode.acceptChild(ASTNode.java:1400)\n        at org.eclipse.jdt.core.dom.ReturnStatement.accept0\n(ReturnStatement.java\n:74)\n        at org.eclipse.jdt.core.dom.ASTNode.accept(ASTNode.java:1353)\n        at org.eclipse.jdt.core.dom.ASTNode.acceptChildren(ASTNode.java:1423)\n        at org.eclipse.jdt.core.dom.Block.accept0(Block.java:81)\n        at org.eclipse.jdt.core.dom.ASTNode.accept(ASTNode.java:1353)\n        at org.eclipse.jdt.core.dom.ASTNode.acceptChild(ASTNode.java:1400)\n        at org.eclipse.jdt.core.dom.MethodDeclaration.accept0\n(MethodDeclaration.\njava:178)\n        at org.eclipse.jdt.core.dom.ASTNode.accept(ASTNode.java:1353)\n        at org.eclipse.jdt.core.dom.ASTNode.acceptChildren(ASTNode.java:1423)\n        at org.eclipse.jdt.core.dom.TypeDeclaration.accept0\n(TypeDeclaration.java\n:161)\n        at org.eclipse.jdt.core.dom.ASTNode.accept(ASTNode.java:1353)\n        at org.eclipse.jdt.core.dom.ASTNode.acceptChildren(ASTNode.java:1423)\n        at org.eclipse.jdt.core.dom.CompilationUnit.accept0\n(CompilationUnit.java\n:159)\n        at org.eclipse.jdt.core.dom.ASTNode.accept(ASTNode.java:1353)\n        at \norg.eclipse.jdt.internal.debug.eval.ast.engine.ASTEvaluationEngine.cr\neateExpressionFromAST(ASTEvaluationEngine.java:237)\n        at \norg.eclipse.jdt.internal.debug.eval.ast.engine.ASTEvaluationEngine.ge\ntCompiledExpression(ASTEvaluationEngine.java:155)\n        at \norg.eclipse.jdt.internal.debug.core.breakpoints.JavaLineBreakpoint.ha\nndleConditionalBreakpointEvent(JavaLineBreakpoint.java:442)\n        at \norg.eclipse.jdt.internal.debug.core.breakpoints.JavaLineBreakpoint.ha\nndleBreakpointEvent(JavaLineBreakpoint.java:359)\n        at \norg.eclipse.jdt.internal.debug.core.breakpoints.JavaBreakpoint.handle\nEvent(JavaBreakpoint.java:261)\n        at org.eclipse.jdt.internal.debug.core.EventDispatcher.dispatch\n(EventDis\npatcher.java:170)\n        at org.eclipse.jdt.internal.debug.core.EventDispatcher.run\n(EventDispatch\ner.java:211)\n        at java.lang.Thread.run(Thread.java:536)\njava.lang.NullPointerException\n        at \norg.eclipse.jdt.internal.debug.eval.ast.engine.ASTInstructionCompiler\n.containsALocalType(ASTInstructionCompiler.java:330)\n        at \norg.eclipse.jdt.internal.debug.eval.ast.engine.ASTInstructionCompiler\n.visit(ASTInstructionCompiler.java:2069)\n        at org.eclipse.jdt.core.dom.MethodInvocation.accept0\n(MethodInvocation.ja\nva:90)\n        at org.eclipse.jdt.core.dom.ASTNode.accept(ASTNode.java:1353)\n        at org.eclipse.jdt.core.dom.ASTNode.acceptChild(ASTNode.java:1400)\n        at org.eclipse.jdt.core.dom.ReturnStatement.accept0\n(ReturnStatement.java\n:74)\n        at org.eclipse.jdt.core.dom.ASTNode.accept(ASTNode.java:1353)\n        at org.eclipse.jdt.core.dom.ASTNode.acceptChildren(ASTNode.java:1423)\n        at org.eclipse.jdt.core.dom.Block.accept0(Block.java:81)\n        at org.eclipse.jdt.core.dom.ASTNode.accept(ASTNode.java:1353)\n        at org.eclipse.jdt.core.dom.ASTNode.acceptChild(ASTNode.java:1400)\n        at org.eclipse.jdt.core.dom.MethodDeclaration.accept0\n(MethodDeclaration.\njava:178)\n        at org.eclipse.jdt.core.dom.ASTNode.accept(ASTNode.java:1353)\n        at org.eclipse.jdt.core.dom.ASTNode.acceptChildren(ASTNode.java:1423)\n        at org.eclipse.jdt.core.dom.TypeDeclaration.accept0\n(TypeDeclaration.java\n:161)\n        at org.eclipse.jdt.core.dom.ASTNode.accept(ASTNode.java:1353)\n        at org.eclipse.jdt.core.dom.ASTNode.acceptChildren(ASTNode.java:1423)\n        at org.eclipse.jdt.core.dom.CompilationUnit.accept0\n(CompilationUnit.java\n:159)\n        at org.eclipse.jdt.core.dom.ASTNode.accept(ASTNode.java:1353)\n        at \norg.eclipse.jdt.internal.debug.eval.ast.engine.ASTEvaluationEngine.cr\neateExpressionFromAST(ASTEvaluationEngine.java:237)\n        at \norg.eclipse.jdt.internal.debug.eval.ast.engine.ASTEvaluationEngine.ge\ntCompiledExpression(ASTEvaluationEngine.java:155)\n        at \norg.eclipse.jdt.internal.debug.core.breakpoints.JavaLineBreakpoint.ha\nndleConditionalBreakpointEvent(JavaLineBreakpoint.java:442)\n        at \norg.eclipse.jdt.internal.debug.core.breakpoints.JavaLineBreakpoint.ha\nndleBreakpointEvent(JavaLineBreakpoint.java:359)\n        at \norg.eclipse.jdt.internal.debug.core.breakpoints.JavaBreakpoint.handle\nEvent(JavaBreakpoint.java:261)\n        at org.eclipse.jdt.internal.debug.core.EventDispatcher.dispatch\n(EventDis\npatcher.java:170)\n        at org.eclipse.jdt.internal.debug.core.EventDispatcher.run\n(EventDispatch\ner.java:211)\n        at java.lang.Thread.run(Thread.java:536)",
    "Moving to JDT/Debug.",
    "Closing.\n\nThe stack frame looks like if the compilation of the expression to evaluate\nfailed, but the evaluation engine didn\u0027t get the notification of the failure and\ntried to continue the process. As the compilation was not complete, some data\nwere not computed and returned null instead of a value.\nNeed to be able to reproduce the problem to solve it.",
    "This happened again with M7. Still no steps to reproduce. Just for the records...",
    "Rafael: I fixed bug 51425 last friday, the stack trace generated looks close to\nthe one you reported.\nWere you in the state of bug 51425 ? i.e. a project has jar in its build path\nwhich references classes from an other jar not in the build path.",
    "Sorry, Luc, I have no idea at what moment it happened nor which code I was\ndebugging. "
  ],
  "commentCreationDates": [
    "2003-04-23T20:18:49+02:00",
    "2003-04-23T21:43:53+02:00",
    "2003-07-15T01:59:07+02:00",
    "2004-02-16T23:06:55+01:00",
    "2004-02-17T18:16:51+01:00",
    "2004-02-17T18:30:08+01:00"
  ],
  "traces": [
    {
      "exceptionType": "java.lang.NullPointerException",
      "elements": [
        {
          "method": "org.eclipse.jdt.internal.debug.eval.ast.engine.ASTInstructionCompiler.containsALocalType",
          "source": "ASTInstructionCompiler.java:330"
        },
        {
          "method": "org.eclipse.jdt.internal.debug.eval.ast.engine.ASTInstructionCompiler.visit",
          "source": "ASTInstructionCompiler.java:2069"
        },
        {
          "method": "org.eclipse.jdt.core.dom.MethodInvocation.accept0",
          "source": "MethodInvocation.ja va:90"
        },
        {
          "method": "org.eclipse.jdt.core.dom.ASTNode.accept",
          "source": "ASTNode.java:1353"
        },
        {
          "method": "org.eclipse.jdt.core.dom.ASTNode.acceptChild",
          "source": "ASTNode.java:1400"
        },
        {
          "method": "org.eclipse.jdt.core.dom.ReturnStatement.accept0",
          "source": "ReturnStatement.java :74"
        },
        {
          "method": "org.eclipse.jdt.core.dom.ASTNode.accept",
          "source": "ASTNode.java:1353"
        },
        {
          "method": "org.eclipse.jdt.core.dom.ASTNode.acceptChildren",
          "source": "ASTNode.java:1423"
        },
        {
          "method": "org.eclipse.jdt.core.dom.Block.accept0",
          "source": "Block.java:81"
        },
        {
          "method": "org.eclipse.jdt.core.dom.ASTNode.accept",
          "source": "ASTNode.java:1353"
        },
        {
          "method": "org.eclipse.jdt.core.dom.ASTNode.acceptChild",
          "source": "ASTNode.java:1400"
        },
        {
          "method": "org.eclipse.jdt.core.dom.MethodDeclaration.accept0",
          "source": "MethodDeclaration. java:178"
        },
        {
          "method": "org.eclipse.jdt.core.dom.ASTNode.accept",
          "source": "ASTNode.java:1353"
        },
        {
          "method": "org.eclipse.jdt.core.dom.ASTNode.acceptChildren",
          "source": "ASTNode.java:1423"
        },
        {
          "method": "org.eclipse.jdt.core.dom.TypeDeclaration.accept0",
          "source": "TypeDeclaration.java :161"
        },
        {
          "method": "org.eclipse.jdt.core.dom.ASTNode.accept",
          "source": "ASTNode.java:1353"
        },
        {
          "method": "org.eclipse.jdt.core.dom.ASTNode.acceptChildren",
          "source": "ASTNode.java:1423"
        },
        {
          "method": "org.eclipse.jdt.core.dom.CompilationUnit.accept0",
          "source": "CompilationUnit.java :159"
        },
        {
          "method": "org.eclipse.jdt.core.dom.ASTNode.accept",
          "source": "ASTNode.java:1353"
        },
        {
          "method": "org.eclipse.jdt.internal.debug.eval.ast.engine.ASTEvaluationEngine.createExpressionFromAST",
          "source": "ASTEvaluationEngine.java:237"
        },
        {
          "method": "org.eclipse.jdt.internal.debug.eval.ast.engine.ASTEvaluationEngine.getCompiledExpression",
          "source": "ASTEvaluationEngine.java:155"
        },
        {
          "method": "org.eclipse.jdt.internal.debug.core.breakpoints.JavaLineBreakpoint.handleConditionalBreakpointEvent",
          "source": "JavaLineBreakpoint.java:442"
        },
        {
          "method": "org.eclipse.jdt.internal.debug.core.breakpoints.JavaLineBreakpoint.handleBreakpointEvent",
          "source": "JavaLineBreakpoint.java:359"
        },
        {
          "method": "org.eclipse.jdt.internal.debug.core.breakpoints.JavaBreakpoint.handleEvent",
          "source": "JavaBreakpoint.java:261"
        },
        {
          "method": "org.eclipse.jdt.internal.debug.core.EventDispatcher.dispatch",
          "source": "EventDis patcher.java:170"
        },
        {
          "method": "org.eclipse.jdt.internal.debug.core.EventDispatcher.run",
          "source": "EventDispatch er.java:211"
        },
        {
          "method": "java.lang.Thread.run",
          "source": "Thread.java:536"
        }
      ],
      "number": 0,
      "commentIndex": 0,
      "bugId": "36807",
      "date": "2003-04-23T20:18:49+02:00",
      "product": "JDT",
      "component": "Debug",
      "severity": "normal"
    },
    {
      "exceptionType": "java.lang.NullPointerException",
      "elements": [
        {
          "method": "org.eclipse.jdt.internal.debug.eval.ast.engine.ASTInstructionCompiler.containsALocalType",
          "source": "ASTInstructionCompiler.java:330"
        },
        {
          "method": "org.eclipse.jdt.internal.debug.eval.ast.engine.ASTInstructionCompiler.visit",
          "source": "ASTInstructionCompiler.java:2069"
        },
        {
          "method": "org.eclipse.jdt.core.dom.MethodInvocation.accept0",
          "source": "MethodInvocation.ja va:90"
        },
        {
          "method": "org.eclipse.jdt.core.dom.ASTNode.accept",
          "source": "ASTNode.java:1353"
        },
        {
          "method": "org.eclipse.jdt.core.dom.ASTNode.acceptChild",
          "source": "ASTNode.java:1400"
        },
        {
          "method": "org.eclipse.jdt.core.dom.ReturnStatement.accept0",
          "source": "ReturnStatement.java :74"
        },
        {
          "method": "org.eclipse.jdt.core.dom.ASTNode.accept",
          "source": "ASTNode.java:1353"
        },
        {
          "method": "org.eclipse.jdt.core.dom.ASTNode.acceptChildren",
          "source": "ASTNode.java:1423"
        },
        {
          "method": "org.eclipse.jdt.core.dom.Block.accept0",
          "source": "Block.java:81"
        },
        {
          "method": "org.eclipse.jdt.core.dom.ASTNode.accept",
          "source": "ASTNode.java:1353"
        },
        {
          "method": "org.eclipse.jdt.core.dom.ASTNode.acceptChild",
          "source": "ASTNode.java:1400"
        },
        {
          "method": "org.eclipse.jdt.core.dom.MethodDeclaration.accept0",
          "source": "MethodDeclaration. java:178"
        },
        {
          "method": "org.eclipse.jdt.core.dom.ASTNode.accept",
          "source": "ASTNode.java:1353"
        },
        {
          "method": "org.eclipse.jdt.core.dom.ASTNode.acceptChildren",
          "source": "ASTNode.java:1423"
        },
        {
          "method": "org.eclipse.jdt.core.dom.TypeDeclaration.accept0",
          "source": "TypeDeclaration.java :161"
        },
        {
          "method": "org.eclipse.jdt.core.dom.ASTNode.accept",
          "source": "ASTNode.java:1353"
        },
        {
          "method": "org.eclipse.jdt.core.dom.ASTNode.acceptChildren",
          "source": "ASTNode.java:1423"
        },
        {
          "method": "org.eclipse.jdt.core.dom.CompilationUnit.accept0",
          "source": "CompilationUnit.java :159"
        },
        {
          "method": "org.eclipse.jdt.core.dom.ASTNode.accept",
          "source": "ASTNode.java:1353"
        },
        {
          "method": "org.eclipse.jdt.internal.debug.eval.ast.engine.ASTEvaluationEngine.createExpressionFromAST",
          "source": "ASTEvaluationEngine.java:237"
        },
        {
          "method": "org.eclipse.jdt.internal.debug.eval.ast.engine.ASTEvaluationEngine.getCompiledExpression",
          "source": "ASTEvaluationEngine.java:155"
        },
        {
          "method": "org.eclipse.jdt.internal.debug.core.breakpoints.JavaLineBreakpoint.handleConditionalBreakpointEvent",
          "source": "JavaLineBreakpoint.java:442"
        },
        {
          "method": "org.eclipse.jdt.internal.debug.core.breakpoints.JavaLineBreakpoint.handleBreakpointEvent",
          "source": "JavaLineBreakpoint.java:359"
        },
        {
          "method": "org.eclipse.jdt.internal.debug.core.breakpoints.JavaBreakpoint.handleEvent",
          "source": "JavaBreakpoint.java:261"
        },
        {
          "method": "org.eclipse.jdt.internal.debug.core.EventDispatcher.dispatch",
          "source": "EventDis patcher.java:170"
        },
        {
          "method": "org.eclipse.jdt.internal.debug.core.EventDispatcher.run",
          "source": "EventDispatch er.java:211"
        },
        {
          "method": "java.lang.Thread.run",
          "source": "Thread.java:536"
        }
      ],
      "number": 1,
      "commentIndex": 0,
      "bugId": "36807",
      "date": "2003-04-23T20:18:49+02:00",
      "product": "JDT",
      "component": "Debug",
      "severity": "normal"
    }
  ],
  "groupId": "36807",
  "bugId": "36807",
  "date": "2003-04-23T20:18:49+02:00",
  "product": "JDT",
  "component": "Debug",
  "severity": "normal"
}