{
  "comments": [
    "Using AspectJ 1.1 RC1 \n \npublic aspect Asp { \n\tpublic Class Trg.member \u003d String.class; \n} \n \npublic class Trg { \n\tpublic static void main(String args[]) { \n\t\tnew Trg(); \n\t\tSystem.out.println(\"All ok\"); \n\t} \n} \n \nCompiling with \"ajc Asp.java Trg.java\" and running Trg, prints \"All ok\", as it should. \n \nCompiling with \"ajc Trg.java Asp.java\" and running Trg gives: \nException in thread \"main\" java.lang.NoSuchFieldError: class$0 \n        at Asp.ajc$interFieldInit$Asp$Trg$member(Asp.java:2) \n        at Trg.\u003cinit\u003e(Trg.java:1) \n        at Trg.main(Trg.java:3) \n \nNote, introduced field must be of type Class, or array of Classes, works fine else.",
    "fixed in tree with test in bugs/interSpecials\n\nThis issue is with the reference String.class, not with the type of the field."
  ],
  "commentCreationDates": [
    "2003-04-25T22:36:56+02:00",
    "2003-04-28T01:26:16+02:00"
  ],
  "traces": [
    {
      "exceptionType": "java.lang.NoSuchFieldError",
      "message": "class$0",
      "elements": [
        {
          "method": "Asp.ajc$interFieldInit$Asp$Trg$member",
          "source": "Asp.java:2"
        },
        {
          "method": "Trg.\u003cinit\u003e",
          "source": "Trg.java:1"
        },
        {
          "method": "Trg.main",
          "source": "Trg.java:3"
        }
      ],
      "number": 0,
      "commentIndex": 0,
      "bugId": "36936",
      "date": "2003-04-25T22:36:56+02:00",
      "product": "AspectJ",
      "component": "Compiler",
      "severity": "normal"
    }
  ],
  "groupId": "36936",
  "bugId": "36936",
  "date": "2003-04-25T22:36:56+02:00",
  "product": "AspectJ",
  "component": "Compiler",
  "severity": "normal"
}