{
  "comments": [
    "Found the following exception in the log. I have no reproducable case.\n\n!MESSAGE Problems occurred when invoking code from plug-\nin: \"org.eclipse.core.re\nsources\".\n!STACK 0\norg.eclipse.swt.SWTException: Invalid thread access\n        at org.eclipse.swt.SWT.error(SWT.java:2350)\n        at org.eclipse.swt.SWT.error(SWT.java:2280)\n        at org.eclipse.swt.widgets.Widget.error(Widget.java:389)\n        at org.eclipse.swt.widgets.Widget.checkWidget(Widget.java:319)\n        at org.eclipse.swt.widgets.Table.setRedraw(Table.java:1761)\n        at org.eclipse.jface.viewers.TableViewer.inputChanged\n(TableViewer.java:3\n95)\n        at org.eclipse.jface.viewers.ContentViewer.setInput\n(ContentViewer.java:2\n38)\n        at org.eclipse.jface.viewers.StructuredViewer.setInput\n(StructuredViewer.\njava:991)\n        at org.eclipse.pde.internal.ui.editor.feature.RequiresSection.update\n(Req\nuiresSection.java:344)\n        at org.eclipse.pde.internal.ui.editor.feature.RequiresSection.update\n(Req\nuiresSection.java:337)\n        at \norg.eclipse.pde.internal.ui.editor.feature.RequiresSection.modelsChan\nged(RequiresSection.java:327)\n        at \norg.eclipse.pde.internal.core.WorkspaceModelManager.fireModelProvider\nEvent(WorkspaceModelManager.java:209)\n        at \norg.eclipse.pde.internal.core.WorkspaceModelManager.processModelChang\nes(WorkspaceModelManager.java:783)\n        at org.eclipse.pde.internal.core.WorkspaceModelManager.resourceChanged\n(W\norkspaceModelManager.java:725)\n        at org.eclipse.core.internal.events.NotificationManager$1.run\n(Notificati\nonManager.java:137)\n        at org.eclipse.core.internal.runtime.InternalPlatform.run\n(InternalPlatfo\nrm.java:1006)\n        at org.eclipse.core.runtime.Platform.run(Platform.java:413)\n        at org.eclipse.core.internal.events.NotificationManager.notify\n(Notificat\nionManager.java:152)\n        at \norg.eclipse.core.internal.events.NotificationManager.broadcastChanges\n(NotificationManager.java:67)\n        at org.eclipse.core.internal.resources.Workspace.broadcastChanges\n(Worksp\nace.java:161)\n        at org.eclipse.core.internal.resources.Workspace.endOperation\n(Workspace.\njava:881)\n        at org.eclipse.core.internal.resources.Workspace.run\n(Workspace.java:1600\n)\n        at org.eclipse.ui.actions.WorkspaceModifyOperation.run\n(WorkspaceModifyOp\neration.java:85)\n        at org.eclipse.jface.operation.ModalContext$ModalContextThread.run\n(Modal\nContext.java:101)",
    "We will trust the log and fix the \u0027update\u0027 method by using asyncExec.",
    "Fixed."
  ],
  "commentCreationDates": [
    "2003-06-05T21:46:56+02:00",
    "2003-06-05T21:55:57+02:00",
    "2003-06-08T08:48:27+02:00"
  ],
  "traces": [
    {
      "exceptionType": "org.eclipse.swt.SWTException",
      "message": "Invalid thread access",
      "elements": [
        {
          "method": "org.eclipse.swt.SWT.error",
          "source": "SWT.java:2350"
        },
        {
          "method": "org.eclipse.swt.SWT.error",
          "source": "SWT.java:2280"
        },
        {
          "method": "org.eclipse.swt.widgets.Widget.error",
          "source": "Widget.java:389"
        },
        {
          "method": "org.eclipse.swt.widgets.Widget.checkWidget",
          "source": "Widget.java:319"
        },
        {
          "method": "org.eclipse.swt.widgets.Table.setRedraw",
          "source": "Table.java:1761"
        },
        {
          "method": "org.eclipse.jface.viewers.TableViewer.inputChanged",
          "source": "TableViewer.java:3 95"
        },
        {
          "method": "org.eclipse.jface.viewers.ContentViewer.setInput",
          "source": "ContentViewer.java:2 38"
        },
        {
          "method": "org.eclipse.jface.viewers.StructuredViewer.setInput",
          "source": "StructuredViewer. java:991"
        },
        {
          "method": "org.eclipse.pde.internal.ui.editor.feature.RequiresSection.update",
          "source": "Req uiresSection.java:344"
        },
        {
          "method": "org.eclipse.pde.internal.ui.editor.feature.RequiresSection.update",
          "source": "Req uiresSection.java:337"
        },
        {
          "method": "org.eclipse.pde.internal.ui.editor.feature.RequiresSection.modelsChanged",
          "source": "RequiresSection.java:327"
        },
        {
          "method": "org.eclipse.pde.internal.core.WorkspaceModelManager.fireModelProviderEvent",
          "source": "WorkspaceModelManager.java:209"
        },
        {
          "method": "org.eclipse.pde.internal.core.WorkspaceModelManager.processModelChanges",
          "source": "WorkspaceModelManager.java:783"
        },
        {
          "method": "org.eclipse.pde.internal.core.WorkspaceModelManager.resourceChanged",
          "source": "W orkspaceModelManager.java:725"
        },
        {
          "method": "org.eclipse.core.internal.events.NotificationManager$1.run",
          "source": "Notificati onManager.java:137"
        },
        {
          "method": "org.eclipse.core.internal.runtime.InternalPlatform.run",
          "source": "InternalPlatfo rm.java:1006"
        },
        {
          "method": "org.eclipse.core.runtime.Platform.run",
          "source": "Platform.java:413"
        },
        {
          "method": "org.eclipse.core.internal.events.NotificationManager.notify",
          "source": "Notificat ionManager.java:152"
        },
        {
          "method": "org.eclipse.core.internal.events.NotificationManager.broadcastChanges",
          "source": "NotificationManager.java:67"
        },
        {
          "method": "org.eclipse.core.internal.resources.Workspace.broadcastChanges",
          "source": "Worksp ace.java:161"
        },
        {
          "method": "org.eclipse.core.internal.resources.Workspace.endOperation",
          "source": "Workspace. java:881"
        },
        {
          "method": "org.eclipse.core.internal.resources.Workspace.run",
          "source": "Workspace.java:1600 "
        },
        {
          "method": "org.eclipse.ui.actions.WorkspaceModifyOperation.run",
          "source": "WorkspaceModifyOp eration.java:85"
        },
        {
          "method": "org.eclipse.jface.operation.ModalContext$ModalContextThread.run",
          "source": "Modal Context.java:101"
        }
      ],
      "number": 0,
      "commentIndex": 0,
      "bugId": "38542",
      "date": "2003-06-05T21:46:56+02:00",
      "product": "PDE",
      "component": "UI",
      "severity": "normal"
    }
  ],
  "groupId": "38542",
  "bugId": "38542",
  "date": "2003-06-05T21:46:56+02:00",
  "product": "PDE",
  "component": "UI",
  "severity": "normal"
}