{
  "comments": [
    "On Linux-GTK, if I attempt to create a simple view that contains a CTabFolder \nwith a CTabItem, the view part can not be created and the following stackTrace \nis in the log.  The constructor for CTabItem fails.\n\nThe same code runs successfully on on Windows and Linux-Motif. \n\n!MESSAGE Problems occurred when invoking code from plug-\nin: \"org.eclipse.ui.workbench\".\n!STACK 0\njava.lang.IllegalArgumentException: Argument not valid\n        at org.eclipse.swt.SWT.error(SWT.java:2318)\n        at org.eclipse.swt.SWT.error(SWT.java:2262)\n        at org.eclipse.swt.graphics.GC.drawImage(GC.java:368)\n        at org.eclipse.swt.graphics.GC.drawImage(GC.java:351)\n        at org.eclipse.swt.custom.CTabFolder.scaleImage(CTabFolder.java:1760)\n        at org.eclipse.swt.custom.CTabFolder.updateArrowBar\n(CTabFolder.java:1883)\n        at org.eclipse.swt.custom.CTabFolder.setButtonBounds\n(CTabFolder.java:969)\n        at org.eclipse.swt.custom.CTabFolder.setItemLocation\n(CTabFolder.java:1044)\n        at org.eclipse.swt.custom.CTabFolder.setItemBounds(CTabFolder.java:1127)\n        at org.eclipse.swt.custom.CTabFolder.resetTabSize(CTabFolder.java:2149)\n        at org.eclipse.swt.custom.CTabFolder.createItem(CTabFolder.java:386)\n        at org.eclipse.swt.custom.CTabItem.\u003cinit\u003e(CTabItem.java:100)\n        at org.eclipse.swt.custom.CTabItem.\u003cinit\u003e(CTabItem.java:67)\n        at LinuxTest2.views.SampleView.createPartControl(SampleView.java:85)\n        at org.eclipse.ui.internal.PartPane$4.run(PartPane.java:141)\n        at org.eclipse.core.internal.runtime.InternalPlatform.run\n(InternalPlatform.java:889)\n        at org.eclipse.core.runtime.Platform.run(Platform.java:413)\n        at org.eclipse.ui.internal.PartPane.createChildControl\n(PartPane.java:137)\n        at org.eclipse.ui.internal.ViewPane.createChildControl\n(ViewPane.java:211)\n        at org.eclipse.ui.internal.PartPane.createControl(PartPane.java:186)\n        at org.eclipse.ui.internal.ViewPane.createControl(ViewPane.java:190)\n        at org.eclipse.ui.internal.PartTabFolder.createPartTab\n(PartTabFolder.java:252)\n        at org.eclipse.ui.internal.PartTabFolder.add(PartTabFolder.java:88)\n        at org.eclipse.ui.internal.PartTabFolder.add(PartTabFolder.java:111)\n        at org.eclipse.ui.internal.PerspectivePresentation.stackView\n(PerspectivePresentation.java:1631)\n        at org.eclipse.ui.internal.PerspectivePresentation.stack\n(PerspectivePresentation.java:1604)\n        at org.eclipse.ui.internal.PerspectivePresentation.addPart\n(PerspectivePresentation.java:138)\n        at org.eclipse.ui.internal.Perspective.showView(Perspective.java:1483)\n        at org.eclipse.ui.internal.WorkbenchPage.busyShowView\n(WorkbenchPage.java:655)\n        at org.eclipse.ui.internal.WorkbenchPage.access$9\n(WorkbenchPage.java:634)\n        at org.eclipse.ui.internal.WorkbenchPage$13.run(WorkbenchPage.java:2777)\n        at org.eclipse.swt.custom.BusyIndicator.showWhile(BusyIndicator.java:69)\n        at org.eclipse.ui.internal.WorkbenchPage.showView\n(WorkbenchPage.java:2774)\n        at org.eclipse.ui.internal.WorkbenchPage.showView\n(WorkbenchPage.java:2764)\n        at org.eclipse.ui.internal.ShowViewMenu.showOther(ShowViewMenu.java:175)\n        at org.eclipse.ui.internal.ShowViewMenu.access$2(ShowViewMenu.java:161)\n\nHere is the code that creates the view:\n\npackage LinuxTest.views;\n\nimport org.eclipse.jface.action.Action;\nimport org.eclipse.jface.viewers.TableViewer;\nimport org.eclipse.swt.SWT;\nimport org.eclipse.swt.custom.CTabFolder;\nimport org.eclipse.swt.custom.CTabItem;\nimport org.eclipse.swt.layout.GridData;\nimport org.eclipse.swt.layout.GridLayout;\nimport org.eclipse.swt.widgets.Composite;\nimport org.eclipse.swt.widgets.Text;\nimport org.eclipse.ui.part.ViewPart;\n\npublic class SampleView extends ViewPart {\n\tprivate TableViewer viewer;\n\tprivate Action action1;\n\tprivate Action action2;\n\tprivate Action doubleClickAction;\n\n\n\n\t/**\n\t * The constructor.\n\t */\n\tpublic SampleView() {\n\t}\n\n\t/**\n\t * This is a callback that will allow us\n\t * to create the viewer and initialize it.\n\t */\n\tpublic void createPartControl(Composite parent) {\n\t\t\n\t\tGridData gd;\n\t\tGridLayout gridLayout \u003d new GridLayout();\n\t\tgridLayout.marginWidth \u003d 0;\n\t\tgridLayout.marginHeight \u003d 0;\n\t\tgridLayout.horizontalSpacing \u003d 0;\n\t\tgridLayout.verticalSpacing \u003d 0;\n\t\t\n\t\tComposite displayArea \u003d new Composite(parent, SWT.NONE);\n\t\tdisplayArea.setLayout(gridLayout);\n\n\t\t\n\t\tCTabFolder pageArea \u003d new CTabFolder(displayArea, SWT.TOP);\n\t\tpageArea.setTabHeight(16);\n\t\n\t\tgd \u003d new GridData(GridData.HORIZONTAL_ALIGN_FILL);\n\t\tgd.verticalAlignment \u003d GridData.FILL;\n\t\tgd.grabExcessVerticalSpace \u003d true;\n\t\tgd.grabExcessHorizontalSpace \u003d true;\n\t\tpageArea.setLayoutData(gd);\n\n\t\t//Page 1 - the Message Page\n\t\tCTabItem messageTab \u003d new CTabItem(pageArea, SWT.NULL);\n\t\tmessageTab.setText(\"First tab\");\n\t\tText messageArea \u003d\n\t\t\tnew Text(\n\t\t\t\tpageArea,\n\t\t\t\tSWT.V_SCROLL\n\t\t\t\t\t| SWT.MULTI\n\t\t\t\t\t| SWT.BORDER\n\t\t\t\t\t| SWT.READ_ONLY\n\t\t\t\t\t| SWT.WRAP);\n\n\t\tmessageArea.setText(\"This is tab 1\");\n\t\tmessageTab.setControl(messageArea);\n\t\n\t}\n\n\n\t/**\n\t * Passing the focus request to the viewer\u0027s control.\n\t */\n\tpublic void setFocus() {\n\t//\tviewer.getControl().setFocus();\n\t}\n}",
    "VI to investigate.",
    "I will investigate.\n\nAs a workaround, comment out the line \"pageArea.setTabHeight(16);\".\n\nNote that setting the tab height to 16 may be a bad idea anyway since the \nsystem font could be much larger than 16 (for users with vision problems etc) \nand this will result in clipped text.",
    "*** Bug 39160 has been marked as a duplicate of this bug. ***",
    "Fixed in 3.0."
  ],
  "commentCreationDates": [
    "2003-06-06T21:38:45+02:00",
    "2003-06-12T17:38:01+02:00",
    "2003-06-12T18:08:31+02:00",
    "2003-08-06T20:46:45+02:00",
    "2003-08-06T20:58:05+02:00"
  ],
  "traces": [
    {
      "exceptionType": "java.lang.IllegalArgumentException",
      "message": "Argument not valid",
      "elements": [
        {
          "method": "org.eclipse.swt.SWT.error",
          "source": "SWT.java:2318"
        },
        {
          "method": "org.eclipse.swt.SWT.error",
          "source": "SWT.java:2262"
        },
        {
          "method": "org.eclipse.swt.graphics.GC.drawImage",
          "source": "GC.java:368"
        },
        {
          "method": "org.eclipse.swt.graphics.GC.drawImage",
          "source": "GC.java:351"
        },
        {
          "method": "org.eclipse.swt.custom.CTabFolder.scaleImage",
          "source": "CTabFolder.java:1760"
        },
        {
          "method": "org.eclipse.swt.custom.CTabFolder.updateArrowBar",
          "source": "CTabFolder.java:1883"
        },
        {
          "method": "org.eclipse.swt.custom.CTabFolder.setButtonBounds",
          "source": "CTabFolder.java:969"
        },
        {
          "method": "org.eclipse.swt.custom.CTabFolder.setItemLocation",
          "source": "CTabFolder.java:1044"
        },
        {
          "method": "org.eclipse.swt.custom.CTabFolder.setItemBounds",
          "source": "CTabFolder.java:1127"
        },
        {
          "method": "org.eclipse.swt.custom.CTabFolder.resetTabSize",
          "source": "CTabFolder.java:2149"
        },
        {
          "method": "org.eclipse.swt.custom.CTabFolder.createItem",
          "source": "CTabFolder.java:386"
        },
        {
          "method": "org.eclipse.swt.custom.CTabItem.\u003cinit\u003e",
          "source": "CTabItem.java:100"
        },
        {
          "method": "org.eclipse.swt.custom.CTabItem.\u003cinit\u003e",
          "source": "CTabItem.java:67"
        },
        {
          "method": "LinuxTest2.views.SampleView.createPartControl",
          "source": "SampleView.java:85"
        },
        {
          "method": "org.eclipse.ui.internal.PartPane$4.run",
          "source": "PartPane.java:141"
        },
        {
          "method": "org.eclipse.core.internal.runtime.InternalPlatform.run",
          "source": "InternalPlatform.java:889"
        },
        {
          "method": "org.eclipse.core.runtime.Platform.run",
          "source": "Platform.java:413"
        },
        {
          "method": "org.eclipse.ui.internal.PartPane.createChildControl",
          "source": "PartPane.java:137"
        },
        {
          "method": "org.eclipse.ui.internal.ViewPane.createChildControl",
          "source": "ViewPane.java:211"
        },
        {
          "method": "org.eclipse.ui.internal.PartPane.createControl",
          "source": "PartPane.java:186"
        },
        {
          "method": "org.eclipse.ui.internal.ViewPane.createControl",
          "source": "ViewPane.java:190"
        },
        {
          "method": "org.eclipse.ui.internal.PartTabFolder.createPartTab",
          "source": "PartTabFolder.java:252"
        },
        {
          "method": "org.eclipse.ui.internal.PartTabFolder.add",
          "source": "PartTabFolder.java:88"
        },
        {
          "method": "org.eclipse.ui.internal.PartTabFolder.add",
          "source": "PartTabFolder.java:111"
        },
        {
          "method": "org.eclipse.ui.internal.PerspectivePresentation.stackView",
          "source": "PerspectivePresentation.java:1631"
        },
        {
          "method": "org.eclipse.ui.internal.PerspectivePresentation.stack",
          "source": "PerspectivePresentation.java:1604"
        },
        {
          "method": "org.eclipse.ui.internal.PerspectivePresentation.addPart",
          "source": "PerspectivePresentation.java:138"
        },
        {
          "method": "org.eclipse.ui.internal.Perspective.showView",
          "source": "Perspective.java:1483"
        },
        {
          "method": "org.eclipse.ui.internal.WorkbenchPage.busyShowView",
          "source": "WorkbenchPage.java:655"
        },
        {
          "method": "org.eclipse.ui.internal.WorkbenchPage.access$9",
          "source": "WorkbenchPage.java:634"
        },
        {
          "method": "org.eclipse.ui.internal.WorkbenchPage$13.run",
          "source": "WorkbenchPage.java:2777"
        },
        {
          "method": "org.eclipse.swt.custom.BusyIndicator.showWhile",
          "source": "BusyIndicator.java:69"
        },
        {
          "method": "org.eclipse.ui.internal.WorkbenchPage.showView",
          "source": "WorkbenchPage.java:2774"
        },
        {
          "method": "org.eclipse.ui.internal.WorkbenchPage.showView",
          "source": "WorkbenchPage.java:2764"
        },
        {
          "method": "org.eclipse.ui.internal.ShowViewMenu.showOther",
          "source": "ShowViewMenu.java:175"
        },
        {
          "method": "org.eclipse.ui.internal.ShowViewMenu.access$2",
          "source": "ShowViewMenu.java:161"
        }
      ],
      "number": 0,
      "commentIndex": 0,
      "bugId": "38605",
      "date": "2003-06-06T21:38:45+02:00",
      "product": "Platform",
      "component": "SWT",
      "severity": "blocker"
    }
  ],
  "groupId": "38605",
  "bugId": "38605",
  "date": "2003-06-06T21:38:45+02:00",
  "product": "Platform",
  "component": "SWT",
  "severity": "blocker"
}