{
  "comments": [
    "I don\u0027t often look in the console window that eclipse is running in but I just \nhappend to do so this time and here is what I saw:\n\njava.lang.NullPointerException\n        at org.eclipse.jdt.internal.compiler.parser.SourceTypeConverter.convert(\nSourceTypeConverter.java:117)\n        at org.eclipse.jdt.internal.compiler.parser.SourceTypeConverter.buildCom\npilationUnit(SourceTypeConverter.java:77)\n        at org.eclipse.jdt.internal.core.CompilationUnitProblemFinder.accept(Com\npilationUnitProblemFinder.java:99)\n        at org.eclipse.jdt.internal.compiler.lookup.LookupEnvironment.askForType\n(LookupEnvironment.java:106)\n        at org.eclipse.jdt.internal.compiler.lookup.PackageBinding.getTypeOrPack\nage(PackageBinding.java:173)\n        at org.eclipse.jdt.internal.compiler.lookup.Scope.getTypeOrPackage(Scope\n.java:1322)\n        at org.eclipse.jdt.internal.compiler.lookup.ClassScope.findSupertype(Cla\nssScope.java:789)\n        at org.eclipse.jdt.internal.compiler.lookup.ClassScope.connectSuperInter\nfaces(ClassScope.java:627)\n        at org.eclipse.jdt.internal.compiler.lookup.ClassScope.connectTypeHierar\nchyWithoutMembers(ClassScope.java:704)\n        at org.eclipse.jdt.internal.compiler.lookup.ClassScope.detectCycle(Class\nScope.java:769)\n        at org.eclipse.jdt.internal.compiler.lookup.ClassScope.findSupertype(Cla\nssScope.java:825)\n        at org.eclipse.jdt.internal.compiler.lookup.ClassScope.connectSuperInter\nfaces(ClassScope.java:627)\n        at org.eclipse.jdt.internal.compiler.lookup.ClassScope.connectTypeHierar\nchyWithoutMembers(ClassScope.java:704)\n        at org.eclipse.jdt.internal.compiler.lookup.ClassScope.detectCycle(Class\nScope.java:769)\n        at org.eclipse.jdt.internal.compiler.lookup.ClassScope.findSupertype(Cla\nssScope.java:825)\n        at org.eclipse.jdt.internal.compiler.lookup.ClassScope.connectSuperInter\nfaces(ClassScope.java:627)\n        at org.eclipse.jdt.internal.compiler.lookup.ClassScope.connectTypeHierar\nchy(ClassScope.java:676)\n        at org.eclipse.jdt.internal.compiler.lookup.CompilationUnitScope.connect\nTypeHierarchy(CompilationUnitScope.java:252)\n        at org.eclipse.jdt.internal.compiler.lookup.LookupEnvironment.completeTy\npeBindings(LookupEnvironment.java:170)\n        at org.eclipse.jdt.internal.compiler.Compiler.beginToCompile(Compiler.ja\nva:310)\n        at org.eclipse.jdt.internal.compiler.Compiler.resolve(Compiler.java:574)\n\n        at org.eclipse.jdt.internal.compiler.Compiler.resolve(Compiler.java:633)\n\n        at org.eclipse.jdt.internal.core.CompilationUnitProblemFinder.process(Co\nmpilationUnitProblemFinder.java:209)\n        at org.eclipse.jdt.internal.core.CompilationUnitProblemFinder.process(Co\nmpilationUnitProblemFinder.java:240)\n        at org.eclipse.jdt.internal.core.ReconcileWorkingCopyOperation.executeOp\neration(ReconcileWorkingCopyOperation.java:62)\n        at org.eclipse.jdt.internal.core.JavaModelOperation.execute(JavaModelOpe\nration.java:365)\n        at org.eclipse.jdt.internal.core.JavaModelOperation.run(JavaModelOperati\non.java:704)\n        at org.eclipse.jdt.internal.core.JavaElement.runOperation(JavaElement.ja\nva:535)\n        at org.eclipse.jdt.internal.core.WorkingCopy.reconcile(WorkingCopy.java:\n524)\n        at org.eclipse.jdt.internal.ui.text.java.JavaReconcilingStrategy.reconci\nle(JavaReconcilingStrategy.java:72)\n        at org.eclipse.jdt.internal.ui.text.java.JavaReconcilingStrategy.initial\nReconcile(JavaReconcilingStrategy.java:126)\n        at org.eclipse.jface.text.reconciler.MonoReconciler.initialProcess(MonoR\neconciler.java:104)\n        at org.eclipse.jface.text.reconciler.AbstractReconciler$BackgroundThread\n.run(AbstractReconciler.java:155)\njava.lang.NullPointerException\n        at org.eclipse.jdt.internal.compiler.parser.SourceTypeConverter.convert(\nSourceTypeConverter.java:117)\n        at org.eclipse.jdt.internal.compiler.parser.SourceTypeConverter.buildCom\npilationUnit(SourceTypeConverter.java:77)\n        at org.eclipse.jdt.internal.core.CompilationUnitProblemFinder.accept(Com\npilationUnitProblemFinder.java:99)\n        at org.eclipse.jdt.internal.compiler.lookup.LookupEnvironment.askForType\n(LookupEnvironment.java:106)\n        at org.eclipse.jdt.internal.compiler.lookup.PackageBinding.getTypeOrPack\nage(PackageBinding.java:173)\n        at org.eclipse.jdt.internal.compiler.lookup.Scope.getTypeOrPackage(Scope\n.java:1322)\n        at org.eclipse.jdt.internal.compiler.lookup.ClassScope.findSupertype(Cla\nssScope.java:789)\n        at org.eclipse.jdt.internal.compiler.lookup.ClassScope.connectSuperInter\nfaces(ClassScope.java:627)\n        at org.eclipse.jdt.internal.compiler.lookup.ClassScope.connectTypeHierar\nchyWithoutMembers(ClassScope.java:704)\n        at org.eclipse.jdt.internal.compiler.lookup.ClassScope.detectCycle(Class\nScope.java:769)\n        at org.eclipse.jdt.internal.compiler.lookup.ClassScope.findSupertype(Cla\nssScope.java:825)\n        at org.eclipse.jdt.internal.compiler.lookup.ClassScope.connectSuperInter\nfaces(ClassScope.java:627)\n        at org.eclipse.jdt.internal.compiler.lookup.ClassScope.connectTypeHierar\nchyWithoutMembers(ClassScope.java:704)\n        at org.eclipse.jdt.internal.compiler.lookup.ClassScope.detectCycle(Class\nScope.java:769)\n        at org.eclipse.jdt.internal.compiler.lookup.ClassScope.findSupertype(Cla\nssScope.java:825)\n        at org.eclipse.jdt.internal.compiler.lookup.ClassScope.connectSuperInter\nfaces(ClassScope.java:627)\n        at org.eclipse.jdt.internal.compiler.lookup.ClassScope.connectTypeHierar\nchy(ClassScope.java:676)\n        at org.eclipse.jdt.internal.compiler.lookup.CompilationUnitScope.connect\nTypeHierarchy(CompilationUnitScope.java:252)\n        at org.eclipse.jdt.internal.compiler.lookup.LookupEnvironment.completeTy\npeBindings(LookupEnvironment.java:170)\n        at org.eclipse.jdt.internal.compiler.Compiler.beginToCompile(Compiler.ja\nva:310)\n        at org.eclipse.jdt.internal.compiler.Compiler.resolve(Compiler.java:574)\n\n        at org.eclipse.jdt.internal.compiler.Compiler.resolve(Compiler.java:633)\n\n        at org.eclipse.jdt.internal.core.CompilationUnitProblemFinder.process(Co\nmpilationUnitProblemFinder.java:209)\n        at org.eclipse.jdt.internal.core.CompilationUnitProblemFinder.process(Co\nmpilationUnitProblemFinder.java:240)\n        at org.eclipse.jdt.internal.core.ReconcileWorkingCopyOperation.executeOp\neration(ReconcileWorkingCopyOperation.java:62)\n        at org.eclipse.jdt.internal.core.JavaModelOperation.execute(JavaModelOpe\nration.java:365)\n        at org.eclipse.jdt.internal.core.JavaModelOperation.run(JavaModelOperati\non.java:704)\n        at org.eclipse.jdt.internal.core.JavaElement.runOperation(JavaElement.ja\nva:535)\n        at org.eclipse.jdt.internal.core.WorkingCopy.reconcile(WorkingCopy.java:\n524)\n        at org.eclipse.jdt.internal.ui.text.java.JavaReconcilingStrategy.reconci\nle(JavaReconcilingStrategy.java:72)\n        at org.eclipse.jdt.internal.ui.text.java.JavaReconcilingStrategy.initial\nReconcile(JavaReconcilingStrategy.java:126)\n        at org.eclipse.jface.text.reconciler.MonoReconciler.initialProcess(MonoR\neconciler.java:104)\n        at org.eclipse.jface.text.reconciler.AbstractReconciler$BackgroundThread\n.run(AbstractReconciler.java:155)",
    "P.S. I am using version 200306051737 (M1)",
    "Which VM are you using to run Eclipse on ?",
    "Z:\\\u003ejava -version\njava version \"1.4.2-beta\"\nJava(TM) 2 Runtime Environment, Standard Edition (build 1.4.2-beta-b19)\nJava HotSpot(TM) Client VM (build 1.4.2-beta-b19, mixed mode)\n\n(From Sun)",
    "\n\n*** This bug has been marked as a duplicate of 36854 ***"
  ],
  "commentCreationDates": [
    "2003-06-10T10:47:10+02:00",
    "2003-06-10T10:48:39+02:00",
    "2003-06-10T12:22:07+02:00",
    "2003-06-10T12:23:27+02:00",
    "2003-06-10T12:38:50+02:00"
  ],
  "traces": [
    {
      "exceptionType": "java.lang.NullPointerException",
      "elements": [
        {
          "method": "org.eclipse.jdt.internal.compiler.parser.SourceTypeConverter.convert",
          "source": " SourceTypeConverter.java:117"
        },
        {
          "method": "org.eclipse.jdt.internal.compiler.parser.SourceTypeConverter.buildCompilationUnit",
          "source": "SourceTypeConverter.java:77"
        },
        {
          "method": "org.eclipse.jdt.internal.core.CompilationUnitProblemFinder.accept",
          "source": "Com pilationUnitProblemFinder.java:99"
        },
        {
          "method": "org.eclipse.jdt.internal.compiler.lookup.LookupEnvironment.askForType",
          "source": "LookupEnvironment.java:106"
        },
        {
          "method": "org.eclipse.jdt.internal.compiler.lookup.PackageBinding.getTypeOrPackage",
          "source": "PackageBinding.java:173"
        },
        {
          "method": "org.eclipse.jdt.internal.compiler.lookup.Scope.getTypeOrPackage",
          "source": "Scope .java:1322"
        },
        {
          "method": "org.eclipse.jdt.internal.compiler.lookup.ClassScope.findSupertype",
          "source": "Cla ssScope.java:789"
        },
        {
          "method": "org.eclipse.jdt.internal.compiler.lookup.ClassScope.connectSuperInterfaces",
          "source": "ClassScope.java:627"
        },
        {
          "method": "org.eclipse.jdt.internal.compiler.lookup.ClassScope.connectTypeHierarchyWithoutMembers",
          "source": "ClassScope.java:704"
        },
        {
          "method": "org.eclipse.jdt.internal.compiler.lookup.ClassScope.detectCycle",
          "source": "Class Scope.java:769"
        },
        {
          "method": "org.eclipse.jdt.internal.compiler.lookup.ClassScope.findSupertype",
          "source": "Cla ssScope.java:825"
        },
        {
          "method": "org.eclipse.jdt.internal.compiler.lookup.ClassScope.connectSuperInterfaces",
          "source": "ClassScope.java:627"
        },
        {
          "method": "org.eclipse.jdt.internal.compiler.lookup.ClassScope.connectTypeHierarchyWithoutMembers",
          "source": "ClassScope.java:704"
        },
        {
          "method": "org.eclipse.jdt.internal.compiler.lookup.ClassScope.detectCycle",
          "source": "Class Scope.java:769"
        },
        {
          "method": "org.eclipse.jdt.internal.compiler.lookup.ClassScope.findSupertype",
          "source": "Cla ssScope.java:825"
        },
        {
          "method": "org.eclipse.jdt.internal.compiler.lookup.ClassScope.connectSuperInterfaces",
          "source": "ClassScope.java:627"
        },
        {
          "method": "org.eclipse.jdt.internal.compiler.lookup.ClassScope.connectTypeHierarchy",
          "source": "ClassScope.java:676"
        },
        {
          "method": "org.eclipse.jdt.internal.compiler.lookup.CompilationUnitScope.connectTypeHierarchy",
          "source": "CompilationUnitScope.java:252"
        },
        {
          "method": "org.eclipse.jdt.internal.compiler.lookup.LookupEnvironment.completeTypeBindings",
          "source": "LookupEnvironment.java:170"
        },
        {
          "method": "org.eclipse.jdt.internal.compiler.Compiler.beginToCompile",
          "source": "Compiler.ja va:310"
        },
        {
          "method": "org.eclipse.jdt.internal.compiler.Compiler.resolve",
          "source": "Compiler.java:574"
        },
        {
          "method": "org.eclipse.jdt.internal.compiler.Compiler.resolve",
          "source": "Compiler.java:633"
        },
        {
          "method": "org.eclipse.jdt.internal.core.CompilationUnitProblemFinder.process",
          "source": "Co mpilationUnitProblemFinder.java:209"
        },
        {
          "method": "org.eclipse.jdt.internal.core.CompilationUnitProblemFinder.process",
          "source": "Co mpilationUnitProblemFinder.java:240"
        },
        {
          "method": "org.eclipse.jdt.internal.core.ReconcileWorkingCopyOperation.executeOperation",
          "source": "ReconcileWorkingCopyOperation.java:62"
        },
        {
          "method": "org.eclipse.jdt.internal.core.JavaModelOperation.execute",
          "source": "JavaModelOpe ration.java:365"
        },
        {
          "method": "org.eclipse.jdt.internal.core.JavaModelOperation.run",
          "source": "JavaModelOperati on.java:704"
        },
        {
          "method": "org.eclipse.jdt.internal.core.JavaElement.runOperation",
          "source": "JavaElement.ja va:535"
        },
        {
          "method": "org.eclipse.jdt.internal.core.WorkingCopy.reconcile",
          "source": "WorkingCopy.java: 524"
        },
        {
          "method": "org.eclipse.jdt.internal.ui.text.java.JavaReconcilingStrategy.reconcile",
          "source": "JavaReconcilingStrategy.java:72"
        },
        {
          "method": "org.eclipse.jdt.internal.ui.text.java.JavaReconcilingStrategy.initialReconcile",
          "source": "JavaReconcilingStrategy.java:126"
        },
        {
          "method": "org.eclipse.jface.text.reconciler.MonoReconciler.initialProcess",
          "source": "MonoR econciler.java:104"
        },
        {
          "method": "org.eclipse.jface.text.reconciler.AbstractReconciler$BackgroundThread.run",
          "source": "AbstractReconciler.java:155"
        }
      ],
      "number": 0,
      "commentIndex": 0,
      "bugId": "38688",
      "duplicateId": "36854",
      "date": "2003-06-10T10:47:10+02:00",
      "product": "JDT",
      "component": "Core",
      "severity": "normal"
    },
    {
      "exceptionType": "java.lang.NullPointerException",
      "elements": [
        {
          "method": "org.eclipse.jdt.internal.compiler.parser.SourceTypeConverter.convert",
          "source": " SourceTypeConverter.java:117"
        },
        {
          "method": "org.eclipse.jdt.internal.compiler.parser.SourceTypeConverter.buildCompilationUnit",
          "source": "SourceTypeConverter.java:77"
        },
        {
          "method": "org.eclipse.jdt.internal.core.CompilationUnitProblemFinder.accept",
          "source": "Com pilationUnitProblemFinder.java:99"
        },
        {
          "method": "org.eclipse.jdt.internal.compiler.lookup.LookupEnvironment.askForType",
          "source": "LookupEnvironment.java:106"
        },
        {
          "method": "org.eclipse.jdt.internal.compiler.lookup.PackageBinding.getTypeOrPackage",
          "source": "PackageBinding.java:173"
        },
        {
          "method": "org.eclipse.jdt.internal.compiler.lookup.Scope.getTypeOrPackage",
          "source": "Scope .java:1322"
        },
        {
          "method": "org.eclipse.jdt.internal.compiler.lookup.ClassScope.findSupertype",
          "source": "Cla ssScope.java:789"
        },
        {
          "method": "org.eclipse.jdt.internal.compiler.lookup.ClassScope.connectSuperInterfaces",
          "source": "ClassScope.java:627"
        },
        {
          "method": "org.eclipse.jdt.internal.compiler.lookup.ClassScope.connectTypeHierarchyWithoutMembers",
          "source": "ClassScope.java:704"
        },
        {
          "method": "org.eclipse.jdt.internal.compiler.lookup.ClassScope.detectCycle",
          "source": "Class Scope.java:769"
        },
        {
          "method": "org.eclipse.jdt.internal.compiler.lookup.ClassScope.findSupertype",
          "source": "Cla ssScope.java:825"
        },
        {
          "method": "org.eclipse.jdt.internal.compiler.lookup.ClassScope.connectSuperInterfaces",
          "source": "ClassScope.java:627"
        },
        {
          "method": "org.eclipse.jdt.internal.compiler.lookup.ClassScope.connectTypeHierarchyWithoutMembers",
          "source": "ClassScope.java:704"
        },
        {
          "method": "org.eclipse.jdt.internal.compiler.lookup.ClassScope.detectCycle",
          "source": "Class Scope.java:769"
        },
        {
          "method": "org.eclipse.jdt.internal.compiler.lookup.ClassScope.findSupertype",
          "source": "Cla ssScope.java:825"
        },
        {
          "method": "org.eclipse.jdt.internal.compiler.lookup.ClassScope.connectSuperInterfaces",
          "source": "ClassScope.java:627"
        },
        {
          "method": "org.eclipse.jdt.internal.compiler.lookup.ClassScope.connectTypeHierarchy",
          "source": "ClassScope.java:676"
        },
        {
          "method": "org.eclipse.jdt.internal.compiler.lookup.CompilationUnitScope.connectTypeHierarchy",
          "source": "CompilationUnitScope.java:252"
        },
        {
          "method": "org.eclipse.jdt.internal.compiler.lookup.LookupEnvironment.completeTypeBindings",
          "source": "LookupEnvironment.java:170"
        },
        {
          "method": "org.eclipse.jdt.internal.compiler.Compiler.beginToCompile",
          "source": "Compiler.ja va:310"
        },
        {
          "method": "org.eclipse.jdt.internal.compiler.Compiler.resolve",
          "source": "Compiler.java:574"
        },
        {
          "method": "org.eclipse.jdt.internal.compiler.Compiler.resolve",
          "source": "Compiler.java:633"
        },
        {
          "method": "org.eclipse.jdt.internal.core.CompilationUnitProblemFinder.process",
          "source": "Co mpilationUnitProblemFinder.java:209"
        },
        {
          "method": "org.eclipse.jdt.internal.core.CompilationUnitProblemFinder.process",
          "source": "Co mpilationUnitProblemFinder.java:240"
        },
        {
          "method": "org.eclipse.jdt.internal.core.ReconcileWorkingCopyOperation.executeOperation",
          "source": "ReconcileWorkingCopyOperation.java:62"
        },
        {
          "method": "org.eclipse.jdt.internal.core.JavaModelOperation.execute",
          "source": "JavaModelOpe ration.java:365"
        },
        {
          "method": "org.eclipse.jdt.internal.core.JavaModelOperation.run",
          "source": "JavaModelOperati on.java:704"
        },
        {
          "method": "org.eclipse.jdt.internal.core.JavaElement.runOperation",
          "source": "JavaElement.ja va:535"
        },
        {
          "method": "org.eclipse.jdt.internal.core.WorkingCopy.reconcile",
          "source": "WorkingCopy.java: 524"
        },
        {
          "method": "org.eclipse.jdt.internal.ui.text.java.JavaReconcilingStrategy.reconcile",
          "source": "JavaReconcilingStrategy.java:72"
        },
        {
          "method": "org.eclipse.jdt.internal.ui.text.java.JavaReconcilingStrategy.initialReconcile",
          "source": "JavaReconcilingStrategy.java:126"
        },
        {
          "method": "org.eclipse.jface.text.reconciler.MonoReconciler.initialProcess",
          "source": "MonoR econciler.java:104"
        },
        {
          "method": "org.eclipse.jface.text.reconciler.AbstractReconciler$BackgroundThread.run",
          "source": "AbstractReconciler.java:155"
        }
      ],
      "number": 1,
      "commentIndex": 0,
      "bugId": "38688",
      "duplicateId": "36854",
      "date": "2003-06-10T10:47:10+02:00",
      "product": "JDT",
      "component": "Core",
      "severity": "normal"
    }
  ],
  "groupId": "36854",
  "bugId": "38688",
  "duplicateId": "36854",
  "date": "2003-06-10T10:47:10+02:00",
  "product": "JDT",
  "component": "Core",
  "severity": "normal"
}