{
  "comments": [
    "IllegalArgumentException in CtabFolder is found when launching eclipse in \nJapanese environment. This Exception is also observed under English \nenvironment when display is VGA.\n\nSee the log below:\n\njava.lang.IllegalArgumentException: Argument not valid\n        at org.eclipse.swt.SWT.error(SWT.java:2318)\n        at org.eclipse.swt.SWT.error(SWT.java:2262)\n        at org.eclipse.swt.graphics.GC.drawImage(GC.java:368)\n        at org.eclipse.swt.graphics.GC.drawImage(GC.java:351)\n        at org.eclipse.swt.custom.CTabFolder.scaleImage(CTabFolder.java:1760)\n        at org.eclipse.swt.custom.CTabFolder.updateArrowBar\n(CTabFolder.java:1883)\n        at org.eclipse.swt.custom.CTabFolder.setButtonBounds\n(CTabFolder.java:969)\n        at org.eclipse.swt.custom.CTabFolder.setItemLocation\n(CTabFolder.java:1044)\n        at org.eclipse.swt.custom.CTabFolder.setItemBounds\n(CTabFolder.java:1127)        at org.eclipse.swt.custom.CTabFolder.onResize\n(CTabFolder.java:1308)\n        at org.eclipse.swt.custom.CTabFolder.access$2(CTabFolder.java:1301)\n        at org.eclipse.swt.custom.CTabFolder$1.handleEvent(CTabFolder.java:199)\n        at org.eclipse.swt.widgets.EventTable.sendEvent(EventTable.java:81)\n        at org.eclipse.swt.widgets.Widget.sendEvent(Widget.java:913)\n        at org.eclipse.swt.widgets.Widget.sendEvent(Widget.java:938)\n        at org.eclipse.swt.widgets.Widget.sendEvent(Widget.java:922)\n        at org.eclipse.swt.widgets.Widget.notifyListeners(Widget.java:793)\n        at org.eclipse.swt.custom.CTabFolder.resetTabSize(CTabFolder.java:2147)\n        at org.eclipse.swt.custom.CTabFolder.createItem(CTabFolder.java:386)\n        at org.eclipse.swt.custom.CTabItem.\u003cinit\u003e(CTabItem.java:100)\n        at org.eclipse.ui.internal.PartTabFolder.createPartTab\n(PartTabFolder.java:247)\n        at org.eclipse.ui.internal.PartTabFolder.createControl\n(PartTabFolder.java:224)\n        at org.eclipse.ui.internal.PartSashContainer.createControl\n(PartSashContainer.java:192)\n        at org.eclipse.ui.internal.PerspectivePresentation.activate\n(PerspectivePresentation.java:96)\n        at org.eclipse.ui.internal.Perspective.onActivate(Perspective.java:725)\n        at org.eclipse.ui.internal.WorkbenchPage.onActivate\n(WorkbenchPage.java:1799)\n        at org.eclipse.ui.internal.WorkbenchWindow$7.run\n(WorkbenchWindow.java:1496)\n        at org.eclipse.swt.custom.BusyIndicator.showWhile\n(BusyIndicator.java:69)        at \norg.eclipse.ui.internal.WorkbenchWindow.setActivePage\n(WorkbenchWindow.java:1483)\n        at org.eclipse.ui.internal.WorkbenchWindow.busyOpenPage\n(WorkbenchWindow.java:416)\n        at org.eclipse.ui.internal.WorkbenchWindow$6.run\n(WorkbenchWindow.java:1188)\n        at org.eclipse.swt.custom.BusyIndicator.showWhile\n(BusyIndicator.java:69)        at \norg.eclipse.ui.internal.WorkbenchWindow.openPage(WorkbenchWindow.java:1185)\n        at org.eclipse.ui.internal.Workbench.openFirstTimeWindow\n(Workbench.java:1074)\n        at org.eclipse.ui.internal.Workbench.init(Workbench.java:874)\n        at org.eclipse.ui.internal.Workbench.run(Workbench.java:1373)\n        at org.eclipse.core.internal.boot.InternalBootLoader.run\n(InternalBootLoader.java:845)\n        at org.eclipse.core.boot.BootLoader.run(BootLoader.java:461)\n        at java.lang.reflect.Method.invoke(Native Method)\n        at org.eclipse.core.launcher.Main.basicRun(Main.java:291)\n        at org.eclipse.core.launcher.Main.run(Main.java:747)\n        at org.eclipse.core.launcher.Main.main(Main.java:583)",
    "VI to investigate and advise.",
    "\n\n*** This bug has been marked as a duplicate of 38605 ***"
  ],
  "commentCreationDates": [
    "2003-06-20T12:43:30+02:00",
    "2003-06-26T23:40:10+02:00",
    "2003-08-06T20:46:44+02:00"
  ],
  "traces": [
    {
      "exceptionType": "java.lang.IllegalArgumentException",
      "message": "Argument not valid",
      "elements": [
        {
          "method": "org.eclipse.swt.SWT.error",
          "source": "SWT.java:2318"
        },
        {
          "method": "org.eclipse.swt.SWT.error",
          "source": "SWT.java:2262"
        },
        {
          "method": "org.eclipse.swt.graphics.GC.drawImage",
          "source": "GC.java:368"
        },
        {
          "method": "org.eclipse.swt.graphics.GC.drawImage",
          "source": "GC.java:351"
        },
        {
          "method": "org.eclipse.swt.custom.CTabFolder.scaleImage",
          "source": "CTabFolder.java:1760"
        },
        {
          "method": "org.eclipse.swt.custom.CTabFolder.updateArrowBar",
          "source": "CTabFolder.java:1883"
        },
        {
          "method": "org.eclipse.swt.custom.CTabFolder.setButtonBounds",
          "source": "CTabFolder.java:969"
        },
        {
          "method": "org.eclipse.swt.custom.CTabFolder.setItemLocation",
          "source": "CTabFolder.java:1044"
        },
        {
          "method": "org.eclipse.swt.custom.CTabFolder.setItemBounds",
          "source": "CTabFolder.java:1127"
        },
        {
          "method": "org.eclipse.swt.custom.CTabFolder.onResize",
          "source": "CTabFolder.java:1308"
        },
        {
          "method": "org.eclipse.swt.custom.CTabFolder.access$2",
          "source": "CTabFolder.java:1301"
        },
        {
          "method": "org.eclipse.swt.custom.CTabFolder$1.handleEvent",
          "source": "CTabFolder.java:199"
        },
        {
          "method": "org.eclipse.swt.widgets.EventTable.sendEvent",
          "source": "EventTable.java:81"
        },
        {
          "method": "org.eclipse.swt.widgets.Widget.sendEvent",
          "source": "Widget.java:913"
        },
        {
          "method": "org.eclipse.swt.widgets.Widget.sendEvent",
          "source": "Widget.java:938"
        },
        {
          "method": "org.eclipse.swt.widgets.Widget.sendEvent",
          "source": "Widget.java:922"
        },
        {
          "method": "org.eclipse.swt.widgets.Widget.notifyListeners",
          "source": "Widget.java:793"
        },
        {
          "method": "org.eclipse.swt.custom.CTabFolder.resetTabSize",
          "source": "CTabFolder.java:2147"
        },
        {
          "method": "org.eclipse.swt.custom.CTabFolder.createItem",
          "source": "CTabFolder.java:386"
        },
        {
          "method": "org.eclipse.swt.custom.CTabItem.\u003cinit\u003e",
          "source": "CTabItem.java:100"
        },
        {
          "method": "org.eclipse.ui.internal.PartTabFolder.createPartTab",
          "source": "PartTabFolder.java:247"
        },
        {
          "method": "org.eclipse.ui.internal.PartTabFolder.createControl",
          "source": "PartTabFolder.java:224"
        },
        {
          "method": "org.eclipse.ui.internal.PartSashContainer.createControl",
          "source": "PartSashContainer.java:192"
        },
        {
          "method": "org.eclipse.ui.internal.PerspectivePresentation.activate",
          "source": "PerspectivePresentation.java:96"
        },
        {
          "method": "org.eclipse.ui.internal.Perspective.onActivate",
          "source": "Perspective.java:725"
        },
        {
          "method": "org.eclipse.ui.internal.WorkbenchPage.onActivate",
          "source": "WorkbenchPage.java:1799"
        },
        {
          "method": "org.eclipse.ui.internal.WorkbenchWindow$7.run",
          "source": "WorkbenchWindow.java:1496"
        },
        {
          "method": "org.eclipse.swt.custom.BusyIndicator.showWhile",
          "source": "BusyIndicator.java:69"
        },
        {
          "method": "org.eclipse.ui.internal.WorkbenchWindow.setActivePage",
          "source": "WorkbenchWindow.java:1483"
        },
        {
          "method": "org.eclipse.ui.internal.WorkbenchWindow.busyOpenPage",
          "source": "WorkbenchWindow.java:416"
        },
        {
          "method": "org.eclipse.ui.internal.WorkbenchWindow$6.run",
          "source": "WorkbenchWindow.java:1188"
        },
        {
          "method": "org.eclipse.swt.custom.BusyIndicator.showWhile",
          "source": "BusyIndicator.java:69"
        },
        {
          "method": "org.eclipse.ui.internal.WorkbenchWindow.openPage",
          "source": "WorkbenchWindow.java:1185"
        },
        {
          "method": "org.eclipse.ui.internal.Workbench.openFirstTimeWindow",
          "source": "Workbench.java:1074"
        },
        {
          "method": "org.eclipse.ui.internal.Workbench.init",
          "source": "Workbench.java:874"
        },
        {
          "method": "org.eclipse.ui.internal.Workbench.run",
          "source": "Workbench.java:1373"
        },
        {
          "method": "org.eclipse.core.internal.boot.InternalBootLoader.run",
          "source": "InternalBootLoader.java:845"
        },
        {
          "method": "org.eclipse.core.boot.BootLoader.run",
          "source": "BootLoader.java:461"
        },
        {
          "method": "java.lang.reflect.Method.invoke",
          "source": "Native Method"
        },
        {
          "method": "org.eclipse.core.launcher.Main.basicRun",
          "source": "Main.java:291"
        },
        {
          "method": "org.eclipse.core.launcher.Main.run",
          "source": "Main.java:747"
        },
        {
          "method": "org.eclipse.core.launcher.Main.main",
          "source": "Main.java:583"
        }
      ],
      "number": 0,
      "commentIndex": 0,
      "bugId": "39160",
      "duplicateId": "38605",
      "date": "2003-06-20T12:43:30+02:00",
      "product": "Platform",
      "component": "SWT",
      "severity": "normal"
    }
  ],
  "groupId": "38605",
  "bugId": "39160",
  "duplicateId": "38605",
  "date": "2003-06-20T12:43:30+02:00",
  "product": "Platform",
  "component": "SWT",
  "severity": "normal"
}