{
  "comments": [
    "Open/Close of a project locks the screen for several minutes.  I have just\nupgraded to Debian 3.0, installed from Knoppix, from Suse 8.  This version of\neclipse had been work well under Suse.\n\nThe version of the libraries are all later than those specified in the SWT for\nEclipse version 2.1.\n\nThe following error gets written to the .log.\n\njava.version\u003d1.4.1_03\njava.vendor\u003dSun Microsystems Inc.\nBootLoader constants: OS\u003dlinux, ARCH\u003dx86, WS\u003dgtk, NL\u003den_US\nCommand-line arguments: -os linux -ws gtk -arch x86 -install\nfile:/home/brent/Documents/bin/eclipse/\n!ENTRY org.eclipse.core.resources 4 2 Jun 23, 2003 23:02:27.283\n!MESSAGE Problems occurred when invoking code from plug-in:\n\"org.eclipse.core.resources\".\n!STACK 0\norg.eclipse.swt.SWTException: Invalid thread access\n        at org.eclipse.swt.SWT.error(SWT.java:2350)\n        at org.eclipse.swt.SWT.error(SWT.java:2280)\n        at org.eclipse.swt.widgets.Widget.error(Widget.java:373)\n        at org.eclipse.swt.widgets.Widget.checkWidget(Widget.java:311)\n        at org.eclipse.swt.widgets.Control.isEnabled(Control.java:1929)\n        at org.eclipse.swt.widgets.Display.eventProc(Display.java:608)\n        at\norg.eclipse.swt.internal.gtk.OS.gtk_clipboard_wait_for_contents(Native Method)\n        at org.eclipse.swt.dnd.Clipboard.getContents(Clipboard.java:150)\n        at\norg.eclipse.ui.views.navigator.PasteAction.updateSelection(PasteAction.java:162)\n        at\norg.eclipse.ui.actions.SelectionListenerAction.selectionChanged(SelectionListenerAction.java:208)\n        at\norg.eclipse.ui.views.navigator.RefactorActionGroup.updateActionBars(RefactorActionGroup.java:139)\n        at\norg.eclipse.ui.views.navigator.MainActionGroup.handleResourceChanged(MainActionGroup.java:107)\n        at\norg.eclipse.ui.views.navigator.MainActionGroup$1.resourceChanged(MainActionGroup.java:74)\n        at\norg.eclipse.core.internal.events.NotificationManager$1.run(NotificationManager.java:137)\n        at\norg.eclipse.core.internal.runtime.InternalPlatform.run(InternalPlatform.java:1006)\n        at org.eclipse.core.runtime.Platform.run(Platform.java:413)\n        at\norg.eclipse.core.internal.events.NotificationManager.notify(NotificationManager.java:152)\n        at\norg.eclipse.core.internal.events.NotificationManager.broadcastChanges(NotificationManager.java:67)\n        at\norg.eclipse.core.internal.resources.Workspace.broadcastChanges(Workspace.java:161)\n        at\norg.eclipse.core.internal.resources.Workspace.endOperation(Workspace.java:892)\n        at org.eclipse.core.internal.resources.Workspace.run(Workspace.java:1600)\n        at\norg.eclipse.ui.actions.WorkspaceModifyOperation.run(WorkspaceModifyOperation.java:85)\n        at\norg.eclipse.jface.operation.ModalContext$ModalContextThread.run(ModalContext.java:101)",
    "Looks like we need the new GTK 2.2 multi-display API?  The clipboard is being \naccess from outside the display thread.  VI to check with CC.",
    "\n\n*** This bug has been marked as a duplicate of 33028 ***",
    "The error is in:\n\norg.eclipse.ui.views.navigator.PasteAction.updateSelection\n(PasteAction.java:162)\n\nThis is code is calling Clipboard.getContents from a thread other than the UI \nthread.  GTK runs an OS event loop when the contents of the clipboard are \nrequested.  This can only be done in the UI thread.  As a result, I have added \na check to the Clipboard API to ensure that it is being called from the UI \nthread.\n\nIn \u003eM2, this will result in an invalid thread access exception.  Please update \nyour code to call all Clipboard API from the UI thread.\n",
    "This has been fixed for a while."
  ],
  "commentCreationDates": [
    "2003-06-23T13:40:08+02:00",
    "2003-06-24T22:46:28+02:00",
    "2003-07-15T20:02:01+02:00",
    "2003-07-17T18:27:03+02:00",
    "2004-04-08T19:37:39+02:00"
  ],
  "traces": [
    {
      "exceptionType": "org.eclipse.swt.SWTException",
      "message": "Invalid thread access",
      "elements": [
        {
          "method": "org.eclipse.swt.SWT.error",
          "source": "SWT.java:2350"
        },
        {
          "method": "org.eclipse.swt.SWT.error",
          "source": "SWT.java:2280"
        },
        {
          "method": "org.eclipse.swt.widgets.Widget.error",
          "source": "Widget.java:373"
        },
        {
          "method": "org.eclipse.swt.widgets.Widget.checkWidget",
          "source": "Widget.java:311"
        },
        {
          "method": "org.eclipse.swt.widgets.Control.isEnabled",
          "source": "Control.java:1929"
        },
        {
          "method": "org.eclipse.swt.widgets.Display.eventProc",
          "source": "Display.java:608"
        },
        {
          "method": "org.eclipse.swt.internal.gtk.OS.gtk_clipboard_wait_for_contents",
          "source": "Native Method"
        },
        {
          "method": "org.eclipse.swt.dnd.Clipboard.getContents",
          "source": "Clipboard.java:150"
        },
        {
          "method": "org.eclipse.ui.views.navigator.PasteAction.updateSelection",
          "source": "PasteAction.java:162"
        },
        {
          "method": "org.eclipse.ui.actions.SelectionListenerAction.selectionChanged",
          "source": "SelectionListenerAction.java:208"
        },
        {
          "method": "org.eclipse.ui.views.navigator.RefactorActionGroup.updateActionBars",
          "source": "RefactorActionGroup.java:139"
        },
        {
          "method": "org.eclipse.ui.views.navigator.MainActionGroup.handleResourceChanged",
          "source": "MainActionGroup.java:107"
        },
        {
          "method": "org.eclipse.ui.views.navigator.MainActionGroup$1.resourceChanged",
          "source": "MainActionGroup.java:74"
        },
        {
          "method": "org.eclipse.core.internal.events.NotificationManager$1.run",
          "source": "NotificationManager.java:137"
        },
        {
          "method": "org.eclipse.core.internal.runtime.InternalPlatform.run",
          "source": "InternalPlatform.java:1006"
        },
        {
          "method": "org.eclipse.core.runtime.Platform.run",
          "source": "Platform.java:413"
        },
        {
          "method": "org.eclipse.core.internal.events.NotificationManager.notify",
          "source": "NotificationManager.java:152"
        },
        {
          "method": "org.eclipse.core.internal.events.NotificationManager.broadcastChanges",
          "source": "NotificationManager.java:67"
        },
        {
          "method": "org.eclipse.core.internal.resources.Workspace.broadcastChanges",
          "source": "Workspace.java:161"
        },
        {
          "method": "org.eclipse.core.internal.resources.Workspace.endOperation",
          "source": "Workspace.java:892"
        },
        {
          "method": "org.eclipse.core.internal.resources.Workspace.run",
          "source": "Workspace.java:1600"
        },
        {
          "method": "org.eclipse.ui.actions.WorkspaceModifyOperation.run",
          "source": "WorkspaceModifyOperation.java:85"
        },
        {
          "method": "org.eclipse.jface.operation.ModalContext$ModalContextThread.run",
          "source": "ModalContext.java:101"
        }
      ],
      "number": 0,
      "commentIndex": 0,
      "bugId": "39223",
      "date": "2003-06-23T13:40:08+02:00",
      "product": "Platform",
      "component": "UI",
      "severity": "major"
    }
  ],
  "groupId": "39223",
  "bugId": "39223",
  "date": "2003-06-23T13:40:08+02:00",
  "product": "Platform",
  "component": "UI",
  "severity": "major"
}