{
  "comments": [
    "I have a JFace Application window with the following createContents method:\n   public Control createContents(Composite comp)   {\n        comp.setLayout(new org.eclipse.swt.layout.FillLayout());\n          Composite contentPanel \u003d new Composite(comp, SWT.NONE);\n        imageRegistry \u003d createImageRegistry();\n     //   setBlockOnOpen(false);\n       contentPanel.setLayout(new org.eclipse.swt.layout.FillLayout());\n        TableViewer viewer \u003d new TableViewer(contentPanel, \norg.eclipse.swt.SWT.BORDER);\n        IStructuredContentProvider contentProvider \u003d \ncreateChronologyContentProvider();\n        viewer.setContentProvider(contentProvider);\n      \n        ChronologyLabelProvider labelProvider \u003d new ChronologyLabelProvider();\n        viewer.setLabelProvider(labelProvider);\n        TableColumn col0 \u003d new TableColumn(viewer.getTable(), SWT.NONE);\n        \n        col0.setWidth(200);\n        col0.setText(\"text\");\n        TableColumn col1 \u003d new TableColumn(viewer.getTable(), SWT.NONE);\n        col1.setText(\"type\");\n        col1.setWidth(50);\n        TableColumn col2 \u003d new TableColumn(viewer.getTable(), SWT.NONE);\n        col2.setWidth(100);\n        col2.setText(\"date\");\n       \n        TableColumn col3 \u003d new TableColumn(viewer.getTable(), SWT.NONE);\n        col3.setWidth(100);\n        col3.setText(\"time\");\n        TableColumn col4 \u003d new TableColumn(viewer.getTable(), SWT.NONE);\n        col4.setWidth(50);\n        col4.setText(\"type\");\n         TableColumn col5 \u003d new TableColumn(viewer.getTable(), SWT.NONE);\n        col5.setWidth(100);\n       col5.setText(\"date\");\n        TableColumn col6 \u003d new TableColumn(viewer.getTable(), SWT.NONE);\n        col6.setWidth(100);\n        col6.setText(\"time\");\n        viewer.getTable().setHeaderVisible(true);\n         viewer.setInput(chronology);\n        return contentPanel;\n        \n    }\n\nWhen run, this throws the Exception:\norg.eclipse.core.internal.runtime.AssertionFailedException: assertion failed: \nThe application has not been initialized.\n        at org.eclipse.core.internal.runtime.Assert.isTrue(Assert.java:101)\n        at org.eclipse.core.internal.runtime.InternalPlatform.assertInitialized\n(InternalPlatform.java:180)\n        at org.eclipse.core.internal.runtime.InternalPlatform.getPluginRegistry\n(InternalPlatform.java:399)\n        at org.eclipse.core.internal.runtime.InternalPlatform.getRuntimePlugin\n(InternalPlatform.java:420)\n        at org.eclipse.core.internal.runtime.InternalPlatform.handleException\n(InternalPlatform.java:431)\n        at org.eclipse.core.internal.runtime.InternalPlatform.run\n(InternalPlatform.java:891)\n        at org.eclipse.core.runtime.Platform.run(Platform.java:413)\n        at org.eclipse.jface.viewers.StructuredViewer.updateItem\n(StructuredViewer.java:1271)\n        at org.eclipse.jface.viewers.TableViewer.internalRefresh\n(TableViewer.java:494)\n        at org.eclipse.jface.viewers.TableViewer.internalRefresh\n(TableViewer.java:431)\n        at org.eclipse.jface.viewers.StructuredViewer$7.run\n(StructuredViewer.java:861)\n        at org.eclipse.jface.viewers.StructuredViewer.preservingSelection\n(StructuredViewer.java:801)\n        at org.eclipse.jface.viewers.StructuredViewer.refresh\n(StructuredViewer.java:859)\n        at org.eclipse.jface.viewers.StructuredViewer.refresh\n(StructuredViewer.java:821)\n        at org.eclipse.jface.viewers.TableViewer.inputChanged\n(TableViewer.java:398)\n        at org.eclipse.jface.viewers.ContentViewer.setInput\n(ContentViewer.java:238)\n        at org.eclipse.jface.viewers.StructuredViewer.setInput\n(StructuredViewer.java:991)\n        at com.eas.chron.ChronologyWindow.createContents\n(ChronologyWindow.java:156)\n     \nIs there a dependency of TableViewer on the Eclipse plugin framework?\n\nI\u0027m using jdk1.4.0 on Windows XP",
    "Reassigning bugs in component areas that are changing ownership.",
    "This should work in 3.3 - please reopen if it does not."
  ],
  "commentCreationDates": [
    "2003-06-26T14:52:36+02:00",
    "2006-03-15T16:47:42+01:00",
    "2007-06-19T21:32:35+02:00"
  ],
  "traces": [
    {
      "exceptionType": "org.eclipse.core.internal.runtime.AssertionFailedException",
      "message": "assertion failed:  The application has not been initialized.",
      "elements": [
        {
          "method": "org.eclipse.core.internal.runtime.Assert.isTrue",
          "source": "Assert.java:101"
        },
        {
          "method": "org.eclipse.core.internal.runtime.InternalPlatform.assertInitialized",
          "source": "InternalPlatform.java:180"
        },
        {
          "method": "org.eclipse.core.internal.runtime.InternalPlatform.getPluginRegistry",
          "source": "InternalPlatform.java:399"
        },
        {
          "method": "org.eclipse.core.internal.runtime.InternalPlatform.getRuntimePlugin",
          "source": "InternalPlatform.java:420"
        },
        {
          "method": "org.eclipse.core.internal.runtime.InternalPlatform.handleException",
          "source": "InternalPlatform.java:431"
        },
        {
          "method": "org.eclipse.core.internal.runtime.InternalPlatform.run",
          "source": "InternalPlatform.java:891"
        },
        {
          "method": "org.eclipse.core.runtime.Platform.run",
          "source": "Platform.java:413"
        },
        {
          "method": "org.eclipse.jface.viewers.StructuredViewer.updateItem",
          "source": "StructuredViewer.java:1271"
        },
        {
          "method": "org.eclipse.jface.viewers.TableViewer.internalRefresh",
          "source": "TableViewer.java:494"
        },
        {
          "method": "org.eclipse.jface.viewers.TableViewer.internalRefresh",
          "source": "TableViewer.java:431"
        },
        {
          "method": "org.eclipse.jface.viewers.StructuredViewer$7.run",
          "source": "StructuredViewer.java:861"
        },
        {
          "method": "org.eclipse.jface.viewers.StructuredViewer.preservingSelection",
          "source": "StructuredViewer.java:801"
        },
        {
          "method": "org.eclipse.jface.viewers.StructuredViewer.refresh",
          "source": "StructuredViewer.java:859"
        },
        {
          "method": "org.eclipse.jface.viewers.StructuredViewer.refresh",
          "source": "StructuredViewer.java:821"
        },
        {
          "method": "org.eclipse.jface.viewers.TableViewer.inputChanged",
          "source": "TableViewer.java:398"
        },
        {
          "method": "org.eclipse.jface.viewers.ContentViewer.setInput",
          "source": "ContentViewer.java:238"
        },
        {
          "method": "org.eclipse.jface.viewers.StructuredViewer.setInput",
          "source": "StructuredViewer.java:991"
        },
        {
          "method": "com.eas.chron.ChronologyWindow.createContents",
          "source": "ChronologyWindow.java:156"
        }
      ],
      "number": 0,
      "commentIndex": 0,
      "bugId": "39365",
      "date": "2003-06-26T14:52:36+02:00",
      "product": "Platform",
      "component": "UI",
      "severity": "normal"
    }
  ],
  "groupId": "39365",
  "bugId": "39365",
  "date": "2003-06-26T14:52:36+02:00",
  "product": "Platform",
  "component": "UI",
  "severity": "normal"
}