{
  "comments": [
    "Example source (Processing.aj):\nimport org.aspectj.lang.*;\nimport org.aspectj.lang.reflect.*;\nimport java.lang.reflect.Method;\n//import java.lang.reflect.InvocationTargetException; \u003c- crash with this line \ncommented out\n\npublic aspect Processing {\n    Object around() : \n            call(* *(..)) \u0026\u0026  !within(ImposterProcessing+) {\n        MethodSignature sig \u003d (MethodSignature)thisJoinPoint.getSignature();\n        try {\n            Method meth \u003d ImposterProcessing.class.getMethod(\"dynamicThrow\", \nnew Class[] { Throwable.class });\n                 meth.invoke(this, new Object[] { null });\n            } catch (InvocationTargetException e) {\n                 throw new RuntimeException(\"framework error in throwing test \nexception \", e);\n            } catch (IllegalAccessException e) {\n                 throw new RuntimeException(\"framework error in throwing test \nexception \", e);\n            }\n        return null;\n    }\n}\n\n---\noutput:\nC:\\devel\\test\\entAJtutorial\\test\u003eajc Processing.aj\njava.lang.NullPointerException\n        at \norg.eclipse.jdt.internal.compiler.ast.SingleTypeReference.getTypeBind\ning(SingleTypeReference.java:39)\n        at \norg.aspectj.ajdt.internal.compiler.ast.AccessForInlineVisitor.endVisi\nt(AccessForInlineVisitor.java:131)\n        at org.eclipse.jdt.internal.compiler.ast.SingleTypeReference.traverse\n(Si\nngleTypeReference.java:59)\n        at org.eclipse.jdt.internal.compiler.ast.AllocationExpression.traverse\n(A\nllocationExpression.java:283)\n        at org.eclipse.jdt.internal.compiler.ast.ThrowStatement.traverse\n(ThrowSt\natement.java:76)\n        at org.eclipse.jdt.internal.compiler.ast.Block.traverse(Block.java:147)\n        at org.eclipse.jdt.internal.compiler.ast.TryStatement.traverse\n(TryStatem\nent.java:528)\n        at org.eclipse.jdt.internal.compiler.ast.MethodDeclaration.traverse\n(Meth\nodDeclaration.java:157)\n        at \norg.aspectj.ajdt.internal.compiler.ast.AdviceDeclaration.resolveState\nments(AdviceDeclaration.java:165)\n        at \norg.eclipse.jdt.internal.compiler.ast.AbstractMethodDeclaration.resol\nve(AbstractMethodDeclaration.java:317)\n        at org.eclipse.jdt.internal.compiler.ast.TypeDeclaration.resolve\n(TypeDec\nlaration.java:804)\n        at org.aspectj.ajdt.internal.compiler.ast.AspectDeclaration.resolve\n(Aspe\nctDeclaration.java:73)\n        at org.eclipse.jdt.internal.compiler.ast.TypeDeclaration.resolve\n(TypeDec\nlaration.java:845)\n        at \norg.eclipse.jdt.internal.compiler.ast.CompilationUnitDeclaration.reso\nlve(CompilationUnitDeclaration.java:251)\n        at org.eclipse.jdt.internal.compiler.Compiler.process\n(Compiler.java:538)\n\n        at org.aspectj.ajdt.internal.compiler.AjCompiler.process\n(AjCompiler.java\n:65)\n        at org.eclipse.jdt.internal.compiler.Compiler.compile\n(Compiler.java:338)\n\n        at \norg.aspectj.ajdt.internal.core.builder.AjBuildManager.performCompilat\nion(AjBuildManager.java:372)\n        at org.aspectj.ajdt.internal.core.builder.AjBuildManager.doBuild\n(AjBuild\nManager.java:133)\n        at org.aspectj.ajdt.internal.core.builder.AjBuildManager.batchBuild\n(AjBu\nildManager.java:78)\n        at org.aspectj.ajdt.ajc.AjdtCommand.doCommand(AjdtCommand.java:106)\n        at org.aspectj.ajdt.ajc.AjdtCommand.runCommand(AjdtCommand.java:60)\n        at org.aspectj.tools.ajc.Main.run(Main.java:217)\n        at org.aspectj.tools.ajc.Main.runMain(Main.java:155)\n        at org.aspectj.tools.ajc.Main.main(Main.java:72)\nC:\\devel\\test\\entAJtutorial\\test\\Processing.aj:0 Internal compiler error\njava.lang.NullPointerException\n        at \norg.eclipse.jdt.internal.compiler.ast.SingleTypeReference.getTypeBind\ning(SingleTypeReference.java:39)\n        at \norg.aspectj.ajdt.internal.compiler.ast.AccessForInlineVisitor.endVisi\nt(AccessForInlineVisitor.java:131)\n        at org.eclipse.jdt.internal.compiler.ast.SingleTypeReference.traverse\n(Si\nngleTypeReference.java:59)\n        at org.eclipse.jdt.internal.compiler.ast.AllocationExpression.traverse\n(A\nllocationExpression.java:283)\n        at org.eclipse.jdt.internal.compiler.ast.ThrowStatement.traverse\n(ThrowSt\natement.java:76)\n        at org.eclipse.jdt.internal.compiler.ast.Block.traverse(Block.java:147)\n        at org.eclipse.jdt.internal.compiler.ast.TryStatement.traverse\n(TryStatem\nent.java:528)\n        at org.eclipse.jdt.internal.compiler.ast.MethodDeclaration.traverse\n(Meth\nodDeclaration.java:157)\n        at \norg.aspectj.ajdt.internal.compiler.ast.AdviceDeclaration.resolveState\nments(AdviceDeclaration.java:165)\n        at \norg.eclipse.jdt.internal.compiler.ast.AbstractMethodDeclaration.resol\nve(AbstractMethodDeclaration.java:317)\n        at org.eclipse.jdt.internal.compiler.ast.TypeDeclaration.resolve\n(TypeDec\nlaration.java:804)\n        at org.aspectj.ajdt.internal.compiler.ast.AspectDeclaration.resolve\n(Aspe\nctDeclaration.java:73)\n        at org.eclipse.jdt.internal.compiler.ast.TypeDeclaration.resolve\n(TypeDec\nlaration.java:845)\n        at \norg.eclipse.jdt.internal.compiler.ast.CompilationUnitDeclaration.reso\nlve(CompilationUnitDeclaration.java:251)\n        at org.eclipse.jdt.internal.compiler.Compiler.process\n(Compiler.java:538)\n\n        at org.aspectj.ajdt.internal.compiler.AjCompiler.process\n(AjCompiler.java\n:65)\n        at org.eclipse.jdt.internal.compiler.Compiler.compile\n(Compiler.java:338)\n\n        at \norg.aspectj.ajdt.internal.core.builder.AjBuildManager.performCompilat\nion(AjBuildManager.java:372)\n        at org.aspectj.ajdt.internal.core.builder.AjBuildManager.doBuild\n(AjBuild\nManager.java:133)\n        at org.aspectj.ajdt.internal.core.builder.AjBuildManager.batchBuild\n(AjBu\nildManager.java:78)\n        at org.aspectj.ajdt.ajc.AjdtCommand.doCommand(AjdtCommand.java:106)\n        at org.aspectj.ajdt.ajc.AjdtCommand.runCommand(AjdtCommand.java:60)\n        at org.aspectj.tools.ajc.Main.run(Main.java:217)\n        at org.aspectj.tools.ajc.Main.runMain(Main.java:155)\n        at org.aspectj.tools.ajc.Main.main(Main.java:72)\n\n\n!! no source information available !!\nC:\\devel\\test\\entAJtutorial\\test\\Processing.aj:13 InvocationTargetException \ncann\not be resolved or is not a type\n} catch (InvocationTargetException e) {\n         ^^^^^^^^^^^^^^^^^^^^^^^^^\nABORT\nException thrown from AspectJ 1.1.0\n\nThis might be logged as a bug already -- find current bugs at\n  http://bugs.eclipse.org/bugs/buglist.cgi?product\u003dAspectJ\u0026component\u003dCompiler\n\nBugs for exceptions thrown have titles File:line from the top stack,\ne.g., \"SomeFile.java:243\"\n\nIf you don\u0027t find the exception below in a bug, please add a new bug\nat http://bugs.eclipse.org/bugs/enter_bug.cgi?product\u003dAspectJ\nTo make the bug a priority, please include a test program\nthat can reproduce this exception.\nnull\njava.lang.NullPointerException\n        at \norg.eclipse.jdt.internal.compiler.ast.SingleTypeReference.getTypeBind\ning(SingleTypeReference.java:39)\n        at \norg.aspectj.ajdt.internal.compiler.ast.AccessForInlineVisitor.endVisi\nt(AccessForInlineVisitor.java:131)\n        at org.eclipse.jdt.internal.compiler.ast.SingleTypeReference.traverse\n(Si\nngleTypeReference.java:59)\n        at org.eclipse.jdt.internal.compiler.ast.AllocationExpression.traverse\n(A\nllocationExpression.java:283)\n        at org.eclipse.jdt.internal.compiler.ast.ThrowStatement.traverse\n(ThrowSt\natement.java:76)\n        at org.eclipse.jdt.internal.compiler.ast.Block.traverse(Block.java:147)\n        at org.eclipse.jdt.internal.compiler.ast.TryStatement.traverse\n(TryStatem\nent.java:528)\n        at org.eclipse.jdt.internal.compiler.ast.MethodDeclaration.traverse\n(Meth\nodDeclaration.java:157)\n        at \norg.aspectj.ajdt.internal.compiler.ast.AdviceDeclaration.resolveState\nments(AdviceDeclaration.java:165)\n        at \norg.eclipse.jdt.internal.compiler.ast.AbstractMethodDeclaration.resol\nve(AbstractMethodDeclaration.java:317)\n        at org.eclipse.jdt.internal.compiler.ast.TypeDeclaration.resolve\n(TypeDec\nlaration.java:804)\n        at org.aspectj.ajdt.internal.compiler.ast.AspectDeclaration.resolve\n(Aspe\nctDeclaration.java:73)\n        at org.eclipse.jdt.internal.compiler.ast.TypeDeclaration.resolve\n(TypeDec\nlaration.java:845)\n        at \norg.eclipse.jdt.internal.compiler.ast.CompilationUnitDeclaration.reso\nlve(CompilationUnitDeclaration.java:251)\n        at org.eclipse.jdt.internal.compiler.Compiler.process\n(Compiler.java:538)\n\n        at org.aspectj.ajdt.internal.compiler.AjCompiler.process\n(AjCompiler.java\n:65)\n        at org.eclipse.jdt.internal.compiler.Compiler.compile\n(Compiler.java:338)\n\n        at \norg.aspectj.ajdt.internal.core.builder.AjBuildManager.performCompilat\nion(AjBuildManager.java:372)\n        at org.aspectj.ajdt.internal.core.builder.AjBuildManager.doBuild\n(AjBuild\nManager.java:133)\n        at org.aspectj.ajdt.internal.core.builder.AjBuildManager.batchBuild\n(AjBu\nildManager.java:78)\n        at org.aspectj.ajdt.ajc.AjdtCommand.doCommand(AjdtCommand.java:106)\n        at org.aspectj.ajdt.ajc.AjdtCommand.runCommand(AjdtCommand.java:60)\n        at org.aspectj.tools.ajc.Main.run(Main.java:217)\n        at org.aspectj.tools.ajc.Main.runMain(Main.java:155)\n        at org.aspectj.tools.ajc.Main.main(Main.java:72)\n\n\n1 fail|abort, 2 errors",
    "Raised priority because this awful error message was simple to fix.\nTest in bugs/MissingImport.java, fix in cvs",
    "updated target milestone field to 1.1.1"
  ],
  "commentCreationDates": [
    "2003-06-30T06:23:24+02:00",
    "2003-07-03T01:13:24+02:00",
    "2003-08-28T14:05:50+02:00"
  ],
  "traces": [
    {
      "exceptionType": "java.lang.NullPointerException",
      "elements": [
        {
          "method": "org.eclipse.jdt.internal.compiler.ast.SingleTypeReference.getTypeBinding",
          "source": "SingleTypeReference.java:39"
        },
        {
          "method": "org.aspectj.ajdt.internal.compiler.ast.AccessForInlineVisitor.endVisit",
          "source": "AccessForInlineVisitor.java:131"
        },
        {
          "method": "org.eclipse.jdt.internal.compiler.ast.SingleTypeReference.traverse",
          "source": "Si ngleTypeReference.java:59"
        },
        {
          "method": "org.eclipse.jdt.internal.compiler.ast.AllocationExpression.traverse",
          "source": "A llocationExpression.java:283"
        },
        {
          "method": "org.eclipse.jdt.internal.compiler.ast.ThrowStatement.traverse",
          "source": "ThrowSt atement.java:76"
        },
        {
          "method": "org.eclipse.jdt.internal.compiler.ast.Block.traverse",
          "source": "Block.java:147"
        },
        {
          "method": "org.eclipse.jdt.internal.compiler.ast.TryStatement.traverse",
          "source": "TryStatem ent.java:528"
        },
        {
          "method": "org.eclipse.jdt.internal.compiler.ast.MethodDeclaration.traverse",
          "source": "Meth odDeclaration.java:157"
        },
        {
          "method": "org.aspectj.ajdt.internal.compiler.ast.AdviceDeclaration.resolveStatements",
          "source": "AdviceDeclaration.java:165"
        },
        {
          "method": "org.eclipse.jdt.internal.compiler.ast.AbstractMethodDeclaration.resolve",
          "source": "AbstractMethodDeclaration.java:317"
        },
        {
          "method": "org.eclipse.jdt.internal.compiler.ast.TypeDeclaration.resolve",
          "source": "TypeDec laration.java:804"
        },
        {
          "method": "org.aspectj.ajdt.internal.compiler.ast.AspectDeclaration.resolve",
          "source": "Aspe ctDeclaration.java:73"
        },
        {
          "method": "org.eclipse.jdt.internal.compiler.ast.TypeDeclaration.resolve",
          "source": "TypeDec laration.java:845"
        },
        {
          "method": "org.eclipse.jdt.internal.compiler.ast.CompilationUnitDeclaration.resolve",
          "source": "CompilationUnitDeclaration.java:251"
        },
        {
          "method": "org.eclipse.jdt.internal.compiler.Compiler.process",
          "source": "Compiler.java:538"
        },
        {
          "method": "org.aspectj.ajdt.internal.compiler.AjCompiler.process",
          "source": "AjCompiler.java :65"
        },
        {
          "method": "org.eclipse.jdt.internal.compiler.Compiler.compile",
          "source": "Compiler.java:338"
        },
        {
          "method": "org.aspectj.ajdt.internal.core.builder.AjBuildManager.performCompilation",
          "source": "AjBuildManager.java:372"
        },
        {
          "method": "org.aspectj.ajdt.internal.core.builder.AjBuildManager.doBuild",
          "source": "AjBuild Manager.java:133"
        },
        {
          "method": "org.aspectj.ajdt.internal.core.builder.AjBuildManager.batchBuild",
          "source": "AjBu ildManager.java:78"
        },
        {
          "method": "org.aspectj.ajdt.ajc.AjdtCommand.doCommand",
          "source": "AjdtCommand.java:106"
        },
        {
          "method": "org.aspectj.ajdt.ajc.AjdtCommand.runCommand",
          "source": "AjdtCommand.java:60"
        },
        {
          "method": "org.aspectj.tools.ajc.Main.run",
          "source": "Main.java:217"
        },
        {
          "method": "org.aspectj.tools.ajc.Main.runMain",
          "source": "Main.java:155"
        },
        {
          "method": "org.aspectj.tools.ajc.Main.main",
          "source": "Main.java:72"
        }
      ],
      "number": 0,
      "commentIndex": 0,
      "bugId": "39460",
      "date": "2003-06-30T06:23:24+02:00",
      "product": "AspectJ",
      "component": "Compiler",
      "severity": "normal"
    },
    {
      "exceptionType": "java.lang.NullPointerException",
      "elements": [
        {
          "method": "org.eclipse.jdt.internal.compiler.ast.SingleTypeReference.getTypeBinding",
          "source": "SingleTypeReference.java:39"
        },
        {
          "method": "org.aspectj.ajdt.internal.compiler.ast.AccessForInlineVisitor.endVisit",
          "source": "AccessForInlineVisitor.java:131"
        },
        {
          "method": "org.eclipse.jdt.internal.compiler.ast.SingleTypeReference.traverse",
          "source": "Si ngleTypeReference.java:59"
        },
        {
          "method": "org.eclipse.jdt.internal.compiler.ast.AllocationExpression.traverse",
          "source": "A llocationExpression.java:283"
        },
        {
          "method": "org.eclipse.jdt.internal.compiler.ast.ThrowStatement.traverse",
          "source": "ThrowSt atement.java:76"
        },
        {
          "method": "org.eclipse.jdt.internal.compiler.ast.Block.traverse",
          "source": "Block.java:147"
        },
        {
          "method": "org.eclipse.jdt.internal.compiler.ast.TryStatement.traverse",
          "source": "TryStatem ent.java:528"
        },
        {
          "method": "org.eclipse.jdt.internal.compiler.ast.MethodDeclaration.traverse",
          "source": "Meth odDeclaration.java:157"
        },
        {
          "method": "org.aspectj.ajdt.internal.compiler.ast.AdviceDeclaration.resolveStatements",
          "source": "AdviceDeclaration.java:165"
        },
        {
          "method": "org.eclipse.jdt.internal.compiler.ast.AbstractMethodDeclaration.resolve",
          "source": "AbstractMethodDeclaration.java:317"
        },
        {
          "method": "org.eclipse.jdt.internal.compiler.ast.TypeDeclaration.resolve",
          "source": "TypeDec laration.java:804"
        },
        {
          "method": "org.aspectj.ajdt.internal.compiler.ast.AspectDeclaration.resolve",
          "source": "Aspe ctDeclaration.java:73"
        },
        {
          "method": "org.eclipse.jdt.internal.compiler.ast.TypeDeclaration.resolve",
          "source": "TypeDec laration.java:845"
        },
        {
          "method": "org.eclipse.jdt.internal.compiler.ast.CompilationUnitDeclaration.resolve",
          "source": "CompilationUnitDeclaration.java:251"
        },
        {
          "method": "org.eclipse.jdt.internal.compiler.Compiler.process",
          "source": "Compiler.java:538"
        },
        {
          "method": "org.aspectj.ajdt.internal.compiler.AjCompiler.process",
          "source": "AjCompiler.java :65"
        },
        {
          "method": "org.eclipse.jdt.internal.compiler.Compiler.compile",
          "source": "Compiler.java:338"
        },
        {
          "method": "org.aspectj.ajdt.internal.core.builder.AjBuildManager.performCompilation",
          "source": "AjBuildManager.java:372"
        },
        {
          "method": "org.aspectj.ajdt.internal.core.builder.AjBuildManager.doBuild",
          "source": "AjBuild Manager.java:133"
        },
        {
          "method": "org.aspectj.ajdt.internal.core.builder.AjBuildManager.batchBuild",
          "source": "AjBu ildManager.java:78"
        },
        {
          "method": "org.aspectj.ajdt.ajc.AjdtCommand.doCommand",
          "source": "AjdtCommand.java:106"
        },
        {
          "method": "org.aspectj.ajdt.ajc.AjdtCommand.runCommand",
          "source": "AjdtCommand.java:60"
        },
        {
          "method": "org.aspectj.tools.ajc.Main.run",
          "source": "Main.java:217"
        },
        {
          "method": "org.aspectj.tools.ajc.Main.runMain",
          "source": "Main.java:155"
        },
        {
          "method": "org.aspectj.tools.ajc.Main.main",
          "source": "Main.java:72"
        }
      ],
      "number": 1,
      "commentIndex": 0,
      "bugId": "39460",
      "date": "2003-06-30T06:23:24+02:00",
      "product": "AspectJ",
      "component": "Compiler",
      "severity": "normal"
    },
    {
      "exceptionType": "java.lang.NullPointerException",
      "elements": [
        {
          "method": "org.eclipse.jdt.internal.compiler.ast.SingleTypeReference.getTypeBinding",
          "source": "SingleTypeReference.java:39"
        },
        {
          "method": "org.aspectj.ajdt.internal.compiler.ast.AccessForInlineVisitor.endVisit",
          "source": "AccessForInlineVisitor.java:131"
        },
        {
          "method": "org.eclipse.jdt.internal.compiler.ast.SingleTypeReference.traverse",
          "source": "Si ngleTypeReference.java:59"
        },
        {
          "method": "org.eclipse.jdt.internal.compiler.ast.AllocationExpression.traverse",
          "source": "A llocationExpression.java:283"
        },
        {
          "method": "org.eclipse.jdt.internal.compiler.ast.ThrowStatement.traverse",
          "source": "ThrowSt atement.java:76"
        },
        {
          "method": "org.eclipse.jdt.internal.compiler.ast.Block.traverse",
          "source": "Block.java:147"
        },
        {
          "method": "org.eclipse.jdt.internal.compiler.ast.TryStatement.traverse",
          "source": "TryStatem ent.java:528"
        },
        {
          "method": "org.eclipse.jdt.internal.compiler.ast.MethodDeclaration.traverse",
          "source": "Meth odDeclaration.java:157"
        },
        {
          "method": "org.aspectj.ajdt.internal.compiler.ast.AdviceDeclaration.resolveStatements",
          "source": "AdviceDeclaration.java:165"
        },
        {
          "method": "org.eclipse.jdt.internal.compiler.ast.AbstractMethodDeclaration.resolve",
          "source": "AbstractMethodDeclaration.java:317"
        },
        {
          "method": "org.eclipse.jdt.internal.compiler.ast.TypeDeclaration.resolve",
          "source": "TypeDec laration.java:804"
        },
        {
          "method": "org.aspectj.ajdt.internal.compiler.ast.AspectDeclaration.resolve",
          "source": "Aspe ctDeclaration.java:73"
        },
        {
          "method": "org.eclipse.jdt.internal.compiler.ast.TypeDeclaration.resolve",
          "source": "TypeDec laration.java:845"
        },
        {
          "method": "org.eclipse.jdt.internal.compiler.ast.CompilationUnitDeclaration.resolve",
          "source": "CompilationUnitDeclaration.java:251"
        },
        {
          "method": "org.eclipse.jdt.internal.compiler.Compiler.process",
          "source": "Compiler.java:538"
        },
        {
          "method": "org.aspectj.ajdt.internal.compiler.AjCompiler.process",
          "source": "AjCompiler.java :65"
        },
        {
          "method": "org.eclipse.jdt.internal.compiler.Compiler.compile",
          "source": "Compiler.java:338"
        },
        {
          "method": "org.aspectj.ajdt.internal.core.builder.AjBuildManager.performCompilation",
          "source": "AjBuildManager.java:372"
        },
        {
          "method": "org.aspectj.ajdt.internal.core.builder.AjBuildManager.doBuild",
          "source": "AjBuild Manager.java:133"
        },
        {
          "method": "org.aspectj.ajdt.internal.core.builder.AjBuildManager.batchBuild",
          "source": "AjBu ildManager.java:78"
        },
        {
          "method": "org.aspectj.ajdt.ajc.AjdtCommand.doCommand",
          "source": "AjdtCommand.java:106"
        },
        {
          "method": "org.aspectj.ajdt.ajc.AjdtCommand.runCommand",
          "source": "AjdtCommand.java:60"
        },
        {
          "method": "org.aspectj.tools.ajc.Main.run",
          "source": "Main.java:217"
        },
        {
          "method": "org.aspectj.tools.ajc.Main.runMain",
          "source": "Main.java:155"
        },
        {
          "method": "org.aspectj.tools.ajc.Main.main",
          "source": "Main.java:72"
        }
      ],
      "number": 2,
      "commentIndex": 0,
      "bugId": "39460",
      "date": "2003-06-30T06:23:24+02:00",
      "product": "AspectJ",
      "component": "Compiler",
      "severity": "normal"
    }
  ],
  "groupId": "39460",
  "bugId": "39460",
  "date": "2003-06-30T06:23:24+02:00",
  "product": "AspectJ",
  "component": "Compiler",
  "severity": "normal"
}