{
  "comments": [
    "Using 20030627 WSAD Installable driver on Win2K\n\nThis error doesn\u0027t seem directly related to the task, but in this case\nI was creating the web project for the JSP and Servlet example, when the \nfollowing NPE occurred:\n!ENTRY org.eclipse.jdt.core 4 4 Jul 01, 2003 08:59:51.925\n!MESSAGE Background Indexer Crash Recovery\n!STACK 0\njava.lang.NullPointerException\n        at java.lang.Throwable.\u003cinit\u003e(Throwable.java)\n        at java.lang.Throwable.\u003cinit\u003e(Throwable.java)\n        at java.lang.NullPointerException.\u003cinit\u003e(NullPointerException.java:63)\n        at org.eclipse.jdt.internal.core.index.impl.Util.quickSort(Util.java)\n        at org.eclipse.jdt.internal.core.index.impl.Util.sort(Util.java:292)\n        at org.eclipse.jdt.internal.core.index.impl.InMemoryIndex.getSortedWordE\nntries(InMemoryIndex.java:134)\n        at org.eclipse.jdt.internal.core.index.impl.SimpleIndexInput.open(Simple\nIndexInput.java:118)\n        at org.eclipse.jdt.internal.core.index.impl.MergeFactory.merge(MergeFact\nory.java:78)\n        at org.eclipse.jdt.internal.core.index.impl.Index.merge(Index.java:243)\n        at org.eclipse.jdt.internal.core.index.impl.Index.save(Index.java:348)\n        at org.eclipse.jdt.internal.core.search.indexing.IndexManager.saveIndex(\nIndexManager.java:453)\n        at org.eclipse.jdt.internal.core.search.indexing.AddJarFileToIndex.execu\nte(AddJarFileToIndex.java)\n        at org.eclipse.jdt.internal.core.search.processing.JobManager.run(JobMan\nager.java:360)\n        at java.lang.Thread.run(Thread.java:801)\njava.lang.NullPointerException\n        at java.lang.Throwable.\u003cinit\u003e(Throwable.java)\n        at java.lang.Throwable.\u003cinit\u003e(Throwable.java)\n        at java.lang.NullPointerException.\u003cinit\u003e(NullPointerException.java:63)\n        at org.eclipse.jdt.internal.core.index.impl.Util.quickSort(Util.java)\n        at org.eclipse.jdt.internal.core.index.impl.Util.sort(Util.java:292)\n        at org.eclipse.jdt.internal.core.index.impl.InMemoryIndex.getSortedWordE\nntries(InMemoryIndex.java:134)\n        at org.eclipse.jdt.internal.core.index.impl.SimpleIndexInput.open(Simple\nIndexInput.java:118)\n        at org.eclipse.jdt.internal.core.index.impl.MergeFactory.merge(MergeFact\nory.java:78)\n        at org.eclipse.jdt.internal.core.index.impl.Index.merge(Index.java:243)\n        at org.eclipse.jdt.internal.core.index.impl.Index.save(Index.java:348)\n        at org.eclipse.jdt.internal.core.search.indexing.IndexManager.saveIndex(\nIndexManager.java:453)\n        at org.eclipse.jdt.internal.core.search.indexing.AddJarFileToIndex.execu\nte(AddJarFileToIndex.java)\n        at org.eclipse.jdt.internal.core.search.processing.JobManager.run(JobMan\nager.java:360)\n        at java.lang.Thread.run(Thread.java:801)\n\n\nDoesn\u0027t impact function from working.",
    "\n\n*** This bug has been marked as a duplicate of 40950 ***"
  ],
  "commentCreationDates": [
    "2003-07-02T15:06:07+02:00",
    "2003-08-11T17:17:28+02:00"
  ],
  "traces": [
    {
      "exceptionType": "java.lang.NullPointerException",
      "elements": [
        {
          "method": "java.lang.Throwable.\u003cinit\u003e",
          "source": "Throwable.java"
        },
        {
          "method": "java.lang.Throwable.\u003cinit\u003e",
          "source": "Throwable.java"
        },
        {
          "method": "java.lang.NullPointerException.\u003cinit\u003e",
          "source": "NullPointerException.java:63"
        },
        {
          "method": "org.eclipse.jdt.internal.core.index.impl.Util.quickSort",
          "source": "Util.java"
        },
        {
          "method": "org.eclipse.jdt.internal.core.index.impl.Util.sort",
          "source": "Util.java:292"
        },
        {
          "method": "org.eclipse.jdt.internal.core.index.impl.InMemoryIndex.getSortedWordEntries",
          "source": "InMemoryIndex.java:134"
        },
        {
          "method": "org.eclipse.jdt.internal.core.index.impl.SimpleIndexInput.open",
          "source": "Simple IndexInput.java:118"
        },
        {
          "method": "org.eclipse.jdt.internal.core.index.impl.MergeFactory.merge",
          "source": "MergeFact ory.java:78"
        },
        {
          "method": "org.eclipse.jdt.internal.core.index.impl.Index.merge",
          "source": "Index.java:243"
        },
        {
          "method": "org.eclipse.jdt.internal.core.index.impl.Index.save",
          "source": "Index.java:348"
        },
        {
          "method": "org.eclipse.jdt.internal.core.search.indexing.IndexManager.saveIndex",
          "source": " IndexManager.java:453"
        },
        {
          "method": "org.eclipse.jdt.internal.core.search.indexing.AddJarFileToIndex.execute",
          "source": "AddJarFileToIndex.java"
        },
        {
          "method": "org.eclipse.jdt.internal.core.search.processing.JobManager.run",
          "source": "JobMan ager.java:360"
        },
        {
          "method": "java.lang.Thread.run",
          "source": "Thread.java:801"
        }
      ],
      "number": 0,
      "commentIndex": 0,
      "bugId": "39545",
      "duplicateId": "40950",
      "date": "2003-07-02T15:06:07+02:00",
      "product": "JDT",
      "component": "Core",
      "severity": "normal"
    },
    {
      "exceptionType": "java.lang.NullPointerException",
      "elements": [
        {
          "method": "java.lang.Throwable.\u003cinit\u003e",
          "source": "Throwable.java"
        },
        {
          "method": "java.lang.Throwable.\u003cinit\u003e",
          "source": "Throwable.java"
        },
        {
          "method": "java.lang.NullPointerException.\u003cinit\u003e",
          "source": "NullPointerException.java:63"
        },
        {
          "method": "org.eclipse.jdt.internal.core.index.impl.Util.quickSort",
          "source": "Util.java"
        },
        {
          "method": "org.eclipse.jdt.internal.core.index.impl.Util.sort",
          "source": "Util.java:292"
        },
        {
          "method": "org.eclipse.jdt.internal.core.index.impl.InMemoryIndex.getSortedWordEntries",
          "source": "InMemoryIndex.java:134"
        },
        {
          "method": "org.eclipse.jdt.internal.core.index.impl.SimpleIndexInput.open",
          "source": "Simple IndexInput.java:118"
        },
        {
          "method": "org.eclipse.jdt.internal.core.index.impl.MergeFactory.merge",
          "source": "MergeFact ory.java:78"
        },
        {
          "method": "org.eclipse.jdt.internal.core.index.impl.Index.merge",
          "source": "Index.java:243"
        },
        {
          "method": "org.eclipse.jdt.internal.core.index.impl.Index.save",
          "source": "Index.java:348"
        },
        {
          "method": "org.eclipse.jdt.internal.core.search.indexing.IndexManager.saveIndex",
          "source": " IndexManager.java:453"
        },
        {
          "method": "org.eclipse.jdt.internal.core.search.indexing.AddJarFileToIndex.execute",
          "source": "AddJarFileToIndex.java"
        },
        {
          "method": "org.eclipse.jdt.internal.core.search.processing.JobManager.run",
          "source": "JobMan ager.java:360"
        },
        {
          "method": "java.lang.Thread.run",
          "source": "Thread.java:801"
        }
      ],
      "number": 1,
      "commentIndex": 0,
      "bugId": "39545",
      "duplicateId": "40950",
      "date": "2003-07-02T15:06:07+02:00",
      "product": "JDT",
      "component": "Core",
      "severity": "normal"
    }
  ],
  "groupId": "40950",
  "bugId": "39545",
  "duplicateId": "40950",
  "date": "2003-07-02T15:06:07+02:00",
  "product": "JDT",
  "component": "Core",
  "severity": "normal"
}