{
  "comments": [
    "Hello, \n \nfirst sorry for my bad english. \n \nwhen i will start eclipse i get the following error  \n \ni have the following system: \n \nMandrake Linux 9.1 \nSUN Java 1.4.2 or 1.4.1_03 or 1.4.1\nAMD Athlon \nATI Radeon 9700 Pro with OpenGL enabled \n \nthank you for your help. \n \nmfg Matthias \n \norg.eclipse.swt.SWTException: Unsupported or unrecognized format \n        at org.eclipse.swt.SWT.error(SWT.java:2332) \n        at org.eclipse.swt.SWT.error(SWT.java:2262) \n        at\norg.eclipse.swt.internal.image.FileFormat.load(FileFormat.java:73) \n        at org.eclipse.swt.graphics.ImageLoader.load(ImageLoader.java:124) \n        at org.eclipse.swt.graphics.ImageData.\u003cinit\u003e(ImageData.java:311) \n        at\norg.eclipse.jface.resource.URLImageDescriptor.getImageData(URLImageDe \nscriptor.java:51) \n        at\norg.eclipse.jface.resource.ImageDescriptor.createImage(ImageDescripto \nr.java:118) \n        at\norg.eclipse.jface.resource.ImageDescriptor.createImage(ImageDescripto \nr.java:94) \n        at\norg.eclipse.jface.resource.ImageDescriptor.createImage(ImageDescripto \nr.java:83) \n        at\norg.eclipse.jface.action.ActionContributionItem$ImageCache.getImage(A \nctionContributionItem.java:117) \n        at\norg.eclipse.jface.action.ActionContributionItem.updateImages(ActionCo \nntributionItem.java:719) \n        at\norg.eclipse.jface.action.ActionContributionItem.update(ActionContribu \ntionItem.java:596) \n        at\norg.eclipse.jface.action.ActionContributionItem.fill(ActionContributi \nonItem.java:302) \n        at\norg.eclipse.jface.action.MenuManager.update(MenuManager.java:555) \n        at\norg.eclipse.jface.action.MenuManager.update(MenuManager.java:456) \n        at org.eclipse.jface.action.MenuManager.fill(MenuManager.java:209) \n        at\norg.eclipse.jface.action.MenuManager.update(MenuManager.java:555) \n        at\norg.eclipse.jface.action.MenuManager.update(MenuManager.java:456) \n        at\norg.eclipse.jface.action.MenuManager.createMenuBar(MenuManager.java:1     \n                                                    \n46) \n        at\norg.eclipse.jface.window.ApplicationWindow.configureShell(Application     \n                                                    \nWindow.java:244) \n        at\norg.eclipse.ui.internal.WorkbenchWindow.configureShell(WorkbenchWindo     \n                                                    \nw.java:578) \n        at org.eclipse.jface.window.Window.createShell(Window.java:350) \n        at org.eclipse.jface.window.Window.create(Window.java:301) \n        at\norg.eclipse.ui.internal.Workbench.openFirstTimeWindow(Workbench.java:     \n                                                    \n1068) \n        at org.eclipse.ui.internal.Workbench.init(Workbench.java:874) \n        at org.eclipse.ui.internal.Workbench.run(Workbench.java:1373) \n        at\norg.eclipse.core.internal.boot.InternalBootLoader.run(InternalBootLoa     \n                                                    \nder.java:858) \n        at org.eclipse.core.boot.BootLoader.run(BootLoader.java:461) \n        at sun.reflect.NativeMethodAccessorImpl.invoke0(Native Method) \n        at\nsun.reflect.NativeMethodAccessorImpl.invoke(NativeMethodAccessorImpl.     \n                                                    \njava:39) \n        at\nsun.reflect.DelegatingMethodAccessorImpl.invoke(DelegatingMethodAcces     \n                                                    \nsorImpl.java:25) \n        at java.lang.reflect.Method.invoke(Method.java:324) \n        at org.eclipse.core.launcher.Main.basicRun(Main.java:291) \n        at org.eclipse.core.launcher.Main.run(Main.java:747) \n        at org.eclipse.core.launcher.Main.main(Main.java:583)",
    "Try to download eclipse again. Let us know if it helps. thanks\n\n",
    "Created an attachment (id\u003d5366)\nThis is the Logfile from 2.1 Version on Java 1.4.1_03\n",
    "Created an attachment (id\u003d5367)\nThis is the Logfile from 2.1.1 Version on Java 1.4.1_03\n",
    "Hi \n \ni have downloaded eclipse again, version 2.1.1; version 2.1; Nightly Build N20030707; \n \nbut i have the same error, \n \ni have added the logfiles  \n \nif you need any more information then tell me. ",
    "This is a known problem with the way you have installed Eclipse.  Please \nfollow the instructions in this FAQ entry.\n\nhttp://dev.eclipse.org/viewcvs/index.cgi/%7Echeckout%7E/platform-swt-\nhome/faq.html#konquerorUnzip\n\nIf the FAQ does not solve your problem, please reopen this bug report.",
    "This question comes up every day in the newsgroup, the problem should be noted\non the download-page very clearly."
  ],
  "commentCreationDates": [
    "2003-07-07T09:54:13+02:00",
    "2003-07-07T17:45:31+02:00",
    "2003-07-07T19:39:51+02:00",
    "2003-07-07T19:41:31+02:00",
    "2003-07-07T19:45:19+02:00",
    "2003-07-10T17:08:37+02:00",
    "2003-08-05T01:12:35+02:00"
  ],
  "traces": [
    {
      "exceptionType": "org.eclipse.swt.SWTException",
      "message": "Unsupported or unrecognized form",
      "elements": [
        {
          "method": "atorg.eclipse.swt.SWT.error",
          "source": "SWT.java:2332"
        },
        {
          "method": "org.eclipse.swt.SWT.error",
          "source": "SWT.java:2262"
        },
        {
          "method": "org.eclipse.swt.internal.image.FileFormat.load",
          "source": "FileFormat.java:73"
        },
        {
          "method": "org.eclipse.swt.graphics.ImageLoader.load",
          "source": "ImageLoader.java:124"
        },
        {
          "method": "org.eclipse.swt.graphics.ImageData.\u003cinit\u003e",
          "source": "ImageData.java:311"
        },
        {
          "method": "org.eclipse.jface.resource.URLImageDescriptor.getImageData",
          "source": "URLImageDe  scriptor.java:51"
        },
        {
          "method": "org.eclipse.jface.resource.ImageDescriptor.createImage",
          "source": "ImageDescripto  r.java:118"
        },
        {
          "method": "org.eclipse.jface.resource.ImageDescriptor.createImage",
          "source": "ImageDescripto  r.java:94"
        },
        {
          "method": "org.eclipse.jface.resource.ImageDescriptor.createImage",
          "source": "ImageDescripto  r.java:83"
        },
        {
          "method": "org.eclipse.jface.action.ActionContributionItem$ImageCache.getImage",
          "source": "A  ctionContributionItem.java:117"
        },
        {
          "method": "org.eclipse.jface.action.ActionContributionItem.updateImages",
          "source": "ActionCo  ntributionItem.java:719"
        },
        {
          "method": "org.eclipse.jface.action.ActionContributionItem.update",
          "source": "ActionContribu  tionItem.java:596"
        },
        {
          "method": "org.eclipse.jface.action.ActionContributionItem.fill",
          "source": "ActionContributi  onItem.java:302"
        },
        {
          "method": "org.eclipse.jface.action.MenuManager.update",
          "source": "MenuManager.java:555"
        },
        {
          "method": "org.eclipse.jface.action.MenuManager.update",
          "source": "MenuManager.java:456"
        },
        {
          "method": "org.eclipse.jface.action.MenuManager.fill",
          "source": "MenuManager.java:209"
        },
        {
          "method": "org.eclipse.jface.action.MenuManager.update",
          "source": "MenuManager.java:555"
        },
        {
          "method": "org.eclipse.jface.action.MenuManager.update",
          "source": "MenuManager.java:456"
        },
        {
          "method": "org.eclipse.jface.action.MenuManager.createMenuBar",
          "source": "MenuManager.java:1                                                           46"
        },
        {
          "method": "org.eclipse.jface.window.ApplicationWindow.configureShell",
          "source": "Application                                                           Window.java:244"
        },
        {
          "method": "org.eclipse.ui.internal.WorkbenchWindow.configureShell",
          "source": "WorkbenchWindo                                                           w.java:578"
        },
        {
          "method": "org.eclipse.jface.window.Window.createShell",
          "source": "Window.java:350"
        },
        {
          "method": "org.eclipse.jface.window.Window.create",
          "source": "Window.java:301"
        },
        {
          "method": "org.eclipse.ui.internal.Workbench.openFirstTimeWindow",
          "source": "Workbench.java:                                                           1068"
        },
        {
          "method": "org.eclipse.ui.internal.Workbench.init",
          "source": "Workbench.java:874"
        },
        {
          "method": "org.eclipse.ui.internal.Workbench.run",
          "source": "Workbench.java:1373"
        },
        {
          "method": "org.eclipse.core.internal.boot.InternalBootLoader.run",
          "source": "InternalBootLoa                                                           der.java:858"
        },
        {
          "method": "org.eclipse.core.boot.BootLoader.run",
          "source": "BootLoader.java:461"
        },
        {
          "method": "sun.reflect.NativeMethodAccessorImpl.invoke0",
          "source": "Native Method"
        },
        {
          "method": "sun.reflect.NativeMethodAccessorImpl.invoke",
          "source": "NativeMethodAccessorImpl.                                                           java:39"
        },
        {
          "method": "sun.reflect.DelegatingMethodAccessorImpl.invoke",
          "source": "DelegatingMethodAcces                                                           sorImpl.java:25"
        },
        {
          "method": "java.lang.reflect.Method.invoke",
          "source": "Method.java:324"
        },
        {
          "method": "org.eclipse.core.launcher.Main.basicRun",
          "source": "Main.java:291"
        },
        {
          "method": "org.eclipse.core.launcher.Main.run",
          "source": "Main.java:747"
        },
        {
          "method": "org.eclipse.core.launcher.Main.main",
          "source": "Main.java:583"
        }
      ],
      "number": 0,
      "commentIndex": 0,
      "bugId": "39670",
      "date": "2003-07-07T09:54:13+02:00",
      "product": "Platform",
      "component": "SWT",
      "severity": "critical"
    }
  ],
  "groupId": "39670",
  "bugId": "39670",
  "date": "2003-07-07T09:54:13+02:00",
  "product": "Platform",
  "component": "SWT",
  "severity": "critical"
}