{
  "comments": [
    "When using the team-\u003ecompare with revision option on a file I get the list of\ncvs revisions. Double clicking on a revision gives the \"an error has occured\"\ndialog box and the following stacktrace in the .log:\n\njava.util.ConcurrentModificationException\n        at java.util.AbstractList$Itr.checkForComodification(AbstractList.java:448)\n        at java.util.AbstractList$Itr.next(AbstractList.java:419)\n        at\norg.eclipse.ui.internal.contexts.ContextActivationService.fireContextActivationServiceChanged(Unknown\nSource)\n        at\norg.eclipse.ui.internal.contexts.ContextActivationService.activateContext(Unknown\nSource)\n        at org.eclipse.ui.internal.KeyBindingService.setScopes(Unknown Source)\n        at org.eclipse.ui.internal.PartSite.getKeyBindingService(Unknown Source)\n        at\norg.eclipse.compare.contentmergeviewer.ContentMergeViewer.buildControl(Unknown\nSource)\n        at org.eclipse.compare.contentmergeviewer.TextMergeViewer.\u003cinit\u003e(Unknown\nSource)\n        at org.eclipse.compare.contentmergeviewer.TextMergeViewer.\u003cinit\u003e(Unknown\nSource)\n        at\norg.eclipse.compare.internal.TextMergeViewerCreator.createViewer(Unknown Source)\n        at org.eclipse.compare.internal.ViewerDescriptor.createViewer(Unknown\nSource)\n        at\norg.eclipse.compare.internal.CompareUIPlugin.findContentViewer(Unknown Source)\n        at org.eclipse.compare.CompareEditorInput.findContentViewer(Unknown Source)\n        at org.eclipse.compare.CompareEditorInput$5.getViewer(Unknown Source)\n        at org.eclipse.compare.CompareViewerSwitchingPane.setInput(Unknown Source)\n        at org.eclipse.compare.CompareEditorInput$11.run(Unknown Source)\n        at org.eclipse.swt.custom.BusyIndicator.showWhile(BusyIndicator.java:84)\n        at org.eclipse.compare.CompareEditorInput.feed1(Unknown Source)\n        at org.eclipse.compare.CompareEditorInput.access$1(Unknown Source)\n        at org.eclipse.compare.CompareEditorInput$6.open(Unknown Source)\n        at org.eclipse.compare.CompareViewerSwitchingPane$1.open(Unknown Source)\n        at org.eclipse.jface.viewers.StructuredViewer$2.run(Unknown Source)\n        at org.eclipse.core.internal.runtime.InternalPlatform.run(Unknown Source)\n        at org.eclipse.core.runtime.Platform.run(Unknown Source)\n        at org.eclipse.jface.viewers.StructuredViewer.fireOpen(Unknown Source)\n        at org.eclipse.jface.viewers.StructuredViewer.handleOpen(Unknown Source)\n        at org.eclipse.jface.viewers.StructuredViewer$6.handleOpen(Unknown Source)\n        at org.eclipse.jface.util.OpenStrategy.fireOpenEvent(Unknown Source)\n        at org.eclipse.jface.util.OpenStrategy.access$2(Unknown Source)\n        at org.eclipse.jface.util.OpenStrategy$1.handleEvent(Unknown Source)\n        at org.eclipse.swt.widgets.EventTable.sendEvent(EventTable.java:82)\n        at org.eclipse.swt.widgets.Widget.sendEvent(Widget.java:943)\n        at org.eclipse.swt.widgets.Display.runDeferredEvents(Display.java:1767)\n        at org.eclipse.swt.widgets.Display.readAndDispatch(Display.java:1569)\n        at org.eclipse.ui.internal.Workbench.runEventLoop(Unknown Source)\n        at org.eclipse.ui.internal.Workbench.run(Unknown Source)\n        at org.eclipse.core.internal.boot.InternalBootLoader.run(Unknown Source)\n        at org.eclipse.core.boot.BootLoader.run(Unknown Source)\n        at sun.reflect.NativeMethodAccessorImpl.invoke0(Native Method)\n        at\nsun.reflect.NativeMethodAccessorImpl.invoke(NativeMethodAccessorImpl.java:39)\n        at\nsun.reflect.DelegatingMethodAccessorImpl.invoke(DelegatingMethodAccessorImpl.java:25)\n        at java.lang.reflect.Method.invoke(Method.java:324)\n        at org.eclipse.core.launcher.Main.basicRun(Unknown Source)\n        at org.eclipse.core.launcher.Main.run(Unknown Source)\n        at org.eclipse.core.launcher.Main.main(Unknown Source)",
    "Using build id 200307150800",
    "\n\n*** This bug has been marked as a duplicate of 40171 ***"
  ],
  "commentCreationDates": [
    "2003-07-16T16:40:14+02:00",
    "2003-07-16T16:41:01+02:00",
    "2003-07-16T17:29:10+02:00"
  ],
  "traces": [
    {
      "exceptionType": "java.util.ConcurrentModificationException",
      "elements": [
        {
          "method": "java.util.AbstractList$Itr.checkForComodification",
          "source": "AbstractList.java:448"
        },
        {
          "method": "java.util.AbstractList$Itr.next",
          "source": "AbstractList.java:419"
        },
        {
          "method": "org.eclipse.ui.internal.contexts.ContextActivationService.fireContextActivationServiceChanged",
          "source": "Unknown Source"
        },
        {
          "method": "org.eclipse.ui.internal.contexts.ContextActivationService.activateContext",
          "source": "Unknown Source"
        },
        {
          "method": "org.eclipse.ui.internal.KeyBindingService.setScopes",
          "source": "Unknown Source"
        },
        {
          "method": "org.eclipse.ui.internal.PartSite.getKeyBindingService",
          "source": "Unknown Source"
        },
        {
          "method": "org.eclipse.compare.contentmergeviewer.ContentMergeViewer.buildControl",
          "source": "Unknown Source"
        },
        {
          "method": "org.eclipse.compare.contentmergeviewer.TextMergeViewer.\u003cinit\u003e",
          "source": "Unknown Source"
        },
        {
          "method": "org.eclipse.compare.contentmergeviewer.TextMergeViewer.\u003cinit\u003e",
          "source": "Unknown Source"
        },
        {
          "method": "org.eclipse.compare.internal.TextMergeViewerCreator.createViewer",
          "source": "Unknown Source"
        },
        {
          "method": "org.eclipse.compare.internal.ViewerDescriptor.createViewer",
          "source": "Unknown Source"
        },
        {
          "method": "org.eclipse.compare.internal.CompareUIPlugin.findContentViewer",
          "source": "Unknown Source"
        },
        {
          "method": "org.eclipse.compare.CompareEditorInput.findContentViewer",
          "source": "Unknown Source"
        },
        {
          "method": "org.eclipse.compare.CompareEditorInput$5.getViewer",
          "source": "Unknown Source"
        },
        {
          "method": "org.eclipse.compare.CompareViewerSwitchingPane.setInput",
          "source": "Unknown Source"
        },
        {
          "method": "org.eclipse.compare.CompareEditorInput$11.run",
          "source": "Unknown Source"
        },
        {
          "method": "org.eclipse.swt.custom.BusyIndicator.showWhile",
          "source": "BusyIndicator.java:84"
        },
        {
          "method": "org.eclipse.compare.CompareEditorInput.feed1",
          "source": "Unknown Source"
        },
        {
          "method": "org.eclipse.compare.CompareEditorInput.access$1",
          "source": "Unknown Source"
        },
        {
          "method": "org.eclipse.compare.CompareEditorInput$6.open",
          "source": "Unknown Source"
        },
        {
          "method": "org.eclipse.compare.CompareViewerSwitchingPane$1.open",
          "source": "Unknown Source"
        },
        {
          "method": "org.eclipse.jface.viewers.StructuredViewer$2.run",
          "source": "Unknown Source"
        },
        {
          "method": "org.eclipse.core.internal.runtime.InternalPlatform.run",
          "source": "Unknown Source"
        },
        {
          "method": "org.eclipse.core.runtime.Platform.run",
          "source": "Unknown Source"
        },
        {
          "method": "org.eclipse.jface.viewers.StructuredViewer.fireOpen",
          "source": "Unknown Source"
        },
        {
          "method": "org.eclipse.jface.viewers.StructuredViewer.handleOpen",
          "source": "Unknown Source"
        },
        {
          "method": "org.eclipse.jface.viewers.StructuredViewer$6.handleOpen",
          "source": "Unknown Source"
        },
        {
          "method": "org.eclipse.jface.util.OpenStrategy.fireOpenEvent",
          "source": "Unknown Source"
        },
        {
          "method": "org.eclipse.jface.util.OpenStrategy.access$2",
          "source": "Unknown Source"
        },
        {
          "method": "org.eclipse.jface.util.OpenStrategy$1.handleEvent",
          "source": "Unknown Source"
        },
        {
          "method": "org.eclipse.swt.widgets.EventTable.sendEvent",
          "source": "EventTable.java:82"
        },
        {
          "method": "org.eclipse.swt.widgets.Widget.sendEvent",
          "source": "Widget.java:943"
        },
        {
          "method": "org.eclipse.swt.widgets.Display.runDeferredEvents",
          "source": "Display.java:1767"
        },
        {
          "method": "org.eclipse.swt.widgets.Display.readAndDispatch",
          "source": "Display.java:1569"
        },
        {
          "method": "org.eclipse.ui.internal.Workbench.runEventLoop",
          "source": "Unknown Source"
        },
        {
          "method": "org.eclipse.ui.internal.Workbench.run",
          "source": "Unknown Source"
        },
        {
          "method": "org.eclipse.core.internal.boot.InternalBootLoader.run",
          "source": "Unknown Source"
        },
        {
          "method": "org.eclipse.core.boot.BootLoader.run",
          "source": "Unknown Source"
        },
        {
          "method": "sun.reflect.NativeMethodAccessorImpl.invoke0",
          "source": "Native Method"
        },
        {
          "method": "sun.reflect.NativeMethodAccessorImpl.invoke",
          "source": "NativeMethodAccessorImpl.java:39"
        },
        {
          "method": "sun.reflect.DelegatingMethodAccessorImpl.invoke",
          "source": "DelegatingMethodAccessorImpl.java:25"
        },
        {
          "method": "java.lang.reflect.Method.invoke",
          "source": "Method.java:324"
        },
        {
          "method": "org.eclipse.core.launcher.Main.basicRun",
          "source": "Unknown Source"
        },
        {
          "method": "org.eclipse.core.launcher.Main.run",
          "source": "Unknown Source"
        },
        {
          "method": "org.eclipse.core.launcher.Main.main",
          "source": "Unknown Source"
        }
      ],
      "number": 0,
      "commentIndex": 0,
      "bugId": "40222",
      "duplicateId": "40171",
      "date": "2003-07-16T16:40:14+02:00",
      "product": "Platform",
      "component": "Team",
      "severity": "normal"
    }
  ],
  "groupId": "40171",
  "bugId": "40222",
  "duplicateId": "40171",
  "date": "2003-07-16T16:40:14+02:00",
  "product": "Platform",
  "component": "Team",
  "severity": "normal"
}