{
  "comments": [
    "i20030716\n\nGot a NPE opening a compare editor from the Synchronize view. It happens\neventually, but I couldn\u0027t find reproducible steps.\n\n!ENTRY org.eclipse.jface 4 2 Jul 16, 2003 12:02:58.125\n!MESSAGE Problems occurred when invoking code from plug-in: \"org.eclipse.jface\".\n\n!STACK 0\njava.lang.NullPointerException\n        at java.lang.Throwable.\u003cinit\u003e(Throwable.java)\n        at java.lang.Throwable.\u003cinit\u003e(Throwable.java)\n        at java.lang.NullPointerException.\u003cinit\u003e(NullPointerException.java:63)\n        at org.eclipse.team.internal.ui.sync.compare.SyncInfoCompareInput.equalD\niffNodes(Unknown Source)\n        at org.eclipse.team.internal.ui.sync.compare.SyncInfoCompareInput.equals\n(Unknown Source)\n        at org.eclipse.ui.internal.EditorManager.findEditor(Unknown Source)\n        at org.eclipse.ui.internal.WorkbenchPage.findEditor(Unknown Source)\n        at org.eclipse.team.internal.ui.sync.actions.OpenInCompareAction.reuseCo\nmpareEditor(Unknown Source)\n        at org.eclipse.team.internal.ui.sync.actions.OpenInCompareAction.openEdi\ntor(Unknown Source)\n        at org.eclipse.team.internal.ui.sync.actions.OpenInCompareAction.run(Unk\nnown Source)\n        at org.eclipse.team.internal.ui.sync.actions.SyncViewerActions.open(Unkn\nown Source)\n        at org.eclipse.team.internal.ui.sync.views.SyncViewer.handleOpen(Unknown\n Source)\n        at org.eclipse.team.internal.ui.sync.views.SyncViewer$6.open(Unknown Sou\nrce)\n        at org.eclipse.jface.viewers.StructuredViewer$2.run(Unknown Source)\n        at org.eclipse.core.internal.runtime.InternalPlatform.run(Unknown Source\n)\n        at org.eclipse.core.runtime.Platform.run(Unknown Source)\n        at org.eclipse.jface.viewers.StructuredViewer.fireOpen(Unknown Source)\n        at org.eclipse.jface.viewers.StructuredViewer.handleOpen(Unknown Source)\n\n        at org.eclipse.jface.viewers.StructuredViewer$6.handleOpen(Unknown Sourc\ne)\n        at org.eclipse.jface.util.OpenStrategy.fireOpenEvent(Unknown Source)\n        at org.eclipse.jface.util.OpenStrategy.access$2(Unknown Source)\n        at org.eclipse.jface.util.OpenStrategy$1.handleEvent(Unknown Source)\n        at org.eclipse.swt.widgets.EventTable.sendEvent(EventTable.java)\n        at org.eclipse.swt.widgets.Widget.sendEvent(Widget.java)\n        at org.eclipse.swt.widgets.Display.runDeferredEvents(Display.java)\n        at org.eclipse.swt.widgets.Display.readAndDispatch(Display.java)\n        at org.eclipse.ui.internal.Workbench.runEventLoop(Unknown Source)\n        at org.eclipse.ui.internal.Workbench.run(Unknown Source)\n        at org.eclipse.core.internal.boot.InternalBootLoader.run(Unknown Source)\n\n        at org.eclipse.core.boot.BootLoader.run(Unknown Source)\n        at java.lang.reflect.AccessibleObject.invokeL(AccessibleObject.java:207)\n\n        at java.lang.reflect.Method.invoke(Method.java:271)\n        at org.eclipse.core.launcher.Main.basicRun(Unknown Source)\n        at org.eclipse.core.launcher.Main.run(Unknown Source)\n        at org.eclipse.core.launcher.Main.main(Unknown Source)",
    "There seems to ba a case where a compare edtiro doesn\u0027t have an input. I\u0027ve seen\nbut is not easily reproduceable. ",
    "This is fixed."
  ],
  "commentCreationDates": [
    "2003-07-16T18:19:54+02:00",
    "2003-07-23T19:38:52+02:00",
    "2003-08-05T16:19:53+02:00"
  ],
  "traces": [
    {
      "exceptionType": "java.lang.NullPointerException",
      "elements": [
        {
          "method": "java.lang.Throwable.\u003cinit\u003e",
          "source": "Throwable.java"
        },
        {
          "method": "java.lang.Throwable.\u003cinit\u003e",
          "source": "Throwable.java"
        },
        {
          "method": "java.lang.NullPointerException.\u003cinit\u003e",
          "source": "NullPointerException.java:63"
        },
        {
          "method": "org.eclipse.team.internal.ui.sync.compare.SyncInfoCompareInput.equalDiffNodes",
          "source": "Unknown Source"
        },
        {
          "method": "org.eclipse.team.internal.ui.sync.compare.SyncInfoCompareInput.equals",
          "source": "Unknown Source"
        },
        {
          "method": "org.eclipse.ui.internal.EditorManager.findEditor",
          "source": "Unknown Source"
        },
        {
          "method": "org.eclipse.ui.internal.WorkbenchPage.findEditor",
          "source": "Unknown Source"
        },
        {
          "method": "org.eclipse.team.internal.ui.sync.actions.OpenInCompareAction.reuseCompareEditor",
          "source": "Unknown Source"
        },
        {
          "method": "org.eclipse.team.internal.ui.sync.actions.OpenInCompareAction.openEditor",
          "source": "Unknown Source"
        },
        {
          "method": "org.eclipse.team.internal.ui.sync.actions.OpenInCompareAction.run",
          "source": "Unk nown Source"
        },
        {
          "method": "org.eclipse.team.internal.ui.sync.actions.SyncViewerActions.open",
          "source": "Unkn own Source"
        },
        {
          "method": "org.eclipse.team.internal.ui.sync.views.SyncViewer.handleOpen",
          "source": "Unknown  Source"
        },
        {
          "method": "org.eclipse.team.internal.ui.sync.views.SyncViewer$6.open",
          "source": "Unknown Sou rce"
        },
        {
          "method": "org.eclipse.jface.viewers.StructuredViewer$2.run",
          "source": "Unknown Source"
        },
        {
          "method": "org.eclipse.core.internal.runtime.InternalPlatform.run",
          "source": "Unknown Source "
        },
        {
          "method": "org.eclipse.core.runtime.Platform.run",
          "source": "Unknown Source"
        },
        {
          "method": "org.eclipse.jface.viewers.StructuredViewer.fireOpen",
          "source": "Unknown Source"
        },
        {
          "method": "org.eclipse.jface.viewers.StructuredViewer.handleOpen",
          "source": "Unknown Source"
        },
        {
          "method": "org.eclipse.jface.viewers.StructuredViewer$6.handleOpen",
          "source": "Unknown Sourc e"
        },
        {
          "method": "org.eclipse.jface.util.OpenStrategy.fireOpenEvent",
          "source": "Unknown Source"
        },
        {
          "method": "org.eclipse.jface.util.OpenStrategy.access$2",
          "source": "Unknown Source"
        },
        {
          "method": "org.eclipse.jface.util.OpenStrategy$1.handleEvent",
          "source": "Unknown Source"
        },
        {
          "method": "org.eclipse.swt.widgets.EventTable.sendEvent",
          "source": "EventTable.java"
        },
        {
          "method": "org.eclipse.swt.widgets.Widget.sendEvent",
          "source": "Widget.java"
        },
        {
          "method": "org.eclipse.swt.widgets.Display.runDeferredEvents",
          "source": "Display.java"
        },
        {
          "method": "org.eclipse.swt.widgets.Display.readAndDispatch",
          "source": "Display.java"
        },
        {
          "method": "org.eclipse.ui.internal.Workbench.runEventLoop",
          "source": "Unknown Source"
        },
        {
          "method": "org.eclipse.ui.internal.Workbench.run",
          "source": "Unknown Source"
        },
        {
          "method": "org.eclipse.core.internal.boot.InternalBootLoader.run",
          "source": "Unknown Source"
        },
        {
          "method": "org.eclipse.core.boot.BootLoader.run",
          "source": "Unknown Source"
        },
        {
          "method": "java.lang.reflect.AccessibleObject.invokeL",
          "source": "AccessibleObject.java:207"
        },
        {
          "method": "java.lang.reflect.Method.invoke",
          "source": "Method.java:271"
        },
        {
          "method": "org.eclipse.core.launcher.Main.basicRun",
          "source": "Unknown Source"
        },
        {
          "method": "org.eclipse.core.launcher.Main.run",
          "source": "Unknown Source"
        },
        {
          "method": "org.eclipse.core.launcher.Main.main",
          "source": "Unknown Source"
        }
      ],
      "number": 0,
      "commentIndex": 0,
      "bugId": "40237",
      "date": "2003-07-16T18:19:54+02:00",
      "product": "Platform",
      "component": "Team",
      "severity": "normal"
    }
  ],
  "groupId": "40237",
  "bugId": "40237",
  "date": "2003-07-16T18:19:54+02:00",
  "product": "Platform",
  "component": "Team",
  "severity": "normal"
}