{
  "comments": [
    "Build 20030716\n\nWhile synchronizing a project, an error dialog poped up indicating that an \ninternal error occured and the following NPE was in the log. The sync view was \nempty after that (not sure if it was because there was no incoming changes or \nbecause of the NPE)\n\n!ENTRY org.eclipse.ui.workbench 4 2 Jul 16, 2003 17:25:40.734\n!MESSAGE Problems occurred when invoking code from plug-\nin: \"org.eclipse.ui.workbench\".\n!STACK 0\njava.lang.NullPointerException\n        at \norg.eclipse.team.internal.ui.sync.views.CompressedFolderContentProvider.getModel\nObject(Unknown Source)\n        at \norg.eclipse.team.internal.ui.sync.views.SyncTreeViewer.handleLabelProviderChange\nd(Unknown Source)\n        at org.eclipse.jface.viewers.ContentViewer$1.labelProviderChanged\n(Unknown Source)\n        at org.eclipse.ui.internal.decorators.DecoratorManager$1.run(Unknown \nSource)\n        at org.eclipse.core.internal.runtime.InternalPlatform.run(Unknown \nSource)\n        at org.eclipse.core.runtime.Platform.run(Unknown Source)\n        at org.eclipse.ui.internal.decorators.DecoratorManager.fireListeners\n(Unknown Source)\n        at \norg.eclipse.ui.internal.decorators.DecorationScheduler$2.runInUIThread(Unknown \nSource)\n        at org.eclipse.ui.progress.UIJob$1.run(Unknown Source)\n        at org.eclipse.swt.widgets.RunnableLock.run(RunnableLock.java:35)\n        at org.eclipse.swt.widgets.Synchronizer.runAsyncMessages\n(Synchronizer.java:102)\n        at org.eclipse.swt.widgets.Display.runAsyncMessages(Display.java:2165)\n        at org.eclipse.swt.widgets.Display.readAndDispatch(Display.java:1882)\n        at org.eclipse.jface.operation.ModalContext$ModalContextThread.block\n(Unknown Source)\n        at org.eclipse.jface.operation.ModalContext.run(Unknown Source)\n        at org.eclipse.jface.window.ApplicationWindow$1.run(Unknown Source)\n        at org.eclipse.swt.custom.BusyIndicator.showWhile(BusyIndicator.java:84)\n        at org.eclipse.jface.window.ApplicationWindow.run(Unknown Source)\n        at org.eclipse.ui.internal.WorkbenchWindow.run(Unknown Source)\n        at org.eclipse.team.internal.ui.sync.views.SyncViewer.run(Unknown \nSource)\n        at org.eclipse.team.internal.ui.sync.views.SyncViewer$8.run(Unknown \nSource)\n        at org.eclipse.swt.widgets.RunnableLock.run(RunnableLock.java:35)\n        at org.eclipse.swt.widgets.Synchronizer.runAsyncMessages\n(Synchronizer.java:102)\n        at org.eclipse.swt.widgets.Display.runAsyncMessages(Display.java:2165)\n        at org.eclipse.swt.widgets.Display.readAndDispatch(Display.java:1882)\n        at org.eclipse.jface.operation.ModalContext$ModalContextThread.block\n(Unknown Source)\n        at org.eclipse.jface.operation.ModalContext.run(Unknown Source)\n        at org.eclipse.jface.window.ApplicationWindow$1.run(Unknown Source)\n        at org.eclipse.swt.custom.BusyIndicator.showWhile(BusyIndicator.java:84)\n        at org.eclipse.jface.window.ApplicationWindow.run(Unknown Source)\n        at org.eclipse.ui.internal.WorkbenchWindow.run(Unknown Source)\n        at org.eclipse.team.internal.ui.sync.views.SyncViewer.run(Unknown \nSource)\n        at org.eclipse.team.internal.ui.sync.actions.RefreshAction.runBlocking\n(Unknown Source)\n        at org.eclipse.team.internal.ui.sync.actions.RefreshAction.run(Unknown \nSource)\n        at org.eclipse.team.internal.ui.sync.views.SyncViewer.refreshWithRemote\n(Unknown Source)\n        at org.eclipse.team.internal.ccvs.ui.actions.SyncAction.execute(Unknown \nSource)\n        at org.eclipse.team.internal.ccvs.ui.actions.CVSAction.run(Unknown \nSource)\n        at org.eclipse.ui.actions.ActionDelegate.runWithEvent(Unknown Source)\n        at org.eclipse.ui.internal.PluginAction.runWithEvent(Unknown Source)\n        at org.eclipse.jface.action.ActionContributionItem.handleWidgetSelection\n(Unknown Source)\n        at org.eclipse.jface.action.ActionContributionItem.access$4(Unknown \nSource)\n        at org.eclipse.jface.action.ActionContributionItem$6.handleEvent\n(Unknown Source)\n        at org.eclipse.swt.widgets.EventTable.sendEvent(EventTable.java:82)\n        at org.eclipse.swt.widgets.Widget.sendEvent(Widget.java:848)\n        at org.eclipse.swt.widgets.Display.runDeferredEvents(Display.java:2188)\n        at org.eclipse.swt.widgets.Display.readAndDispatch(Display.java:1878)\n        at org.eclipse.ui.internal.Workbench.runEventLoop(Unknown Source)\n        at org.eclipse.ui.internal.Workbench.run(Unknown Source)\n        at org.eclipse.core.internal.boot.InternalBootLoader.run(Unknown Source)\n        at org.eclipse.core.boot.BootLoader.run(Unknown Source)\n        at sun.reflect.NativeMethodAccessorImpl.invoke0(Native Method)\n        at sun.reflect.NativeMethodAccessorImpl.invoke\n(NativeMethodAccessorImpl.java:39)\n        at sun.reflect.DelegatingMethodAccessorImpl.invoke\n(DelegatingMethodAccessorImpl.java:25)\n        at java.lang.reflect.Method.invoke(Method.java:324)\n        at org.eclipse.core.launcher.Main.basicRun(Unknown Source)\n        at org.eclipse.core.launcher.Main.run(Unknown Source)\n        at org.eclipse.core.launcher.Main.main(Unknown Source)",
    "Did you happen to switch sync view layouts? For example from tree mode to table\nmode? Was the sync view open before running the action?",
    "No, I didn\u0027t switch sync view layouts. I just had restarted my 20030715 \nworkspace with build I20030716. The view existed, but it was stacked under the \npackage explorer view. I started the synchronize operation from the package \nexplorer. This brought the sync view to the front.",
    "Fix released to HEAD. The content provider did not need a handle to the viewer."
  ],
  "commentCreationDates": [
    "2003-07-16T17:38:49+02:00",
    "2003-07-16T18:13:55+02:00",
    "2003-07-16T18:24:32+02:00",
    "2003-07-23T19:31:04+02:00"
  ],
  "traces": [
    {
      "exceptionType": "java.lang.NullPointerException",
      "elements": [
        {
          "method": "org.eclipse.team.internal.ui.sync.views.CompressedFolderContentProvider.getModelObject",
          "source": "Unknown Source"
        },
        {
          "method": "org.eclipse.team.internal.ui.sync.views.SyncTreeViewer.handleLabelProviderChanged",
          "source": "Unknown Source"
        },
        {
          "method": "org.eclipse.jface.viewers.ContentViewer$1.labelProviderChanged",
          "source": "Unknown Source"
        },
        {
          "method": "org.eclipse.ui.internal.decorators.DecoratorManager$1.run",
          "source": "Unknown  Source"
        },
        {
          "method": "org.eclipse.core.internal.runtime.InternalPlatform.run",
          "source": "Unknown  Source"
        },
        {
          "method": "org.eclipse.core.runtime.Platform.run",
          "source": "Unknown Source"
        },
        {
          "method": "org.eclipse.ui.internal.decorators.DecoratorManager.fireListeners",
          "source": "Unknown Source"
        },
        {
          "method": "org.eclipse.ui.internal.decorators.DecorationScheduler$2.runInUIThread",
          "source": "Unknown  Source"
        },
        {
          "method": "org.eclipse.ui.progress.UIJob$1.run",
          "source": "Unknown Source"
        },
        {
          "method": "org.eclipse.swt.widgets.RunnableLock.run",
          "source": "RunnableLock.java:35"
        },
        {
          "method": "org.eclipse.swt.widgets.Synchronizer.runAsyncMessages",
          "source": "Synchronizer.java:102"
        },
        {
          "method": "org.eclipse.swt.widgets.Display.runAsyncMessages",
          "source": "Display.java:2165"
        },
        {
          "method": "org.eclipse.swt.widgets.Display.readAndDispatch",
          "source": "Display.java:1882"
        },
        {
          "method": "org.eclipse.jface.operation.ModalContext$ModalContextThread.block",
          "source": "Unknown Source"
        },
        {
          "method": "org.eclipse.jface.operation.ModalContext.run",
          "source": "Unknown Source"
        },
        {
          "method": "org.eclipse.jface.window.ApplicationWindow$1.run",
          "source": "Unknown Source"
        },
        {
          "method": "org.eclipse.swt.custom.BusyIndicator.showWhile",
          "source": "BusyIndicator.java:84"
        },
        {
          "method": "org.eclipse.jface.window.ApplicationWindow.run",
          "source": "Unknown Source"
        },
        {
          "method": "org.eclipse.ui.internal.WorkbenchWindow.run",
          "source": "Unknown Source"
        },
        {
          "method": "org.eclipse.team.internal.ui.sync.views.SyncViewer.run",
          "source": "Unknown  Source"
        },
        {
          "method": "org.eclipse.team.internal.ui.sync.views.SyncViewer$8.run",
          "source": "Unknown  Source"
        },
        {
          "method": "org.eclipse.swt.widgets.RunnableLock.run",
          "source": "RunnableLock.java:35"
        },
        {
          "method": "org.eclipse.swt.widgets.Synchronizer.runAsyncMessages",
          "source": "Synchronizer.java:102"
        },
        {
          "method": "org.eclipse.swt.widgets.Display.runAsyncMessages",
          "source": "Display.java:2165"
        },
        {
          "method": "org.eclipse.swt.widgets.Display.readAndDispatch",
          "source": "Display.java:1882"
        },
        {
          "method": "org.eclipse.jface.operation.ModalContext$ModalContextThread.block",
          "source": "Unknown Source"
        },
        {
          "method": "org.eclipse.jface.operation.ModalContext.run",
          "source": "Unknown Source"
        },
        {
          "method": "org.eclipse.jface.window.ApplicationWindow$1.run",
          "source": "Unknown Source"
        },
        {
          "method": "org.eclipse.swt.custom.BusyIndicator.showWhile",
          "source": "BusyIndicator.java:84"
        },
        {
          "method": "org.eclipse.jface.window.ApplicationWindow.run",
          "source": "Unknown Source"
        },
        {
          "method": "org.eclipse.ui.internal.WorkbenchWindow.run",
          "source": "Unknown Source"
        },
        {
          "method": "org.eclipse.team.internal.ui.sync.views.SyncViewer.run",
          "source": "Unknown  Source"
        },
        {
          "method": "org.eclipse.team.internal.ui.sync.actions.RefreshAction.runBlocking",
          "source": "Unknown Source"
        },
        {
          "method": "org.eclipse.team.internal.ui.sync.actions.RefreshAction.run",
          "source": "Unknown  Source"
        },
        {
          "method": "org.eclipse.team.internal.ui.sync.views.SyncViewer.refreshWithRemote",
          "source": "Unknown Source"
        },
        {
          "method": "org.eclipse.team.internal.ccvs.ui.actions.SyncAction.execute",
          "source": "Unknown  Source"
        },
        {
          "method": "org.eclipse.team.internal.ccvs.ui.actions.CVSAction.run",
          "source": "Unknown  Source"
        },
        {
          "method": "org.eclipse.ui.actions.ActionDelegate.runWithEvent",
          "source": "Unknown Source"
        },
        {
          "method": "org.eclipse.ui.internal.PluginAction.runWithEvent",
          "source": "Unknown Source"
        },
        {
          "method": "org.eclipse.jface.action.ActionContributionItem.handleWidgetSelection",
          "source": "Unknown Source"
        },
        {
          "method": "org.eclipse.jface.action.ActionContributionItem.access$4",
          "source": "Unknown  Source"
        },
        {
          "method": "org.eclipse.jface.action.ActionContributionItem$6.handleEvent",
          "source": "Unknown Source"
        },
        {
          "method": "org.eclipse.swt.widgets.EventTable.sendEvent",
          "source": "EventTable.java:82"
        },
        {
          "method": "org.eclipse.swt.widgets.Widget.sendEvent",
          "source": "Widget.java:848"
        },
        {
          "method": "org.eclipse.swt.widgets.Display.runDeferredEvents",
          "source": "Display.java:2188"
        },
        {
          "method": "org.eclipse.swt.widgets.Display.readAndDispatch",
          "source": "Display.java:1878"
        },
        {
          "method": "org.eclipse.ui.internal.Workbench.runEventLoop",
          "source": "Unknown Source"
        },
        {
          "method": "org.eclipse.ui.internal.Workbench.run",
          "source": "Unknown Source"
        },
        {
          "method": "org.eclipse.core.internal.boot.InternalBootLoader.run",
          "source": "Unknown Source"
        },
        {
          "method": "org.eclipse.core.boot.BootLoader.run",
          "source": "Unknown Source"
        },
        {
          "method": "sun.reflect.NativeMethodAccessorImpl.invoke0",
          "source": "Native Method"
        },
        {
          "method": "sun.reflect.NativeMethodAccessorImpl.invoke",
          "source": "NativeMethodAccessorImpl.java:39"
        },
        {
          "method": "sun.reflect.DelegatingMethodAccessorImpl.invoke",
          "source": "DelegatingMethodAccessorImpl.java:25"
        },
        {
          "method": "java.lang.reflect.Method.invoke",
          "source": "Method.java:324"
        },
        {
          "method": "org.eclipse.core.launcher.Main.basicRun",
          "source": "Unknown Source"
        },
        {
          "method": "org.eclipse.core.launcher.Main.run",
          "source": "Unknown Source"
        },
        {
          "method": "org.eclipse.core.launcher.Main.main",
          "source": "Unknown Source"
        }
      ],
      "number": 0,
      "commentIndex": 0,
      "bugId": "40231",
      "date": "2003-07-16T17:38:49+02:00",
      "product": "Platform",
      "component": "Team",
      "severity": "normal"
    }
  ],
  "groupId": "40231",
  "bugId": "40231",
  "date": "2003-07-16T17:38:49+02:00",
  "product": "Platform",
  "component": "Team",
  "severity": "normal"
}