{
  "comments": [
    "Build 20030716\n\nGot the following NPE exiting the workbench:\n\n!ENTRY org.eclipse.ui.workbench 4 2 Jul 17, 2003 12:18:49.238\n!MESSAGE Problems occurred when invoking code from plug-\nin: \"org.eclipse.ui.workbench\".\n!STACK 0\norg.eclipse.jface.text.Assert$AssertionFailedException: Assertion failed:\n        at org.eclipse.jface.text.Assert.isTrue(Unknown Source)\n        at org.eclipse.jface.text.Assert.isTrue(Unknown Source)\n        at org.eclipse.jface.text.source.AnnotationModel.disconnect(Unknown \nSource)\n        at org.eclipse.jface.text.source.VisualAnnotationModel.disconnect\n(Unknown Source)\n        at org.eclipse.jface.text.source.SourceViewer.setDocument(Unknown \nSource)\n        at org.eclipse.jface.text.source.SourceViewer.setDocument(Unknown \nSource)\n        at org.eclipse.jface.text.TextViewer$1.widgetDisposed(Unknown Source)\n        at org.eclipse.swt.widgets.TypedListener.handleEvent\n(TypedListener.java:100)\n        at org.eclipse.swt.widgets.EventTable.sendEvent(EventTable.java:82)\n        at org.eclipse.swt.widgets.Widget.sendEvent(Widget.java:848)\n        at org.eclipse.swt.widgets.Widget.sendEvent(Widget.java:872)\n        at org.eclipse.swt.widgets.Widget.sendEvent(Widget.java:853)\n        at org.eclipse.swt.widgets.Widget.releaseWidget(Widget.java:760)\n        at org.eclipse.swt.widgets.Control.releaseWidget(Control.java:1421)\n        at org.eclipse.swt.widgets.Scrollable.releaseWidget(Scrollable.java:188)\n        at org.eclipse.swt.widgets.Composite.releaseWidget(Composite.java:369)\n        at org.eclipse.swt.widgets.Canvas.releaseWidget(Canvas.java:118)\n        at org.eclipse.swt.widgets.Widget.releaseResources(Widget.java:725)\n        at org.eclipse.swt.widgets.Composite.releaseChildren(Composite.java:320)\n        at org.eclipse.swt.widgets.Composite.releaseWidget(Composite.java:368)\n        at org.eclipse.swt.widgets.Canvas.releaseWidget(Canvas.java:118)\n        at org.eclipse.swt.widgets.Widget.releaseResources(Widget.java:725)\n        at org.eclipse.swt.widgets.Composite.releaseChildren(Composite.java:320)\n        at org.eclipse.swt.widgets.Composite.releaseWidget(Composite.java:368)\n        at org.eclipse.swt.widgets.Widget.releaseResources(Widget.java:725)\n        at org.eclipse.swt.widgets.Composite.releaseChildren(Composite.java:320)\n        at org.eclipse.swt.widgets.Composite.releaseWidget(Composite.java:368)\n        at org.eclipse.swt.widgets.Widget.releaseResources(Widget.java:725)\n        at org.eclipse.swt.widgets.Composite.releaseChildren(Composite.java:320)\n        at org.eclipse.swt.widgets.Composite.releaseWidget(Composite.java:368)\n        at org.eclipse.swt.widgets.Widget.releaseResources(Widget.java:725)\n        at org.eclipse.swt.widgets.Composite.releaseChildren(Composite.java:320)\n        at org.eclipse.swt.widgets.Composite.releaseWidget(Composite.java:368)\n        at org.eclipse.swt.widgets.Widget.releaseResources(Widget.java:725)\n        at org.eclipse.swt.widgets.Composite.releaseChildren(Composite.java:320)\n        at org.eclipse.swt.widgets.Composite.releaseWidget(Composite.java:368)\n        at org.eclipse.swt.widgets.Widget.releaseResources(Widget.java:725)\n        at org.eclipse.swt.widgets.Composite.releaseChildren(Composite.java:320)\n        at org.eclipse.swt.widgets.Composite.releaseWidget(Composite.java:368)\n        at org.eclipse.swt.widgets.Widget.releaseResources(Widget.java:725)\n        at org.eclipse.swt.widgets.Composite.releaseChildren(Composite.java:320)\n        at org.eclipse.swt.widgets.Composite.releaseWidget(Composite.java:368)\n        at org.eclipse.swt.widgets.Widget.releaseResources(Widget.java:725)\n        at org.eclipse.swt.widgets.Composite.releaseChildren(Composite.java:320)\n        at org.eclipse.swt.widgets.Composite.releaseWidget(Composite.java:368)\n        at org.eclipse.swt.widgets.Canvas.releaseWidget(Canvas.java:118)\n        at org.eclipse.swt.widgets.Decorations.releaseWidget\n(Decorations.java:632)\n        at org.eclipse.swt.widgets.Shell.releaseWidget(Shell.java:740)\n        at org.eclipse.swt.widgets.Widget.dispose(Widget.java:376)\n        at org.eclipse.swt.widgets.Decorations.dispose(Decorations.java:365)\n        at org.eclipse.swt.widgets.Shell.dispose(Shell.java:485)\n        at org.eclipse.jface.window.Window.close(Unknown Source)\n        at org.eclipse.jface.window.ApplicationWindow.close(Unknown Source)\n        at org.eclipse.ui.internal.WorkbenchWindow.hardClose(Unknown Source)\n        at org.eclipse.ui.internal.WorkbenchWindow.busyClose(Unknown Source)\n        at org.eclipse.ui.internal.WorkbenchWindow.access$3(Unknown Source)\n        at org.eclipse.ui.internal.WorkbenchWindow$2.run(Unknown Source)\n        at org.eclipse.swt.custom.BusyIndicator.showWhile(BusyIndicator.java:84)\n        at org.eclipse.ui.internal.WorkbenchWindow.close(Unknown Source)\n        at org.eclipse.jface.window.WindowManager.close(Unknown Source)\n        at org.eclipse.ui.internal.Workbench$12.run(Unknown Source)\n        at org.eclipse.core.internal.runtime.InternalPlatform.run(Unknown \nSource)\n        at org.eclipse.core.runtime.Platform.run(Unknown Source)\n        at org.eclipse.ui.internal.Workbench.busyClose(Unknown Source)\n        at org.eclipse.ui.internal.Workbench.access$8(Unknown Source)\n        at org.eclipse.ui.internal.Workbench$14.run(Unknown Source)\n        at org.eclipse.swt.custom.BusyIndicator.showWhile(BusyIndicator.java:84)\n        at org.eclipse.ui.internal.Workbench.close(Unknown Source)\n        at org.eclipse.ui.internal.Workbench.close(Unknown Source)\n        at org.eclipse.ui.internal.Workbench.close(Unknown Source)\n        at org.eclipse.ui.internal.QuitAction.run(Unknown Source)\n        at org.eclipse.jface.action.Action.runWithEvent(Unknown Source)\n        at org.eclipse.jface.action.ActionContributionItem.handleWidgetSelection\n(Unknown Source)\n        at org.eclipse.jface.action.ActionContributionItem.access$4(Unknown \nSource)\n        at org.eclipse.jface.action.ActionContributionItem$6.handleEvent\n(Unknown Source)\n        at org.eclipse.swt.widgets.EventTable.sendEvent(EventTable.java:82)\n        at org.eclipse.swt.widgets.Widget.sendEvent(Widget.java:848)\n        at org.eclipse.swt.widgets.Display.runDeferredEvents(Display.java:2188)\n        at org.eclipse.swt.widgets.Display.readAndDispatch(Display.java:1878)\n        at org.eclipse.ui.internal.Workbench.runEventLoop(Unknown Source)\n        at org.eclipse.ui.internal.Workbench.run(Unknown Source)\n        at org.eclipse.core.internal.boot.InternalBootLoader.run(Unknown Source)\n        at org.eclipse.core.boot.BootLoader.run(Unknown Source)\n        at sun.reflect.NativeMethodAccessorImpl.invoke0(Native Method)\n        at sun.reflect.NativeMethodAccessorImpl.invoke\n(NativeMethodAccessorImpl.java:39)\n        at sun.reflect.DelegatingMethodAccessorImpl.invoke\n(DelegatingMethodAccessorImpl.java:25)\n        at java.lang.reflect.Method.invoke(Method.java:324)\n        at org.eclipse.core.launcher.Main.basicRun(Unknown Source)\n        at org.eclipse.core.launcher.Main.run(Unknown Source)\n        at org.eclipse.core.launcher.Main.main(Unknown Source)",
    "\n\n*** This bug has been marked as a duplicate of 40339 ***"
  ],
  "commentCreationDates": [
    "2003-07-17T12:27:29+02:00",
    "2003-07-17T18:31:42+02:00"
  ],
  "traces": [
    {
      "exceptionType": "org.eclipse.jface.text.Assert$AssertionFailedException",
      "message": "Assertion failed:",
      "elements": [
        {
          "method": "org.eclipse.jface.text.Assert.isTrue",
          "source": "Unknown Source"
        },
        {
          "method": "org.eclipse.jface.text.Assert.isTrue",
          "source": "Unknown Source"
        },
        {
          "method": "org.eclipse.jface.text.source.AnnotationModel.disconnect",
          "source": "Unknown  Source"
        },
        {
          "method": "org.eclipse.jface.text.source.VisualAnnotationModel.disconnect",
          "source": "Unknown Source"
        },
        {
          "method": "org.eclipse.jface.text.source.SourceViewer.setDocument",
          "source": "Unknown  Source"
        },
        {
          "method": "org.eclipse.jface.text.source.SourceViewer.setDocument",
          "source": "Unknown  Source"
        },
        {
          "method": "org.eclipse.jface.text.TextViewer$1.widgetDisposed",
          "source": "Unknown Source"
        },
        {
          "method": "org.eclipse.swt.widgets.TypedListener.handleEvent",
          "source": "TypedListener.java:100"
        },
        {
          "method": "org.eclipse.swt.widgets.EventTable.sendEvent",
          "source": "EventTable.java:82"
        },
        {
          "method": "org.eclipse.swt.widgets.Widget.sendEvent",
          "source": "Widget.java:848"
        },
        {
          "method": "org.eclipse.swt.widgets.Widget.sendEvent",
          "source": "Widget.java:872"
        },
        {
          "method": "org.eclipse.swt.widgets.Widget.sendEvent",
          "source": "Widget.java:853"
        },
        {
          "method": "org.eclipse.swt.widgets.Widget.releaseWidget",
          "source": "Widget.java:760"
        },
        {
          "method": "org.eclipse.swt.widgets.Control.releaseWidget",
          "source": "Control.java:1421"
        },
        {
          "method": "org.eclipse.swt.widgets.Scrollable.releaseWidget",
          "source": "Scrollable.java:188"
        },
        {
          "method": "org.eclipse.swt.widgets.Composite.releaseWidget",
          "source": "Composite.java:369"
        },
        {
          "method": "org.eclipse.swt.widgets.Canvas.releaseWidget",
          "source": "Canvas.java:118"
        },
        {
          "method": "org.eclipse.swt.widgets.Widget.releaseResources",
          "source": "Widget.java:725"
        },
        {
          "method": "org.eclipse.swt.widgets.Composite.releaseChildren",
          "source": "Composite.java:320"
        },
        {
          "method": "org.eclipse.swt.widgets.Composite.releaseWidget",
          "source": "Composite.java:368"
        },
        {
          "method": "org.eclipse.swt.widgets.Canvas.releaseWidget",
          "source": "Canvas.java:118"
        },
        {
          "method": "org.eclipse.swt.widgets.Widget.releaseResources",
          "source": "Widget.java:725"
        },
        {
          "method": "org.eclipse.swt.widgets.Composite.releaseChildren",
          "source": "Composite.java:320"
        },
        {
          "method": "org.eclipse.swt.widgets.Composite.releaseWidget",
          "source": "Composite.java:368"
        },
        {
          "method": "org.eclipse.swt.widgets.Widget.releaseResources",
          "source": "Widget.java:725"
        },
        {
          "method": "org.eclipse.swt.widgets.Composite.releaseChildren",
          "source": "Composite.java:320"
        },
        {
          "method": "org.eclipse.swt.widgets.Composite.releaseWidget",
          "source": "Composite.java:368"
        },
        {
          "method": "org.eclipse.swt.widgets.Widget.releaseResources",
          "source": "Widget.java:725"
        },
        {
          "method": "org.eclipse.swt.widgets.Composite.releaseChildren",
          "source": "Composite.java:320"
        },
        {
          "method": "org.eclipse.swt.widgets.Composite.releaseWidget",
          "source": "Composite.java:368"
        },
        {
          "method": "org.eclipse.swt.widgets.Widget.releaseResources",
          "source": "Widget.java:725"
        },
        {
          "method": "org.eclipse.swt.widgets.Composite.releaseChildren",
          "source": "Composite.java:320"
        },
        {
          "method": "org.eclipse.swt.widgets.Composite.releaseWidget",
          "source": "Composite.java:368"
        },
        {
          "method": "org.eclipse.swt.widgets.Widget.releaseResources",
          "source": "Widget.java:725"
        },
        {
          "method": "org.eclipse.swt.widgets.Composite.releaseChildren",
          "source": "Composite.java:320"
        },
        {
          "method": "org.eclipse.swt.widgets.Composite.releaseWidget",
          "source": "Composite.java:368"
        },
        {
          "method": "org.eclipse.swt.widgets.Widget.releaseResources",
          "source": "Widget.java:725"
        },
        {
          "method": "org.eclipse.swt.widgets.Composite.releaseChildren",
          "source": "Composite.java:320"
        },
        {
          "method": "org.eclipse.swt.widgets.Composite.releaseWidget",
          "source": "Composite.java:368"
        },
        {
          "method": "org.eclipse.swt.widgets.Widget.releaseResources",
          "source": "Widget.java:725"
        },
        {
          "method": "org.eclipse.swt.widgets.Composite.releaseChildren",
          "source": "Composite.java:320"
        },
        {
          "method": "org.eclipse.swt.widgets.Composite.releaseWidget",
          "source": "Composite.java:368"
        },
        {
          "method": "org.eclipse.swt.widgets.Widget.releaseResources",
          "source": "Widget.java:725"
        },
        {
          "method": "org.eclipse.swt.widgets.Composite.releaseChildren",
          "source": "Composite.java:320"
        },
        {
          "method": "org.eclipse.swt.widgets.Composite.releaseWidget",
          "source": "Composite.java:368"
        },
        {
          "method": "org.eclipse.swt.widgets.Canvas.releaseWidget",
          "source": "Canvas.java:118"
        },
        {
          "method": "org.eclipse.swt.widgets.Decorations.releaseWidget",
          "source": "Decorations.java:632"
        },
        {
          "method": "org.eclipse.swt.widgets.Shell.releaseWidget",
          "source": "Shell.java:740"
        },
        {
          "method": "org.eclipse.swt.widgets.Widget.dispose",
          "source": "Widget.java:376"
        },
        {
          "method": "org.eclipse.swt.widgets.Decorations.dispose",
          "source": "Decorations.java:365"
        },
        {
          "method": "org.eclipse.swt.widgets.Shell.dispose",
          "source": "Shell.java:485"
        },
        {
          "method": "org.eclipse.jface.window.Window.close",
          "source": "Unknown Source"
        },
        {
          "method": "org.eclipse.jface.window.ApplicationWindow.close",
          "source": "Unknown Source"
        },
        {
          "method": "org.eclipse.ui.internal.WorkbenchWindow.hardClose",
          "source": "Unknown Source"
        },
        {
          "method": "org.eclipse.ui.internal.WorkbenchWindow.busyClose",
          "source": "Unknown Source"
        },
        {
          "method": "org.eclipse.ui.internal.WorkbenchWindow.access$3",
          "source": "Unknown Source"
        },
        {
          "method": "org.eclipse.ui.internal.WorkbenchWindow$2.run",
          "source": "Unknown Source"
        },
        {
          "method": "org.eclipse.swt.custom.BusyIndicator.showWhile",
          "source": "BusyIndicator.java:84"
        },
        {
          "method": "org.eclipse.ui.internal.WorkbenchWindow.close",
          "source": "Unknown Source"
        },
        {
          "method": "org.eclipse.jface.window.WindowManager.close",
          "source": "Unknown Source"
        },
        {
          "method": "org.eclipse.ui.internal.Workbench$12.run",
          "source": "Unknown Source"
        },
        {
          "method": "org.eclipse.core.internal.runtime.InternalPlatform.run",
          "source": "Unknown  Source"
        },
        {
          "method": "org.eclipse.core.runtime.Platform.run",
          "source": "Unknown Source"
        },
        {
          "method": "org.eclipse.ui.internal.Workbench.busyClose",
          "source": "Unknown Source"
        },
        {
          "method": "org.eclipse.ui.internal.Workbench.access$8",
          "source": "Unknown Source"
        },
        {
          "method": "org.eclipse.ui.internal.Workbench$14.run",
          "source": "Unknown Source"
        },
        {
          "method": "org.eclipse.swt.custom.BusyIndicator.showWhile",
          "source": "BusyIndicator.java:84"
        },
        {
          "method": "org.eclipse.ui.internal.Workbench.close",
          "source": "Unknown Source"
        },
        {
          "method": "org.eclipse.ui.internal.Workbench.close",
          "source": "Unknown Source"
        },
        {
          "method": "org.eclipse.ui.internal.Workbench.close",
          "source": "Unknown Source"
        },
        {
          "method": "org.eclipse.ui.internal.QuitAction.run",
          "source": "Unknown Source"
        },
        {
          "method": "org.eclipse.jface.action.Action.runWithEvent",
          "source": "Unknown Source"
        },
        {
          "method": "org.eclipse.jface.action.ActionContributionItem.handleWidgetSelection",
          "source": "Unknown Source"
        },
        {
          "method": "org.eclipse.jface.action.ActionContributionItem.access$4",
          "source": "Unknown  Source"
        },
        {
          "method": "org.eclipse.jface.action.ActionContributionItem$6.handleEvent",
          "source": "Unknown Source"
        },
        {
          "method": "org.eclipse.swt.widgets.EventTable.sendEvent",
          "source": "EventTable.java:82"
        },
        {
          "method": "org.eclipse.swt.widgets.Widget.sendEvent",
          "source": "Widget.java:848"
        },
        {
          "method": "org.eclipse.swt.widgets.Display.runDeferredEvents",
          "source": "Display.java:2188"
        },
        {
          "method": "org.eclipse.swt.widgets.Display.readAndDispatch",
          "source": "Display.java:1878"
        },
        {
          "method": "org.eclipse.ui.internal.Workbench.runEventLoop",
          "source": "Unknown Source"
        },
        {
          "method": "org.eclipse.ui.internal.Workbench.run",
          "source": "Unknown Source"
        },
        {
          "method": "org.eclipse.core.internal.boot.InternalBootLoader.run",
          "source": "Unknown Source"
        },
        {
          "method": "org.eclipse.core.boot.BootLoader.run",
          "source": "Unknown Source"
        },
        {
          "method": "sun.reflect.NativeMethodAccessorImpl.invoke0",
          "source": "Native Method"
        },
        {
          "method": "sun.reflect.NativeMethodAccessorImpl.invoke",
          "source": "NativeMethodAccessorImpl.java:39"
        },
        {
          "method": "sun.reflect.DelegatingMethodAccessorImpl.invoke",
          "source": "DelegatingMethodAccessorImpl.java:25"
        },
        {
          "method": "java.lang.reflect.Method.invoke",
          "source": "Method.java:324"
        },
        {
          "method": "org.eclipse.core.launcher.Main.basicRun",
          "source": "Unknown Source"
        },
        {
          "method": "org.eclipse.core.launcher.Main.run",
          "source": "Unknown Source"
        },
        {
          "method": "org.eclipse.core.launcher.Main.main",
          "source": "Unknown Source"
        }
      ],
      "number": 0,
      "commentIndex": 0,
      "bugId": "40307",
      "duplicateId": "40339",
      "date": "2003-07-17T12:27:29+02:00",
      "product": "Platform",
      "component": "Text",
      "severity": "critical"
    }
  ],
  "groupId": "40339",
  "bugId": "40307",
  "duplicateId": "40339",
  "date": "2003-07-17T12:27:29+02:00",
  "product": "Platform",
  "component": "Text",
  "severity": "critical"
}