{
  "comments": [
    "Build 20030716\n\nDebugger was working well, until it ceased showing me source associated with \nstack frame. Glancing at the log, I found the following trace:\n\n!ENTRY org.eclipse.jface 4 2 Jul 17, 2003 12:48:22.857\n!MESSAGE Problems occurred when invoking code from plug-in: \"org.eclipse.jface\".\n!STACK 0\njava.lang.NullPointerException\n        at \norg.eclipse.ui.internal.editors.quickdiff.LastSaveReferenceProvider.dispose\n(Unknown Source)\n        at \norg.eclipse.ui.internal.editors.quickdiff.DocumentLineDiffer.disconnect(Unknown \nSource)\n        at org.eclipse.jface.text.source.AnnotationModel.disconnect(Unknown \nSource)\n        at org.eclipse.jface.text.source.VisualAnnotationModel.disconnect\n(Unknown Source)\n        at org.eclipse.jface.text.source.SourceViewer.setDocument(Unknown \nSource)\n        at org.eclipse.jface.text.source.SourceViewer.setDocument(Unknown \nSource)\n        at org.eclipse.jface.text.TextViewer$1.widgetDisposed(Unknown Source)\n        at org.eclipse.swt.widgets.TypedListener.handleEvent\n(TypedListener.java:100)\n        at org.eclipse.swt.widgets.EventTable.sendEvent(EventTable.java:82)\n        at org.eclipse.swt.widgets.Widget.sendEvent(Widget.java:848)\n        at org.eclipse.swt.widgets.Widget.sendEvent(Widget.java:872)\n        at org.eclipse.swt.widgets.Widget.sendEvent(Widget.java:853)\n        at org.eclipse.swt.widgets.Widget.releaseWidget(Widget.java:760)\n        at org.eclipse.swt.widgets.Control.releaseWidget(Control.java:1421)\n        at org.eclipse.swt.widgets.Scrollable.releaseWidget(Scrollable.java:188)\n        at org.eclipse.swt.widgets.Composite.releaseWidget(Composite.java:369)\n        at org.eclipse.swt.widgets.Canvas.releaseWidget(Canvas.java:118)\n        at org.eclipse.swt.widgets.Widget.releaseResources(Widget.java:725)\n        at org.eclipse.swt.widgets.Composite.releaseChildren(Composite.java:320)\n        at org.eclipse.swt.widgets.Composite.releaseWidget(Composite.java:368)\n        at org.eclipse.swt.widgets.Canvas.releaseWidget(Canvas.java:118)\n        at org.eclipse.swt.widgets.Widget.releaseResources(Widget.java:725)\n        at org.eclipse.swt.widgets.Composite.releaseChildren(Composite.java:320)\n        at org.eclipse.swt.widgets.Composite.releaseWidget(Composite.java:368)\n        at org.eclipse.swt.widgets.Widget.releaseResources(Widget.java:725)\n        at org.eclipse.swt.widgets.Composite.releaseChildren(Composite.java:320)\n        at org.eclipse.swt.widgets.Composite.releaseWidget(Composite.java:368)\n        at org.eclipse.swt.widgets.Widget.releaseResources(Widget.java:725)\n        at org.eclipse.swt.widgets.Composite.releaseChildren(Composite.java:320)\n        at org.eclipse.swt.widgets.Composite.releaseWidget(Composite.java:368)\n        at org.eclipse.swt.widgets.Widget.releaseResources(Widget.java:725)\n        at org.eclipse.swt.widgets.Composite.releaseChildren(Composite.java:320)\n        at org.eclipse.swt.widgets.Composite.releaseWidget(Composite.java:368)\n        at org.eclipse.swt.widgets.Widget.releaseResources(Widget.java:725)\n        at org.eclipse.swt.widgets.Composite.releaseChildren(Composite.java:320)\n        at org.eclipse.swt.widgets.Composite.releaseWidget(Composite.java:368)\n        at org.eclipse.swt.widgets.Widget.releaseResources(Widget.java:725)\n        at org.eclipse.swt.widgets.Composite.releaseChildren(Composite.java:320)\n        at org.eclipse.swt.widgets.Composite.releaseWidget(Composite.java:368)\n        at org.eclipse.swt.widgets.Widget.dispose(Widget.java:376)\n        at org.eclipse.ui.internal.PartPane.dispose(Unknown Source)\n        at org.eclipse.ui.internal.EditorPresentation.closeEditor(Unknown \nSource)\n        at org.eclipse.ui.internal.EditorPresentation.closeEditor(Unknown \nSource)\n        at org.eclipse.ui.internal.EditorManager.closeEditor(Unknown Source)\n        at org.eclipse.ui.internal.WorkbenchPage.closeEditor(Unknown Source)\n        at org.eclipse.debug.internal.ui.views.launch.LaunchView.openEditor\n(Unknown Source)\n        at \norg.eclipse.debug.internal.ui.views.launch.LaunchView.openEditorForStackFrame\n(Unknown Source)\n        at \norg.eclipse.debug.internal.ui.views.launch.LaunchView.showEditorForCurrentSelect\nion(Unknown Source)\n        at \norg.eclipse.debug.internal.ui.views.launch.LaunchView.selectionChanged(Unknown \nSource)\n        at org.eclipse.jface.viewers.Viewer$2.run(Unknown Source)\n        at org.eclipse.core.internal.runtime.InternalPlatform.run(Unknown \nSource)\n        at org.eclipse.core.runtime.Platform.run(Unknown Source)\n        at org.eclipse.jface.viewers.Viewer.fireSelectionChanged(Unknown Source)\n        at org.eclipse.jface.viewers.StructuredViewer.updateSelection(Unknown \nSource)\n        at org.eclipse.jface.viewers.StructuredViewer.setSelection(Unknown \nSource)\n        at org.eclipse.debug.internal.ui.views.launch.LaunchView.autoExpand\n(Unknown Source)\n        at \norg.eclipse.debug.internal.ui.views.launch.LaunchViewEventHandler.doHandleSuspen\ndThreadEvent(Unknown Source)\n        at \norg.eclipse.debug.internal.ui.views.launch.LaunchViewEventHandler.doHandleSuspen\ndEvent(Unknown Source)\n        at \norg.eclipse.debug.internal.ui.views.launch.LaunchViewEventHandler.doHandleDebugE\nvents(Unknown Source)\n        at org.eclipse.debug.internal.ui.views.AbstractDebugEventHandler$1.run\n(Unknown Source)\n        at org.eclipse.swt.widgets.RunnableLock.run(RunnableLock.java:35)\n        at org.eclipse.swt.widgets.Synchronizer.runAsyncMessages\n(Synchronizer.java:102)\n        at org.eclipse.swt.widgets.Display.runAsyncMessages(Display.java:2165)\n        at org.eclipse.swt.widgets.Display.readAndDispatch(Display.java:1882)\n        at org.eclipse.ui.internal.Workbench.runEventLoop(Unknown Source)\n        at org.eclipse.ui.internal.Workbench.run(Unknown Source)\n        at org.eclipse.core.internal.boot.InternalBootLoader.run(Unknown Source)\n        at org.eclipse.core.boot.BootLoader.run(Unknown Source)\n        at sun.reflect.NativeMethodAccessorImpl.invoke0(Native Method)\n        at sun.reflect.NativeMethodAccessorImpl.invoke\n(NativeMethodAccessorImpl.java:39)\n        at sun.reflect.DelegatingMethodAccessorImpl.invoke\n(DelegatingMethodAccessorImpl.java:25)\n        at java.lang.reflect.Method.invoke(Method.java:324)\n        at org.eclipse.core.launcher.Main.basicRun(Unknown Source)\n        at org.eclipse.core.launcher.Main.run(Unknown Source)\n        at org.eclipse.core.launcher.Main.main(Unknown Source)",
    "Attempting to close this debugger:\n\n!ENTRY org.eclipse.ui 4 0 Jul 17, 2003 12:53:38.120\n!MESSAGE Assertion failed:\n!STACK 0\norg.eclipse.jface.text.Assert$AssertionFailedException: Assertion failed:\n        at org.eclipse.jface.text.Assert.isTrue(Unknown Source)\n        at org.eclipse.jface.text.Assert.isTrue(Unknown Source)\n        at org.eclipse.jface.text.source.AnnotationModel.disconnect(Unknown \nSource)\n        at org.eclipse.jface.text.source.VisualAnnotationModel.disconnect\n(Unknown Source)\n        at org.eclipse.jface.text.source.SourceViewer.setDocument(Unknown \nSource)\n        at org.eclipse.jface.text.source.SourceViewer.setDocument(Unknown \nSource)\n        at org.eclipse.jface.text.TextViewer$1.widgetDisposed(Unknown Source)\n        at org.eclipse.swt.widgets.TypedListener.handleEvent\n(TypedListener.java:100)\n        at org.eclipse.swt.widgets.EventTable.sendEvent(EventTable.java:82)\n        at org.eclipse.swt.widgets.Widget.sendEvent(Widget.java:848)\n        at org.eclipse.swt.widgets.Widget.sendEvent(Widget.java:872)\n        at org.eclipse.swt.widgets.Widget.sendEvent(Widget.java:853)\n        at org.eclipse.swt.widgets.Widget.releaseWidget(Widget.java:760)\n        at org.eclipse.swt.widgets.Control.releaseWidget(Control.java:1421)\n        at org.eclipse.swt.widgets.Scrollable.releaseWidget(Scrollable.java:188)\n        at org.eclipse.swt.widgets.Composite.releaseWidget(Composite.java:369)\n        at org.eclipse.swt.widgets.Canvas.releaseWidget(Canvas.java:118)\n        at org.eclipse.swt.widgets.Widget.releaseResources(Widget.java:725)\n        at org.eclipse.swt.widgets.Composite.releaseChildren(Composite.java:320)\n        at org.eclipse.swt.widgets.Composite.releaseWidget(Composite.java:368)\n        at org.eclipse.swt.widgets.Canvas.releaseWidget(Canvas.java:118)\n        at org.eclipse.swt.widgets.Widget.releaseResources(Widget.java:725)\n        at org.eclipse.swt.widgets.Composite.releaseChildren(Composite.java:320)\n        at org.eclipse.swt.widgets.Composite.releaseWidget(Composite.java:368)\n        at org.eclipse.swt.widgets.Widget.releaseResources(Widget.java:725)\n        at org.eclipse.swt.widgets.Composite.releaseChildren(Composite.java:320)\n        at org.eclipse.swt.widgets.Composite.releaseWidget(Composite.java:368)\n        at org.eclipse.swt.widgets.Widget.releaseResources(Widget.java:725)\n        at org.eclipse.swt.widgets.Composite.releaseChildren(Composite.java:320)\n        at org.eclipse.swt.widgets.Composite.releaseWidget(Composite.java:368)\n        at org.eclipse.swt.widgets.Widget.releaseResources(Widget.java:725)\n        at org.eclipse.swt.widgets.Composite.releaseChildren(Composite.java:320)\n        at org.eclipse.swt.widgets.Composite.releaseWidget(Composite.java:368)\n        at org.eclipse.swt.widgets.Widget.releaseResources(Widget.java:725)\n        at org.eclipse.swt.widgets.Composite.releaseChildren(Composite.java:320)\n        at org.eclipse.swt.widgets.Composite.releaseWidget(Composite.java:368)\n        at org.eclipse.swt.widgets.Widget.releaseResources(Widget.java:725)\n        at org.eclipse.swt.widgets.Composite.releaseChildren(Composite.java:320)\n        at org.eclipse.swt.widgets.Composite.releaseWidget(Composite.java:368)\n        at org.eclipse.swt.widgets.Widget.releaseResources(Widget.java:725)\n        at org.eclipse.swt.widgets.Composite.releaseChildren(Composite.java:320)\n        at org.eclipse.swt.widgets.Composite.releaseWidget(Composite.java:368)\n        at org.eclipse.swt.widgets.Widget.releaseResources(Widget.java:725)\n        at org.eclipse.swt.widgets.Composite.releaseChildren(Composite.java:320)\n        at org.eclipse.swt.widgets.Composite.releaseWidget(Composite.java:368)\n        at org.eclipse.swt.widgets.Widget.releaseResources(Widget.java:725)\n        at org.eclipse.swt.widgets.Composite.releaseChildren(Composite.java:320)\n        at org.eclipse.swt.widgets.Composite.releaseWidget(Composite.java:368)\n        at org.eclipse.swt.widgets.Widget.releaseResources(Widget.java:725)\n        at org.eclipse.swt.widgets.Composite.releaseChildren(Composite.java:320)\n        at org.eclipse.swt.widgets.Composite.releaseWidget(Composite.java:368)\n        at org.eclipse.swt.widgets.Canvas.releaseWidget(Canvas.java:118)\n        at org.eclipse.swt.widgets.Decorations.releaseWidget\n(Decorations.java:632)\n        at org.eclipse.swt.widgets.Shell.releaseWidget(Shell.java:740)\n        at org.eclipse.swt.widgets.Widget.dispose(Widget.java:376)\n        at org.eclipse.swt.widgets.Decorations.dispose(Decorations.java:365)\n        at org.eclipse.swt.widgets.Shell.dispose(Shell.java:485)\n        at org.eclipse.jface.window.Window.close(Unknown Source)\n        at org.eclipse.jface.window.ApplicationWindow.close(Unknown Source)\n        at org.eclipse.ui.internal.WorkbenchWindow.hardClose(Unknown Source)\n        at org.eclipse.ui.internal.WorkbenchWindow.busyClose(Unknown Source)\n        at org.eclipse.ui.internal.WorkbenchWindow.access$3(Unknown Source)\n        at org.eclipse.ui.internal.WorkbenchWindow$2.run(Unknown Source)\n        at org.eclipse.swt.custom.BusyIndicator.showWhile(BusyIndicator.java:84)\n        at org.eclipse.ui.internal.WorkbenchWindow.close(Unknown Source)\n        at org.eclipse.jface.window.Window.handleShellCloseEvent(Unknown Source)\n        at org.eclipse.jface.window.Window$2.shellClosed(Unknown Source)\n        at org.eclipse.swt.widgets.TypedListener.handleEvent\n(TypedListener.java:154)\n        at org.eclipse.swt.widgets.EventTable.sendEvent(EventTable.java:82)\n        at org.eclipse.swt.widgets.Widget.sendEvent(Widget.java:848)\n        at org.eclipse.swt.widgets.Widget.sendEvent(Widget.java:872)\n        at org.eclipse.swt.widgets.Widget.sendEvent(Widget.java:857)\n        at org.eclipse.swt.widgets.Decorations.WM_CLOSE(Decorations.java:1359)\n        at org.eclipse.swt.widgets.Shell.WM_CLOSE(Shell.java:1220)\n        at org.eclipse.swt.widgets.Control.windowProc(Control.java:2874)\n        at org.eclipse.swt.widgets.Decorations.windowProc(Decorations.java:1303)\n        at org.eclipse.swt.widgets.Display.windowProc(Display.java:2713)\n        at org.eclipse.swt.internal.win32.OS.DefWindowProcW(Native Method)\n        at org.eclipse.swt.internal.win32.OS.DefWindowProc(OS.java:1333)\n        at org.eclipse.swt.widgets.Shell.callWindowProc(Shell.java:397)\n        at org.eclipse.swt.widgets.Control.windowProc(Control.java:2951)\n        at org.eclipse.swt.widgets.Decorations.windowProc(Decorations.java:1303)\n        at org.eclipse.swt.widgets.Display.windowProc(Display.java:2713)\n        at org.eclipse.swt.internal.win32.OS.DefWindowProcW(Native Method)\n        at org.eclipse.swt.internal.win32.OS.DefWindowProc(OS.java:1333)\n        at org.eclipse.swt.widgets.Shell.callWindowProc(Shell.java:397)\n        at org.eclipse.swt.widgets.Control.windowProc(Control.java:2951)\n        at org.eclipse.swt.widgets.Decorations.windowProc(Decorations.java:1303)\n        at org.eclipse.swt.widgets.Display.windowProc(Display.java:2713)\n        at org.eclipse.swt.internal.win32.OS.DispatchMessageW(Native Method)\n        at org.eclipse.swt.internal.win32.OS.DispatchMessage(OS.java:1338)\n        at org.eclipse.swt.widgets.Display.readAndDispatch(Display.java:1876)\n        at org.eclipse.ui.internal.Workbench.runEventLoop(Unknown Source)\n        at org.eclipse.ui.internal.Workbench.run(Unknown Source)\n        at org.eclipse.core.internal.boot.InternalBootLoader.run(Unknown Source)\n        at org.eclipse.core.boot.BootLoader.run(Unknown Source)\n        at sun.reflect.NativeMethodAccessorImpl.invoke0(Native Method)\n        at sun.reflect.NativeMethodAccessorImpl.invoke\n(NativeMethodAccessorImpl.java:39)\n        at sun.reflect.DelegatingMethodAccessorImpl.invoke\n(DelegatingMethodAccessorImpl.java:25)\n        at java.lang.reflect.Method.invoke(Method.java:324)\n        at org.eclipse.core.launcher.Main.basicRun(Unknown Source)\n        at org.eclipse.core.launcher.Main.run(Unknown Source)\n        at org.eclipse.core.launcher.Main.main(Unknown Source)\nAssertion failed:",
    "Doesn\u0027t look like a debugger problem - moving to text.",
    "Fixed in HEAD.\nMust fix for I20030717-rebuild.\n",
    "test case:\nopen two windows, open same file in both editors, close the editor in one window\nthen in the other.\n\nverified in I20030717-rebuild"
  ],
  "commentCreationDates": [
    "2003-07-17T12:59:44+02:00",
    "2003-07-17T13:00:44+02:00",
    "2003-07-17T15:18:42+02:00",
    "2003-07-17T18:23:35+02:00",
    "2003-07-18T15:45:52+02:00"
  ],
  "traces": [
    {
      "exceptionType": "java.lang.NullPointerException",
      "elements": [
        {
          "method": "org.eclipse.ui.internal.editors.quickdiff.LastSaveReferenceProvider.dispose",
          "source": "Unknown Source"
        },
        {
          "method": "org.eclipse.ui.internal.editors.quickdiff.DocumentLineDiffer.disconnect",
          "source": "Unknown  Source"
        },
        {
          "method": "org.eclipse.jface.text.source.AnnotationModel.disconnect",
          "source": "Unknown  Source"
        },
        {
          "method": "org.eclipse.jface.text.source.VisualAnnotationModel.disconnect",
          "source": "Unknown Source"
        },
        {
          "method": "org.eclipse.jface.text.source.SourceViewer.setDocument",
          "source": "Unknown  Source"
        },
        {
          "method": "org.eclipse.jface.text.source.SourceViewer.setDocument",
          "source": "Unknown  Source"
        },
        {
          "method": "org.eclipse.jface.text.TextViewer$1.widgetDisposed",
          "source": "Unknown Source"
        },
        {
          "method": "org.eclipse.swt.widgets.TypedListener.handleEvent",
          "source": "TypedListener.java:100"
        },
        {
          "method": "org.eclipse.swt.widgets.EventTable.sendEvent",
          "source": "EventTable.java:82"
        },
        {
          "method": "org.eclipse.swt.widgets.Widget.sendEvent",
          "source": "Widget.java:848"
        },
        {
          "method": "org.eclipse.swt.widgets.Widget.sendEvent",
          "source": "Widget.java:872"
        },
        {
          "method": "org.eclipse.swt.widgets.Widget.sendEvent",
          "source": "Widget.java:853"
        },
        {
          "method": "org.eclipse.swt.widgets.Widget.releaseWidget",
          "source": "Widget.java:760"
        },
        {
          "method": "org.eclipse.swt.widgets.Control.releaseWidget",
          "source": "Control.java:1421"
        },
        {
          "method": "org.eclipse.swt.widgets.Scrollable.releaseWidget",
          "source": "Scrollable.java:188"
        },
        {
          "method": "org.eclipse.swt.widgets.Composite.releaseWidget",
          "source": "Composite.java:369"
        },
        {
          "method": "org.eclipse.swt.widgets.Canvas.releaseWidget",
          "source": "Canvas.java:118"
        },
        {
          "method": "org.eclipse.swt.widgets.Widget.releaseResources",
          "source": "Widget.java:725"
        },
        {
          "method": "org.eclipse.swt.widgets.Composite.releaseChildren",
          "source": "Composite.java:320"
        },
        {
          "method": "org.eclipse.swt.widgets.Composite.releaseWidget",
          "source": "Composite.java:368"
        },
        {
          "method": "org.eclipse.swt.widgets.Canvas.releaseWidget",
          "source": "Canvas.java:118"
        },
        {
          "method": "org.eclipse.swt.widgets.Widget.releaseResources",
          "source": "Widget.java:725"
        },
        {
          "method": "org.eclipse.swt.widgets.Composite.releaseChildren",
          "source": "Composite.java:320"
        },
        {
          "method": "org.eclipse.swt.widgets.Composite.releaseWidget",
          "source": "Composite.java:368"
        },
        {
          "method": "org.eclipse.swt.widgets.Widget.releaseResources",
          "source": "Widget.java:725"
        },
        {
          "method": "org.eclipse.swt.widgets.Composite.releaseChildren",
          "source": "Composite.java:320"
        },
        {
          "method": "org.eclipse.swt.widgets.Composite.releaseWidget",
          "source": "Composite.java:368"
        },
        {
          "method": "org.eclipse.swt.widgets.Widget.releaseResources",
          "source": "Widget.java:725"
        },
        {
          "method": "org.eclipse.swt.widgets.Composite.releaseChildren",
          "source": "Composite.java:320"
        },
        {
          "method": "org.eclipse.swt.widgets.Composite.releaseWidget",
          "source": "Composite.java:368"
        },
        {
          "method": "org.eclipse.swt.widgets.Widget.releaseResources",
          "source": "Widget.java:725"
        },
        {
          "method": "org.eclipse.swt.widgets.Composite.releaseChildren",
          "source": "Composite.java:320"
        },
        {
          "method": "org.eclipse.swt.widgets.Composite.releaseWidget",
          "source": "Composite.java:368"
        },
        {
          "method": "org.eclipse.swt.widgets.Widget.releaseResources",
          "source": "Widget.java:725"
        },
        {
          "method": "org.eclipse.swt.widgets.Composite.releaseChildren",
          "source": "Composite.java:320"
        },
        {
          "method": "org.eclipse.swt.widgets.Composite.releaseWidget",
          "source": "Composite.java:368"
        },
        {
          "method": "org.eclipse.swt.widgets.Widget.releaseResources",
          "source": "Widget.java:725"
        },
        {
          "method": "org.eclipse.swt.widgets.Composite.releaseChildren",
          "source": "Composite.java:320"
        },
        {
          "method": "org.eclipse.swt.widgets.Composite.releaseWidget",
          "source": "Composite.java:368"
        },
        {
          "method": "org.eclipse.swt.widgets.Widget.dispose",
          "source": "Widget.java:376"
        },
        {
          "method": "org.eclipse.ui.internal.PartPane.dispose",
          "source": "Unknown Source"
        },
        {
          "method": "org.eclipse.ui.internal.EditorPresentation.closeEditor",
          "source": "Unknown  Source"
        },
        {
          "method": "org.eclipse.ui.internal.EditorPresentation.closeEditor",
          "source": "Unknown  Source"
        },
        {
          "method": "org.eclipse.ui.internal.EditorManager.closeEditor",
          "source": "Unknown Source"
        },
        {
          "method": "org.eclipse.ui.internal.WorkbenchPage.closeEditor",
          "source": "Unknown Source"
        },
        {
          "method": "org.eclipse.debug.internal.ui.views.launch.LaunchView.openEditor",
          "source": "Unknown Source"
        },
        {
          "method": "org.eclipse.debug.internal.ui.views.launch.LaunchView.openEditorForStackFrame",
          "source": "Unknown Source"
        },
        {
          "method": "org.eclipse.debug.internal.ui.views.launch.LaunchView.showEditorForCurrentSelection",
          "source": "Unknown Source"
        },
        {
          "method": "org.eclipse.debug.internal.ui.views.launch.LaunchView.selectionChanged",
          "source": "Unknown  Source"
        },
        {
          "method": "org.eclipse.jface.viewers.Viewer$2.run",
          "source": "Unknown Source"
        },
        {
          "method": "org.eclipse.core.internal.runtime.InternalPlatform.run",
          "source": "Unknown  Source"
        },
        {
          "method": "org.eclipse.core.runtime.Platform.run",
          "source": "Unknown Source"
        },
        {
          "method": "org.eclipse.jface.viewers.Viewer.fireSelectionChanged",
          "source": "Unknown Source"
        },
        {
          "method": "org.eclipse.jface.viewers.StructuredViewer.updateSelection",
          "source": "Unknown  Source"
        },
        {
          "method": "org.eclipse.jface.viewers.StructuredViewer.setSelection",
          "source": "Unknown  Source"
        },
        {
          "method": "org.eclipse.debug.internal.ui.views.launch.LaunchView.autoExpand",
          "source": "Unknown Source"
        },
        {
          "method": "org.eclipse.debug.internal.ui.views.launch.LaunchViewEventHandler.doHandleSuspendThreadEvent",
          "source": "Unknown Source"
        },
        {
          "method": "org.eclipse.debug.internal.ui.views.launch.LaunchViewEventHandler.doHandleSuspendEvent",
          "source": "Unknown Source"
        },
        {
          "method": "org.eclipse.debug.internal.ui.views.launch.LaunchViewEventHandler.doHandleDebugEvents",
          "source": "Unknown Source"
        },
        {
          "method": "org.eclipse.debug.internal.ui.views.AbstractDebugEventHandler$1.run",
          "source": "Unknown Source"
        },
        {
          "method": "org.eclipse.swt.widgets.RunnableLock.run",
          "source": "RunnableLock.java:35"
        },
        {
          "method": "org.eclipse.swt.widgets.Synchronizer.runAsyncMessages",
          "source": "Synchronizer.java:102"
        },
        {
          "method": "org.eclipse.swt.widgets.Display.runAsyncMessages",
          "source": "Display.java:2165"
        },
        {
          "method": "org.eclipse.swt.widgets.Display.readAndDispatch",
          "source": "Display.java:1882"
        },
        {
          "method": "org.eclipse.ui.internal.Workbench.runEventLoop",
          "source": "Unknown Source"
        },
        {
          "method": "org.eclipse.ui.internal.Workbench.run",
          "source": "Unknown Source"
        },
        {
          "method": "org.eclipse.core.internal.boot.InternalBootLoader.run",
          "source": "Unknown Source"
        },
        {
          "method": "org.eclipse.core.boot.BootLoader.run",
          "source": "Unknown Source"
        },
        {
          "method": "sun.reflect.NativeMethodAccessorImpl.invoke0",
          "source": "Native Method"
        },
        {
          "method": "sun.reflect.NativeMethodAccessorImpl.invoke",
          "source": "NativeMethodAccessorImpl.java:39"
        },
        {
          "method": "sun.reflect.DelegatingMethodAccessorImpl.invoke",
          "source": "DelegatingMethodAccessorImpl.java:25"
        },
        {
          "method": "java.lang.reflect.Method.invoke",
          "source": "Method.java:324"
        },
        {
          "method": "org.eclipse.core.launcher.Main.basicRun",
          "source": "Unknown Source"
        },
        {
          "method": "org.eclipse.core.launcher.Main.run",
          "source": "Unknown Source"
        },
        {
          "method": "org.eclipse.core.launcher.Main.main",
          "source": "Unknown Source"
        }
      ],
      "number": 0,
      "commentIndex": 0,
      "bugId": "40319",
      "date": "2003-07-17T12:59:44+02:00",
      "product": "Platform",
      "component": "Text",
      "severity": "critical"
    },
    {
      "exceptionType": "org.eclipse.jface.text.Assert$AssertionFailedException",
      "message": "Assertion failed:",
      "elements": [
        {
          "method": "org.eclipse.jface.text.Assert.isTrue",
          "source": "Unknown Source"
        },
        {
          "method": "org.eclipse.jface.text.Assert.isTrue",
          "source": "Unknown Source"
        },
        {
          "method": "org.eclipse.jface.text.source.AnnotationModel.disconnect",
          "source": "Unknown  Source"
        },
        {
          "method": "org.eclipse.jface.text.source.VisualAnnotationModel.disconnect",
          "source": "Unknown Source"
        },
        {
          "method": "org.eclipse.jface.text.source.SourceViewer.setDocument",
          "source": "Unknown  Source"
        },
        {
          "method": "org.eclipse.jface.text.source.SourceViewer.setDocument",
          "source": "Unknown  Source"
        },
        {
          "method": "org.eclipse.jface.text.TextViewer$1.widgetDisposed",
          "source": "Unknown Source"
        },
        {
          "method": "org.eclipse.swt.widgets.TypedListener.handleEvent",
          "source": "TypedListener.java:100"
        },
        {
          "method": "org.eclipse.swt.widgets.EventTable.sendEvent",
          "source": "EventTable.java:82"
        },
        {
          "method": "org.eclipse.swt.widgets.Widget.sendEvent",
          "source": "Widget.java:848"
        },
        {
          "method": "org.eclipse.swt.widgets.Widget.sendEvent",
          "source": "Widget.java:872"
        },
        {
          "method": "org.eclipse.swt.widgets.Widget.sendEvent",
          "source": "Widget.java:853"
        },
        {
          "method": "org.eclipse.swt.widgets.Widget.releaseWidget",
          "source": "Widget.java:760"
        },
        {
          "method": "org.eclipse.swt.widgets.Control.releaseWidget",
          "source": "Control.java:1421"
        },
        {
          "method": "org.eclipse.swt.widgets.Scrollable.releaseWidget",
          "source": "Scrollable.java:188"
        },
        {
          "method": "org.eclipse.swt.widgets.Composite.releaseWidget",
          "source": "Composite.java:369"
        },
        {
          "method": "org.eclipse.swt.widgets.Canvas.releaseWidget",
          "source": "Canvas.java:118"
        },
        {
          "method": "org.eclipse.swt.widgets.Widget.releaseResources",
          "source": "Widget.java:725"
        },
        {
          "method": "org.eclipse.swt.widgets.Composite.releaseChildren",
          "source": "Composite.java:320"
        },
        {
          "method": "org.eclipse.swt.widgets.Composite.releaseWidget",
          "source": "Composite.java:368"
        },
        {
          "method": "org.eclipse.swt.widgets.Canvas.releaseWidget",
          "source": "Canvas.java:118"
        },
        {
          "method": "org.eclipse.swt.widgets.Widget.releaseResources",
          "source": "Widget.java:725"
        },
        {
          "method": "org.eclipse.swt.widgets.Composite.releaseChildren",
          "source": "Composite.java:320"
        },
        {
          "method": "org.eclipse.swt.widgets.Composite.releaseWidget",
          "source": "Composite.java:368"
        },
        {
          "method": "org.eclipse.swt.widgets.Widget.releaseResources",
          "source": "Widget.java:725"
        },
        {
          "method": "org.eclipse.swt.widgets.Composite.releaseChildren",
          "source": "Composite.java:320"
        },
        {
          "method": "org.eclipse.swt.widgets.Composite.releaseWidget",
          "source": "Composite.java:368"
        },
        {
          "method": "org.eclipse.swt.widgets.Widget.releaseResources",
          "source": "Widget.java:725"
        },
        {
          "method": "org.eclipse.swt.widgets.Composite.releaseChildren",
          "source": "Composite.java:320"
        },
        {
          "method": "org.eclipse.swt.widgets.Composite.releaseWidget",
          "source": "Composite.java:368"
        },
        {
          "method": "org.eclipse.swt.widgets.Widget.releaseResources",
          "source": "Widget.java:725"
        },
        {
          "method": "org.eclipse.swt.widgets.Composite.releaseChildren",
          "source": "Composite.java:320"
        },
        {
          "method": "org.eclipse.swt.widgets.Composite.releaseWidget",
          "source": "Composite.java:368"
        },
        {
          "method": "org.eclipse.swt.widgets.Widget.releaseResources",
          "source": "Widget.java:725"
        },
        {
          "method": "org.eclipse.swt.widgets.Composite.releaseChildren",
          "source": "Composite.java:320"
        },
        {
          "method": "org.eclipse.swt.widgets.Composite.releaseWidget",
          "source": "Composite.java:368"
        },
        {
          "method": "org.eclipse.swt.widgets.Widget.releaseResources",
          "source": "Widget.java:725"
        },
        {
          "method": "org.eclipse.swt.widgets.Composite.releaseChildren",
          "source": "Composite.java:320"
        },
        {
          "method": "org.eclipse.swt.widgets.Composite.releaseWidget",
          "source": "Composite.java:368"
        },
        {
          "method": "org.eclipse.swt.widgets.Widget.releaseResources",
          "source": "Widget.java:725"
        },
        {
          "method": "org.eclipse.swt.widgets.Composite.releaseChildren",
          "source": "Composite.java:320"
        },
        {
          "method": "org.eclipse.swt.widgets.Composite.releaseWidget",
          "source": "Composite.java:368"
        },
        {
          "method": "org.eclipse.swt.widgets.Widget.releaseResources",
          "source": "Widget.java:725"
        },
        {
          "method": "org.eclipse.swt.widgets.Composite.releaseChildren",
          "source": "Composite.java:320"
        },
        {
          "method": "org.eclipse.swt.widgets.Composite.releaseWidget",
          "source": "Composite.java:368"
        },
        {
          "method": "org.eclipse.swt.widgets.Widget.releaseResources",
          "source": "Widget.java:725"
        },
        {
          "method": "org.eclipse.swt.widgets.Composite.releaseChildren",
          "source": "Composite.java:320"
        },
        {
          "method": "org.eclipse.swt.widgets.Composite.releaseWidget",
          "source": "Composite.java:368"
        },
        {
          "method": "org.eclipse.swt.widgets.Widget.releaseResources",
          "source": "Widget.java:725"
        },
        {
          "method": "org.eclipse.swt.widgets.Composite.releaseChildren",
          "source": "Composite.java:320"
        },
        {
          "method": "org.eclipse.swt.widgets.Composite.releaseWidget",
          "source": "Composite.java:368"
        },
        {
          "method": "org.eclipse.swt.widgets.Canvas.releaseWidget",
          "source": "Canvas.java:118"
        },
        {
          "method": "org.eclipse.swt.widgets.Decorations.releaseWidget",
          "source": "Decorations.java:632"
        },
        {
          "method": "org.eclipse.swt.widgets.Shell.releaseWidget",
          "source": "Shell.java:740"
        },
        {
          "method": "org.eclipse.swt.widgets.Widget.dispose",
          "source": "Widget.java:376"
        },
        {
          "method": "org.eclipse.swt.widgets.Decorations.dispose",
          "source": "Decorations.java:365"
        },
        {
          "method": "org.eclipse.swt.widgets.Shell.dispose",
          "source": "Shell.java:485"
        },
        {
          "method": "org.eclipse.jface.window.Window.close",
          "source": "Unknown Source"
        },
        {
          "method": "org.eclipse.jface.window.ApplicationWindow.close",
          "source": "Unknown Source"
        },
        {
          "method": "org.eclipse.ui.internal.WorkbenchWindow.hardClose",
          "source": "Unknown Source"
        },
        {
          "method": "org.eclipse.ui.internal.WorkbenchWindow.busyClose",
          "source": "Unknown Source"
        },
        {
          "method": "org.eclipse.ui.internal.WorkbenchWindow.access$3",
          "source": "Unknown Source"
        },
        {
          "method": "org.eclipse.ui.internal.WorkbenchWindow$2.run",
          "source": "Unknown Source"
        },
        {
          "method": "org.eclipse.swt.custom.BusyIndicator.showWhile",
          "source": "BusyIndicator.java:84"
        },
        {
          "method": "org.eclipse.ui.internal.WorkbenchWindow.close",
          "source": "Unknown Source"
        },
        {
          "method": "org.eclipse.jface.window.Window.handleShellCloseEvent",
          "source": "Unknown Source"
        },
        {
          "method": "org.eclipse.jface.window.Window$2.shellClosed",
          "source": "Unknown Source"
        },
        {
          "method": "org.eclipse.swt.widgets.TypedListener.handleEvent",
          "source": "TypedListener.java:154"
        },
        {
          "method": "org.eclipse.swt.widgets.EventTable.sendEvent",
          "source": "EventTable.java:82"
        },
        {
          "method": "org.eclipse.swt.widgets.Widget.sendEvent",
          "source": "Widget.java:848"
        },
        {
          "method": "org.eclipse.swt.widgets.Widget.sendEvent",
          "source": "Widget.java:872"
        },
        {
          "method": "org.eclipse.swt.widgets.Widget.sendEvent",
          "source": "Widget.java:857"
        },
        {
          "method": "org.eclipse.swt.widgets.Decorations.WM_CLOSE",
          "source": "Decorations.java:1359"
        },
        {
          "method": "org.eclipse.swt.widgets.Shell.WM_CLOSE",
          "source": "Shell.java:1220"
        },
        {
          "method": "org.eclipse.swt.widgets.Control.windowProc",
          "source": "Control.java:2874"
        },
        {
          "method": "org.eclipse.swt.widgets.Decorations.windowProc",
          "source": "Decorations.java:1303"
        },
        {
          "method": "org.eclipse.swt.widgets.Display.windowProc",
          "source": "Display.java:2713"
        },
        {
          "method": "org.eclipse.swt.internal.win32.OS.DefWindowProcW",
          "source": "Native Method"
        },
        {
          "method": "org.eclipse.swt.internal.win32.OS.DefWindowProc",
          "source": "OS.java:1333"
        },
        {
          "method": "org.eclipse.swt.widgets.Shell.callWindowProc",
          "source": "Shell.java:397"
        },
        {
          "method": "org.eclipse.swt.widgets.Control.windowProc",
          "source": "Control.java:2951"
        },
        {
          "method": "org.eclipse.swt.widgets.Decorations.windowProc",
          "source": "Decorations.java:1303"
        },
        {
          "method": "org.eclipse.swt.widgets.Display.windowProc",
          "source": "Display.java:2713"
        },
        {
          "method": "org.eclipse.swt.internal.win32.OS.DefWindowProcW",
          "source": "Native Method"
        },
        {
          "method": "org.eclipse.swt.internal.win32.OS.DefWindowProc",
          "source": "OS.java:1333"
        },
        {
          "method": "org.eclipse.swt.widgets.Shell.callWindowProc",
          "source": "Shell.java:397"
        },
        {
          "method": "org.eclipse.swt.widgets.Control.windowProc",
          "source": "Control.java:2951"
        },
        {
          "method": "org.eclipse.swt.widgets.Decorations.windowProc",
          "source": "Decorations.java:1303"
        },
        {
          "method": "org.eclipse.swt.widgets.Display.windowProc",
          "source": "Display.java:2713"
        },
        {
          "method": "org.eclipse.swt.internal.win32.OS.DispatchMessageW",
          "source": "Native Method"
        },
        {
          "method": "org.eclipse.swt.internal.win32.OS.DispatchMessage",
          "source": "OS.java:1338"
        },
        {
          "method": "org.eclipse.swt.widgets.Display.readAndDispatch",
          "source": "Display.java:1876"
        },
        {
          "method": "org.eclipse.ui.internal.Workbench.runEventLoop",
          "source": "Unknown Source"
        },
        {
          "method": "org.eclipse.ui.internal.Workbench.run",
          "source": "Unknown Source"
        },
        {
          "method": "org.eclipse.core.internal.boot.InternalBootLoader.run",
          "source": "Unknown Source"
        },
        {
          "method": "org.eclipse.core.boot.BootLoader.run",
          "source": "Unknown Source"
        },
        {
          "method": "sun.reflect.NativeMethodAccessorImpl.invoke0",
          "source": "Native Method"
        },
        {
          "method": "sun.reflect.NativeMethodAccessorImpl.invoke",
          "source": "NativeMethodAccessorImpl.java:39"
        },
        {
          "method": "sun.reflect.DelegatingMethodAccessorImpl.invoke",
          "source": "DelegatingMethodAccessorImpl.java:25"
        },
        {
          "method": "java.lang.reflect.Method.invoke",
          "source": "Method.java:324"
        },
        {
          "method": "org.eclipse.core.launcher.Main.basicRun",
          "source": "Unknown Source"
        },
        {
          "method": "org.eclipse.core.launcher.Main.run",
          "source": "Unknown Source"
        },
        {
          "method": "org.eclipse.core.launcher.Main.main",
          "source": "Unknown Source"
        }
      ],
      "number": 1,
      "commentIndex": 1,
      "bugId": "40319",
      "date": "2003-07-17T13:00:44+02:00",
      "product": "Platform",
      "component": "Text",
      "severity": "critical"
    }
  ],
  "groupId": "40319",
  "bugId": "40319",
  "date": "2003-07-17T12:59:44+02:00",
  "product": "Platform",
  "component": "Text",
  "severity": "critical"
}