{
  "comments": [
    "Build 20030716\n\nIf the compiler throws an internal error, it is captured into an extra problem. \nIf the compiler failure arises during reconciling (with problem detection), \nthen the exception is surfaced, possibly damaging all tools in the vicinity.\n\nFor instance, due to bug 40288, I couldn\u0027t open other types in editor \ncorrectly, since the offending original type kept throwing exceptions when the \nmodel was trying to populate it.",
    "Example of issues logged with steps from bug 40288, and trying to open \nNegativeTest.\n\njava.lang.NullPointerException\n        at \norg.eclipse.jdt.internal.compiler.lookup.CompilationUnitScope.recordTypeReferenc\nes(Unknown Source)\n        at org.eclipse.jdt.internal.compiler.lookup.Scope.findExactMethod\n(Unknown Source)\n        at org.eclipse.jdt.internal.compiler.lookup.BlockScope.getImplicitMethod\n(Unknown Source)\n        at \norg.eclipse.jdt.internal.compiler.ast.CastExpression.checkAlternateBinding\n(Unknown Source)\n        at \norg.eclipse.jdt.internal.compiler.ast.CastExpression.checkNeedForArgumentCasts\n(Unknown Source)\n        at org.eclipse.jdt.internal.compiler.ast.MessageSend.resolveType\n(Unknown Source)\n        at org.eclipse.jdt.internal.compiler.ast.Expression.resolve(Unknown \nSource)\n        at \norg.eclipse.jdt.internal.compiler.ast.AbstractMethodDeclaration.resolveStatement\ns(Unknown Source)\n        at \norg.eclipse.jdt.internal.compiler.ast.MethodDeclaration.resolveStatements\n(Unknown Source)\n        at \norg.eclipse.jdt.internal.compiler.ast.AbstractMethodDeclaration.resolve(Unknown \nSource)\n        at org.eclipse.jdt.internal.compiler.ast.TypeDeclaration.resolve\n(Unknown Source)\n        at org.eclipse.jdt.internal.compiler.ast.TypeDeclaration.resolve\n(Unknown Source)\n        at \norg.eclipse.jdt.internal.compiler.ast.CompilationUnitDeclaration.resolve\n(Unknown Source)\n        at org.eclipse.jdt.internal.compiler.Compiler.resolve(Unknown Source)\n        at org.eclipse.jdt.internal.core.CompilationUnitProblemFinder.process\n(Unknown Source)\n        at org.eclipse.jdt.internal.core.CompilationUnit.buildStructure(Unknown \nSource)\n        at org.eclipse.jdt.internal.core.Openable.generateInfos(Unknown Source)\n        at org.eclipse.jdt.internal.core.JavaElement.openWhenClosed(Unknown \nSource)\n        at org.eclipse.jdt.internal.core.CompilationUnit.makeConsistent(Unknown \nSource)\n        at \norg.eclipse.jdt.internal.core.ReconcileWorkingCopyOperation.executeOperation\n(Unknown Source)\n        at org.eclipse.jdt.internal.core.JavaModelOperation.execute(Unknown \nSource)\n        at org.eclipse.jdt.internal.core.JavaModelOperation.run(Unknown Source)\n        at org.eclipse.jdt.internal.core.JavaElement.runOperation(Unknown \nSource)\n        at org.eclipse.jdt.internal.core.CompilationUnit.reconcile(Unknown \nSource)\n        at org.eclipse.jdt.internal.core.CompilationUnit.reconcile(Unknown \nSource)\n        at org.eclipse.jdt.internal.core.CompilationUnit.reconcile(Unknown \nSource)\n        at \norg.eclipse.jdt.internal.ui.javaeditor.CompilationUnitDocumentProvider.doSaveDoc\nument(Unknown Source)\n        at org.eclipse.ui.texteditor.AbstractDocumentProvider.saveDocument\n(Unknown Source)\n        at org.eclipse.ui.texteditor.AbstractTextEditor$11.execute(Unknown \nSource)\n        at org.eclipse.ui.actions.WorkspaceModifyOperation$1.run(Unknown Source)\n        at org.eclipse.core.internal.resources.Workspace.run(Unknown Source)\n        at org.eclipse.ui.actions.WorkspaceModifyOperation.run(Unknown Source)\n        at org.eclipse.ui.texteditor.AbstractTextEditor.performSaveOperation\n(Unknown Source)\n        at \norg.eclipse.jdt.internal.ui.javaeditor.CompilationUnitEditor.performSaveOperatio\nn(Unknown Source)\n        at org.eclipse.jdt.internal.ui.javaeditor.CompilationUnitEditor.doSave\n(Unknown Source)\n        at org.eclipse.ui.internal.EditorManager$11.run(Unknown Source)\n        at org.eclipse.ui.internal.EditorManager$8.run(Unknown Source)\n        at org.eclipse.jface.operation.ModalContext.runInCurrentThread(Unknown \nSource)\n        at org.eclipse.jface.operation.ModalContext.run(Unknown Source)\n        at org.eclipse.jface.window.ApplicationWindow$1.run(Unknown Source)\n        at org.eclipse.swt.custom.BusyIndicator.showWhile(BusyIndicator.java:84)\n        at org.eclipse.jface.window.ApplicationWindow.run(Unknown Source)\n        at org.eclipse.ui.internal.WorkbenchWindow.run(Unknown Source)\n        at org.eclipse.ui.internal.EditorManager.runProgressMonitorOperation\n(Unknown Source)\n        at org.eclipse.ui.internal.EditorManager.savePart(Unknown Source)\n        at org.eclipse.ui.internal.WorkbenchPage.savePart(Unknown Source)\n        at org.eclipse.ui.internal.WorkbenchPage.saveEditor(Unknown Source)\n        at org.eclipse.ui.internal.SaveAction.run(Unknown Source)\n        at org.eclipse.jface.action.Action.runWithEvent(Unknown Source)\n        at org.eclipse.ui.internal.commands.old.ActionHandler.execute(Unknown \nSource)\n        at org.eclipse.ui.internal.commands.old.ContextAndHandlerManager.pressed\n(Unknown Source)\n        at \norg.eclipse.ui.internal.commands.old.ContextAndHandlerManager.access$1(Unknown \nSource)\n        at \norg.eclipse.ui.internal.commands.old.ContextAndHandlerManager$7.widgetSelected\n(Unknown Source)\n        at org.eclipse.ui.internal.AcceleratorMenu$2.handleEvent(Unknown Source)\n        at org.eclipse.swt.widgets.EventTable.sendEvent(EventTable.java:82)\n        at org.eclipse.swt.widgets.Widget.sendEvent(Widget.java:848)\n        at org.eclipse.swt.widgets.Display.runDeferredEvents(Display.java:2188)\n        at org.eclipse.swt.widgets.Display.readAndDispatch(Display.java:1878)\n        at org.eclipse.ui.internal.Workbench.runEventLoop(Unknown Source)\n        at org.eclipse.ui.internal.Workbench.run(Unknown Source)\n        at org.eclipse.core.internal.boot.InternalBootLoader.run(Unknown Source)\n        at org.eclipse.core.boot.BootLoader.run(Unknown Source)\n        at sun.reflect.NativeMethodAccessorImpl.invoke0(Native Method)\n        at sun.reflect.NativeMethodAccessorImpl.invoke\n(NativeMethodAccessorImpl.java:39)\n        at sun.reflect.DelegatingMethodAccessorImpl.invoke\n(DelegatingMethodAccessorImpl.java:25)\n        at java.lang.reflect.Method.invoke(Method.java:324)\n        at org.eclipse.core.launcher.Main.basicRun(Unknown Source)\n        at org.eclipse.core.launcher.Main.run(Unknown Source)\n        at org.eclipse.core.launcher.Main.main(Unknown Source)\n!ENTRY org.eclipse.ui 4 4 Jul 17, 2003 13:55:19.706\n!MESSAGE Save Failed\nSave Failed\nReason:\n!ENTRY org.eclipse.ui 2 0 Jul 17, 2003 13:55:19.722\n!MESSAGE Save Failed\n!STACK 0\njava.lang.NullPointerException\n        at \norg.eclipse.jdt.internal.compiler.lookup.CompilationUnitScope.recordTypeReferenc\nes(Unknown Source)\n        at org.eclipse.jdt.internal.compiler.lookup.Scope.findExactMethod\n(Unknown Source)\n        at org.eclipse.jdt.internal.compiler.lookup.BlockScope.getImplicitMethod\n(Unknown Source)\n        at \norg.eclipse.jdt.internal.compiler.ast.CastExpression.checkAlternateBinding\n(Unknown Source)\n        at \norg.eclipse.jdt.internal.compiler.ast.CastExpression.checkNeedForArgumentCasts\n(Unknown Source)\n        at org.eclipse.jdt.internal.compiler.ast.MessageSend.resolveType\n(Unknown Source)\n        at org.eclipse.jdt.internal.compiler.ast.Expression.resolve(Unknown \nSource)\n        at \norg.eclipse.jdt.internal.compiler.ast.AbstractMethodDeclaration.resolveStatement\ns(Unknown Source)\n        at \norg.eclipse.jdt.internal.compiler.ast.MethodDeclaration.resolveStatements\n(Unknown Source)\n        at \norg.eclipse.jdt.internal.compiler.ast.AbstractMethodDeclaration.resolve(Unknown \nSource)\n        at org.eclipse.jdt.internal.compiler.ast.TypeDeclaration.resolve\n(Unknown Source)\n        at org.eclipse.jdt.internal.compiler.ast.TypeDeclaration.resolve\n(Unknown Source)\n        at \norg.eclipse.jdt.internal.compiler.ast.CompilationUnitDeclaration.resolve\n(Unknown Source)\n        at org.eclipse.jdt.internal.compiler.Compiler.resolve(Unknown Source)\n        at org.eclipse.jdt.internal.core.CompilationUnitProblemFinder.process\n(Unknown Source)\n        at org.eclipse.jdt.internal.core.CompilationUnit.buildStructure(Unknown \nSource)\n        at org.eclipse.jdt.internal.core.Openable.generateInfos(Unknown Source)\n        at org.eclipse.jdt.internal.core.JavaElement.openWhenClosed(Unknown \nSource)\n        at org.eclipse.jdt.internal.core.CompilationUnit.makeConsistent(Unknown \nSource)\n        at \norg.eclipse.jdt.internal.core.ReconcileWorkingCopyOperation.executeOperation\n(Unknown Source)\n        at org.eclipse.jdt.internal.core.JavaModelOperation.execute(Unknown \nSource)\n        at org.eclipse.jdt.internal.core.JavaModelOperation.run(Unknown Source)\n        at org.eclipse.jdt.internal.core.JavaElement.runOperation(Unknown \nSource)\n        at org.eclipse.jdt.internal.core.CompilationUnit.reconcile(Unknown \nSource)\n        at org.eclipse.jdt.internal.core.CompilationUnit.reconcile(Unknown \nSource)\n        at org.eclipse.jdt.internal.core.CompilationUnit.reconcile(Unknown \nSource)\n        at \norg.eclipse.jdt.internal.ui.javaeditor.CompilationUnitDocumentProvider.doSaveDoc\nument(Unknown Source)\n        at org.eclipse.ui.texteditor.AbstractDocumentProvider.saveDocument\n(Unknown Source)\n        at org.eclipse.ui.texteditor.AbstractTextEditor$11.execute(Unknown \nSource)\n        at org.eclipse.ui.actions.WorkspaceModifyOperation$1.run(Unknown Source)\n        at org.eclipse.core.internal.resources.Workspace.run(Unknown Source)\n        at org.eclipse.ui.actions.WorkspaceModifyOperation.run(Unknown Source)\n        at org.eclipse.ui.texteditor.AbstractTextEditor.performSaveOperation\n(Unknown Source)\n        at \norg.eclipse.jdt.internal.ui.javaeditor.CompilationUnitEditor.performSaveOperatio\nn(Unknown Source)\n        at org.eclipse.jdt.internal.ui.javaeditor.CompilationUnitEditor.doSave\n(Unknown Source)\n        at org.eclipse.ui.internal.EditorManager$11.run(Unknown Source)\n        at org.eclipse.ui.internal.EditorManager$8.run(Unknown Source)\n        at org.eclipse.jface.operation.ModalContext.runInCurrentThread(Unknown \nSource)\n        at org.eclipse.jface.operation.ModalContext.run(Unknown Source)\n        at org.eclipse.jface.window.ApplicationWindow$1.run(Unknown Source)\n        at org.eclipse.swt.custom.BusyIndicator.showWhile(BusyIndicator.java:84)\n        at org.eclipse.jface.window.ApplicationWindow.run(Unknown Source)\n        at org.eclipse.ui.internal.WorkbenchWindow.run(Unknown Source)\n        at org.eclipse.ui.internal.EditorManager.runProgressMonitorOperation\n(Unknown Source)\n        at org.eclipse.ui.internal.EditorManager.savePart(Unknown Source)\n        at org.eclipse.ui.internal.WorkbenchPage.savePart(Unknown Source)\n        at org.eclipse.ui.internal.WorkbenchPage.saveEditor(Unknown Source)\n        at org.eclipse.ui.internal.SaveAction.run(Unknown Source)\n        at org.eclipse.jface.action.Action.runWithEvent(Unknown Source)\n        at org.eclipse.ui.internal.commands.old.ActionHandler.execute(Unknown \nSource)\n        at org.eclipse.ui.internal.commands.old.ContextAndHandlerManager.pressed\n(Unknown Source)\n        at \norg.eclipse.ui.internal.commands.old.ContextAndHandlerManager.access$1(Unknown \nSource)\n        at \norg.eclipse.ui.internal.commands.old.ContextAndHandlerManager$7.widgetSelected\n(Unknown Source)\n        at org.eclipse.ui.internal.AcceleratorMenu$2.handleEvent(Unknown Source)\n        at org.eclipse.swt.widgets.EventTable.sendEvent(EventTable.java:82)\n        at org.eclipse.swt.widgets.Widget.sendEvent(Widget.java:848)\n        at org.eclipse.swt.widgets.Display.runDeferredEvents(Display.java:2188)\n        at org.eclipse.swt.widgets.Display.readAndDispatch(Display.java:1878)\n        at org.eclipse.ui.internal.Workbench.runEventLoop(Unknown Source)\n        at org.eclipse.ui.internal.Workbench.run(Unknown Source)\n        at org.eclipse.core.internal.boot.InternalBootLoader.run(Unknown Source)\n        at org.eclipse.core.boot.BootLoader.run(Unknown Source)\n        at sun.reflect.NativeMethodAccessorImpl.invoke0(Native Method)\n        at sun.reflect.NativeMethodAccessorImpl.invoke\n(NativeMethodAccessorImpl.java:39)\n        at sun.reflect.DelegatingMethodAccessorImpl.invoke\n(DelegatingMethodAccessorImpl.java:25)\n        at java.lang.reflect.Method.invoke(Method.java:324)\n        at org.eclipse.core.launcher.Main.basicRun(Unknown Source)\n        at org.eclipse.core.launcher.Main.run(Unknown Source)\n        at org.eclipse.core.launcher.Main.main(Unknown Source)\nSave Failed\njava.lang.NullPointerException\n        at \norg.eclipse.jdt.internal.compiler.lookup.CompilationUnitScope.recordTypeReferenc\nes(Unknown Source)\n        at org.eclipse.jdt.internal.compiler.lookup.Scope.findExactMethod\n(Unknown Source)\n        at org.eclipse.jdt.internal.compiler.lookup.BlockScope.getImplicitMethod\n(Unknown Source)\n        at \norg.eclipse.jdt.internal.compiler.ast.CastExpression.checkAlternateBinding\n(Unknown Source)\n        at \norg.eclipse.jdt.internal.compiler.ast.CastExpression.checkNeedForArgumentCasts\n(Unknown Source)\n        at org.eclipse.jdt.internal.compiler.ast.MessageSend.resolveType\n(Unknown Source)\n        at org.eclipse.jdt.internal.compiler.ast.Expression.resolve(Unknown \nSource)\n        at \norg.eclipse.jdt.internal.compiler.ast.AbstractMethodDeclaration.resolveStatement\ns(Unknown Source)\n        at \norg.eclipse.jdt.internal.compiler.ast.MethodDeclaration.resolveStatements\n(Unknown Source)\n        at \norg.eclipse.jdt.internal.compiler.ast.AbstractMethodDeclaration.resolve(Unknown \nSource)\n        at org.eclipse.jdt.internal.compiler.ast.TypeDeclaration.resolve\n(Unknown Source)\n        at org.eclipse.jdt.internal.compiler.ast.TypeDeclaration.resolve\n(Unknown Source)\n\n...\n\nlots of them ...        ",
    "Changed CompilationUnitProblemFinder to log runtime exceptions, and convert \nthem in JavaModelException (with compiler failure status).\n\nFixed",
    "Verified."
  ],
  "commentCreationDates": [
    "2003-07-17T13:52:27+02:00",
    "2003-07-17T14:05:07+02:00",
    "2003-07-17T17:10:22+02:00",
    "2003-08-28T10:47:24+02:00"
  ],
  "traces": [
    {
      "exceptionType": "java.lang.NullPointerException",
      "elements": [
        {
          "method": "org.eclipse.jdt.internal.compiler.lookup.CompilationUnitScope.recordTypeReferences",
          "source": "Unknown Source"
        },
        {
          "method": "org.eclipse.jdt.internal.compiler.lookup.Scope.findExactMethod",
          "source": "Unknown Source"
        },
        {
          "method": "org.eclipse.jdt.internal.compiler.lookup.BlockScope.getImplicitMethod",
          "source": "Unknown Source"
        },
        {
          "method": "org.eclipse.jdt.internal.compiler.ast.CastExpression.checkAlternateBinding",
          "source": "Unknown Source"
        },
        {
          "method": "org.eclipse.jdt.internal.compiler.ast.CastExpression.checkNeedForArgumentCasts",
          "source": "Unknown Source"
        },
        {
          "method": "org.eclipse.jdt.internal.compiler.ast.MessageSend.resolveType",
          "source": "Unknown Source"
        },
        {
          "method": "org.eclipse.jdt.internal.compiler.ast.Expression.resolve",
          "source": "Unknown  Source"
        },
        {
          "method": "org.eclipse.jdt.internal.compiler.ast.AbstractMethodDeclaration.resolveStatements",
          "source": "Unknown Source"
        },
        {
          "method": "org.eclipse.jdt.internal.compiler.ast.MethodDeclaration.resolveStatements",
          "source": "Unknown Source"
        },
        {
          "method": "org.eclipse.jdt.internal.compiler.ast.AbstractMethodDeclaration.resolve",
          "source": "Unknown  Source"
        },
        {
          "method": "org.eclipse.jdt.internal.compiler.ast.TypeDeclaration.resolve",
          "source": "Unknown Source"
        },
        {
          "method": "org.eclipse.jdt.internal.compiler.ast.TypeDeclaration.resolve",
          "source": "Unknown Source"
        },
        {
          "method": "org.eclipse.jdt.internal.compiler.ast.CompilationUnitDeclaration.resolve",
          "source": "Unknown Source"
        },
        {
          "method": "org.eclipse.jdt.internal.compiler.Compiler.resolve",
          "source": "Unknown Source"
        },
        {
          "method": "org.eclipse.jdt.internal.core.CompilationUnitProblemFinder.process",
          "source": "Unknown Source"
        },
        {
          "method": "org.eclipse.jdt.internal.core.CompilationUnit.buildStructure",
          "source": "Unknown  Source"
        },
        {
          "method": "org.eclipse.jdt.internal.core.Openable.generateInfos",
          "source": "Unknown Source"
        },
        {
          "method": "org.eclipse.jdt.internal.core.JavaElement.openWhenClosed",
          "source": "Unknown  Source"
        },
        {
          "method": "org.eclipse.jdt.internal.core.CompilationUnit.makeConsistent",
          "source": "Unknown  Source"
        },
        {
          "method": "org.eclipse.jdt.internal.core.ReconcileWorkingCopyOperation.executeOperation",
          "source": "Unknown Source"
        },
        {
          "method": "org.eclipse.jdt.internal.core.JavaModelOperation.execute",
          "source": "Unknown  Source"
        },
        {
          "method": "org.eclipse.jdt.internal.core.JavaModelOperation.run",
          "source": "Unknown Source"
        },
        {
          "method": "org.eclipse.jdt.internal.core.JavaElement.runOperation",
          "source": "Unknown  Source"
        },
        {
          "method": "org.eclipse.jdt.internal.core.CompilationUnit.reconcile",
          "source": "Unknown  Source"
        },
        {
          "method": "org.eclipse.jdt.internal.core.CompilationUnit.reconcile",
          "source": "Unknown  Source"
        },
        {
          "method": "org.eclipse.jdt.internal.core.CompilationUnit.reconcile",
          "source": "Unknown  Source"
        },
        {
          "method": "org.eclipse.jdt.internal.ui.javaeditor.CompilationUnitDocumentProvider.doSaveDocument",
          "source": "Unknown Source"
        },
        {
          "method": "org.eclipse.ui.texteditor.AbstractDocumentProvider.saveDocument",
          "source": "Unknown Source"
        },
        {
          "method": "org.eclipse.ui.texteditor.AbstractTextEditor$11.execute",
          "source": "Unknown  Source"
        },
        {
          "method": "org.eclipse.ui.actions.WorkspaceModifyOperation$1.run",
          "source": "Unknown Source"
        },
        {
          "method": "org.eclipse.core.internal.resources.Workspace.run",
          "source": "Unknown Source"
        },
        {
          "method": "org.eclipse.ui.actions.WorkspaceModifyOperation.run",
          "source": "Unknown Source"
        },
        {
          "method": "org.eclipse.ui.texteditor.AbstractTextEditor.performSaveOperation",
          "source": "Unknown Source"
        },
        {
          "method": "org.eclipse.jdt.internal.ui.javaeditor.CompilationUnitEditor.performSaveOperation",
          "source": "Unknown Source"
        },
        {
          "method": "org.eclipse.jdt.internal.ui.javaeditor.CompilationUnitEditor.doSave",
          "source": "Unknown Source"
        },
        {
          "method": "org.eclipse.ui.internal.EditorManager$11.run",
          "source": "Unknown Source"
        },
        {
          "method": "org.eclipse.ui.internal.EditorManager$8.run",
          "source": "Unknown Source"
        },
        {
          "method": "org.eclipse.jface.operation.ModalContext.runInCurrentThread",
          "source": "Unknown  Source"
        },
        {
          "method": "org.eclipse.jface.operation.ModalContext.run",
          "source": "Unknown Source"
        },
        {
          "method": "org.eclipse.jface.window.ApplicationWindow$1.run",
          "source": "Unknown Source"
        },
        {
          "method": "org.eclipse.swt.custom.BusyIndicator.showWhile",
          "source": "BusyIndicator.java:84"
        },
        {
          "method": "org.eclipse.jface.window.ApplicationWindow.run",
          "source": "Unknown Source"
        },
        {
          "method": "org.eclipse.ui.internal.WorkbenchWindow.run",
          "source": "Unknown Source"
        },
        {
          "method": "org.eclipse.ui.internal.EditorManager.runProgressMonitorOperation",
          "source": "Unknown Source"
        },
        {
          "method": "org.eclipse.ui.internal.EditorManager.savePart",
          "source": "Unknown Source"
        },
        {
          "method": "org.eclipse.ui.internal.WorkbenchPage.savePart",
          "source": "Unknown Source"
        },
        {
          "method": "org.eclipse.ui.internal.WorkbenchPage.saveEditor",
          "source": "Unknown Source"
        },
        {
          "method": "org.eclipse.ui.internal.SaveAction.run",
          "source": "Unknown Source"
        },
        {
          "method": "org.eclipse.jface.action.Action.runWithEvent",
          "source": "Unknown Source"
        },
        {
          "method": "org.eclipse.ui.internal.commands.old.ActionHandler.execute",
          "source": "Unknown  Source"
        },
        {
          "method": "org.eclipse.ui.internal.commands.old.ContextAndHandlerManager.pressed",
          "source": "Unknown Source"
        },
        {
          "method": "org.eclipse.ui.internal.commands.old.ContextAndHandlerManager.access$1",
          "source": "Unknown  Source"
        },
        {
          "method": "org.eclipse.ui.internal.commands.old.ContextAndHandlerManager$7.widgetSelected",
          "source": "Unknown Source"
        },
        {
          "method": "org.eclipse.ui.internal.AcceleratorMenu$2.handleEvent",
          "source": "Unknown Source"
        },
        {
          "method": "org.eclipse.swt.widgets.EventTable.sendEvent",
          "source": "EventTable.java:82"
        },
        {
          "method": "org.eclipse.swt.widgets.Widget.sendEvent",
          "source": "Widget.java:848"
        },
        {
          "method": "org.eclipse.swt.widgets.Display.runDeferredEvents",
          "source": "Display.java:2188"
        },
        {
          "method": "org.eclipse.swt.widgets.Display.readAndDispatch",
          "source": "Display.java:1878"
        },
        {
          "method": "org.eclipse.ui.internal.Workbench.runEventLoop",
          "source": "Unknown Source"
        },
        {
          "method": "org.eclipse.ui.internal.Workbench.run",
          "source": "Unknown Source"
        },
        {
          "method": "org.eclipse.core.internal.boot.InternalBootLoader.run",
          "source": "Unknown Source"
        },
        {
          "method": "org.eclipse.core.boot.BootLoader.run",
          "source": "Unknown Source"
        },
        {
          "method": "sun.reflect.NativeMethodAccessorImpl.invoke0",
          "source": "Native Method"
        },
        {
          "method": "sun.reflect.NativeMethodAccessorImpl.invoke",
          "source": "NativeMethodAccessorImpl.java:39"
        },
        {
          "method": "sun.reflect.DelegatingMethodAccessorImpl.invoke",
          "source": "DelegatingMethodAccessorImpl.java:25"
        },
        {
          "method": "java.lang.reflect.Method.invoke",
          "source": "Method.java:324"
        },
        {
          "method": "org.eclipse.core.launcher.Main.basicRun",
          "source": "Unknown Source"
        },
        {
          "method": "org.eclipse.core.launcher.Main.run",
          "source": "Unknown Source"
        },
        {
          "method": "org.eclipse.core.launcher.Main.main",
          "source": "Unknown Source"
        }
      ],
      "number": 0,
      "commentIndex": 1,
      "bugId": "40334",
      "date": "2003-07-17T14:05:07+02:00",
      "product": "JDT",
      "component": "Core",
      "severity": "normal"
    },
    {
      "exceptionType": "java.lang.NullPointerException",
      "elements": [
        {
          "method": "org.eclipse.jdt.internal.compiler.lookup.CompilationUnitScope.recordTypeReferences",
          "source": "Unknown Source"
        },
        {
          "method": "org.eclipse.jdt.internal.compiler.lookup.Scope.findExactMethod",
          "source": "Unknown Source"
        },
        {
          "method": "org.eclipse.jdt.internal.compiler.lookup.BlockScope.getImplicitMethod",
          "source": "Unknown Source"
        },
        {
          "method": "org.eclipse.jdt.internal.compiler.ast.CastExpression.checkAlternateBinding",
          "source": "Unknown Source"
        },
        {
          "method": "org.eclipse.jdt.internal.compiler.ast.CastExpression.checkNeedForArgumentCasts",
          "source": "Unknown Source"
        },
        {
          "method": "org.eclipse.jdt.internal.compiler.ast.MessageSend.resolveType",
          "source": "Unknown Source"
        },
        {
          "method": "org.eclipse.jdt.internal.compiler.ast.Expression.resolve",
          "source": "Unknown  Source"
        },
        {
          "method": "org.eclipse.jdt.internal.compiler.ast.AbstractMethodDeclaration.resolveStatements",
          "source": "Unknown Source"
        },
        {
          "method": "org.eclipse.jdt.internal.compiler.ast.MethodDeclaration.resolveStatements",
          "source": "Unknown Source"
        },
        {
          "method": "org.eclipse.jdt.internal.compiler.ast.AbstractMethodDeclaration.resolve",
          "source": "Unknown  Source"
        },
        {
          "method": "org.eclipse.jdt.internal.compiler.ast.TypeDeclaration.resolve",
          "source": "Unknown Source"
        },
        {
          "method": "org.eclipse.jdt.internal.compiler.ast.TypeDeclaration.resolve",
          "source": "Unknown Source"
        },
        {
          "method": "org.eclipse.jdt.internal.compiler.ast.CompilationUnitDeclaration.resolve",
          "source": "Unknown Source"
        },
        {
          "method": "org.eclipse.jdt.internal.compiler.Compiler.resolve",
          "source": "Unknown Source"
        },
        {
          "method": "org.eclipse.jdt.internal.core.CompilationUnitProblemFinder.process",
          "source": "Unknown Source"
        },
        {
          "method": "org.eclipse.jdt.internal.core.CompilationUnit.buildStructure",
          "source": "Unknown  Source"
        },
        {
          "method": "org.eclipse.jdt.internal.core.Openable.generateInfos",
          "source": "Unknown Source"
        },
        {
          "method": "org.eclipse.jdt.internal.core.JavaElement.openWhenClosed",
          "source": "Unknown  Source"
        },
        {
          "method": "org.eclipse.jdt.internal.core.CompilationUnit.makeConsistent",
          "source": "Unknown  Source"
        },
        {
          "method": "org.eclipse.jdt.internal.core.ReconcileWorkingCopyOperation.executeOperation",
          "source": "Unknown Source"
        },
        {
          "method": "org.eclipse.jdt.internal.core.JavaModelOperation.execute",
          "source": "Unknown  Source"
        },
        {
          "method": "org.eclipse.jdt.internal.core.JavaModelOperation.run",
          "source": "Unknown Source"
        },
        {
          "method": "org.eclipse.jdt.internal.core.JavaElement.runOperation",
          "source": "Unknown  Source"
        },
        {
          "method": "org.eclipse.jdt.internal.core.CompilationUnit.reconcile",
          "source": "Unknown  Source"
        },
        {
          "method": "org.eclipse.jdt.internal.core.CompilationUnit.reconcile",
          "source": "Unknown  Source"
        },
        {
          "method": "org.eclipse.jdt.internal.core.CompilationUnit.reconcile",
          "source": "Unknown  Source"
        },
        {
          "method": "org.eclipse.jdt.internal.ui.javaeditor.CompilationUnitDocumentProvider.doSaveDocument",
          "source": "Unknown Source"
        },
        {
          "method": "org.eclipse.ui.texteditor.AbstractDocumentProvider.saveDocument",
          "source": "Unknown Source"
        },
        {
          "method": "org.eclipse.ui.texteditor.AbstractTextEditor$11.execute",
          "source": "Unknown  Source"
        },
        {
          "method": "org.eclipse.ui.actions.WorkspaceModifyOperation$1.run",
          "source": "Unknown Source"
        },
        {
          "method": "org.eclipse.core.internal.resources.Workspace.run",
          "source": "Unknown Source"
        },
        {
          "method": "org.eclipse.ui.actions.WorkspaceModifyOperation.run",
          "source": "Unknown Source"
        },
        {
          "method": "org.eclipse.ui.texteditor.AbstractTextEditor.performSaveOperation",
          "source": "Unknown Source"
        },
        {
          "method": "org.eclipse.jdt.internal.ui.javaeditor.CompilationUnitEditor.performSaveOperation",
          "source": "Unknown Source"
        },
        {
          "method": "org.eclipse.jdt.internal.ui.javaeditor.CompilationUnitEditor.doSave",
          "source": "Unknown Source"
        },
        {
          "method": "org.eclipse.ui.internal.EditorManager$11.run",
          "source": "Unknown Source"
        },
        {
          "method": "org.eclipse.ui.internal.EditorManager$8.run",
          "source": "Unknown Source"
        },
        {
          "method": "org.eclipse.jface.operation.ModalContext.runInCurrentThread",
          "source": "Unknown  Source"
        },
        {
          "method": "org.eclipse.jface.operation.ModalContext.run",
          "source": "Unknown Source"
        },
        {
          "method": "org.eclipse.jface.window.ApplicationWindow$1.run",
          "source": "Unknown Source"
        },
        {
          "method": "org.eclipse.swt.custom.BusyIndicator.showWhile",
          "source": "BusyIndicator.java:84"
        },
        {
          "method": "org.eclipse.jface.window.ApplicationWindow.run",
          "source": "Unknown Source"
        },
        {
          "method": "org.eclipse.ui.internal.WorkbenchWindow.run",
          "source": "Unknown Source"
        },
        {
          "method": "org.eclipse.ui.internal.EditorManager.runProgressMonitorOperation",
          "source": "Unknown Source"
        },
        {
          "method": "org.eclipse.ui.internal.EditorManager.savePart",
          "source": "Unknown Source"
        },
        {
          "method": "org.eclipse.ui.internal.WorkbenchPage.savePart",
          "source": "Unknown Source"
        },
        {
          "method": "org.eclipse.ui.internal.WorkbenchPage.saveEditor",
          "source": "Unknown Source"
        },
        {
          "method": "org.eclipse.ui.internal.SaveAction.run",
          "source": "Unknown Source"
        },
        {
          "method": "org.eclipse.jface.action.Action.runWithEvent",
          "source": "Unknown Source"
        },
        {
          "method": "org.eclipse.ui.internal.commands.old.ActionHandler.execute",
          "source": "Unknown  Source"
        },
        {
          "method": "org.eclipse.ui.internal.commands.old.ContextAndHandlerManager.pressed",
          "source": "Unknown Source"
        },
        {
          "method": "org.eclipse.ui.internal.commands.old.ContextAndHandlerManager.access$1",
          "source": "Unknown  Source"
        },
        {
          "method": "org.eclipse.ui.internal.commands.old.ContextAndHandlerManager$7.widgetSelected",
          "source": "Unknown Source"
        },
        {
          "method": "org.eclipse.ui.internal.AcceleratorMenu$2.handleEvent",
          "source": "Unknown Source"
        },
        {
          "method": "org.eclipse.swt.widgets.EventTable.sendEvent",
          "source": "EventTable.java:82"
        },
        {
          "method": "org.eclipse.swt.widgets.Widget.sendEvent",
          "source": "Widget.java:848"
        },
        {
          "method": "org.eclipse.swt.widgets.Display.runDeferredEvents",
          "source": "Display.java:2188"
        },
        {
          "method": "org.eclipse.swt.widgets.Display.readAndDispatch",
          "source": "Display.java:1878"
        },
        {
          "method": "org.eclipse.ui.internal.Workbench.runEventLoop",
          "source": "Unknown Source"
        },
        {
          "method": "org.eclipse.ui.internal.Workbench.run",
          "source": "Unknown Source"
        },
        {
          "method": "org.eclipse.core.internal.boot.InternalBootLoader.run",
          "source": "Unknown Source"
        },
        {
          "method": "org.eclipse.core.boot.BootLoader.run",
          "source": "Unknown Source"
        },
        {
          "method": "sun.reflect.NativeMethodAccessorImpl.invoke0",
          "source": "Native Method"
        },
        {
          "method": "sun.reflect.NativeMethodAccessorImpl.invoke",
          "source": "NativeMethodAccessorImpl.java:39"
        },
        {
          "method": "sun.reflect.DelegatingMethodAccessorImpl.invoke",
          "source": "DelegatingMethodAccessorImpl.java:25"
        },
        {
          "method": "java.lang.reflect.Method.invoke",
          "source": "Method.java:324"
        },
        {
          "method": "org.eclipse.core.launcher.Main.basicRun",
          "source": "Unknown Source"
        },
        {
          "method": "org.eclipse.core.launcher.Main.run",
          "source": "Unknown Source"
        },
        {
          "method": "org.eclipse.core.launcher.Main.main",
          "source": "Unknown Source"
        }
      ],
      "number": 1,
      "commentIndex": 1,
      "bugId": "40334",
      "date": "2003-07-17T14:05:07+02:00",
      "product": "JDT",
      "component": "Core",
      "severity": "normal"
    },
    {
      "exceptionType": "java.lang.NullPointerException",
      "elements": [
        {
          "method": "org.eclipse.jdt.internal.compiler.lookup.CompilationUnitScope.recordTypeReferences",
          "source": "Unknown Source"
        },
        {
          "method": "org.eclipse.jdt.internal.compiler.lookup.Scope.findExactMethod",
          "source": "Unknown Source"
        },
        {
          "method": "org.eclipse.jdt.internal.compiler.lookup.BlockScope.getImplicitMethod",
          "source": "Unknown Source"
        },
        {
          "method": "org.eclipse.jdt.internal.compiler.ast.CastExpression.checkAlternateBinding",
          "source": "Unknown Source"
        },
        {
          "method": "org.eclipse.jdt.internal.compiler.ast.CastExpression.checkNeedForArgumentCasts",
          "source": "Unknown Source"
        },
        {
          "method": "org.eclipse.jdt.internal.compiler.ast.MessageSend.resolveType",
          "source": "Unknown Source"
        },
        {
          "method": "org.eclipse.jdt.internal.compiler.ast.Expression.resolve",
          "source": "Unknown  Source"
        },
        {
          "method": "org.eclipse.jdt.internal.compiler.ast.AbstractMethodDeclaration.resolveStatements",
          "source": "Unknown Source"
        },
        {
          "method": "org.eclipse.jdt.internal.compiler.ast.MethodDeclaration.resolveStatements",
          "source": "Unknown Source"
        },
        {
          "method": "org.eclipse.jdt.internal.compiler.ast.AbstractMethodDeclaration.resolve",
          "source": "Unknown  Source"
        },
        {
          "method": "org.eclipse.jdt.internal.compiler.ast.TypeDeclaration.resolve",
          "source": "Unknown Source"
        },
        {
          "method": "org.eclipse.jdt.internal.compiler.ast.TypeDeclaration.resolve",
          "source": "Unknown Source"
        }
      ],
      "number": 2,
      "commentIndex": 1,
      "bugId": "40334",
      "date": "2003-07-17T14:05:07+02:00",
      "product": "JDT",
      "component": "Core",
      "severity": "normal"
    }
  ],
  "groupId": "40334",
  "bugId": "40334",
  "date": "2003-07-17T13:52:27+02:00",
  "product": "JDT",
  "component": "Core",
  "severity": "normal"
}