{
  "comments": [
    "Build 20030716\n\nDuring shutdown, I noticed the following log entry. I had CVS decoration \nenabled.\n\norg.eclipse.jface.text.Assert$AssertionFailedException: Assertion failed:\n        at org.eclipse.jface.text.Assert.isTrue(Unknown Source)\n        at org.eclipse.jface.text.Assert.isTrue(Unknown Source)\n        at org.eclipse.jface.text.source.AnnotationModel.disconnect(Unknown \nSource)\n        at org.eclipse.jface.text.source.VisualAnnotationModel.disconnect\n(Unknown Source)\n        at org.eclipse.jface.text.source.SourceViewer.setDocument(Unknown \nSource)\n        at org.eclipse.jface.text.source.SourceViewer.setDocument(Unknown \nSource)\n        at org.eclipse.jface.text.TextViewer$1.widgetDisposed(Unknown Source)\n        at org.eclipse.swt.widgets.TypedListener.handleEvent\n(TypedListener.java:100)\n        at org.eclipse.swt.widgets.EventTable.sendEvent(EventTable.java:82)\n        at org.eclipse.swt.widgets.Widget.sendEvent(Widget.java:848)\n        at org.eclipse.swt.widgets.Widget.sendEvent(Widget.java:872)\n        at org.eclipse.swt.widgets.Widget.sendEvent(Widget.java:853)\n        at org.eclipse.swt.widgets.Widget.releaseWidget(Widget.java:760)\n        at org.eclipse.swt.widgets.Control.releaseWidget(Control.java:1421)\n        at org.eclipse.swt.widgets.Scrollable.releaseWidget(Scrollable.java:188)\n        at org.eclipse.swt.widgets.Composite.releaseWidget(Composite.java:369)\n        at org.eclipse.swt.widgets.Canvas.releaseWidget(Canvas.java:118)\n        at org.eclipse.swt.widgets.Widget.releaseResources(Widget.java:725)\n        at org.eclipse.swt.widgets.Composite.releaseChildren(Composite.java:320)\n        at org.eclipse.swt.widgets.Composite.releaseWidget(Composite.java:368)\n        at org.eclipse.swt.widgets.Canvas.releaseWidget(Canvas.java:118)\n        at org.eclipse.swt.widgets.Widget.releaseResources(Widget.java:725)\n        at org.eclipse.swt.widgets.Composite.releaseChildren(Composite.java:320)\n        at org.eclipse.swt.widgets.Composite.releaseWidget(Composite.java:368)\n        at org.eclipse.swt.widgets.Widget.releaseResources(Widget.java:725)\n        at org.eclipse.swt.widgets.Composite.releaseChildren(Composite.java:320)\n        at org.eclipse.swt.widgets.Composite.releaseWidget(Composite.java:368)\n        at org.eclipse.swt.widgets.Widget.releaseResources(Widget.java:725)\n        at org.eclipse.swt.widgets.Composite.releaseChildren(Composite.java:320)\n        at org.eclipse.swt.widgets.Composite.releaseWidget(Composite.java:368)\n        at org.eclipse.swt.widgets.Widget.releaseResources(Widget.java:725)\n        at org.eclipse.swt.widgets.Composite.releaseChildren(Composite.java:320)\n        at org.eclipse.swt.widgets.Composite.releaseWidget(Composite.java:368)\n        at org.eclipse.swt.widgets.Widget.releaseResources(Widget.java:725)\n        at org.eclipse.swt.widgets.Composite.releaseChildren(Composite.java:320)\n        at org.eclipse.swt.widgets.Composite.releaseWidget(Composite.java:368)\n        at org.eclipse.swt.widgets.Widget.releaseResources(Widget.java:725)\n        at org.eclipse.swt.widgets.Composite.releaseChildren(Composite.java:320)\n        at org.eclipse.swt.widgets.Composite.releaseWidget(Composite.java:368)\n        at org.eclipse.swt.widgets.Widget.releaseResources(Widget.java:725)\n        at org.eclipse.swt.widgets.Composite.releaseChildren(Composite.java:320)\n        at org.eclipse.swt.widgets.Composite.releaseWidget(Composite.java:368)\n        at org.eclipse.swt.widgets.Widget.releaseResources(Widget.java:725)\n        at org.eclipse.swt.widgets.Composite.releaseChildren(Composite.java:320)\n        at org.eclipse.swt.widgets.Composite.releaseWidget(Composite.java:368)\n        at org.eclipse.swt.widgets.Canvas.releaseWidget(Canvas.java:118)\n        at org.eclipse.swt.widgets.Decorations.releaseWidget\n(Decorations.java:632)\n        at org.eclipse.swt.widgets.Shell.releaseWidget(Shell.java:740)\n        at org.eclipse.swt.widgets.Widget.dispose(Widget.java:376)\n        at org.eclipse.swt.widgets.Decorations.dispose(Decorations.java:365)\n        at org.eclipse.swt.widgets.Shell.dispose(Shell.java:485)\n        at org.eclipse.swt.widgets.Display.release(Display.java:1927)\n        at org.eclipse.swt.graphics.Device.dispose(Device.java:212)\n        at org.eclipse.ui.internal.Workbench.run(Unknown Source)\n        at org.eclipse.core.internal.boot.InternalBootLoader.run(Unknown Source)\n        at org.eclipse.core.boot.BootLoader.run(Unknown Source)\n        at sun.reflect.NativeMethodAccessorImpl.invoke0(Native Method)\n        at sun.reflect.NativeMethodAccessorImpl.invoke\n(NativeMethodAccessorImpl.java:39)\n        at sun.reflect.DelegatingMethodAccessorImpl.invoke\n(DelegatingMethodAccessorImpl.java:25)\n        at java.lang.reflect.Method.invoke(Method.java:324)\n        at org.eclipse.core.launcher.Main.basicRun(Unknown Source)\n        at org.eclipse.core.launcher.Main.run(Unknown Source)\n        at org.eclipse.core.launcher.Main.main(Unknown Source)",
    "This is actually due to Decorations (SWT) disposing the widget not decorators \nand is in the shutdown for Text.\n\nMoving to component owner.",
    "*** Bug 40354 has been marked as a duplicate of this bug. ***",
    "How were you shutting down the workbench?\n\nBy the time Workbench.run calls Device(Display).dispose(), the windows should\nalready have been closed (in busyClose).\n",
    "I am exiting through File menu\u003eExit.",
    "Multiple windows open?",
    "Of course \u003cg\u003e",
    "Still occurs in 20030717, I have line numbers now...\n\norg.eclipse.jface.text.Assert$AssertionFailedException: Assertion failed:\n        at org.eclipse.jface.text.Assert.isTrue(Assert.java:175)\n        at org.eclipse.jface.text.Assert.isTrue(Assert.java:160)\n        at org.eclipse.jface.text.source.AnnotationModel.disconnect\n(AnnotationModel.java:172)\n        at org.eclipse.jface.text.source.VisualAnnotationModel.disconnect\n(VisualAnnotationModel.java:83\n        at org.eclipse.jface.text.source.SourceViewer.setDocument\n(SourceViewer.java:365)\n        at org.eclipse.jface.text.source.SourceViewer.setDocument\n(SourceViewer.java:333)\n        at org.eclipse.jface.text.TextViewer$1.widgetDisposed\n(TextViewer.java:1296)\n        at org.eclipse.swt.widgets.TypedListener.handleEvent\n(TypedListener.java:100)\n        at org.eclipse.swt.widgets.EventTable.sendEvent(EventTable.java:82)\n        at org.eclipse.swt.widgets.Widget.sendEvent(Widget.java:848)\n        at org.eclipse.swt.widgets.Widget.sendEvent(Widget.java:872)\n        at org.eclipse.swt.widgets.Widget.sendEvent(Widget.java:853)\n        at org.eclipse.swt.widgets.Widget.releaseWidget(Widget.java:760)\n        at org.eclipse.swt.widgets.Control.releaseWidget(Control.java:1421)\n        at org.eclipse.swt.widgets.Scrollable.releaseWidget(Scrollable.java:188)\n        at org.eclipse.swt.widgets.Composite.releaseWidget(Composite.java:369)\n        at org.eclipse.swt.widgets.Canvas.releaseWidget(Canvas.java:118)\n        at org.eclipse.swt.widgets.Widget.releaseResources(Widget.java:725)\n        at org.eclipse.swt.widgets.Composite.releaseChildren(Composite.java:320)\n        at org.eclipse.swt.widgets.Composite.releaseWidget(Composite.java:368)\n        at org.eclipse.swt.widgets.Canvas.releaseWidget(Canvas.java:118)\n        at org.eclipse.swt.widgets.Widget.releaseResources(Widget.java:725)\n        at org.eclipse.swt.widgets.Composite.releaseChildren(Composite.java:320)\n        at org.eclipse.swt.widgets.Composite.releaseWidget(Composite.java:368)\n        at org.eclipse.swt.widgets.Widget.releaseResources(Widget.java:725)\n        at org.eclipse.swt.widgets.Composite.releaseChildren(Composite.java:320)\n        at org.eclipse.swt.widgets.Composite.releaseWidget(Composite.java:368)\n        at org.eclipse.swt.widgets.Widget.releaseResources(Widget.java:725)\n        at org.eclipse.swt.widgets.Composite.releaseChildren(Composite.java:320)\n        at org.eclipse.swt.widgets.Composite.releaseWidget(Composite.java:368)\n        at org.eclipse.swt.widgets.Widget.releaseResources(Widget.java:725)\n        at org.eclipse.swt.widgets.Composite.releaseChildren(Composite.java:320)\n        at org.eclipse.swt.widgets.Composite.releaseWidget(Composite.java:368)\n        at org.eclipse.swt.widgets.Widget.releaseResources(Widget.java:725)\n        at org.eclipse.swt.widgets.Composite.releaseChildren(Composite.java:320)\n        at org.eclipse.swt.widgets.Composite.releaseWidget(Composite.java:368)\n        at org.eclipse.swt.widgets.Widget.releaseResources(Widget.java:725)\n        at org.eclipse.swt.widgets.Composite.releaseChildren(Composite.java:320)\n        at org.eclipse.swt.widgets.Composite.releaseWidget(Composite.java:368)\n        at org.eclipse.swt.widgets.Widget.releaseResources(Widget.java:725)\n        at org.eclipse.swt.widgets.Composite.releaseChildren(Composite.java:320)\n        at org.eclipse.swt.widgets.Composite.releaseWidget(Composite.java:368)\n        at org.eclipse.swt.widgets.Widget.releaseResources(Widget.java:725)\n        at org.eclipse.swt.widgets.Composite.releaseChildren(Composite.java:320)\n        at org.eclipse.swt.widgets.Composite.releaseWidget(Composite.java:368)\n        at org.eclipse.swt.widgets.Canvas.releaseWidget(Canvas.java:118)\n        at org.eclipse.swt.widgets.Decorations.releaseWidget\n(Decorations.java:632)\n        at org.eclipse.swt.widgets.Shell.releaseWidget(Shell.java:740)\n        at org.eclipse.swt.widgets.Widget.dispose(Widget.java:376)\n        at org.eclipse.swt.widgets.Decorations.dispose(Decorations.java:365)\n        at org.eclipse.swt.widgets.Shell.dispose(Shell.java:485)\n        at org.eclipse.swt.widgets.Display.release(Display.java:1927)\n        at org.eclipse.swt.graphics.Device.dispose(Device.java:212)\n        at org.eclipse.ui.internal.Workbench.run(Workbench.java:1618)\n        at org.eclipse.core.internal.boot.InternalBootLoader.run\n(InternalBootLoader.java:858)\n        at org.eclipse.core.boot.BootLoader.run(BootLoader.java:461)\n        at sun.reflect.NativeMethodAccessorImpl.invoke0(Native Method)\n        at sun.reflect.NativeMethodAccessorImpl.invoke\n(NativeMethodAccessorImpl.java:39)\n        at sun.reflect.DelegatingMethodAccessorImpl.invoke\n(DelegatingMethodAccessorImpl.java:25)\n        at java.lang.reflect.Method.invoke(Method.java:324)\n        at org.eclipse.core.launcher.Main.basicRun(Main.java:291)\n        at org.eclipse.core.launcher.Main.run(Main.java:747)\n        at org.eclipse.core.launcher.Main.main(Main.java:583)\n",
    "Fixed in HEAD.\nMust fix for I20030717-rebuild.",
    "*** Bug 40307 has been marked as a duplicate of this bug. ***",
    "I\u0027m still puzzled by this stack.  The one from Jerome in bug 40307 goes through \nQuitAction (File / Exit) but Philippe\u0027s does not - the shell is being disposed \nin Display.dispose(), but it should not have made it this far.\nI\u0027m investigating, but if you know of any other differences in your setup, \nplease provide details.",
    "They are both triggered by a follow up to bug 40319. You can also see that they\nare related by the Jeromes bug: in the summary he writes NPE but then he\nattached an AssertionFailedException stack.\n",
    "In my stack trace (Bug 40354) I am using multiple windows, I exited via File -\n\u003e exit, and I also had encountered \"ctrl-s not working\", bug 40303, although \nperhaps it is unrelated.",
    "The stack trace is result of an inconsistent state when closing an editor \ncaused by a previous exception you don\u0027t always see in the log. It does not \nmatter how you close the editor. See Bug #40319.",
    "test case:\nopen two windows, open same file in both editors, close the editor in one window\nthen in the other.\n\nverified in I20030717-rebuild"
  ],
  "commentCreationDates": [
    "2003-07-17T14:11:55+02:00",
    "2003-07-17T15:48:14+02:00",
    "2003-07-17T16:22:15+02:00",
    "2003-07-17T17:42:37+02:00",
    "2003-07-17T18:06:48+02:00",
    "2003-07-17T18:16:15+02:00",
    "2003-07-17T18:23:08+02:00",
    "2003-07-17T18:24:32+02:00",
    "2003-07-17T18:28:37+02:00",
    "2003-07-17T18:31:43+02:00",
    "2003-07-17T19:09:14+02:00",
    "2003-07-17T19:18:55+02:00",
    "2003-07-17T19:19:45+02:00",
    "2003-07-17T19:23:28+02:00",
    "2003-07-18T15:41:32+02:00"
  ],
  "traces": [
    {
      "exceptionType": "org.eclipse.jface.text.Assert$AssertionFailedException",
      "message": "Assertion failed:",
      "elements": [
        {
          "method": "org.eclipse.jface.text.Assert.isTrue",
          "source": "Unknown Source"
        },
        {
          "method": "org.eclipse.jface.text.Assert.isTrue",
          "source": "Unknown Source"
        },
        {
          "method": "org.eclipse.jface.text.source.AnnotationModel.disconnect",
          "source": "Unknown  Source"
        },
        {
          "method": "org.eclipse.jface.text.source.VisualAnnotationModel.disconnect",
          "source": "Unknown Source"
        },
        {
          "method": "org.eclipse.jface.text.source.SourceViewer.setDocument",
          "source": "Unknown  Source"
        },
        {
          "method": "org.eclipse.jface.text.source.SourceViewer.setDocument",
          "source": "Unknown  Source"
        },
        {
          "method": "org.eclipse.jface.text.TextViewer$1.widgetDisposed",
          "source": "Unknown Source"
        },
        {
          "method": "org.eclipse.swt.widgets.TypedListener.handleEvent",
          "source": "TypedListener.java:100"
        },
        {
          "method": "org.eclipse.swt.widgets.EventTable.sendEvent",
          "source": "EventTable.java:82"
        },
        {
          "method": "org.eclipse.swt.widgets.Widget.sendEvent",
          "source": "Widget.java:848"
        },
        {
          "method": "org.eclipse.swt.widgets.Widget.sendEvent",
          "source": "Widget.java:872"
        },
        {
          "method": "org.eclipse.swt.widgets.Widget.sendEvent",
          "source": "Widget.java:853"
        },
        {
          "method": "org.eclipse.swt.widgets.Widget.releaseWidget",
          "source": "Widget.java:760"
        },
        {
          "method": "org.eclipse.swt.widgets.Control.releaseWidget",
          "source": "Control.java:1421"
        },
        {
          "method": "org.eclipse.swt.widgets.Scrollable.releaseWidget",
          "source": "Scrollable.java:188"
        },
        {
          "method": "org.eclipse.swt.widgets.Composite.releaseWidget",
          "source": "Composite.java:369"
        },
        {
          "method": "org.eclipse.swt.widgets.Canvas.releaseWidget",
          "source": "Canvas.java:118"
        },
        {
          "method": "org.eclipse.swt.widgets.Widget.releaseResources",
          "source": "Widget.java:725"
        },
        {
          "method": "org.eclipse.swt.widgets.Composite.releaseChildren",
          "source": "Composite.java:320"
        },
        {
          "method": "org.eclipse.swt.widgets.Composite.releaseWidget",
          "source": "Composite.java:368"
        },
        {
          "method": "org.eclipse.swt.widgets.Canvas.releaseWidget",
          "source": "Canvas.java:118"
        },
        {
          "method": "org.eclipse.swt.widgets.Widget.releaseResources",
          "source": "Widget.java:725"
        },
        {
          "method": "org.eclipse.swt.widgets.Composite.releaseChildren",
          "source": "Composite.java:320"
        },
        {
          "method": "org.eclipse.swt.widgets.Composite.releaseWidget",
          "source": "Composite.java:368"
        },
        {
          "method": "org.eclipse.swt.widgets.Widget.releaseResources",
          "source": "Widget.java:725"
        },
        {
          "method": "org.eclipse.swt.widgets.Composite.releaseChildren",
          "source": "Composite.java:320"
        },
        {
          "method": "org.eclipse.swt.widgets.Composite.releaseWidget",
          "source": "Composite.java:368"
        },
        {
          "method": "org.eclipse.swt.widgets.Widget.releaseResources",
          "source": "Widget.java:725"
        },
        {
          "method": "org.eclipse.swt.widgets.Composite.releaseChildren",
          "source": "Composite.java:320"
        },
        {
          "method": "org.eclipse.swt.widgets.Composite.releaseWidget",
          "source": "Composite.java:368"
        },
        {
          "method": "org.eclipse.swt.widgets.Widget.releaseResources",
          "source": "Widget.java:725"
        },
        {
          "method": "org.eclipse.swt.widgets.Composite.releaseChildren",
          "source": "Composite.java:320"
        },
        {
          "method": "org.eclipse.swt.widgets.Composite.releaseWidget",
          "source": "Composite.java:368"
        },
        {
          "method": "org.eclipse.swt.widgets.Widget.releaseResources",
          "source": "Widget.java:725"
        },
        {
          "method": "org.eclipse.swt.widgets.Composite.releaseChildren",
          "source": "Composite.java:320"
        },
        {
          "method": "org.eclipse.swt.widgets.Composite.releaseWidget",
          "source": "Composite.java:368"
        },
        {
          "method": "org.eclipse.swt.widgets.Widget.releaseResources",
          "source": "Widget.java:725"
        },
        {
          "method": "org.eclipse.swt.widgets.Composite.releaseChildren",
          "source": "Composite.java:320"
        },
        {
          "method": "org.eclipse.swt.widgets.Composite.releaseWidget",
          "source": "Composite.java:368"
        },
        {
          "method": "org.eclipse.swt.widgets.Widget.releaseResources",
          "source": "Widget.java:725"
        },
        {
          "method": "org.eclipse.swt.widgets.Composite.releaseChildren",
          "source": "Composite.java:320"
        },
        {
          "method": "org.eclipse.swt.widgets.Composite.releaseWidget",
          "source": "Composite.java:368"
        },
        {
          "method": "org.eclipse.swt.widgets.Widget.releaseResources",
          "source": "Widget.java:725"
        },
        {
          "method": "org.eclipse.swt.widgets.Composite.releaseChildren",
          "source": "Composite.java:320"
        },
        {
          "method": "org.eclipse.swt.widgets.Composite.releaseWidget",
          "source": "Composite.java:368"
        },
        {
          "method": "org.eclipse.swt.widgets.Canvas.releaseWidget",
          "source": "Canvas.java:118"
        },
        {
          "method": "org.eclipse.swt.widgets.Decorations.releaseWidget",
          "source": "Decorations.java:632"
        },
        {
          "method": "org.eclipse.swt.widgets.Shell.releaseWidget",
          "source": "Shell.java:740"
        },
        {
          "method": "org.eclipse.swt.widgets.Widget.dispose",
          "source": "Widget.java:376"
        },
        {
          "method": "org.eclipse.swt.widgets.Decorations.dispose",
          "source": "Decorations.java:365"
        },
        {
          "method": "org.eclipse.swt.widgets.Shell.dispose",
          "source": "Shell.java:485"
        },
        {
          "method": "org.eclipse.swt.widgets.Display.release",
          "source": "Display.java:1927"
        },
        {
          "method": "org.eclipse.swt.graphics.Device.dispose",
          "source": "Device.java:212"
        },
        {
          "method": "org.eclipse.ui.internal.Workbench.run",
          "source": "Unknown Source"
        },
        {
          "method": "org.eclipse.core.internal.boot.InternalBootLoader.run",
          "source": "Unknown Source"
        },
        {
          "method": "org.eclipse.core.boot.BootLoader.run",
          "source": "Unknown Source"
        },
        {
          "method": "sun.reflect.NativeMethodAccessorImpl.invoke0",
          "source": "Native Method"
        },
        {
          "method": "sun.reflect.NativeMethodAccessorImpl.invoke",
          "source": "NativeMethodAccessorImpl.java:39"
        },
        {
          "method": "sun.reflect.DelegatingMethodAccessorImpl.invoke",
          "source": "DelegatingMethodAccessorImpl.java:25"
        },
        {
          "method": "java.lang.reflect.Method.invoke",
          "source": "Method.java:324"
        },
        {
          "method": "org.eclipse.core.launcher.Main.basicRun",
          "source": "Unknown Source"
        },
        {
          "method": "org.eclipse.core.launcher.Main.run",
          "source": "Unknown Source"
        },
        {
          "method": "org.eclipse.core.launcher.Main.main",
          "source": "Unknown Source"
        }
      ],
      "number": 0,
      "commentIndex": 0,
      "bugId": "40339",
      "date": "2003-07-17T14:11:55+02:00",
      "product": "Platform",
      "component": "Text",
      "severity": "critical"
    },
    {
      "exceptionType": "org.eclipse.jface.text.Assert$AssertionFailedException",
      "message": "Assertion failed:",
      "elements": [
        {
          "method": "org.eclipse.jface.text.Assert.isTrue",
          "source": "Assert.java:175"
        },
        {
          "method": "org.eclipse.jface.text.Assert.isTrue",
          "source": "Assert.java:160"
        },
        {
          "method": "org.eclipse.jface.text.source.AnnotationModel.disconnect",
          "source": "AnnotationModel.java:172"
        }
      ],
      "number": 1,
      "commentIndex": 7,
      "bugId": "40339",
      "date": "2003-07-17T18:24:32+02:00",
      "product": "Platform",
      "component": "Text",
      "severity": "critical"
    }
  ],
  "groupId": "40339",
  "bugId": "40339",
  "date": "2003-07-17T14:11:55+02:00",
  "product": "Platform",
  "component": "Text",
  "severity": "critical"
}