{
  "comments": [
    "Build 20030716\n\nAttempting to close editors, one did not close since was having unsaved \nchanges, and I told it not to close. From thereon, all attempts to close \nmanually other editors through their tab did fail, dumping following exception:\nAlso see attached screenshot with unpainted white tab.\n\n\n!ENTRY org.eclipse.ui 4 4 Jul 17, 2003 16:49:40.808\n!MESSAGE Unhandled exception caught in event loop.\nUnhandled exception caught in event loop.\nReason:\n!ENTRY org.eclipse.ui 4 0 Jul 17, 2003 16:49:40.824\n!MESSAGE Graphic is disposed\n!STACK 0\norg.eclipse.swt.SWTException: Graphic is disposed\n        at org.eclipse.swt.SWT.error(SWT.java:2365)\n        at org.eclipse.swt.SWT.error(SWT.java:2295)\n        at org.eclipse.swt.graphics.Image.getBounds(Image.java:943)\n        at org.eclipse.swt.custom.CTabItem.onPaint(CTabItem.java:346)\n        at org.eclipse.swt.custom.CTabFolder.onPaint(CTabFolder.java:1197)\n        at org.eclipse.swt.custom.CTabFolder.access$1(CTabFolder.java:1152)\n        at org.eclipse.swt.custom.CTabFolder$1.handleEvent(CTabFolder.java:198)\n        at org.eclipse.swt.widgets.EventTable.sendEvent(EventTable.java:82)\n        at org.eclipse.swt.widgets.Widget.sendEvent(Widget.java:848)\n        at org.eclipse.swt.widgets.Widget.sendEvent(Widget.java:872)\n        at org.eclipse.swt.widgets.Widget.sendEvent(Widget.java:857)\n        at org.eclipse.swt.widgets.Composite.WM_PAINT(Composite.java:749)\n        at org.eclipse.swt.widgets.Control.windowProc(Control.java:2921)\n        at org.eclipse.swt.widgets.Display.windowProc(Display.java:2713)\n        at org.eclipse.swt.internal.win32.OS.DispatchMessageW(Native Method)\n        at org.eclipse.swt.internal.win32.OS.DispatchMessage(OS.java:1338)\n        at org.eclipse.swt.widgets.Display.readAndDispatch(Display.java:1876)\n        at org.eclipse.ui.internal.Workbench.runEventLoop(Unknown Source)\n        at org.eclipse.ui.internal.Workbench.run(Unknown Source)\n        at org.eclipse.core.internal.boot.InternalBootLoader.run(Unknown Source)\n        at org.eclipse.core.boot.BootLoader.run(Unknown Source)\n        at sun.reflect.NativeMethodAccessorImpl.invoke0(Native Method)\n        at sun.reflect.NativeMethodAccessorImpl.invoke\n(NativeMethodAccessorImpl.java:39)\n        at sun.reflect.DelegatingMethodAccessorImpl.invoke\n(DelegatingMethodAccessorImpl.java:25)\n        at java.lang.reflect.Method.invoke(Method.java:324)\n        at org.eclipse.core.launcher.Main.basicRun(Unknown Source)\n        at org.eclipse.core.launcher.Main.run(Unknown Source)\n        at org.eclipse.core.launcher.Main.main(Unknown Source)\nGraphic is disposed",
    "Created an attachment (id\u003d5497)\nobserve stale white editor tab\n",
    "Created an attachment (id\u003d5499)\nobserve stale white editor tab\n",
    "\n\n*** This bug has been marked as a duplicate of 40191 ***"
  ],
  "commentCreationDates": [
    "2003-07-17T17:00:19+02:00",
    "2003-07-17T17:01:14+02:00",
    "2003-07-17T17:03:31+02:00",
    "2003-07-17T20:02:40+02:00"
  ],
  "traces": [
    {
      "exceptionType": "org.eclipse.swt.SWTException",
      "message": "Graphic is disposed",
      "elements": [
        {
          "method": "org.eclipse.swt.SWT.error",
          "source": "SWT.java:2365"
        },
        {
          "method": "org.eclipse.swt.SWT.error",
          "source": "SWT.java:2295"
        },
        {
          "method": "org.eclipse.swt.graphics.Image.getBounds",
          "source": "Image.java:943"
        },
        {
          "method": "org.eclipse.swt.custom.CTabItem.onPaint",
          "source": "CTabItem.java:346"
        },
        {
          "method": "org.eclipse.swt.custom.CTabFolder.onPaint",
          "source": "CTabFolder.java:1197"
        },
        {
          "method": "org.eclipse.swt.custom.CTabFolder.access$1",
          "source": "CTabFolder.java:1152"
        },
        {
          "method": "org.eclipse.swt.custom.CTabFolder$1.handleEvent",
          "source": "CTabFolder.java:198"
        },
        {
          "method": "org.eclipse.swt.widgets.EventTable.sendEvent",
          "source": "EventTable.java:82"
        },
        {
          "method": "org.eclipse.swt.widgets.Widget.sendEvent",
          "source": "Widget.java:848"
        },
        {
          "method": "org.eclipse.swt.widgets.Widget.sendEvent",
          "source": "Widget.java:872"
        },
        {
          "method": "org.eclipse.swt.widgets.Widget.sendEvent",
          "source": "Widget.java:857"
        },
        {
          "method": "org.eclipse.swt.widgets.Composite.WM_PAINT",
          "source": "Composite.java:749"
        },
        {
          "method": "org.eclipse.swt.widgets.Control.windowProc",
          "source": "Control.java:2921"
        },
        {
          "method": "org.eclipse.swt.widgets.Display.windowProc",
          "source": "Display.java:2713"
        },
        {
          "method": "org.eclipse.swt.internal.win32.OS.DispatchMessageW",
          "source": "Native Method"
        },
        {
          "method": "org.eclipse.swt.internal.win32.OS.DispatchMessage",
          "source": "OS.java:1338"
        },
        {
          "method": "org.eclipse.swt.widgets.Display.readAndDispatch",
          "source": "Display.java:1876"
        },
        {
          "method": "org.eclipse.ui.internal.Workbench.runEventLoop",
          "source": "Unknown Source"
        },
        {
          "method": "org.eclipse.ui.internal.Workbench.run",
          "source": "Unknown Source"
        },
        {
          "method": "org.eclipse.core.internal.boot.InternalBootLoader.run",
          "source": "Unknown Source"
        },
        {
          "method": "org.eclipse.core.boot.BootLoader.run",
          "source": "Unknown Source"
        },
        {
          "method": "sun.reflect.NativeMethodAccessorImpl.invoke0",
          "source": "Native Method"
        },
        {
          "method": "sun.reflect.NativeMethodAccessorImpl.invoke",
          "source": "NativeMethodAccessorImpl.java:39"
        },
        {
          "method": "sun.reflect.DelegatingMethodAccessorImpl.invoke",
          "source": "DelegatingMethodAccessorImpl.java:25"
        },
        {
          "method": "java.lang.reflect.Method.invoke",
          "source": "Method.java:324"
        },
        {
          "method": "org.eclipse.core.launcher.Main.basicRun",
          "source": "Unknown Source"
        },
        {
          "method": "org.eclipse.core.launcher.Main.run",
          "source": "Unknown Source"
        },
        {
          "method": "org.eclipse.core.launcher.Main.main",
          "source": "Unknown Source"
        }
      ],
      "number": 0,
      "commentIndex": 0,
      "bugId": "40379",
      "duplicateId": "40191",
      "date": "2003-07-17T17:00:19+02:00",
      "product": "Platform",
      "component": "SWT",
      "severity": "normal"
    }
  ],
  "groupId": "40191",
  "bugId": "40379",
  "duplicateId": "40191",
  "date": "2003-07-17T17:00:19+02:00",
  "product": "Platform",
  "component": "SWT",
  "severity": "normal"
}