{
  "comments": [
    "Build 20030717\n\nSince I took this build, many debug executions are not terminating properly. \nThe process remains in the debug view, though it is not longer reacting.\n\nLog contains the following entries:\n\n!ENTRY org.eclipse.jdt.debug.ui 4 150 Jul 18, 2003 14:51:03.480\n!MESSAGE Internal Error\n!STACK 1\norg.eclipse.debug.core.DebugException[5010]: org.eclipse.jdi.TimeoutException\n        at org.eclipse.jdi.internal.connect.PacketReceiveManager.getReply\n(PacketReceiveManager.java:149)\n        at org.eclipse.jdi.internal.connect.PacketReceiveManager.getReply\n(PacketReceiveManager.java:158)\n        at org.eclipse.jdi.internal.MirrorImpl.requestVM(MirrorImpl.java:173)\n        at org.eclipse.jdi.internal.MirrorImpl.requestVM(MirrorImpl.java:191)\n        at org.eclipse.jdi.internal.MirrorImpl.requestVM(MirrorImpl.java:206)\n        at org.eclipse.jdi.internal.ThreadReferenceImpl.frameCount\n(ThreadReferenceImpl.java:147)\n        at \norg.eclipse.jdt.internal.debug.core.model.JDIThread.getUnderlyingFrameCount\n(JDIThread.java:599)\n        at \norg.eclipse.jdt.internal.debug.core.model.JDIThread.createAllStackFrames\n(JDIThread.java:520)\n        at \norg.eclipse.jdt.internal.debug.core.model.JDIThread.computeStackFrames\n(JDIThread.java:396)\n        at \norg.eclipse.jdt.internal.debug.core.model.JDIThread.computeStackFrames\n(JDIThread.java:492)\n        at org.eclipse.jdt.internal.debug.core.model.JDIThread.getTopStackFrame\n(JDIThread.java:989)\n        at org.eclipse.jdt.internal.debug.ui.JavaDebugOptionsManager.getProblem\n(JavaDebugOptionsManager.java:624)\n        at \norg.eclipse.jdt.internal.debug.ui.JavaDebugOptionsManager.breakpointHit\n(JavaDebugOptionsManager.java:607)\n        at org.eclipse.jdt.internal.debug.core.JDIDebugPlugin$HitNotifier.run\n(JDIDebugPlugin.java:510)\n        at org.eclipse.core.internal.runtime.InternalPlatform.run\n(InternalPlatform.java:1015)\n        at org.eclipse.core.runtime.Platform.run(Platform.java:420)\n        at \norg.eclipse.jdt.internal.debug.core.JDIDebugPlugin$HitNotifier.notifyHit\n(JDIDebugPlugin.java:528)\n        at org.eclipse.jdt.internal.debug.core.JDIDebugPlugin.fireBreakpointHit\n(JDIDebugPlugin.java:322)\n        at \norg.eclipse.jdt.internal.debug.core.model.JDIThread.handleSuspendForBreakpoint\n(JDIThread.java:1018)\n        at \norg.eclipse.jdt.internal.debug.core.breakpoints.JavaBreakpoint.suspend\n(JavaBreakpoint.java:307)\n        at \norg.eclipse.jdt.internal.debug.core.breakpoints.JavaExceptionBreakpoint.handleBr\neakpointEvent(JavaExceptionBreakpoint.java:292)\n        at \norg.eclipse.jdt.internal.debug.core.breakpoints.JavaBreakpoint.handleEvent\n(JavaBreakpoint.java:262)\n        at org.eclipse.jdt.internal.debug.core.EventDispatcher.dispatch\n(EventDispatcher.java:136)\n        at org.eclipse.jdt.internal.debug.core.EventDispatcher.run\n(EventDispatcher.java:214)\n        at java.lang.Thread.run(Thread.java:536)\n!ENTRY org.eclipse.jdt.debug 4 5010 Jul 18, 2003 14:51:03.480\n!MESSAGE org.eclipse.jdi.TimeoutException occurred retrieving frame count.\n!STACK 0\norg.eclipse.jdi.TimeoutException\n        at org.eclipse.jdi.internal.connect.PacketReceiveManager.getReply\n(PacketReceiveManager.java:149)\n        at org.eclipse.jdi.internal.connect.PacketReceiveManager.getReply\n(PacketReceiveManager.java:158)\n        at org.eclipse.jdi.internal.MirrorImpl.requestVM(MirrorImpl.java:173)\n        at org.eclipse.jdi.internal.MirrorImpl.requestVM(MirrorImpl.java:191)\n        at org.eclipse.jdi.internal.MirrorImpl.requestVM(MirrorImpl.java:206)\n        at org.eclipse.jdi.internal.ThreadReferenceImpl.frameCount\n(ThreadReferenceImpl.java:147)\n        at \norg.eclipse.jdt.internal.debug.core.model.JDIThread.getUnderlyingFrameCount\n(JDIThread.java:599)\n        at \norg.eclipse.jdt.internal.debug.core.model.JDIThread.createAllStackFrames\n(JDIThread.java:520)\n        at \norg.eclipse.jdt.internal.debug.core.model.JDIThread.computeStackFrames\n(JDIThread.java:396)\n        at \norg.eclipse.jdt.internal.debug.core.model.JDIThread.computeStackFrames\n(JDIThread.java:492)\n        at org.eclipse.jdt.internal.debug.core.model.JDIThread.getTopStackFrame\n(JDIThread.java:989)\n        at org.eclipse.jdt.internal.debug.ui.JavaDebugOptionsManager.getProblem\n(JavaDebugOptionsManager.java:624)\n        at \norg.eclipse.jdt.internal.debug.ui.JavaDebugOptionsManager.breakpointHit\n(JavaDebugOptionsManager.java:607)\n        at org.eclipse.jdt.internal.debug.core.JDIDebugPlugin$HitNotifier.run\n(JDIDebugPlugin.java:510)\n        at org.eclipse.core.internal.runtime.InternalPlatform.run\n(InternalPlatform.java:1015)\n        at org.eclipse.core.runtime.Platform.run(Platform.java:420)\n        at \norg.eclipse.jdt.internal.debug.core.JDIDebugPlugin$HitNotifier.notifyHit\n(JDIDebugPlugin.java:528)\n        at org.eclipse.jdt.internal.debug.core.JDIDebugPlugin.fireBreakpointHit\n(JDIDebugPlugin.java:322)\n        at \norg.eclipse.jdt.internal.debug.core.model.JDIThread.handleSuspendForBreakpoint\n(JDIThread.java:1018)\n        at \norg.eclipse.jdt.internal.debug.core.breakpoints.JavaBreakpoint.suspend\n(JavaBreakpoint.java:307)\n        at \norg.eclipse.jdt.internal.debug.core.breakpoints.JavaExceptionBreakpoint.handleBr\neakpointEvent(JavaExceptionBreakpoint.java:292)\n        at \norg.eclipse.jdt.internal.debug.core.breakpoints.JavaBreakpoint.handleEvent\n(JavaBreakpoint.java:262)\n        at org.eclipse.jdt.internal.debug.core.EventDispatcher.dispatch\n(EventDispatcher.java:136)\n        at org.eclipse.jdt.internal.debug.core.EventDispatcher.run\n(EventDispatcher.java:214)\n        at java.lang.Thread.run(Thread.java:536)\norg.eclipse.jdi.TimeoutException\n        at org.eclipse.jdi.internal.connect.PacketReceiveManager.getReply\n(PacketReceiveManager.java:149)\n        at org.eclipse.jdi.internal.connect.PacketReceiveManager.getReply\n(PacketReceiveManager.java:158)\n        at org.eclipse.jdi.internal.MirrorImpl.requestVM(MirrorImpl.java:173)\n        at org.eclipse.jdi.internal.MirrorImpl.requestVM(MirrorImpl.java:191)\n        at org.eclipse.jdi.internal.MirrorImpl.requestVM(MirrorImpl.java:206)\n        at org.eclipse.jdi.internal.ThreadReferenceImpl.resume\n(ThreadReferenceImpl.java:326)\n        at org.eclipse.jdi.internal.event.EventSetImpl.resumeThreads\n(EventSetImpl.java:119)\n        at org.eclipse.jdi.internal.event.EventSetImpl.resume\n(EventSetImpl.java:100)\n        at org.eclipse.jdt.internal.debug.core.EventDispatcher.dispatch\n(EventDispatcher.java:184)\n        at org.eclipse.jdt.internal.debug.core.EventDispatcher.run\n(EventDispatcher.java:214)\n        at java.lang.Thread.run(Thread.java:536)\n!ENTRY org.eclipse.jdt.debug.ui 4 150 Jul 18, 2003 14:53:33.292\n!MESSAGE Internal Error\n!STACK 1\norg.eclipse.debug.core.DebugException[5010]: org.eclipse.jdi.TimeoutException\n        at org.eclipse.jdi.internal.connect.PacketReceiveManager.getReply\n(PacketReceiveManager.java:149)\n        at org.eclipse.jdi.internal.connect.PacketReceiveManager.getReply\n(PacketReceiveManager.java:158)\n        at org.eclipse.jdi.internal.MirrorImpl.requestVM(MirrorImpl.java:173)\n        at org.eclipse.jdi.internal.MirrorImpl.requestVM(MirrorImpl.java:191)\n        at org.eclipse.jdi.internal.MirrorImpl.requestVM(MirrorImpl.java:206)\n        at org.eclipse.jdi.internal.ThreadReferenceImpl.frameCount\n(ThreadReferenceImpl.java:147)\n        at \norg.eclipse.jdt.internal.debug.core.model.JDIThread.getUnderlyingFrameCount\n(JDIThread.java:599)\n        at \norg.eclipse.jdt.internal.debug.core.model.JDIThread.createAllStackFrames\n(JDIThread.java:520)\n        at \norg.eclipse.jdt.internal.debug.core.model.JDIThread.computeStackFrames\n(JDIThread.java:396)\n        at \norg.eclipse.jdt.internal.debug.core.model.JDIThread.computeStackFrames\n(JDIThread.java:492)\n        at org.eclipse.jdt.internal.debug.core.model.JDIThread.getTopStackFrame\n(JDIThread.java:989)\n        at org.eclipse.jdt.internal.debug.ui.JavaDebugOptionsManager.getProblem\n(JavaDebugOptionsManager.java:624)\n        at \norg.eclipse.jdt.internal.debug.ui.JavaDebugOptionsManager.breakpointHit\n(JavaDebugOptionsManager.java:607)\n        at org.eclipse.jdt.internal.debug.core.JDIDebugPlugin$HitNotifier.run\n(JDIDebugPlugin.java:510)\n        at org.eclipse.core.internal.runtime.InternalPlatform.run\n(InternalPlatform.java:1015)\n        at org.eclipse.core.runtime.Platform.run(Platform.java:420)\n        at \norg.eclipse.jdt.internal.debug.core.JDIDebugPlugin$HitNotifier.notifyHit\n(JDIDebugPlugin.java:528)\n        at org.eclipse.jdt.internal.debug.core.JDIDebugPlugin.fireBreakpointHit\n(JDIDebugPlugin.java:322)\n        at \norg.eclipse.jdt.internal.debug.core.model.JDIThread.handleSuspendForBreakpoint\n(JDIThread.java:1018)\n        at \norg.eclipse.jdt.internal.debug.core.breakpoints.JavaBreakpoint.suspend\n(JavaBreakpoint.java:307)\n        at \norg.eclipse.jdt.internal.debug.core.breakpoints.JavaExceptionBreakpoint.handleBr\neakpointEvent(JavaExceptionBreakpoint.java:292)\n        at \norg.eclipse.jdt.internal.debug.core.breakpoints.JavaBreakpoint.handleEvent\n(JavaBreakpoint.java:262)\n        at org.eclipse.jdt.internal.debug.core.EventDispatcher.dispatch\n(EventDispatcher.java:136)\n        at org.eclipse.jdt.internal.debug.core.EventDispatcher.run\n(EventDispatcher.java:214)\n        at java.lang.Thread.run(Thread.java:536)\n!ENTRY org.eclipse.jdt.debug 4 5010 Jul 18, 2003 14:53:33.307\n!MESSAGE org.eclipse.jdi.TimeoutException occurred retrieving frame count.\n!STACK 0\norg.eclipse.jdi.TimeoutException\n        at org.eclipse.jdi.internal.connect.PacketReceiveManager.getReply\n(PacketReceiveManager.java:149)\n        at org.eclipse.jdi.internal.connect.PacketReceiveManager.getReply\n(PacketReceiveManager.java:158)\n        at org.eclipse.jdi.internal.MirrorImpl.requestVM(MirrorImpl.java:173)\n        at org.eclipse.jdi.internal.MirrorImpl.requestVM(MirrorImpl.java:191)\n        at org.eclipse.jdi.internal.MirrorImpl.requestVM(MirrorImpl.java:206)\n        at org.eclipse.jdi.internal.ThreadReferenceImpl.frameCount\n(ThreadReferenceImpl.java:147)\n        at \norg.eclipse.jdt.internal.debug.core.model.JDIThread.getUnderlyingFrameCount\n(JDIThread.java:599)\n        at \norg.eclipse.jdt.internal.debug.core.model.JDIThread.createAllStackFrames\n(JDIThread.java:520)\n        at \norg.eclipse.jdt.internal.debug.core.model.JDIThread.computeStackFrames\n(JDIThread.java:396)\n        at \norg.eclipse.jdt.internal.debug.core.model.JDIThread.computeStackFrames\n(JDIThread.java:492)\n        at org.eclipse.jdt.internal.debug.core.model.JDIThread.getTopStackFrame\n(JDIThread.java:989)\n        at org.eclipse.jdt.internal.debug.ui.JavaDebugOptionsManager.getProblem\n(JavaDebugOptionsManager.java:624)\n        at \norg.eclipse.jdt.internal.debug.ui.JavaDebugOptionsManager.breakpointHit\n(JavaDebugOptionsManager.java:607)\n        at org.eclipse.jdt.internal.debug.core.JDIDebugPlugin$HitNotifier.run\n(JDIDebugPlugin.java:510)\n        at org.eclipse.core.internal.runtime.InternalPlatform.run\n(InternalPlatform.java:1015)\n        at org.eclipse.core.runtime.Platform.run(Platform.java:420)\n        at \norg.eclipse.jdt.internal.debug.core.JDIDebugPlugin$HitNotifier.notifyHit\n(JDIDebugPlugin.java:528)\n        at org.eclipse.jdt.internal.debug.core.JDIDebugPlugin.fireBreakpointHit\n(JDIDebugPlugin.java:322)\n        at \norg.eclipse.jdt.internal.debug.core.model.JDIThread.handleSuspendForBreakpoint\n(JDIThread.java:1018)\n        at \norg.eclipse.jdt.internal.debug.core.breakpoints.JavaBreakpoint.suspend\n(JavaBreakpoint.java:307)\n        at \norg.eclipse.jdt.internal.debug.core.breakpoints.JavaExceptionBreakpoint.handleBr\neakpointEvent(JavaExceptionBreakpoint.java:292)\n        at \norg.eclipse.jdt.internal.debug.core.breakpoints.JavaBreakpoint.handleEvent\n(JavaBreakpoint.java:262)\n        at org.eclipse.jdt.internal.debug.core.EventDispatcher.dispatch\n(EventDispatcher.java:136)\n        at org.eclipse.jdt.internal.debug.core.EventDispatcher.run\n(EventDispatcher.java:214)\n        at java.lang.Thread.run(Thread.java:536)\norg.eclipse.jdi.TimeoutException\n        at org.eclipse.jdi.internal.connect.PacketReceiveManager.getReply\n(PacketReceiveManager.java:149)\n        at org.eclipse.jdi.internal.connect.PacketReceiveManager.getReply\n(PacketReceiveManager.java:158)\n        at org.eclipse.jdi.internal.MirrorImpl.requestVM(MirrorImpl.java:173)\n        at org.eclipse.jdi.internal.MirrorImpl.requestVM(MirrorImpl.java:191)\n        at org.eclipse.jdi.internal.MirrorImpl.requestVM(MirrorImpl.java:206)\n        at org.eclipse.jdi.internal.ThreadReferenceImpl.resume\n(ThreadReferenceImpl.java:326)\n        at org.eclipse.jdi.internal.event.EventSetImpl.resumeThreads\n(EventSetImpl.java:119)\n        at org.eclipse.jdi.internal.event.EventSetImpl.resume\n(EventSetImpl.java:100)\n        at org.eclipse.jdt.internal.debug.core.EventDispatcher.dispatch\n(EventDispatcher.java:184)\n        at org.eclipse.jdt.internal.debug.core.EventDispatcher.run\n(EventDispatcher.java:214)\n        at java.lang.Thread.run(Thread.java:536)\n\nStarting build of Crap @ Fri Jul 18 14:56:23 CEST 2003\nFound source delta for: Crap\nClearing last state : State for Crap (#10 @ Fri Jul 18 14:39:24 CEST 2003)\nINCREMENTAL build\nCompile this changed source file src/Compile.java\nAbout to compile src/Compile.java\nWriting changed class file Compile.class\nRecording new state : State for Crap (#11 @ Fri Jul 18 14:39:24 CEST 2003)\nFinished build of Crap @ Fri Jul 18 14:56:23 CEST 2003\n!ENTRY org.eclipse.jdt.debug 4 120 Jul 18, 2003 14:56:24.291\n!MESSAGE Internal error logged from JDI Debug:\n!STACK 0\ncom.sun.jdi.VMDisconnectedException: Got IOException from Virtual Machine\n        at org.eclipse.jdi.internal.connect.PacketSendManager.sendPacket\n(PacketSendManager.java:79)\n        at org.eclipse.jdi.internal.MirrorImpl.requestVM(MirrorImpl.java:169)\n        at org.eclipse.jdi.internal.MirrorImpl.requestVM(MirrorImpl.java:191)\n        at org.eclipse.jdi.internal.VirtualMachineImpl.classesBySignature\n(VirtualMachineImpl.java:522)\n        at org.eclipse.jdi.internal.VirtualMachineImpl.classesByName\n(VirtualMachineImpl.java:549)\n        at \norg.eclipse.jdt.internal.debug.core.model.JDIDebugTarget.jdiClassesByName\n(JDIDebugTarget.java:1318)\n        at \norg.eclipse.jdt.internal.debug.core.hcr.JavaHotCodeReplaceManager.getTypesToByte\ns(JavaHotCodeReplaceManager.java:544)\n        at \norg.eclipse.jdt.internal.debug.core.hcr.JavaHotCodeReplaceManager.redefineTypesJ\nDK(JavaHotCodeReplaceManager.java:478)\n        at \norg.eclipse.jdt.internal.debug.core.hcr.JavaHotCodeReplaceManager.doHotCodeRepla\nce(JavaHotCodeReplaceManager.java:385)\n        at \norg.eclipse.jdt.internal.debug.core.hcr.JavaHotCodeReplaceManager.access$0\n(JavaHotCodeReplaceManager.java:358)\n        at \norg.eclipse.jdt.internal.debug.core.hcr.JavaHotCodeReplaceManager$1.run\n(JavaHotCodeReplaceManager.java:287)\n        at org.eclipse.core.internal.resources.Workspace.run\n(Workspace.java:1595)\n        at \norg.eclipse.jdt.internal.debug.core.hcr.JavaHotCodeReplaceManager$3.run\n(JavaHotCodeReplaceManager.java:1105)\n        at java.lang.Thread.run(Thread.java:536)",
    "Note that these processes are not completely dead since they keep reacting to \nhotcode replace, and send me some update failure notifications.",
    "Created an attachment (id\u003d5509)\nstale launches\n",
    "Which VM/version?",
    "(and...) are there difinitive steps to reproduce? Are you performing a \"large\" \nHCR (perhaps re-building the workspace?)",
    "VM is 1.4.1_01. I was only touching one class at a time. The HCR notice isn\u0027t \nvery interesting, other than it shows that the processes were not fully dead. \nBasically, there should have been no process alive left at that stage.",
    "V1.4.1_01 is old. Can you upgrade and see if the problems still occurr?",
    "marking as \"works for me\" unless this is still an issue."
  ],
  "commentCreationDates": [
    "2003-07-18T15:05:53+02:00",
    "2003-07-18T15:06:32+02:00",
    "2003-07-18T15:10:35+02:00",
    "2003-07-18T15:16:18+02:00",
    "2003-07-18T15:17:03+02:00",
    "2003-07-18T16:44:25+02:00",
    "2003-08-07T20:12:45+02:00",
    "2003-09-15T05:00:07+02:00"
  ],
  "traces": [
    {
      "exceptionType": "org.eclipse.jdi.TimeoutException",
      "elements": [
        {
          "method": "org.eclipse.jdi.internal.connect.PacketReceiveManager.getReply",
          "source": "PacketReceiveManager.java:149"
        },
        {
          "method": "org.eclipse.jdi.internal.connect.PacketReceiveManager.getReply",
          "source": "PacketReceiveManager.java:158"
        },
        {
          "method": "org.eclipse.jdi.internal.MirrorImpl.requestVM",
          "source": "MirrorImpl.java:173"
        },
        {
          "method": "org.eclipse.jdi.internal.MirrorImpl.requestVM",
          "source": "MirrorImpl.java:191"
        },
        {
          "method": "org.eclipse.jdi.internal.MirrorImpl.requestVM",
          "source": "MirrorImpl.java:206"
        },
        {
          "method": "org.eclipse.jdi.internal.ThreadReferenceImpl.frameCount",
          "source": "ThreadReferenceImpl.java:147"
        },
        {
          "method": "org.eclipse.jdt.internal.debug.core.model.JDIThread.getUnderlyingFrameCount",
          "source": "JDIThread.java:599"
        },
        {
          "method": "org.eclipse.jdt.internal.debug.core.model.JDIThread.createAllStackFrames",
          "source": "JDIThread.java:520"
        },
        {
          "method": "org.eclipse.jdt.internal.debug.core.model.JDIThread.computeStackFrames",
          "source": "JDIThread.java:396"
        },
        {
          "method": "org.eclipse.jdt.internal.debug.core.model.JDIThread.computeStackFrames",
          "source": "JDIThread.java:492"
        },
        {
          "method": "org.eclipse.jdt.internal.debug.core.model.JDIThread.getTopStackFrame",
          "source": "JDIThread.java:989"
        },
        {
          "method": "org.eclipse.jdt.internal.debug.ui.JavaDebugOptionsManager.getProblem",
          "source": "JavaDebugOptionsManager.java:624"
        },
        {
          "method": "org.eclipse.jdt.internal.debug.ui.JavaDebugOptionsManager.breakpointHit",
          "source": "JavaDebugOptionsManager.java:607"
        },
        {
          "method": "org.eclipse.jdt.internal.debug.core.JDIDebugPlugin$HitNotifier.run",
          "source": "JDIDebugPlugin.java:510"
        },
        {
          "method": "org.eclipse.core.internal.runtime.InternalPlatform.run",
          "source": "InternalPlatform.java:1015"
        },
        {
          "method": "org.eclipse.core.runtime.Platform.run",
          "source": "Platform.java:420"
        },
        {
          "method": "org.eclipse.jdt.internal.debug.core.JDIDebugPlugin$HitNotifier.notifyHit",
          "source": "JDIDebugPlugin.java:528"
        },
        {
          "method": "org.eclipse.jdt.internal.debug.core.JDIDebugPlugin.fireBreakpointHit",
          "source": "JDIDebugPlugin.java:322"
        },
        {
          "method": "org.eclipse.jdt.internal.debug.core.model.JDIThread.handleSuspendForBreakpoint",
          "source": "JDIThread.java:1018"
        },
        {
          "method": "org.eclipse.jdt.internal.debug.core.breakpoints.JavaBreakpoint.suspend",
          "source": "JavaBreakpoint.java:307"
        },
        {
          "method": "org.eclipse.jdt.internal.debug.core.breakpoints.JavaExceptionBreakpoint.handleBreakpointEvent",
          "source": "JavaExceptionBreakpoint.java:292"
        },
        {
          "method": "org.eclipse.jdt.internal.debug.core.breakpoints.JavaBreakpoint.handleEvent",
          "source": "JavaBreakpoint.java:262"
        },
        {
          "method": "org.eclipse.jdt.internal.debug.core.EventDispatcher.dispatch",
          "source": "EventDispatcher.java:136"
        },
        {
          "method": "org.eclipse.jdt.internal.debug.core.EventDispatcher.run",
          "source": "EventDispatcher.java:214"
        },
        {
          "method": "java.lang.Thread.run",
          "source": "Thread.java:536"
        }
      ],
      "number": 0,
      "commentIndex": 0,
      "bugId": "40463",
      "date": "2003-07-18T15:05:53+02:00",
      "product": "JDT",
      "component": "Debug",
      "severity": "normal"
    },
    {
      "exceptionType": "org.eclipse.jdi.TimeoutException",
      "elements": [
        {
          "method": "org.eclipse.jdi.internal.connect.PacketReceiveManager.getReply",
          "source": "PacketReceiveManager.java:149"
        },
        {
          "method": "org.eclipse.jdi.internal.connect.PacketReceiveManager.getReply",
          "source": "PacketReceiveManager.java:158"
        },
        {
          "method": "org.eclipse.jdi.internal.MirrorImpl.requestVM",
          "source": "MirrorImpl.java:173"
        },
        {
          "method": "org.eclipse.jdi.internal.MirrorImpl.requestVM",
          "source": "MirrorImpl.java:191"
        },
        {
          "method": "org.eclipse.jdi.internal.MirrorImpl.requestVM",
          "source": "MirrorImpl.java:206"
        },
        {
          "method": "org.eclipse.jdi.internal.ThreadReferenceImpl.frameCount",
          "source": "ThreadReferenceImpl.java:147"
        },
        {
          "method": "org.eclipse.jdt.internal.debug.core.model.JDIThread.getUnderlyingFrameCount",
          "source": "JDIThread.java:599"
        },
        {
          "method": "org.eclipse.jdt.internal.debug.core.model.JDIThread.createAllStackFrames",
          "source": "JDIThread.java:520"
        },
        {
          "method": "org.eclipse.jdt.internal.debug.core.model.JDIThread.computeStackFrames",
          "source": "JDIThread.java:396"
        },
        {
          "method": "org.eclipse.jdt.internal.debug.core.model.JDIThread.computeStackFrames",
          "source": "JDIThread.java:492"
        },
        {
          "method": "org.eclipse.jdt.internal.debug.core.model.JDIThread.getTopStackFrame",
          "source": "JDIThread.java:989"
        },
        {
          "method": "org.eclipse.jdt.internal.debug.ui.JavaDebugOptionsManager.getProblem",
          "source": "JavaDebugOptionsManager.java:624"
        },
        {
          "method": "org.eclipse.jdt.internal.debug.ui.JavaDebugOptionsManager.breakpointHit",
          "source": "JavaDebugOptionsManager.java:607"
        },
        {
          "method": "org.eclipse.jdt.internal.debug.core.JDIDebugPlugin$HitNotifier.run",
          "source": "JDIDebugPlugin.java:510"
        },
        {
          "method": "org.eclipse.core.internal.runtime.InternalPlatform.run",
          "source": "InternalPlatform.java:1015"
        },
        {
          "method": "org.eclipse.core.runtime.Platform.run",
          "source": "Platform.java:420"
        },
        {
          "method": "org.eclipse.jdt.internal.debug.core.JDIDebugPlugin$HitNotifier.notifyHit",
          "source": "JDIDebugPlugin.java:528"
        },
        {
          "method": "org.eclipse.jdt.internal.debug.core.JDIDebugPlugin.fireBreakpointHit",
          "source": "JDIDebugPlugin.java:322"
        },
        {
          "method": "org.eclipse.jdt.internal.debug.core.model.JDIThread.handleSuspendForBreakpoint",
          "source": "JDIThread.java:1018"
        },
        {
          "method": "org.eclipse.jdt.internal.debug.core.breakpoints.JavaBreakpoint.suspend",
          "source": "JavaBreakpoint.java:307"
        },
        {
          "method": "org.eclipse.jdt.internal.debug.core.breakpoints.JavaExceptionBreakpoint.handleBreakpointEvent",
          "source": "JavaExceptionBreakpoint.java:292"
        },
        {
          "method": "org.eclipse.jdt.internal.debug.core.breakpoints.JavaBreakpoint.handleEvent",
          "source": "JavaBreakpoint.java:262"
        },
        {
          "method": "org.eclipse.jdt.internal.debug.core.EventDispatcher.dispatch",
          "source": "EventDispatcher.java:136"
        },
        {
          "method": "org.eclipse.jdt.internal.debug.core.EventDispatcher.run",
          "source": "EventDispatcher.java:214"
        },
        {
          "method": "java.lang.Thread.run",
          "source": "Thread.java:536"
        }
      ],
      "number": 1,
      "commentIndex": 0,
      "bugId": "40463",
      "date": "2003-07-18T15:05:53+02:00",
      "product": "JDT",
      "component": "Debug",
      "severity": "normal"
    },
    {
      "exceptionType": "org.eclipse.jdi.TimeoutException",
      "elements": [
        {
          "method": "org.eclipse.jdi.internal.connect.PacketReceiveManager.getReply",
          "source": "PacketReceiveManager.java:149"
        },
        {
          "method": "org.eclipse.jdi.internal.connect.PacketReceiveManager.getReply",
          "source": "PacketReceiveManager.java:158"
        },
        {
          "method": "org.eclipse.jdi.internal.MirrorImpl.requestVM",
          "source": "MirrorImpl.java:173"
        },
        {
          "method": "org.eclipse.jdi.internal.MirrorImpl.requestVM",
          "source": "MirrorImpl.java:191"
        },
        {
          "method": "org.eclipse.jdi.internal.MirrorImpl.requestVM",
          "source": "MirrorImpl.java:206"
        },
        {
          "method": "org.eclipse.jdi.internal.ThreadReferenceImpl.resume",
          "source": "ThreadReferenceImpl.java:326"
        },
        {
          "method": "org.eclipse.jdi.internal.event.EventSetImpl.resumeThreads",
          "source": "EventSetImpl.java:119"
        },
        {
          "method": "org.eclipse.jdi.internal.event.EventSetImpl.resume",
          "source": "EventSetImpl.java:100"
        },
        {
          "method": "org.eclipse.jdt.internal.debug.core.EventDispatcher.dispatch",
          "source": "EventDispatcher.java:184"
        },
        {
          "method": "org.eclipse.jdt.internal.debug.core.EventDispatcher.run",
          "source": "EventDispatcher.java:214"
        },
        {
          "method": "java.lang.Thread.run",
          "source": "Thread.java:536"
        }
      ],
      "number": 2,
      "commentIndex": 0,
      "bugId": "40463",
      "date": "2003-07-18T15:05:53+02:00",
      "product": "JDT",
      "component": "Debug",
      "severity": "normal"
    },
    {
      "exceptionType": "org.eclipse.jdi.TimeoutException",
      "elements": [
        {
          "method": "org.eclipse.jdi.internal.connect.PacketReceiveManager.getReply",
          "source": "PacketReceiveManager.java:149"
        },
        {
          "method": "org.eclipse.jdi.internal.connect.PacketReceiveManager.getReply",
          "source": "PacketReceiveManager.java:158"
        },
        {
          "method": "org.eclipse.jdi.internal.MirrorImpl.requestVM",
          "source": "MirrorImpl.java:173"
        },
        {
          "method": "org.eclipse.jdi.internal.MirrorImpl.requestVM",
          "source": "MirrorImpl.java:191"
        },
        {
          "method": "org.eclipse.jdi.internal.MirrorImpl.requestVM",
          "source": "MirrorImpl.java:206"
        },
        {
          "method": "org.eclipse.jdi.internal.ThreadReferenceImpl.frameCount",
          "source": "ThreadReferenceImpl.java:147"
        },
        {
          "method": "org.eclipse.jdt.internal.debug.core.model.JDIThread.getUnderlyingFrameCount",
          "source": "JDIThread.java:599"
        },
        {
          "method": "org.eclipse.jdt.internal.debug.core.model.JDIThread.createAllStackFrames",
          "source": "JDIThread.java:520"
        },
        {
          "method": "org.eclipse.jdt.internal.debug.core.model.JDIThread.computeStackFrames",
          "source": "JDIThread.java:396"
        },
        {
          "method": "org.eclipse.jdt.internal.debug.core.model.JDIThread.computeStackFrames",
          "source": "JDIThread.java:492"
        },
        {
          "method": "org.eclipse.jdt.internal.debug.core.model.JDIThread.getTopStackFrame",
          "source": "JDIThread.java:989"
        },
        {
          "method": "org.eclipse.jdt.internal.debug.ui.JavaDebugOptionsManager.getProblem",
          "source": "JavaDebugOptionsManager.java:624"
        },
        {
          "method": "org.eclipse.jdt.internal.debug.ui.JavaDebugOptionsManager.breakpointHit",
          "source": "JavaDebugOptionsManager.java:607"
        },
        {
          "method": "org.eclipse.jdt.internal.debug.core.JDIDebugPlugin$HitNotifier.run",
          "source": "JDIDebugPlugin.java:510"
        },
        {
          "method": "org.eclipse.core.internal.runtime.InternalPlatform.run",
          "source": "InternalPlatform.java:1015"
        },
        {
          "method": "org.eclipse.core.runtime.Platform.run",
          "source": "Platform.java:420"
        },
        {
          "method": "org.eclipse.jdt.internal.debug.core.JDIDebugPlugin$HitNotifier.notifyHit",
          "source": "JDIDebugPlugin.java:528"
        },
        {
          "method": "org.eclipse.jdt.internal.debug.core.JDIDebugPlugin.fireBreakpointHit",
          "source": "JDIDebugPlugin.java:322"
        },
        {
          "method": "org.eclipse.jdt.internal.debug.core.model.JDIThread.handleSuspendForBreakpoint",
          "source": "JDIThread.java:1018"
        },
        {
          "method": "org.eclipse.jdt.internal.debug.core.breakpoints.JavaBreakpoint.suspend",
          "source": "JavaBreakpoint.java:307"
        },
        {
          "method": "org.eclipse.jdt.internal.debug.core.breakpoints.JavaExceptionBreakpoint.handleBreakpointEvent",
          "source": "JavaExceptionBreakpoint.java:292"
        },
        {
          "method": "org.eclipse.jdt.internal.debug.core.breakpoints.JavaBreakpoint.handleEvent",
          "source": "JavaBreakpoint.java:262"
        },
        {
          "method": "org.eclipse.jdt.internal.debug.core.EventDispatcher.dispatch",
          "source": "EventDispatcher.java:136"
        },
        {
          "method": "org.eclipse.jdt.internal.debug.core.EventDispatcher.run",
          "source": "EventDispatcher.java:214"
        },
        {
          "method": "java.lang.Thread.run",
          "source": "Thread.java:536"
        }
      ],
      "number": 3,
      "commentIndex": 0,
      "bugId": "40463",
      "date": "2003-07-18T15:05:53+02:00",
      "product": "JDT",
      "component": "Debug",
      "severity": "normal"
    },
    {
      "exceptionType": "org.eclipse.jdi.TimeoutException",
      "elements": [
        {
          "method": "org.eclipse.jdi.internal.connect.PacketReceiveManager.getReply",
          "source": "PacketReceiveManager.java:149"
        },
        {
          "method": "org.eclipse.jdi.internal.connect.PacketReceiveManager.getReply",
          "source": "PacketReceiveManager.java:158"
        },
        {
          "method": "org.eclipse.jdi.internal.MirrorImpl.requestVM",
          "source": "MirrorImpl.java:173"
        },
        {
          "method": "org.eclipse.jdi.internal.MirrorImpl.requestVM",
          "source": "MirrorImpl.java:191"
        },
        {
          "method": "org.eclipse.jdi.internal.MirrorImpl.requestVM",
          "source": "MirrorImpl.java:206"
        },
        {
          "method": "org.eclipse.jdi.internal.ThreadReferenceImpl.frameCount",
          "source": "ThreadReferenceImpl.java:147"
        },
        {
          "method": "org.eclipse.jdt.internal.debug.core.model.JDIThread.getUnderlyingFrameCount",
          "source": "JDIThread.java:599"
        },
        {
          "method": "org.eclipse.jdt.internal.debug.core.model.JDIThread.createAllStackFrames",
          "source": "JDIThread.java:520"
        },
        {
          "method": "org.eclipse.jdt.internal.debug.core.model.JDIThread.computeStackFrames",
          "source": "JDIThread.java:396"
        },
        {
          "method": "org.eclipse.jdt.internal.debug.core.model.JDIThread.computeStackFrames",
          "source": "JDIThread.java:492"
        },
        {
          "method": "org.eclipse.jdt.internal.debug.core.model.JDIThread.getTopStackFrame",
          "source": "JDIThread.java:989"
        },
        {
          "method": "org.eclipse.jdt.internal.debug.ui.JavaDebugOptionsManager.getProblem",
          "source": "JavaDebugOptionsManager.java:624"
        },
        {
          "method": "org.eclipse.jdt.internal.debug.ui.JavaDebugOptionsManager.breakpointHit",
          "source": "JavaDebugOptionsManager.java:607"
        },
        {
          "method": "org.eclipse.jdt.internal.debug.core.JDIDebugPlugin$HitNotifier.run",
          "source": "JDIDebugPlugin.java:510"
        },
        {
          "method": "org.eclipse.core.internal.runtime.InternalPlatform.run",
          "source": "InternalPlatform.java:1015"
        },
        {
          "method": "org.eclipse.core.runtime.Platform.run",
          "source": "Platform.java:420"
        },
        {
          "method": "org.eclipse.jdt.internal.debug.core.JDIDebugPlugin$HitNotifier.notifyHit",
          "source": "JDIDebugPlugin.java:528"
        },
        {
          "method": "org.eclipse.jdt.internal.debug.core.JDIDebugPlugin.fireBreakpointHit",
          "source": "JDIDebugPlugin.java:322"
        },
        {
          "method": "org.eclipse.jdt.internal.debug.core.model.JDIThread.handleSuspendForBreakpoint",
          "source": "JDIThread.java:1018"
        },
        {
          "method": "org.eclipse.jdt.internal.debug.core.breakpoints.JavaBreakpoint.suspend",
          "source": "JavaBreakpoint.java:307"
        },
        {
          "method": "org.eclipse.jdt.internal.debug.core.breakpoints.JavaExceptionBreakpoint.handleBreakpointEvent",
          "source": "JavaExceptionBreakpoint.java:292"
        },
        {
          "method": "org.eclipse.jdt.internal.debug.core.breakpoints.JavaBreakpoint.handleEvent",
          "source": "JavaBreakpoint.java:262"
        },
        {
          "method": "org.eclipse.jdt.internal.debug.core.EventDispatcher.dispatch",
          "source": "EventDispatcher.java:136"
        },
        {
          "method": "org.eclipse.jdt.internal.debug.core.EventDispatcher.run",
          "source": "EventDispatcher.java:214"
        },
        {
          "method": "java.lang.Thread.run",
          "source": "Thread.java:536"
        }
      ],
      "number": 4,
      "commentIndex": 0,
      "bugId": "40463",
      "date": "2003-07-18T15:05:53+02:00",
      "product": "JDT",
      "component": "Debug",
      "severity": "normal"
    },
    {
      "exceptionType": "org.eclipse.jdi.TimeoutException",
      "elements": [
        {
          "method": "org.eclipse.jdi.internal.connect.PacketReceiveManager.getReply",
          "source": "PacketReceiveManager.java:149"
        },
        {
          "method": "org.eclipse.jdi.internal.connect.PacketReceiveManager.getReply",
          "source": "PacketReceiveManager.java:158"
        },
        {
          "method": "org.eclipse.jdi.internal.MirrorImpl.requestVM",
          "source": "MirrorImpl.java:173"
        },
        {
          "method": "org.eclipse.jdi.internal.MirrorImpl.requestVM",
          "source": "MirrorImpl.java:191"
        },
        {
          "method": "org.eclipse.jdi.internal.MirrorImpl.requestVM",
          "source": "MirrorImpl.java:206"
        },
        {
          "method": "org.eclipse.jdi.internal.ThreadReferenceImpl.resume",
          "source": "ThreadReferenceImpl.java:326"
        },
        {
          "method": "org.eclipse.jdi.internal.event.EventSetImpl.resumeThreads",
          "source": "EventSetImpl.java:119"
        },
        {
          "method": "org.eclipse.jdi.internal.event.EventSetImpl.resume",
          "source": "EventSetImpl.java:100"
        },
        {
          "method": "org.eclipse.jdt.internal.debug.core.EventDispatcher.dispatch",
          "source": "EventDispatcher.java:184"
        },
        {
          "method": "org.eclipse.jdt.internal.debug.core.EventDispatcher.run",
          "source": "EventDispatcher.java:214"
        },
        {
          "method": "java.lang.Thread.run",
          "source": "Thread.java:536"
        }
      ],
      "number": 5,
      "commentIndex": 0,
      "bugId": "40463",
      "date": "2003-07-18T15:05:53+02:00",
      "product": "JDT",
      "component": "Debug",
      "severity": "normal"
    },
    {
      "exceptionType": "com.sun.jdi.VMDisconnectedException",
      "message": "Got IOException from Virtual Machine",
      "elements": [
        {
          "method": "org.eclipse.jdi.internal.connect.PacketSendManager.sendPacket",
          "source": "PacketSendManager.java:79"
        },
        {
          "method": "org.eclipse.jdi.internal.MirrorImpl.requestVM",
          "source": "MirrorImpl.java:169"
        },
        {
          "method": "org.eclipse.jdi.internal.MirrorImpl.requestVM",
          "source": "MirrorImpl.java:191"
        },
        {
          "method": "org.eclipse.jdi.internal.VirtualMachineImpl.classesBySignature",
          "source": "VirtualMachineImpl.java:522"
        },
        {
          "method": "org.eclipse.jdi.internal.VirtualMachineImpl.classesByName",
          "source": "VirtualMachineImpl.java:549"
        },
        {
          "method": "org.eclipse.jdt.internal.debug.core.model.JDIDebugTarget.jdiClassesByName",
          "source": "JDIDebugTarget.java:1318"
        },
        {
          "method": "org.eclipse.jdt.internal.debug.core.hcr.JavaHotCodeReplaceManager.getTypesToBytes",
          "source": "JavaHotCodeReplaceManager.java:544"
        },
        {
          "method": "org.eclipse.jdt.internal.debug.core.hcr.JavaHotCodeReplaceManager.redefineTypesJDK",
          "source": "JavaHotCodeReplaceManager.java:478"
        },
        {
          "method": "org.eclipse.jdt.internal.debug.core.hcr.JavaHotCodeReplaceManager.doHotCodeReplace",
          "source": "JavaHotCodeReplaceManager.java:385"
        },
        {
          "method": "org.eclipse.jdt.internal.debug.core.hcr.JavaHotCodeReplaceManager.access$0",
          "source": "JavaHotCodeReplaceManager.java:358"
        },
        {
          "method": "org.eclipse.jdt.internal.debug.core.hcr.JavaHotCodeReplaceManager$1.run",
          "source": "JavaHotCodeReplaceManager.java:287"
        },
        {
          "method": "org.eclipse.core.internal.resources.Workspace.run",
          "source": "Workspace.java:1595"
        },
        {
          "method": "org.eclipse.jdt.internal.debug.core.hcr.JavaHotCodeReplaceManager$3.run",
          "source": "JavaHotCodeReplaceManager.java:1105"
        },
        {
          "method": "java.lang.Thread.run",
          "source": "Thread.java:536"
        }
      ],
      "number": 6,
      "commentIndex": 0,
      "bugId": "40463",
      "date": "2003-07-18T15:05:53+02:00",
      "product": "JDT",
      "component": "Debug",
      "severity": "normal"
    }
  ],
  "groupId": "40463",
  "bugId": "40463",
  "date": "2003-07-18T15:05:53+02:00",
  "product": "JDT",
  "component": "Debug",
  "severity": "normal"
}