{
  "comments": [
    "When starting Eclipse, tjchiass@ca.ibm.com gets this stack trace as reported \nBy Kevin H.\n\n!SESSION ----------------------------------------------------------------------\n!ENTRY org.eclipse.core.launcher 4 0 Jul 29, 2003 10:33:23.402\n!MESSAGE Exception launching the Eclipse Platform:\n!STACK\njava.lang.reflect.InvocationTargetException: \njava.lang.reflect.InvocationTargetE\nxception: org.eclipse.swt.SWTError: No more handles\n        at org.eclipse.swt.SWT.error(SWT.java:2358)\n        at org.eclipse.swt.SWT.error(SWT.java:2262)\n        at org.eclipse.swt.graphics.GC.createRenderTable(GC.java:961)\n        at org.eclipse.swt.graphics.GC.textExtent(GC.java:2474)\n        at org.eclipse.swt.graphics.GC.textExtent(GC.java:2437)\n        at org.eclipse.swt.custom.CLabel.getTotalSize(CLabel.java:199)\n        at org.eclipse.swt.custom.CLabel.computeSize(CLabel.java:141)\n        at org.eclipse.swt.layout.GridLayout.calculateGridDimensions\n(GridLayout.\njava:248)\n        at org.eclipse.swt.layout.GridLayout.computeLayoutSize\n(GridLayout.java:3\n30)\n        at org.eclipse.swt.layout.GridLayout.computeSize(GridLayout.java:377)\n        at org.eclipse.swt.widgets.Composite.computeSize(Composite.java:131)\n        at org.eclipse.swt.layout.GridLayout.calculateGridDimensions\n(GridLayout.\njava:248)\n        at org.eclipse.swt.layout.GridLayout.computeLayoutSize\n(GridLayout.java:3\n30)\n        at org.eclipse.swt.layout.GridLayout.computeSize(GridLayout.java:377)\n        at org.eclipse.swt.layout.GridLayout.layout(GridLayout.java:509)\n        at org.eclipse.swt.widgets.Composite.setBounds(Composite.java:546)\n        at org.eclipse.swt.widgets.Control.setBounds(Control.java:1831)\n        at org.eclipse.swt.layout.FillLayout.layout(FillLayout.java:101)\n        at org.eclipse.swt.widgets.Composite.setBounds(Composite.java:546)\n        at org.eclipse.swt.widgets.Control.setBounds(Control.java:1831)\n        at org.eclipse.swt.custom.ViewForm.layout(ViewForm.java:341)\n        at org.eclipse.swt.widgets.Composite.layout(Composite.java:342)\n        at org.eclipse.swt.custom.ViewForm.onResize(ViewForm.java:419)\n        at org.eclipse.swt.custom.ViewForm.access$1(ViewForm.java:418)\n        at org.eclipse.swt.custom.ViewForm$2.controlResized(ViewForm.java:135)\n        at org.eclipse.swt.widgets.TypedListener.handleEvent\n(TypedListener.java:\n144)\n        at org.eclipse.swt.widgets.EventTable.sendEvent(EventTable.java:81)\n        at org.eclipse.swt.widgets.Widget.sendEvent(Widget.java:810)\n        at org.eclipse.swt.widgets.Widget.sendEvent(Widget.java:832)\n        at org.eclipse.swt.widgets.Widget.sendEvent(Widget.java:814)\n        at org.eclipse.swt.widgets.Control.setBounds(Control.java:1780)\n        at org.eclipse.swt.widgets.Composite.setBounds(Composite.java:539)\n        at org.eclipse.swt.widgets.Control.setBounds(Control.java:1854)\n        at org.eclipse.ui.internal.LayoutPart.setBounds(LayoutPart.java:245)\n        at org.eclipse.ui.internal.EditorWorkbook.setControlSize\n(EditorWorkbook.\njava:915)\n        at org.eclipse.ui.internal.EditorWorkbook.setVisibleEditor\n(EditorWorkboo\nk.java:945)\n        at org.eclipse.ui.internal.EditorWorkbook.add(EditorWorkbook.java:124)\n        at org.eclipse.ui.internal.EditorArea.addEditor(EditorArea.java:55)\n        at org.eclipse.ui.internal.EditorPresentation.openEditor\n(EditorPresentat\nion.java:351)\n        at org.eclipse.ui.internal.EditorManager$2.run(EditorManager.java:585)\n        at org.eclipse.swt.custom.BusyIndicator.showWhile\n(BusyIndicator.java:69)\n        at org.eclipse.ui.internal.EditorManager.createEditorTab\n(EditorManager.j\nava:574)\n        at org.eclipse.ui.internal.EditorManager.openInternalEditor\n(EditorManage\nr.java:668)\n        at org.eclipse.ui.internal.EditorManager.openEditorFromDescriptor\n(Editor\nManager.java:459)\n        at org.eclipse.ui.internal.EditorManager.openEditor\n(EditorManager.java:4\n31)\n        at org.eclipse.ui.internal.WorkbenchPage.busyOpenEditor\n(WorkbenchPage.ja\nva:2054)\n        at org.eclipse.ui.internal.WorkbenchPage.access$6\n(WorkbenchPage.java:200\n4)\n        at org.eclipse.ui.internal.WorkbenchPage$9.run(WorkbenchPage.java:1991)\n        at org.eclipse.swt.custom.BusyIndicator.showWhile\n(BusyIndicator.java:69)\n        at org.eclipse.ui.internal.WorkbenchPage.openEditor\n(WorkbenchPage.java:1\n986)\n        at org.eclipse.ui.internal.WorkbenchPage.openEditor\n(WorkbenchPage.java:1\n919)\n        at org.eclipse.ui.internal.WorkbenchPage.openEditor\n(WorkbenchPage.java:1\n911)\n        at org.eclipse.ui.internal.WorkbenchConfigurationInfo.openEditor\n(Workben\nchConfigurationInfo.java:345)\n        at \norg.eclipse.ui.internal.WorkbenchConfigurationInfo.openWelcomeEditors\n(WorkbenchConfigurationInfo.java:103)\n        at org.eclipse.ui.internal.Workbench.init(Workbench.java:884)\n        at org.eclipse.ui.internal.Workbench.run(Workbench.java:1373)\n        at org.eclipse.core.internal.boot.InternalBootLoader.run\n(InternalBootLoa\nder.java:858)\n        at org.eclipse.core.boot.BootLoader.run(BootLoader.java:461)\n        at java.lang.reflect.Method.invoke(Native Method)\n        at org.eclipse.core.launcher.Main.basicRun(Main.java:291)\n        at org.eclipse.core.launcher.Main.run(Main.java:747)\n        at org.eclipse.core.launcher.Main.main(Main.java:583)",
    "Hi Chris.\nHere is the locale information.\nEclipse works if you run locally, or if LC_ALL is set to (e.g. en_US.iso88591)\n\npiclbld:/home/piclbld\u003elocale\nLANG\u003d\nLC_CTYPE\u003d\"C\"\nLC_COLLATE\u003d\"C\"\nLC_MONETARY\u003d\"C\"\nLC_NUMERIC\u003d\"C\"\nLC_TIME\u003d\"C\"\nLC_MESSAGES\u003d\"C\"\nLC_ALL\u003d\npiclbld:/home/piclbld\u003e",
    "*** Bug 40903 has been marked as a duplicate of this bug. ***",
    "Ted:\n\nwhat is the locale when you run locally on HP (with success). Is it the same \nas the one you mention in comment 1?\n\nIs the following correct?\n- 2.1.1 always runs locally on your HP box regardless of the locale (C, en_US).\n- the problem only occurs when running from a remote linux box with the \nlocale \"C\". It works remotely if the locale is set to en_US.iso88591.",
    "2.1.1 always seems to run locally (with locale set to \"C\")\nThe problem occurs any time you run eclipse remotely.\nI tried it on a Solaris box as well, with the display exported.\nIt will work if the locale is set to an existant english locale.\nThe reason why I believe this defect to be serious is because this is the \ndefault setting.\nMost Unix boxes out there come with their locale set to \"C\" by default.\nI also believe that most people who work with HPUX systems do not work with the \nHP box as their desktop machine.",
    "We can reproduce the problem.",
    "Current workaround is to change the locale on the HP box from the default C \none to \"en_US.iso88591\" for example.",
    "*** Bug 40902 has been marked as a duplicate of this bug. ***",
    "Fixed \u003e 0808 with SSQ.  For some reason the C locale was causing problems with \nFontSets, so in this case we now use a Font struct instead.\n",
    "*** Bug 68459 has been marked as a duplicate of this bug. ***"
  ],
  "commentCreationDates": [
    "2003-07-29T17:56:17+02:00",
    "2003-07-29T18:19:27+02:00",
    "2003-07-29T18:27:55+02:00",
    "2003-07-29T18:37:45+02:00",
    "2003-07-29T18:56:27+02:00",
    "2003-07-29T20:29:20+02:00",
    "2003-07-29T20:36:58+02:00",
    "2003-08-07T17:46:43+02:00",
    "2003-08-08T23:24:42+02:00",
    "2004-06-24T21:45:17+02:00"
  ],
  "traces": [
    {
      "exceptionType": "org.eclipse.swt.SWTError",
      "message": "No more handles",
      "elements": [
        {
          "method": "org.eclipse.swt.SWT.error",
          "source": "SWT.java:2358"
        },
        {
          "method": "org.eclipse.swt.SWT.error",
          "source": "SWT.java:2262"
        },
        {
          "method": "org.eclipse.swt.graphics.GC.createRenderTable",
          "source": "GC.java:961"
        },
        {
          "method": "org.eclipse.swt.graphics.GC.textExtent",
          "source": "GC.java:2474"
        },
        {
          "method": "org.eclipse.swt.graphics.GC.textExtent",
          "source": "GC.java:2437"
        },
        {
          "method": "org.eclipse.swt.custom.CLabel.getTotalSize",
          "source": "CLabel.java:199"
        },
        {
          "method": "org.eclipse.swt.custom.CLabel.computeSize",
          "source": "CLabel.java:141"
        },
        {
          "method": "org.eclipse.swt.layout.GridLayout.calculateGridDimensions",
          "source": "GridLayout. java:248"
        },
        {
          "method": "org.eclipse.swt.layout.GridLayout.computeLayoutSize",
          "source": "GridLayout.java:3 30"
        },
        {
          "method": "org.eclipse.swt.layout.GridLayout.computeSize",
          "source": "GridLayout.java:377"
        },
        {
          "method": "org.eclipse.swt.widgets.Composite.computeSize",
          "source": "Composite.java:131"
        },
        {
          "method": "org.eclipse.swt.layout.GridLayout.calculateGridDimensions",
          "source": "GridLayout. java:248"
        },
        {
          "method": "org.eclipse.swt.layout.GridLayout.computeLayoutSize",
          "source": "GridLayout.java:3 30"
        },
        {
          "method": "org.eclipse.swt.layout.GridLayout.computeSize",
          "source": "GridLayout.java:377"
        },
        {
          "method": "org.eclipse.swt.layout.GridLayout.layout",
          "source": "GridLayout.java:509"
        },
        {
          "method": "org.eclipse.swt.widgets.Composite.setBounds",
          "source": "Composite.java:546"
        },
        {
          "method": "org.eclipse.swt.widgets.Control.setBounds",
          "source": "Control.java:1831"
        },
        {
          "method": "org.eclipse.swt.layout.FillLayout.layout",
          "source": "FillLayout.java:101"
        },
        {
          "method": "org.eclipse.swt.widgets.Composite.setBounds",
          "source": "Composite.java:546"
        },
        {
          "method": "org.eclipse.swt.widgets.Control.setBounds",
          "source": "Control.java:1831"
        },
        {
          "method": "org.eclipse.swt.custom.ViewForm.layout",
          "source": "ViewForm.java:341"
        },
        {
          "method": "org.eclipse.swt.widgets.Composite.layout",
          "source": "Composite.java:342"
        },
        {
          "method": "org.eclipse.swt.custom.ViewForm.onResize",
          "source": "ViewForm.java:419"
        },
        {
          "method": "org.eclipse.swt.custom.ViewForm.access$1",
          "source": "ViewForm.java:418"
        },
        {
          "method": "org.eclipse.swt.custom.ViewForm$2.controlResized",
          "source": "ViewForm.java:135"
        },
        {
          "method": "org.eclipse.swt.widgets.TypedListener.handleEvent",
          "source": "TypedListener.java: 144"
        },
        {
          "method": "org.eclipse.swt.widgets.EventTable.sendEvent",
          "source": "EventTable.java:81"
        },
        {
          "method": "org.eclipse.swt.widgets.Widget.sendEvent",
          "source": "Widget.java:810"
        },
        {
          "method": "org.eclipse.swt.widgets.Widget.sendEvent",
          "source": "Widget.java:832"
        },
        {
          "method": "org.eclipse.swt.widgets.Widget.sendEvent",
          "source": "Widget.java:814"
        },
        {
          "method": "org.eclipse.swt.widgets.Control.setBounds",
          "source": "Control.java:1780"
        },
        {
          "method": "org.eclipse.swt.widgets.Composite.setBounds",
          "source": "Composite.java:539"
        },
        {
          "method": "org.eclipse.swt.widgets.Control.setBounds",
          "source": "Control.java:1854"
        },
        {
          "method": "org.eclipse.ui.internal.LayoutPart.setBounds",
          "source": "LayoutPart.java:245"
        },
        {
          "method": "org.eclipse.ui.internal.EditorWorkbook.setControlSize",
          "source": "EditorWorkbook. java:915"
        },
        {
          "method": "org.eclipse.ui.internal.EditorWorkbook.setVisibleEditor",
          "source": "EditorWorkboo k.java:945"
        },
        {
          "method": "org.eclipse.ui.internal.EditorWorkbook.add",
          "source": "EditorWorkbook.java:124"
        },
        {
          "method": "org.eclipse.ui.internal.EditorArea.addEditor",
          "source": "EditorArea.java:55"
        },
        {
          "method": "org.eclipse.ui.internal.EditorPresentation.openEditor",
          "source": "EditorPresentat ion.java:351"
        },
        {
          "method": "org.eclipse.ui.internal.EditorManager$2.run",
          "source": "EditorManager.java:585"
        },
        {
          "method": "org.eclipse.swt.custom.BusyIndicator.showWhile",
          "source": "BusyIndicator.java:69"
        },
        {
          "method": "org.eclipse.ui.internal.EditorManager.createEditorTab",
          "source": "EditorManager.j ava:574"
        },
        {
          "method": "org.eclipse.ui.internal.EditorManager.openInternalEditor",
          "source": "EditorManage r.java:668"
        },
        {
          "method": "org.eclipse.ui.internal.EditorManager.openEditorFromDescriptor",
          "source": "Editor Manager.java:459"
        },
        {
          "method": "org.eclipse.ui.internal.EditorManager.openEditor",
          "source": "EditorManager.java:4 31"
        },
        {
          "method": "org.eclipse.ui.internal.WorkbenchPage.busyOpenEditor",
          "source": "WorkbenchPage.ja va:2054"
        },
        {
          "method": "org.eclipse.ui.internal.WorkbenchPage.access$6",
          "source": "WorkbenchPage.java:200 4"
        },
        {
          "method": "org.eclipse.ui.internal.WorkbenchPage$9.run",
          "source": "WorkbenchPage.java:1991"
        },
        {
          "method": "org.eclipse.swt.custom.BusyIndicator.showWhile",
          "source": "BusyIndicator.java:69"
        },
        {
          "method": "org.eclipse.ui.internal.WorkbenchPage.openEditor",
          "source": "WorkbenchPage.java:1 986"
        },
        {
          "method": "org.eclipse.ui.internal.WorkbenchPage.openEditor",
          "source": "WorkbenchPage.java:1 919"
        },
        {
          "method": "org.eclipse.ui.internal.WorkbenchPage.openEditor",
          "source": "WorkbenchPage.java:1 911"
        },
        {
          "method": "org.eclipse.ui.internal.WorkbenchConfigurationInfo.openEditor",
          "source": "Workben chConfigurationInfo.java:345"
        },
        {
          "method": "org.eclipse.ui.internal.WorkbenchConfigurationInfo.openWelcomeEditors",
          "source": "WorkbenchConfigurationInfo.java:103"
        },
        {
          "method": "org.eclipse.ui.internal.Workbench.init",
          "source": "Workbench.java:884"
        },
        {
          "method": "org.eclipse.ui.internal.Workbench.run",
          "source": "Workbench.java:1373"
        },
        {
          "method": "org.eclipse.core.internal.boot.InternalBootLoader.run",
          "source": "InternalBootLoa der.java:858"
        },
        {
          "method": "org.eclipse.core.boot.BootLoader.run",
          "source": "BootLoader.java:461"
        },
        {
          "method": "java.lang.reflect.Method.invoke",
          "source": "Native Method"
        },
        {
          "method": "org.eclipse.core.launcher.Main.basicRun",
          "source": "Main.java:291"
        },
        {
          "method": "org.eclipse.core.launcher.Main.run",
          "source": "Main.java:747"
        },
        {
          "method": "org.eclipse.core.launcher.Main.main",
          "source": "Main.java:583"
        }
      ],
      "number": 0,
      "commentIndex": 0,
      "bugId": "40899",
      "date": "2003-07-29T17:56:17+02:00",
      "product": "Platform",
      "component": "SWT",
      "severity": "normal"
    }
  ],
  "groupId": "40899",
  "bugId": "40899",
  "date": "2003-07-29T17:56:17+02:00",
  "product": "Platform",
  "component": "SWT",
  "severity": "normal"
}