{
  "comments": [
    "This morning when I started my Eclipse M1 workspace, I accidentally started it\ntwice.  I realize that is a separate bug report for Linux-GTK, since you\u0027re not\nsupposed to be able to do that.  However, I did do it, and I quickly closed one\nof the workspaces and began work on the other one.\n\nApparently, this brief period of having the same workspace open twice hosed\nsomething in my metadata.  When I try to launch anything in the workspace, I get\nthe following error (copied from the .log):\n\n!ENTRY org.eclipse.debug.ui 4 120 Jul 30, 2003 10:14:57.29\n!MESSAGE Error logged from Debug UI:\n!STACK 1\norg.eclipse.core.runtime.CoreException: Source locator does not exist:\norg.eclipse.jdt.debug.ui.javaSourceLocator\n        at\norg.eclipse.debug.internal.core.LaunchManager.newSourceLocator(LaunchManager.java:1101)\n        at\norg.eclipse.debug.internal.core.LaunchConfiguration.initializeSourceLocator(LaunchConfiguration.java:180)\n        at\norg.eclipse.debug.internal.core.LaunchConfiguration.launch(LaunchConfiguration.java:155)\n        at\norg.eclipse.debug.internal.ui.DebugUIPlugin.buildAndLaunch(DebugUIPlugin.java:732)\n        at org.eclipse.debug.ui.DebugUITools.buildAndLaunch(DebugUITools.java:550)\n        at org.eclipse.debug.ui.DebugUITools$2.run(DebugUITools.java:499)\n        at\norg.eclipse.jface.operation.ModalContext$ModalContextThread.run(ModalContext.java:101)\n!ENTRY org.eclipse.debug.core 4 5013 Jul 30, 2003 10:14:57.29\n!MESSAGE Source locator does not exist: org.eclipse.jdt.debug.ui.javaSourceLocator\n\nThis is a big problem for me since I just recently had to rebuild my workspace,\nand I don\u0027t want to do it again.  Can this problem be avoided with code, if the\nsame workspace happens to be opened multiple times?  Is there a way I can hack\nmy metadata to get around the problem?",
    "I don\u0027t know how the dupe bug happened.\n\n*** This bug has been marked as a duplicate of 40947 ***"
  ],
  "commentCreationDates": [
    "2003-07-30T16:37:11+02:00",
    "2003-07-30T16:38:53+02:00"
  ],
  "traces": [
    {
      "exceptionType": "org.eclipse.core.runtime.CoreException",
      "message": "Source locator does not exist: org.eclipse.jdt.debug.ui.javaSourceLocator",
      "elements": [
        {
          "method": "org.eclipse.debug.internal.core.LaunchManager.newSourceLocator",
          "source": "LaunchManager.java:1101"
        },
        {
          "method": "org.eclipse.debug.internal.core.LaunchConfiguration.initializeSourceLocator",
          "source": "LaunchConfiguration.java:180"
        },
        {
          "method": "org.eclipse.debug.internal.core.LaunchConfiguration.launch",
          "source": "LaunchConfiguration.java:155"
        },
        {
          "method": "org.eclipse.debug.internal.ui.DebugUIPlugin.buildAndLaunch",
          "source": "DebugUIPlugin.java:732"
        },
        {
          "method": "org.eclipse.debug.ui.DebugUITools.buildAndLaunch",
          "source": "DebugUITools.java:550"
        },
        {
          "method": "org.eclipse.debug.ui.DebugUITools$2.run",
          "source": "DebugUITools.java:499"
        },
        {
          "method": "org.eclipse.jface.operation.ModalContext$ModalContextThread.run",
          "source": "ModalContext.java:101"
        }
      ],
      "number": 0,
      "commentIndex": 0,
      "bugId": "40949",
      "duplicateId": "40947",
      "date": "2003-07-30T16:37:11+02:00",
      "product": "JDT",
      "component": "Debug",
      "severity": "normal"
    }
  ],
  "groupId": "40947",
  "bugId": "40949",
  "duplicateId": "40947",
  "date": "2003-07-30T16:37:11+02:00",
  "product": "JDT",
  "component": "Debug",
  "severity": "normal"
}