{
  "comments": [
    "2 input files:\npackage b;\n\nclass Foo {\n    public pointcut bar();\n}\n\n\npackage a;\naspect MsgForPCD {\n    before() : Foo.bar() {}\n}\n\nExample compilation:\nC:\\devel\\test\\cmsg\u003eajc a\\*.aj b\\*.aj\nC:\\devel\\test\\cmsg\\a\\MsgForPCD.aj:3 can\u0027t bind type name \u0027Foo\u0027\norg.aspectj.weaver.BCException: Bad type signature: \u003cmissing\u003e\n        at org.aspectj.weaver.TypeX.signatureToName(TypeX.java:565)\n        at org.aspectj.weaver.TypeX.getName(TypeX.java:205)\n        at org.aspectj.weaver.bcel.BcelWorld.resolveObjectType\n(BcelWorld.java:18\n2)\n        at org.aspectj.weaver.World.resolveObjectType(World.java:98)\n        at org.aspectj.weaver.World.resolve(World.java:80)\n        at org.aspectj.weaver.World.resolve(World.java:68)\n        at org.aspectj.weaver.patterns.ReferencePointcut.resolveBindings\n(Referen\ncePointcut.java:120)\n        at org.aspectj.weaver.patterns.Pointcut.resolve(Pointcut.java:100)\n        at \norg.aspectj.ajdt.internal.compiler.ast.PointcutDesignator.finishResol\nveTypes(PointcutDesignator.java:82)\n        at \norg.aspectj.ajdt.internal.compiler.ast.AdviceDeclaration.resolveState\nments(AdviceDeclaration.java:112)\n        at \norg.eclipse.jdt.internal.compiler.ast.AbstractMethodDeclaration.resol\nve(AbstractMethodDeclaration.java:317)\n        at org.eclipse.jdt.internal.compiler.ast.TypeDeclaration.resolve\n(TypeDec\nlaration.java:804)\n        at org.aspectj.ajdt.internal.compiler.ast.AspectDeclaration.resolve\n(Aspe\nctDeclaration.java:73)\n        at org.eclipse.jdt.internal.compiler.ast.TypeDeclaration.resolve\n(TypeDec\nlaration.java:845)\n        at \norg.eclipse.jdt.internal.compiler.ast.CompilationUnitDeclaration.reso\nlve(CompilationUnitDeclaration.java:251)\n        at org.eclipse.jdt.internal.compiler.Compiler.process\n(Compiler.java:538)\n\n        at org.aspectj.ajdt.internal.compiler.AjCompiler.process\n(AjCompiler.java\n:65)\n        at org.eclipse.jdt.internal.compiler.Compiler.compile\n(Compiler.java:338)\n\n        at \norg.aspectj.ajdt.internal.core.builder.AjBuildManager.performCompilat\nion(AjBuildManager.java:372)\n        at org.aspectj.ajdt.internal.core.builder.AjBuildManager.doBuild\n(AjBuild\nManager.java:133)\n        at org.aspectj.ajdt.internal.core.builder.AjBuildManager.batchBuild\n(AjBu\nildManager.java:78)\n        at org.aspectj.ajdt.ajc.AjdtCommand.doCommand(AjdtCommand.java:106)\n        at org.aspectj.ajdt.ajc.AjdtCommand.runCommand(AjdtCommand.java:60)\n        at org.aspectj.tools.ajc.Main.run(Main.java:217)\n        at org.aspectj.tools.ajc.Main.runMain(Main.java:155)\n        at org.aspectj.tools.ajc.Main.main(Main.java:72)\nC:\\devel\\test\\cmsg\\a\\MsgForPCD.aj:0 Internal compiler error\norg.aspectj.weaver.BCException: Bad type signature: \u003cmissing\u003e\n        at org.aspectj.weaver.TypeX.signatureToName(TypeX.java:565)\n        at org.aspectj.weaver.TypeX.getName(TypeX.java:205)\n        at org.aspectj.weaver.bcel.BcelWorld.resolveObjectType\n(BcelWorld.java:18\n2)\n        at org.aspectj.weaver.World.resolveObjectType(World.java:98)\n        at org.aspectj.weaver.World.resolve(World.java:80)\n        at org.aspectj.weaver.World.resolve(World.java:68)\n        at org.aspectj.weaver.patterns.ReferencePointcut.resolveBindings\n(Referen\ncePointcut.java:120)\n        at org.aspectj.weaver.patterns.Pointcut.resolve(Pointcut.java:100)\n        at \norg.aspectj.ajdt.internal.compiler.ast.PointcutDesignator.finishResol\nveTypes(PointcutDesignator.java:82)\n        at \norg.aspectj.ajdt.internal.compiler.ast.AdviceDeclaration.resolveState\nments(AdviceDeclaration.java:112)\n        at \norg.eclipse.jdt.internal.compiler.ast.AbstractMethodDeclaration.resol\nve(AbstractMethodDeclaration.java:317)\n        at org.eclipse.jdt.internal.compiler.ast.TypeDeclaration.resolve\n(TypeDec\nlaration.java:804)\n        at org.aspectj.ajdt.internal.compiler.ast.AspectDeclaration.resolve\n(Aspe\nctDeclaration.java:73)\n        at org.eclipse.jdt.internal.compiler.ast.TypeDeclaration.resolve\n(TypeDec\nlaration.java:845)\n        at \norg.eclipse.jdt.internal.compiler.ast.CompilationUnitDeclaration.reso\nlve(CompilationUnitDeclaration.java:251)\n        at org.eclipse.jdt.internal.compiler.Compiler.process\n(Compiler.java:538)\n\n        at org.aspectj.ajdt.internal.compiler.AjCompiler.process\n(AjCompiler.java\n:65)\n        at org.eclipse.jdt.internal.compiler.Compiler.compile\n(Compiler.java:338)\n\n        at \norg.aspectj.ajdt.internal.core.builder.AjBuildManager.performCompilat\nion(AjBuildManager.java:372)\n        at org.aspectj.ajdt.internal.core.builder.AjBuildManager.doBuild\n(AjBuild\nManager.java:133)\n        at org.aspectj.ajdt.internal.core.builder.AjBuildManager.batchBuild\n(AjBu\nildManager.java:78)\n        at org.aspectj.ajdt.ajc.AjdtCommand.doCommand(AjdtCommand.java:106)\n        at org.aspectj.ajdt.ajc.AjdtCommand.runCommand(AjdtCommand.java:60)\n        at org.aspectj.tools.ajc.Main.run(Main.java:217)\n        at org.aspectj.tools.ajc.Main.runMain(Main.java:155)\n        at org.aspectj.tools.ajc.Main.main(Main.java:72)\n\n\n!! no source information available !!\nABORT\nException thrown from AspectJ 1.1.0\n\nThis might be logged as a bug already -- find current bugs at\n  http://bugs.eclipse.org/bugs/buglist.cgi?product\u003dAspectJ\u0026component\u003dCompiler\n\nBugs for exceptions thrown have titles File:line from the top stack,\ne.g., \"SomeFile.java:243\"\n\nIf you don\u0027t find the exception below in a bug, please add a new bug\nat http://bugs.eclipse.org/bugs/enter_bug.cgi?product\u003dAspectJ\nTo make the bug a priority, please include a test program\nthat can reproduce this exception.\nBad type signature: \u003cmissing\u003e\nBad type signature: \u003cmissing\u003e\norg.aspectj.weaver.BCException: Bad type signature: \u003cmissing\u003e\n        at org.aspectj.weaver.TypeX.signatureToName(TypeX.java:565)\n        at org.aspectj.weaver.TypeX.getName(TypeX.java:205)\n        at org.aspectj.weaver.bcel.BcelWorld.resolveObjectType\n(BcelWorld.java:18\n2)\n        at org.aspectj.weaver.World.resolveObjectType(World.java:98)\n        at org.aspectj.weaver.World.resolve(World.java:80)\n        at org.aspectj.weaver.World.resolve(World.java:68)\n        at org.aspectj.weaver.patterns.ReferencePointcut.resolveBindings\n(Referen\ncePointcut.java:120)\n        at org.aspectj.weaver.patterns.Pointcut.resolve(Pointcut.java:100)\n        at \norg.aspectj.ajdt.internal.compiler.ast.PointcutDesignator.finishResol\nveTypes(PointcutDesignator.java:82)\n        at \norg.aspectj.ajdt.internal.compiler.ast.AdviceDeclaration.resolveState\nments(AdviceDeclaration.java:112)\n        at \norg.eclipse.jdt.internal.compiler.ast.AbstractMethodDeclaration.resol\nve(AbstractMethodDeclaration.java:317)\n        at org.eclipse.jdt.internal.compiler.ast.TypeDeclaration.resolve\n(TypeDec\nlaration.java:804)\n        at org.aspectj.ajdt.internal.compiler.ast.AspectDeclaration.resolve\n(Aspe\nctDeclaration.java:73)\n        at org.eclipse.jdt.internal.compiler.ast.TypeDeclaration.resolve\n(TypeDec\nlaration.java:845)\n        at \norg.eclipse.jdt.internal.compiler.ast.CompilationUnitDeclaration.reso\nlve(CompilationUnitDeclaration.java:251)\n        at org.eclipse.jdt.internal.compiler.Compiler.process\n(Compiler.java:538)\n\n        at org.aspectj.ajdt.internal.compiler.AjCompiler.process\n(AjCompiler.java\n:65)\n        at org.eclipse.jdt.internal.compiler.Compiler.compile\n(Compiler.java:338)\n\n        at \norg.aspectj.ajdt.internal.core.builder.AjBuildManager.performCompilat\nion(AjBuildManager.java:372)\n        at org.aspectj.ajdt.internal.core.builder.AjBuildManager.doBuild\n(AjBuild\nManager.java:133)\n        at org.aspectj.ajdt.internal.core.builder.AjBuildManager.batchBuild\n(AjBu\nildManager.java:78)\n        at org.aspectj.ajdt.ajc.AjdtCommand.doCommand(AjdtCommand.java:106)\n        at org.aspectj.ajdt.ajc.AjdtCommand.runCommand(AjdtCommand.java:60)\n        at org.aspectj.tools.ajc.Main.run(Main.java:217)\n        at org.aspectj.tools.ajc.Main.runMain(Main.java:155)\n        at org.aspectj.tools.ajc.Main.main(Main.java:72)\n\n\n1 fail|abort, 2 errors",
    "This is the same bug uncovered by Wes a couple of days ago and fixed in the tree.\n\n*** This bug has been marked as a duplicate of 40858 ***"
  ],
  "commentCreationDates": [
    "2003-08-05T05:40:13+02:00",
    "2003-08-05T23:09:39+02:00"
  ],
  "traces": [
    {
      "exceptionType": "org.aspectj.weaver.BCException",
      "message": "Bad type signature: \u003cmissing\u003e",
      "elements": [
        {
          "method": "org.aspectj.weaver.TypeX.signatureToName",
          "source": "TypeX.java:565"
        },
        {
          "method": "org.aspectj.weaver.TypeX.getName",
          "source": "TypeX.java:205"
        },
        {
          "method": "org.aspectj.weaver.bcel.BcelWorld.resolveObjectType",
          "source": "BcelWorld.java:18 2"
        },
        {
          "method": "org.aspectj.weaver.World.resolveObjectType",
          "source": "World.java:98"
        },
        {
          "method": "org.aspectj.weaver.World.resolve",
          "source": "World.java:80"
        },
        {
          "method": "org.aspectj.weaver.World.resolve",
          "source": "World.java:68"
        },
        {
          "method": "org.aspectj.weaver.patterns.ReferencePointcut.resolveBindings",
          "source": "Referen cePointcut.java:120"
        },
        {
          "method": "org.aspectj.weaver.patterns.Pointcut.resolve",
          "source": "Pointcut.java:100"
        },
        {
          "method": "org.aspectj.ajdt.internal.compiler.ast.PointcutDesignator.finishResolveTypes",
          "source": "PointcutDesignator.java:82"
        },
        {
          "method": "org.aspectj.ajdt.internal.compiler.ast.AdviceDeclaration.resolveStatements",
          "source": "AdviceDeclaration.java:112"
        },
        {
          "method": "org.eclipse.jdt.internal.compiler.ast.AbstractMethodDeclaration.resolve",
          "source": "AbstractMethodDeclaration.java:317"
        },
        {
          "method": "org.eclipse.jdt.internal.compiler.ast.TypeDeclaration.resolve",
          "source": "TypeDec laration.java:804"
        },
        {
          "method": "org.aspectj.ajdt.internal.compiler.ast.AspectDeclaration.resolve",
          "source": "Aspe ctDeclaration.java:73"
        },
        {
          "method": "org.eclipse.jdt.internal.compiler.ast.TypeDeclaration.resolve",
          "source": "TypeDec laration.java:845"
        },
        {
          "method": "org.eclipse.jdt.internal.compiler.ast.CompilationUnitDeclaration.resolve",
          "source": "CompilationUnitDeclaration.java:251"
        },
        {
          "method": "org.eclipse.jdt.internal.compiler.Compiler.process",
          "source": "Compiler.java:538"
        },
        {
          "method": "org.aspectj.ajdt.internal.compiler.AjCompiler.process",
          "source": "AjCompiler.java :65"
        },
        {
          "method": "org.eclipse.jdt.internal.compiler.Compiler.compile",
          "source": "Compiler.java:338"
        },
        {
          "method": "org.aspectj.ajdt.internal.core.builder.AjBuildManager.performCompilation",
          "source": "AjBuildManager.java:372"
        },
        {
          "method": "org.aspectj.ajdt.internal.core.builder.AjBuildManager.doBuild",
          "source": "AjBuild Manager.java:133"
        },
        {
          "method": "org.aspectj.ajdt.internal.core.builder.AjBuildManager.batchBuild",
          "source": "AjBu ildManager.java:78"
        },
        {
          "method": "org.aspectj.ajdt.ajc.AjdtCommand.doCommand",
          "source": "AjdtCommand.java:106"
        },
        {
          "method": "org.aspectj.ajdt.ajc.AjdtCommand.runCommand",
          "source": "AjdtCommand.java:60"
        },
        {
          "method": "org.aspectj.tools.ajc.Main.run",
          "source": "Main.java:217"
        },
        {
          "method": "org.aspectj.tools.ajc.Main.runMain",
          "source": "Main.java:155"
        },
        {
          "method": "org.aspectj.tools.ajc.Main.main",
          "source": "Main.java:72"
        }
      ],
      "number": 0,
      "commentIndex": 0,
      "bugId": "41121",
      "duplicateId": "40858",
      "date": "2003-08-05T05:40:13+02:00",
      "product": "AspectJ",
      "component": "Compiler",
      "severity": "normal"
    },
    {
      "exceptionType": "org.aspectj.weaver.BCException",
      "message": "Bad type signature: \u003cmissing\u003e",
      "elements": [
        {
          "method": "org.aspectj.weaver.TypeX.signatureToName",
          "source": "TypeX.java:565"
        },
        {
          "method": "org.aspectj.weaver.TypeX.getName",
          "source": "TypeX.java:205"
        },
        {
          "method": "org.aspectj.weaver.bcel.BcelWorld.resolveObjectType",
          "source": "BcelWorld.java:18 2"
        },
        {
          "method": "org.aspectj.weaver.World.resolveObjectType",
          "source": "World.java:98"
        },
        {
          "method": "org.aspectj.weaver.World.resolve",
          "source": "World.java:80"
        },
        {
          "method": "org.aspectj.weaver.World.resolve",
          "source": "World.java:68"
        },
        {
          "method": "org.aspectj.weaver.patterns.ReferencePointcut.resolveBindings",
          "source": "Referen cePointcut.java:120"
        },
        {
          "method": "org.aspectj.weaver.patterns.Pointcut.resolve",
          "source": "Pointcut.java:100"
        },
        {
          "method": "org.aspectj.ajdt.internal.compiler.ast.PointcutDesignator.finishResolveTypes",
          "source": "PointcutDesignator.java:82"
        },
        {
          "method": "org.aspectj.ajdt.internal.compiler.ast.AdviceDeclaration.resolveStatements",
          "source": "AdviceDeclaration.java:112"
        },
        {
          "method": "org.eclipse.jdt.internal.compiler.ast.AbstractMethodDeclaration.resolve",
          "source": "AbstractMethodDeclaration.java:317"
        },
        {
          "method": "org.eclipse.jdt.internal.compiler.ast.TypeDeclaration.resolve",
          "source": "TypeDec laration.java:804"
        },
        {
          "method": "org.aspectj.ajdt.internal.compiler.ast.AspectDeclaration.resolve",
          "source": "Aspe ctDeclaration.java:73"
        },
        {
          "method": "org.eclipse.jdt.internal.compiler.ast.TypeDeclaration.resolve",
          "source": "TypeDec laration.java:845"
        },
        {
          "method": "org.eclipse.jdt.internal.compiler.ast.CompilationUnitDeclaration.resolve",
          "source": "CompilationUnitDeclaration.java:251"
        },
        {
          "method": "org.eclipse.jdt.internal.compiler.Compiler.process",
          "source": "Compiler.java:538"
        },
        {
          "method": "org.aspectj.ajdt.internal.compiler.AjCompiler.process",
          "source": "AjCompiler.java :65"
        },
        {
          "method": "org.eclipse.jdt.internal.compiler.Compiler.compile",
          "source": "Compiler.java:338"
        },
        {
          "method": "org.aspectj.ajdt.internal.core.builder.AjBuildManager.performCompilation",
          "source": "AjBuildManager.java:372"
        },
        {
          "method": "org.aspectj.ajdt.internal.core.builder.AjBuildManager.doBuild",
          "source": "AjBuild Manager.java:133"
        },
        {
          "method": "org.aspectj.ajdt.internal.core.builder.AjBuildManager.batchBuild",
          "source": "AjBu ildManager.java:78"
        },
        {
          "method": "org.aspectj.ajdt.ajc.AjdtCommand.doCommand",
          "source": "AjdtCommand.java:106"
        },
        {
          "method": "org.aspectj.ajdt.ajc.AjdtCommand.runCommand",
          "source": "AjdtCommand.java:60"
        },
        {
          "method": "org.aspectj.tools.ajc.Main.run",
          "source": "Main.java:217"
        },
        {
          "method": "org.aspectj.tools.ajc.Main.runMain",
          "source": "Main.java:155"
        },
        {
          "method": "org.aspectj.tools.ajc.Main.main",
          "source": "Main.java:72"
        }
      ],
      "number": 1,
      "commentIndex": 0,
      "bugId": "41121",
      "duplicateId": "40858",
      "date": "2003-08-05T05:40:13+02:00",
      "product": "AspectJ",
      "component": "Compiler",
      "severity": "normal"
    },
    {
      "exceptionType": "org.aspectj.weaver.BCException",
      "message": "Bad type signature: \u003cmissing\u003e",
      "elements": [
        {
          "method": "org.aspectj.weaver.TypeX.signatureToName",
          "source": "TypeX.java:565"
        },
        {
          "method": "org.aspectj.weaver.TypeX.getName",
          "source": "TypeX.java:205"
        },
        {
          "method": "org.aspectj.weaver.bcel.BcelWorld.resolveObjectType",
          "source": "BcelWorld.java:18 2"
        },
        {
          "method": "org.aspectj.weaver.World.resolveObjectType",
          "source": "World.java:98"
        },
        {
          "method": "org.aspectj.weaver.World.resolve",
          "source": "World.java:80"
        },
        {
          "method": "org.aspectj.weaver.World.resolve",
          "source": "World.java:68"
        },
        {
          "method": "org.aspectj.weaver.patterns.ReferencePointcut.resolveBindings",
          "source": "Referen cePointcut.java:120"
        },
        {
          "method": "org.aspectj.weaver.patterns.Pointcut.resolve",
          "source": "Pointcut.java:100"
        },
        {
          "method": "org.aspectj.ajdt.internal.compiler.ast.PointcutDesignator.finishResolveTypes",
          "source": "PointcutDesignator.java:82"
        },
        {
          "method": "org.aspectj.ajdt.internal.compiler.ast.AdviceDeclaration.resolveStatements",
          "source": "AdviceDeclaration.java:112"
        },
        {
          "method": "org.eclipse.jdt.internal.compiler.ast.AbstractMethodDeclaration.resolve",
          "source": "AbstractMethodDeclaration.java:317"
        },
        {
          "method": "org.eclipse.jdt.internal.compiler.ast.TypeDeclaration.resolve",
          "source": "TypeDec laration.java:804"
        },
        {
          "method": "org.aspectj.ajdt.internal.compiler.ast.AspectDeclaration.resolve",
          "source": "Aspe ctDeclaration.java:73"
        },
        {
          "method": "org.eclipse.jdt.internal.compiler.ast.TypeDeclaration.resolve",
          "source": "TypeDec laration.java:845"
        },
        {
          "method": "org.eclipse.jdt.internal.compiler.ast.CompilationUnitDeclaration.resolve",
          "source": "CompilationUnitDeclaration.java:251"
        },
        {
          "method": "org.eclipse.jdt.internal.compiler.Compiler.process",
          "source": "Compiler.java:538"
        },
        {
          "method": "org.aspectj.ajdt.internal.compiler.AjCompiler.process",
          "source": "AjCompiler.java :65"
        },
        {
          "method": "org.eclipse.jdt.internal.compiler.Compiler.compile",
          "source": "Compiler.java:338"
        },
        {
          "method": "org.aspectj.ajdt.internal.core.builder.AjBuildManager.performCompilation",
          "source": "AjBuildManager.java:372"
        },
        {
          "method": "org.aspectj.ajdt.internal.core.builder.AjBuildManager.doBuild",
          "source": "AjBuild Manager.java:133"
        },
        {
          "method": "org.aspectj.ajdt.internal.core.builder.AjBuildManager.batchBuild",
          "source": "AjBu ildManager.java:78"
        },
        {
          "method": "org.aspectj.ajdt.ajc.AjdtCommand.doCommand",
          "source": "AjdtCommand.java:106"
        },
        {
          "method": "org.aspectj.ajdt.ajc.AjdtCommand.runCommand",
          "source": "AjdtCommand.java:60"
        },
        {
          "method": "org.aspectj.tools.ajc.Main.run",
          "source": "Main.java:217"
        },
        {
          "method": "org.aspectj.tools.ajc.Main.runMain",
          "source": "Main.java:155"
        },
        {
          "method": "org.aspectj.tools.ajc.Main.main",
          "source": "Main.java:72"
        }
      ],
      "number": 2,
      "commentIndex": 0,
      "bugId": "41121",
      "duplicateId": "40858",
      "date": "2003-08-05T05:40:13+02:00",
      "product": "AspectJ",
      "component": "Compiler",
      "severity": "normal"
    }
  ],
  "groupId": "40858",
  "bugId": "41121",
  "duplicateId": "40858",
  "date": "2003-08-05T05:40:13+02:00",
  "product": "AspectJ",
  "component": "Compiler",
  "severity": "normal"
}