{
  "comments": [
    "Eclipse: 200308201005 on Mac OS X Jaguar\n\nFiles I\u0027m editing and saving are not being saved to disk. There are no errors in the logs. It appears that \nthis is an editor problem, because the compiler compiles what is on disk.\n\nChang",
    "Sorry, there is something in the logs that looks suspicious but I was able to save succesfully after this:\n\n!ENTRY org.eclipse.ui 4 0 Aug 22, 2003 11:00:04.481\n!MESSAGE Assertion failed: \n!STACK 0\norg.eclipse.jface.text.Assert$AssertionFailedException: Assertion failed: \n        at org.eclipse.jface.text.Assert.isTrue(Assert.java:175)\n        at org.eclipse.jface.text.Assert.isTrue(Assert.java:160)\n        at org.eclipse.jface.text.Position.setLength(Position.java:176)\n        at \norg.eclipse.jdt.internal.ui.text.link.LinkedPositionManager.update(LinkedPositionManager.java:557)\n        at org.eclipse.jface.text.AbstractDocument.updatePositions(AbstractDocument.java:991)\n        at \norg.eclipse.jface.text.AbstractDocument.updateDocumentStructures(AbstractDocument.java:582)\n        at org.eclipse.jface.text.AbstractDocument.fireDocumentChanged(AbstractDocument.java:667)\n        at org.eclipse.jface.text.AbstractDocument.replace(AbstractDocument.java:961)\n        at \norg.eclipse.jdt.internal.ui.javaeditor.PartiallySynchronizedDocument.replace(PartiallySynchronizedDocum\nent.java:61)\n        at org.eclipse.jface.text.DocumentCommand$Command.execute(DocumentCommand.java:95)\n        at org.eclipse.jface.text.DocumentCommand.execute(DocumentCommand.java:444)\n        at org.eclipse.jface.text.TextViewer.handleVerifyEvent(TextViewer.java:3114)\n        at org.eclipse.jface.text.TextViewer$TextVerifyListener.verifyText(TextViewer.java:318)\n        at org.eclipse.swt.widgets.TypedListener.handleEvent(TypedListener.java:189)\n        at org.eclipse.swt.widgets.EventTable.sendEvent(EventTable.java:82)\n        at org.eclipse.swt.widgets.Widget.notifyListeners(Widget.java:1027)\n        at org.eclipse.swt.custom.StyledText.modifyContent(StyledText.java:5808)\n        at org.eclipse.swt.custom.StyledText.sendKeyEvent(StyledText.java:6794)\n        at org.eclipse.swt.custom.StyledText.doDelete(StyledText.java:2641)\n        at org.eclipse.swt.custom.StyledText.invokeAction(StyledText.java:5649)\n        at org.eclipse.swt.custom.StyledText.handleKey(StyledText.java:5191)\n        at org.eclipse.swt.custom.StyledText.handleKeyDown(StyledText.java:5210)\n        at org.eclipse.swt.custom.StyledText$8.handleEvent(StyledText.java:4957)\n        at org.eclipse.swt.widgets.EventTable.sendEvent(EventTable.java:82)\n        at org.eclipse.swt.widgets.Widget.sendEvent(Widget.java:1170)\n        at org.eclipse.swt.widgets.Widget.sendEvent(Widget.java:1194)\n        at org.eclipse.swt.widgets.Widget.sendEvent(Widget.java:1179)\n        at org.eclipse.swt.widgets.Control.sendKeyEvent(Control.java:1901)\n        at org.eclipse.swt.widgets.Control.sendKeyEvent(Control.java:1896)\n        at org.eclipse.swt.widgets.Control.kEventTextInputUnicodeForKeyEvent(Control.java:1441)\n        at org.eclipse.swt.widgets.Composite.kEventTextInputUnicodeForKeyEvent(Composite.java:368)\n        at org.eclipse.swt.widgets.Widget.textInputProc(Widget.java:1519)\n        at org.eclipse.swt.widgets.Display.textInputProc(Display.java:2653)\n        at org.eclipse.swt.internal.carbon.OS.SendEventToEventTarget(Native Method)\n        at org.eclipse.swt.widgets.Display.readAndDispatch(Display.java:1874)\n        at org.eclipse.ui.internal.Workbench.runEventLoop(Workbench.java:1676)\n        at org.eclipse.ui.internal.Workbench.run(Workbench.java:1659)\n        at org.eclipse.core.internal.boot.InternalBootLoader.run(InternalBootLoader.java:858)\n        at org.eclipse.core.boot.BootLoader.run(BootLoader.java:461)\n        at sun.reflect.NativeMethodAccessorImpl.invoke0(Native Method)\n        at sun.reflect.NativeMethodAccessorImpl.invoke(NativeMethodAccessorImpl.java:39)\n        at sun.reflect.DelegatingMethodAccessorImpl.invoke(DelegatingMethodAccessorImpl.java:25)\n        at java.lang.reflect.Method.invoke(Method.java:324)\n        at org.eclipse.core.launcher.Main.basicRun(Main.java:291)\n        at org.eclipse.core.launcher.Main.run(Main.java:747)\n        at org.eclipse.core.launcher.Main.main(Main.java:583)\n",
    "The exception stems from the new Asserts in Position (see bug 35470) and reveals\na bug in LinkedPositionManager. I cannot reproduce it - do you have steps?\n\nHowever, I suspect the inability to save documents to disk are rather a side\neffect of bug 41807 - are you sure it is related to the exception you mentioned? ",
    "Hi,\nits very possible that my problems occurred whilst editing the file outside and and then returning to it. I \ndid edit the file outside, but did a refresh.\n\nSo, no I cannot be certain that the stack is a cause of the problem.",
    "Ok, I assume that the \"Files are not being saved\" is a duplicate of bug 41807.\nAdjusting summary and severity.",
    "ok, thanks.",
    "this is a fix candidate for M3",
    "200308201005 + newest cvs update\n\nSteps:\n1. Start to type a method call and invoke content assist, so that parameters\nproposals are presented. The proposal popup for the first parameter is open.\n2. Choose Edit-\u003eShow Tooltip description (F2)\n-\u003e AssertionException happens \n",
    "Are you sure it is the same stack trace? I get a BadLocationException.\n\nA possible problem in the code could be that one of the positions gets\ninvalidated  and hence length can get \u003c 0.\n\nI could add a guard but this would hide the real cause of the problem.\n",
    "Build id: 200308260800, default preferences\n\n- create file MyClass.java:\n\npublic class MyClass {\n\tpublic static void ping() {\n\t}\n}\n\n- place cursor between \"(\" and \")\"\n- press key \"(\" \n- press Delete\n-\u003e Assertion failed",
    "Created an attachment (id\u003d5873)\npatch on LinkedPositionManager.java\n\nFix. LinkedPositionManager now leaves when a linked position gets deleted by a\ndocument change.",
    "The fix is too risky to go into M3.\n",
    "Tom and I finally chased it down and found a fix.\n",
    "*** Bug 42240 has been marked as a duplicate of this bug. ***",
    "*** Bug 43390 has been marked as a duplicate of this bug. ***"
  ],
  "commentCreationDates": [
    "2003-08-22T11:59:47+02:00",
    "2003-08-22T12:04:42+02:00",
    "2003-08-25T08:39:02+02:00",
    "2003-08-25T09:22:39+02:00",
    "2003-08-25T09:40:10+02:00",
    "2003-08-25T10:35:19+02:00",
    "2003-08-25T13:31:01+02:00",
    "2003-08-25T18:18:33+02:00",
    "2003-08-25T18:42:52+02:00",
    "2003-08-26T19:48:21+02:00",
    "2003-08-27T18:04:53+02:00",
    "2003-08-27T19:15:03+02:00",
    "2003-08-29T12:50:27+02:00",
    "2003-08-29T12:51:49+02:00",
    "2003-09-23T09:57:00+02:00"
  ],
  "traces": [
    {
      "exceptionType": "org.eclipse.jface.text.Assert$AssertionFailedException",
      "message": "Assertion failed:",
      "elements": [
        {
          "method": "org.eclipse.jface.text.Assert.isTrue",
          "source": "Assert.java:175"
        },
        {
          "method": "org.eclipse.jface.text.Assert.isTrue",
          "source": "Assert.java:160"
        },
        {
          "method": "org.eclipse.jface.text.Position.setLength",
          "source": "Position.java:176"
        },
        {
          "method": "org.eclipse.jdt.internal.ui.text.link.LinkedPositionManager.update",
          "source": "LinkedPositionManager.java:557"
        },
        {
          "method": "org.eclipse.jface.text.AbstractDocument.updatePositions",
          "source": "AbstractDocument.java:991"
        },
        {
          "method": "org.eclipse.jface.text.AbstractDocument.updateDocumentStructures",
          "source": "AbstractDocument.java:582"
        },
        {
          "method": "org.eclipse.jface.text.AbstractDocument.fireDocumentChanged",
          "source": "AbstractDocument.java:667"
        },
        {
          "method": "org.eclipse.jface.text.AbstractDocument.replace",
          "source": "AbstractDocument.java:961"
        },
        {
          "method": "org.eclipse.jdt.internal.ui.javaeditor.PartiallySynchronizedDocument.replace",
          "source": "PartiallySynchronizedDocum ent.java:61"
        },
        {
          "method": "org.eclipse.jface.text.DocumentCommand$Command.execute",
          "source": "DocumentCommand.java:95"
        },
        {
          "method": "org.eclipse.jface.text.DocumentCommand.execute",
          "source": "DocumentCommand.java:444"
        },
        {
          "method": "org.eclipse.jface.text.TextViewer.handleVerifyEvent",
          "source": "TextViewer.java:3114"
        },
        {
          "method": "org.eclipse.jface.text.TextViewer$TextVerifyListener.verifyText",
          "source": "TextViewer.java:318"
        },
        {
          "method": "org.eclipse.swt.widgets.TypedListener.handleEvent",
          "source": "TypedListener.java:189"
        },
        {
          "method": "org.eclipse.swt.widgets.EventTable.sendEvent",
          "source": "EventTable.java:82"
        },
        {
          "method": "org.eclipse.swt.widgets.Widget.notifyListeners",
          "source": "Widget.java:1027"
        },
        {
          "method": "org.eclipse.swt.custom.StyledText.modifyContent",
          "source": "StyledText.java:5808"
        },
        {
          "method": "org.eclipse.swt.custom.StyledText.sendKeyEvent",
          "source": "StyledText.java:6794"
        },
        {
          "method": "org.eclipse.swt.custom.StyledText.doDelete",
          "source": "StyledText.java:2641"
        },
        {
          "method": "org.eclipse.swt.custom.StyledText.invokeAction",
          "source": "StyledText.java:5649"
        },
        {
          "method": "org.eclipse.swt.custom.StyledText.handleKey",
          "source": "StyledText.java:5191"
        },
        {
          "method": "org.eclipse.swt.custom.StyledText.handleKeyDown",
          "source": "StyledText.java:5210"
        },
        {
          "method": "org.eclipse.swt.custom.StyledText$8.handleEvent",
          "source": "StyledText.java:4957"
        },
        {
          "method": "org.eclipse.swt.widgets.EventTable.sendEvent",
          "source": "EventTable.java:82"
        },
        {
          "method": "org.eclipse.swt.widgets.Widget.sendEvent",
          "source": "Widget.java:1170"
        },
        {
          "method": "org.eclipse.swt.widgets.Widget.sendEvent",
          "source": "Widget.java:1194"
        },
        {
          "method": "org.eclipse.swt.widgets.Widget.sendEvent",
          "source": "Widget.java:1179"
        },
        {
          "method": "org.eclipse.swt.widgets.Control.sendKeyEvent",
          "source": "Control.java:1901"
        },
        {
          "method": "org.eclipse.swt.widgets.Control.sendKeyEvent",
          "source": "Control.java:1896"
        },
        {
          "method": "org.eclipse.swt.widgets.Control.kEventTextInputUnicodeForKeyEvent",
          "source": "Control.java:1441"
        },
        {
          "method": "org.eclipse.swt.widgets.Composite.kEventTextInputUnicodeForKeyEvent",
          "source": "Composite.java:368"
        },
        {
          "method": "org.eclipse.swt.widgets.Widget.textInputProc",
          "source": "Widget.java:1519"
        },
        {
          "method": "org.eclipse.swt.widgets.Display.textInputProc",
          "source": "Display.java:2653"
        },
        {
          "method": "org.eclipse.swt.internal.carbon.OS.SendEventToEventTarget",
          "source": "Native Method"
        },
        {
          "method": "org.eclipse.swt.widgets.Display.readAndDispatch",
          "source": "Display.java:1874"
        },
        {
          "method": "org.eclipse.ui.internal.Workbench.runEventLoop",
          "source": "Workbench.java:1676"
        },
        {
          "method": "org.eclipse.ui.internal.Workbench.run",
          "source": "Workbench.java:1659"
        },
        {
          "method": "org.eclipse.core.internal.boot.InternalBootLoader.run",
          "source": "InternalBootLoader.java:858"
        },
        {
          "method": "org.eclipse.core.boot.BootLoader.run",
          "source": "BootLoader.java:461"
        },
        {
          "method": "sun.reflect.NativeMethodAccessorImpl.invoke0",
          "source": "Native Method"
        },
        {
          "method": "sun.reflect.NativeMethodAccessorImpl.invoke",
          "source": "NativeMethodAccessorImpl.java:39"
        },
        {
          "method": "sun.reflect.DelegatingMethodAccessorImpl.invoke",
          "source": "DelegatingMethodAccessorImpl.java:25"
        },
        {
          "method": "java.lang.reflect.Method.invoke",
          "source": "Method.java:324"
        },
        {
          "method": "org.eclipse.core.launcher.Main.basicRun",
          "source": "Main.java:291"
        },
        {
          "method": "org.eclipse.core.launcher.Main.run",
          "source": "Main.java:747"
        },
        {
          "method": "org.eclipse.core.launcher.Main.main",
          "source": "Main.java:583"
        }
      ],
      "number": 0,
      "commentIndex": 1,
      "bugId": "41849",
      "date": "2003-08-22T12:04:42+02:00",
      "product": "JDT",
      "component": "Text",
      "severity": "normal"
    }
  ],
  "groupId": "41849",
  "bugId": "41849",
  "date": "2003-08-22T11:59:47+02:00",
  "product": "JDT",
  "component": "Text",
  "severity": "normal"
}