{
  "comments": [
    "The stack below was generated and eclipse crashed...\n\n!MESSAGE Assertion failed: Invariant violated (lines: 357 size: 327)\n!STACK 0\norg.eclipse.jface.util.Assert$AssertionFailedException: Assertion failed: Invariant violated (lines: 357 \nsize: 327)\n        at org.eclipse.jface.util.Assert.isTrue(Assert.java:168)\n        at \norg.eclipse.ui.internal.texteditor.quickdiff.DocumentLineDiffer.invariant(DocumentLineDiffer.java:984)\n        at \norg.eclipse.ui.internal.texteditor.quickdiff.DocumentLineDiffer.disconnect(DocumentLineDiffer.java:1022\n)\n        at org.eclipse.jface.text.source.AnnotationModel.disconnect(AnnotationModel.java:182)\n        at org.eclipse.jface.text.source.VisualAnnotationModel.disconnect(VisualAnnotationModel.java:86)\n        at org.eclipse.jface.text.source.SourceViewer.setDocument(SourceViewer.java:367)\n        at org.eclipse.jface.text.source.SourceViewer.setDocument(SourceViewer.java:335)\n        at org.eclipse.jface.text.TextViewer$1.widgetDisposed(TextViewer.java:1296)\n        at org.eclipse.swt.widgets.TypedListener.handleEvent(TypedListener.java:100)\n        at org.eclipse.swt.widgets.EventTable.sendEvent(EventTable.java:82)\n        at org.eclipse.swt.widgets.Widget.sendEvent(Widget.java:1170)\n        at org.eclipse.swt.widgets.Widget.sendEvent(Widget.java:1194)\n        at org.eclipse.swt.widgets.Widget.sendEvent(Widget.java:1175)\n        at org.eclipse.swt.widgets.Widget.releaseWidget(Widget.java:1081)\n        at org.eclipse.swt.widgets.Control.releaseWidget(Control.java:1594)\n        at org.eclipse.swt.widgets.Scrollable.releaseWidget(Scrollable.java:336)\n        at org.eclipse.swt.widgets.Composite.releaseWidget(Composite.java:464)\n        at org.eclipse.swt.widgets.Canvas.releaseWidget(Canvas.java:127)\n        at org.eclipse.swt.widgets.Widget.releaseResources(Widget.java:1076)\n        at org.eclipse.swt.widgets.Composite.releaseChildren(Composite.java:458)\n        at org.eclipse.swt.widgets.Composite.releaseWidget(Composite.java:463)\n        at org.eclipse.swt.widgets.Canvas.releaseWidget(Canvas.java:127)\n        at org.eclipse.swt.widgets.Widget.releaseResources(Widget.java:1076)\n        at org.eclipse.swt.widgets.Composite.releaseChildren(Composite.java:458)\n        at org.eclipse.swt.widgets.Composite.releaseWidget(Composite.java:463)\n        at org.eclipse.swt.widgets.Widget.releaseResources(Widget.java:1076)\n        at org.eclipse.swt.widgets.Composite.releaseChildren(Composite.java:458)\n        at org.eclipse.swt.widgets.Composite.releaseWidget(Composite.java:463)\n        at org.eclipse.swt.widgets.Widget.releaseResources(Widget.java:1076)\n        at org.eclipse.swt.widgets.Composite.releaseChildren(Composite.java:458)\n        at org.eclipse.swt.widgets.Composite.releaseWidget(Composite.java:463)\n        at org.eclipse.swt.widgets.Widget.releaseResources(Widget.java:1076)\n        at org.eclipse.swt.widgets.Composite.releaseChildren(Composite.java:458)\n        at org.eclipse.swt.widgets.Composite.releaseWidget(Composite.java:463)\n        at org.eclipse.swt.widgets.Widget.dispose(Widget.java:484)\n        at org.eclipse.ui.internal.PartPane.dispose(PartPane.java:205)\n        at org.eclipse.ui.internal.EditorPresentation.closeAllEditors(EditorPresentation.java:51)\n        at org.eclipse.ui.internal.EditorManager.closeAll(EditorManager.java:81)\n        at org.eclipse.ui.internal.WorkbenchPage.closeAllEditors(WorkbenchPage.java:783)\n        at org.eclipse.ui.internal.CloseAllAction.run(CloseAllAction.java:78)\n        at org.eclipse.jface.action.Action.runWithEvent(Action.java:842)\n        at \norg.eclipse.jface.action.ActionContributionItem.handleWidgetSelection(ActionContributionItem.java:542)\n        at org.eclipse.jface.action.ActionContributionItem.access$4(ActionContributionItem.java:483)\n        at org.eclipse.jface.action.ActionContributionItem$6.handleEvent(ActionContributionItem.java:455)\n        at org.eclipse.swt.widgets.EventTable.sendEvent(EventTable.java:82)\n        at org.eclipse.swt.widgets.Widget.notifyListeners(Widget.java:1027)\n        at org.eclipse.swt.widgets.Display.runDeferredEvents(Display.java:2180)\n        at org.eclipse.swt.widgets.Display.readAndDispatch(Display.java:1878)\n        at org.eclipse.ui.internal.Workbench.runEventLoop(Workbench.java:1676)\n        at org.eclipse.ui.internal.Workbench.run(Workbench.java:1659)\n        at org.eclipse.core.internal.boot.InternalBootLoader.run(InternalBootLoader.java:858)\n        at org.eclipse.core.boot.BootLoader.run(BootLoader.java:461)\n        at sun.reflect.NativeMethodAccessorImpl.invoke0(Native Method)\n        at sun.reflect.NativeMethodAccessorImpl.invoke(NativeMethodAccessorImpl.java:39)\n        at sun.reflect.DelegatingMethodAccessorImpl.invoke(DelegatingMethodAccessorImpl.java:25)\n        at java.lang.reflect.Method.invoke(Method.java:324)\n        at org.eclipse.core.launcher.Main.basicRun(Main.java:291)\n        at org.eclipse.core.launcher.Main.run(Main.java:747)\n        at org.eclipse.core.launcher.Main.main(Main.java:583)",
    "When did the exception occur - did you issue a \"Close All\" command, as the stack\ntrace indicates? Can you reproduce it? I have seen similar cases, but was not\nable to reproduce.",
    "Hi,\nyes I did issue a close all comand, and no I cannot reproduce it :-(\n\nChanning",
    "Still cannot reproduce. \u003e 20030911 has been modified to me more graceful when\nquick diff goes out of sync, so one can still edit a file and does not need to\nrestart the workbench.\n\n- Lowering priority as no reproduceable steps.\n- Chaging platform, as similar erros have been seen on several platforms.",
    "ok, I\u0027ll look out for it in case it happens again, but I haven\u0027t seen it for a while.",
    "fixed \u003e 20030930\n\nquick diff generation has completely been redone."
  ],
  "commentCreationDates": [
    "2003-08-24T23:14:34+02:00",
    "2003-08-25T08:23:58+02:00",
    "2003-08-25T09:20:31+02:00",
    "2003-09-11T19:05:36+02:00",
    "2003-09-11T20:17:33+02:00",
    "2003-09-30T11:15:16+02:00"
  ],
  "traces": [
    {
      "exceptionType": "org.eclipse.jface.util.Assert$AssertionFailedException",
      "message": "Assertion failed: Invariant violated (lines: 357  size: 327)",
      "elements": [
        {
          "method": "org.eclipse.jface.util.Assert.isTrue",
          "source": "Assert.java:168"
        },
        {
          "method": "org.eclipse.ui.internal.texteditor.quickdiff.DocumentLineDiffer.invariant",
          "source": "DocumentLineDiffer.java:984"
        },
        {
          "method": "org.eclipse.ui.internal.texteditor.quickdiff.DocumentLineDiffer.disconnect",
          "source": "DocumentLineDiffer.java:1022 "
        },
        {
          "method": "org.eclipse.jface.text.source.AnnotationModel.disconnect",
          "source": "AnnotationModel.java:182"
        },
        {
          "method": "org.eclipse.jface.text.source.VisualAnnotationModel.disconnect",
          "source": "VisualAnnotationModel.java:86"
        },
        {
          "method": "org.eclipse.jface.text.source.SourceViewer.setDocument",
          "source": "SourceViewer.java:367"
        },
        {
          "method": "org.eclipse.jface.text.source.SourceViewer.setDocument",
          "source": "SourceViewer.java:335"
        },
        {
          "method": "org.eclipse.jface.text.TextViewer$1.widgetDisposed",
          "source": "TextViewer.java:1296"
        },
        {
          "method": "org.eclipse.swt.widgets.TypedListener.handleEvent",
          "source": "TypedListener.java:100"
        },
        {
          "method": "org.eclipse.swt.widgets.EventTable.sendEvent",
          "source": "EventTable.java:82"
        },
        {
          "method": "org.eclipse.swt.widgets.Widget.sendEvent",
          "source": "Widget.java:1170"
        },
        {
          "method": "org.eclipse.swt.widgets.Widget.sendEvent",
          "source": "Widget.java:1194"
        },
        {
          "method": "org.eclipse.swt.widgets.Widget.sendEvent",
          "source": "Widget.java:1175"
        },
        {
          "method": "org.eclipse.swt.widgets.Widget.releaseWidget",
          "source": "Widget.java:1081"
        },
        {
          "method": "org.eclipse.swt.widgets.Control.releaseWidget",
          "source": "Control.java:1594"
        },
        {
          "method": "org.eclipse.swt.widgets.Scrollable.releaseWidget",
          "source": "Scrollable.java:336"
        },
        {
          "method": "org.eclipse.swt.widgets.Composite.releaseWidget",
          "source": "Composite.java:464"
        },
        {
          "method": "org.eclipse.swt.widgets.Canvas.releaseWidget",
          "source": "Canvas.java:127"
        },
        {
          "method": "org.eclipse.swt.widgets.Widget.releaseResources",
          "source": "Widget.java:1076"
        },
        {
          "method": "org.eclipse.swt.widgets.Composite.releaseChildren",
          "source": "Composite.java:458"
        },
        {
          "method": "org.eclipse.swt.widgets.Composite.releaseWidget",
          "source": "Composite.java:463"
        },
        {
          "method": "org.eclipse.swt.widgets.Canvas.releaseWidget",
          "source": "Canvas.java:127"
        },
        {
          "method": "org.eclipse.swt.widgets.Widget.releaseResources",
          "source": "Widget.java:1076"
        },
        {
          "method": "org.eclipse.swt.widgets.Composite.releaseChildren",
          "source": "Composite.java:458"
        },
        {
          "method": "org.eclipse.swt.widgets.Composite.releaseWidget",
          "source": "Composite.java:463"
        },
        {
          "method": "org.eclipse.swt.widgets.Widget.releaseResources",
          "source": "Widget.java:1076"
        },
        {
          "method": "org.eclipse.swt.widgets.Composite.releaseChildren",
          "source": "Composite.java:458"
        },
        {
          "method": "org.eclipse.swt.widgets.Composite.releaseWidget",
          "source": "Composite.java:463"
        },
        {
          "method": "org.eclipse.swt.widgets.Widget.releaseResources",
          "source": "Widget.java:1076"
        },
        {
          "method": "org.eclipse.swt.widgets.Composite.releaseChildren",
          "source": "Composite.java:458"
        },
        {
          "method": "org.eclipse.swt.widgets.Composite.releaseWidget",
          "source": "Composite.java:463"
        },
        {
          "method": "org.eclipse.swt.widgets.Widget.releaseResources",
          "source": "Widget.java:1076"
        },
        {
          "method": "org.eclipse.swt.widgets.Composite.releaseChildren",
          "source": "Composite.java:458"
        },
        {
          "method": "org.eclipse.swt.widgets.Composite.releaseWidget",
          "source": "Composite.java:463"
        },
        {
          "method": "org.eclipse.swt.widgets.Widget.dispose",
          "source": "Widget.java:484"
        },
        {
          "method": "org.eclipse.ui.internal.PartPane.dispose",
          "source": "PartPane.java:205"
        },
        {
          "method": "org.eclipse.ui.internal.EditorPresentation.closeAllEditors",
          "source": "EditorPresentation.java:51"
        },
        {
          "method": "org.eclipse.ui.internal.EditorManager.closeAll",
          "source": "EditorManager.java:81"
        },
        {
          "method": "org.eclipse.ui.internal.WorkbenchPage.closeAllEditors",
          "source": "WorkbenchPage.java:783"
        },
        {
          "method": "org.eclipse.ui.internal.CloseAllAction.run",
          "source": "CloseAllAction.java:78"
        },
        {
          "method": "org.eclipse.jface.action.Action.runWithEvent",
          "source": "Action.java:842"
        },
        {
          "method": "org.eclipse.jface.action.ActionContributionItem.handleWidgetSelection",
          "source": "ActionContributionItem.java:542"
        },
        {
          "method": "org.eclipse.jface.action.ActionContributionItem.access$4",
          "source": "ActionContributionItem.java:483"
        },
        {
          "method": "org.eclipse.jface.action.ActionContributionItem$6.handleEvent",
          "source": "ActionContributionItem.java:455"
        },
        {
          "method": "org.eclipse.swt.widgets.EventTable.sendEvent",
          "source": "EventTable.java:82"
        },
        {
          "method": "org.eclipse.swt.widgets.Widget.notifyListeners",
          "source": "Widget.java:1027"
        },
        {
          "method": "org.eclipse.swt.widgets.Display.runDeferredEvents",
          "source": "Display.java:2180"
        },
        {
          "method": "org.eclipse.swt.widgets.Display.readAndDispatch",
          "source": "Display.java:1878"
        },
        {
          "method": "org.eclipse.ui.internal.Workbench.runEventLoop",
          "source": "Workbench.java:1676"
        },
        {
          "method": "org.eclipse.ui.internal.Workbench.run",
          "source": "Workbench.java:1659"
        },
        {
          "method": "org.eclipse.core.internal.boot.InternalBootLoader.run",
          "source": "InternalBootLoader.java:858"
        },
        {
          "method": "org.eclipse.core.boot.BootLoader.run",
          "source": "BootLoader.java:461"
        },
        {
          "method": "sun.reflect.NativeMethodAccessorImpl.invoke0",
          "source": "Native Method"
        },
        {
          "method": "sun.reflect.NativeMethodAccessorImpl.invoke",
          "source": "NativeMethodAccessorImpl.java:39"
        },
        {
          "method": "sun.reflect.DelegatingMethodAccessorImpl.invoke",
          "source": "DelegatingMethodAccessorImpl.java:25"
        },
        {
          "method": "java.lang.reflect.Method.invoke",
          "source": "Method.java:324"
        },
        {
          "method": "org.eclipse.core.launcher.Main.basicRun",
          "source": "Main.java:291"
        },
        {
          "method": "org.eclipse.core.launcher.Main.run",
          "source": "Main.java:747"
        },
        {
          "method": "org.eclipse.core.launcher.Main.main",
          "source": "Main.java:583"
        }
      ],
      "number": 0,
      "commentIndex": 0,
      "bugId": "41904",
      "date": "2003-08-24T23:14:34+02:00",
      "product": "Platform",
      "component": "Text",
      "severity": "normal"
    }
  ],
  "groupId": "41904",
  "bugId": "41904",
  "date": "2003-08-24T23:14:34+02:00",
  "product": "Platform",
  "component": "Text",
  "severity": "normal"
}