{
  "comments": [
    "Create a .cpp file, and fill it with some bad C++, eg.\n  int ++;\nSave.\n\nCheck the console and you have this noise. (see below)\nPresumably for debug purposes, but when is it going to go away?\n\n\nParse Exception in Outline View\norg.eclipse.cdt.internal.core.parser.ParserException: Parse failure\n        at org.eclipse.cdt.internal.core.model.CModelBuilder.parse\n(CModelBuilder.java:82)\n        at org.eclipse.cdt.internal.core.model.CModelBuilder.parse\n(CModelBuilder.java:88)\n        at org.eclipse.cdt.internal.core.model.CModelBuilder.parse\n(CModelBuilder.java:108)\n        at org.eclipse.cdt.internal.core.model.TranslationUnit.parse\n(TranslationUnit.java:215)\n        at org.eclipse.cdt.internal.core.model.TranslationUnit.parse\n(TranslationUnit.java:489)\n        at org.eclipse.cdt.internal.core.model.TranslationUnit.generateInfos\n(TranslationUnit.java:324)\n        at org.eclipse.cdt.internal.core.model.TranslationUnit.buildStructure\n(TranslationUnit.java:243)\n        at org.eclipse.cdt.internal.core.model.TranslationUnit.makeConsistent\n(TranslationUnit.java:449)\n        at org.eclipse.cdt.internal.core.model.TranslationUnit.makeConsistent\n(TranslationUnit.java:443)\n        at org.eclipse.cdt.internal.core.model.WorkingCopy.reconcile\n(WorkingCopy.java:313)\n        at org.eclipse.cdt.internal.ui.text.CReconcilingStrategy.reconcile\n(CReconcilingStrategy.java:88)\n        at org.eclipse.cdt.internal.ui.text.CReconcilingStrategy.reconcile\n(CReconcilingStrategy.java:66)\n        at org.eclipse.jface.text.reconciler.Reconciler.process\n(Reconciler.java:124)\n        at \norg.eclipse.jface.text.reconciler.AbstractReconciler$BackgroundThread.run\n(AbstractReconciler.java:189)",
    "Hoda\u0027s stuff in the outline view should be using the Util.debugLog rather than \nSystem.out.print*.\n\nReassigning to Hoda   ",
    "Solved.\nThe CModel Builder now uses Util.debugLog instead of System.out.println",
    "Verified on 1.2.0.35 on Linux.\n"
  ],
  "commentCreationDates": [
    "2003-08-27T20:03:20+02:00",
    "2003-08-28T16:36:40+02:00",
    "2003-08-28T17:44:59+02:00",
    "2003-09-04T22:52:29+02:00"
  ],
  "traces": [
    {
      "exceptionType": "org.eclipse.cdt.internal.core.parser.ParserException",
      "message": "Parse failure",
      "elements": [
        {
          "method": "org.eclipse.cdt.internal.core.model.CModelBuilder.parse",
          "source": "CModelBuilder.java:82"
        },
        {
          "method": "org.eclipse.cdt.internal.core.model.CModelBuilder.parse",
          "source": "CModelBuilder.java:88"
        },
        {
          "method": "org.eclipse.cdt.internal.core.model.CModelBuilder.parse",
          "source": "CModelBuilder.java:108"
        },
        {
          "method": "org.eclipse.cdt.internal.core.model.TranslationUnit.parse",
          "source": "TranslationUnit.java:215"
        },
        {
          "method": "org.eclipse.cdt.internal.core.model.TranslationUnit.parse",
          "source": "TranslationUnit.java:489"
        },
        {
          "method": "org.eclipse.cdt.internal.core.model.TranslationUnit.generateInfos",
          "source": "TranslationUnit.java:324"
        },
        {
          "method": "org.eclipse.cdt.internal.core.model.TranslationUnit.buildStructure",
          "source": "TranslationUnit.java:243"
        },
        {
          "method": "org.eclipse.cdt.internal.core.model.TranslationUnit.makeConsistent",
          "source": "TranslationUnit.java:449"
        },
        {
          "method": "org.eclipse.cdt.internal.core.model.TranslationUnit.makeConsistent",
          "source": "TranslationUnit.java:443"
        },
        {
          "method": "org.eclipse.cdt.internal.core.model.WorkingCopy.reconcile",
          "source": "WorkingCopy.java:313"
        },
        {
          "method": "org.eclipse.cdt.internal.ui.text.CReconcilingStrategy.reconcile",
          "source": "CReconcilingStrategy.java:88"
        },
        {
          "method": "org.eclipse.cdt.internal.ui.text.CReconcilingStrategy.reconcile",
          "source": "CReconcilingStrategy.java:66"
        },
        {
          "method": "org.eclipse.jface.text.reconciler.Reconciler.process",
          "source": "Reconciler.java:124"
        },
        {
          "method": "org.eclipse.jface.text.reconciler.AbstractReconciler$BackgroundThread.run",
          "source": "AbstractReconciler.java:189"
        }
      ],
      "number": 0,
      "commentIndex": 0,
      "bugId": "42163",
      "date": "2003-08-27T20:03:20+02:00",
      "product": "CDT",
      "component": "CDT-parser",
      "severity": "normal"
    }
  ],
  "groupId": "42163",
  "bugId": "42163",
  "date": "2003-08-27T20:03:20+02:00",
  "product": "CDT",
  "component": "CDT-parser",
  "severity": "normal"
}