{
  "comments": [
    "3.0M3 on an old workspace.\n\nI clicked on java\u003ecompiler in the preferences dialog and got an error dialog.\nThe .log file contains the following stack trace :\n\njava.lang.NullPointerException\n        at java.lang.Throwable.\u003cinit\u003e(Throwable.java)\n        at java.lang.Throwable.\u003cinit\u003e(Throwable.java)\n        at java.lang.NullPointerException.\u003cinit\u003e(NullPointerException.java:63)\n        at\norg.eclipse.jdt.internal.ui.preferences.CompilerConfigurationBlock.updateEnableStates(CompilerConfigurationBlock.java:593)\n        at\norg.eclipse.jdt.internal.ui.preferences.CompilerConfigurationBlock.validateSettings(CompilerConfigurationBlock.java:576)\n        at\norg.eclipse.jdt.internal.ui.preferences.OptionsConfigurationBlock.controlChanged(OptionsConfigurationBlock.java:263)\n        at\norg.eclipse.jdt.internal.ui.preferences.OptionsConfigurationBlock$1.widgetSelected(OptionsConfigurationBlock.java:233)\n        at org.eclipse.swt.widgets.TypedListener.handleEvent(TypedListener.java)\n        at org.eclipse.swt.widgets.EventTable.sendEvent(EventTable.java)\n        at org.eclipse.swt.widgets.Widget.sendEvent(Widget.java)\n        at org.eclipse.swt.widgets.Widget.sendEvent(Widget.java)\n        at org.eclipse.swt.widgets.Widget.sendEvent(Widget.java)\n        at org.eclipse.swt.widgets.Combo.gtk_changed(Combo.java:745)\n        at org.eclipse.swt.widgets.Widget.windowProc(Widget.java:1174)\n        at org.eclipse.swt.widgets.Display.windowProc(Display.java)\n        at org.eclipse.swt.internal.gtk.OS.gtk_entry_set_text(Native Method)\n        at org.eclipse.swt.widgets.Combo.setText(Combo.java:1216)\n        at org.eclipse.swt.widgets.Combo.select(Combo.java:1050)\n        at\norg.eclipse.jdt.internal.ui.preferences.OptionsConfigurationBlock.addComboBox(OptionsConfigurationBlock.java:197)\n        at\norg.eclipse.jdt.internal.ui.preferences.CompilerConfigurationBlock.createUnusedCodeTabContent(CompilerConfigurationBlock.java:354)\n        at\norg.eclipse.jdt.internal.ui.preferences.CompilerConfigurationBlock.createContents(CompilerConfigurationBlock.java:183)\n        at\norg.eclipse.jdt.internal.ui.preferences.CompilerPreferencePage.createContents(CompilerPreferencePage.java:65)\n        at\norg.eclipse.jface.preference.PreferencePage.createControl(PreferencePage.java:217)\n        at\norg.eclipse.jdt.internal.ui.preferences.CompilerPreferencePage.createControl(CompilerPreferencePage.java:57)\n        at\norg.eclipse.jface.preference.PreferenceDialog$12.run(PreferenceDialog.java:986)\n        at\norg.eclipse.core.internal.runtime.InternalPlatform.run(InternalPlatform.java)\n        at org.eclipse.core.runtime.Platform.run(Platform.java)\n        at\norg.eclipse.jface.preference.PreferenceDialog.showPage(PreferenceDialog.java:984)\n        at\norg.eclipse.jface.preference.PreferenceDialog.selectSavedItem(PreferenceDialog.java:670)\n        at\norg.eclipse.jface.preference.PreferenceDialog$3.run(PreferenceDialog.java:297)\n        at org.eclipse.swt.custom.BusyIndicator.showWhile(BusyIndicator.java)\n        at\norg.eclipse.jface.preference.PreferenceDialog.createContents(PreferenceDialog.java:292)\n        at org.eclipse.jface.window.Window.create(Window.java:302)\n        at org.eclipse.jface.dialogs.Dialog.create(Dialog.java:876)\n        at\norg.eclipse.ui.internal.OpenPreferencesAction.run(OpenPreferencesAction.java:51)\n        at org.eclipse.jface.action.Action.runWithEvent(Action.java:842)\n        at\norg.eclipse.jface.action.ActionContributionItem.handleWidgetSelection(ActionContributionItem.java:529)\n        at\norg.eclipse.jface.action.ActionContributionItem.access$4(ActionContributionItem.java:482)\n        at\norg.eclipse.jface.action.ActionContributionItem$6.handleEvent(ActionContributionItem.java:454)\n        at org.eclipse.swt.widgets.EventTable.sendEvent(EventTable.java)\n        at org.eclipse.swt.widgets.Widget.sendEvent(Widget.java)\n        at org.eclipse.swt.widgets.Display.runDeferredEvents(Display.java)\n        at org.eclipse.swt.widgets.Display.readAndDispatch(Display.java)\n        at org.eclipse.ui.internal.Workbench.runEventLoop(Workbench.java:2036)\n        at org.eclipse.ui.internal.Workbench.run(Workbench.java:2019)\n        at\norg.eclipse.core.internal.boot.InternalBootLoader.run(InternalBootLoader.java:858)\n        at org.eclipse.core.boot.BootLoader.run(BootLoader.java:461)\n        at java.lang.reflect.AccessibleObject.invokeL(AccessibleObject.java:207)\n        at java.lang.reflect.Method.invoke(Method.java:271)\n        at org.eclipse.core.launcher.Main.basicRun(Main.java:295)\n        at org.eclipse.core.launcher.Main.run(Main.java:751)\n        at org.eclipse.core.launcher.Main.main(Main.java:587)",
    "Created an attachment (id\u003d5910)\nan export of my preferences\n\nI can reproduce the problem by importing this preference file on a new\nworkspace then opening the java\u003ecompiler preference page.",
    "This is Linux/GTK problem only. It works fine on Windows and Mac.\n\nThere is no need to import the the preferences. On Linux/GTK, opening the\njava\u003ecompiler preference page on a new workspace generate the problem.\n\nIt may be SWT/GTK problem.",
    "It may be relate to bug 39781",
    "Moving to SWT for comments.\n\nHere is what out code does: we create a bunch of check boxes and to identify \nthem later we put an id into the data slot. For some reason the widget doesn\u0027t \nexist under Linux GTK or it doesn\u0027t find the right one.\n\nLuc, do you have another exception in the log which might indicate that the \nwidget could not be created.",
    "*** Bug 42301 has been marked as a duplicate of this bug. ***",
    "Too bad we have this in M3. It happens in a new workspace as well.\nA bad change in the Combo cause it to send Selection events when the API \nsetText is called.\n\nThis is fixed in HEAD \u003e 20030902.\n\n",
    "*** Bug 42446 has been marked as a duplicate of this bug. ***",
    "Was this fix supposed to be in the 20030903 build?",
    "It\u0027s fixed in 20030910"
  ],
  "commentCreationDates": [
    "2003-08-29T20:00:23+02:00",
    "2003-08-29T20:06:32+02:00",
    "2003-08-29T20:20:37+02:00",
    "2003-08-29T22:22:54+02:00",
    "2003-09-01T10:07:49+02:00",
    "2003-09-01T10:38:15+02:00",
    "2003-09-02T18:39:32+02:00",
    "2003-09-03T17:46:46+02:00",
    "2003-09-08T20:35:12+02:00",
    "2003-09-10T20:12:32+02:00"
  ],
  "traces": [
    {
      "exceptionType": "java.lang.NullPointerException",
      "elements": [
        {
          "method": "java.lang.Throwable.\u003cinit\u003e",
          "source": "Throwable.java"
        },
        {
          "method": "java.lang.Throwable.\u003cinit\u003e",
          "source": "Throwable.java"
        },
        {
          "method": "java.lang.NullPointerException.\u003cinit\u003e",
          "source": "NullPointerException.java:63"
        },
        {
          "method": "org.eclipse.jdt.internal.ui.preferences.CompilerConfigurationBlock.updateEnableStates",
          "source": "CompilerConfigurationBlock.java:593"
        },
        {
          "method": "org.eclipse.jdt.internal.ui.preferences.CompilerConfigurationBlock.validateSettings",
          "source": "CompilerConfigurationBlock.java:576"
        },
        {
          "method": "org.eclipse.jdt.internal.ui.preferences.OptionsConfigurationBlock.controlChanged",
          "source": "OptionsConfigurationBlock.java:263"
        },
        {
          "method": "org.eclipse.jdt.internal.ui.preferences.OptionsConfigurationBlock$1.widgetSelected",
          "source": "OptionsConfigurationBlock.java:233"
        },
        {
          "method": "org.eclipse.swt.widgets.TypedListener.handleEvent",
          "source": "TypedListener.java"
        },
        {
          "method": "org.eclipse.swt.widgets.EventTable.sendEvent",
          "source": "EventTable.java"
        },
        {
          "method": "org.eclipse.swt.widgets.Widget.sendEvent",
          "source": "Widget.java"
        },
        {
          "method": "org.eclipse.swt.widgets.Widget.sendEvent",
          "source": "Widget.java"
        },
        {
          "method": "org.eclipse.swt.widgets.Widget.sendEvent",
          "source": "Widget.java"
        },
        {
          "method": "org.eclipse.swt.widgets.Combo.gtk_changed",
          "source": "Combo.java:745"
        },
        {
          "method": "org.eclipse.swt.widgets.Widget.windowProc",
          "source": "Widget.java:1174"
        },
        {
          "method": "org.eclipse.swt.widgets.Display.windowProc",
          "source": "Display.java"
        },
        {
          "method": "org.eclipse.swt.internal.gtk.OS.gtk_entry_set_text",
          "source": "Native Method"
        },
        {
          "method": "org.eclipse.swt.widgets.Combo.setText",
          "source": "Combo.java:1216"
        },
        {
          "method": "org.eclipse.swt.widgets.Combo.select",
          "source": "Combo.java:1050"
        },
        {
          "method": "org.eclipse.jdt.internal.ui.preferences.OptionsConfigurationBlock.addComboBox",
          "source": "OptionsConfigurationBlock.java:197"
        },
        {
          "method": "org.eclipse.jdt.internal.ui.preferences.CompilerConfigurationBlock.createUnusedCodeTabContent",
          "source": "CompilerConfigurationBlock.java:354"
        },
        {
          "method": "org.eclipse.jdt.internal.ui.preferences.CompilerConfigurationBlock.createContents",
          "source": "CompilerConfigurationBlock.java:183"
        },
        {
          "method": "org.eclipse.jdt.internal.ui.preferences.CompilerPreferencePage.createContents",
          "source": "CompilerPreferencePage.java:65"
        },
        {
          "method": "org.eclipse.jface.preference.PreferencePage.createControl",
          "source": "PreferencePage.java:217"
        },
        {
          "method": "org.eclipse.jdt.internal.ui.preferences.CompilerPreferencePage.createControl",
          "source": "CompilerPreferencePage.java:57"
        },
        {
          "method": "org.eclipse.jface.preference.PreferenceDialog$12.run",
          "source": "PreferenceDialog.java:986"
        },
        {
          "method": "org.eclipse.core.internal.runtime.InternalPlatform.run",
          "source": "InternalPlatform.java"
        },
        {
          "method": "org.eclipse.core.runtime.Platform.run",
          "source": "Platform.java"
        },
        {
          "method": "org.eclipse.jface.preference.PreferenceDialog.showPage",
          "source": "PreferenceDialog.java:984"
        },
        {
          "method": "org.eclipse.jface.preference.PreferenceDialog.selectSavedItem",
          "source": "PreferenceDialog.java:670"
        },
        {
          "method": "org.eclipse.jface.preference.PreferenceDialog$3.run",
          "source": "PreferenceDialog.java:297"
        },
        {
          "method": "org.eclipse.swt.custom.BusyIndicator.showWhile",
          "source": "BusyIndicator.java"
        },
        {
          "method": "org.eclipse.jface.preference.PreferenceDialog.createContents",
          "source": "PreferenceDialog.java:292"
        },
        {
          "method": "org.eclipse.jface.window.Window.create",
          "source": "Window.java:302"
        },
        {
          "method": "org.eclipse.jface.dialogs.Dialog.create",
          "source": "Dialog.java:876"
        },
        {
          "method": "org.eclipse.ui.internal.OpenPreferencesAction.run",
          "source": "OpenPreferencesAction.java:51"
        },
        {
          "method": "org.eclipse.jface.action.Action.runWithEvent",
          "source": "Action.java:842"
        },
        {
          "method": "org.eclipse.jface.action.ActionContributionItem.handleWidgetSelection",
          "source": "ActionContributionItem.java:529"
        },
        {
          "method": "org.eclipse.jface.action.ActionContributionItem.access$4",
          "source": "ActionContributionItem.java:482"
        },
        {
          "method": "org.eclipse.jface.action.ActionContributionItem$6.handleEvent",
          "source": "ActionContributionItem.java:454"
        },
        {
          "method": "org.eclipse.swt.widgets.EventTable.sendEvent",
          "source": "EventTable.java"
        },
        {
          "method": "org.eclipse.swt.widgets.Widget.sendEvent",
          "source": "Widget.java"
        },
        {
          "method": "org.eclipse.swt.widgets.Display.runDeferredEvents",
          "source": "Display.java"
        },
        {
          "method": "org.eclipse.swt.widgets.Display.readAndDispatch",
          "source": "Display.java"
        },
        {
          "method": "org.eclipse.ui.internal.Workbench.runEventLoop",
          "source": "Workbench.java:2036"
        },
        {
          "method": "org.eclipse.ui.internal.Workbench.run",
          "source": "Workbench.java:2019"
        },
        {
          "method": "org.eclipse.core.internal.boot.InternalBootLoader.run",
          "source": "InternalBootLoader.java:858"
        },
        {
          "method": "org.eclipse.core.boot.BootLoader.run",
          "source": "BootLoader.java:461"
        },
        {
          "method": "java.lang.reflect.AccessibleObject.invokeL",
          "source": "AccessibleObject.java:207"
        },
        {
          "method": "java.lang.reflect.Method.invoke",
          "source": "Method.java:271"
        },
        {
          "method": "org.eclipse.core.launcher.Main.basicRun",
          "source": "Main.java:295"
        },
        {
          "method": "org.eclipse.core.launcher.Main.run",
          "source": "Main.java:751"
        },
        {
          "method": "org.eclipse.core.launcher.Main.main",
          "source": "Main.java:587"
        }
      ],
      "number": 0,
      "commentIndex": 0,
      "bugId": "42266",
      "date": "2003-08-29T20:00:23+02:00",
      "product": "Platform",
      "component": "SWT",
      "severity": "normal"
    }
  ],
  "groupId": "42266",
  "bugId": "42266",
  "date": "2003-08-29T20:00:23+02:00",
  "product": "Platform",
  "component": "SWT",
  "severity": "normal"
}