{
  "comments": [
    "When target is 1.2, the debug evaluation tests fail with a VerifyError.\njava.lang.VerifyError: (class: CodeSnippet_3, method: run signature: ()V)\nIncompatible type for getting or setting field\n\tat java.lang.Class.forName0(Native Method)\n\tat java.lang.Class.forName(Class.java:140)\n\tat\norg.eclipse.jdt.core.tests.eval.target.CodeSnippetRunner.processClasses(CodeSnippetRunner.java:285)\n\tat\norg.eclipse.jdt.core.tests.eval.target.CodeSnippetRunner$3.run(CodeSnippetRunner.java:385)\n\nThis is due to the update of the declaring class. It doesn\u0027t check the\ndelegateThis is any and wrongly update the declaring class for field.",
    "Fixed and released.\n",
    "Verified."
  ],
  "commentCreationDates": [
    "2003-09-03T17:50:14+02:00",
    "2003-09-03T20:30:06+02:00",
    "2003-10-08T13:31:01+02:00"
  ],
  "traces": [
    {
      "exceptionType": "java.lang.VerifyError",
      "message": "(class: CodeSnippet_3, method: run signature: ()V) Incompatible type for getting or setting field",
      "elements": [
        {
          "method": "java.lang.Class.forName0",
          "source": "Native Method"
        },
        {
          "method": "java.lang.Class.forName",
          "source": "Class.java:140"
        },
        {
          "method": "org.eclipse.jdt.core.tests.eval.target.CodeSnippetRunner.processClasses",
          "source": "CodeSnippetRunner.java:285"
        },
        {
          "method": "org.eclipse.jdt.core.tests.eval.target.CodeSnippetRunner$3.run",
          "source": "CodeSnippetRunner.java:385"
        }
      ],
      "number": 0,
      "commentIndex": 0,
      "bugId": "42459",
      "date": "2003-09-03T17:50:14+02:00",
      "product": "JDT",
      "component": "Core",
      "severity": "normal"
    }
  ],
  "groupId": "42459",
  "bugId": "42459",
  "date": "2003-09-03T17:50:14+02:00",
  "product": "JDT",
  "component": "Core",
  "severity": "normal"
}