{
  "comments": [
    "---- Content of  uniqueId/Numbered.java ---\npackage uniqueId;\npublic interface Numbered {}\n\n---- Content of uniqueId/Bug.aj ----\npackage uniqueid;\n\npublic aspect Bug {\n    private long Numbered.objId;\n}\n\n[erik@oden test] ajc uniqueid/Numbered.java\n[erik@oden test] ajc uniqueid/Bug.aj \ncan\u0027t find type uniqueId.Numbered\njava.lang.NullPointerException\n        at org.aspectj.weaver.ResolvedTypeMunger.matches(ResolvedTypeMunger.\njava:53)\n        at org.aspectj.weaver.ConcreteTypeMunger.matches(ConcreteTypeMunger.\njava:52)\n        at org.aspectj.ajdt.internal.compiler.lookup.AjLookupEnvironment.\nweaveInterTypeDeclarations(AjLookupEnvironment.java:172)\n        at org.aspectj.ajdt.internal.compiler.lookup.AjLookupEnvironment.\nweaveInterTypeDeclarations(AjLookupEnvironment.java:150)\n        at org.aspectj.ajdt.internal.compiler.lookup.AjLookupEnvironment.\ndoPendingWeaves(AjLookupEnvironment.java:111)\n        at org.aspectj.ajdt.internal.compiler.lookup.AjLookupEnvironment.\ncompleteTypeBindings(AjLookupEnvironment.java:97)\n        at org.eclipse.jdt.internal.compiler.Compiler.beginToCompile(Compiler.\njava:310)\n        at org.eclipse.jdt.internal.compiler.Compiler.compile(Compiler.java:324)\n        at org.aspectj.ajdt.internal.core.builder.AjBuildManager.\nperformCompilation(AjBuildManager.java:372)\n        at org.aspectj.ajdt.internal.core.builder.AjBuildManager.\ndoBuild(AjBuildManager.java:133)\n        at org.aspectj.ajdt.internal.core.builder.AjBuildManager.\nbatchBuild(AjBuildManager.java:78)\n        at org.aspectj.ajdt.ajc.AjdtCommand.doCommand(AjdtCommand.java:106)\n        at org.aspectj.ajdt.ajc.AjdtCommand.runCommand(AjdtCommand.java:60)\n        at org.aspectj.tools.ajc.Main.run(Main.java:217)\n        at org.aspectj.tools.ajc.Main.runMain(Main.java:155)\n        at org.aspectj.tools.ajc.Main.main(Main.java:72)\n/export/home/erik/aspectT60/test/uniqueid/Bug.aj:0 Internal compiler error\njava.lang.NullPointerException\n        at org.aspectj.weaver.ResolvedTypeMunger.matches(ResolvedTypeMunger.\njava:53)\n        at org.aspectj.weaver.ConcreteTypeMunger.matches(ConcreteTypeMunger.\njava:52)\n        at org.aspectj.ajdt.internal.compiler.lookup.AjLookupEnvironment.\nweaveInterTypeDeclarations(AjLookupEnvironment.java:172)\n        at org.aspectj.ajdt.internal.compiler.lookup.AjLookupEnvironment.\nweaveInterTypeDeclarations(AjLookupEnvironment.java:150)\n        at org.aspectj.ajdt.internal.compiler.lookup.AjLookupEnvironment.\ndoPendingWeaves(AjLookupEnvironment.java:111)\n        at org.aspectj.ajdt.internal.compiler.lookup.AjLookupEnvironment.\ncompleteTypeBindings(AjLookupEnvironment.java:97)\n        at org.eclipse.jdt.internal.compiler.Compiler.beginToCompile(Compiler.\njava:310)\n        at org.eclipse.jdt.internal.compiler.Compiler.compile(Compiler.java:324)\n        at org.aspectj.ajdt.internal.core.builder.AjBuildManager.\nperformCompilation(AjBuildManager.java:372)\n        at org.aspectj.ajdt.internal.core.builder.AjBuildManager.\ndoBuild(AjBuildManager.java:133)\n        at org.aspectj.ajdt.internal.core.builder.AjBuildManager.\nbatchBuild(AjBuildManager.java:78)\n        at org.aspectj.ajdt.ajc.AjdtCommand.doCommand(AjdtCommand.java:106)\n        at org.aspectj.ajdt.ajc.AjdtCommand.runCommand(AjdtCommand.java:60)\n        at org.aspectj.tools.ajc.Main.run(Main.java:217)\n        at org.aspectj.tools.ajc.Main.runMain(Main.java:155)\n        at org.aspectj.tools.ajc.Main.main(Main.java:72)\n \n \n!! no source information available !!\nABORT\nException thrown from AspectJ 1.1.0\n \nThis might be logged as a bug already -- find current bugs at\n  http://bugs.eclipse.org/bugs/buglist.cgi?product\u003dAspectJ\u0026component\u003dCompiler\n \nBugs for exceptions thrown have titles File:line from the top stack, \ne.g., \"SomeFile.java:243\"\n \nIf you don\u0027t find the exception below in a bug, please add a new bug\nat http://bugs.eclipse.org/bugs/enter_bug.cgi?product\u003dAspectJ\nTo make the bug a priority, please include a test program\nthat can reproduce this exception.\nnull\njava.lang.NullPointerException\n        at org.aspectj.weaver.ResolvedTypeMunger.matches(ResolvedTypeMunger.\njava:53)\n        at org.aspectj.weaver.ConcreteTypeMunger.matches(ConcreteTypeMunger.\njava:52)\n        at org.aspectj.ajdt.internal.compiler.lookup.AjLookupEnvironment.\nweaveInterTypeDeclarations(AjLookupEnvironment.java:172)\n        at org.aspectj.ajdt.internal.compiler.lookup.AjLookupEnvironment.\nweaveInterTypeDeclarations(AjLookupEnvironment.java:150)\n        at org.aspectj.ajdt.internal.compiler.lookup.AjLookupEnvironment.\ndoPendingWeaves(AjLookupEnvironment.java:111)\n        at org.aspectj.ajdt.internal.compiler.lookup.AjLookupEnvironment.\ncompleteTypeBindings(AjLookupEnvironment.java:97)\n        at org.eclipse.jdt.internal.compiler.Compiler.beginToCompile(Compiler.\njava:310)\n        at org.eclipse.jdt.internal.compiler.Compiler.compile(Compiler.java:324)\n        at org.aspectj.ajdt.internal.core.builder.AjBuildManager.\nperformCompilation(AjBuildManager.java:372)\n        at org.aspectj.ajdt.internal.core.builder.AjBuildManager.\ndoBuild(AjBuildManager.java:133)\n        at org.aspectj.ajdt.internal.core.builder.AjBuildManager.\nbatchBuild(AjBuildManager.java:78)\n        at org.aspectj.ajdt.ajc.AjdtCommand.doCommand(AjdtCommand.java:106)\n        at org.aspectj.ajdt.ajc.AjdtCommand.runCommand(AjdtCommand.java:60)\n        at org.aspectj.tools.ajc.Main.run(Main.java:217)\n        at org.aspectj.tools.ajc.Main.runMain(Main.java:155)\n        at org.aspectj.tools.ajc.Main.main(Main.java:72)\n \n \n1 fail|abort, 2 errors\n[erik@oden test]",
    "I am able to reproduce this on windows xp, although with slightly different\nerrors.  The os is probably relevant because the bug has to do with case\nsensitivity in file and package names.\n\nThere is a bug in your program.  The cases of the directories and package names\ndon\u0027t match between these files.  You appear to be using both \u0027uniqueid\u0027 and\n\u0027uniqueId\u0027 inconsistently.  ajc should handle this much more gracefully and I\u0027m\nleaving this open as a P3 bug because we need to improve this hideous error\nmessage.  You should just get a simple error that the type \"uniqueId.Numbered\"\ncan\u0027t be found\" when compiling Bug.aj which is in the \"uniqueid\" package.\n\nIf you fix the cases in your own code and directories then the bug should no\nlonger trouble you.\n",
    "I tested this against the current tree. I believe the problem has been fixed by \nthe improved error reporting we inherited from the switch to the latest jdt.\ncore.\n\nInstead of the failure in the bug report, ajc will now report:\nuniqueId\\Bug.aj:4:0 Numbered cannot be resolved or is not a type\n\nThis is the correct message since ajc allows source files to be placed in \npackages that do not match directory names. As uniqueid.Bug is in a different \npackage to uniqueId.Numbered, and Numbered is not imported, the Numbered type \ncannot be resolved.\n\nTest case added to ajcTests.xml"
  ],
  "commentCreationDates": [
    "2003-09-04T13:12:20+02:00",
    "2003-09-04T21:01:44+02:00",
    "2004-01-15T12:57:04+01:00"
  ],
  "traces": [
    {
      "exceptionType": "java.lang.NullPointerException",
      "elements": [
        {
          "method": "org.aspectj.weaver.ResolvedTypeMunger.matches",
          "source": "ResolvedTypeMunger. java:53"
        },
        {
          "method": "org.aspectj.weaver.ConcreteTypeMunger.matches",
          "source": "ConcreteTypeMunger. java:52"
        },
        {
          "method": "org.aspectj.ajdt.internal.compiler.lookup.AjLookupEnvironment.weaveInterTypeDeclarations",
          "source": "AjLookupEnvironment.java:172"
        },
        {
          "method": "org.aspectj.ajdt.internal.compiler.lookup.AjLookupEnvironment.weaveInterTypeDeclarations",
          "source": "AjLookupEnvironment.java:150"
        },
        {
          "method": "org.aspectj.ajdt.internal.compiler.lookup.AjLookupEnvironment.doPendingWeaves",
          "source": "AjLookupEnvironment.java:111"
        },
        {
          "method": "org.aspectj.ajdt.internal.compiler.lookup.AjLookupEnvironment.completeTypeBindings",
          "source": "AjLookupEnvironment.java:97"
        },
        {
          "method": "org.eclipse.jdt.internal.compiler.Compiler.beginToCompile",
          "source": "Compiler. java:310"
        },
        {
          "method": "org.eclipse.jdt.internal.compiler.Compiler.compile",
          "source": "Compiler.java:324"
        },
        {
          "method": "org.aspectj.ajdt.internal.core.builder.AjBuildManager.performCompilation",
          "source": "AjBuildManager.java:372"
        },
        {
          "method": "org.aspectj.ajdt.internal.core.builder.AjBuildManager.doBuild",
          "source": "AjBuildManager.java:133"
        },
        {
          "method": "org.aspectj.ajdt.internal.core.builder.AjBuildManager.batchBuild",
          "source": "AjBuildManager.java:78"
        },
        {
          "method": "org.aspectj.ajdt.ajc.AjdtCommand.doCommand",
          "source": "AjdtCommand.java:106"
        },
        {
          "method": "org.aspectj.ajdt.ajc.AjdtCommand.runCommand",
          "source": "AjdtCommand.java:60"
        },
        {
          "method": "org.aspectj.tools.ajc.Main.run",
          "source": "Main.java:217"
        },
        {
          "method": "org.aspectj.tools.ajc.Main.runMain",
          "source": "Main.java:155"
        },
        {
          "method": "org.aspectj.tools.ajc.Main.main",
          "source": "Main.java:72"
        }
      ],
      "number": 0,
      "commentIndex": 0,
      "bugId": "42515",
      "date": "2003-09-04T13:12:20+02:00",
      "product": "AspectJ",
      "component": "Compiler",
      "severity": "normal"
    },
    {
      "exceptionType": "java.lang.NullPointerException",
      "elements": [
        {
          "method": "org.aspectj.weaver.ResolvedTypeMunger.matches",
          "source": "ResolvedTypeMunger. java:53"
        },
        {
          "method": "org.aspectj.weaver.ConcreteTypeMunger.matches",
          "source": "ConcreteTypeMunger. java:52"
        },
        {
          "method": "org.aspectj.ajdt.internal.compiler.lookup.AjLookupEnvironment.weaveInterTypeDeclarations",
          "source": "AjLookupEnvironment.java:172"
        },
        {
          "method": "org.aspectj.ajdt.internal.compiler.lookup.AjLookupEnvironment.weaveInterTypeDeclarations",
          "source": "AjLookupEnvironment.java:150"
        },
        {
          "method": "org.aspectj.ajdt.internal.compiler.lookup.AjLookupEnvironment.doPendingWeaves",
          "source": "AjLookupEnvironment.java:111"
        },
        {
          "method": "org.aspectj.ajdt.internal.compiler.lookup.AjLookupEnvironment.completeTypeBindings",
          "source": "AjLookupEnvironment.java:97"
        },
        {
          "method": "org.eclipse.jdt.internal.compiler.Compiler.beginToCompile",
          "source": "Compiler. java:310"
        },
        {
          "method": "org.eclipse.jdt.internal.compiler.Compiler.compile",
          "source": "Compiler.java:324"
        },
        {
          "method": "org.aspectj.ajdt.internal.core.builder.AjBuildManager.performCompilation",
          "source": "AjBuildManager.java:372"
        },
        {
          "method": "org.aspectj.ajdt.internal.core.builder.AjBuildManager.doBuild",
          "source": "AjBuildManager.java:133"
        },
        {
          "method": "org.aspectj.ajdt.internal.core.builder.AjBuildManager.batchBuild",
          "source": "AjBuildManager.java:78"
        },
        {
          "method": "org.aspectj.ajdt.ajc.AjdtCommand.doCommand",
          "source": "AjdtCommand.java:106"
        },
        {
          "method": "org.aspectj.ajdt.ajc.AjdtCommand.runCommand",
          "source": "AjdtCommand.java:60"
        },
        {
          "method": "org.aspectj.tools.ajc.Main.run",
          "source": "Main.java:217"
        },
        {
          "method": "org.aspectj.tools.ajc.Main.runMain",
          "source": "Main.java:155"
        },
        {
          "method": "org.aspectj.tools.ajc.Main.main",
          "source": "Main.java:72"
        }
      ],
      "number": 1,
      "commentIndex": 0,
      "bugId": "42515",
      "date": "2003-09-04T13:12:20+02:00",
      "product": "AspectJ",
      "component": "Compiler",
      "severity": "normal"
    },
    {
      "exceptionType": "java.lang.NullPointerException",
      "elements": [
        {
          "method": "org.aspectj.weaver.ResolvedTypeMunger.matches",
          "source": "ResolvedTypeMunger. java:53"
        },
        {
          "method": "org.aspectj.weaver.ConcreteTypeMunger.matches",
          "source": "ConcreteTypeMunger. java:52"
        },
        {
          "method": "org.aspectj.ajdt.internal.compiler.lookup.AjLookupEnvironment.weaveInterTypeDeclarations",
          "source": "AjLookupEnvironment.java:172"
        },
        {
          "method": "org.aspectj.ajdt.internal.compiler.lookup.AjLookupEnvironment.weaveInterTypeDeclarations",
          "source": "AjLookupEnvironment.java:150"
        },
        {
          "method": "org.aspectj.ajdt.internal.compiler.lookup.AjLookupEnvironment.doPendingWeaves",
          "source": "AjLookupEnvironment.java:111"
        },
        {
          "method": "org.aspectj.ajdt.internal.compiler.lookup.AjLookupEnvironment.completeTypeBindings",
          "source": "AjLookupEnvironment.java:97"
        },
        {
          "method": "org.eclipse.jdt.internal.compiler.Compiler.beginToCompile",
          "source": "Compiler. java:310"
        },
        {
          "method": "org.eclipse.jdt.internal.compiler.Compiler.compile",
          "source": "Compiler.java:324"
        },
        {
          "method": "org.aspectj.ajdt.internal.core.builder.AjBuildManager.performCompilation",
          "source": "AjBuildManager.java:372"
        },
        {
          "method": "org.aspectj.ajdt.internal.core.builder.AjBuildManager.doBuild",
          "source": "AjBuildManager.java:133"
        },
        {
          "method": "org.aspectj.ajdt.internal.core.builder.AjBuildManager.batchBuild",
          "source": "AjBuildManager.java:78"
        },
        {
          "method": "org.aspectj.ajdt.ajc.AjdtCommand.doCommand",
          "source": "AjdtCommand.java:106"
        },
        {
          "method": "org.aspectj.ajdt.ajc.AjdtCommand.runCommand",
          "source": "AjdtCommand.java:60"
        },
        {
          "method": "org.aspectj.tools.ajc.Main.run",
          "source": "Main.java:217"
        },
        {
          "method": "org.aspectj.tools.ajc.Main.runMain",
          "source": "Main.java:155"
        },
        {
          "method": "org.aspectj.tools.ajc.Main.main",
          "source": "Main.java:72"
        }
      ],
      "number": 2,
      "commentIndex": 0,
      "bugId": "42515",
      "date": "2003-09-04T13:12:20+02:00",
      "product": "AspectJ",
      "component": "Compiler",
      "severity": "normal"
    }
  ],
  "groupId": "42515",
  "bugId": "42515",
  "date": "2003-09-04T13:12:20+02:00",
  "product": "AspectJ",
  "component": "Compiler",
  "severity": "normal"
}