{
  "comments": [
    "After ending a debug session of a simple HelloWorld on Solaris,\nthe following error appears in the .metadata/.log file.\n(Nothing otherwise appears to be wrong; I was looking for something else.)\nOn JDK 1.3.1, I get both messages below.\nOn JDK 1.4.1, I only get the second message.\nThe messages occurred even if the HelloWorld application did not actually\nread from nor write to the console.\n\n\n!ENTRY org.eclipse.debug.core 4 120 Sep 04, 2003 17:01:26.731\n!MESSAGE Error logged from Debug Core: \n!STACK 0\njava.io.IOException: read error\n        at org.eclipse.cdt.utils.pty.PTYInputStream.read0(Native Method)\n        at org.eclipse.cdt.utils.pty.PTYInputStream.read(PTYInputStream.java:49)\n        at java.io.InputStream.read(InputStream.java:86)\n        at org.eclipse.debug.internal.core.OutputStreamMonitor.read\n(OutputStreamMonitor.java:132)\n        at org.eclipse.debug.internal.core.OutputStreamMonitor.access$1\n(OutputStreamMonitor.java:124)\n        at org.eclipse.debug.internal.core.OutputStreamMonitor$1.run\n(OutputStreamMonitor.java:177)\n        at java.lang.Thread.run(Thread.java:479)\n!ENTRY org.eclipse.debug.core 4 120 Sep 04, 2003 17:01:26.776\n!MESSAGE Error logged from Debug Core: \n!STACK 0\njava.io.IOException: close error\n        at org.eclipse.cdt.utils.pty.PTYOutputStream.close\n(PTYOutputStream.java:62)\n        at org.eclipse.debug.internal.core.InputStreamMonitor.write\n(InputStreamMonitor.java:102)\n        at org.eclipse.debug.internal.core.InputStreamMonitor$1.run\n(InputStreamMonitor.java:75)\n        at java.lang.Thread.run(Thread.java:479)",
    "Alain, can you look at this.",
    "They are actually harmeless.\n\nIt is because the PTYStream is close by the debugger\n__and__ also close multiple times by the eclipse framework.\nUnfortunately they log the exception.\n\nI will look for a solution.\n\nThanks for the reminder",
    "Should be fix in the head.\n\nThanks for the PR.",
    "Reopening.  Still seeing the following in 1.2.0.44:\n\n!ENTRY org.eclipse.debug.core 4 120 Sep 15, 2003 18:13:39.979\n!MESSAGE Error logged from Debug Core: \n!STACK 0\njava.io.IOException: read error\n        at org.eclipse.cdt.utils.pty.PTYInputStream.read0(Native Method)\n        at org.eclipse.cdt.utils.pty.PTYInputStream.read(PTYInputStream.java:52)\n        at java.io.InputStream.read(InputStream.java:86)\n        at org.eclipse.debug.internal.core.OutputStreamMonitor.read\n(OutputStreamMonitor.java:132)\n        at org.eclipse.debug.internal.core.OutputStreamMonitor.access$1\n(OutputStreamMonitor.java:124)\n        at org.eclipse.debug.internal.core.OutputStreamMonitor$1.run\n(OutputStreamMonitor.java:177)\n        at java.lang.Thread.run(Thread.java:479)\n\n\nTest HelloWorld uses cout, cerr, but not cin.\n",
    "\u003e Reopening.  Still seeing the following in 1.2.0.44:\n\nBrent are you sure about this ?\nCheck the time log entry, maybe it was not for the session.\n\nDoe this still happen ?\nAlthough harmless, I would like to resolve this asap.\n",
    "No longer reproduces with CDT 1.2.1 (build 20040302),\nor with CDT 2.0.0.200403170301.\n"
  ],
  "commentCreationDates": [
    "2003-09-04T23:27:47+02:00",
    "2003-09-04T23:35:29+02:00",
    "2003-09-05T16:19:37+02:00",
    "2003-09-05T18:28:30+02:00",
    "2003-09-16T00:18:49+02:00",
    "2003-10-28T15:41:15+01:00",
    "2004-05-12T17:00:01+02:00"
  ],
  "traces": [
    {
      "exceptionType": "java.io.IOException",
      "message": "read error",
      "elements": [
        {
          "method": "org.eclipse.cdt.utils.pty.PTYInputStream.read0",
          "source": "Native Method"
        },
        {
          "method": "org.eclipse.cdt.utils.pty.PTYInputStream.read",
          "source": "PTYInputStream.java:49"
        },
        {
          "method": "java.io.InputStream.read",
          "source": "InputStream.java:86"
        },
        {
          "method": "org.eclipse.debug.internal.core.OutputStreamMonitor.read",
          "source": "OutputStreamMonitor.java:132"
        },
        {
          "method": "org.eclipse.debug.internal.core.OutputStreamMonitor.access$1",
          "source": "OutputStreamMonitor.java:124"
        },
        {
          "method": "org.eclipse.debug.internal.core.OutputStreamMonitor$1.run",
          "source": "OutputStreamMonitor.java:177"
        },
        {
          "method": "java.lang.Thread.run",
          "source": "Thread.java:479"
        }
      ],
      "number": 0,
      "commentIndex": 0,
      "bugId": "42571",
      "date": "2003-09-04T23:27:47+02:00",
      "product": "CDT",
      "component": "cdt-debug",
      "severity": "normal"
    },
    {
      "exceptionType": "java.io.IOException",
      "message": "close error",
      "elements": [
        {
          "method": "org.eclipse.cdt.utils.pty.PTYOutputStream.close",
          "source": "PTYOutputStream.java:62"
        },
        {
          "method": "org.eclipse.debug.internal.core.InputStreamMonitor.write",
          "source": "InputStreamMonitor.java:102"
        },
        {
          "method": "org.eclipse.debug.internal.core.InputStreamMonitor$1.run",
          "source": "InputStreamMonitor.java:75"
        },
        {
          "method": "java.lang.Thread.run",
          "source": "Thread.java:479"
        }
      ],
      "number": 1,
      "commentIndex": 0,
      "bugId": "42571",
      "date": "2003-09-04T23:27:47+02:00",
      "product": "CDT",
      "component": "cdt-debug",
      "severity": "normal"
    },
    {
      "exceptionType": "java.io.IOException",
      "message": "read error",
      "elements": [
        {
          "method": "org.eclipse.cdt.utils.pty.PTYInputStream.read0",
          "source": "Native Method"
        },
        {
          "method": "org.eclipse.cdt.utils.pty.PTYInputStream.read",
          "source": "PTYInputStream.java:52"
        },
        {
          "method": "java.io.InputStream.read",
          "source": "InputStream.java:86"
        },
        {
          "method": "org.eclipse.debug.internal.core.OutputStreamMonitor.read",
          "source": "OutputStreamMonitor.java:132"
        },
        {
          "method": "org.eclipse.debug.internal.core.OutputStreamMonitor.access$1",
          "source": "OutputStreamMonitor.java:124"
        },
        {
          "method": "org.eclipse.debug.internal.core.OutputStreamMonitor$1.run",
          "source": "OutputStreamMonitor.java:177"
        },
        {
          "method": "java.lang.Thread.run",
          "source": "Thread.java:479"
        }
      ],
      "number": 2,
      "commentIndex": 4,
      "bugId": "42571",
      "date": "2003-09-16T00:18:49+02:00",
      "product": "CDT",
      "component": "cdt-debug",
      "severity": "normal"
    }
  ],
  "groupId": "42571",
  "bugId": "42571",
  "date": "2003-09-04T23:27:47+02:00",
  "product": "CDT",
  "component": "cdt-debug",
  "severity": "normal"
}