{
  "comments": [
    "OSX 10.2.6\nEclipse 200308281813\n\nThis error occurs fairly often for me - I cannot determine anything consistent about when it happens \nunfortunately.\n\n!ENTRY org.eclipse.ui 4 0 Sep 08, 2003 17:22:26.800\n!MESSAGE Assertion failed: \n!STACK 0\norg.eclipse.jface.text.Assert$AssertionFailedException: Assertion failed: \n        at org.eclipse.jface.text.Assert.isTrue(Assert.java:175)\n        at org.eclipse.jface.text.Assert.isTrue(Assert.java:160)\n        at \norg.eclipse.jdt.internal.ui.text.link.LinkedPositionManager.getPositions(LinkedPositionManager.java:426)\n        at \norg.eclipse.jdt.internal.ui.text.link.LinkedPositionManager.uninstall(LinkedPositionManager.java:295)\n        at org.eclipse.jdt.internal.ui.text.link.LinkedPositionUI.leave(LinkedPositionUI.java:327)\n        at org.eclipse.jdt.internal.ui.text.link.LinkedPositionUI.shellDeactivated(LinkedPositionUI.java:818)\n        at org.eclipse.swt.widgets.TypedListener.handleEvent(TypedListener.java:163)\n        at org.eclipse.swt.widgets.EventTable.sendEvent(EventTable.java:82)\n        at org.eclipse.swt.widgets.Widget.notifyListeners(Widget.java:1027)\n        at org.eclipse.swt.widgets.Display.runDeferredEvents(Display.java:2180)\n        at org.eclipse.swt.widgets.Display.readAndDispatch(Display.java:1878)\n        at org.eclipse.jface.operation.ModalContext$ModalContextThread.block(ModalContext.java:136)\n        at org.eclipse.jface.operation.ModalContext.run(ModalContext.java:261)\n        at org.eclipse.jface.dialogs.ProgressMonitorDialog.run(ProgressMonitorDialog.java:357)\n        at org.eclipse.team.internal.ui.sync.SyncView.run(SyncView.java:270)\n        at org.eclipse.team.internal.ui.sync.SyncView.showSync(SyncView.java:389)\n        at org.eclipse.team.internal.ccvs.ui.actions.SyncAction.executeInOldSyncView(SyncAction.java:64)\n        at org.eclipse.team.internal.ccvs.ui.actions.SyncAction.execute(SyncAction.java:52)\n        at org.eclipse.team.internal.ccvs.ui.actions.CVSAction.run(CVSAction.java:68)\n        at org.eclipse.ui.actions.ActionDelegate.runWithEvent(ActionDelegate.java:71)\n        at org.eclipse.ui.internal.PluginAction.runWithEvent(PluginAction.java:253)\n        at \norg.eclipse.jface.action.ActionContributionItem.handleWidgetSelection(ActionContributionItem.java:529)\n        at org.eclipse.jface.action.ActionContributionItem.access$4(ActionContributionItem.java:482)\n        at org.eclipse.jface.action.ActionContributionItem$6.handleEvent(ActionContributionItem.java:454)\n        at org.eclipse.swt.widgets.EventTable.sendEvent(EventTable.java:82)\n        at org.eclipse.swt.widgets.Widget.notifyListeners(Widget.java:1027)\n        at org.eclipse.swt.widgets.Display.runDeferredEvents(Display.java:2180)\n        at org.eclipse.swt.widgets.Display.readAndDispatch(Display.java:1878)\n        at org.eclipse.ui.internal.Workbench.runEventLoop(Workbench.java:2036)\n        at org.eclipse.ui.internal.Workbench.run(Workbench.java:2019)\n        at org.eclipse.core.internal.boot.InternalBootLoader.run(InternalBootLoader.java:858)\n        at org.eclipse.core.boot.BootLoader.run(BootLoader.java:461)\n        at sun.reflect.NativeMethodAccessorImpl.invoke0(Native Method)\n        at sun.reflect.NativeMethodAccessorImpl.invoke(NativeMethodAccessorImpl.java:39)\n        at sun.reflect.DelegatingMethodAccessorImpl.invoke(DelegatingMethodAccessorImpl.java:25)\n        at java.lang.reflect.Method.invoke(Method.java:324)\n        at org.eclipse.core.launcher.Main.basicRun(Main.java:295)\n        at org.eclipse.core.launcher.Main.run(Main.java:751)\n        at org.eclipse.core.launcher.Main.main(Main.java:587)",
    "this should be covered by a recent fix \u003e 20030909. Closing, please reopen if you\ncan still see this in newer builds.",
    "OK, thanks."
  ],
  "commentCreationDates": [
    "2003-09-08T21:48:08+02:00",
    "2003-09-10T08:46:31+02:00",
    "2003-09-10T10:32:11+02:00"
  ],
  "traces": [
    {
      "exceptionType": "org.eclipse.jface.text.Assert$AssertionFailedException",
      "message": "Assertion failed:",
      "elements": [
        {
          "method": "org.eclipse.jface.text.Assert.isTrue",
          "source": "Assert.java:175"
        },
        {
          "method": "org.eclipse.jface.text.Assert.isTrue",
          "source": "Assert.java:160"
        },
        {
          "method": "org.eclipse.jdt.internal.ui.text.link.LinkedPositionManager.getPositions",
          "source": "LinkedPositionManager.java:426"
        },
        {
          "method": "org.eclipse.jdt.internal.ui.text.link.LinkedPositionManager.uninstall",
          "source": "LinkedPositionManager.java:295"
        },
        {
          "method": "org.eclipse.jdt.internal.ui.text.link.LinkedPositionUI.leave",
          "source": "LinkedPositionUI.java:327"
        },
        {
          "method": "org.eclipse.jdt.internal.ui.text.link.LinkedPositionUI.shellDeactivated",
          "source": "LinkedPositionUI.java:818"
        },
        {
          "method": "org.eclipse.swt.widgets.TypedListener.handleEvent",
          "source": "TypedListener.java:163"
        },
        {
          "method": "org.eclipse.swt.widgets.EventTable.sendEvent",
          "source": "EventTable.java:82"
        },
        {
          "method": "org.eclipse.swt.widgets.Widget.notifyListeners",
          "source": "Widget.java:1027"
        },
        {
          "method": "org.eclipse.swt.widgets.Display.runDeferredEvents",
          "source": "Display.java:2180"
        },
        {
          "method": "org.eclipse.swt.widgets.Display.readAndDispatch",
          "source": "Display.java:1878"
        },
        {
          "method": "org.eclipse.jface.operation.ModalContext$ModalContextThread.block",
          "source": "ModalContext.java:136"
        },
        {
          "method": "org.eclipse.jface.operation.ModalContext.run",
          "source": "ModalContext.java:261"
        },
        {
          "method": "org.eclipse.jface.dialogs.ProgressMonitorDialog.run",
          "source": "ProgressMonitorDialog.java:357"
        },
        {
          "method": "org.eclipse.team.internal.ui.sync.SyncView.run",
          "source": "SyncView.java:270"
        },
        {
          "method": "org.eclipse.team.internal.ui.sync.SyncView.showSync",
          "source": "SyncView.java:389"
        },
        {
          "method": "org.eclipse.team.internal.ccvs.ui.actions.SyncAction.executeInOldSyncView",
          "source": "SyncAction.java:64"
        },
        {
          "method": "org.eclipse.team.internal.ccvs.ui.actions.SyncAction.execute",
          "source": "SyncAction.java:52"
        },
        {
          "method": "org.eclipse.team.internal.ccvs.ui.actions.CVSAction.run",
          "source": "CVSAction.java:68"
        },
        {
          "method": "org.eclipse.ui.actions.ActionDelegate.runWithEvent",
          "source": "ActionDelegate.java:71"
        },
        {
          "method": "org.eclipse.ui.internal.PluginAction.runWithEvent",
          "source": "PluginAction.java:253"
        },
        {
          "method": "org.eclipse.jface.action.ActionContributionItem.handleWidgetSelection",
          "source": "ActionContributionItem.java:529"
        },
        {
          "method": "org.eclipse.jface.action.ActionContributionItem.access$4",
          "source": "ActionContributionItem.java:482"
        },
        {
          "method": "org.eclipse.jface.action.ActionContributionItem$6.handleEvent",
          "source": "ActionContributionItem.java:454"
        },
        {
          "method": "org.eclipse.swt.widgets.EventTable.sendEvent",
          "source": "EventTable.java:82"
        },
        {
          "method": "org.eclipse.swt.widgets.Widget.notifyListeners",
          "source": "Widget.java:1027"
        },
        {
          "method": "org.eclipse.swt.widgets.Display.runDeferredEvents",
          "source": "Display.java:2180"
        },
        {
          "method": "org.eclipse.swt.widgets.Display.readAndDispatch",
          "source": "Display.java:1878"
        },
        {
          "method": "org.eclipse.ui.internal.Workbench.runEventLoop",
          "source": "Workbench.java:2036"
        },
        {
          "method": "org.eclipse.ui.internal.Workbench.run",
          "source": "Workbench.java:2019"
        },
        {
          "method": "org.eclipse.core.internal.boot.InternalBootLoader.run",
          "source": "InternalBootLoader.java:858"
        },
        {
          "method": "org.eclipse.core.boot.BootLoader.run",
          "source": "BootLoader.java:461"
        },
        {
          "method": "sun.reflect.NativeMethodAccessorImpl.invoke0",
          "source": "Native Method"
        },
        {
          "method": "sun.reflect.NativeMethodAccessorImpl.invoke",
          "source": "NativeMethodAccessorImpl.java:39"
        },
        {
          "method": "sun.reflect.DelegatingMethodAccessorImpl.invoke",
          "source": "DelegatingMethodAccessorImpl.java:25"
        },
        {
          "method": "java.lang.reflect.Method.invoke",
          "source": "Method.java:324"
        },
        {
          "method": "org.eclipse.core.launcher.Main.basicRun",
          "source": "Main.java:295"
        },
        {
          "method": "org.eclipse.core.launcher.Main.run",
          "source": "Main.java:751"
        },
        {
          "method": "org.eclipse.core.launcher.Main.main",
          "source": "Main.java:587"
        }
      ],
      "number": 0,
      "commentIndex": 0,
      "bugId": "42722",
      "date": "2003-09-08T21:48:08+02:00",
      "product": "JDT",
      "component": "Text",
      "severity": "normal"
    }
  ],
  "groupId": "42722",
  "bugId": "42722",
  "date": "2003-09-08T21:48:08+02:00",
  "product": "JDT",
  "component": "Text",
  "severity": "normal"
}