{
  "comments": [
    "The compiler crashed on a simple test case; I will send this in a separate \nemail. This crash still occurs in the version from CVS head as of 9/8/03. I \nbelieve the first error message is also a compiler bug - it should be possible \nto use declare soft on a non-concrete pointcut.\n\nC:\\eclipse\\workspace\\atrack\u003eajc @narrow.lst\nC:\\eclipse\\workspace\\atrack\\src\\org\\atrack\\policy\\ExceptionHandling.java:25 \nexac\nt type pattern required\njava.lang.NullPointerException\n        at org.aspectj.weaver.patterns.ReferencePointcut.concretize1\n(ReferencePo\nintcut.java:243)\n        at org.aspectj.weaver.patterns.AndPointcut.concretize1\n(AndPointcut.java:\n88)\n        at org.aspectj.weaver.patterns.ReferencePointcut.concretize1\n(ReferencePo\nintcut.java:272)\n        at org.aspectj.weaver.patterns.Pointcut.concretize(Pointcut.java:127)\n        at org.aspectj.weaver.patterns.Pointcut.concretize(Pointcut.java:110)\n        at org.aspectj.weaver.CrosscuttingMembers.addDeclare\n(CrosscuttingMembers\n.java:111)\n        at org.aspectj.weaver.CrosscuttingMembers.addDeclares\n(CrosscuttingMember\ns.java:92)\n        at org.aspectj.weaver.ResolvedTypeX.collectCrosscuttingMembers\n(ResolvedT\nypeX.java:332)\n        at org.aspectj.weaver.CrosscuttingMembersSet.addOrReplaceAspect\n(Crosscut\ntingMembersSet.java:50)\n        at \norg.aspectj.ajdt.internal.compiler.ast.AspectDeclaration.buildInterTy\npeAndPerClause(AspectDeclaration.java:754)\n        at \norg.aspectj.ajdt.internal.compiler.lookup.AjLookupEnvironment.buildIn\nterTypeAndPerClause(AjLookupEnvironment.java:124)\n        at \norg.aspectj.ajdt.internal.compiler.lookup.AjLookupEnvironment.complet\neTypeBindings(AjLookupEnvironment.java:91)\n        at org.eclipse.jdt.internal.compiler.Compiler.beginToCompile\n(Compiler.ja\nva:310)\n        at org.eclipse.jdt.internal.compiler.Compiler.compile\n(Compiler.java:324)\n\n        at \norg.aspectj.ajdt.internal.core.builder.AjBuildManager.performCompilat\nion(AjBuildManager.java:373)\n        at org.aspectj.ajdt.internal.core.builder.AjBuildManager.doBuild\n(AjBuild\nManager.java:125)\n        at org.aspectj.ajdt.internal.core.builder.AjBuildManager.batchBuild\n(AjBu\nildManager.java:70)\n        at org.aspectj.ajdt.ajc.AjdtCommand.doCommand(AjdtCommand.java:99)\n        at org.aspectj.ajdt.ajc.AjdtCommand.runCommand(AjdtCommand.java:53)\n        at org.aspectj.tools.ajc.Main.run(Main.java:217)\n        at org.aspectj.tools.ajc.Main.runMain(Main.java:155)\n        at org.aspectj.tools.ajc.Main.main(Main.java:72)\nC:\\eclipse\\workspace\\atrack\\src\\org\\atrack\\policy\\ExceptionHandling.java:0 \nInter\nnal compiler error\njava.lang.NullPointerException\n        at org.aspectj.weaver.patterns.ReferencePointcut.concretize1\n(ReferencePo\nintcut.java:243)\n        at org.aspectj.weaver.patterns.AndPointcut.concretize1\n(AndPointcut.java:\n88)\n        at org.aspectj.weaver.patterns.ReferencePointcut.concretize1\n(ReferencePo\nintcut.java:272)\n        at org.aspectj.weaver.patterns.Pointcut.concretize(Pointcut.java:127)\n        at org.aspectj.weaver.patterns.Pointcut.concretize(Pointcut.java:110)\n        at org.aspectj.weaver.CrosscuttingMembers.addDeclare\n(CrosscuttingMembers\n.java:111)\n        at org.aspectj.weaver.CrosscuttingMembers.addDeclares\n(CrosscuttingMember\ns.java:92)\n        at org.aspectj.weaver.ResolvedTypeX.collectCrosscuttingMembers\n(ResolvedT\nypeX.java:332)\n        at org.aspectj.weaver.CrosscuttingMembersSet.addOrReplaceAspect\n(Crosscut\ntingMembersSet.java:50)\n        at \norg.aspectj.ajdt.internal.compiler.ast.AspectDeclaration.buildInterTy\npeAndPerClause(AspectDeclaration.java:754)\n        at \norg.aspectj.ajdt.internal.compiler.lookup.AjLookupEnvironment.buildIn\nterTypeAndPerClause(AjLookupEnvironment.java:124)\n        at \norg.aspectj.ajdt.internal.compiler.lookup.AjLookupEnvironment.complet\neTypeBindings(AjLookupEnvironment.java:91)\n        at org.eclipse.jdt.internal.compiler.Compiler.beginToCompile\n(Compiler.ja\nva:310)\n        at org.eclipse.jdt.internal.compiler.Compiler.compile\n(Compiler.java:324)\n\n        at \norg.aspectj.ajdt.internal.core.builder.AjBuildManager.performCompilat\nion(AjBuildManager.java:373)\n        at org.aspectj.ajdt.internal.core.builder.AjBuildManager.doBuild\n(AjBuild\nManager.java:125)\n        at org.aspectj.ajdt.internal.core.builder.AjBuildManager.batchBuild\n(AjBu\nildManager.java:70)\n        at org.aspectj.ajdt.ajc.AjdtCommand.doCommand(AjdtCommand.java:99)\n        at org.aspectj.ajdt.ajc.AjdtCommand.runCommand(AjdtCommand.java:53)\n        at org.aspectj.tools.ajc.Main.run(Main.java:217)\n        at org.aspectj.tools.ajc.Main.runMain(Main.java:155)\n        at org.aspectj.tools.ajc.Main.main(Main.java:72)\n\n\n!! no source information available !!\nC:\\eclipse\\workspace\\atrack\\src\\org\\atrack\\policy\\ExceptionHandling.java:18 The\ntype ExceptionHandling is already defined\npublic abstract aspect ExceptionHandling {\n                       ^^^^^^^^^^^^^^^^^\nABORT\nException thrown from AspectJ DEVELOPMENT\n\nThis might be logged as a bug already -- find current bugs at\n  http://bugs.eclipse.org/bugs/buglist.cgi?product\u003dAspectJ\u0026component\u003dCompiler\n\nBugs for exceptions thrown have titles File:line from the top stack,\ne.g., \"SomeFile.java:243\"\n\nIf you don\u0027t find the exception below in a bug, please add a new bug\nat http://bugs.eclipse.org/bugs/enter_bug.cgi?product\u003dAspectJ\nTo make the bug a priority, please include a test program\nthat can reproduce this exception.\nnull\njava.lang.NullPointerException\n        at org.aspectj.weaver.patterns.ReferencePointcut.concretize1\n(ReferencePo\nintcut.java:243)\n        at org.aspectj.weaver.patterns.AndPointcut.concretize1\n(AndPointcut.java:\n88)\n        at org.aspectj.weaver.patterns.ReferencePointcut.concretize1\n(ReferencePo\nintcut.java:272)\n        at org.aspectj.weaver.patterns.Pointcut.concretize(Pointcut.java:127)\n        at org.aspectj.weaver.patterns.Pointcut.concretize(Pointcut.java:110)\n        at org.aspectj.weaver.CrosscuttingMembers.addDeclare\n(CrosscuttingMembers\n.java:111)\n        at org.aspectj.weaver.CrosscuttingMembers.addDeclares\n(CrosscuttingMember\ns.java:92)\n        at org.aspectj.weaver.ResolvedTypeX.collectCrosscuttingMembers\n(ResolvedT\nypeX.java:332)\n        at org.aspectj.weaver.CrosscuttingMembersSet.addOrReplaceAspect\n(Crosscut\ntingMembersSet.java:50)\n        at \norg.aspectj.ajdt.internal.compiler.ast.AspectDeclaration.buildInterTy\npeAndPerClause(AspectDeclaration.java:754)\n        at \norg.aspectj.ajdt.internal.compiler.lookup.AjLookupEnvironment.buildIn\nterTypeAndPerClause(AjLookupEnvironment.java:124)\n        at \norg.aspectj.ajdt.internal.compiler.lookup.AjLookupEnvironment.complet\neTypeBindings(AjLookupEnvironment.java:91)\n        at org.eclipse.jdt.internal.compiler.Compiler.beginToCompile\n(Compiler.ja\nva:310)\n        at org.eclipse.jdt.internal.compiler.Compiler.compile\n(Compiler.java:324)\n\n        at \norg.aspectj.ajdt.internal.core.builder.AjBuildManager.performCompilat\nion(AjBuildManager.java:373)\n        at org.aspectj.ajdt.internal.core.builder.AjBuildManager.doBuild\n(AjBuild\nManager.java:125)\n        at org.aspectj.ajdt.internal.core.builder.AjBuildManager.batchBuild\n(AjBu\nildManager.java:70)\n        at org.aspectj.ajdt.ajc.AjdtCommand.doCommand(AjdtCommand.java:99)\n        at org.aspectj.ajdt.ajc.AjdtCommand.runCommand(AjdtCommand.java:53)\n        at org.aspectj.tools.ajc.Main.run(Main.java:217)\n        at org.aspectj.tools.ajc.Main.runMain(Main.java:155)\n        at org.aspectj.tools.ajc.Main.main(Main.java:72)\n\n\n1 fail|abort, 3 errors",
    "I believe this should be fixed by the same changes that fixed your two related\ndeclare error and declare soft bug reports.  Please confirm that this is fixed\nfor you in CVS head, and reopen the bug if you still see the NPE.",
    "fixing target milestone",
    "The following program demonstrates a related NPE, resulting from a derived \nclass that doesn\u0027t implement an abstract pointcut. This is less serious, since \nit is caused by an invalid program.\n\nsource:\npublic abstract aspect Base {\n    public abstract pointcut scope();\n    declare soft: Exception: scope();\n}\n\naspect Derived extends Base {\n}\n\nexample output (from cvs head):\nC:\\temp\\eclipse\\workspace\\atrack\u003eajc Base.java\njava.lang.NullPointerException\n        at org.aspectj.weaver.patterns.ReferencePointcut.concretize1\n(ReferencePo\nintcut.java:243)\n        at org.aspectj.weaver.patterns.Pointcut.concretize(Pointcut.java:127)\n        at org.aspectj.weaver.patterns.Pointcut.concretize(Pointcut.java:110)\n        at org.aspectj.weaver.CrosscuttingMembers.addDeclare\n(CrosscuttingMembers\n.java:111)\n        at org.aspectj.weaver.CrosscuttingMembers.addDeclares\n(CrosscuttingMember\ns.java:92)\n        at org.aspectj.weaver.ResolvedTypeX.collectCrosscuttingMembers\n(ResolvedT\nypeX.java:332)\n        at org.aspectj.weaver.CrosscuttingMembersSet.addOrReplaceAspect\n(Crosscut\ntingMembersSet.java:50)\n        at \norg.aspectj.ajdt.internal.compiler.ast.AspectDeclaration.buildInterTy\npeAndPerClause(AspectDeclaration.java:754)\n        at \norg.aspectj.ajdt.internal.compiler.lookup.AjLookupEnvironment.buildIn\nterTypeAndPerClause(AjLookupEnvironment.java:124)\n        at \norg.aspectj.ajdt.internal.compiler.lookup.AjLookupEnvironment.complet\neTypeBindings(AjLookupEnvironment.java:91)\n        at org.eclipse.jdt.internal.compiler.Compiler.beginToCompile\n(Compiler.ja\nva:310)\n        at org.eclipse.jdt.internal.compiler.Compiler.compile\n(Compiler.java:324)\n\n        at \norg.aspectj.ajdt.internal.core.builder.AjBuildManager.performCompilat\nion(AjBuildManager.java:373)\n        at org.aspectj.ajdt.internal.core.builder.AjBuildManager.doBuild\n(AjBuild\nManager.java:125)\n        at org.aspectj.ajdt.internal.core.builder.AjBuildManager.batchBuild\n(AjBu\nildManager.java:70)\n        at org.aspectj.ajdt.ajc.AjdtCommand.doCommand(AjdtCommand.java:99)\n        at org.aspectj.ajdt.ajc.AjdtCommand.runCommand(AjdtCommand.java:53)\n        at org.aspectj.tools.ajc.Main.run(Main.java:217)\n        at org.aspectj.tools.ajc.Main.runMain(Main.java:155)\n        at org.aspectj.tools.ajc.Main.main(Main.java:72)\nC:\\temp\\eclipse\\workspace\\atrack\\Base.java:0 Internal compiler error\njava.lang.NullPointerException\n        at org.aspectj.weaver.patterns.ReferencePointcut.concretize1\n(ReferencePo\nintcut.java:243)\n        at org.aspectj.weaver.patterns.Pointcut.concretize(Pointcut.java:127)\n        at org.aspectj.weaver.patterns.Pointcut.concretize(Pointcut.java:110)\n        at org.aspectj.weaver.CrosscuttingMembers.addDeclare\n(CrosscuttingMembers\n.java:111)\n        at org.aspectj.weaver.CrosscuttingMembers.addDeclares\n(CrosscuttingMember\ns.java:92)\n        at org.aspectj.weaver.ResolvedTypeX.collectCrosscuttingMembers\n(ResolvedT\nypeX.java:332)\n        at org.aspectj.weaver.CrosscuttingMembersSet.addOrReplaceAspect\n(Crosscut\ntingMembersSet.java:50)\n        at \norg.aspectj.ajdt.internal.compiler.ast.AspectDeclaration.buildInterTy\npeAndPerClause(AspectDeclaration.java:754)\n        at \norg.aspectj.ajdt.internal.compiler.lookup.AjLookupEnvironment.buildIn\nterTypeAndPerClause(AjLookupEnvironment.java:124)\n        at \norg.aspectj.ajdt.internal.compiler.lookup.AjLookupEnvironment.complet\neTypeBindings(AjLookupEnvironment.java:91)\n        at org.eclipse.jdt.internal.compiler.Compiler.beginToCompile\n(Compiler.ja\nva:310)\n        at org.eclipse.jdt.internal.compiler.Compiler.compile\n(Compiler.java:324)\n\n        at \norg.aspectj.ajdt.internal.core.builder.AjBuildManager.performCompilat\nion(AjBuildManager.java:373)\n        at org.aspectj.ajdt.internal.core.builder.AjBuildManager.doBuild\n(AjBuild\nManager.java:125)\n        at org.aspectj.ajdt.internal.core.builder.AjBuildManager.batchBuild\n(AjBu\nildManager.java:70)\n        at org.aspectj.ajdt.ajc.AjdtCommand.doCommand(AjdtCommand.java:99)\n        at org.aspectj.ajdt.ajc.AjdtCommand.runCommand(AjdtCommand.java:53)\n        at org.aspectj.tools.ajc.Main.run(Main.java:217)\n        at org.aspectj.tools.ajc.Main.runMain(Main.java:155)\n        at org.aspectj.tools.ajc.Main.main(Main.java:72)\n\n\n!! no source information available !!\nABORT\nException thrown from AspectJ DEVELOPMENT\n\nThis might be logged as a bug already -- find current bugs at\n  http://bugs.eclipse.org/bugs/buglist.cgi?product\u003dAspectJ\u0026component\u003dCompiler\n\nBugs for exceptions thrown have titles File:line from the top stack,\ne.g., \"SomeFile.java:243\"\n\nIf you don\u0027t find the exception below in a bug, please add a new bug\nat http://bugs.eclipse.org/bugs/enter_bug.cgi?product\u003dAspectJ\nTo make the bug a priority, please include a test program\nthat can reproduce this exception.\nnull\njava.lang.NullPointerException\n        at org.aspectj.weaver.patterns.ReferencePointcut.concretize1\n(ReferencePo\nintcut.java:243)\n        at org.aspectj.weaver.patterns.Pointcut.concretize(Pointcut.java:127)\n        at org.aspectj.weaver.patterns.Pointcut.concretize(Pointcut.java:110)\n        at org.aspectj.weaver.CrosscuttingMembers.addDeclare\n(CrosscuttingMembers\n.java:111)\n        at org.aspectj.weaver.CrosscuttingMembers.addDeclares\n(CrosscuttingMember\ns.java:92)\n        at org.aspectj.weaver.ResolvedTypeX.collectCrosscuttingMembers\n(ResolvedT\nypeX.java:332)\n        at org.aspectj.weaver.CrosscuttingMembersSet.addOrReplaceAspect\n(Crosscut\ntingMembersSet.java:50)\n        at \norg.aspectj.ajdt.internal.compiler.ast.AspectDeclaration.buildInterTy\npeAndPerClause(AspectDeclaration.java:754)\n        at \norg.aspectj.ajdt.internal.compiler.lookup.AjLookupEnvironment.buildIn\nterTypeAndPerClause(AjLookupEnvironment.java:124)\n        at \norg.aspectj.ajdt.internal.compiler.lookup.AjLookupEnvironment.complet\neTypeBindings(AjLookupEnvironment.java:91)\n        at org.eclipse.jdt.internal.compiler.Compiler.beginToCompile\n(Compiler.ja\nva:310)\n        at org.eclipse.jdt.internal.compiler.Compiler.compile\n(Compiler.java:324)\n\n        at \norg.aspectj.ajdt.internal.core.builder.AjBuildManager.performCompilat\nion(AjBuildManager.java:373)\n        at org.aspectj.ajdt.internal.core.builder.AjBuildManager.doBuild\n(AjBuild\nManager.java:125)\n        at org.aspectj.ajdt.internal.core.builder.AjBuildManager.batchBuild\n(AjBu\nildManager.java:70)\n        at org.aspectj.ajdt.ajc.AjdtCommand.doCommand(AjdtCommand.java:99)\n        at org.aspectj.ajdt.ajc.AjdtCommand.runCommand(AjdtCommand.java:53)\n        at org.aspectj.tools.ajc.Main.run(Main.java:217)\n        at org.aspectj.tools.ajc.Main.runMain(Main.java:155)\n        at org.aspectj.tools.ajc.Main.main(Main.java:72)\n\n\n1 fail|abort, 1 error\n",
    "Using the test code supplied in comment #3 I do not see the NPE but, instead, \nsee the following (logical) compiler errors :-\n\n* inherited abstract pointcut Base.scope() is not made concrete in Derived\n* pointcut Base.scope() is abstract\n* inherited abstract pointcut Base.scope() is not made concrete in Derived\n\nwhich go away when a concrete version of the pointcut is supplied in the Derived \naspect. Is this still a bug ?",
    "This was probably fixed some time in the tree.",
    "updating target flag to indicate inclusion in 1.2 release."
  ],
  "commentCreationDates": [
    "2003-09-09T02:22:29+02:00",
    "2003-09-10T02:38:18+02:00",
    "2003-09-10T02:40:02+02:00",
    "2003-09-11T00:38:13+02:00",
    "2003-10-17T02:32:08+02:00",
    "2004-01-14T16:07:19+01:00",
    "2004-03-19T14:51:33+01:00"
  ],
  "traces": [
    {
      "exceptionType": "java.lang.NullPointerException",
      "elements": [
        {
          "method": "org.aspectj.weaver.patterns.ReferencePointcut.concretize1",
          "source": "ReferencePo intcut.java:243"
        },
        {
          "method": "org.aspectj.weaver.patterns.AndPointcut.concretize1",
          "source": "AndPointcut.java: 88"
        },
        {
          "method": "org.aspectj.weaver.patterns.ReferencePointcut.concretize1",
          "source": "ReferencePo intcut.java:272"
        },
        {
          "method": "org.aspectj.weaver.patterns.Pointcut.concretize",
          "source": "Pointcut.java:127"
        },
        {
          "method": "org.aspectj.weaver.patterns.Pointcut.concretize",
          "source": "Pointcut.java:110"
        },
        {
          "method": "org.aspectj.weaver.CrosscuttingMembers.addDeclare",
          "source": "CrosscuttingMembers .java:111"
        },
        {
          "method": "org.aspectj.weaver.CrosscuttingMembers.addDeclares",
          "source": "CrosscuttingMember s.java:92"
        },
        {
          "method": "org.aspectj.weaver.ResolvedTypeX.collectCrosscuttingMembers",
          "source": "ResolvedT ypeX.java:332"
        },
        {
          "method": "org.aspectj.weaver.CrosscuttingMembersSet.addOrReplaceAspect",
          "source": "Crosscut tingMembersSet.java:50"
        },
        {
          "method": "org.aspectj.ajdt.internal.compiler.ast.AspectDeclaration.buildInterTypeAndPerClause",
          "source": "AspectDeclaration.java:754"
        },
        {
          "method": "org.aspectj.ajdt.internal.compiler.lookup.AjLookupEnvironment.buildInterTypeAndPerClause",
          "source": "AjLookupEnvironment.java:124"
        },
        {
          "method": "org.aspectj.ajdt.internal.compiler.lookup.AjLookupEnvironment.completeTypeBindings",
          "source": "AjLookupEnvironment.java:91"
        },
        {
          "method": "org.eclipse.jdt.internal.compiler.Compiler.beginToCompile",
          "source": "Compiler.ja va:310"
        },
        {
          "method": "org.eclipse.jdt.internal.compiler.Compiler.compile",
          "source": "Compiler.java:324"
        },
        {
          "method": "org.aspectj.ajdt.internal.core.builder.AjBuildManager.performCompilation",
          "source": "AjBuildManager.java:373"
        },
        {
          "method": "org.aspectj.ajdt.internal.core.builder.AjBuildManager.doBuild",
          "source": "AjBuild Manager.java:125"
        },
        {
          "method": "org.aspectj.ajdt.internal.core.builder.AjBuildManager.batchBuild",
          "source": "AjBu ildManager.java:70"
        },
        {
          "method": "org.aspectj.ajdt.ajc.AjdtCommand.doCommand",
          "source": "AjdtCommand.java:99"
        },
        {
          "method": "org.aspectj.ajdt.ajc.AjdtCommand.runCommand",
          "source": "AjdtCommand.java:53"
        },
        {
          "method": "org.aspectj.tools.ajc.Main.run",
          "source": "Main.java:217"
        },
        {
          "method": "org.aspectj.tools.ajc.Main.runMain",
          "source": "Main.java:155"
        },
        {
          "method": "org.aspectj.tools.ajc.Main.main",
          "source": "Main.java:72"
        }
      ],
      "number": 0,
      "commentIndex": 0,
      "bugId": "42739",
      "date": "2003-09-09T02:22:29+02:00",
      "product": "AspectJ",
      "component": "Compiler",
      "severity": "major"
    },
    {
      "exceptionType": "java.lang.NullPointerException",
      "elements": [
        {
          "method": "org.aspectj.weaver.patterns.ReferencePointcut.concretize1",
          "source": "ReferencePo intcut.java:243"
        },
        {
          "method": "org.aspectj.weaver.patterns.AndPointcut.concretize1",
          "source": "AndPointcut.java: 88"
        },
        {
          "method": "org.aspectj.weaver.patterns.ReferencePointcut.concretize1",
          "source": "ReferencePo intcut.java:272"
        },
        {
          "method": "org.aspectj.weaver.patterns.Pointcut.concretize",
          "source": "Pointcut.java:127"
        },
        {
          "method": "org.aspectj.weaver.patterns.Pointcut.concretize",
          "source": "Pointcut.java:110"
        },
        {
          "method": "org.aspectj.weaver.CrosscuttingMembers.addDeclare",
          "source": "CrosscuttingMembers .java:111"
        },
        {
          "method": "org.aspectj.weaver.CrosscuttingMembers.addDeclares",
          "source": "CrosscuttingMember s.java:92"
        },
        {
          "method": "org.aspectj.weaver.ResolvedTypeX.collectCrosscuttingMembers",
          "source": "ResolvedT ypeX.java:332"
        },
        {
          "method": "org.aspectj.weaver.CrosscuttingMembersSet.addOrReplaceAspect",
          "source": "Crosscut tingMembersSet.java:50"
        },
        {
          "method": "org.aspectj.ajdt.internal.compiler.ast.AspectDeclaration.buildInterTypeAndPerClause",
          "source": "AspectDeclaration.java:754"
        },
        {
          "method": "org.aspectj.ajdt.internal.compiler.lookup.AjLookupEnvironment.buildInterTypeAndPerClause",
          "source": "AjLookupEnvironment.java:124"
        },
        {
          "method": "org.aspectj.ajdt.internal.compiler.lookup.AjLookupEnvironment.completeTypeBindings",
          "source": "AjLookupEnvironment.java:91"
        },
        {
          "method": "org.eclipse.jdt.internal.compiler.Compiler.beginToCompile",
          "source": "Compiler.ja va:310"
        },
        {
          "method": "org.eclipse.jdt.internal.compiler.Compiler.compile",
          "source": "Compiler.java:324"
        },
        {
          "method": "org.aspectj.ajdt.internal.core.builder.AjBuildManager.performCompilation",
          "source": "AjBuildManager.java:373"
        },
        {
          "method": "org.aspectj.ajdt.internal.core.builder.AjBuildManager.doBuild",
          "source": "AjBuild Manager.java:125"
        },
        {
          "method": "org.aspectj.ajdt.internal.core.builder.AjBuildManager.batchBuild",
          "source": "AjBu ildManager.java:70"
        },
        {
          "method": "org.aspectj.ajdt.ajc.AjdtCommand.doCommand",
          "source": "AjdtCommand.java:99"
        },
        {
          "method": "org.aspectj.ajdt.ajc.AjdtCommand.runCommand",
          "source": "AjdtCommand.java:53"
        },
        {
          "method": "org.aspectj.tools.ajc.Main.run",
          "source": "Main.java:217"
        },
        {
          "method": "org.aspectj.tools.ajc.Main.runMain",
          "source": "Main.java:155"
        },
        {
          "method": "org.aspectj.tools.ajc.Main.main",
          "source": "Main.java:72"
        }
      ],
      "number": 1,
      "commentIndex": 0,
      "bugId": "42739",
      "date": "2003-09-09T02:22:29+02:00",
      "product": "AspectJ",
      "component": "Compiler",
      "severity": "major"
    },
    {
      "exceptionType": "java.lang.NullPointerException",
      "elements": [
        {
          "method": "org.aspectj.weaver.patterns.ReferencePointcut.concretize1",
          "source": "ReferencePo intcut.java:243"
        },
        {
          "method": "org.aspectj.weaver.patterns.AndPointcut.concretize1",
          "source": "AndPointcut.java: 88"
        },
        {
          "method": "org.aspectj.weaver.patterns.ReferencePointcut.concretize1",
          "source": "ReferencePo intcut.java:272"
        },
        {
          "method": "org.aspectj.weaver.patterns.Pointcut.concretize",
          "source": "Pointcut.java:127"
        },
        {
          "method": "org.aspectj.weaver.patterns.Pointcut.concretize",
          "source": "Pointcut.java:110"
        },
        {
          "method": "org.aspectj.weaver.CrosscuttingMembers.addDeclare",
          "source": "CrosscuttingMembers .java:111"
        },
        {
          "method": "org.aspectj.weaver.CrosscuttingMembers.addDeclares",
          "source": "CrosscuttingMember s.java:92"
        },
        {
          "method": "org.aspectj.weaver.ResolvedTypeX.collectCrosscuttingMembers",
          "source": "ResolvedT ypeX.java:332"
        },
        {
          "method": "org.aspectj.weaver.CrosscuttingMembersSet.addOrReplaceAspect",
          "source": "Crosscut tingMembersSet.java:50"
        },
        {
          "method": "org.aspectj.ajdt.internal.compiler.ast.AspectDeclaration.buildInterTypeAndPerClause",
          "source": "AspectDeclaration.java:754"
        },
        {
          "method": "org.aspectj.ajdt.internal.compiler.lookup.AjLookupEnvironment.buildInterTypeAndPerClause",
          "source": "AjLookupEnvironment.java:124"
        },
        {
          "method": "org.aspectj.ajdt.internal.compiler.lookup.AjLookupEnvironment.completeTypeBindings",
          "source": "AjLookupEnvironment.java:91"
        },
        {
          "method": "org.eclipse.jdt.internal.compiler.Compiler.beginToCompile",
          "source": "Compiler.ja va:310"
        },
        {
          "method": "org.eclipse.jdt.internal.compiler.Compiler.compile",
          "source": "Compiler.java:324"
        },
        {
          "method": "org.aspectj.ajdt.internal.core.builder.AjBuildManager.performCompilation",
          "source": "AjBuildManager.java:373"
        },
        {
          "method": "org.aspectj.ajdt.internal.core.builder.AjBuildManager.doBuild",
          "source": "AjBuild Manager.java:125"
        },
        {
          "method": "org.aspectj.ajdt.internal.core.builder.AjBuildManager.batchBuild",
          "source": "AjBu ildManager.java:70"
        },
        {
          "method": "org.aspectj.ajdt.ajc.AjdtCommand.doCommand",
          "source": "AjdtCommand.java:99"
        },
        {
          "method": "org.aspectj.ajdt.ajc.AjdtCommand.runCommand",
          "source": "AjdtCommand.java:53"
        },
        {
          "method": "org.aspectj.tools.ajc.Main.run",
          "source": "Main.java:217"
        },
        {
          "method": "org.aspectj.tools.ajc.Main.runMain",
          "source": "Main.java:155"
        },
        {
          "method": "org.aspectj.tools.ajc.Main.main",
          "source": "Main.java:72"
        }
      ],
      "number": 2,
      "commentIndex": 0,
      "bugId": "42739",
      "date": "2003-09-09T02:22:29+02:00",
      "product": "AspectJ",
      "component": "Compiler",
      "severity": "major"
    },
    {
      "exceptionType": "java.lang.NullPointerException",
      "elements": [
        {
          "method": "org.aspectj.weaver.patterns.ReferencePointcut.concretize1",
          "source": "ReferencePo intcut.java:243"
        },
        {
          "method": "org.aspectj.weaver.patterns.Pointcut.concretize",
          "source": "Pointcut.java:127"
        },
        {
          "method": "org.aspectj.weaver.patterns.Pointcut.concretize",
          "source": "Pointcut.java:110"
        },
        {
          "method": "org.aspectj.weaver.CrosscuttingMembers.addDeclare",
          "source": "CrosscuttingMembers .java:111"
        },
        {
          "method": "org.aspectj.weaver.CrosscuttingMembers.addDeclares",
          "source": "CrosscuttingMember s.java:92"
        },
        {
          "method": "org.aspectj.weaver.ResolvedTypeX.collectCrosscuttingMembers",
          "source": "ResolvedT ypeX.java:332"
        },
        {
          "method": "org.aspectj.weaver.CrosscuttingMembersSet.addOrReplaceAspect",
          "source": "Crosscut tingMembersSet.java:50"
        },
        {
          "method": "org.aspectj.ajdt.internal.compiler.ast.AspectDeclaration.buildInterTypeAndPerClause",
          "source": "AspectDeclaration.java:754"
        },
        {
          "method": "org.aspectj.ajdt.internal.compiler.lookup.AjLookupEnvironment.buildInterTypeAndPerClause",
          "source": "AjLookupEnvironment.java:124"
        },
        {
          "method": "org.aspectj.ajdt.internal.compiler.lookup.AjLookupEnvironment.completeTypeBindings",
          "source": "AjLookupEnvironment.java:91"
        },
        {
          "method": "org.eclipse.jdt.internal.compiler.Compiler.beginToCompile",
          "source": "Compiler.ja va:310"
        },
        {
          "method": "org.eclipse.jdt.internal.compiler.Compiler.compile",
          "source": "Compiler.java:324"
        },
        {
          "method": "org.aspectj.ajdt.internal.core.builder.AjBuildManager.performCompilation",
          "source": "AjBuildManager.java:373"
        },
        {
          "method": "org.aspectj.ajdt.internal.core.builder.AjBuildManager.doBuild",
          "source": "AjBuild Manager.java:125"
        },
        {
          "method": "org.aspectj.ajdt.internal.core.builder.AjBuildManager.batchBuild",
          "source": "AjBu ildManager.java:70"
        },
        {
          "method": "org.aspectj.ajdt.ajc.AjdtCommand.doCommand",
          "source": "AjdtCommand.java:99"
        },
        {
          "method": "org.aspectj.ajdt.ajc.AjdtCommand.runCommand",
          "source": "AjdtCommand.java:53"
        },
        {
          "method": "org.aspectj.tools.ajc.Main.run",
          "source": "Main.java:217"
        },
        {
          "method": "org.aspectj.tools.ajc.Main.runMain",
          "source": "Main.java:155"
        },
        {
          "method": "org.aspectj.tools.ajc.Main.main",
          "source": "Main.java:72"
        }
      ],
      "number": 3,
      "commentIndex": 3,
      "bugId": "42739",
      "date": "2003-09-11T00:38:13+02:00",
      "product": "AspectJ",
      "component": "Compiler",
      "severity": "major"
    },
    {
      "exceptionType": "java.lang.NullPointerException",
      "elements": [
        {
          "method": "org.aspectj.weaver.patterns.ReferencePointcut.concretize1",
          "source": "ReferencePo intcut.java:243"
        },
        {
          "method": "org.aspectj.weaver.patterns.Pointcut.concretize",
          "source": "Pointcut.java:127"
        },
        {
          "method": "org.aspectj.weaver.patterns.Pointcut.concretize",
          "source": "Pointcut.java:110"
        },
        {
          "method": "org.aspectj.weaver.CrosscuttingMembers.addDeclare",
          "source": "CrosscuttingMembers .java:111"
        },
        {
          "method": "org.aspectj.weaver.CrosscuttingMembers.addDeclares",
          "source": "CrosscuttingMember s.java:92"
        },
        {
          "method": "org.aspectj.weaver.ResolvedTypeX.collectCrosscuttingMembers",
          "source": "ResolvedT ypeX.java:332"
        },
        {
          "method": "org.aspectj.weaver.CrosscuttingMembersSet.addOrReplaceAspect",
          "source": "Crosscut tingMembersSet.java:50"
        },
        {
          "method": "org.aspectj.ajdt.internal.compiler.ast.AspectDeclaration.buildInterTypeAndPerClause",
          "source": "AspectDeclaration.java:754"
        },
        {
          "method": "org.aspectj.ajdt.internal.compiler.lookup.AjLookupEnvironment.buildInterTypeAndPerClause",
          "source": "AjLookupEnvironment.java:124"
        },
        {
          "method": "org.aspectj.ajdt.internal.compiler.lookup.AjLookupEnvironment.completeTypeBindings",
          "source": "AjLookupEnvironment.java:91"
        },
        {
          "method": "org.eclipse.jdt.internal.compiler.Compiler.beginToCompile",
          "source": "Compiler.ja va:310"
        },
        {
          "method": "org.eclipse.jdt.internal.compiler.Compiler.compile",
          "source": "Compiler.java:324"
        },
        {
          "method": "org.aspectj.ajdt.internal.core.builder.AjBuildManager.performCompilation",
          "source": "AjBuildManager.java:373"
        },
        {
          "method": "org.aspectj.ajdt.internal.core.builder.AjBuildManager.doBuild",
          "source": "AjBuild Manager.java:125"
        },
        {
          "method": "org.aspectj.ajdt.internal.core.builder.AjBuildManager.batchBuild",
          "source": "AjBu ildManager.java:70"
        },
        {
          "method": "org.aspectj.ajdt.ajc.AjdtCommand.doCommand",
          "source": "AjdtCommand.java:99"
        },
        {
          "method": "org.aspectj.ajdt.ajc.AjdtCommand.runCommand",
          "source": "AjdtCommand.java:53"
        },
        {
          "method": "org.aspectj.tools.ajc.Main.run",
          "source": "Main.java:217"
        },
        {
          "method": "org.aspectj.tools.ajc.Main.runMain",
          "source": "Main.java:155"
        },
        {
          "method": "org.aspectj.tools.ajc.Main.main",
          "source": "Main.java:72"
        }
      ],
      "number": 4,
      "commentIndex": 3,
      "bugId": "42739",
      "date": "2003-09-11T00:38:13+02:00",
      "product": "AspectJ",
      "component": "Compiler",
      "severity": "major"
    },
    {
      "exceptionType": "java.lang.NullPointerException",
      "elements": [
        {
          "method": "org.aspectj.weaver.patterns.ReferencePointcut.concretize1",
          "source": "ReferencePo intcut.java:243"
        },
        {
          "method": "org.aspectj.weaver.patterns.Pointcut.concretize",
          "source": "Pointcut.java:127"
        },
        {
          "method": "org.aspectj.weaver.patterns.Pointcut.concretize",
          "source": "Pointcut.java:110"
        },
        {
          "method": "org.aspectj.weaver.CrosscuttingMembers.addDeclare",
          "source": "CrosscuttingMembers .java:111"
        },
        {
          "method": "org.aspectj.weaver.CrosscuttingMembers.addDeclares",
          "source": "CrosscuttingMember s.java:92"
        },
        {
          "method": "org.aspectj.weaver.ResolvedTypeX.collectCrosscuttingMembers",
          "source": "ResolvedT ypeX.java:332"
        },
        {
          "method": "org.aspectj.weaver.CrosscuttingMembersSet.addOrReplaceAspect",
          "source": "Crosscut tingMembersSet.java:50"
        },
        {
          "method": "org.aspectj.ajdt.internal.compiler.ast.AspectDeclaration.buildInterTypeAndPerClause",
          "source": "AspectDeclaration.java:754"
        },
        {
          "method": "org.aspectj.ajdt.internal.compiler.lookup.AjLookupEnvironment.buildInterTypeAndPerClause",
          "source": "AjLookupEnvironment.java:124"
        },
        {
          "method": "org.aspectj.ajdt.internal.compiler.lookup.AjLookupEnvironment.completeTypeBindings",
          "source": "AjLookupEnvironment.java:91"
        },
        {
          "method": "org.eclipse.jdt.internal.compiler.Compiler.beginToCompile",
          "source": "Compiler.ja va:310"
        },
        {
          "method": "org.eclipse.jdt.internal.compiler.Compiler.compile",
          "source": "Compiler.java:324"
        },
        {
          "method": "org.aspectj.ajdt.internal.core.builder.AjBuildManager.performCompilation",
          "source": "AjBuildManager.java:373"
        },
        {
          "method": "org.aspectj.ajdt.internal.core.builder.AjBuildManager.doBuild",
          "source": "AjBuild Manager.java:125"
        },
        {
          "method": "org.aspectj.ajdt.internal.core.builder.AjBuildManager.batchBuild",
          "source": "AjBu ildManager.java:70"
        },
        {
          "method": "org.aspectj.ajdt.ajc.AjdtCommand.doCommand",
          "source": "AjdtCommand.java:99"
        },
        {
          "method": "org.aspectj.ajdt.ajc.AjdtCommand.runCommand",
          "source": "AjdtCommand.java:53"
        },
        {
          "method": "org.aspectj.tools.ajc.Main.run",
          "source": "Main.java:217"
        },
        {
          "method": "org.aspectj.tools.ajc.Main.runMain",
          "source": "Main.java:155"
        },
        {
          "method": "org.aspectj.tools.ajc.Main.main",
          "source": "Main.java:72"
        }
      ],
      "number": 5,
      "commentIndex": 3,
      "bugId": "42739",
      "date": "2003-09-11T00:38:13+02:00",
      "product": "AspectJ",
      "component": "Compiler",
      "severity": "major"
    }
  ],
  "groupId": "42739",
  "bugId": "42739",
  "date": "2003-09-09T02:22:29+02:00",
  "product": "AspectJ",
  "component": "Compiler",
  "severity": "major"
}