{
  "comments": [
    "This happens when you try to use a pointcut that is multiply defined (as if \noverloaded) in a cflow pointcut. It\u0027s not a priority to create a reproducable \ntest case; the workaround is simple: use different names for the pointcuts)\n\nABORT\nException thrown from AspectJ DEVELOPMENT\n\nThis might be logged as a bug already -- find current bugs at\n  http://bugs.eclipse.org/bugs/buglist.cgi?product\u003dAspectJ\u0026component\u003dCompiler\n\nBugs for exceptions thrown have titles File:line from the top stack,\ne.g., \"SomeFile.java:243\"\n\nIf you don\u0027t find the exception below in a bug, please add a new bug\nat http://bugs.eclipse.org/bugs/enter_bug.cgi?product\u003dAspectJ\nTo make the bug a priority, please include a test program\nthat can reproduce this exception.\nillegal change to pointcut declaration: \najee.component.StrutsPointcuts.actionExe\ncute(*, *, *, BindingTypePattern(javax.servlet.http.HttpServletRequest, 0), *)\nillegal change to pointcut declaration: \najee.component.StrutsPointcuts.actionExe\ncute(*, *, *, BindingTypePattern(javax.servlet.http.HttpServletRequest, 0), *)\norg.aspectj.weaver.BCException: illegal change to pointcut declaration: \najee.com\nponent.StrutsPointcuts.actionExecute(*, *, *, BindingTypePattern\n(javax.servlet.h\nttp.HttpServletRequest, 0), *)\n        at org.aspectj.weaver.patterns.ReferencePointcut.concretize1\n(ReferencePo\nintcut.java:261)\n        at org.aspectj.weaver.patterns.Pointcut.concretize(Pointcut.java:127)\n        at org.aspectj.weaver.patterns.CflowPointcut.concretize1\n(CflowPointcut.j\nava:145)\n        at org.aspectj.weaver.patterns.Pointcut.concretize(Pointcut.java:127)\n        at org.aspectj.weaver.patterns.Pointcut.concretize(Pointcut.java:120)\n        at org.aspectj.weaver.Advice.concretize(Advice.java:216)\n        at org.aspectj.weaver.CrosscuttingMembers.addShadowMunger\n(CrosscuttingMe\nmbers.java:78)\n        at org.aspectj.weaver.CrosscuttingMembers.addShadowMungers\n(CrosscuttingM\nembers.java:72)\n        at org.aspectj.weaver.ResolvedTypeX.collectCrosscuttingMembers\n(ResolvedT\nypeX.java:330)\n        at org.aspectj.weaver.CrosscuttingMembersSet.addOrReplaceAspect\n(Crosscut\ntingMembersSet.java:54)\n        at org.aspectj.weaver.bcel.BcelWeaver.prepareForWeave\n(BcelWeaver.java:20\n2)\n        at org.aspectj.weaver.bcel.BcelWeaver.weave(BcelWeaver.java:276)\n        at \norg.aspectj.ajdt.internal.core.builder.AjBuildManager.weaveAndGenerat\neClassFiles(AjBuildManager.java:256)\n        at org.aspectj.ajdt.internal.core.builder.AjBuildManager.doBuild\n(AjBuild\nManager.java:156)\n        at org.aspectj.ajdt.internal.core.builder.AjBuildManager.batchBuild\n(AjBu\nildManager.java:70)\n        at org.aspectj.ajdt.ajc.AjdtCommand.doCommand(AjdtCommand.java:99)\n        at org.aspectj.ajdt.ajc.AjdtCommand.runCommand(AjdtCommand.java:53)\n        at org.aspectj.tools.ajc.Main.run(Main.java:217)\n        at org.aspectj.tools.ajc.Main.runMain(Main.java:155)\n        at org.aspectj.tools.ajc.Main.main(Main.java:72)",
    "also a bug in 1.1",
    "This appears to be another issue with error checking for overloaded pointcut \ndeclarations.  Marking this as a dup of the fixed #49457 that included a nice \nreproducable test case.  If this isn\u0027t fixed in the tree, please submit a test \ncase.\n\n*** This bug has been marked as a duplicate of 49457 ***"
  ],
  "commentCreationDates": [
    "2003-09-10T02:07:13+02:00",
    "2003-09-10T02:07:42+02:00",
    "2004-01-28T01:29:41+01:00"
  ],
  "traces": [
    {
      "exceptionType": "org.aspectj.weaver.BCException",
      "message": "illegal change to pointcut declaration:  ajee.com ponent.StrutsPointcuts.actionExecute(*, *, *, BindingTypePattern (javax.servlet.h ttp.HttpServletRequest, 0), *)",
      "elements": [
        {
          "method": "org.aspectj.weaver.patterns.ReferencePointcut.concretize1",
          "source": "ReferencePo intcut.java:261"
        },
        {
          "method": "org.aspectj.weaver.patterns.Pointcut.concretize",
          "source": "Pointcut.java:127"
        },
        {
          "method": "org.aspectj.weaver.patterns.CflowPointcut.concretize1",
          "source": "CflowPointcut.j ava:145"
        },
        {
          "method": "org.aspectj.weaver.patterns.Pointcut.concretize",
          "source": "Pointcut.java:127"
        },
        {
          "method": "org.aspectj.weaver.patterns.Pointcut.concretize",
          "source": "Pointcut.java:120"
        },
        {
          "method": "org.aspectj.weaver.Advice.concretize",
          "source": "Advice.java:216"
        },
        {
          "method": "org.aspectj.weaver.CrosscuttingMembers.addShadowMunger",
          "source": "CrosscuttingMe mbers.java:78"
        },
        {
          "method": "org.aspectj.weaver.CrosscuttingMembers.addShadowMungers",
          "source": "CrosscuttingM embers.java:72"
        },
        {
          "method": "org.aspectj.weaver.ResolvedTypeX.collectCrosscuttingMembers",
          "source": "ResolvedT ypeX.java:330"
        },
        {
          "method": "org.aspectj.weaver.CrosscuttingMembersSet.addOrReplaceAspect",
          "source": "Crosscut tingMembersSet.java:54"
        },
        {
          "method": "org.aspectj.weaver.bcel.BcelWeaver.prepareForWeave",
          "source": "BcelWeaver.java:20 2"
        },
        {
          "method": "org.aspectj.weaver.bcel.BcelWeaver.weave",
          "source": "BcelWeaver.java:276"
        },
        {
          "method": "org.aspectj.ajdt.internal.core.builder.AjBuildManager.weaveAndGenerateClassFiles",
          "source": "AjBuildManager.java:256"
        },
        {
          "method": "org.aspectj.ajdt.internal.core.builder.AjBuildManager.doBuild",
          "source": "AjBuild Manager.java:156"
        },
        {
          "method": "org.aspectj.ajdt.internal.core.builder.AjBuildManager.batchBuild",
          "source": "AjBu ildManager.java:70"
        },
        {
          "method": "org.aspectj.ajdt.ajc.AjdtCommand.doCommand",
          "source": "AjdtCommand.java:99"
        },
        {
          "method": "org.aspectj.ajdt.ajc.AjdtCommand.runCommand",
          "source": "AjdtCommand.java:53"
        },
        {
          "method": "org.aspectj.tools.ajc.Main.run",
          "source": "Main.java:217"
        },
        {
          "method": "org.aspectj.tools.ajc.Main.runMain",
          "source": "Main.java:155"
        },
        {
          "method": "org.aspectj.tools.ajc.Main.main",
          "source": "Main.java:72"
        }
      ],
      "number": 0,
      "commentIndex": 0,
      "bugId": "42842",
      "duplicateId": "49457",
      "date": "2003-09-10T02:07:13+02:00",
      "product": "AspectJ",
      "component": "Compiler",
      "severity": "minor"
    }
  ],
  "groupId": "49457",
  "bugId": "42842",
  "duplicateId": "49457",
  "date": "2003-09-10T02:07:13+02:00",
  "product": "AspectJ",
  "component": "Compiler",
  "severity": "minor"
}