{
  "comments": [
    "This must be caused by the fix to concretization...\n\nInput sources:\npackage base;\n\npublic abstract aspect ExceptionHandling {\n    public abstract pointcut scope();\n    declare soft: Exception: scope();\n}\n\npackage model;\n\nimport base.ExceptionHandling;\n\npublic aspect ModelExceptionHandling extends ExceptionHandling {\n    public pointcut scope() : within(*);\n\n    protected RuntimeException convertCheckedException(Throwable t) {\n        return new RuntimeException(t.getMessage(), t\n}\n\nCompiler output:\nC:\\eclipse\\workspace\\atrack\u003eajc -d debug @narrow.lst\njava.lang.NullPointerException\n        at org.aspectj.weaver.patterns.ReferencePointcut.concretize1\n(ReferencePo\nintcut.java:243)\n        at org.aspectj.weaver.patterns.Pointcut.concretize(Pointcut.java:127)\n        at org.aspectj.weaver.patterns.Pointcut.concretize(Pointcut.java:110)\n        at org.aspectj.weaver.CrosscuttingMembers.addDeclare\n(CrosscuttingMembers\n.java:111)\n        at org.aspectj.weaver.CrosscuttingMembers.addDeclares\n(CrosscuttingMember\ns.java:92)\n        at org.aspectj.weaver.ResolvedTypeX.collectCrosscuttingMembers\n(ResolvedT\nypeX.java:332)\n        at org.aspectj.weaver.CrosscuttingMembersSet.addOrReplaceAspect\n(Crosscut\ntingMembersSet.java:50)\n        at \norg.aspectj.ajdt.internal.compiler.ast.AspectDeclaration.buildInterTy\npeAndPerClause(AspectDeclaration.java:754)\n        at \norg.aspectj.ajdt.internal.compiler.lookup.AjLookupEnvironment.buildIn\nterTypeAndPerClause(AjLookupEnvironment.java:124)\n        at \norg.aspectj.ajdt.internal.compiler.lookup.AjLookupEnvironment.complet\neTypeBindings(AjLookupEnvironment.java:91)\n        at org.eclipse.jdt.internal.compiler.Compiler.beginToCompile\n(Compiler.ja\nva:310)\n        at org.eclipse.jdt.internal.compiler.Compiler.compile\n(Compiler.java:324)\n\n        at \norg.aspectj.ajdt.internal.core.builder.AjBuildManager.performCompilat\nion(AjBuildManager.java:373)\n        at org.aspectj.ajdt.internal.core.builder.AjBuildManager.doBuild\n(AjBuild\nManager.java:125)\n        at org.aspectj.ajdt.internal.core.builder.AjBuildManager.batchBuild\n(AjBu\nildManager.java:70)\n        at org.aspectj.ajdt.ajc.AjdtCommand.doCommand(AjdtCommand.java:99)\n        at org.aspectj.ajdt.ajc.AjdtCommand.runCommand(AjdtCommand.java:53)\n        at org.aspectj.tools.ajc.Main.run(Main.java:217)\n        at org.aspectj.tools.ajc.Main.runMain(Main.java:155)\n        at org.aspectj.tools.ajc.Main.main(Main.java:72)\nC:\\eclipse\\workspace\\atrack\\src\\org\\atrack\\model\\error\\impl\\ModelExceptionHandl\ni\nng.java:0 Internal compiler error\njava.lang.NullPointerException\n        at org.aspectj.weaver.patterns.ReferencePointcut.concretize1\n(ReferencePo\nintcut.java:243)\n        at org.aspectj.weaver.patterns.Pointcut.concretize(Pointcut.java:127)\n        at org.aspectj.weaver.patterns.Pointcut.concretize(Pointcut.java:110)\n        at org.aspectj.weaver.CrosscuttingMembers.addDeclare\n(CrosscuttingMembers\n.java:111)\n        at org.aspectj.weaver.CrosscuttingMembers.addDeclares\n(CrosscuttingMember\ns.java:92)\n        at org.aspectj.weaver.ResolvedTypeX.collectCrosscuttingMembers\n(ResolvedT\nypeX.java:332)\n        at org.aspectj.weaver.CrosscuttingMembersSet.addOrReplaceAspect\n(Crosscut\ntingMembersSet.java:50)\n        at \norg.aspectj.ajdt.internal.compiler.ast.AspectDeclaration.buildInterTy\npeAndPerClause(AspectDeclaration.java:754)\n        at \norg.aspectj.ajdt.internal.compiler.lookup.AjLookupEnvironment.buildIn\nterTypeAndPerClause(AjLookupEnvironment.java:124)\n        at \norg.aspectj.ajdt.internal.compiler.lookup.AjLookupEnvironment.complet\neTypeBindings(AjLookupEnvironment.java:91)\n        at org.eclipse.jdt.internal.compiler.Compiler.beginToCompile\n(Compiler.ja\nva:310)\n        at org.eclipse.jdt.internal.compiler.Compiler.compile\n(Compiler.java:324)\n\n        at \norg.aspectj.ajdt.internal.core.builder.AjBuildManager.performCompilat\nion(AjBuildManager.java:373)\n        at org.aspectj.ajdt.internal.core.builder.AjBuildManager.doBuild\n(AjBuild\nManager.java:125)\n        at org.aspectj.ajdt.internal.core.builder.AjBuildManager.batchBuild\n(AjBu\nildManager.java:70)\n        at org.aspectj.ajdt.ajc.AjdtCommand.doCommand(AjdtCommand.java:99)\n        at org.aspectj.ajdt.ajc.AjdtCommand.runCommand(AjdtCommand.java:53)\n        at org.aspectj.tools.ajc.Main.run(Main.java:217)\n        at org.aspectj.tools.ajc.Main.runMain(Main.java:155)\n        at org.aspectj.tools.ajc.Main.main(Main.java:72)\n\n\n!! no source information available !!\nC:\\eclipse\\workspace\\atrack\\src\\org\\atrack\\model\\error\\impl\\ModelExceptionHandl\ni\nng.java:23 Unmatched bracket\nreturn new RuntimeException(t.getMessage(), t\n                           ^\nABORT\nException thrown from AspectJ DEVELOPMENT\n\nThis might be logged as a bug already -- find current bugs at\n  http://bugs.eclipse.org/bugs/buglist.cgi?product\u003dAspectJ\u0026component\u003dCompiler\n\nBugs for exceptions thrown have titles File:line from the top stack,\ne.g., \"SomeFile.java:243\"\n\nIf you don\u0027t find the exception below in a bug, please add a new bug\nat http://bugs.eclipse.org/bugs/enter_bug.cgi?product\u003dAspectJ\nTo make the bug a priority, please include a test program\nthat can reproduce this exception.\nnull\njava.lang.NullPointerException\n        at org.aspectj.weaver.patterns.ReferencePointcut.concretize1\n(ReferencePo\nintcut.java:243)\n        at org.aspectj.weaver.patterns.Pointcut.concretize(Pointcut.java:127)\n        at org.aspectj.weaver.patterns.Pointcut.concretize(Pointcut.java:110)\n        at org.aspectj.weaver.CrosscuttingMembers.addDeclare\n(CrosscuttingMembers\n.java:111)\n        at org.aspectj.weaver.CrosscuttingMembers.addDeclares\n(CrosscuttingMember\ns.java:92)\n        at org.aspectj.weaver.ResolvedTypeX.collectCrosscuttingMembers\n(ResolvedT\nypeX.java:332)\n        at org.aspectj.weaver.CrosscuttingMembersSet.addOrReplaceAspect\n(Crosscut\ntingMembersSet.java:50)\n        at \norg.aspectj.ajdt.internal.compiler.ast.AspectDeclaration.buildInterTy\npeAndPerClause(AspectDeclaration.java:754)\n        at \norg.aspectj.ajdt.internal.compiler.lookup.AjLookupEnvironment.buildIn\nterTypeAndPerClause(AjLookupEnvironment.java:124)\n        at \norg.aspectj.ajdt.internal.compiler.lookup.AjLookupEnvironment.complet\neTypeBindings(AjLookupEnvironment.java:91)\n        at org.eclipse.jdt.internal.compiler.Compiler.beginToCompile\n(Compiler.ja\nva:310)\n        at org.eclipse.jdt.internal.compiler.Compiler.compile\n(Compiler.java:324)\n\n        at \norg.aspectj.ajdt.internal.core.builder.AjBuildManager.performCompilat\nion(AjBuildManager.java:373)\n        at org.aspectj.ajdt.internal.core.builder.AjBuildManager.doBuild\n(AjBuild\nManager.java:125)\n        at org.aspectj.ajdt.internal.core.builder.AjBuildManager.batchBuild\n(AjBu\nildManager.java:70)\n        at org.aspectj.ajdt.ajc.AjdtCommand.doCommand(AjdtCommand.java:99)\n        at org.aspectj.ajdt.ajc.AjdtCommand.runCommand(AjdtCommand.java:53)\n        at org.aspectj.tools.ajc.Main.run(Main.java:217)\n        at org.aspectj.tools.ajc.Main.runMain(Main.java:155)\n        at org.aspectj.tools.ajc.Main.main(Main.java:72)\n\n\n1 fail|abort, 2 errors\n\nC:\\eclipse\\workspace\\atrack\u003ecd \\devel\\test\\excHandling\\c1\n\nC:\\devel\\test\\excHandling\\c1\u003eajc base\\ExceptionHandling.java \nmodel\\ModelExceptio\nnHandling.java\njava.lang.NullPointerException\n        at org.aspectj.weaver.patterns.ReferencePointcut.concretize1\n(ReferencePo\nintcut.java:243)\n        at org.aspectj.weaver.patterns.Pointcut.concretize(Pointcut.java:127)\n        at org.aspectj.weaver.patterns.Pointcut.concretize(Pointcut.java:110)\n        at org.aspectj.weaver.CrosscuttingMembers.addDeclare\n(CrosscuttingMembers\n.java:111)\n        at org.aspectj.weaver.CrosscuttingMembers.addDeclares\n(CrosscuttingMember\ns.java:92)\n        at org.aspectj.weaver.ResolvedTypeX.collectCrosscuttingMembers\n(ResolvedT\nypeX.java:332)\n        at org.aspectj.weaver.CrosscuttingMembersSet.addOrReplaceAspect\n(Crosscut\ntingMembersSet.java:50)\n        at \norg.aspectj.ajdt.internal.compiler.ast.AspectDeclaration.buildInterTy\npeAndPerClause(AspectDeclaration.java:754)\n        at \norg.aspectj.ajdt.internal.compiler.lookup.AjLookupEnvironment.buildIn\nterTypeAndPerClause(AjLookupEnvironment.java:124)\n        at \norg.aspectj.ajdt.internal.compiler.lookup.AjLookupEnvironment.complet\neTypeBindings(AjLookupEnvironment.java:91)\n        at org.eclipse.jdt.internal.compiler.Compiler.beginToCompile\n(Compiler.ja\nva:310)\n        at org.eclipse.jdt.internal.compiler.Compiler.compile\n(Compiler.java:324)\n\n        at \norg.aspectj.ajdt.internal.core.builder.AjBuildManager.performCompilat\nion(AjBuildManager.java:373)\n        at org.aspectj.ajdt.internal.core.builder.AjBuildManager.doBuild\n(AjBuild\nManager.java:125)\n        at org.aspectj.ajdt.internal.core.builder.AjBuildManager.batchBuild\n(AjBu\nildManager.java:70)\n        at org.aspectj.ajdt.ajc.AjdtCommand.doCommand(AjdtCommand.java:99)\n        at org.aspectj.ajdt.ajc.AjdtCommand.runCommand(AjdtCommand.java:53)\n        at org.aspectj.tools.ajc.Main.run(Main.java:217)\n        at org.aspectj.tools.ajc.Main.runMain(Main.java:155)\n        at org.aspectj.tools.ajc.Main.main(Main.java:72)\nC:\\devel\\test\\excHandling\\c1\\model\\ModelExceptionHandling.java:0 Internal \ncompil\ner error\njava.lang.NullPointerException\n        at org.aspectj.weaver.patterns.ReferencePointcut.concretize1\n(ReferencePo\nintcut.java:243)\n        at org.aspectj.weaver.patterns.Pointcut.concretize(Pointcut.java:127)\n        at org.aspectj.weaver.patterns.Pointcut.concretize(Pointcut.java:110)\n        at org.aspectj.weaver.CrosscuttingMembers.addDeclare\n(CrosscuttingMembers\n.java:111)\n        at org.aspectj.weaver.CrosscuttingMembers.addDeclares\n(CrosscuttingMember\ns.java:92)\n        at org.aspectj.weaver.ResolvedTypeX.collectCrosscuttingMembers\n(ResolvedT\nypeX.java:332)\n        at org.aspectj.weaver.CrosscuttingMembersSet.addOrReplaceAspect\n(Crosscut\ntingMembersSet.java:50)\n        at \norg.aspectj.ajdt.internal.compiler.ast.AspectDeclaration.buildInterTy\npeAndPerClause(AspectDeclaration.java:754)\n        at \norg.aspectj.ajdt.internal.compiler.lookup.AjLookupEnvironment.buildIn\nterTypeAndPerClause(AjLookupEnvironment.java:124)\n        at \norg.aspectj.ajdt.internal.compiler.lookup.AjLookupEnvironment.complet\neTypeBindings(AjLookupEnvironment.java:91)\n        at org.eclipse.jdt.internal.compiler.Compiler.beginToCompile\n(Compiler.ja\nva:310)\n        at org.eclipse.jdt.internal.compiler.Compiler.compile\n(Compiler.java:324)\n\n        at \norg.aspectj.ajdt.internal.core.builder.AjBuildManager.performCompilat\nion(AjBuildManager.java:373)\n        at org.aspectj.ajdt.internal.core.builder.AjBuildManager.doBuild\n(AjBuild\nManager.java:125)\n        at org.aspectj.ajdt.internal.core.builder.AjBuildManager.batchBuild\n(AjBu\nildManager.java:70)\n        at org.aspectj.ajdt.ajc.AjdtCommand.doCommand(AjdtCommand.java:99)\n        at org.aspectj.ajdt.ajc.AjdtCommand.runCommand(AjdtCommand.java:53)\n        at org.aspectj.tools.ajc.Main.run(Main.java:217)\n        at org.aspectj.tools.ajc.Main.runMain(Main.java:155)\n        at org.aspectj.tools.ajc.Main.main(Main.java:72)\n\n\n!! no source information available !!\nC:\\devel\\test\\excHandling\\c1\\model\\ModelExceptionHandling.java:9 Unmatched \nbrack\net\nreturn new RuntimeException(t.getMessage(), t\n                           ^\nABORT\nException thrown from AspectJ DEVELOPMENT\n\nThis might be logged as a bug already -- find current bugs at\n  http://bugs.eclipse.org/bugs/buglist.cgi?product\u003dAspectJ\u0026component\u003dCompiler\n\nBugs for exceptions thrown have titles File:line from the top stack,\ne.g., \"SomeFile.java:243\"\n\nIf you don\u0027t find the exception below in a bug, please add a new bug\nat http://bugs.eclipse.org/bugs/enter_bug.cgi?product\u003dAspectJ\nTo make the bug a priority, please include a test program\nthat can reproduce this exception.\nnull\njava.lang.NullPointerException\n        at org.aspectj.weaver.patterns.ReferencePointcut.concretize1\n(ReferencePo\nintcut.java:243)\n        at org.aspectj.weaver.patterns.Pointcut.concretize(Pointcut.java:127)\n        at org.aspectj.weaver.patterns.Pointcut.concretize(Pointcut.java:110)\n        at org.aspectj.weaver.CrosscuttingMembers.addDeclare\n(CrosscuttingMembers\n.java:111)\n        at org.aspectj.weaver.CrosscuttingMembers.addDeclares\n(CrosscuttingMember\ns.java:92)\n        at org.aspectj.weaver.ResolvedTypeX.collectCrosscuttingMembers\n(ResolvedT\nypeX.java:332)\n        at org.aspectj.weaver.CrosscuttingMembersSet.addOrReplaceAspect\n(Crosscut\ntingMembersSet.java:50)\n        at \norg.aspectj.ajdt.internal.compiler.ast.AspectDeclaration.buildInterTy\npeAndPerClause(AspectDeclaration.java:754)\n        at \norg.aspectj.ajdt.internal.compiler.lookup.AjLookupEnvironment.buildIn\nterTypeAndPerClause(AjLookupEnvironment.java:124)\n        at \norg.aspectj.ajdt.internal.compiler.lookup.AjLookupEnvironment.complet\neTypeBindings(AjLookupEnvironment.java:91)\n        at org.eclipse.jdt.internal.compiler.Compiler.beginToCompile\n(Compiler.ja\nva:310)\n        at org.eclipse.jdt.internal.compiler.Compiler.compile\n(Compiler.java:324)\n\n        at \norg.aspectj.ajdt.internal.core.builder.AjBuildManager.performCompilat\nion(AjBuildManager.java:373)\n        at org.aspectj.ajdt.internal.core.builder.AjBuildManager.doBuild\n(AjBuild\nManager.java:125)\n        at org.aspectj.ajdt.internal.core.builder.AjBuildManager.batchBuild\n(AjBu\nildManager.java:70)\n        at org.aspectj.ajdt.ajc.AjdtCommand.doCommand(AjdtCommand.java:99)\n        at org.aspectj.ajdt.ajc.AjdtCommand.runCommand(AjdtCommand.java:53)\n        at org.aspectj.tools.ajc.Main.run(Main.java:217)\n        at org.aspectj.tools.ajc.Main.runMain(Main.java:155)\n        at org.aspectj.tools.ajc.Main.main(Main.java:72)\n\n\n1 fail|abort, 2 errors",
    "Created an attachment (id\u003d6145)\nMinor fix to avoid the NPE\n",
    "Andy seems to be on top of this one.",
    "I\u0027ve sent the test suite changes direct to Adrian to integrate.  They consist \nof the programs Ron provided.\n\n- Andy.",
    "Fixed by patch and test cases contributed by Andy Clement."
  ],
  "commentCreationDates": [
    "2003-09-12T19:34:02+02:00",
    "2003-09-18T17:59:39+02:00",
    "2003-09-18T18:34:21+02:00",
    "2003-09-18T22:53:10+02:00",
    "2003-09-19T09:48:06+02:00"
  ],
  "traces": [
    {
      "exceptionType": "java.lang.NullPointerException",
      "elements": [
        {
          "method": "org.aspectj.weaver.patterns.ReferencePointcut.concretize1",
          "source": "ReferencePo intcut.java:243"
        },
        {
          "method": "org.aspectj.weaver.patterns.Pointcut.concretize",
          "source": "Pointcut.java:127"
        },
        {
          "method": "org.aspectj.weaver.patterns.Pointcut.concretize",
          "source": "Pointcut.java:110"
        },
        {
          "method": "org.aspectj.weaver.CrosscuttingMembers.addDeclare",
          "source": "CrosscuttingMembers .java:111"
        },
        {
          "method": "org.aspectj.weaver.CrosscuttingMembers.addDeclares",
          "source": "CrosscuttingMember s.java:92"
        },
        {
          "method": "org.aspectj.weaver.ResolvedTypeX.collectCrosscuttingMembers",
          "source": "ResolvedT ypeX.java:332"
        },
        {
          "method": "org.aspectj.weaver.CrosscuttingMembersSet.addOrReplaceAspect",
          "source": "Crosscut tingMembersSet.java:50"
        },
        {
          "method": "org.aspectj.ajdt.internal.compiler.ast.AspectDeclaration.buildInterTypeAndPerClause",
          "source": "AspectDeclaration.java:754"
        },
        {
          "method": "org.aspectj.ajdt.internal.compiler.lookup.AjLookupEnvironment.buildInterTypeAndPerClause",
          "source": "AjLookupEnvironment.java:124"
        },
        {
          "method": "org.aspectj.ajdt.internal.compiler.lookup.AjLookupEnvironment.completeTypeBindings",
          "source": "AjLookupEnvironment.java:91"
        },
        {
          "method": "org.eclipse.jdt.internal.compiler.Compiler.beginToCompile",
          "source": "Compiler.ja va:310"
        },
        {
          "method": "org.eclipse.jdt.internal.compiler.Compiler.compile",
          "source": "Compiler.java:324"
        },
        {
          "method": "org.aspectj.ajdt.internal.core.builder.AjBuildManager.performCompilation",
          "source": "AjBuildManager.java:373"
        },
        {
          "method": "org.aspectj.ajdt.internal.core.builder.AjBuildManager.doBuild",
          "source": "AjBuild Manager.java:125"
        },
        {
          "method": "org.aspectj.ajdt.internal.core.builder.AjBuildManager.batchBuild",
          "source": "AjBu ildManager.java:70"
        },
        {
          "method": "org.aspectj.ajdt.ajc.AjdtCommand.doCommand",
          "source": "AjdtCommand.java:99"
        },
        {
          "method": "org.aspectj.ajdt.ajc.AjdtCommand.runCommand",
          "source": "AjdtCommand.java:53"
        },
        {
          "method": "org.aspectj.tools.ajc.Main.run",
          "source": "Main.java:217"
        },
        {
          "method": "org.aspectj.tools.ajc.Main.runMain",
          "source": "Main.java:155"
        },
        {
          "method": "org.aspectj.tools.ajc.Main.main",
          "source": "Main.java:72"
        }
      ],
      "number": 0,
      "commentIndex": 0,
      "bugId": "43033",
      "date": "2003-09-12T19:34:02+02:00",
      "product": "AspectJ",
      "component": "Compiler",
      "severity": "normal"
    },
    {
      "exceptionType": "java.lang.NullPointerException",
      "elements": [
        {
          "method": "org.aspectj.weaver.patterns.ReferencePointcut.concretize1",
          "source": "ReferencePo intcut.java:243"
        },
        {
          "method": "org.aspectj.weaver.patterns.Pointcut.concretize",
          "source": "Pointcut.java:127"
        },
        {
          "method": "org.aspectj.weaver.patterns.Pointcut.concretize",
          "source": "Pointcut.java:110"
        },
        {
          "method": "org.aspectj.weaver.CrosscuttingMembers.addDeclare",
          "source": "CrosscuttingMembers .java:111"
        },
        {
          "method": "org.aspectj.weaver.CrosscuttingMembers.addDeclares",
          "source": "CrosscuttingMember s.java:92"
        },
        {
          "method": "org.aspectj.weaver.ResolvedTypeX.collectCrosscuttingMembers",
          "source": "ResolvedT ypeX.java:332"
        },
        {
          "method": "org.aspectj.weaver.CrosscuttingMembersSet.addOrReplaceAspect",
          "source": "Crosscut tingMembersSet.java:50"
        },
        {
          "method": "org.aspectj.ajdt.internal.compiler.ast.AspectDeclaration.buildInterTypeAndPerClause",
          "source": "AspectDeclaration.java:754"
        },
        {
          "method": "org.aspectj.ajdt.internal.compiler.lookup.AjLookupEnvironment.buildInterTypeAndPerClause",
          "source": "AjLookupEnvironment.java:124"
        },
        {
          "method": "org.aspectj.ajdt.internal.compiler.lookup.AjLookupEnvironment.completeTypeBindings",
          "source": "AjLookupEnvironment.java:91"
        },
        {
          "method": "org.eclipse.jdt.internal.compiler.Compiler.beginToCompile",
          "source": "Compiler.ja va:310"
        },
        {
          "method": "org.eclipse.jdt.internal.compiler.Compiler.compile",
          "source": "Compiler.java:324"
        },
        {
          "method": "org.aspectj.ajdt.internal.core.builder.AjBuildManager.performCompilation",
          "source": "AjBuildManager.java:373"
        },
        {
          "method": "org.aspectj.ajdt.internal.core.builder.AjBuildManager.doBuild",
          "source": "AjBuild Manager.java:125"
        },
        {
          "method": "org.aspectj.ajdt.internal.core.builder.AjBuildManager.batchBuild",
          "source": "AjBu ildManager.java:70"
        },
        {
          "method": "org.aspectj.ajdt.ajc.AjdtCommand.doCommand",
          "source": "AjdtCommand.java:99"
        },
        {
          "method": "org.aspectj.ajdt.ajc.AjdtCommand.runCommand",
          "source": "AjdtCommand.java:53"
        },
        {
          "method": "org.aspectj.tools.ajc.Main.run",
          "source": "Main.java:217"
        },
        {
          "method": "org.aspectj.tools.ajc.Main.runMain",
          "source": "Main.java:155"
        },
        {
          "method": "org.aspectj.tools.ajc.Main.main",
          "source": "Main.java:72"
        }
      ],
      "number": 1,
      "commentIndex": 0,
      "bugId": "43033",
      "date": "2003-09-12T19:34:02+02:00",
      "product": "AspectJ",
      "component": "Compiler",
      "severity": "normal"
    },
    {
      "exceptionType": "java.lang.NullPointerException",
      "elements": [
        {
          "method": "org.aspectj.weaver.patterns.ReferencePointcut.concretize1",
          "source": "ReferencePo intcut.java:243"
        },
        {
          "method": "org.aspectj.weaver.patterns.Pointcut.concretize",
          "source": "Pointcut.java:127"
        },
        {
          "method": "org.aspectj.weaver.patterns.Pointcut.concretize",
          "source": "Pointcut.java:110"
        },
        {
          "method": "org.aspectj.weaver.CrosscuttingMembers.addDeclare",
          "source": "CrosscuttingMembers .java:111"
        },
        {
          "method": "org.aspectj.weaver.CrosscuttingMembers.addDeclares",
          "source": "CrosscuttingMember s.java:92"
        },
        {
          "method": "org.aspectj.weaver.ResolvedTypeX.collectCrosscuttingMembers",
          "source": "ResolvedT ypeX.java:332"
        },
        {
          "method": "org.aspectj.weaver.CrosscuttingMembersSet.addOrReplaceAspect",
          "source": "Crosscut tingMembersSet.java:50"
        },
        {
          "method": "org.aspectj.ajdt.internal.compiler.ast.AspectDeclaration.buildInterTypeAndPerClause",
          "source": "AspectDeclaration.java:754"
        },
        {
          "method": "org.aspectj.ajdt.internal.compiler.lookup.AjLookupEnvironment.buildInterTypeAndPerClause",
          "source": "AjLookupEnvironment.java:124"
        },
        {
          "method": "org.aspectj.ajdt.internal.compiler.lookup.AjLookupEnvironment.completeTypeBindings",
          "source": "AjLookupEnvironment.java:91"
        },
        {
          "method": "org.eclipse.jdt.internal.compiler.Compiler.beginToCompile",
          "source": "Compiler.ja va:310"
        },
        {
          "method": "org.eclipse.jdt.internal.compiler.Compiler.compile",
          "source": "Compiler.java:324"
        },
        {
          "method": "org.aspectj.ajdt.internal.core.builder.AjBuildManager.performCompilation",
          "source": "AjBuildManager.java:373"
        },
        {
          "method": "org.aspectj.ajdt.internal.core.builder.AjBuildManager.doBuild",
          "source": "AjBuild Manager.java:125"
        },
        {
          "method": "org.aspectj.ajdt.internal.core.builder.AjBuildManager.batchBuild",
          "source": "AjBu ildManager.java:70"
        },
        {
          "method": "org.aspectj.ajdt.ajc.AjdtCommand.doCommand",
          "source": "AjdtCommand.java:99"
        },
        {
          "method": "org.aspectj.ajdt.ajc.AjdtCommand.runCommand",
          "source": "AjdtCommand.java:53"
        },
        {
          "method": "org.aspectj.tools.ajc.Main.run",
          "source": "Main.java:217"
        },
        {
          "method": "org.aspectj.tools.ajc.Main.runMain",
          "source": "Main.java:155"
        },
        {
          "method": "org.aspectj.tools.ajc.Main.main",
          "source": "Main.java:72"
        }
      ],
      "number": 2,
      "commentIndex": 0,
      "bugId": "43033",
      "date": "2003-09-12T19:34:02+02:00",
      "product": "AspectJ",
      "component": "Compiler",
      "severity": "normal"
    },
    {
      "exceptionType": "java.lang.NullPointerException",
      "elements": [
        {
          "method": "org.aspectj.weaver.patterns.ReferencePointcut.concretize1",
          "source": "ReferencePo intcut.java:243"
        },
        {
          "method": "org.aspectj.weaver.patterns.Pointcut.concretize",
          "source": "Pointcut.java:127"
        },
        {
          "method": "org.aspectj.weaver.patterns.Pointcut.concretize",
          "source": "Pointcut.java:110"
        },
        {
          "method": "org.aspectj.weaver.CrosscuttingMembers.addDeclare",
          "source": "CrosscuttingMembers .java:111"
        },
        {
          "method": "org.aspectj.weaver.CrosscuttingMembers.addDeclares",
          "source": "CrosscuttingMember s.java:92"
        },
        {
          "method": "org.aspectj.weaver.ResolvedTypeX.collectCrosscuttingMembers",
          "source": "ResolvedT ypeX.java:332"
        },
        {
          "method": "org.aspectj.weaver.CrosscuttingMembersSet.addOrReplaceAspect",
          "source": "Crosscut tingMembersSet.java:50"
        },
        {
          "method": "org.aspectj.ajdt.internal.compiler.ast.AspectDeclaration.buildInterTypeAndPerClause",
          "source": "AspectDeclaration.java:754"
        },
        {
          "method": "org.aspectj.ajdt.internal.compiler.lookup.AjLookupEnvironment.buildInterTypeAndPerClause",
          "source": "AjLookupEnvironment.java:124"
        },
        {
          "method": "org.aspectj.ajdt.internal.compiler.lookup.AjLookupEnvironment.completeTypeBindings",
          "source": "AjLookupEnvironment.java:91"
        },
        {
          "method": "org.eclipse.jdt.internal.compiler.Compiler.beginToCompile",
          "source": "Compiler.ja va:310"
        },
        {
          "method": "org.eclipse.jdt.internal.compiler.Compiler.compile",
          "source": "Compiler.java:324"
        },
        {
          "method": "org.aspectj.ajdt.internal.core.builder.AjBuildManager.performCompilation",
          "source": "AjBuildManager.java:373"
        },
        {
          "method": "org.aspectj.ajdt.internal.core.builder.AjBuildManager.doBuild",
          "source": "AjBuild Manager.java:125"
        },
        {
          "method": "org.aspectj.ajdt.internal.core.builder.AjBuildManager.batchBuild",
          "source": "AjBu ildManager.java:70"
        },
        {
          "method": "org.aspectj.ajdt.ajc.AjdtCommand.doCommand",
          "source": "AjdtCommand.java:99"
        },
        {
          "method": "org.aspectj.ajdt.ajc.AjdtCommand.runCommand",
          "source": "AjdtCommand.java:53"
        },
        {
          "method": "org.aspectj.tools.ajc.Main.run",
          "source": "Main.java:217"
        },
        {
          "method": "org.aspectj.tools.ajc.Main.runMain",
          "source": "Main.java:155"
        },
        {
          "method": "org.aspectj.tools.ajc.Main.main",
          "source": "Main.java:72"
        }
      ],
      "number": 3,
      "commentIndex": 0,
      "bugId": "43033",
      "date": "2003-09-12T19:34:02+02:00",
      "product": "AspectJ",
      "component": "Compiler",
      "severity": "normal"
    },
    {
      "exceptionType": "java.lang.NullPointerException",
      "elements": [
        {
          "method": "org.aspectj.weaver.patterns.ReferencePointcut.concretize1",
          "source": "ReferencePo intcut.java:243"
        },
        {
          "method": "org.aspectj.weaver.patterns.Pointcut.concretize",
          "source": "Pointcut.java:127"
        },
        {
          "method": "org.aspectj.weaver.patterns.Pointcut.concretize",
          "source": "Pointcut.java:110"
        },
        {
          "method": "org.aspectj.weaver.CrosscuttingMembers.addDeclare",
          "source": "CrosscuttingMembers .java:111"
        },
        {
          "method": "org.aspectj.weaver.CrosscuttingMembers.addDeclares",
          "source": "CrosscuttingMember s.java:92"
        },
        {
          "method": "org.aspectj.weaver.ResolvedTypeX.collectCrosscuttingMembers",
          "source": "ResolvedT ypeX.java:332"
        },
        {
          "method": "org.aspectj.weaver.CrosscuttingMembersSet.addOrReplaceAspect",
          "source": "Crosscut tingMembersSet.java:50"
        },
        {
          "method": "org.aspectj.ajdt.internal.compiler.ast.AspectDeclaration.buildInterTypeAndPerClause",
          "source": "AspectDeclaration.java:754"
        },
        {
          "method": "org.aspectj.ajdt.internal.compiler.lookup.AjLookupEnvironment.buildInterTypeAndPerClause",
          "source": "AjLookupEnvironment.java:124"
        },
        {
          "method": "org.aspectj.ajdt.internal.compiler.lookup.AjLookupEnvironment.completeTypeBindings",
          "source": "AjLookupEnvironment.java:91"
        },
        {
          "method": "org.eclipse.jdt.internal.compiler.Compiler.beginToCompile",
          "source": "Compiler.ja va:310"
        },
        {
          "method": "org.eclipse.jdt.internal.compiler.Compiler.compile",
          "source": "Compiler.java:324"
        },
        {
          "method": "org.aspectj.ajdt.internal.core.builder.AjBuildManager.performCompilation",
          "source": "AjBuildManager.java:373"
        },
        {
          "method": "org.aspectj.ajdt.internal.core.builder.AjBuildManager.doBuild",
          "source": "AjBuild Manager.java:125"
        },
        {
          "method": "org.aspectj.ajdt.internal.core.builder.AjBuildManager.batchBuild",
          "source": "AjBu ildManager.java:70"
        },
        {
          "method": "org.aspectj.ajdt.ajc.AjdtCommand.doCommand",
          "source": "AjdtCommand.java:99"
        },
        {
          "method": "org.aspectj.ajdt.ajc.AjdtCommand.runCommand",
          "source": "AjdtCommand.java:53"
        },
        {
          "method": "org.aspectj.tools.ajc.Main.run",
          "source": "Main.java:217"
        },
        {
          "method": "org.aspectj.tools.ajc.Main.runMain",
          "source": "Main.java:155"
        },
        {
          "method": "org.aspectj.tools.ajc.Main.main",
          "source": "Main.java:72"
        }
      ],
      "number": 4,
      "commentIndex": 0,
      "bugId": "43033",
      "date": "2003-09-12T19:34:02+02:00",
      "product": "AspectJ",
      "component": "Compiler",
      "severity": "normal"
    },
    {
      "exceptionType": "java.lang.NullPointerException",
      "elements": [
        {
          "method": "org.aspectj.weaver.patterns.ReferencePointcut.concretize1",
          "source": "ReferencePo intcut.java:243"
        },
        {
          "method": "org.aspectj.weaver.patterns.Pointcut.concretize",
          "source": "Pointcut.java:127"
        },
        {
          "method": "org.aspectj.weaver.patterns.Pointcut.concretize",
          "source": "Pointcut.java:110"
        },
        {
          "method": "org.aspectj.weaver.CrosscuttingMembers.addDeclare",
          "source": "CrosscuttingMembers .java:111"
        },
        {
          "method": "org.aspectj.weaver.CrosscuttingMembers.addDeclares",
          "source": "CrosscuttingMember s.java:92"
        },
        {
          "method": "org.aspectj.weaver.ResolvedTypeX.collectCrosscuttingMembers",
          "source": "ResolvedT ypeX.java:332"
        },
        {
          "method": "org.aspectj.weaver.CrosscuttingMembersSet.addOrReplaceAspect",
          "source": "Crosscut tingMembersSet.java:50"
        },
        {
          "method": "org.aspectj.ajdt.internal.compiler.ast.AspectDeclaration.buildInterTypeAndPerClause",
          "source": "AspectDeclaration.java:754"
        },
        {
          "method": "org.aspectj.ajdt.internal.compiler.lookup.AjLookupEnvironment.buildInterTypeAndPerClause",
          "source": "AjLookupEnvironment.java:124"
        },
        {
          "method": "org.aspectj.ajdt.internal.compiler.lookup.AjLookupEnvironment.completeTypeBindings",
          "source": "AjLookupEnvironment.java:91"
        },
        {
          "method": "org.eclipse.jdt.internal.compiler.Compiler.beginToCompile",
          "source": "Compiler.ja va:310"
        },
        {
          "method": "org.eclipse.jdt.internal.compiler.Compiler.compile",
          "source": "Compiler.java:324"
        },
        {
          "method": "org.aspectj.ajdt.internal.core.builder.AjBuildManager.performCompilation",
          "source": "AjBuildManager.java:373"
        },
        {
          "method": "org.aspectj.ajdt.internal.core.builder.AjBuildManager.doBuild",
          "source": "AjBuild Manager.java:125"
        },
        {
          "method": "org.aspectj.ajdt.internal.core.builder.AjBuildManager.batchBuild",
          "source": "AjBu ildManager.java:70"
        },
        {
          "method": "org.aspectj.ajdt.ajc.AjdtCommand.doCommand",
          "source": "AjdtCommand.java:99"
        },
        {
          "method": "org.aspectj.ajdt.ajc.AjdtCommand.runCommand",
          "source": "AjdtCommand.java:53"
        },
        {
          "method": "org.aspectj.tools.ajc.Main.run",
          "source": "Main.java:217"
        },
        {
          "method": "org.aspectj.tools.ajc.Main.runMain",
          "source": "Main.java:155"
        },
        {
          "method": "org.aspectj.tools.ajc.Main.main",
          "source": "Main.java:72"
        }
      ],
      "number": 5,
      "commentIndex": 0,
      "bugId": "43033",
      "date": "2003-09-12T19:34:02+02:00",
      "product": "AspectJ",
      "component": "Compiler",
      "severity": "normal"
    }
  ],
  "groupId": "43033",
  "bugId": "43033",
  "date": "2003-09-12T19:34:02+02:00",
  "product": "AspectJ",
  "component": "Compiler",
  "severity": "normal"
}