{
  "comments": [
    "OSX 10.2.6\nEclipse I20030916\n\nDoing a surround with try catch:\n\n!ENTRY org.eclipse.jdt.ui 4 10004 Sep 16, 2003 15:13:55.722\n!MESSAGE Unrecoverable error occurred while performing the refactoring.\n!STACK 0\nChangeAbortException: org.eclipse.jdt.internal.corext.refactoring.base.ChangeAbortException\n        at \norg.eclipse.jdt.internal.ui.refactoring.changes.AbortChangeExceptionHandler.handle(AbortChangeExcept\nionHandler.java:28)\n        at org.eclipse.jdt.internal.corext.refactoring.base.Change.handleException(Change.java:108)\n        at \norg.eclipse.jdt.internal.corext.refactoring.changes.AbstractTextChange.perform(AbstractTextChange.jav\na:201)\n        at \norg.eclipse.jdt.internal.corext.refactoring.changes.TextFileChange.perform(TextFileChange.java:208)\n        at \norg.eclipse.jdt.internal.ui.refactoring.PerformChangeOperation$1.run(PerformChangeOperation.java:173\n)\n        at org.eclipse.jdt.internal.core.BatchOperation.executeOperation(BatchOperation.java:34)\n        at org.eclipse.jdt.internal.core.JavaModelOperation.execute(JavaModelOperation.java:366)\n        at org.eclipse.jdt.internal.core.JavaModelOperation.run(JavaModelOperation.java:705)\n        at org.eclipse.core.internal.resources.Workspace.run(Workspace.java:1571)\n        at org.eclipse.core.internal.resources.Workspace.run(Workspace.java:1588)\n        at org.eclipse.jdt.core.JavaCore.run(JavaCore.java:2963)\n        at \norg.eclipse.jdt.internal.ui.refactoring.PerformChangeOperation.executeChange(PerformChangeOperation\n.java:183)\n        at \norg.eclipse.jdt.internal.ui.refactoring.PerformChangeOperation.run(PerformChangeOperation.java:151)\n        at \norg.eclipse.jdt.internal.ui.util.BusyIndicatorRunnableContext$BusyRunnable.internalRun(BusyIndicatorRu\nnnableContext.java:113)\n        at \norg.eclipse.jdt.internal.ui.util.BusyIndicatorRunnableContext$BusyRunnable.run(BusyIndicatorRunnableC\nontext.java:80)\n        at org.eclipse.swt.custom.BusyIndicator.showWhile(BusyIndicator.java:84)\n        at \norg.eclipse.jdt.internal.ui.util.BusyIndicatorRunnableContext.run(BusyIndicatorRunnableContext.java:126\n)\n        at \norg.eclipse.jdt.ui.actions.SurroundWithTryCatchAction.run(SurroundWithTryCatchAction.java:127)\n        at org.eclipse.jdt.ui.actions.SelectionDispatchAction.dispatchRun(SelectionDispatchAction.java:196)\n        at org.eclipse.jdt.ui.actions.SelectionDispatchAction.run(SelectionDispatchAction.java:172)\n        at org.eclipse.jface.action.Action.runWithEvent(Action.java:842)\n        at \norg.eclipse.jface.action.ActionContributionItem.handleWidgetSelection(ActionContributionItem.java:529)\n        at org.eclipse.jface.action.ActionContributionItem.access$4(ActionContributionItem.java:482)\n        at org.eclipse.jface.action.ActionContributionItem$6.handleEvent(ActionContributionItem.java:454)\n        at org.eclipse.swt.widgets.EventTable.sendEvent(EventTable.java:82)\n        at org.eclipse.swt.widgets.Widget.notifyListeners(Widget.java:1027)\n        at org.eclipse.swt.widgets.Display.runDeferredEvents(Display.java:2180)\n        at org.eclipse.swt.widgets.Display.readAndDispatch(Display.java:1878)\n        at org.eclipse.ui.internal.Workbench.runEventLoop(Workbench.java:2037)\n        at org.eclipse.ui.internal.Workbench.run(Workbench.java:2020)\n        at org.eclipse.core.internal.boot.InternalBootLoader.run(InternalBootLoader.java:858)\n        at org.eclipse.core.boot.BootLoader.run(BootLoader.java:461)\n        at sun.reflect.NativeMethodAccessorImpl.invoke0(Native Method)\n        at sun.reflect.NativeMethodAccessorImpl.invoke(NativeMethodAccessorImpl.java:39)\n        at sun.reflect.DelegatingMethodAccessorImpl.invoke(DelegatingMethodAccessorImpl.java:25)\n        at java.lang.reflect.Method.invoke(Method.java:324)\n        at org.eclipse.core.launcher.Main.basicRun(Main.java:295)\n        at org.eclipse.core.launcher.Main.run(Main.java:751)\n        at org.eclipse.core.launcher.Main.main(Main.java:587)\nException wrapped by ChangeAbortException: org.eclipse.jface.text.Assert$AssertionFailedException: \nAssertion failed: \n        at org.eclipse.jface.text.Assert.isTrue(Assert.java:175)\n        at org.eclipse.jface.text.Assert.isTrue(Assert.java:160)\n        at \norg.eclipse.jdt.internal.ui.text.link.LinkedPositionManager.getPositions(LinkedPositionManager.java:427)\n        at \norg.eclipse.jdt.internal.ui.text.link.LinkedPositionManager.documentAboutToBeChanged(LinkedPosition\nManager.java:477)\n        at \norg.eclipse.jface.text.AbstractDocument.fireDocumentAboutToBeChanged(AbstractDocument.java:549)\n        at org.eclipse.jface.text.AbstractDocument.replace(AbstractDocument.java:956)\n        at \norg.eclipse.jdt.internal.ui.javaeditor.PartiallySynchronizedDocument.replace(PartiallySynchronizedDocum\nent.java:61)\n        at org.eclipse.jdt.internal.corext.textmanipulation.TextEdit.performReplace(TextEdit.java:401)\n        at org.eclipse.jdt.internal.corext.textmanipulation.SimpleTextEdit.perform(SimpleTextEdit.java:80)\n        at org.eclipse.jdt.internal.corext.textmanipulation.EditProcessor.execute(EditProcessor.java:183)\n        at org.eclipse.jdt.internal.corext.textmanipulation.EditProcessor.execute(EditProcessor.java:178)\n        at org.eclipse.jdt.internal.corext.textmanipulation.EditProcessor.execute(EditProcessor.java:178)\n        at org.eclipse.jdt.internal.corext.textmanipulation.EditProcessor.execute(EditProcessor.java:178)\n        at org.eclipse.jdt.internal.corext.textmanipulation.EditProcessor.executeDo(EditProcessor.java:163)\n        at \norg.eclipse.jdt.internal.corext.textmanipulation.EditProcessor.performEdits(EditProcessor.java:121)\n        at \norg.eclipse.jdt.internal.corext.textmanipulation.TextBufferEditor.performEdits(TextBufferEditor.java:55)\n        at \norg.eclipse.jdt.internal.corext.refactoring.changes.AbstractTextChange.perform(AbstractTextChange.jav\na:199)\n        at \norg.eclipse.jdt.internal.corext.refactoring.changes.TextFileChange.perform(TextFileChange.java:208)\n        at \norg.eclipse.jdt.internal.ui.refactoring.PerformChangeOperation$1.run(PerformChangeOperation.java:173\n)\n        at org.eclipse.jdt.internal.core.BatchOperation.executeOperation(BatchOperation.java:34)\n        at org.eclipse.jdt.internal.core.JavaModelOperation.execute(JavaModelOperation.java:366)\n        at org.eclipse.jdt.internal.core.JavaModelOperation.run(JavaModelOperation.java:705)\n        at org.eclipse.core.internal.resources.Workspace.run(Workspace.java:1571)\n        at org.eclipse.core.internal.resources.Workspace.run(Workspace.java:1588)\n        at org.eclipse.jdt.core.JavaCore.run(JavaCore.java:2963)\n        at \norg.eclipse.jdt.internal.ui.refactoring.PerformChangeOperation.executeChange(PerformChangeOperation\n.java:183)\n        at \norg.eclipse.jdt.internal.ui.refactoring.PerformChangeOperation.run(PerformChangeOperation.java:151)\n        at \norg.eclipse.jdt.internal.ui.util.BusyIndicatorRunnableContext$BusyRunnable.internalRun(BusyIndicatorRu\nnnableContext.java:113)\n        at \norg.eclipse.jdt.internal.ui.util.BusyIndicatorRunnableContext$BusyRunnable.run(BusyIndicatorRunnableC\nontext.java:80)\n        at org.eclipse.swt.custom.BusyIndicator.showWhile(BusyIndicator.java:84)\n        at \norg.eclipse.jdt.internal.ui.util.BusyIndicatorRunnableContext.run(BusyIndicatorRunnableContext.java:126\n)\n        at \norg.eclipse.jdt.ui.actions.SurroundWithTryCatchAction.run(SurroundWithTryCatchAction.java:127)\n        at org.eclipse.jdt.ui.actions.SelectionDispatchAction.dispatchRun(SelectionDispatchAction.java:196)\n        at org.eclipse.jdt.ui.actions.SelectionDispatchAction.run(SelectionDispatchAction.java:172)\n        at org.eclipse.jface.action.Action.runWithEvent(Action.java:842)\n        at \norg.eclipse.jface.action.ActionContributionItem.handleWidgetSelection(ActionContributionItem.java:529)\n        at org.eclipse.jface.action.ActionContributionItem.access$4(ActionContributionItem.java:482)\n        at org.eclipse.jface.action.ActionContributionItem$6.handleEvent(ActionContributionItem.java:454)\n        at org.eclipse.swt.widgets.EventTable.sendEvent(EventTable.java:82)\n        at org.eclipse.swt.widgets.Widget.notifyListeners(Widget.java:1027)\n        at org.eclipse.swt.widgets.Display.runDeferredEvents(Display.java:2180)\n        at org.eclipse.swt.widgets.Display.readAndDispatch(Display.java:1878)\n        at org.eclipse.ui.internal.Workbench.runEventLoop(Workbench.java:2037)\n        at org.eclipse.ui.internal.Workbench.run(Workbench.java:2020)\n        at org.eclipse.core.internal.boot.InternalBootLoader.run(InternalBootLoader.java:858)\n        at org.eclipse.core.boot.BootLoader.run(BootLoader.java:461)\n        at sun.reflect.NativeMethodAccessorImpl.invoke0(Native Method)\n        at sun.reflect.NativeMethodAccessorImpl.invoke(NativeMethodAccessorImpl.java:39)\n        at sun.reflect.DelegatingMethodAccessorImpl.invoke(DelegatingMethodAccessorImpl.java:25)\n        at java.lang.reflect.Method.invoke(Method.java:324)\n        at org.eclipse.core.launcher.Main.basicRun(Main.java:295)\n        at org.eclipse.core.launcher.Main.run(Main.java:751)\n        at org.eclipse.core.launcher.Main.main(Main.java:587)",
    "The actual exception happens in \norg.eclipse.jdt.internal.ui.text.link.LinkedPositionManager.getPositions. \nAsking text how to avoid the assertion failure.",
    "Do you have repeatable steps? Did you use the template or Source \u003e Surround with\ntry/catch Block?\n\nCannot reproduce using I20030916 and several code snippets.\n",
    "I could not reproduce this in I20030916 after it happened - I just closed the editor and reopened it.\nI had highlighted a block of code and used the context menu to select Source \u003e Surround with\ntry/catch Block\n\nChang",
    "Tom,\nthis might be related to what you discussed today with Kai.\n",
    "*** Bug 43449 has been marked as a duplicate of this bug. ***",
    "fixed \u003e 20030924\n\nThe problem should be fixed by the most recent addition. Please reopen if you\nstill see this.",
    "will do, thanks.",
    "started verifying...",
    "Couldn\u0027t reproduce problem for various situations.\nSince more detailled steps are missing I mark as verified."
  ],
  "commentCreationDates": [
    "2003-09-16T16:17:54+02:00",
    "2003-09-17T10:17:26+02:00",
    "2003-09-17T11:55:43+02:00",
    "2003-09-17T12:14:56+02:00",
    "2003-09-17T14:33:08+02:00",
    "2003-09-23T09:50:18+02:00",
    "2003-09-24T14:08:35+02:00",
    "2003-09-24T18:11:28+02:00",
    "2003-10-08T14:29:53+02:00",
    "2003-10-08T14:56:48+02:00"
  ],
  "traces": [
    {
      "exceptionType": "org.eclipse.jdt.internal.corext.refactoring.base.ChangeAbortException",
      "elements": [
        {
          "method": "org.eclipse.jdt.internal.ui.refactoring.changes.AbortChangeExceptionHandler.handle",
          "source": "AbortChangeExcept ionHandler.java:28"
        },
        {
          "method": "org.eclipse.jdt.internal.corext.refactoring.base.Change.handleException",
          "source": "Change.java:108"
        },
        {
          "method": "org.eclipse.jdt.internal.corext.refactoring.changes.AbstractTextChange.perform",
          "source": "AbstractTextChange.jav a:201"
        },
        {
          "method": "org.eclipse.jdt.internal.corext.refactoring.changes.TextFileChange.perform",
          "source": "TextFileChange.java:208"
        },
        {
          "method": "org.eclipse.jdt.internal.ui.refactoring.PerformChangeOperation$1.run",
          "source": "PerformChangeOperation.java:173 "
        },
        {
          "method": "org.eclipse.jdt.internal.core.BatchOperation.executeOperation",
          "source": "BatchOperation.java:34"
        },
        {
          "method": "org.eclipse.jdt.internal.core.JavaModelOperation.execute",
          "source": "JavaModelOperation.java:366"
        },
        {
          "method": "org.eclipse.jdt.internal.core.JavaModelOperation.run",
          "source": "JavaModelOperation.java:705"
        },
        {
          "method": "org.eclipse.core.internal.resources.Workspace.run",
          "source": "Workspace.java:1571"
        },
        {
          "method": "org.eclipse.core.internal.resources.Workspace.run",
          "source": "Workspace.java:1588"
        },
        {
          "method": "org.eclipse.jdt.core.JavaCore.run",
          "source": "JavaCore.java:2963"
        },
        {
          "method": "org.eclipse.jdt.internal.ui.refactoring.PerformChangeOperation.executeChange",
          "source": "PerformChangeOperation .java:183"
        },
        {
          "method": "org.eclipse.jdt.internal.ui.refactoring.PerformChangeOperation.run",
          "source": "PerformChangeOperation.java:151"
        },
        {
          "method": "org.eclipse.jdt.internal.ui.util.BusyIndicatorRunnableContext$BusyRunnable.internalRun",
          "source": "BusyIndicatorRu nnableContext.java:113"
        },
        {
          "method": "org.eclipse.jdt.internal.ui.util.BusyIndicatorRunnableContext$BusyRunnable.run",
          "source": "BusyIndicatorRunnableC ontext.java:80"
        },
        {
          "method": "org.eclipse.swt.custom.BusyIndicator.showWhile",
          "source": "BusyIndicator.java:84"
        },
        {
          "method": "org.eclipse.jdt.internal.ui.util.BusyIndicatorRunnableContext.run",
          "source": "BusyIndicatorRunnableContext.java:126 "
        },
        {
          "method": "org.eclipse.jdt.ui.actions.SurroundWithTryCatchAction.run",
          "source": "SurroundWithTryCatchAction.java:127"
        },
        {
          "method": "org.eclipse.jdt.ui.actions.SelectionDispatchAction.dispatchRun",
          "source": "SelectionDispatchAction.java:196"
        },
        {
          "method": "org.eclipse.jdt.ui.actions.SelectionDispatchAction.run",
          "source": "SelectionDispatchAction.java:172"
        },
        {
          "method": "org.eclipse.jface.action.Action.runWithEvent",
          "source": "Action.java:842"
        },
        {
          "method": "org.eclipse.jface.action.ActionContributionItem.handleWidgetSelection",
          "source": "ActionContributionItem.java:529"
        },
        {
          "method": "org.eclipse.jface.action.ActionContributionItem.access$4",
          "source": "ActionContributionItem.java:482"
        },
        {
          "method": "org.eclipse.jface.action.ActionContributionItem$6.handleEvent",
          "source": "ActionContributionItem.java:454"
        },
        {
          "method": "org.eclipse.swt.widgets.EventTable.sendEvent",
          "source": "EventTable.java:82"
        },
        {
          "method": "org.eclipse.swt.widgets.Widget.notifyListeners",
          "source": "Widget.java:1027"
        },
        {
          "method": "org.eclipse.swt.widgets.Display.runDeferredEvents",
          "source": "Display.java:2180"
        },
        {
          "method": "org.eclipse.swt.widgets.Display.readAndDispatch",
          "source": "Display.java:1878"
        },
        {
          "method": "org.eclipse.ui.internal.Workbench.runEventLoop",
          "source": "Workbench.java:2037"
        },
        {
          "method": "org.eclipse.ui.internal.Workbench.run",
          "source": "Workbench.java:2020"
        },
        {
          "method": "org.eclipse.core.internal.boot.InternalBootLoader.run",
          "source": "InternalBootLoader.java:858"
        },
        {
          "method": "org.eclipse.core.boot.BootLoader.run",
          "source": "BootLoader.java:461"
        },
        {
          "method": "sun.reflect.NativeMethodAccessorImpl.invoke0",
          "source": "Native Method"
        },
        {
          "method": "sun.reflect.NativeMethodAccessorImpl.invoke",
          "source": "NativeMethodAccessorImpl.java:39"
        },
        {
          "method": "sun.reflect.DelegatingMethodAccessorImpl.invoke",
          "source": "DelegatingMethodAccessorImpl.java:25"
        },
        {
          "method": "java.lang.reflect.Method.invoke",
          "source": "Method.java:324"
        },
        {
          "method": "org.eclipse.core.launcher.Main.basicRun",
          "source": "Main.java:295"
        },
        {
          "method": "org.eclipse.core.launcher.Main.run",
          "source": "Main.java:751"
        },
        {
          "method": "org.eclipse.core.launcher.Main.main",
          "source": "Main.java:587"
        }
      ],
      "number": 0,
      "commentIndex": 0,
      "bugId": "43146",
      "date": "2003-09-16T16:17:54+02:00",
      "product": "JDT",
      "component": "Text",
      "severity": "normal"
    },
    {
      "exceptionType": "org.eclipse.jface.text.Assert$AssertionFailedException",
      "message": "Assertion failed:",
      "elements": [
        {
          "method": "org.eclipse.jface.text.Assert.isTrue",
          "source": "Assert.java:175"
        },
        {
          "method": "org.eclipse.jface.text.Assert.isTrue",
          "source": "Assert.java:160"
        },
        {
          "method": "org.eclipse.jdt.internal.ui.text.link.LinkedPositionManager.getPositions",
          "source": "LinkedPositionManager.java:427"
        },
        {
          "method": "org.eclipse.jdt.internal.ui.text.link.LinkedPositionManager.documentAboutToBeChanged",
          "source": "LinkedPosition Manager.java:477"
        },
        {
          "method": "org.eclipse.jface.text.AbstractDocument.fireDocumentAboutToBeChanged",
          "source": "AbstractDocument.java:549"
        },
        {
          "method": "org.eclipse.jface.text.AbstractDocument.replace",
          "source": "AbstractDocument.java:956"
        },
        {
          "method": "org.eclipse.jdt.internal.ui.javaeditor.PartiallySynchronizedDocument.replace",
          "source": "PartiallySynchronizedDocum ent.java:61"
        },
        {
          "method": "org.eclipse.jdt.internal.corext.textmanipulation.TextEdit.performReplace",
          "source": "TextEdit.java:401"
        },
        {
          "method": "org.eclipse.jdt.internal.corext.textmanipulation.SimpleTextEdit.perform",
          "source": "SimpleTextEdit.java:80"
        },
        {
          "method": "org.eclipse.jdt.internal.corext.textmanipulation.EditProcessor.execute",
          "source": "EditProcessor.java:183"
        },
        {
          "method": "org.eclipse.jdt.internal.corext.textmanipulation.EditProcessor.execute",
          "source": "EditProcessor.java:178"
        },
        {
          "method": "org.eclipse.jdt.internal.corext.textmanipulation.EditProcessor.execute",
          "source": "EditProcessor.java:178"
        },
        {
          "method": "org.eclipse.jdt.internal.corext.textmanipulation.EditProcessor.execute",
          "source": "EditProcessor.java:178"
        },
        {
          "method": "org.eclipse.jdt.internal.corext.textmanipulation.EditProcessor.executeDo",
          "source": "EditProcessor.java:163"
        },
        {
          "method": "org.eclipse.jdt.internal.corext.textmanipulation.EditProcessor.performEdits",
          "source": "EditProcessor.java:121"
        },
        {
          "method": "org.eclipse.jdt.internal.corext.textmanipulation.TextBufferEditor.performEdits",
          "source": "TextBufferEditor.java:55"
        },
        {
          "method": "org.eclipse.jdt.internal.corext.refactoring.changes.AbstractTextChange.perform",
          "source": "AbstractTextChange.jav a:199"
        },
        {
          "method": "org.eclipse.jdt.internal.corext.refactoring.changes.TextFileChange.perform",
          "source": "TextFileChange.java:208"
        },
        {
          "method": "org.eclipse.jdt.internal.ui.refactoring.PerformChangeOperation$1.run",
          "source": "PerformChangeOperation.java:173 "
        },
        {
          "method": "org.eclipse.jdt.internal.core.BatchOperation.executeOperation",
          "source": "BatchOperation.java:34"
        },
        {
          "method": "org.eclipse.jdt.internal.core.JavaModelOperation.execute",
          "source": "JavaModelOperation.java:366"
        },
        {
          "method": "org.eclipse.jdt.internal.core.JavaModelOperation.run",
          "source": "JavaModelOperation.java:705"
        },
        {
          "method": "org.eclipse.core.internal.resources.Workspace.run",
          "source": "Workspace.java:1571"
        },
        {
          "method": "org.eclipse.core.internal.resources.Workspace.run",
          "source": "Workspace.java:1588"
        },
        {
          "method": "org.eclipse.jdt.core.JavaCore.run",
          "source": "JavaCore.java:2963"
        },
        {
          "method": "org.eclipse.jdt.internal.ui.refactoring.PerformChangeOperation.executeChange",
          "source": "PerformChangeOperation .java:183"
        },
        {
          "method": "org.eclipse.jdt.internal.ui.refactoring.PerformChangeOperation.run",
          "source": "PerformChangeOperation.java:151"
        },
        {
          "method": "org.eclipse.jdt.internal.ui.util.BusyIndicatorRunnableContext$BusyRunnable.internalRun",
          "source": "BusyIndicatorRu nnableContext.java:113"
        },
        {
          "method": "org.eclipse.jdt.internal.ui.util.BusyIndicatorRunnableContext$BusyRunnable.run",
          "source": "BusyIndicatorRunnableC ontext.java:80"
        },
        {
          "method": "org.eclipse.swt.custom.BusyIndicator.showWhile",
          "source": "BusyIndicator.java:84"
        },
        {
          "method": "org.eclipse.jdt.internal.ui.util.BusyIndicatorRunnableContext.run",
          "source": "BusyIndicatorRunnableContext.java:126 "
        },
        {
          "method": "org.eclipse.jdt.ui.actions.SurroundWithTryCatchAction.run",
          "source": "SurroundWithTryCatchAction.java:127"
        },
        {
          "method": "org.eclipse.jdt.ui.actions.SelectionDispatchAction.dispatchRun",
          "source": "SelectionDispatchAction.java:196"
        },
        {
          "method": "org.eclipse.jdt.ui.actions.SelectionDispatchAction.run",
          "source": "SelectionDispatchAction.java:172"
        },
        {
          "method": "org.eclipse.jface.action.Action.runWithEvent",
          "source": "Action.java:842"
        },
        {
          "method": "org.eclipse.jface.action.ActionContributionItem.handleWidgetSelection",
          "source": "ActionContributionItem.java:529"
        },
        {
          "method": "org.eclipse.jface.action.ActionContributionItem.access$4",
          "source": "ActionContributionItem.java:482"
        },
        {
          "method": "org.eclipse.jface.action.ActionContributionItem$6.handleEvent",
          "source": "ActionContributionItem.java:454"
        },
        {
          "method": "org.eclipse.swt.widgets.EventTable.sendEvent",
          "source": "EventTable.java:82"
        },
        {
          "method": "org.eclipse.swt.widgets.Widget.notifyListeners",
          "source": "Widget.java:1027"
        },
        {
          "method": "org.eclipse.swt.widgets.Display.runDeferredEvents",
          "source": "Display.java:2180"
        },
        {
          "method": "org.eclipse.swt.widgets.Display.readAndDispatch",
          "source": "Display.java:1878"
        },
        {
          "method": "org.eclipse.ui.internal.Workbench.runEventLoop",
          "source": "Workbench.java:2037"
        },
        {
          "method": "org.eclipse.ui.internal.Workbench.run",
          "source": "Workbench.java:2020"
        },
        {
          "method": "org.eclipse.core.internal.boot.InternalBootLoader.run",
          "source": "InternalBootLoader.java:858"
        },
        {
          "method": "org.eclipse.core.boot.BootLoader.run",
          "source": "BootLoader.java:461"
        },
        {
          "method": "sun.reflect.NativeMethodAccessorImpl.invoke0",
          "source": "Native Method"
        },
        {
          "method": "sun.reflect.NativeMethodAccessorImpl.invoke",
          "source": "NativeMethodAccessorImpl.java:39"
        },
        {
          "method": "sun.reflect.DelegatingMethodAccessorImpl.invoke",
          "source": "DelegatingMethodAccessorImpl.java:25"
        },
        {
          "method": "java.lang.reflect.Method.invoke",
          "source": "Method.java:324"
        },
        {
          "method": "org.eclipse.core.launcher.Main.basicRun",
          "source": "Main.java:295"
        },
        {
          "method": "org.eclipse.core.launcher.Main.run",
          "source": "Main.java:751"
        },
        {
          "method": "org.eclipse.core.launcher.Main.main",
          "source": "Main.java:587"
        }
      ],
      "number": 1,
      "commentIndex": 0,
      "bugId": "43146",
      "date": "2003-09-16T16:17:54+02:00",
      "product": "JDT",
      "component": "Text",
      "severity": "normal"
    }
  ],
  "groupId": "43146",
  "bugId": "43146",
  "date": "2003-09-16T16:17:54+02:00",
  "product": "JDT",
  "component": "Text",
  "severity": "normal"
}