{
  "comments": [
    "Platform:\nVersion: 3.0.0\nBuild id: 200308281813\n\nThe formatting feature seems to be broken.\n\nHow to reproduce:\n1. Create a class anywhere in a java project with the creation wizard.\nHere is what it generates in my IDE:\n/*\n * Created on Sep 19, 2003\n *\n * To change the template for this generated file go to\n * Window - Preferences - Java - Code Generation - Code and Comments\n */\npackage test;\n\n/**\n * @author user\n *\n * To change the template for this generated type comment go to\n * Window - Preferences - Java - Code Generation - Code and Comments\n */\npublic class Asd {}\n\n2. Click-right on the code and call the formatter\nresult:\n/*\n * Created on Sep 19, 2003\n *\n * To change the template for this generated file go to\n * Window - Preferences - Java - Code Generation - Code and Comments\n */package test;\n/**\n * @author user\n *\n * To change the template for this generated type comment go to\n * Window - Preferences - Java - Code Generation - Code and Comments\n */public class Asd {}\n\n3. Erase the first comment region.\nResult:\npackage com.fimasys.services.tools;\n/**\n * @author user\n *\n * To change the template for this generated type comment go to\n * Window - Preferences - Java - Code Generation - Code and Comments\n */public class Asd {}\n\nThere\u0027s nothing in the .log file for now.\n\n4. Call the formatter again on that code.\nIt does nothing to the code, but here is what has been added to the log during \nthis formatting attempt:\n!SESSION Sep 19, 2003 17:21:26.534 ---------------------------------------------\njava.version\u003d1.3.1_03\njava.vendor\u003dSun Microsystems Inc.\nBootLoader constants: OS\u003dwin32, ARCH\u003dx86, WS\u003dwin32, NL\u003den_US\nCommand-line arguments: -os win32 -ws win32 -arch x86 -install \nfile:C:/TEMP/eclipse/\n!ENTRY org.eclipse.ui 4 4 Sep 19, 2003 17:21:26.549\n!MESSAGE Unhandled exception caught in event loop.\n!ENTRY org.eclipse.ui 4 0 Sep 19, 2003 17:21:26.549\n!MESSAGE java.lang.NullPointerException\n!STACK 0\njava.lang.NullPointerException\n\tat org.eclipse.jdt.internal.ui.text.comment.CommentRegion.scanLines\n(CommentRegion.java:158)\n\tat org.eclipse.jdt.internal.ui.text.comment.CommentRegion.formatRegion\n(CommentRegion.java:83)\n\tat org.eclipse.jdt.internal.ui.text.comment.CommentFormatter.format\n(CommentFormatter.java:46)\n\tat \norg.eclipse.jdt.internal.ui.text.comment.CommentFormattingStrategy.format\n(CommentFormattingStrategy.java:57)\n\tat org.eclipse.jface.text.formatter.ContentFormatter.format\n(ContentFormatter.java:521)\n\tat org.eclipse.jface.text.formatter.ContentFormatter.format\n(ContentFormatter.java:495)\n\tat org.eclipse.jface.text.formatter.ContentFormatter.formatPartitions\n(ContentFormatter.java:413)\n\tat org.eclipse.jface.text.formatter.ContentFormatter.format\n(ContentFormatter.java:387)\n\tat org.eclipse.jface.text.source.SourceViewer.doOperation\n(SourceViewer.java:519)\n\tat org.eclipse.jdt.internal.ui.javaeditor.JavaSourceViewer.doOperation\n(JavaSourceViewer.java:72)\n\tat \norg.eclipse.jdt.internal.ui.javaeditor.CompilationUnitEditor$AdaptedSourceViewer\n.doOperation(CompilationUnitEditor.java:167)\n\tat org.eclipse.ui.texteditor.TextOperationAction$1.run\n(TextOperationAction.java:127)\n\tat org.eclipse.swt.custom.BusyIndicator.showWhile(BusyIndicator.java:84)\n\tat org.eclipse.ui.texteditor.TextOperationAction.run\n(TextOperationAction.java:125)\n\tat org.eclipse.jface.action.Action.runWithEvent(Action.java:842)\n\tat org.eclipse.jface.action.ActionContributionItem.handleWidgetSelection\n(ActionContributionItem.java:529)\n\tat org.eclipse.jface.action.ActionContributionItem.access$4\n(ActionContributionItem.java:482)\n\tat org.eclipse.jface.action.ActionContributionItem$6.handleEvent\n(ActionContributionItem.java:454)\n\tat org.eclipse.swt.widgets.EventTable.sendEvent(EventTable.java:82)\n\tat org.eclipse.swt.widgets.Widget.sendEvent(Widget.java:847)\n\tat org.eclipse.swt.widgets.Display.runDeferredEvents(Display.java:2188)\n\tat org.eclipse.swt.widgets.Display.readAndDispatch(Display.java:1878)\n\tat org.eclipse.ui.internal.Workbench.runEventLoop(Workbench.java:2036)\n\tat org.eclipse.ui.internal.Workbench.run(Workbench.java:2019)\n\tat org.eclipse.core.internal.boot.InternalBootLoader.run\n(InternalBootLoader.java:858)\n\tat org.eclipse.core.boot.BootLoader.run(BootLoader.java:461)\n\tat java.lang.reflect.Method.invoke(Native Method)\n\tat org.eclipse.core.launcher.Main.basicRun(Main.java:295)\n\tat org.eclipse.core.launcher.Main.run(Main.java:751)\n\tat org.eclipse.core.launcher.Main.main(Main.java:587)\n\nI\u0027m able to reproduce it as many times as I want to.\nOnce the first formatting attempt has been done, any new attempt in any class \nwill raise an exception in .log file and nothing will ever happen in the code.",
    "\n\n*** This bug has been marked as a duplicate of 41953 ***"
  ],
  "commentCreationDates": [
    "2003-09-19T17:25:28+02:00",
    "2003-09-19T17:52:25+02:00"
  ],
  "traces": [
    {
      "exceptionType": "java.lang.NullPointerException",
      "elements": [
        {
          "method": "org.eclipse.jdt.internal.ui.text.comment.CommentRegion.scanLines",
          "source": "CommentRegion.java:158"
        },
        {
          "method": "org.eclipse.jdt.internal.ui.text.comment.CommentRegion.formatRegion",
          "source": "CommentRegion.java:83"
        },
        {
          "method": "org.eclipse.jdt.internal.ui.text.comment.CommentFormatter.format",
          "source": "CommentFormatter.java:46"
        },
        {
          "method": "org.eclipse.jdt.internal.ui.text.comment.CommentFormattingStrategy.format",
          "source": "CommentFormattingStrategy.java:57"
        },
        {
          "method": "org.eclipse.jface.text.formatter.ContentFormatter.format",
          "source": "ContentFormatter.java:521"
        },
        {
          "method": "org.eclipse.jface.text.formatter.ContentFormatter.format",
          "source": "ContentFormatter.java:495"
        },
        {
          "method": "org.eclipse.jface.text.formatter.ContentFormatter.formatPartitions",
          "source": "ContentFormatter.java:413"
        },
        {
          "method": "org.eclipse.jface.text.formatter.ContentFormatter.format",
          "source": "ContentFormatter.java:387"
        },
        {
          "method": "org.eclipse.jface.text.source.SourceViewer.doOperation",
          "source": "SourceViewer.java:519"
        },
        {
          "method": "org.eclipse.jdt.internal.ui.javaeditor.JavaSourceViewer.doOperation",
          "source": "JavaSourceViewer.java:72"
        },
        {
          "method": "org.eclipse.jdt.internal.ui.javaeditor.CompilationUnitEditor$AdaptedSourceViewer.doOperation",
          "source": "CompilationUnitEditor.java:167"
        },
        {
          "method": "org.eclipse.ui.texteditor.TextOperationAction$1.run",
          "source": "TextOperationAction.java:127"
        },
        {
          "method": "org.eclipse.swt.custom.BusyIndicator.showWhile",
          "source": "BusyIndicator.java:84"
        },
        {
          "method": "org.eclipse.ui.texteditor.TextOperationAction.run",
          "source": "TextOperationAction.java:125"
        },
        {
          "method": "org.eclipse.jface.action.Action.runWithEvent",
          "source": "Action.java:842"
        },
        {
          "method": "org.eclipse.jface.action.ActionContributionItem.handleWidgetSelection",
          "source": "ActionContributionItem.java:529"
        },
        {
          "method": "org.eclipse.jface.action.ActionContributionItem.access$4",
          "source": "ActionContributionItem.java:482"
        },
        {
          "method": "org.eclipse.jface.action.ActionContributionItem$6.handleEvent",
          "source": "ActionContributionItem.java:454"
        },
        {
          "method": "org.eclipse.swt.widgets.EventTable.sendEvent",
          "source": "EventTable.java:82"
        },
        {
          "method": "org.eclipse.swt.widgets.Widget.sendEvent",
          "source": "Widget.java:847"
        },
        {
          "method": "org.eclipse.swt.widgets.Display.runDeferredEvents",
          "source": "Display.java:2188"
        },
        {
          "method": "org.eclipse.swt.widgets.Display.readAndDispatch",
          "source": "Display.java:1878"
        },
        {
          "method": "org.eclipse.ui.internal.Workbench.runEventLoop",
          "source": "Workbench.java:2036"
        },
        {
          "method": "org.eclipse.ui.internal.Workbench.run",
          "source": "Workbench.java:2019"
        },
        {
          "method": "org.eclipse.core.internal.boot.InternalBootLoader.run",
          "source": "InternalBootLoader.java:858"
        },
        {
          "method": "org.eclipse.core.boot.BootLoader.run",
          "source": "BootLoader.java:461"
        },
        {
          "method": "java.lang.reflect.Method.invoke",
          "source": "Native Method"
        },
        {
          "method": "org.eclipse.core.launcher.Main.basicRun",
          "source": "Main.java:295"
        },
        {
          "method": "org.eclipse.core.launcher.Main.run",
          "source": "Main.java:751"
        },
        {
          "method": "org.eclipse.core.launcher.Main.main",
          "source": "Main.java:587"
        }
      ],
      "number": 0,
      "commentIndex": 0,
      "bugId": "43357",
      "duplicateId": "41953",
      "date": "2003-09-19T17:25:28+02:00",
      "product": "JDT",
      "component": "Text",
      "severity": "normal"
    }
  ],
  "groupId": "41953",
  "bugId": "43357",
  "duplicateId": "41953",
  "date": "2003-09-19T17:25:28+02:00",
  "product": "JDT",
  "component": "Text",
  "severity": "normal"
}