{
  "comments": [
    "Mac OSX 10.2.8 (doh!)\nEclipse:200309240800\n\nWhen expanding the java preferences node in the preferences tree, the workbench disappeared. This \nwas in the logs:\n\n!SESSION Sep 25, 2003 08:33:26.227 ---------------------------------------------\njava.version\u003d1.4.1_01\njava.vendor\u003dApple Computer, Inc.\nBootLoader constants: OS\u003dmacosx, ARCH\u003dppc, WS\u003dcarbon, NL\u003den_GB\nCommand-line arguments: -os macosx -ws carbon -arch ppc -psn_0_32636929 -consoleLog -\nshowlocation -data workspace -install file:/Users/channingwalton/java/eclipse/\n!ENTRY org.eclipse.ui 4 4 Sep 25, 2003 08:33:26.229\n!MESSAGE Unhandled exception caught in event loop.\n!ENTRY org.eclipse.ui 4 0 Sep 25, 2003 08:33:26.261\n!MESSAGE Device is disposed\n!STACK 0\norg.eclipse.swt.SWTException: Device is disposed\n        at org.eclipse.swt.SWT.error(SWT.java:2369)\n        at org.eclipse.swt.SWT.error(SWT.java:2299)\n        at org.eclipse.swt.widgets.Display.error(Display.java:796)\n        at org.eclipse.swt.widgets.Display.checkDevice(Display.java:501)\n        at org.eclipse.swt.widgets.Display.update(Display.java:2761)\n        at org.eclipse.jface.window.Window.runEventLoop(Window.java:589)\n        at org.eclipse.jface.window.Window.open(Window.java:563)\n        at org.eclipse.ui.internal.OpenPreferencesAction.run(OpenPreferencesAction.java:53)\n        at org.eclipse.jface.action.Action.runWithEvent(Action.java:842)\n        at \norg.eclipse.jface.action.ActionContributionItem.handleWidgetSelection(ActionContributionItem.java:529)\n        at org.eclipse.jface.action.ActionContributionItem.access$4(ActionContributionItem.java:482)\n        at org.eclipse.jface.action.ActionContributionItem$6.handleEvent(ActionContributionItem.java:454)\n        at org.eclipse.swt.widgets.EventTable.sendEvent(EventTable.java:82)\n        at org.eclipse.swt.widgets.Widget.notifyListeners(Widget.java:1032)\n        at org.eclipse.swt.widgets.Display.runDeferredEvents(Display.java:2185)\n        at org.eclipse.swt.widgets.Display.readAndDispatch(Display.java:1883)\n        at org.eclipse.ui.internal.Workbench.runEventLoop(Workbench.java:2064)\n        at org.eclipse.ui.internal.Workbench.run(Workbench.java:2047)\n        at org.eclipse.core.internal.boot.InternalBootLoader.run(InternalBootLoader.java:858)\n        at org.eclipse.core.boot.BootLoader.run(BootLoader.java:461)\n        at sun.reflect.NativeMethodAccessorImpl.invoke0(Native Method)\n        at sun.reflect.NativeMethodAccessorImpl.invoke(NativeMethodAccessorImpl.java:39)\n        at sun.reflect.DelegatingMethodAccessorImpl.invoke(DelegatingMethodAccessorImpl.java:25)\n        at java.lang.reflect.Method.invoke(Method.java:324)\n        at org.eclipse.core.launcher.Main.basicRun(Main.java:298)\n        at org.eclipse.core.launcher.Main.run(Main.java:764)\n        at org.eclipse.core.launcher.Main.main(Main.java:598)",
    "The only way this exception can happen is if the Device.dispose() was called previously.    \nThis would normally happen only when Eclipse is exiting, so some other exception must \nhave happened before.  Actually, maybe this exception is old and is not related to the \ncrash. \n\nAre you able to reproduce this? If so, could you add here the contents of the Mac \nconsole.log after reproducing it.",
    "I am not able to reproduce this, prefs work perfectly now.\n \nThis happened after moving from a previous integration release to this one - I simply moved the \nworkspace into the new install (which was the same location as the old one).\n\nThe console log doesn\u0027t show anything happening (in eclipse) prior to the crash.\n\nChanning",
    "I am going to close this, since I cannot reproduce it. Please reopen if you \ncan...",
    "ok, hasn\u0027t happened again."
  ],
  "commentCreationDates": [
    "2003-09-25T09:41:06+02:00",
    "2003-09-25T18:43:12+02:00",
    "2003-09-25T19:07:56+02:00",
    "2003-11-08T08:35:01+01:00",
    "2003-11-08T08:58:08+01:00"
  ],
  "traces": [
    {
      "exceptionType": "org.eclipse.swt.SWTException",
      "message": "Device is disposed",
      "elements": [
        {
          "method": "org.eclipse.swt.SWT.error",
          "source": "SWT.java:2369"
        },
        {
          "method": "org.eclipse.swt.SWT.error",
          "source": "SWT.java:2299"
        },
        {
          "method": "org.eclipse.swt.widgets.Display.error",
          "source": "Display.java:796"
        },
        {
          "method": "org.eclipse.swt.widgets.Display.checkDevice",
          "source": "Display.java:501"
        },
        {
          "method": "org.eclipse.swt.widgets.Display.update",
          "source": "Display.java:2761"
        },
        {
          "method": "org.eclipse.jface.window.Window.runEventLoop",
          "source": "Window.java:589"
        },
        {
          "method": "org.eclipse.jface.window.Window.open",
          "source": "Window.java:563"
        },
        {
          "method": "org.eclipse.ui.internal.OpenPreferencesAction.run",
          "source": "OpenPreferencesAction.java:53"
        },
        {
          "method": "org.eclipse.jface.action.Action.runWithEvent",
          "source": "Action.java:842"
        },
        {
          "method": "org.eclipse.jface.action.ActionContributionItem.handleWidgetSelection",
          "source": "ActionContributionItem.java:529"
        },
        {
          "method": "org.eclipse.jface.action.ActionContributionItem.access$4",
          "source": "ActionContributionItem.java:482"
        },
        {
          "method": "org.eclipse.jface.action.ActionContributionItem$6.handleEvent",
          "source": "ActionContributionItem.java:454"
        },
        {
          "method": "org.eclipse.swt.widgets.EventTable.sendEvent",
          "source": "EventTable.java:82"
        },
        {
          "method": "org.eclipse.swt.widgets.Widget.notifyListeners",
          "source": "Widget.java:1032"
        },
        {
          "method": "org.eclipse.swt.widgets.Display.runDeferredEvents",
          "source": "Display.java:2185"
        },
        {
          "method": "org.eclipse.swt.widgets.Display.readAndDispatch",
          "source": "Display.java:1883"
        },
        {
          "method": "org.eclipse.ui.internal.Workbench.runEventLoop",
          "source": "Workbench.java:2064"
        },
        {
          "method": "org.eclipse.ui.internal.Workbench.run",
          "source": "Workbench.java:2047"
        },
        {
          "method": "org.eclipse.core.internal.boot.InternalBootLoader.run",
          "source": "InternalBootLoader.java:858"
        },
        {
          "method": "org.eclipse.core.boot.BootLoader.run",
          "source": "BootLoader.java:461"
        },
        {
          "method": "sun.reflect.NativeMethodAccessorImpl.invoke0",
          "source": "Native Method"
        },
        {
          "method": "sun.reflect.NativeMethodAccessorImpl.invoke",
          "source": "NativeMethodAccessorImpl.java:39"
        },
        {
          "method": "sun.reflect.DelegatingMethodAccessorImpl.invoke",
          "source": "DelegatingMethodAccessorImpl.java:25"
        },
        {
          "method": "java.lang.reflect.Method.invoke",
          "source": "Method.java:324"
        },
        {
          "method": "org.eclipse.core.launcher.Main.basicRun",
          "source": "Main.java:298"
        },
        {
          "method": "org.eclipse.core.launcher.Main.run",
          "source": "Main.java:764"
        },
        {
          "method": "org.eclipse.core.launcher.Main.main",
          "source": "Main.java:598"
        }
      ],
      "number": 0,
      "commentIndex": 0,
      "bugId": "43631",
      "date": "2003-09-25T09:41:06+02:00",
      "product": "Platform",
      "component": "SWT",
      "severity": "major"
    }
  ],
  "groupId": "43631",
  "bugId": "43631",
  "date": "2003-09-25T09:41:06+02:00",
  "product": "Platform",
  "component": "SWT",
  "severity": "major"
}