{
  "comments": [
    "Build 20030925\n\nGot lots of exceptions during CVS replace with latest from HEAD (contents from \njdt.core projects into existing workspace).\n\nSee attached log",
    "Created an attachment (id\u003d6264)\nZipped log with exceptions\n",
    "I also got a dialog indicating that sync info could not be cached.",
    "Exit/restart, still same problem occurs:\n\n!ENTRY org.eclipse.team.cvs.core 2 0 Sep 27, 2003 12:11:42.641\n!MESSAGE Synchronization information could not be cached \nfor /org.eclipse.jdt.core/model/org/eclipse/jdt/core/CodeFormatter.java. The \nonly negative effect of th\nis may be decreased performance.\n!STACK 1\norg.eclipse.team.internal.ccvs.core.CVSException: Synchronization information \ncould not be cached \nfor /org.eclipse.jdt.core/model/org/eclipse/jdt/core/CodeForma\ntter.java. The only negative effect of this may be decreased performance.\n        at \norg.eclipse.team.internal.ccvs.core.resources.SynchronizerSyncInfoCache.checkCan\nModifyWorkspace(SynchronizerSyncInfoCache.java:155)\n        at \norg.eclipse.team.internal.ccvs.core.resources.SynchronizerSyncInfoCache.setCache\ndSyncBytes(SynchronizerSyncInfoCache.java:139)\n        at \norg.eclipse.team.internal.ccvs.core.resources.EclipseSynchronizer.cacheResourceS\nyncForChildren(EclipseSynchronizer.java:746)\n        at \norg.eclipse.team.internal.ccvs.core.resources.EclipseSynchronizer.members\n(EclipseSynchronizer.java:444)\n        at org.eclipse.team.internal.ccvs.core.resources.EclipseFolder.members\n(EclipseFolder.java:56)\n        at \norg.eclipse.team.internal.ccvs.core.resources.EclipseFolder.acceptChildren\n(EclipseFolder.java:135)\n        at \norg.eclipse.team.internal.ccvs.core.util.PrepareForReplaceVisitor.visitFolder\n(PrepareForReplaceVisitor.java:75)\n        at org.eclipse.team.internal.ccvs.core.resources.EclipseFolder.accept\n(EclipseFolder.java:149)\n        at \norg.eclipse.team.internal.ccvs.core.resources.EclipseFolder.acceptChildren\n(EclipseFolder.java:141)\n        at \norg.eclipse.team.internal.ccvs.core.util.PrepareForReplaceVisitor.visitFolder\n(PrepareForReplaceVisitor.java:75)\n        at org.eclipse.team.internal.ccvs.core.resources.EclipseFolder.accept\n(EclipseFolder.java:149)\n        at \norg.eclipse.team.internal.ccvs.core.resources.EclipseFolder.acceptChildren\n(EclipseFolder.java:141)\n        at \norg.eclipse.team.internal.ccvs.core.util.PrepareForReplaceVisitor.visitFolder\n(PrepareForReplaceVisitor.java:75)\n        at org.eclipse.team.internal.ccvs.core.resources.EclipseFolder.accept\n(EclipseFolder.java:149)\n        at \norg.eclipse.team.internal.ccvs.core.resources.EclipseFolder.acceptChildren\n(EclipseFolder.java:141)\n        at \norg.eclipse.team.internal.ccvs.core.util.PrepareForReplaceVisitor.visitFolder\n(PrepareForReplaceVisitor.java:75)\n        at org.eclipse.team.internal.ccvs.core.resources.EclipseFolder.accept\n(EclipseFolder.java:149)\n        at \norg.eclipse.team.internal.ccvs.core.resources.EclipseFolder.acceptChildren\n(EclipseFolder.java:141)\n        at \norg.eclipse.team.internal.ccvs.core.util.PrepareForReplaceVisitor.visitFolder\n(PrepareForReplaceVisitor.java:75)\n        at org.eclipse.team.internal.ccvs.core.resources.EclipseFolder.accept\n(EclipseFolder.java:149)\n        at \norg.eclipse.team.internal.ccvs.core.resources.EclipseFolder.acceptChildren\n(EclipseFolder.java:141)\n        at \norg.eclipse.team.internal.ccvs.core.util.PrepareForReplaceVisitor.visitFolder\n(PrepareForReplaceVisitor.java:75)\n        at org.eclipse.team.internal.ccvs.core.resources.EclipseFolder.accept\n(EclipseFolder.java:149)\n        at \norg.eclipse.team.internal.ccvs.core.util.PrepareForReplaceVisitor$1.run\n(PrepareForReplaceVisitor.java:105)\n        at org.eclipse.team.internal.ccvs.core.resources.EclipseSynchronizer.run\n(EclipseSynchronizer.java:1317)\n        at org.eclipse.team.internal.ccvs.core.resources.EclipseFolder$3.run\n(EclipseFolder.java:298)\n        at org.eclipse.core.internal.resources.Workspace.run\n(Workspace.java:1555)\n        at org.eclipse.team.internal.ccvs.core.resources.EclipseFolder.run\n(EclipseFolder.java:295)\n        at \norg.eclipse.team.internal.ccvs.core.util.PrepareForReplaceVisitor.visitResources\n(PrepareForReplaceVisitor.java:96)\n        at org.eclipse.team.internal.ccvs.core.CVSTeamProvider.get\n(CVSTeamProvider.java:651)\n        at org.eclipse.team.internal.ccvs.core.CVSTeamProvider.get\n(CVSTeamProvider.java:635)\n        at \norg.eclipse.team.internal.ccvs.ui.actions.ReplaceWithRemoteAction.performReplace\n(ReplaceWithRemoteAction.java:66)\n        at \norg.eclipse.team.internal.ccvs.ui.actions.ReplaceWithRemoteAction$1.execute\n(ReplaceWithRemoteAction.java:43)\n        at org.eclipse.ui.actions.WorkspaceModifyOperation$1.run\n(WorkspaceModifyOperation.java:71)\n        at org.eclipse.core.internal.resources.Workspace.run\n(Workspace.java:1555)\n        at org.eclipse.core.internal.resources.Workspace.run\n(Workspace.java:1572)\n        at org.eclipse.ui.actions.WorkspaceModifyOperation.run\n(WorkspaceModifyOperation.java:85)\n        at org.eclipse.team.internal.ccvs.ui.repo.RepositoryManager.run\n(RepositoryManager.java:802)\n        at org.eclipse.team.internal.ccvs.ui.actions.CVSAction$1.run\n(CVSAction.java:241)\n        at org.eclipse.jface.operation.ModalContext$ModalContextThread.run\n(ModalContext.java:101)\n!ENTRY org.eclipse.team.cvs.core 2 -25 Sep 27, 2003 12:11:42.651\n!MESSAGE Synchronization information could not be cached \nfor /org.eclipse.jdt.core/model/org/eclipse/jdt/core/CodeFormatter.java. The \nonly negative effect of th\nis may be decreased performance.\n!ENTRY org.eclipse.team.cvs.ui 2 0 Sep 27, 2003 12:11:45.845\n!MESSAGE Synchronization information could not be cached \nfor /org.eclipse.jdt.core/model/org/eclipse/jdt/core/CodeFormatter.java. The \nonly negative effect of th\nis may be decreased performance.\n!STACK 1\norg.eclipse.team.internal.ccvs.core.CVSException: Synchronization information \ncould not be cached \nfor /org.eclipse.jdt.core/model/org/eclipse/jdt/core/CodeForma\ntter.java. The only negative effect of this may be decreased performance.\n        at \norg.eclipse.team.internal.ccvs.core.resources.SynchronizerSyncInfoCache.checkCan\nModifyWorkspace(SynchronizerSyncInfoCache.java:155)\n        at \norg.eclipse.team.internal.ccvs.core.resources.SynchronizerSyncInfoCache.setCache\ndSyncBytes(SynchronizerSyncInfoCache.java:139)\n        at \norg.eclipse.team.internal.ccvs.core.resources.EclipseSynchronizer.cacheResourceS\nyncForChildren(EclipseSynchronizer.java:746)\n        at \norg.eclipse.team.internal.ccvs.core.resources.EclipseSynchronizer.deleteResource\nSync(EclipseSynchronizer.java:344)\n        at \norg.eclipse.team.internal.ccvs.core.resources.EclipseResource.unmanage\n(EclipseResource.java:243)\n        at org.eclipse.team.internal.ccvs.core.resources.EclipseFile.access$0\n(EclipseFile.java:1)\n        at org.eclipse.team.internal.ccvs.core.resources.EclipseFile$3.run\n(EclipseFile.java:490)\n        at org.eclipse.team.internal.ccvs.core.resources.EclipseSynchronizer.run\n(EclipseSynchronizer.java:1317)\n        at org.eclipse.team.internal.ccvs.core.resources.EclipseFolder$3.run\n(EclipseFolder.java:298)\n        at org.eclipse.core.internal.resources.Workspace.run\n(Workspace.java:1555)\n        at org.eclipse.team.internal.ccvs.core.resources.EclipseFolder.run\n(EclipseFolder.java:295)\n        at org.eclipse.team.internal.ccvs.core.resources.EclipseFile.run\n(EclipseFile.java:556)\n        at org.eclipse.team.internal.ccvs.core.resources.EclipseFile.unmanage\n(EclipseFile.java:488)\n        at \norg.eclipse.team.internal.ccvs.core.util.PrepareForReplaceVisitor.visitFile\n(PrepareForReplaceVisitor.java:59)\n        at org.eclipse.team.internal.ccvs.core.resources.EclipseFile.accept\n(EclipseFile.java:166)\n        at \norg.eclipse.team.internal.ccvs.core.resources.EclipseFolder.acceptChildren\n(EclipseFolder.java:137)\n        at \norg.eclipse.team.internal.ccvs.core.util.PrepareForReplaceVisitor.visitFolder\n(PrepareForReplaceVisitor.java:75)\n        at org.eclipse.team.internal.ccvs.core.resources.EclipseFolder.accept\n(EclipseFolder.java:149)\n        at \norg.eclipse.team.internal.ccvs.core.resources.EclipseFolder.acceptChildren\n(EclipseFolder.java:141)\n        at \norg.eclipse.team.internal.ccvs.core.util.PrepareForReplaceVisitor.visitFolder\n(PrepareForReplaceVisitor.java:75)\n        at org.eclipse.team.internal.ccvs.core.resources.EclipseFolder.accept\n(EclipseFolder.java:149)\n        at \norg.eclipse.team.internal.ccvs.core.resources.EclipseFolder.acceptChildren\n(EclipseFolder.java:141)\n        at \norg.eclipse.team.internal.ccvs.core.util.PrepareForReplaceVisitor.visitFolder\n(PrepareForReplaceVisitor.java:75)\n        at org.eclipse.team.internal.ccvs.core.resources.EclipseFolder.accept\n(EclipseFolder.java:149)\n        at \norg.eclipse.team.internal.ccvs.core.resources.EclipseFolder.acceptChildren\n(EclipseFolder.java:141)\n        at \norg.eclipse.team.internal.ccvs.core.util.PrepareForReplaceVisitor.visitFolder\n(PrepareForReplaceVisitor.java:75)\n        at org.eclipse.team.internal.ccvs.core.resources.EclipseFolder.accept\n(EclipseFolder.java:149)\n        at \norg.eclipse.team.internal.ccvs.core.resources.EclipseFolder.acceptChildren\n(EclipseFolder.java:141)\n        at \norg.eclipse.team.internal.ccvs.core.util.PrepareForReplaceVisitor.visitFolder\n(PrepareForReplaceVisitor.java:75)\n        at org.eclipse.team.internal.ccvs.core.resources.EclipseFolder.accept\n(EclipseFolder.java:149)\n        at \norg.eclipse.team.internal.ccvs.core.resources.EclipseFolder.acceptChildren\n(EclipseFolder.java:141)\n        at \norg.eclipse.team.internal.ccvs.core.util.PrepareForReplaceVisitor.visitFolder\n(PrepareForReplaceVisitor.java:75)\n        at org.eclipse.team.internal.ccvs.core.resources.EclipseFolder.accept\n(EclipseFolder.java:149)\n        at \norg.eclipse.team.internal.ccvs.core.util.PrepareForReplaceVisitor$1.run\n(PrepareForReplaceVisitor.java:105)\n        at org.eclipse.team.internal.ccvs.core.resources.EclipseSynchronizer.run\n(EclipseSynchronizer.java:1317)\n        at org.eclipse.team.internal.ccvs.core.resources.EclipseFolder$3.run\n(EclipseFolder.java:298)\n        at org.eclipse.core.internal.resources.Workspace.run\n(Workspace.java:1555)\n        at org.eclipse.team.internal.ccvs.core.resources.EclipseFolder.run\n(EclipseFolder.java:295)\n        at \norg.eclipse.team.internal.ccvs.core.util.PrepareForReplaceVisitor.visitResources\n(PrepareForReplaceVisitor.java:96)\n        at org.eclipse.team.internal.ccvs.core.CVSTeamProvider.get\n(CVSTeamProvider.java:651)\n        at org.eclipse.team.internal.ccvs.core.CVSTeamProvider.get\n(CVSTeamProvider.java:635)\n        at \norg.eclipse.team.internal.ccvs.ui.actions.ReplaceWithRemoteAction.performReplace\n(ReplaceWithRemoteAction.java:66)\n        at \norg.eclipse.team.internal.ccvs.ui.actions.ReplaceWithRemoteAction$1.execute\n(ReplaceWithRemoteAction.java:43)\n        at org.eclipse.ui.actions.WorkspaceModifyOperation$1.run\n(WorkspaceModifyOperation.java:71)\n        at org.eclipse.core.internal.resources.Workspace.run\n(Workspace.java:1555)\n        at org.eclipse.core.internal.resources.Workspace.run\n(Workspace.java:1572)\n        at org.eclipse.ui.actions.WorkspaceModifyOperation.run\n(WorkspaceModifyOperation.java:85)\n        at org.eclipse.team.internal.ccvs.ui.repo.RepositoryManager.run\n(RepositoryManager.java:802)\n        at org.eclipse.team.internal.ccvs.ui.actions.CVSAction$1.run\n(CVSAction.java:241)\n        at org.eclipse.jface.operation.ModalContext$ModalContextThread.run\n(ModalContext.java:101)\n!ENTRY org.eclipse.team.cvs.core 2 -25 Sep 27, 2003 12:11:45.855\n!MESSAGE Synchronization information could not be cached \nfor /org.eclipse.jdt.core/model/org/eclipse/jdt/core/CodeFormatter.java. The \nonly negative effect of th\nis may be decreased performance.",
    "The warning about performance is wrong, it actually did not catchup some \nresources, and will consistently fail grabbing them.",
    "\n\n*** This bug has been marked as a duplicate of 43716 ***"
  ],
  "commentCreationDates": [
    "2003-09-27T11:34:33+02:00",
    "2003-09-27T11:35:13+02:00",
    "2003-09-27T11:36:07+02:00",
    "2003-09-27T12:33:03+02:00",
    "2003-09-27T12:44:22+02:00",
    "2003-09-29T14:58:19+02:00"
  ],
  "traces": [
    {
      "exceptionType": "org.eclipse.team.internal.ccvs.core.CVSException",
      "message": "Synchronization information  could not be cached  for /org.eclipse.jdt.core/model/org/eclipse/jdt/core/CodeForma tter.java. The only negative effect of this may be decreased performance.",
      "elements": [
        {
          "method": "org.eclipse.team.internal.ccvs.core.resources.SynchronizerSyncInfoCache.checkCanModifyWorkspace",
          "source": "SynchronizerSyncInfoCache.java:155"
        },
        {
          "method": "org.eclipse.team.internal.ccvs.core.resources.SynchronizerSyncInfoCache.setCachedSyncBytes",
          "source": "SynchronizerSyncInfoCache.java:139"
        },
        {
          "method": "org.eclipse.team.internal.ccvs.core.resources.EclipseSynchronizer.cacheResourceSyncForChildren",
          "source": "EclipseSynchronizer.java:746"
        },
        {
          "method": "org.eclipse.team.internal.ccvs.core.resources.EclipseSynchronizer.members",
          "source": "EclipseSynchronizer.java:444"
        },
        {
          "method": "org.eclipse.team.internal.ccvs.core.resources.EclipseFolder.members",
          "source": "EclipseFolder.java:56"
        },
        {
          "method": "org.eclipse.team.internal.ccvs.core.resources.EclipseFolder.acceptChildren",
          "source": "EclipseFolder.java:135"
        },
        {
          "method": "org.eclipse.team.internal.ccvs.core.util.PrepareForReplaceVisitor.visitFolder",
          "source": "PrepareForReplaceVisitor.java:75"
        },
        {
          "method": "org.eclipse.team.internal.ccvs.core.resources.EclipseFolder.accept",
          "source": "EclipseFolder.java:149"
        },
        {
          "method": "org.eclipse.team.internal.ccvs.core.resources.EclipseFolder.acceptChildren",
          "source": "EclipseFolder.java:141"
        },
        {
          "method": "org.eclipse.team.internal.ccvs.core.util.PrepareForReplaceVisitor.visitFolder",
          "source": "PrepareForReplaceVisitor.java:75"
        },
        {
          "method": "org.eclipse.team.internal.ccvs.core.resources.EclipseFolder.accept",
          "source": "EclipseFolder.java:149"
        },
        {
          "method": "org.eclipse.team.internal.ccvs.core.resources.EclipseFolder.acceptChildren",
          "source": "EclipseFolder.java:141"
        },
        {
          "method": "org.eclipse.team.internal.ccvs.core.util.PrepareForReplaceVisitor.visitFolder",
          "source": "PrepareForReplaceVisitor.java:75"
        },
        {
          "method": "org.eclipse.team.internal.ccvs.core.resources.EclipseFolder.accept",
          "source": "EclipseFolder.java:149"
        },
        {
          "method": "org.eclipse.team.internal.ccvs.core.resources.EclipseFolder.acceptChildren",
          "source": "EclipseFolder.java:141"
        },
        {
          "method": "org.eclipse.team.internal.ccvs.core.util.PrepareForReplaceVisitor.visitFolder",
          "source": "PrepareForReplaceVisitor.java:75"
        },
        {
          "method": "org.eclipse.team.internal.ccvs.core.resources.EclipseFolder.accept",
          "source": "EclipseFolder.java:149"
        },
        {
          "method": "org.eclipse.team.internal.ccvs.core.resources.EclipseFolder.acceptChildren",
          "source": "EclipseFolder.java:141"
        },
        {
          "method": "org.eclipse.team.internal.ccvs.core.util.PrepareForReplaceVisitor.visitFolder",
          "source": "PrepareForReplaceVisitor.java:75"
        },
        {
          "method": "org.eclipse.team.internal.ccvs.core.resources.EclipseFolder.accept",
          "source": "EclipseFolder.java:149"
        },
        {
          "method": "org.eclipse.team.internal.ccvs.core.resources.EclipseFolder.acceptChildren",
          "source": "EclipseFolder.java:141"
        },
        {
          "method": "org.eclipse.team.internal.ccvs.core.util.PrepareForReplaceVisitor.visitFolder",
          "source": "PrepareForReplaceVisitor.java:75"
        },
        {
          "method": "org.eclipse.team.internal.ccvs.core.resources.EclipseFolder.accept",
          "source": "EclipseFolder.java:149"
        },
        {
          "method": "org.eclipse.team.internal.ccvs.core.util.PrepareForReplaceVisitor$1.run",
          "source": "PrepareForReplaceVisitor.java:105"
        },
        {
          "method": "org.eclipse.team.internal.ccvs.core.resources.EclipseSynchronizer.run",
          "source": "EclipseSynchronizer.java:1317"
        },
        {
          "method": "org.eclipse.team.internal.ccvs.core.resources.EclipseFolder$3.run",
          "source": "EclipseFolder.java:298"
        },
        {
          "method": "org.eclipse.core.internal.resources.Workspace.run",
          "source": "Workspace.java:1555"
        },
        {
          "method": "org.eclipse.team.internal.ccvs.core.resources.EclipseFolder.run",
          "source": "EclipseFolder.java:295"
        },
        {
          "method": "org.eclipse.team.internal.ccvs.core.util.PrepareForReplaceVisitor.visitResources",
          "source": "PrepareForReplaceVisitor.java:96"
        },
        {
          "method": "org.eclipse.team.internal.ccvs.core.CVSTeamProvider.get",
          "source": "CVSTeamProvider.java:651"
        },
        {
          "method": "org.eclipse.team.internal.ccvs.core.CVSTeamProvider.get",
          "source": "CVSTeamProvider.java:635"
        },
        {
          "method": "org.eclipse.team.internal.ccvs.ui.actions.ReplaceWithRemoteAction.performReplace",
          "source": "ReplaceWithRemoteAction.java:66"
        },
        {
          "method": "org.eclipse.team.internal.ccvs.ui.actions.ReplaceWithRemoteAction$1.execute",
          "source": "ReplaceWithRemoteAction.java:43"
        },
        {
          "method": "org.eclipse.ui.actions.WorkspaceModifyOperation$1.run",
          "source": "WorkspaceModifyOperation.java:71"
        },
        {
          "method": "org.eclipse.core.internal.resources.Workspace.run",
          "source": "Workspace.java:1555"
        },
        {
          "method": "org.eclipse.core.internal.resources.Workspace.run",
          "source": "Workspace.java:1572"
        },
        {
          "method": "org.eclipse.ui.actions.WorkspaceModifyOperation.run",
          "source": "WorkspaceModifyOperation.java:85"
        },
        {
          "method": "org.eclipse.team.internal.ccvs.ui.repo.RepositoryManager.run",
          "source": "RepositoryManager.java:802"
        },
        {
          "method": "org.eclipse.team.internal.ccvs.ui.actions.CVSAction$1.run",
          "source": "CVSAction.java:241"
        },
        {
          "method": "org.eclipse.jface.operation.ModalContext$ModalContextThread.run",
          "source": "ModalContext.java:101"
        }
      ],
      "number": 0,
      "commentIndex": 3,
      "bugId": "43789",
      "duplicateId": "43716",
      "date": "2003-09-27T12:33:03+02:00",
      "product": "Platform",
      "component": "Team",
      "severity": "normal"
    },
    {
      "exceptionType": "org.eclipse.team.internal.ccvs.core.CVSException",
      "message": "Synchronization information  could not be cached  for /org.eclipse.jdt.core/model/org/eclipse/jdt/core/CodeForma tter.java. The only negative effect of this may be decreased performance.",
      "elements": [
        {
          "method": "org.eclipse.team.internal.ccvs.core.resources.SynchronizerSyncInfoCache.checkCanModifyWorkspace",
          "source": "SynchronizerSyncInfoCache.java:155"
        },
        {
          "method": "org.eclipse.team.internal.ccvs.core.resources.SynchronizerSyncInfoCache.setCachedSyncBytes",
          "source": "SynchronizerSyncInfoCache.java:139"
        },
        {
          "method": "org.eclipse.team.internal.ccvs.core.resources.EclipseSynchronizer.cacheResourceSyncForChildren",
          "source": "EclipseSynchronizer.java:746"
        },
        {
          "method": "org.eclipse.team.internal.ccvs.core.resources.EclipseSynchronizer.deleteResourceSync",
          "source": "EclipseSynchronizer.java:344"
        },
        {
          "method": "org.eclipse.team.internal.ccvs.core.resources.EclipseResource.unmanage",
          "source": "EclipseResource.java:243"
        },
        {
          "method": "org.eclipse.team.internal.ccvs.core.resources.EclipseFile.access$0",
          "source": "EclipseFile.java:1"
        },
        {
          "method": "org.eclipse.team.internal.ccvs.core.resources.EclipseFile$3.run",
          "source": "EclipseFile.java:490"
        },
        {
          "method": "org.eclipse.team.internal.ccvs.core.resources.EclipseSynchronizer.run",
          "source": "EclipseSynchronizer.java:1317"
        },
        {
          "method": "org.eclipse.team.internal.ccvs.core.resources.EclipseFolder$3.run",
          "source": "EclipseFolder.java:298"
        },
        {
          "method": "org.eclipse.core.internal.resources.Workspace.run",
          "source": "Workspace.java:1555"
        },
        {
          "method": "org.eclipse.team.internal.ccvs.core.resources.EclipseFolder.run",
          "source": "EclipseFolder.java:295"
        },
        {
          "method": "org.eclipse.team.internal.ccvs.core.resources.EclipseFile.run",
          "source": "EclipseFile.java:556"
        },
        {
          "method": "org.eclipse.team.internal.ccvs.core.resources.EclipseFile.unmanage",
          "source": "EclipseFile.java:488"
        },
        {
          "method": "org.eclipse.team.internal.ccvs.core.util.PrepareForReplaceVisitor.visitFile",
          "source": "PrepareForReplaceVisitor.java:59"
        },
        {
          "method": "org.eclipse.team.internal.ccvs.core.resources.EclipseFile.accept",
          "source": "EclipseFile.java:166"
        },
        {
          "method": "org.eclipse.team.internal.ccvs.core.resources.EclipseFolder.acceptChildren",
          "source": "EclipseFolder.java:137"
        },
        {
          "method": "org.eclipse.team.internal.ccvs.core.util.PrepareForReplaceVisitor.visitFolder",
          "source": "PrepareForReplaceVisitor.java:75"
        },
        {
          "method": "org.eclipse.team.internal.ccvs.core.resources.EclipseFolder.accept",
          "source": "EclipseFolder.java:149"
        },
        {
          "method": "org.eclipse.team.internal.ccvs.core.resources.EclipseFolder.acceptChildren",
          "source": "EclipseFolder.java:141"
        },
        {
          "method": "org.eclipse.team.internal.ccvs.core.util.PrepareForReplaceVisitor.visitFolder",
          "source": "PrepareForReplaceVisitor.java:75"
        },
        {
          "method": "org.eclipse.team.internal.ccvs.core.resources.EclipseFolder.accept",
          "source": "EclipseFolder.java:149"
        },
        {
          "method": "org.eclipse.team.internal.ccvs.core.resources.EclipseFolder.acceptChildren",
          "source": "EclipseFolder.java:141"
        },
        {
          "method": "org.eclipse.team.internal.ccvs.core.util.PrepareForReplaceVisitor.visitFolder",
          "source": "PrepareForReplaceVisitor.java:75"
        },
        {
          "method": "org.eclipse.team.internal.ccvs.core.resources.EclipseFolder.accept",
          "source": "EclipseFolder.java:149"
        },
        {
          "method": "org.eclipse.team.internal.ccvs.core.resources.EclipseFolder.acceptChildren",
          "source": "EclipseFolder.java:141"
        },
        {
          "method": "org.eclipse.team.internal.ccvs.core.util.PrepareForReplaceVisitor.visitFolder",
          "source": "PrepareForReplaceVisitor.java:75"
        },
        {
          "method": "org.eclipse.team.internal.ccvs.core.resources.EclipseFolder.accept",
          "source": "EclipseFolder.java:149"
        },
        {
          "method": "org.eclipse.team.internal.ccvs.core.resources.EclipseFolder.acceptChildren",
          "source": "EclipseFolder.java:141"
        },
        {
          "method": "org.eclipse.team.internal.ccvs.core.util.PrepareForReplaceVisitor.visitFolder",
          "source": "PrepareForReplaceVisitor.java:75"
        },
        {
          "method": "org.eclipse.team.internal.ccvs.core.resources.EclipseFolder.accept",
          "source": "EclipseFolder.java:149"
        },
        {
          "method": "org.eclipse.team.internal.ccvs.core.resources.EclipseFolder.acceptChildren",
          "source": "EclipseFolder.java:141"
        },
        {
          "method": "org.eclipse.team.internal.ccvs.core.util.PrepareForReplaceVisitor.visitFolder",
          "source": "PrepareForReplaceVisitor.java:75"
        },
        {
          "method": "org.eclipse.team.internal.ccvs.core.resources.EclipseFolder.accept",
          "source": "EclipseFolder.java:149"
        },
        {
          "method": "org.eclipse.team.internal.ccvs.core.util.PrepareForReplaceVisitor$1.run",
          "source": "PrepareForReplaceVisitor.java:105"
        },
        {
          "method": "org.eclipse.team.internal.ccvs.core.resources.EclipseSynchronizer.run",
          "source": "EclipseSynchronizer.java:1317"
        },
        {
          "method": "org.eclipse.team.internal.ccvs.core.resources.EclipseFolder$3.run",
          "source": "EclipseFolder.java:298"
        },
        {
          "method": "org.eclipse.core.internal.resources.Workspace.run",
          "source": "Workspace.java:1555"
        },
        {
          "method": "org.eclipse.team.internal.ccvs.core.resources.EclipseFolder.run",
          "source": "EclipseFolder.java:295"
        },
        {
          "method": "org.eclipse.team.internal.ccvs.core.util.PrepareForReplaceVisitor.visitResources",
          "source": "PrepareForReplaceVisitor.java:96"
        },
        {
          "method": "org.eclipse.team.internal.ccvs.core.CVSTeamProvider.get",
          "source": "CVSTeamProvider.java:651"
        },
        {
          "method": "org.eclipse.team.internal.ccvs.core.CVSTeamProvider.get",
          "source": "CVSTeamProvider.java:635"
        },
        {
          "method": "org.eclipse.team.internal.ccvs.ui.actions.ReplaceWithRemoteAction.performReplace",
          "source": "ReplaceWithRemoteAction.java:66"
        },
        {
          "method": "org.eclipse.team.internal.ccvs.ui.actions.ReplaceWithRemoteAction$1.execute",
          "source": "ReplaceWithRemoteAction.java:43"
        },
        {
          "method": "org.eclipse.ui.actions.WorkspaceModifyOperation$1.run",
          "source": "WorkspaceModifyOperation.java:71"
        },
        {
          "method": "org.eclipse.core.internal.resources.Workspace.run",
          "source": "Workspace.java:1555"
        },
        {
          "method": "org.eclipse.core.internal.resources.Workspace.run",
          "source": "Workspace.java:1572"
        },
        {
          "method": "org.eclipse.ui.actions.WorkspaceModifyOperation.run",
          "source": "WorkspaceModifyOperation.java:85"
        },
        {
          "method": "org.eclipse.team.internal.ccvs.ui.repo.RepositoryManager.run",
          "source": "RepositoryManager.java:802"
        },
        {
          "method": "org.eclipse.team.internal.ccvs.ui.actions.CVSAction$1.run",
          "source": "CVSAction.java:241"
        },
        {
          "method": "org.eclipse.jface.operation.ModalContext$ModalContextThread.run",
          "source": "ModalContext.java:101"
        }
      ],
      "number": 1,
      "commentIndex": 3,
      "bugId": "43789",
      "duplicateId": "43716",
      "date": "2003-09-27T12:33:03+02:00",
      "product": "Platform",
      "component": "Team",
      "severity": "normal"
    }
  ],
  "groupId": "43592",
  "bugId": "43789",
  "duplicateId": "43716",
  "date": "2003-09-27T11:34:33+02:00",
  "product": "Platform",
  "component": "Team",
  "severity": "normal"
}