{
  "comments": [
    "This occured just once for me, while I editing a java source. After this error,\nI couldn\u0027t save the file, nor could I compile.\n\n\n\n!ENTRY org.eclipse.jdt.core 4 4 szept. 28, 2003 20:02:47.14\n!MESSAGE Exception occurred during problem detection:\n!STACK 0\njava.lang.NullPointerException\n        at\norg.eclipse.jdt.internal.compiler.codegen.ConstantPool.literalIndex(ConstantPool.java(Compiled\nCode))\n        at\norg.eclipse.jdt.internal.compiler.ClassFile.addFieldInfo(ClassFile.java:406)\n        at\norg.eclipse.jdt.internal.compiler.ClassFile.addFieldInfos(ClassFile.java:539)\n        at\norg.eclipse.jdt.internal.compiler.ast.TypeDeclaration.generateCode(TypeDeclaration.java(Compiled\nCode))\n        at\norg.eclipse.jdt.internal.compiler.ast.TypeDeclaration.generateCode(TypeDeclaration.java:531)\n        at\norg.eclipse.jdt.internal.compiler.ast.CompilationUnitDeclaration.generateCode(CompilationUnitDeclaration.java:176)\n        at org.eclipse.jdt.internal.compiler.Compiler.resolve(Compiler.java:598)\n        at\norg.eclipse.jdt.internal.core.CompilationUnitProblemFinder.process(CompilationUnitProblemFinder.java:172)\n        at\norg.eclipse.jdt.internal.core.CompilationUnit.buildStructure(CompilationUnit.java:139)\n        at org.eclipse.jdt.internal.core.Openable.generateInfos(Openable.java:198)\n        at\norg.eclipse.jdt.internal.core.JavaElement.openWhenClosed(JavaElement.java:448)\n        at\norg.eclipse.jdt.internal.core.CompilationUnit.makeConsistent(CompilationUnit.java:881)\n        at\norg.eclipse.jdt.internal.core.ReconcileWorkingCopyOperation.executeOperation(ReconcileWorkingCopyOperation.java:48)\n        at\norg.eclipse.jdt.internal.core.JavaModelOperation.execute(JavaModelOperation.java:365)\n        at\norg.eclipse.jdt.internal.core.JavaModelOperation.run(JavaModelOperation.java:704)\n        at\norg.eclipse.jdt.internal.core.JavaElement.runOperation(JavaElement.java:484)\n        at\norg.eclipse.jdt.internal.core.CompilationUnit.reconcile(CompilationUnit.java:994)\n        at\norg.eclipse.jdt.internal.core.CompilationUnit.reconcile(CompilationUnit.java:970)\n        at\norg.eclipse.jdt.internal.core.CompilationUnit.reconcile(CompilationUnit.java:963)\n        at\norg.eclipse.jdt.internal.ui.javaeditor.filebuffers.CompilationUnitDocumentProvider2.saveDocument(CompilationUnitDocumentProvider2.java:822)\n        at\norg.eclipse.ui.texteditor.AbstractTextEditor$17.execute(AbstractTextEditor.java:3170)\n        at\norg.eclipse.ui.actions.WorkspaceModifyOperation$1.run(WorkspaceModifyOperation.java:71)",
    "Which JRE are you running Eclipse on ?",
    "Offending code is:\nint descriptorIndex \u003d constantPool.literalIndex(fieldBinding.type.signature());\n\nWould be a field binding with no type.",
    "Would you have steps to reproduce ? Likely, the source of the file you were \nediting would do it.",
    "I use IBM JDK 1.4.1 on Linux.\n",
    "We had some cases like this that were JIT issues. Disabling the JIT fixed all \nof them.\nHave a look at bug 38146, bug 41231, bug 41398 and bug 41818. Try changing the \nVM for a Sun VM or disable the jit (-Djava.compiler\u003dNONE).",
    "This JRE is indeed known to have defficiencies (not final build yet).\nPlease reopen if symptoms persist with alternate VM (or disabling the JIT). \nThen we will need steps to reproduce.\n\n"
  ],
  "commentCreationDates": [
    "2003-09-28T20:42:37+02:00",
    "2003-09-29T10:15:16+02:00",
    "2003-09-29T10:21:54+02:00",
    "2003-09-29T10:50:05+02:00",
    "2003-09-29T11:10:00+02:00",
    "2003-09-29T13:44:06+02:00",
    "2003-09-29T15:22:23+02:00"
  ],
  "traces": [
    {
      "exceptionType": "java.lang.NullPointerException",
      "elements": [
        {
          "method": "org.eclipse.jdt.internal.compiler.codegen.ConstantPool.literalIndex",
          "source": "ConstantPool.java(Compiled Code)"
        },
        {
          "method": "org.eclipse.jdt.internal.compiler.ClassFile.addFieldInfo",
          "source": "ClassFile.java:406"
        },
        {
          "method": "org.eclipse.jdt.internal.compiler.ClassFile.addFieldInfos",
          "source": "ClassFile.java:539"
        },
        {
          "method": "org.eclipse.jdt.internal.compiler.ast.TypeDeclaration.generateCode",
          "source": "TypeDeclaration.java(Compiled Code)"
        },
        {
          "method": "org.eclipse.jdt.internal.compiler.ast.TypeDeclaration.generateCode",
          "source": "TypeDeclaration.java:531"
        },
        {
          "method": "org.eclipse.jdt.internal.compiler.ast.CompilationUnitDeclaration.generateCode",
          "source": "CompilationUnitDeclaration.java:176"
        },
        {
          "method": "org.eclipse.jdt.internal.compiler.Compiler.resolve",
          "source": "Compiler.java:598"
        },
        {
          "method": "org.eclipse.jdt.internal.core.CompilationUnitProblemFinder.process",
          "source": "CompilationUnitProblemFinder.java:172"
        },
        {
          "method": "org.eclipse.jdt.internal.core.CompilationUnit.buildStructure",
          "source": "CompilationUnit.java:139"
        },
        {
          "method": "org.eclipse.jdt.internal.core.Openable.generateInfos",
          "source": "Openable.java:198"
        },
        {
          "method": "org.eclipse.jdt.internal.core.JavaElement.openWhenClosed",
          "source": "JavaElement.java:448"
        },
        {
          "method": "org.eclipse.jdt.internal.core.CompilationUnit.makeConsistent",
          "source": "CompilationUnit.java:881"
        },
        {
          "method": "org.eclipse.jdt.internal.core.ReconcileWorkingCopyOperation.executeOperation",
          "source": "ReconcileWorkingCopyOperation.java:48"
        },
        {
          "method": "org.eclipse.jdt.internal.core.JavaModelOperation.execute",
          "source": "JavaModelOperation.java:365"
        },
        {
          "method": "org.eclipse.jdt.internal.core.JavaModelOperation.run",
          "source": "JavaModelOperation.java:704"
        },
        {
          "method": "org.eclipse.jdt.internal.core.JavaElement.runOperation",
          "source": "JavaElement.java:484"
        },
        {
          "method": "org.eclipse.jdt.internal.core.CompilationUnit.reconcile",
          "source": "CompilationUnit.java:994"
        },
        {
          "method": "org.eclipse.jdt.internal.core.CompilationUnit.reconcile",
          "source": "CompilationUnit.java:970"
        },
        {
          "method": "org.eclipse.jdt.internal.core.CompilationUnit.reconcile",
          "source": "CompilationUnit.java:963"
        },
        {
          "method": "org.eclipse.jdt.internal.ui.javaeditor.filebuffers.CompilationUnitDocumentProvider2.saveDocument",
          "source": "CompilationUnitDocumentProvider2.java:822"
        },
        {
          "method": "org.eclipse.ui.texteditor.AbstractTextEditor$17.execute",
          "source": "AbstractTextEditor.java:3170"
        },
        {
          "method": "org.eclipse.ui.actions.WorkspaceModifyOperation$1.run",
          "source": "WorkspaceModifyOperation.java:71"
        }
      ],
      "number": 0,
      "commentIndex": 0,
      "bugId": "43809",
      "date": "2003-09-28T20:42:37+02:00",
      "product": "JDT",
      "component": "Core",
      "severity": "normal"
    }
  ],
  "groupId": "43809",
  "bugId": "43809",
  "date": "2003-09-28T20:42:37+02:00",
  "product": "JDT",
  "component": "Core",
  "severity": "normal"
}