{
  "comments": [
    "The 3.0M3 build is failing to startup on my Solaris 8 system running JDK\n1.4.2_01.  The stacktrace follows:\n\njava.lang.UnsatisfiedLinkError:\n/opt/eclipse/plugins/org.eclipse.swt.motif_3.0.0/os/solaris/sparc/libswt-motif-3019.so:\nld.so.1: /usr/local/bin/java: fatal: libXp.so.1: open failed: No such file or\ndirectory\n        at java.lang.ClassLoader$NativeLibrary.load(Native Method)\n        at java.lang.ClassLoader.loadLibrary0(ClassLoader.java:1560)\n        at java.lang.ClassLoader.loadLibrary(ClassLoader.java:1469)\n        at java.lang.Runtime.loadLibrary0(Runtime.java:788)\n        at java.lang.System.loadLibrary(System.java:834)\n        at org.eclipse.swt.internal.Library.loadLibrary(Library.java:108)\n        at org.eclipse.swt.internal.motif.OS.\u003cclinit\u003e(OS.java:20)\n        at org.eclipse.swt.widgets.Display.createDisplay(Display.java:614)\n        at org.eclipse.swt.widgets.Display.create(Display.java:600)\n        at org.eclipse.swt.graphics.Device.\u003cinit\u003e(Device.java:126)\n        at org.eclipse.swt.widgets.Display.\u003cinit\u003e(Display.java:350)\n        at org.eclipse.swt.widgets.Display.\u003cinit\u003e(Display.java:347)\n        at org.eclipse.ui.internal.Workbench.run(Workbench.java:1989)\n        at\norg.eclipse.core.internal.boot.InternalBootLoader.run(InternalBootLoader.java:858)\n        at org.eclipse.core.boot.BootLoader.run(BootLoader.java:461)\n        at sun.reflect.NativeMethodAccessorImpl.invoke0(Native Method)\n        at\nsun.reflect.NativeMethodAccessorImpl.invoke(NativeMethodAccessorImpl.java:39)\n        at\nsun.reflect.DelegatingMethodAccessorImpl.invoke(DelegatingMethodAccessorImpl.java:25)\n        at java.lang.reflect.Method.invoke(Method.java:324)\n        at org.eclipse.core.launcher.Main.basicRun(Main.java:295)\n        at org.eclipse.core.launcher.Main.run(Main.java:751)\n        at org.eclipse.core.launcher.Main.main(Main.java:587)\n\nPlease advise.",
    "Failure loading SWT\u0027s native library. Moving to SWT for comments.",
    "Could be related to bug 40940 (?)\n",
    "The Xprint library is not being found since it hasn\u0027t been explicitly installed \non your box.  This is a problem with our library which will be fixed quite \nsoon.  In the meantime you can work around this by adding /usr/openwin/lib to \nyour LD_LIBRARY_PATH before running Eclipse.\n",
    "This is also a problem in the most recent 2.1.2 build, so the fix needs to go \ninto both streams.  The fix for previous bug 40490 introduced a 2.1.2 \nregression that makes Eclipse no longer run on Solaris if Xprint is not \ninstalled, which is quite bad (bug 40490 fixed the scenario in which Xprint was \ninstalled and active in the background).\n\nThe fix is to add /usr/openwin/lib to the dynamic library search path of the \nswt library, since in the Xprint-not-installed case this is the only location \nwhere libXp.so lives.  So it\u0027s a change to our makefile and the swt library.\n",
    "For reference see http://xprint.mozdev.org/bugs/show_bug.cgi?id\u003d4195\nSolaris stores all X11 libs in /usr/openwin/lib, entries in /usr/libs are only\nsoftlinks to the files in /usr/openwin/lib",
    "Their should be one bug per version, or how will people searching for changes to\n3.0 know that this was fixed? their is no 3x level target.  unless i don\u0027t\nunderstand bugzilla correctly."
  ],
  "commentCreationDates": [
    "2003-09-29T01:48:47+02:00",
    "2003-09-29T16:55:23+02:00",
    "2003-09-29T17:17:49+02:00",
    "2003-10-16T17:36:02+02:00",
    "2003-10-16T20:59:36+02:00",
    "2003-10-29T01:53:04+01:00",
    "2004-01-12T19:17:42+01:00"
  ],
  "traces": [
    {
      "exceptionType": "java.lang.UnsatisfiedLinkError",
      "message": "/opt/eclipse/plugins/org.eclipse.swt.motif_3.0.0/os/solaris/sparc/libswt-motif-3019.so: ld.so.1: /usr/local/bin/java: fatal: libXp.so.1: open failed: No such file or directory",
      "elements": [
        {
          "method": "java.lang.ClassLoader$NativeLibrary.load",
          "source": "Native Method"
        },
        {
          "method": "java.lang.ClassLoader.loadLibrary0",
          "source": "ClassLoader.java:1560"
        },
        {
          "method": "java.lang.ClassLoader.loadLibrary",
          "source": "ClassLoader.java:1469"
        },
        {
          "method": "java.lang.Runtime.loadLibrary0",
          "source": "Runtime.java:788"
        },
        {
          "method": "java.lang.System.loadLibrary",
          "source": "System.java:834"
        },
        {
          "method": "org.eclipse.swt.internal.Library.loadLibrary",
          "source": "Library.java:108"
        },
        {
          "method": "org.eclipse.swt.internal.motif.OS.\u003cclinit\u003e",
          "source": "OS.java:20"
        },
        {
          "method": "org.eclipse.swt.widgets.Display.createDisplay",
          "source": "Display.java:614"
        },
        {
          "method": "org.eclipse.swt.widgets.Display.create",
          "source": "Display.java:600"
        },
        {
          "method": "org.eclipse.swt.graphics.Device.\u003cinit\u003e",
          "source": "Device.java:126"
        },
        {
          "method": "org.eclipse.swt.widgets.Display.\u003cinit\u003e",
          "source": "Display.java:350"
        },
        {
          "method": "org.eclipse.swt.widgets.Display.\u003cinit\u003e",
          "source": "Display.java:347"
        },
        {
          "method": "org.eclipse.ui.internal.Workbench.run",
          "source": "Workbench.java:1989"
        },
        {
          "method": "org.eclipse.core.internal.boot.InternalBootLoader.run",
          "source": "InternalBootLoader.java:858"
        },
        {
          "method": "org.eclipse.core.boot.BootLoader.run",
          "source": "BootLoader.java:461"
        },
        {
          "method": "sun.reflect.NativeMethodAccessorImpl.invoke0",
          "source": "Native Method"
        },
        {
          "method": "sun.reflect.NativeMethodAccessorImpl.invoke",
          "source": "NativeMethodAccessorImpl.java:39"
        },
        {
          "method": "sun.reflect.DelegatingMethodAccessorImpl.invoke",
          "source": "DelegatingMethodAccessorImpl.java:25"
        },
        {
          "method": "java.lang.reflect.Method.invoke",
          "source": "Method.java:324"
        },
        {
          "method": "org.eclipse.core.launcher.Main.basicRun",
          "source": "Main.java:295"
        },
        {
          "method": "org.eclipse.core.launcher.Main.run",
          "source": "Main.java:751"
        },
        {
          "method": "org.eclipse.core.launcher.Main.main",
          "source": "Main.java:587"
        }
      ],
      "number": 0,
      "commentIndex": 0,
      "bugId": "43811",
      "date": "2003-09-29T01:48:47+02:00",
      "product": "Platform",
      "component": "SWT",
      "severity": "critical"
    }
  ],
  "groupId": "43811",
  "bugId": "43811",
  "date": "2003-09-29T01:48:47+02:00",
  "product": "Platform",
  "component": "SWT",
  "severity": "critical"
}