{
  "comments": [
    "Eclipse 3.0 M3\njava.fullversion\u003dJ2RE 1.4.1 IBM Windows 32 build cn1411-20030915 (JIT enabled: \njitc)\nBootLoader constants: OS\u003dwin32, ARCH\u003dx86, WS\u003dwin32, NL\u003den_US\nCommand-line arguments: -os win32 -ws win32 -arch x86 -data ..\\was51 -install \nfile:E:/eclipse2/eclipse/\n\njava.lang.NoSuchMethodError: org.apache.xerces.parsers.DOMBuilderImpl: method \nsetFeature(Ljava/lang/String;Z)V not found\n        at \norg.eclipse.pde.internal.core.plugin.XMLDocumentModelBuilder.initialize\n(XMLDocumentModelBuilder.java:71)\n        at org.eclipse.pde.internal.core.plugin.XMLDocumentModelBuilder.\u003cinit\u003e\n(XMLDocumentModelBuilder.java:67)\n        at org.eclipse.pde.internal.core.plugin.XMLCore.createXMLModelBuilder\n(XMLCore.java:61)\n        at org.eclipse.pde.internal.core.plugin.DocumentModel.\u003cinit\u003e\n(DocumentModel.java:44)\n        at \norg.eclipse.pde.internal.core.plugin.AbstractPluginModelBase.getDocumentModel\n(AbstractPluginModelBase.java:51)\n        at org.eclipse.pde.internal.core.plugin.AbstractPluginModelBase.load\n(AbstractPluginModelBase.java:151)\n        at org.eclipse.pde.internal.core.plugin.WorkspacePluginModelBase.load\n(WorkspacePluginModelBase.java:129)\n        at \norg.eclipse.pde.internal.builders.ManifestConsistencyChecker.validatePlugin\n(ManifestConsistencyChecker.java:252)\n        at \norg.eclipse.pde.internal.builders.ManifestConsistencyChecker.checkFile\n(ManifestConsistencyChecker.java:222)\n        at \norg.eclipse.pde.internal.builders.ManifestConsistencyChecker.checkThisProject\n(ManifestConsistencyChecker.java:155)\n        at org.eclipse.pde.internal.builders.ManifestConsistencyChecker.build\n(ManifestConsistencyChecker.java:120)\n        at org.eclipse.core.internal.events.BuildManager$2.run\n(BuildManager.java:440)\n        at org.eclipse.core.internal.runtime.InternalPlatform.run\n(InternalPlatform.java(Inlined Compiled Code))\n        at org.eclipse.core.runtime.Platform.run(Platform.java(Compiled Code))\n        at org.eclipse.core.internal.events.BuildManager.basicBuild\n(BuildManager.java:128)\n        at org.eclipse.core.internal.events.BuildManager.basicBuild\n(BuildManager.java:184)\n        at org.eclipse.core.internal.events.BuildManager.basicBuild\n(BuildManager.java:194)\n        at org.eclipse.core.internal.events.BuildManager$1.run\n(BuildManager.java:154)\n        at org.eclipse.core.internal.runtime.InternalPlatform.run\n(InternalPlatform.java(Inlined Compiled Code))\n        at org.eclipse.core.runtime.Platform.run(Platform.java(Compiled Code))\n        at org.eclipse.core.internal.events.BuildManager.basicBuild\n(BuildManager.java:168)\n        at org.eclipse.core.internal.events.BuildManager.basicBuildLoop\n(BuildManager.java:256)\n        at org.eclipse.core.internal.events.BuildManager.build\n(BuildManager.java:224)\n        at org.eclipse.core.internal.resources.Workspace.build\n(Workspace.java:175)\n        at org.eclipse.ui.actions.GlobalBuildAction$1.run\n(GlobalBuildAction.java:174)\n        at org.eclipse.jface.operation.ModalContext$ModalContextThread.run\n(ModalContext.java:101)",
    "This is a known problem using an IBM 1.4 JRE with the latest Eclipse builds.\nTemporarily you should use an alternate VM. More information will be sent to the\nEclipse-dev mailing list when it is available.",
    "\n\n*** This bug has been marked as a duplicate of 39187 ***"
  ],
  "commentCreationDates": [
    "2003-09-29T21:38:40+02:00",
    "2003-09-29T21:52:55+02:00",
    "2003-09-29T23:54:08+02:00"
  ],
  "traces": [
    {
      "exceptionType": "java.lang.NoSuchMethodError",
      "message": "org.apache.xerces.parsers.DOMBuilderImpl: method  setFeature(Ljava/lang/String;Z)V not found",
      "elements": [
        {
          "method": "org.eclipse.pde.internal.core.plugin.XMLDocumentModelBuilder.initialize",
          "source": "XMLDocumentModelBuilder.java:71"
        },
        {
          "method": "org.eclipse.pde.internal.core.plugin.XMLDocumentModelBuilder.\u003cinit\u003e",
          "source": "XMLDocumentModelBuilder.java:67"
        },
        {
          "method": "org.eclipse.pde.internal.core.plugin.XMLCore.createXMLModelBuilder",
          "source": "XMLCore.java:61"
        },
        {
          "method": "org.eclipse.pde.internal.core.plugin.DocumentModel.\u003cinit\u003e",
          "source": "DocumentModel.java:44"
        },
        {
          "method": "org.eclipse.pde.internal.core.plugin.AbstractPluginModelBase.getDocumentModel",
          "source": "AbstractPluginModelBase.java:51"
        },
        {
          "method": "org.eclipse.pde.internal.core.plugin.AbstractPluginModelBase.load",
          "source": "AbstractPluginModelBase.java:151"
        },
        {
          "method": "org.eclipse.pde.internal.core.plugin.WorkspacePluginModelBase.load",
          "source": "WorkspacePluginModelBase.java:129"
        },
        {
          "method": "org.eclipse.pde.internal.builders.ManifestConsistencyChecker.validatePlugin",
          "source": "ManifestConsistencyChecker.java:252"
        },
        {
          "method": "org.eclipse.pde.internal.builders.ManifestConsistencyChecker.checkFile",
          "source": "ManifestConsistencyChecker.java:222"
        },
        {
          "method": "org.eclipse.pde.internal.builders.ManifestConsistencyChecker.checkThisProject",
          "source": "ManifestConsistencyChecker.java:155"
        },
        {
          "method": "org.eclipse.pde.internal.builders.ManifestConsistencyChecker.build",
          "source": "ManifestConsistencyChecker.java:120"
        },
        {
          "method": "org.eclipse.core.internal.events.BuildManager$2.run",
          "source": "BuildManager.java:440"
        },
        {
          "method": "org.eclipse.core.internal.runtime.InternalPlatform.run",
          "source": "InternalPlatform.java(Inlined Compiled Code)"
        },
        {
          "method": "org.eclipse.core.runtime.Platform.run",
          "source": "Platform.java(Compiled Code)"
        },
        {
          "method": "org.eclipse.core.internal.events.BuildManager.basicBuild",
          "source": "BuildManager.java:128"
        },
        {
          "method": "org.eclipse.core.internal.events.BuildManager.basicBuild",
          "source": "BuildManager.java:184"
        },
        {
          "method": "org.eclipse.core.internal.events.BuildManager.basicBuild",
          "source": "BuildManager.java:194"
        },
        {
          "method": "org.eclipse.core.internal.events.BuildManager$1.run",
          "source": "BuildManager.java:154"
        },
        {
          "method": "org.eclipse.core.internal.runtime.InternalPlatform.run",
          "source": "InternalPlatform.java(Inlined Compiled Code)"
        },
        {
          "method": "org.eclipse.core.runtime.Platform.run",
          "source": "Platform.java(Compiled Code)"
        },
        {
          "method": "org.eclipse.core.internal.events.BuildManager.basicBuild",
          "source": "BuildManager.java:168"
        },
        {
          "method": "org.eclipse.core.internal.events.BuildManager.basicBuildLoop",
          "source": "BuildManager.java:256"
        },
        {
          "method": "org.eclipse.core.internal.events.BuildManager.build",
          "source": "BuildManager.java:224"
        },
        {
          "method": "org.eclipse.core.internal.resources.Workspace.build",
          "source": "Workspace.java:175"
        },
        {
          "method": "org.eclipse.ui.actions.GlobalBuildAction$1.run",
          "source": "GlobalBuildAction.java:174"
        },
        {
          "method": "org.eclipse.jface.operation.ModalContext$ModalContextThread.run",
          "source": "ModalContext.java:101"
        }
      ],
      "number": 0,
      "commentIndex": 0,
      "bugId": "43860",
      "duplicateId": "39187",
      "date": "2003-09-29T21:38:40+02:00",
      "product": "Platform",
      "component": "Resources",
      "severity": "normal"
    }
  ],
  "groupId": "37696",
  "bugId": "43860",
  "duplicateId": "39187",
  "date": "2003-09-29T21:38:40+02:00",
  "product": "Platform",
  "component": "Resources",
  "severity": "normal"
}