{
  "comments": [
    "I20030930\n\nI launched Eclipse and got an error in the progress view :\n\nERROR: Initializing Quick Diff : An internal error occurs during: \"Initializing\nQuick Diff\"\n\nThe .log file contains:\n\n!MESSAGE An internal error occurred during: \"Initializing Quick Diff\".\n!STACK 0\norg.eclipse.core.internal.runtime.AssertionFailedException: assertion failed:\n        at org.eclipse.core.internal.runtime.Assert.isTrue(Assert.java:101)\n        at org.eclipse.core.internal.runtime.Assert.isTrue(Assert.java:88)\n        at org.eclipse.core.internal.jobs.JobQueue.enqueue(JobQueue.java:79)\n        at\norg.eclipse.core.internal.jobs.JobManager.changeState(JobManager.java:195)\n        at org.eclipse.core.internal.jobs.JobManager.schedule(JobManager.java:502)\n        at org.eclipse.core.internal.jobs.InternalJob.schedule(InternalJob.java:205)\n        at org.eclipse.core.runtime.jobs.Job.schedule(Job.java:342)\n        at\norg.eclipse.core.internal.events.AutoBuildJob.endTopLevel(AutoBuildJob.java:92)\n        at\norg.eclipse.core.internal.events.BuildManager.endTopLevel(BuildManager.java:377)\n        at\norg.eclipse.core.internal.resources.Workspace.endOperation(Workspace.java:867)\n        at org.eclipse.core.internal.resources.Workspace.run(Workspace.java:1562)\n        at\norg.eclipse.team.internal.ccvs.core.resources.EclipseFolder.run(EclipseFolder.java:297)\n        at\norg.eclipse.team.internal.ccvs.core.client.Command.execute(Command.java:346)\n        at\norg.eclipse.team.internal.ccvs.core.resources.RemoteFolderTreeBuilder.fetchDelta(RemoteFolderTreeBuilder.java:627)\n        at\norg.eclipse.team.internal.ccvs.core.resources.RemoteFolderTreeBuilder.buildTree(RemoteFolderTreeBuilder.java:304)\n        at\norg.eclipse.team.internal.ccvs.core.resources.RemoteFolderTreeBuilder.buildRemoteTree(RemoteFolderTreeBuilder.java:163)\n        at\norg.eclipse.team.internal.ccvs.core.resources.CVSWorkspaceRoot.getRemoteTree(CVSWorkspaceRoot.java:616)\n        at\norg.eclipse.team.internal.ccvs.core.resources.CVSWorkspaceRoot.getRemoteTree(CVSWorkspaceRoot.java:583)\n        at\norg.eclipse.team.internal.ccvs.ui.RemoteRevisionQuickDiffProvider.readDocument(RemoteRevisionQuickDiffProvider.java:205)\n        at\norg.eclipse.team.internal.ccvs.ui.RemoteRevisionQuickDiffProvider.getReference(RemoteRevisionQuickDiffProvider.java:114)\n        at\norg.eclipse.ui.internal.texteditor.quickdiff.DocumentLineDiffer$1.run(DocumentLineDiffer.java:510)\n        at org.eclipse.core.internal.jobs.Worker.run(Worker.java:61)",
    "Tom, this looks like a bug in the CVS quick diff reference provider. Please\nforward to Platform VCM if I am right.\n",
    "More looks like a problem in the Job infrastructure. Moving to platform-core,\nchanging summary.",
    "\n\n*** This bug has been marked as a duplicate of 43589 ***"
  ],
  "commentCreationDates": [
    "2003-10-02T19:52:30+02:00",
    "2003-10-02T19:55:19+02:00",
    "2003-10-03T10:22:08+02:00",
    "2003-10-03T16:31:07+02:00"
  ],
  "traces": [
    {
      "exceptionType": "org.eclipse.core.internal.runtime.AssertionFailedException",
      "message": "assertion failed:",
      "elements": [
        {
          "method": "org.eclipse.core.internal.runtime.Assert.isTrue",
          "source": "Assert.java:101"
        },
        {
          "method": "org.eclipse.core.internal.runtime.Assert.isTrue",
          "source": "Assert.java:88"
        },
        {
          "method": "org.eclipse.core.internal.jobs.JobQueue.enqueue",
          "source": "JobQueue.java:79"
        },
        {
          "method": "org.eclipse.core.internal.jobs.JobManager.changeState",
          "source": "JobManager.java:195"
        },
        {
          "method": "org.eclipse.core.internal.jobs.JobManager.schedule",
          "source": "JobManager.java:502"
        },
        {
          "method": "org.eclipse.core.internal.jobs.InternalJob.schedule",
          "source": "InternalJob.java:205"
        },
        {
          "method": "org.eclipse.core.runtime.jobs.Job.schedule",
          "source": "Job.java:342"
        },
        {
          "method": "org.eclipse.core.internal.events.AutoBuildJob.endTopLevel",
          "source": "AutoBuildJob.java:92"
        },
        {
          "method": "org.eclipse.core.internal.events.BuildManager.endTopLevel",
          "source": "BuildManager.java:377"
        },
        {
          "method": "org.eclipse.core.internal.resources.Workspace.endOperation",
          "source": "Workspace.java:867"
        },
        {
          "method": "org.eclipse.core.internal.resources.Workspace.run",
          "source": "Workspace.java:1562"
        },
        {
          "method": "org.eclipse.team.internal.ccvs.core.resources.EclipseFolder.run",
          "source": "EclipseFolder.java:297"
        },
        {
          "method": "org.eclipse.team.internal.ccvs.core.client.Command.execute",
          "source": "Command.java:346"
        },
        {
          "method": "org.eclipse.team.internal.ccvs.core.resources.RemoteFolderTreeBuilder.fetchDelta",
          "source": "RemoteFolderTreeBuilder.java:627"
        },
        {
          "method": "org.eclipse.team.internal.ccvs.core.resources.RemoteFolderTreeBuilder.buildTree",
          "source": "RemoteFolderTreeBuilder.java:304"
        },
        {
          "method": "org.eclipse.team.internal.ccvs.core.resources.RemoteFolderTreeBuilder.buildRemoteTree",
          "source": "RemoteFolderTreeBuilder.java:163"
        },
        {
          "method": "org.eclipse.team.internal.ccvs.core.resources.CVSWorkspaceRoot.getRemoteTree",
          "source": "CVSWorkspaceRoot.java:616"
        },
        {
          "method": "org.eclipse.team.internal.ccvs.core.resources.CVSWorkspaceRoot.getRemoteTree",
          "source": "CVSWorkspaceRoot.java:583"
        },
        {
          "method": "org.eclipse.team.internal.ccvs.ui.RemoteRevisionQuickDiffProvider.readDocument",
          "source": "RemoteRevisionQuickDiffProvider.java:205"
        },
        {
          "method": "org.eclipse.team.internal.ccvs.ui.RemoteRevisionQuickDiffProvider.getReference",
          "source": "RemoteRevisionQuickDiffProvider.java:114"
        },
        {
          "method": "org.eclipse.ui.internal.texteditor.quickdiff.DocumentLineDiffer$1.run",
          "source": "DocumentLineDiffer.java:510"
        },
        {
          "method": "org.eclipse.core.internal.jobs.Worker.run",
          "source": "Worker.java:61"
        }
      ],
      "number": 0,
      "commentIndex": 0,
      "bugId": "44094",
      "duplicateId": "43589",
      "date": "2003-10-02T19:52:30+02:00",
      "product": "Platform",
      "component": "Resources",
      "severity": "normal"
    }
  ],
  "groupId": "43589",
  "bugId": "44094",
  "duplicateId": "43589",
  "date": "2003-10-02T19:52:30+02:00",
  "product": "Platform",
  "component": "Resources",
  "severity": "normal"
}