{
  "comments": [
    "3.0M3 on linux gtk\nfound this in log\n\njava.lang.NullPointerException\n        at\norg.eclipse.jdt.internal.corext.template.java.CompilationUnitCompletion.isSubclassOf(CompilationUnitCompletion.java:196)\n        at\norg.eclipse.jdt.internal.corext.template.java.CompilationUnitCompletion.findLocalCollections(CompilationUnitCompletion.java:151)\n        at\norg.eclipse.jdt.internal.corext.template.java.JavaContext.guessCollection(JavaContext.java:403)\n        at\norg.eclipse.jdt.internal.corext.template.java.JavaContextType$Collection.evaluate(JavaContextType.java:71)\n        at\norg.eclipse.jdt.internal.corext.template.ContextType.edit(ContextType.java:130)\n        at\norg.eclipse.jdt.internal.corext.template.java.JavaContext.evaluate(JavaContext.java:104)\n        at\norg.eclipse.jdt.internal.ui.text.template.TemplateProposal.apply(TemplateProposal.java:123)\n        at\norg.eclipse.jface.text.contentassist.CompletionProposalPopup.insertProposal(CompletionProposalPopup.java:323)\n        at\norg.eclipse.jface.text.contentassist.CompletionProposalPopup.selectProposalWithMask(CompletionProposalPopup.java:292)\n        at\norg.eclipse.jface.text.contentassist.CompletionProposalPopup.verifyKey(CompletionProposalPopup.java:585)\n        at\norg.eclipse.jface.text.contentassist.ContentAssistant$InternalListener.verifyKey(ContentAssistant.java:601)\n        at\norg.eclipse.jface.text.TextViewer$VerifyKeyListenersManager.verifyKey(TextViewer.java:402)\n        at\norg.eclipse.swt.custom.StyledTextListener.handleEvent(StyledTextListener.java:55)\n        at org.eclipse.swt.widgets.EventTable.sendEvent(EventTable.java:82)\n        at org.eclipse.swt.widgets.Widget.sendEvent(Widget.java:953)\n        at org.eclipse.swt.widgets.Widget.sendEvent(Widget.java:977)\n        at org.eclipse.swt.widgets.Widget.sendEvent(Widget.java:962)\n        at org.eclipse.swt.widgets.Widget.notifyListeners(Widget.java:832)\n        at org.eclipse.swt.custom.StyledText.handleKeyDown(StyledText.java:5208)\n        at org.eclipse.swt.custom.StyledText$8.handleEvent(StyledText.java:4957)\n        at org.eclipse.swt.widgets.EventTable.sendEvent(EventTable.java:82)\n        at org.eclipse.swt.widgets.Widget.sendEvent(Widget.java:953)\n        at org.eclipse.swt.widgets.Widget.sendEvent(Widget.java:977)\n        at org.eclipse.swt.widgets.Widget.sendEvent(Widget.java:962)\n        at org.eclipse.swt.widgets.Control.sendKeyEvent(Control.java:2203)\n        at org.eclipse.swt.widgets.Control.gtk_key_press_event(Control.java:1760)\n        at org.eclipse.swt.widgets.Composite.gtk_key_press_event(Composite.java:443)\n        at org.eclipse.swt.widgets.Widget.windowProc(Widget.java:1207)\n        at org.eclipse.swt.widgets.Display.windowProc(Display.java:2350)\n        at org.eclipse.swt.internal.gtk.OS.gtk_main_do_event(Native Method)\n        at org.eclipse.swt.widgets.Display.eventProc(Display.java:681)\n        at org.eclipse.swt.internal.gtk.OS.gtk_main_iteration(Native Method)\n        at org.eclipse.swt.widgets.Display.readAndDispatch(Display.java:1651)\n        at org.eclipse.ui.internal.Workbench.runEventLoop(Workbench.java:2036)\n        at org.eclipse.ui.internal.Workbench.run(Workbench.java:2019)\n        at\norg.eclipse.core.internal.boot.InternalBootLoader.run(InternalBootLoader.java:858)\n        at org.eclipse.core.boot.BootLoader.run(BootLoader.java:461)\n        at sun.reflect.NativeMethodAccessorImpl.invoke0(Native Method)\n        at\nsun.reflect.NativeMethodAccessorImpl.invoke(NativeMethodAccessorImpl.java:39)\n        at\nsun.reflect.DelegatingMethodAccessorImpl.invoke(DelegatingMethodAccessorImpl.java:25)\n        at java.lang.reflect.Method.invoke(Method.java:324)\n        at org.eclipse.core.launcher.Main.basicRun(Main.java:295)\n        at org.eclipse.core.launcher.Main.run(Main.java:751)\n        at org.eclipse.core.launcher.Main.main(Main.java:587)",
    "Fixed in HEAD.\nAvailable in builds \u003e 20031006"
  ],
  "commentCreationDates": [
    "2003-10-04T01:29:50+02:00",
    "2003-10-06T12:56:55+02:00"
  ],
  "traces": [
    {
      "exceptionType": "java.lang.NullPointerException",
      "elements": [
        {
          "method": "org.eclipse.jdt.internal.corext.template.java.CompilationUnitCompletion.isSubclassOf",
          "source": "CompilationUnitCompletion.java:196"
        },
        {
          "method": "org.eclipse.jdt.internal.corext.template.java.CompilationUnitCompletion.findLocalCollections",
          "source": "CompilationUnitCompletion.java:151"
        },
        {
          "method": "org.eclipse.jdt.internal.corext.template.java.JavaContext.guessCollection",
          "source": "JavaContext.java:403"
        },
        {
          "method": "org.eclipse.jdt.internal.corext.template.java.JavaContextType$Collection.evaluate",
          "source": "JavaContextType.java:71"
        },
        {
          "method": "org.eclipse.jdt.internal.corext.template.ContextType.edit",
          "source": "ContextType.java:130"
        },
        {
          "method": "org.eclipse.jdt.internal.corext.template.java.JavaContext.evaluate",
          "source": "JavaContext.java:104"
        },
        {
          "method": "org.eclipse.jdt.internal.ui.text.template.TemplateProposal.apply",
          "source": "TemplateProposal.java:123"
        },
        {
          "method": "org.eclipse.jface.text.contentassist.CompletionProposalPopup.insertProposal",
          "source": "CompletionProposalPopup.java:323"
        },
        {
          "method": "org.eclipse.jface.text.contentassist.CompletionProposalPopup.selectProposalWithMask",
          "source": "CompletionProposalPopup.java:292"
        },
        {
          "method": "org.eclipse.jface.text.contentassist.CompletionProposalPopup.verifyKey",
          "source": "CompletionProposalPopup.java:585"
        },
        {
          "method": "org.eclipse.jface.text.contentassist.ContentAssistant$InternalListener.verifyKey",
          "source": "ContentAssistant.java:601"
        },
        {
          "method": "org.eclipse.jface.text.TextViewer$VerifyKeyListenersManager.verifyKey",
          "source": "TextViewer.java:402"
        },
        {
          "method": "org.eclipse.swt.custom.StyledTextListener.handleEvent",
          "source": "StyledTextListener.java:55"
        },
        {
          "method": "org.eclipse.swt.widgets.EventTable.sendEvent",
          "source": "EventTable.java:82"
        },
        {
          "method": "org.eclipse.swt.widgets.Widget.sendEvent",
          "source": "Widget.java:953"
        },
        {
          "method": "org.eclipse.swt.widgets.Widget.sendEvent",
          "source": "Widget.java:977"
        },
        {
          "method": "org.eclipse.swt.widgets.Widget.sendEvent",
          "source": "Widget.java:962"
        },
        {
          "method": "org.eclipse.swt.widgets.Widget.notifyListeners",
          "source": "Widget.java:832"
        },
        {
          "method": "org.eclipse.swt.custom.StyledText.handleKeyDown",
          "source": "StyledText.java:5208"
        },
        {
          "method": "org.eclipse.swt.custom.StyledText$8.handleEvent",
          "source": "StyledText.java:4957"
        },
        {
          "method": "org.eclipse.swt.widgets.EventTable.sendEvent",
          "source": "EventTable.java:82"
        },
        {
          "method": "org.eclipse.swt.widgets.Widget.sendEvent",
          "source": "Widget.java:953"
        },
        {
          "method": "org.eclipse.swt.widgets.Widget.sendEvent",
          "source": "Widget.java:977"
        },
        {
          "method": "org.eclipse.swt.widgets.Widget.sendEvent",
          "source": "Widget.java:962"
        },
        {
          "method": "org.eclipse.swt.widgets.Control.sendKeyEvent",
          "source": "Control.java:2203"
        },
        {
          "method": "org.eclipse.swt.widgets.Control.gtk_key_press_event",
          "source": "Control.java:1760"
        },
        {
          "method": "org.eclipse.swt.widgets.Composite.gtk_key_press_event",
          "source": "Composite.java:443"
        },
        {
          "method": "org.eclipse.swt.widgets.Widget.windowProc",
          "source": "Widget.java:1207"
        },
        {
          "method": "org.eclipse.swt.widgets.Display.windowProc",
          "source": "Display.java:2350"
        },
        {
          "method": "org.eclipse.swt.internal.gtk.OS.gtk_main_do_event",
          "source": "Native Method"
        },
        {
          "method": "org.eclipse.swt.widgets.Display.eventProc",
          "source": "Display.java:681"
        },
        {
          "method": "org.eclipse.swt.internal.gtk.OS.gtk_main_iteration",
          "source": "Native Method"
        },
        {
          "method": "org.eclipse.swt.widgets.Display.readAndDispatch",
          "source": "Display.java:1651"
        },
        {
          "method": "org.eclipse.ui.internal.Workbench.runEventLoop",
          "source": "Workbench.java:2036"
        },
        {
          "method": "org.eclipse.ui.internal.Workbench.run",
          "source": "Workbench.java:2019"
        },
        {
          "method": "org.eclipse.core.internal.boot.InternalBootLoader.run",
          "source": "InternalBootLoader.java:858"
        },
        {
          "method": "org.eclipse.core.boot.BootLoader.run",
          "source": "BootLoader.java:461"
        },
        {
          "method": "sun.reflect.NativeMethodAccessorImpl.invoke0",
          "source": "Native Method"
        },
        {
          "method": "sun.reflect.NativeMethodAccessorImpl.invoke",
          "source": "NativeMethodAccessorImpl.java:39"
        },
        {
          "method": "sun.reflect.DelegatingMethodAccessorImpl.invoke",
          "source": "DelegatingMethodAccessorImpl.java:25"
        },
        {
          "method": "java.lang.reflect.Method.invoke",
          "source": "Method.java:324"
        },
        {
          "method": "org.eclipse.core.launcher.Main.basicRun",
          "source": "Main.java:295"
        },
        {
          "method": "org.eclipse.core.launcher.Main.run",
          "source": "Main.java:751"
        },
        {
          "method": "org.eclipse.core.launcher.Main.main",
          "source": "Main.java:587"
        }
      ],
      "number": 0,
      "commentIndex": 0,
      "bugId": "44167",
      "date": "2003-10-04T01:29:50+02:00",
      "product": "JDT",
      "component": "Text",
      "severity": "normal"
    }
  ],
  "groupId": "44167",
  "bugId": "44167",
  "date": "2003-10-04T01:29:50+02:00",
  "product": "JDT",
  "component": "Text",
  "severity": "normal"
}