{
  "comments": [
    "build 2003-10-07 (08:00)\nSUN 1.4.2\n\nHere\u0027s what I did:\n\n1) startup with a new workspace\n2) create new project, asdf\n3) create a new class, Balk\n4) write a new method, like so:\n\n\tpublic void foo(Object bar) {\n\t\tif (!bar instanceof Cloneable)\n\t\t\treturn;\n\n5) type \"syso\" and hit ctrl-space\n6) observe: you get an exception:\n\n!ENTRY org.eclipse.jdt.ui 2 0 Oct 08, 2003 10:52:38.313\n!MESSAGE LinkedPositionUI is not active: LinkedPositionUI.caret.position3\n!STACK 0\njava.lang.IllegalStateException\n        at org.eclipse.jdt.internal.ui.text.link.LinkedPositionUI.getSelectedReg\nion(LinkedPositionUI.java:335)\n        at org.eclipse.jdt.internal.ui.text.template.TemplateProposal.apply(Temp\nlateProposal.java:160)\n        at org.eclipse.jface.text.contentassist.CompletionProposalPopup.insertPr\noposal(CompletionProposalPopup.java:367)\n        at org.eclipse.jface.text.contentassist.CompletionProposalPopup.access$1\n0(CompletionProposalPopup.java:348)\n        at org.eclipse.jface.text.contentassist.CompletionProposalPopup$2.run(Co\nmpletionProposalPopup.java:199)\n        at org.eclipse.swt.custom.BusyIndicator.showWhile(BusyIndicator.java:84)\n\n        at org.eclipse.jface.text.contentassist.CompletionProposalPopup.showProp\nosals(CompletionProposalPopup.java:183)\n        at org.eclipse.jface.text.contentassist.ContentAssistant.showPossibleCom\npletions(ContentAssistant.java:1243)\n        at org.eclipse.jdt.internal.ui.javaeditor.CompilationUnitEditor$AdaptedS\nourceViewer.doOperation(CompilationUnitEditor.java:154)\n        at org.eclipse.ui.texteditor.ContentAssistAction$1.run(ContentAssistActi\non.java:83)\n        at org.eclipse.swt.custom.BusyIndicator.showWhile(BusyIndicator.java:84)\n\n        at org.eclipse.ui.texteditor.ContentAssistAction.run(ContentAssistAction\n.java:81)\n        at org.eclipse.ui.texteditor.RetargetTextEditorAction.run(RetargetTextEd\nitorAction.java:239)\n        at org.eclipse.jface.action.Action.runWithEvent(Action.java:842)\n        at org.eclipse.ui.actions.RetargetAction.runWithEvent(RetargetAction.jav\na:203)\n        at org.eclipse.jface.action.ActionContributionItem.handleWidgetSelection\n(ActionContributionItem.java:543)\n        at org.eclipse.jface.action.ActionContributionItem.access$4(ActionContri\nbutionItem.java:496)\n        at org.eclipse.jface.action.ActionContributionItem$6.handleEvent(ActionC\nontributionItem.java:468)\n        at org.eclipse.swt.widgets.EventTable.sendEvent(EventTable.java:82)\n        at org.eclipse.swt.widgets.Widget.sendEvent(Widget.java:847)\n        at org.eclipse.swt.widgets.Display.runDeferredEvents(Display.java:2173)\n        at org.eclipse.swt.widgets.Display.readAndDispatch(Display.java:1863)\n        at org.eclipse.ui.internal.Workbench.runEventLoop(Workbench.java:2315)\n        at org.eclipse.ui.internal.Workbench.run(Workbench.java:2298)\n        at org.eclipse.core.internal.boot.InternalBootLoader.run(InternalBootLoa\nder.java:858)\n        at org.eclipse.core.boot.BootLoader.run(BootLoader.java:461)\n        at sun.reflect.NativeMethodAccessorImpl.invoke0(Native Method)\n        at sun.reflect.NativeMethodAccessorImpl.invoke(NativeMethodAccessorImpl.\njava:39)\n        at sun.reflect.DelegatingMethodAccessorImpl.invoke(DelegatingMethodAcces\nsorImpl.java:25)\n        at java.lang.reflect.Method.invoke(Method.java:324)\n        at org.eclipse.core.launcher.Main.basicRun(Main.java:298)\n        at org.eclipse.core.launcher.Main.run(Main.java:764)\n        at org.eclipse.core.launcher.Main.main(Main.java:598)\n\n\nNote that the String \"System.out.println()\" is still inserted correctly.",
    "Tom, I think this is a dup which is already in your inbox.\n",
    "\n\n*** This bug has been marked as a duplicate of 43977 ***"
  ],
  "commentCreationDates": [
    "2003-10-08T11:01:29+02:00",
    "2003-10-08T12:22:28+02:00",
    "2003-10-08T12:34:09+02:00"
  ],
  "traces": [
    {
      "exceptionType": "java.lang.IllegalStateException",
      "elements": [
        {
          "method": "org.eclipse.jdt.internal.ui.text.link.LinkedPositionUI.getSelectedRegion",
          "source": "LinkedPositionUI.java:335"
        },
        {
          "method": "org.eclipse.jdt.internal.ui.text.template.TemplateProposal.apply",
          "source": "Temp lateProposal.java:160"
        },
        {
          "method": "org.eclipse.jface.text.contentassist.CompletionProposalPopup.insertProposal",
          "source": "CompletionProposalPopup.java:367"
        },
        {
          "method": "org.eclipse.jface.text.contentassist.CompletionProposalPopup.access$10",
          "source": "CompletionProposalPopup.java:348"
        },
        {
          "method": "org.eclipse.jface.text.contentassist.CompletionProposalPopup$2.run",
          "source": "Co mpletionProposalPopup.java:199"
        },
        {
          "method": "org.eclipse.swt.custom.BusyIndicator.showWhile",
          "source": "BusyIndicator.java:84"
        },
        {
          "method": "org.eclipse.jface.text.contentassist.CompletionProposalPopup.showProposals",
          "source": "CompletionProposalPopup.java:183"
        },
        {
          "method": "org.eclipse.jface.text.contentassist.ContentAssistant.showPossibleCompletions",
          "source": "ContentAssistant.java:1243"
        },
        {
          "method": "org.eclipse.jdt.internal.ui.javaeditor.CompilationUnitEditor$AdaptedSourceViewer.doOperation",
          "source": "CompilationUnitEditor.java:154"
        },
        {
          "method": "org.eclipse.ui.texteditor.ContentAssistAction$1.run",
          "source": "ContentAssistActi on.java:83"
        },
        {
          "method": "org.eclipse.swt.custom.BusyIndicator.showWhile",
          "source": "BusyIndicator.java:84"
        },
        {
          "method": "org.eclipse.ui.texteditor.ContentAssistAction.run",
          "source": "ContentAssistAction .java:81"
        },
        {
          "method": "org.eclipse.ui.texteditor.RetargetTextEditorAction.run",
          "source": "RetargetTextEd itorAction.java:239"
        },
        {
          "method": "org.eclipse.jface.action.Action.runWithEvent",
          "source": "Action.java:842"
        },
        {
          "method": "org.eclipse.ui.actions.RetargetAction.runWithEvent",
          "source": "RetargetAction.jav a:203"
        },
        {
          "method": "org.eclipse.jface.action.ActionContributionItem.handleWidgetSelection",
          "source": "ActionContributionItem.java:543"
        },
        {
          "method": "org.eclipse.jface.action.ActionContributionItem.access$4",
          "source": "ActionContri butionItem.java:496"
        },
        {
          "method": "org.eclipse.jface.action.ActionContributionItem$6.handleEvent",
          "source": "ActionC ontributionItem.java:468"
        },
        {
          "method": "org.eclipse.swt.widgets.EventTable.sendEvent",
          "source": "EventTable.java:82"
        },
        {
          "method": "org.eclipse.swt.widgets.Widget.sendEvent",
          "source": "Widget.java:847"
        },
        {
          "method": "org.eclipse.swt.widgets.Display.runDeferredEvents",
          "source": "Display.java:2173"
        },
        {
          "method": "org.eclipse.swt.widgets.Display.readAndDispatch",
          "source": "Display.java:1863"
        },
        {
          "method": "org.eclipse.ui.internal.Workbench.runEventLoop",
          "source": "Workbench.java:2315"
        },
        {
          "method": "org.eclipse.ui.internal.Workbench.run",
          "source": "Workbench.java:2298"
        },
        {
          "method": "org.eclipse.core.internal.boot.InternalBootLoader.run",
          "source": "InternalBootLoa der.java:858"
        },
        {
          "method": "org.eclipse.core.boot.BootLoader.run",
          "source": "BootLoader.java:461"
        },
        {
          "method": "sun.reflect.NativeMethodAccessorImpl.invoke0",
          "source": "Native Method"
        },
        {
          "method": "sun.reflect.NativeMethodAccessorImpl.invoke",
          "source": "NativeMethodAccessorImpl. java:39"
        },
        {
          "method": "sun.reflect.DelegatingMethodAccessorImpl.invoke",
          "source": "DelegatingMethodAcces sorImpl.java:25"
        },
        {
          "method": "java.lang.reflect.Method.invoke",
          "source": "Method.java:324"
        },
        {
          "method": "org.eclipse.core.launcher.Main.basicRun",
          "source": "Main.java:298"
        },
        {
          "method": "org.eclipse.core.launcher.Main.run",
          "source": "Main.java:764"
        },
        {
          "method": "org.eclipse.core.launcher.Main.main",
          "source": "Main.java:598"
        }
      ],
      "number": 0,
      "commentIndex": 0,
      "bugId": "44394",
      "duplicateId": "43977",
      "date": "2003-10-08T11:01:29+02:00",
      "product": "JDT",
      "component": "Text",
      "severity": "normal"
    }
  ],
  "groupId": "43977",
  "bugId": "44394",
  "duplicateId": "43977",
  "date": "2003-10-08T11:01:29+02:00",
  "product": "JDT",
  "component": "Text",
  "severity": "normal"
}