{
  "comments": [
    "When I\u0027m using the JSP editor from the Java Family examples, I get a lot of\nStringIndexOutOfBoundsException in .log :\n\njava.lang.StringIndexOutOfBoundsException: String index out of range: 4\n        at java.lang.String.charAt(String.java:444)\n        at\norg.eclipse.jsp.AbstractJspParser.parseAttributes(AbstractJspParser.java:154)\n        at org.eclipse.jsp.AbstractJspParser.parseTag(AbstractJspParser.java:87)\n        at org.eclipse.jsp.AbstractJspParser.parse(AbstractJspParser.java:282)\n        at org.eclipse.jsp.JspTranslator.translate(JspTranslator.java:125)\n        at\norg.eclipse.jdt.internal.ui.examples.jspeditor.Jsp2JavaReconcileStep.reconcileModel(Jsp2JavaReconcileStep.java:76)\n        at\norg.eclipse.jface.text.reconciler.AbstractReconcileStep.reconcile(AbstractReconcileStep.java:82)\n        at\norg.eclipse.jdt.internal.ui.examples.jspeditor.JspReconcilingStrategy.reconcile(JspReconcilingStrategy.java:79)\n        at\norg.eclipse.jface.text.reconciler.MonoReconciler.process(MonoReconciler.java:76)\n        at\norg.eclipse.jface.text.reconciler.AbstractReconciler$BackgroundThread.run(AbstractReconciler.java:189)",
    "fixed for N20031030"
  ],
  "commentCreationDates": [
    "2003-10-28T22:21:36+01:00",
    "2003-10-29T10:19:04+01:00"
  ],
  "traces": [
    {
      "exceptionType": "java.lang.StringIndexOutOfBoundsException",
      "message": "String index out of range: 4",
      "elements": [
        {
          "method": "java.lang.String.charAt",
          "source": "String.java:444"
        },
        {
          "method": "org.eclipse.jsp.AbstractJspParser.parseAttributes",
          "source": "AbstractJspParser.java:154"
        },
        {
          "method": "org.eclipse.jsp.AbstractJspParser.parseTag",
          "source": "AbstractJspParser.java:87"
        },
        {
          "method": "org.eclipse.jsp.AbstractJspParser.parse",
          "source": "AbstractJspParser.java:282"
        },
        {
          "method": "org.eclipse.jsp.JspTranslator.translate",
          "source": "JspTranslator.java:125"
        },
        {
          "method": "org.eclipse.jdt.internal.ui.examples.jspeditor.Jsp2JavaReconcileStep.reconcileModel",
          "source": "Jsp2JavaReconcileStep.java:76"
        },
        {
          "method": "org.eclipse.jface.text.reconciler.AbstractReconcileStep.reconcile",
          "source": "AbstractReconcileStep.java:82"
        },
        {
          "method": "org.eclipse.jdt.internal.ui.examples.jspeditor.JspReconcilingStrategy.reconcile",
          "source": "JspReconcilingStrategy.java:79"
        },
        {
          "method": "org.eclipse.jface.text.reconciler.MonoReconciler.process",
          "source": "MonoReconciler.java:76"
        },
        {
          "method": "org.eclipse.jface.text.reconciler.AbstractReconciler$BackgroundThread.run",
          "source": "AbstractReconciler.java:189"
        }
      ],
      "number": 0,
      "commentIndex": 0,
      "bugId": "45696",
      "date": "2003-10-28T22:21:36+01:00",
      "product": "JDT",
      "component": "UI",
      "severity": "normal"
    }
  ],
  "groupId": "45696",
  "bugId": "45696",
  "date": "2003-10-28T22:21:36+01:00",
  "product": "JDT",
  "component": "UI",
  "severity": "normal"
}