{
  "comments": [
    "I found this in my Eclipse console. I don\u0027t know what I did to make it happen:\n\njava.lang.NullPointerException\n        at org.eclipse.jdt.internal.core.Buffer.getChar(Buffer.java:115)\n        at org.eclipse.jdt.internal.corext.javadoc.JavaDocCommentReader.read(Jav\naDocCommentReader.java:48)\n        at java.io.FilterReader.read(FilterReader.java:48)\n        at java.io.PushbackReader.read(PushbackReader.java:73)\n        at org.eclipse.jdt.internal.ui.text.SubstitutionTextReader.nextChar(Subs\ntitutionTextReader.java:82)\n        at org.eclipse.jdt.internal.ui.text.SubstitutionTextReader.read(Substitu\ntionTextReader.java:106)\n        at org.eclipse.jdt.internal.corext.javadoc.SingleCharReader.read(SingleC\nharReader.java:30)\n        at java.io.Reader.read(Reader.java:100)\n        at org.eclipse.jdt.internal.ui.text.HTMLPrinter.read(HTMLPrinter.java:64\n)\n        at org.eclipse.jdt.internal.ui.text.HTMLPrinter.addParagraph(HTMLPrinter\n.java:150)\n        at org.eclipse.jdt.internal.ui.text.java.hover.JavadocHover.getHoverInfo\n(JavadocHover.java:67)\n        at org.eclipse.jdt.internal.ui.text.java.hover.AbstractJavaEditorTextHov\ner.getHoverInfo(AbstractJavaEditorTextHover.java:105)\n        at org.eclipse.jdt.internal.ui.text.java.hover.BestMatchHover.getHoverIn\nfo(BestMatchHover.java:140)\n        at org.eclipse.jdt.internal.ui.text.java.hover.JavaEditorTextHoverProxy.\ngetHoverInfo(JavaEditorTextHoverProxy.java:69)\n        at org.eclipse.jface.text.TextViewerHoverManager$2.run(TextViewerHoverMa\nnager.java:119)",
    "Build I20031029",
    "getChar(int) was called on a closed buffer. Fixed spec and implementation to \nreturn an undefined char instead of throwing an exception.\n\nAdded regression test BufferTests.testGetChar2()",
    "Verified with build I200312160010.\n\nAs there\u0027s no user test case, just verify both code modif and added regression \ntest.\n"
  ],
  "commentCreationDates": [
    "2003-11-04T17:19:46+01:00",
    "2003-11-04T17:20:08+01:00",
    "2003-12-15T16:25:53+01:00",
    "2003-12-16T18:47:07+01:00"
  ],
  "traces": [
    {
      "exceptionType": "java.lang.NullPointerException",
      "elements": [
        {
          "method": "org.eclipse.jdt.internal.core.Buffer.getChar",
          "source": "Buffer.java:115"
        },
        {
          "method": "org.eclipse.jdt.internal.corext.javadoc.JavaDocCommentReader.read",
          "source": "Jav aDocCommentReader.java:48"
        },
        {
          "method": "java.io.FilterReader.read",
          "source": "FilterReader.java:48"
        },
        {
          "method": "java.io.PushbackReader.read",
          "source": "PushbackReader.java:73"
        },
        {
          "method": "org.eclipse.jdt.internal.ui.text.SubstitutionTextReader.nextChar",
          "source": "Subs titutionTextReader.java:82"
        },
        {
          "method": "org.eclipse.jdt.internal.ui.text.SubstitutionTextReader.read",
          "source": "Substitu tionTextReader.java:106"
        },
        {
          "method": "org.eclipse.jdt.internal.corext.javadoc.SingleCharReader.read",
          "source": "SingleC harReader.java:30"
        },
        {
          "method": "java.io.Reader.read",
          "source": "Reader.java:100"
        },
        {
          "method": "org.eclipse.jdt.internal.ui.text.HTMLPrinter.read",
          "source": "HTMLPrinter.java:64 "
        },
        {
          "method": "org.eclipse.jdt.internal.ui.text.HTMLPrinter.addParagraph",
          "source": "HTMLPrinter .java:150"
        },
        {
          "method": "org.eclipse.jdt.internal.ui.text.java.hover.JavadocHover.getHoverInfo",
          "source": "JavadocHover.java:67"
        },
        {
          "method": "org.eclipse.jdt.internal.ui.text.java.hover.AbstractJavaEditorTextHover.getHoverInfo",
          "source": "AbstractJavaEditorTextHover.java:105"
        },
        {
          "method": "org.eclipse.jdt.internal.ui.text.java.hover.BestMatchHover.getHoverInfo",
          "source": "BestMatchHover.java:140"
        },
        {
          "method": "org.eclipse.jdt.internal.ui.text.java.hover.JavaEditorTextHoverProxy.getHoverInfo",
          "source": "JavaEditorTextHoverProxy.java:69"
        },
        {
          "method": "org.eclipse.jface.text.TextViewerHoverManager$2.run",
          "source": "TextViewerHoverMa nager.java:119"
        }
      ],
      "number": 0,
      "commentIndex": 0,
      "bugId": "46040",
      "date": "2003-11-04T17:19:46+01:00",
      "product": "JDT",
      "component": "Core",
      "severity": "normal"
    }
  ],
  "groupId": "46040",
  "bugId": "46040",
  "date": "2003-11-04T17:19:46+01:00",
  "product": "JDT",
  "component": "Core",
  "severity": "normal"
}