{
  "comments": [
    "Using WSAD v5.1 (Eclipse v2.1.1) the following was displayed in the console:\n\nFri Oct 31 03:32:20 PST 2003 - Computing delta for project: eLVISTests\nFri Oct 31 03:32:20 PST 2003 - Finished computing delta, time: 0ms\nFri Oct 31 03:32:20 PST 2003 - Builder finished: ServiceProjectBuilder(eLVISTest\ns) time: 0ms\nFri Oct 31 03:32:20 PST 2003 - Checking if need to build. Starting delta computa\ntion between: ElementTree(9888) and ElementTree(10209)\nFri Oct 31 03:32:20 PST 2003 - End delta computation. (16ms).\n!\n{Global GC: Time elapsed (ms): 854.185\n  Objects live:02229304 dead:00850157\n  Bytes   live:113103988 dead:53587568\n  Physical heap memory:178257920}\njava.lang.NullPointerException\n        at java.lang.Throwable.\u003cinit\u003e(Throwable.java)\n        at java.lang.Throwable.\u003cinit\u003e(Throwable.java)\n        at java.lang.NullPointerException.\u003cinit\u003e(NullPointerException.java:63)\n        at org.eclipse.jdt.internal.core.index.impl.Util.quickSort(Util.java)\n        at org.eclipse.jdt.internal.core.index.impl.Util.sort(Util.java:292)\n        at org.eclipse.jdt.internal.core.index.impl.InMemoryIndex.getSortedWordE\nntries(InMemoryIndex.java:134)\n        at org.eclipse.jdt.internal.core.index.impl.SimpleIndexInput.open(Simple\nIndexInput.java:118)\n        at org.eclipse.jdt.internal.core.index.impl.MergeFactory.merge(MergeFact\nory.java:78)\n        at org.eclipse.jdt.internal.core.index.impl.Index.merge(Index.java:243)\n        at org.eclipse.jdt.internal.core.index.impl.Index.save(Index.java:348)\n        at org.eclipse.jdt.internal.core.search.indexing.IndexManager.saveIndex(\nIndexManager.java)\n        at org.eclipse.jdt.internal.core.search.indexing.AddJarFileToIndex.execu\nte(AddJarFileToIndex.java)\n        at org.eclipse.jdt.internal.core.search.processing.JobManager.run(JobMan\nager.java:360)\n        at java.lang.Thread.run(Thread.java:802)\n[Thread[Snapshot,5,main]] Operation started... :-)\nSnapshot: starting...\nTotal Snap Markers: 266ms\nTotal Snap Sync Info: 0ms\nSnapshot: 1953ms\n\nJVM being used:\n\njava version \"1.3.1\"\nJ9 - VM for the Java(TM) platform (build 2.1)\nIBM J9SE VM (build 2.1, J2RE 1.3.1 IBM J9 build 20030904 (JIT enabled))\n\nDo you believe this to be a problem with the Eclipse code, or the JVM?",
    "The asArray() method discards null entries, but does not resize the array.\nI didn\u0027t read close enough to determine if this may cause a NPE later.",
    "This exception shouldn\u0027t be fatal, and the indexer will simply restart what it \nwas doing (in background).\n\n",
    "\n\n*** This bug has been marked as a duplicate of 40950 ***",
    "Closing old bug that is now fixed."
  ],
  "commentCreationDates": [
    "2003-11-06T20:10:50+01:00",
    "2003-11-06T20:29:59+01:00",
    "2003-11-06T20:32:35+01:00",
    "2003-11-06T20:52:34+01:00",
    "2005-05-24T17:24:40+02:00"
  ],
  "traces": [
    {
      "exceptionType": "java.lang.NullPointerException",
      "elements": [
        {
          "method": "java.lang.Throwable.\u003cinit\u003e",
          "source": "Throwable.java"
        },
        {
          "method": "java.lang.Throwable.\u003cinit\u003e",
          "source": "Throwable.java"
        },
        {
          "method": "java.lang.NullPointerException.\u003cinit\u003e",
          "source": "NullPointerException.java:63"
        },
        {
          "method": "org.eclipse.jdt.internal.core.index.impl.Util.quickSort",
          "source": "Util.java"
        },
        {
          "method": "org.eclipse.jdt.internal.core.index.impl.Util.sort",
          "source": "Util.java:292"
        },
        {
          "method": "org.eclipse.jdt.internal.core.index.impl.InMemoryIndex.getSortedWordEntries",
          "source": "InMemoryIndex.java:134"
        },
        {
          "method": "org.eclipse.jdt.internal.core.index.impl.SimpleIndexInput.open",
          "source": "Simple IndexInput.java:118"
        },
        {
          "method": "org.eclipse.jdt.internal.core.index.impl.MergeFactory.merge",
          "source": "MergeFact ory.java:78"
        },
        {
          "method": "org.eclipse.jdt.internal.core.index.impl.Index.merge",
          "source": "Index.java:243"
        },
        {
          "method": "org.eclipse.jdt.internal.core.index.impl.Index.save",
          "source": "Index.java:348"
        },
        {
          "method": "org.eclipse.jdt.internal.core.search.indexing.IndexManager.saveIndex",
          "source": " IndexManager.java"
        },
        {
          "method": "org.eclipse.jdt.internal.core.search.indexing.AddJarFileToIndex.execute",
          "source": "AddJarFileToIndex.java"
        },
        {
          "method": "org.eclipse.jdt.internal.core.search.processing.JobManager.run",
          "source": "JobMan ager.java:360"
        },
        {
          "method": "java.lang.Thread.run",
          "source": "Thread.java:802"
        }
      ],
      "number": 0,
      "commentIndex": 0,
      "bugId": "46234",
      "duplicateId": "40950",
      "date": "2003-11-06T20:10:50+01:00",
      "product": "JDT",
      "component": "Core",
      "severity": "normal"
    }
  ],
  "groupId": "40950",
  "bugId": "46234",
  "duplicateId": "40950",
  "date": "2003-11-06T20:10:50+01:00",
  "product": "JDT",
  "component": "Core",
  "severity": "normal"
}