{
  "comments": [
    "I dont have extra information about this problem  but this is what the defect\nowner asked me to document in a bugzilla defect\n\nI have a Web project named Web1 I rename the WebContent folder in the project to\nWeb1 (right click web project Properties-\u003eWeb Project Features)\n\nNow I use Data-\u003eSQL wizard to connect to a database and create a SQL statement.\nThis wizard stores database information in the web project\nIt usually stores it in Web1/WebContent/WEB-INF/databases folder\nbut after I rename WebContent to Web1 the wizard fails to store the database\ninformation \n\napparently some emf class called PassthruResourceSet\n\"This is a more generic problem.  The reason for the NPE is that \nthe database documents get created in the incorrect location.\nThe URI that is passed to the PassthruResourceSet.createResource()\nis correct  (ie. web1/web1/WEB-INF/databases/sample.dbxmi)\nHowever, the resource that gets created is put in web1/web1/web1/WEB-INF/databases/\nThis seems to be a problem with either EMFWorkbench or the web nature.\n\"\n \u003cNote by ramanday (Mandayam, Rajasimhan A.), 2003/04/06 13:35:21, seq: 1 rel: 0\n action: open\u003e\nBUILD 0331 W2 WSAD\n\nSelect web project say \u0027Web1\u0027, go to Properties-\u003eWeb and change its Web Content\nfolder name to \u0027Web1\u0027 itself.\n\nNow launch Data-\u003eSQL stmt wizard.\n\nConnect to default db2 db and hit finish. wizard doesnt go away.\n\nerror in stack trace.\n\n!STACK 0\njava.lang.NullPointerException\n\tat\ncom.ibm.etools.sqlbuilder.model.SQLResourceHelper.saveDocument(SQLResourceHelper.java:76)\n\tat com.ibm.etools.sqlwizard.SQLWizardNew.performFinish(SQLWizardNew.java:209)\n\tat org.eclipse.jface.wizard.WizardDialog.finishPressed(WizardDialog.java:602)\n\tat org.eclipse.jface.wizard.WizardDialog.buttonPressed(WizardDialog.java:315)\n\tat org.eclipse.jface.dialogs.Dialog$1.widgetSelected(Dialog.java:417)\n\tat\norg.eclipse.swt.widgets.TypedListener.handleEvent(TypedListener.java(Compiled Code))\n\tat org.eclipse.swt.widgets.EventTable.sendEvent(EventTable.java(Compiled Code))\n\tat org.eclipse.swt.widgets.Display.runDeferredEvents(Display.java(Compiled Code))\n\tat org.eclipse.swt.widgets.Display.runDeferredEvents(Display.java(Compiled Code))\n\tat org.eclipse.swt.widgets.Display.readAndDispatch(Display.java(Compiled Code))\n\tat org.eclipse.jface.window.Window.runEventLoop(Window.java(Compiled Code))\n\tat org.eclipse.jface.window.Window.open(Window.java:557)\n\tat org.eclipse.ui.actions.NewWizardAction.run(NewWizardAction.java:123)\n\tat org.eclipse.jface.action.Action.runWithEvent(Action.java:841)\n\tat\norg.eclipse.ui.internal.WWinKeyBindingService.pressed(WWinKeyBindingService.java:146)\n\tat\norg.eclipse.ui.internal.WWinKeyBindingService$5.widgetSelected(WWinKeyBindingService.java:327)\n\tat org.eclipse.ui.internal.AcceleratorMenu$2.handleEvent(AcceleratorMenu.java:55)\n\tat org.eclipse.swt.widgets.EventTable.sendEvent(EventTable.java(Compiled Code))\n\tat org.eclipse.swt.widgets.Display.runDeferredEvents(Display.java(Compiled Code))\n\tat org.eclipse.swt.widgets.Display.runDeferredEvents(Display.java(Compiled Code))\n\tat org.eclipse.swt.widgets.Display.readAndDispatch(Display.java(Compiled Code))\n\tat org.eclipse.ui.internal.Workbench.runEventLoop(Workbench.java(Compiled Code))\n\tat org.eclipse.ui.internal.Workbench.run(Workbench.java:1254)\n\tat\norg.eclipse.core.internal.boot.InternalBootLoader.run(InternalBootLoader.java:845)\n\tat org.eclipse.core.boot.BootLoader.run(BootLoader.java:461)\n\tat java.lang.reflect.Method.invoke(Native Method)\n\tat org.eclipse.core.launcher.Main.basicRun(Main.java:247)\n\tat org.eclipse.core.launcher.Main.run(Main.java:703)\n\tat org.eclipse.core.launcher.Main.main(Main.java:539)\n\n\nAlso two  extra folders within the web project named Web1 which are inconsistent\nwith project structure.\n\nWeb1/Web Content \u0026 Web1/Web1/Web1\n\n    \u003cNote by joan (Joan Haggarty), 2003/04/15 17:09:44, seq: 2 rel: 0  action:\nmodify\u003e\nOld priority  5\nNew priority  1\n\n\n\n    \u003cNote by joan (Joan Haggarty), 2003/04/15 17:13:19, seq: 3 rel: 0  action:\nassign\u003e\nOld Component: com.ibm.etools.sqlwizard\nNew Component: wsa.xml.sqlbuilder\n\n\n\n    \u003cNote by joan (Joan Haggarty), 2003/04/16 12:34:17, seq: 4 rel: 0  action:\nreturn\u003e\nthis is caused by the same problem as 243725 so I\u0027m returning this one.\n\n    \u003cNote by peddles (Scott Peddle), 2003/07/18 14:39:28, seq: 5 rel: 0  action:\nnote\u003e\nAction is required on this defect to\nreduce a backlog of defects in \nreturned/verify state.  We need to\nreduce this backlog to meet QCERT\nnumbers for V5.1.\n\nPlease handle as soon as possible.\n\n    \u003cNote by ramanday (Mandayam, Rajasimhan A.), 2003/07/18 15:27:19, seq: 6\nrel: 0  action: reopen\u003e\nI can still reproduce it in 0714 2135 v51d\nWizard doesnt finish error in \nstack trace\nProblems reading container: F/Web2/Web2/Web2/WEB-INF/databases\n!ENTRY org.eclipse.ui 4 4 Jul 18, 2003 15:21:47.108\n!MESSAGE Unhandled exception caught in event loop.\nUnhandled exception caught in event loop.\nReason:\n!ENTRY org.eclipse.ui 4 0 Jul 18, 2003 15:21:47.168\n!MESSAGE java.lang.NullPointerException\n!STACK 0\njava.lang.NullPointerException\n        at java.lang.Throwable.\u003cinit\u003e(Throwable.java)\n        at java.lang.Throwable.\u003cinit\u003e(Throwable.java)\n        at java.lang.NullPointerException.\u003cinit\u003e(NullPointerException.java:63)\n        at com.ibm.etools.sqlbuilder.model.SQLResourceHelper.getStatementDocumen\ntName(SQLResourceHelper.java:52)\n        at com.ibm.etools.sqlbuilder.model.SQLResourceHelper.saveDocument(SQLRes\nourceHelper.java:73)\n        at com.ibm.etools.sqlwizard.SQLWizardNew.performFinish(SQLWizardNew.java\n:250)\n        at org.eclipse.jface.wizard.WizardDialog.finishPressed(WizardDialog.java\n:608)\n        at org.eclipse.jface.wizard.WizardDialog.buttonPressed(WizardDialog.java\n:321)\n        at org.eclipse.jface.dialogs.Dialog$1.widgetSelected(Dialog.java:423)\n        at org.eclipse.swt.widgets.TypedListener.handleEvent(TypedListener.java)\n\n        at org.eclipse.swt.widgets.EventTable.sendEvent(EventTable.java)\n        at org.eclipse.swt.widgets.Widget.sendEvent(Widget.java)\n        at org.eclipse.swt.widgets.Display.runDeferredEvents(Display.java)\n        at org.eclipse.swt.widgets.Display.readAndDispatch(Display.java)\n        at org.eclipse.jface.window.Window.runEventLoop(Window.java)\n        at org.eclipse.jface.window.Window.open(Window.java:563)\n        at org.eclipse.ui.actions.NewWizardAction.run(NewWizardAction.java:136)\n        at org.eclipse.jface.action.Action.runWithEvent(Action.java:842)\n        at org.eclipse.jface.action.ActionContributionItem.handleWidgetSelection\n(ActionContributionItem.java:456)\n        at org.eclipse.jface.action.ActionContributionItem.handleWidgetEvent(Act\nionContributionItem.java)\n        at org.eclipse.jface.action.ActionContributionItem.access$0(ActionContri\nbutionItem.java)\n        at org.eclipse.jface.action.ActionContributionItem$ActionListener.handle\nEvent(ActionContributionItem.java)\n        at org.eclipse.swt.widgets.EventTable.sendEvent(EventTable.java)\n        at org.eclipse.swt.widgets.Widget.sendEvent(Widget.java)\n        at org.eclipse.swt.widgets.Display.runDeferredEvents(Display.java)\n        at org.eclipse.swt.widgets.Display.readAndDispatch(Display.java)\n        at org.eclipse.ui.internal.Workbench.runEventLoop(Workbench.java:1402)\n        at org.eclipse.ui.internal.Workbench.run(Workbench.java:1385)\n        at org.eclipse.core.internal.boot.InternalBootLoader.run(InternalBootLoa\nder.java:858)\n        at org.eclipse.core.boot.BootLoader.run(BootLoader.java:461)\n        at java.lang.reflect.AccessibleObject.invokeL(AccessibleObject.java:207)\n\n        at java.lang.reflect.Method.invoke(Method.java:271)\n        at org.eclipse.core.launcher.Main.basicRun(Main.java:291)\n        at org.eclipse.core.launcher.Main.run(Main.java:747)\n        at org.eclipse.core.launcher.Main.main(Main.java:583)\njava.lang.NullPointerException\n\n    \u003cNote by joan (Joan Haggarty), 2003/09/10 16:51:00, seq: 7 rel: 0  action:\nassign\u003e\nThis is a more generic problem.  The reason for the NPE is that \nthe database documents get created in the incorrect location.\nThe URI that is passed to the PassthruResourceSet.createResource()\nis correct  (ie. web1/web1/WEB-INF/databases/sample.dbxmi)\nHowever, the resource that gets created is put in web1/web1/web1/WEB-INF/databases/\nThis seems to be a problem with either EMFWorkbench or the web nature.\nThanks. Joan.\nOld Component: wsa.etools.rsc.sqlbuilder\nNew Component: wsa.web.tooling\n\n\n\n    \u003cNote by jcagle (Cagle, J.E. (Jay)), 2003/09/14 13:48:05, seq: 8 rel: 0 \naction: modify\u003e\nOld Target:  v51w3\nNew Target:  v511\n\n\n\n    \u003cNote by jcagle (Cagle, J.E. (Jay)), 2003/09/19 14:52:44, seq: 9 rel: 0 \naction: return\u003e\nRaj, can you open a Bugzilla defect against EMF for this.  Thanks.",
    "Raj,\n\nPassthruResourceSet is not an EMF component. Nor is EMFWorkbench, for that \nmatter.  These are extensions written in WSAD and you need to find the right \nowner for those.\n\n",
    "closing long standing defect"
  ],
  "commentCreationDates": [
    "2003-11-10T21:01:27+01:00",
    "2003-11-12T12:58:57+01:00",
    "2005-09-19T22:19:22+02:00"
  ],
  "traces": [
    {
      "exceptionType": "java.lang.NullPointerException",
      "elements": [
        {
          "method": "com.ibm.etools.sqlbuilder.model.SQLResourceHelper.saveDocument",
          "source": "SQLResourceHelper.java:76"
        },
        {
          "method": "com.ibm.etools.sqlwizard.SQLWizardNew.performFinish",
          "source": "SQLWizardNew.java:209"
        },
        {
          "method": "org.eclipse.jface.wizard.WizardDialog.finishPressed",
          "source": "WizardDialog.java:602"
        },
        {
          "method": "org.eclipse.jface.wizard.WizardDialog.buttonPressed",
          "source": "WizardDialog.java:315"
        },
        {
          "method": "org.eclipse.jface.dialogs.Dialog$1.widgetSelected",
          "source": "Dialog.java:417"
        },
        {
          "method": "org.eclipse.swt.widgets.TypedListener.handleEvent",
          "source": "TypedListener.java(Compiled Code)"
        },
        {
          "method": "org.eclipse.swt.widgets.EventTable.sendEvent",
          "source": "EventTable.java(Compiled Code)"
        },
        {
          "method": "org.eclipse.swt.widgets.Display.runDeferredEvents",
          "source": "Display.java(Compiled Code)"
        },
        {
          "method": "org.eclipse.swt.widgets.Display.runDeferredEvents",
          "source": "Display.java(Compiled Code)"
        },
        {
          "method": "org.eclipse.swt.widgets.Display.readAndDispatch",
          "source": "Display.java(Compiled Code)"
        },
        {
          "method": "org.eclipse.jface.window.Window.runEventLoop",
          "source": "Window.java(Compiled Code)"
        },
        {
          "method": "org.eclipse.jface.window.Window.open",
          "source": "Window.java:557"
        },
        {
          "method": "org.eclipse.ui.actions.NewWizardAction.run",
          "source": "NewWizardAction.java:123"
        },
        {
          "method": "org.eclipse.jface.action.Action.runWithEvent",
          "source": "Action.java:841"
        },
        {
          "method": "org.eclipse.ui.internal.WWinKeyBindingService.pressed",
          "source": "WWinKeyBindingService.java:146"
        },
        {
          "method": "org.eclipse.ui.internal.WWinKeyBindingService$5.widgetSelected",
          "source": "WWinKeyBindingService.java:327"
        },
        {
          "method": "org.eclipse.ui.internal.AcceleratorMenu$2.handleEvent",
          "source": "AcceleratorMenu.java:55"
        },
        {
          "method": "org.eclipse.swt.widgets.EventTable.sendEvent",
          "source": "EventTable.java(Compiled Code)"
        },
        {
          "method": "org.eclipse.swt.widgets.Display.runDeferredEvents",
          "source": "Display.java(Compiled Code)"
        },
        {
          "method": "org.eclipse.swt.widgets.Display.runDeferredEvents",
          "source": "Display.java(Compiled Code)"
        },
        {
          "method": "org.eclipse.swt.widgets.Display.readAndDispatch",
          "source": "Display.java(Compiled Code)"
        },
        {
          "method": "org.eclipse.ui.internal.Workbench.runEventLoop",
          "source": "Workbench.java(Compiled Code)"
        },
        {
          "method": "org.eclipse.ui.internal.Workbench.run",
          "source": "Workbench.java:1254"
        },
        {
          "method": "org.eclipse.core.internal.boot.InternalBootLoader.run",
          "source": "InternalBootLoader.java:845"
        },
        {
          "method": "org.eclipse.core.boot.BootLoader.run",
          "source": "BootLoader.java:461"
        },
        {
          "method": "java.lang.reflect.Method.invoke",
          "source": "Native Method"
        },
        {
          "method": "org.eclipse.core.launcher.Main.basicRun",
          "source": "Main.java:247"
        },
        {
          "method": "org.eclipse.core.launcher.Main.run",
          "source": "Main.java:703"
        },
        {
          "method": "org.eclipse.core.launcher.Main.main",
          "source": "Main.java:539"
        }
      ],
      "number": 0,
      "commentIndex": 0,
      "bugId": "46372",
      "date": "2003-11-10T21:01:27+01:00",
      "product": "EMF",
      "component": "Core",
      "severity": "normal"
    },
    {
      "exceptionType": "java.lang.NullPointerException",
      "elements": [
        {
          "method": "java.lang.Throwable.\u003cinit\u003e",
          "source": "Throwable.java"
        },
        {
          "method": "java.lang.Throwable.\u003cinit\u003e",
          "source": "Throwable.java"
        },
        {
          "method": "java.lang.NullPointerException.\u003cinit\u003e",
          "source": "NullPointerException.java:63"
        },
        {
          "method": "com.ibm.etools.sqlbuilder.model.SQLResourceHelper.getStatementDocumentName",
          "source": "SQLResourceHelper.java:52"
        },
        {
          "method": "com.ibm.etools.sqlbuilder.model.SQLResourceHelper.saveDocument",
          "source": "SQLRes ourceHelper.java:73"
        },
        {
          "method": "com.ibm.etools.sqlwizard.SQLWizardNew.performFinish",
          "source": "SQLWizardNew.java :250"
        },
        {
          "method": "org.eclipse.jface.wizard.WizardDialog.finishPressed",
          "source": "WizardDialog.java :608"
        },
        {
          "method": "org.eclipse.jface.wizard.WizardDialog.buttonPressed",
          "source": "WizardDialog.java :321"
        },
        {
          "method": "org.eclipse.jface.dialogs.Dialog$1.widgetSelected",
          "source": "Dialog.java:423"
        },
        {
          "method": "org.eclipse.swt.widgets.TypedListener.handleEvent",
          "source": "TypedListener.java"
        },
        {
          "method": "org.eclipse.swt.widgets.EventTable.sendEvent",
          "source": "EventTable.java"
        },
        {
          "method": "org.eclipse.swt.widgets.Widget.sendEvent",
          "source": "Widget.java"
        },
        {
          "method": "org.eclipse.swt.widgets.Display.runDeferredEvents",
          "source": "Display.java"
        },
        {
          "method": "org.eclipse.swt.widgets.Display.readAndDispatch",
          "source": "Display.java"
        },
        {
          "method": "org.eclipse.jface.window.Window.runEventLoop",
          "source": "Window.java"
        },
        {
          "method": "org.eclipse.jface.window.Window.open",
          "source": "Window.java:563"
        },
        {
          "method": "org.eclipse.ui.actions.NewWizardAction.run",
          "source": "NewWizardAction.java:136"
        },
        {
          "method": "org.eclipse.jface.action.Action.runWithEvent",
          "source": "Action.java:842"
        },
        {
          "method": "org.eclipse.jface.action.ActionContributionItem.handleWidgetSelection",
          "source": "ActionContributionItem.java:456"
        },
        {
          "method": "org.eclipse.jface.action.ActionContributionItem.handleWidgetEvent",
          "source": "Act ionContributionItem.java"
        },
        {
          "method": "org.eclipse.jface.action.ActionContributionItem.access$0",
          "source": "ActionContri butionItem.java"
        },
        {
          "method": "org.eclipse.jface.action.ActionContributionItem$ActionListener.handleEvent",
          "source": "ActionContributionItem.java"
        },
        {
          "method": "org.eclipse.swt.widgets.EventTable.sendEvent",
          "source": "EventTable.java"
        },
        {
          "method": "org.eclipse.swt.widgets.Widget.sendEvent",
          "source": "Widget.java"
        },
        {
          "method": "org.eclipse.swt.widgets.Display.runDeferredEvents",
          "source": "Display.java"
        },
        {
          "method": "org.eclipse.swt.widgets.Display.readAndDispatch",
          "source": "Display.java"
        },
        {
          "method": "org.eclipse.ui.internal.Workbench.runEventLoop",
          "source": "Workbench.java:1402"
        },
        {
          "method": "org.eclipse.ui.internal.Workbench.run",
          "source": "Workbench.java:1385"
        },
        {
          "method": "org.eclipse.core.internal.boot.InternalBootLoader.run",
          "source": "InternalBootLoa der.java:858"
        },
        {
          "method": "org.eclipse.core.boot.BootLoader.run",
          "source": "BootLoader.java:461"
        },
        {
          "method": "java.lang.reflect.AccessibleObject.invokeL",
          "source": "AccessibleObject.java:207"
        },
        {
          "method": "java.lang.reflect.Method.invoke",
          "source": "Method.java:271"
        },
        {
          "method": "org.eclipse.core.launcher.Main.basicRun",
          "source": "Main.java:291"
        },
        {
          "method": "org.eclipse.core.launcher.Main.run",
          "source": "Main.java:747"
        },
        {
          "method": "org.eclipse.core.launcher.Main.main",
          "source": "Main.java:583"
        }
      ],
      "number": 1,
      "commentIndex": 0,
      "bugId": "46372",
      "date": "2003-11-10T21:01:27+01:00",
      "product": "EMF",
      "component": "Core",
      "severity": "normal"
    }
  ],
  "groupId": "46372",
  "bugId": "46372",
  "date": "2003-11-10T21:01:27+01:00",
  "product": "EMF",
  "component": "Core",
  "severity": "normal"
}