{
  "comments": [
    "I20031111\n\n- triggered a build and found the following core exception in the console.\n\norg.eclipse.core.runtime.CoreException[2]: java.io.EOFException\n        at java.io.DataInputStream.readInt(DataInputStream.java:448)\n        at org.eclipse.jdt.internal.core.builder.State.read(State.java:259)\n        at org.eclipse.jdt.internal.core.builder.JavaBuilder.readState\n(JavaBuild\ner.java:112)\n        at org.eclipse.jdt.internal.core.JavaModelManager.readState\n(JavaModelMan\nager.java:1146)\n        at org.eclipse.jdt.internal.core.JavaModelManager.getLastBuiltState\n(Java\nModelManager.java:773)\n        at org.eclipse.jdt.internal.core.builder.JavaBuilder.getLastState\n(JavaBu\nilder.java:321)\n        at org.eclipse.jdt.internal.core.builder.JavaBuilder.build\n(JavaBuilder.j\nava:137)\n        at org.eclipse.core.internal.events.BuildManager$2.run\n(BuildManager.java\n:475)\n        at org.eclipse.core.internal.runtime.InternalPlatform.run\n(InternalPlatfo\nrm.java:1123)\n        at org.eclipse.core.runtime.Platform.run(Platform.java:461)\n        at org.eclipse.core.internal.events.BuildManager.basicBuild\n(BuildManager\n.java:130)\n        at org.eclipse.core.internal.events.BuildManager.basicBuild\n(BuildManager\n.java:201)\n        at org.eclipse.core.internal.events.BuildManager.basicBuild\n(BuildManager\n.java:156)\n        at org.eclipse.core.internal.events.BuildManager$1.run\n(BuildManager.java\n:182)\n        at org.eclipse.core.internal.runtime.InternalPlatform.run\n(InternalPlatfo\nrm.java:1123)\n        at org.eclipse.core.runtime.Platform.run(Platform.java:461)\n        at org.eclipse.core.internal.events.BuildManager.basicBuild\n(BuildManager\n.java:185)\n        at org.eclipse.core.internal.events.BuildManager.basicBuildLoop\n(BuildMan\nager.java:219)\n        at org.eclipse.core.internal.events.BuildManager.build\n(BuildManager.java\n:247)\n        at org.eclipse.core.internal.events.AutoBuildJob.doBuild\n(AutoBuildJob.ja\nva:76)\n        at org.eclipse.core.internal.events.AutoBuildJob.run\n(AutoBuildJob.java:1\n09)\n        at org.eclipse.core.internal.jobs.Worker.run(Worker.java:62)",
    "Dirk - would you happen to have a copy of the workspace you were building ? \n\nPresumably some badness had occurred to our built state file, and we were \nunable to read it back in during the next session. \n\nWas this workspace properly shutdown in the previous session ? (i.e. did you \nnot exit by killing the VM/ctrl-C ?).",
    "From Dirk:\n- was indeed the first build during the session\n- was an existing self-hosted workspace which got started on latest RCP build \nfor the first time.\n\nKent:\nwould the perf change for reading built state would have affected the built \nstate reading ?",
    "No the performance change would not cause this. All we did was change some \narrays to sets to hold info we were reading.\n\nThis looks like the build state file was truncated for some reason.\n\nDirk: Any chance your disk was full?",
    "No, 35.7 GB free disk space",
    "Dirk was running JRE 1.4.2",
    "There is not enough here to go on without the actual file for the build state. \nWe have not seen anything like this so far. We will keep it around in case \nsomething else shows up.\n\nIt could have been anything including a disk controller failure or vm problem.",
    "just experienced the same exception on I20031119_latest_of_the_day\n- under Linux RH 9.0 (-\u003e ajusted OS)\n- workspace has worked before with the same build, and it was not the first\nbuild / startup\n- shutdown had been semi-normal, I remember an IllegalStateException thrown from\nJobManager.",
    "Did you keep the build state files?",
    "sorry, no - not much help I guess."
  ],
  "commentCreationDates": [
    "2003-11-11T22:53:37+01:00",
    "2003-11-12T10:18:24+01:00",
    "2003-11-12T10:40:26+01:00",
    "2003-11-12T15:52:25+01:00",
    "2003-11-12T16:08:00+01:00",
    "2003-11-12T17:08:35+01:00",
    "2003-11-13T19:45:17+01:00",
    "2003-11-20T16:08:52+01:00",
    "2003-11-20T19:37:22+01:00",
    "2003-11-20T20:17:48+01:00"
  ],
  "traces": [
    {
      "exceptionType": "java.io.EOFException",
      "elements": [
        {
          "method": "java.io.DataInputStream.readInt",
          "source": "DataInputStream.java:448"
        },
        {
          "method": "org.eclipse.jdt.internal.core.builder.State.read",
          "source": "State.java:259"
        },
        {
          "method": "org.eclipse.jdt.internal.core.builder.JavaBuilder.readState",
          "source": "JavaBuild er.java:112"
        },
        {
          "method": "org.eclipse.jdt.internal.core.JavaModelManager.readState",
          "source": "JavaModelMan ager.java:1146"
        },
        {
          "method": "org.eclipse.jdt.internal.core.JavaModelManager.getLastBuiltState",
          "source": "Java ModelManager.java:773"
        },
        {
          "method": "org.eclipse.jdt.internal.core.builder.JavaBuilder.getLastState",
          "source": "JavaBu ilder.java:321"
        },
        {
          "method": "org.eclipse.jdt.internal.core.builder.JavaBuilder.build",
          "source": "JavaBuilder.j ava:137"
        },
        {
          "method": "org.eclipse.core.internal.events.BuildManager$2.run",
          "source": "BuildManager.java :475"
        },
        {
          "method": "org.eclipse.core.internal.runtime.InternalPlatform.run",
          "source": "InternalPlatfo rm.java:1123"
        },
        {
          "method": "org.eclipse.core.runtime.Platform.run",
          "source": "Platform.java:461"
        },
        {
          "method": "org.eclipse.core.internal.events.BuildManager.basicBuild",
          "source": "BuildManager .java:130"
        },
        {
          "method": "org.eclipse.core.internal.events.BuildManager.basicBuild",
          "source": "BuildManager .java:201"
        },
        {
          "method": "org.eclipse.core.internal.events.BuildManager.basicBuild",
          "source": "BuildManager .java:156"
        },
        {
          "method": "org.eclipse.core.internal.events.BuildManager$1.run",
          "source": "BuildManager.java :182"
        },
        {
          "method": "org.eclipse.core.internal.runtime.InternalPlatform.run",
          "source": "InternalPlatfo rm.java:1123"
        },
        {
          "method": "org.eclipse.core.runtime.Platform.run",
          "source": "Platform.java:461"
        },
        {
          "method": "org.eclipse.core.internal.events.BuildManager.basicBuild",
          "source": "BuildManager .java:185"
        },
        {
          "method": "org.eclipse.core.internal.events.BuildManager.basicBuildLoop",
          "source": "BuildMan ager.java:219"
        },
        {
          "method": "org.eclipse.core.internal.events.BuildManager.build",
          "source": "BuildManager.java :247"
        },
        {
          "method": "org.eclipse.core.internal.events.AutoBuildJob.doBuild",
          "source": "AutoBuildJob.ja va:76"
        },
        {
          "method": "org.eclipse.core.internal.events.AutoBuildJob.run",
          "source": "AutoBuildJob.java:1 09"
        },
        {
          "method": "org.eclipse.core.internal.jobs.Worker.run",
          "source": "Worker.java:62"
        }
      ],
      "number": 0,
      "commentIndex": 0,
      "bugId": "46446",
      "date": "2003-11-11T22:53:37+01:00",
      "product": "JDT",
      "component": "Core",
      "severity": "normal"
    }
  ],
  "groupId": "46446",
  "bugId": "46446",
  "date": "2003-11-11T22:53:37+01:00",
  "product": "JDT",
  "component": "Core",
  "severity": "normal"
}