{
  "comments": [
    "I\u0027m starting Eclipse 3.0M4 as follows:\n\naxel@asterix:/apps/eclipse\u003e ./eclipse -data /pub/tmp\n\nIt fails displaying a message box: \"Problems during startup.Check the .log file\nin the .metadata directory of your workspace.\"\n\nThe log file content is:\n\n!ENTRY org.eclipse.core.launcher 4 0 Nov 13, 2003 18:52:20.377\n!MESSAGE Exception launching the Eclipse Platform:\n!STACK\njava.lang.reflect.InvocationTargetException\n        at sun.reflect.NativeMethodAccessorImpl.invoke0(Native Method)\n        at\nsun.reflect.NativeMethodAccessorImpl.invoke(NativeMethodAccessorImpl.java:39)\n        at\nsun.reflect.DelegatingMethodAccessorImpl.invoke(DelegatingMethodAccessorImpl.java:25)\n        at java.lang.reflect.Method.invoke(Method.java:324)\n        at org.eclipse.core.launcher.Main.basicRun(Main.java:299)\n        at org.eclipse.core.launcher.Main.run(Main.java:765)\n        at org.eclipse.core.launcher.Main.main(Main.java:599)\nCaused by: java.lang.reflect.InvocationTargetException\n        at sun.reflect.NativeMethodAccessorImpl.invoke0(Native Method)\n        at\nsun.reflect.NativeMethodAccessorImpl.invoke(NativeMethodAccessorImpl.java:39)\n        at\nsun.reflect.DelegatingMethodAccessorImpl.invoke(DelegatingMethodAccessorImpl.java:25)\n        at java.lang.reflect.Method.invoke(Method.java:324)\n        at\norg.eclipse.core.internal.boot.InternalBootLoader.startup(InternalBootLoader.java:1049)\n        at\norg.eclipse.core.internal.boot.InternalBootLoader.run(InternalBootLoader.java:838)\n        at org.eclipse.core.boot.BootLoader.run(BootLoader.java:461)\n        ... 7 more\nCaused by: org.eclipse.core.runtime.CoreException: Unable to create platform\nlock file: /pub/tmp/.metadata/.lock.\n        at\norg.eclipse.core.internal.runtime.InternalPlatform.createLockFile(InternalPlatform.java:225)\n        at\norg.eclipse.core.internal.runtime.InternalPlatform.loaderStartup(InternalPlatform.java:677)\n        ... 14 more\n\nI tried several directories: As soon as the directory is located on an NFS\nvolume, it fails. Otherwise Eclipse starts up without problems.",
    "\n\n*** This bug has been marked as a duplicate of 44735 ***"
  ],
  "commentCreationDates": [
    "2003-11-13T18:08:09+01:00",
    "2003-11-13T18:38:37+01:00"
  ],
  "traces": [
    {
      "exceptionType": "java.lang.reflect.InvocationTargetException",
      "elements": [
        {
          "method": "sun.reflect.NativeMethodAccessorImpl.invoke0",
          "source": "Native Method"
        },
        {
          "method": "sun.reflect.NativeMethodAccessorImpl.invoke",
          "source": "NativeMethodAccessorImpl.java:39"
        },
        {
          "method": "sun.reflect.DelegatingMethodAccessorImpl.invoke",
          "source": "DelegatingMethodAccessorImpl.java:25"
        },
        {
          "method": "java.lang.reflect.Method.invoke",
          "source": "Method.java:324"
        },
        {
          "method": "org.eclipse.core.launcher.Main.basicRun",
          "source": "Main.java:299"
        },
        {
          "method": "org.eclipse.core.launcher.Main.run",
          "source": "Main.java:765"
        },
        {
          "method": "org.eclipse.core.launcher.Main.main",
          "source": "Main.java:599"
        }
      ],
      "causedBy": {
        "exceptionType": "java.lang.reflect.InvocationTargetException",
        "elements": [
          {
            "method": "sun.reflect.NativeMethodAccessorImpl.invoke0",
            "source": "Native Method"
          },
          {
            "method": "sun.reflect.NativeMethodAccessorImpl.invoke",
            "source": "NativeMethodAccessorImpl.java:39"
          },
          {
            "method": "sun.reflect.DelegatingMethodAccessorImpl.invoke",
            "source": "DelegatingMethodAccessorImpl.java:25"
          },
          {
            "method": "java.lang.reflect.Method.invoke",
            "source": "Method.java:324"
          },
          {
            "method": "org.eclipse.core.internal.boot.InternalBootLoader.startup",
            "source": "InternalBootLoader.java:1049"
          },
          {
            "method": "org.eclipse.core.internal.boot.InternalBootLoader.run",
            "source": "InternalBootLoader.java:838"
          },
          {
            "method": "org.eclipse.core.boot.BootLoader.run",
            "source": "BootLoader.java:461"
          }
        ],
        "causedBy": {
          "exceptionType": "org.eclipse.core.runtime.CoreException",
          "message": "Unable to create platform lock file: /pub/tmp/.metadata/.lock.",
          "elements": [
            {
              "method": "org.eclipse.core.internal.runtime.InternalPlatform.createLockFile",
              "source": "InternalPlatform.java:225"
            },
            {
              "method": "org.eclipse.core.internal.runtime.InternalPlatform.loaderStartup",
              "source": "InternalPlatform.java:677"
            }
          ],
          "number": 0,
          "commentIndex": 0
        },
        "number": 0,
        "commentIndex": 0
      },
      "number": 0,
      "commentIndex": 0,
      "bugId": "46603",
      "duplicateId": "44735",
      "date": "2003-11-13T18:08:09+01:00",
      "product": "Platform",
      "component": "Resources",
      "severity": "normal"
    }
  ],
  "groupId": "44735",
  "bugId": "46603",
  "duplicateId": "44735",
  "date": "2003-11-13T18:08:09+01:00",
  "product": "Platform",
  "component": "Resources",
  "severity": "normal"
}