{
  "comments": [
    "Eclipse 200311050952\nOSX 10.3.1 on Dual G5\n\nMy logs are full of the error below but it doesn\u0027t seem to effect me in any way.\nI do not have any of the auto refresh options on in the Synchronize view preferences.\n\n!MESSAGE Problems occurred when invoking code from plug-in: \"org.eclipse.team.ui\".\n!STACK 0\njava.lang.NullPointerException\n        at org.eclipse.team.internal.ui.jobs.JobBusyCursor.showCursor(JobBusyCursor.java:48)\n        at org.eclipse.team.internal.ui.jobs.JobBusyCursor.finished(JobBusyCursor.java:93)\n        at org.eclipse.team.internal.ui.jobs.JobStatusHandler$2.notify(JobStatusHandler.java:224)\n        at org.eclipse.team.internal.ui.jobs.JobStatusHandler$Notification.run(JobStatusHandler.java:\n46)\n        at org.eclipse.core.internal.runtime.InternalPlatform.run(InternalPlatform.java:1143)\n        at org.eclipse.core.runtime.Platform.run(Platform.java:461)\n        at org.eclipse.team.internal.ui.jobs.JobStatusHandler$Notification.run(JobStatusHandler.java:\n43)\n        at org.eclipse.team.internal.ui.jobs.JobStatusHandler.fireNotification(JobStatusHandler.java:\n174)\n        at \norg.eclipse.team.internal.ui.jobs.JobStatusHandler.fireEndNotification(JobStatusHandler.java:222)\n        at org.eclipse.team.internal.ui.jobs.JobStatusHandler.jobDone(JobStatusHandler.java:216)\n        at org.eclipse.team.internal.ui.jobs.JobStatusHandler.done(JobStatusHandler.java:150)\n        at org.eclipse.core.internal.jobs.JobListeners$3.notify(JobListeners.java:37)\n        at org.eclipse.core.internal.jobs.JobListeners$7.run(JobListeners.java:106)\n        at org.eclipse.core.internal.runtime.InternalPlatform.run(InternalPlatform.java:1143)\n        at org.eclipse.core.runtime.Platform.run(Platform.java:461)\n        at org.eclipse.core.internal.jobs.JobListeners.doNotify(JobListeners.java:86)\n        at org.eclipse.core.internal.jobs.JobListeners.done(JobListeners.java:125)\n        at org.eclipse.core.internal.jobs.JobManager.endJob(JobManager.java:305)\n        at org.eclipse.core.internal.jobs.WorkerPool.endJob(WorkerPool.java:85)\n        at org.eclipse.core.internal.jobs.Worker.run(Worker.java:72)",
    "\n\n*** This bug has been marked as a duplicate of 46116 ***"
  ],
  "commentCreationDates": [
    "2003-11-14T10:50:00+01:00",
    "2003-11-14T14:15:17+01:00"
  ],
  "traces": [
    {
      "exceptionType": "java.lang.NullPointerException",
      "elements": [
        {
          "method": "org.eclipse.team.internal.ui.jobs.JobBusyCursor.showCursor",
          "source": "JobBusyCursor.java:48"
        },
        {
          "method": "org.eclipse.team.internal.ui.jobs.JobBusyCursor.finished",
          "source": "JobBusyCursor.java:93"
        },
        {
          "method": "org.eclipse.team.internal.ui.jobs.JobStatusHandler$2.notify",
          "source": "JobStatusHandler.java:224"
        },
        {
          "method": "org.eclipse.team.internal.ui.jobs.JobStatusHandler$Notification.run",
          "source": "JobStatusHandler.java: 46"
        },
        {
          "method": "org.eclipse.core.internal.runtime.InternalPlatform.run",
          "source": "InternalPlatform.java:1143"
        },
        {
          "method": "org.eclipse.core.runtime.Platform.run",
          "source": "Platform.java:461"
        },
        {
          "method": "org.eclipse.team.internal.ui.jobs.JobStatusHandler$Notification.run",
          "source": "JobStatusHandler.java: 43"
        },
        {
          "method": "org.eclipse.team.internal.ui.jobs.JobStatusHandler.fireNotification",
          "source": "JobStatusHandler.java: 174"
        },
        {
          "method": "org.eclipse.team.internal.ui.jobs.JobStatusHandler.fireEndNotification",
          "source": "JobStatusHandler.java:222"
        },
        {
          "method": "org.eclipse.team.internal.ui.jobs.JobStatusHandler.jobDone",
          "source": "JobStatusHandler.java:216"
        },
        {
          "method": "org.eclipse.team.internal.ui.jobs.JobStatusHandler.done",
          "source": "JobStatusHandler.java:150"
        },
        {
          "method": "org.eclipse.core.internal.jobs.JobListeners$3.notify",
          "source": "JobListeners.java:37"
        },
        {
          "method": "org.eclipse.core.internal.jobs.JobListeners$7.run",
          "source": "JobListeners.java:106"
        },
        {
          "method": "org.eclipse.core.internal.runtime.InternalPlatform.run",
          "source": "InternalPlatform.java:1143"
        },
        {
          "method": "org.eclipse.core.runtime.Platform.run",
          "source": "Platform.java:461"
        },
        {
          "method": "org.eclipse.core.internal.jobs.JobListeners.doNotify",
          "source": "JobListeners.java:86"
        },
        {
          "method": "org.eclipse.core.internal.jobs.JobListeners.done",
          "source": "JobListeners.java:125"
        },
        {
          "method": "org.eclipse.core.internal.jobs.JobManager.endJob",
          "source": "JobManager.java:305"
        },
        {
          "method": "org.eclipse.core.internal.jobs.WorkerPool.endJob",
          "source": "WorkerPool.java:85"
        },
        {
          "method": "org.eclipse.core.internal.jobs.Worker.run",
          "source": "Worker.java:72"
        }
      ],
      "number": 0,
      "commentIndex": 0,
      "bugId": "46661",
      "duplicateId": "46116",
      "date": "2003-11-14T10:50:00+01:00",
      "product": "Platform",
      "component": "Team",
      "severity": "normal"
    }
  ],
  "groupId": "46116",
  "bugId": "46661",
  "duplicateId": "46116",
  "date": "2003-11-14T10:50:00+01:00",
  "product": "Platform",
  "component": "Team",
  "severity": "normal"
}