{
  "comments": [
    "I20031105\nmy eclipse deadlocked somehow after I tried creating a new file through right \nclicking in the package explorer and selecting new-\u003efile. \nhere is the thread dump at that stage:\n\nFull thread dump Java HotSpot(TM) Client VM (1.4.2_02-b03 mixed mode):\n\n\"Worker-50\" prio\u003d5 tid\u003d0x2d5cb438 nid\u003d0x5e0 in Object.wait() [32b8f000..32b8fd88\n]\n        at java.lang.Object.wait(Native Method)\n        - waiting on \u003c0x11db6e68\u003e (a org.eclipse.core.internal.jobs.WorkerPool)\n        at org.eclipse.core.internal.jobs.WorkerPool.sleep(WorkerPool.java:155)\n        - locked \u003c0x11db6e68\u003e (a org.eclipse.core.internal.jobs.WorkerPool)\n        at org.eclipse.core.internal.jobs.WorkerPool.startJob(WorkerPool.java:18\n1)\n        at org.eclipse.core.internal.jobs.Worker.run(Worker.java:55)\n\n\"Worker-49\" prio\u003d5 tid\u003d0x2d6f9c18 nid\u003d0x134 in Object.wait() [32b3f000..32b3fd88\n]\n        at java.lang.Object.wait(Native Method)\n        - waiting on \u003c0x11db6e68\u003e (a org.eclipse.core.internal.jobs.WorkerPool)\n        at org.eclipse.core.internal.jobs.WorkerPool.sleep(WorkerPool.java:155)\n        - locked \u003c0x11db6e68\u003e (a org.eclipse.core.internal.jobs.WorkerPool)\n        at org.eclipse.core.internal.jobs.WorkerPool.startJob(WorkerPool.java:18\n1)\n        at org.eclipse.core.internal.jobs.Worker.run(Worker.java:55)\n\n\"Worker-48\" prio\u003d5 tid\u003d0x2c535770 nid\u003d0x8bc in Object.wait() [32aff000..32affd88\n]\n        at java.lang.Object.wait(Native Method)\n        - waiting on \u003c0x11db6e68\u003e (a org.eclipse.core.internal.jobs.WorkerPool)\n        at org.eclipse.core.internal.jobs.WorkerPool.sleep(WorkerPool.java:155)\n        - locked \u003c0x11db6e68\u003e (a org.eclipse.core.internal.jobs.WorkerPool)\n        at org.eclipse.core.internal.jobs.WorkerPool.startJob(WorkerPool.java:18\n1)\n        at org.eclipse.core.internal.jobs.Worker.run(Worker.java:55)\n\n\"Worker-44\" prio\u003d5 tid\u003d0x2d66e250 nid\u003d0x6b0 in Object.wait() [3287f000..3287fd88\n]\n        at java.lang.Object.wait(Native Method)\n        - waiting on \u003c0x11db6e68\u003e (a org.eclipse.core.internal.jobs.WorkerPool)\n        at org.eclipse.core.internal.jobs.WorkerPool.sleep(WorkerPool.java:155)\n        - locked \u003c0x11db6e68\u003e (a org.eclipse.core.internal.jobs.WorkerPool)\n        at org.eclipse.core.internal.jobs.WorkerPool.startJob(WorkerPool.java:18\n1)\n        at org.eclipse.core.internal.jobs.Worker.run(Worker.java:55)\n\n\"org.eclipse.jdt.internal.ui.text.JavaReconciler\" daemon prio\u003d2 tid\u003d0x2d5c8910 n\nid\u003d0x9ac in Object.wait() [326bf000..326bfd88]\n        at java.lang.Object.wait(Native Method)\n        at org.eclipse.jface.text.reconciler.AbstractReconciler$BackgroundThread\n.run(AbstractReconciler.java:161)\n        - locked \u003c0x148340f0\u003e (a org.eclipse.jface.text.reconciler.DirtyRegionQu\neue)\n\n\"org.eclipse.jdt.internal.ui.text.JavaReconciler\" daemon prio\u003d2 tid\u003d0x2c50e5f0 n\nid\u003d0x794 in Object.wait() [3219f000..3219fd88]\n        at java.lang.Object.wait(Native Method)\n        at org.eclipse.jface.text.reconciler.AbstractReconciler$BackgroundThread\n.run(AbstractReconciler.java:161)\n        - locked \u003c0x13e39d18\u003e (a org.eclipse.jface.text.reconciler.DirtyRegionQu\neue)\n\n\"org.eclipse.jdt.internal.ui.text.JavaReconciler\" daemon prio\u003d2 tid\u003d0x2d6a3f18 n\nid\u003d0x8e4 in Object.wait() [3212f000..3212fd88]\n        at java.lang.Object.wait(Native Method)\n        at org.eclipse.jface.text.reconciler.AbstractReconciler$BackgroundThread\n.run(AbstractReconciler.java:161)\n        - locked \u003c0x13d6d520\u003e (a org.eclipse.jface.text.reconciler.DirtyRegionQu\neue)\n\n\"ServerConnection\" prio\u003d7 tid\u003d0x2d8fdb50 nid\u003d0x868 runnable [3143f000..3143fd88]\n\n        at java.net.PlainSocketImpl.socketAccept(Native Method)\n        at java.net.PlainSocketImpl.accept(PlainSocketImpl.java:353)\n        - locked \u003c0x13a85890\u003e (a java.net.PlainSocketImpl)\n        at java.net.ServerSocket.implAccept(ServerSocket.java:448)\n        at java.net.ServerSocket.accept(ServerSocket.java:419)\n        at org.eclipse.jdt.internal.junit.ui.RemoteTestRunnerClient$ServerConnec\ntion.run(RemoteTestRunnerClient.java:102)\n\n\"Thread-1\" daemon prio\u003d7 tid\u003d0x2c914d98 nid\u003d0x910 in Object.wait() [2ddff000..2d\ndffd88]\n        at java.lang.Object.wait(Native Method)\n        - waiting on \u003c0x130c2680\u003e (a java.util.TaskQueue)\n        at java.util.TimerThread.mainLoop(Timer.java:429)\n        - locked \u003c0x130c2680\u003e (a java.util.TaskQueue)\n        at java.util.TimerThread.run(Timer.java:382)\n\n\"Java indexing\" daemon prio\u003d4 tid\u003d0x2c49de58 nid\u003d0x8c8 in Object.wait() [2d20f00\n0..2d20fd88]\n        at java.lang.Object.wait(Native Method)\n        - waiting on \u003c0x12c27880\u003e (a org.eclipse.jdt.internal.core.search.indexi\nng.IndexManager)\n        at java.lang.Object.wait(Object.java:429)\n        at org.eclipse.jdt.internal.core.search.processing.JobManager.run(JobMan\nager.java:331)\n        - locked \u003c0x12c27880\u003e (a org.eclipse.jdt.internal.core.search.indexing.I\nndexManager)\n        at java.lang.Thread.run(Thread.java:534)\n\n\"Signal Dispatcher\" daemon prio\u003d10 tid\u003d0x00921f80 nid\u003d0x600 waiting on condition\n [0..0]\n\n\"Finalizer\" daemon prio\u003d9 tid\u003d0x0091f150 nid\u003d0x9dc in Object.wait() [2c2af000..2\nc2afd88]\n        at java.lang.Object.wait(Native Method)\n        at java.lang.ref.ReferenceQueue.remove(ReferenceQueue.java:111)\n        - locked \u003c0x11d9b3f0\u003e (a java.lang.ref.ReferenceQueue$Lock)\n        at java.lang.ref.ReferenceQueue.remove(ReferenceQueue.java:127)\n        at java.lang.ref.Finalizer$FinalizerThread.run(Finalizer.java:159)\n\n\"Reference Handler\" daemon prio\u003d10 tid\u003d0x0091dcc8 nid\u003d0x328 in Object.wait() [2c\n26f000..2c26fd88]\n        at java.lang.Object.wait(Native Method)\n        - waiting on \u003c0x11d9b458\u003e (a java.lang.ref.Reference$Lock)\n        at java.lang.Object.wait(Object.java:429)\n        at java.lang.ref.Reference$ReferenceHandler.run(Reference.java:115)\n        - locked \u003c0x11d9b458\u003e (a java.lang.ref.Reference$Lock)\n\n\"main\" prio\u003d5 tid\u003d0x00235b00 nid\u003d0x694 runnable [6f000..6fc3c]\n        at org.eclipse.swt.internal.win32.OS.WaitMessage(Native Method)\n        at org.eclipse.swt.widgets.Display.sleep(Display.java:2484)\n        at org.eclipse.jface.window.Window.runEventLoop(Window.java:584)\n        at org.eclipse.jface.window.Window.open(Window.java:563)\n        at org.eclipse.ui.internal.NewWizardShortcutAction.run(NewWizardShortcut\nAction.java:96)\n        at org.eclipse.jface.action.Action.runWithEvent(Action.java:842)\n        at org.eclipse.jface.action.ActionContributionItem.handleWidgetSelection\n(ActionContributionItem.java:542)\n        at org.eclipse.jface.action.ActionContributionItem.access$4(ActionContri\nbutionItem.java:494)\n        at org.eclipse.jface.action.ActionContributionItem$6.handleEvent(ActionC\nontributionItem.java:466)\n        at org.eclipse.swt.widgets.EventTable.sendEvent(EventTable.java:82)\n        at org.eclipse.swt.widgets.Widget.sendEvent(Widget.java:847)\n        at org.eclipse.swt.widgets.Display.runDeferredEvents(Display.java:2187)\n        at org.eclipse.swt.widgets.Display.readAndDispatch(Display.java:1877)\n        at org.eclipse.ui.internal.Workbench.runEventLoop(Workbench.java:1611)\n        at org.eclipse.ui.internal.Workbench.run(Workbench.java:1594)\n        at org.eclipse.core.internal.boot.InternalBootLoader.run(InternalBootLoa\nder.java:858)\n        at org.eclipse.core.boot.BootLoader.run(BootLoader.java:461)\n        at sun.reflect.NativeMethodAccessorImpl.invoke0(Native Method)\n        at sun.reflect.NativeMethodAccessorImpl.invoke(NativeMethodAccessorImpl.\njava:39)\n        at sun.reflect.DelegatingMethodAccessorImpl.invoke(DelegatingMethodAcces\nsorImpl.java:25)\n        at java.lang.reflect.Method.invoke(Method.java:324)\n        at org.eclipse.core.launcher.Main.basicRun(Main.java:299)\n        at org.eclipse.core.launcher.Main.run(Main.java:765)\n        at org.eclipse.core.launcher.Main.main(Main.java:599)\n\n\"VM Thread\" prio\u003d5 tid\u003d0x0095d2a0 nid\u003d0x294 runnable\n\n\"VM Periodic Task Thread\" prio\u003d10 tid\u003d0x0023ee88 nid\u003d0x988 waiting on condition\n\n\"Suspend Checker Thread\" prio\u003d10 tid\u003d0x00921630 nid\u003d0x948 runnable\n\n\n\n\n\n\nAfter I killed eclipse it couldn\u0027t start up it game me this error:\n\n\n!SESSION ----------------------------------------------------------------------\n!ENTRY org.eclipse.core.launcher 4 0 Nov 14, 2003 11:03:06.269\n!MESSAGE Exception launching the Eclipse Platform:\n!STACK\njava.lang.reflect.InvocationTargetException\n\tat sun.reflect.NativeMethodAccessorImpl.invoke0(Native Method)\n\tat sun.reflect.NativeMethodAccessorImpl.invoke\n(NativeMethodAccessorImpl.java:39)\n\tat sun.reflect.DelegatingMethodAccessorImpl.invoke\n(DelegatingMethodAccessorImpl.java:25)\n\tat java.lang.reflect.Method.invoke(Method.java:324)\n\tat org.eclipse.core.launcher.Main.basicRun(Main.java:299)\n\tat org.eclipse.core.launcher.Main.run(Main.java:765)\n\tat org.eclipse.core.launcher.Main.main(Main.java:599)\nCaused by: java.lang.reflect.InvocationTargetException\n\tat org.eclipse.core.internal.boot.InternalBootLoader.run\n(InternalBootLoader.java:861)\n\tat org.eclipse.core.boot.BootLoader.run(BootLoader.java:461)\n\t... 7 more\nCaused by: org.eclipse.swt.SWTException: Invalid thread access\n\tat org.eclipse.swt.SWT.error(SWT.java:2538)\n\tat org.eclipse.swt.SWT.error(SWT.java:2468)\n\tat org.eclipse.swt.widgets.Display.error(Display.java:656)\n\tat org.eclipse.swt.widgets.Display.checkDevice(Display.java:509)\n\tat org.eclipse.swt.widgets.Display.getSystemColor(Display.java:1328)\n\tat org.eclipse.ui.internal.WorkbenchColors.getSystemColor\n(WorkbenchColors.java:166)\n\tat org.eclipse.ui.internal.WorkbenchColors.startup\n(WorkbenchColors.java:270)\n\tat org.eclipse.ui.internal.Workbench.init(Workbench.java:985)\n\tat org.eclipse.ui.internal.Workbench.run(Workbench.java:1582)\n\tat org.eclipse.core.internal.boot.InternalBootLoader.run\n(InternalBootLoader.java:858)\n\t... 8 more",
    "Moving to UI, problem could be same or related to bug 46562.  Note that bug \n46562 is marked fixed as of yesterday.\n",
    "The initial hang may be bug 46562 although it was a problem running the java \ntest suites.\n\nThe more interesting issue is how the workbench can start up outside of the UI \nThread. This code is now obsolete (org.eclipse.ui.internal.Workbench.run has \nbeen deleted so this will not happen post 20031111. \n\nI will keep this problem report open as the refactoring may not have taken \ncare of the problem.",
    "Likely a duplicate of Bug 46957",
    "Closing as I beleive this was fixed for M5. Please reopen if you get this post \nM5.",
    "Marking closed"
  ],
  "commentCreationDates": [
    "2003-11-14T11:18:38+01:00",
    "2003-11-14T15:02:49+01:00",
    "2003-11-17T20:55:10+01:00",
    "2003-11-19T13:59:33+01:00",
    "2003-11-24T20:06:35+01:00",
    "2005-05-10T20:56:30+02:00"
  ],
  "traces": [
    {
      "exceptionType": "java.lang.reflect.InvocationTargetException",
      "elements": [
        {
          "method": "sun.reflect.NativeMethodAccessorImpl.invoke0",
          "source": "Native Method"
        },
        {
          "method": "sun.reflect.NativeMethodAccessorImpl.invoke",
          "source": "NativeMethodAccessorImpl.java:39"
        },
        {
          "method": "sun.reflect.DelegatingMethodAccessorImpl.invoke",
          "source": "DelegatingMethodAccessorImpl.java:25"
        },
        {
          "method": "java.lang.reflect.Method.invoke",
          "source": "Method.java:324"
        },
        {
          "method": "org.eclipse.core.launcher.Main.basicRun",
          "source": "Main.java:299"
        },
        {
          "method": "org.eclipse.core.launcher.Main.run",
          "source": "Main.java:765"
        },
        {
          "method": "org.eclipse.core.launcher.Main.main",
          "source": "Main.java:599"
        }
      ],
      "causedBy": {
        "exceptionType": "java.lang.reflect.InvocationTargetException",
        "elements": [
          {
            "method": "org.eclipse.core.internal.boot.InternalBootLoader.run",
            "source": "InternalBootLoader.java:861"
          },
          {
            "method": "org.eclipse.core.boot.BootLoader.run",
            "source": "BootLoader.java:461"
          }
        ],
        "causedBy": {
          "exceptionType": "org.eclipse.swt.SWTException",
          "message": "Invalid thread access",
          "elements": [
            {
              "method": "org.eclipse.swt.SWT.error",
              "source": "SWT.java:2538"
            },
            {
              "method": "org.eclipse.swt.SWT.error",
              "source": "SWT.java:2468"
            },
            {
              "method": "org.eclipse.swt.widgets.Display.error",
              "source": "Display.java:656"
            },
            {
              "method": "org.eclipse.swt.widgets.Display.checkDevice",
              "source": "Display.java:509"
            },
            {
              "method": "org.eclipse.swt.widgets.Display.getSystemColor",
              "source": "Display.java:1328"
            },
            {
              "method": "org.eclipse.ui.internal.WorkbenchColors.getSystemColor",
              "source": "WorkbenchColors.java:166"
            },
            {
              "method": "org.eclipse.ui.internal.WorkbenchColors.startup",
              "source": "WorkbenchColors.java:270"
            },
            {
              "method": "org.eclipse.ui.internal.Workbench.init",
              "source": "Workbench.java:985"
            },
            {
              "method": "org.eclipse.ui.internal.Workbench.run",
              "source": "Workbench.java:1582"
            },
            {
              "method": "org.eclipse.core.internal.boot.InternalBootLoader.run",
              "source": "InternalBootLoader.java:858"
            }
          ],
          "number": 0,
          "commentIndex": 0
        },
        "number": 0,
        "commentIndex": 0
      },
      "number": 0,
      "commentIndex": 0,
      "bugId": "46663",
      "date": "2003-11-14T11:18:38+01:00",
      "product": "Platform",
      "component": "UI",
      "severity": "normal"
    }
  ],
  "groupId": "46663",
  "bugId": "46663",
  "date": "2003-11-14T11:18:38+01:00",
  "product": "Platform",
  "component": "UI",
  "severity": "normal"
}