{
  "comments": [
    "To duplicate this exception, create a repository location in the CVS\nPerspective. Use an unqualified host name on your network (\"acme\" instead of\n\"acme.company.com\"). Then remove the DNS suffix of your Network Interface, so\nthat \"acme\" no longer resolves to a valid host (\"acme.company.com\"). Close and\nre-open Eclipse. Try to open the branches or HEAD to browse the tree. You should\nget an UnkonwnHostException. The result is that the Tree Viewer loses all\nelements of its display. \n\nI found the problem in 3.0M4, but I have not done any investigation to see if it\nexists in previous 3.0 builds. \n\nThe exception I found: \n\n!ENTRY org.eclipse.team.cvs.ui 4 0 Nov 16, 2003 21:12:41.94\n!MESSAGE Internal error\n!STACK 1\norg.eclipse.team.internal.ccvs.core.CVSException[0]: java.net.UnknownHostExcepti\non: aixsrv04\n        at java.net.PlainSocketImpl.connect(PlainSocketImpl.java:153)\n        at java.net.Socket.connect(Socket.java:426)\n        at java.net.Socket.connect(Socket.java:376)\n        at java.net.Socket.\u003cinit\u003e(Socket.java:291)\n        at java.net.Socket.\u003cinit\u003e(Socket.java:119)\n        at org.eclipse.team.internal.ccvs.core.util.Util$1.run(Util.java:182)\n        at java.lang.Thread.run(Thread.java:536)\n!ENTRY org.eclipse.team.cvs.core 4 0 Nov 16, 2003 21:12:41.94\n!MESSAGE Cannot locate host\n!STACK 0\njava.net.UnknownHostException: aixsrv04\n        at java.net.PlainSocketImpl.connect(PlainSocketImpl.java:153)\n        at java.net.Socket.connect(Socket.java:426)\n        at java.net.Socket.connect(Socket.java:376)\n        at java.net.Socket.\u003cinit\u003e(Socket.java:291)\n        at java.net.Socket.\u003cinit\u003e(Socket.java:119)\n        at org.eclipse.team.internal.ccvs.core.util.Util$1.run(Util.java:182)\n        at java.lang.Thread.run(Thread.java:536)\n!ENTRY org.eclipse.ui 4 4 Nov 16, 2003 21:12:41.114\n!MESSAGE Unhandled exception caught in event loop.\nUnhandled exception caught in event loop.\nReason:\n!ENTRY org.eclipse.ui 4 0 Nov 16, 2003 21:12:41.134\n!MESSAGE Failed to execute runnable (java.lang.NullPointerException)\n!STACK 0\norg.eclipse.swt.SWTException: Failed to execute runnable (java.lang.NullPointerE\nxception)\n        at org.eclipse.swt.SWT.error(SWT.java:2369)\n        at org.eclipse.swt.widgets.Synchronizer.runAsyncMessages(Synchronizer.ja\nva:105)\n        at org.eclipse.swt.widgets.Display.runAsyncMessages(Display.java:2150)\n        at org.eclipse.swt.widgets.Display.readAndDispatch(Display.java:1867)\n        at org.eclipse.ui.internal.Workbench.runEventLoop(Workbench.java:2347)\n        at org.eclipse.ui.internal.Workbench.run(Workbench.java:2330)\n        at org.eclipse.core.internal.boot.InternalBootLoader.run(InternalBootLoa\nder.java:858)\n        at org.eclipse.core.boot.BootLoader.run(BootLoader.java:461)\n        at sun.reflect.NativeMethodAccessorImpl.invoke0(Native Method)\n        at sun.reflect.NativeMethodAccessorImpl.invoke(NativeMethodAccessorImpl.\njava:39)\n        at sun.reflect.DelegatingMethodAccessorImpl.invoke(DelegatingMethodAcces\nsorImpl.java:25)\n        at java.lang.reflect.Method.invoke(Method.java:324)\n        at org.eclipse.core.launcher.Main.basicRun(Main.java:299)\n        at org.eclipse.core.launcher.Main.run(Main.java:765)\n        at org.eclipse.core.launcher.Main.main(Main.java:599)\nFailed to execute runnable (java.lang.NullPointerException)\n!ENTRY org.eclipse.ui 4 4 Nov 16, 2003 21:12:41.144\n!MESSAGE\n*** Stack trace of contained exception ***\n\n*** Stack trace of contained exception ***\nReason:\n!ENTRY org.eclipse.ui 4 0 Nov 16, 2003 21:12:41.154\n!MESSAGE java.lang.NullPointerException\n!STACK 0\njava.lang.NullPointerException\n        at org.eclipse.jface.viewers.AbstractTreeViewer.createAddedElement(Abstr\nactTreeViewer.java:174)\n        at org.eclipse.jface.viewers.AbstractTreeViewer.add(AbstractTreeViewer.j\nava:156)\n        at org.eclipse.ui.progress.DeferredTreeContentManager$4.runInUIThread(De\nferredTreeContentManager.java:235)\n        at org.eclipse.ui.progress.UIJob$1.run(UIJob.java:81)\n        at org.eclipse.swt.widgets.RunnableLock.run(RunnableLock.java:35)\n        at org.eclipse.swt.widgets.Synchronizer.runAsyncMessages(Synchronizer.ja\nva:102)\n        at org.eclipse.swt.widgets.Display.runAsyncMessages(Display.java:2150)\n        at org.eclipse.swt.widgets.Display.readAndDispatch(Display.java:1867)\n        at org.eclipse.ui.internal.Workbench.runEventLoop(Workbench.java:2347)\n        at org.eclipse.ui.internal.Workbench.run(Workbench.java:2330)\n        at org.eclipse.core.internal.boot.InternalBootLoader.run(InternalBootLoa\nder.java:858)\n        at org.eclipse.core.boot.BootLoader.run(BootLoader.java:461)\n        at sun.reflect.NativeMethodAccessorImpl.invoke0(Native Method)\n        at sun.reflect.NativeMethodAccessorImpl.invoke(NativeMethodAccessorImpl.\njava:39)\n        at sun.reflect.DelegatingMethodAccessorImpl.invoke(DelegatingMethodAcces\nsorImpl.java:25)\n        at java.lang.reflect.Method.invoke(Method.java:324)\n        at org.eclipse.core.launcher.Main.basicRun(Main.java:299)\n        at org.eclipse.core.launcher.Main.run(Main.java:765)\n        at org.eclipse.core.launcher.Main.main(Main.java:599)\njava.lang.NullPointerException\n!ENTRY org.eclipse.ui 4 4 Nov 16, 2003 21:13:24.807\n!MESSAGE Unhandled exception caught in event loop.\nUnhandled exception caught in event loop.\nReason:\n!ENTRY org.eclipse.ui 4 0 Nov 16, 2003 21:13:24.817\n!MESSAGE Failed to execute runnable (java.lang.NullPointerException)\n!STACK 0\norg.eclipse.swt.SWTException: Failed to execute runnable (java.lang.NullPointerE\nxception)\n        at org.eclipse.swt.SWT.error(SWT.java:2369)\n        at org.eclipse.swt.widgets.Synchronizer.runAsyncMessages(Synchronizer.ja\nva:105)\n        at org.eclipse.swt.widgets.Display.runAsyncMessages(Display.java:2150)\n        at org.eclipse.swt.widgets.Display.readAndDispatch(Display.java:1867)\n        at org.eclipse.ui.internal.Workbench.runEventLoop(Workbench.java:2347)\n        at org.eclipse.ui.internal.Workbench.run(Workbench.java:2330)\n        at org.eclipse.core.internal.boot.InternalBootLoader.run(InternalBootLoa\nder.java:858)\n        at org.eclipse.core.boot.BootLoader.run(BootLoader.java:461)\n        at sun.reflect.NativeMethodAccessorImpl.invoke0(Native Method)\n        at sun.reflect.NativeMethodAccessorImpl.invoke(NativeMethodAccessorImpl.\njava:39)\n        at sun.reflect.DelegatingMethodAccessorImpl.invoke(DelegatingMethodAcces\nsorImpl.java:25)\n        at java.lang.reflect.Method.invoke(Method.java:324)\n        at org.eclipse.core.launcher.Main.basicRun(Main.java:299)\n        at org.eclipse.core.launcher.Main.run(Main.java:765)\n        at org.eclipse.core.launcher.Main.main(Main.java:599)\nFailed to execute runnable (java.lang.NullPointerException)\n!ENTRY org.eclipse.ui 4 4 Nov 16, 2003 21:13:24.827\n!MESSAGE\n*** Stack trace of contained exception ***\n\n*** Stack trace of contained exception ***\nReason:\n!ENTRY org.eclipse.ui 4 0 Nov 16, 2003 21:13:24.837\n!MESSAGE java.lang.NullPointerException\n!STACK 0\njava.lang.NullPointerException\n        at org.eclipse.jface.viewers.AbstractTreeViewer.createAddedElement(Abstr\nactTreeViewer.java:174)\n        at org.eclipse.jface.viewers.AbstractTreeViewer.add(AbstractTreeViewer.j\nava:156)\n        at org.eclipse.ui.progress.DeferredTreeContentManager$4.runInUIThread(De\nferredTreeContentManager.java:235)\n        at org.eclipse.ui.progress.UIJob$1.run(UIJob.java:81)\n        at org.eclipse.swt.widgets.RunnableLock.run(RunnableLock.java:35)\n        at org.eclipse.swt.widgets.Synchronizer.runAsyncMessages(Synchronizer.ja\nva:102)\n        at org.eclipse.swt.widgets.Display.runAsyncMessages(Display.java:2150)\n        at org.eclipse.swt.widgets.Display.readAndDispatch(Display.java:1867)\n        at org.eclipse.ui.internal.Workbench.runEventLoop(Workbench.java:2347)\n        at org.eclipse.ui.internal.Workbench.run(Workbench.java:2330)\n        at org.eclipse.core.internal.boot.InternalBootLoader.run(InternalBootLoa\nder.java:858)\n        at org.eclipse.core.boot.BootLoader.run(BootLoader.java:461)\n        at sun.reflect.NativeMethodAccessorImpl.invoke0(Native Method)\n        at sun.reflect.NativeMethodAccessorImpl.invoke(NativeMethodAccessorImpl.\njava:39)\n        at sun.reflect.DelegatingMethodAccessorImpl.invoke(DelegatingMethodAcces\nsorImpl.java:25)\n        at java.lang.reflect.Method.invoke(Method.java:324)\n        at org.eclipse.core.launcher.Main.basicRun(Main.java:299)\n        at org.eclipse.core.launcher.Main.run(Main.java:765)\n        at org.eclipse.core.launcher.Main.main(Main.java:599)\njava.lang.NullPointerException",
    "I am unable to reproduce this using I20031113 on Windows XP. We\u0027ll have to \ntest it on Win 2000 to ensure it\u0027s not a platform specific problem.",
    "This works for me using M5 on Win 2000 (i.e. connection fails but there is no \nNPE).",
    "OK"
  ],
  "commentCreationDates": [
    "2003-11-17T02:33:25+01:00",
    "2003-11-17T14:34:18+01:00",
    "2003-12-03T20:52:32+01:00",
    "2005-03-02T14:52:46+01:00"
  ],
  "traces": [
    {
      "exceptionType": "java.net.UnknownHostException",
      "message": "aixsrv04",
      "elements": [
        {
          "method": "java.net.PlainSocketImpl.connect",
          "source": "PlainSocketImpl.java:153"
        },
        {
          "method": "java.net.Socket.connect",
          "source": "Socket.java:426"
        },
        {
          "method": "java.net.Socket.connect",
          "source": "Socket.java:376"
        },
        {
          "method": "java.net.Socket.\u003cinit\u003e",
          "source": "Socket.java:291"
        },
        {
          "method": "java.net.Socket.\u003cinit\u003e",
          "source": "Socket.java:119"
        },
        {
          "method": "org.eclipse.team.internal.ccvs.core.util.Util$1.run",
          "source": "Util.java:182"
        },
        {
          "method": "java.lang.Thread.run",
          "source": "Thread.java:536"
        }
      ],
      "number": 0,
      "commentIndex": 0,
      "bugId": "46749",
      "date": "2003-11-17T02:33:25+01:00",
      "product": "Platform",
      "component": "Team",
      "severity": "normal"
    },
    {
      "exceptionType": "org.eclipse.swt.SWTException",
      "message": "Failed to execute runnable (java.lang.NullPointerE xception)",
      "elements": [
        {
          "method": "org.eclipse.swt.SWT.error",
          "source": "SWT.java:2369"
        },
        {
          "method": "org.eclipse.swt.widgets.Synchronizer.runAsyncMessages",
          "source": "Synchronizer.ja va:105"
        },
        {
          "method": "org.eclipse.swt.widgets.Display.runAsyncMessages",
          "source": "Display.java:2150"
        },
        {
          "method": "org.eclipse.swt.widgets.Display.readAndDispatch",
          "source": "Display.java:1867"
        },
        {
          "method": "org.eclipse.ui.internal.Workbench.runEventLoop",
          "source": "Workbench.java:2347"
        },
        {
          "method": "org.eclipse.ui.internal.Workbench.run",
          "source": "Workbench.java:2330"
        },
        {
          "method": "org.eclipse.core.internal.boot.InternalBootLoader.run",
          "source": "InternalBootLoa der.java:858"
        },
        {
          "method": "org.eclipse.core.boot.BootLoader.run",
          "source": "BootLoader.java:461"
        },
        {
          "method": "sun.reflect.NativeMethodAccessorImpl.invoke0",
          "source": "Native Method"
        },
        {
          "method": "sun.reflect.NativeMethodAccessorImpl.invoke",
          "source": "NativeMethodAccessorImpl. java:39"
        },
        {
          "method": "sun.reflect.DelegatingMethodAccessorImpl.invoke",
          "source": "DelegatingMethodAcces sorImpl.java:25"
        },
        {
          "method": "java.lang.reflect.Method.invoke",
          "source": "Method.java:324"
        },
        {
          "method": "org.eclipse.core.launcher.Main.basicRun",
          "source": "Main.java:299"
        },
        {
          "method": "org.eclipse.core.launcher.Main.run",
          "source": "Main.java:765"
        },
        {
          "method": "org.eclipse.core.launcher.Main.main",
          "source": "Main.java:599"
        }
      ],
      "number": 1,
      "commentIndex": 0,
      "bugId": "46749",
      "date": "2003-11-17T02:33:25+01:00",
      "product": "Platform",
      "component": "Team",
      "severity": "normal"
    },
    {
      "exceptionType": "java.lang.NullPointerException",
      "elements": [
        {
          "method": "org.eclipse.jface.viewers.AbstractTreeViewer.createAddedElement",
          "source": "Abstr actTreeViewer.java:174"
        },
        {
          "method": "org.eclipse.jface.viewers.AbstractTreeViewer.add",
          "source": "AbstractTreeViewer.j ava:156"
        },
        {
          "method": "org.eclipse.ui.progress.DeferredTreeContentManager$4.runInUIThread",
          "source": "De ferredTreeContentManager.java:235"
        },
        {
          "method": "org.eclipse.ui.progress.UIJob$1.run",
          "source": "UIJob.java:81"
        },
        {
          "method": "org.eclipse.swt.widgets.RunnableLock.run",
          "source": "RunnableLock.java:35"
        },
        {
          "method": "org.eclipse.swt.widgets.Synchronizer.runAsyncMessages",
          "source": "Synchronizer.ja va:102"
        },
        {
          "method": "org.eclipse.swt.widgets.Display.runAsyncMessages",
          "source": "Display.java:2150"
        },
        {
          "method": "org.eclipse.swt.widgets.Display.readAndDispatch",
          "source": "Display.java:1867"
        },
        {
          "method": "org.eclipse.ui.internal.Workbench.runEventLoop",
          "source": "Workbench.java:2347"
        },
        {
          "method": "org.eclipse.ui.internal.Workbench.run",
          "source": "Workbench.java:2330"
        },
        {
          "method": "org.eclipse.core.internal.boot.InternalBootLoader.run",
          "source": "InternalBootLoa der.java:858"
        },
        {
          "method": "org.eclipse.core.boot.BootLoader.run",
          "source": "BootLoader.java:461"
        },
        {
          "method": "sun.reflect.NativeMethodAccessorImpl.invoke0",
          "source": "Native Method"
        },
        {
          "method": "sun.reflect.NativeMethodAccessorImpl.invoke",
          "source": "NativeMethodAccessorImpl. java:39"
        },
        {
          "method": "sun.reflect.DelegatingMethodAccessorImpl.invoke",
          "source": "DelegatingMethodAcces sorImpl.java:25"
        },
        {
          "method": "java.lang.reflect.Method.invoke",
          "source": "Method.java:324"
        },
        {
          "method": "org.eclipse.core.launcher.Main.basicRun",
          "source": "Main.java:299"
        },
        {
          "method": "org.eclipse.core.launcher.Main.run",
          "source": "Main.java:765"
        },
        {
          "method": "org.eclipse.core.launcher.Main.main",
          "source": "Main.java:599"
        }
      ],
      "number": 2,
      "commentIndex": 0,
      "bugId": "46749",
      "date": "2003-11-17T02:33:25+01:00",
      "product": "Platform",
      "component": "Team",
      "severity": "normal"
    },
    {
      "exceptionType": "org.eclipse.swt.SWTException",
      "message": "Failed to execute runnable (java.lang.NullPointerE xception)",
      "elements": [
        {
          "method": "org.eclipse.swt.SWT.error",
          "source": "SWT.java:2369"
        },
        {
          "method": "org.eclipse.swt.widgets.Synchronizer.runAsyncMessages",
          "source": "Synchronizer.ja va:105"
        },
        {
          "method": "org.eclipse.swt.widgets.Display.runAsyncMessages",
          "source": "Display.java:2150"
        },
        {
          "method": "org.eclipse.swt.widgets.Display.readAndDispatch",
          "source": "Display.java:1867"
        },
        {
          "method": "org.eclipse.ui.internal.Workbench.runEventLoop",
          "source": "Workbench.java:2347"
        },
        {
          "method": "org.eclipse.ui.internal.Workbench.run",
          "source": "Workbench.java:2330"
        },
        {
          "method": "org.eclipse.core.internal.boot.InternalBootLoader.run",
          "source": "InternalBootLoa der.java:858"
        },
        {
          "method": "org.eclipse.core.boot.BootLoader.run",
          "source": "BootLoader.java:461"
        },
        {
          "method": "sun.reflect.NativeMethodAccessorImpl.invoke0",
          "source": "Native Method"
        },
        {
          "method": "sun.reflect.NativeMethodAccessorImpl.invoke",
          "source": "NativeMethodAccessorImpl. java:39"
        },
        {
          "method": "sun.reflect.DelegatingMethodAccessorImpl.invoke",
          "source": "DelegatingMethodAcces sorImpl.java:25"
        },
        {
          "method": "java.lang.reflect.Method.invoke",
          "source": "Method.java:324"
        },
        {
          "method": "org.eclipse.core.launcher.Main.basicRun",
          "source": "Main.java:299"
        },
        {
          "method": "org.eclipse.core.launcher.Main.run",
          "source": "Main.java:765"
        },
        {
          "method": "org.eclipse.core.launcher.Main.main",
          "source": "Main.java:599"
        }
      ],
      "number": 3,
      "commentIndex": 0,
      "bugId": "46749",
      "date": "2003-11-17T02:33:25+01:00",
      "product": "Platform",
      "component": "Team",
      "severity": "normal"
    },
    {
      "exceptionType": "java.lang.NullPointerException",
      "elements": [
        {
          "method": "org.eclipse.jface.viewers.AbstractTreeViewer.createAddedElement",
          "source": "Abstr actTreeViewer.java:174"
        },
        {
          "method": "org.eclipse.jface.viewers.AbstractTreeViewer.add",
          "source": "AbstractTreeViewer.j ava:156"
        },
        {
          "method": "org.eclipse.ui.progress.DeferredTreeContentManager$4.runInUIThread",
          "source": "De ferredTreeContentManager.java:235"
        },
        {
          "method": "org.eclipse.ui.progress.UIJob$1.run",
          "source": "UIJob.java:81"
        },
        {
          "method": "org.eclipse.swt.widgets.RunnableLock.run",
          "source": "RunnableLock.java:35"
        },
        {
          "method": "org.eclipse.swt.widgets.Synchronizer.runAsyncMessages",
          "source": "Synchronizer.ja va:102"
        },
        {
          "method": "org.eclipse.swt.widgets.Display.runAsyncMessages",
          "source": "Display.java:2150"
        },
        {
          "method": "org.eclipse.swt.widgets.Display.readAndDispatch",
          "source": "Display.java:1867"
        },
        {
          "method": "org.eclipse.ui.internal.Workbench.runEventLoop",
          "source": "Workbench.java:2347"
        },
        {
          "method": "org.eclipse.ui.internal.Workbench.run",
          "source": "Workbench.java:2330"
        },
        {
          "method": "org.eclipse.core.internal.boot.InternalBootLoader.run",
          "source": "InternalBootLoa der.java:858"
        },
        {
          "method": "org.eclipse.core.boot.BootLoader.run",
          "source": "BootLoader.java:461"
        },
        {
          "method": "sun.reflect.NativeMethodAccessorImpl.invoke0",
          "source": "Native Method"
        },
        {
          "method": "sun.reflect.NativeMethodAccessorImpl.invoke",
          "source": "NativeMethodAccessorImpl. java:39"
        },
        {
          "method": "sun.reflect.DelegatingMethodAccessorImpl.invoke",
          "source": "DelegatingMethodAcces sorImpl.java:25"
        },
        {
          "method": "java.lang.reflect.Method.invoke",
          "source": "Method.java:324"
        },
        {
          "method": "org.eclipse.core.launcher.Main.basicRun",
          "source": "Main.java:299"
        },
        {
          "method": "org.eclipse.core.launcher.Main.run",
          "source": "Main.java:765"
        },
        {
          "method": "org.eclipse.core.launcher.Main.main",
          "source": "Main.java:599"
        }
      ],
      "number": 4,
      "commentIndex": 0,
      "bugId": "46749",
      "date": "2003-11-17T02:33:25+01:00",
      "product": "Platform",
      "component": "Team",
      "severity": "normal"
    }
  ],
  "groupId": "46749",
  "bugId": "46749",
  "date": "2003-11-17T02:33:25+01:00",
  "product": "Platform",
  "component": "Team",
  "severity": "normal"
}