{
  "comments": [
    "I believe this occurred while trying to execute a CVS synchronize while the user\ninterface was still in the process of coming up.\n\nENTRY org.eclipse.core.runtime 4 2 Nov 18, 2003 15:58:19.212\n!MESSAGE Problems occurred when invoking code from plug-in:\n\"org.eclipse.core.runtime\".\n!STACK 0\njava.lang.IndexOutOfBoundsException: Index: 1, Size: 1\n        at java.util.ArrayList.RangeCheck(ArrayList.java:507)\n        at java.util.ArrayList.get(ArrayList.java:324)\n        at java.util.Collections$SynchronizedList.get(Collections.java:1786)\n        at org.eclipse.core.internal.jobs.JobListeners$7.run(JobListeners.java:104)\n        at\norg.eclipse.core.internal.runtime.InternalPlatform.run(InternalPlatform.java:1127)\n        at org.eclipse.core.runtime.Platform.run(Platform.java:464)\n        at\norg.eclipse.core.internal.jobs.JobListeners.doNotify(JobListeners.java:86)\n        at org.eclipse.core.internal.jobs.JobListeners.done(JobListeners.java:125)\n        at org.eclipse.core.internal.jobs.JobManager.endJob(JobManager.java:281)\n        at org.eclipse.core.internal.jobs.WorkerPool.endJob(WorkerPool.java:120)\n        at org.eclipse.core.internal.jobs.Worker.run(Worker.java:72)",
    "Fixed."
  ],
  "commentCreationDates": [
    "2003-11-18T21:10:23+01:00",
    "2003-11-19T22:21:16+01:00"
  ],
  "traces": [
    {
      "exceptionType": "java.lang.IndexOutOfBoundsException",
      "message": "Index: 1, Size: 1",
      "elements": [
        {
          "method": "java.util.ArrayList.RangeCheck",
          "source": "ArrayList.java:507"
        },
        {
          "method": "java.util.ArrayList.get",
          "source": "ArrayList.java:324"
        },
        {
          "method": "java.util.Collections$SynchronizedList.get",
          "source": "Collections.java:1786"
        },
        {
          "method": "org.eclipse.core.internal.jobs.JobListeners$7.run",
          "source": "JobListeners.java:104"
        },
        {
          "method": "org.eclipse.core.internal.runtime.InternalPlatform.run",
          "source": "InternalPlatform.java:1127"
        },
        {
          "method": "org.eclipse.core.runtime.Platform.run",
          "source": "Platform.java:464"
        },
        {
          "method": "org.eclipse.core.internal.jobs.JobListeners.doNotify",
          "source": "JobListeners.java:86"
        },
        {
          "method": "org.eclipse.core.internal.jobs.JobListeners.done",
          "source": "JobListeners.java:125"
        },
        {
          "method": "org.eclipse.core.internal.jobs.JobManager.endJob",
          "source": "JobManager.java:281"
        },
        {
          "method": "org.eclipse.core.internal.jobs.WorkerPool.endJob",
          "source": "WorkerPool.java:120"
        },
        {
          "method": "org.eclipse.core.internal.jobs.Worker.run",
          "source": "Worker.java:72"
        }
      ],
      "number": 0,
      "commentIndex": 0,
      "bugId": "46883",
      "date": "2003-11-18T21:10:23+01:00",
      "product": "Platform",
      "component": "Resources",
      "severity": "normal"
    }
  ],
  "groupId": "46883",
  "bugId": "46883",
  "date": "2003-11-18T21:10:23+01:00",
  "product": "Platform",
  "component": "Resources",
  "severity": "normal"
}