{
  "comments": [
    "N2003114\n\nFound the folloiwng exception in the console while shuting down Eclipse.\n\norg.eclipse.core.internal.runtime.AssertionFailedException: assertion failed: Th\ne application has not been initialized.\n        at org.eclipse.core.internal.runtime.Assert.isTrue(Assert.java:101)\n        at org.eclipse.core.internal.runtime.InternalPlatform.assertInitialized(\nInternalPlatform.java:201)\n        at org.eclipse.core.internal.runtime.InternalPlatform.getPluginRegistry(\nInternalPlatform.java:369)\n        at org.eclipse.core.internal.runtime.InternalPlatform.getRuntimePlugin(I\nnternalPlatform.java:390)\n        at org.eclipse.core.internal.runtime.InternalPlatform.handleException(In\nternalPlatform.java:401)\n        at org.eclipse.core.internal.runtime.InternalPlatform.run(InternalPlatfo\nrm.java:1129)",
    "The bottom of the stack is missing.  This is caused by a thread calling\nPlatform.run(ISafeRunnable) after the platform has been shutdown.  Closing since\nwe don\u0027t know who the culprit is."
  ],
  "commentCreationDates": [
    "2003-11-19T10:39:43+01:00",
    "2003-12-03T16:53:21+01:00"
  ],
  "traces": [
    {
      "exceptionType": "org.eclipse.core.internal.runtime.AssertionFailedException",
      "message": "assertion failed: Th e application has not been initialized.",
      "elements": [
        {
          "method": "org.eclipse.core.internal.runtime.Assert.isTrue",
          "source": "Assert.java:101"
        },
        {
          "method": "org.eclipse.core.internal.runtime.InternalPlatform.assertInitialized",
          "source": " InternalPlatform.java:201"
        },
        {
          "method": "org.eclipse.core.internal.runtime.InternalPlatform.getPluginRegistry",
          "source": " InternalPlatform.java:369"
        },
        {
          "method": "org.eclipse.core.internal.runtime.InternalPlatform.getRuntimePlugin",
          "source": "I nternalPlatform.java:390"
        },
        {
          "method": "org.eclipse.core.internal.runtime.InternalPlatform.handleException",
          "source": "In ternalPlatform.java:401"
        },
        {
          "method": "org.eclipse.core.internal.runtime.InternalPlatform.run",
          "source": "InternalPlatfo rm.java:1129"
        }
      ],
      "number": 0,
      "commentIndex": 0,
      "bugId": "46932",
      "date": "2003-11-19T10:39:43+01:00",
      "product": "Platform",
      "component": "Resources",
      "severity": "normal"
    }
  ],
  "groupId": "46932",
  "bugId": "46932",
  "date": "2003-11-19T10:39:43+01:00",
  "product": "Platform",
  "component": "Resources",
  "severity": "normal"
}