{
  "comments": [
    "build i1119 (noon build), sunjdk 1.4.2 , winxp\n\nJust noticed this in my log file, no user dialog or visual indication that\nsomething went wrong.\n\n!ENTRY org.eclipse.ui 4 4 Nov 19, 2003 13:11:20.343\n!MESSAGE Action for command \u0027org.eclipse.ui.edit.text.delete.line\u0027 failed to exe\ncute properly.\nAction for command \u0027org.eclipse.ui.edit.text.delete.line\u0027 failed to execute prop\nerly.\nReason:\n!ENTRY org.eclipse.ui 4 0 Nov 19, 2003 13:11:20.363\n!MESSAGE Action for command \u0027org.eclipse.ui.edit.text.delete.line\u0027 failed to exe\ncute properly.\n!STACK 0\njava.lang.NullPointerException\n        at org.eclipse.jface.text.presentation.PresentationReconciler.getDamage(\nPresentationReconciler.java:459)\n        at org.eclipse.jface.text.presentation.PresentationReconciler.access$11(\nPresentationReconciler.java:456)\n        at org.eclipse.jface.text.presentation.PresentationReconciler$InternalLi\nstener.textChanged(PresentationReconciler.java:214)\n        at org.eclipse.jface.text.TextViewer.updateTextListeners(TextViewer.java\n:2222)\n        at org.eclipse.jface.text.TextViewer$DocumentListener.documentChanged(Te\nxtViewer.java:287)\n        at org.eclipse.jface.text.AbstractDocument.doFireDocumentChanged2(Abstra\nctDocument.java:673)\n        at org.eclipse.jface.text.AbstractDocument.doFireDocumentChanged(Abstrac\ntDocument.java:638)\n        at org.eclipse.jface.text.AbstractDocument.doFireDocumentChanged(Abstrac\ntDocument.java:623)\n        at org.eclipse.jface.text.AbstractDocument.fireDocumentChanged(AbstractD\nocument.java:698)\n        at org.eclipse.jface.text.AbstractDocument.replace(AbstractDocument.java\n:989)\n        at org.eclipse.ui.texteditor.DeleteLineTarget.deleteLine(DeleteLineTarge\nt.java:323)\n        at org.eclipse.ui.texteditor.DeleteLineAction.run(DeleteLineAction.java:\n145)\n        at org.eclipse.jface.action.Action.runWithEvent(Action.java:842)\n        at org.eclipse.ui.internal.commands.ActionHandler.execute(ActionHandler.\njava:40)\n        at org.eclipse.ui.internal.WorkbenchActivitiesCommandsAndRoles.press(Wor\nkbenchActivitiesCommandsAndRoles.java:504)\n        at org.eclipse.ui.internal.WorkbenchActivitiesCommandsAndRoles.processKe\nyEvent(WorkbenchActivitiesCommandsAndRoles.java:533)\n        at org.eclipse.ui.internal.WorkbenchActivitiesCommandsAndRoles.filterKey\nSequenceBindings(WorkbenchActivitiesCommandsAndRoles.java:406)\n        at org.eclipse.ui.internal.WorkbenchActivitiesCommandsAndRoles$6.handleE\nvent(WorkbenchActivitiesCommandsAndRoles.java:264)\n        at org.eclipse.swt.widgets.EventTable.sendEvent(EventTable.java:82)\n        at org.eclipse.swt.widgets.Display.filterEvent(Display.java:660)\n        at org.eclipse.swt.widgets.Widget.sendEvent(Widget.java:846)\n        at org.eclipse.swt.widgets.Widget.sendEvent(Widget.java:871)\n        at org.eclipse.swt.widgets.Widget.sendEvent(Widget.java:856)\n        at org.eclipse.swt.widgets.Control.sendKeyEvent(Control.java:1716)\n        at org.eclipse.swt.widgets.Control.sendKeyEvent(Control.java:1712)\n        at org.eclipse.swt.widgets.Control.WM_CHAR(Control.java:3029)\n        at org.eclipse.swt.widgets.Control.windowProc(Control.java:2932)\n        at org.eclipse.swt.widgets.Display.windowProc(Display.java:2712)\n        at org.eclipse.swt.internal.win32.OS.DispatchMessageW(Native Method)\n        at org.eclipse.swt.internal.win32.OS.DispatchMessage(OS.java:1361)\n        at org.eclipse.swt.widgets.Display.readAndDispatch(Display.java:1875)\n        at org.eclipse.ui.internal.Workbench.runEventLoop(Workbench.java:1405)\n        at org.eclipse.ui.internal.Workbench.runUI(Workbench.java:1381)\n        at org.eclipse.ui.internal.Workbench.createAndRunWorkbench(Workbench.jav\na:237)\n        at org.eclipse.ui.PlatformUI.createAndRunWorkbench(PlatformUI.java:139)\n        at org.eclipse.ui.internal.ide.IDEApplication.run(IDEApplication.java:47\n)\n        at org.eclipse.core.internal.boot.InternalBootLoader.run(InternalBootLoa\nder.java:858)\n        at org.eclipse.core.boot.BootLoader.run(BootLoader.java:461)\n        at sun.reflect.NativeMethodAccessorImpl.invoke0(Native Method)\n        at sun.reflect.NativeMethodAccessorImpl.invoke(NativeMethodAccessorImpl.\njava:39)\n        at sun.reflect.DelegatingMethodAccessorImpl.invoke(DelegatingMethodAcces\nsorImpl.java:25)\n        at java.lang.reflect.Method.invoke(Method.java:324)\n        at org.eclipse.core.launcher.Main.basicRun(Main.java:299)\n        at org.eclipse.core.launcher.Main.run(Main.java:767)\n        at org.eclipse.core.launcher.Main.main(Main.java:601)\nAction for command \u0027org.eclipse.ui.edit.text.delete.line\u0027 failed to execute prop\nerly.",
    "I got this when I had UI loaded but not JDT - did you get this self hosting or \nin your workbench? It went away for me when I brought JDT into my workspace.",
    "It was in my dev.\nI got the same thing this morning with build i1119 (2030)",
    "20031120.",
    "verified using I20031120"
  ],
  "commentCreationDates": [
    "2003-11-19T18:16:28+01:00",
    "2003-11-20T16:27:15+01:00",
    "2003-11-20T16:41:19+01:00",
    "2003-11-20T17:05:12+01:00",
    "2003-11-21T10:53:37+01:00"
  ],
  "traces": [
    {
      "exceptionType": "java.lang.NullPointerException",
      "elements": [
        {
          "method": "org.eclipse.jface.text.presentation.PresentationReconciler.getDamage",
          "source": " PresentationReconciler.java:459"
        },
        {
          "method": "org.eclipse.jface.text.presentation.PresentationReconciler.access$11",
          "source": " PresentationReconciler.java:456"
        },
        {
          "method": "org.eclipse.jface.text.presentation.PresentationReconciler$InternalListener.textChanged",
          "source": "PresentationReconciler.java:214"
        },
        {
          "method": "org.eclipse.jface.text.TextViewer.updateTextListeners",
          "source": "TextViewer.java :2222"
        },
        {
          "method": "org.eclipse.jface.text.TextViewer$DocumentListener.documentChanged",
          "source": "Te xtViewer.java:287"
        },
        {
          "method": "org.eclipse.jface.text.AbstractDocument.doFireDocumentChanged2",
          "source": "Abstra ctDocument.java:673"
        },
        {
          "method": "org.eclipse.jface.text.AbstractDocument.doFireDocumentChanged",
          "source": "Abstrac tDocument.java:638"
        },
        {
          "method": "org.eclipse.jface.text.AbstractDocument.doFireDocumentChanged",
          "source": "Abstrac tDocument.java:623"
        },
        {
          "method": "org.eclipse.jface.text.AbstractDocument.fireDocumentChanged",
          "source": "AbstractD ocument.java:698"
        },
        {
          "method": "org.eclipse.jface.text.AbstractDocument.replace",
          "source": "AbstractDocument.java :989"
        },
        {
          "method": "org.eclipse.ui.texteditor.DeleteLineTarget.deleteLine",
          "source": "DeleteLineTarge t.java:323"
        },
        {
          "method": "org.eclipse.ui.texteditor.DeleteLineAction.run",
          "source": "DeleteLineAction.java: 145"
        },
        {
          "method": "org.eclipse.jface.action.Action.runWithEvent",
          "source": "Action.java:842"
        },
        {
          "method": "org.eclipse.ui.internal.commands.ActionHandler.execute",
          "source": "ActionHandler. java:40"
        },
        {
          "method": "org.eclipse.ui.internal.WorkbenchActivitiesCommandsAndRoles.press",
          "source": "Wor kbenchActivitiesCommandsAndRoles.java:504"
        },
        {
          "method": "org.eclipse.ui.internal.WorkbenchActivitiesCommandsAndRoles.processKeyEvent",
          "source": "WorkbenchActivitiesCommandsAndRoles.java:533"
        },
        {
          "method": "org.eclipse.ui.internal.WorkbenchActivitiesCommandsAndRoles.filterKeySequenceBindings",
          "source": "WorkbenchActivitiesCommandsAndRoles.java:406"
        },
        {
          "method": "org.eclipse.ui.internal.WorkbenchActivitiesCommandsAndRoles$6.handleEvent",
          "source": "WorkbenchActivitiesCommandsAndRoles.java:264"
        },
        {
          "method": "org.eclipse.swt.widgets.EventTable.sendEvent",
          "source": "EventTable.java:82"
        },
        {
          "method": "org.eclipse.swt.widgets.Display.filterEvent",
          "source": "Display.java:660"
        },
        {
          "method": "org.eclipse.swt.widgets.Widget.sendEvent",
          "source": "Widget.java:846"
        },
        {
          "method": "org.eclipse.swt.widgets.Widget.sendEvent",
          "source": "Widget.java:871"
        },
        {
          "method": "org.eclipse.swt.widgets.Widget.sendEvent",
          "source": "Widget.java:856"
        },
        {
          "method": "org.eclipse.swt.widgets.Control.sendKeyEvent",
          "source": "Control.java:1716"
        },
        {
          "method": "org.eclipse.swt.widgets.Control.sendKeyEvent",
          "source": "Control.java:1712"
        },
        {
          "method": "org.eclipse.swt.widgets.Control.WM_CHAR",
          "source": "Control.java:3029"
        },
        {
          "method": "org.eclipse.swt.widgets.Control.windowProc",
          "source": "Control.java:2932"
        },
        {
          "method": "org.eclipse.swt.widgets.Display.windowProc",
          "source": "Display.java:2712"
        },
        {
          "method": "org.eclipse.swt.internal.win32.OS.DispatchMessageW",
          "source": "Native Method"
        },
        {
          "method": "org.eclipse.swt.internal.win32.OS.DispatchMessage",
          "source": "OS.java:1361"
        },
        {
          "method": "org.eclipse.swt.widgets.Display.readAndDispatch",
          "source": "Display.java:1875"
        },
        {
          "method": "org.eclipse.ui.internal.Workbench.runEventLoop",
          "source": "Workbench.java:1405"
        },
        {
          "method": "org.eclipse.ui.internal.Workbench.runUI",
          "source": "Workbench.java:1381"
        },
        {
          "method": "org.eclipse.ui.internal.Workbench.createAndRunWorkbench",
          "source": "Workbench.jav a:237"
        },
        {
          "method": "org.eclipse.ui.PlatformUI.createAndRunWorkbench",
          "source": "PlatformUI.java:139"
        },
        {
          "method": "org.eclipse.ui.internal.ide.IDEApplication.run",
          "source": "IDEApplication.java:47 "
        },
        {
          "method": "org.eclipse.core.internal.boot.InternalBootLoader.run",
          "source": "InternalBootLoa der.java:858"
        },
        {
          "method": "org.eclipse.core.boot.BootLoader.run",
          "source": "BootLoader.java:461"
        },
        {
          "method": "sun.reflect.NativeMethodAccessorImpl.invoke0",
          "source": "Native Method"
        },
        {
          "method": "sun.reflect.NativeMethodAccessorImpl.invoke",
          "source": "NativeMethodAccessorImpl. java:39"
        },
        {
          "method": "sun.reflect.DelegatingMethodAccessorImpl.invoke",
          "source": "DelegatingMethodAcces sorImpl.java:25"
        },
        {
          "method": "java.lang.reflect.Method.invoke",
          "source": "Method.java:324"
        },
        {
          "method": "org.eclipse.core.launcher.Main.basicRun",
          "source": "Main.java:299"
        },
        {
          "method": "org.eclipse.core.launcher.Main.run",
          "source": "Main.java:767"
        },
        {
          "method": "org.eclipse.core.launcher.Main.main",
          "source": "Main.java:601"
        }
      ],
      "number": 0,
      "commentIndex": 0,
      "bugId": "47017",
      "date": "2003-11-19T18:16:28+01:00",
      "product": "Platform",
      "component": "Text",
      "severity": "normal"
    }
  ],
  "groupId": "47017",
  "bugId": "47017",
  "date": "2003-11-19T18:16:28+01:00",
  "product": "Platform",
  "component": "Text",
  "severity": "normal"
}