{
  "comments": [
    "I200311192030\n\n- create a new java project with a class MyClass\n- close the project\n- try to open the file MyClass.java via File -\u003e Open External File...\n-\u003e Exception in the log\n\nFunny, but OK:\n- delete the project from the workspace but leave it on the file system\n-\u003e now, it can be openend as external file\n- leave the editor open and re-create the project\n-\u003e now, I can open a java editor on MyClass in addition to the external file editor\n\n\norg.eclipse.ui.PartInitException: File does not exist\n        at\norg.eclipse.ui.texteditor.AbstractTextEditor.internalInit(AbstractTextEditor.java:1998)\n        at\norg.eclipse.ui.texteditor.AbstractTextEditor.init(AbstractTextEditor.java:2011)\n        at org.eclipse.ui.internal.EditorManager.createSite(EditorManager.java:564)\n        at\norg.eclipse.ui.internal.EditorManager.openInternalEditor(EditorManager.java:628)\n        at\norg.eclipse.ui.internal.EditorManager.openEditorFromDescriptor(EditorManager.java:433)\n        at org.eclipse.ui.internal.EditorManager.openEditor(EditorManager.java:421)\n        at\norg.eclipse.ui.internal.WorkbenchPage.busyOpenEditor(WorkbenchPage.java:1974)\n        at org.eclipse.ui.internal.WorkbenchPage.access$6(WorkbenchPage.java:1926)\n        at org.eclipse.ui.internal.WorkbenchPage$9.run(WorkbenchPage.java:1913)\n        at org.eclipse.swt.custom.BusyIndicator.showWhile(BusyIndicator.java:84)\n        at org.eclipse.ui.internal.WorkbenchPage.openEditor(WorkbenchPage.java:1908)\n        at org.eclipse.ui.internal.WorkbenchPage.openEditor(WorkbenchPage.java:1896)\n        at\norg.eclipse.ui.internal.editors.text.OpenExternalFileAction.run(OpenExternalFileAction.java:112)\n        at\norg.eclipse.ui.internal.editors.text.OpenExternalFileAction.run(OpenExternalFileAction.java:84)\n        at org.eclipse.ui.internal.PluginAction.runWithEvent(PluginAction.java:270)\n        at\norg.eclipse.ui.internal.WWinPluginAction.runWithEvent(WWinPluginAction.java:207)\n        at\norg.eclipse.jface.action.ActionContributionItem.handleWidgetSelection(ActionContributionItem.java:542)\n        at\norg.eclipse.jface.action.ActionContributionItem.access$4(ActionContributionItem.java:494)\n        at\norg.eclipse.jface.action.ActionContributionItem$6.handleEvent(ActionContributionItem.java:466)\n        at org.eclipse.swt.widgets.EventTable.sendEvent(EventTable.java:82)\n        at org.eclipse.swt.widgets.Widget.sendEvent(Widget.java:847)\n        at org.eclipse.swt.widgets.Display.runDeferredEvents(Display.java:2187)\n        at org.eclipse.swt.widgets.Display.readAndDispatch(Display.java:1877)\n        at org.eclipse.ui.internal.Workbench.runEventLoop(Workbench.java:1405)\n        at org.eclipse.ui.internal.Workbench.runUI(Workbench.java:1381)\n        at\norg.eclipse.ui.internal.Workbench.createAndRunWorkbench(Workbench.java:237)\n        at org.eclipse.ui.PlatformUI.createAndRunWorkbench(PlatformUI.java:139)\n        at org.eclipse.ui.internal.ide.IDEApplication.run(IDEApplication.java:47)\n        at\norg.eclipse.core.internal.boot.InternalBootLoader.run(InternalBootLoader.java:858)\n        at org.eclipse.core.boot.BootLoader.run(BootLoader.java:461)\n        at sun.reflect.NativeMethodAccessorImpl.invoke0(Native Method)\n        at\nsun.reflect.NativeMethodAccessorImpl.invoke(NativeMethodAccessorImpl.java:39)\n        at\nsun.reflect.DelegatingMethodAccessorImpl.invoke(DelegatingMethodAccessorImpl.java:25)\n        at java.lang.reflect.Method.invoke(Method.java:324)\n        at org.eclipse.core.launcher.Main.basicRun(Main.java:299)\n        at org.eclipse.core.launcher.Main.run(Main.java:767)\n        at org.eclipse.core.launcher.Main.main(Main.java:601)",
    "not for M5\n",
    "works for me using N20050602-0010"
  ],
  "commentCreationDates": [
    "2003-11-20T11:57:42+01:00",
    "2003-11-20T15:22:40+01:00",
    "2005-06-02T10:27:36+02:00"
  ],
  "traces": [
    {
      "exceptionType": "org.eclipse.ui.PartInitException",
      "message": "File does not exist",
      "elements": [
        {
          "method": "org.eclipse.ui.texteditor.AbstractTextEditor.internalInit",
          "source": "AbstractTextEditor.java:1998"
        },
        {
          "method": "org.eclipse.ui.texteditor.AbstractTextEditor.init",
          "source": "AbstractTextEditor.java:2011"
        },
        {
          "method": "org.eclipse.ui.internal.EditorManager.createSite",
          "source": "EditorManager.java:564"
        },
        {
          "method": "org.eclipse.ui.internal.EditorManager.openInternalEditor",
          "source": "EditorManager.java:628"
        },
        {
          "method": "org.eclipse.ui.internal.EditorManager.openEditorFromDescriptor",
          "source": "EditorManager.java:433"
        },
        {
          "method": "org.eclipse.ui.internal.EditorManager.openEditor",
          "source": "EditorManager.java:421"
        },
        {
          "method": "org.eclipse.ui.internal.WorkbenchPage.busyOpenEditor",
          "source": "WorkbenchPage.java:1974"
        },
        {
          "method": "org.eclipse.ui.internal.WorkbenchPage.access$6",
          "source": "WorkbenchPage.java:1926"
        },
        {
          "method": "org.eclipse.ui.internal.WorkbenchPage$9.run",
          "source": "WorkbenchPage.java:1913"
        },
        {
          "method": "org.eclipse.swt.custom.BusyIndicator.showWhile",
          "source": "BusyIndicator.java:84"
        },
        {
          "method": "org.eclipse.ui.internal.WorkbenchPage.openEditor",
          "source": "WorkbenchPage.java:1908"
        },
        {
          "method": "org.eclipse.ui.internal.WorkbenchPage.openEditor",
          "source": "WorkbenchPage.java:1896"
        },
        {
          "method": "org.eclipse.ui.internal.editors.text.OpenExternalFileAction.run",
          "source": "OpenExternalFileAction.java:112"
        },
        {
          "method": "org.eclipse.ui.internal.editors.text.OpenExternalFileAction.run",
          "source": "OpenExternalFileAction.java:84"
        },
        {
          "method": "org.eclipse.ui.internal.PluginAction.runWithEvent",
          "source": "PluginAction.java:270"
        },
        {
          "method": "org.eclipse.ui.internal.WWinPluginAction.runWithEvent",
          "source": "WWinPluginAction.java:207"
        },
        {
          "method": "org.eclipse.jface.action.ActionContributionItem.handleWidgetSelection",
          "source": "ActionContributionItem.java:542"
        },
        {
          "method": "org.eclipse.jface.action.ActionContributionItem.access$4",
          "source": "ActionContributionItem.java:494"
        },
        {
          "method": "org.eclipse.jface.action.ActionContributionItem$6.handleEvent",
          "source": "ActionContributionItem.java:466"
        },
        {
          "method": "org.eclipse.swt.widgets.EventTable.sendEvent",
          "source": "EventTable.java:82"
        },
        {
          "method": "org.eclipse.swt.widgets.Widget.sendEvent",
          "source": "Widget.java:847"
        },
        {
          "method": "org.eclipse.swt.widgets.Display.runDeferredEvents",
          "source": "Display.java:2187"
        },
        {
          "method": "org.eclipse.swt.widgets.Display.readAndDispatch",
          "source": "Display.java:1877"
        },
        {
          "method": "org.eclipse.ui.internal.Workbench.runEventLoop",
          "source": "Workbench.java:1405"
        },
        {
          "method": "org.eclipse.ui.internal.Workbench.runUI",
          "source": "Workbench.java:1381"
        },
        {
          "method": "org.eclipse.ui.internal.Workbench.createAndRunWorkbench",
          "source": "Workbench.java:237"
        },
        {
          "method": "org.eclipse.ui.PlatformUI.createAndRunWorkbench",
          "source": "PlatformUI.java:139"
        },
        {
          "method": "org.eclipse.ui.internal.ide.IDEApplication.run",
          "source": "IDEApplication.java:47"
        },
        {
          "method": "org.eclipse.core.internal.boot.InternalBootLoader.run",
          "source": "InternalBootLoader.java:858"
        },
        {
          "method": "org.eclipse.core.boot.BootLoader.run",
          "source": "BootLoader.java:461"
        },
        {
          "method": "sun.reflect.NativeMethodAccessorImpl.invoke0",
          "source": "Native Method"
        },
        {
          "method": "sun.reflect.NativeMethodAccessorImpl.invoke",
          "source": "NativeMethodAccessorImpl.java:39"
        },
        {
          "method": "sun.reflect.DelegatingMethodAccessorImpl.invoke",
          "source": "DelegatingMethodAccessorImpl.java:25"
        },
        {
          "method": "java.lang.reflect.Method.invoke",
          "source": "Method.java:324"
        },
        {
          "method": "org.eclipse.core.launcher.Main.basicRun",
          "source": "Main.java:299"
        },
        {
          "method": "org.eclipse.core.launcher.Main.run",
          "source": "Main.java:767"
        },
        {
          "method": "org.eclipse.core.launcher.Main.main",
          "source": "Main.java:601"
        }
      ],
      "number": 0,
      "commentIndex": 0,
      "bugId": "47073",
      "date": "2003-11-20T11:57:42+01:00",
      "product": "Platform",
      "component": "Text",
      "severity": "minor"
    }
  ],
  "groupId": "47073",
  "bugId": "47073",
  "date": "2003-11-20T11:57:42+01:00",
  "product": "Platform",
  "component": "Text",
  "severity": "minor"
}