{
  "comments": [
    "Using I200311192030 I right clicked on plugin.xml, selected Export, selected \none plug-in, deployable zip file, include source, specified a filename, and \npressed Finish. Eclipse switched to the Progress view which said \u0027ERROR: PDE \nExport: An internal error occurred during: \"PDE Export\"\u0027. The .log file is \ncopied below.\n\n!ENTRY org.eclipse.core.runtime 4 2 Nov 20, 2003 10:20:59.839\n!MESSAGE An internal error occurred during: \"PDE Export\".\n!STACK 0\njava.lang.NullPointerException\n\tat java.io.File.\u003cinit\u003e(Unknown Source)\n\tat \norg.eclipse.pde.internal.build.builder.ModelBuildScriptGenerator.filterNonExist\ningSourceFolders(ModelBuildScriptGenerator.java:705)\n\tat \norg.eclipse.pde.internal.build.builder.ModelBuildScriptGenerator.generateSRCTar\nget(ModelBuildScriptGenerator.java:677)\n\tat \norg.eclipse.pde.internal.build.builder.ModelBuildScriptGenerator.generateBuildJ\narsTarget(ModelBuildScriptGenerator.java:579)\n\tat \norg.eclipse.pde.internal.build.builder.ModelBuildScriptGenerator.generateBuildS\ncript(ModelBuildScriptGenerator.java:148)\n\tat \norg.eclipse.pde.internal.build.builder.ModelBuildScriptGenerator.generate\n(ModelBuildScriptGenerator.java:110)\n\tat \norg.eclipse.pde.internal.ui.wizards.exports.PluginExportJob.makeScript\n(PluginExportJob.java:148)\n\tat org.eclipse.pde.internal.ui.wizards.exports.PluginExportJob.doExport\n(PluginExportJob.java:96)\n\tat org.eclipse.pde.internal.ui.wizards.exports.BaseExportJob.doExports\n(BaseExportJob.java:179)\n\tat org.eclipse.pde.internal.ui.wizards.exports.BaseExportJob.run\n(BaseExportJob.java:133)\n\tat org.eclipse.core.internal.jobs.Worker.run(Worker.java:62)\n\n\nbuild.properties says:\n\nsource.sds.jar \u003d src/\nbin.includes \u003d plugin.xml,\\\n               about.html,\\\n               icons/,\\\n               audio/,\\\n               sds.jar\n\n\nI think I see the problem, I don\u0027t actually have a src/ directory (I call mine \nSource/Java). After fixing build.properties to the following, the export \ncompleted without error:\n\nbin.includes \u003d plugin.xml,\\\n               about.html,\\\n               icons/,\\\n               audio/,\\\n               sds.jar\nsource.sds.jar \u003d Source/Java/\noutput.sds.jar \u003d build/\nsrc.includes \u003d Source/Java/",
    "Good information in your bug report, thanks.\nFixed and released to HEAD.\n",
    "*** Bug 46078 has been marked as a duplicate of this bug. ***"
  ],
  "commentCreationDates": [
    "2003-11-20T16:44:53+01:00",
    "2003-11-20T17:10:43+01:00",
    "2003-11-20T17:14:05+01:00"
  ],
  "traces": [
    {
      "exceptionType": "java.lang.NullPointerException",
      "elements": [
        {
          "method": "java.io.File.\u003cinit\u003e",
          "source": "Unknown Source"
        },
        {
          "method": "org.eclipse.pde.internal.build.builder.ModelBuildScriptGenerator.filterNonExistingSourceFolders",
          "source": "ModelBuildScriptGenerator.java:705"
        },
        {
          "method": "org.eclipse.pde.internal.build.builder.ModelBuildScriptGenerator.generateSRCTarget",
          "source": "ModelBuildScriptGenerator.java:677"
        },
        {
          "method": "org.eclipse.pde.internal.build.builder.ModelBuildScriptGenerator.generateBuildJarsTarget",
          "source": "ModelBuildScriptGenerator.java:579"
        },
        {
          "method": "org.eclipse.pde.internal.build.builder.ModelBuildScriptGenerator.generateBuildScript",
          "source": "ModelBuildScriptGenerator.java:148"
        },
        {
          "method": "org.eclipse.pde.internal.build.builder.ModelBuildScriptGenerator.generate",
          "source": "ModelBuildScriptGenerator.java:110"
        },
        {
          "method": "org.eclipse.pde.internal.ui.wizards.exports.PluginExportJob.makeScript",
          "source": "PluginExportJob.java:148"
        },
        {
          "method": "org.eclipse.pde.internal.ui.wizards.exports.PluginExportJob.doExport",
          "source": "PluginExportJob.java:96"
        },
        {
          "method": "org.eclipse.pde.internal.ui.wizards.exports.BaseExportJob.doExports",
          "source": "BaseExportJob.java:179"
        },
        {
          "method": "org.eclipse.pde.internal.ui.wizards.exports.BaseExportJob.run",
          "source": "BaseExportJob.java:133"
        },
        {
          "method": "org.eclipse.core.internal.jobs.Worker.run",
          "source": "Worker.java:62"
        }
      ],
      "number": 0,
      "commentIndex": 0,
      "bugId": "47106",
      "date": "2003-11-20T16:44:53+01:00",
      "product": "PDE",
      "component": "Build",
      "severity": "normal"
    }
  ],
  "groupId": "47106",
  "bugId": "47106",
  "date": "2003-11-20T16:44:53+01:00",
  "product": "PDE",
  "component": "Build",
  "severity": "normal"
}