{
  "comments": [
    "!MESSAGE Internal error logged from JDI Debug:\n!STACK 1\norg.eclipse.debug.core.DebugException: Thread not suspended, stack frame unavail\nable.\n        at org.eclipse.jdt.internal.debug.core.model.JDIDebugElement.throwDebugE\nxception(JDIDebugElement.java:284)\n        at org.eclipse.jdt.internal.debug.core.model.JDIDebugElement.requestFail\ned(JDIDebugElement.java:242)\n        at org.eclipse.jdt.internal.debug.core.model.JDIStackFrame.getUnderlying\nStackFrame(JDIStackFrame.java:931)\n        at org.eclipse.jdt.internal.debug.core.model.JDILocalVariable.retrieveVa\nlue(JDILocalVariable.java:56)\n        at org.eclipse.jdt.internal.debug.core.model.JDIVariable.getCurrentValue\n(JDIVariable.java:67)\n        at org.eclipse.jdt.internal.debug.core.model.JDIModificationVariable.sup\nportsValueModification(JDIModificationVariable.java:50)\n        at org.eclipse.debug.internal.ui.actions.ChangeVariableValueAction.updat\ne(ChangeVariableValueAction.java:120)\n        at org.eclipse.debug.internal.ui.actions.ChangeVariableValueAction.selec\ntionChanged(ChangeVariableValueAction.java:143)\n        at org.eclipse.ui.actions.SelectionProviderAction.selectionChanged(Selec\ntionProviderAction.java:132)\n        at org.eclipse.jface.viewers.Viewer$2.run(Viewer.java:159)\n        at org.eclipse.core.internal.runtime.InternalPlatform.run(InternalPlatfo\nrm.java:1006)\n        at org.eclipse.core.runtime.Platform.run(Platform.java:413)\n        at org.eclipse.jface.viewers.Viewer.fireSelectionChanged(Viewer.java:157\n)\n        at org.eclipse.jface.viewers.StructuredViewer.updateSelection(Structured\nViewer.java:1290)\n        at org.eclipse.jface.viewers.StructuredViewer.handleSelect(StructuredVie\nwer.java:657)\n        at org.eclipse.jface.viewers.StructuredViewer$4.widgetSelected(Structure\ndViewer.java:681)\n        at org.eclipse.jface.util.OpenStrategy.fireSelectionEvent(OpenStrategy.j\nava:178)\n        at org.eclipse.jface.util.OpenStrategy.access$3(OpenStrategy.java:173)\n        at org.eclipse.jface.util.OpenStrategy$1.handleEvent(OpenStrategy.java:3\n                                                                    08)\n        at org.eclipse.swt.widgets.EventTable.sendEvent(EventTable.java:81)\n        at org.eclipse.swt.widgets.Widget.sendEvent(Widget.java:923)\n        at org.eclipse.swt.widgets.Display.runDeferredEvents(Display.java:1847)\n        at org.eclipse.swt.widgets.Display.readAndDispatch(Display.java:1639)\n        at org.eclipse.ui.internal.Workbench.runEventLoop(Workbench.java:1402)\n        at org.eclipse.ui.internal.Workbench.run(Workbench.java:1385)\n        at org.eclipse.core.internal.boot.InternalBootLoader.run(InternalBootLoa\n                                                                    der.java:858)\n        at org.eclipse.core.boot.BootLoader.run(BootLoader.java:461)\n        at sun.reflect.NativeMethodAccessorImpl.invoke0(Native Method)\n        at sun.reflect.NativeMethodAccessorImpl.invoke(NativeMethodAccessorImpl.\n                                                                    java:39)\n        at sun.reflect.DelegatingMethodAccessorImpl.invoke(DelegatingMethodAcces\n                                                                    sorImpl.java:25)\n        at java.lang.reflect.Method.invoke(Method.java:324)\n        at org.eclipse.core.launcher.Main.basicRun(Main.java:291)\n        at org.eclipse.core.launcher.Main.run(Main.java:747)\n        at org.eclipse.core.launcher.Main.main(Main.java:583)\n!ENTRY org.eclipse.jdt.debug 4 100 Nov 20, 2003 15:04:50.726\n!MESSAGE Thread not suspended, stack frame unavailable.",
    "Please could you see whether this still fails with AJDT 1.1.11 with Eclipse 3.0\nfinal. If so, include recreate steps if possible.",
    "No response so assuming this is no longer a problem."
  ],
  "commentCreationDates": [
    "2003-11-20T18:23:31+01:00",
    "2004-07-26T16:03:57+02:00",
    "2004-08-09T12:20:18+02:00"
  ],
  "traces": [
    {
      "exceptionType": "org.eclipse.debug.core.DebugException",
      "message": "Thread not suspended, stack frame unavail able.",
      "elements": [
        {
          "method": "org.eclipse.jdt.internal.debug.core.model.JDIDebugElement.throwDebugException",
          "source": "JDIDebugElement.java:284"
        },
        {
          "method": "org.eclipse.jdt.internal.debug.core.model.JDIDebugElement.requestFailed",
          "source": "JDIDebugElement.java:242"
        },
        {
          "method": "org.eclipse.jdt.internal.debug.core.model.JDIStackFrame.getUnderlyingStackFrame",
          "source": "JDIStackFrame.java:931"
        },
        {
          "method": "org.eclipse.jdt.internal.debug.core.model.JDILocalVariable.retrieveValue",
          "source": "JDILocalVariable.java:56"
        },
        {
          "method": "org.eclipse.jdt.internal.debug.core.model.JDIVariable.getCurrentValue",
          "source": "JDIVariable.java:67"
        },
        {
          "method": "org.eclipse.jdt.internal.debug.core.model.JDIModificationVariable.supportsValueModification",
          "source": "JDIModificationVariable.java:50"
        },
        {
          "method": "org.eclipse.debug.internal.ui.actions.ChangeVariableValueAction.update",
          "source": "ChangeVariableValueAction.java:120"
        },
        {
          "method": "org.eclipse.debug.internal.ui.actions.ChangeVariableValueAction.selectionChanged",
          "source": "ChangeVariableValueAction.java:143"
        },
        {
          "method": "org.eclipse.ui.actions.SelectionProviderAction.selectionChanged",
          "source": "Selec tionProviderAction.java:132"
        },
        {
          "method": "org.eclipse.jface.viewers.Viewer$2.run",
          "source": "Viewer.java:159"
        },
        {
          "method": "org.eclipse.core.internal.runtime.InternalPlatform.run",
          "source": "InternalPlatfo rm.java:1006"
        },
        {
          "method": "org.eclipse.core.runtime.Platform.run",
          "source": "Platform.java:413"
        },
        {
          "method": "org.eclipse.jface.viewers.Viewer.fireSelectionChanged",
          "source": "Viewer.java:157 "
        },
        {
          "method": "org.eclipse.jface.viewers.StructuredViewer.updateSelection",
          "source": "Structured Viewer.java:1290"
        },
        {
          "method": "org.eclipse.jface.viewers.StructuredViewer.handleSelect",
          "source": "StructuredVie wer.java:657"
        },
        {
          "method": "org.eclipse.jface.viewers.StructuredViewer$4.widgetSelected",
          "source": "Structure dViewer.java:681"
        },
        {
          "method": "org.eclipse.jface.util.OpenStrategy.fireSelectionEvent",
          "source": "OpenStrategy.j ava:178"
        },
        {
          "method": "org.eclipse.jface.util.OpenStrategy.access$3",
          "source": "OpenStrategy.java:173"
        },
        {
          "method": "org.eclipse.jface.util.OpenStrategy$1.handleEvent",
          "source": "OpenStrategy.java:3                                                                     08"
        },
        {
          "method": "org.eclipse.swt.widgets.EventTable.sendEvent",
          "source": "EventTable.java:81"
        },
        {
          "method": "org.eclipse.swt.widgets.Widget.sendEvent",
          "source": "Widget.java:923"
        },
        {
          "method": "org.eclipse.swt.widgets.Display.runDeferredEvents",
          "source": "Display.java:1847"
        },
        {
          "method": "org.eclipse.swt.widgets.Display.readAndDispatch",
          "source": "Display.java:1639"
        },
        {
          "method": "org.eclipse.ui.internal.Workbench.runEventLoop",
          "source": "Workbench.java:1402"
        },
        {
          "method": "org.eclipse.ui.internal.Workbench.run",
          "source": "Workbench.java:1385"
        },
        {
          "method": "org.eclipse.core.internal.boot.InternalBootLoader.run",
          "source": "InternalBootLoa                                                                     der.java:858"
        },
        {
          "method": "org.eclipse.core.boot.BootLoader.run",
          "source": "BootLoader.java:461"
        },
        {
          "method": "sun.reflect.NativeMethodAccessorImpl.invoke0",
          "source": "Native Method"
        },
        {
          "method": "sun.reflect.NativeMethodAccessorImpl.invoke",
          "source": "NativeMethodAccessorImpl.                                                                     java:39"
        },
        {
          "method": "sun.reflect.DelegatingMethodAccessorImpl.invoke",
          "source": "DelegatingMethodAcces                                                                     sorImpl.java:25"
        },
        {
          "method": "java.lang.reflect.Method.invoke",
          "source": "Method.java:324"
        },
        {
          "method": "org.eclipse.core.launcher.Main.basicRun",
          "source": "Main.java:291"
        },
        {
          "method": "org.eclipse.core.launcher.Main.run",
          "source": "Main.java:747"
        },
        {
          "method": "org.eclipse.core.launcher.Main.main",
          "source": "Main.java:583"
        }
      ],
      "number": 0,
      "commentIndex": 0,
      "bugId": "47129",
      "date": "2003-11-20T18:23:31+01:00",
      "product": "AJDT",
      "component": "Core",
      "severity": "normal"
    }
  ],
  "groupId": "47129",
  "bugId": "47129",
  "date": "2003-11-20T18:23:31+01:00",
  "product": "AJDT",
  "component": "Core",
  "severity": "normal"
}