{
  "comments": [
    "Build 200311192030\n\nMy steps:\n1. Open Type on \"TreeViewer\" in a selfhosting workspace with JFace imported as binary.\n2. Go to the method internalRemove(Object[])\n3. Hover the word parentItems on the second line of the method. The following is dumped the the \nconsole. Nothing is written to the log file.\n\njava.lang.ClassCastException\n        at org.eclipse.jdt.internal.core.util.HandleFactory$1$Visitor.visit(HandleFactory.java:205)\n        at org.eclipse.jdt.internal.compiler.ast.FieldDeclaration.traverse(FieldDeclaration.java:234)\n        at org.eclipse.jdt.internal.compiler.ast.TypeDeclaration.traverse(TypeDeclaration.java:927)\n        at org.eclipse.jdt.internal.compiler.ast.CompilationUnitDeclaration.\ntraverse(CompilationUnitDeclaration.java:305)\n        at org.eclipse.jdt.internal.core.util.HandleFactory.createElement(HandleFactory.java:296)\n        at org.eclipse.jdt.internal.core.SelectionRequestor.acceptLocalVariable(SelectionRequestor.\njava:191)\n        at org.eclipse.jdt.internal.codeassist.SelectionEngine.selectFrom(SelectionEngine.java:650)\n        at org.eclipse.jdt.internal.codeassist.SelectionEngine.select(SelectionEngine.java:520)\n        at org.eclipse.jdt.internal.core.Openable.codeSelect(Openable.java:169)\n        at org.eclipse.jdt.internal.core.ClassFile.codeSelect(ClassFile.java:135)\n        at org.eclipse.jdt.internal.core.ClassFile.codeSelect(ClassFile.java:120)\n        at org.eclipse.jdt.internal.ui.text.java.hover.AbstractJavaEditorTextHover.\ngetHoverInfo(AbstractJavaEditorTextHover.java:95)\n        at org.eclipse.jdt.internal.ui.text.java.hover.BestMatchHover.getHoverInfo(BestMatchHover.\njava:140)\n        at org.eclipse.jdt.internal.ui.text.java.hover.JavaEditorTextHoverProxy.\ngetHoverInfo(JavaEditorTextHoverProxy.java:69)\n        at org.eclipse.jface.text.TextViewerHoverManager$2.run(TextViewerHoverManager.java:\n119)",
    "Fixed.\n\nNow the hover on the local variable works properly.\n",
    "Verified in 200311211210.",
    "Note to reproduce: the class is AbstractTreeViewer (and not TreeViewer)",
    "*** Bug 47895 has been marked as a duplicate of this bug. ***"
  ],
  "commentCreationDates": [
    "2003-11-20T21:27:13+01:00",
    "2003-11-21T12:19:14+01:00",
    "2003-11-21T18:43:41+01:00",
    "2003-12-12T11:20:37+01:00",
    "2003-12-16T14:46:02+01:00"
  ],
  "traces": [
    {
      "exceptionType": "java.lang.ClassCastException",
      "elements": [
        {
          "method": "org.eclipse.jdt.internal.core.util.HandleFactory$1$Visitor.visit",
          "source": "HandleFactory.java:205"
        },
        {
          "method": "org.eclipse.jdt.internal.compiler.ast.FieldDeclaration.traverse",
          "source": "FieldDeclaration.java:234"
        },
        {
          "method": "org.eclipse.jdt.internal.compiler.ast.TypeDeclaration.traverse",
          "source": "TypeDeclaration.java:927"
        },
        {
          "method": "org.eclipse.jdt.internal.compiler.ast.CompilationUnitDeclaration.traverse",
          "source": "CompilationUnitDeclaration.java:305"
        },
        {
          "method": "org.eclipse.jdt.internal.core.util.HandleFactory.createElement",
          "source": "HandleFactory.java:296"
        },
        {
          "method": "org.eclipse.jdt.internal.core.SelectionRequestor.acceptLocalVariable",
          "source": "SelectionRequestor. java:191"
        },
        {
          "method": "org.eclipse.jdt.internal.codeassist.SelectionEngine.selectFrom",
          "source": "SelectionEngine.java:650"
        },
        {
          "method": "org.eclipse.jdt.internal.codeassist.SelectionEngine.select",
          "source": "SelectionEngine.java:520"
        },
        {
          "method": "org.eclipse.jdt.internal.core.Openable.codeSelect",
          "source": "Openable.java:169"
        },
        {
          "method": "org.eclipse.jdt.internal.core.ClassFile.codeSelect",
          "source": "ClassFile.java:135"
        },
        {
          "method": "org.eclipse.jdt.internal.core.ClassFile.codeSelect",
          "source": "ClassFile.java:120"
        },
        {
          "method": "org.eclipse.jdt.internal.ui.text.java.hover.AbstractJavaEditorTextHover.getHoverInfo",
          "source": "AbstractJavaEditorTextHover.java:95"
        },
        {
          "method": "org.eclipse.jdt.internal.ui.text.java.hover.BestMatchHover.getHoverInfo",
          "source": "BestMatchHover. java:140"
        },
        {
          "method": "org.eclipse.jdt.internal.ui.text.java.hover.JavaEditorTextHoverProxy.getHoverInfo",
          "source": "JavaEditorTextHoverProxy.java:69"
        },
        {
          "method": "org.eclipse.jface.text.TextViewerHoverManager$2.run",
          "source": "TextViewerHoverManager.java: 119"
        }
      ],
      "number": 0,
      "commentIndex": 0,
      "bugId": "47177",
      "date": "2003-11-20T21:27:13+01:00",
      "product": "JDT",
      "component": "Core",
      "severity": "normal"
    }
  ],
  "groupId": "47177",
  "bugId": "47177",
  "date": "2003-11-20T21:27:13+01:00",
  "product": "JDT",
  "component": "Core",
  "severity": "normal"
}