{
  "comments": [
    "build i1119 (2030) + Core JARS for bug 46894\nWinXP, sunjdk1.4.2\n\nI was testing a fix for the above-mentioned report and got the following in my\n.log file. Not sure if its related to the \"got a delta when I wasn\u0027t expecting\nit\" problems, but thought that I should report it just in case. My test case was\n(with auto-build off) check out all the projects from eclipse.org in groups of\n5-15. (multiple concurrent checkouts)\n\n!ENTRY org.eclipse.core.resources 4 2 Nov 20, 2003 16:27:31.928\n!MESSAGE Problems occurred when invoking code from plug-in: \"org.eclipse.core.re\nsources\".\n!STACK 0\njava.lang.NullPointerException\n        at org.eclipse.jdt.internal.core.DeltaProcessor.traverseDelta(DeltaProce\nssor.java:1940)\n        at org.eclipse.jdt.internal.core.DeltaProcessor.traverseDelta(DeltaProce\nssor.java:1932)\n        at org.eclipse.jdt.internal.core.DeltaProcessor.traverseDelta(DeltaProce\nssor.java:1932)\n        at org.eclipse.jdt.internal.core.DeltaProcessor.traverseDelta(DeltaProce\nssor.java:1932)\n        at org.eclipse.jdt.internal.core.DeltaProcessor.traverseDelta(DeltaProce\nssor.java:1932)\n        at org.eclipse.jdt.internal.core.DeltaProcessor.traverseDelta(DeltaProce\nssor.java:1932)\n        at org.eclipse.jdt.internal.core.DeltaProcessor.traverseDelta(DeltaProce\nssor.java:1932)\n        at org.eclipse.jdt.internal.core.DeltaProcessor.processResourceDelta(Del\ntaProcessor.java:1589)\n        at org.eclipse.jdt.internal.core.DeltaProcessor.resourceChanged(DeltaPro\ncessor.java:1813)\n        at org.eclipse.jdt.internal.core.DeltaProcessingState.resourceChanged(De\nltaProcessingState.java:226)\n        at org.eclipse.core.internal.events.NotificationManager$2.run(Notificati\nonManager.java:251)\n        at org.eclipse.core.internal.runtime.InternalPlatform.run(InternalPlatfo\nrm.java:1127)\n        at org.eclipse.core.runtime.Platform.run(Platform.java:464)\n        at org.eclipse.core.internal.events.NotificationManager.notify(Notificat\nionManager.java:244)\n        at org.eclipse.core.internal.events.NotificationManager.broadcastChanges\n(NotificationManager.java:138)\n        at org.eclipse.core.internal.resources.Workspace.broadcastChanges(Worksp\nace.java:146)\n        at org.eclipse.core.internal.resources.Workspace.endOperation(Workspace.\njava:847)\n        at org.eclipse.core.internal.resources.Resource.setLocal(Resource.java:1\n185)\n        at org.eclipse.core.internal.resources.Folder.internalCreate(Folder.java\n:162)\n        at org.eclipse.core.internal.resources.Folder.create(Folder.java:99)\n        at org.eclipse.core.internal.resources.Folder.create(Folder.java:116)\n        at org.eclipse.team.internal.ccvs.core.resources.EclipseFolder.mkdir(Ecl\nipseFolder.java:115)\n        at org.eclipse.team.internal.ccvs.core.client.ResponseHandler.createFold\ner(ResponseHandler.java:76)\n        at org.eclipse.team.internal.ccvs.core.client.StickyHandler.handle(Stick\nyHandler.java:65)\n        at org.eclipse.team.internal.ccvs.core.client.Request.executeRequest(Req\nuest.java:232)\n        at org.eclipse.team.internal.ccvs.core.client.Command.doExecute(Command.\njava:404)\n        at org.eclipse.team.internal.ccvs.core.client.Checkout.doExecute(Checkou\nt.java:166)\n        at org.eclipse.team.internal.ccvs.core.client.CheckoutWithOverwrite.doEx\necute(CheckoutWithOverwrite.java:52)\n        at org.eclipse.team.internal.ccvs.core.client.Command$1.run(Command.java\n:336)\n        at org.eclipse.team.internal.ccvs.core.resources.EclipseSynchronizer.run\n(EclipseSynchronizer.java:1381)\n        at org.eclipse.team.internal.ccvs.core.resources.EclipseFolder$3.run(Ecl\nipseFolder.java:300)\n        at org.eclipse.core.internal.resources.Workspace.run(Workspace.java:1554\n)\n        at org.eclipse.core.internal.resources.Workspace.run(Workspace.java:1579\n)\n        at org.eclipse.team.internal.ccvs.core.resources.EclipseFolder.run(Eclip\nseFolder.java:297)\n        at org.eclipse.team.internal.ccvs.core.client.Command.execute(Command.ja\nva:347)\n        at org.eclipse.team.internal.ccvs.ui.operations.CheckoutProjectOperation\n.performCheckout(CheckoutProjectOperation.java:227)\n        at org.eclipse.team.internal.ccvs.ui.operations.CheckoutProjectOperation\n$1.run(CheckoutProjectOperation.java:155)\n        at org.eclipse.team.internal.ccvs.core.resources.EclipseSynchronizer.run\n(EclipseSynchronizer.java:1381)\n        at org.eclipse.team.internal.ccvs.ui.operations.CheckoutProjectOperation\n.checkout(CheckoutProjectOperation.java:153)\n        at org.eclipse.team.internal.ccvs.ui.operations.CheckoutMultipleProjects\nOperation.checkout(CheckoutMultipleProjectsOperation.java:52)\n        at org.eclipse.team.internal.ccvs.ui.operations.CheckoutOperation.checko\nut(CheckoutOperation.java:46)\n        at org.eclipse.team.internal.ccvs.ui.operations.CheckoutOperation.execut\ne(CheckoutOperation.java:31)\n        at org.eclipse.team.internal.ccvs.ui.operations.CVSOperation.run(CVSOper\nation.java:127)\n        at org.eclipse.team.internal.ccvs.ui.operations.CVSNonblockingRunnableCo\nntext.run(CVSNonblockingRunnableContext.java:47)\n        at org.eclipse.team.internal.ccvs.ui.operations.CVSNonblockingRunnableCo\nntext$2.runInWorkspace(CVSNonblockingRunnableContext.java:67)\n        at org.eclipse.core.internal.resources.InternalWorkspaceJob.run(Internal\nWorkspaceJob.java:37)\n        at org.eclipse.core.internal.jobs.Worker.run(Worker.java:62)",
    "Inverted the equals() check, as the current element could be the IJavaModel and \nreturn null.",
    "Could not reproduce in 200311211210.\nVerified."
  ],
  "commentCreationDates": [
    "2003-11-20T21:35:52+01:00",
    "2003-11-21T15:55:48+01:00",
    "2003-11-21T19:02:41+01:00"
  ],
  "traces": [
    {
      "exceptionType": "java.lang.NullPointerException",
      "elements": [
        {
          "method": "org.eclipse.jdt.internal.core.DeltaProcessor.traverseDelta",
          "source": "DeltaProce ssor.java:1940"
        },
        {
          "method": "org.eclipse.jdt.internal.core.DeltaProcessor.traverseDelta",
          "source": "DeltaProce ssor.java:1932"
        },
        {
          "method": "org.eclipse.jdt.internal.core.DeltaProcessor.traverseDelta",
          "source": "DeltaProce ssor.java:1932"
        },
        {
          "method": "org.eclipse.jdt.internal.core.DeltaProcessor.traverseDelta",
          "source": "DeltaProce ssor.java:1932"
        },
        {
          "method": "org.eclipse.jdt.internal.core.DeltaProcessor.traverseDelta",
          "source": "DeltaProce ssor.java:1932"
        },
        {
          "method": "org.eclipse.jdt.internal.core.DeltaProcessor.traverseDelta",
          "source": "DeltaProce ssor.java:1932"
        },
        {
          "method": "org.eclipse.jdt.internal.core.DeltaProcessor.traverseDelta",
          "source": "DeltaProce ssor.java:1932"
        },
        {
          "method": "org.eclipse.jdt.internal.core.DeltaProcessor.processResourceDelta",
          "source": "Del taProcessor.java:1589"
        },
        {
          "method": "org.eclipse.jdt.internal.core.DeltaProcessor.resourceChanged",
          "source": "DeltaPro cessor.java:1813"
        },
        {
          "method": "org.eclipse.jdt.internal.core.DeltaProcessingState.resourceChanged",
          "source": "De ltaProcessingState.java:226"
        },
        {
          "method": "org.eclipse.core.internal.events.NotificationManager$2.run",
          "source": "Notificati onManager.java:251"
        },
        {
          "method": "org.eclipse.core.internal.runtime.InternalPlatform.run",
          "source": "InternalPlatfo rm.java:1127"
        },
        {
          "method": "org.eclipse.core.runtime.Platform.run",
          "source": "Platform.java:464"
        },
        {
          "method": "org.eclipse.core.internal.events.NotificationManager.notify",
          "source": "Notificat ionManager.java:244"
        },
        {
          "method": "org.eclipse.core.internal.events.NotificationManager.broadcastChanges",
          "source": "NotificationManager.java:138"
        },
        {
          "method": "org.eclipse.core.internal.resources.Workspace.broadcastChanges",
          "source": "Worksp ace.java:146"
        },
        {
          "method": "org.eclipse.core.internal.resources.Workspace.endOperation",
          "source": "Workspace. java:847"
        },
        {
          "method": "org.eclipse.core.internal.resources.Resource.setLocal",
          "source": "Resource.java:1 185"
        },
        {
          "method": "org.eclipse.core.internal.resources.Folder.internalCreate",
          "source": "Folder.java :162"
        },
        {
          "method": "org.eclipse.core.internal.resources.Folder.create",
          "source": "Folder.java:99"
        },
        {
          "method": "org.eclipse.core.internal.resources.Folder.create",
          "source": "Folder.java:116"
        },
        {
          "method": "org.eclipse.team.internal.ccvs.core.resources.EclipseFolder.mkdir",
          "source": "Ecl ipseFolder.java:115"
        },
        {
          "method": "org.eclipse.team.internal.ccvs.core.client.ResponseHandler.createFolder",
          "source": "ResponseHandler.java:76"
        },
        {
          "method": "org.eclipse.team.internal.ccvs.core.client.StickyHandler.handle",
          "source": "Stick yHandler.java:65"
        },
        {
          "method": "org.eclipse.team.internal.ccvs.core.client.Request.executeRequest",
          "source": "Req uest.java:232"
        },
        {
          "method": "org.eclipse.team.internal.ccvs.core.client.Command.doExecute",
          "source": "Command. java:404"
        },
        {
          "method": "org.eclipse.team.internal.ccvs.core.client.Checkout.doExecute",
          "source": "Checkou t.java:166"
        },
        {
          "method": "org.eclipse.team.internal.ccvs.core.client.CheckoutWithOverwrite.doExecute",
          "source": "CheckoutWithOverwrite.java:52"
        },
        {
          "method": "org.eclipse.team.internal.ccvs.core.client.Command$1.run",
          "source": "Command.java :336"
        },
        {
          "method": "org.eclipse.team.internal.ccvs.core.resources.EclipseSynchronizer.run",
          "source": "EclipseSynchronizer.java:1381"
        },
        {
          "method": "org.eclipse.team.internal.ccvs.core.resources.EclipseFolder$3.run",
          "source": "Ecl ipseFolder.java:300"
        },
        {
          "method": "org.eclipse.core.internal.resources.Workspace.run",
          "source": "Workspace.java:1554 "
        },
        {
          "method": "org.eclipse.core.internal.resources.Workspace.run",
          "source": "Workspace.java:1579 "
        },
        {
          "method": "org.eclipse.team.internal.ccvs.core.resources.EclipseFolder.run",
          "source": "Eclip seFolder.java:297"
        },
        {
          "method": "org.eclipse.team.internal.ccvs.core.client.Command.execute",
          "source": "Command.ja va:347"
        },
        {
          "method": "org.eclipse.team.internal.ccvs.ui.operations.CheckoutProjectOperation.performCheckout",
          "source": "CheckoutProjectOperation.java:227"
        },
        {
          "method": "org.eclipse.team.internal.ccvs.ui.operations.CheckoutProjectOperation$1.run",
          "source": "CheckoutProjectOperation.java:155"
        },
        {
          "method": "org.eclipse.team.internal.ccvs.core.resources.EclipseSynchronizer.run",
          "source": "EclipseSynchronizer.java:1381"
        },
        {
          "method": "org.eclipse.team.internal.ccvs.ui.operations.CheckoutProjectOperation.checkout",
          "source": "CheckoutProjectOperation.java:153"
        },
        {
          "method": "org.eclipse.team.internal.ccvs.ui.operations.CheckoutMultipleProjectsOperation.checkout",
          "source": "CheckoutMultipleProjectsOperation.java:52"
        },
        {
          "method": "org.eclipse.team.internal.ccvs.ui.operations.CheckoutOperation.checkout",
          "source": "CheckoutOperation.java:46"
        },
        {
          "method": "org.eclipse.team.internal.ccvs.ui.operations.CheckoutOperation.execute",
          "source": "CheckoutOperation.java:31"
        },
        {
          "method": "org.eclipse.team.internal.ccvs.ui.operations.CVSOperation.run",
          "source": "CVSOper ation.java:127"
        },
        {
          "method": "org.eclipse.team.internal.ccvs.ui.operations.CVSNonblockingRunnableContext.run",
          "source": "CVSNonblockingRunnableContext.java:47"
        },
        {
          "method": "org.eclipse.team.internal.ccvs.ui.operations.CVSNonblockingRunnableContext$2.runInWorkspace",
          "source": "CVSNonblockingRunnableContext.java:67"
        },
        {
          "method": "org.eclipse.core.internal.resources.InternalWorkspaceJob.run",
          "source": "Internal WorkspaceJob.java:37"
        },
        {
          "method": "org.eclipse.core.internal.jobs.Worker.run",
          "source": "Worker.java:62"
        }
      ],
      "number": 0,
      "commentIndex": 0,
      "bugId": "47180",
      "date": "2003-11-20T21:35:52+01:00",
      "product": "JDT",
      "component": "Core",
      "severity": "normal"
    }
  ],
  "groupId": "47180",
  "bugId": "47180",
  "date": "2003-11-20T21:35:52+01:00",
  "product": "JDT",
  "component": "Core",
  "severity": "normal"
}