{
  "comments": [
    "build i1121\nj9sc 0915\nwinxp\n\n- I started the new build on an old workspace.\n- in the Navigator I tried to open a closed project\n- I got the following in my log file\n- note the project was opened in the end\n\n!ENTRY org.eclipse.core.resources 4 2 Nov 21, 2003 13:46:14.764\n!MESSAGE Problems occurred when invoking code from plug-in: \"org.eclipse.core.re\nsources\".\n!STACK 0\norg.eclipse.swt.SWTException: Invalid thread access\n        at java.lang.Throwable.\u003cinit\u003e(Throwable.java)\n        at java.lang.Throwable.\u003cinit\u003e(Throwable.java)\n        at org.eclipse.swt.SWTException.\u003cinit\u003e(SWTException.java:73)\n        at org.eclipse.swt.SWTException.\u003cinit\u003e(SWTException.java:62)\n        at org.eclipse.swt.SWT.error(SWT.java:2592)\n        at org.eclipse.swt.SWT.error(SWT.java:2522)\n        at org.eclipse.swt.dnd.DND.error(DND.java:230)\n        at org.eclipse.swt.dnd.DND.error(DND.java:181)\n        at org.eclipse.swt.dnd.Clipboard.checkWidget(Clipboard.java:129)\n        at org.eclipse.swt.dnd.Clipboard.getAvailableTypes(Clipboard.java:409)\n        at org.eclipse.ui.views.navigator.PasteAction.updateSelection(PasteActio\nn.java:220)\n        at org.eclipse.ui.actions.BaseSelectionListenerAction.selectionChanged(B\naseSelectionListenerAction.java:102)\n        at org.eclipse.ui.views.navigator.RefactorActionGroup.updateActionBars(R\nefactorActionGroup.java:139)\n        at org.eclipse.ui.views.navigator.MainActionGroup.handleResourceChanged(\nMainActionGroup.java:109)\n        at org.eclipse.ui.views.navigator.MainActionGroup$1.resourceChanged(Main\nActionGroup.java:76)\n        at org.eclipse.core.internal.events.NotificationManager$2.run(Notificati\nonManager.java:251)\n        at org.eclipse.core.internal.runtime.InternalPlatform.run(InternalPlatfo\nrm.java)\n        at org.eclipse.core.runtime.Platform.run(Platform.java)\n        at org.eclipse.core.internal.events.NotificationManager.notify(Notificat\nionManager.java:244)\n        at org.eclipse.core.internal.events.NotificationManager.broadcastChanges\n(NotificationManager.java:138)\n        at org.eclipse.core.internal.resources.Workspace.broadcastChanges(Worksp\nace.java:146)\n        at org.eclipse.core.internal.resources.Workspace.endOperation(Workspace.\njava)\n        at org.eclipse.core.internal.resources.Workspace.run(Workspace.java:1563\n)\n        at org.eclipse.ui.actions.WorkspaceModifyOperation.run(WorkspaceModifyOp\neration.java:105)\n        at org.eclipse.jface.operation.ModalContext$ModalContextThread.run(Modal\nContext.java:101)",
    "\n\n*** This bug has been marked as a duplicate of 42176 ***"
  ],
  "commentCreationDates": [
    "2003-11-21T18:53:20+01:00",
    "2003-11-21T19:05:20+01:00"
  ],
  "traces": [
    {
      "exceptionType": "org.eclipse.swt.SWTException",
      "message": "Invalid thread access",
      "elements": [
        {
          "method": "java.lang.Throwable.\u003cinit\u003e",
          "source": "Throwable.java"
        },
        {
          "method": "java.lang.Throwable.\u003cinit\u003e",
          "source": "Throwable.java"
        },
        {
          "method": "org.eclipse.swt.SWTException.\u003cinit\u003e",
          "source": "SWTException.java:73"
        },
        {
          "method": "org.eclipse.swt.SWTException.\u003cinit\u003e",
          "source": "SWTException.java:62"
        },
        {
          "method": "org.eclipse.swt.SWT.error",
          "source": "SWT.java:2592"
        },
        {
          "method": "org.eclipse.swt.SWT.error",
          "source": "SWT.java:2522"
        },
        {
          "method": "org.eclipse.swt.dnd.DND.error",
          "source": "DND.java:230"
        },
        {
          "method": "org.eclipse.swt.dnd.DND.error",
          "source": "DND.java:181"
        },
        {
          "method": "org.eclipse.swt.dnd.Clipboard.checkWidget",
          "source": "Clipboard.java:129"
        },
        {
          "method": "org.eclipse.swt.dnd.Clipboard.getAvailableTypes",
          "source": "Clipboard.java:409"
        },
        {
          "method": "org.eclipse.ui.views.navigator.PasteAction.updateSelection",
          "source": "PasteActio n.java:220"
        },
        {
          "method": "org.eclipse.ui.actions.BaseSelectionListenerAction.selectionChanged",
          "source": "B aseSelectionListenerAction.java:102"
        },
        {
          "method": "org.eclipse.ui.views.navigator.RefactorActionGroup.updateActionBars",
          "source": "R efactorActionGroup.java:139"
        },
        {
          "method": "org.eclipse.ui.views.navigator.MainActionGroup.handleResourceChanged",
          "source": " MainActionGroup.java:109"
        },
        {
          "method": "org.eclipse.ui.views.navigator.MainActionGroup$1.resourceChanged",
          "source": "Main ActionGroup.java:76"
        },
        {
          "method": "org.eclipse.core.internal.events.NotificationManager$2.run",
          "source": "Notificati onManager.java:251"
        },
        {
          "method": "org.eclipse.core.internal.runtime.InternalPlatform.run",
          "source": "InternalPlatfo rm.java"
        },
        {
          "method": "org.eclipse.core.runtime.Platform.run",
          "source": "Platform.java"
        },
        {
          "method": "org.eclipse.core.internal.events.NotificationManager.notify",
          "source": "Notificat ionManager.java:244"
        },
        {
          "method": "org.eclipse.core.internal.events.NotificationManager.broadcastChanges",
          "source": "NotificationManager.java:138"
        },
        {
          "method": "org.eclipse.core.internal.resources.Workspace.broadcastChanges",
          "source": "Worksp ace.java:146"
        },
        {
          "method": "org.eclipse.core.internal.resources.Workspace.endOperation",
          "source": "Workspace. java"
        },
        {
          "method": "org.eclipse.core.internal.resources.Workspace.run",
          "source": "Workspace.java:1563 "
        },
        {
          "method": "org.eclipse.ui.actions.WorkspaceModifyOperation.run",
          "source": "WorkspaceModifyOp eration.java:105"
        },
        {
          "method": "org.eclipse.jface.operation.ModalContext$ModalContextThread.run",
          "source": "Modal Context.java:101"
        }
      ],
      "number": 0,
      "commentIndex": 0,
      "bugId": "47261",
      "duplicateId": "42176",
      "date": "2003-11-21T18:53:20+01:00",
      "product": "Platform",
      "component": "UI",
      "severity": "normal"
    }
  ],
  "groupId": "42176",
  "bugId": "47261",
  "duplicateId": "42176",
  "date": "2003-11-21T18:53:20+01:00",
  "product": "Platform",
  "component": "UI",
  "severity": "normal"
}