{
  "comments": [
    "Choosing the Source-\u003eGenerate Getter/Setter action seems to be broken.  I tried \nexplicitly choosing the class in the outline view, but it doesn\u0027t seem to help.\n\nTried in several different classes, and tried a restart of the workbench, but \nstill the same effect.\n\nMajor PITA.  \n\nStack trace follows:\n\n!ENTRY org.eclipse.ui 4 0 Nov 25, 2003 11:28:01.568\n!MESSAGE null argument;\n!STACK 0\norg.eclipse.jface.util.Assert$AssertionFailedException: null argument;\n        at org.eclipse.jface.util.Assert.isNotNull(Assert.java:139)\n        at org.eclipse.jface.util.Assert.isNotNull(Assert.java:116)\n        at org.eclipse.jface.viewers.AbstractTreeViewer.\nreveal(AbstractTreeViewer.java:1233)\n        at org.eclipse.jdt.ui.actions.\nAddGetterSetterAction$GetterSetterTreeSelectionDialog.\ncreateDialogArea(AddGetterSetterAction.java:972)\n        at org.eclipse.jface.dialogs.Dialog.createContents(Dialog.java:573)\n        at org.eclipse.jface.window.Window.create(Window.java:305)\n        at org.eclipse.jface.dialogs.Dialog.create(Dialog.java:883)\n        at org.eclipse.ui.dialogs.SelectionStatusDialog.\ncreate(SelectionStatusDialog.java:143)\n        at org.eclipse.ui.dialogs.CheckedTreeSelectionDialog.\naccess$superCreate(CheckedTreeSelectionDialog.java:215)\n        at org.eclipse.ui.dialogs.CheckedTreeSelectionDialog.\naccess$0(CheckedTreeSelectionDialog.java:214)\n        at org.eclipse.ui.dialogs.CheckedTreeSelectionDialog$1.\nrun(CheckedTreeSelectionDialog.java:240)\n        at org.eclipse.swt.custom.BusyIndicator.showWhile(BusyIndicator.java:84)\n        at org.eclipse.ui.dialogs.CheckedTreeSelectionDialog.\ncreate(CheckedTreeSelectionDialog.java:238)\n        at org.eclipse.jface.window.Window.open(Window.java:555)\n        at org.eclipse.ui.dialogs.CheckedTreeSelectionDialog.\nopen(CheckedTreeSelectionDialog.java:209)\n        at org.eclipse.jdt.ui.actions.AddGetterSetterAction.\nrun(AddGetterSetterAction.java:255)\n        at org.eclipse.jdt.ui.actions.AddGetterSetterAction.\nrun(AddGetterSetterAction.java:505)\n        at org.eclipse.jdt.ui.actions.SelectionDispatchAction.\ndispatchRun(SelectionDispatchAction.java:196)\n        at org.eclipse.jdt.ui.actions.SelectionDispatchAction.\nrun(SelectionDispatchAction.java:172)\n        at org.eclipse.jface.action.Action.runWithEvent(Action.java:842)\n        at org.eclipse.jface.action.ActionContributionItem.\nhandleWidgetSelection(ActionContributionItem.java:542)\n        at org.eclipse.jface.action.ActionContributionItem.\naccess$4(ActionContributionItem.java:494)\n        at org.eclipse.jface.action.ActionContributionItem$6.\nhandleEvent(ActionContributionItem.java:466)\n        at org.eclipse.swt.widgets.EventTable.sendEvent(EventTable.java:82)\n        at org.eclipse.swt.widgets.Widget.sendEvent(Widget.java:967)\n        at org.eclipse.swt.widgets.Display.runDeferredEvents(Display.java:1839)\n        at org.eclipse.swt.widgets.Display.readAndDispatch(Display.java:1619)\n        at org.eclipse.ui.internal.Workbench.runEventLoop(Workbench.java:1405)\n        at org.eclipse.ui.internal.Workbench.runUI(Workbench.java:1381)\n        at org.eclipse.ui.internal.Workbench.createAndRunWorkbench(Workbench.\njava:237)\n        at org.eclipse.ui.PlatformUI.createAndRunWorkbench(PlatformUI.java:139)\n        at org.eclipse.ui.internal.ide.IDEApplication.run(IDEApplication.java:\n47)\n        at org.eclipse.core.internal.boot.InternalBootLoader.\nrun(InternalBootLoader.java:858)\n        at org.eclipse.core.boot.BootLoader.run(BootLoader.java:461)\n        at sun.reflect.NativeMethodAccessorImpl.invoke0(Native Method)\n        at sun.reflect.NativeMethodAccessorImpl.invoke(NativeMethodAccessorImpl.\njava:39)\n        at sun.reflect.DelegatingMethodAccessorImpl.\ninvoke(DelegatingMethodAccessorImpl.java:25)\n        at java.lang.reflect.Method.invoke(Method.java:324)\n        at org.eclipse.core.launcher.Main.basicRun(Main.java:299)\n        at org.eclipse.core.launcher.Main.run(Main.java:767)\n        at org.eclipse.core.launcher.Main.main(Main.java:601)",
    "fixed \u003e 20031114\n\nAs workaround select a field, not a type, when activating \u0027Generate \nGetter/Setter)",
    "Thanks Martin for the workaround, I didn\u0027t try that one..works a treat.",
    "*** Bug 47330 has been marked as a duplicate of this bug. ***",
    "*** Bug 47489 has been marked as a duplicate of this bug. ***",
    "*** Bug 48065 has been marked as a duplicate of this bug. ***",
    "Will there be a maintainance update for 3.0M5? Would be nice, because this is a\nmajor feature that is broken and I am not like using a nightly build... Thanks!",
    "no, we don\u0027t do maintnance builds for milestone builds. But I can recommend you \nto use I20031203 which works nice for me.",
    "*** Bug 48303 has been marked as a duplicate of this bug. ***",
    "start verify",
    "verified using I200312162000"
  ],
  "commentCreationDates": [
    "2003-11-25T00:36:52+01:00",
    "2003-11-25T11:45:24+01:00",
    "2003-11-26T01:58:55+01:00",
    "2003-11-26T16:11:45+01:00",
    "2003-11-26T16:12:00+01:00",
    "2003-12-04T17:55:15+01:00",
    "2003-12-08T09:59:35+01:00",
    "2003-12-08T10:02:03+01:00",
    "2003-12-09T16:08:39+01:00",
    "2003-12-17T12:54:17+01:00",
    "2003-12-17T15:29:20+01:00"
  ],
  "traces": [
    {
      "exceptionType": "org.eclipse.jface.util.Assert$AssertionFailedException",
      "message": "null argument;",
      "elements": [
        {
          "method": "org.eclipse.jface.util.Assert.isNotNull",
          "source": "Assert.java:139"
        },
        {
          "method": "org.eclipse.jface.util.Assert.isNotNull",
          "source": "Assert.java:116"
        },
        {
          "method": "org.eclipse.jface.viewers.AbstractTreeViewer.reveal",
          "source": "AbstractTreeViewer.java:1233"
        },
        {
          "method": "org.eclipse.jdt.ui.actions.AddGetterSetterAction$GetterSetterTreeSelectionDialog.createDialogArea",
          "source": "AddGetterSetterAction.java:972"
        },
        {
          "method": "org.eclipse.jface.dialogs.Dialog.createContents",
          "source": "Dialog.java:573"
        },
        {
          "method": "org.eclipse.jface.window.Window.create",
          "source": "Window.java:305"
        },
        {
          "method": "org.eclipse.jface.dialogs.Dialog.create",
          "source": "Dialog.java:883"
        },
        {
          "method": "org.eclipse.ui.dialogs.SelectionStatusDialog.create",
          "source": "SelectionStatusDialog.java:143"
        },
        {
          "method": "org.eclipse.ui.dialogs.CheckedTreeSelectionDialog.access$superCreate",
          "source": "CheckedTreeSelectionDialog.java:215"
        },
        {
          "method": "org.eclipse.ui.dialogs.CheckedTreeSelectionDialog.access$0",
          "source": "CheckedTreeSelectionDialog.java:214"
        },
        {
          "method": "org.eclipse.ui.dialogs.CheckedTreeSelectionDialog$1.run",
          "source": "CheckedTreeSelectionDialog.java:240"
        },
        {
          "method": "org.eclipse.swt.custom.BusyIndicator.showWhile",
          "source": "BusyIndicator.java:84"
        },
        {
          "method": "org.eclipse.ui.dialogs.CheckedTreeSelectionDialog.create",
          "source": "CheckedTreeSelectionDialog.java:238"
        },
        {
          "method": "org.eclipse.jface.window.Window.open",
          "source": "Window.java:555"
        },
        {
          "method": "org.eclipse.ui.dialogs.CheckedTreeSelectionDialog.open",
          "source": "CheckedTreeSelectionDialog.java:209"
        },
        {
          "method": "org.eclipse.jdt.ui.actions.AddGetterSetterAction.run",
          "source": "AddGetterSetterAction.java:255"
        },
        {
          "method": "org.eclipse.jdt.ui.actions.AddGetterSetterAction.run",
          "source": "AddGetterSetterAction.java:505"
        },
        {
          "method": "org.eclipse.jdt.ui.actions.SelectionDispatchAction.dispatchRun",
          "source": "SelectionDispatchAction.java:196"
        },
        {
          "method": "org.eclipse.jdt.ui.actions.SelectionDispatchAction.run",
          "source": "SelectionDispatchAction.java:172"
        },
        {
          "method": "org.eclipse.jface.action.Action.runWithEvent",
          "source": "Action.java:842"
        },
        {
          "method": "org.eclipse.jface.action.ActionContributionItem.handleWidgetSelection",
          "source": "ActionContributionItem.java:542"
        },
        {
          "method": "org.eclipse.jface.action.ActionContributionItem.access$4",
          "source": "ActionContributionItem.java:494"
        },
        {
          "method": "org.eclipse.jface.action.ActionContributionItem$6.handleEvent",
          "source": "ActionContributionItem.java:466"
        },
        {
          "method": "org.eclipse.swt.widgets.EventTable.sendEvent",
          "source": "EventTable.java:82"
        },
        {
          "method": "org.eclipse.swt.widgets.Widget.sendEvent",
          "source": "Widget.java:967"
        },
        {
          "method": "org.eclipse.swt.widgets.Display.runDeferredEvents",
          "source": "Display.java:1839"
        },
        {
          "method": "org.eclipse.swt.widgets.Display.readAndDispatch",
          "source": "Display.java:1619"
        },
        {
          "method": "org.eclipse.ui.internal.Workbench.runEventLoop",
          "source": "Workbench.java:1405"
        },
        {
          "method": "org.eclipse.ui.internal.Workbench.runUI",
          "source": "Workbench.java:1381"
        },
        {
          "method": "org.eclipse.ui.internal.Workbench.createAndRunWorkbench",
          "source": "Workbench. java:237"
        },
        {
          "method": "org.eclipse.ui.PlatformUI.createAndRunWorkbench",
          "source": "PlatformUI.java:139"
        },
        {
          "method": "org.eclipse.ui.internal.ide.IDEApplication.run",
          "source": "IDEApplication.java: 47"
        },
        {
          "method": "org.eclipse.core.internal.boot.InternalBootLoader.run",
          "source": "InternalBootLoader.java:858"
        },
        {
          "method": "org.eclipse.core.boot.BootLoader.run",
          "source": "BootLoader.java:461"
        },
        {
          "method": "sun.reflect.NativeMethodAccessorImpl.invoke0",
          "source": "Native Method"
        },
        {
          "method": "sun.reflect.NativeMethodAccessorImpl.invoke",
          "source": "NativeMethodAccessorImpl. java:39"
        },
        {
          "method": "sun.reflect.DelegatingMethodAccessorImpl.invoke",
          "source": "DelegatingMethodAccessorImpl.java:25"
        },
        {
          "method": "java.lang.reflect.Method.invoke",
          "source": "Method.java:324"
        },
        {
          "method": "org.eclipse.core.launcher.Main.basicRun",
          "source": "Main.java:299"
        },
        {
          "method": "org.eclipse.core.launcher.Main.run",
          "source": "Main.java:767"
        },
        {
          "method": "org.eclipse.core.launcher.Main.main",
          "source": "Main.java:601"
        }
      ],
      "number": 0,
      "commentIndex": 0,
      "bugId": "47378",
      "date": "2003-11-25T00:36:52+01:00",
      "product": "JDT",
      "component": "UI",
      "severity": "critical"
    }
  ],
  "groupId": "47378",
  "bugId": "47378",
  "date": "2003-11-25T00:36:52+01:00",
  "product": "JDT",
  "component": "UI",
  "severity": "critical"
}