{
  "comments": [
    "Build 20031121\n\nGot the following error while importing plugin projects:\n!ENTRY org.eclipse.pde.ui 4 0 Nov 25, 2003 11:28:36.925\n!MESSAGE Problems detected while importing plug-ins\n!SUBENTRY 1 org.eclipse.core.resources 4 272 Nov 25, 2003 11:28:36.925\n!MESSAGE Indexed store transactions did not commit properly: \nd:\\eclipse\\workspace\\plugins\\.metadata\\.plugins\\org.eclipse.core.resources\\.proj\nects\\org.eclipse.jdt.ui\\.properties.\n!STACK 0\nIndexedStoreException:Error committing the indexed store.\norg.eclipse.core.internal.indexing.ObjectStoreException: Object is too large \nfor page.\n        at org.eclipse.core.internal.indexing.IndexedStore.commit\n(IndexedStore.java:139)\n        at org.eclipse.core.internal.properties.IndexedStoreWrapper.commit\n(IndexedStoreWrapper.java:86)\n        at org.eclipse.core.internal.properties.PropertyStore.commit\n(PropertyStore.java:449)\n        at org.eclipse.core.internal.properties.PropertyManager.setProperty\n(PropertyManager.java:173)\n        at org.eclipse.core.internal.resources.Resource.setPersistentProperty\n(Resource.java:1213)\n        at \norg.eclipse.pde.internal.ui.wizards.imports.PluginImportOperation.createProject\n(PluginImportOperation.java:217)\n        at org.eclipse.pde.internal.ui.wizards.imports.PluginImportOperation.run\n(PluginImportOperation.java:109)\n        at org.eclipse.core.internal.resources.Workspace.run\n(Workspace.java:1554)\n        at org.eclipse.core.internal.resources.Workspace.run\n(Workspace.java:1573)\n        at org.eclipse.pde.internal.ui.wizards.imports.PluginImportWizard$2.run\n(PluginImportWizard.java:118)\n        at org.eclipse.jface.operation.ModalContext$ModalContextThread.run\n(ModalContext.java:101)\norg.eclipse.core.internal.indexing.ObjectStoreException: Object is too large \nfor page.\n        at org.eclipse.core.internal.indexing.ObjectPage.insertObject\n(ObjectPage.java:110)\n        at org.eclipse.core.internal.indexing.ObjectStore.commit\n(ObjectStore.java:172)\n        at org.eclipse.core.internal.indexing.IndexedStore.commit\n(IndexedStore.java:137)\n        at org.eclipse.core.internal.properties.IndexedStoreWrapper.commit\n(IndexedStoreWrapper.java:86)\n        at org.eclipse.core.internal.properties.PropertyStore.commit\n(PropertyStore.java:449)\n        at org.eclipse.core.internal.properties.PropertyManager.setProperty\n(PropertyManager.java:173)\n        at org.eclipse.core.internal.resources.Resource.setPersistentProperty\n(Resource.java:1213)\n        at \norg.eclipse.pde.internal.ui.wizards.imports.PluginImportOperation.createProject\n(PluginImportOperation.java:217)\n        at org.eclipse.pde.internal.ui.wizards.imports.PluginImportOperation.run\n(PluginImportOperation.java:109)\n        at org.eclipse.core.internal.resources.Workspace.run\n(Workspace.java:1554)\n        at org.eclipse.core.internal.resources.Workspace.run\n(Workspace.java:1573)\n        at org.eclipse.pde.internal.ui.wizards.imports.PluginImportWizard$2.run\n(PluginImportWizard.java:118)\n        at org.eclipse.jface.operation.ModalContext$ModalContextThread.run\n(ModalContext.java:101)",
    "\n\n*** This bug has been marked as a duplicate of 78099 ***"
  ],
  "commentCreationDates": [
    "2003-11-25T10:33:27+01:00",
    "2004-11-08T20:18:13+01:00"
  ],
  "traces": [
    {
      "exceptionType": "org.eclipse.core.internal.indexing.ObjectStoreException",
      "message": "Object is too large  for page.",
      "elements": [
        {
          "method": "org.eclipse.core.internal.indexing.IndexedStore.commit",
          "source": "IndexedStore.java:139"
        },
        {
          "method": "org.eclipse.core.internal.properties.IndexedStoreWrapper.commit",
          "source": "IndexedStoreWrapper.java:86"
        },
        {
          "method": "org.eclipse.core.internal.properties.PropertyStore.commit",
          "source": "PropertyStore.java:449"
        },
        {
          "method": "org.eclipse.core.internal.properties.PropertyManager.setProperty",
          "source": "PropertyManager.java:173"
        },
        {
          "method": "org.eclipse.core.internal.resources.Resource.setPersistentProperty",
          "source": "Resource.java:1213"
        },
        {
          "method": "org.eclipse.pde.internal.ui.wizards.imports.PluginImportOperation.createProject",
          "source": "PluginImportOperation.java:217"
        },
        {
          "method": "org.eclipse.pde.internal.ui.wizards.imports.PluginImportOperation.run",
          "source": "PluginImportOperation.java:109"
        },
        {
          "method": "org.eclipse.core.internal.resources.Workspace.run",
          "source": "Workspace.java:1554"
        },
        {
          "method": "org.eclipse.core.internal.resources.Workspace.run",
          "source": "Workspace.java:1573"
        },
        {
          "method": "org.eclipse.pde.internal.ui.wizards.imports.PluginImportWizard$2.run",
          "source": "PluginImportWizard.java:118"
        },
        {
          "method": "org.eclipse.jface.operation.ModalContext$ModalContextThread.run",
          "source": "ModalContext.java:101"
        }
      ],
      "number": 0,
      "commentIndex": 0,
      "bugId": "47399",
      "duplicateId": "78099",
      "date": "2003-11-25T10:33:27+01:00",
      "product": "Platform",
      "component": "Resources",
      "severity": "normal"
    },
    {
      "exceptionType": "org.eclipse.core.internal.indexing.ObjectStoreException",
      "message": "Object is too large  for page.",
      "elements": [
        {
          "method": "org.eclipse.core.internal.indexing.ObjectPage.insertObject",
          "source": "ObjectPage.java:110"
        },
        {
          "method": "org.eclipse.core.internal.indexing.ObjectStore.commit",
          "source": "ObjectStore.java:172"
        },
        {
          "method": "org.eclipse.core.internal.indexing.IndexedStore.commit",
          "source": "IndexedStore.java:137"
        },
        {
          "method": "org.eclipse.core.internal.properties.IndexedStoreWrapper.commit",
          "source": "IndexedStoreWrapper.java:86"
        },
        {
          "method": "org.eclipse.core.internal.properties.PropertyStore.commit",
          "source": "PropertyStore.java:449"
        },
        {
          "method": "org.eclipse.core.internal.properties.PropertyManager.setProperty",
          "source": "PropertyManager.java:173"
        },
        {
          "method": "org.eclipse.core.internal.resources.Resource.setPersistentProperty",
          "source": "Resource.java:1213"
        },
        {
          "method": "org.eclipse.pde.internal.ui.wizards.imports.PluginImportOperation.createProject",
          "source": "PluginImportOperation.java:217"
        },
        {
          "method": "org.eclipse.pde.internal.ui.wizards.imports.PluginImportOperation.run",
          "source": "PluginImportOperation.java:109"
        },
        {
          "method": "org.eclipse.core.internal.resources.Workspace.run",
          "source": "Workspace.java:1554"
        },
        {
          "method": "org.eclipse.core.internal.resources.Workspace.run",
          "source": "Workspace.java:1573"
        },
        {
          "method": "org.eclipse.pde.internal.ui.wizards.imports.PluginImportWizard$2.run",
          "source": "PluginImportWizard.java:118"
        },
        {
          "method": "org.eclipse.jface.operation.ModalContext$ModalContextThread.run",
          "source": "ModalContext.java:101"
        }
      ],
      "number": 1,
      "commentIndex": 0,
      "bugId": "47399",
      "duplicateId": "78099",
      "date": "2003-11-25T10:33:27+01:00",
      "product": "Platform",
      "component": "Resources",
      "severity": "normal"
    }
  ],
  "groupId": "78099",
  "bugId": "47399",
  "duplicateId": "78099",
  "date": "2003-11-25T10:33:27+01:00",
  "product": "Platform",
  "component": "Resources",
  "severity": "normal"
}