{
  "comments": [
    "Using M5, I got this stack trace debugging some code. I could not reproduce it.\nMight be a timing issue.\n\njava.util.ConcurrentModificationException\n        at java.util.AbstractList$Itr.checkForComodification(AbstractList.java:444)\n        at java.util.AbstractList$Itr.next(AbstractList.java:421)\n        at\norg.eclipse.jdt.internal.debug.core.hcr.JavaHotCodeReplaceManager.doHotCodeReplace(JavaHotCodeReplaceManager.java:362)\n        at\norg.eclipse.jdt.internal.debug.core.hcr.JavaHotCodeReplaceManager.access$0(JavaHotCodeReplaceManager.java:358)\n        at\norg.eclipse.jdt.internal.debug.core.hcr.JavaHotCodeReplaceManager$1.run(JavaHotCodeReplaceManager.java:287)\n        at org.eclipse.core.internal.resources.Workspace.run(Workspace.java:1554)\n        at org.eclipse.core.internal.resources.Workspace.run(Workspace.java:1573)\n        at\norg.eclipse.jdt.internal.debug.core.hcr.JavaHotCodeReplaceManager$3.run(JavaHotCodeReplaceManager.java:1105)\n        at java.lang.Thread.run(Thread.java:536)",
    "\n\n*** This bug has been marked as a duplicate of 45068 ***"
  ],
  "commentCreationDates": [
    "2003-11-25T16:05:51+01:00",
    "2003-11-25T16:09:43+01:00"
  ],
  "traces": [
    {
      "exceptionType": "java.util.ConcurrentModificationException",
      "elements": [
        {
          "method": "java.util.AbstractList$Itr.checkForComodification",
          "source": "AbstractList.java:444"
        },
        {
          "method": "java.util.AbstractList$Itr.next",
          "source": "AbstractList.java:421"
        },
        {
          "method": "org.eclipse.jdt.internal.debug.core.hcr.JavaHotCodeReplaceManager.doHotCodeReplace",
          "source": "JavaHotCodeReplaceManager.java:362"
        },
        {
          "method": "org.eclipse.jdt.internal.debug.core.hcr.JavaHotCodeReplaceManager.access$0",
          "source": "JavaHotCodeReplaceManager.java:358"
        },
        {
          "method": "org.eclipse.jdt.internal.debug.core.hcr.JavaHotCodeReplaceManager$1.run",
          "source": "JavaHotCodeReplaceManager.java:287"
        },
        {
          "method": "org.eclipse.core.internal.resources.Workspace.run",
          "source": "Workspace.java:1554"
        },
        {
          "method": "org.eclipse.core.internal.resources.Workspace.run",
          "source": "Workspace.java:1573"
        },
        {
          "method": "org.eclipse.jdt.internal.debug.core.hcr.JavaHotCodeReplaceManager$3.run",
          "source": "JavaHotCodeReplaceManager.java:1105"
        },
        {
          "method": "java.lang.Thread.run",
          "source": "Thread.java:536"
        }
      ],
      "number": 0,
      "commentIndex": 0,
      "bugId": "47429",
      "duplicateId": "45068",
      "date": "2003-11-25T16:05:51+01:00",
      "product": "JDT",
      "component": "Debug",
      "severity": "normal"
    }
  ],
  "groupId": "45068",
  "bugId": "47429",
  "duplicateId": "45068",
  "date": "2003-11-25T16:05:51+01:00",
  "product": "JDT",
  "component": "Debug",
  "severity": "normal"
}