{
  "comments": [
    "If you try to build a Make Target AND you have auto-save-before-build turned on\nAND you have unsaved changes, you get:\n\n    Target Build Error\n\n    Error Building Target\n\n    Reason:\n     Internal Error\n\nThe log shows:\n\n!ENTRY org.eclipse.cdt.make.ui 4 0 Nov 25, 2003 15:44:18.359\n!MESSAGE Invalid thread access\n!STACK 0\norg.eclipse.swt.SWTException: Invalid thread access\n    at org.eclipse.swt.SWT.error(SWT.java:2330)\n    at org.eclipse.swt.SWT.error(SWT.java:2260)\n    at org.eclipse.swt.widgets.Widget.error(Widget.java:385)\n    at org.eclipse.swt.widgets.Widget.checkWidget(Widget.java:315)\n    at org.eclipse.swt.widgets.Control.isEnabled(Control.java:1108)\n    at org.eclipse.ui.internal.WorkbenchWindow.run(WorkbenchWindow.java:1381)\n    at\norg.eclipse.ui.internal.EditorManager.runProgressMonitorOperation(EditorManager.java:966)\n    at org.eclipse.ui.internal.EditorManager.savePart(EditorManager.java:1095)\n    at org.eclipse.ui.internal.WorkbenchPage.savePart(WorkbenchPage.java:2353)\n    at org.eclipse.ui.internal.WorkbenchPage.saveEditor(WorkbenchPage.java:2365)\n    at org.eclipse.cdt.make.ui.TargetBuild.saveAllResources(TargetBuild.java:63)\n    at org.eclipse.cdt.make.ui.TargetBuild$2.run(TargetBuild.java:88)\n    at org.eclipse.core.internal.resources.Workspace.run(Workspace.java:1595)\n    at org.eclipse.cdt.make.ui.TargetBuild$1.run(TargetBuild.java:95)\n    at\norg.eclipse.jface.operation.ModalContext$ModalContextThread.run(ModalContext.java:101)",
    "fixed int cdt_1_2 and HEAD"
  ],
  "commentCreationDates": [
    "2003-11-26T23:40:14+01:00",
    "2003-11-28T21:43:10+01:00"
  ],
  "traces": [
    {
      "exceptionType": "org.eclipse.swt.SWTException",
      "message": "Invalid thread access",
      "elements": [
        {
          "method": "org.eclipse.swt.SWT.error",
          "source": "SWT.java:2330"
        },
        {
          "method": "org.eclipse.swt.SWT.error",
          "source": "SWT.java:2260"
        },
        {
          "method": "org.eclipse.swt.widgets.Widget.error",
          "source": "Widget.java:385"
        },
        {
          "method": "org.eclipse.swt.widgets.Widget.checkWidget",
          "source": "Widget.java:315"
        },
        {
          "method": "org.eclipse.swt.widgets.Control.isEnabled",
          "source": "Control.java:1108"
        },
        {
          "method": "org.eclipse.ui.internal.WorkbenchWindow.run",
          "source": "WorkbenchWindow.java:1381"
        },
        {
          "method": "org.eclipse.ui.internal.EditorManager.runProgressMonitorOperation",
          "source": "EditorManager.java:966"
        },
        {
          "method": "org.eclipse.ui.internal.EditorManager.savePart",
          "source": "EditorManager.java:1095"
        },
        {
          "method": "org.eclipse.ui.internal.WorkbenchPage.savePart",
          "source": "WorkbenchPage.java:2353"
        },
        {
          "method": "org.eclipse.ui.internal.WorkbenchPage.saveEditor",
          "source": "WorkbenchPage.java:2365"
        },
        {
          "method": "org.eclipse.cdt.make.ui.TargetBuild.saveAllResources",
          "source": "TargetBuild.java:63"
        },
        {
          "method": "org.eclipse.cdt.make.ui.TargetBuild$2.run",
          "source": "TargetBuild.java:88"
        },
        {
          "method": "org.eclipse.core.internal.resources.Workspace.run",
          "source": "Workspace.java:1595"
        },
        {
          "method": "org.eclipse.cdt.make.ui.TargetBuild$1.run",
          "source": "TargetBuild.java:95"
        },
        {
          "method": "org.eclipse.jface.operation.ModalContext$ModalContextThread.run",
          "source": "ModalContext.java:101"
        }
      ],
      "number": 0,
      "commentIndex": 0,
      "bugId": "47598",
      "date": "2003-11-26T23:40:14+01:00",
      "product": "CDT",
      "component": "cdt-core",
      "severity": "normal"
    }
  ],
  "groupId": "47598",
  "bugId": "47598",
  "date": "2003-11-26T23:40:14+01:00",
  "product": "CDT",
  "component": "cdt-core",
  "severity": "normal"
}