{
  "comments": [
    "SunOS cyclone 5.8 Generic_108528-19 sun4u sparc SUNW,Ultra-5_10\nJRE 1.4.2_01\nEclipse 3.0 M5 build 200311211210\n\nProblem\n-------\nTwo exceptions occurred when running a default feature project.\n\nProcedure\n---------\n1. Select File-\u003eNew-\u003eProject from the workbench menu bar.\n\n2. From the \u0027New Project\u0027 wizard, select \u0027Plug-in Development\u0027 adn \u0027Feature \nProject\u0027 sub option.\n\n3. Set the name of the feature to \"Sample Feature\" and press Next.\n\n4. Set the feature id to \"com.example.feature\", feature version to \"1.2.2\". \nFeature provider to \"Example\". Click Finish.\n\n5. Select any \u0027plugin\u0027 or \u0027plug-in fragment\u0027 projects defined in the current \nworkspace from the list of projects in the \u0027New Feature Project\u0027 wizard. (if \nthere are any)\n\n6. Click Finish in the New Feature Project wizard.\n\n7. Select Upate URLs and select New-\u003eUpdate URL from its context menu.\n\n8. In the properties view change the label of the update URL to Our Update Site \nand URL to htpp:\\\\www.eclipse.org\n\n9. Click on the Sample Feature feature.xml.\n\n10. Select the \"feature.xml\" item in the Sample Feature project in the pachage \nexplorer, and from its context menu select \"Create Ant Build File\" under the \nPDE Tools sub-menu.\n\n11. Select \"Run ANT\" from the context menu of the Sample Feature build.xml file \nin the Pachage Explorer view...an click \"Run\" in the displayed window.\n\n\nExpected Results\n----------------\n\nThe Run completes with no exceptions.\n\nObserved Results\n----------------\n\nRun completed but 2 exceptions were generated. See below.\n\nNote(s)\n----\nThe problem is reproducible.\n\n\nNote...this message occurs after execution of step 10 described above.\n!SESSION Nov 28, 2003 13:07:34.637 ---------------------------------------------\njava.version\u003d1.4.2_01\njava.vendor\u003dSun Microsystems Inc.\nBootLoader constants: OS\u003dsolaris, ARCH\u003dsparc, WS\u003dmotif, NL\u003den_CA\nCommand-line arguments: -os solaris -ws motif -arch sparc -\ndata /cyclonedsk/rational/dfigoni/myWorkSpace -install \nfile:/cyclonedsk/rational/dfigoni/eclipse/\n!ENTRY org.eclipse.core.resources 1 1 Nov 28, 2003 13:07:34.643\n!MESSAGE Could not load library: libcore_2_1_0b.so.  This library provides \nplatform-specific optimizations for certain file system operations.  This \nlibrary is not present on all platforms, so this may not be an error.  The \nresources plug-in will safely fall back to using java.io.File functionality.\n^Ccyclone:/cyclonedsk/rational/dfigoni/myWorkSpace/.metadata(9)\n\nNote...\nThe Sample Feature feature.xml dialog box (when user chooses \"Run ANT\") says..\nfile:/cyclonedsk....feature.xml:6: Config file is not of expected XML type\n\nNote...these are generated after the run is completed (step 11 above)\n!ENTRY org.eclipse.debug.ui 4 120 Nov 28, 2003 13:15:26.200\n!MESSAGE Internal message logged from Debug UI: An attempt was made to append \ntext to the console, after it was closed.\n!ENTRY org.eclipse.ui 4 4 Nov 28, 2003 13:15:26.359\n!MESSAGE Unhandled event loop exception\n!ENTRY org.eclipse.ui 4 0 Nov 28, 2003 13:15:26.364\n!MESSAGE Failed to execute runnable (java.lang.StringIndexOutOfBoundsException: \nString index out of range: -1)\n!STACK 0\norg.eclipse.swt.SWTException: Failed to execute runnable \n(java.lang.StringIndexOutOfBoundsException: String index out of range: -1)\n        at org.eclipse.swt.SWT.error(SWT.java:2592)\n        at org.eclipse.swt.widgets.Synchronizer.runAsyncMessages\n(Synchronizer.java:105)\n        at org.eclipse.swt.widgets.Display.runAsyncMessages(Display.java:2334)\n        at org.eclipse.swt.widgets.Display.readAndDispatch(Display.java:2116)\n        at org.eclipse.ui.internal.Workbench.runEventLoop(Workbench.java:1405)\n        at org.eclipse.ui.internal.Workbench.runUI(Workbench.java:1381)\n        at org.eclipse.ui.internal.Workbench.createAndRunWorkbench\n(Workbench.java:237)\n        at org.eclipse.ui.PlatformUI.createAndRunWorkbench(PlatformUI.java:139)\n        at org.eclipse.ui.internal.ide.IDEApplication.run\n(IDEApplication.java:47)\n        at org.eclipse.core.internal.boot.InternalBootLoader.run\n(InternalBootLoader.java:858)\n        at org.eclipse.core.boot.BootLoader.run(BootLoader.java:461)\n        at sun.reflect.NativeMethodAccessorImpl.invoke0(Native Method)\n        at sun.reflect.NativeMethodAccessorImpl.invoke(Unknown Source)\n        at sun.reflect.DelegatingMethodAccessorImpl.invoke(Unknown Source)\n        at java.lang.reflect.Method.invoke(Unknown Source)\n        at org.eclipse.core.launcher.Main.basicRun(Main.java:299)\n        at org.eclipse.core.launcher.Main.run(Main.java:767)\n        at org.eclipse.core.launcher.Main.main(Main.java:601)\n!ENTRY org.eclipse.ui 4 4 Nov 28, 2003 13:15:26.372\n!MESSAGE *** SWT nested exception\n!ENTRY org.eclipse.ui 4 0 Nov 28, 2003 13:15:26.379\n!MESSAGE String index out of range: -1\n!STACK 0\njava.lang.StringIndexOutOfBoundsException: String index out of range: -1\n        at java.lang.String.substring(Unknown Source)\n        at org.eclipse.ant.internal.ui.console.BuildFailedTracker.lineAppended\n(BuildFailedTracker.java:66)\n        at \norg.eclipse.debug.internal.ui.views.console.ConsoleLineNotifier.processNewLines\n(ConsoleLineNotifier.java:133)\n        at \norg.eclipse.debug.internal.ui.views.console.ConsoleLineNotifier.consoleChanged\n(ConsoleLineNotifier.java:80)\n        at \norg.eclipse.debug.internal.ui.views.console.ConsoleDocumentPartitioner.documentC\nhanged2(ConsoleDocumentPartitioner.java:366)\n        at org.eclipse.jface.text.AbstractDocument.updateDocumentStructures\n(AbstractDocument.java:599)\n        at org.eclipse.jface.text.AbstractDocument.fireDocumentChanged\n(AbstractDocument.java:695)\n        at org.eclipse.jface.text.AbstractDocument.replace\n(AbstractDocument.java:989)\n        at \norg.eclipse.debug.internal.ui.views.console.ConsoleDocumentPartitioner$3.run\n(ConsoleDocumentPartitioner.java:697)\n        at org.eclipse.swt.widgets.RunnableLock.run(RunnableLock.java:35)\n        at org.eclipse.swt.widgets.Synchronizer.runAsyncMessages\n(Synchronizer.java:102)\n        at org.eclipse.swt.widgets.Display.runAsyncMessages(Display.java:2334)\n        at org.eclipse.swt.widgets.Display.readAndDispatch(Display.java:2116)\n        at org.eclipse.ui.internal.Workbench.runEventLoop(Workbench.java:1405)\n        at org.eclipse.ui.internal.Workbench.runUI(Workbench.java:1381)\n        at org.eclipse.ui.internal.Workbench.createAndRunWorkbench\n(Workbench.java:237)\n        at org.eclipse.ui.PlatformUI.createAndRunWorkbench(PlatformUI.java:139)\n        at org.eclipse.ui.internal.ide.IDEApplication.run\n(IDEApplication.java:47)\n        at org.eclipse.core.internal.boot.InternalBootLoader.run\n(InternalBootLoader.java:858)\n        at org.eclipse.core.boot.BootLoader.run(BootLoader.java:461)\n        at sun.reflect.NativeMethodAccessorImpl.invoke0(Native Method)\n        at sun.reflect.NativeMethodAccessorImpl.invoke(Unknown Source)\n        at sun.reflect.DelegatingMethodAccessorImpl.invoke(Unknown Source)\n        at java.lang.reflect.Method.invoke(Unknown Source)\n        at org.eclipse.core.launcher.Main.basicRun(Main.java:299)\n        at org.eclipse.core.launcher.Main.run(Main.java:767)\n        at org.eclipse.core.launcher.Main.main(Main.java:601)",
    "\n\n*** This bug has been marked as a duplicate of 44565 ***",
    "Verified during 3.0M6 (build 200312182000) testing.\nSolaris 9 JRE 1.4.2_01\nFix seems to of resolved the problem."
  ],
  "commentCreationDates": [
    "2003-11-28T18:33:42+01:00",
    "2003-12-02T18:13:21+01:00",
    "2003-12-22T20:51:09+01:00"
  ],
  "traces": [
    {
      "exceptionType": "java.lang.StringIndexOutOfBoundsException",
      "message": "String index out of range: -1)",
      "elements": [
        {
          "method": "org.eclipse.swt.SWT.error",
          "source": "SWT.java:2592"
        },
        {
          "method": "org.eclipse.swt.widgets.Synchronizer.runAsyncMessages",
          "source": "Synchronizer.java:105"
        },
        {
          "method": "org.eclipse.swt.widgets.Display.runAsyncMessages",
          "source": "Display.java:2334"
        },
        {
          "method": "org.eclipse.swt.widgets.Display.readAndDispatch",
          "source": "Display.java:2116"
        },
        {
          "method": "org.eclipse.ui.internal.Workbench.runEventLoop",
          "source": "Workbench.java:1405"
        },
        {
          "method": "org.eclipse.ui.internal.Workbench.runUI",
          "source": "Workbench.java:1381"
        },
        {
          "method": "org.eclipse.ui.internal.Workbench.createAndRunWorkbench",
          "source": "Workbench.java:237"
        },
        {
          "method": "org.eclipse.ui.PlatformUI.createAndRunWorkbench",
          "source": "PlatformUI.java:139"
        },
        {
          "method": "org.eclipse.ui.internal.ide.IDEApplication.run",
          "source": "IDEApplication.java:47"
        },
        {
          "method": "org.eclipse.core.internal.boot.InternalBootLoader.run",
          "source": "InternalBootLoader.java:858"
        },
        {
          "method": "org.eclipse.core.boot.BootLoader.run",
          "source": "BootLoader.java:461"
        },
        {
          "method": "sun.reflect.NativeMethodAccessorImpl.invoke0",
          "source": "Native Method"
        },
        {
          "method": "sun.reflect.NativeMethodAccessorImpl.invoke",
          "source": "Unknown Source"
        },
        {
          "method": "sun.reflect.DelegatingMethodAccessorImpl.invoke",
          "source": "Unknown Source"
        },
        {
          "method": "java.lang.reflect.Method.invoke",
          "source": "Unknown Source"
        },
        {
          "method": "org.eclipse.core.launcher.Main.basicRun",
          "source": "Main.java:299"
        },
        {
          "method": "org.eclipse.core.launcher.Main.run",
          "source": "Main.java:767"
        },
        {
          "method": "org.eclipse.core.launcher.Main.main",
          "source": "Main.java:601"
        }
      ],
      "number": 0,
      "commentIndex": 0,
      "bugId": "47728",
      "duplicateId": "44565",
      "date": "2003-11-28T18:33:42+01:00",
      "product": "Platform",
      "component": "Ant",
      "severity": "normal"
    },
    {
      "exceptionType": "java.lang.StringIndexOutOfBoundsException",
      "message": "String index out of range: -1",
      "elements": [
        {
          "method": "java.lang.String.substring",
          "source": "Unknown Source"
        },
        {
          "method": "org.eclipse.ant.internal.ui.console.BuildFailedTracker.lineAppended",
          "source": "BuildFailedTracker.java:66"
        },
        {
          "method": "org.eclipse.debug.internal.ui.views.console.ConsoleLineNotifier.processNewLines",
          "source": "ConsoleLineNotifier.java:133"
        },
        {
          "method": "org.eclipse.debug.internal.ui.views.console.ConsoleLineNotifier.consoleChanged",
          "source": "ConsoleLineNotifier.java:80"
        },
        {
          "method": "org.eclipse.debug.internal.ui.views.console.ConsoleDocumentPartitioner.documentChanged2",
          "source": "ConsoleDocumentPartitioner.java:366"
        },
        {
          "method": "org.eclipse.jface.text.AbstractDocument.updateDocumentStructures",
          "source": "AbstractDocument.java:599"
        },
        {
          "method": "org.eclipse.jface.text.AbstractDocument.fireDocumentChanged",
          "source": "AbstractDocument.java:695"
        },
        {
          "method": "org.eclipse.jface.text.AbstractDocument.replace",
          "source": "AbstractDocument.java:989"
        },
        {
          "method": "org.eclipse.debug.internal.ui.views.console.ConsoleDocumentPartitioner$3.run",
          "source": "ConsoleDocumentPartitioner.java:697"
        },
        {
          "method": "org.eclipse.swt.widgets.RunnableLock.run",
          "source": "RunnableLock.java:35"
        },
        {
          "method": "org.eclipse.swt.widgets.Synchronizer.runAsyncMessages",
          "source": "Synchronizer.java:102"
        },
        {
          "method": "org.eclipse.swt.widgets.Display.runAsyncMessages",
          "source": "Display.java:2334"
        },
        {
          "method": "org.eclipse.swt.widgets.Display.readAndDispatch",
          "source": "Display.java:2116"
        },
        {
          "method": "org.eclipse.ui.internal.Workbench.runEventLoop",
          "source": "Workbench.java:1405"
        },
        {
          "method": "org.eclipse.ui.internal.Workbench.runUI",
          "source": "Workbench.java:1381"
        },
        {
          "method": "org.eclipse.ui.internal.Workbench.createAndRunWorkbench",
          "source": "Workbench.java:237"
        },
        {
          "method": "org.eclipse.ui.PlatformUI.createAndRunWorkbench",
          "source": "PlatformUI.java:139"
        },
        {
          "method": "org.eclipse.ui.internal.ide.IDEApplication.run",
          "source": "IDEApplication.java:47"
        },
        {
          "method": "org.eclipse.core.internal.boot.InternalBootLoader.run",
          "source": "InternalBootLoader.java:858"
        },
        {
          "method": "org.eclipse.core.boot.BootLoader.run",
          "source": "BootLoader.java:461"
        },
        {
          "method": "sun.reflect.NativeMethodAccessorImpl.invoke0",
          "source": "Native Method"
        },
        {
          "method": "sun.reflect.NativeMethodAccessorImpl.invoke",
          "source": "Unknown Source"
        },
        {
          "method": "sun.reflect.DelegatingMethodAccessorImpl.invoke",
          "source": "Unknown Source"
        },
        {
          "method": "java.lang.reflect.Method.invoke",
          "source": "Unknown Source"
        },
        {
          "method": "org.eclipse.core.launcher.Main.basicRun",
          "source": "Main.java:299"
        },
        {
          "method": "org.eclipse.core.launcher.Main.run",
          "source": "Main.java:767"
        },
        {
          "method": "org.eclipse.core.launcher.Main.main",
          "source": "Main.java:601"
        }
      ],
      "number": 1,
      "commentIndex": 0,
      "bugId": "47728",
      "duplicateId": "44565",
      "date": "2003-11-28T18:33:42+01:00",
      "product": "Platform",
      "component": "Ant",
      "severity": "normal"
    }
  ],
  "groupId": "44565",
  "bugId": "47728",
  "duplicateId": "44565",
  "date": "2003-11-28T18:33:42+01:00",
  "product": "Platform",
  "component": "Ant",
  "severity": "normal"
}