{
  "comments": [
    "Under certain scenarios, highlighting a block of code and performing a \u0027left \nshift\u0027 on the indentation (from the Source menu) caused eclipse to crash while \nediting java source files. All changes to my source files were lost, so I \nguess this bug is critical...?\n\nHere is the relevant log entry:\n\n!SESSION Nov 29, 2003 16:52:35.43 ---------------------------------------------\n-\njava.version\u003d1.4.1_02\njava.vendor\u003dSun Microsystems Inc.\nBootLoader constants: OS\u003dwin32, ARCH\u003dx86, WS\u003dwin32, NL\u003den_CA\nCommand-line arguments: -os win32 -ws win32 -arch x86 -install file:C:/Program \nFiles/eclipse/\n!ENTRY org.eclipse.ui 4 4 Nov 29, 2003 16:52:35.43\n!MESSAGE Unhandled event loop exception\n!ENTRY org.eclipse.ui 4 0 Nov 29, 2003 16:52:35.43\n!MESSAGE java.lang.OutOfMemoryError\n!STACK 0\njava.lang.OutOfMemoryError\n!ENTRY org.eclipse.ui 4 4 Nov 29, 2003 16:52:48.663\n!MESSAGE Unhandled event loop exception\n!ENTRY org.eclipse.ui 4 0 Nov 29, 2003 16:52:48.673\n!MESSAGE Failed to execute runnable (java.lang.OutOfMemoryError)\n!STACK 0\norg.eclipse.swt.SWTException: Failed to execute runnable \n(java.lang.OutOfMemoryError)\n\tat org.eclipse.swt.SWT.error(SWT.java:2592)\n\tat org.eclipse.swt.widgets.Synchronizer.runAsyncMessages\n(Synchronizer.java:105)\n\tat org.eclipse.swt.widgets.Display.runAsyncMessages(Display.java:2164)\n\tat org.eclipse.swt.widgets.Display.readAndDispatch(Display.java:1881)\n\tat org.eclipse.jface.window.Window.runEventLoop(Window.java:586)\n\tat org.eclipse.jface.window.Window.open(Window.java:566)\n\tat org.eclipse.ui.internal.ide.dialogs.InternalErrorDialog.open\n(InternalErrorDialog.java:71)\n\tat \norg.eclipse.ui.internal.ide.dialogs.InternalErrorDialog.openQuestion\n(InternalErrorDialog.java:173)\n\tat org.eclipse.ui.internal.ide.IDEExceptionHandler.openQuestionDialog\n(IDEExceptionHandler.java:147)\n\tat org.eclipse.ui.internal.ide.IDEExceptionHandler.handleException\n(IDEExceptionHandler.java:79)\n\tat org.eclipse.ui.internal.ide.IDEWorkbenchAdvisor.eventLoopException\n(IDEWorkbenchAdvisor.java:285)\n\tat org.eclipse.ui.internal.ExceptionHandler.handleException\n(ExceptionHandler.java:53)\n\tat org.eclipse.ui.internal.Workbench.runEventLoop(Workbench.java:1409)\n\tat org.eclipse.ui.internal.Workbench.runUI(Workbench.java:1381)\n\tat org.eclipse.ui.internal.Workbench.createAndRunWorkbench\n(Workbench.java:237)\n\tat org.eclipse.ui.PlatformUI.createAndRunWorkbench\n(PlatformUI.java:139)\n\tat org.eclipse.ui.internal.ide.IDEApplication.run\n(IDEApplication.java:47)\n\tat org.eclipse.core.internal.boot.InternalBootLoader.run\n(InternalBootLoader.java:858)\n\tat org.eclipse.core.boot.BootLoader.run(BootLoader.java:461)\n\tat sun.reflect.NativeMethodAccessorImpl.invoke0(Native Method)\n\tat sun.reflect.NativeMethodAccessorImpl.invoke\n(NativeMethodAccessorImpl.java:39)\n\tat sun.reflect.DelegatingMethodAccessorImpl.invoke\n(DelegatingMethodAccessorImpl.java:25)\n\tat java.lang.reflect.Method.invoke(Method.java:324)\n\tat org.eclipse.core.launcher.Main.basicRun(Main.java:299)\n\tat org.eclipse.core.launcher.Main.run(Main.java:767)\n\tat org.eclipse.core.launcher.Main.main(Main.java:601)\n\nI am running a 1.4 GHz AMD Athlon XP with 512 MB ram under Windows XP SP1\n\nThis bug has made eclipse crash on several occasions. This bug happened in \nversion 2.1.2, so I upgraded to 3.0M5, but it still crashes intermittently in \n3.0. This bug seems to occur when changing the indentation of a large number \nof lines of code (ex: 500 or more). I haven\u0027t been able to find an exact set \nof steps to reproduce the bug, but it seemed to happen after copying and \npasting chunks of code in or out of the file whose indentation was changed.\n\nThis bug might be related to the fact that I use 2 spaces as the step for \nindentation of my java source files. As such, I am using the following \npreference settings:\n\nPreferences-\u003eJava-\u003eEditor-\u003eAppearance-\u003eDisplayed Tab Width: 2\nPreferences-\u003eJava-\u003eEditor-\u003eTyping-\u003eInsert Spaces For Tab: true\nPreferences-\u003eJava-\u003eCode Fromatter-\u003eStyle-\u003eInsert tabs for indentation, not \nspaces: false\nPreferences-\u003eJava-\u003eCode Fromatter-\u003eStyle-\u003eNumber of spaces representing an \nindentation level: 2\n\nPlease let me know if I can provide any more details.",
    "As a work around until we have a better implementation please give Eclipse \nmore memory. With sun jdk, add the VM argument \"-Xmx250M\". I assume when \nshifting left is running out of memory, there are several others which have \nthe same problem. However, we have to make sure that no work is lost.",
    "Jon, do you remember whether QuickDiff was enabled? Can you still reproduce it?\nDoes disabling QuickDiff resolve it?\n",
    "Using the settings from comment 1 an object allocation trace shows 33MB\nallocated live objects and 151MB collected (i.e., temporary) objects during\nindenting JavaEditor.java (this includes object from the reconciler). This is\nwith QuickDiff disabled.\n\nReproduced while QuickDiff was enabled. The stack trace from comment 0 can occur\nafter QuickDiff ran out of memory and the error dialog appeared (the main thread\nthen also ran out of memory and a second error dialog about an internal error\nwas shown).\n\nMarking as duplicate, please reopen if disabling QuickDiff does not solve the\nproblem.\n\n*** This bug has been marked as a duplicate of 62662 ***",
    "Christof, I haven\u0027t had this bug occur in quite sometime, but then again I \nhaven\u0027t been doing a lot of cutting-and-pasting of huge chunks of source code \nlately. I recall that I was sometimes able to reproduce the bug by repeatedly \ncutting-and-pasting or copying-and-pasting large chunks of code between files \nin the editor windows.\n\nI don\u0027t think I ever deliberately changed the quick-dif settings... I am \nfairly certain that when I observed this bug, the quick-dif settings were set \nto the defaults shipped with eclipse 3.0 M5.\n\nI think I only changed editor and code formatter settings, and perhaps a \ncouple of other things like \u0027show line numbers\u0027. I see that I never mentioned \nthat I usually turn on \u0027show line numbers\u0027. Maybe this could be a cause of the \nbug.\n\nSorry I can\u0027t be of more help.\nIf I have some spare time, I\u0027ll try and see if I can reproduce the bug on 3.0 \nRC1.\n"
  ],
  "commentCreationDates": [
    "2003-11-30T01:33:20+01:00",
    "2003-12-01T10:59:42+01:00",
    "2004-06-15T16:53:35+02:00",
    "2004-06-16T11:41:00+02:00",
    "2004-06-16T12:06:30+02:00"
  ],
  "traces": [
    {
      "exceptionType": "org.eclipse.swt.SWTException",
      "message": "Failed to execute runnable  (java.lang.OutOfMemoryError)",
      "elements": [
        {
          "method": "org.eclipse.swt.SWT.error",
          "source": "SWT.java:2592"
        },
        {
          "method": "org.eclipse.swt.widgets.Synchronizer.runAsyncMessages",
          "source": "Synchronizer.java:105"
        },
        {
          "method": "org.eclipse.swt.widgets.Display.runAsyncMessages",
          "source": "Display.java:2164"
        },
        {
          "method": "org.eclipse.swt.widgets.Display.readAndDispatch",
          "source": "Display.java:1881"
        },
        {
          "method": "org.eclipse.jface.window.Window.runEventLoop",
          "source": "Window.java:586"
        },
        {
          "method": "org.eclipse.jface.window.Window.open",
          "source": "Window.java:566"
        },
        {
          "method": "org.eclipse.ui.internal.ide.dialogs.InternalErrorDialog.open",
          "source": "InternalErrorDialog.java:71"
        },
        {
          "method": "org.eclipse.ui.internal.ide.dialogs.InternalErrorDialog.openQuestion",
          "source": "InternalErrorDialog.java:173"
        },
        {
          "method": "org.eclipse.ui.internal.ide.IDEExceptionHandler.openQuestionDialog",
          "source": "IDEExceptionHandler.java:147"
        },
        {
          "method": "org.eclipse.ui.internal.ide.IDEExceptionHandler.handleException",
          "source": "IDEExceptionHandler.java:79"
        },
        {
          "method": "org.eclipse.ui.internal.ide.IDEWorkbenchAdvisor.eventLoopException",
          "source": "IDEWorkbenchAdvisor.java:285"
        },
        {
          "method": "org.eclipse.ui.internal.ExceptionHandler.handleException",
          "source": "ExceptionHandler.java:53"
        },
        {
          "method": "org.eclipse.ui.internal.Workbench.runEventLoop",
          "source": "Workbench.java:1409"
        },
        {
          "method": "org.eclipse.ui.internal.Workbench.runUI",
          "source": "Workbench.java:1381"
        },
        {
          "method": "org.eclipse.ui.internal.Workbench.createAndRunWorkbench",
          "source": "Workbench.java:237"
        },
        {
          "method": "org.eclipse.ui.PlatformUI.createAndRunWorkbench",
          "source": "PlatformUI.java:139"
        },
        {
          "method": "org.eclipse.ui.internal.ide.IDEApplication.run",
          "source": "IDEApplication.java:47"
        },
        {
          "method": "org.eclipse.core.internal.boot.InternalBootLoader.run",
          "source": "InternalBootLoader.java:858"
        },
        {
          "method": "org.eclipse.core.boot.BootLoader.run",
          "source": "BootLoader.java:461"
        },
        {
          "method": "sun.reflect.NativeMethodAccessorImpl.invoke0",
          "source": "Native Method"
        },
        {
          "method": "sun.reflect.NativeMethodAccessorImpl.invoke",
          "source": "NativeMethodAccessorImpl.java:39"
        },
        {
          "method": "sun.reflect.DelegatingMethodAccessorImpl.invoke",
          "source": "DelegatingMethodAccessorImpl.java:25"
        },
        {
          "method": "java.lang.reflect.Method.invoke",
          "source": "Method.java:324"
        },
        {
          "method": "org.eclipse.core.launcher.Main.basicRun",
          "source": "Main.java:299"
        },
        {
          "method": "org.eclipse.core.launcher.Main.run",
          "source": "Main.java:767"
        },
        {
          "method": "org.eclipse.core.launcher.Main.main",
          "source": "Main.java:601"
        }
      ],
      "number": 0,
      "commentIndex": 0,
      "bugId": "47765",
      "duplicateId": "62662",
      "date": "2003-11-30T01:33:20+01:00",
      "product": "Platform",
      "component": "Text",
      "severity": "critical"
    }
  ],
  "groupId": "62662",
  "bugId": "47765",
  "duplicateId": "62662",
  "date": "2003-11-30T01:33:20+01:00",
  "product": "Platform",
  "component": "Text",
  "severity": "critical"
}