{
  "comments": [
    "after installing eclipse3.0 eclipse won\u0027t start. 2.1.2 is working on same \nmachine. error reported regarding \"creating .lock file\", but .lock file is \ncreated (size 0) and is writtable by user running eclipse. \n\nerror stack : \n\n!SESSION ----------------------------------------------------------------------\n!ENTRY org.eclipse.core.launcher 4 0 Dec 01, 2003 09:10:08.266\n!MESSAGE Exception launching the Eclipse Platform:\n!STACK\njava.lang.reflect.InvocationTargetException\n        at sun.reflect.NativeMethodAccessorImpl.invoke0(Native Method)\n        at sun.reflect.NativeMethodAccessorImpl.invoke\n(NativeMethodAccessorImpl.java:39)\n        at sun.reflect.DelegatingMethodAccessorImpl.invoke\n(DelegatingMethodAccessorImpl.java:25)\n        at java.lang.reflect.Method.invoke(Method.java:324)\n        at org.eclipse.core.internal.boot.InternalBootLoader.startup\n(InternalBootLoader.java:1049)\n        at org.eclipse.core.internal.boot.InternalBootLoader.run\n(InternalBootLoader.java:838)\n        at org.eclipse.core.boot.BootLoader.run(BootLoader.java:461)\n        at sun.reflect.NativeMethodAccessorImpl.invoke0(Native Method)\n        at sun.reflect.NativeMethodAccessorImpl.invoke\n(NativeMethodAccessorImpl.java:39)\n        at sun.reflect.DelegatingMethodAccessorImpl.invoke\n(DelegatingMethodAccessorImpl.java:25)\n        at java.lang.reflect.Method.invoke(Method.java:324)\n        at org.eclipse.core.launcher.Main.basicRun(Main.java:299)\n        at org.eclipse.core.launcher.Main.run(Main.java:767)\n        at org.eclipse.core.launcher.Main.main(Main.java:601)\nCaused by: org.eclipse.core.runtime.CoreException: Unable to create platform \nlock file: /opt/eclipse3/workspace/.metadata/.lock.\n        at org.eclipse.core.internal.runtime.InternalPlatform.createLockFile\n(InternalPlatform.java:228)\n        at org.eclipse.core.internal.runtime.InternalPlatform.loaderStartup\n(InternalPlatform.java:641)\n        ... 14 more\n\n\nmy platform is RH7.3 .",
    "Eclipse 3.0 requires a JDK 1.4 VM.  What VM are you using?",
    "Also, do you have your workspace on a NFS-based location? If so,\nthis would be a duplicate of bug 44735.",
    "Closing as duplicate of bug 44735. Please reopen if you believe your problem is\nnot the same.\n\n*** This bug has been marked as a duplicate of 44735 ***"
  ],
  "commentCreationDates": [
    "2003-12-01T07:18:09+01:00",
    "2003-12-01T14:15:25+01:00",
    "2003-12-01T18:37:46+01:00",
    "2003-12-04T17:43:45+01:00"
  ],
  "traces": [
    {
      "exceptionType": "java.lang.reflect.InvocationTargetException",
      "elements": [
        {
          "method": "sun.reflect.NativeMethodAccessorImpl.invoke0",
          "source": "Native Method"
        },
        {
          "method": "sun.reflect.NativeMethodAccessorImpl.invoke",
          "source": "NativeMethodAccessorImpl.java:39"
        },
        {
          "method": "sun.reflect.DelegatingMethodAccessorImpl.invoke",
          "source": "DelegatingMethodAccessorImpl.java:25"
        },
        {
          "method": "java.lang.reflect.Method.invoke",
          "source": "Method.java:324"
        },
        {
          "method": "org.eclipse.core.internal.boot.InternalBootLoader.startup",
          "source": "InternalBootLoader.java:1049"
        },
        {
          "method": "org.eclipse.core.internal.boot.InternalBootLoader.run",
          "source": "InternalBootLoader.java:838"
        },
        {
          "method": "org.eclipse.core.boot.BootLoader.run",
          "source": "BootLoader.java:461"
        },
        {
          "method": "sun.reflect.NativeMethodAccessorImpl.invoke0",
          "source": "Native Method"
        },
        {
          "method": "sun.reflect.NativeMethodAccessorImpl.invoke",
          "source": "NativeMethodAccessorImpl.java:39"
        },
        {
          "method": "sun.reflect.DelegatingMethodAccessorImpl.invoke",
          "source": "DelegatingMethodAccessorImpl.java:25"
        },
        {
          "method": "java.lang.reflect.Method.invoke",
          "source": "Method.java:324"
        },
        {
          "method": "org.eclipse.core.launcher.Main.basicRun",
          "source": "Main.java:299"
        },
        {
          "method": "org.eclipse.core.launcher.Main.run",
          "source": "Main.java:767"
        },
        {
          "method": "org.eclipse.core.launcher.Main.main",
          "source": "Main.java:601"
        }
      ],
      "causedBy": {
        "exceptionType": "org.eclipse.core.runtime.CoreException",
        "message": "Unable to create platform  lock file: /opt/eclipse3/workspace/.metadata/.lock.",
        "elements": [
          {
            "method": "org.eclipse.core.internal.runtime.InternalPlatform.createLockFile",
            "source": "InternalPlatform.java:228"
          },
          {
            "method": "org.eclipse.core.internal.runtime.InternalPlatform.loaderStartup",
            "source": "InternalPlatform.java:641"
          }
        ],
        "number": 0,
        "commentIndex": 0
      },
      "number": 0,
      "commentIndex": 0,
      "bugId": "47777",
      "duplicateId": "44735",
      "date": "2003-12-01T07:18:09+01:00",
      "product": "Platform",
      "component": "Resources",
      "severity": "normal"
    }
  ],
  "groupId": "44735",
  "bugId": "47777",
  "duplicateId": "44735",
  "date": "2003-12-01T07:18:09+01:00",
  "product": "Platform",
  "component": "Resources",
  "severity": "normal"
}