{
  "comments": [
    "Build 20031126 + latest JDT Core\n\n1. Create the following class:\npublic class X {\n\tX(Object arg) {\n\t}\n\tvoid foo() {\n\t\tnew X(\"\") {\n\t\t\tvoid bar() {\n\t\t\t\tnew Object() {\n\t\t\t\t\tvoid selectMe() {\n\t\t\t\t\t}\n\t\t\t\t};\n\t\t\t}\n\t\t};\n\t}\n}\n2. Select \u0027selectMe()\u0027 and press F3\nObserve: You get the following NPE:\njava.lang.NullPointerException\n        at org.eclipse.jdt.internal.core.Util.typeSignature(Util.java:1490)\n        at org.eclipse.jdt.internal.core.Util.typeParameterSignatures\n(Util.java:1478)\n        at org.eclipse.jdt.internal.core.util.HandleFactory$1$Visitor.visit\n(HandleFactory.java:184)\n        at org.eclipse.jdt.internal.compiler.ast.ConstructorDeclaration.traverse\n(ConstructorDeclaration.java:435)\n        at org.eclipse.jdt.internal.compiler.ast.TypeDeclaration.traverse\n(TypeDeclaration.java:1066)\n        at \norg.eclipse.jdt.internal.compiler.ast.QualifiedAllocationExpression.traverse\n(QualifiedAllocationExpression.java:342)\n        at org.eclipse.jdt.internal.compiler.ast.MethodDeclaration.traverse\n(MethodDeclaration.java:160)\n        at org.eclipse.jdt.internal.compiler.ast.TypeDeclaration.traverse\n(TypeDeclaration.java:1022)\n        at \norg.eclipse.jdt.internal.compiler.ast.CompilationUnitDeclaration.traverse\n(CompilationUnitDeclaration.java:305)\n        at org.eclipse.jdt.internal.core.util.HandleFactory.createElement\n(HandleFactory.java:296)\n        at org.eclipse.jdt.internal.core.SelectionRequestor.acceptLocalMethod\n(SelectionRequestor.java:149)\n        at org.eclipse.jdt.internal.codeassist.SelectionEngine.selectFrom\n(SelectionEngine.java:607)\n        at org.eclipse.jdt.internal.codeassist.SelectionEngine.select\n(SelectionEngine.java:520)\n        at org.eclipse.jdt.internal.core.Openable.codeSelect(Openable.java:169)\n        at org.eclipse.jdt.internal.core.CompilationUnit.codeSelect\n(CompilationUnit.java:269)\n        at org.eclipse.jdt.internal.core.CompilationUnit.codeSelect\n(CompilationUnit.java:263)\n        at \norg.eclipse.jdt.internal.ui.text.java.hover.AbstractJavaEditorTextHover.getHover\nInfo(AbstractJavaEditorTextHover.java:95)\n        at \norg.eclipse.jdt.internal.ui.text.java.hover.BestMatchHover.getHoverInfo\n(BestMatchHover.java:140)\n        at \norg.eclipse.jdt.internal.ui.text.java.hover.JavaEditorTextHoverProxy.getHoverInf\no(JavaEditorTextHoverProxy.java:69)\n        at org.eclipse.jface.text.TextViewerHoverManager$2.run\n(TextViewerHoverManager.java:119)",
    "Rewrote HandleFactory. Added regression test \nResolveTests.testMethodDeclarationInAnonymous3()",
    "Verified for 3.0 M6 with build I200312162000"
  ],
  "commentCreationDates": [
    "2003-12-01T13:03:15+01:00",
    "2003-12-15T12:36:04+01:00",
    "2003-12-17T12:05:02+01:00"
  ],
  "traces": [
    {
      "exceptionType": "java.lang.NullPointerException",
      "elements": [
        {
          "method": "org.eclipse.jdt.internal.core.Util.typeSignature",
          "source": "Util.java:1490"
        },
        {
          "method": "org.eclipse.jdt.internal.core.Util.typeParameterSignatures",
          "source": "Util.java:1478"
        },
        {
          "method": "org.eclipse.jdt.internal.core.util.HandleFactory$1$Visitor.visit",
          "source": "HandleFactory.java:184"
        },
        {
          "method": "org.eclipse.jdt.internal.compiler.ast.ConstructorDeclaration.traverse",
          "source": "ConstructorDeclaration.java:435"
        },
        {
          "method": "org.eclipse.jdt.internal.compiler.ast.TypeDeclaration.traverse",
          "source": "TypeDeclaration.java:1066"
        },
        {
          "method": "org.eclipse.jdt.internal.compiler.ast.QualifiedAllocationExpression.traverse",
          "source": "QualifiedAllocationExpression.java:342"
        },
        {
          "method": "org.eclipse.jdt.internal.compiler.ast.MethodDeclaration.traverse",
          "source": "MethodDeclaration.java:160"
        },
        {
          "method": "org.eclipse.jdt.internal.compiler.ast.TypeDeclaration.traverse",
          "source": "TypeDeclaration.java:1022"
        },
        {
          "method": "org.eclipse.jdt.internal.compiler.ast.CompilationUnitDeclaration.traverse",
          "source": "CompilationUnitDeclaration.java:305"
        },
        {
          "method": "org.eclipse.jdt.internal.core.util.HandleFactory.createElement",
          "source": "HandleFactory.java:296"
        },
        {
          "method": "org.eclipse.jdt.internal.core.SelectionRequestor.acceptLocalMethod",
          "source": "SelectionRequestor.java:149"
        },
        {
          "method": "org.eclipse.jdt.internal.codeassist.SelectionEngine.selectFrom",
          "source": "SelectionEngine.java:607"
        },
        {
          "method": "org.eclipse.jdt.internal.codeassist.SelectionEngine.select",
          "source": "SelectionEngine.java:520"
        },
        {
          "method": "org.eclipse.jdt.internal.core.Openable.codeSelect",
          "source": "Openable.java:169"
        },
        {
          "method": "org.eclipse.jdt.internal.core.CompilationUnit.codeSelect",
          "source": "CompilationUnit.java:269"
        },
        {
          "method": "org.eclipse.jdt.internal.core.CompilationUnit.codeSelect",
          "source": "CompilationUnit.java:263"
        },
        {
          "method": "org.eclipse.jdt.internal.ui.text.java.hover.AbstractJavaEditorTextHover.getHoverInfo",
          "source": "AbstractJavaEditorTextHover.java:95"
        },
        {
          "method": "org.eclipse.jdt.internal.ui.text.java.hover.BestMatchHover.getHoverInfo",
          "source": "BestMatchHover.java:140"
        },
        {
          "method": "org.eclipse.jdt.internal.ui.text.java.hover.JavaEditorTextHoverProxy.getHoverInfo",
          "source": "JavaEditorTextHoverProxy.java:69"
        },
        {
          "method": "org.eclipse.jface.text.TextViewerHoverManager$2.run",
          "source": "TextViewerHoverManager.java:119"
        }
      ],
      "number": 0,
      "commentIndex": 0,
      "bugId": "47795",
      "date": "2003-12-01T13:03:15+01:00",
      "product": "JDT",
      "component": "Core",
      "severity": "normal"
    }
  ],
  "groupId": "47795",
  "bugId": "47795",
  "date": "2003-12-01T13:03:15+01:00",
  "product": "JDT",
  "component": "Core",
  "severity": "normal"
}