{
  "comments": [
    "As I was editing my plugin.xml file, the following was dumped to the console. We should avoid \ndumping exceptions to the console when the user makes a syntax error.\n\norg.xml.sax.SAXParseException: Expected \"\u003c/activityPatternBinding\u003e\" to terminate  element \nstarting on line 2,218.\n        at org.apache.crimson.parser.Parser2.fatal(Parser2.java:3182)\n        at org.apache.crimson.parser.Parser2.fatal(Parser2.java:3176)\n        at org.apache.crimson.parser.Parser2.maybeElement(Parser2.java:1513)\n        at org.apache.crimson.parser.Parser2.content(Parser2.java:1779)\n        at org.apache.crimson.parser.Parser2.maybeElement(Parser2.java:1507)\n        at org.apache.crimson.parser.Parser2.content(Parser2.java:1779)\n        at org.apache.crimson.parser.Parser2.maybeElement(Parser2.java:1507)\n        at org.apache.crimson.parser.Parser2.parseInternal(Parser2.java:500)\n        at org.apache.crimson.parser.Parser2.parse(Parser2.java:305)\n        at org.apache.crimson.parser.XMLReaderImpl.parse(XMLReaderImpl.java:442)\n        at javax.xml.parsers.SAXParser.parse(SAXParser.java:345)\n        at javax.xml.parsers.SAXParser.parse(SAXParser.java:143)\n        at org.eclipse.pde.internal.core.plugin.AbstractPluginModelBase.loadOrig \n(AbstractPluginModelBase.java:166)\n        at org.eclipse.pde.internal.core.plugin.AbstractPluginModelBase.load(Abs \ntractPluginModelBase.java:149)\n        at org.eclipse.pde.internal.core.WorkspaceModelManager.loadWorkspaceMode \nl(WorkspaceModelManager.java:632)\n        at org.eclipse.pde.internal.core.WorkspaceModelManager.reloadWorkspaceMo \ndel(WorkspaceModelManager.java:681)\n        at org.eclipse.pde.internal.core.WorkspaceModelManager.handleFileDelta(W \norkspaceModelManager.java:403)\n        at org.eclipse.pde.internal.core.WorkspaceModelManager.visit(WorkspaceMo delManager.\njava:828)\n        at org.eclipse.core.internal.events.ResourceDelta.accept(ResourceDelta.j ava:67)\n        at org.eclipse.core.internal.events.ResourceDelta.accept(ResourceDelta.j ava:76)\n        at org.eclipse.core.internal.events.ResourceDelta.accept(ResourceDelta.j ava:76)\n        at org.eclipse.core.internal.events.ResourceDelta.accept(ResourceDelta.j ava:49)\n        at org.eclipse.pde.internal.core.WorkspaceModelManager.handleResourceDel \nta(WorkspaceModelManager.java:471)\n        at org.eclipse.pde.internal.core.WorkspaceModelManager.resourceChanged(W \norkspaceModelManager.java:726)\n        at org.eclipse.core.internal.events.NotificationManager$2.run(Notificati onManager.java:251)\n        at org.eclipse.core.internal.runtime.InternalPlatform.run(InternalPlatfo rm.java:1127)\n        at org.eclipse.core.runtime.Platform.run(Platform.java:464)\n        at org.eclipse.core.internal.events.NotificationManager.notify(Notificat ionManager.java:244)\n        at org.eclipse.core.internal.events.NotificationManager.broadcastChanges \n(NotificationManager.java:138)\n        at org.eclipse.core.internal.events.AutoBuildJob.broadcastChanges(AutoBu ildJob.java:46)\n        at org.eclipse.core.internal.events.AutoBuildJob.doBuild(AutoBuildJob.ja va:74)\n        at org.eclipse.core.internal.events.AutoBuildJob.run(AutoBuildJob.java:1 12)\n        at org.eclipse.core.internal.jobs.Worker.run(Worker.java:62)",
    "Fixed. obviously an oversight."
  ],
  "commentCreationDates": [
    "2003-12-02T01:31:34+01:00",
    "2003-12-02T05:17:23+01:00"
  ],
  "traces": [
    {
      "exceptionType": "org.xml.sax.SAXParseException",
      "message": "Expected \"\u003c/activityPatternBinding\u003e\" to terminate  element  starting on line 2,218.",
      "elements": [
        {
          "method": "org.apache.crimson.parser.Parser2.fatal",
          "source": "Parser2.java:3182"
        },
        {
          "method": "org.apache.crimson.parser.Parser2.fatal",
          "source": "Parser2.java:3176"
        },
        {
          "method": "org.apache.crimson.parser.Parser2.maybeElement",
          "source": "Parser2.java:1513"
        },
        {
          "method": "org.apache.crimson.parser.Parser2.content",
          "source": "Parser2.java:1779"
        },
        {
          "method": "org.apache.crimson.parser.Parser2.maybeElement",
          "source": "Parser2.java:1507"
        },
        {
          "method": "org.apache.crimson.parser.Parser2.content",
          "source": "Parser2.java:1779"
        },
        {
          "method": "org.apache.crimson.parser.Parser2.maybeElement",
          "source": "Parser2.java:1507"
        },
        {
          "method": "org.apache.crimson.parser.Parser2.parseInternal",
          "source": "Parser2.java:500"
        },
        {
          "method": "org.apache.crimson.parser.Parser2.parse",
          "source": "Parser2.java:305"
        },
        {
          "method": "org.apache.crimson.parser.XMLReaderImpl.parse",
          "source": "XMLReaderImpl.java:442"
        },
        {
          "method": "javax.xml.parsers.SAXParser.parse",
          "source": "SAXParser.java:345"
        },
        {
          "method": "javax.xml.parsers.SAXParser.parse",
          "source": "SAXParser.java:143"
        },
        {
          "method": "org.eclipse.pde.internal.core.plugin.AbstractPluginModelBase.loadOrig",
          "source": "AbstractPluginModelBase.java:166"
        },
        {
          "method": "org.eclipse.pde.internal.core.plugin.AbstractPluginModelBase.load",
          "source": "Abs  tractPluginModelBase.java:149"
        },
        {
          "method": "org.eclipse.pde.internal.core.WorkspaceModelManager.loadWorkspaceModel",
          "source": "WorkspaceModelManager.java:632"
        },
        {
          "method": "org.eclipse.pde.internal.core.WorkspaceModelManager.reloadWorkspaceModel",
          "source": "WorkspaceModelManager.java:681"
        },
        {
          "method": "org.eclipse.pde.internal.core.WorkspaceModelManager.handleFileDelta",
          "source": "W  orkspaceModelManager.java:403"
        },
        {
          "method": "org.eclipse.pde.internal.core.WorkspaceModelManager.visit",
          "source": "WorkspaceMo delManager. java:828"
        },
        {
          "method": "org.eclipse.core.internal.events.ResourceDelta.accept",
          "source": "ResourceDelta.j ava:67"
        },
        {
          "method": "org.eclipse.core.internal.events.ResourceDelta.accept",
          "source": "ResourceDelta.j ava:76"
        },
        {
          "method": "org.eclipse.core.internal.events.ResourceDelta.accept",
          "source": "ResourceDelta.j ava:76"
        },
        {
          "method": "org.eclipse.core.internal.events.ResourceDelta.accept",
          "source": "ResourceDelta.j ava:49"
        },
        {
          "method": "org.eclipse.pde.internal.core.WorkspaceModelManager.handleResourceDelta",
          "source": "WorkspaceModelManager.java:471"
        },
        {
          "method": "org.eclipse.pde.internal.core.WorkspaceModelManager.resourceChanged",
          "source": "W  orkspaceModelManager.java:726"
        },
        {
          "method": "org.eclipse.core.internal.events.NotificationManager$2.run",
          "source": "Notificati onManager.java:251"
        },
        {
          "method": "org.eclipse.core.internal.runtime.InternalPlatform.run",
          "source": "InternalPlatfo rm.java:1127"
        },
        {
          "method": "org.eclipse.core.runtime.Platform.run",
          "source": "Platform.java:464"
        },
        {
          "method": "org.eclipse.core.internal.events.NotificationManager.notify",
          "source": "Notificat ionManager.java:244"
        },
        {
          "method": "org.eclipse.core.internal.events.NotificationManager.broadcastChanges",
          "source": "NotificationManager.java:138"
        },
        {
          "method": "org.eclipse.core.internal.events.AutoBuildJob.broadcastChanges",
          "source": "AutoBu ildJob.java:46"
        },
        {
          "method": "org.eclipse.core.internal.events.AutoBuildJob.doBuild",
          "source": "AutoBuildJob.ja va:74"
        },
        {
          "method": "org.eclipse.core.internal.events.AutoBuildJob.run",
          "source": "AutoBuildJob.java:1 12"
        },
        {
          "method": "org.eclipse.core.internal.jobs.Worker.run",
          "source": "Worker.java:62"
        }
      ],
      "number": 0,
      "commentIndex": 0,
      "bugId": "47858",
      "date": "2003-12-02T01:31:34+01:00",
      "product": "PDE",
      "component": "UI",
      "severity": "normal"
    }
  ],
  "groupId": "47858",
  "bugId": "47858",
  "date": "2003-12-02T01:31:34+01:00",
  "product": "PDE",
  "component": "UI",
  "severity": "normal"
}