{
  "comments": [
    "I got this error when launhing eclipse. It worked fine after the message.\nI have jfacedbc and VE installed.\n\n!MESSAGE Exception launching the Eclipse Platform:\n!STACK\njava.lang.reflect.InvocationTargetException\n        at sun.reflect.NativeMethodAccessorImpl.invoke0(Native Method)\n        at\nsun.reflect.NativeMethodAccessorImpl.invoke(NativeMethodAccessorImpl.java:39)\n        at\nsun.reflect.DelegatingMethodAccessorImpl.invoke(DelegatingMethodAccessorImpl.java:25)\n        at java.lang.reflect.Method.invoke(Method.java:324)\n        at org.eclipse.core.launcher.Main.basicRun(Main.java:291)\n        at org.eclipse.core.launcher.Main.run(Main.java:747)\n        at org.eclipse.core.launcher.Main.main(Main.java:583)\nCaused by: java.lang.IllegalArgumentException: Application not found:\norg.eclipse.ui.workbench.\n        at\norg.eclipse.core.internal.boot.InternalBootLoader.run(InternalBootLoader.java:856)\n        at org.eclipse.core.boot.BootLoader.run(BootLoader.java:461)\n        ... 7 more",
    "I have the same mistake... but i cannot work with eclipse. My eclipse cannot \nlaunch and it is closed. :(\n\nP.D.: Sorry my bad english",
    "I forget to say i have windows 2000 and my version of eclipse is 2.1.2\n\nThanks",
    "See:\nhttp://dev.eclipse.org/viewcvs/index.cgi/%7Echeckout%7E/platform-text-home/development/bug-incomplete.htm"
  ],
  "commentCreationDates": [
    "2003-12-04T01:55:49+01:00",
    "2003-12-19T08:13:03+01:00",
    "2003-12-19T08:20:55+01:00",
    "2004-11-24T19:21:41+01:00"
  ],
  "traces": [
    {
      "exceptionType": "java.lang.reflect.InvocationTargetException",
      "elements": [
        {
          "method": "sun.reflect.NativeMethodAccessorImpl.invoke0",
          "source": "Native Method"
        },
        {
          "method": "sun.reflect.NativeMethodAccessorImpl.invoke",
          "source": "NativeMethodAccessorImpl.java:39"
        },
        {
          "method": "sun.reflect.DelegatingMethodAccessorImpl.invoke",
          "source": "DelegatingMethodAccessorImpl.java:25"
        },
        {
          "method": "java.lang.reflect.Method.invoke",
          "source": "Method.java:324"
        },
        {
          "method": "org.eclipse.core.launcher.Main.basicRun",
          "source": "Main.java:291"
        },
        {
          "method": "org.eclipse.core.launcher.Main.run",
          "source": "Main.java:747"
        },
        {
          "method": "org.eclipse.core.launcher.Main.main",
          "source": "Main.java:583"
        }
      ],
      "causedBy": {
        "exceptionType": "java.lang.IllegalArgumentException",
        "message": "Application not found: org.eclipse.ui.workbench.",
        "elements": [
          {
            "method": "org.eclipse.core.internal.boot.InternalBootLoader.run",
            "source": "InternalBootLoader.java:856"
          },
          {
            "method": "org.eclipse.core.boot.BootLoader.run",
            "source": "BootLoader.java:461"
          }
        ],
        "number": 0,
        "commentIndex": 0
      },
      "number": 0,
      "commentIndex": 0,
      "bugId": "48049",
      "date": "2003-12-04T01:55:49+01:00",
      "product": "Platform",
      "component": "Resources",
      "severity": "normal"
    }
  ],
  "groupId": "48049",
  "bugId": "48049",
  "date": "2003-12-04T01:55:49+01:00",
  "product": "Platform",
  "component": "Resources",
  "severity": "normal"
}