{
  "comments": [
    "The build fails when doing a \"Rebuild All\", which prevents me from getting a\nfunctional workspace.  The error meessage is:\n\nBuild problems\n  Errors during build.\n    java.lang.NullPointerException encountered while running\norg.eclipse.jdt.internal.core.builder.JavaBuilder.\n\nThe machine is a Gentoo Linux box running Sun\u0027s JDK 1.4.2_02, kernel\n2.6.0-test11, GNOME desktop environment, and the Enlightenment window manager.\n\nThe stack trace is as follows:\n!ENTRY org.eclipse.core.resources 4 2 Dec 04, 2003 09:51:55.188\n!MESSAGE Problems occurred when invoking code from plug-in:\n\"org.eclipse.core.resources\".\n!STACK 0\njava.lang.NullPointerException\n        at\norg.eclipse.jdt.internal.compiler.lookup.MethodBinding.areParametersEqual(MethodBinding.java:63)\n        at org.eclipse.jdt.internal.compiler.ast.Javadoc.resolve(Javadoc.java:141)\n        at\norg.eclipse.jdt.internal.compiler.ast.AbstractMethodDeclaration.resolveJavadoc(AbstractMethodDeclaration.java:366)\n        at\norg.eclipse.jdt.internal.compiler.ast.ConstructorDeclaration.resolveJavadoc(ConstructorDeclaration.java:397)\n        at\norg.eclipse.jdt.internal.compiler.ast.AbstractMethodDeclaration.resolve(AbstractMethodDeclaration.java:356)\n        at\norg.eclipse.jdt.internal.compiler.ast.TypeDeclaration.resolve(TypeDeclaration.java:926)\n        at\norg.eclipse.jdt.internal.compiler.ast.TypeDeclaration.resolve(TypeDeclaration.java:975)\n        at\norg.eclipse.jdt.internal.compiler.ast.CompilationUnitDeclaration.resolve(CompilationUnitDeclaration.java:271)\n        at org.eclipse.jdt.internal.compiler.Compiler.process(Compiler.java:515)\n       at org.eclipse.jdt.internal.compiler.Compiler.compile(Compiler.java:328)\n       at\norg.eclipse.jdt.internal.core.builder.AbstractImageBuilder.compile(AbstractImageBuilder.java:205)\n        at\norg.eclipse.jdt.internal.core.builder.AbstractImageBuilder.compile(AbstractImageBuilder.java:155)\n        at\norg.eclipse.jdt.internal.core.builder.BatchImageBuilder.build(BatchImageBuilder.java:51)\n        at\norg.eclipse.jdt.internal.core.builder.JavaBuilder.buildAll(JavaBuilder.java:212)\n        at\norg.eclipse.jdt.internal.core.builder.JavaBuilder.build(JavaBuilder.java:135)\n        at\norg.eclipse.core.internal.events.BuildManager$2.run(BuildManager.java:493)\n        at\norg.eclipse.core.internal.runtime.InternalPlatform.run(InternalPlatform.java:824)\n        at org.eclipse.core.runtime.Platform.run(Platform.java:479)\n        at\norg.eclipse.core.internal.events.BuildManager.basicBuild(BuildManager.java:138)\n        at\norg.eclipse.core.internal.events.BuildManager.basicBuild(BuildManager.java:209)\n        at\norg.eclipse.core.internal.events.BuildManager.basicBuild(BuildManager.java:164)\n        at\norg.eclipse.core.internal.events.BuildManager$1.run(BuildManager.java:190)\n        at\norg.eclipse.core.internal.runtime.InternalPlatform.run(InternalPlatform.java:824)\n        at org.eclipse.core.runtime.Platform.run(Platform.java:479)\n        at\norg.eclipse.core.internal.events.BuildManager.basicBuild(BuildManager.java:193)\n        at\norg.eclipse.core.internal.events.BuildManager.basicBuildLoop(BuildManager.java:227)\n        at\norg.eclipse.core.internal.events.BuildManager.build(BuildManager.java:255)\n        at org.eclipse.core.internal.resources.Workspace.build(Workspace.java:165)\n        at\norg.eclipse.ui.actions.GlobalBuildAction$1.run(GlobalBuildAction.java:184)\n        at\norg.eclipse.jface.operation.ModalContext$ModalContextThread.run(ModalContext.java:101)",
    "Could you please provide your test case?",
    "Do you have the same error if the option \u0027Problems in Javadoc tags\u0027 is set \nto \u0027Ignore\u0027?\n",
    "Thank you for your help.  Setting \"Preferences \u003e Java \u003e Compiler \u003e Problems in\nJavadoc tags\" to \"Ignore\" makes the problem go away.  Previously, I had it set\nto \"Warning\".\n\nDowngrading to major, since a workaround exists, but the functionality is\nsomewhat important (?).",
    "It would be really helpful for me to have a test case. Or, would it be possible \nfor you to apply a patch on source file(s) if I cannot reproduce the problem?\n",
    "I can reproduce the problem:\nfile X.java:\npublic class X {\n\tX(String str) {}\n}\nfile Y.java\npublic class Y extends X {\n\t/**\n\t * @see X#X(STRING)\n\t */\n\tY(String str) {super(str);}\n}\nWhen you save file Y.java, then you get the NPE...\n\nIf you remove the @see reference or fix the invalid type in argument:\npublic class Y extends X {\n\t/**\n\t * @see X#X(String)\n\t */\n\tY(String str) {super(str);}\n}\nthen the NPE also disappear...\n\nThis can be another workaround if you can easily identify where the invalid \nreference is...\n\nOtherwise, the fix is ready and after performing all tests, it will be released \nsurely for integration build next week\n",
    "Fixed.\n\nBinding control was invalid before starting looking at @see reference in \noverriden methods (see bug 47339).\n\nTest cases added in jdt.core.tests.compiler.regression.JavadocTestMixed\n",
    "Verified for 3.0M6"
  ],
  "commentCreationDates": [
    "2003-12-04T14:55:54+01:00",
    "2003-12-04T15:04:33+01:00",
    "2003-12-04T15:11:59+01:00",
    "2003-12-04T15:21:50+01:00",
    "2003-12-04T15:31:12+01:00",
    "2003-12-04T16:54:31+01:00",
    "2003-12-04T18:29:06+01:00",
    "2003-12-16T12:02:58+01:00"
  ],
  "traces": [
    {
      "exceptionType": "java.lang.NullPointerException",
      "elements": [
        {
          "method": "org.eclipse.jdt.internal.compiler.lookup.MethodBinding.areParametersEqual",
          "source": "MethodBinding.java:63"
        },
        {
          "method": "org.eclipse.jdt.internal.compiler.ast.Javadoc.resolve",
          "source": "Javadoc.java:141"
        },
        {
          "method": "org.eclipse.jdt.internal.compiler.ast.AbstractMethodDeclaration.resolveJavadoc",
          "source": "AbstractMethodDeclaration.java:366"
        },
        {
          "method": "org.eclipse.jdt.internal.compiler.ast.ConstructorDeclaration.resolveJavadoc",
          "source": "ConstructorDeclaration.java:397"
        },
        {
          "method": "org.eclipse.jdt.internal.compiler.ast.AbstractMethodDeclaration.resolve",
          "source": "AbstractMethodDeclaration.java:356"
        },
        {
          "method": "org.eclipse.jdt.internal.compiler.ast.TypeDeclaration.resolve",
          "source": "TypeDeclaration.java:926"
        },
        {
          "method": "org.eclipse.jdt.internal.compiler.ast.TypeDeclaration.resolve",
          "source": "TypeDeclaration.java:975"
        },
        {
          "method": "org.eclipse.jdt.internal.compiler.ast.CompilationUnitDeclaration.resolve",
          "source": "CompilationUnitDeclaration.java:271"
        },
        {
          "method": "org.eclipse.jdt.internal.compiler.Compiler.process",
          "source": "Compiler.java:515"
        },
        {
          "method": "org.eclipse.jdt.internal.compiler.Compiler.compile",
          "source": "Compiler.java:328"
        },
        {
          "method": "org.eclipse.jdt.internal.core.builder.AbstractImageBuilder.compile",
          "source": "AbstractImageBuilder.java:205"
        },
        {
          "method": "org.eclipse.jdt.internal.core.builder.AbstractImageBuilder.compile",
          "source": "AbstractImageBuilder.java:155"
        },
        {
          "method": "org.eclipse.jdt.internal.core.builder.BatchImageBuilder.build",
          "source": "BatchImageBuilder.java:51"
        },
        {
          "method": "org.eclipse.jdt.internal.core.builder.JavaBuilder.buildAll",
          "source": "JavaBuilder.java:212"
        },
        {
          "method": "org.eclipse.jdt.internal.core.builder.JavaBuilder.build",
          "source": "JavaBuilder.java:135"
        },
        {
          "method": "org.eclipse.core.internal.events.BuildManager$2.run",
          "source": "BuildManager.java:493"
        },
        {
          "method": "org.eclipse.core.internal.runtime.InternalPlatform.run",
          "source": "InternalPlatform.java:824"
        },
        {
          "method": "org.eclipse.core.runtime.Platform.run",
          "source": "Platform.java:479"
        },
        {
          "method": "org.eclipse.core.internal.events.BuildManager.basicBuild",
          "source": "BuildManager.java:138"
        },
        {
          "method": "org.eclipse.core.internal.events.BuildManager.basicBuild",
          "source": "BuildManager.java:209"
        },
        {
          "method": "org.eclipse.core.internal.events.BuildManager.basicBuild",
          "source": "BuildManager.java:164"
        },
        {
          "method": "org.eclipse.core.internal.events.BuildManager$1.run",
          "source": "BuildManager.java:190"
        },
        {
          "method": "org.eclipse.core.internal.runtime.InternalPlatform.run",
          "source": "InternalPlatform.java:824"
        },
        {
          "method": "org.eclipse.core.runtime.Platform.run",
          "source": "Platform.java:479"
        },
        {
          "method": "org.eclipse.core.internal.events.BuildManager.basicBuild",
          "source": "BuildManager.java:193"
        },
        {
          "method": "org.eclipse.core.internal.events.BuildManager.basicBuildLoop",
          "source": "BuildManager.java:227"
        },
        {
          "method": "org.eclipse.core.internal.events.BuildManager.build",
          "source": "BuildManager.java:255"
        },
        {
          "method": "org.eclipse.core.internal.resources.Workspace.build",
          "source": "Workspace.java:165"
        },
        {
          "method": "org.eclipse.ui.actions.GlobalBuildAction$1.run",
          "source": "GlobalBuildAction.java:184"
        },
        {
          "method": "org.eclipse.jface.operation.ModalContext$ModalContextThread.run",
          "source": "ModalContext.java:101"
        }
      ],
      "number": 0,
      "commentIndex": 0,
      "bugId": "48064",
      "date": "2003-12-04T14:55:54+01:00",
      "product": "JDT",
      "component": "Core",
      "severity": "major"
    }
  ],
  "groupId": "48064",
  "bugId": "48064",
  "date": "2003-12-04T14:55:54+01:00",
  "product": "JDT",
  "component": "Core",
  "severity": "major"
}