{
  "comments": [
    "Eclipse 3.0 version Motif build 200312030800\n\nI got some error at startup :\n\nemersonc@elbassan:~/eclipse3/eclipse\u003e ./eclipse\n\nEclipse OSGi Framework 3.6.0\n\nOSGi Service Platform Release 3\n\nCopyright (c) 2003 IBM Corporation and others.\nAll rights reserved. This program and the accompanying materials\nare made available under the terms of the Common Public License v1.0\nwhich accompanies this distribution, and is available at\nhttp://www.eclipse.org/legal/cpl-v10.html\nContributors:\n     IBM Corporation - initial API and implementation\nInitialize the framework: 533\nTime (re)start the framework: 38\nThe application \"org.eclipse.update.core.reconciler\" returned with code: 23.\nService Unregistering:\nService Unregistering:\nService Unregistering:\n\nEclipse OSGi Framework 3.6.0\n\nOSGi Service Platform Release 3\n\nCopyright (c) 2003 IBM Corporation and others.\nAll rights reserved. This program and the accompanying materials\nare made available under the terms of the Common Public License v1.0\nwhich accompanies this distribution, and is available at\nhttp://www.eclipse.org/legal/cpl-v10.html\nContributors:\n     IBM Corporation - initial API and implementation\nInitialize the framework: 1172\nTime (re)start the framework: 90\nfree(): invalid pointer 0x4d549b58!\nfree(): invalid pointer 0x4d549b58!\nfree(): invalid pointer 0x4d549b58!\nfree(): invalid pointer 0x4d549b58!\nfree(): invalid pointer 0x4d549b58!\nfree(): invalid pointer 0x4d549b58!\n\n\nAnd here\u0027s my .log file. Theres another log snippet under this, with a error\nwhen synchonizing. (the last one appeared on the progress view : \"An error\noccured while synchronizing with remote contents.\n  An error occurred refreshing /certidoes: Resource is out of sync with the file\nsystem: /certidoes/config/CVS/Entries.\n\")\n\n\n!ENTRY org.eclipse.team.ui 4 2 Dez 05, 2003 13:34:24.901\n!MESSAGE Problems occurred when invoking code from plug-in: \"org.eclipse.team.ui\".\n!STACK 0\njava.lang.IllegalArgumentException: Group not found:\norg.eclipse.team.internal.ccvs.ui.subscriber.WorkspaceSynchronizeParticipant@2613b\n        at\norg.eclipse.jface.action.ContributionManager.addToGroup(ContributionManager.java:113)\n        at\norg.eclipse.jface.action.ContributionManager.prependToGroup(ContributionManager.java:325)\n        at\norg.eclipse.jface.action.SubContributionManager.prependToGroup(SubContributionManager.java:232)\n        at\norg.eclipse.team.internal.ui.synchronize.actions.WorkingSetFilterActionGroup.updateMruContribution(WorkingSetFilterActionGroup.java:77)\n        at\norg.eclipse.team.internal.ui.synchronize.actions.WorkingSetFilterActionGroup.setWorkingSet(WorkingSetFilterActionGroup.java:124)\n        at\norg.eclipse.team.ui.synchronize.TeamSubscriberParticipantPage.propertyChange(TeamSubscriberParticipantPage.java:549)\n        at\norg.eclipse.team.internal.ccvs.ui.subscriber.CVSSynchronizeViewPage.propertyChange(CVSSynchronizeViewPage.java:119)\n        at\norg.eclipse.team.ui.synchronize.AbstractSynchronizeParticipant$PropertyNotifier.run(AbstractSynchronizeParticipant.java:61)\n        at\norg.eclipse.core.internal.runtime.InternalPlatform.run(InternalPlatform.java:824)\n        at org.eclipse.core.runtime.Platform.run(Platform.java:479)\n        at\norg.eclipse.team.ui.synchronize.AbstractSynchronizeParticipant$PropertyNotifier.notify(AbstractSynchronizeParticipant.java:78)\n        at\norg.eclipse.team.ui.synchronize.AbstractSynchronizeParticipant.firePropertyChange(AbstractSynchronizeParticipant.java:154)\n        at\norg.eclipse.team.ui.synchronize.TeamSubscriberParticipant.setWorkingSet(TeamSubscriberParticipant.java:119)\n        at\norg.eclipse.team.internal.ccvs.ui.CVSUIPlugin.showInSyncView(CVSUIPlugin.java:746)\n        at\norg.eclipse.team.internal.ccvs.ui.actions.SyncAction.execute(SyncAction.java:35)\n        at\norg.eclipse.team.internal.ccvs.ui.actions.CVSAction.run(CVSAction.java:69)\n        at\norg.eclipse.ui.actions.ActionDelegate.runWithEvent(ActionDelegate.java:71)\n        at org.eclipse.ui.internal.PluginAction.runWithEvent(PluginAction.java:261)\n        at\norg.eclipse.jface.action.ActionContributionItem.handleWidgetSelection(ActionContributionItem.java:535)\n        at\norg.eclipse.jface.action.ActionContributionItem.access$4(ActionContributionItem.java:487)\n        at\norg.eclipse.jface.action.ActionContributionItem$6.handleEvent(ActionContributionItem.java:459)\n        at org.eclipse.swt.widgets.EventTable.sendEvent(EventTable.java:82)\n        at org.eclipse.swt.widgets.Widget.sendEvent(Widget.java:745)\n        at org.eclipse.swt.widgets.Display.runDeferredEvents(Display.java:2356)\n        at org.eclipse.swt.widgets.Display.readAndDispatch(Display.java:2113)\n        at org.eclipse.ui.internal.Workbench.runEventLoop(Workbench.java:1486)\n        at org.eclipse.ui.internal.Workbench.runUI(Workbench.java:1462)\n        at\norg.eclipse.ui.internal.Workbench.createAndRunWorkbench(Workbench.java:242)\n        at org.eclipse.ui.PlatformUI.createAndRunWorkbench(PlatformUI.java:139)\n        at org.eclipse.ui.internal.ide.IDEApplication.run(IDEApplication.java:47)\n        at\norg.eclipse.core.internal.applicationrunner.ApplicationRunnerActivator$1.run(ApplicationRunnerActivator.java:85)\n        at\norg.eclipse.core.runtime.adaptor.EclipseStarter.run(EclipseStarter.java:87)\n        at sun.reflect.NativeMethodAccessorImpl.invoke0(Native Method)\n        at\nsun.reflect.NativeMethodAccessorImpl.invoke(NativeMethodAccessorImpl.java:39)\n        at\nsun.reflect.DelegatingMethodAccessorImpl.invoke(DelegatingMethodAccessorImpl.java:25)\n        at java.lang.reflect.Method.invoke(Method.java:324)\n        at\norg.eclipse.core.internal.boot.OSGiBootLoader.basicRun(OSGiBootLoader.java:239)\n        at\norg.eclipse.core.internal.boot.OSGiBootLoader.run(OSGiBootLoader.java:665)\n        at\norg.eclipse.core.internal.boot.OSGiBootLoader.run(OSGiBootLoader.java:652)\n        at sun.reflect.NativeMethodAccessorImpl.invoke0(Native Method)\n        at\nsun.reflect.NativeMethodAccessorImpl.invoke(NativeMethodAccessorImpl.java:39)\n        at\nsun.reflect.DelegatingMethodAccessorImpl.invoke(DelegatingMethodAccessorImpl.java:25)\n        at java.lang.reflect.Method.invoke(Method.java:324)\n        at org.eclipse.core.launcher.Main.basicRun(Main.java:299)\n        at org.eclipse.core.launcher.Main.run(Main.java:767)\n        at org.eclipse.core.launcher.Main.main(Main.java:601)\n!ENTRY org.eclipse.team.ui 4 0 Dez 05, 2003 13:34:25.109\n!MESSAGE Exception notifying participant listeners of changes.\n!STACK 0\njava.lang.IllegalArgumentException: Group not found:\norg.eclipse.team.internal.ccvs.ui.subscriber.WorkspaceSynchronizeParticipant@2613b\n        at\norg.eclipse.jface.action.ContributionManager.addToGroup(ContributionManager.java:113)\n        at\norg.eclipse.jface.action.ContributionManager.prependToGroup(ContributionManager.java:325)\n        at\norg.eclipse.jface.action.SubContributionManager.prependToGroup(SubContributionManager.java:232)\n        at\norg.eclipse.team.internal.ui.synchronize.actions.WorkingSetFilterActionGroup.updateMruContribution(WorkingSetFilterActionGroup.java:77)\n        at\norg.eclipse.team.internal.ui.synchronize.actions.WorkingSetFilterActionGroup.setWorkingSet(WorkingSetFilterActionGroup.java:124)\n        at\norg.eclipse.team.ui.synchronize.TeamSubscriberParticipantPage.propertyChange(TeamSubscriberParticipantPage.java:549)\n        at\norg.eclipse.team.internal.ccvs.ui.subscriber.CVSSynchronizeViewPage.propertyChange(CVSSynchronizeViewPage.java:119)\n        at\norg.eclipse.team.ui.synchronize.AbstractSynchronizeParticipant$PropertyNotifier.run(AbstractSynchronizeParticipant.java:61)\n        at\norg.eclipse.core.internal.runtime.InternalPlatform.run(InternalPlatform.java:824)\n        at org.eclipse.core.runtime.Platform.run(Platform.java:479)\n        at\norg.eclipse.team.ui.synchronize.AbstractSynchronizeParticipant$PropertyNotifier.notify(AbstractSynchronizeParticipant.java:78)\n        at\norg.eclipse.team.ui.synchronize.AbstractSynchronizeParticipant.firePropertyChange(AbstractSynchronizeParticipant.java:154)\n        at\norg.eclipse.team.ui.synchronize.TeamSubscriberParticipant.setWorkingSet(TeamSubscriberParticipant.java:119)\n        at\norg.eclipse.team.internal.ccvs.ui.CVSUIPlugin.showInSyncView(CVSUIPlugin.java:746)\n        at\norg.eclipse.team.internal.ccvs.ui.actions.SyncAction.execute(SyncAction.java:35)\n        at\norg.eclipse.team.internal.ccvs.ui.actions.CVSAction.run(CVSAction.java:69)\n        at\norg.eclipse.ui.actions.ActionDelegate.runWithEvent(ActionDelegate.java:71)\n        at org.eclipse.ui.internal.PluginAction.runWithEvent(PluginAction.java:261)\n        at\norg.eclipse.jface.action.ActionContributionItem.handleWidgetSelection(ActionContributionItem.java:535)\n        at\norg.eclipse.jface.action.ActionContributionItem.access$4(ActionContributionItem.java:487)\n        at\norg.eclipse.jface.action.ActionContributionItem$6.handleEvent(ActionContributionItem.java:459)\n        at org.eclipse.swt.widgets.EventTable.sendEvent(EventTable.java:82)\n        at org.eclipse.swt.widgets.Widget.sendEvent(Widget.java:745)\n        at org.eclipse.swt.widgets.Display.runDeferredEvents(Display.java:2356)\n        at org.eclipse.swt.widgets.Display.readAndDispatch(Display.java:2113)\n        at org.eclipse.ui.internal.Workbench.runEventLoop(Workbench.java:1486)\n        at org.eclipse.ui.internal.Workbench.runUI(Workbench.java:1462)\n        at\norg.eclipse.ui.internal.Workbench.createAndRunWorkbench(Workbench.java:242)\n        at org.eclipse.ui.PlatformUI.createAndRunWorkbench(PlatformUI.java:139)\n        at org.eclipse.ui.internal.ide.IDEApplication.run(IDEApplication.java:47)\n        at\norg.eclipse.core.internal.applicationrunner.ApplicationRunnerActivator$1.run(ApplicationRunnerActivator.java:85)\n        at\norg.eclipse.core.runtime.adaptor.EclipseStarter.run(EclipseStarter.java:87)\n        at sun.reflect.NativeMethodAccessorImpl.invoke0(Native Method)\n        at\nsun.reflect.NativeMethodAccessorImpl.invoke(NativeMethodAccessorImpl.java:39)\n        at\nsun.reflect.DelegatingMethodAccessorImpl.invoke(DelegatingMethodAccessorImpl.java:25)\n        at java.lang.reflect.Method.invoke(Method.java:324)\n        at\norg.eclipse.core.internal.boot.OSGiBootLoader.basicRun(OSGiBootLoader.java:239)\n        at\norg.eclipse.core.internal.boot.OSGiBootLoader.run(OSGiBootLoader.java:665)\n        at\norg.eclipse.core.internal.boot.OSGiBootLoader.run(OSGiBootLoader.java:652)\n        at sun.reflect.NativeMethodAccessorImpl.invoke0(Native Method)\n        at\nsun.reflect.NativeMethodAccessorImpl.invoke(NativeMethodAccessorImpl.java:39)\n        at\nsun.reflect.DelegatingMethodAccessorImpl.invoke(DelegatingMethodAccessorImpl.java:25)\n        at java.lang.reflect.Method.invoke(Method.java:324)\n        at org.eclipse.core.launcher.Main.basicRun(Main.java:299)\n        at org.eclipse.core.launcher.Main.run(Main.java:767)\n        at org.eclipse.core.launcher.Main.main(Main.java:601)\n!ENTRY org.eclipse.team.cvs.ui 4 0 Dez 05, 2003 13:35:14.689\n!MESSAGE Cannot display annotation for connmanager.jsp because it doesnt have an\nremote revision.\n!STACK 1\norg.eclipse.team.internal.ccvs.core.CVSException: Cannot display annotation for\nconnmanager.jsp because it doesnt have an remote revision.\n        at\norg.eclipse.team.internal.ccvs.ui.actions.ShowAnnotationAction.execute(ShowAnnotationAction.java:67)\n        at\norg.eclipse.team.internal.ccvs.ui.actions.ShowAnnotationAction.execute(ShowAnnotationAction.java:53)\n        at\norg.eclipse.team.internal.ccvs.ui.actions.CVSAction.run(CVSAction.java:69)\n        at\norg.eclipse.ui.actions.ActionDelegate.runWithEvent(ActionDelegate.java:71)\n        at org.eclipse.ui.internal.PluginAction.runWithEvent(PluginAction.java:261)\n        at\norg.eclipse.jface.action.ActionContributionItem.handleWidgetSelection(ActionContributionItem.java:535)\n        at\norg.eclipse.jface.action.ActionContributionItem.access$4(ActionContributionItem.java:487)\n        at\norg.eclipse.jface.action.ActionContributionItem$6.handleEvent(ActionContributionItem.java:459)\n        at org.eclipse.swt.widgets.EventTable.sendEvent(EventTable.java:82)\n        at org.eclipse.swt.widgets.Widget.sendEvent(Widget.java:745)\n        at org.eclipse.swt.widgets.Display.runDeferredEvents(Display.java:2356)\n        at org.eclipse.swt.widgets.Display.readAndDispatch(Display.java:2113)\n        at org.eclipse.ui.internal.Workbench.runEventLoop(Workbench.java:1486)\n        at org.eclipse.ui.internal.Workbench.runUI(Workbench.java:1462)\n        at\norg.eclipse.ui.internal.Workbench.createAndRunWorkbench(Workbench.java:242)\n        at org.eclipse.ui.PlatformUI.createAndRunWorkbench(PlatformUI.java:139)\n        at org.eclipse.ui.internal.ide.IDEApplication.run(IDEApplication.java:47)\n        at\norg.eclipse.core.internal.applicationrunner.ApplicationRunnerActivator$1.run(ApplicationRunnerActivator.java:85)\n        at\norg.eclipse.core.runtime.adaptor.EclipseStarter.run(EclipseStarter.java:87)\n        at sun.reflect.NativeMethodAccessorImpl.invoke0(Native Method)\n        at\nsun.reflect.NativeMethodAccessorImpl.invoke(NativeMethodAccessorImpl.java:39)\n        at\nsun.reflect.DelegatingMethodAccessorImpl.invoke(DelegatingMethodAccessorImpl.java:25)\n        at java.lang.reflect.Method.invoke(Method.java:324)\n        at\norg.eclipse.core.internal.boot.OSGiBootLoader.basicRun(OSGiBootLoader.java:239)\n        at\norg.eclipse.core.internal.boot.OSGiBootLoader.run(OSGiBootLoader.java:665)\n        at\norg.eclipse.core.internal.boot.OSGiBootLoader.run(OSGiBootLoader.java:652)\n        at sun.reflect.NativeMethodAccessorImpl.invoke0(Native Method)\n        at\nsun.reflect.NativeMethodAccessorImpl.invoke(NativeMethodAccessorImpl.java:39)\n        at\nsun.reflect.DelegatingMethodAccessorImpl.invoke(DelegatingMethodAccessorImpl.java:25)\n        at java.lang.reflect.Method.invoke(Method.java:324)\n        at org.eclipse.core.launcher.Main.basicRun(Main.java:299)\n        at org.eclipse.core.launcher.Main.run(Main.java:767)\n        at org.eclipse.core.launcher.Main.main(Main.java:601)\n!ENTRY org.eclipse.team.cvs.core 4 -6 Dez 05, 2003 13:35:14.691\n!MESSAGE Cannot display annotation for connmanager.jsp because it doesnt have an\nremote revision.",
    "Interesting... not sure why the group cannot be found?",
    "Found a possible reaaon for this to occur. Basically, if the menu hasn\u0027t been \ncreated yet and a working set is created, then there is no need to update the \nmru set. It can be delayed until the menu is created.Fix released to HEAD."
  ],
  "commentCreationDates": [
    "2003-12-05T20:16:10+01:00",
    "2003-12-08T15:29:40+01:00",
    "2003-12-12T19:26:21+01:00"
  ],
  "traces": [
    {
      "exceptionType": "java.lang.IllegalArgumentException",
      "message": "Group not found: org.eclipse.team.internal.ccvs.ui.subscriber.WorkspaceSynchronizeParticipant@2613b",
      "elements": [
        {
          "method": "org.eclipse.jface.action.ContributionManager.addToGroup",
          "source": "ContributionManager.java:113"
        },
        {
          "method": "org.eclipse.jface.action.ContributionManager.prependToGroup",
          "source": "ContributionManager.java:325"
        },
        {
          "method": "org.eclipse.jface.action.SubContributionManager.prependToGroup",
          "source": "SubContributionManager.java:232"
        },
        {
          "method": "org.eclipse.team.internal.ui.synchronize.actions.WorkingSetFilterActionGroup.updateMruContribution",
          "source": "WorkingSetFilterActionGroup.java:77"
        },
        {
          "method": "org.eclipse.team.internal.ui.synchronize.actions.WorkingSetFilterActionGroup.setWorkingSet",
          "source": "WorkingSetFilterActionGroup.java:124"
        },
        {
          "method": "org.eclipse.team.ui.synchronize.TeamSubscriberParticipantPage.propertyChange",
          "source": "TeamSubscriberParticipantPage.java:549"
        },
        {
          "method": "org.eclipse.team.internal.ccvs.ui.subscriber.CVSSynchronizeViewPage.propertyChange",
          "source": "CVSSynchronizeViewPage.java:119"
        },
        {
          "method": "org.eclipse.team.ui.synchronize.AbstractSynchronizeParticipant$PropertyNotifier.run",
          "source": "AbstractSynchronizeParticipant.java:61"
        },
        {
          "method": "org.eclipse.core.internal.runtime.InternalPlatform.run",
          "source": "InternalPlatform.java:824"
        },
        {
          "method": "org.eclipse.core.runtime.Platform.run",
          "source": "Platform.java:479"
        },
        {
          "method": "org.eclipse.team.ui.synchronize.AbstractSynchronizeParticipant$PropertyNotifier.notify",
          "source": "AbstractSynchronizeParticipant.java:78"
        },
        {
          "method": "org.eclipse.team.ui.synchronize.AbstractSynchronizeParticipant.firePropertyChange",
          "source": "AbstractSynchronizeParticipant.java:154"
        },
        {
          "method": "org.eclipse.team.ui.synchronize.TeamSubscriberParticipant.setWorkingSet",
          "source": "TeamSubscriberParticipant.java:119"
        },
        {
          "method": "org.eclipse.team.internal.ccvs.ui.CVSUIPlugin.showInSyncView",
          "source": "CVSUIPlugin.java:746"
        },
        {
          "method": "org.eclipse.team.internal.ccvs.ui.actions.SyncAction.execute",
          "source": "SyncAction.java:35"
        },
        {
          "method": "org.eclipse.team.internal.ccvs.ui.actions.CVSAction.run",
          "source": "CVSAction.java:69"
        },
        {
          "method": "org.eclipse.ui.actions.ActionDelegate.runWithEvent",
          "source": "ActionDelegate.java:71"
        },
        {
          "method": "org.eclipse.ui.internal.PluginAction.runWithEvent",
          "source": "PluginAction.java:261"
        },
        {
          "method": "org.eclipse.jface.action.ActionContributionItem.handleWidgetSelection",
          "source": "ActionContributionItem.java:535"
        },
        {
          "method": "org.eclipse.jface.action.ActionContributionItem.access$4",
          "source": "ActionContributionItem.java:487"
        },
        {
          "method": "org.eclipse.jface.action.ActionContributionItem$6.handleEvent",
          "source": "ActionContributionItem.java:459"
        },
        {
          "method": "org.eclipse.swt.widgets.EventTable.sendEvent",
          "source": "EventTable.java:82"
        },
        {
          "method": "org.eclipse.swt.widgets.Widget.sendEvent",
          "source": "Widget.java:745"
        },
        {
          "method": "org.eclipse.swt.widgets.Display.runDeferredEvents",
          "source": "Display.java:2356"
        },
        {
          "method": "org.eclipse.swt.widgets.Display.readAndDispatch",
          "source": "Display.java:2113"
        },
        {
          "method": "org.eclipse.ui.internal.Workbench.runEventLoop",
          "source": "Workbench.java:1486"
        },
        {
          "method": "org.eclipse.ui.internal.Workbench.runUI",
          "source": "Workbench.java:1462"
        },
        {
          "method": "org.eclipse.ui.internal.Workbench.createAndRunWorkbench",
          "source": "Workbench.java:242"
        },
        {
          "method": "org.eclipse.ui.PlatformUI.createAndRunWorkbench",
          "source": "PlatformUI.java:139"
        },
        {
          "method": "org.eclipse.ui.internal.ide.IDEApplication.run",
          "source": "IDEApplication.java:47"
        },
        {
          "method": "org.eclipse.core.internal.applicationrunner.ApplicationRunnerActivator$1.run",
          "source": "ApplicationRunnerActivator.java:85"
        },
        {
          "method": "org.eclipse.core.runtime.adaptor.EclipseStarter.run",
          "source": "EclipseStarter.java:87"
        },
        {
          "method": "sun.reflect.NativeMethodAccessorImpl.invoke0",
          "source": "Native Method"
        },
        {
          "method": "sun.reflect.NativeMethodAccessorImpl.invoke",
          "source": "NativeMethodAccessorImpl.java:39"
        },
        {
          "method": "sun.reflect.DelegatingMethodAccessorImpl.invoke",
          "source": "DelegatingMethodAccessorImpl.java:25"
        },
        {
          "method": "java.lang.reflect.Method.invoke",
          "source": "Method.java:324"
        },
        {
          "method": "org.eclipse.core.internal.boot.OSGiBootLoader.basicRun",
          "source": "OSGiBootLoader.java:239"
        },
        {
          "method": "org.eclipse.core.internal.boot.OSGiBootLoader.run",
          "source": "OSGiBootLoader.java:665"
        },
        {
          "method": "org.eclipse.core.internal.boot.OSGiBootLoader.run",
          "source": "OSGiBootLoader.java:652"
        },
        {
          "method": "sun.reflect.NativeMethodAccessorImpl.invoke0",
          "source": "Native Method"
        },
        {
          "method": "sun.reflect.NativeMethodAccessorImpl.invoke",
          "source": "NativeMethodAccessorImpl.java:39"
        },
        {
          "method": "sun.reflect.DelegatingMethodAccessorImpl.invoke",
          "source": "DelegatingMethodAccessorImpl.java:25"
        },
        {
          "method": "java.lang.reflect.Method.invoke",
          "source": "Method.java:324"
        },
        {
          "method": "org.eclipse.core.launcher.Main.basicRun",
          "source": "Main.java:299"
        },
        {
          "method": "org.eclipse.core.launcher.Main.run",
          "source": "Main.java:767"
        },
        {
          "method": "org.eclipse.core.launcher.Main.main",
          "source": "Main.java:601"
        }
      ],
      "number": 0,
      "commentIndex": 0,
      "bugId": "48185",
      "date": "2003-12-05T20:16:10+01:00",
      "product": "Platform",
      "component": "Team",
      "severity": "normal"
    },
    {
      "exceptionType": "java.lang.IllegalArgumentException",
      "message": "Group not found: org.eclipse.team.internal.ccvs.ui.subscriber.WorkspaceSynchronizeParticipant@2613b",
      "elements": [
        {
          "method": "org.eclipse.jface.action.ContributionManager.addToGroup",
          "source": "ContributionManager.java:113"
        },
        {
          "method": "org.eclipse.jface.action.ContributionManager.prependToGroup",
          "source": "ContributionManager.java:325"
        },
        {
          "method": "org.eclipse.jface.action.SubContributionManager.prependToGroup",
          "source": "SubContributionManager.java:232"
        },
        {
          "method": "org.eclipse.team.internal.ui.synchronize.actions.WorkingSetFilterActionGroup.updateMruContribution",
          "source": "WorkingSetFilterActionGroup.java:77"
        },
        {
          "method": "org.eclipse.team.internal.ui.synchronize.actions.WorkingSetFilterActionGroup.setWorkingSet",
          "source": "WorkingSetFilterActionGroup.java:124"
        },
        {
          "method": "org.eclipse.team.ui.synchronize.TeamSubscriberParticipantPage.propertyChange",
          "source": "TeamSubscriberParticipantPage.java:549"
        },
        {
          "method": "org.eclipse.team.internal.ccvs.ui.subscriber.CVSSynchronizeViewPage.propertyChange",
          "source": "CVSSynchronizeViewPage.java:119"
        },
        {
          "method": "org.eclipse.team.ui.synchronize.AbstractSynchronizeParticipant$PropertyNotifier.run",
          "source": "AbstractSynchronizeParticipant.java:61"
        },
        {
          "method": "org.eclipse.core.internal.runtime.InternalPlatform.run",
          "source": "InternalPlatform.java:824"
        },
        {
          "method": "org.eclipse.core.runtime.Platform.run",
          "source": "Platform.java:479"
        },
        {
          "method": "org.eclipse.team.ui.synchronize.AbstractSynchronizeParticipant$PropertyNotifier.notify",
          "source": "AbstractSynchronizeParticipant.java:78"
        },
        {
          "method": "org.eclipse.team.ui.synchronize.AbstractSynchronizeParticipant.firePropertyChange",
          "source": "AbstractSynchronizeParticipant.java:154"
        },
        {
          "method": "org.eclipse.team.ui.synchronize.TeamSubscriberParticipant.setWorkingSet",
          "source": "TeamSubscriberParticipant.java:119"
        },
        {
          "method": "org.eclipse.team.internal.ccvs.ui.CVSUIPlugin.showInSyncView",
          "source": "CVSUIPlugin.java:746"
        },
        {
          "method": "org.eclipse.team.internal.ccvs.ui.actions.SyncAction.execute",
          "source": "SyncAction.java:35"
        },
        {
          "method": "org.eclipse.team.internal.ccvs.ui.actions.CVSAction.run",
          "source": "CVSAction.java:69"
        },
        {
          "method": "org.eclipse.ui.actions.ActionDelegate.runWithEvent",
          "source": "ActionDelegate.java:71"
        },
        {
          "method": "org.eclipse.ui.internal.PluginAction.runWithEvent",
          "source": "PluginAction.java:261"
        },
        {
          "method": "org.eclipse.jface.action.ActionContributionItem.handleWidgetSelection",
          "source": "ActionContributionItem.java:535"
        },
        {
          "method": "org.eclipse.jface.action.ActionContributionItem.access$4",
          "source": "ActionContributionItem.java:487"
        },
        {
          "method": "org.eclipse.jface.action.ActionContributionItem$6.handleEvent",
          "source": "ActionContributionItem.java:459"
        },
        {
          "method": "org.eclipse.swt.widgets.EventTable.sendEvent",
          "source": "EventTable.java:82"
        },
        {
          "method": "org.eclipse.swt.widgets.Widget.sendEvent",
          "source": "Widget.java:745"
        },
        {
          "method": "org.eclipse.swt.widgets.Display.runDeferredEvents",
          "source": "Display.java:2356"
        },
        {
          "method": "org.eclipse.swt.widgets.Display.readAndDispatch",
          "source": "Display.java:2113"
        },
        {
          "method": "org.eclipse.ui.internal.Workbench.runEventLoop",
          "source": "Workbench.java:1486"
        },
        {
          "method": "org.eclipse.ui.internal.Workbench.runUI",
          "source": "Workbench.java:1462"
        },
        {
          "method": "org.eclipse.ui.internal.Workbench.createAndRunWorkbench",
          "source": "Workbench.java:242"
        },
        {
          "method": "org.eclipse.ui.PlatformUI.createAndRunWorkbench",
          "source": "PlatformUI.java:139"
        },
        {
          "method": "org.eclipse.ui.internal.ide.IDEApplication.run",
          "source": "IDEApplication.java:47"
        },
        {
          "method": "org.eclipse.core.internal.applicationrunner.ApplicationRunnerActivator$1.run",
          "source": "ApplicationRunnerActivator.java:85"
        },
        {
          "method": "org.eclipse.core.runtime.adaptor.EclipseStarter.run",
          "source": "EclipseStarter.java:87"
        },
        {
          "method": "sun.reflect.NativeMethodAccessorImpl.invoke0",
          "source": "Native Method"
        },
        {
          "method": "sun.reflect.NativeMethodAccessorImpl.invoke",
          "source": "NativeMethodAccessorImpl.java:39"
        },
        {
          "method": "sun.reflect.DelegatingMethodAccessorImpl.invoke",
          "source": "DelegatingMethodAccessorImpl.java:25"
        },
        {
          "method": "java.lang.reflect.Method.invoke",
          "source": "Method.java:324"
        },
        {
          "method": "org.eclipse.core.internal.boot.OSGiBootLoader.basicRun",
          "source": "OSGiBootLoader.java:239"
        },
        {
          "method": "org.eclipse.core.internal.boot.OSGiBootLoader.run",
          "source": "OSGiBootLoader.java:665"
        },
        {
          "method": "org.eclipse.core.internal.boot.OSGiBootLoader.run",
          "source": "OSGiBootLoader.java:652"
        },
        {
          "method": "sun.reflect.NativeMethodAccessorImpl.invoke0",
          "source": "Native Method"
        },
        {
          "method": "sun.reflect.NativeMethodAccessorImpl.invoke",
          "source": "NativeMethodAccessorImpl.java:39"
        },
        {
          "method": "sun.reflect.DelegatingMethodAccessorImpl.invoke",
          "source": "DelegatingMethodAccessorImpl.java:25"
        },
        {
          "method": "java.lang.reflect.Method.invoke",
          "source": "Method.java:324"
        },
        {
          "method": "org.eclipse.core.launcher.Main.basicRun",
          "source": "Main.java:299"
        },
        {
          "method": "org.eclipse.core.launcher.Main.run",
          "source": "Main.java:767"
        },
        {
          "method": "org.eclipse.core.launcher.Main.main",
          "source": "Main.java:601"
        }
      ],
      "number": 1,
      "commentIndex": 0,
      "bugId": "48185",
      "date": "2003-12-05T20:16:10+01:00",
      "product": "Platform",
      "component": "Team",
      "severity": "normal"
    },
    {
      "exceptionType": "org.eclipse.team.internal.ccvs.core.CVSException",
      "message": "Cannot display annotation for connmanager.jsp because it doesnt have an remote revision.",
      "elements": [
        {
          "method": "org.eclipse.team.internal.ccvs.ui.actions.ShowAnnotationAction.execute",
          "source": "ShowAnnotationAction.java:67"
        },
        {
          "method": "org.eclipse.team.internal.ccvs.ui.actions.ShowAnnotationAction.execute",
          "source": "ShowAnnotationAction.java:53"
        },
        {
          "method": "org.eclipse.team.internal.ccvs.ui.actions.CVSAction.run",
          "source": "CVSAction.java:69"
        },
        {
          "method": "org.eclipse.ui.actions.ActionDelegate.runWithEvent",
          "source": "ActionDelegate.java:71"
        },
        {
          "method": "org.eclipse.ui.internal.PluginAction.runWithEvent",
          "source": "PluginAction.java:261"
        },
        {
          "method": "org.eclipse.jface.action.ActionContributionItem.handleWidgetSelection",
          "source": "ActionContributionItem.java:535"
        },
        {
          "method": "org.eclipse.jface.action.ActionContributionItem.access$4",
          "source": "ActionContributionItem.java:487"
        },
        {
          "method": "org.eclipse.jface.action.ActionContributionItem$6.handleEvent",
          "source": "ActionContributionItem.java:459"
        },
        {
          "method": "org.eclipse.swt.widgets.EventTable.sendEvent",
          "source": "EventTable.java:82"
        },
        {
          "method": "org.eclipse.swt.widgets.Widget.sendEvent",
          "source": "Widget.java:745"
        },
        {
          "method": "org.eclipse.swt.widgets.Display.runDeferredEvents",
          "source": "Display.java:2356"
        },
        {
          "method": "org.eclipse.swt.widgets.Display.readAndDispatch",
          "source": "Display.java:2113"
        },
        {
          "method": "org.eclipse.ui.internal.Workbench.runEventLoop",
          "source": "Workbench.java:1486"
        },
        {
          "method": "org.eclipse.ui.internal.Workbench.runUI",
          "source": "Workbench.java:1462"
        },
        {
          "method": "org.eclipse.ui.internal.Workbench.createAndRunWorkbench",
          "source": "Workbench.java:242"
        },
        {
          "method": "org.eclipse.ui.PlatformUI.createAndRunWorkbench",
          "source": "PlatformUI.java:139"
        },
        {
          "method": "org.eclipse.ui.internal.ide.IDEApplication.run",
          "source": "IDEApplication.java:47"
        },
        {
          "method": "org.eclipse.core.internal.applicationrunner.ApplicationRunnerActivator$1.run",
          "source": "ApplicationRunnerActivator.java:85"
        },
        {
          "method": "org.eclipse.core.runtime.adaptor.EclipseStarter.run",
          "source": "EclipseStarter.java:87"
        },
        {
          "method": "sun.reflect.NativeMethodAccessorImpl.invoke0",
          "source": "Native Method"
        },
        {
          "method": "sun.reflect.NativeMethodAccessorImpl.invoke",
          "source": "NativeMethodAccessorImpl.java:39"
        },
        {
          "method": "sun.reflect.DelegatingMethodAccessorImpl.invoke",
          "source": "DelegatingMethodAccessorImpl.java:25"
        },
        {
          "method": "java.lang.reflect.Method.invoke",
          "source": "Method.java:324"
        },
        {
          "method": "org.eclipse.core.internal.boot.OSGiBootLoader.basicRun",
          "source": "OSGiBootLoader.java:239"
        },
        {
          "method": "org.eclipse.core.internal.boot.OSGiBootLoader.run",
          "source": "OSGiBootLoader.java:665"
        },
        {
          "method": "org.eclipse.core.internal.boot.OSGiBootLoader.run",
          "source": "OSGiBootLoader.java:652"
        },
        {
          "method": "sun.reflect.NativeMethodAccessorImpl.invoke0",
          "source": "Native Method"
        },
        {
          "method": "sun.reflect.NativeMethodAccessorImpl.invoke",
          "source": "NativeMethodAccessorImpl.java:39"
        },
        {
          "method": "sun.reflect.DelegatingMethodAccessorImpl.invoke",
          "source": "DelegatingMethodAccessorImpl.java:25"
        },
        {
          "method": "java.lang.reflect.Method.invoke",
          "source": "Method.java:324"
        },
        {
          "method": "org.eclipse.core.launcher.Main.basicRun",
          "source": "Main.java:299"
        },
        {
          "method": "org.eclipse.core.launcher.Main.run",
          "source": "Main.java:767"
        },
        {
          "method": "org.eclipse.core.launcher.Main.main",
          "source": "Main.java:601"
        }
      ],
      "number": 2,
      "commentIndex": 0,
      "bugId": "48185",
      "date": "2003-12-05T20:16:10+01:00",
      "product": "Platform",
      "component": "Team",
      "severity": "normal"
    }
  ],
  "groupId": "48185",
  "bugId": "48185",
  "date": "2003-12-05T20:16:10+01:00",
  "product": "Platform",
  "component": "Team",
  "severity": "normal"
}