{
  "comments": [
    "Eclipse crashes on the remote X11.\nI tested with cygwin X11 and X11 bundled MacOSX10.3.\n\nEclipse writes log lines following;\njava.lang.reflect.InvocationTargetException\n        at sun.reflect.NativeMethodAccessorImpl.invoke0(Native Method)\n        at sun.reflect.NativeMethodAccessorImpl.invoke(NativeMethodAccessorImpl.\njava:39)\n        at sun.reflect.DelegatingMethodAccessorImpl.invoke(DelegatingMethodAcces\nsorImpl.java:25)\n        at java.lang.reflect.Method.invoke(Method.java:324)\n        at org.eclipse.core.launcher.Main.basicRun(Main.java:291)\n        at org.eclipse.core.launcher.Main.run(Main.java:747)\n        at org.eclipse.core.launcher.Main.main(Main.java:583)\nCaused by: java.lang.reflect.InvocationTargetException\n        at org.eclipse.core.internal.boot.InternalBootLoader.run(InternalBootLoa\nder.java:861)\n        at org.eclipse.core.boot.BootLoader.run(BootLoader.java:461)\n        ... 7 more\nCaused by: java.lang.IllegalArgumentException: Argument not valid\n        at org.eclipse.swt.SWT.error(SWT.java:2316)\n        at org.eclipse.swt.SWT.error(SWT.java:2260)\n        at org.eclipse.swt.graphics.GC.drawImage(GC.java:378)\n        at org.eclipse.swt.graphics.GC.drawImage(GC.java:361)\njava.lang.IllegalArgumentException: Argument not valid\n at org.",
    "The block in GC that\u0027s throwing the error is\n\n   if (srcX + srcWidth \u003e imgWidth || srcY + srcHeight \u003e imgHeight) {\n      SWT.error(SWT.ERROR_INVALID_ARGUMENT);\n   }\n\nSo an Image didn\u0027t load properly?  SSQ to investigate.\n",
    "This bug is really old. I can run Eclipse 3.1 with gtk 2.4.x from Window Xp using Cgwin and from Mac \nusing the Mac X server. Please reopen if you still have this problem."
  ],
  "commentCreationDates": [
    "2003-12-08T09:18:38+01:00",
    "2003-12-11T15:25:00+01:00",
    "2005-05-11T18:45:20+02:00"
  ],
  "traces": [
    {
      "exceptionType": "java.lang.reflect.InvocationTargetException",
      "elements": [
        {
          "method": "sun.reflect.NativeMethodAccessorImpl.invoke0",
          "source": "Native Method"
        },
        {
          "method": "sun.reflect.NativeMethodAccessorImpl.invoke",
          "source": "NativeMethodAccessorImpl. java:39"
        },
        {
          "method": "sun.reflect.DelegatingMethodAccessorImpl.invoke",
          "source": "DelegatingMethodAcces sorImpl.java:25"
        },
        {
          "method": "java.lang.reflect.Method.invoke",
          "source": "Method.java:324"
        },
        {
          "method": "org.eclipse.core.launcher.Main.basicRun",
          "source": "Main.java:291"
        },
        {
          "method": "org.eclipse.core.launcher.Main.run",
          "source": "Main.java:747"
        },
        {
          "method": "org.eclipse.core.launcher.Main.main",
          "source": "Main.java:583"
        }
      ],
      "causedBy": {
        "exceptionType": "java.lang.reflect.InvocationTargetException",
        "elements": [
          {
            "method": "org.eclipse.core.internal.boot.InternalBootLoader.run",
            "source": "InternalBootLoa der.java:861"
          },
          {
            "method": "org.eclipse.core.boot.BootLoader.run",
            "source": "BootLoader.java:461"
          }
        ],
        "causedBy": {
          "exceptionType": "java.lang.IllegalArgumentException",
          "message": "Argument not valid",
          "elements": [
            {
              "method": "org.eclipse.swt.SWT.error",
              "source": "SWT.java:2316"
            },
            {
              "method": "org.eclipse.swt.SWT.error",
              "source": "SWT.java:2260"
            },
            {
              "method": "org.eclipse.swt.graphics.GC.drawImage",
              "source": "GC.java:378"
            },
            {
              "method": "org.eclipse.swt.graphics.GC.drawImage",
              "source": "GC.java:361"
            }
          ],
          "number": 0,
          "commentIndex": 0
        },
        "number": 0,
        "commentIndex": 0
      },
      "number": 0,
      "commentIndex": 0,
      "bugId": "48255",
      "date": "2003-12-08T09:18:38+01:00",
      "product": "Platform",
      "component": "SWT",
      "severity": "normal"
    }
  ],
  "groupId": "48255",
  "bugId": "48255",
  "date": "2003-12-08T09:18:38+01:00",
  "product": "Platform",
  "component": "SWT",
  "severity": "normal"
}