{
  "comments": [
    "200312091137\n\nquite regularly, after searching for references, then double clicking a result, the progress view is \nbrought to top, empty of content, and annoyingly, obstructing my search view.\n\nfirst problem is that the view shouldn\u0027t be brought to top if there is no content. i switched to \n\u0027verbose\u0027 to see the reason it was popping up..\n\ni get an error entry on \u0027updating workspace (system)\u0027. clicking \u0027show error\u0027 says \u0027internal error when \nupdating workspace\u0027\n\nsecond problem is perhaps this error message could use some work..\n\ni check in the .log and see this entry (third problem..):\n\n!ENTRY org.eclipse.core.runtime 4 2 Dec 10, 2003 14:24:48.821\n!MESSAGE An internal error occurred during: \"Updating workspace\".\n!STACK 0\norg.eclipse.core.internal.utils.AssertionFailedException: Assertion failed: Mismatched begin/\nendOperation\n        at org.eclipse.core.internal.utils.Assert.isTrue(Assert.java:101)\n        at org.eclipse.core.internal.resources.Workspace.endOperation(Workspace.java:836)\n        at org.eclipse.core.internal.resources.Workspace.run(Workspace.java:1564)\n        at \norg.eclipse.core.internal.events.NotificationManager$NotifyJob.run(NotificationManager.java:37)\n        at org.eclipse.core.internal.jobs.Worker.run(Worker.java:62)",
    "Progress view no longer comes to front eagerly. The internal error has not been\nreproduced since and is in code that has changed significantly in the past year.\nClosing."
  ],
  "commentCreationDates": [
    "2003-12-10T19:38:24+01:00",
    "2004-11-02T16:42:40+01:00"
  ],
  "traces": [
    {
      "exceptionType": "org.eclipse.core.internal.utils.AssertionFailedException",
      "message": "Assertion failed: Mismatched begin/ endOperation",
      "elements": [
        {
          "method": "org.eclipse.core.internal.utils.Assert.isTrue",
          "source": "Assert.java:101"
        },
        {
          "method": "org.eclipse.core.internal.resources.Workspace.endOperation",
          "source": "Workspace.java:836"
        },
        {
          "method": "org.eclipse.core.internal.resources.Workspace.run",
          "source": "Workspace.java:1564"
        },
        {
          "method": "org.eclipse.core.internal.events.NotificationManager$NotifyJob.run",
          "source": "NotificationManager.java:37"
        },
        {
          "method": "org.eclipse.core.internal.jobs.Worker.run",
          "source": "Worker.java:62"
        }
      ],
      "number": 0,
      "commentIndex": 0,
      "bugId": "48434",
      "date": "2003-12-10T19:38:24+01:00",
      "product": "Platform",
      "component": "Resources",
      "severity": "normal"
    }
  ],
  "groupId": "48434",
  "bugId": "48434",
  "date": "2003-12-10T19:38:24+01:00",
  "product": "Platform",
  "component": "Resources",
  "severity": "normal"
}