{
  "comments": [
    "build i1210:1227, winxp, j9sc1104\n\nI got the following stack trace printed to the console when I was switching\nperspectives. The log file was empty.\n\njava.lang.IllegalArgumentException: Argument not valid\n        at java.lang.Throwable.\u003cinit\u003e(Throwable.java)\n        at java.lang.Throwable.\u003cinit\u003e(Throwable.java)\n        at org.eclipse.swt.SWT.error(SWT.java:2578)\n        at org.eclipse.swt.SWT.error(SWT.java:2522)\n        at org.eclipse.swt.widgets.Widget.error(Widget.java:388)\n        at org.eclipse.swt.widgets.Composite.setTabList(Composite.java:478)\n        at org.eclipse.jface.action.CoolBarManager.updateTabOrder(CoolBarManager\n.java:262)\n        at org.eclipse.jface.action.CoolBarManager.update(CoolBarManager.java)\n        at org.eclipse.ui.internal.ActionSetActionBars.setActive(ActionSetAction\nBars.java)\n        at org.eclipse.ui.SubActionBars.deactivate(SubActionBars.java:128)\n        at org.eclipse.ui.SubActionBars.deactivate(SubActionBars.java:116)\n        at org.eclipse.ui.internal.ActionPresentation.setActionSets(ActionPresen\ntation.java:109)\n        at org.eclipse.ui.internal.WorkbenchWindow.updateActionSets(WorkbenchWin\ndow.java:1833)\n        at org.eclipse.ui.internal.WorkbenchPage.setPerspective(WorkbenchPage.ja\nva:2620)\n        at org.eclipse.ui.internal.WorkbenchPage.busySetPerspective(WorkbenchPag\ne.java:695)\n        at org.eclipse.ui.internal.WorkbenchPage.access$8(WorkbenchPage.java:680\n)\n        at org.eclipse.ui.internal.WorkbenchPage$12.run(WorkbenchPage.java:2725)\n\n        at org.eclipse.swt.custom.BusyIndicator.showWhile(BusyIndicator.java:84)\n\n        at org.eclipse.ui.internal.WorkbenchPage.setPerspective(WorkbenchPage.ja\nva:2723)\n        at org.eclipse.ui.internal.SetPagePerspectiveAction.run(SetPagePerspecti\nveAction.java:72)\n        at org.eclipse.jface.action.Action.runWithEvent(Action.java:842)\n        at org.eclipse.jface.action.ActionContributionItem.handleWidgetSelection\n(ActionContributionItem.java:509)\n        at org.eclipse.jface.action.ActionContributionItem.access$2(ActionContri\nbutionItem.java:461)\n        at org.eclipse.jface.action.ActionContributionItem$6.handleEvent(ActionC\nontributionItem.java:433)\n        at org.eclipse.swt.widgets.EventTable.sendEvent(EventTable.java)\n        at org.eclipse.swt.widgets.Widget.sendEvent(Widget.java)\n        at org.eclipse.swt.widgets.Display.runDeferredEvents(Display.java)\n        at org.eclipse.swt.widgets.Display.readAndDispatch(Display.java)\n        at org.eclipse.ui.internal.Workbench.runEventLoop(Workbench.java:1547)\n        at org.eclipse.ui.internal.Workbench.runUI(Workbench.java:1523)\n        at org.eclipse.ui.internal.Workbench.createAndRunWorkbench(Workbench.jav\na:242)\n        at org.eclipse.ui.PlatformUI.createAndRunWorkbench(PlatformUI.java:139)\n        at org.eclipse.ui.internal.ide.IDEApplication.run(IDEApplication.java:47\n)\n        at org.eclipse.core.internal.runtime.PlatformActivator$1.run(PlatformAct\nivator.java:242)\n        at org.eclipse.core.runtime.adaptor.EclipseStarter.run(EclipseStarter.ja\nva:84)\n        at sun.reflect.NativeMethodAccessorImpl.invoke0(Native Method)\n        at sun.reflect.NativeMethodAccessorImpl.invoke(NativeMethodAccessorImpl.\njava:79)\n        at sun.reflect.DelegatingMethodAccessorImpl.invoke(DelegatingMethodAcces\nsorImpl.java:41)\n        at java.lang.reflect.Method.invoke(Method.java:386)\n        at org.eclipse.core.internal.boot.OSGiBootLoader.basicRun(OSGiBootLoader\n.java:239)\n        at org.eclipse.core.internal.boot.OSGiBootLoader.run(OSGiBootLoader.java\n:665)\n        at org.eclipse.core.internal.boot.OSGiBootLoader.run(OSGiBootLoader.java\n:652)\n        at sun.reflect.NativeMethodAccessorImpl.invoke0(Native Method)\n        at sun.reflect.NativeMethodAccessorImpl.invoke(NativeMethodAccessorImpl.\njava:79)\n        at sun.reflect.DelegatingMethodAccessorImpl.invoke(DelegatingMethodAcces\nsorImpl.java:41)\n        at java.lang.reflect.Method.invoke(Method.java:386)\n        at org.eclipse.core.launcher.Main.basicRun(Main.java:299)\n        at org.eclipse.core.launcher.Main.run(Main.java:767)\n        at org.eclipse.core.launcher.Main.main(Main.java:601)",
    "Is this part of the recent CoolBar work?",
    "Created an attachment (id\u003d7172)\nPatch for CoolBarManager.java\n\nApply the patch to coolBarManager.java in org.eclipse.jface.action package",
    "Although I cannot duplicate this bug, I have made the \nCoolBarManager.updateTabOrder method more robust to handle null entries. This \nshould fix the problem. The patch also fixes issues with stack trace dumps \nappearing in the console instead of the log file. ",
    "Fix has been released"
  ],
  "commentCreationDates": [
    "2003-12-10T21:41:59+01:00",
    "2003-12-11T15:31:45+01:00",
    "2003-12-15T19:50:52+01:00",
    "2003-12-15T19:56:43+01:00",
    "2003-12-15T20:07:26+01:00"
  ],
  "traces": [
    {
      "exceptionType": "java.lang.IllegalArgumentException",
      "message": "Argument not valid",
      "elements": [
        {
          "method": "java.lang.Throwable.\u003cinit\u003e",
          "source": "Throwable.java"
        },
        {
          "method": "java.lang.Throwable.\u003cinit\u003e",
          "source": "Throwable.java"
        },
        {
          "method": "org.eclipse.swt.SWT.error",
          "source": "SWT.java:2578"
        },
        {
          "method": "org.eclipse.swt.SWT.error",
          "source": "SWT.java:2522"
        },
        {
          "method": "org.eclipse.swt.widgets.Widget.error",
          "source": "Widget.java:388"
        },
        {
          "method": "org.eclipse.swt.widgets.Composite.setTabList",
          "source": "Composite.java:478"
        },
        {
          "method": "org.eclipse.jface.action.CoolBarManager.updateTabOrder",
          "source": "CoolBarManager .java:262"
        },
        {
          "method": "org.eclipse.jface.action.CoolBarManager.update",
          "source": "CoolBarManager.java"
        },
        {
          "method": "org.eclipse.ui.internal.ActionSetActionBars.setActive",
          "source": "ActionSetAction Bars.java"
        },
        {
          "method": "org.eclipse.ui.SubActionBars.deactivate",
          "source": "SubActionBars.java:128"
        },
        {
          "method": "org.eclipse.ui.SubActionBars.deactivate",
          "source": "SubActionBars.java:116"
        },
        {
          "method": "org.eclipse.ui.internal.ActionPresentation.setActionSets",
          "source": "ActionPresen tation.java:109"
        },
        {
          "method": "org.eclipse.ui.internal.WorkbenchWindow.updateActionSets",
          "source": "WorkbenchWin dow.java:1833"
        },
        {
          "method": "org.eclipse.ui.internal.WorkbenchPage.setPerspective",
          "source": "WorkbenchPage.ja va:2620"
        },
        {
          "method": "org.eclipse.ui.internal.WorkbenchPage.busySetPerspective",
          "source": "WorkbenchPag e.java:695"
        },
        {
          "method": "org.eclipse.ui.internal.WorkbenchPage.access$8",
          "source": "WorkbenchPage.java:680 "
        },
        {
          "method": "org.eclipse.ui.internal.WorkbenchPage$12.run",
          "source": "WorkbenchPage.java:2725"
        },
        {
          "method": "org.eclipse.swt.custom.BusyIndicator.showWhile",
          "source": "BusyIndicator.java:84"
        },
        {
          "method": "org.eclipse.ui.internal.WorkbenchPage.setPerspective",
          "source": "WorkbenchPage.ja va:2723"
        },
        {
          "method": "org.eclipse.ui.internal.SetPagePerspectiveAction.run",
          "source": "SetPagePerspecti veAction.java:72"
        },
        {
          "method": "org.eclipse.jface.action.Action.runWithEvent",
          "source": "Action.java:842"
        },
        {
          "method": "org.eclipse.jface.action.ActionContributionItem.handleWidgetSelection",
          "source": "ActionContributionItem.java:509"
        },
        {
          "method": "org.eclipse.jface.action.ActionContributionItem.access$2",
          "source": "ActionContri butionItem.java:461"
        },
        {
          "method": "org.eclipse.jface.action.ActionContributionItem$6.handleEvent",
          "source": "ActionC ontributionItem.java:433"
        },
        {
          "method": "org.eclipse.swt.widgets.EventTable.sendEvent",
          "source": "EventTable.java"
        },
        {
          "method": "org.eclipse.swt.widgets.Widget.sendEvent",
          "source": "Widget.java"
        },
        {
          "method": "org.eclipse.swt.widgets.Display.runDeferredEvents",
          "source": "Display.java"
        },
        {
          "method": "org.eclipse.swt.widgets.Display.readAndDispatch",
          "source": "Display.java"
        },
        {
          "method": "org.eclipse.ui.internal.Workbench.runEventLoop",
          "source": "Workbench.java:1547"
        },
        {
          "method": "org.eclipse.ui.internal.Workbench.runUI",
          "source": "Workbench.java:1523"
        },
        {
          "method": "org.eclipse.ui.internal.Workbench.createAndRunWorkbench",
          "source": "Workbench.jav a:242"
        },
        {
          "method": "org.eclipse.ui.PlatformUI.createAndRunWorkbench",
          "source": "PlatformUI.java:139"
        },
        {
          "method": "org.eclipse.ui.internal.ide.IDEApplication.run",
          "source": "IDEApplication.java:47 "
        },
        {
          "method": "org.eclipse.core.internal.runtime.PlatformActivator$1.run",
          "source": "PlatformAct ivator.java:242"
        },
        {
          "method": "org.eclipse.core.runtime.adaptor.EclipseStarter.run",
          "source": "EclipseStarter.ja va:84"
        },
        {
          "method": "sun.reflect.NativeMethodAccessorImpl.invoke0",
          "source": "Native Method"
        },
        {
          "method": "sun.reflect.NativeMethodAccessorImpl.invoke",
          "source": "NativeMethodAccessorImpl. java:79"
        },
        {
          "method": "sun.reflect.DelegatingMethodAccessorImpl.invoke",
          "source": "DelegatingMethodAcces sorImpl.java:41"
        },
        {
          "method": "java.lang.reflect.Method.invoke",
          "source": "Method.java:386"
        },
        {
          "method": "org.eclipse.core.internal.boot.OSGiBootLoader.basicRun",
          "source": "OSGiBootLoader .java:239"
        },
        {
          "method": "org.eclipse.core.internal.boot.OSGiBootLoader.run",
          "source": "OSGiBootLoader.java :665"
        },
        {
          "method": "org.eclipse.core.internal.boot.OSGiBootLoader.run",
          "source": "OSGiBootLoader.java :652"
        },
        {
          "method": "sun.reflect.NativeMethodAccessorImpl.invoke0",
          "source": "Native Method"
        },
        {
          "method": "sun.reflect.NativeMethodAccessorImpl.invoke",
          "source": "NativeMethodAccessorImpl. java:79"
        },
        {
          "method": "sun.reflect.DelegatingMethodAccessorImpl.invoke",
          "source": "DelegatingMethodAcces sorImpl.java:41"
        },
        {
          "method": "java.lang.reflect.Method.invoke",
          "source": "Method.java:386"
        },
        {
          "method": "org.eclipse.core.launcher.Main.basicRun",
          "source": "Main.java:299"
        },
        {
          "method": "org.eclipse.core.launcher.Main.run",
          "source": "Main.java:767"
        },
        {
          "method": "org.eclipse.core.launcher.Main.main",
          "source": "Main.java:601"
        }
      ],
      "number": 0,
      "commentIndex": 0,
      "bugId": "48448",
      "date": "2003-12-10T21:41:59+01:00",
      "product": "Platform",
      "component": "UI",
      "severity": "major"
    }
  ],
  "groupId": "48448",
  "bugId": "48448",
  "date": "2003-12-10T21:41:59+01:00",
  "product": "Platform",
  "component": "UI",
  "severity": "major"
}