{
  "comments": [
    "When the user changes the directory for the project contents of the \nApache Log Correlation/Analyzer Sample, the following exception is thrown:\n\njava.lang.NullPointerException\n       at java.lang.Throwable.\u003cinit\u003e(Throwable.java)\n       at java.lang.Throwable.\u003cinit\u003e(Throwable.java)\n       at java.lang.NullPointerException.\u003cinit\u003e(NullPointerException.java:63)\n       at \norg.eclipse.hyades.trace.sample.loganalyzer.LogAnalyzerCreationWizard.analyzeErr\norLog(LogAnalyzerCreationWizard.java:179)\n       at \norg.eclipse.hyades.trace.sample.loganalyzer.LogAnalyzerCreationWizard.performFin\nish(LogAnalyzerCreationWizard.java:261)\n       at org.eclipse.jface.wizard.WizardDialog.finishPressed\n(WizardDialog.java:608)\n       at org.eclipse.jface.wizard.WizardDialog.buttonPressed\n(WizardDialog.java:321)\n       at org.eclipse.jface.dialogs.Dialog$1.widgetSelected(Dialog.java:423)\n       at org.eclipse.swt.widgets.TypedListener.handleEvent\n(TypedListener.java:89)\n       at org.eclipse.swt.widgets.EventTable.sendEvent(EventTable.java)\n       at org.eclipse.swt.widgets.Widget.sendEvent(Widget.java)\n       at org.eclipse.swt.widgets.Display.runDeferredEvents(Display.java)\n       at org.eclipse.swt.widgets.Display.readAndDispatch(Display.java)\n       at org.eclipse.jface.window.Window.runEventLoop(Window.java:583)\n       at org.eclipse.jface.window.Window.open(Window.java:563)\n       at org.eclipse.ui.actions.NewExampleAction.run(NewExampleAction.java:121)\n       at org.eclipse.jface.action.Action.runWithEvent(Action.java:842)\n       at org.eclipse.jface.action.ActionContributionItem.handleWidgetSelection\n(ActionContributionItem.java:456)\n       at org.eclipse.jface.action.ActionContributionItem.handleWidgetEvent\n(ActionContributionItem.java:403)\n       at org.eclipse.jface.action.ActionContributionItem.access$0\n(ActionContributionItem.java:397)\n       at \norg.eclipse.jface.action.ActionContributionItem$ActionListener.handleEvent\n(ActionContributionItem.java:72)\n       at org.eclipse.swt.widgets.EventTable.sendEvent(EventTable.java)\n       at org.eclipse.swt.widgets.Widget.sendEvent(Widget.java:840)\n       at org.eclipse.swt.widgets.Display.runDeferredEvents(Display.java:2021)\n       at org.eclipse.swt.widgets.Display.readAndDispatch(Display.java:1728)\n       at org.eclipse.ui.internal.Workbench.runEventLoop(Workbench.java:1402)\n       at org.eclipse.ui.internal.Workbench.run(Workbench.java:1385)\n       at org.eclipse.core.internal.boot.InternalBootLoader.run\n(InternalBootLoader.java:858)\n       at org.eclipse.core.boot.BootLoader.run(BootLoader.java:461)\n       at java.lang.reflect.AccessibleObject.invokeL(AccessibleObject.java:207)\n       at java.lang.reflect.Method.invoke(Method.java:271)\n       at org.eclipse.core.launcher.Main.basicRun(Main.java:291)\n       at org.eclipse.core.launcher.Main.run(Main.java:747)\n       at org.eclipse.core.launcher.Main.main(Main.java:583)\n\n\nSteps to reproduce:\n\nAuthor: Paul Slauenwhite\nDate: 07/07/2003\nPurpose: To test the Apache Log Correlation/Analyzer example.\nTest Steps:\n1) Open the \u0027New Example\u0027 dialog (File \u003e\u003e New \u003e\u003e Example...).\n2) Verify the \u0027Apache Log Correlation/Analyzer Sample\u0027 entry is visible on the \nright when the \u0027Hyades Logging\u0027 entry is selected on the right is selected.\n3) Verify the description at the top of the \u0027New Example\u0027 dialog accurately \ndescribes the Apache Log Correlation/Analyzer example.\n4) Click \u0027Next\u0027.\n5) Verify the description at the top of the \u0027Log Analyzer and Correlation \nSample Project\u0027 dialog accurately describes the pane\u0027s function.\n6) Click \u0027Next\u0027.\n7) Verify the description at the top of the \u0027Log Analyzer and Correlation \nSample Options\u0027 dialog accurately describes the pane\u0027s function.\n8) Click \u0027Finish\u0027.\n9) Verify the project specified in the \u0027Log Analyzer and Correlation Sample \nProject\u0027 dialog is created in the Profiling perspective with the following \nfiles:\n\n-readme.html\n-access.log\n-error.log\n-symptomdb.trcdbxmi\n\n10) Verify the \u0027Working with the Apache Log Correlation/Analyzer Sample\u0027 readme \nappears in the web browser.\n11) Read the entire \u0027Working with the Apache Log Correlation/Analyzer Sample\u0027 \nreadme.\n12) Execute each of the steps and verify that the outcome is correct.\n13) Close and reopen the workbench and verify the project structure as \nspecified in step 9 is correct.\n14) Redo steps 1 - 10 except selecting a alternative \u0027Project name\u0027 after step \n4.  Verify the remaining steps are completed successfully.\n15) Redo steps 1 - 10 except deselect the \u0027Use default\u0027 check box and select an \nalternative directory after step 4.  Verify the remaining steps are completed \nsuccessfully.\n\nNote the exception in the .log file.\n\n    \u003cNote by paules (Paul Slauenwhite), 2003/09/23 07:17:20, seq: 2 rel: 0  \naction: modify\u003e\nOld Target:  \nNew Target:  AC-1.2\n\n\n\n    \u003cNote by popescu (Valentina Popescu), 2003/10/06 08:04:13, seq: 3 rel: 0  \naction: assign\u003e\nOld Owner: sleeloy\nNew Owner: cmaier\n\n\n\n    \u003cNote by cmaier (Cindy Maier), 2003/10/06 12:44:31, seq: 4 rel: 0  action: \nreturn\u003e\nI cannot reproduce the error using the 20031001_1306 AC_ship.zip file.\n\n    \u003cNote by paules (Paul Slauenwhite), 2003/10/06 14:31:40, seq: 5 rel: 0  \naction: reopen\u003e\nThe defect was reproduced using the 20031001_1306 AC-Ship.zip driver.  Try \nusing a directory with spaces in the\npath (e.g. Desktop) since it cannot be reproduced with a directory without \nspaces.  Also, try root directory as well.\n\nThe follow (new) exception was generated:\n\norg.eclipse.core.internal.resources.ResourceException: Invalid project \ndescription.\n       at org.eclipse.core.internal.resources.Project.checkDescription\n(Project.java:131)\n       at org.eclipse.core.internal.resources.Project.create(Project.java:220)\n       at \norg.eclipse.hyades.ui.internal.wizard.exampleproject.CreationOperation.configNew\nProject(CreationOperation.java:207)\n       at \norg.eclipse.hyades.ui.internal.wizard.exampleproject.CreationOperation.createPro\nject(CreationOperation.java:150)\n       at \norg.eclipse.hyades.ui.internal.wizard.exampleproject.CreationOperation.run\n(CreationOperation.java:110)\n       at org.eclipse.ui.actions.WorkspaceModifyDelegatingOperation.execute\n(WorkspaceModifyDelegatingOperation.java:45)\n       at org.eclipse.ui.actions.WorkspaceModifyOperation$1.run\n(WorkspaceModifyOperation.java:71)\n       at org.eclipse.core.internal.resources.Workspace.run(Workspace.java:1595)\n       at org.eclipse.ui.actions.WorkspaceModifyOperation.run\n(WorkspaceModifyOperation.java:85)\n       at org.eclipse.jface.operation.ModalContext.runInCurrentThread\n(ModalContext.java:302)\n       at org.eclipse.jface.operation.ModalContext.run(ModalContext.java:252)\n       at org.eclipse.jface.wizard.WizardDialog.run(WizardDialog.java:758)\n       at \norg.eclipse.hyades.ui.internal.wizard.exampleproject.CreationWizard.performFinis\nh(CreationWizard.java:384)\n       at org.eclipse.jface.wizard.WizardDialog.finishPressed\n(WizardDialog.java:608)\n       at org.eclipse.jface.wizard.WizardDialog.buttonPressed\n(WizardDialog.java:321)\n       at org.eclipse.jface.dialogs.Dialog$1.widgetSelected(Dialog.java:423)\n       at org.eclipse.swt.widgets.TypedListener.handleEvent\n(TypedListener.java:89)\n       at org.eclipse.swt.widgets.Display.runDeferredEvents(Display.java\n(Compiled Code))\n       at org.eclipse.swt.widgets.Display.readAndDispatch(Display.java(Compiled \nCode))\n       at org.eclipse.jface.window.Window.runEventLoop(Window.java(Compiled \nCode))\n       at org.eclipse.jface.window.Window.open(Window.java:563)\n       at org.eclipse.ui.actions.NewExampleAction.run(NewExampleAction.java:121)\n       at org.eclipse.jface.action.Action.runWithEvent(Action.java:842)\n       at org.eclipse.jface.action.ActionContributionItem.handleWidgetSelection\n(ActionContributionItem.java:456)\n       at org.eclipse.jface.action.ActionContributionItem.handleWidgetEvent\n(ActionContributionItem.java:403)\n       at org.eclipse.jface.action.ActionContributionItem.access$0\n(ActionContributionItem.java:397)\n       at \norg.eclipse.jface.action.ActionContributionItem$ActionListener.handleEvent\n(ActionContributionItem.java:72)\n       at org.eclipse.swt.widgets.EventTable.sendEvent(EventTable.java(Compiled \nCode))\n       at org.eclipse.swt.widgets.Widget.sendEvent(Widget.java:840)\n       at org.eclipse.swt.widgets.Display.runDeferredEvents(Display.java:2021)\n       at org.eclipse.swt.widgets.Display.readAndDispatch(Display.java:1728)\n       at org.eclipse.ui.internal.Workbench.runEventLoop(Workbench.java:1402)\n       at org.eclipse.ui.internal.Workbench.run(Workbench.java:1385)\n       at org.eclipse.core.internal.boot.InternalBootLoader.run\n(InternalBootLoader.java:858)\n       at org.eclipse.core.boot.BootLoader.run(BootLoader.java:461)\n       at java.lang.reflect.Method.invoke(Native Method)\n       at org.eclipse.core.launcher.Main.basicRun(Main.java:291)\n       at org.eclipse.core.launcher.Main.run(Main.java:747)\n       at org.eclipse.core.launcher.Main.main(Main.java:583)\n\n    \u003cNote by cmaier (Cindy Maier), 2003/10/07 11:20:16, seq: 6 rel: 0  action: \nnote\u003e\nOkay.  I see the exception now.  Thanks...\n\n    \u003cNote by popescu (Valentina Popescu), 2003/12/09 12:59:01, seq: 7 rel: 0  \naction: assign\u003e\nOld Owner: cmaier\nNew Owner: znensi",
    "patch dropped to cvs on 15dec,2003 11:47a",
    "patch dropped to cvs on 15dec,2003 11:47a\n",
    "Closing bug.",
    "house keeping"
  ],
  "commentCreationDates": [
    "2003-12-11T17:27:23+01:00",
    "2003-12-15T16:47:33+01:00",
    "2003-12-15T16:49:21+01:00",
    "2004-04-01T17:13:53+02:00",
    "2004-11-03T16:16:13+01:00"
  ],
  "traces": [
    {
      "exceptionType": "java.lang.NullPointerException",
      "elements": [
        {
          "method": "java.lang.Throwable.\u003cinit\u003e",
          "source": "Throwable.java"
        },
        {
          "method": "java.lang.Throwable.\u003cinit\u003e",
          "source": "Throwable.java"
        },
        {
          "method": "java.lang.NullPointerException.\u003cinit\u003e",
          "source": "NullPointerException.java:63"
        },
        {
          "method": "org.eclipse.hyades.trace.sample.loganalyzer.LogAnalyzerCreationWizard.analyzeErrorLog",
          "source": "LogAnalyzerCreationWizard.java:179"
        },
        {
          "method": "org.eclipse.hyades.trace.sample.loganalyzer.LogAnalyzerCreationWizard.performFinish",
          "source": "LogAnalyzerCreationWizard.java:261"
        },
        {
          "method": "org.eclipse.jface.wizard.WizardDialog.finishPressed",
          "source": "WizardDialog.java:608"
        },
        {
          "method": "org.eclipse.jface.wizard.WizardDialog.buttonPressed",
          "source": "WizardDialog.java:321"
        },
        {
          "method": "org.eclipse.jface.dialogs.Dialog$1.widgetSelected",
          "source": "Dialog.java:423"
        },
        {
          "method": "org.eclipse.swt.widgets.TypedListener.handleEvent",
          "source": "TypedListener.java:89"
        },
        {
          "method": "org.eclipse.swt.widgets.EventTable.sendEvent",
          "source": "EventTable.java"
        },
        {
          "method": "org.eclipse.swt.widgets.Widget.sendEvent",
          "source": "Widget.java"
        },
        {
          "method": "org.eclipse.swt.widgets.Display.runDeferredEvents",
          "source": "Display.java"
        },
        {
          "method": "org.eclipse.swt.widgets.Display.readAndDispatch",
          "source": "Display.java"
        },
        {
          "method": "org.eclipse.jface.window.Window.runEventLoop",
          "source": "Window.java:583"
        },
        {
          "method": "org.eclipse.jface.window.Window.open",
          "source": "Window.java:563"
        },
        {
          "method": "org.eclipse.ui.actions.NewExampleAction.run",
          "source": "NewExampleAction.java:121"
        },
        {
          "method": "org.eclipse.jface.action.Action.runWithEvent",
          "source": "Action.java:842"
        },
        {
          "method": "org.eclipse.jface.action.ActionContributionItem.handleWidgetSelection",
          "source": "ActionContributionItem.java:456"
        },
        {
          "method": "org.eclipse.jface.action.ActionContributionItem.handleWidgetEvent",
          "source": "ActionContributionItem.java:403"
        },
        {
          "method": "org.eclipse.jface.action.ActionContributionItem.access$0",
          "source": "ActionContributionItem.java:397"
        },
        {
          "method": "org.eclipse.jface.action.ActionContributionItem$ActionListener.handleEvent",
          "source": "ActionContributionItem.java:72"
        },
        {
          "method": "org.eclipse.swt.widgets.EventTable.sendEvent",
          "source": "EventTable.java"
        },
        {
          "method": "org.eclipse.swt.widgets.Widget.sendEvent",
          "source": "Widget.java:840"
        },
        {
          "method": "org.eclipse.swt.widgets.Display.runDeferredEvents",
          "source": "Display.java:2021"
        },
        {
          "method": "org.eclipse.swt.widgets.Display.readAndDispatch",
          "source": "Display.java:1728"
        },
        {
          "method": "org.eclipse.ui.internal.Workbench.runEventLoop",
          "source": "Workbench.java:1402"
        },
        {
          "method": "org.eclipse.ui.internal.Workbench.run",
          "source": "Workbench.java:1385"
        },
        {
          "method": "org.eclipse.core.internal.boot.InternalBootLoader.run",
          "source": "InternalBootLoader.java:858"
        },
        {
          "method": "org.eclipse.core.boot.BootLoader.run",
          "source": "BootLoader.java:461"
        },
        {
          "method": "java.lang.reflect.AccessibleObject.invokeL",
          "source": "AccessibleObject.java:207"
        },
        {
          "method": "java.lang.reflect.Method.invoke",
          "source": "Method.java:271"
        },
        {
          "method": "org.eclipse.core.launcher.Main.basicRun",
          "source": "Main.java:291"
        },
        {
          "method": "org.eclipse.core.launcher.Main.run",
          "source": "Main.java:747"
        },
        {
          "method": "org.eclipse.core.launcher.Main.main",
          "source": "Main.java:583"
        }
      ],
      "number": 0,
      "commentIndex": 0,
      "bugId": "48506",
      "date": "2003-12-11T17:27:23+01:00",
      "product": "Hyades",
      "component": "UI",
      "severity": "normal"
    },
    {
      "exceptionType": "org.eclipse.core.internal.resources.ResourceException",
      "message": "Invalid project  description.",
      "elements": [
        {
          "method": "org.eclipse.core.internal.resources.Project.checkDescription",
          "source": "Project.java:131"
        },
        {
          "method": "org.eclipse.core.internal.resources.Project.create",
          "source": "Project.java:220"
        },
        {
          "method": "org.eclipse.hyades.ui.internal.wizard.exampleproject.CreationOperation.configNewProject",
          "source": "CreationOperation.java:207"
        },
        {
          "method": "org.eclipse.hyades.ui.internal.wizard.exampleproject.CreationOperation.createProject",
          "source": "CreationOperation.java:150"
        },
        {
          "method": "org.eclipse.hyades.ui.internal.wizard.exampleproject.CreationOperation.run",
          "source": "CreationOperation.java:110"
        },
        {
          "method": "org.eclipse.ui.actions.WorkspaceModifyDelegatingOperation.execute",
          "source": "WorkspaceModifyDelegatingOperation.java:45"
        },
        {
          "method": "org.eclipse.ui.actions.WorkspaceModifyOperation$1.run",
          "source": "WorkspaceModifyOperation.java:71"
        },
        {
          "method": "org.eclipse.core.internal.resources.Workspace.run",
          "source": "Workspace.java:1595"
        },
        {
          "method": "org.eclipse.ui.actions.WorkspaceModifyOperation.run",
          "source": "WorkspaceModifyOperation.java:85"
        },
        {
          "method": "org.eclipse.jface.operation.ModalContext.runInCurrentThread",
          "source": "ModalContext.java:302"
        },
        {
          "method": "org.eclipse.jface.operation.ModalContext.run",
          "source": "ModalContext.java:252"
        },
        {
          "method": "org.eclipse.jface.wizard.WizardDialog.run",
          "source": "WizardDialog.java:758"
        },
        {
          "method": "org.eclipse.hyades.ui.internal.wizard.exampleproject.CreationWizard.performFinish",
          "source": "CreationWizard.java:384"
        },
        {
          "method": "org.eclipse.jface.wizard.WizardDialog.finishPressed",
          "source": "WizardDialog.java:608"
        },
        {
          "method": "org.eclipse.jface.wizard.WizardDialog.buttonPressed",
          "source": "WizardDialog.java:321"
        },
        {
          "method": "org.eclipse.jface.dialogs.Dialog$1.widgetSelected",
          "source": "Dialog.java:423"
        },
        {
          "method": "org.eclipse.swt.widgets.TypedListener.handleEvent",
          "source": "TypedListener.java:89"
        },
        {
          "method": "org.eclipse.swt.widgets.Display.runDeferredEvents",
          "source": "Display.java (Compiled Code)"
        },
        {
          "method": "org.eclipse.swt.widgets.Display.readAndDispatch",
          "source": "Display.java(Compiled  Code)"
        },
        {
          "method": "org.eclipse.jface.window.Window.runEventLoop",
          "source": "Window.java(Compiled  Code)"
        },
        {
          "method": "org.eclipse.jface.window.Window.open",
          "source": "Window.java:563"
        },
        {
          "method": "org.eclipse.ui.actions.NewExampleAction.run",
          "source": "NewExampleAction.java:121"
        },
        {
          "method": "org.eclipse.jface.action.Action.runWithEvent",
          "source": "Action.java:842"
        },
        {
          "method": "org.eclipse.jface.action.ActionContributionItem.handleWidgetSelection",
          "source": "ActionContributionItem.java:456"
        },
        {
          "method": "org.eclipse.jface.action.ActionContributionItem.handleWidgetEvent",
          "source": "ActionContributionItem.java:403"
        },
        {
          "method": "org.eclipse.jface.action.ActionContributionItem.access$0",
          "source": "ActionContributionItem.java:397"
        },
        {
          "method": "org.eclipse.jface.action.ActionContributionItem$ActionListener.handleEvent",
          "source": "ActionContributionItem.java:72"
        },
        {
          "method": "org.eclipse.swt.widgets.EventTable.sendEvent",
          "source": "EventTable.java(Compiled  Code)"
        },
        {
          "method": "org.eclipse.swt.widgets.Widget.sendEvent",
          "source": "Widget.java:840"
        },
        {
          "method": "org.eclipse.swt.widgets.Display.runDeferredEvents",
          "source": "Display.java:2021"
        },
        {
          "method": "org.eclipse.swt.widgets.Display.readAndDispatch",
          "source": "Display.java:1728"
        },
        {
          "method": "org.eclipse.ui.internal.Workbench.runEventLoop",
          "source": "Workbench.java:1402"
        },
        {
          "method": "org.eclipse.ui.internal.Workbench.run",
          "source": "Workbench.java:1385"
        },
        {
          "method": "org.eclipse.core.internal.boot.InternalBootLoader.run",
          "source": "InternalBootLoader.java:858"
        },
        {
          "method": "org.eclipse.core.boot.BootLoader.run",
          "source": "BootLoader.java:461"
        },
        {
          "method": "java.lang.reflect.Method.invoke",
          "source": "Native Method"
        },
        {
          "method": "org.eclipse.core.launcher.Main.basicRun",
          "source": "Main.java:291"
        },
        {
          "method": "org.eclipse.core.launcher.Main.run",
          "source": "Main.java:747"
        },
        {
          "method": "org.eclipse.core.launcher.Main.main",
          "source": "Main.java:583"
        }
      ],
      "number": 1,
      "commentIndex": 0,
      "bugId": "48506",
      "date": "2003-12-11T17:27:23+01:00",
      "product": "Hyades",
      "component": "UI",
      "severity": "normal"
    }
  ],
  "groupId": "48506",
  "bugId": "48506",
  "date": "2003-12-11T17:27:23+01:00",
  "product": "Hyades",
  "component": "UI",
  "severity": "normal"
}