{
  "comments": [
    "Multiple occurrences of the following the in the log.  This occurs on build\nI20031211.\n\n\n!MESSAGE Unhandled event loop exception\n!ENTRY org.eclipse.ui 4 0 Dec 12, 2003 11:23:09.901\n!MESSAGE java.lang.NullPointerException\n!STACK 0\njava.lang.NullPointerException\n        at org.eclipse.swt.custom.StyledText.performPaint(StyledText.java:6084)\n        at org.eclipse.swt.custom.StyledText.handlePaint(StyledText.java:5396)\n        at org.eclipse.swt.custom.StyledText$13.handleEvent(StyledText.java:5095)\n        at org.eclipse.swt.widgets.EventTable.sendEvent(EventTable.java:82)\n        at org.eclipse.swt.widgets.Widget.sendEvent(Widget.java:967)\n        at org.eclipse.swt.widgets.Widget.sendEvent(Widget.java:991)\n        at org.eclipse.swt.widgets.Widget.sendEvent(Widget.java:976)\n        at org.eclipse.swt.widgets.Control.gtk_expose_event(Control.java:1697)\n        at org.eclipse.swt.widgets.Composite.gtk_expose_event(Composite.java:404)\n        at org.eclipse.swt.widgets.Canvas.gtk_expose_event(Canvas.java:105)\n        at org.eclipse.swt.widgets.Widget.windowProc(Widget.java:1224)\n        at org.eclipse.swt.widgets.Display.windowProc(Display.java:2317)\n        at org.eclipse.swt.internal.gtk.OS.gtk_main_do_event(Native Method)\n        at org.eclipse.swt.widgets.Display.eventProc(Display.java:710)\n        at org.eclipse.swt.internal.gtk.OS.gtk_main_iteration(Native Method)\n        at org.eclipse.swt.widgets.Display.readAndDispatch(Display.java:1618)\n        at org.eclipse.ui.internal.Workbench.runEventLoop(Workbench.java:1506)\n        at org.eclipse.ui.internal.Workbench.runUI(Workbench.java:1482)\n        at\norg.eclipse.ui.internal.Workbench.createAndRunWorkbench(Workbench.java:246)\n        at org.eclipse.ui.PlatformUI.createAndRunWorkbench(PlatformUI.java:139)\n        at org.eclipse.ui.internal.ide.IDEApplication.run(IDEApplication.java:47)\n        at\norg.eclipse.core.internal.runtime.PlatformActivator$1.run(PlatformActivator.java:242)\n        at\norg.eclipse.core.runtime.adaptor.EclipseStarter.run(EclipseStarter.java:84)\n        at sun.reflect.NativeMethodAccessorImpl.invoke0(Native Method)\n        at\nsun.reflect.NativeMethodAccessorImpl.invoke(NativeMethodAccessorImpl.java:39)\n        at\nsun.reflect.DelegatingMethodAccessorImpl.invoke(DelegatingMethodAccessorImpl.java:25)\n        at java.lang.reflect.Method.invoke(Method.java:324)\n        at\norg.eclipse.core.internal.boot.OSGiBootLoader.basicRun(OSGiBootLoader.java:239)\n        at\norg.eclipse.core.internal.boot.OSGiBootLoader.run(OSGiBootLoader.java:665)\n        at\norg.eclipse.core.internal.boot.OSGiBootLoader.run(OSGiBootLoader.java:652)\n        at sun.reflect.NativeMethodAccessorImpl.invoke0(Native Method)\n        at\nsun.reflect.NativeMethodAccessorImpl.invoke(NativeMethodAccessorImpl.java:39)\n        at\nsun.reflect.DelegatingMethodAccessorImpl.invoke(DelegatingMethodAccessorImpl.java:25)\n        at java.lang.reflect.Method.invoke(Method.java:324)\n        at org.eclipse.core.launcher.Main.basicRun(Main.java:299)\n        at org.eclipse.core.launcher.Main.run(Main.java:767)\n        at org.eclipse.core.launcher.Main.main(Main.java:601)",
    "I\u0027ve still got this in I200312162000, as well as a NPE in StyledText.getGC()\n[line 3715].  Both seem to indicate the renderer is set to null, which seems to\nmean that the styled text is still processing these methods after it has been\ndisposed.",
    "The StyledText must be getting disposed at some point after the platform calls \nback to Display.windowProc with the Paint event, because once a widget is \ndisposed it is removed from the widget table and therefore should not be able \nto receive any events.\n\nA repeatable case would be very helpful to see what\u0027s happening here.  SN \nsuggests that perhaps a filterEvent listener is disposing it, or another \nthread, or something is running the gtk event loop at a bad time.\n",
    "*** Bug 49468 has been marked as a duplicate of this bug. ***",
    "*** Bug 49936 has been marked as a duplicate of this bug. ***",
    "This was fixed last week, and apparently is behaving well in recent nightly \nbuilds.  Changing to FIXED.\n"
  ],
  "commentCreationDates": [
    "2003-12-12T18:44:41+01:00",
    "2003-12-17T21:48:03+01:00",
    "2003-12-18T18:32:43+01:00",
    "2004-01-06T20:48:53+01:00",
    "2004-01-19T15:20:28+01:00",
    "2004-01-19T15:24:22+01:00"
  ],
  "traces": [
    {
      "exceptionType": "java.lang.NullPointerException",
      "elements": [
        {
          "method": "org.eclipse.swt.custom.StyledText.performPaint",
          "source": "StyledText.java:6084"
        },
        {
          "method": "org.eclipse.swt.custom.StyledText.handlePaint",
          "source": "StyledText.java:5396"
        },
        {
          "method": "org.eclipse.swt.custom.StyledText$13.handleEvent",
          "source": "StyledText.java:5095"
        },
        {
          "method": "org.eclipse.swt.widgets.EventTable.sendEvent",
          "source": "EventTable.java:82"
        },
        {
          "method": "org.eclipse.swt.widgets.Widget.sendEvent",
          "source": "Widget.java:967"
        },
        {
          "method": "org.eclipse.swt.widgets.Widget.sendEvent",
          "source": "Widget.java:991"
        },
        {
          "method": "org.eclipse.swt.widgets.Widget.sendEvent",
          "source": "Widget.java:976"
        },
        {
          "method": "org.eclipse.swt.widgets.Control.gtk_expose_event",
          "source": "Control.java:1697"
        },
        {
          "method": "org.eclipse.swt.widgets.Composite.gtk_expose_event",
          "source": "Composite.java:404"
        },
        {
          "method": "org.eclipse.swt.widgets.Canvas.gtk_expose_event",
          "source": "Canvas.java:105"
        },
        {
          "method": "org.eclipse.swt.widgets.Widget.windowProc",
          "source": "Widget.java:1224"
        },
        {
          "method": "org.eclipse.swt.widgets.Display.windowProc",
          "source": "Display.java:2317"
        },
        {
          "method": "org.eclipse.swt.internal.gtk.OS.gtk_main_do_event",
          "source": "Native Method"
        },
        {
          "method": "org.eclipse.swt.widgets.Display.eventProc",
          "source": "Display.java:710"
        },
        {
          "method": "org.eclipse.swt.internal.gtk.OS.gtk_main_iteration",
          "source": "Native Method"
        },
        {
          "method": "org.eclipse.swt.widgets.Display.readAndDispatch",
          "source": "Display.java:1618"
        },
        {
          "method": "org.eclipse.ui.internal.Workbench.runEventLoop",
          "source": "Workbench.java:1506"
        },
        {
          "method": "org.eclipse.ui.internal.Workbench.runUI",
          "source": "Workbench.java:1482"
        },
        {
          "method": "org.eclipse.ui.internal.Workbench.createAndRunWorkbench",
          "source": "Workbench.java:246"
        },
        {
          "method": "org.eclipse.ui.PlatformUI.createAndRunWorkbench",
          "source": "PlatformUI.java:139"
        },
        {
          "method": "org.eclipse.ui.internal.ide.IDEApplication.run",
          "source": "IDEApplication.java:47"
        },
        {
          "method": "org.eclipse.core.internal.runtime.PlatformActivator$1.run",
          "source": "PlatformActivator.java:242"
        },
        {
          "method": "org.eclipse.core.runtime.adaptor.EclipseStarter.run",
          "source": "EclipseStarter.java:84"
        },
        {
          "method": "sun.reflect.NativeMethodAccessorImpl.invoke0",
          "source": "Native Method"
        },
        {
          "method": "sun.reflect.NativeMethodAccessorImpl.invoke",
          "source": "NativeMethodAccessorImpl.java:39"
        },
        {
          "method": "sun.reflect.DelegatingMethodAccessorImpl.invoke",
          "source": "DelegatingMethodAccessorImpl.java:25"
        },
        {
          "method": "java.lang.reflect.Method.invoke",
          "source": "Method.java:324"
        },
        {
          "method": "org.eclipse.core.internal.boot.OSGiBootLoader.basicRun",
          "source": "OSGiBootLoader.java:239"
        },
        {
          "method": "org.eclipse.core.internal.boot.OSGiBootLoader.run",
          "source": "OSGiBootLoader.java:665"
        },
        {
          "method": "org.eclipse.core.internal.boot.OSGiBootLoader.run",
          "source": "OSGiBootLoader.java:652"
        },
        {
          "method": "sun.reflect.NativeMethodAccessorImpl.invoke0",
          "source": "Native Method"
        },
        {
          "method": "sun.reflect.NativeMethodAccessorImpl.invoke",
          "source": "NativeMethodAccessorImpl.java:39"
        },
        {
          "method": "sun.reflect.DelegatingMethodAccessorImpl.invoke",
          "source": "DelegatingMethodAccessorImpl.java:25"
        },
        {
          "method": "java.lang.reflect.Method.invoke",
          "source": "Method.java:324"
        },
        {
          "method": "org.eclipse.core.launcher.Main.basicRun",
          "source": "Main.java:299"
        },
        {
          "method": "org.eclipse.core.launcher.Main.run",
          "source": "Main.java:767"
        },
        {
          "method": "org.eclipse.core.launcher.Main.main",
          "source": "Main.java:601"
        }
      ],
      "number": 0,
      "commentIndex": 0,
      "bugId": "48653",
      "date": "2003-12-12T18:44:41+01:00",
      "product": "Platform",
      "component": "SWT",
      "severity": "normal"
    }
  ],
  "groupId": "48653",
  "bugId": "48653",
  "date": "2003-12-12T18:44:41+01:00",
  "product": "Platform",
  "component": "SWT",
  "severity": "normal"
}