{
  "comments": [
    "Hi PDE Team\n\nI am trying to debug a plugin within the same Eclipse workbench for testing \npurpose and it seems that the configration file makes the pdelauch looping \nsomewhere. Here is the lof of the runtime-workspace...In the log of the \nworkspace, nothing is logged!!\n\nContext:\nEclipse Platform\n\nVersion: 2.1.2\nBuild id: 200311030802\n\nRegards\n\n !SESSION d?c. 13, 2003 19:14:20.108 -------------------------------------------\n-\njava.version\u003d1.4.1_02\njava.vendor\u003dSun Microsystems Inc.\nBootLoader constants: OS\u003dwin32, ARCH\u003dx86, WS\u003dwin32, NL\u003dfr_FR\nCommand-line arguments: -pdelaunch -dev ,bin -feature org.eclipse.platform -\ndata D:\\Eclipse\\2.1.2\\eclipse\\runtime-workspace -debug file:D:\\Eclipse\\2.1.2\n\\eclipse\\workspace\\.metadata\\.plugins\\org.eclipse.pde.core\\.options -os win32 -\nws win32 -arch x86 -nl fr_FR -configuration \nfile:D:/Eclipse/2.1.2/eclipse/workspace/.metadata/.plugins/org.eclipse.pde.core/\nD__Eclipse_2.1.2_eclipse_runtime-workspace/platform.cfg -install \nfile:D:/Eclipse/2.1.2/eclipse/\n!ENTRY org.eclipse.core.runtime 2 1 d?c. 13, 2003 19:14:20.108\n!MESSAGE Problems encountered loading the plug-in registry.\n!SUBENTRY 1 org.eclipse.core.runtime 2 1 d?c. 13, 2003 19:14:20.108\n!MESSAGE Detected prerequisite loop from \"org.eclipse.swt\" to \"org.eclipse.swt\".\n!SUBENTRY 1 org.eclipse.core.runtime 2 1 d?c. 13, 2003 19:14:20.108\n!MESSAGE Plug-in \"org.eclipse.swt\" was disabled due to missing or disabled \nprerequisite plug-in \"org.eclipse.swt\".\n!SUBENTRY 1 org.eclipse.core.runtime 2 1 d?c. 13, 2003 19:14:20.108\n!MESSAGE Plug-in \"org.eclipse.ui\" was disabled due to missing or disabled \nprerequisite plug-in \"org.eclipse.swt\".\n!SUBENTRY 1 org.eclipse.core.runtime 2 1 d?c. 13, 2003 19:14:20.108\n!MESSAGE Plug-in \"org.eclipse.jdt.junit\" was disabled due to missing or \ndisabled prerequisite plug-in \"org.eclipse.ui\".\n!SUBENTRY 1 org.eclipse.core.runtime 2 1 d?c. 13, 2003 19:14:20.108\n!MESSAGE Unable to satisfy prerequisite constraint from \"org.eclipse.update.ui\" \nto \"org.eclipse.ui\".\n!SUBENTRY 1 org.eclipse.core.runtime 2 1 d?c. 13, 2003 19:14:20.108\n!MESSAGE Unable to satisfy prerequisite constraint from \"org.eclipse.search\" \nto \"org.eclipse.ui\".\n!SUBENTRY 1 org.eclipse.core.runtime 2 1 d?c. 13, 2003 19:14:20.108\n!MESSAGE Plug-in \"org.eclipse.help.ui\" was disabled due to missing or disabled \nprerequisite plug-in \"org.eclipse.search\".\n!SUBENTRY 1 org.eclipse.core.runtime 2 1 d?c. 13, 2003 19:14:20.108\n!MESSAGE Unable to satisfy prerequisite constraint \nfrom \"org.eclipse.pde.runtime\" to \"org.eclipse.ui\".\n!SUBENTRY 1 org.eclipse.core.runtime 2 1 d?c. 13, 2003 19:14:20.108\n!MESSAGE Unable to satisfy prerequisite constraint from \"org.eclipse.debug.ui\" \nto \"org.eclipse.ui\".\n!SUBENTRY 1 org.eclipse.core.runtime 2 1 d?c. 13, 2003 19:14:20.108\n!MESSAGE Plug-in \"org.eclipse.cobol.debug.ui\" was disabled due to missing or \ndisabled prerequisite plug-in \"org.eclipse.debug.ui\".\n!SUBENTRY 1 org.eclipse.core.runtime 2 1 d?c. 13, 2003 19:14:20.108\n!MESSAGE Unable to satisfy prerequisite constraint \nfrom \"org.eclipse.team.cvs.ui\" to \"org.eclipse.ui\".\n!SUBENTRY 1 org.eclipse.core.runtime 2 1 d?c. 13, 2003 19:14:20.108\n!MESSAGE Unable to satisfy prerequisite constraint from \"org.eclipse.pde.ui\" \nto \"org.eclipse.ui\".\n!SUBENTRY 1 org.eclipse.core.runtime 2 1 d?c. 13, 2003 19:14:20.108\n!MESSAGE Unable to satisfy prerequisite constraint \nfrom \"org.eclipse.platform.doc.isv\" to \"org.eclipse.ui\".\n!SUBENTRY 1 org.eclipse.core.runtime 2 1 d?c. 13, 2003 19:14:20.108\n!MESSAGE Unable to satisfy prerequisite constraint from \"org.eclipse.cobol\" \nto \"org.eclipse.ui\".\n!SUBENTRY 1 org.eclipse.core.runtime 2 1 d?c. 13, 2003 19:14:20.108\n!MESSAGE Unable to satisfy prerequisite constraint \nfrom \"org.eclipse.ui.versioncheck\" to \"org.eclipse.swt\".\n!SUBENTRY 1 org.eclipse.core.runtime 2 1 d?c. 13, 2003 19:14:20.108\n!MESSAGE Unable to satisfy prerequisite constraint \nfrom \"org.eclipse.cobol.debug\" to \"org.eclipse.ui\".\n!SUBENTRY 1 org.eclipse.core.runtime 2 1 d?c. 13, 2003 19:14:20.108\n!MESSAGE Unable to satisfy prerequisite constraint from \"org.eclipse.jface\" \nto \"org.eclipse.swt\".\n!SUBENTRY 1 org.eclipse.core.runtime 2 1 d?c. 13, 2003 19:14:20.108\n!MESSAGE Plug-in \"org.eclipse.ui.views\" was disabled due to missing or disabled \nprerequisite plug-in \"org.eclipse.jface\".\n!SUBENTRY 1 org.eclipse.core.runtime 2 1 d?c. 13, 2003 19:14:20.108\n!MESSAGE Unable to satisfy prerequisite constraint \nfrom \"org.eclipse.jface.text\" to \"org.eclipse.swt\".\n!SUBENTRY 1 org.eclipse.core.runtime 2 1 d?c. 13, 2003 19:14:20.108\n!MESSAGE Unable to satisfy prerequisite constraint \nfrom \"org.eclipse.update.ui.forms\" to \"org.eclipse.ui\".\n!SUBENTRY 1 org.eclipse.core.runtime 2 1 d?c. 13, 2003 19:14:20.108\n!MESSAGE Unable to satisfy prerequisite constraint from \"org.eclipse.jdt.ui\" \nto \"org.eclipse.ui\".\n!SUBENTRY 1 org.eclipse.core.runtime 2 1 d?c. 13, 2003 19:14:20.108\n!MESSAGE Unable to satisfy prerequisite constraint \nfrom \"org.eclipse.ui.workbench.texteditor\" to \"org.eclipse.jface\".\n!SUBENTRY 1 org.eclipse.core.runtime 2 1 d?c. 13, 2003 19:14:20.108\n!MESSAGE Unable to satisfy prerequisite constraint from \"org.eclipse.compare\" \nto \"org.eclipse.ui\".\n!SUBENTRY 1 org.eclipse.core.runtime 2 1 d?c. 13, 2003 19:14:20.108\n!MESSAGE Unable to satisfy prerequisite constraint \nfrom \"org.eclipse.cobol.core\" to \"org.eclipse.ui\".\n!SUBENTRY 1 org.eclipse.core.runtime 2 1 d?c. 13, 2003 19:14:20.108\n!MESSAGE Unable to satisfy prerequisite constraint \nfrom \"org.eclipse.ui.workbench\" to \"org.eclipse.jface\".\n!SUBENTRY 1 org.eclipse.core.runtime 2 1 d?c. 13, 2003 19:14:20.108\n!MESSAGE Unable to satisfy prerequisite constraint from \"org.eclipse.cobol.ui\" \nto \"org.eclipse.cobol.debug\".\n!SUBENTRY 1 org.eclipse.core.runtime 2 1 d?c. 13, 2003 19:14:20.108\n!MESSAGE Unable to satisfy prerequisite constraint \nfrom \"org.eclipse.ui.editors\" to \"org.eclipse.ui.views\".\n!SUBENTRY 1 org.eclipse.core.runtime 2 1 d?c. 13, 2003 19:14:20.108\n!MESSAGE Unable to satisfy prerequisite constraint from \"org.eclipse.team.ui\" \nto \"org.eclipse.ui\".\n!SUBENTRY 1 org.eclipse.core.runtime 2 1 d?c. 13, 2003 19:14:20.108\n!MESSAGE Unable to satisfy prerequisite constraint \nfrom \"org.eclipse.jdt.debug.ui\" to \"org.eclipse.ui\".\n!SUBENTRY 1 org.eclipse.core.runtime 2 1 d?c. 13, 2003 19:14:20.108\n!MESSAGE Unable to satisfy prerequisite constraint \nfrom \"org.eclipse.ui.externaltools\" to \"org.eclipse.ui\".\n!SESSION ----------------------------------------------------------------------\n!ENTRY org.eclipse.core.launcher 4 0 d?c. 13, 2003 19:14:20.155\n!MESSAGE Exception launching the Eclipse Platform:\n!STACK\njava.lang.reflect.InvocationTargetException\n\tat sun.reflect.NativeMethodAccessorImpl.invoke0(Native Method)\n\tat sun.reflect.NativeMethodAccessorImpl.invoke\n(NativeMethodAccessorImpl.java:39)\n\tat sun.reflect.DelegatingMethodAccessorImpl.invoke\n(DelegatingMethodAccessorImpl.java:25)\n\tat java.lang.reflect.Method.invoke(Method.java:324)\n\tat org.eclipse.core.launcher.Main.basicRun(Main.java:291)\n\tat org.eclipse.core.launcher.Main.run(Main.java:747)\n\tat org.eclipse.core.launcher.Main.main(Main.java:583)\nCaused by: java.lang.IllegalArgumentException: Application not found: \norg.eclipse.ui.workbench.\n\tat org.eclipse.core.internal.boot.InternalBootLoader.run\n(InternalBootLoader.java:856)\n\tat org.eclipse.core.boot.BootLoader.run(BootLoader.java:461)\n\t... 7 more",
    "It seems to me that your prerequisites are incorrect. You either introduced a \ncycle in your dependencies or miss a plugin.\nCheck your target platform and the prereqs of your plugin.",
    "Hi Pascal\n\nI have made additional tests. First of all, I remove from the Runtime \nworkbench, all fragments and then the pdelaunch was working. After all, I \nfinally find out what was the pertinent fragment that was producing this error.\nI have 3 fragments and only one does not reference the org.eclipse.swt plugin \nand when I add any of the 2 others, the pdelaunch is looping. So, IMO, the \nproblem could be reproduced anytime you add a fragment that references the \norg.eclipse.plugin as mine:\n\u003c?xml version\u003d\"1.0\" encoding\u003d\"UTF-8\"?\u003e\n\u003cfragment\n   id\u003d\"com.pac.iwc.swt\"\n   name\u003d\"com.pac.iwc.swt\"\n   version\u003d\"1.0.0\"\n   plugin-id\u003d\"org.eclipse.swt\"\n   plugin-version\u003d\"2.1.2\"\u003e\n\n   \u003cruntime\u003e\n      \u003clibrary name\u003d\"swt.jar\"\u003e\n         \u003cexport name\u003d\"*\"/\u003e\n         \u003cpackages prefixes\u003d\"org.eclipse.swt.custom\"/\u003e\n      \u003c/library\u003e\n   \u003c/runtime\u003e\n\n   \u003crequires\u003e\n      \u003cimport plugin\u003d\"org.eclipse.swt\" export\u003d\"true\"/\u003e\n   \u003c/requires\u003e\n\n\n\u003c/fragment\u003e\n\n\nRegards\n\nFA",
    "Steps to reproduce:\n- create a fragment for plug-in A\n- also put plug-in A in the \u003crequires\u003e clause in the fragment.xml\n\nWork around: don\u0027t include the plug-in in the requires clause.",
    "Marking as invalid.\n\nYou shouldn\u0027t put the plug-in in the requires clause. A fragment is basically an\naddition to the hosting plug-in.\n\nPresumably you would get the same error if you created a plug-in A and required\nyourself in your plugin.xml."
  ],
  "commentCreationDates": [
    "2003-12-13T18:24:58+01:00",
    "2003-12-15T13:57:51+01:00",
    "2003-12-15T17:09:57+01:00",
    "2003-12-18T18:28:29+01:00",
    "2003-12-18T18:31:18+01:00"
  ],
  "traces": [
    {
      "exceptionType": "java.lang.reflect.InvocationTargetException",
      "elements": [
        {
          "method": "sun.reflect.NativeMethodAccessorImpl.invoke0",
          "source": "Native Method"
        },
        {
          "method": "sun.reflect.NativeMethodAccessorImpl.invoke",
          "source": "NativeMethodAccessorImpl.java:39"
        },
        {
          "method": "sun.reflect.DelegatingMethodAccessorImpl.invoke",
          "source": "DelegatingMethodAccessorImpl.java:25"
        },
        {
          "method": "java.lang.reflect.Method.invoke",
          "source": "Method.java:324"
        },
        {
          "method": "org.eclipse.core.launcher.Main.basicRun",
          "source": "Main.java:291"
        },
        {
          "method": "org.eclipse.core.launcher.Main.run",
          "source": "Main.java:747"
        },
        {
          "method": "org.eclipse.core.launcher.Main.main",
          "source": "Main.java:583"
        }
      ],
      "causedBy": {
        "exceptionType": "java.lang.IllegalArgumentException",
        "message": "Application not found:  org.eclipse.ui.workbench.",
        "elements": [
          {
            "method": "org.eclipse.core.internal.boot.InternalBootLoader.run",
            "source": "InternalBootLoader.java:856"
          },
          {
            "method": "org.eclipse.core.boot.BootLoader.run",
            "source": "BootLoader.java:461"
          }
        ],
        "number": 0,
        "commentIndex": 0
      },
      "number": 0,
      "commentIndex": 0,
      "bugId": "48700",
      "date": "2003-12-13T18:24:58+01:00",
      "product": "Platform",
      "component": "Resources",
      "severity": "normal"
    }
  ],
  "groupId": "48700",
  "bugId": "48700",
  "date": "2003-12-13T18:24:58+01:00",
  "product": "Platform",
  "component": "Resources",
  "severity": "normal"
}