{
  "comments": [
    "A user on EC encountered the following error while loading a plugin.\n\nThe platform was \"Connectix VirtualPC on X\"\n\njava.lang.reflect.InvocationTargetException:\njava.lang.reflect.InvocationTargetException: java.lang.IllegalArgumentException: \nIllegal Load factor: 0.75\n        at java.util.HashMap.\u003cinit\u003e(HashMap.java:142)\n        at java.util.HashMap.\u003cinit\u003e(HashMap.java:168)\n        at org.eclipse.core.internal.plugins.RegistryResolver.resolve(RegistryRe\nsolver.java:684)\n        at org.eclipse.core.runtime.model.PluginRegistryModel.resolve(PluginRegi\nstryModel.java:357)\n        at org.eclipse.core.internal.runtime.InternalPlatform.loadRegistry(Inter\nnalPlatform.java:617)\n        at org.eclipse.core.internal.runtime.InternalPlatform.loaderStartup(Inte\nrnalPlatform.java:526)\n        at java.lang.reflect.Method.invoke(Native Method)\n        at org.eclipse.core.internal.boot.InternalBootLoader.startup(InternalBoo\ntLoader.java:912)\n        at org.eclipse.core.internal.boot.InternalBootLoader.run(InternalBootLoa\nder.java:803)\n        at org.eclipse.core.boot.BootLoader.run(BootLoader.java:285)\n        at java.lang.reflect.Method.invoke(Native Method)\n        at org.eclipse.core.launcher.Main.basicRun(Main.java:151)\n        at org.eclipse.core.launcher.Main.run(Main.java:433)\n        at org.eclipse.core.launcher.Main.main(Main.java:306)",
    "To clarify the OS used, it was Macintosh OS X.",
    "This was a long time ago and we now have more people experimenting with the \nMAC builds and we haven\u0027t seen this since.\n\nThis is an error when doing a \"new HashMap()\" which uses the default values \nfor the load factor.\n\nClosing. Please re-open if this surfaces again."
  ],
  "commentCreationDates": [
    "2001-10-12T16:57:48+02:00",
    "2001-10-12T17:01:51+02:00",
    "2002-05-23T17:14:54+02:00"
  ],
  "traces": [
    {
      "exceptionType": "java.lang.IllegalArgumentException",
      "message": "Illegal Load factor: 0.75",
      "elements": [
        {
          "method": "java.util.HashMap.\u003cinit\u003e",
          "source": "HashMap.java:142"
        },
        {
          "method": "java.util.HashMap.\u003cinit\u003e",
          "source": "HashMap.java:168"
        },
        {
          "method": "org.eclipse.core.internal.plugins.RegistryResolver.resolve",
          "source": "RegistryRe solver.java:684"
        },
        {
          "method": "org.eclipse.core.runtime.model.PluginRegistryModel.resolve",
          "source": "PluginRegi stryModel.java:357"
        },
        {
          "method": "org.eclipse.core.internal.runtime.InternalPlatform.loadRegistry",
          "source": "Inter nalPlatform.java:617"
        },
        {
          "method": "org.eclipse.core.internal.runtime.InternalPlatform.loaderStartup",
          "source": "Inte rnalPlatform.java:526"
        },
        {
          "method": "java.lang.reflect.Method.invoke",
          "source": "Native Method"
        },
        {
          "method": "org.eclipse.core.internal.boot.InternalBootLoader.startup",
          "source": "InternalBoo tLoader.java:912"
        },
        {
          "method": "org.eclipse.core.internal.boot.InternalBootLoader.run",
          "source": "InternalBootLoa der.java:803"
        },
        {
          "method": "org.eclipse.core.boot.BootLoader.run",
          "source": "BootLoader.java:285"
        },
        {
          "method": "java.lang.reflect.Method.invoke",
          "source": "Native Method"
        },
        {
          "method": "org.eclipse.core.launcher.Main.basicRun",
          "source": "Main.java:151"
        },
        {
          "method": "org.eclipse.core.launcher.Main.run",
          "source": "Main.java:433"
        },
        {
          "method": "org.eclipse.core.launcher.Main.main",
          "source": "Main.java:306"
        }
      ],
      "number": 0,
      "commentIndex": 0,
      "bugId": "4930",
      "date": "2001-10-12T16:57:48+02:00",
      "product": "Platform",
      "component": "Resources",
      "severity": "major"
    }
  ],
  "groupId": "4930",
  "bugId": "4930",
  "date": "2001-10-12T16:57:48+02:00",
  "product": "Platform",
  "component": "Resources",
  "severity": "major"
}