{
  "comments": [
    "I hit this problem in trying to weave a 3rd party library (from Oracle) after\n\nmanifest not copied: \u0027META-INF/MANIFEST.MF\u0027 in JAR \u0027D:\\devel\\dl\\toplink10g\\topli\nnk\\jlib\\toplink.jar\u0027\ncan\u0027t find type weblogic.ejb20.interfaces.BeanManager\ncan\u0027t find type javax.ejb.deployment.EntityDescriptor\ncan\u0027t find type org.omg.CosTransactions._SynchronizationImplBase\ncan\u0027t find type com.inprise.vbroker.CORBA.portable.ObjectImpl\ncan\u0027t find type com.inprise.vbroker.CORBA.Object\ncan\u0027t find type com.oracle.server.ejb.persistence.pm.PersistenceManager\ncan\u0027t find type javax.jdo.Transaction\ncan\u0027t find type com.ibm.ivj.ejb.tools.analyzer.EJBean\ncan\u0027t find type javax.jdo.PersistenceManagerFactory\ncan\u0027t find type com.ibm.ivj.ejb.tools.codeGenerator.EJBGenRemoteHome\ncan\u0027t find type javax.xml.bind.Unmarshaller\ncan\u0027t find type com.ibm.ivj.ejb.tools.codeGenerator.EJBGenRemoteEntity\ncan\u0027t find type weblogic.ejb20.persistence.spi.CMPCodeGenerator\ncan\u0027t find type oracle.xml.parser.v2.NSResolver\ncan\u0027t find type weblogic.ejb20.persistence.spi.PersistenceManager\ncan\u0027t find type weblogic.ejb20.persistence.spi.CMPDeployer\ncan\u0027t find type oracle.xml.parser.v2.XMLPrintDriver\ncan\u0027t find type com.ibm.ivj.ejb.tools.deployment.EJBDeploy\ncan\u0027t find type javax.jdo.Extent\ncan\u0027t find type javax.jdo.Query\ncan\u0027t find type com.ibm.ivj.ejb.tools.codeGenerator.EJBGenHomeEntity\ncan\u0027t find type javax.xml.bind.UnmarshallerHandler\ncan\u0027t find type oracle.xml.parser.v2.DocumentBuilder\ncan\u0027t find type javax.xml.bind.Validator\ncan\u0027t find type javax.jdo.PersistenceManager\ncan\u0027t find type com.ibm.ejs.persistence.EJSFinder\ncan\u0027t find type javax.xml.bind.Marshaller\ncan\u0027t find type com.ibm.ejs.persistence.EJSJDBCFinder\ncan\u0027t find type com.ibm.ejs.persistence.EJSJDBCPersister\ncan\u0027t find type weblogic.ejb20.persistence.spi.JarDeployment\ncan\u0027t find type com.ibm.ivj.ejb.tools.codeGenerator.EJBGenPersister\ncan\u0027t find type weblogic.rmi.server.UnicastRemoteObject\ncan\u0027t find type javax.xml.bind.JAXBContext\ncan\u0027t find type com.oracle.server.ejb.persistence.deployment.EntityDescriptor\ntrouble in:\npublic class oracle.toplink.internal.ejb.cmp.oc4j.defaultmapping.SerializedObjec\ntMappingGenerator extends oracle.toplink.internal.ejb.cmp.oc4j.defaultmapping.Di\nrectToFieldMappingGenerator implements ajee.logging.Loggable:\n  public static final org.aspectj.lang.JoinPoint$StaticPart ajc$tjp_0\n  public void \u003cinit\u003e(com.oracle.server.ejb.persistence.deployment.EntityDescript\nor, oracle.toplink.publicinterface.Descriptor, String, String, java.util.Collect\nion, oracle.toplink.internal.ejb.cmp.oc4j.defaultmapping.NamingGenerator):\n                    ALOAD_0     // oracle.toplink.internal.ejb.cmp.oc4j.defaultm\napping.SerializedObjectMappingGenerator this   (line 23)\n                    ALOAD_1     // com.oracle.server.ejb.persistence.deployment.\nEntityDescriptor arg0\n                    ALOAD_2     // oracle.toplink.publicinterface.Descriptor arg\n1\n                    ALOAD_3     // java.lang.String arg2\n                    ALOAD 4     // java.lang.String arg3\n                    ALOAD 5     // java.util.Collection arg4\n                    ALOAD 6     // oracle.toplink.internal.ejb.cmp.oc4j.defaultm\napping.NamingGenerator arg5\n                    INVOKESPECIAL oracle.toplink.internal.ejb.cmp.oc4j.defaultma\npping.DirectToFieldMappingGenerator.\u003cinit\u003e (Lcom/oracle/server/ejb/persistence/d\neployment/EntityDescriptor;Loracle/toplink/publicinterface/Descriptor;Ljava/lang\n/String;Ljava/lang/String;Ljava/util/Collection;Loracle/toplink/internal/ejb/cmp\n/oc4j/defaultmapping/NamingGenerator;)V\n    constructor-execution(void oracle.toplink.internal.ejb.cmp.oc4j.defaultmappi\nng.SerializedObjectMappingGenerator.\u003cinit\u003e(com.oracle.server.ejb.persistence.dep\nloyment.EntityDescriptor, oracle.toplink.publicinterface.Descriptor, java.lang.S\ntring, java.lang.String, java.util.Collection, oracle.toplink.internal.ejb.cmp.o\nc4j.defaultmapping.NamingGenerator))\n    |               RETURN   (line 24)\n    constructor-execution(void oracle.toplink.internal.ejb.cmp.oc4j.defaultmappi\nng.SerializedObjectMappingGenerator.\u003cinit\u003e(com.oracle.server.ejb.persistence.dep\nloyment.EntityDescriptor, oracle.toplink.publicinterface.Descriptor, java.lang.S\ntring, java.lang.String, java.util.Collection, oracle.toplink.internal.ejb.cmp.o\nc4j.defaultmapping.NamingGenerator))\n  end public void \u003cinit\u003e(com.oracle.server.ejb.persistence.deployment.EntityDesc\nriptor, oracle.toplink.publicinterface.Descriptor, String, String, java.util.Col\nlection, oracle.toplink.internal.ejb.cmp.oc4j.defaultmapping.NamingGenerator)\n\n  public void generate():\n    method-execution(void oracle.toplink.internal.ejb.cmp.oc4j.defaultmapping.Se\nrializedObjectMappingGenerator.generate())\n    |               NEW oracle.toplink.mappings.SerializedObjectMapping   (line\n30)\n    |               DUP\n    | constructor-call(void oracle.toplink.mappings.SerializedObjectMapping.\u003cini\nt\u003e())\n    | |             INVOKESPECIAL oracle.toplink.mappings.SerializedObjectMappin\ng.\u003cinit\u003e ()V\n    | constructor-call(void oracle.toplink.mappings.SerializedObjectMapping.\u003cini\nt\u003e())\n    |               ASTORE_1\n    |               ALOAD_1   (line 31)\n    |               ALOAD_0     // oracle.toplink.internal.ejb.cmp.oc4j.defaultm\napping.SerializedObjectMappingGenerator this\n    | field-get(java.lang.String oracle.toplink.internal.ejb.cmp.oc4j.defaultmap\nping.SerializedObjectMappingGenerator.cmpFieldName)\n    | |             GETFIELD oracle.toplink.internal.ejb.cmp.oc4j.defaultmapping\n.SerializedObjectMappingGenerator.cmpFieldName Ljava/lang/String;\n    | field-get(java.lang.String oracle.toplink.internal.ejb.cmp.oc4j.defaultmap\nping.SerializedObjectMappingGenerator.cmpFieldName)\n    | method-call(void oracle.toplink.mappings.SerializedObjectMapping.setAttrib\nuteName(java.lang.String))\n    | |             INVOKEVIRTUAL oracle.toplink.mappings.SerializedObjectMappin\ng.setAttributeName (Ljava/lang/String;)V\n    | method-call(void oracle.toplink.mappings.SerializedObjectMapping.setAttrib\nuteName(java.lang.String))\n    |               ALOAD_1   (line 32)\n    |               ALOAD_0     // oracle.toplink.internal.ejb.cmp.oc4j.defaultm\napping.SerializedObjectMappingGenerator this\n    | field-get(java.lang.String oracle.toplink.internal.ejb.cmp.oc4j.defaultmap\nping.SerializedObjectMappingGenerator.mappedTblFieldName)\n    | |             GETFIELD oracle.toplink.internal.ejb.cmp.oc4j.defaultmapping\n.SerializedObjectMappingGenerator.mappedTblFieldName Ljava/lang/String;\n    | field-get(java.lang.String oracle.toplink.internal.ejb.cmp.oc4j.defaultmap\nping.SerializedObjectMappingGenerator.mappedTblFieldName)\n    | method-call(void oracle.toplink.mappings.SerializedObjectMapping.setFieldN\name(java.lang.String))\n    | |             INVOKEVIRTUAL oracle.toplink.mappings.SerializedObjectMappin\ng.setFieldName (Ljava/lang/String;)V\n    | method-call(void oracle.toplink.mappings.SerializedObjectMapping.setFieldN\name(java.lang.String))\n    |               ALOAD_0     // oracle.toplink.internal.ejb.cmp.oc4j.defaultm\napping.SerializedObjectMappingGenerator this   (line 33)\n    | field-get(oracle.toplink.publicinterface.Descriptor oracle.toplink.interna\nl.ejb.cmp.oc4j.defaultmapping.SerializedObjectMappingGenerator.tlDesc)\n    | |             GETFIELD oracle.toplink.internal.ejb.cmp.oc4j.defaultmapping\n.SerializedObjectMappingGenerator.tlDesc Loracle/toplink/publicinterface/Descrip\ntor;\n    | field-get(oracle.toplink.publicinterface.Descriptor oracle.toplink.interna\nl.ejb.cmp.oc4j.defaultmapping.SerializedObjectMappingGenerator.tlDesc)\n    |               ALOAD_1\n    | method-call(oracle.toplink.mappings.DatabaseMapping oracle.toplink.publici\nnterface.Descriptor.addMapping(oracle.toplink.mappings.DatabaseMapping))\n    | |             INVOKEVIRTUAL oracle.toplink.publicinterface.Descriptor.addM\napping (Loracle/toplink/mappings/DatabaseMapping;)Loracle/toplink/mappings/Datab\naseMapping;\n    | method-call(oracle.toplink.mappings.DatabaseMapping oracle.toplink.publici\nnterface.Descriptor.addMapping(oracle.toplink.mappings.DatabaseMapping))\n    |               POP\n    |               RETURN   (line 34)\n    method-execution(void oracle.toplink.internal.ejb.cmp.oc4j.defaultmapping.Se\nrializedObjectMappingGenerator.generate())\n  end public void generate()\n\nend public class oracle.toplink.internal.ejb.cmp.oc4j.defaultmapping.SerializedO\nbjectMappingGenerator\nABORT\nException thrown from AspectJ 1.1.1\n\nThis might be logged as a bug already -- find current bugs at\n  http://bugs.eclipse.org/bugs/buglist.cgi?product\u003dAspectJ\u0026component\u003dCompiler\n\nBugs for exceptions thrown have titles File:line from the top stack,\ne.g., \"SomeFile.java:243\"\n\nIf you don\u0027t find the exception below in a bug, please add a new bug\nat http://bugs.eclipse.org/bugs/enter_bug.cgi?product\u003dAspectJ\nTo make the bug a priority, please include a test program\nthat can reproduce this exception.\nInvalid method signature: \u003cmissing\u003e\nInvalid method signature: \u003cmissing\u003e\njava.lang.ClassFormatError: Invalid method signature: \u003cmissing\u003e\n        at org.apache.bcel.classfile.Utility.typeOfSignature(Utility.java:1019)\n        at org.apache.bcel.generic.Type.getType(Type.java:159)\n        at org.aspectj.weaver.bcel.BcelWorld.makeBcelType(BcelWorld.java:153)\n        at org.aspectj.weaver.bcel.BcelVar.createCopyFrom(BcelVar.java:64)\n        at org.aspectj.weaver.bcel.BcelShadow.initializeArgVars(BcelShadow.java:\n912)\n        at org.aspectj.weaver.bcel.BcelShadow.getArgVar(BcelShadow.java:761)\n        at org.aspectj.weaver.bcel.BcelShadow.makeArgsObjectArray(BcelShadow.jav\na:854)\n        at org.aspectj.weaver.bcel.BcelShadow.getThisJoinPointBcelVar(BcelShadow\n.java:797)\n        at org.aspectj.weaver.bcel.BcelShadow.getThisJoinPointVar(BcelShadow.jav\na:771)\n        at org.aspectj.weaver.bcel.BcelAdvice.specializeOn(BcelAdvice.java:95)\n        at org.aspectj.weaver.bcel.BcelShadow.prepareForMungers(BcelShadow.java:\n254)\n        at org.aspectj.weaver.Shadow.implement(Shadow.java:312)\n        at org.aspectj.weaver.bcel.BcelClassWeaver.implement(BcelClassWeaver.jav\na:1006)\n        at org.aspectj.weaver.bcel.BcelClassWeaver.weave(BcelClassWeaver.java:29\n9)\n        at org.aspectj.weaver.bcel.BcelClassWeaver.weave(BcelClassWeaver.java:77\n)\n        at org.aspectj.weaver.bcel.BcelWeaver.weave(BcelWeaver.java:417)\n        at org.aspectj.weaver.bcel.BcelWeaver.weave(BcelWeaver.java:390)\n        at org.aspectj.weaver.bcel.BcelWeaver.weave(BcelWeaver.java:327)\n        at org.aspectj.weaver.bcel.BcelWeaver.weave(BcelWeaver.java:268)\n        at org.aspectj.ajdt.internal.core.builder.AjBuildManager.weaveAndGenerat\neClassFiles(AjBuildManager.java:254)\n        at org.aspectj.ajdt.internal.core.builder.AjBuildManager.doBuild(AjBuild\nManager.java:156)\n        at org.aspectj.ajdt.internal.core.builder.AjBuildManager.batchBuild(AjBu\nildManager.java:70)\n        at org.aspectj.ajdt.ajc.AjdtCommand.doCommand(AjdtCommand.java:99)\n        at org.aspectj.ajdt.ajc.AjdtCommand.runCommand(AjdtCommand.java:53)\n        at org.aspectj.tools.ajc.Main.run(Main.java:217)\n        at org.aspectj.tools.ajc.Main.runMain(Main.java:155)\n        at org.aspectj.tools.ajc.Main.main(Main.java:72)\n\n\n1 fail|abort, 34 errors, 1 warning",
    "Marking this as INVALID since I can\u0027t reproduce.  I wish there was a \nNOT_REPRODUCIBLE setting to use instead.  Reopen this if you see it again \nunder 1.2 preferrably with a test case to reproduce.",
    "How can I reopen this bug? I have the same problem with AspectJ 1.2 under Linux.\nIt seems that the compiler needs some infos/dependencies from other classes not\nin the jar file. As a workaround I give the compiler some external jars using\nthe -classpath attribut.\n\nHere is the workaround call:\najc -classpath\njfachwert-bin.jar:libs/lapext.jar:libs/ps-edgextend.jar:libs/beandt.jar:libs/mqs/com.ibm.mq.jar:libs/jdom.jar:/usr/java/aspectj/lib/aspectjrt.jar\n-inpath basis-bin.jar -sourceroots Logging/src -outjar out/log-basis-bin.jar\n"
  ],
  "commentCreationDates": [
    "2003-12-23T17:45:06+01:00",
    "2004-03-18T19:41:33+01:00",
    "2004-07-21T21:07:10+02:00"
  ],
  "traces": [
    {
      "exceptionType": "java.lang.ClassFormatError",
      "message": "Invalid method signature: \u003cmissing\u003e",
      "elements": [
        {
          "method": "org.apache.bcel.classfile.Utility.typeOfSignature",
          "source": "Utility.java:1019"
        },
        {
          "method": "org.apache.bcel.generic.Type.getType",
          "source": "Type.java:159"
        },
        {
          "method": "org.aspectj.weaver.bcel.BcelWorld.makeBcelType",
          "source": "BcelWorld.java:153"
        },
        {
          "method": "org.aspectj.weaver.bcel.BcelVar.createCopyFrom",
          "source": "BcelVar.java:64"
        },
        {
          "method": "org.aspectj.weaver.bcel.BcelShadow.initializeArgVars",
          "source": "BcelShadow.java: 912"
        },
        {
          "method": "org.aspectj.weaver.bcel.BcelShadow.getArgVar",
          "source": "BcelShadow.java:761"
        },
        {
          "method": "org.aspectj.weaver.bcel.BcelShadow.makeArgsObjectArray",
          "source": "BcelShadow.jav a:854"
        },
        {
          "method": "org.aspectj.weaver.bcel.BcelShadow.getThisJoinPointBcelVar",
          "source": "BcelShadow .java:797"
        },
        {
          "method": "org.aspectj.weaver.bcel.BcelShadow.getThisJoinPointVar",
          "source": "BcelShadow.jav a:771"
        },
        {
          "method": "org.aspectj.weaver.bcel.BcelAdvice.specializeOn",
          "source": "BcelAdvice.java:95"
        },
        {
          "method": "org.aspectj.weaver.bcel.BcelShadow.prepareForMungers",
          "source": "BcelShadow.java: 254"
        },
        {
          "method": "org.aspectj.weaver.Shadow.implement",
          "source": "Shadow.java:312"
        },
        {
          "method": "org.aspectj.weaver.bcel.BcelClassWeaver.implement",
          "source": "BcelClassWeaver.jav a:1006"
        },
        {
          "method": "org.aspectj.weaver.bcel.BcelClassWeaver.weave",
          "source": "BcelClassWeaver.java:29 9"
        },
        {
          "method": "org.aspectj.weaver.bcel.BcelClassWeaver.weave",
          "source": "BcelClassWeaver.java:77 "
        },
        {
          "method": "org.aspectj.weaver.bcel.BcelWeaver.weave",
          "source": "BcelWeaver.java:417"
        },
        {
          "method": "org.aspectj.weaver.bcel.BcelWeaver.weave",
          "source": "BcelWeaver.java:390"
        },
        {
          "method": "org.aspectj.weaver.bcel.BcelWeaver.weave",
          "source": "BcelWeaver.java:327"
        },
        {
          "method": "org.aspectj.weaver.bcel.BcelWeaver.weave",
          "source": "BcelWeaver.java:268"
        },
        {
          "method": "org.aspectj.ajdt.internal.core.builder.AjBuildManager.weaveAndGenerateClassFiles",
          "source": "AjBuildManager.java:254"
        },
        {
          "method": "org.aspectj.ajdt.internal.core.builder.AjBuildManager.doBuild",
          "source": "AjBuild Manager.java:156"
        },
        {
          "method": "org.aspectj.ajdt.internal.core.builder.AjBuildManager.batchBuild",
          "source": "AjBu ildManager.java:70"
        },
        {
          "method": "org.aspectj.ajdt.ajc.AjdtCommand.doCommand",
          "source": "AjdtCommand.java:99"
        },
        {
          "method": "org.aspectj.ajdt.ajc.AjdtCommand.runCommand",
          "source": "AjdtCommand.java:53"
        },
        {
          "method": "org.aspectj.tools.ajc.Main.run",
          "source": "Main.java:217"
        },
        {
          "method": "org.aspectj.tools.ajc.Main.runMain",
          "source": "Main.java:155"
        },
        {
          "method": "org.aspectj.tools.ajc.Main.main",
          "source": "Main.java:72"
        }
      ],
      "number": 0,
      "commentIndex": 0,
      "bugId": "49317",
      "date": "2003-12-23T17:45:06+01:00",
      "product": "AspectJ",
      "component": "Compiler",
      "severity": "normal"
    }
  ],
  "groupId": "49317",
  "bugId": "49317",
  "date": "2003-12-23T17:45:06+01:00",
  "product": "AspectJ",
  "component": "Compiler",
  "severity": "normal"
}