{
  "comments": [
    "jdk1.4.2\ngtk2.2.4\n\n# ./eclipse -ws gtk -data /root/workspace/\njava.lang.IllegalArgumentException: Argument not valid\n        at org.eclipse.swt.SWT.error(SWT.java:2316)\n        at org.eclipse.swt.SWT.error(SWT.java:2260)\n        at org.eclipse.swt.graphics.GC.drawImage(GC.java:378)\n        at org.eclipse.swt.graphics.GC.drawImage(GC.java:361)\n        at org.eclipse.swt.custom.CTabFolder.scaleImage(CTabFolder.java:1761)\n        at org.eclipse.swt.custom.CTabFolder.updateArrowBar(CTabFolder.java:1884)\n        at org.eclipse.swt.custom.CTabFolder.setButtonBounds(CTabFolder.java:970)\n        at org.eclipse.swt.custom.CTabFolder.setItemLocation(CTabFolder.java:1045)\n        at org.eclipse.swt.custom.CTabFolder.setItemBounds(CTabFolder.java:1128)\n        at org.eclipse.swt.custom.CTabFolder.onResize(CTabFolder.java:1309)\n        at org.eclipse.swt.custom.CTabFolder.access$2(CTabFolder.java:1302)\n        at org.eclipse.swt.custom.CTabFolder$1.handleEvent(CTabFolder.java:199)\n        at org.eclipse.swt.widgets.EventTable.sendEvent(EventTable.java:81)\n        at org.eclipse.swt.widgets.Widget.sendEvent(Widget.java:923)\n        at org.eclipse.swt.widgets.Widget.sendEvent(Widget.java:948)\n        at org.eclipse.swt.widgets.Widget.sendEvent(Widget.java:932)\n        at org.eclipse.swt.widgets.Widget.notifyListeners(Widget.java:803)\n        at org.eclipse.swt.custom.CTabFolder.resetTabSize(CTabFolder.java:2148)\n        at org.eclipse.swt.custom.CTabFolder.createItem(CTabFolder.java:386)\n        at org.eclipse.swt.custom.CTabItem.\u003cinit\u003e(CTabItem.java:100)\n        at\norg.eclipse.ui.internal.PartTabFolder.createPartTab(PartTabFolder.java:247)\n        at\norg.eclipse.ui.internal.PartTabFolder.createControl(PartTabFolder.java:224)\n        at\norg.eclipse.ui.internal.PartSashContainer.createControl(PartSashContainer.java:192)\n        at\norg.eclipse.ui.internal.PerspectivePresentation.activate(PerspectivePresentation.java:96)\n        at org.eclipse.ui.internal.Perspective.onActivate(Perspective.java:725)\n        at org.eclipse.ui.internal.WorkbenchPage.onActivate(WorkbenchPage.java:1799)\n        at org.eclipse.ui.internal.WorkbenchWindow$7.run(WorkbenchWindow.java:1496)\n        at org.eclipse.swt.custom.BusyIndicator.showWhile(BusyIndicator.java:69)\n        at\norg.eclipse.ui.internal.WorkbenchWindow.setActivePage(WorkbenchWindow.java:1483)\n        at\norg.eclipse.ui.internal.WorkbenchWindow.busyOpenPage(WorkbenchWindow.java:416)\n        at org.eclipse.ui.internal.WorkbenchWindow$6.run(WorkbenchWindow.java:1188)\n        at org.eclipse.swt.custom.BusyIndicator.showWhile(BusyIndicator.java:69)\n        at\norg.eclipse.ui.internal.WorkbenchWindow.openPage(WorkbenchWindow.java:1185)\n        at\norg.eclipse.ui.internal.Workbench.openFirstTimeWindow(Workbench.java:1074)\n        at org.eclipse.ui.internal.Workbench.init(Workbench.java:874)\n        at org.eclipse.ui.internal.Workbench.run(Workbench.java:1373)\n        at\norg.eclipse.core.internal.boot.InternalBootLoader.run(InternalBootLoader.java:858)\n        at org.eclipse.core.boot.BootLoader.run(BootLoader.java:461)\n        at sun.reflect.NativeMethodAccessorImpl.invoke0(Native Method)\n        at\nsun.reflect.NativeMethodAccessorImpl.invoke(NativeMethodAccessorImpl.java:39)\n        at\nsun.reflect.DelegatingMethodAccessorImpl.invoke(DelegatingMethodAccessorImpl.java:25)\n        at java.lang.reflect.Method.invoke(Method.java:324)\n        at org.eclipse.core.launcher.Main.basicRun(Main.java:291)\n        at org.eclipse.core.launcher.Main.run(Main.java:747)\n        at org.eclipse.core.launcher.Main.main(Main.java:583)",
    "RH7.3 is not a supported platform, see \nhttp://www.eclipse.org/eclipse/development/eclipse_project_plan_2_1.html .\n\nIf you see this happen on RH8 or RH9 then please reopen this report, and if \npossible provide reproduceable steps that show the problem.  Thank-you.\n",
    "RH7.3 is not a supported platform"
  ],
  "commentCreationDates": [
    "2003-12-28T06:43:06+01:00",
    "2004-01-05T21:46:57+01:00",
    "2004-01-06T01:42:28+01:00"
  ],
  "traces": [
    {
      "exceptionType": "java.lang.IllegalArgumentException",
      "message": "Argument not valid",
      "elements": [
        {
          "method": "org.eclipse.swt.SWT.error",
          "source": "SWT.java:2316"
        },
        {
          "method": "org.eclipse.swt.SWT.error",
          "source": "SWT.java:2260"
        },
        {
          "method": "org.eclipse.swt.graphics.GC.drawImage",
          "source": "GC.java:378"
        },
        {
          "method": "org.eclipse.swt.graphics.GC.drawImage",
          "source": "GC.java:361"
        },
        {
          "method": "org.eclipse.swt.custom.CTabFolder.scaleImage",
          "source": "CTabFolder.java:1761"
        },
        {
          "method": "org.eclipse.swt.custom.CTabFolder.updateArrowBar",
          "source": "CTabFolder.java:1884"
        },
        {
          "method": "org.eclipse.swt.custom.CTabFolder.setButtonBounds",
          "source": "CTabFolder.java:970"
        },
        {
          "method": "org.eclipse.swt.custom.CTabFolder.setItemLocation",
          "source": "CTabFolder.java:1045"
        },
        {
          "method": "org.eclipse.swt.custom.CTabFolder.setItemBounds",
          "source": "CTabFolder.java:1128"
        },
        {
          "method": "org.eclipse.swt.custom.CTabFolder.onResize",
          "source": "CTabFolder.java:1309"
        },
        {
          "method": "org.eclipse.swt.custom.CTabFolder.access$2",
          "source": "CTabFolder.java:1302"
        },
        {
          "method": "org.eclipse.swt.custom.CTabFolder$1.handleEvent",
          "source": "CTabFolder.java:199"
        },
        {
          "method": "org.eclipse.swt.widgets.EventTable.sendEvent",
          "source": "EventTable.java:81"
        },
        {
          "method": "org.eclipse.swt.widgets.Widget.sendEvent",
          "source": "Widget.java:923"
        },
        {
          "method": "org.eclipse.swt.widgets.Widget.sendEvent",
          "source": "Widget.java:948"
        },
        {
          "method": "org.eclipse.swt.widgets.Widget.sendEvent",
          "source": "Widget.java:932"
        },
        {
          "method": "org.eclipse.swt.widgets.Widget.notifyListeners",
          "source": "Widget.java:803"
        },
        {
          "method": "org.eclipse.swt.custom.CTabFolder.resetTabSize",
          "source": "CTabFolder.java:2148"
        },
        {
          "method": "org.eclipse.swt.custom.CTabFolder.createItem",
          "source": "CTabFolder.java:386"
        },
        {
          "method": "org.eclipse.swt.custom.CTabItem.\u003cinit\u003e",
          "source": "CTabItem.java:100"
        },
        {
          "method": "org.eclipse.ui.internal.PartTabFolder.createPartTab",
          "source": "PartTabFolder.java:247"
        },
        {
          "method": "org.eclipse.ui.internal.PartTabFolder.createControl",
          "source": "PartTabFolder.java:224"
        },
        {
          "method": "org.eclipse.ui.internal.PartSashContainer.createControl",
          "source": "PartSashContainer.java:192"
        },
        {
          "method": "org.eclipse.ui.internal.PerspectivePresentation.activate",
          "source": "PerspectivePresentation.java:96"
        },
        {
          "method": "org.eclipse.ui.internal.Perspective.onActivate",
          "source": "Perspective.java:725"
        },
        {
          "method": "org.eclipse.ui.internal.WorkbenchPage.onActivate",
          "source": "WorkbenchPage.java:1799"
        },
        {
          "method": "org.eclipse.ui.internal.WorkbenchWindow$7.run",
          "source": "WorkbenchWindow.java:1496"
        },
        {
          "method": "org.eclipse.swt.custom.BusyIndicator.showWhile",
          "source": "BusyIndicator.java:69"
        },
        {
          "method": "org.eclipse.ui.internal.WorkbenchWindow.setActivePage",
          "source": "WorkbenchWindow.java:1483"
        },
        {
          "method": "org.eclipse.ui.internal.WorkbenchWindow.busyOpenPage",
          "source": "WorkbenchWindow.java:416"
        },
        {
          "method": "org.eclipse.ui.internal.WorkbenchWindow$6.run",
          "source": "WorkbenchWindow.java:1188"
        },
        {
          "method": "org.eclipse.swt.custom.BusyIndicator.showWhile",
          "source": "BusyIndicator.java:69"
        },
        {
          "method": "org.eclipse.ui.internal.WorkbenchWindow.openPage",
          "source": "WorkbenchWindow.java:1185"
        },
        {
          "method": "org.eclipse.ui.internal.Workbench.openFirstTimeWindow",
          "source": "Workbench.java:1074"
        },
        {
          "method": "org.eclipse.ui.internal.Workbench.init",
          "source": "Workbench.java:874"
        },
        {
          "method": "org.eclipse.ui.internal.Workbench.run",
          "source": "Workbench.java:1373"
        },
        {
          "method": "org.eclipse.core.internal.boot.InternalBootLoader.run",
          "source": "InternalBootLoader.java:858"
        },
        {
          "method": "org.eclipse.core.boot.BootLoader.run",
          "source": "BootLoader.java:461"
        },
        {
          "method": "sun.reflect.NativeMethodAccessorImpl.invoke0",
          "source": "Native Method"
        },
        {
          "method": "sun.reflect.NativeMethodAccessorImpl.invoke",
          "source": "NativeMethodAccessorImpl.java:39"
        },
        {
          "method": "sun.reflect.DelegatingMethodAccessorImpl.invoke",
          "source": "DelegatingMethodAccessorImpl.java:25"
        },
        {
          "method": "java.lang.reflect.Method.invoke",
          "source": "Method.java:324"
        },
        {
          "method": "org.eclipse.core.launcher.Main.basicRun",
          "source": "Main.java:291"
        },
        {
          "method": "org.eclipse.core.launcher.Main.run",
          "source": "Main.java:747"
        },
        {
          "method": "org.eclipse.core.launcher.Main.main",
          "source": "Main.java:583"
        }
      ],
      "number": 0,
      "commentIndex": 0,
      "bugId": "49364",
      "date": "2003-12-28T06:43:06+01:00",
      "product": "Platform",
      "component": "SWT",
      "severity": "normal"
    }
  ],
  "groupId": "49364",
  "bugId": "49364",
  "date": "2003-12-28T06:43:06+01:00",
  "product": "Platform",
  "component": "SWT",
  "severity": "normal"
}