{
  "comments": [
    "!ENTRY org.eclipse.ui 4 0 Dec 28, 2003 11:18:33.934\n!MESSAGE java.lang.NullPointerException\n!STACK 0\njava.lang.NullPointerException\n        at org.eclipse.jdt.internal.ui.preferences.EditTemplateDialog$3.\ntextChanged(EditTemplateDialog.java:405)\n        at org.eclipse.jface.text.TextViewer.updateTextListeners(TextViewer.\njava:1885)\n        at org.eclipse.jface.text.TextViewer.fireRedrawChanged(TextViewer.java:\n3782)\n        at org.eclipse.jface.text.TextViewer.enabledRedrawing(TextViewer.java:\n3836)\n        at org.eclipse.jface.text.TextViewer.setRedraw(TextViewer.java:3888)\n        at org.eclipse.jface.text.DefaultUndoManager$CompoundTextCommand.\nundo(DefaultUndoManager.java:235)\n        at org.eclipse.jface.text.DefaultUndoManager.\ninternalUndo(DefaultUndoManager.java:532)\n        at org.eclipse.jface.text.DefaultUndoManager.undo(DefaultUndoManager.\njava:812)\n        at org.eclipse.jface.text.TextViewer.doOperation(TextViewer.java:2925)\n        at org.eclipse.jface.text.source.SourceViewer.doOperation(SourceViewer.\njava:505)\n        at org.eclipse.jdt.internal.ui.preferences.EditTemplateDialog.\nhandleVerifyKeyPressed(EditTemplateDialog.java:465)\n        at org.eclipse.jdt.internal.ui.preferences.EditTemplateDialog.\naccess$1(EditTemplateDialog.java:450)\n        at org.eclipse.jdt.internal.ui.preferences.EditTemplateDialog$5.\nverifyKey(EditTemplateDialog.java:418)\n        at org.eclipse.jface.text.TextViewer$VerifyKeyListenersManager.\nverifyKey(TextViewer.java:368)\n        at org.eclipse.swt.custom.StyledTextListener.\nhandleEvent(StyledTextListener.java:55)\n        at org.eclipse.swt.widgets.EventTable.sendEvent(EventTable.java:81)\n        at org.eclipse.swt.widgets.Widget.sendEvent(Widget.java:923)\n        at org.eclipse.swt.widgets.Widget.sendEvent(Widget.java:948)\n        at org.eclipse.swt.widgets.Widget.sendEvent(Widget.java:932)\n        at org.eclipse.swt.widgets.Widget.notifyListeners(Widget.java:803)\n        at org.eclipse.swt.custom.StyledText.handleKeyDown(StyledText.java:5231)\n        at org.eclipse.swt.custom.StyledText$8.handleEvent(StyledText.java:4980)\n        at org.eclipse.swt.widgets.EventTable.sendEvent(EventTable.java:81)\n        at org.eclipse.swt.widgets.Widget.sendEvent(Widget.java:923)\n        at org.eclipse.swt.widgets.Display.runDeferredEvents(Display.java:1847)\n        at org.eclipse.swt.widgets.Display.readAndDispatch(Display.java:1639)\n        at org.eclipse.jface.window.Window.runEventLoop(Window.java:583)\n        at org.eclipse.jface.window.Window.open(Window.java:563)\n        at org.eclipse.jdt.internal.ui.preferences.CodeTemplateBlock.\nedit(CodeTemplateBlock.java:345)\n        at org.eclipse.jdt.internal.ui.preferences.CodeTemplateBlock.\ndoButtonPressed(CodeTemplateBlock.java:332)\n        at org.eclipse.jdt.internal.ui.preferences.\nCodeTemplateBlock$CodeTemplateAdapter.customButtonPressed(CodeTemplateBlock.\njava:70)\n        at org.eclipse.jdt.internal.ui.wizards.dialogfields.TreeListDialogField.\nbuttonPressed(TreeListDialogField.java:171)\n        at org.eclipse.jdt.internal.ui.wizards.dialogfields.TreeListDialogField.\ndoButtonSelected(TreeListDialogField.java:386)\n        at org.eclipse.jdt.internal.ui.wizards.dialogfields.TreeListDialogField.\naccess$2(TreeListDialogField.java:382)\n        at org.eclipse.jdt.internal.ui.wizards.dialogfields.\nTreeListDialogField$2.widgetSelected(TreeListDialogField.java:349)\n        at org.eclipse.swt.widgets.TypedListener.handleEvent(TypedListener.java:\n89)\n        at org.eclipse.swt.widgets.EventTable.sendEvent(EventTable.java:81)\n        at org.eclipse.swt.widgets.Widget.sendEvent(Widget.java:923)\n        at org.eclipse.swt.widgets.Display.runDeferredEvents(Display.java:1847)\n        at org.eclipse.swt.widgets.Display.readAndDispatch(Display.java:1639)\n        at org.eclipse.jface.window.Window.runEventLoop(Window.java:583)\n        at org.eclipse.jface.window.Window.open(Window.java:563)\n        at org.eclipse.ui.internal.OpenPreferencesAction.\nrun(OpenPreferencesAction.java:53)\n        at org.eclipse.jface.action.Action.runWithEvent(Action.java:842)\n        at org.eclipse.jface.action.ActionContributionItem.\nhandleWidgetSelection(ActionContributionItem.java:456)\n        at org.eclipse.jface.action.ActionContributionItem.\nhandleWidgetEvent(ActionContributionItem.java:403)\n        at org.eclipse.jface.action.ActionContributionItem.\naccess$000(ActionContributionItem.java:44)\n        at org.eclipse.jface.action.ActionContributionItem$ActionListener.\nhandleEvent(ActionContributionItem.java:72)\n        at org.eclipse.swt.widgets.EventTable.sendEvent(EventTable.java:81)\n        at org.eclipse.swt.widgets.Widget.sendEvent(Widget.java:923)\n        at org.eclipse.swt.widgets.Display.runDeferredEvents(Display.java:1847)\n        at org.eclipse.swt.widgets.Display.readAndDispatch(Display.java:1639)\n        at org.eclipse.ui.internal.Workbench.runEventLoop(Workbench.java:1402)\n        at org.eclipse.ui.internal.Workbench.run(Workbench.java:1385)\n        at org.eclipse.core.internal.boot.InternalBootLoader.\nrun(InternalBootLoader.java:858)\n        at org.eclipse.core.boot.BootLoader.run(BootLoader.java:461)\n        at sun.reflect.NativeMethodAccessorImpl.invoke0(Native Method)\n        at sun.reflect.NativeMethodAccessorImpl.invoke(NativeMethodAccessorImpl.\njava:39)\n        at sun.reflect.DelegatingMethodAccessorImpl.\ninvoke(DelegatingMethodAccessorImpl.java:25)\n        at java.lang.reflect.Method.invoke(Method.java:324)\n        at org.eclipse.core.launcher.Main.basicRun(Main.java:291)\n        at org.eclipse.core.launcher.Main.run(Main.java:747)\n        at org.eclipse.core.launcher.Main.main(Main.java:583)",
    "Created an attachment (id\u003d7297)\nWhole Logfile\n\nEclipse doesn\u0027t start.",
    "verified in 3.0 M6"
  ],
  "commentCreationDates": [
    "2003-12-30T19:10:11+01:00",
    "2003-12-30T19:12:58+01:00",
    "2004-01-05T11:41:33+01:00"
  ],
  "traces": [
    {
      "exceptionType": "java.lang.NullPointerException",
      "elements": [
        {
          "method": "org.eclipse.jdt.internal.ui.preferences.EditTemplateDialog$3.textChanged",
          "source": "EditTemplateDialog.java:405"
        },
        {
          "method": "org.eclipse.jface.text.TextViewer.updateTextListeners",
          "source": "TextViewer. java:1885"
        },
        {
          "method": "org.eclipse.jface.text.TextViewer.fireRedrawChanged",
          "source": "TextViewer.java: 3782"
        },
        {
          "method": "org.eclipse.jface.text.TextViewer.enabledRedrawing",
          "source": "TextViewer.java: 3836"
        },
        {
          "method": "org.eclipse.jface.text.TextViewer.setRedraw",
          "source": "TextViewer.java:3888"
        },
        {
          "method": "org.eclipse.jface.text.DefaultUndoManager$CompoundTextCommand.undo",
          "source": "DefaultUndoManager.java:235"
        },
        {
          "method": "org.eclipse.jface.text.DefaultUndoManager.internalUndo",
          "source": "DefaultUndoManager.java:532"
        },
        {
          "method": "org.eclipse.jface.text.DefaultUndoManager.undo",
          "source": "DefaultUndoManager. java:812"
        },
        {
          "method": "org.eclipse.jface.text.TextViewer.doOperation",
          "source": "TextViewer.java:2925"
        },
        {
          "method": "org.eclipse.jface.text.source.SourceViewer.doOperation",
          "source": "SourceViewer. java:505"
        },
        {
          "method": "org.eclipse.jdt.internal.ui.preferences.EditTemplateDialog.handleVerifyKeyPressed",
          "source": "EditTemplateDialog.java:465"
        },
        {
          "method": "org.eclipse.jdt.internal.ui.preferences.EditTemplateDialog.access$1",
          "source": "EditTemplateDialog.java:450"
        },
        {
          "method": "org.eclipse.jdt.internal.ui.preferences.EditTemplateDialog$5.verifyKey",
          "source": "EditTemplateDialog.java:418"
        },
        {
          "method": "org.eclipse.jface.text.TextViewer$VerifyKeyListenersManager.verifyKey",
          "source": "TextViewer.java:368"
        },
        {
          "method": "org.eclipse.swt.custom.StyledTextListener.handleEvent",
          "source": "StyledTextListener.java:55"
        },
        {
          "method": "org.eclipse.swt.widgets.EventTable.sendEvent",
          "source": "EventTable.java:81"
        },
        {
          "method": "org.eclipse.swt.widgets.Widget.sendEvent",
          "source": "Widget.java:923"
        },
        {
          "method": "org.eclipse.swt.widgets.Widget.sendEvent",
          "source": "Widget.java:948"
        },
        {
          "method": "org.eclipse.swt.widgets.Widget.sendEvent",
          "source": "Widget.java:932"
        },
        {
          "method": "org.eclipse.swt.widgets.Widget.notifyListeners",
          "source": "Widget.java:803"
        },
        {
          "method": "org.eclipse.swt.custom.StyledText.handleKeyDown",
          "source": "StyledText.java:5231"
        },
        {
          "method": "org.eclipse.swt.custom.StyledText$8.handleEvent",
          "source": "StyledText.java:4980"
        },
        {
          "method": "org.eclipse.swt.widgets.EventTable.sendEvent",
          "source": "EventTable.java:81"
        },
        {
          "method": "org.eclipse.swt.widgets.Widget.sendEvent",
          "source": "Widget.java:923"
        },
        {
          "method": "org.eclipse.swt.widgets.Display.runDeferredEvents",
          "source": "Display.java:1847"
        },
        {
          "method": "org.eclipse.swt.widgets.Display.readAndDispatch",
          "source": "Display.java:1639"
        },
        {
          "method": "org.eclipse.jface.window.Window.runEventLoop",
          "source": "Window.java:583"
        },
        {
          "method": "org.eclipse.jface.window.Window.open",
          "source": "Window.java:563"
        },
        {
          "method": "org.eclipse.jdt.internal.ui.preferences.CodeTemplateBlock.edit",
          "source": "CodeTemplateBlock.java:345"
        },
        {
          "method": "org.eclipse.jdt.internal.ui.preferences.CodeTemplateBlock.doButtonPressed",
          "source": "CodeTemplateBlock.java:332"
        },
        {
          "method": "org.eclipse.jdt.internal.ui.preferences.CodeTemplateBlock$CodeTemplateAdapter.customButtonPressed",
          "source": "CodeTemplateBlock. java:70"
        },
        {
          "method": "org.eclipse.jdt.internal.ui.wizards.dialogfields.TreeListDialogField.buttonPressed",
          "source": "TreeListDialogField.java:171"
        },
        {
          "method": "org.eclipse.jdt.internal.ui.wizards.dialogfields.TreeListDialogField.doButtonSelected",
          "source": "TreeListDialogField.java:386"
        },
        {
          "method": "org.eclipse.jdt.internal.ui.wizards.dialogfields.TreeListDialogField.access$2",
          "source": "TreeListDialogField.java:382"
        },
        {
          "method": "org.eclipse.jdt.internal.ui.wizards.dialogfields.TreeListDialogField$2.widgetSelected",
          "source": "TreeListDialogField.java:349"
        },
        {
          "method": "org.eclipse.swt.widgets.TypedListener.handleEvent",
          "source": "TypedListener.java: 89"
        },
        {
          "method": "org.eclipse.swt.widgets.EventTable.sendEvent",
          "source": "EventTable.java:81"
        },
        {
          "method": "org.eclipse.swt.widgets.Widget.sendEvent",
          "source": "Widget.java:923"
        },
        {
          "method": "org.eclipse.swt.widgets.Display.runDeferredEvents",
          "source": "Display.java:1847"
        },
        {
          "method": "org.eclipse.swt.widgets.Display.readAndDispatch",
          "source": "Display.java:1639"
        },
        {
          "method": "org.eclipse.jface.window.Window.runEventLoop",
          "source": "Window.java:583"
        },
        {
          "method": "org.eclipse.jface.window.Window.open",
          "source": "Window.java:563"
        },
        {
          "method": "org.eclipse.ui.internal.OpenPreferencesAction.run",
          "source": "OpenPreferencesAction.java:53"
        },
        {
          "method": "org.eclipse.jface.action.Action.runWithEvent",
          "source": "Action.java:842"
        },
        {
          "method": "org.eclipse.jface.action.ActionContributionItem.handleWidgetSelection",
          "source": "ActionContributionItem.java:456"
        },
        {
          "method": "org.eclipse.jface.action.ActionContributionItem.handleWidgetEvent",
          "source": "ActionContributionItem.java:403"
        },
        {
          "method": "org.eclipse.jface.action.ActionContributionItem.access$000",
          "source": "ActionContributionItem.java:44"
        },
        {
          "method": "org.eclipse.jface.action.ActionContributionItem$ActionListener.handleEvent",
          "source": "ActionContributionItem.java:72"
        },
        {
          "method": "org.eclipse.swt.widgets.EventTable.sendEvent",
          "source": "EventTable.java:81"
        },
        {
          "method": "org.eclipse.swt.widgets.Widget.sendEvent",
          "source": "Widget.java:923"
        },
        {
          "method": "org.eclipse.swt.widgets.Display.runDeferredEvents",
          "source": "Display.java:1847"
        },
        {
          "method": "org.eclipse.swt.widgets.Display.readAndDispatch",
          "source": "Display.java:1639"
        },
        {
          "method": "org.eclipse.ui.internal.Workbench.runEventLoop",
          "source": "Workbench.java:1402"
        },
        {
          "method": "org.eclipse.ui.internal.Workbench.run",
          "source": "Workbench.java:1385"
        },
        {
          "method": "org.eclipse.core.internal.boot.InternalBootLoader.run",
          "source": "InternalBootLoader.java:858"
        },
        {
          "method": "org.eclipse.core.boot.BootLoader.run",
          "source": "BootLoader.java:461"
        },
        {
          "method": "sun.reflect.NativeMethodAccessorImpl.invoke0",
          "source": "Native Method"
        },
        {
          "method": "sun.reflect.NativeMethodAccessorImpl.invoke",
          "source": "NativeMethodAccessorImpl. java:39"
        },
        {
          "method": "sun.reflect.DelegatingMethodAccessorImpl.invoke",
          "source": "DelegatingMethodAccessorImpl.java:25"
        },
        {
          "method": "java.lang.reflect.Method.invoke",
          "source": "Method.java:324"
        },
        {
          "method": "org.eclipse.core.launcher.Main.basicRun",
          "source": "Main.java:291"
        },
        {
          "method": "org.eclipse.core.launcher.Main.run",
          "source": "Main.java:747"
        },
        {
          "method": "org.eclipse.core.launcher.Main.main",
          "source": "Main.java:583"
        }
      ],
      "number": 0,
      "commentIndex": 0,
      "bugId": "49424",
      "date": "2003-12-30T19:10:11+01:00",
      "product": "JDT",
      "component": "Text",
      "severity": "trivial"
    }
  ],
  "groupId": "49424",
  "bugId": "49424",
  "date": "2003-12-30T19:10:11+01:00",
  "product": "JDT",
  "component": "Text",
  "severity": "trivial"
}