{
  "comments": [
    "Eclipse is bombing our several times a day with the \"No More Handles\" message \nas per the trace extract below. I have looked at various postings for similar \nproblems and none seem to offer any kind of solution - They simply say you have \nrun out of operating system handles. If nothing can be done about this and the \nonly solution is to terminate the the eclipse JVM could someone please tell me, \nin simple terms what the shortage is,  so that I can look at correcting it or \nworking around it.   \n\n!ENTRY org.eclipse.ui 4 0 Dec 31, 2003 19:28:15.482\n!MESSAGE No more handles\n!STACK 0\norg.eclipse.swt.SWTError: No more handles\n\tat org.eclipse.swt.SWT.error(SWT.java:2358)\n\tat org.eclipse.swt.SWT.error(SWT.java:2262)\n\tat org.eclipse.swt.graphics.Image.internal_new_GC(Image.java:1756)\n\tat org.eclipse.swt.graphics.GC.\u003cinit\u003e(GC.java:74)\n\tat org.eclipse.swt.widgets.ToolItem.createDisabledImage\n(ToolItem.java:194)\n\tat org.eclipse.swt.widgets.ToolItem.updateImages(ToolItem.java:790)\n\tat org.eclipse.swt.widgets.ToolItem.setEnabled(ToolItem.java:552)\n\tat org.eclipse.jface.action.ActionContributionItem.update\n(ActionContributionItem.java:541)\n\tat org.eclipse.jface.action.ActionContributionItem.act",
    "\"No More Handles\" means that an OS limit on concurrently open resources has \nbeen reached.  This should not happen, especially if you\u0027re using win2000, and \nas a user there isn\u0027t anything you can do about it at runtime.\n\nSo there are probably plug-ins that aren\u0027t freeing their resources when done \nwith them (resources \u003d Images + Fonts + GCs + Colors + Regions).  If you\u0027re \nusing any non-eclipse plugins then I would suspect them first, since there have \nnot been many reports of the base eclipse 2.1.1 running out of handles on \nwin2000.\n\nAs is mentioned in bug 49471, I\u0027m going to do some more resource leak looking \nin the 3.0M6 build.\n\n\n*** This bug has been marked as a duplicate of 49471 ***"
  ],
  "commentCreationDates": [
    "2004-01-01T04:10:48+01:00",
    "2004-01-05T20:07:09+01:00"
  ],
  "traces": [
    {
      "exceptionType": "org.eclipse.swt.SWTError",
      "message": "No more handles",
      "elements": [
        {
          "method": "org.eclipse.swt.SWT.error",
          "source": "SWT.java:2358"
        },
        {
          "method": "org.eclipse.swt.SWT.error",
          "source": "SWT.java:2262"
        },
        {
          "method": "org.eclipse.swt.graphics.Image.internal_new_GC",
          "source": "Image.java:1756"
        },
        {
          "method": "org.eclipse.swt.graphics.GC.\u003cinit\u003e",
          "source": "GC.java:74"
        },
        {
          "method": "org.eclipse.swt.widgets.ToolItem.createDisabledImage",
          "source": "ToolItem.java:194"
        },
        {
          "method": "org.eclipse.swt.widgets.ToolItem.updateImages",
          "source": "ToolItem.java:790"
        },
        {
          "method": "org.eclipse.swt.widgets.ToolItem.setEnabled",
          "source": "ToolItem.java:552"
        },
        {
          "method": "org.eclipse.jface.action.ActionContributionItem.update",
          "source": "ActionContributionItem.java:541"
        }
      ],
      "number": 0,
      "commentIndex": 0,
      "bugId": "49448",
      "duplicateId": "49471",
      "date": "2004-01-01T04:10:48+01:00",
      "product": "Platform",
      "component": "SWT",
      "severity": "major"
    }
  ],
  "groupId": "49471",
  "bugId": "49448",
  "duplicateId": "49471",
  "date": "2004-01-01T04:10:48+01:00",
  "product": "Platform",
  "component": "SWT",
  "severity": "major"
}