{
  "comments": [
    "At some point after opening some files in the editor (after the first file but\nbefore the 10th) A daialog box appears informing of an error and to check the\n.log file.  This (appears) to only happen when opening a file from the Package\nExplorer via a \"double click\" of the mouse.  Opening by right clicking and\nselecting open from the context menu works, even after the error.  After the\nerror double clicking on files from the PAckage Explorer does not open the files\nand simply results in more errors in the .log file.\nThe log file:\n\n!SESSION Jan 04, 2004 08:51:55.427 ---------------------------------------------\njava.fullversion\u003dJ2RE 1.4.1 IBM build cxia321411-20030930 (JIT enabled: jitc)\nBootLoader constants: OS\u003dlinux, ARCH\u003dx86, WS\u003dgtk, NL\u003den_US\nCommand-line arguments: -os linux -ws gtk -arch x86 -vmagrs -Xmx256m\n!ENTRY org.eclipse.core.runtime 4 2 Jan 04, 2004 08:51:55.430\n!MESSAGE Problems occurred when invoking code from plug-in:\n\"org.eclipse.core.runtime\".\n!STACK 0\norg.eclipse.swt.SWTException: Widget is disposed\n        at org.eclipse.swt.SWT.error(SWT.java:2592)\n        at org.eclipse.swt.SWT.error(SWT.java(Inlined Compiled Code))\n        at org.eclipse.swt.widgets.Widget.error(Widget.java(Inlined Compiled Code))\n        at org.eclipse.swt.widgets.Widget.checkWidget(Widget.java(Compiled Code))\n        at org.eclipse.swt.widgets.CoolBar.setLocked(CoolBar.java(Inlined\nCompiled Code))\n        at\norg.eclipse.jface.action.CoolBarManager.update(CoolBarManager.java(Compiled Code))\n        at\norg.eclipse.ui.internal.EditorActionBars.setVisible(EditorActionBars.java:312)\n        at\norg.eclipse.ui.internal.EditorActionBars.setActive(EditorActionBars.java:229)\n        at\norg.eclipse.ui.internal.EditorActionBars.activate(EditorActionBars.java:76)\n        at\norg.eclipse.ui.internal.WorkbenchPage$ActionSwitcher.activateContributions(WorkbenchPage.java:289)\n        at\norg.eclipse.ui.internal.WorkbenchPage$ActionSwitcher.updateActivePart(WorkbenchPage.java:195)\n        at\norg.eclipse.ui.internal.WorkbenchPage.setActivePart(WorkbenchPage.java:2511)\n        at org.eclipse.ui.internal.WorkbenchPage.activate(WorkbenchPage.java:448)\n        at\norg.eclipse.ui.internal.WorkbenchPage.busyOpenEditor(WorkbenchPage.java:2061)\n        at org.eclipse.ui.internal.WorkbenchPage.access$6(WorkbenchPage.java:1990)\n        at org.eclipse.ui.internal.WorkbenchPage$9.run(WorkbenchPage.java:1977)\n        at org.eclipse.swt.custom.BusyIndicator.showWhile(BusyIndicator.java:84)\n        at org.eclipse.ui.internal.WorkbenchPage.openEditor(WorkbenchPage.java:1972)\n        at org.eclipse.ui.ide.IDE.openEditor(IDE.java:265)\n        at\norg.eclipse.jdt.internal.ui.javaeditor.EditorUtility.openInEditor(EditorUtility.java:133)\n        at\norg.eclipse.jdt.internal.ui.javaeditor.EditorUtility.openInEditor(EditorUtility.java:106)\n        at\norg.eclipse.jdt.internal.ui.actions.OpenActionUtil.open(OpenActionUtil.java:49)\n        at org.eclipse.jdt.ui.actions.OpenAction.run(OpenAction.java:158)\n        at org.eclipse.jdt.ui.actions.OpenAction.run(OpenAction.java:147)\n        at\norg.eclipse.jdt.ui.actions.SelectionDispatchAction.dispatchRun(SelectionDispatchAction.java:212)\n        at\norg.eclipse.jdt.ui.actions.SelectionDispatchAction.run(SelectionDispatchAction.java:188)\n        at\norg.eclipse.jdt.internal.ui.packageview.PackageExplorerActionGroup.handleOpen(PackageExplorerActionGroup.java:329)\n        at\norg.eclipse.jdt.internal.ui.packageview.PackageExplorerPart$5.open(PackageExplorerPart.java:326)\n        at\norg.eclipse.jface.viewers.StructuredViewer$2.run(StructuredViewer.java:406)\n        at org.eclipse.core.runtime.Platform.run(Platform.java(Compiled Code))\n        at\norg.eclipse.jface.viewers.StructuredViewer.fireOpen(StructuredViewer.java:404)\n        at\norg.eclipse.jface.viewers.StructuredViewer.handleOpen(StructuredViewer.java:614)\n        at\norg.eclipse.jface.viewers.StructuredViewer$6.handleOpen(StructuredViewer.java:703)\n        at org.eclipse.jface.util.OpenStrategy.fireOpenEvent(OpenStrategy.java:209)\n        at org.eclipse.jface.util.OpenStrategy.access$2(OpenStrategy.java:204)\n        at org.eclipse.jface.util.OpenStrategy$1.handleEvent(OpenStrategy.java:233)\n        at org.eclipse.swt.widgets.EventTable.sendEvent(EventTable.java(Compiled\nCode))\n        at org.eclipse.swt.widgets.Widget.sendEvent(Widget.java:967)\n        at org.eclipse.swt.widgets.Display.runDeferredEvents(Display.java:1845)\n        at org.eclipse.swt.widgets.Display.readAndDispatch(Display.java:1625)\n        at org.eclipse.ui.internal.Workbench.runEventLoop(Workbench.java:1506)\n        at org.eclipse.ui.internal.Workbench.runUI(Workbench.java:1482)\n        at\norg.eclipse.ui.internal.Workbench.createAndRunWorkbench(Workbench.java:246)\n        at org.eclipse.ui.PlatformUI.createAndRunWorkbench(PlatformUI.java:139)\n        at org.eclipse.ui.internal.ide.IDEApplication.run(IDEApplication.java:47)\n        at\norg.eclipse.core.internal.runtime.PlatformActivator$1.run(PlatformActivator.java:226)\n        at\norg.eclipse.core.runtime.adaptor.EclipseStarter.run(EclipseStarter.java:85)\n        at sun.reflect.NativeMethodAccessorImpl.invoke0(Native Method)\n        at\nsun.reflect.NativeMethodAccessorImpl.invoke(NativeMethodAccessorImpl.java:79)\n        at\nsun.reflect.DelegatingMethodAccessorImpl.invoke(DelegatingMethodAccessorImpl.java:41)\n        at java.lang.reflect.Method.invoke(Method.java:386)\n        at org.eclipse.core.launcher.Main.basicRun(Main.java:279)\n        at org.eclipse.core.launcher.Main.run(Main.java:742)\n        at org.eclipse.core.launcher.Main.main(Main.java:581)",
    "I cannot reproduce this with the 3.0M6 build on gtk 2.0.6 or gtk 2.2.1.  Which \neclipse build and gtk version are you using?  And does this happen for you \nconsistently?  If so, are there any preconditions that aren\u0027t in your original \ndescription?  Thanks...\n",
    "I am running GTK 2.2.4 under Fedora.  \nThe Eclipse Build is the M6 (build id 200312182000)\nI start Eclipse with this command:\n/usr/local/eclipse/eclipse -data /home/robert/workspace/ -vmagrs -Xmx256m\n\nI can produce the problem in one of two ways.\n\nThe first and most consistent:\n1) Start Eclipse with no editors open (close all editors before closing Eclipse)\n2) Open any java file\n3) Close that Java file\n4) Reopen that java file.\nResults: SWTException, Widget is disposed\n\nThe secod methdo, less consistent\n1) Start Eclipse with no editors open (close all editors before closing Eclipse)\n2) Open n editors, 5\u003cn\u003c10\nResults: SWTException, Widget is disposed\n\nThe third method, a form of method 2\n1) Leave n editors open (5\u003cn\u003c10), and close eclipse\n2) Start eclipse\n3) Open an additional editor\nResults: SWTException, Widget is disposed",
    "FH please try this with 2.2.4.\n",
    "It works for me too.\nWhich destop manager and theme are you using ?\nWhat \"fedora\" means ?\n",
    "Using gnome as a desktop manager with bluecurve, the default redhat theme and\nfedora is the \"non-enterprise\" falvor distro from redhat\n(http://fedora.redhat.com/).",
    "This error persists in the Integration Build I20040129",
    "Does this problem still happen with Eclipse 3.0 ?",
    "Works for me on Fedora Core 3. Eclipse 3.1 RC2.\nPlease, reopen this problem if it still happen to you.\nNote: Try to update from Fedora Core 1 to something more recent. FC1 is not \ntoo good to run Eclipse."
  ],
  "commentCreationDates": [
    "2004-01-04T17:07:38+01:00",
    "2004-01-05T19:52:06+01:00",
    "2004-01-06T15:50:15+01:00",
    "2004-01-06T21:18:07+01:00",
    "2004-01-06T21:25:54+01:00",
    "2004-01-06T22:49:25+01:00",
    "2004-02-08T20:07:57+01:00",
    "2004-07-05T22:58:39+02:00",
    "2005-06-16T19:36:21+02:00"
  ],
  "traces": [
    {
      "exceptionType": "org.eclipse.swt.SWTException",
      "message": "Widget is disposed",
      "elements": [
        {
          "method": "org.eclipse.swt.SWT.error",
          "source": "SWT.java:2592"
        },
        {
          "method": "org.eclipse.swt.SWT.error",
          "source": "SWT.java(Inlined Compiled Code)"
        },
        {
          "method": "org.eclipse.swt.widgets.Widget.error",
          "source": "Widget.java(Inlined Compiled Code)"
        },
        {
          "method": "org.eclipse.swt.widgets.Widget.checkWidget",
          "source": "Widget.java(Compiled Code)"
        },
        {
          "method": "org.eclipse.swt.widgets.CoolBar.setLocked",
          "source": "CoolBar.java(Inlined Compiled Code)"
        },
        {
          "method": "org.eclipse.jface.action.CoolBarManager.update",
          "source": "CoolBarManager.java(Compiled Code)"
        },
        {
          "method": "org.eclipse.ui.internal.EditorActionBars.setVisible",
          "source": "EditorActionBars.java:312"
        },
        {
          "method": "org.eclipse.ui.internal.EditorActionBars.setActive",
          "source": "EditorActionBars.java:229"
        },
        {
          "method": "org.eclipse.ui.internal.EditorActionBars.activate",
          "source": "EditorActionBars.java:76"
        },
        {
          "method": "org.eclipse.ui.internal.WorkbenchPage$ActionSwitcher.activateContributions",
          "source": "WorkbenchPage.java:289"
        },
        {
          "method": "org.eclipse.ui.internal.WorkbenchPage$ActionSwitcher.updateActivePart",
          "source": "WorkbenchPage.java:195"
        },
        {
          "method": "org.eclipse.ui.internal.WorkbenchPage.setActivePart",
          "source": "WorkbenchPage.java:2511"
        },
        {
          "method": "org.eclipse.ui.internal.WorkbenchPage.activate",
          "source": "WorkbenchPage.java:448"
        },
        {
          "method": "org.eclipse.ui.internal.WorkbenchPage.busyOpenEditor",
          "source": "WorkbenchPage.java:2061"
        },
        {
          "method": "org.eclipse.ui.internal.WorkbenchPage.access$6",
          "source": "WorkbenchPage.java:1990"
        },
        {
          "method": "org.eclipse.ui.internal.WorkbenchPage$9.run",
          "source": "WorkbenchPage.java:1977"
        },
        {
          "method": "org.eclipse.swt.custom.BusyIndicator.showWhile",
          "source": "BusyIndicator.java:84"
        },
        {
          "method": "org.eclipse.ui.internal.WorkbenchPage.openEditor",
          "source": "WorkbenchPage.java:1972"
        },
        {
          "method": "org.eclipse.ui.ide.IDE.openEditor",
          "source": "IDE.java:265"
        },
        {
          "method": "org.eclipse.jdt.internal.ui.javaeditor.EditorUtility.openInEditor",
          "source": "EditorUtility.java:133"
        },
        {
          "method": "org.eclipse.jdt.internal.ui.javaeditor.EditorUtility.openInEditor",
          "source": "EditorUtility.java:106"
        },
        {
          "method": "org.eclipse.jdt.internal.ui.actions.OpenActionUtil.open",
          "source": "OpenActionUtil.java:49"
        },
        {
          "method": "org.eclipse.jdt.ui.actions.OpenAction.run",
          "source": "OpenAction.java:158"
        },
        {
          "method": "org.eclipse.jdt.ui.actions.OpenAction.run",
          "source": "OpenAction.java:147"
        },
        {
          "method": "org.eclipse.jdt.ui.actions.SelectionDispatchAction.dispatchRun",
          "source": "SelectionDispatchAction.java:212"
        },
        {
          "method": "org.eclipse.jdt.ui.actions.SelectionDispatchAction.run",
          "source": "SelectionDispatchAction.java:188"
        },
        {
          "method": "org.eclipse.jdt.internal.ui.packageview.PackageExplorerActionGroup.handleOpen",
          "source": "PackageExplorerActionGroup.java:329"
        },
        {
          "method": "org.eclipse.jdt.internal.ui.packageview.PackageExplorerPart$5.open",
          "source": "PackageExplorerPart.java:326"
        },
        {
          "method": "org.eclipse.jface.viewers.StructuredViewer$2.run",
          "source": "StructuredViewer.java:406"
        },
        {
          "method": "org.eclipse.core.runtime.Platform.run",
          "source": "Platform.java(Compiled Code)"
        },
        {
          "method": "org.eclipse.jface.viewers.StructuredViewer.fireOpen",
          "source": "StructuredViewer.java:404"
        },
        {
          "method": "org.eclipse.jface.viewers.StructuredViewer.handleOpen",
          "source": "StructuredViewer.java:614"
        },
        {
          "method": "org.eclipse.jface.viewers.StructuredViewer$6.handleOpen",
          "source": "StructuredViewer.java:703"
        },
        {
          "method": "org.eclipse.jface.util.OpenStrategy.fireOpenEvent",
          "source": "OpenStrategy.java:209"
        },
        {
          "method": "org.eclipse.jface.util.OpenStrategy.access$2",
          "source": "OpenStrategy.java:204"
        },
        {
          "method": "org.eclipse.jface.util.OpenStrategy$1.handleEvent",
          "source": "OpenStrategy.java:233"
        },
        {
          "method": "org.eclipse.swt.widgets.EventTable.sendEvent",
          "source": "EventTable.java(Compiled Code)"
        },
        {
          "method": "org.eclipse.swt.widgets.Widget.sendEvent",
          "source": "Widget.java:967"
        },
        {
          "method": "org.eclipse.swt.widgets.Display.runDeferredEvents",
          "source": "Display.java:1845"
        },
        {
          "method": "org.eclipse.swt.widgets.Display.readAndDispatch",
          "source": "Display.java:1625"
        },
        {
          "method": "org.eclipse.ui.internal.Workbench.runEventLoop",
          "source": "Workbench.java:1506"
        },
        {
          "method": "org.eclipse.ui.internal.Workbench.runUI",
          "source": "Workbench.java:1482"
        },
        {
          "method": "org.eclipse.ui.internal.Workbench.createAndRunWorkbench",
          "source": "Workbench.java:246"
        },
        {
          "method": "org.eclipse.ui.PlatformUI.createAndRunWorkbench",
          "source": "PlatformUI.java:139"
        },
        {
          "method": "org.eclipse.ui.internal.ide.IDEApplication.run",
          "source": "IDEApplication.java:47"
        },
        {
          "method": "org.eclipse.core.internal.runtime.PlatformActivator$1.run",
          "source": "PlatformActivator.java:226"
        },
        {
          "method": "org.eclipse.core.runtime.adaptor.EclipseStarter.run",
          "source": "EclipseStarter.java:85"
        },
        {
          "method": "sun.reflect.NativeMethodAccessorImpl.invoke0",
          "source": "Native Method"
        },
        {
          "method": "sun.reflect.NativeMethodAccessorImpl.invoke",
          "source": "NativeMethodAccessorImpl.java:79"
        },
        {
          "method": "sun.reflect.DelegatingMethodAccessorImpl.invoke",
          "source": "DelegatingMethodAccessorImpl.java:41"
        },
        {
          "method": "java.lang.reflect.Method.invoke",
          "source": "Method.java:386"
        },
        {
          "method": "org.eclipse.core.launcher.Main.basicRun",
          "source": "Main.java:279"
        },
        {
          "method": "org.eclipse.core.launcher.Main.run",
          "source": "Main.java:742"
        },
        {
          "method": "org.eclipse.core.launcher.Main.main",
          "source": "Main.java:581"
        }
      ],
      "number": 0,
      "commentIndex": 0,
      "bugId": "49501",
      "date": "2004-01-04T17:07:38+01:00",
      "product": "Platform",
      "component": "SWT",
      "severity": "normal"
    }
  ],
  "groupId": "49501",
  "bugId": "49501",
  "date": "2004-01-04T17:07:38+01:00",
  "product": "Platform",
  "component": "SWT",
  "severity": "normal"
}