{
  "comments": [
    "I use Eclipse 3.0M6 and cannot get Eclipse format some Java files (see stack\ntrace below). I was not able to reproduce this bug under Windows.\nI insert a copy of the file that make this happen after the trace.\n\n!SESSION Jan 05, 2004 18:36:58.403 ---------------------------------------------\njava.fullversion\u003dJ2RE 1.4.1 IBM build cxia32141-20030522 (JIT enabled: jitc)\nBootLoader constants: OS\u003dlinux, ARCH\u003dx86, WS\u003dgtk, NL\u003den_US\nCommand-line arguments: -os linux -ws gtk -arch x86\n!ENTRY org.eclipse.ui 4 4 Jan 05, 2004 18:36:58.404\n!MESSAGE Action for command \u0027org.eclipse.jdt.ui.edit.text.java.format\u0027 failed to\nexecute properly.\n!ENTRY org.eclipse.ui 4 0 Jan 05, 2004 18:36:58.406\n!MESSAGE Action for command \u0027org.eclipse.jdt.ui.edit.text.java.format\u0027 failed to\nexecute properly.\n!STACK 0\njava.lang.NullPointerException\n        at java.util.LinkedList$ListItr.previous(LinkedList.java:523)\n        at\norg.eclipse.jdt.internal.ui.text.comment.MultiCommentRegion.markRegion(MultiCommentRegion.java:222)\n        at\norg.eclipse.jdt.internal.ui.text.comment.CommentRegion.format(CommentRegion.java:285)\n        at\norg.eclipse.jdt.internal.ui.text.comment.JavaDocRegion.format(JavaDocRegion.java:194)\n        at\norg.eclipse.jdt.internal.ui.text.comment.CommentFormattingStrategy.format(CommentFormattingStrategy.java:133)\n        at\norg.eclipse.jface.text.formatter.ContentFormatter2.format(ContentFormatter2.java:772)\n        at\norg.eclipse.jface.text.formatter.ContentFormatter2.formatPartitions(ContentFormatter2.java:599)\n        at\norg.eclipse.jface.text.formatter.ContentFormatter2.format(ContentFormatter2.java:489)\n        at\norg.eclipse.jface.text.source.SourceViewer.doOperation(SourceViewer.java:668)\n        at\norg.eclipse.jdt.internal.ui.javaeditor.JavaSourceViewer.doOperation(JavaSourceViewer.java:124)\n        at\norg.eclipse.jdt.internal.ui.javaeditor.CompilationUnitEditor$AdaptedSourceViewer.doOperation(CompilationUnitEditor.java:187)\n        at\norg.eclipse.ui.texteditor.TextOperationAction$1.run(TextOperationAction.java:122)\n        at org.eclipse.swt.custom.BusyIndicator.showWhile(BusyIndicator.java:84)\n        at\norg.eclipse.ui.texteditor.TextOperationAction.run(TextOperationAction.java:120)\n        at org.eclipse.jface.action.Action.runWithEvent(Action.java:842)\n        at\norg.eclipse.ui.internal.commands.ActionHandler.execute(ActionHandler.java:40)\n        at\norg.eclipse.ui.internal.keys.WorkbenchKeyboard.executeCommand(WorkbenchKeyboard.java:390)\n        at\norg.eclipse.ui.internal.keys.WorkbenchKeyboard.press(WorkbenchKeyboard.java:763)\n        at\norg.eclipse.ui.internal.keys.WorkbenchKeyboard.processKeyEvent(WorkbenchKeyboard.java:803)\n        at\norg.eclipse.ui.internal.keys.WorkbenchKeyboard.filterKeySequenceBindings(WorkbenchKeyboard.java:486)\n        at\norg.eclipse.ui.internal.keys.WorkbenchKeyboard.access$0(WorkbenchKeyboard.java:421)\n        at\norg.eclipse.ui.internal.keys.WorkbenchKeyboard$1.handleEvent(WorkbenchKeyboard.java:215)\n        at org.eclipse.swt.widgets.EventTable.sendEvent(EventTable.java(Compiled\nCode))\n        at org.eclipse.swt.widgets.Display.filterEvent(Display.java:817)\n        at org.eclipse.swt.widgets.Widget.sendEvent(Widget.java:966)\n        at org.eclipse.swt.widgets.Widget.sendEvent(Widget.java:991)\n        at org.eclipse.swt.widgets.Widget.sendEvent(Widget.java:976)\n        at org.eclipse.swt.widgets.Control.sendKeyEvent(Control.java:2238)\n        at org.eclipse.swt.widgets.Control.gtk_key_press_event(Control.java:1751)\n        at org.eclipse.swt.widgets.Widget.windowProc(Widget.java:1228)\n        at org.eclipse.swt.widgets.Display.windowProc(Display.java:2323)\n        at org.eclipse.swt.internal.gtk.OS.gtk_main_do_event(Native Method)\n        at org.eclipse.swt.widgets.Display.eventProc(Display.java:710)\n        at org.eclipse.swt.internal.gtk.OS.gtk_main_iteration(Native Method)\n        at org.eclipse.swt.widgets.Display.readAndDispatch(Display.java:1624)\n        at org.eclipse.ui.internal.Workbench.runEventLoop(Workbench.java:1506)\n        at org.eclipse.ui.internal.Workbench.runUI(Workbench.java:1482)\n        at\norg.eclipse.ui.internal.Workbench.createAndRunWorkbench(Workbench.java:246)\n        at org.eclipse.ui.PlatformUI.createAndRunWorkbench(PlatformUI.java:139)\n        at org.eclipse.ui.internal.ide.IDEApplication.run(IDEApplication.java:47)\n        at\norg.eclipse.core.internal.runtime.PlatformActivator$1.run(PlatformActivator.java:226)\n        at\norg.eclipse.core.runtime.adaptor.EclipseStarter.run(EclipseStarter.java:85)\n        at sun.reflect.NativeMethodAccessorImpl.invoke0(Native Method)\n        at\nsun.reflect.NativeMethodAccessorImpl.invoke(NativeMethodAccessorImpl.java:79)\n        at\nsun.reflect.DelegatingMethodAccessorImpl.invoke(DelegatingMethodAccessorImpl.java:41)\n        at java.lang.reflect.Method.invoke(Method.java:371)\n        at org.eclipse.core.launcher.Main.basicRun(Main.java:279)\n        at org.eclipse.core.launcher.Main.run(Main.java:742)\n        at org.eclipse.core.launcher.Main.main(Main.java:581)\n\n\n---------------------------------- BEGIN OF JAVA FILE ------------------------\n/*\n * C-JDBC: Clustered JDBC.\n * Copyright (C) 2002, 2003 French National Institute For Research In Computer\n * Science And Control (INRIA).\n * Contact: c-jdbc@objectweb.org\n * \n * This library is free software; you can redistribute it and/or modify it\n * under the terms of the GNU Lesser General Public License as published by the\n * Free Software Foundation; either version 2.1 of the License, or any later\n * version.\n * \n * This library is distributed in the hope that it will be useful, but WITHOUT\n * ANY WARRANTY; without even the implied warranty of MERCHANTABILITY or\n * FITNESS FOR A PARTICULAR PURPOSE. See the GNU Lesser General Public License\n * for more details.\n * \n * You should have received a copy of the GNU Lesser General Public License\n * along with this library; if not, write to the Free Software Foundation,\n * Inc., 59 Temple Place, Suite 330, Boston, MA 02111-1307 USA.\n *\n * Initial developer(s): Nicolas Modrzyk\n * Contributor(s): \n */\n\npackage org.objectweb.cjdbc.controller.backup;\n\nimport java.util.Hashtable;\n\n/**\n * Class to map useful values for octopus\n * \n * @author \u003ca href\u003d\"mailto:Nicolas.Modrzyk@inrialpes.fr\"\u003eNicolas Modrzyk\u003c/a\u003e\n *\n */\npublic final class OctopusConstants\n{\n static final int FROM_URL \u003d 0;\n static final int DRIVER \u003d 1;\n static final int FULL_NAME \u003d 2;\n static final int PREFIX_URL \u003d 3;\n \n static final String[] HSQL \u003d { \"hsqldb\", \"hsql\",\"HypersonicSQL\", \"jdbc:hsqldb:\" };\n static final String[] CSV \u003d { \"csv\", \"csv\", \"Csv\", \"jdbc:relique:csv:\" };\n \n static final Hashtable TYPES;\n static {\n  TYPES \u003d new Hashtable();\n  TYPES.put(HSQL[0], HSQL);\n  TYPES.put(CSV[0], CSV);\n }\n \n /** Get octopus type.\n  * @param type from url\n  * @return value from hashtable or null\n  */\n public static String getOctopusType(String type)\n {\n  if(type\u003d\u003dnull) return null;\n  return ((String[])TYPES.get(type))[FULL_NAME];\n }\n \n /** Get octopus driver.\n   * @param type from url\n   * @return value from hashtable or null\n   */\n public static String getOctopusDriver(String type)\n {\n  if(type\u003d\u003dnull) return null;\n  return ((String[])TYPES.get(type))[DRIVER];\n }\n \n /** Get Octopus url prefix \n  * @param type from url\n  * @return value from hashtable or null\n  */\n public static String getUrlPrefix(String type)\n {\n  if(type\u003d\u003dnull) return null;\n  return ((String[])TYPES.get(type))[PREFIX_URL];\n }\n\n}\n--------------------------------------- END OF JAVA FILE ----------------------",
    "This is a known bug in your JDK (see Sun\u0027s bug parade)."
  ],
  "commentCreationDates": [
    "2004-01-05T18:07:14+01:00",
    "2004-01-06T08:17:21+01:00"
  ],
  "traces": [
    {
      "exceptionType": "java.lang.NullPointerException",
      "elements": [
        {
          "method": "java.util.LinkedList$ListItr.previous",
          "source": "LinkedList.java:523"
        },
        {
          "method": "org.eclipse.jdt.internal.ui.text.comment.MultiCommentRegion.markRegion",
          "source": "MultiCommentRegion.java:222"
        },
        {
          "method": "org.eclipse.jdt.internal.ui.text.comment.CommentRegion.format",
          "source": "CommentRegion.java:285"
        },
        {
          "method": "org.eclipse.jdt.internal.ui.text.comment.JavaDocRegion.format",
          "source": "JavaDocRegion.java:194"
        },
        {
          "method": "org.eclipse.jdt.internal.ui.text.comment.CommentFormattingStrategy.format",
          "source": "CommentFormattingStrategy.java:133"
        },
        {
          "method": "org.eclipse.jface.text.formatter.ContentFormatter2.format",
          "source": "ContentFormatter2.java:772"
        },
        {
          "method": "org.eclipse.jface.text.formatter.ContentFormatter2.formatPartitions",
          "source": "ContentFormatter2.java:599"
        },
        {
          "method": "org.eclipse.jface.text.formatter.ContentFormatter2.format",
          "source": "ContentFormatter2.java:489"
        },
        {
          "method": "org.eclipse.jface.text.source.SourceViewer.doOperation",
          "source": "SourceViewer.java:668"
        },
        {
          "method": "org.eclipse.jdt.internal.ui.javaeditor.JavaSourceViewer.doOperation",
          "source": "JavaSourceViewer.java:124"
        },
        {
          "method": "org.eclipse.jdt.internal.ui.javaeditor.CompilationUnitEditor$AdaptedSourceViewer.doOperation",
          "source": "CompilationUnitEditor.java:187"
        },
        {
          "method": "org.eclipse.ui.texteditor.TextOperationAction$1.run",
          "source": "TextOperationAction.java:122"
        },
        {
          "method": "org.eclipse.swt.custom.BusyIndicator.showWhile",
          "source": "BusyIndicator.java:84"
        },
        {
          "method": "org.eclipse.ui.texteditor.TextOperationAction.run",
          "source": "TextOperationAction.java:120"
        },
        {
          "method": "org.eclipse.jface.action.Action.runWithEvent",
          "source": "Action.java:842"
        },
        {
          "method": "org.eclipse.ui.internal.commands.ActionHandler.execute",
          "source": "ActionHandler.java:40"
        },
        {
          "method": "org.eclipse.ui.internal.keys.WorkbenchKeyboard.executeCommand",
          "source": "WorkbenchKeyboard.java:390"
        },
        {
          "method": "org.eclipse.ui.internal.keys.WorkbenchKeyboard.press",
          "source": "WorkbenchKeyboard.java:763"
        },
        {
          "method": "org.eclipse.ui.internal.keys.WorkbenchKeyboard.processKeyEvent",
          "source": "WorkbenchKeyboard.java:803"
        },
        {
          "method": "org.eclipse.ui.internal.keys.WorkbenchKeyboard.filterKeySequenceBindings",
          "source": "WorkbenchKeyboard.java:486"
        },
        {
          "method": "org.eclipse.ui.internal.keys.WorkbenchKeyboard.access$0",
          "source": "WorkbenchKeyboard.java:421"
        },
        {
          "method": "org.eclipse.ui.internal.keys.WorkbenchKeyboard$1.handleEvent",
          "source": "WorkbenchKeyboard.java:215"
        },
        {
          "method": "org.eclipse.swt.widgets.EventTable.sendEvent",
          "source": "EventTable.java(Compiled Code)"
        },
        {
          "method": "org.eclipse.swt.widgets.Display.filterEvent",
          "source": "Display.java:817"
        },
        {
          "method": "org.eclipse.swt.widgets.Widget.sendEvent",
          "source": "Widget.java:966"
        },
        {
          "method": "org.eclipse.swt.widgets.Widget.sendEvent",
          "source": "Widget.java:991"
        },
        {
          "method": "org.eclipse.swt.widgets.Widget.sendEvent",
          "source": "Widget.java:976"
        },
        {
          "method": "org.eclipse.swt.widgets.Control.sendKeyEvent",
          "source": "Control.java:2238"
        },
        {
          "method": "org.eclipse.swt.widgets.Control.gtk_key_press_event",
          "source": "Control.java:1751"
        },
        {
          "method": "org.eclipse.swt.widgets.Widget.windowProc",
          "source": "Widget.java:1228"
        },
        {
          "method": "org.eclipse.swt.widgets.Display.windowProc",
          "source": "Display.java:2323"
        },
        {
          "method": "org.eclipse.swt.internal.gtk.OS.gtk_main_do_event",
          "source": "Native Method"
        },
        {
          "method": "org.eclipse.swt.widgets.Display.eventProc",
          "source": "Display.java:710"
        },
        {
          "method": "org.eclipse.swt.internal.gtk.OS.gtk_main_iteration",
          "source": "Native Method"
        },
        {
          "method": "org.eclipse.swt.widgets.Display.readAndDispatch",
          "source": "Display.java:1624"
        },
        {
          "method": "org.eclipse.ui.internal.Workbench.runEventLoop",
          "source": "Workbench.java:1506"
        },
        {
          "method": "org.eclipse.ui.internal.Workbench.runUI",
          "source": "Workbench.java:1482"
        },
        {
          "method": "org.eclipse.ui.internal.Workbench.createAndRunWorkbench",
          "source": "Workbench.java:246"
        },
        {
          "method": "org.eclipse.ui.PlatformUI.createAndRunWorkbench",
          "source": "PlatformUI.java:139"
        },
        {
          "method": "org.eclipse.ui.internal.ide.IDEApplication.run",
          "source": "IDEApplication.java:47"
        },
        {
          "method": "org.eclipse.core.internal.runtime.PlatformActivator$1.run",
          "source": "PlatformActivator.java:226"
        },
        {
          "method": "org.eclipse.core.runtime.adaptor.EclipseStarter.run",
          "source": "EclipseStarter.java:85"
        },
        {
          "method": "sun.reflect.NativeMethodAccessorImpl.invoke0",
          "source": "Native Method"
        },
        {
          "method": "sun.reflect.NativeMethodAccessorImpl.invoke",
          "source": "NativeMethodAccessorImpl.java:79"
        },
        {
          "method": "sun.reflect.DelegatingMethodAccessorImpl.invoke",
          "source": "DelegatingMethodAccessorImpl.java:41"
        },
        {
          "method": "java.lang.reflect.Method.invoke",
          "source": "Method.java:371"
        },
        {
          "method": "org.eclipse.core.launcher.Main.basicRun",
          "source": "Main.java:279"
        },
        {
          "method": "org.eclipse.core.launcher.Main.run",
          "source": "Main.java:742"
        },
        {
          "method": "org.eclipse.core.launcher.Main.main",
          "source": "Main.java:581"
        }
      ],
      "number": 0,
      "commentIndex": 0,
      "bugId": "49538",
      "date": "2004-01-05T18:07:14+01:00",
      "product": "JDT",
      "component": "Text",
      "severity": "major"
    }
  ],
  "groupId": "49538",
  "bugId": "49538",
  "date": "2004-01-05T18:07:14+01:00",
  "product": "JDT",
  "component": "Text",
  "severity": "major"
}