{
  "comments": [
    "I tested this with the embedded browser example. go to page which has a form\nsubmnitted using a javascript submit(). When you try to do it, it won\u0027t work.\nHaven\u0027t tested it with a form submitted without javascript. One guess might be\nthat Mozilla is trying to display dialog if I want to remember the values and\nthis dialog will be displayed.\n\nAlso when the page contains javascript alerts (e.g. window.alert(\"..\")) these\nwill not be displayed.",
    "Also print dialog displayed with window.print() doesn\u0027t work. Sorry I have found\nfew similar bugs to this, but none of them summarizes the problem. The problem\nreally is that SWT doesn\u0027t support when Mozilla wants to display some window\nwhich is causing all kinds of problems.",
    "Miroslav:\nCan you download the latest SWT and Example Plug-Ins - the Example Plug-Ins \n(on the Eclipse download page) includes the SWT examples. In particular, it \ncontains the org.eclipse.swt.examples.browser.BrowserExample.\n\nWhen you run this BrowserExample, does the window.print work? It does for me.\nHow are your other cases doing?\n\nThanks",
    "I have tried it with 3.0M6 on Fedora Core 1 with Mozilla upgraded using RPMs \nfor Fedora Core1 downloadable from mozilla.org. Is there a newer version of \nswt? I am going to try it with the snippet again (I though I already did that).",
    "This is my status. I cannot run build M6 on my installation of Fedora Core 1 \n(an non root) because of following error\n\n!SESSION ----------------------------------------------------------------------\n!ENTRY org.eclipse.core.launcher 4 0 Jan 24, 2004 24:08:28.465\n!MESSAGE Exception launching the Eclipse Platform:\n!STACK\njava.lang.IllegalStateException: Unable to acquire application service\n\tat org.eclipse.core.runtime.adaptor.EclipseStarter.run\n(EclipseStarter.java:84)\n\tat sun.reflect.NativeMethodAccessorImpl.invoke0(Native Method)\n\tat sun.reflect.NativeMethodAccessorImpl.invoke\n(NativeMethodAccessorImpl.java:39)\n\tat sun.reflect.DelegatingMethodAccessorImpl.invoke\n(DelegatingMethodAccessorImpl.java:25)\n\tat java.lang.reflect.Method.invoke(Method.java:324)\n\tat org.eclipse.core.launcher.Main.basicRun(Main.java:279)\n\tat org.eclipse.core.launcher.Main.run(Main.java:742)\n\tat org.eclipse.core.launcher.Main.main(Main.java:581)\n\nTherefore I am still using build M5 for IDE. Our application and sample are \nrunning using 3.0M6 SWT libraries. Therefore I have not tried the plugin but I \nhave compiled and run directly the snippets. \n\n1. The bring up the browser\nYou cannot submit form in this browser. THerefore I open normal mozilla, go to \nmapquest to display some address and then select print link. On the page I get \nis link send to printer which brings the Print dialog. In mozilla it works \nfine. I copy the link to the SWT embedded browser. The page loads but when I \nclick on the Send to printer link, it doesn\u0027t do anything.\n\n2. The render HTML with relative link.\nI modified the link to include onclick\u003d\"window.print();\" When I click on the \nlink the print dialog doesn\u0027t show and I just get the eclipse page.\n\nTherefore it doesn\u0027t work for me.",
    "\n\n*** This bug has been marked as a duplicate of 56981 ***"
  ],
  "commentCreationDates": [
    "2004-01-08T11:25:53+01:00",
    "2004-01-08T14:18:23+01:00",
    "2004-01-23T22:56:33+01:00",
    "2004-01-23T23:01:39+01:00",
    "2004-01-24T06:25:18+01:00",
    "2004-04-02T19:40:51+02:00"
  ],
  "traces": [
    {
      "exceptionType": "java.lang.IllegalStateException",
      "message": "Unable to acquire application service",
      "elements": [
        {
          "method": "org.eclipse.core.runtime.adaptor.EclipseStarter.run",
          "source": "EclipseStarter.java:84"
        },
        {
          "method": "sun.reflect.NativeMethodAccessorImpl.invoke0",
          "source": "Native Method"
        },
        {
          "method": "sun.reflect.NativeMethodAccessorImpl.invoke",
          "source": "NativeMethodAccessorImpl.java:39"
        },
        {
          "method": "sun.reflect.DelegatingMethodAccessorImpl.invoke",
          "source": "DelegatingMethodAccessorImpl.java:25"
        },
        {
          "method": "java.lang.reflect.Method.invoke",
          "source": "Method.java:324"
        },
        {
          "method": "org.eclipse.core.launcher.Main.basicRun",
          "source": "Main.java:279"
        },
        {
          "method": "org.eclipse.core.launcher.Main.run",
          "source": "Main.java:742"
        },
        {
          "method": "org.eclipse.core.launcher.Main.main",
          "source": "Main.java:581"
        }
      ],
      "number": 0,
      "commentIndex": 4,
      "bugId": "49679",
      "duplicateId": "56981",
      "date": "2004-01-24T06:25:18+01:00",
      "product": "Platform",
      "component": "SWT",
      "severity": "normal"
    }
  ],
  "groupId": "56981",
  "bugId": "49679",
  "duplicateId": "56981",
  "date": "2004-01-08T11:25:53+01:00",
  "product": "Platform",
  "component": "SWT",
  "severity": "normal"
}