{
  "comments": [
    "I\u0027m using 3.0 M6\n\nIf you attempt to commit a java project that has a package with \u0027cvs\u0027 as part of the name (ie \norg.eclipse.cvs.core), the commit will fail.  I set up a simple test project with the package:\n\ncom.cvs.test.code\n\nadded a couple of java files, and then did a share project and commit.  Here is the details from the \nlog file:\n\n!MESSAGE A resource already exists on disk /Users/bhunt/Downloads/eclipse/workspace/\nTestJava/src/com/CVS.\n!SUBENTRY 1 org.eclipse.team.cvs.core 4 -6 Jan 16, 2004 10:12:55.974\n!MESSAGE CVS synchronization information could not be found for folder \u0027/TestJava/src/com/cvs/\ntest/code\u0027\n!SUBENTRY 1 org.eclipse.core.resources 4 272 Jan 16, 2004 10:12:55.974\n!MESSAGE A resource already exists on disk /Users/bhunt/Downloads/eclipse/workspace/\nTestJava/src/com/CVS.\n!STACK 1\norg.eclipse.core.internal.resources.ResourceException: A resource already exists on disk /Users/\nbhunt/Downloads/eclipse/workspace/TestJav\na/src/com/CVS.\n        at org.eclipse.core.internal.resources.Folder.assertCreateRequirements(Folder.java:45)\n        at org.eclipse.core.internal.resources.Folder.create(Folder.java:86)\n        at org.eclipse.core.internal.resources.Folder.create(Folder.java:116)\n        at org.eclipse.team.internal.ccvs.core.util.SyncFileWriter$1.run(SyncFileWriter.java:380)\n        at org.eclipse.core.internal.resources.Workspace.run(Workspace.java:1555)\n        at org.eclipse.core.internal.resources.Workspace.run(Workspace.java:1580)\n        at \norg.eclipse.team.internal.ccvs.core.util.SyncFileWriter.createCVSSubdirectory(SyncFileWriter.java:\n378)\n        at \norg.eclipse.team.internal.ccvs.core.util.SyncFileWriter.writeAllResourceSync(SyncFileWriter.java:134)\n        at \norg.eclipse.team.internal.ccvs.core.resources.EclipseSynchronizer.commitCache(EclipseSynchronize\nr.java:950)\n        at \norg.eclipse.team.internal.ccvs.core.resources.EclipseSynchronizer$1.run(EclipseSynchronizer.java:\n523)\n        at org.eclipse.core.internal.resources.Workspace.run(Workspace.java:1555)\n        at \norg.eclipse.team.internal.ccvs.core.resources.EclipseSynchronizer.flush(EclipseSynchronizer.java:\n521)\n        at \norg.eclipse.team.internal.ccvs.core.syncinfo.ReentrantLock$ThreadInfo.flush(ReentrantLock.java:\n179)\n        at \norg.eclipse.team.internal.ccvs.core.syncinfo.ReentrantLock$ThreadInfo.popRule(ReentrantLock.java\n:105)\n        at org.eclipse.team.internal.ccvs.core.syncinfo.ReentrantLock.release(ReentrantLock.java:292)\n        at \norg.eclipse.team.internal.ccvs.core.resources.EclipseSynchronizer.endBatching(EclipseSynchronizer.\njava:507)\n        at \norg.eclipse.team.internal.ccvs.core.resources.EclipseSynchronizer.run(EclipseSynchronizer.java:\n1393)\n        at \norg.eclipse.team.internal.ccvs.ui.subscriber.CVSSubscriberAction$1.run(CVSSubscriberAction.java:\n174)\n        at \norg.eclipse.team.internal.ccvs.ui.operations.CVSNonblockingRunnableContext.run(CVSNonblocking\nRunnableContext.java:47)\n        at \norg.eclipse.team.internal.ccvs.ui.operations.CVSNonblockingRunnableContext$2.runInWorkspace(C\nVSNonblockingRunnableContext.java\n:67)\n        at org.eclipse.core.internal.resources.InternalWorkspaceJob.run(InternalWorkspaceJob.java:37)\n        at org.eclipse.core.internal.jobs.Worker.run(Worker.java:62)\n!ENTRY org.eclipse.core.resources 4 272 Jan 16, 2004 10:12:55.974\n!MESSAGE A resource already exists on disk /Users/bhunt/Downloads/eclipse/workspace/\nTestJava/src/com/CVS.\n\n\nI\u0027m guessing that there is a case-sensitivity issue here.  The net result is that I am unable to \ncommit my production code to CVS.",
    "google knows all and found the following \"fix\" for this problem:\n\nhttp://homepage.mac.com/lgw4/iblog/C675550648/E871090033/\n\nI might try it this weekend if I\u0027m feeling VERY brave.",
    "The Mac file system is not case sensitive (which is a suprise to me but test \nreveal that it is true. I guess the fix you mentioned corrects this) so the \ncreation of the lower case cvs directory interferes with the creation of the \nCVS meta-data directory. You should rename your package. Convention is to use \nccvs as the segment name (at least that\u0027s what we do;-). You should do this \neven if you make your Mac case sensitive as users of other OSes that are \nworking on these packages will have the same problem.\n\n*** This bug has been marked as a duplicate of 12345 ***"
  ],
  "commentCreationDates": [
    "2004-01-16T16:28:20+01:00",
    "2004-01-16T16:44:21+01:00",
    "2004-01-16T16:49:35+01:00"
  ],
  "traces": [
    {
      "exceptionType": "org.eclipse.core.internal.resources.ResourceException",
      "message": "A resource already exists on disk /Users/ bhunt/Downloads/eclipse/workspace/TestJav a/src/com/CVS.",
      "elements": [
        {
          "method": "org.eclipse.core.internal.resources.Folder.assertCreateRequirements",
          "source": "Folder.java:45"
        },
        {
          "method": "org.eclipse.core.internal.resources.Folder.create",
          "source": "Folder.java:86"
        },
        {
          "method": "org.eclipse.core.internal.resources.Folder.create",
          "source": "Folder.java:116"
        },
        {
          "method": "org.eclipse.team.internal.ccvs.core.util.SyncFileWriter$1.run",
          "source": "SyncFileWriter.java:380"
        },
        {
          "method": "org.eclipse.core.internal.resources.Workspace.run",
          "source": "Workspace.java:1555"
        },
        {
          "method": "org.eclipse.core.internal.resources.Workspace.run",
          "source": "Workspace.java:1580"
        },
        {
          "method": "org.eclipse.team.internal.ccvs.core.util.SyncFileWriter.createCVSSubdirectory",
          "source": "SyncFileWriter.java: 378"
        },
        {
          "method": "org.eclipse.team.internal.ccvs.core.util.SyncFileWriter.writeAllResourceSync",
          "source": "SyncFileWriter.java:134"
        },
        {
          "method": "org.eclipse.team.internal.ccvs.core.resources.EclipseSynchronizer.commitCache",
          "source": "EclipseSynchronize r.java:950"
        },
        {
          "method": "org.eclipse.team.internal.ccvs.core.resources.EclipseSynchronizer$1.run",
          "source": "EclipseSynchronizer.java: 523"
        },
        {
          "method": "org.eclipse.core.internal.resources.Workspace.run",
          "source": "Workspace.java:1555"
        },
        {
          "method": "org.eclipse.team.internal.ccvs.core.resources.EclipseSynchronizer.flush",
          "source": "EclipseSynchronizer.java: 521"
        },
        {
          "method": "org.eclipse.team.internal.ccvs.core.syncinfo.ReentrantLock$ThreadInfo.flush",
          "source": "ReentrantLock.java: 179"
        },
        {
          "method": "org.eclipse.team.internal.ccvs.core.syncinfo.ReentrantLock$ThreadInfo.popRule",
          "source": "ReentrantLock.java :105"
        },
        {
          "method": "org.eclipse.team.internal.ccvs.core.syncinfo.ReentrantLock.release",
          "source": "ReentrantLock.java:292"
        },
        {
          "method": "org.eclipse.team.internal.ccvs.core.resources.EclipseSynchronizer.endBatching",
          "source": "EclipseSynchronizer. java:507"
        },
        {
          "method": "org.eclipse.team.internal.ccvs.core.resources.EclipseSynchronizer.run",
          "source": "EclipseSynchronizer.java: 1393"
        },
        {
          "method": "org.eclipse.team.internal.ccvs.ui.subscriber.CVSSubscriberAction$1.run",
          "source": "CVSSubscriberAction.java: 174"
        },
        {
          "method": "org.eclipse.team.internal.ccvs.ui.operations.CVSNonblockingRunnableContext.run",
          "source": "CVSNonblocking RunnableContext.java:47"
        },
        {
          "method": "org.eclipse.team.internal.ccvs.ui.operations.CVSNonblockingRunnableContext$2.runInWorkspace",
          "source": "C VSNonblockingRunnableContext.java :67"
        },
        {
          "method": "org.eclipse.core.internal.resources.InternalWorkspaceJob.run",
          "source": "InternalWorkspaceJob.java:37"
        },
        {
          "method": "org.eclipse.core.internal.jobs.Worker.run",
          "source": "Worker.java:62"
        }
      ],
      "number": 0,
      "commentIndex": 0,
      "bugId": "50143",
      "duplicateId": "12345",
      "date": "2004-01-16T16:28:20+01:00",
      "product": "Platform",
      "component": "CVS",
      "severity": "normal"
    }
  ],
  "groupId": "12345",
  "bugId": "50143",
  "duplicateId": "12345",
  "date": "2004-01-16T16:28:20+01:00",
  "product": "Platform",
  "component": "CVS",
  "severity": "normal"
}