{
  "comments": [
    "Hi all,\n\nI try to use SWT_AWT in a ViewPart but I can\u0027t get my plugin working, the\nworkbench tells me there was an error creating view. Here it is, taken from\nplatform .log :\n\n!ENTRY org.eclipse.ui 4 4 janv. 23, 2004 12:04:50.246\n!MESSAGE Unhandled event loop exception\n!ENTRY org.eclipse.ui 4 0 janv. 23, 2004 12:04:50.246\n!MESSAGE java.lang.NullPointerException\n!STACK 0\njava.lang.NullPointerException\n    at org.eclipse.swt.internal.BidiUtil.windowProc(BidiUtil.java:647)\n    at org.eclipse.swt.internal.win32.OS.PeekMessageW(Native Method)\n    at org.eclipse.swt.internal.win32.OS.PeekMessage(OS.java:1757)\n    at org.eclipse.swt.widgets.Display.readAndDispatch(Display.java:1986)\n    at org.eclipse.ui.internal.Workbench.runEventLoop(Workbench.java:1506)\n    at org.eclipse.ui.internal.Workbench.runUI(Workbench.java:1482)\n    at org.eclipse.ui.internal.Workbench.createAndRunWorkbench(Workbench.java:246)\n    at org.eclipse.ui.PlatformUI.createAndRunWorkbench(PlatformUI.java:139)\n    at org.eclipse.ui.internal.ide.IDEApplication.run(IDEApplication.java:47)\n    at\norg.eclipse.core.internal.runtime.PlatformActivator$1.run(PlatformActivator.java:226)\n    at org.eclipse.core.runtime.adaptor.EclipseStarter.run(EclipseStarter.java:85)\n    at sun.reflect.NativeMethodAccessorImpl.invoke0(Native Method)\n    at sun.reflect.NativeMethodAccessorImpl.invoke(Unknown Source)\n    at sun.reflect.DelegatingMethodAccessorImpl.invoke(Unknown Source)\n    at java.lang.reflect.Method.invoke(Unknown Source)\n    at org.eclipse.core.launcher.Main.basicRun(Main.java:279)\n    at org.eclipse.core.launcher.Main.run(Main.java:742)\n    at org.eclipse.core.launcher.Main.main(Main.java:581)\n\n\n\nThis error happens on the following line in the given snippet :\nSWT_AWT.newFrame(...) in the following snippet. When I execute the same outside\na eclipse (in a shell), this works fine.\nDoes somebody know how to solve this problem? Is it a bug?\nThanks for help.\n\nMathieu Fougeray.\n\n\nimport org.eclipse.jface.viewers.IStructuredContentProvider;\nimport org.eclipse.jface.viewers.ITableLabelProvider;\nimport org.eclipse.jface.viewers.LabelProvider;\nimport org.eclipse.jface.viewers.TableViewer;\nimport org.eclipse.jface.viewers.Viewer;\nimport org.eclipse.swt.SWT;\nimport org.eclipse.swt.graphics.Image;\nimport org.eclipse.swt.widgets.Composite;\nimport org.eclipse.ui.ISharedImages;\nimport org.eclipse.ui.PlatformUI;\nimport org.eclipse.ui.part.ViewPart;\nimport eurobios.orsis.Messages;\n\npublic class MyView extends ViewPart {\n   public static final String ID_VIEW \u003d \"eurobios.orsis.views.BarChartView\";\n//$NON-NLS-1$\n     public MyView () {\n   }\n\n   public void createPartControl(Composite parent) {\n       Composite comp \u003d new Composite(parent, SWT.EMBEDDED);\n       java.awt.Frame frame \u003d SWT_AWT.new_Frame(comp);\n   }\n\n   public void setFocus() {\n   }\n}",
    "*** Bug 50484 has been marked as a duplicate of this bug. ***",
    "Please could you try the latest? We\u0027ve made changes that will probably fix the \nproblem, but I cannot confirm that since I was unable to reproduce the problem.\n\nYou need to get a nightly build greater than 20030123 or use HEAD from CVS.",
    "You\u0027re right. When I take the last swt plugin coming from nightly build\n(i20040121) and put it in my 3.0M6 version, it works! So I can import jfreechart\n.jar and have my charts working in eclipse workbench :) Keep it like that please!\nThanks all!!!\n\nMathieu",
    "Fixed \u003e 20030124."
  ],
  "commentCreationDates": [
    "2004-01-23T17:36:37+01:00",
    "2004-01-23T21:29:17+01:00",
    "2004-01-23T22:56:29+01:00",
    "2004-01-26T10:35:42+01:00",
    "2004-01-26T16:37:05+01:00"
  ],
  "traces": [
    {
      "exceptionType": "java.lang.NullPointerException",
      "elements": [
        {
          "method": "org.eclipse.swt.internal.BidiUtil.windowProc",
          "source": "BidiUtil.java:647"
        },
        {
          "method": "org.eclipse.swt.internal.win32.OS.PeekMessageW",
          "source": "Native Method"
        },
        {
          "method": "org.eclipse.swt.internal.win32.OS.PeekMessage",
          "source": "OS.java:1757"
        },
        {
          "method": "org.eclipse.swt.widgets.Display.readAndDispatch",
          "source": "Display.java:1986"
        },
        {
          "method": "org.eclipse.ui.internal.Workbench.runEventLoop",
          "source": "Workbench.java:1506"
        },
        {
          "method": "org.eclipse.ui.internal.Workbench.runUI",
          "source": "Workbench.java:1482"
        },
        {
          "method": "org.eclipse.ui.internal.Workbench.createAndRunWorkbench",
          "source": "Workbench.java:246"
        },
        {
          "method": "org.eclipse.ui.PlatformUI.createAndRunWorkbench",
          "source": "PlatformUI.java:139"
        },
        {
          "method": "org.eclipse.ui.internal.ide.IDEApplication.run",
          "source": "IDEApplication.java:47"
        },
        {
          "method": "org.eclipse.core.internal.runtime.PlatformActivator$1.run",
          "source": "PlatformActivator.java:226"
        },
        {
          "method": "org.eclipse.core.runtime.adaptor.EclipseStarter.run",
          "source": "EclipseStarter.java:85"
        },
        {
          "method": "sun.reflect.NativeMethodAccessorImpl.invoke0",
          "source": "Native Method"
        },
        {
          "method": "sun.reflect.NativeMethodAccessorImpl.invoke",
          "source": "Unknown Source"
        },
        {
          "method": "sun.reflect.DelegatingMethodAccessorImpl.invoke",
          "source": "Unknown Source"
        },
        {
          "method": "java.lang.reflect.Method.invoke",
          "source": "Unknown Source"
        },
        {
          "method": "org.eclipse.core.launcher.Main.basicRun",
          "source": "Main.java:279"
        },
        {
          "method": "org.eclipse.core.launcher.Main.run",
          "source": "Main.java:742"
        },
        {
          "method": "org.eclipse.core.launcher.Main.main",
          "source": "Main.java:581"
        }
      ],
      "number": 0,
      "commentIndex": 0,
      "bugId": "50483",
      "date": "2004-01-23T17:36:37+01:00",
      "product": "Platform",
      "component": "SWT",
      "severity": "normal"
    }
  ],
  "groupId": "50483",
  "bugId": "50483",
  "date": "2004-01-23T17:36:37+01:00",
  "product": "Platform",
  "component": "SWT",
  "severity": "normal"
}