{
  "comments": [
    "I20040121 + plugin-export of 20030127\n\nFound this in the log (no steps). Dani, not sure whether this is already fixed.\n\n!MESSAGE Action for command \u0027org.eclipse.ui.edit.text.delete.line\u0027 failed to\nexecute properly.\n!STACK 0\njava.lang.IllegalArgumentException: Index out of bounds\n        at java.lang.Throwable.\u003cinit\u003e(Throwable.java)\n        at java.lang.Throwable.\u003cinit\u003e(Throwable.java)\n        at org.eclipse.swt.SWT.error(SWT.java:2594)\n        at org.eclipse.swt.SWT.error(SWT.java:2538)\n        at org.eclipse.swt.custom.StyledText.replaceStyleRanges(StyledText.java)\n        at org.eclipse.jface.text.TextViewer.addPresentation(TextViewer.java)\n        at org.eclipse.jface.text.TextViewer.changeTextPresentation(TextViewer.java)\n        at\norg.eclipse.jface.text.presentation.PresentationReconciler.applyTextRegionCollection(PresentationReconciler.java)\n        at\norg.eclipse.jface.text.presentation.PresentationReconciler.processDamage(PresentationReconciler.java)\n        at\norg.eclipse.jface.text.presentation.PresentationReconciler.access$5(PresentationReconciler.java)\n        at\norg.eclipse.jface.text.presentation.PresentationReconciler$InternalListener.textChanged(PresentationReconciler.java)\n        at org.eclipse.jface.text.TextViewer.updateTextListeners(TextViewer.java)\n        at\norg.eclipse.jface.text.TextViewer$DocumentListener.documentChanged(TextViewer.java)\n        at\norg.eclipse.jface.text.AbstractDocument.doFireDocumentChanged2(AbstractDocument.java:673)\n        at\norg.eclipse.jface.text.AbstractDocument.doFireDocumentChanged(AbstractDocument.java)\n        at\norg.eclipse.jface.text.AbstractDocument.doFireDocumentChanged(AbstractDocument.java)\n        at\norg.eclipse.jface.text.AbstractDocument.fireDocumentChanged(AbstractDocument.java)\n        at org.eclipse.jface.text.AbstractDocument.replace(AbstractDocument.java)\n        at\norg.eclipse.jdt.internal.ui.javaeditor.PartiallySynchronizedDocument.replace(PartiallySynchronizedDocument.java)\n        at\norg.eclipse.ui.texteditor.DeleteLineTarget.deleteLine(DeleteLineTarget.java:323)\n        at org.eclipse.ui.texteditor.DeleteLineAction.run(DeleteLineAction.java:145)\n        at org.eclipse.jface.action.Action.runWithEvent(Action.java:881)\n        at\norg.eclipse.ui.internal.commands.ActionHandler.execute(ActionHandler.java:40)\n        at\norg.eclipse.ui.internal.keys.WorkbenchKeyboard.executeCommand(WorkbenchKeyboard.java:414)\n        at\norg.eclipse.ui.internal.keys.WorkbenchKeyboard.press(WorkbenchKeyboard.java)\n        at\norg.eclipse.ui.internal.keys.WorkbenchKeyboard.processKeyEvent(WorkbenchKeyboard.java)\n        at\norg.eclipse.ui.internal.keys.WorkbenchKeyboard.filterKeySequenceBindings(WorkbenchKeyboard.java)\n        at\norg.eclipse.ui.internal.keys.WorkbenchKeyboard.access$2(WorkbenchKeyboard.java)\n        at\norg.eclipse.ui.internal.keys.WorkbenchKeyboard$1.handleEvent(WorkbenchKeyboard.java)\n        at org.eclipse.swt.widgets.EventTable.sendEvent(EventTable.java)\n        at org.eclipse.swt.widgets.Display.filterEvent(Display.java)\n        at org.eclipse.swt.widgets.Widget.sendEvent(Widget.java)\n        at org.eclipse.swt.widgets.Widget.sendEvent(Widget.java)\n        at org.eclipse.swt.widgets.Widget.sendEvent(Widget.java)\n        at org.eclipse.swt.widgets.Control.sendKeyEvent(Control.java)\n        at org.eclipse.swt.widgets.Control.gtk_key_press_event(Control.java)\n        at org.eclipse.swt.widgets.Composite.gtk_key_press_event(Composite.java)\n        at org.eclipse.swt.widgets.Widget.windowProc(Widget.java)\n        at org.eclipse.swt.widgets.Display.windowProc(Display.java)\n        at org.eclipse.swt.internal.gtk.OS.gtk_main_do_event(Native Method)\n        at org.eclipse.swt.widgets.Display.eventProc(Display.java)\n        at org.eclipse.swt.internal.gtk.OS.gtk_main_iteration(Native Method)\n        at org.eclipse.swt.widgets.Display.readAndDispatch(Display.java)\n        at org.eclipse.ui.internal.Workbench.runEventLoop(Workbench.java:1530)\n        at org.eclipse.ui.internal.Workbench.runUI(Workbench.java:1506)\n        at\norg.eclipse.ui.internal.Workbench.createAndRunWorkbench(Workbench.java:265)\n        at org.eclipse.ui.PlatformUI.createAndRunWorkbench(PlatformUI.java:139)\n        at org.eclipse.ui.internal.ide.IDEApplication.run(IDEApplication.java:47)\n        at\norg.eclipse.core.internal.runtime.PlatformActivator$1.run(PlatformActivator.java:248)\n        at\norg.eclipse.core.runtime.adaptor.EclipseStarter.run(EclipseStarter.java:85)\n        at sun.reflect.NativeMethodAccessorImpl.invoke0(Native Method)\n        at\nsun.reflect.NativeMethodAccessorImpl.invoke(NativeMethodAccessorImpl.java:79)\n        at\nsun.reflect.DelegatingMethodAccessorImpl.invoke(DelegatingMethodAccessorImpl.java:41)\n        at java.lang.reflect.Method.invoke(Method.java:386)\n        at org.eclipse.core.launcher.Main.basicRun(Main.java:279)\n        at org.eclipse.core.launcher.Main.run(Main.java:742)\n        at org.eclipse.core.launcher.Main.main(Main.java:581)\nAction for command \u0027org.eclipse.ui.edit.text.delete.line\u0027 failed to execute\nproperly.\n!ENTRY org.eclipse.jdt.ui 4 10001 Jan 27, 2004 12:33:31.996\n!MESSAGE Internal Error\n!STACK 0\njava.lang.IllegalArgumentException: Index out of bounds\n        at java.lang.Throwable.\u003cinit\u003e(Throwable.java)\n        at java.lang.Throwable.\u003cinit\u003e(Throwable.java)\n        at org.eclipse.swt.SWT.error(SWT.java:2594)\n        at org.eclipse.swt.SWT.error(SWT.java:2538)\n        at org.eclipse.swt.custom.StyledText.redrawRange(StyledText.java)\n        at\norg.eclipse.jdt.internal.ui.javaeditor.JavaEditor$MouseClickListener.repairRepresentation(JavaEditor.java:497)\n        at\norg.eclipse.jdt.internal.ui.javaeditor.JavaEditor$MouseClickListener.deactivate(JavaEditor.java)\n        at\norg.eclipse.jdt.internal.ui.javaeditor.JavaEditor$MouseClickListener.deactivate(JavaEditor.java)\n        at\norg.eclipse.jdt.internal.ui.javaeditor.JavaEditor$MouseClickListener.keyReleased(JavaEditor.java)\n        at org.eclipse.swt.widgets.TypedListener.handleEvent(TypedListener.java)\n        at org.eclipse.swt.widgets.EventTable.sendEvent(EventTable.java)\n        at org.eclipse.swt.widgets.Widget.sendEvent(Widget.java)\n        at org.eclipse.swt.widgets.Widget.sendEvent(Widget.java)\n        at org.eclipse.swt.widgets.Widget.sendEvent(Widget.java)\n        at org.eclipse.swt.widgets.Control.sendKeyEvent(Control.java)\n        at org.eclipse.swt.widgets.Control.gtk_key_release_event(Control.java)\n        at org.eclipse.swt.widgets.Widget.windowProc(Widget.java)\n        at org.eclipse.swt.widgets.Display.windowProc(Display.java)\n        at org.eclipse.swt.internal.gtk.OS.gtk_main_do_event(Native Method)\n        at org.eclipse.swt.widgets.Display.eventProc(Display.java)\n        at org.eclipse.swt.internal.gtk.OS.gtk_main_iteration(Native Method)\n        at org.eclipse.swt.widgets.Display.readAndDispatch(Display.java)\n        at org.eclipse.ui.internal.Workbench.runEventLoop(Workbench.java:1530)\n        at org.eclipse.ui.internal.Workbench.runUI(Workbench.java:1506)\n        at\norg.eclipse.ui.internal.Workbench.createAndRunWorkbench(Workbench.java:265)\n        at org.eclipse.ui.PlatformUI.createAndRunWorkbench(PlatformUI.java:139)\n        at org.eclipse.ui.internal.ide.IDEApplication.run(IDEApplication.java:47)\n        at\norg.eclipse.core.internal.runtime.PlatformActivator$1.run(PlatformActivator.java:248)\n        at\norg.eclipse.core.runtime.adaptor.EclipseStarter.run(EclipseStarter.java:85)\n        at sun.reflect.NativeMethodAccessorImpl.invoke0(Native Method)\n        at\nsun.reflect.NativeMethodAccessorImpl.invoke(NativeMethodAccessorImpl.java:79)\n        at\nsun.reflect.DelegatingMethodAccessorImpl.invoke(DelegatingMethodAccessorImpl.java:41)\n        at java.lang.reflect.Method.invoke(Method.java:386)\n        at org.eclipse.core.launcher.Main.basicRun(Main.java:279)\n        at org.eclipse.core.launcher.Main.run(Main.java:742)\n        at org.eclipse.core.launcher.Main.main(Main.java:581)",
    "I\u0027ve released a fix yesterday."
  ],
  "commentCreationDates": [
    "2004-01-28T07:49:23+01:00",
    "2004-01-28T10:02:37+01:00"
  ],
  "traces": [
    {
      "exceptionType": "java.lang.IllegalArgumentException",
      "message": "Index out of bounds",
      "elements": [
        {
          "method": "java.lang.Throwable.\u003cinit\u003e",
          "source": "Throwable.java"
        },
        {
          "method": "java.lang.Throwable.\u003cinit\u003e",
          "source": "Throwable.java"
        },
        {
          "method": "org.eclipse.swt.SWT.error",
          "source": "SWT.java:2594"
        },
        {
          "method": "org.eclipse.swt.SWT.error",
          "source": "SWT.java:2538"
        },
        {
          "method": "org.eclipse.swt.custom.StyledText.replaceStyleRanges",
          "source": "StyledText.java"
        },
        {
          "method": "org.eclipse.jface.text.TextViewer.addPresentation",
          "source": "TextViewer.java"
        },
        {
          "method": "org.eclipse.jface.text.TextViewer.changeTextPresentation",
          "source": "TextViewer.java"
        },
        {
          "method": "org.eclipse.jface.text.presentation.PresentationReconciler.applyTextRegionCollection",
          "source": "PresentationReconciler.java"
        },
        {
          "method": "org.eclipse.jface.text.presentation.PresentationReconciler.processDamage",
          "source": "PresentationReconciler.java"
        },
        {
          "method": "org.eclipse.jface.text.presentation.PresentationReconciler.access$5",
          "source": "PresentationReconciler.java"
        },
        {
          "method": "org.eclipse.jface.text.presentation.PresentationReconciler$InternalListener.textChanged",
          "source": "PresentationReconciler.java"
        },
        {
          "method": "org.eclipse.jface.text.TextViewer.updateTextListeners",
          "source": "TextViewer.java"
        },
        {
          "method": "org.eclipse.jface.text.TextViewer$DocumentListener.documentChanged",
          "source": "TextViewer.java"
        },
        {
          "method": "org.eclipse.jface.text.AbstractDocument.doFireDocumentChanged2",
          "source": "AbstractDocument.java:673"
        },
        {
          "method": "org.eclipse.jface.text.AbstractDocument.doFireDocumentChanged",
          "source": "AbstractDocument.java"
        },
        {
          "method": "org.eclipse.jface.text.AbstractDocument.doFireDocumentChanged",
          "source": "AbstractDocument.java"
        },
        {
          "method": "org.eclipse.jface.text.AbstractDocument.fireDocumentChanged",
          "source": "AbstractDocument.java"
        },
        {
          "method": "org.eclipse.jface.text.AbstractDocument.replace",
          "source": "AbstractDocument.java"
        },
        {
          "method": "org.eclipse.jdt.internal.ui.javaeditor.PartiallySynchronizedDocument.replace",
          "source": "PartiallySynchronizedDocument.java"
        },
        {
          "method": "org.eclipse.ui.texteditor.DeleteLineTarget.deleteLine",
          "source": "DeleteLineTarget.java:323"
        },
        {
          "method": "org.eclipse.ui.texteditor.DeleteLineAction.run",
          "source": "DeleteLineAction.java:145"
        },
        {
          "method": "org.eclipse.jface.action.Action.runWithEvent",
          "source": "Action.java:881"
        },
        {
          "method": "org.eclipse.ui.internal.commands.ActionHandler.execute",
          "source": "ActionHandler.java:40"
        },
        {
          "method": "org.eclipse.ui.internal.keys.WorkbenchKeyboard.executeCommand",
          "source": "WorkbenchKeyboard.java:414"
        },
        {
          "method": "org.eclipse.ui.internal.keys.WorkbenchKeyboard.press",
          "source": "WorkbenchKeyboard.java"
        },
        {
          "method": "org.eclipse.ui.internal.keys.WorkbenchKeyboard.processKeyEvent",
          "source": "WorkbenchKeyboard.java"
        },
        {
          "method": "org.eclipse.ui.internal.keys.WorkbenchKeyboard.filterKeySequenceBindings",
          "source": "WorkbenchKeyboard.java"
        },
        {
          "method": "org.eclipse.ui.internal.keys.WorkbenchKeyboard.access$2",
          "source": "WorkbenchKeyboard.java"
        },
        {
          "method": "org.eclipse.ui.internal.keys.WorkbenchKeyboard$1.handleEvent",
          "source": "WorkbenchKeyboard.java"
        },
        {
          "method": "org.eclipse.swt.widgets.EventTable.sendEvent",
          "source": "EventTable.java"
        },
        {
          "method": "org.eclipse.swt.widgets.Display.filterEvent",
          "source": "Display.java"
        },
        {
          "method": "org.eclipse.swt.widgets.Widget.sendEvent",
          "source": "Widget.java"
        },
        {
          "method": "org.eclipse.swt.widgets.Widget.sendEvent",
          "source": "Widget.java"
        },
        {
          "method": "org.eclipse.swt.widgets.Widget.sendEvent",
          "source": "Widget.java"
        },
        {
          "method": "org.eclipse.swt.widgets.Control.sendKeyEvent",
          "source": "Control.java"
        },
        {
          "method": "org.eclipse.swt.widgets.Control.gtk_key_press_event",
          "source": "Control.java"
        },
        {
          "method": "org.eclipse.swt.widgets.Composite.gtk_key_press_event",
          "source": "Composite.java"
        },
        {
          "method": "org.eclipse.swt.widgets.Widget.windowProc",
          "source": "Widget.java"
        },
        {
          "method": "org.eclipse.swt.widgets.Display.windowProc",
          "source": "Display.java"
        },
        {
          "method": "org.eclipse.swt.internal.gtk.OS.gtk_main_do_event",
          "source": "Native Method"
        },
        {
          "method": "org.eclipse.swt.widgets.Display.eventProc",
          "source": "Display.java"
        },
        {
          "method": "org.eclipse.swt.internal.gtk.OS.gtk_main_iteration",
          "source": "Native Method"
        },
        {
          "method": "org.eclipse.swt.widgets.Display.readAndDispatch",
          "source": "Display.java"
        },
        {
          "method": "org.eclipse.ui.internal.Workbench.runEventLoop",
          "source": "Workbench.java:1530"
        },
        {
          "method": "org.eclipse.ui.internal.Workbench.runUI",
          "source": "Workbench.java:1506"
        },
        {
          "method": "org.eclipse.ui.internal.Workbench.createAndRunWorkbench",
          "source": "Workbench.java:265"
        },
        {
          "method": "org.eclipse.ui.PlatformUI.createAndRunWorkbench",
          "source": "PlatformUI.java:139"
        },
        {
          "method": "org.eclipse.ui.internal.ide.IDEApplication.run",
          "source": "IDEApplication.java:47"
        },
        {
          "method": "org.eclipse.core.internal.runtime.PlatformActivator$1.run",
          "source": "PlatformActivator.java:248"
        },
        {
          "method": "org.eclipse.core.runtime.adaptor.EclipseStarter.run",
          "source": "EclipseStarter.java:85"
        },
        {
          "method": "sun.reflect.NativeMethodAccessorImpl.invoke0",
          "source": "Native Method"
        },
        {
          "method": "sun.reflect.NativeMethodAccessorImpl.invoke",
          "source": "NativeMethodAccessorImpl.java:79"
        },
        {
          "method": "sun.reflect.DelegatingMethodAccessorImpl.invoke",
          "source": "DelegatingMethodAccessorImpl.java:41"
        },
        {
          "method": "java.lang.reflect.Method.invoke",
          "source": "Method.java:386"
        },
        {
          "method": "org.eclipse.core.launcher.Main.basicRun",
          "source": "Main.java:279"
        },
        {
          "method": "org.eclipse.core.launcher.Main.run",
          "source": "Main.java:742"
        },
        {
          "method": "org.eclipse.core.launcher.Main.main",
          "source": "Main.java:581"
        }
      ],
      "number": 0,
      "commentIndex": 0,
      "bugId": "50739",
      "date": "2004-01-28T07:49:23+01:00",
      "product": "Platform",
      "component": "Text",
      "severity": "normal"
    },
    {
      "exceptionType": "java.lang.IllegalArgumentException",
      "message": "Index out of bounds",
      "elements": [
        {
          "method": "java.lang.Throwable.\u003cinit\u003e",
          "source": "Throwable.java"
        },
        {
          "method": "java.lang.Throwable.\u003cinit\u003e",
          "source": "Throwable.java"
        },
        {
          "method": "org.eclipse.swt.SWT.error",
          "source": "SWT.java:2594"
        },
        {
          "method": "org.eclipse.swt.SWT.error",
          "source": "SWT.java:2538"
        },
        {
          "method": "org.eclipse.swt.custom.StyledText.redrawRange",
          "source": "StyledText.java"
        },
        {
          "method": "org.eclipse.jdt.internal.ui.javaeditor.JavaEditor$MouseClickListener.repairRepresentation",
          "source": "JavaEditor.java:497"
        },
        {
          "method": "org.eclipse.jdt.internal.ui.javaeditor.JavaEditor$MouseClickListener.deactivate",
          "source": "JavaEditor.java"
        },
        {
          "method": "org.eclipse.jdt.internal.ui.javaeditor.JavaEditor$MouseClickListener.deactivate",
          "source": "JavaEditor.java"
        },
        {
          "method": "org.eclipse.jdt.internal.ui.javaeditor.JavaEditor$MouseClickListener.keyReleased",
          "source": "JavaEditor.java"
        },
        {
          "method": "org.eclipse.swt.widgets.TypedListener.handleEvent",
          "source": "TypedListener.java"
        },
        {
          "method": "org.eclipse.swt.widgets.EventTable.sendEvent",
          "source": "EventTable.java"
        },
        {
          "method": "org.eclipse.swt.widgets.Widget.sendEvent",
          "source": "Widget.java"
        },
        {
          "method": "org.eclipse.swt.widgets.Widget.sendEvent",
          "source": "Widget.java"
        },
        {
          "method": "org.eclipse.swt.widgets.Widget.sendEvent",
          "source": "Widget.java"
        },
        {
          "method": "org.eclipse.swt.widgets.Control.sendKeyEvent",
          "source": "Control.java"
        },
        {
          "method": "org.eclipse.swt.widgets.Control.gtk_key_release_event",
          "source": "Control.java"
        },
        {
          "method": "org.eclipse.swt.widgets.Widget.windowProc",
          "source": "Widget.java"
        },
        {
          "method": "org.eclipse.swt.widgets.Display.windowProc",
          "source": "Display.java"
        },
        {
          "method": "org.eclipse.swt.internal.gtk.OS.gtk_main_do_event",
          "source": "Native Method"
        },
        {
          "method": "org.eclipse.swt.widgets.Display.eventProc",
          "source": "Display.java"
        },
        {
          "method": "org.eclipse.swt.internal.gtk.OS.gtk_main_iteration",
          "source": "Native Method"
        },
        {
          "method": "org.eclipse.swt.widgets.Display.readAndDispatch",
          "source": "Display.java"
        },
        {
          "method": "org.eclipse.ui.internal.Workbench.runEventLoop",
          "source": "Workbench.java:1530"
        },
        {
          "method": "org.eclipse.ui.internal.Workbench.runUI",
          "source": "Workbench.java:1506"
        },
        {
          "method": "org.eclipse.ui.internal.Workbench.createAndRunWorkbench",
          "source": "Workbench.java:265"
        },
        {
          "method": "org.eclipse.ui.PlatformUI.createAndRunWorkbench",
          "source": "PlatformUI.java:139"
        },
        {
          "method": "org.eclipse.ui.internal.ide.IDEApplication.run",
          "source": "IDEApplication.java:47"
        },
        {
          "method": "org.eclipse.core.internal.runtime.PlatformActivator$1.run",
          "source": "PlatformActivator.java:248"
        },
        {
          "method": "org.eclipse.core.runtime.adaptor.EclipseStarter.run",
          "source": "EclipseStarter.java:85"
        },
        {
          "method": "sun.reflect.NativeMethodAccessorImpl.invoke0",
          "source": "Native Method"
        },
        {
          "method": "sun.reflect.NativeMethodAccessorImpl.invoke",
          "source": "NativeMethodAccessorImpl.java:79"
        },
        {
          "method": "sun.reflect.DelegatingMethodAccessorImpl.invoke",
          "source": "DelegatingMethodAccessorImpl.java:41"
        },
        {
          "method": "java.lang.reflect.Method.invoke",
          "source": "Method.java:386"
        },
        {
          "method": "org.eclipse.core.launcher.Main.basicRun",
          "source": "Main.java:279"
        },
        {
          "method": "org.eclipse.core.launcher.Main.run",
          "source": "Main.java:742"
        },
        {
          "method": "org.eclipse.core.launcher.Main.main",
          "source": "Main.java:581"
        }
      ],
      "number": 1,
      "commentIndex": 0,
      "bugId": "50739",
      "date": "2004-01-28T07:49:23+01:00",
      "product": "Platform",
      "component": "Text",
      "severity": "normal"
    }
  ],
  "groupId": "50739",
  "bugId": "50739",
  "date": "2004-01-28T07:49:23+01:00",
  "product": "Platform",
  "component": "Text",
  "severity": "normal"
}