{
  "comments": [
    "Note: I had plenty of compile and syntax errors in my source (-\u003e refactoring\nusing regexprs and other brute force methods). But all the\nparens/braces/brackets were matched, so I nevertheless expected the indenter to\nproduce valid output.\n\n\n!MESSAGE Action for command \u0027org.eclipse.jdt.ui.edit.text.java.indent\u0027 failed to\nexecute properly.\n!STACK 0\njava.lang.StringIndexOutOfBoundsException: String index out of range: 0\n        at java.lang.StringBuffer.charAt(StringBuffer.java:283)\n        at\norg.eclipse.jdt.internal.ui.actions.IndentAction.indentLine(IndentAction.java:257)\n        at\norg.eclipse.jdt.internal.ui.actions.IndentAction.access$1(IndentAction.java:211)\n        at\norg.eclipse.jdt.internal.ui.actions.IndentAction$1.run(IndentAction.java:133)\n        at org.eclipse.swt.custom.BusyIndicator.showWhile(BusyIndicator.java:84)\n        at\norg.eclipse.jdt.internal.ui.actions.IndentAction.run(IndentAction.java:172)\n        at org.eclipse.jface.action.Action.runWithEvent(Action.java:881)\n        at\norg.eclipse.ui.internal.commands.ActionHandler.execute(ActionHandler.java:40)\n        at\norg.eclipse.ui.internal.keys.WorkbenchKeyboard.executeCommand(WorkbenchKeyboard.java:414)\n        at\norg.eclipse.ui.internal.keys.WorkbenchKeyboard.press(WorkbenchKeyboard.java:778)\n        at\norg.eclipse.ui.internal.keys.WorkbenchKeyboard.processKeyEvent(WorkbenchKeyboard.java:815)\n        at\norg.eclipse.ui.internal.keys.WorkbenchKeyboard.filterKeySequenceBindings(WorkbenchKeyboard.java:505)\n        at\norg.eclipse.ui.internal.keys.WorkbenchKeyboard.access$2(WorkbenchKeyboard.java:444)\n        at\norg.eclipse.ui.internal.keys.WorkbenchKeyboard$1.handleEvent(WorkbenchKeyboard.java:233)\n        at org.eclipse.swt.widgets.EventTable.sendEvent(EventTable.java:82)\n        at org.eclipse.swt.widgets.Display.filterEvent(Display.java:699)\n        at org.eclipse.swt.widgets.Widget.sendEvent(Widget.java:832)\n        at org.eclipse.swt.widgets.Widget.sendEvent(Widget.java:857)\n        at org.eclipse.swt.widgets.Widget.sendEvent(Widget.java:842)\n        at org.eclipse.swt.widgets.Control.sendKeyEvent(Control.java:1716)\n        at org.eclipse.swt.widgets.Control.sendKeyEvent(Control.java:1712)\n        at org.eclipse.swt.widgets.Control.WM_CHAR(Control.java:3037)\n        at org.eclipse.swt.widgets.Control.windowProc(Control.java:2940)\n        at org.eclipse.swt.widgets.Display.windowProc(Display.java:2865)\n        at org.eclipse.swt.internal.win32.OS.DispatchMessageW(Native Method)\n        at org.eclipse.swt.internal.win32.OS.DispatchMessage(OS.java:1371)\n        at org.eclipse.swt.widgets.Display.readAndDispatch(Display.java:2019)\n        at org.eclipse.ui.internal.Workbench.runEventLoop(Workbench.java:1530)\n        at org.eclipse.ui.internal.Workbench.runUI(Workbench.java:1506)\n        at\norg.eclipse.ui.internal.Workbench.createAndRunWorkbench(Workbench.java:265)\n        at org.eclipse.ui.PlatformUI.createAndRunWorkbench(PlatformUI.java:139)\n        at org.eclipse.ui.internal.ide.IDEApplication.run(IDEApplication.java:47)\n        at\norg.eclipse.core.internal.runtime.PlatformActivator$1.run(PlatformActivator.java:248)\n        at\norg.eclipse.core.runtime.adaptor.EclipseStarter.run(EclipseStarter.java:85)\n        at sun.reflect.NativeMethodAccessorImpl.invoke0(Native Method)\n        at\nsun.reflect.NativeMethodAccessorImpl.invoke(NativeMethodAccessorImpl.java:39)\n        at\nsun.reflect.DelegatingMethodAccessorImpl.invoke(DelegatingMethodAccessorImpl.java:25)\n        at java.lang.reflect.Method.invoke(Method.java:324)\n        at org.eclipse.core.launcher.Main.basicRun(Main.java:279)\n        at org.eclipse.core.launcher.Main.run(Main.java:742)\n        at org.eclipse.core.launcher.Main.main(Main.java:581)\nAction for command \u0027org.eclipse.jdt.ui.edit.text.java.indent\u0027 failed to execute\nproperly.",
    "Can you attach that file. Is it reproducible?",
    "I don\u0027t have the file anymore and cannot provide further steps, as I was only\naware of the exception several minutes later.",
    "So, nothing in the UI? Did the indent command work or not?",
    "this is a bug. will happen when indenting single line comments in a zero-indent\nsection.\n\n\nsteps: indent the comment line below:\n\npackage bla;\n\n// comment \u003c- hit ctrl-I\n\n",
    "fixed \u003e 20040128"
  ],
  "commentCreationDates": [
    "2004-01-28T09:52:36+01:00",
    "2004-01-28T09:57:33+01:00",
    "2004-01-28T10:08:50+01:00",
    "2004-01-28T10:14:58+01:00",
    "2004-01-28T10:29:49+01:00",
    "2004-01-28T10:58:13+01:00"
  ],
  "traces": [
    {
      "exceptionType": "java.lang.StringIndexOutOfBoundsException",
      "message": "String index out of range: 0",
      "elements": [
        {
          "method": "java.lang.StringBuffer.charAt",
          "source": "StringBuffer.java:283"
        },
        {
          "method": "org.eclipse.jdt.internal.ui.actions.IndentAction.indentLine",
          "source": "IndentAction.java:257"
        },
        {
          "method": "org.eclipse.jdt.internal.ui.actions.IndentAction.access$1",
          "source": "IndentAction.java:211"
        },
        {
          "method": "org.eclipse.jdt.internal.ui.actions.IndentAction$1.run",
          "source": "IndentAction.java:133"
        },
        {
          "method": "org.eclipse.swt.custom.BusyIndicator.showWhile",
          "source": "BusyIndicator.java:84"
        },
        {
          "method": "org.eclipse.jdt.internal.ui.actions.IndentAction.run",
          "source": "IndentAction.java:172"
        },
        {
          "method": "org.eclipse.jface.action.Action.runWithEvent",
          "source": "Action.java:881"
        },
        {
          "method": "org.eclipse.ui.internal.commands.ActionHandler.execute",
          "source": "ActionHandler.java:40"
        },
        {
          "method": "org.eclipse.ui.internal.keys.WorkbenchKeyboard.executeCommand",
          "source": "WorkbenchKeyboard.java:414"
        },
        {
          "method": "org.eclipse.ui.internal.keys.WorkbenchKeyboard.press",
          "source": "WorkbenchKeyboard.java:778"
        },
        {
          "method": "org.eclipse.ui.internal.keys.WorkbenchKeyboard.processKeyEvent",
          "source": "WorkbenchKeyboard.java:815"
        },
        {
          "method": "org.eclipse.ui.internal.keys.WorkbenchKeyboard.filterKeySequenceBindings",
          "source": "WorkbenchKeyboard.java:505"
        },
        {
          "method": "org.eclipse.ui.internal.keys.WorkbenchKeyboard.access$2",
          "source": "WorkbenchKeyboard.java:444"
        },
        {
          "method": "org.eclipse.ui.internal.keys.WorkbenchKeyboard$1.handleEvent",
          "source": "WorkbenchKeyboard.java:233"
        },
        {
          "method": "org.eclipse.swt.widgets.EventTable.sendEvent",
          "source": "EventTable.java:82"
        },
        {
          "method": "org.eclipse.swt.widgets.Display.filterEvent",
          "source": "Display.java:699"
        },
        {
          "method": "org.eclipse.swt.widgets.Widget.sendEvent",
          "source": "Widget.java:832"
        },
        {
          "method": "org.eclipse.swt.widgets.Widget.sendEvent",
          "source": "Widget.java:857"
        },
        {
          "method": "org.eclipse.swt.widgets.Widget.sendEvent",
          "source": "Widget.java:842"
        },
        {
          "method": "org.eclipse.swt.widgets.Control.sendKeyEvent",
          "source": "Control.java:1716"
        },
        {
          "method": "org.eclipse.swt.widgets.Control.sendKeyEvent",
          "source": "Control.java:1712"
        },
        {
          "method": "org.eclipse.swt.widgets.Control.WM_CHAR",
          "source": "Control.java:3037"
        },
        {
          "method": "org.eclipse.swt.widgets.Control.windowProc",
          "source": "Control.java:2940"
        },
        {
          "method": "org.eclipse.swt.widgets.Display.windowProc",
          "source": "Display.java:2865"
        },
        {
          "method": "org.eclipse.swt.internal.win32.OS.DispatchMessageW",
          "source": "Native Method"
        },
        {
          "method": "org.eclipse.swt.internal.win32.OS.DispatchMessage",
          "source": "OS.java:1371"
        },
        {
          "method": "org.eclipse.swt.widgets.Display.readAndDispatch",
          "source": "Display.java:2019"
        },
        {
          "method": "org.eclipse.ui.internal.Workbench.runEventLoop",
          "source": "Workbench.java:1530"
        },
        {
          "method": "org.eclipse.ui.internal.Workbench.runUI",
          "source": "Workbench.java:1506"
        },
        {
          "method": "org.eclipse.ui.internal.Workbench.createAndRunWorkbench",
          "source": "Workbench.java:265"
        },
        {
          "method": "org.eclipse.ui.PlatformUI.createAndRunWorkbench",
          "source": "PlatformUI.java:139"
        },
        {
          "method": "org.eclipse.ui.internal.ide.IDEApplication.run",
          "source": "IDEApplication.java:47"
        },
        {
          "method": "org.eclipse.core.internal.runtime.PlatformActivator$1.run",
          "source": "PlatformActivator.java:248"
        },
        {
          "method": "org.eclipse.core.runtime.adaptor.EclipseStarter.run",
          "source": "EclipseStarter.java:85"
        },
        {
          "method": "sun.reflect.NativeMethodAccessorImpl.invoke0",
          "source": "Native Method"
        },
        {
          "method": "sun.reflect.NativeMethodAccessorImpl.invoke",
          "source": "NativeMethodAccessorImpl.java:39"
        },
        {
          "method": "sun.reflect.DelegatingMethodAccessorImpl.invoke",
          "source": "DelegatingMethodAccessorImpl.java:25"
        },
        {
          "method": "java.lang.reflect.Method.invoke",
          "source": "Method.java:324"
        },
        {
          "method": "org.eclipse.core.launcher.Main.basicRun",
          "source": "Main.java:279"
        },
        {
          "method": "org.eclipse.core.launcher.Main.run",
          "source": "Main.java:742"
        },
        {
          "method": "org.eclipse.core.launcher.Main.main",
          "source": "Main.java:581"
        }
      ],
      "number": 0,
      "commentIndex": 0,
      "bugId": "50745",
      "date": "2004-01-28T09:52:36+01:00",
      "product": "JDT",
      "component": "Text",
      "severity": "major"
    }
  ],
  "groupId": "50745",
  "bugId": "50745",
  "date": "2004-01-28T09:52:36+01:00",
  "product": "JDT",
  "component": "Text",
  "severity": "major"
}