{
  "comments": [
    "This is on a Windows 2000 workstation with SP4 installed. I tried cleaning out \na re-installing 3.0M6 many times. Other people I know who were using 2.1.x did \nnot have this problem. I finally reverted to 2.1.2 and everything worked fine.\n\nI followed every possible example of how to create a plug-in, including using \nthe example projects provided. Everything works fine until I try to Run or \nDebug as Run-time Workbench. The UI launches, the splash screen appears, the \nprogram terminates, and the splash screen is still open. It can only be shut \ndown by killing the process. The .log file shows:\n\n!SESSION Jan 27, 2004 14:31:20.262 ---------------------------------------------\njava.version\u003d1.4.1_02\njava.vendor\u003dSun Microsystems Inc.\nBootLoader constants: OS\u003dwin32, ARCH\u003dx86, WS\u003dwin32, NL\u003den_US\nCommand-line arguments: -pdelaunch -dev bin -os win32 -ws win32 -arch x86 -nl \nen_US\n!ENTRY org.eclipse.core.runtime 4 13 Jan 27, 2004 14:31:20.262\n!MESSAGE Unable to locate application extension: org.eclipse.ui.workbench\n!STACK 0\njava.lang.RuntimeException: Unable to locate application extension: \norg.eclipse.ui.workbench\n\tat org.eclipse.core.internal.runtime.PlatformActivator$1.run\n(PlatformActivator.java:205)\n\tat org.eclipse.core.runtime.adaptor.EclipseStarter.run\n(EclipseStarter.java:85)\n\tat sun.reflect.NativeMethodAccessorImpl.invoke0(Native Method)\n\tat sun.reflect.NativeMethodAccessorImpl.invoke(Unknown Source)\n\tat sun.reflect.DelegatingMethodAccessorImpl.invoke(Unknown Source)\n\tat java.lang.reflect.Method.invoke(Unknown Source)\n\tat org.eclipse.core.launcher.Main.basicRun(Main.java:279)\n\tat org.eclipse.core.launcher.Main.run(Main.java:742)\n\tat org.eclipse.core.launcher.Main.main(Main.java:581)",
    "marking as fixed in R3.0"
  ],
  "commentCreationDates": [
    "2004-02-02T22:03:14+01:00",
    "2004-10-22T21:49:33+02:00"
  ],
  "traces": [
    {
      "exceptionType": "java.lang.RuntimeException",
      "message": "Unable to locate application extension:  org.eclipse.ui.workbench",
      "elements": [
        {
          "method": "org.eclipse.core.internal.runtime.PlatformActivator$1.run",
          "source": "PlatformActivator.java:205"
        },
        {
          "method": "org.eclipse.core.runtime.adaptor.EclipseStarter.run",
          "source": "EclipseStarter.java:85"
        },
        {
          "method": "sun.reflect.NativeMethodAccessorImpl.invoke0",
          "source": "Native Method"
        },
        {
          "method": "sun.reflect.NativeMethodAccessorImpl.invoke",
          "source": "Unknown Source"
        },
        {
          "method": "sun.reflect.DelegatingMethodAccessorImpl.invoke",
          "source": "Unknown Source"
        },
        {
          "method": "java.lang.reflect.Method.invoke",
          "source": "Unknown Source"
        },
        {
          "method": "org.eclipse.core.launcher.Main.basicRun",
          "source": "Main.java:279"
        },
        {
          "method": "org.eclipse.core.launcher.Main.run",
          "source": "Main.java:742"
        },
        {
          "method": "org.eclipse.core.launcher.Main.main",
          "source": "Main.java:581"
        }
      ],
      "number": 0,
      "commentIndex": 0,
      "bugId": "51085",
      "date": "2004-02-02T22:03:14+01:00",
      "product": "Platform",
      "component": "UI",
      "severity": "major"
    }
  ],
  "groupId": "51085",
  "bugId": "51085",
  "date": "2004-02-02T22:03:14+01:00",
  "product": "Platform",
  "component": "UI",
  "severity": "major"
}