{
  "comments": [
    "I just set eclipse to not ask when exiting and got a null pointer at the command\nline and the following stacktrace at .log file. I couldn\u0027t reproduce the error...\n\n!SESSION Fev 03, 2004 19:35:21.480 ---------------------------------------------\njava.version\u003d1.4.2\njava.vendor\u003dSun Microsystems Inc.\nBootLoader constants: OS\u003dlinux, ARCH\u003dx86, WS\u003dgtk, NL\u003dpt_BR\nCommand-line arguments: -os linux -ws gtk -arch x86\n!ENTRY org.eclipse.ui 4 4 Fev 03, 2004 19:35:21.481\n!MESSAGE Unhandled event loop exception\n!ENTRY org.eclipse.ui 4 0 Fev 03, 2004 19:35:21.495\n!MESSAGE java.lang.NullPointerException\n!STACK 0\njava.lang.NullPointerException\n        at\norg.eclipse.jdt.internal.ui.javaeditor.JavaEditor.setSelection(JavaEditor.java:1904)\n        at\norg.eclipse.jdt.internal.ui.javaeditor.JavaEditor$EditorSelectionChangedListener.selectionChanged(JavaEditor.java:271)\n        at\norg.eclipse.jdt.internal.ui.javaeditor.JavaEditor$EditorSelectionChangedListener.selectionChanged(JavaEditor.java:264)\n        at\norg.eclipse.jface.text.TextViewer.firePostSelectionChanged(TextViewer.java:2157)\n        at\norg.eclipse.jface.text.TextViewer.firePostSelectionChanged(TextViewer.java:2110)\n        at org.eclipse.jface.text.TextViewer$4.run(TextViewer.java:2089)\n        at org.eclipse.swt.widgets.Display.timerProc(Display.java:2188)\n        at org.eclipse.swt.internal.gtk.OS.gtk_main_iteration(Native Method)\n        at org.eclipse.swt.widgets.Display.readAndDispatch(Display.java:1628)\n        at org.eclipse.ui.internal.Workbench.runEventLoop(Workbench.java:1531)\n        at org.eclipse.ui.internal.Workbench.runUI(Workbench.java:1507)\n        at\norg.eclipse.ui.internal.Workbench.createAndRunWorkbench(Workbench.java:265)\n        at org.eclipse.ui.PlatformUI.createAndRunWorkbench(PlatformUI.java:139)\n        at org.eclipse.ui.internal.ide.IDEApplication.run(IDEApplication.java:47)\n        at\norg.eclipse.core.internal.runtime.PlatformActivator$1.run(PlatformActivator.java:248)\n        at\norg.eclipse.core.runtime.adaptor.EclipseStarter.run(EclipseStarter.java:85)\n        at sun.reflect.NativeMethodAccessorImpl.invoke0(Native Method)\n        at\nsun.reflect.NativeMethodAccessorImpl.invoke(NativeMethodAccessorImpl.java:39)\n        at\nsun.reflect.DelegatingMethodAccessorImpl.invoke(DelegatingMethodAccessorImpl.java:25)\n        at java.lang.reflect.Method.invoke(Method.java:324)\n        at org.eclipse.core.launcher.Main.basicRun(Main.java:279)\n        at org.eclipse.core.launcher.Main.run(Main.java:742)\n        at org.eclipse.core.launcher.Main.main(Main.java:581)",
    "Which build?",
    "Cannot reproduce either. This looks like a side-effect of another bug: when\nshutting down we first unregister the listeners and then null-out the fields.\n\nWe need the build Id in order to map the line number to the code where the NPE\nhappens.",
    "waiting for answer",
    "Get rid of deprecated state.",
    "."
  ],
  "commentCreationDates": [
    "2004-02-03T21:43:07+01:00",
    "2004-02-06T07:27:40+01:00",
    "2004-02-06T14:15:34+01:00",
    "2004-08-29T22:56:38+02:00",
    "2007-06-22T15:59:06+02:00",
    "2007-06-22T16:04:25+02:00"
  ],
  "traces": [
    {
      "exceptionType": "java.lang.NullPointerException",
      "elements": [
        {
          "method": "org.eclipse.jdt.internal.ui.javaeditor.JavaEditor.setSelection",
          "source": "JavaEditor.java:1904"
        },
        {
          "method": "org.eclipse.jdt.internal.ui.javaeditor.JavaEditor$EditorSelectionChangedListener.selectionChanged",
          "source": "JavaEditor.java:271"
        },
        {
          "method": "org.eclipse.jdt.internal.ui.javaeditor.JavaEditor$EditorSelectionChangedListener.selectionChanged",
          "source": "JavaEditor.java:264"
        },
        {
          "method": "org.eclipse.jface.text.TextViewer.firePostSelectionChanged",
          "source": "TextViewer.java:2157"
        },
        {
          "method": "org.eclipse.jface.text.TextViewer.firePostSelectionChanged",
          "source": "TextViewer.java:2110"
        },
        {
          "method": "org.eclipse.jface.text.TextViewer$4.run",
          "source": "TextViewer.java:2089"
        },
        {
          "method": "org.eclipse.swt.widgets.Display.timerProc",
          "source": "Display.java:2188"
        },
        {
          "method": "org.eclipse.swt.internal.gtk.OS.gtk_main_iteration",
          "source": "Native Method"
        },
        {
          "method": "org.eclipse.swt.widgets.Display.readAndDispatch",
          "source": "Display.java:1628"
        },
        {
          "method": "org.eclipse.ui.internal.Workbench.runEventLoop",
          "source": "Workbench.java:1531"
        },
        {
          "method": "org.eclipse.ui.internal.Workbench.runUI",
          "source": "Workbench.java:1507"
        },
        {
          "method": "org.eclipse.ui.internal.Workbench.createAndRunWorkbench",
          "source": "Workbench.java:265"
        },
        {
          "method": "org.eclipse.ui.PlatformUI.createAndRunWorkbench",
          "source": "PlatformUI.java:139"
        },
        {
          "method": "org.eclipse.ui.internal.ide.IDEApplication.run",
          "source": "IDEApplication.java:47"
        },
        {
          "method": "org.eclipse.core.internal.runtime.PlatformActivator$1.run",
          "source": "PlatformActivator.java:248"
        },
        {
          "method": "org.eclipse.core.runtime.adaptor.EclipseStarter.run",
          "source": "EclipseStarter.java:85"
        },
        {
          "method": "sun.reflect.NativeMethodAccessorImpl.invoke0",
          "source": "Native Method"
        },
        {
          "method": "sun.reflect.NativeMethodAccessorImpl.invoke",
          "source": "NativeMethodAccessorImpl.java:39"
        },
        {
          "method": "sun.reflect.DelegatingMethodAccessorImpl.invoke",
          "source": "DelegatingMethodAccessorImpl.java:25"
        },
        {
          "method": "java.lang.reflect.Method.invoke",
          "source": "Method.java:324"
        },
        {
          "method": "org.eclipse.core.launcher.Main.basicRun",
          "source": "Main.java:279"
        },
        {
          "method": "org.eclipse.core.launcher.Main.run",
          "source": "Main.java:742"
        },
        {
          "method": "org.eclipse.core.launcher.Main.main",
          "source": "Main.java:581"
        }
      ],
      "number": 0,
      "commentIndex": 0,
      "bugId": "51138",
      "date": "2004-02-03T21:43:07+01:00",
      "product": "JDT",
      "component": "Text",
      "severity": "normal"
    }
  ],
  "groupId": "51138",
  "bugId": "51138",
  "date": "2004-02-03T21:43:07+01:00",
  "product": "JDT",
  "component": "Text",
  "severity": "normal"
}