{
  "comments": [
    "3.0 M6 (200312182000)\n\nI was trying to open the context menu of an XML file containing a DTD and the \nUI (and windows) was unresponsive for a minute or so.  The file referenced a \nDTD at sourceforge.net, which was unresponsive to http requests.\n\nIt looks like the XML parser in PropertyParser was trying to load the DTD and \neventually gave up when a connection could not be established.  The code in \nPropertyParser does say DTD loading is normal, but is there any way it can be \ndone in another thread?  I would assume somehitng similar would be observeable \nwith a slow internet connection.\n\nHere is the stacktrace:\n\njava.net.ConnectException: Connection timed out: connect\nat org.apache.crimson.parser.Parser2.fatal(Unknown Source)\nat org.apache.crimson.parser.Parser2.externalParameterEntity(Unknown Source)\nat org.apache.crimson.parser.Parser2.maybeDoctypeDecl(Unknown Source)\nat org.apache.crimson.parser.Parser2.parseInternal(Unknown Source)\nat org.apache.crimson.parser.Parser2.parse(Unknown Source)\nat org.apache.crimson.parser.XMLReaderImpl.parse(Unknown Source)\nat javax.xml.parsers.SAXParser.parse(Unknown Source)\nat javax.xml.parsers.SAXParser.parse(Unknown Source)\nat org.eclipse.ui.internal.ide.model.PropertyParser.parseResource\n(PropertyParser.java:125)\nat org.eclipse.ui.internal.ide.model.WorkbenchResource.testXMLProperty\n(WorkbenchResource.java:243)\nat org.eclipse.ui.internal.ide.model.WorkbenchResource.testAttribute\n(WorkbenchResource.java:118)",
    "\n\n*** This bug has been marked as a duplicate of 51008 ***"
  ],
  "commentCreationDates": [
    "2004-02-04T09:22:42+01:00",
    "2004-02-04T13:37:26+01:00"
  ],
  "traces": [
    {
      "exceptionType": "java.net.ConnectException",
      "message": "Connection timed out: connect",
      "elements": [
        {
          "method": "org.apache.crimson.parser.Parser2.fatal",
          "source": "Unknown Source"
        },
        {
          "method": "org.apache.crimson.parser.Parser2.externalParameterEntity",
          "source": "Unknown Source"
        },
        {
          "method": "org.apache.crimson.parser.Parser2.maybeDoctypeDecl",
          "source": "Unknown Source"
        },
        {
          "method": "org.apache.crimson.parser.Parser2.parseInternal",
          "source": "Unknown Source"
        },
        {
          "method": "org.apache.crimson.parser.Parser2.parse",
          "source": "Unknown Source"
        },
        {
          "method": "org.apache.crimson.parser.XMLReaderImpl.parse",
          "source": "Unknown Source"
        },
        {
          "method": "javax.xml.parsers.SAXParser.parse",
          "source": "Unknown Source"
        },
        {
          "method": "javax.xml.parsers.SAXParser.parse",
          "source": "Unknown Source"
        },
        {
          "method": "org.eclipse.ui.internal.ide.model.PropertyParser.parseResource",
          "source": "PropertyParser.java:125"
        },
        {
          "method": "org.eclipse.ui.internal.ide.model.WorkbenchResource.testXMLProperty",
          "source": "WorkbenchResource.java:243"
        },
        {
          "method": "org.eclipse.ui.internal.ide.model.WorkbenchResource.testAttribute",
          "source": "WorkbenchResource.java:118"
        }
      ],
      "number": 0,
      "commentIndex": 0,
      "bugId": "51152",
      "duplicateId": "51008",
      "date": "2004-02-04T09:22:42+01:00",
      "product": "Platform",
      "component": "UI",
      "severity": "normal"
    }
  ],
  "groupId": "51008",
  "bugId": "51152",
  "duplicateId": "51008",
  "date": "2004-02-04T09:22:42+01:00",
  "product": "Platform",
  "component": "UI",
  "severity": "normal"
}