{
  "comments": [
    "Introduce method with an unknown type as an arguement as follows:\nclass A {}\npublic abstract aspect B\n{\n  public void A.someMethod(WCharType a) { //blah }\n}\n\nWCharType is an unknown type or is forgotten to be imported (in my case).\n\nThis shall cause ajc to puke the following:\njava.lang.NullPointerException\n        at\norg.aspectj.ajdt.internal.compiler.ast.InterTypeMethodDeclaration.build(InterTypeMethodDeclaration\n.java:87)\n        at\norg.aspectj.ajdt.internal.compiler.ast.AspectDeclaration.buildInterTypeAndPerClause(AspectDeclarat\nion.java:744)\n        at\norg.aspectj.ajdt.internal.compiler.lookup.AjLookupEnvironment.buildInterTypeAndPerClause(AjLookupE\nnvironment.java:206)\n        at\norg.aspectj.ajdt.internal.compiler.lookup.AjLookupEnvironment.completeTypeBindings(AjLookupEnviron\nment.java:94)\n        at\norg.eclipse.jdt.internal.compiler.Compiler.beginToCompile(Compiler.java:310)\n        at org.eclipse.jdt.internal.compiler.Compiler.compile(Compiler.java:324)\n        at\norg.aspectj.ajdt.internal.core.builder.AjBuildManager.performCompilation(AjBuildManager.java:373)\n        at\norg.aspectj.ajdt.internal.core.builder.AjBuildManager.doBuild(AjBuildManager.java:125)\n        at\norg.aspectj.ajdt.internal.core.builder.AjBuildManager.batchBuild(AjBuildManager.java:70)\n        at org.aspectj.ajdt.ajc.AjdtCommand.doCommand(AjdtCommand.java:99)\n        at org.aspectj.ajdt.ajc.AjdtCommand.runCommand(AjdtCommand.java:53)\n        at org.aspectj.tools.ajc.Main.run(Main.java:217)\n        at org.aspectj.tools.ajc.Main.runMain(Main.java:155)\n        at org.aspectj.tools.ajc.Main.main(Main.java:72)\n/home/czhang/eclipse/workspace/lib/libajob/org/omg/PortableServer/portable/Delegate.java:0\nInternal compiler error\njava.lang.NullPointerException\n        at\norg.aspectj.ajdt.internal.compiler.ast.InterTypeMethodDeclaration.build(InterTypeMethodDeclaration\n.java:87)\n        at\norg.aspectj.ajdt.internal.compiler.ast.AspectDeclaration.buildInterTypeAndPerClause(AspectDeclarat\nion.java:744)\n        at\norg.aspectj.ajdt.internal.compiler.lookup.AjLookupEnvironment.buildInterTypeAndPerClause(AjLookupE\nnvironment.java:206)\n        at\norg.aspectj.ajdt.internal.compiler.lookup.AjLookupEnvironment.completeTypeBindings(AjLookupEnviron\nment.java:94)\n        at\norg.eclipse.jdt.internal.compiler.Compiler.beginToCompile(Compiler.java:310)\n        at org.eclipse.jdt.internal.compiler.Compiler.compile(Compiler.java:324)\n        at\norg.aspectj.ajdt.internal.core.builder.AjBuildManager.performCompilation(AjBuildManager.java:373)\n        at\norg.aspectj.ajdt.internal.core.builder.AjBuildManager.doBuild(AjBuildManager.java:125)\n        at\norg.aspectj.ajdt.internal.core.builder.AjBuildManager.batchBuild(AjBuildManager.java:70)\n        at org.aspectj.ajdt.ajc.AjdtCommand.doCommand(AjdtCommand.java:99)\n        at org.aspectj.ajdt.ajc.AjdtCommand.runCommand(AjdtCommand.java:53)\n        at org.aspectj.tools.ajc.Main.run(Main.java:217)\n        at org.aspectj.tools.ajc.Main.runMain(Main.java:155)\n        at org.aspectj.tools.ajc.Main.main(Main.java:72)\n \n \n!! no source information available !!\n!! no source information available !!\nABORT\nException thrown from AspectJ 1.1.1\n \nThis might be logged as a bug already -- find current bugs at\n  http://bugs.eclipse.org/bugs/buglist.cgi?product\u003dAspectJ\u0026component\u003dCompiler\n \nBugs for exceptions thrown have titles File:line from the top stack,\ne.g., \"SomeFile.java:243\"\n \nIf you don\u0027t find the exception below in a bug, please add a new bug\nat http://bugs.eclipse.org/bugs/enter_bug.cgi?product\u003dAspectJ\nTo make the bug a priority, please include a test program\nthat can reproduce this exception.\nnull\njava.lang.NullPointerException\n        at\norg.aspectj.ajdt.internal.compiler.ast.InterTypeMethodDeclaration.build(InterTypeMethodDeclaration\n.java:87)\n        at\norg.aspectj.ajdt.internal.compiler.ast.AspectDeclaration.buildInterTypeAndPerClause(AspectDeclarat\nion.java:744)\n        at\norg.aspectj.ajdt.internal.compiler.lookup.AjLookupEnvironment.buildInterTypeAndPerClause(AjLookupE\nnvironment.java:206)\n        at\norg.aspectj.ajdt.internal.compiler.lookup.AjLookupEnvironment.completeTypeBindings(AjLookupEnviron\nment.java:94)\n        at\norg.eclipse.jdt.internal.compiler.Compiler.beginToCompile(Compiler.java:310)\n        at org.eclipse.jdt.internal.compiler.Compiler.compile(Compiler.java:324)\n        at\norg.aspectj.ajdt.internal.core.builder.AjBuildManager.performCompilation(AjBuildManager.java:373)\n        at\norg.aspectj.ajdt.internal.core.builder.AjBuildManager.doBuild(AjBuildManager.java:125)\n        at\norg.aspectj.ajdt.internal.core.builder.AjBuildManager.batchBuild(AjBuildManager.java:70)\n        at org.aspectj.ajdt.ajc.AjdtCommand.doCommand(AjdtCommand.java:99)\n        at org.aspectj.ajdt.ajc.AjdtCommand.runCommand(AjdtCommand.java:53)\n        at org.aspectj.tools.ajc.Main.run(Main.java:217)\n        at org.aspectj.tools.ajc.Main.runMain(Main.java:155)\n        at org.aspectj.tools.ajc.Main.main(Main.java:72)\n \n \n1 fail|abort, 1 error",
    "Now fixed in tree."
  ],
  "commentCreationDates": [
    "2004-02-07T22:11:16+01:00",
    "2004-03-15T22:43:09+01:00"
  ],
  "traces": [
    {
      "exceptionType": "java.lang.NullPointerException",
      "elements": [
        {
          "method": "org.aspectj.ajdt.internal.compiler.ast.InterTypeMethodDeclaration.build",
          "source": "InterTypeMethodDeclaration .java:87"
        },
        {
          "method": "org.aspectj.ajdt.internal.compiler.ast.AspectDeclaration.buildInterTypeAndPerClause",
          "source": "AspectDeclarat ion.java:744"
        },
        {
          "method": "org.aspectj.ajdt.internal.compiler.lookup.AjLookupEnvironment.buildInterTypeAndPerClause",
          "source": "AjLookupE nvironment.java:206"
        },
        {
          "method": "org.aspectj.ajdt.internal.compiler.lookup.AjLookupEnvironment.completeTypeBindings",
          "source": "AjLookupEnviron ment.java:94"
        },
        {
          "method": "org.eclipse.jdt.internal.compiler.Compiler.beginToCompile",
          "source": "Compiler.java:310"
        },
        {
          "method": "org.eclipse.jdt.internal.compiler.Compiler.compile",
          "source": "Compiler.java:324"
        },
        {
          "method": "org.aspectj.ajdt.internal.core.builder.AjBuildManager.performCompilation",
          "source": "AjBuildManager.java:373"
        },
        {
          "method": "org.aspectj.ajdt.internal.core.builder.AjBuildManager.doBuild",
          "source": "AjBuildManager.java:125"
        },
        {
          "method": "org.aspectj.ajdt.internal.core.builder.AjBuildManager.batchBuild",
          "source": "AjBuildManager.java:70"
        },
        {
          "method": "org.aspectj.ajdt.ajc.AjdtCommand.doCommand",
          "source": "AjdtCommand.java:99"
        },
        {
          "method": "org.aspectj.ajdt.ajc.AjdtCommand.runCommand",
          "source": "AjdtCommand.java:53"
        },
        {
          "method": "org.aspectj.tools.ajc.Main.run",
          "source": "Main.java:217"
        },
        {
          "method": "org.aspectj.tools.ajc.Main.runMain",
          "source": "Main.java:155"
        },
        {
          "method": "org.aspectj.tools.ajc.Main.main",
          "source": "Main.java:72"
        }
      ],
      "number": 0,
      "commentIndex": 0,
      "bugId": "51322",
      "date": "2004-02-07T22:11:16+01:00",
      "product": "AspectJ",
      "component": "Compiler",
      "severity": "normal"
    },
    {
      "exceptionType": "java.lang.NullPointerException",
      "elements": [
        {
          "method": "org.aspectj.ajdt.internal.compiler.ast.InterTypeMethodDeclaration.build",
          "source": "InterTypeMethodDeclaration .java:87"
        },
        {
          "method": "org.aspectj.ajdt.internal.compiler.ast.AspectDeclaration.buildInterTypeAndPerClause",
          "source": "AspectDeclarat ion.java:744"
        },
        {
          "method": "org.aspectj.ajdt.internal.compiler.lookup.AjLookupEnvironment.buildInterTypeAndPerClause",
          "source": "AjLookupE nvironment.java:206"
        },
        {
          "method": "org.aspectj.ajdt.internal.compiler.lookup.AjLookupEnvironment.completeTypeBindings",
          "source": "AjLookupEnviron ment.java:94"
        },
        {
          "method": "org.eclipse.jdt.internal.compiler.Compiler.beginToCompile",
          "source": "Compiler.java:310"
        },
        {
          "method": "org.eclipse.jdt.internal.compiler.Compiler.compile",
          "source": "Compiler.java:324"
        },
        {
          "method": "org.aspectj.ajdt.internal.core.builder.AjBuildManager.performCompilation",
          "source": "AjBuildManager.java:373"
        },
        {
          "method": "org.aspectj.ajdt.internal.core.builder.AjBuildManager.doBuild",
          "source": "AjBuildManager.java:125"
        },
        {
          "method": "org.aspectj.ajdt.internal.core.builder.AjBuildManager.batchBuild",
          "source": "AjBuildManager.java:70"
        },
        {
          "method": "org.aspectj.ajdt.ajc.AjdtCommand.doCommand",
          "source": "AjdtCommand.java:99"
        },
        {
          "method": "org.aspectj.ajdt.ajc.AjdtCommand.runCommand",
          "source": "AjdtCommand.java:53"
        },
        {
          "method": "org.aspectj.tools.ajc.Main.run",
          "source": "Main.java:217"
        },
        {
          "method": "org.aspectj.tools.ajc.Main.runMain",
          "source": "Main.java:155"
        },
        {
          "method": "org.aspectj.tools.ajc.Main.main",
          "source": "Main.java:72"
        }
      ],
      "number": 1,
      "commentIndex": 0,
      "bugId": "51322",
      "date": "2004-02-07T22:11:16+01:00",
      "product": "AspectJ",
      "component": "Compiler",
      "severity": "normal"
    },
    {
      "exceptionType": "java.lang.NullPointerException",
      "elements": [
        {
          "method": "org.aspectj.ajdt.internal.compiler.ast.InterTypeMethodDeclaration.build",
          "source": "InterTypeMethodDeclaration .java:87"
        },
        {
          "method": "org.aspectj.ajdt.internal.compiler.ast.AspectDeclaration.buildInterTypeAndPerClause",
          "source": "AspectDeclarat ion.java:744"
        },
        {
          "method": "org.aspectj.ajdt.internal.compiler.lookup.AjLookupEnvironment.buildInterTypeAndPerClause",
          "source": "AjLookupE nvironment.java:206"
        },
        {
          "method": "org.aspectj.ajdt.internal.compiler.lookup.AjLookupEnvironment.completeTypeBindings",
          "source": "AjLookupEnviron ment.java:94"
        },
        {
          "method": "org.eclipse.jdt.internal.compiler.Compiler.beginToCompile",
          "source": "Compiler.java:310"
        },
        {
          "method": "org.eclipse.jdt.internal.compiler.Compiler.compile",
          "source": "Compiler.java:324"
        },
        {
          "method": "org.aspectj.ajdt.internal.core.builder.AjBuildManager.performCompilation",
          "source": "AjBuildManager.java:373"
        },
        {
          "method": "org.aspectj.ajdt.internal.core.builder.AjBuildManager.doBuild",
          "source": "AjBuildManager.java:125"
        },
        {
          "method": "org.aspectj.ajdt.internal.core.builder.AjBuildManager.batchBuild",
          "source": "AjBuildManager.java:70"
        },
        {
          "method": "org.aspectj.ajdt.ajc.AjdtCommand.doCommand",
          "source": "AjdtCommand.java:99"
        },
        {
          "method": "org.aspectj.ajdt.ajc.AjdtCommand.runCommand",
          "source": "AjdtCommand.java:53"
        },
        {
          "method": "org.aspectj.tools.ajc.Main.run",
          "source": "Main.java:217"
        },
        {
          "method": "org.aspectj.tools.ajc.Main.runMain",
          "source": "Main.java:155"
        },
        {
          "method": "org.aspectj.tools.ajc.Main.main",
          "source": "Main.java:72"
        }
      ],
      "number": 2,
      "commentIndex": 0,
      "bugId": "51322",
      "date": "2004-02-07T22:11:16+01:00",
      "product": "AspectJ",
      "component": "Compiler",
      "severity": "normal"
    }
  ],
  "groupId": "51322",
  "bugId": "51322",
  "date": "2004-02-07T22:11:16+01:00",
  "product": "AspectJ",
  "component": "Compiler",
  "severity": "normal"
}