{
  "comments": [
    "Happens repeatedly.  Right-clicking on a item in the synchronize tree view does\nnot bring up a context menu.  Prevents me from doing an \"open with\".\n\n\njava.lang.ClassCastException\n        at\norg.eclipse.team.internal.ui.synchronize.actions.OpenWithActionGroup.fillContextMenu(OpenWithActionGroup.java:48)\n        at\norg.eclipse.team.ui.synchronize.TeamSubscriberParticipantPage.setContextMenu(TeamSubscriberParticipantPage.java:215)\n        at\norg.eclipse.team.ui.synchronize.TeamSubscriberParticipantPage.access$0(TeamSubscriberParticipantPage.java:214)\n        at\norg.eclipse.team.ui.synchronize.TeamSubscriberParticipantPage$3.menuAboutToShow(TeamSubscriberParticipantPage.java:185)\n        at\norg.eclipse.jface.action.MenuManager.fireAboutToShow(MenuManager.java:286)\n        at\norg.eclipse.jface.action.MenuManager.handleAboutToShow(MenuManager.java:370)\n        at org.eclipse.jface.action.MenuManager.access$0(MenuManager.java:367)\n        at org.eclipse.jface.action.MenuManager$2.menuShown(MenuManager.java:383)\n        at org.eclipse.swt.widgets.TypedListener.handleEvent(TypedListener.java:116)\n        at org.eclipse.swt.widgets.EventTable.sendEvent(EventTable.java:82)\n        at org.eclipse.swt.widgets.Widget.sendEvent(Widget.java:953)\n        at org.eclipse.swt.widgets.Widget.sendEvent(Widget.java:977)\n        at org.eclipse.swt.widgets.Widget.sendEvent(Widget.java:958)\n        at org.eclipse.swt.widgets.Menu._setVisible(Menu.java:174)\n        at org.eclipse.swt.widgets.Display.runPopups(Display.java:1894)\n        at org.eclipse.swt.widgets.Display.readAndDispatch(Display.java:1639)\n        at org.eclipse.ui.internal.Workbench.runEventLoop(Workbench.java:1550)\n        at org.eclipse.ui.internal.Workbench.runUI(Workbench.java:1526)\n        at\norg.eclipse.ui.internal.Workbench.createAndRunWorkbench(Workbench.java:265)\n        at org.eclipse.ui.PlatformUI.createAndRunWorkbench(PlatformUI.java:139)\n        at org.eclipse.ui.internal.ide.IDEApplication.run(IDEApplication.java:47)\n        at\norg.eclipse.core.internal.runtime.PlatformActivator$1.run(PlatformActivator.java:236)\n        at\norg.eclipse.core.runtime.adaptor.EclipseStarter.run(EclipseStarter.java:101)\n        at sun.reflect.NativeMethodAccessorImpl.invoke0(Native Method)\n        at\nsun.reflect.NativeMethodAccessorImpl.invoke(NativeMethodAccessorImpl.java:39)\n        at\nsun.reflect.DelegatingMethodAccessorImpl.invoke(DelegatingMethodAccessorImpl.java:25)\n        at java.lang.reflect.Method.invoke(Method.java:324)\n        at org.eclipse.core.launcher.Main.basicRun(Main.java:279)\n        at org.eclipse.core.launcher.Main.run(Main.java:742)\n        at org.eclipse.core.launcher.Main.main(Main.java:581)",
    "Looks like we expect an IStructuredSelection but it is something else. What is \nselected at the time of the operation? I don\u0027t get this on windows so perhaps \nthere is a difference in how selections are handled on GTK. Will investigate.",
    "One of the files in the Synchronize View.  In this case, I believe it was a\n\"plugin.xml\" file.   But, I believe I may have seen this happen on other types\nof files.",
    "Moving to M8 as I cannot reproduce this. We need to change the selection \nhandling code to ensure that the selection is an IStructuredSelection.",
    "Fix released to HEAD"
  ],
  "commentCreationDates": [
    "2004-02-09T20:32:06+01:00",
    "2004-02-09T21:02:58+01:00",
    "2004-02-09T21:10:46+01:00",
    "2004-02-11T18:48:01+01:00",
    "2004-03-23T03:21:01+01:00"
  ],
  "traces": [
    {
      "exceptionType": "java.lang.ClassCastException",
      "elements": [
        {
          "method": "org.eclipse.team.internal.ui.synchronize.actions.OpenWithActionGroup.fillContextMenu",
          "source": "OpenWithActionGroup.java:48"
        },
        {
          "method": "org.eclipse.team.ui.synchronize.TeamSubscriberParticipantPage.setContextMenu",
          "source": "TeamSubscriberParticipantPage.java:215"
        },
        {
          "method": "org.eclipse.team.ui.synchronize.TeamSubscriberParticipantPage.access$0",
          "source": "TeamSubscriberParticipantPage.java:214"
        },
        {
          "method": "org.eclipse.team.ui.synchronize.TeamSubscriberParticipantPage$3.menuAboutToShow",
          "source": "TeamSubscriberParticipantPage.java:185"
        },
        {
          "method": "org.eclipse.jface.action.MenuManager.fireAboutToShow",
          "source": "MenuManager.java:286"
        },
        {
          "method": "org.eclipse.jface.action.MenuManager.handleAboutToShow",
          "source": "MenuManager.java:370"
        },
        {
          "method": "org.eclipse.jface.action.MenuManager.access$0",
          "source": "MenuManager.java:367"
        },
        {
          "method": "org.eclipse.jface.action.MenuManager$2.menuShown",
          "source": "MenuManager.java:383"
        },
        {
          "method": "org.eclipse.swt.widgets.TypedListener.handleEvent",
          "source": "TypedListener.java:116"
        },
        {
          "method": "org.eclipse.swt.widgets.EventTable.sendEvent",
          "source": "EventTable.java:82"
        },
        {
          "method": "org.eclipse.swt.widgets.Widget.sendEvent",
          "source": "Widget.java:953"
        },
        {
          "method": "org.eclipse.swt.widgets.Widget.sendEvent",
          "source": "Widget.java:977"
        },
        {
          "method": "org.eclipse.swt.widgets.Widget.sendEvent",
          "source": "Widget.java:958"
        },
        {
          "method": "org.eclipse.swt.widgets.Menu._setVisible",
          "source": "Menu.java:174"
        },
        {
          "method": "org.eclipse.swt.widgets.Display.runPopups",
          "source": "Display.java:1894"
        },
        {
          "method": "org.eclipse.swt.widgets.Display.readAndDispatch",
          "source": "Display.java:1639"
        },
        {
          "method": "org.eclipse.ui.internal.Workbench.runEventLoop",
          "source": "Workbench.java:1550"
        },
        {
          "method": "org.eclipse.ui.internal.Workbench.runUI",
          "source": "Workbench.java:1526"
        },
        {
          "method": "org.eclipse.ui.internal.Workbench.createAndRunWorkbench",
          "source": "Workbench.java:265"
        },
        {
          "method": "org.eclipse.ui.PlatformUI.createAndRunWorkbench",
          "source": "PlatformUI.java:139"
        },
        {
          "method": "org.eclipse.ui.internal.ide.IDEApplication.run",
          "source": "IDEApplication.java:47"
        },
        {
          "method": "org.eclipse.core.internal.runtime.PlatformActivator$1.run",
          "source": "PlatformActivator.java:236"
        },
        {
          "method": "org.eclipse.core.runtime.adaptor.EclipseStarter.run",
          "source": "EclipseStarter.java:101"
        },
        {
          "method": "sun.reflect.NativeMethodAccessorImpl.invoke0",
          "source": "Native Method"
        },
        {
          "method": "sun.reflect.NativeMethodAccessorImpl.invoke",
          "source": "NativeMethodAccessorImpl.java:39"
        },
        {
          "method": "sun.reflect.DelegatingMethodAccessorImpl.invoke",
          "source": "DelegatingMethodAccessorImpl.java:25"
        },
        {
          "method": "java.lang.reflect.Method.invoke",
          "source": "Method.java:324"
        },
        {
          "method": "org.eclipse.core.launcher.Main.basicRun",
          "source": "Main.java:279"
        },
        {
          "method": "org.eclipse.core.launcher.Main.run",
          "source": "Main.java:742"
        },
        {
          "method": "org.eclipse.core.launcher.Main.main",
          "source": "Main.java:581"
        }
      ],
      "number": 0,
      "commentIndex": 0,
      "bugId": "51394",
      "date": "2004-02-09T20:32:06+01:00",
      "product": "Platform",
      "component": "Team",
      "severity": "major"
    }
  ],
  "groupId": "51394",
  "bugId": "51394",
  "date": "2004-02-09T20:32:06+01:00",
  "product": "Platform",
  "component": "Team",
  "severity": "major"
}