{
  "comments": [
    "Whenever running an Ant script in build 205, I get the following stack trace \ndumped in the log:\n\njava.lang.UnsatisfiedLinkError: no core203  (core203.dll) in java.library.path\n        at java.lang.ClassLoader.loadLibrary(ClassLoader.java:1380)\n        at java.lang.Runtime.loadLibrary0(Runtime.java:766)\n        at java.lang.System.loadLibrary(System.java:849)\n        at org.eclipse.ant.core.EclipseProject.\u003cclinit\u003e(EclipseProject.java:40)\n        at org.eclipse.ant.internal.ui.AntAction.extractProject(AntAction.java:6\n2)\n        at org.eclipse.ant.internal.ui.AntAction.run(AntAction.java:49)\n        at org.eclipse.ant.internal.ui.RunAntActionDelegate.run(RunAntActionDele\ngate.java:43)\n        at org.eclipse.ui.internal.PluginAction.run(PluginAction.java:125)\n        at org.eclipse.jface.action.Action.runWithEvent(Action.java:451)\n        at org.eclipse.jface.action.ActionContributionItem.handleWidgetSelection\n(ActionContributionItem.java:407)\n        at org.eclipse.jface.action.ActionContributionItem.handleWidgetEvent(Act\nionContributionItem.java:361)\n        at org.eclipse.jface.action.ActionContributionItem.access$0(ActionContri\nbutionItem.java:352)\n        at org.eclipse.jface.action.ActionContributionItem$ActionListener.handle\nEvent(ActionContributionItem.java:47)\n        at org.eclipse.swt.widgets.Widget.notifyListeners(Widget.java(Compiled C\node))\n        at org.eclipse.swt.widgets.Widget.notifyListeners(Widget.java(Compiled C\node))\n        at org.eclipse.swt.widgets.Display.runDeferredEvents(Display.java(Compil\ned Code))\n        at org.eclipse.swt.widgets.Display.readAndDispatch(Display.java(Compiled\n Code))\n        at org.eclipse.ui.internal.Workbench.runEventLoop(Workbench.java(Compile\nd Code))\n        at org.eclipse.ui.internal.Workbench.run(Workbench.java:658)\n        at org.eclipse.core.internal.boot.InternalBootLoader.run(InternalBootLoa\nder.java:820)\n        at org.eclipse.core.boot.BootLoader.run(BootLoader.java:285)\n        at java.lang.reflect.Method.invoke(Native Method)\n        at org.eclipse.core.launcher.Main.basicRun(Main.java:151)\n        at org.eclipse.core.launcher.Main.run(Main.java:433)\n        at org.eclipse.core.launcher.UIMain.main(UIMain.java:52)",
    "Fixed. Problem was not to include the libraries in the build.properties file.",
    "Fixed in v208"
  ],
  "commentCreationDates": [
    "2001-10-23T11:54:01+02:00",
    "2001-11-02T22:00:00+01:00",
    "2001-11-05T15:43:06+01:00"
  ],
  "traces": [
    {
      "exceptionType": "java.lang.UnsatisfiedLinkError",
      "message": "no core203  (core203.dll) in java.library.path",
      "elements": [
        {
          "method": "java.lang.ClassLoader.loadLibrary",
          "source": "ClassLoader.java:1380"
        },
        {
          "method": "java.lang.Runtime.loadLibrary0",
          "source": "Runtime.java:766"
        },
        {
          "method": "java.lang.System.loadLibrary",
          "source": "System.java:849"
        },
        {
          "method": "org.eclipse.ant.core.EclipseProject.\u003cclinit\u003e",
          "source": "EclipseProject.java:40"
        },
        {
          "method": "org.eclipse.ant.internal.ui.AntAction.extractProject",
          "source": "AntAction.java:6 2"
        },
        {
          "method": "org.eclipse.ant.internal.ui.AntAction.run",
          "source": "AntAction.java:49"
        },
        {
          "method": "org.eclipse.ant.internal.ui.RunAntActionDelegate.run",
          "source": "RunAntActionDele gate.java:43"
        },
        {
          "method": "org.eclipse.ui.internal.PluginAction.run",
          "source": "PluginAction.java:125"
        },
        {
          "method": "org.eclipse.jface.action.Action.runWithEvent",
          "source": "Action.java:451"
        },
        {
          "method": "org.eclipse.jface.action.ActionContributionItem.handleWidgetSelection",
          "source": "ActionContributionItem.java:407"
        },
        {
          "method": "org.eclipse.jface.action.ActionContributionItem.handleWidgetEvent",
          "source": "Act ionContributionItem.java:361"
        },
        {
          "method": "org.eclipse.jface.action.ActionContributionItem.access$0",
          "source": "ActionContri butionItem.java:352"
        },
        {
          "method": "org.eclipse.jface.action.ActionContributionItem$ActionListener.handleEvent",
          "source": "ActionContributionItem.java:47"
        },
        {
          "method": "org.eclipse.swt.widgets.Widget.notifyListeners",
          "source": "Widget.java(Compiled C ode)"
        },
        {
          "method": "org.eclipse.swt.widgets.Widget.notifyListeners",
          "source": "Widget.java(Compiled C ode)"
        },
        {
          "method": "org.eclipse.swt.widgets.Display.runDeferredEvents",
          "source": "Display.java(Compil ed Code)"
        },
        {
          "method": "org.eclipse.swt.widgets.Display.readAndDispatch",
          "source": "Display.java(Compiled  Code)"
        },
        {
          "method": "org.eclipse.ui.internal.Workbench.runEventLoop",
          "source": "Workbench.java(Compile d Code)"
        },
        {
          "method": "org.eclipse.ui.internal.Workbench.run",
          "source": "Workbench.java:658"
        },
        {
          "method": "org.eclipse.core.internal.boot.InternalBootLoader.run",
          "source": "InternalBootLoa der.java:820"
        },
        {
          "method": "org.eclipse.core.boot.BootLoader.run",
          "source": "BootLoader.java:285"
        },
        {
          "method": "java.lang.reflect.Method.invoke",
          "source": "Native Method"
        },
        {
          "method": "org.eclipse.core.launcher.Main.basicRun",
          "source": "Main.java:151"
        },
        {
          "method": "org.eclipse.core.launcher.Main.run",
          "source": "Main.java:433"
        },
        {
          "method": "org.eclipse.core.launcher.UIMain.main",
          "source": "UIMain.java:52"
        }
      ],
      "number": 0,
      "commentIndex": 0,
      "bugId": "5169",
      "date": "2001-10-23T11:54:01+02:00",
      "product": "Platform",
      "component": "Ant",
      "severity": "normal"
    }
  ],
  "groupId": "5169",
  "bugId": "5169",
  "date": "2001-10-23T11:54:01+02:00",
  "product": "Platform",
  "component": "Ant",
  "severity": "normal"
}