{
  "comments": [
    "I got the java.util.ConcurrentModificationException below when editing code.\n\nI was editing a unit test TestCase subclass. I commented out the last method in\nthe file. In the method above that one, I when to the last line in the method,\nhit \u003cEnter\u003e and typed \"assertF\" and ctrl-space. Around that time, a dialog poped\nup telling me to look at the log for an error. I got the following in the console:\n\nok\nRESULT\u003e Status OKorg.eclipse.team.cvs.core code\u003d0 ok null\n!ENTRY org.eclipse.core.runtime 4 2 Feb 11, 2004 15:40:04.656\n!MESSAGE Problems occurred when invoking code from plug-in:\n\"org.eclipse.core.runtime\".\n!STACK 0\njava.util.ConcurrentModificationException\n        at java.util.AbstractList$Itr.checkForComodification(AbstractList.java:448)\n        at java.util.AbstractList$Itr.next(AbstractList.java:419)\n        at\norg.eclipse.jdt.internal.ui.javaeditor.filebuffers.CompilationUnitDocumentProvider2$CompilationUnitAnnotation\nModel.endReporting(CompilationUnitDocumentProvider2.java:439)\n        at\norg.eclipse.jdt.internal.core.JavaModelManager$PerWorkingCopyInfo.endReporting(JavaModelManager.java:516)\n        at\norg.eclipse.jdt.internal.core.CompilationUnit.buildStructure(CompilationUnit.java:142)\n        at org.eclipse.jdt.internal.core.Openable.generateInfos(Openable.java:200)\n        at\norg.eclipse.jdt.internal.core.JavaElement.openWhenClosed(JavaElement.java:488)\n        at\norg.eclipse.jdt.internal.core.CompilationUnit.makeConsistent(CompilationUnit.java:933)\n        at\norg.eclipse.jdt.internal.core.ReconcileWorkingCopyOperation.executeOperation(ReconcileWorkingCopyOperation.ja\nva:49)\n        at\norg.eclipse.jdt.internal.core.JavaModelOperation.execute(JavaModelOperation.java:364)\n        at\norg.eclipse.jdt.internal.core.JavaModelOperation.run(JavaModelOperation.java:703)\n        at\norg.eclipse.jdt.internal.core.JavaElement.runOperation(JavaElement.java:524)\n        at\norg.eclipse.jdt.internal.core.CompilationUnit.reconcile(CompilationUnit.java:1050)\n        at\norg.eclipse.jdt.internal.core.CompilationUnit.reconcile(CompilationUnit.java:1022)\n        at\norg.eclipse.jdt.internal.core.CompilationUnit.reconcile(CompilationUnit.java:1015)\n        at\norg.eclipse.jdt.internal.ui.browsing.JavaBrowsingPart.getElementForInputAt(JavaBrowsingPart.java:1243)\n        at\norg.eclipse.jdt.internal.ui.browsing.JavaBrowsingPart.setSelectionFromEditor(JavaBrowsingPart.java:1135)\n        at\norg.eclipse.jdt.internal.ui.browsing.JavaBrowsingPart.selectionChanged(JavaBrowsingPart.java:687)\n        at\norg.eclipse.jdt.internal.ui.browsing.ProjectsView.selectionChanged(ProjectsView.java:214)\n        at\norg.eclipse.ui.internal.AbstractSelectionService$4.run(AbstractSelectionService.java:178)\n        at\norg.eclipse.core.internal.runtime.InternalPlatform.run(InternalPlatform.java:813)\n        at org.eclipse.core.runtime.Platform.run(Platform.java:457)\n        at\norg.eclipse.ui.internal.AbstractSelectionService.firePostSelection(AbstractSelectionService.java:176)\n        at\norg.eclipse.ui.internal.AbstractSelectionService$2.selectionChanged(AbstractSelectionService.java:76)\n        at\norg.eclipse.jface.text.TextViewer.firePostSelectionChanged(TextViewer.java:2151)\n        at\norg.eclipse.jface.text.TextViewer.firePostSelectionChanged(TextViewer.java:2104)\n        at org.eclipse.jface.text.TextViewer$4.run(TextViewer.java:2083)\n        at org.eclipse.swt.widgets.Display.runTimer(Display.java:2353)\n        at org.eclipse.swt.widgets.Display.messageProc(Display.java:1878)\n        at org.eclipse.swt.internal.win32.OS.DispatchMessageW(Native Method)\n        at org.eclipse.swt.internal.win32.OS.DispatchMessage(OS.java:1369)\n        at org.eclipse.swt.widgets.Display.readAndDispatch(Display.java:1990)\n        at org.eclipse.ui.internal.Workbench.runEventLoop(Workbench.java:1506)\n        at org.eclipse.ui.internal.Workbench.runUI(Workbench.java:1482)\n        at\norg.eclipse.ui.internal.Workbench.createAndRunWorkbench(Workbench.java:246)\n        at org.eclipse.ui.PlatformUI.createAndRunWorkbench(PlatformUI.java:139)\n        at org.eclipse.ui.internal.ide.IDEApplication.run(IDEApplication.java:47)\n        at\norg.eclipse.core.internal.runtime.PlatformActivator$1.run(PlatformActivator.java:226)\n        at\norg.eclipse.core.runtime.adaptor.EclipseStarter.run(EclipseStarter.java:85)\n        at sun.reflect.NativeMethodAccessorImpl.invoke0(Native Method)\n        at\nsun.reflect.NativeMethodAccessorImpl.invoke(NativeMethodAccessorImpl.java:39)\n        at\nsun.reflect.DelegatingMethodAccessorImpl.invoke(DelegatingMethodAccessorImpl.java:25)\n        at java.lang.reflect.Method.invoke(Method.java:324)\n        at org.eclipse.core.launcher.Main.basicRun(Main.java:279)\n        at org.eclipse.core.launcher.Main.run(Main.java:742)\n        at org.eclipse.core.launcher.Main.main(Main.java:581)",
    "Version 3.0.m6.",
    "\n\n*** This bug has been marked as a duplicate of 48057 ***"
  ],
  "commentCreationDates": [
    "2004-02-11T23:52:16+01:00",
    "2004-02-11T23:52:31+01:00",
    "2004-02-12T07:31:16+01:00"
  ],
  "traces": [
    {
      "exceptionType": "java.util.ConcurrentModificationException",
      "elements": [
        {
          "method": "java.util.AbstractList$Itr.checkForComodification",
          "source": "AbstractList.java:448"
        },
        {
          "method": "java.util.AbstractList$Itr.next",
          "source": "AbstractList.java:419"
        },
        {
          "method": "org.eclipse.jdt.internal.ui.javaeditor.filebuffers.CompilationUnitDocumentProvider2$CompilationUnitAnnotationModel.endReporting",
          "source": "CompilationUnitDocumentProvider2.java:439"
        },
        {
          "method": "org.eclipse.jdt.internal.core.JavaModelManager$PerWorkingCopyInfo.endReporting",
          "source": "JavaModelManager.java:516"
        },
        {
          "method": "org.eclipse.jdt.internal.core.CompilationUnit.buildStructure",
          "source": "CompilationUnit.java:142"
        },
        {
          "method": "org.eclipse.jdt.internal.core.Openable.generateInfos",
          "source": "Openable.java:200"
        },
        {
          "method": "org.eclipse.jdt.internal.core.JavaElement.openWhenClosed",
          "source": "JavaElement.java:488"
        },
        {
          "method": "org.eclipse.jdt.internal.core.CompilationUnit.makeConsistent",
          "source": "CompilationUnit.java:933"
        },
        {
          "method": "org.eclipse.jdt.internal.core.ReconcileWorkingCopyOperation.executeOperation",
          "source": "ReconcileWorkingCopyOperation.ja va:49"
        },
        {
          "method": "org.eclipse.jdt.internal.core.JavaModelOperation.execute",
          "source": "JavaModelOperation.java:364"
        },
        {
          "method": "org.eclipse.jdt.internal.core.JavaModelOperation.run",
          "source": "JavaModelOperation.java:703"
        },
        {
          "method": "org.eclipse.jdt.internal.core.JavaElement.runOperation",
          "source": "JavaElement.java:524"
        },
        {
          "method": "org.eclipse.jdt.internal.core.CompilationUnit.reconcile",
          "source": "CompilationUnit.java:1050"
        },
        {
          "method": "org.eclipse.jdt.internal.core.CompilationUnit.reconcile",
          "source": "CompilationUnit.java:1022"
        },
        {
          "method": "org.eclipse.jdt.internal.core.CompilationUnit.reconcile",
          "source": "CompilationUnit.java:1015"
        },
        {
          "method": "org.eclipse.jdt.internal.ui.browsing.JavaBrowsingPart.getElementForInputAt",
          "source": "JavaBrowsingPart.java:1243"
        },
        {
          "method": "org.eclipse.jdt.internal.ui.browsing.JavaBrowsingPart.setSelectionFromEditor",
          "source": "JavaBrowsingPart.java:1135"
        },
        {
          "method": "org.eclipse.jdt.internal.ui.browsing.JavaBrowsingPart.selectionChanged",
          "source": "JavaBrowsingPart.java:687"
        },
        {
          "method": "org.eclipse.jdt.internal.ui.browsing.ProjectsView.selectionChanged",
          "source": "ProjectsView.java:214"
        },
        {
          "method": "org.eclipse.ui.internal.AbstractSelectionService$4.run",
          "source": "AbstractSelectionService.java:178"
        },
        {
          "method": "org.eclipse.core.internal.runtime.InternalPlatform.run",
          "source": "InternalPlatform.java:813"
        },
        {
          "method": "org.eclipse.core.runtime.Platform.run",
          "source": "Platform.java:457"
        },
        {
          "method": "org.eclipse.ui.internal.AbstractSelectionService.firePostSelection",
          "source": "AbstractSelectionService.java:176"
        },
        {
          "method": "org.eclipse.ui.internal.AbstractSelectionService$2.selectionChanged",
          "source": "AbstractSelectionService.java:76"
        },
        {
          "method": "org.eclipse.jface.text.TextViewer.firePostSelectionChanged",
          "source": "TextViewer.java:2151"
        },
        {
          "method": "org.eclipse.jface.text.TextViewer.firePostSelectionChanged",
          "source": "TextViewer.java:2104"
        },
        {
          "method": "org.eclipse.jface.text.TextViewer$4.run",
          "source": "TextViewer.java:2083"
        },
        {
          "method": "org.eclipse.swt.widgets.Display.runTimer",
          "source": "Display.java:2353"
        },
        {
          "method": "org.eclipse.swt.widgets.Display.messageProc",
          "source": "Display.java:1878"
        },
        {
          "method": "org.eclipse.swt.internal.win32.OS.DispatchMessageW",
          "source": "Native Method"
        },
        {
          "method": "org.eclipse.swt.internal.win32.OS.DispatchMessage",
          "source": "OS.java:1369"
        },
        {
          "method": "org.eclipse.swt.widgets.Display.readAndDispatch",
          "source": "Display.java:1990"
        },
        {
          "method": "org.eclipse.ui.internal.Workbench.runEventLoop",
          "source": "Workbench.java:1506"
        },
        {
          "method": "org.eclipse.ui.internal.Workbench.runUI",
          "source": "Workbench.java:1482"
        },
        {
          "method": "org.eclipse.ui.internal.Workbench.createAndRunWorkbench",
          "source": "Workbench.java:246"
        },
        {
          "method": "org.eclipse.ui.PlatformUI.createAndRunWorkbench",
          "source": "PlatformUI.java:139"
        },
        {
          "method": "org.eclipse.ui.internal.ide.IDEApplication.run",
          "source": "IDEApplication.java:47"
        },
        {
          "method": "org.eclipse.core.internal.runtime.PlatformActivator$1.run",
          "source": "PlatformActivator.java:226"
        },
        {
          "method": "org.eclipse.core.runtime.adaptor.EclipseStarter.run",
          "source": "EclipseStarter.java:85"
        },
        {
          "method": "sun.reflect.NativeMethodAccessorImpl.invoke0",
          "source": "Native Method"
        },
        {
          "method": "sun.reflect.NativeMethodAccessorImpl.invoke",
          "source": "NativeMethodAccessorImpl.java:39"
        },
        {
          "method": "sun.reflect.DelegatingMethodAccessorImpl.invoke",
          "source": "DelegatingMethodAccessorImpl.java:25"
        },
        {
          "method": "java.lang.reflect.Method.invoke",
          "source": "Method.java:324"
        },
        {
          "method": "org.eclipse.core.launcher.Main.basicRun",
          "source": "Main.java:279"
        },
        {
          "method": "org.eclipse.core.launcher.Main.run",
          "source": "Main.java:742"
        },
        {
          "method": "org.eclipse.core.launcher.Main.main",
          "source": "Main.java:581"
        }
      ],
      "number": 0,
      "commentIndex": 0,
      "bugId": "51802",
      "duplicateId": "48057",
      "date": "2004-02-11T23:52:16+01:00",
      "product": "JDT",
      "component": "Text",
      "severity": "normal"
    }
  ],
  "groupId": "48057",
  "bugId": "51802",
  "duplicateId": "48057",
  "date": "2004-02-11T23:52:16+01:00",
  "product": "JDT",
  "component": "Text",
  "severity": "normal"
}