{
  "comments": [
    "I20040212 - 1200\n\nI found the following in my log when using today\u0027s noon build:\n\norg.eclipse.swt.SWTException: Widget is disposed\n\tat org.eclipse.swt.SWT.error(SWT.java:2608)\n\tat org.eclipse.swt.SWT.error(SWT.java:2538)\n\tat org.eclipse.swt.widgets.Widget.error(Widget.java:373)\n\tat org.eclipse.swt.widgets.Widget.checkWidget(Widget.java:309)\n\tat org.eclipse.swt.widgets.Widget.addDisposeListener(Widget.java:199)\n\tat\norg.eclipse.jface.text.AbstractInformationControlManager.install(AbstractInformationControlManager.java:347)",
    "Created an attachment (id\u003d7878)\nLog file showing stack trace\n",
    "This might be caused by the leak reported in bug 51866.\n",
    "FWIW, I just got an identical error with 3.0m7/WindowsXP when trying to save a\n.java file.  I\u0027ll attach the stack trace.",
    "Actually, rather than an attachment I\u0027ll just paste in the log entry here. \nAlso, I had left the computer for several hours and I think this was my first\nsave after the long break, though I could be wrong about that part.  Finally, I\nnoticed that Simon Tardell\u0027s \"Resources\" plugin is in the stack trace; it\u0027s\nconceivable that it\u0027s the culprit and not Eclipse.\n\n!ENTRY org.eclipse.ui 4 0 Feb 14, 2004 18:30:10.125\n!MESSAGE Widget is disposed\n!STACK 0\norg.eclipse.swt.SWTException: Widget is disposed\n        at org.eclipse.swt.SWT.error(SWT.java:2608)\n        at org.eclipse.swt.SWT.error(SWT.java:2538)\n        at org.eclipse.swt.widgets.Widget.error(Widget.java:377)\n        at org.eclipse.swt.widgets.Widget.checkWidget(Widget.java:306)\n        at org.eclipse.swt.widgets.Table.setSelection(Table.java:2068)\n        at\norg.eclipse.jface.viewers.TableViewer.setSelectionToWidget(TableViewer.java:658)\n        at\norg.eclipse.jface.viewers.StructuredViewer.setSelectionToWidget(StructuredViewer.java:106\n6)\n        at\norg.eclipse.jface.viewers.StructuredViewer.preservingSelection(StructuredViewer.java:817)\n\n        at\norg.eclipse.jface.viewers.StructuredViewer.refresh(StructuredViewer.java:893)\n        at\norg.eclipse.jface.viewers.StructuredViewer.refresh(StructuredViewer.java:853)\n        at\nse.tardell.simon.eclipse.resources.views.ResourcesView$3.run(ResourcesView.java:159)\n        at org.eclipse.swt.widgets.RunnableLock.run(RunnableLock.java:35)\n        at\norg.eclipse.swt.widgets.Synchronizer.runAsyncMessages(Synchronizer.java:102)\n        at org.eclipse.swt.widgets.Display.runAsyncMessages(Display.java:2325)\n        at org.eclipse.swt.widgets.Display.readAndDispatch(Display.java:2033)\n        at org.eclipse.ui.internal.Workbench.runEventLoop(Workbench.java:1550)\n        at org.eclipse.ui.internal.Workbench.runUI(Workbench.java:1526)\n        at\norg.eclipse.ui.internal.Workbench.createAndRunWorkbench(Workbench.java:265)\n        at org.eclipse.ui.PlatformUI.createAndRunWorkbench(PlatformUI.java:139)\n        at org.eclipse.ui.internal.ide.IDEApplication.run(IDEApplication.java:47)\n        at\norg.eclipse.core.internal.runtime.PlatformActivator$1.run(PlatformActivator.java:257)\n        at\norg.eclipse.core.runtime.adaptor.EclipseStarter.run(EclipseStarter.java:104)\n        at sun.reflect.NativeMethodAccessorImpl.invoke0(Native Method)\n        at\nsun.reflect.NativeMethodAccessorImpl.invoke(NativeMethodAccessorImpl.java:39)\n        at\nsun.reflect.DelegatingMethodAccessorImpl.invoke(DelegatingMethodAccessorImpl.java:25)\n        at java.lang.reflect.Method.invoke(Method.java:324)\n        at org.eclipse.core.launcher.Main.basicRun(Main.java:279)\n        at org.eclipse.core.launcher.Main.run(Main.java:742)\n        at org.eclipse.core.launcher.Main.main(Main.java:581)",
    "Laura, this is unrelated since it happens in a non-Eclipse SDK part\n(se.tardell.simon.eclipse.resources.views.ResourcesView$3). I assume this part\nposts some runnable asynchronous but when run doesn\u0027t check whether the widget\nstill exists.",
    "Please mark as duplicate of Bug 52646.\n",
    "\n\n*** This bug has been marked as a duplicate of 52646 ***"
  ],
  "commentCreationDates": [
    "2004-02-12T22:31:42+01:00",
    "2004-02-12T22:32:08+01:00",
    "2004-02-12T23:53:41+01:00",
    "2004-02-15T02:45:40+01:00",
    "2004-02-15T02:53:43+01:00",
    "2004-02-16T08:12:57+01:00",
    "2004-03-29T11:15:37+02:00",
    "2004-03-29T11:23:37+02:00"
  ],
  "traces": [
    {
      "exceptionType": "org.eclipse.swt.SWTException",
      "message": "Widget is disposed",
      "elements": [
        {
          "method": "org.eclipse.swt.SWT.error",
          "source": "SWT.java:2608"
        },
        {
          "method": "org.eclipse.swt.SWT.error",
          "source": "SWT.java:2538"
        },
        {
          "method": "org.eclipse.swt.widgets.Widget.error",
          "source": "Widget.java:373"
        },
        {
          "method": "org.eclipse.swt.widgets.Widget.checkWidget",
          "source": "Widget.java:309"
        },
        {
          "method": "org.eclipse.swt.widgets.Widget.addDisposeListener",
          "source": "Widget.java:199"
        },
        {
          "method": "org.eclipse.jface.text.AbstractInformationControlManager.install",
          "source": "AbstractInformationControlManager.java:347"
        }
      ],
      "number": 0,
      "commentIndex": 0,
      "bugId": "51912",
      "duplicateId": "52646",
      "date": "2004-02-12T22:31:42+01:00",
      "product": "Platform",
      "component": "Text",
      "severity": "major"
    },
    {
      "exceptionType": "org.eclipse.swt.SWTException",
      "message": "Widget is disposed",
      "elements": [
        {
          "method": "org.eclipse.swt.SWT.error",
          "source": "SWT.java:2608"
        },
        {
          "method": "org.eclipse.swt.SWT.error",
          "source": "SWT.java:2538"
        },
        {
          "method": "org.eclipse.swt.widgets.Widget.error",
          "source": "Widget.java:377"
        },
        {
          "method": "org.eclipse.swt.widgets.Widget.checkWidget",
          "source": "Widget.java:306"
        },
        {
          "method": "org.eclipse.swt.widgets.Table.setSelection",
          "source": "Table.java:2068"
        },
        {
          "method": "org.eclipse.jface.viewers.TableViewer.setSelectionToWidget",
          "source": "TableViewer.java:658"
        },
        {
          "method": "org.eclipse.jface.viewers.StructuredViewer.setSelectionToWidget",
          "source": "StructuredViewer.java:106 6"
        },
        {
          "method": "org.eclipse.jface.viewers.StructuredViewer.preservingSelection",
          "source": "StructuredViewer.java:817"
        },
        {
          "method": "org.eclipse.jface.viewers.StructuredViewer.refresh",
          "source": "StructuredViewer.java:893"
        },
        {
          "method": "org.eclipse.jface.viewers.StructuredViewer.refresh",
          "source": "StructuredViewer.java:853"
        },
        {
          "method": "se.tardell.simon.eclipse.resources.views.ResourcesView$3.run",
          "source": "ResourcesView.java:159"
        },
        {
          "method": "org.eclipse.swt.widgets.RunnableLock.run",
          "source": "RunnableLock.java:35"
        },
        {
          "method": "org.eclipse.swt.widgets.Synchronizer.runAsyncMessages",
          "source": "Synchronizer.java:102"
        },
        {
          "method": "org.eclipse.swt.widgets.Display.runAsyncMessages",
          "source": "Display.java:2325"
        },
        {
          "method": "org.eclipse.swt.widgets.Display.readAndDispatch",
          "source": "Display.java:2033"
        },
        {
          "method": "org.eclipse.ui.internal.Workbench.runEventLoop",
          "source": "Workbench.java:1550"
        },
        {
          "method": "org.eclipse.ui.internal.Workbench.runUI",
          "source": "Workbench.java:1526"
        },
        {
          "method": "org.eclipse.ui.internal.Workbench.createAndRunWorkbench",
          "source": "Workbench.java:265"
        },
        {
          "method": "org.eclipse.ui.PlatformUI.createAndRunWorkbench",
          "source": "PlatformUI.java:139"
        },
        {
          "method": "org.eclipse.ui.internal.ide.IDEApplication.run",
          "source": "IDEApplication.java:47"
        },
        {
          "method": "org.eclipse.core.internal.runtime.PlatformActivator$1.run",
          "source": "PlatformActivator.java:257"
        },
        {
          "method": "org.eclipse.core.runtime.adaptor.EclipseStarter.run",
          "source": "EclipseStarter.java:104"
        },
        {
          "method": "sun.reflect.NativeMethodAccessorImpl.invoke0",
          "source": "Native Method"
        },
        {
          "method": "sun.reflect.NativeMethodAccessorImpl.invoke",
          "source": "NativeMethodAccessorImpl.java:39"
        },
        {
          "method": "sun.reflect.DelegatingMethodAccessorImpl.invoke",
          "source": "DelegatingMethodAccessorImpl.java:25"
        },
        {
          "method": "java.lang.reflect.Method.invoke",
          "source": "Method.java:324"
        },
        {
          "method": "org.eclipse.core.launcher.Main.basicRun",
          "source": "Main.java:279"
        },
        {
          "method": "org.eclipse.core.launcher.Main.run",
          "source": "Main.java:742"
        },
        {
          "method": "org.eclipse.core.launcher.Main.main",
          "source": "Main.java:581"
        }
      ],
      "number": 1,
      "commentIndex": 4,
      "bugId": "51912",
      "duplicateId": "52646",
      "date": "2004-02-15T02:53:43+01:00",
      "product": "Platform",
      "component": "Text",
      "severity": "major"
    }
  ],
  "groupId": "52646",
  "bugId": "51912",
  "duplicateId": "52646",
  "date": "2004-02-12T22:31:42+01:00",
  "product": "Platform",
  "component": "Text",
  "severity": "major"
}