{
  "comments": [
    "The following code causes the compiler to fail with a NPE in the version that \nwas included in ajdt 1.1.6 (developer build).\n\npublic aspect LogManager {\n    public void Loggable.logTrace(Object message) {\n    }\n    // no crash if the next method on the next line is renamed\n    public void Loggable.logTrace(Object message, Throwable t)  {\n    }\n}\n\npublic interface Loggable {\n}\n\nExample crash:\nC:\\eclipse\\workspace\\atrack\u003eajc -d build @isolateError.lst\ntrouble in:\nABORT\nException thrown from AspectJ DEVELOPMENT\n\nThis might be logged as a bug already -- find current bugs at\n  http://bugs.eclipse.org/bugs/buglist.cgi?product\u003dAspectJ\u0026component\u003dCompiler\n\nBugs for exceptions thrown have titles File:line from the top stack,\ne.g., \"SomeFile.java:243\"\n\nIf you don\u0027t find the exception below in a bug, please add a new bug\nat http://bugs.eclipse.org/bugs/enter_bug.cgi?product\u003dAspectJ\nTo make the bug a priority, please include a test program\nthat can reproduce this exception.\nnull\njava.lang.NullPointerException\n        at org.aspectj.weaver.bcel.LazyMethodGen.getSignature\n(LazyMethodGen.java\n:1225)\n        at org.aspectj.weaver.bcel.BcelClassWeaver$1.compare\n(BcelClassWeaver.jav\na:676)\n        at java.util.Arrays.mergeSort(Arrays.java:1278)\n        at java.util.Arrays.sort(Arrays.java:1219)\n        at java.util.Collections.sort(Collections.java:155)\n        at org.aspectj.weaver.bcel.BcelClassWeaver.weaveInAddedMethods\n(BcelClass\nWeaver.java:669)\n        at org.aspectj.weaver.bcel.BcelClassWeaver.weave\n(BcelClassWeaver.java:35\n2)\n        at org.aspectj.weaver.bcel.BcelClassWeaver.weave\n(BcelClassWeaver.java:79\n)\n        at org.aspectj.weaver.bcel.BcelWeaver.weave(BcelWeaver.java:484)\n        at org.aspectj.weaver.bcel.BcelWeaver.weave(BcelWeaver.java:455)\n        at org.aspectj.weaver.bcel.BcelWeaver.weave(BcelWeaver.java:392)\n        at \norg.aspectj.ajdt.internal.core.builder.AjBuildManager.weaveAndGenerat\neClassFiles(AjBuildManager.java:262)\n        at org.aspectj.ajdt.internal.core.builder.AjBuildManager.doBuild\n(AjBuild\nManager.java:156)\n        at org.aspectj.ajdt.internal.core.builder.AjBuildManager.batchBuild\n(AjBu\nildManager.java:70)\n        at org.aspectj.ajdt.ajc.AjdtCommand.doCommand(AjdtCommand.java:102)\n        at org.aspectj.ajdt.ajc.AjdtCommand.runCommand(AjdtCommand.java:53)\n        at org.aspectj.tools.ajc.Main.run(Main.java:231)\n        at org.aspectj.tools.ajc.Main.runMain(Main.java:168)\n        at org.aspectj.tools.ajc.Main.main(Main.java:81)\n\n\n1 fail|abort",
    "*** Bug 51902 has been marked as a duplicate of this bug. ***",
    "This occurs because of an assumption in LazyMethodGen.  It assumes for an \nintertype declaration, it can create a skeleton form of the LazyMethodGen.  \nThis means we don\u0027t create the necessary containing object (memberView) that \nhas the method signature in it.\n\nThe stack trace shows a call from a snippet of code that is used to compare \nintertype declarations.  If the names for two intertype declarations are the \nsame, it continues on to compare the signatures - because the memberView does \nnot exist, the getSignature() method blows up NPE.  The fix is to say that if \nthe memberView is null, conjure up the right signature on the spot to allow \nthe comparison to be done.  I\u0027ll check the fix in tomorrow morning.",
    "Fix checked in."
  ],
  "commentCreationDates": [
    "2004-02-12T23:12:48+01:00",
    "2004-02-12T23:14:03+01:00",
    "2004-02-23T20:38:02+01:00",
    "2004-02-24T10:12:57+01:00"
  ],
  "traces": [
    {
      "exceptionType": "java.lang.NullPointerException",
      "elements": [
        {
          "method": "org.aspectj.weaver.bcel.LazyMethodGen.getSignature",
          "source": "LazyMethodGen.java :1225"
        },
        {
          "method": "org.aspectj.weaver.bcel.BcelClassWeaver$1.compare",
          "source": "BcelClassWeaver.jav a:676"
        },
        {
          "method": "java.util.Arrays.mergeSort",
          "source": "Arrays.java:1278"
        },
        {
          "method": "java.util.Arrays.sort",
          "source": "Arrays.java:1219"
        },
        {
          "method": "java.util.Collections.sort",
          "source": "Collections.java:155"
        },
        {
          "method": "org.aspectj.weaver.bcel.BcelClassWeaver.weaveInAddedMethods",
          "source": "BcelClass Weaver.java:669"
        },
        {
          "method": "org.aspectj.weaver.bcel.BcelClassWeaver.weave",
          "source": "BcelClassWeaver.java:35 2"
        },
        {
          "method": "org.aspectj.weaver.bcel.BcelClassWeaver.weave",
          "source": "BcelClassWeaver.java:79 "
        },
        {
          "method": "org.aspectj.weaver.bcel.BcelWeaver.weave",
          "source": "BcelWeaver.java:484"
        },
        {
          "method": "org.aspectj.weaver.bcel.BcelWeaver.weave",
          "source": "BcelWeaver.java:455"
        },
        {
          "method": "org.aspectj.weaver.bcel.BcelWeaver.weave",
          "source": "BcelWeaver.java:392"
        },
        {
          "method": "org.aspectj.ajdt.internal.core.builder.AjBuildManager.weaveAndGenerateClassFiles",
          "source": "AjBuildManager.java:262"
        },
        {
          "method": "org.aspectj.ajdt.internal.core.builder.AjBuildManager.doBuild",
          "source": "AjBuild Manager.java:156"
        },
        {
          "method": "org.aspectj.ajdt.internal.core.builder.AjBuildManager.batchBuild",
          "source": "AjBu ildManager.java:70"
        },
        {
          "method": "org.aspectj.ajdt.ajc.AjdtCommand.doCommand",
          "source": "AjdtCommand.java:102"
        },
        {
          "method": "org.aspectj.ajdt.ajc.AjdtCommand.runCommand",
          "source": "AjdtCommand.java:53"
        },
        {
          "method": "org.aspectj.tools.ajc.Main.run",
          "source": "Main.java:231"
        },
        {
          "method": "org.aspectj.tools.ajc.Main.runMain",
          "source": "Main.java:168"
        },
        {
          "method": "org.aspectj.tools.ajc.Main.main",
          "source": "Main.java:81"
        }
      ],
      "number": 0,
      "commentIndex": 0,
      "bugId": "51919",
      "date": "2004-02-12T23:12:48+01:00",
      "product": "AspectJ",
      "component": "Compiler",
      "severity": "normal"
    }
  ],
  "groupId": "51919",
  "bugId": "51919",
  "date": "2004-02-12T23:12:48+01:00",
  "product": "AspectJ",
  "component": "Compiler",
  "severity": "normal"
}