{
  "comments": [
    "Eclipse 3.0 M6, M7 on Windows XP Pro.\nJDK 1.4.2_03\nThe remote server is cvsnt, authentication uses pserver. Access to the server\nthrough a corporate VPN.\n\nWhen I try to expand the HEAD, Branches or Versions tag in the CVS repository\nview, no project is shown in the view and the log shows the exception below.\nThis does not happen with a local cvsnt server.\n\nOther people in my company have no such problem, so I guess something is wrong\non my machine, but I\u0027ve no clue what. I did a complete uninstall/reinstall of\nEclipse, but it didn\u0027t help. What did I miss?\n\n!ENTRY org.eclipse.team.cvs.ui 4 0 Feb 15, 2004 12:20:38.336\n!MESSAGE Internal error\n!STACK 1\norg.eclipse.team.internal.ccvs.core.CVSException: The server reported an error\nwhile performing the \"cvs update\" command.\n\tat\norg.eclipse.team.internal.ccvs.core.connection.CVSRepositoryLocation.members(CVSRepositoryLocation.java:229)\n\tat\norg.eclipse.team.internal.ccvs.ui.repo.RepositoryManager.getFoldersForTag(RepositoryManager.java:221)\n\tat\norg.eclipse.team.internal.ccvs.ui.model.VersionCategory.getProjectVersionChildren(VersionCategory.java:97)\n\tat\norg.eclipse.team.internal.ccvs.ui.model.VersionCategory.fetchChildren(VersionCategory.java:64)\n\tat\norg.eclipse.team.internal.ccvs.ui.model.VersionCategory.fetchDeferredChildren(VersionCategory.java:162)\n\tat\norg.eclipse.ui.progress.DeferredTreeContentManager$2.run(DeferredTreeContentManager.java:188)\n\tat org.eclipse.core.internal.jobs.Worker.run(Worker.java:62)\n!ENTRY org.eclipse.team.cvs.core 4 -10 Feb 15, 2004 12:20:38.346\n!MESSAGE The server reported an error while performing the \"cvs update\" command.\n!SUBENTRY 1 org.eclipse.team.cvs.core 4 -14 Feb 15, 2004 12:20:38.356\n!MESSAGE : cvs [server aborted]: cannot find .: No such file or directory\n\n-Laurent Cohen",
    "Strange. The error is \"cannot find .\" which is the root directory of the \nrepository. Possible causes I can think of include:\n\n- server configuration problem (Eclipse does no support repository prefix and \nimpersonation should be enabled)\n- improperly initialized repository directory (does the directory contain the \nCVSROOT folder which indicates that the directory is a CVS repository)\n\nCan you access the repo from other machines using your account? Can others \naccess the repo with their accounts? The answer to these questions may help \ndetermine the problem.\n\nIn any case, I don\u0027t think this is an error in Eclipse. A better place for \nquestions like this is the eclipse-platform newsgroup. Of course, if you \nfurther investigate this and do find a bug, by all means reopen."
  ],
  "commentCreationDates": [
    "2004-02-15T18:45:01+01:00",
    "2004-02-23T02:54:06+01:00"
  ],
  "traces": [
    {
      "exceptionType": "org.eclipse.team.internal.ccvs.core.CVSException",
      "message": "The server reported an error while performing the \"cvs update\" command.",
      "elements": [
        {
          "method": "org.eclipse.team.internal.ccvs.core.connection.CVSRepositoryLocation.members",
          "source": "CVSRepositoryLocation.java:229"
        },
        {
          "method": "org.eclipse.team.internal.ccvs.ui.repo.RepositoryManager.getFoldersForTag",
          "source": "RepositoryManager.java:221"
        },
        {
          "method": "org.eclipse.team.internal.ccvs.ui.model.VersionCategory.getProjectVersionChildren",
          "source": "VersionCategory.java:97"
        },
        {
          "method": "org.eclipse.team.internal.ccvs.ui.model.VersionCategory.fetchChildren",
          "source": "VersionCategory.java:64"
        },
        {
          "method": "org.eclipse.team.internal.ccvs.ui.model.VersionCategory.fetchDeferredChildren",
          "source": "VersionCategory.java:162"
        },
        {
          "method": "org.eclipse.ui.progress.DeferredTreeContentManager$2.run",
          "source": "DeferredTreeContentManager.java:188"
        },
        {
          "method": "org.eclipse.core.internal.jobs.Worker.run",
          "source": "Worker.java:62"
        }
      ],
      "number": 0,
      "commentIndex": 0,
      "bugId": "52104",
      "date": "2004-02-15T18:45:01+01:00",
      "product": "Platform",
      "component": "CVS",
      "severity": "normal"
    }
  ],
  "groupId": "52104",
  "bugId": "52104",
  "date": "2004-02-15T18:45:01+01:00",
  "product": "Platform",
  "component": "CVS",
  "severity": "normal"
}