{
  "comments": [
    "Eclipse3.0M7\nCDT 2.0M7\nSun Java 1.4.2_02\n-----------------\n\nThe following exception appears on the command line when exiting from Eclipse\nafter using CDT:\n\norg.osgi.framework.BundleException: Exception in\norg.eclipse.core.internal.compatibility.PluginActivator.stop()\n        at\norg.eclipse.osgi.framework.internal.core.BundleContext.stop(BundleContext.java:1170)\n        at\norg.eclipse.osgi.framework.internal.core.BundleHost.stopWorker(BundleHost.java:481)\n        at org.eclipse.osgi.framework.internal.core.Bundle.stop(Bundle.java:457)\n       at\norg.eclipse.core.internal.plugins.PluginStopper.run(PluginStopper.java:101)\n        at\norg.eclipse.core.internal.runtime.PlatformActivator.stopLegacyBundles(PlatformActivator.java:286)\n        at\norg.eclipse.core.internal.runtime.PlatformActivator$1.run(PlatformActivator.java:268)\n        at\norg.eclipse.core.runtime.adaptor.EclipseStarter.run(EclipseStarter.java:104)\n        at sun.reflect.NativeMethodAccessorImpl.invoke0(Native Method)\n        at sun.reflect.NativeMethodAccessorImpl.invoke(Unknown Source)\n        at sun.reflect.DelegatingMethodAccessorImpl.invoke(Unknown Source)\n        at java.lang.reflect.Method.invoke(Unknown Source)\n        at org.eclipse.core.launcher.Main.basicRun(Main.java:279)\n        at org.eclipse.core.launcher.Main.run(Main.java:742)\n        at org.eclipse.core.launcher.Main.main(Main.java:581)\n\n\nThis exception does not appear when using Eclipse and JDT (i.e. no CDT installation)\n\n* FYI: The same behaviour exists with:\n           Eclipse3.0M6\n           CDT 2.0.0.0031\n           Sun Java 1.4.2_02",
    "Redirected to Doug the king of Eclipse-3.0 migration.\n\nI\u0027ve seen this before on M6 but it appears less on M7",
    "Doug, I\u0027m chasing this out.  So I\u0027ll take this from you.",
    "This is cause by the DebugUIPlugin.shutdown().\n\n  getActiveWorkbenchWindow() is returning null.\n\nThe question remains on why the listener is needed and how\nit will work for multiple Workbench.",
    "To be clear the exception is cause by the CDT Debug UI plugin\nshutdown() sequence.  I\u0027ve use the big hammer to mute this.\nMikhail is planning to remove this part of the code anyway,\nit is part of the big shake up in aligning the CDT Debugger\nfor Eclipse-3.0.\n\nThe PR is still open for the followup.  But you should no\nlonger see the exception.\n\nThanks",
    "We needed this code to syncronize the threads and frames selected in the Debug \nview with gdb. As we have decided, this synchronization is not necessary for \n2.0, so we will remove this code completely as soon as we make the changes.",
    "The rest of the call frame (within PluginActivator.stop) is\n  org.eclipse.ui.PlatformUI.getWorkbench()\n  org.eclipse.ui.plugin.AbstractUIPlugin.getWorkbench()\n  org.eclipse.cdt.debug.ui.CDebugUIPlugin.getActiveWorkbenchWindow()\n  org.eclipse.cdt.debug.ui.CDebugUIPlugin.shutdown()",
    "PR was not targeted to any particular release. Changing target milestone to 2.1",
    "Fix in the head/branch"
  ],
  "commentCreationDates": [
    "2004-02-16T15:53:39+01:00",
    "2004-02-16T20:17:00+01:00",
    "2004-02-19T16:11:36+01:00",
    "2004-02-19T16:32:37+01:00",
    "2004-02-20T17:58:02+01:00",
    "2004-02-20T20:18:38+01:00",
    "2004-03-04T16:04:28+01:00",
    "2004-07-07T22:58:13+02:00",
    "2004-12-03T20:49:40+01:00"
  ],
  "traces": [
    {
      "exceptionType": "org.osgi.framework.BundleException",
      "message": "Exception in org.eclipse.core.internal.compatibility.PluginActivator.stop()",
      "elements": [
        {
          "method": "org.eclipse.osgi.framework.internal.core.BundleContext.stop",
          "source": "BundleContext.java:1170"
        },
        {
          "method": "org.eclipse.osgi.framework.internal.core.BundleHost.stopWorker",
          "source": "BundleHost.java:481"
        },
        {
          "method": "org.eclipse.osgi.framework.internal.core.Bundle.stop",
          "source": "Bundle.java:457"
        },
        {
          "method": "org.eclipse.core.internal.plugins.PluginStopper.run",
          "source": "PluginStopper.java:101"
        },
        {
          "method": "org.eclipse.core.internal.runtime.PlatformActivator.stopLegacyBundles",
          "source": "PlatformActivator.java:286"
        },
        {
          "method": "org.eclipse.core.internal.runtime.PlatformActivator$1.run",
          "source": "PlatformActivator.java:268"
        },
        {
          "method": "org.eclipse.core.runtime.adaptor.EclipseStarter.run",
          "source": "EclipseStarter.java:104"
        },
        {
          "method": "sun.reflect.NativeMethodAccessorImpl.invoke0",
          "source": "Native Method"
        },
        {
          "method": "sun.reflect.NativeMethodAccessorImpl.invoke",
          "source": "Unknown Source"
        },
        {
          "method": "sun.reflect.DelegatingMethodAccessorImpl.invoke",
          "source": "Unknown Source"
        },
        {
          "method": "java.lang.reflect.Method.invoke",
          "source": "Unknown Source"
        },
        {
          "method": "org.eclipse.core.launcher.Main.basicRun",
          "source": "Main.java:279"
        },
        {
          "method": "org.eclipse.core.launcher.Main.run",
          "source": "Main.java:742"
        },
        {
          "method": "org.eclipse.core.launcher.Main.main",
          "source": "Main.java:581"
        }
      ],
      "number": 0,
      "commentIndex": 0,
      "bugId": "52155",
      "date": "2004-02-16T15:53:39+01:00",
      "product": "CDT",
      "component": "cdt-core",
      "severity": "normal"
    }
  ],
  "groupId": "52155",
  "bugId": "52155",
  "date": "2004-02-16T15:53:39+01:00",
  "product": "CDT",
  "component": "cdt-core",
  "severity": "normal"
}