{
  "comments": [
    "I\u0027m testing the new layout of eclipse workbench\n(https://bugs.eclipse.org/bugs/show_bug.cgi?id\u003d37997) on GTK, Suse 9.0.\n\nWhen I click at the button at the right side of the file name opened, I get the\nerror:\n\n!ENTRY org.eclipse.ui 4 4 Fev 18, 2004 15:32:33.557\n!MESSAGE Unhandled event loop exception\n!ENTRY org.eclipse.ui 4 0 Fev 18, 2004 15:32:33.562\n!MESSAGE Widget is disposed\n!STACK 0\norg.eclipse.swt.SWTException: Widget is disposed\n        at org.eclipse.swt.SWT.error(SWT.java:2608)\n        at org.eclipse.swt.SWT.error(SWT.java:2538)\n        at org.eclipse.swt.widgets.Widget.error(Widget.java:373)\n        at org.eclipse.swt.widgets.Widget.checkWidget(Widget.java:309)\n        at org.eclipse.swt.widgets.Text.setText(Text.java:1450)\n        at\norg.eclipse.ui.internal.AbstractTableInformationControl.inputChanged(AbstractTableInformationControl.java:437)\n        at\norg.eclipse.ui.internal.EditorsInformationControl.setInput(EditorsInformationControl.java:51)\n        at\norg.eclipse.ui.internal.TabbedEditorWorkbook$4.showList(TabbedEditorWorkbook.java:226)\n        at\norg.eclipse.ui.internal.TabbedEditorWorkbook$4.showList(TabbedEditorWorkbook.java:222)\n        at org.eclipse.swt.custom.CTabFolder2.onMouse(CTabFolder2.java:1904)\n        at org.eclipse.swt.custom.CTabFolder2$1.handleEvent(CTabFolder2.java:268)\n        at org.eclipse.swt.widgets.EventTable.sendEvent(EventTable.java:82)\n        at org.eclipse.swt.widgets.Widget.sendEvent(Widget.java:956)\n        at org.eclipse.swt.widgets.Display.runDeferredEvents(Display.java:1871)\n        at org.eclipse.swt.widgets.Display.readAndDispatch(Display.java:1649)\n        at org.eclipse.ui.internal.Workbench.runEventLoop(Workbench.java:1550)\n        at org.eclipse.ui.internal.Workbench.runUI(Workbench.java:1526)\n        at\norg.eclipse.ui.internal.Workbench.createAndRunWorkbench(Workbench.java:265)\n        at org.eclipse.ui.PlatformUI.createAndRunWorkbench(PlatformUI.java:139)\n        at org.eclipse.ui.internal.ide.IDEApplication.run(IDEApplication.java:47)\n        at\norg.eclipse.core.internal.runtime.PlatformActivator$1.run(PlatformActivator.java:257)\n        at\norg.eclipse.core.runtime.adaptor.EclipseStarter.run(EclipseStarter.java:104)\n        at sun.reflect.NativeMethodAccessorImpl.invoke0(Native Method)\n        at\nsun.reflect.NativeMethodAccessorImpl.invoke(NativeMethodAccessorImpl.java:39)\n        at\nsun.reflect.DelegatingMethodAccessorImpl.invoke(DelegatingMethodAccessorImpl.java:25)\n        at java.lang.reflect.Method.invoke(Method.java:324)\n        at org.eclipse.core.launcher.Main.basicRun(Main.java:279)\n        at org.eclipse.core.launcher.Main.run(Main.java:742)\n        at org.eclipse.core.launcher.Main.main(Main.java:581)\nemersonc@elbassan:~/eclipse\u003e kedit Unhandled event loop exception\nReason:\nWidget is disposed",
    "I do not see this in the February 17th integration build.  Is this the build \nthat you are using (or a newer one)?  If not then please try a newer build, as \nthere have been lots of changes made in this area over the last week.\n\nIf it still happens for you then some more info is needed, such as:\n- how many editors are open at the time?\n- are they on one shared tab, or each on a separate tab?\n- what kind(s) of file(s) are open?\n- does it happen in a particular perspective?\n- other relevant info?\n\nThanks!\n",
    "*** Bug 52914 has been marked as a duplicate of this bug. ***",
    "Bug 52914 indicates that this problem may exist on other platforms (WinXP is \nnoted).\n",
    "This might be related to the \"Use multiple editor tabs\" preference.",
    "Steps to reproduce:\n- open an editor\n- press CTRL+Tab to give focus to its tab\n- press Shift+F10 to show its menu\n- press Esc to dismiss the menu, focus reverts to the StyledText\n- press CTRL+Tab to give focus to its tab\n- press Shift+F10 to show its menu   \u003c-- exception\n",
    "*** Bug 53088 has been marked as a duplicate of this bug. ***",
    "I can no longer reproduce this with the steps that previously made this happen \nfor me (comment 5).  Please reopen this report if you still see this problem, \nthanks.\n"
  ],
  "commentCreationDates": [
    "2004-02-18T19:04:58+01:00",
    "2004-02-19T14:44:22+01:00",
    "2004-02-24T15:20:48+01:00",
    "2004-02-24T15:21:54+01:00",
    "2004-02-24T15:30:34+01:00",
    "2004-02-24T21:14:22+01:00",
    "2004-02-25T18:58:48+01:00",
    "2004-08-19T22:20:23+02:00"
  ],
  "traces": [
    {
      "exceptionType": "org.eclipse.swt.SWTException",
      "message": "Widget is disposed",
      "elements": [
        {
          "method": "org.eclipse.swt.SWT.error",
          "source": "SWT.java:2608"
        },
        {
          "method": "org.eclipse.swt.SWT.error",
          "source": "SWT.java:2538"
        },
        {
          "method": "org.eclipse.swt.widgets.Widget.error",
          "source": "Widget.java:373"
        },
        {
          "method": "org.eclipse.swt.widgets.Widget.checkWidget",
          "source": "Widget.java:309"
        },
        {
          "method": "org.eclipse.swt.widgets.Text.setText",
          "source": "Text.java:1450"
        },
        {
          "method": "org.eclipse.ui.internal.AbstractTableInformationControl.inputChanged",
          "source": "AbstractTableInformationControl.java:437"
        },
        {
          "method": "org.eclipse.ui.internal.EditorsInformationControl.setInput",
          "source": "EditorsInformationControl.java:51"
        },
        {
          "method": "org.eclipse.ui.internal.TabbedEditorWorkbook$4.showList",
          "source": "TabbedEditorWorkbook.java:226"
        },
        {
          "method": "org.eclipse.ui.internal.TabbedEditorWorkbook$4.showList",
          "source": "TabbedEditorWorkbook.java:222"
        },
        {
          "method": "org.eclipse.swt.custom.CTabFolder2.onMouse",
          "source": "CTabFolder2.java:1904"
        },
        {
          "method": "org.eclipse.swt.custom.CTabFolder2$1.handleEvent",
          "source": "CTabFolder2.java:268"
        },
        {
          "method": "org.eclipse.swt.widgets.EventTable.sendEvent",
          "source": "EventTable.java:82"
        },
        {
          "method": "org.eclipse.swt.widgets.Widget.sendEvent",
          "source": "Widget.java:956"
        },
        {
          "method": "org.eclipse.swt.widgets.Display.runDeferredEvents",
          "source": "Display.java:1871"
        },
        {
          "method": "org.eclipse.swt.widgets.Display.readAndDispatch",
          "source": "Display.java:1649"
        },
        {
          "method": "org.eclipse.ui.internal.Workbench.runEventLoop",
          "source": "Workbench.java:1550"
        },
        {
          "method": "org.eclipse.ui.internal.Workbench.runUI",
          "source": "Workbench.java:1526"
        },
        {
          "method": "org.eclipse.ui.internal.Workbench.createAndRunWorkbench",
          "source": "Workbench.java:265"
        },
        {
          "method": "org.eclipse.ui.PlatformUI.createAndRunWorkbench",
          "source": "PlatformUI.java:139"
        },
        {
          "method": "org.eclipse.ui.internal.ide.IDEApplication.run",
          "source": "IDEApplication.java:47"
        },
        {
          "method": "org.eclipse.core.internal.runtime.PlatformActivator$1.run",
          "source": "PlatformActivator.java:257"
        },
        {
          "method": "org.eclipse.core.runtime.adaptor.EclipseStarter.run",
          "source": "EclipseStarter.java:104"
        },
        {
          "method": "sun.reflect.NativeMethodAccessorImpl.invoke0",
          "source": "Native Method"
        },
        {
          "method": "sun.reflect.NativeMethodAccessorImpl.invoke",
          "source": "NativeMethodAccessorImpl.java:39"
        },
        {
          "method": "sun.reflect.DelegatingMethodAccessorImpl.invoke",
          "source": "DelegatingMethodAccessorImpl.java:25"
        },
        {
          "method": "java.lang.reflect.Method.invoke",
          "source": "Method.java:324"
        },
        {
          "method": "org.eclipse.core.launcher.Main.basicRun",
          "source": "Main.java:279"
        },
        {
          "method": "org.eclipse.core.launcher.Main.run",
          "source": "Main.java:742"
        },
        {
          "method": "org.eclipse.core.launcher.Main.main",
          "source": "Main.java:581"
        }
      ],
      "number": 0,
      "commentIndex": 0,
      "bugId": "52399",
      "date": "2004-02-18T19:04:58+01:00",
      "product": "Platform",
      "component": "SWT",
      "severity": "normal"
    }
  ],
  "groupId": "52399",
  "bugId": "52399",
  "date": "2004-02-18T19:04:58+01:00",
  "product": "Platform",
  "component": "SWT",
  "severity": "normal"
}