{
  "comments": [
    "I was running in console mode for other reasons, when I spotted this stack \ntrace, that did not appear in the log.\n\nThis is in M7; JDK 1.4.2_03. I just turned on spell checking in the In \nProgress pref pane but didn\u0027t otherwise do anything to configure. I don\u0027t know \nwhat specific action triggered this (nor did I observe any effect).\n\njava.lang.StringIndexOutOfBoundsException: String index out of range: 7\n[Dynamic-linking native method java.lang.Throwable.getStackTraceDepth ... JNI]\n[Dynamic-linking native method java.lang.Throwable.getStackTraceElement ... \nJNI]\n        at java.lang.String.charAt(String.java:444)\n        at \norg.eclipse.jdt.internal.ui.text.spelling.SpellCheckIterator.nextToken\n(SpellCheckIterator.java:297)\n        at org.eclipse.jdt.internal.ui.text.spelling.SpellCheckIterator.next\n(SpellCheckIterator.java:241)\n        at \norg.eclipse.jdt.internal.ui.text.spelling.engine.DefaultSpellChecker.execute\n(DefaultSpellChecker.java:208)\n        at \norg.eclipse.jdt.internal.ui.text.spelling.SpellReconcileStrategy.reconcile\n(SpellReconcileStrategy.java:347)\n        at \norg.eclipse.jface.text.reconciler.CompositeReconcilingStrategy.reconcile\n(CompositeReconcilingStrategy.java:83)\n        at \norg.eclipse.jdt.internal.ui.text.JavaCompositeReconcilingStrategy.reconcile\n(JavaCompositeReconcilingStrategy.java:97)\n        at org.eclipse.jface.text.reconciler.MonoReconciler.process\n(MonoReconciler.java:76)\n        at \norg.eclipse.jface.text.reconciler.AbstractReconciler$BackgroundThread.run\n(AbstractReconciler.java:189)",
    "I\u0027ve seen this as well.\n\nFixed.\nAvailable in builds \u003e 20040219.\n",
    "start verifying...",
    "Verified by inspection of code change."
  ],
  "commentCreationDates": [
    "2004-02-19T09:05:26+01:00",
    "2004-02-19T09:28:57+01:00",
    "2004-03-26T10:42:33+01:00",
    "2004-03-26T10:58:54+01:00"
  ],
  "traces": [
    {
      "exceptionType": "java.lang.StringIndexOutOfBoundsException",
      "message": "String index out of range: 7 [Dynamic-linking native method java.lang.Throwable.getStackTraceDepth ... JNI] [Dynamic-linking native method java.lang.Throwable.getStackTraceElement ...  JNI]",
      "elements": [
        {
          "method": "java.lang.String.charAt",
          "source": "String.java:444"
        },
        {
          "method": "org.eclipse.jdt.internal.ui.text.spelling.SpellCheckIterator.nextToken",
          "source": "SpellCheckIterator.java:297"
        },
        {
          "method": "org.eclipse.jdt.internal.ui.text.spelling.SpellCheckIterator.next",
          "source": "SpellCheckIterator.java:241"
        },
        {
          "method": "org.eclipse.jdt.internal.ui.text.spelling.engine.DefaultSpellChecker.execute",
          "source": "DefaultSpellChecker.java:208"
        },
        {
          "method": "org.eclipse.jdt.internal.ui.text.spelling.SpellReconcileStrategy.reconcile",
          "source": "SpellReconcileStrategy.java:347"
        },
        {
          "method": "org.eclipse.jface.text.reconciler.CompositeReconcilingStrategy.reconcile",
          "source": "CompositeReconcilingStrategy.java:83"
        },
        {
          "method": "org.eclipse.jdt.internal.ui.text.JavaCompositeReconcilingStrategy.reconcile",
          "source": "JavaCompositeReconcilingStrategy.java:97"
        },
        {
          "method": "org.eclipse.jface.text.reconciler.MonoReconciler.process",
          "source": "MonoReconciler.java:76"
        },
        {
          "method": "org.eclipse.jface.text.reconciler.AbstractReconciler$BackgroundThread.run",
          "source": "AbstractReconciler.java:189"
        }
      ],
      "number": 0,
      "commentIndex": 0,
      "bugId": "52460",
      "date": "2004-02-19T09:05:26+01:00",
      "product": "Platform",
      "component": "Text",
      "severity": "major"
    }
  ],
  "groupId": "52460",
  "bugId": "52460",
  "date": "2004-02-19T09:05:26+01:00",
  "product": "Platform",
  "component": "Text",
  "severity": "major"
}