{
  "comments": [
    "Versions:     Eclipse V3M7, CDT V2.0M7, JavaVM 1.4.2_03-b02\nStarted with: eclipse.exe -consolelog -vmargs -Xmx384M\n\nWhen searching for a declaration the \"Progress Information\" Dialog appears and \ncount down from ~4200 files to index. While \nindexing \"java.lang.StackOverflowError\" message appears and after the indexing, \nthe follwing message appears:\n\n!SESSION Feb 19, 2004 11:14:26.168 ---------------------------------------------\n\njava.version\u003d1.4.2_03\njava.vendor\u003dSun Microsystems Inc.\nBootLoader constants: OS\u003dwin32, ARCH\u003dx86, WS\u003dwin32, NL\u003dde_DE\n!ENTRY org.eclipse.cdt.core 4 4 Feb 19, 2004 11:14:26.168\n!MESSAGE Background Indexer Crash Recovery\n!STACK 0\njava.lang.ArrayIndexOutOfBoundsException: 1190\n        at org.eclipse.cdt.internal.core.index.impl.IncludeEntry.mapRefs(Include\nEntry.java:161)\n        at org.eclipse.cdt.internal.core.index.impl.MergeFactory.mergeIncludes(M\nergeFactory.java:211)\n        at org.eclipse.cdt.internal.core.index.impl.MergeFactory.merge(MergeFact\nory.java:82)\n        at org.eclipse.cdt.internal.core.index.impl.Index.merge(Index.java:262)\n        at org.eclipse.cdt.internal.core.index.impl.Index.save(Index.java:426)\n        at org.eclipse.cdt.internal.core.search.indexing.IndexManager.saveIndex(\nIndexManager.java:422)\n        at org.eclipse.cdt.internal.core.search.indexing.SaveIndex.execute(SaveI\nndex.java:40)\n        at org.eclipse.cdt.internal.core.search.processing.JobManager.run(JobMan\nager.java:384)\n        at java.lang.Thread.run(Unknown Source)\njava.lang.ArrayIndexOutOfBoundsException: 1190\n        at org.eclipse.cdt.internal.core.index.impl.IncludeEntry.mapRefs(Include\nEntry.java:161)\n        at org.eclipse.cdt.internal.core.index.impl.MergeFactory.mergeIncludes(M\nergeFactory.java:211)\n        at org.eclipse.cdt.internal.core.index.impl.MergeFactory.merge(MergeFact\nory.java:82)\n        at org.eclipse.cdt.internal.core.index.impl.Index.merge(Index.java:262)\n        at org.eclipse.cdt.internal.core.index.impl.Index.save(Index.java:426)\n        at org.eclipse.cdt.internal.core.search.indexing.IndexManager.saveIndex(\nIndexManager.java:422)\n        at org.eclipse.cdt.internal.core.search.indexing.SaveIndex.execute(SaveI\nndex.java:40)\n        at org.eclipse.cdt.internal.core.search.processing.JobManager.run(JobMan\nager.java:384)\n        at java.lang.Thread.run(Unknown Source)",
    "Added mapping range checking to IncludeEntry to avoid out of bounds exceptions\n\nBG"
  ],
  "commentCreationDates": [
    "2004-02-19T10:32:17+01:00",
    "2004-04-21T04:15:20+02:00"
  ],
  "traces": [
    {
      "exceptionType": "java.lang.ArrayIndexOutOfBoundsException",
      "message": "1190",
      "elements": [
        {
          "method": "org.eclipse.cdt.internal.core.index.impl.IncludeEntry.mapRefs",
          "source": "Include Entry.java:161"
        },
        {
          "method": "org.eclipse.cdt.internal.core.index.impl.MergeFactory.mergeIncludes",
          "source": "M ergeFactory.java:211"
        },
        {
          "method": "org.eclipse.cdt.internal.core.index.impl.MergeFactory.merge",
          "source": "MergeFact ory.java:82"
        },
        {
          "method": "org.eclipse.cdt.internal.core.index.impl.Index.merge",
          "source": "Index.java:262"
        },
        {
          "method": "org.eclipse.cdt.internal.core.index.impl.Index.save",
          "source": "Index.java:426"
        },
        {
          "method": "org.eclipse.cdt.internal.core.search.indexing.IndexManager.saveIndex",
          "source": " IndexManager.java:422"
        },
        {
          "method": "org.eclipse.cdt.internal.core.search.indexing.SaveIndex.execute",
          "source": "SaveI ndex.java:40"
        },
        {
          "method": "org.eclipse.cdt.internal.core.search.processing.JobManager.run",
          "source": "JobMan ager.java:384"
        },
        {
          "method": "java.lang.Thread.run",
          "source": "Unknown Source"
        }
      ],
      "number": 0,
      "commentIndex": 0,
      "bugId": "52467",
      "date": "2004-02-19T10:32:17+01:00",
      "product": "CDT",
      "component": "CDT-parser",
      "severity": "major"
    },
    {
      "exceptionType": "java.lang.ArrayIndexOutOfBoundsException",
      "message": "1190",
      "elements": [
        {
          "method": "org.eclipse.cdt.internal.core.index.impl.IncludeEntry.mapRefs",
          "source": "Include Entry.java:161"
        },
        {
          "method": "org.eclipse.cdt.internal.core.index.impl.MergeFactory.mergeIncludes",
          "source": "M ergeFactory.java:211"
        },
        {
          "method": "org.eclipse.cdt.internal.core.index.impl.MergeFactory.merge",
          "source": "MergeFact ory.java:82"
        },
        {
          "method": "org.eclipse.cdt.internal.core.index.impl.Index.merge",
          "source": "Index.java:262"
        },
        {
          "method": "org.eclipse.cdt.internal.core.index.impl.Index.save",
          "source": "Index.java:426"
        },
        {
          "method": "org.eclipse.cdt.internal.core.search.indexing.IndexManager.saveIndex",
          "source": " IndexManager.java:422"
        },
        {
          "method": "org.eclipse.cdt.internal.core.search.indexing.SaveIndex.execute",
          "source": "SaveI ndex.java:40"
        },
        {
          "method": "org.eclipse.cdt.internal.core.search.processing.JobManager.run",
          "source": "JobMan ager.java:384"
        },
        {
          "method": "java.lang.Thread.run",
          "source": "Unknown Source"
        }
      ],
      "number": 1,
      "commentIndex": 0,
      "bugId": "52467",
      "date": "2004-02-19T10:32:17+01:00",
      "product": "CDT",
      "component": "CDT-parser",
      "severity": "major"
    }
  ],
  "groupId": "52467",
  "bugId": "52467",
  "date": "2004-02-19T10:32:17+01:00",
  "product": "CDT",
  "component": "CDT-parser",
  "severity": "major"
}