{
  "comments": [
    "Version 3.0.m7.\n\no Right-click/Source/Sort Members.\no Ctrl-S (Save) right away.\n\nYou get a \"Save Failed\" dialog and the following on the console.\n\n!MESSAGE Save Failed\nSave Failed\nReason:\n!ENTRY org.eclipse.ui 2 0 Feb 24, 2004 13:01:46.744\n!MESSAGE Save Failed\n!STACK 0\njava.lang.NullPointerException\n        at\norg.eclipse.search2.internal.ui.text.PositionTracker$3.run(PositionTracker.java:262)\n        at\norg.eclipse.search2.internal.ui.text.PositionTracker.doForExistingMatchesIn(PositionTracker.java:197)\n        at\norg.eclipse.search2.internal.ui.text.PositionTracker.dirtyStateChanged(PositionTracker.java:252)\n        at\norg.eclipse.core.internal.filebuffers.TextFileBufferManager.fireDirtyStateChanged(TextFileBufferManager.j\n226)\n        at\norg.eclipse.core.internal.filebuffers.ResourceFileBuffer.commit(ResourceFileBuffer.java:286)\n        at\norg.eclipse.jdt.internal.ui.javaeditor.filebuffers.DocumentAdapter2.save(DocumentAdapter2.java:356)\n        at\norg.eclipse.jdt.internal.core.CommitWorkingCopyOperation.executeOperation(CommitWorkingCopyOperation.java\n)\n        at\norg.eclipse.jdt.internal.core.JavaModelOperation.run(JavaModelOperation.java:700)\n        at org.eclipse.core.internal.resources.Workspace.run(Workspace.java:1567)\n        at\norg.eclipse.jdt.internal.core.JavaModelOperation.runOperation(JavaModelOperation.java:744)\n        at\norg.eclipse.jdt.internal.core.CompilationUnit.commitWorkingCopy(CompilationUnit.java:281)\n        at\norg.eclipse.jdt.internal.ui.javaeditor.filebuffers.CompilationUnitDocumentProvider2.commitWorkingCopy(Com\ntionUnitDocumentProvider2.java:880)\n        at\norg.eclipse.jdt.internal.ui.javaeditor.filebuffers.CompilationUnitDocumentProvider2$2.execute(Compilation\nDocumentProvider2.java:928)\n        at\norg.eclipse.ui.editors.text.TextFileDocumentProvider$DocumentProviderOperation.run(TextFileDocumentProvid\nava:93)\n        at\norg.eclipse.ui.actions.WorkspaceModifyDelegatingOperation.execute(WorkspaceModifyDelegatingOperation.java\n\n        at\norg.eclipse.ui.actions.WorkspaceModifyOperation$1.run(WorkspaceModifyOperation.java:91)\n        at org.eclipse.core.internal.resources.Workspace.run(Workspace.java:1567)\n        at\norg.eclipse.ui.actions.WorkspaceModifyOperation.run(WorkspaceModifyOperation.java:105)\n        at\norg.eclipse.ui.editors.text.WorkspaceOperationRunner.run(WorkspaceOperationRunner.java:72)\n        at\norg.eclipse.ui.editors.text.WorkspaceOperationRunner.run(WorkspaceOperationRunner.java:62)\n        at\norg.eclipse.ui.editors.text.TextFileDocumentProvider.executeOperation(TextFileDocumentProvider.java:391)\n        at\norg.eclipse.ui.editors.text.TextFileDocumentProvider.saveDocument(TextFileDocumentProvider.java:602)\n        at\norg.eclipse.ui.texteditor.AbstractTextEditor.performSave(AbstractTextEditor.java:3056)\n        at\norg.eclipse.jdt.internal.ui.javaeditor.CompilationUnitEditor.performSave(CompilationUnitEditor.java:1150)\n        at\norg.eclipse.jdt.internal.ui.javaeditor.CompilationUnitEditor.doSave(CompilationUnitEditor.java:1214)\n        at org.eclipse.ui.internal.EditorManager$10.run(EditorManager.java:1015)\n        at org.eclipse.ui.internal.EditorManager$8.run(EditorManager.java:870)\n        at\norg.eclipse.jface.operation.ModalContext.runInCurrentThread(ModalContext.java:302)\n        at org.eclipse.jface.operation.ModalContext.run(ModalContext.java:252)\n        at\norg.eclipse.jface.window.ApplicationWindow$1.run(ApplicationWindow.java:550)\n        at org.eclipse.swt.custom.BusyIndicator.showWhile(BusyIndicator.java:84)\n        at\norg.eclipse.jface.window.ApplicationWindow.run(ApplicationWindow.java:547)\n        at org.eclipse.ui.internal.WorkbenchWindow.run(WorkbenchWindow.java:1644)\n        at\norg.eclipse.ui.internal.EditorManager.runProgressMonitorOperation(EditorManager.java:876)\n        at org.eclipse.ui.internal.EditorManager.savePart(EditorManager.java:1020)\n        at org.eclipse.ui.internal.WorkbenchPage.savePart(WorkbenchPage.java:2420)\n        at org.eclipse.ui.internal.WorkbenchPage.saveEditor(WorkbenchPage.java:2432)\n        at org.eclipse.ui.internal.SaveAction.run(SaveAction.java:72)\n        at org.eclipse.jface.action.Action.runWithEvent(Action.java:881)\n        at\norg.eclipse.ui.internal.commands.ActionHandler.execute(ActionHandler.java:40)\n        at\norg.eclipse.ui.internal.keys.WorkbenchKeyboard.executeCommand(WorkbenchKeyboard.java:427)\n        at\norg.eclipse.ui.internal.keys.WorkbenchKeyboard.press(WorkbenchKeyboard.java:815)\n        at\norg.eclipse.ui.internal.keys.WorkbenchKeyboard.processKeyEvent(WorkbenchKeyboard.java:856)\n        at\norg.eclipse.ui.internal.keys.WorkbenchKeyboard.filterKeySequenceBindings(WorkbenchKeyboard.java:526)\n        at\norg.eclipse.ui.internal.keys.WorkbenchKeyboard.access$2(WorkbenchKeyboard.java:458)\n        at\norg.eclipse.ui.internal.keys.WorkbenchKeyboard$1.handleEvent(WorkbenchKeyboard.java:241)\n        at org.eclipse.swt.widgets.EventTable.sendEvent(EventTable.java:82)\n        at org.eclipse.swt.widgets.Display.filterEvent(Display.java:699)\n        at org.eclipse.swt.widgets.Widget.sendEvent(Widget.java:832)\n        at org.eclipse.swt.widgets.Widget.sendEvent(Widget.java:857)\n        at org.eclipse.swt.widgets.Widget.sendEvent(Widget.java:842)\n        at org.eclipse.swt.widgets.Control.sendKeyEvent(Control.java:1716)\n        at org.eclipse.swt.widgets.Control.sendKeyEvent(Control.java:1712)\n        at org.eclipse.swt.widgets.Control.WM_CHAR(Control.java:3037)\n        at org.eclipse.swt.widgets.Control.windowProc(Control.java:2940)\n        at org.eclipse.swt.widgets.Display.windowProc(Display.java:2873)\n        at org.eclipse.swt.internal.win32.OS.DispatchMessageW(Native Method)\n        at org.eclipse.swt.internal.win32.OS.DispatchMessage(OS.java:1371)\n        at org.eclipse.swt.widgets.Display.readAndDispatch(Display.java:2027)\n        at org.eclipse.ui.internal.Workbench.runEventLoop(Workbench.java:1550)\n        at org.eclipse.ui.internal.Workbench.runUI(Workbench.java:1526)\n        at\norg.eclipse.ui.internal.Workbench.createAndRunWorkbench(Workbench.java:265)\n        at org.eclipse.ui.PlatformUI.createAndRunWorkbench(PlatformUI.java:139)\n        at org.eclipse.ui.internal.ide.IDEApplication.run(IDEApplication.java:47)\n        at\norg.eclipse.core.internal.runtime.PlatformActivator$1.run(PlatformActivator.java:257)\n        at\norg.eclipse.core.runtime.adaptor.EclipseStarter.run(EclipseStarter.java:104)\n        at sun.reflect.NativeMethodAccessorImpl.invoke0(Native Method)\n        at\nsun.reflect.NativeMethodAccessorImpl.invoke(NativeMethodAccessorImpl.java:39)\n        at\nsun.reflect.DelegatingMethodAccessorImpl.invoke(DelegatingMethodAccessorImpl.java:25)\n        at java.lang.reflect.Method.invoke(Method.java:324)\n        at org.eclipse.core.launcher.Main.basicRun(Main.java:279)\n        at org.eclipse.core.launcher.Main.run(Main.java:742)\n        at org.eclipse.core.launcher.Main.main(Main.java:581)\nSave Failed",
    "Could you please attach the source of the compilation unit?",
    "Move to Platform/Search",
    "fixed in builds \u003e 2004-03-17"
  ],
  "commentCreationDates": [
    "2004-02-24T21:15:34+01:00",
    "2004-02-24T23:05:59+01:00",
    "2004-03-24T16:14:24+01:00",
    "2004-03-24T17:00:58+01:00"
  ],
  "traces": [
    {
      "exceptionType": "java.lang.NullPointerException",
      "elements": [
        {
          "method": "org.eclipse.search2.internal.ui.text.PositionTracker$3.run",
          "source": "PositionTracker.java:262"
        },
        {
          "method": "org.eclipse.search2.internal.ui.text.PositionTracker.doForExistingMatchesIn",
          "source": "PositionTracker.java:197"
        },
        {
          "method": "org.eclipse.search2.internal.ui.text.PositionTracker.dirtyStateChanged",
          "source": "PositionTracker.java:252"
        },
        {
          "method": "org.eclipse.core.internal.filebuffers.TextFileBufferManager.fireDirtyStateChanged",
          "source": "TextFileBufferManager.j 226"
        },
        {
          "method": "org.eclipse.core.internal.filebuffers.ResourceFileBuffer.commit",
          "source": "ResourceFileBuffer.java:286"
        },
        {
          "method": "org.eclipse.jdt.internal.ui.javaeditor.filebuffers.DocumentAdapter2.save",
          "source": "DocumentAdapter2.java:356"
        },
        {
          "method": "org.eclipse.jdt.internal.core.CommitWorkingCopyOperation.executeOperation",
          "source": "CommitWorkingCopyOperation.java "
        },
        {
          "method": "org.eclipse.jdt.internal.core.JavaModelOperation.run",
          "source": "JavaModelOperation.java:700"
        },
        {
          "method": "org.eclipse.core.internal.resources.Workspace.run",
          "source": "Workspace.java:1567"
        },
        {
          "method": "org.eclipse.jdt.internal.core.JavaModelOperation.runOperation",
          "source": "JavaModelOperation.java:744"
        },
        {
          "method": "org.eclipse.jdt.internal.core.CompilationUnit.commitWorkingCopy",
          "source": "CompilationUnit.java:281"
        },
        {
          "method": "org.eclipse.jdt.internal.ui.javaeditor.filebuffers.CompilationUnitDocumentProvider2.commitWorkingCopy",
          "source": "Com tionUnitDocumentProvider2.java:880"
        },
        {
          "method": "org.eclipse.jdt.internal.ui.javaeditor.filebuffers.CompilationUnitDocumentProvider2$2.execute",
          "source": "Compilation DocumentProvider2.java:928"
        },
        {
          "method": "org.eclipse.ui.editors.text.TextFileDocumentProvider$DocumentProviderOperation.run",
          "source": "TextFileDocumentProvid ava:93"
        }
      ],
      "number": 0,
      "commentIndex": 0,
      "bugId": "52987",
      "date": "2004-02-24T21:15:34+01:00",
      "product": "Platform",
      "component": "Search",
      "severity": "normal"
    }
  ],
  "groupId": "52987",
  "bugId": "52987",
  "date": "2004-02-24T21:15:34+01:00",
  "product": "Platform",
  "component": "Search",
  "severity": "normal"
}