{
  "comments": [
    "Build 20040225 - win32 - multiple windows\n\nEditor tab offers list of open files. This worked for a few minutes, until it \nsuddenly did not any longer, issuing console dumps (see below).\n\n\n!ENTRY org.eclipse.ui 4 4 Feb 25, 2004 18:31:30.430\n!MESSAGE Unhandled event loop exception\nUnhandled event loop exception\nReason:\n!ENTRY org.eclipse.ui 4 0 Feb 25, 2004 18:31:30.470\n!MESSAGE Widget is disposed\n!STACK 0\norg.eclipse.swt.SWTException: Widget is disposed\n        at org.eclipse.swt.SWT.error(SWT.java:2625)\n        at org.eclipse.swt.SWT.error(SWT.java:2555)\n        at org.eclipse.swt.widgets.Widget.error(Widget.java:377)\n        at org.eclipse.swt.widgets.Widget.checkWidget(Widget.java:306)\n        at org.eclipse.swt.widgets.Text.setText(Text.java:1559)\n        at org.eclipse.ui.internal.AbstractTableInformationControl.inputChanged\n(AbstractTableInformationControl.java:437)\n        at org.eclipse.ui.internal.EditorsInformationControl.setInput\n(EditorsInformationControl.java:51)\n        at org.eclipse.ui.internal.TabbedEditorWorkbook$4.showList\n(TabbedEditorWorkbook.java:224)\n        at org.eclipse.ui.internal.TabbedEditorWorkbook$4.showList\n(TabbedEditorWorkbook.java:220)\n        at org.eclipse.swt.custom.CTabFolder2.onMouse(CTabFolder2.java:1992)\n        at org.eclipse.swt.custom.CTabFolder2$1.handleEvent\n(CTabFolder2.java:283)\n        at org.eclipse.swt.widgets.EventTable.sendEvent(EventTable.java:82)\n        at org.eclipse.swt.widgets.Widget.sendEvent(Widget.java:833)\n        at org.eclipse.swt.widgets.Display.runDeferredEvents(Display.java:2352)\n        at org.eclipse.swt.widgets.Display.readAndDispatch(Display.java:2033)\n        at org.eclipse.ui.internal.Workbench.runEventLoop(Workbench.java:1566)\n        at org.eclipse.ui.internal.Workbench.runUI(Workbench.java:1542)\n        at org.eclipse.ui.internal.Workbench.createAndRunWorkbench\n(Workbench.java:263)\n        at org.eclipse.ui.PlatformUI.createAndRunWorkbench(PlatformUI.java:139)\n        at org.eclipse.ui.internal.ide.IDEApplication.run\n(IDEApplication.java:47)\n        at org.eclipse.core.internal.runtime.PlatformActivator$1.run\n(PlatformActivator.java:256)\n        at org.eclipse.core.runtime.adaptor.EclipseStarter.run\n(EclipseStarter.java:100)\n        at sun.reflect.NativeMethodAccessorImpl.invoke0(Native Method)\n        at sun.reflect.NativeMethodAccessorImpl.invoke\n(NativeMethodAccessorImpl.java:39)\n        at sun.reflect.DelegatingMethodAccessorImpl.invoke\n(DelegatingMethodAccessorImpl.java:25)\n        at java.lang.reflect.Method.invoke(Method.java:324)\n        at org.eclipse.core.launcher.Main.basicRun(Main.java:279)\n        at org.eclipse.core.launcher.Main.run(Main.java:742)\n        at org.eclipse.core.launcher.Main.main(Main.java:581)\nWidget is disposed",
    "When pressing on the little icon (triangle pointing down) to reveal list of \nopen files, it fails too.",
    "\n\n*** This bug has been marked as a duplicate of 52399 ***"
  ],
  "commentCreationDates": [
    "2004-02-25T17:46:05+01:00",
    "2004-02-25T17:48:04+01:00",
    "2004-02-25T18:58:48+01:00"
  ],
  "traces": [
    {
      "exceptionType": "org.eclipse.swt.SWTException",
      "message": "Widget is disposed",
      "elements": [
        {
          "method": "org.eclipse.swt.SWT.error",
          "source": "SWT.java:2625"
        },
        {
          "method": "org.eclipse.swt.SWT.error",
          "source": "SWT.java:2555"
        },
        {
          "method": "org.eclipse.swt.widgets.Widget.error",
          "source": "Widget.java:377"
        },
        {
          "method": "org.eclipse.swt.widgets.Widget.checkWidget",
          "source": "Widget.java:306"
        },
        {
          "method": "org.eclipse.swt.widgets.Text.setText",
          "source": "Text.java:1559"
        },
        {
          "method": "org.eclipse.ui.internal.AbstractTableInformationControl.inputChanged",
          "source": "AbstractTableInformationControl.java:437"
        },
        {
          "method": "org.eclipse.ui.internal.EditorsInformationControl.setInput",
          "source": "EditorsInformationControl.java:51"
        },
        {
          "method": "org.eclipse.ui.internal.TabbedEditorWorkbook$4.showList",
          "source": "TabbedEditorWorkbook.java:224"
        },
        {
          "method": "org.eclipse.ui.internal.TabbedEditorWorkbook$4.showList",
          "source": "TabbedEditorWorkbook.java:220"
        },
        {
          "method": "org.eclipse.swt.custom.CTabFolder2.onMouse",
          "source": "CTabFolder2.java:1992"
        },
        {
          "method": "org.eclipse.swt.custom.CTabFolder2$1.handleEvent",
          "source": "CTabFolder2.java:283"
        },
        {
          "method": "org.eclipse.swt.widgets.EventTable.sendEvent",
          "source": "EventTable.java:82"
        },
        {
          "method": "org.eclipse.swt.widgets.Widget.sendEvent",
          "source": "Widget.java:833"
        },
        {
          "method": "org.eclipse.swt.widgets.Display.runDeferredEvents",
          "source": "Display.java:2352"
        },
        {
          "method": "org.eclipse.swt.widgets.Display.readAndDispatch",
          "source": "Display.java:2033"
        },
        {
          "method": "org.eclipse.ui.internal.Workbench.runEventLoop",
          "source": "Workbench.java:1566"
        },
        {
          "method": "org.eclipse.ui.internal.Workbench.runUI",
          "source": "Workbench.java:1542"
        },
        {
          "method": "org.eclipse.ui.internal.Workbench.createAndRunWorkbench",
          "source": "Workbench.java:263"
        },
        {
          "method": "org.eclipse.ui.PlatformUI.createAndRunWorkbench",
          "source": "PlatformUI.java:139"
        },
        {
          "method": "org.eclipse.ui.internal.ide.IDEApplication.run",
          "source": "IDEApplication.java:47"
        },
        {
          "method": "org.eclipse.core.internal.runtime.PlatformActivator$1.run",
          "source": "PlatformActivator.java:256"
        },
        {
          "method": "org.eclipse.core.runtime.adaptor.EclipseStarter.run",
          "source": "EclipseStarter.java:100"
        },
        {
          "method": "sun.reflect.NativeMethodAccessorImpl.invoke0",
          "source": "Native Method"
        },
        {
          "method": "sun.reflect.NativeMethodAccessorImpl.invoke",
          "source": "NativeMethodAccessorImpl.java:39"
        },
        {
          "method": "sun.reflect.DelegatingMethodAccessorImpl.invoke",
          "source": "DelegatingMethodAccessorImpl.java:25"
        },
        {
          "method": "java.lang.reflect.Method.invoke",
          "source": "Method.java:324"
        },
        {
          "method": "org.eclipse.core.launcher.Main.basicRun",
          "source": "Main.java:279"
        },
        {
          "method": "org.eclipse.core.launcher.Main.run",
          "source": "Main.java:742"
        },
        {
          "method": "org.eclipse.core.launcher.Main.main",
          "source": "Main.java:581"
        }
      ],
      "number": 0,
      "commentIndex": 0,
      "bugId": "53088",
      "duplicateId": "52399",
      "date": "2004-02-25T17:46:05+01:00",
      "product": "Platform",
      "component": "UI",
      "severity": "normal"
    }
  ],
  "groupId": "52399",
  "bugId": "53088",
  "duplicateId": "52399",
  "date": "2004-02-25T17:46:05+01:00",
  "product": "Platform",
  "component": "UI",
  "severity": "normal"
}