{
  "comments": [
    "I did an edit and Ctrl-S (quickly, one after the other) on a 2500+ lines\nbuild.xml and Eclipse appear to lock up with 70% CPU usage and then dumped the\nfollowing on the console. Version 3.0.m7.\n\nReason:\n!ENTRY org.eclipse.ui 4 0 Feb 25, 2004 18:28:23.503\n!MESSAGE java.lang.ClassCastException\n!STACK 0\njava.lang.ClassCastException\n        at\norg.eclipse.ant.internal.ui.editor.AntEditorCompletionProcessor.getEnclosingTargetName(AntEditorCompletionPro\ncessor.java:1096)\n        at\norg.eclipse.ant.internal.ui.editor.AntEditorCompletionProcessor.findPropertiesFromDocument(AntEditorCompletio\nnProcessor.java:957)\n        at\norg.eclipse.ant.internal.ui.editor.AntEditorCompletionProcessor.getPropertyProposals(AntEditorCompletionProce\nssor.java:480)\n        at\norg.eclipse.ant.internal.ui.editor.AntEditorCompletionProcessor.getProposalsFromDocument(AntEditorCompletionP\nrocessor.java:289)\n        at\norg.eclipse.ant.internal.ui.editor.AntEditorCompletionProcessor.determineProposals(AntEditorCompletionProcess\nor.java:240)\n        at\norg.eclipse.ant.internal.ui.editor.AntEditorCompletionProcessor.computeCompletionProposals(AntEditorCompletio\nnProcessor.java:181)\n        at\norg.eclipse.jface.text.contentassist.ContentAssistant.computeCompletionProposals(ContentAssistant.java:1433)\n        at\norg.eclipse.jface.text.contentassist.CompletionProposalPopup.computeProposals(CompletionProposalPopup.java:23\n1)\n        at\norg.eclipse.jface.text.contentassist.CompletionProposalPopup.access$7(CompletionProposalPopup.java:227)\n        at\norg.eclipse.jface.text.contentassist.CompletionProposalPopup$1.run(CompletionProposalPopup.java:190)\n        at org.eclipse.swt.custom.BusyIndicator.showWhile(BusyIndicator.java:84)\n        at\norg.eclipse.jface.text.contentassist.CompletionProposalPopup.showProposals(CompletionProposalPopup.java:185)\n        at\norg.eclipse.jface.text.contentassist.ContentAssistant$2.run(ContentAssistant.java:319)\n        at org.eclipse.swt.widgets.RunnableLock.run(RunnableLock.java:35)\n        at\norg.eclipse.swt.widgets.Synchronizer.runAsyncMessages(Synchronizer.java:102)\n        at org.eclipse.swt.widgets.Display.runAsyncMessages(Display.java:2325)\n        at org.eclipse.swt.widgets.Display.readAndDispatch(Display.java:2033)\n        at org.eclipse.ui.internal.Workbench.runEventLoop(Workbench.java:1550)\n        at org.eclipse.ui.internal.Workbench.runUI(Workbench.java:1526)\n        at\norg.eclipse.ui.internal.Workbench.createAndRunWorkbench(Workbench.java:265)\n        at org.eclipse.ui.PlatformUI.createAndRunWorkbench(PlatformUI.java:139)\n        at org.eclipse.ui.internal.ide.IDEApplication.run(IDEApplication.java:47)\n        at\norg.eclipse.core.internal.runtime.PlatformActivator$1.run(PlatformActivator.java:257)\n        at\norg.eclipse.core.runtime.adaptor.EclipseStarter.run(EclipseStarter.java:104)\n        at sun.reflect.NativeMethodAccessorImpl.invoke0(Native Method)\n        at\nsun.reflect.NativeMethodAccessorImpl.invoke(NativeMethodAccessorImpl.java:39)\n        at\nsun.reflect.DelegatingMethodAccessorImpl.invoke(DelegatingMethodAccessorImpl.java:25)\n        at java.lang.reflect.Method.invoke(Method.java:324)\n        at org.eclipse.core.launcher.Main.basicRun(Main.java:279)\n        at org.eclipse.core.launcher.Main.run(Main.java:742)\n        at org.eclipse.core.launcher.Main.main(Main.java:581)\njava.lang.ClassCastException",
    "This exception is triggered from doing a code completion for properties on a \ntop level task or type. The CPU being busy is likely from the code assist \ntriggered a reconcile (see bug 52202).\n\nFixed in AntEditorCompletionProcessor.",
    "Test case:\n\u003cproject default\u003d\"environ\"\u003e\n    \u003cimport file\u003d\"${\"/\u003e\n\u003c/project\u003e\n\nCode assist after the \"${\"\n\nPlease verify Jared.",
    "Verified."
  ],
  "commentCreationDates": [
    "2004-02-26T02:43:37+01:00",
    "2004-02-26T02:53:36+01:00",
    "2004-02-26T02:55:06+01:00",
    "2004-03-01T23:24:22+01:00"
  ],
  "traces": [
    {
      "exceptionType": "java.lang.ClassCastException",
      "elements": [
        {
          "method": "org.eclipse.ant.internal.ui.editor.AntEditorCompletionProcessor.getEnclosingTargetName",
          "source": "AntEditorCompletionPro cessor.java:1096"
        },
        {
          "method": "org.eclipse.ant.internal.ui.editor.AntEditorCompletionProcessor.findPropertiesFromDocument",
          "source": "AntEditorCompletio nProcessor.java:957"
        },
        {
          "method": "org.eclipse.ant.internal.ui.editor.AntEditorCompletionProcessor.getPropertyProposals",
          "source": "AntEditorCompletionProce ssor.java:480"
        },
        {
          "method": "org.eclipse.ant.internal.ui.editor.AntEditorCompletionProcessor.getProposalsFromDocument",
          "source": "AntEditorCompletionP rocessor.java:289"
        },
        {
          "method": "org.eclipse.ant.internal.ui.editor.AntEditorCompletionProcessor.determineProposals",
          "source": "AntEditorCompletionProcess or.java:240"
        },
        {
          "method": "org.eclipse.ant.internal.ui.editor.AntEditorCompletionProcessor.computeCompletionProposals",
          "source": "AntEditorCompletio nProcessor.java:181"
        },
        {
          "method": "org.eclipse.jface.text.contentassist.ContentAssistant.computeCompletionProposals",
          "source": "ContentAssistant.java:1433"
        },
        {
          "method": "org.eclipse.jface.text.contentassist.CompletionProposalPopup.computeProposals",
          "source": "CompletionProposalPopup.java:23 1"
        },
        {
          "method": "org.eclipse.jface.text.contentassist.CompletionProposalPopup.access$7",
          "source": "CompletionProposalPopup.java:227"
        },
        {
          "method": "org.eclipse.jface.text.contentassist.CompletionProposalPopup$1.run",
          "source": "CompletionProposalPopup.java:190"
        },
        {
          "method": "org.eclipse.swt.custom.BusyIndicator.showWhile",
          "source": "BusyIndicator.java:84"
        },
        {
          "method": "org.eclipse.jface.text.contentassist.CompletionProposalPopup.showProposals",
          "source": "CompletionProposalPopup.java:185"
        },
        {
          "method": "org.eclipse.jface.text.contentassist.ContentAssistant$2.run",
          "source": "ContentAssistant.java:319"
        },
        {
          "method": "org.eclipse.swt.widgets.RunnableLock.run",
          "source": "RunnableLock.java:35"
        },
        {
          "method": "org.eclipse.swt.widgets.Synchronizer.runAsyncMessages",
          "source": "Synchronizer.java:102"
        },
        {
          "method": "org.eclipse.swt.widgets.Display.runAsyncMessages",
          "source": "Display.java:2325"
        },
        {
          "method": "org.eclipse.swt.widgets.Display.readAndDispatch",
          "source": "Display.java:2033"
        },
        {
          "method": "org.eclipse.ui.internal.Workbench.runEventLoop",
          "source": "Workbench.java:1550"
        },
        {
          "method": "org.eclipse.ui.internal.Workbench.runUI",
          "source": "Workbench.java:1526"
        },
        {
          "method": "org.eclipse.ui.internal.Workbench.createAndRunWorkbench",
          "source": "Workbench.java:265"
        },
        {
          "method": "org.eclipse.ui.PlatformUI.createAndRunWorkbench",
          "source": "PlatformUI.java:139"
        },
        {
          "method": "org.eclipse.ui.internal.ide.IDEApplication.run",
          "source": "IDEApplication.java:47"
        },
        {
          "method": "org.eclipse.core.internal.runtime.PlatformActivator$1.run",
          "source": "PlatformActivator.java:257"
        },
        {
          "method": "org.eclipse.core.runtime.adaptor.EclipseStarter.run",
          "source": "EclipseStarter.java:104"
        },
        {
          "method": "sun.reflect.NativeMethodAccessorImpl.invoke0",
          "source": "Native Method"
        },
        {
          "method": "sun.reflect.NativeMethodAccessorImpl.invoke",
          "source": "NativeMethodAccessorImpl.java:39"
        },
        {
          "method": "sun.reflect.DelegatingMethodAccessorImpl.invoke",
          "source": "DelegatingMethodAccessorImpl.java:25"
        },
        {
          "method": "java.lang.reflect.Method.invoke",
          "source": "Method.java:324"
        },
        {
          "method": "org.eclipse.core.launcher.Main.basicRun",
          "source": "Main.java:279"
        },
        {
          "method": "org.eclipse.core.launcher.Main.run",
          "source": "Main.java:742"
        },
        {
          "method": "org.eclipse.core.launcher.Main.main",
          "source": "Main.java:581"
        }
      ],
      "number": 0,
      "commentIndex": 0,
      "bugId": "53142",
      "date": "2004-02-26T02:43:37+01:00",
      "product": "Platform",
      "component": "Ant",
      "severity": "normal"
    }
  ],
  "groupId": "53142",
  "bugId": "53142",
  "date": "2004-02-26T02:43:37+01:00",
  "product": "Platform",
  "component": "Ant",
  "severity": "normal"
}