{
  "comments": [
    "build M0225 (r2.1.3 candidate), winxp, ibm jre 1.3.1 sr2\n\n- empty workspace\n- create PDE plug-in X with default structure\n- modify plugin.xml to optionally require a non-existant plug-in\n      \u003cimport plugin\u003d\"a\" optional\u003d\"true\"/\u003e\n- File -\u003e Deploy plug-in and Create Ant Build File give the same error.\n\n!ENTRY org.eclipse.pde.ui 4 0 Feb 26, 2004 13:24:53.702\n!MESSAGE null argument:A plug-in version identifier must be non-empty.\n!STACK 0\norg.eclipse.core.internal.runtime.AssertionFailedException: null argument:A plug\n-in version identifier must be non-empty.\n        at org.eclipse.core.runtime.PluginVersionIdentifier.parseVersion(PluginV\nersionIdentifier.java(Compiled Code))\n        at org.eclipse.core.runtime.PluginVersionIdentifier.parseVersion(PluginV\nersionIdentifier.java(Compiled Code))\n        at org.eclipse.core.runtime.PluginVersionIdentifier.\u003cinit\u003e(PluginVersion\nIdentifier.java(Compiled Code))\n        at org.eclipse.pde.internal.build.AbstractBuildScriptGenerator.internalG\netPlugin(AbstractBuildScriptGenerator.java:279)\n        at org.eclipse.pde.internal.build.AbstractBuildScriptGenerator.getPlugin\n(AbstractBuildScriptGenerator.java(Compiled Code))\n        at org.eclipse.pde.internal.build.AbstractBuildScriptGenerator.addPrereq\nuisites(AbstractBuildScriptGenerator.java:544)\n        at org.eclipse.pde.internal.build.AbstractBuildScriptGenerator.getClassp\nath(AbstractBuildScriptGenerator.java:134)\n        at org.eclipse.pde.internal.build.AbstractBuildScriptGenerator.generateB\nuildJarsTarget(AbstractBuildScriptGenerator.java:651)\n        at org.eclipse.pde.internal.build.ModelBuildScriptGenerator.generateBuil\ndScript(ModelBuildScriptGenerator.java:83)\n        at org.eclipse.pde.internal.build.ModelBuildScriptGenerator.generate(Mod\nelBuildScriptGenerator.java:64)\n        at org.eclipse.pde.internal.ui.feature.BuildPluginAction.makeScripts(Bui\nldPluginAction.java:216)\n        at org.eclipse.pde.internal.ui.feature.BuildPluginAction.doBuildPlugin(B\nuildPluginAction.java:145)\n        at org.eclipse.pde.internal.ui.feature.BuildPluginAction.access$0(BuildP\nluginAction.java:136)\n        at org.eclipse.pde.internal.ui.feature.BuildPluginAction$2.run(BuildPlug\ninAction.java:59)\n        at org.eclipse.core.internal.resources.Workspace.run(Workspace.java:1595\n)\n        at org.eclipse.pde.internal.ui.feature.BuildPluginAction$1.run(BuildPlug\ninAction.java:66)\n        at org.eclipse.jface.operation.ModalContext.runInCurrentThread(ModalCont\next.java:302)\n        at org.eclipse.jface.operation.ModalContext.run(ModalContext.java:252)\n        at org.eclipse.jface.dialogs.ProgressMonitorDialog.run(ProgressMonitorDi\nalog.java:357)\n        at org.eclipse.pde.internal.ui.feature.BuildPluginAction.run(BuildPlugin\nAction.java:76)\n        at org.eclipse.ui.internal.PluginAction.runWithEvent(PluginAction.java:2\n51)\n        at org.eclipse.jface.action.ActionContributionItem.handleWidgetSelection\n(ActionContributionItem.java:456)\n        at org.eclipse.jface.action.ActionContributionItem.handleWidgetEvent(Act\nionContributionItem.java:403)\n        at org.eclipse.jface.action.ActionContributionItem.access$0(ActionContri\nbutionItem.java:397)\n        at org.eclipse.jface.action.ActionContributionItem$ActionListener.handle\nEvent(ActionContributionItem.java:72)\n        at org.eclipse.swt.widgets.Display.runDeferredEvents(Display.java(Compil\ned Code))\n        at org.eclipse.swt.widgets.Display.readAndDispatch(Display.java(Compiled\n Code))\n        at org.eclipse.ui.internal.Workbench.runEventLoop(Workbench.java(Compile\nd Code))\n        at org.eclipse.ui.internal.Workbench.run(Workbench.java:1385)\n        at org.eclipse.core.internal.boot.InternalBootLoader.run(InternalBootLoa\nder.java:858)\n        at org.eclipse.core.boot.BootLoader.run(BootLoader.java:461)\n        at java.lang.reflect.Method.invoke(Native Method)\n        at org.eclipse.core.launcher.Main.basicRun(Main.java:291)\n        at org.eclipse.core.launcher.Main.run(Main.java:747)\n        at org.eclipse.core.launcher.Main.main(Main.java:583)",
    "Looks like an error in the code that we added in AbstractBuildScriptGenerator.\nNeed to handle the case where we have an optional prereq without a specified\nversion in #internalGetPlugin(prereq);",
    "Fixed and released to r21x maintenance branch.\n\nPascal, I did NOT update HEAD since the code in the branch and that in HEAD in\nthe same class differ so much. Please port change to new code stream or take fix\ninto consideration when writing the new code."
  ],
  "commentCreationDates": [
    "2004-02-26T18:39:48+01:00",
    "2004-02-26T19:35:18+01:00",
    "2004-02-26T19:45:21+01:00"
  ],
  "traces": [
    {
      "exceptionType": "org.eclipse.core.internal.runtime.AssertionFailedException",
      "message": "null argument:A plug -in version identifier must be non-empty.",
      "elements": [
        {
          "method": "org.eclipse.core.runtime.PluginVersionIdentifier.parseVersion",
          "source": "PluginV ersionIdentifier.java(Compiled Code)"
        },
        {
          "method": "org.eclipse.core.runtime.PluginVersionIdentifier.parseVersion",
          "source": "PluginV ersionIdentifier.java(Compiled Code)"
        },
        {
          "method": "org.eclipse.core.runtime.PluginVersionIdentifier.\u003cinit\u003e",
          "source": "PluginVersion Identifier.java(Compiled Code)"
        },
        {
          "method": "org.eclipse.pde.internal.build.AbstractBuildScriptGenerator.internalGetPlugin",
          "source": "AbstractBuildScriptGenerator.java:279"
        },
        {
          "method": "org.eclipse.pde.internal.build.AbstractBuildScriptGenerator.getPlugin",
          "source": "AbstractBuildScriptGenerator.java(Compiled Code)"
        },
        {
          "method": "org.eclipse.pde.internal.build.AbstractBuildScriptGenerator.addPrerequisites",
          "source": "AbstractBuildScriptGenerator.java:544"
        },
        {
          "method": "org.eclipse.pde.internal.build.AbstractBuildScriptGenerator.getClasspath",
          "source": "AbstractBuildScriptGenerator.java:134"
        },
        {
          "method": "org.eclipse.pde.internal.build.AbstractBuildScriptGenerator.generateBuildJarsTarget",
          "source": "AbstractBuildScriptGenerator.java:651"
        },
        {
          "method": "org.eclipse.pde.internal.build.ModelBuildScriptGenerator.generateBuildScript",
          "source": "ModelBuildScriptGenerator.java:83"
        },
        {
          "method": "org.eclipse.pde.internal.build.ModelBuildScriptGenerator.generate",
          "source": "Mod elBuildScriptGenerator.java:64"
        },
        {
          "method": "org.eclipse.pde.internal.ui.feature.BuildPluginAction.makeScripts",
          "source": "Bui ldPluginAction.java:216"
        },
        {
          "method": "org.eclipse.pde.internal.ui.feature.BuildPluginAction.doBuildPlugin",
          "source": "B uildPluginAction.java:145"
        },
        {
          "method": "org.eclipse.pde.internal.ui.feature.BuildPluginAction.access$0",
          "source": "BuildP luginAction.java:136"
        },
        {
          "method": "org.eclipse.pde.internal.ui.feature.BuildPluginAction$2.run",
          "source": "BuildPlug inAction.java:59"
        },
        {
          "method": "org.eclipse.core.internal.resources.Workspace.run",
          "source": "Workspace.java:1595 "
        },
        {
          "method": "org.eclipse.pde.internal.ui.feature.BuildPluginAction$1.run",
          "source": "BuildPlug inAction.java:66"
        },
        {
          "method": "org.eclipse.jface.operation.ModalContext.runInCurrentThread",
          "source": "ModalCont ext.java:302"
        },
        {
          "method": "org.eclipse.jface.operation.ModalContext.run",
          "source": "ModalContext.java:252"
        },
        {
          "method": "org.eclipse.jface.dialogs.ProgressMonitorDialog.run",
          "source": "ProgressMonitorDi alog.java:357"
        },
        {
          "method": "org.eclipse.pde.internal.ui.feature.BuildPluginAction.run",
          "source": "BuildPlugin Action.java:76"
        },
        {
          "method": "org.eclipse.ui.internal.PluginAction.runWithEvent",
          "source": "PluginAction.java:2 51"
        },
        {
          "method": "org.eclipse.jface.action.ActionContributionItem.handleWidgetSelection",
          "source": "ActionContributionItem.java:456"
        },
        {
          "method": "org.eclipse.jface.action.ActionContributionItem.handleWidgetEvent",
          "source": "Act ionContributionItem.java:403"
        },
        {
          "method": "org.eclipse.jface.action.ActionContributionItem.access$0",
          "source": "ActionContri butionItem.java:397"
        },
        {
          "method": "org.eclipse.jface.action.ActionContributionItem$ActionListener.handleEvent",
          "source": "ActionContributionItem.java:72"
        },
        {
          "method": "org.eclipse.swt.widgets.Display.runDeferredEvents",
          "source": "Display.java(Compil ed Code)"
        },
        {
          "method": "org.eclipse.swt.widgets.Display.readAndDispatch",
          "source": "Display.java(Compiled  Code)"
        },
        {
          "method": "org.eclipse.ui.internal.Workbench.runEventLoop",
          "source": "Workbench.java(Compile d Code)"
        },
        {
          "method": "org.eclipse.ui.internal.Workbench.run",
          "source": "Workbench.java:1385"
        },
        {
          "method": "org.eclipse.core.internal.boot.InternalBootLoader.run",
          "source": "InternalBootLoa der.java:858"
        },
        {
          "method": "org.eclipse.core.boot.BootLoader.run",
          "source": "BootLoader.java:461"
        },
        {
          "method": "java.lang.reflect.Method.invoke",
          "source": "Native Method"
        },
        {
          "method": "org.eclipse.core.launcher.Main.basicRun",
          "source": "Main.java:291"
        },
        {
          "method": "org.eclipse.core.launcher.Main.run",
          "source": "Main.java:747"
        },
        {
          "method": "org.eclipse.core.launcher.Main.main",
          "source": "Main.java:583"
        }
      ],
      "number": 0,
      "commentIndex": 0,
      "bugId": "53205",
      "date": "2004-02-26T18:39:48+01:00",
      "product": "PDE",
      "component": "Build",
      "severity": "major"
    }
  ],
  "groupId": "53205",
  "bugId": "53205",
  "date": "2004-02-26T18:39:48+01:00",
  "product": "PDE",
  "component": "Build",
  "severity": "major"
}