{
  "comments": [
    "build i0226, winxp, j9sc20031212\n\nNoticed these exceptions in my log file. Sorry, no reproducable steps and I\ndon\u0027t know what caused them. I should mention that I use j9sc for my dev and\nsunjdk1.4.2 for running my runtime workbench.\n\nWill attach full log. Here\u0027s a sample...\n\n!SUBENTRY 1 org.eclipse.jdt.debug 4 5010 Feb 27, 2004 13:53:23.982\n!MESSAGE com.sun.jdi.InternalException: Got error code in reply: 35 occurred whi\nle retrieving value.\n!STACK 0\ncom.sun.jdi.InternalException: Got error code in reply: 35\n        at java.lang.Throwable.\u003cinit\u003e(Throwable.java)\n        at java.lang.Throwable.\u003cinit\u003e(Throwable.java)\n        at com.sun.jdi.InternalException.\u003cinit\u003e(InternalException.java)\n        at org.eclipse.jdi.internal.MirrorImpl.defaultReplyErrorHandler(MirrorIm\npl.java)\n        at org.eclipse.jdi.internal.StackFrameImpl.getValues(StackFrameImpl.java\n:131)\n        at org.eclipse.jdi.internal.StackFrameImpl.getValue(StackFrameImpl.java:\n72)\n        at org.eclipse.jdt.internal.debug.core.model.JDILocalVariable.retrieveVa\nlue(JDILocalVariable.java:56)",
    "Created an attachment (id\u003d8220)\nlog file\n",
    "\n\n*** This bug has been marked as a duplicate of 46835 ***"
  ],
  "commentCreationDates": [
    "2004-02-27T19:37:02+01:00",
    "2004-02-27T19:37:31+01:00",
    "2004-02-27T20:04:05+01:00"
  ],
  "traces": [
    {
      "exceptionType": "com.sun.jdi.InternalException",
      "message": "Got error code in reply: 35",
      "elements": [
        {
          "method": "java.lang.Throwable.\u003cinit\u003e",
          "source": "Throwable.java"
        },
        {
          "method": "java.lang.Throwable.\u003cinit\u003e",
          "source": "Throwable.java"
        },
        {
          "method": "com.sun.jdi.InternalException.\u003cinit\u003e",
          "source": "InternalException.java"
        },
        {
          "method": "org.eclipse.jdi.internal.MirrorImpl.defaultReplyErrorHandler",
          "source": "MirrorIm pl.java"
        },
        {
          "method": "org.eclipse.jdi.internal.StackFrameImpl.getValues",
          "source": "StackFrameImpl.java :131"
        },
        {
          "method": "org.eclipse.jdi.internal.StackFrameImpl.getValue",
          "source": "StackFrameImpl.java: 72"
        },
        {
          "method": "org.eclipse.jdt.internal.debug.core.model.JDILocalVariable.retrieveValue",
          "source": "JDILocalVariable.java:56"
        }
      ],
      "number": 0,
      "commentIndex": 0,
      "bugId": "53306",
      "duplicateId": "46835",
      "date": "2004-02-27T19:37:02+01:00",
      "product": "JDT",
      "component": "Debug",
      "severity": "normal"
    }
  ],
  "groupId": "46835",
  "bugId": "53306",
  "duplicateId": "46835",
  "date": "2004-02-27T19:37:02+01:00",
  "product": "JDT",
  "component": "Debug",
  "severity": "normal"
}