{
  "comments": [
    "N20030229 + debug plug-ins from HEAD\n\nI get this error in the log about every time I launch the Debug test suite. I\ndon\u0027t get this error in the log of the host, or of a normal (non-test) target.\n\n!SUBENTRY 1 org.eclipse.jdt.debug 4 4 Feb 29, 2004 21:53:03.305\n!MESSAGE Invalid stack frame\n!ENTRY org.eclipse.core.runtime.compatibility 4 1 Feb 29, 2004 21:53:56.912\n!MESSAGE Error while stopping plug-in\n\"reference:file:/home/luc/target/org.eclipse.debug.core/ [6]\".\n!STACK 0\norg.osgi.framework.BundleException: Exception in\norg.eclipse.core.internal.compatibility.PluginActivator.stop()\n        at\norg.eclipse.osgi.framework.internal.core.BundleContext.stop(BundleContext.java:1045)\n        at\norg.eclipse.osgi.framework.internal.core.BundleHost.stopWorker(BundleHost.java:481)\n        at org.eclipse.osgi.framework.internal.core.Bundle.stop(Bundle.java:477)\n        at\norg.eclipse.core.internal.plugins.PluginStopper.run(PluginStopper.java:101)\n        at\norg.eclipse.core.internal.runtime.PlatformActivator.stopLegacyBundles(PlatformActivator.java:290)\n        at\norg.eclipse.core.internal.runtime.PlatformActivator$1.run(PlatformActivator.java:272)\n        at\norg.eclipse.core.runtime.adaptor.EclipseStarter.run(EclipseStarter.java:173)\n        at\norg.eclipse.core.runtime.adaptor.EclipseStarter.run(EclipseStarter.java:106)\n        at sun.reflect.NativeMethodAccessorImpl.invoke0(Native Method)\n        at\nsun.reflect.NativeMethodAccessorImpl.invoke(NativeMethodAccessorImpl.java:39)\n        at\nsun.reflect.DelegatingMethodAccessorImpl.invoke(DelegatingMethodAccessorImpl.java:25)\n        at java.lang.reflect.Method.invoke(Method.java:324)\n        at org.eclipse.core.launcher.Main.basicRun(Main.java:305)\n        at org.eclipse.core.launcher.Main.run(Main.java:745)\n        at org.eclipse.core.launcher.Main.main(Main.java:713)\nNested exception:\njava.lang.NullPointerException\n        at\norg.eclipse.debug.internal.core.sourcelookup.SourceLookupUtils.shutdown(SourceLookupUtils.java:255)\n        at org.eclipse.debug.core.DebugPlugin.shutdown(DebugPlugin.java:445)\n        at\norg.eclipse.core.internal.compatibility.PluginActivator.stop(PluginActivator.java:66)\n        at\norg.eclipse.osgi.framework.internal.core.BundleContext$2.run(BundleContext.java:1029)\n        at java.security.AccessController.doPrivileged(Native Method)\n        at\norg.eclipse.osgi.framework.internal.core.BundleContext.stop(BundleContext.java:1025)\n        at\norg.eclipse.osgi.framework.internal.core.BundleHost.stopWorker(BundleHost.java:481)\n        at org.eclipse.osgi.framework.internal.core.Bundle.stop(Bundle.java:477)\n        at\norg.eclipse.core.internal.plugins.PluginStopper.run(PluginStopper.java:101)\n        at\norg.eclipse.core.internal.runtime.PlatformActivator.stopLegacyBundles(PlatformActivator.java:290)\n        at\norg.eclipse.core.internal.runtime.PlatformActivator$1.run(PlatformActivator.java:272)\n        at\norg.eclipse.core.runtime.adaptor.EclipseStarter.run(EclipseStarter.java:173)\n        at\norg.eclipse.core.runtime.adaptor.EclipseStarter.run(EclipseStarter.java:106)\n        at sun.reflect.NativeMethodAccessorImpl.invoke0(Native Method)\n        at\nsun.reflect.NativeMethodAccessorImpl.invoke(NativeMethodAccessorImpl.java:39)\n        at\nsun.reflect.DelegatingMethodAccessorImpl.invoke(DelegatingMethodAccessorImpl.java:25)\n        at java.lang.reflect.Method.invoke(Method.java:324)\n        at org.eclipse.core.launcher.Main.basicRun(Main.java:305)\n        at org.eclipse.core.launcher.Main.run(Main.java:745)\n        at org.eclipse.core.launcher.Main.main(Main.java:713)",
    "Fixed. The DebugPlugin was set to \"null\" before we called the \nSourceLookupUtils shutdown. Obvious problem :-) Fixed in DebugPlugin.shutdown()",
    "Please verift, Luc.",
    "Verifted. :)"
  ],
  "commentCreationDates": [
    "2004-03-01T06:29:06+01:00",
    "2004-03-01T14:03:43+01:00",
    "2004-03-01T14:04:02+01:00",
    "2004-03-01T23:32:58+01:00"
  ],
  "traces": [
    {
      "exceptionType": "org.osgi.framework.BundleException",
      "message": "Exception in org.eclipse.core.internal.compatibility.PluginActivator.stop()",
      "elements": [
        {
          "method": "org.eclipse.osgi.framework.internal.core.BundleContext.stop",
          "source": "BundleContext.java:1045"
        },
        {
          "method": "org.eclipse.osgi.framework.internal.core.BundleHost.stopWorker",
          "source": "BundleHost.java:481"
        },
        {
          "method": "org.eclipse.osgi.framework.internal.core.Bundle.stop",
          "source": "Bundle.java:477"
        },
        {
          "method": "org.eclipse.core.internal.plugins.PluginStopper.run",
          "source": "PluginStopper.java:101"
        },
        {
          "method": "org.eclipse.core.internal.runtime.PlatformActivator.stopLegacyBundles",
          "source": "PlatformActivator.java:290"
        },
        {
          "method": "org.eclipse.core.internal.runtime.PlatformActivator$1.run",
          "source": "PlatformActivator.java:272"
        },
        {
          "method": "org.eclipse.core.runtime.adaptor.EclipseStarter.run",
          "source": "EclipseStarter.java:173"
        },
        {
          "method": "org.eclipse.core.runtime.adaptor.EclipseStarter.run",
          "source": "EclipseStarter.java:106"
        },
        {
          "method": "sun.reflect.NativeMethodAccessorImpl.invoke0",
          "source": "Native Method"
        },
        {
          "method": "sun.reflect.NativeMethodAccessorImpl.invoke",
          "source": "NativeMethodAccessorImpl.java:39"
        },
        {
          "method": "sun.reflect.DelegatingMethodAccessorImpl.invoke",
          "source": "DelegatingMethodAccessorImpl.java:25"
        },
        {
          "method": "java.lang.reflect.Method.invoke",
          "source": "Method.java:324"
        },
        {
          "method": "org.eclipse.core.launcher.Main.basicRun",
          "source": "Main.java:305"
        },
        {
          "method": "org.eclipse.core.launcher.Main.run",
          "source": "Main.java:745"
        },
        {
          "method": "org.eclipse.core.launcher.Main.main",
          "source": "Main.java:713"
        }
      ],
      "number": 0,
      "commentIndex": 0,
      "bugId": "53374",
      "date": "2004-03-01T06:29:06+01:00",
      "product": "Platform",
      "component": "Debug",
      "severity": "normal"
    },
    {
      "exceptionType": "java.lang.NullPointerException",
      "elements": [
        {
          "method": "org.eclipse.debug.internal.core.sourcelookup.SourceLookupUtils.shutdown",
          "source": "SourceLookupUtils.java:255"
        },
        {
          "method": "org.eclipse.debug.core.DebugPlugin.shutdown",
          "source": "DebugPlugin.java:445"
        },
        {
          "method": "org.eclipse.core.internal.compatibility.PluginActivator.stop",
          "source": "PluginActivator.java:66"
        },
        {
          "method": "org.eclipse.osgi.framework.internal.core.BundleContext$2.run",
          "source": "BundleContext.java:1029"
        },
        {
          "method": "java.security.AccessController.doPrivileged",
          "source": "Native Method"
        },
        {
          "method": "org.eclipse.osgi.framework.internal.core.BundleContext.stop",
          "source": "BundleContext.java:1025"
        },
        {
          "method": "org.eclipse.osgi.framework.internal.core.BundleHost.stopWorker",
          "source": "BundleHost.java:481"
        },
        {
          "method": "org.eclipse.osgi.framework.internal.core.Bundle.stop",
          "source": "Bundle.java:477"
        },
        {
          "method": "org.eclipse.core.internal.plugins.PluginStopper.run",
          "source": "PluginStopper.java:101"
        },
        {
          "method": "org.eclipse.core.internal.runtime.PlatformActivator.stopLegacyBundles",
          "source": "PlatformActivator.java:290"
        },
        {
          "method": "org.eclipse.core.internal.runtime.PlatformActivator$1.run",
          "source": "PlatformActivator.java:272"
        },
        {
          "method": "org.eclipse.core.runtime.adaptor.EclipseStarter.run",
          "source": "EclipseStarter.java:173"
        },
        {
          "method": "org.eclipse.core.runtime.adaptor.EclipseStarter.run",
          "source": "EclipseStarter.java:106"
        },
        {
          "method": "sun.reflect.NativeMethodAccessorImpl.invoke0",
          "source": "Native Method"
        },
        {
          "method": "sun.reflect.NativeMethodAccessorImpl.invoke",
          "source": "NativeMethodAccessorImpl.java:39"
        },
        {
          "method": "sun.reflect.DelegatingMethodAccessorImpl.invoke",
          "source": "DelegatingMethodAccessorImpl.java:25"
        },
        {
          "method": "java.lang.reflect.Method.invoke",
          "source": "Method.java:324"
        },
        {
          "method": "org.eclipse.core.launcher.Main.basicRun",
          "source": "Main.java:305"
        },
        {
          "method": "org.eclipse.core.launcher.Main.run",
          "source": "Main.java:745"
        },
        {
          "method": "org.eclipse.core.launcher.Main.main",
          "source": "Main.java:713"
        }
      ],
      "number": 1,
      "commentIndex": 0,
      "bugId": "53374",
      "date": "2004-03-01T06:29:06+01:00",
      "product": "Platform",
      "component": "Debug",
      "severity": "normal"
    }
  ],
  "groupId": "53374",
  "bugId": "53374",
  "date": "2004-03-01T06:29:06+01:00",
  "product": "Platform",
  "component": "Debug",
  "severity": "normal"
}