{
  "comments": [
    "I20040226\n\n1. Go to preferences, Workbench-\u003eAppearance\n2. Deselect \"Use platform colors\" and press the button for the view foreground color\n-\u003e the color chooser dialog appears\n\n3. Hover over the color chooser area with the mouse, keep the left mouse button\npressed.\n4. While keeping the mouse button pressed, leave the dialog with the cursor and\nmove the cursor around the screen.\n\n-\u003e I get tons of these (various out of bounds indices):\n\n!ENTRY org.eclipse.ui 4 4 Mar 01, 2004 16:01:43.99\n!MESSAGE Unhandled event loop exception\nUnhandled event loop exception\nReason:\n!ENTRY org.eclipse.ui 4 0 Mar 01, 2004 16:01:43.100\n!MESSAGE -1\n!STACK 0\njava.lang.ArrayIndexOutOfBoundsException: -1\n        at org.eclipse.swt.widgets.ColorDialog.mouseMove(ColorDialog.java:333)\n        at org.eclipse.swt.widgets.ColorDialog.handleEvents(ColorDialog.java:217)\n        at org.eclipse.swt.widgets.ColorDialog$1.handleEvent(ColorDialog.java:314)\n        at org.eclipse.swt.widgets.EventTable.sendEvent(EventTable.java:82)\n        at org.eclipse.swt.widgets.Widget.sendEvent(Widget.java:731)\n        at org.eclipse.swt.widgets.Display.runDeferredEvents(Display.java:2400)\n        at org.eclipse.swt.widgets.Display.readAndDispatch(Display.java:2157)\n        at org.eclipse.jface.window.Window.runEventLoop(Window.java:643)\n        at org.eclipse.jface.window.Window.open(Window.java:623)\n        at\norg.eclipse.ui.internal.OpenPreferencesAction.run(OpenPreferencesAction.java:72)\n        at org.eclipse.jface.action.Action.runWithEvent(Action.java:881)\n        at\norg.eclipse.jface.action.ActionContributionItem.handleWidgetSelection(ActionContributionItem.java:550)\n        at\norg.eclipse.jface.action.ActionContributionItem.access$2(ActionContributionItem.java:502)\n        at\norg.eclipse.jface.action.ActionContributionItem$5.handleEvent(ActionContributionItem.java:435)\n        at org.eclipse.swt.widgets.EventTable.sendEvent(EventTable.java:82)\n        at org.eclipse.swt.widgets.Widget.sendEvent(Widget.java:731)\n        at org.eclipse.swt.widgets.Display.runDeferredEvents(Display.java:2400)\n        at org.eclipse.swt.widgets.Display.readAndDispatch(Display.java:2157)\n        at org.eclipse.ui.internal.Workbench.runEventLoop(Workbench.java:1566)\n        at org.eclipse.ui.internal.Workbench.runUI(Workbench.java:1542)\n        at\norg.eclipse.ui.internal.Workbench.createAndRunWorkbench(Workbench.java:263)\n        at org.eclipse.ui.PlatformUI.createAndRunWorkbench(PlatformUI.java:139)\n        at org.eclipse.ui.internal.ide.IDEApplication.run(IDEApplication.java:47)\n        at\norg.eclipse.core.internal.runtime.PlatformActivator$1.run(PlatformActivator.java:256)\n        at\norg.eclipse.core.runtime.adaptor.EclipseStarter.run(EclipseStarter.java:100)\n        at sun.reflect.NativeMethodAccessorImpl.invoke0(Native Method)\n        at\nsun.reflect.NativeMethodAccessorImpl.invoke(NativeMethodAccessorImpl.java:39)\n        at\nsun.reflect.DelegatingMethodAccessorImpl.invoke(DelegatingMethodAccessorImpl.java:25)\n        at java.lang.reflect.Method.invoke(Method.java:324)\n        at org.eclipse.core.launcher.Main.basicRun(Main.java:279)\n        at org.eclipse.core.launcher.Main.run(Main.java:742)\n        at org.eclipse.core.launcher.Main.main(Main.java:581)\n-1",
    "fixed \u003e 0303\n"
  ],
  "commentCreationDates": [
    "2004-03-01T15:03:58+01:00",
    "2004-03-03T23:25:39+01:00"
  ],
  "traces": [
    {
      "exceptionType": "java.lang.ArrayIndexOutOfBoundsException",
      "message": "-1",
      "elements": [
        {
          "method": "org.eclipse.swt.widgets.ColorDialog.mouseMove",
          "source": "ColorDialog.java:333"
        },
        {
          "method": "org.eclipse.swt.widgets.ColorDialog.handleEvents",
          "source": "ColorDialog.java:217"
        },
        {
          "method": "org.eclipse.swt.widgets.ColorDialog$1.handleEvent",
          "source": "ColorDialog.java:314"
        },
        {
          "method": "org.eclipse.swt.widgets.EventTable.sendEvent",
          "source": "EventTable.java:82"
        },
        {
          "method": "org.eclipse.swt.widgets.Widget.sendEvent",
          "source": "Widget.java:731"
        },
        {
          "method": "org.eclipse.swt.widgets.Display.runDeferredEvents",
          "source": "Display.java:2400"
        },
        {
          "method": "org.eclipse.swt.widgets.Display.readAndDispatch",
          "source": "Display.java:2157"
        },
        {
          "method": "org.eclipse.jface.window.Window.runEventLoop",
          "source": "Window.java:643"
        },
        {
          "method": "org.eclipse.jface.window.Window.open",
          "source": "Window.java:623"
        },
        {
          "method": "org.eclipse.ui.internal.OpenPreferencesAction.run",
          "source": "OpenPreferencesAction.java:72"
        },
        {
          "method": "org.eclipse.jface.action.Action.runWithEvent",
          "source": "Action.java:881"
        },
        {
          "method": "org.eclipse.jface.action.ActionContributionItem.handleWidgetSelection",
          "source": "ActionContributionItem.java:550"
        },
        {
          "method": "org.eclipse.jface.action.ActionContributionItem.access$2",
          "source": "ActionContributionItem.java:502"
        },
        {
          "method": "org.eclipse.jface.action.ActionContributionItem$5.handleEvent",
          "source": "ActionContributionItem.java:435"
        },
        {
          "method": "org.eclipse.swt.widgets.EventTable.sendEvent",
          "source": "EventTable.java:82"
        },
        {
          "method": "org.eclipse.swt.widgets.Widget.sendEvent",
          "source": "Widget.java:731"
        },
        {
          "method": "org.eclipse.swt.widgets.Display.runDeferredEvents",
          "source": "Display.java:2400"
        },
        {
          "method": "org.eclipse.swt.widgets.Display.readAndDispatch",
          "source": "Display.java:2157"
        },
        {
          "method": "org.eclipse.ui.internal.Workbench.runEventLoop",
          "source": "Workbench.java:1566"
        },
        {
          "method": "org.eclipse.ui.internal.Workbench.runUI",
          "source": "Workbench.java:1542"
        },
        {
          "method": "org.eclipse.ui.internal.Workbench.createAndRunWorkbench",
          "source": "Workbench.java:263"
        },
        {
          "method": "org.eclipse.ui.PlatformUI.createAndRunWorkbench",
          "source": "PlatformUI.java:139"
        },
        {
          "method": "org.eclipse.ui.internal.ide.IDEApplication.run",
          "source": "IDEApplication.java:47"
        },
        {
          "method": "org.eclipse.core.internal.runtime.PlatformActivator$1.run",
          "source": "PlatformActivator.java:256"
        },
        {
          "method": "org.eclipse.core.runtime.adaptor.EclipseStarter.run",
          "source": "EclipseStarter.java:100"
        },
        {
          "method": "sun.reflect.NativeMethodAccessorImpl.invoke0",
          "source": "Native Method"
        },
        {
          "method": "sun.reflect.NativeMethodAccessorImpl.invoke",
          "source": "NativeMethodAccessorImpl.java:39"
        },
        {
          "method": "sun.reflect.DelegatingMethodAccessorImpl.invoke",
          "source": "DelegatingMethodAccessorImpl.java:25"
        },
        {
          "method": "java.lang.reflect.Method.invoke",
          "source": "Method.java:324"
        },
        {
          "method": "org.eclipse.core.launcher.Main.basicRun",
          "source": "Main.java:279"
        },
        {
          "method": "org.eclipse.core.launcher.Main.run",
          "source": "Main.java:742"
        },
        {
          "method": "org.eclipse.core.launcher.Main.main",
          "source": "Main.java:581"
        }
      ],
      "number": 0,
      "commentIndex": 0,
      "bugId": "53394",
      "date": "2004-03-01T15:03:58+01:00",
      "product": "Platform",
      "component": "SWT",
      "severity": "normal"
    }
  ],
  "groupId": "53394",
  "bugId": "53394",
  "date": "2004-03-01T15:03:58+01:00",
  "product": "Platform",
  "component": "SWT",
  "severity": "normal"
}