{
  "comments": [
    "M7 + new sync view code\nI\u0027ve seen the viewer object contributions in sync view pages not show. If you \nclose/re-open the view they appear again. I\u0027m not sure how this happens, but \nwhat is worse is that often they will appear for a while an then disapear. \n\nThe viewer contributions are being added by sync pages and all we are doing is \nregistering the context menu with a particular id (e.g. the targetID in the \nviewer contribution) with the workbench.\n\nI suspect a workbench problem, but would like to get a reproduceable case.",
    "*** Bug 53545 has been marked as a duplicate of this bug. ***",
    "*** Bug 53588 has been marked as a duplicate of this bug. ***",
    "*** Bug 53593 has been marked as a duplicate of this bug. ***",
    "Increasing priority. The current workaround is to close the sync view and\nre-open. Ensure that the sync view is closed in all perspectives in the same\nwindow. I\u0027m not sure what may of changed in the workbench to cause this, we are\nsimply using viewer contributions, nothing special.",
    "The workaround doesn\u0027t work for me. Closing and reopening the sync view doesn\u0027t \nchange the behavior.",
    "Fix released to HEAD. I\u0027ve will mail a patch to people on the cc\u0027list. I\u0027ve\ntried in vain to attach a patch this this bug, bugzilla is returning a software\nerror.",
    "verified the fix on linux-gtk - everything works as expected.",
    "Reopening. The problem is back on one of my machines again (not the original \none), with I20040303.\nI suspect it has to do with me previewing changes after a sync. Once I did \nthat, and updated my workspace in this way, actions were gone in the sync view.",
    "Unclear whether this is related, but while performing updates through the \npreview dialog, I got the following errors:\n\n!ENTRY org.eclipse.ui 4 4 Mar 04, 2004 12:26:01.906\n!MESSAGE Unhandled event loop exception\nUnhandled event loop exception\nReason:\n!ENTRY org.eclipse.ui 4 0 Mar 04, 2004 12:26:01.921\n!MESSAGE Widget is disposed\n!STACK 0\norg.eclipse.swt.SWTException: Widget is disposed\n        at org.eclipse.swt.SWT.error(SWT.java:2625)\n        at org.eclipse.swt.SWT.error(SWT.java:2555)\n        at org.eclipse.swt.widgets.Widget.error(Widget.java:377)\n        at org.eclipse.swt.widgets.Widget.checkWidget(Widget.java:306)\n        at org.eclipse.swt.widgets.Tree.getItems(Tree.java:488)\n        at org.eclipse.jface.viewers.TreeViewer.getChildren(TreeViewer.java:122)\n        at org.eclipse.jface.viewers.AbstractTreeViewer.doFindItem\n(AbstractTreeViewer.java:430)\n        at org.eclipse.jface.viewers.StructuredViewer.findItem\n(StructuredViewer.java:365)\n        at org.eclipse.jface.viewers.StructuredViewer.update\n(StructuredViewer.java:1235)\n        at org.eclipse.jface.viewers.StructuredViewer.update\n(StructuredViewer.java:1200)\n        at \norg.eclipse.team.ui.synchronize.viewers.SynchronizeModelProvider$LabelUpdateJob.\nrunInUIThread(SynchronizeModelProvider.java:86)\n        at org.eclipse.ui.progress.UIJob$1.run(UIJob.java:90)\n        at org.eclipse.swt.widgets.RunnableLock.run(RunnableLock.java:35)\n        at org.eclipse.swt.widgets.Synchronizer.runAsyncMessages\n(Synchronizer.java:106)\n        at org.eclipse.swt.widgets.Display.runAsyncMessages(Display.java:2329)\n        at org.eclipse.swt.widgets.Display.readAndDispatch(Display.java:2037)\n        at org.eclipse.ui.internal.Workbench.runEventLoop(Workbench.java:1509)\n        at org.eclipse.ui.internal.Workbench.runUI(Workbench.java:1480)\n        at org.eclipse.ui.internal.Workbench.createAndRunWorkbench\n(Workbench.java:257)\n        at org.eclipse.ui.PlatformUI.createAndRunWorkbench(PlatformUI.java:139)\n        at org.eclipse.ui.internal.ide.IDEApplication.run\n(IDEApplication.java:48)\n        at org.eclipse.core.internal.runtime.PlatformActivator$1.run\n(PlatformActivator.java:260)\n        at org.eclipse.core.runtime.adaptor.EclipseStarter.run\n(EclipseStarter.java:173)\n        at org.eclipse.core.runtime.adaptor.EclipseStarter.run\n(EclipseStarter.java:106)\n        at sun.reflect.NativeMethodAccessorImpl.invoke0(Native Method)\n        at sun.reflect.NativeMethodAccessorImpl.invoke\n(NativeMethodAccessorImpl.java:39)\n        at sun.reflect.DelegatingMethodAccessorImpl.invoke\n(DelegatingMethodAccessorImpl.java:25)\n        at java.lang.reflect.Method.invoke(Method.java:324)\n        at org.eclipse.core.launcher.Main.basicRun(Main.java:305)\n        at org.eclipse.core.launcher.Main.run(Main.java:745)\n        at org.eclipse.core.launcher.Main.main(Main.java:713)\nWidget is disposed",
    "Also checked that closing all sync views/perspectives doesn\u0027t help either.\nBTW I am running multiple windows.",
    "Must be related to multiple window scenario. I checked on my other machine, and \nthe problem exists there as well, but only in one of my 2 windows. One sync \nview has all menu entries, one has the minimum.",
    "Created an attachment (id\u003d8326)\nOffending menu without sync actions\n\nOnly one of my windows is lacking these menu actions.",
    "Exiting/restarting doesn\u0027t seem to help either. I will zip my workspace up, and \npost it (URL to be sent to Jean-Michel). It is quite big as it is a self-\nhosting workspace.",
    "Actually, did your fix make it in the build ? I guess no, since the rebuild \nnever occurred. I applied again the patch you gave me, and the problem was \ngone. ",
    "*** Bug 53720 has been marked as a duplicate of this bug. ***",
    "So I guess you can close it definitely now. ",
    "Fix is in todays I build."
  ],
  "commentCreationDates": [
    "2004-03-01T19:25:56+01:00",
    "2004-03-03T02:13:01+01:00",
    "2004-03-03T13:34:27+01:00",
    "2004-03-03T13:36:03+01:00",
    "2004-03-03T13:37:34+01:00",
    "2004-03-03T13:47:53+01:00",
    "2004-03-03T14:30:24+01:00",
    "2004-03-03T14:52:42+01:00",
    "2004-03-04T11:26:37+01:00",
    "2004-03-04T11:29:27+01:00",
    "2004-03-04T11:31:19+01:00",
    "2004-03-04T11:35:20+01:00",
    "2004-03-04T11:39:32+01:00",
    "2004-03-04T11:42:15+01:00",
    "2004-03-04T12:04:48+01:00",
    "2004-03-04T14:14:00+01:00",
    "2004-03-04T14:32:04+01:00",
    "2004-03-04T14:43:49+01:00"
  ],
  "traces": [
    {
      "exceptionType": "org.eclipse.swt.SWTException",
      "message": "Widget is disposed",
      "elements": [
        {
          "method": "org.eclipse.swt.SWT.error",
          "source": "SWT.java:2625"
        },
        {
          "method": "org.eclipse.swt.SWT.error",
          "source": "SWT.java:2555"
        },
        {
          "method": "org.eclipse.swt.widgets.Widget.error",
          "source": "Widget.java:377"
        },
        {
          "method": "org.eclipse.swt.widgets.Widget.checkWidget",
          "source": "Widget.java:306"
        },
        {
          "method": "org.eclipse.swt.widgets.Tree.getItems",
          "source": "Tree.java:488"
        },
        {
          "method": "org.eclipse.jface.viewers.TreeViewer.getChildren",
          "source": "TreeViewer.java:122"
        },
        {
          "method": "org.eclipse.jface.viewers.AbstractTreeViewer.doFindItem",
          "source": "AbstractTreeViewer.java:430"
        },
        {
          "method": "org.eclipse.jface.viewers.StructuredViewer.findItem",
          "source": "StructuredViewer.java:365"
        },
        {
          "method": "org.eclipse.jface.viewers.StructuredViewer.update",
          "source": "StructuredViewer.java:1235"
        },
        {
          "method": "org.eclipse.jface.viewers.StructuredViewer.update",
          "source": "StructuredViewer.java:1200"
        },
        {
          "method": "org.eclipse.team.ui.synchronize.viewers.SynchronizeModelProvider$LabelUpdateJob.runInUIThread",
          "source": "SynchronizeModelProvider.java:86"
        },
        {
          "method": "org.eclipse.ui.progress.UIJob$1.run",
          "source": "UIJob.java:90"
        },
        {
          "method": "org.eclipse.swt.widgets.RunnableLock.run",
          "source": "RunnableLock.java:35"
        },
        {
          "method": "org.eclipse.swt.widgets.Synchronizer.runAsyncMessages",
          "source": "Synchronizer.java:106"
        },
        {
          "method": "org.eclipse.swt.widgets.Display.runAsyncMessages",
          "source": "Display.java:2329"
        },
        {
          "method": "org.eclipse.swt.widgets.Display.readAndDispatch",
          "source": "Display.java:2037"
        },
        {
          "method": "org.eclipse.ui.internal.Workbench.runEventLoop",
          "source": "Workbench.java:1509"
        },
        {
          "method": "org.eclipse.ui.internal.Workbench.runUI",
          "source": "Workbench.java:1480"
        },
        {
          "method": "org.eclipse.ui.internal.Workbench.createAndRunWorkbench",
          "source": "Workbench.java:257"
        },
        {
          "method": "org.eclipse.ui.PlatformUI.createAndRunWorkbench",
          "source": "PlatformUI.java:139"
        },
        {
          "method": "org.eclipse.ui.internal.ide.IDEApplication.run",
          "source": "IDEApplication.java:48"
        },
        {
          "method": "org.eclipse.core.internal.runtime.PlatformActivator$1.run",
          "source": "PlatformActivator.java:260"
        },
        {
          "method": "org.eclipse.core.runtime.adaptor.EclipseStarter.run",
          "source": "EclipseStarter.java:173"
        },
        {
          "method": "org.eclipse.core.runtime.adaptor.EclipseStarter.run",
          "source": "EclipseStarter.java:106"
        },
        {
          "method": "sun.reflect.NativeMethodAccessorImpl.invoke0",
          "source": "Native Method"
        },
        {
          "method": "sun.reflect.NativeMethodAccessorImpl.invoke",
          "source": "NativeMethodAccessorImpl.java:39"
        },
        {
          "method": "sun.reflect.DelegatingMethodAccessorImpl.invoke",
          "source": "DelegatingMethodAccessorImpl.java:25"
        },
        {
          "method": "java.lang.reflect.Method.invoke",
          "source": "Method.java:324"
        },
        {
          "method": "org.eclipse.core.launcher.Main.basicRun",
          "source": "Main.java:305"
        },
        {
          "method": "org.eclipse.core.launcher.Main.run",
          "source": "Main.java:745"
        },
        {
          "method": "org.eclipse.core.launcher.Main.main",
          "source": "Main.java:713"
        }
      ],
      "number": 0,
      "commentIndex": 9,
      "bugId": "53426",
      "date": "2004-03-04T11:29:27+01:00",
      "product": "Platform",
      "component": "Team",
      "severity": "blocker"
    }
  ],
  "groupId": "53426",
  "bugId": "53426",
  "date": "2004-03-01T19:25:56+01:00",
  "product": "Platform",
  "component": "Team",
  "severity": "blocker"
}