{
  "comments": [
    "1. display the content assist pop-up\n2. hit [ctrl+right] ([ctrl+left] works too, maybe others too)\n\nerror in the log:\n\njava.lang.ArithmeticException: / by zero\n        at\norg.eclipse.jface.text.contentassist.CompletionProposalPopup.verifyKey(CompletionProposalPopup.java:603)\n        at\norg.eclipse.jface.text.contentassist.ContentAssistant$InternalListener.verifyKey(ContentAssistant.java:624)\n        at\norg.eclipse.jface.text.TextViewer$VerifyKeyListenersManager.verifyKey(TextViewer.java:378)\n        at\norg.eclipse.swt.custom.StyledTextListener.handleEvent(StyledTextListener.java:55)\n        at org.eclipse.swt.widgets.EventTable.sendEvent(EventTable.java:82)\n        at org.eclipse.swt.widgets.Widget.sendEvent(Widget.java:956)\n        at org.eclipse.swt.widgets.Widget.sendEvent(Widget.java:980)\n        at org.eclipse.swt.widgets.Widget.sendEvent(Widget.java:965)\n        at org.eclipse.swt.widgets.Widget.notifyListeners(Widget.java:835)\n        at org.eclipse.swt.custom.StyledText.handleKeyDown(StyledText.java:5325)\n        at org.eclipse.swt.custom.StyledText$7.handleEvent(StyledText.java:5070)\n        at org.eclipse.swt.widgets.EventTable.sendEvent(EventTable.java:82)\n        at org.eclipse.swt.widgets.Widget.sendEvent(Widget.java:956)\n        at org.eclipse.swt.widgets.Widget.sendEvent(Widget.java:980)\n        at org.eclipse.swt.widgets.Widget.sendEvent(Widget.java:965)\n        at org.eclipse.swt.widgets.Control.sendKeyEvent(Control.java:2239)\n        at org.eclipse.swt.widgets.Control.gtk_key_press_event(Control.java:1751)\n        at org.eclipse.swt.widgets.Composite.gtk_key_press_event(Composite.java:441)\n        at org.eclipse.swt.widgets.Widget.windowProc(Widget.java:1217)\n        at org.eclipse.swt.widgets.Display.windowProc(Display.java:2362)\n        at org.eclipse.swt.internal.gtk.OS.gtk_main_do_event(Native Method)\n        at org.eclipse.swt.widgets.Display.eventProc(Display.java:728)\n        at org.eclipse.swt.internal.gtk.OS.gtk_main_iteration(Native Method)\n        at org.eclipse.swt.widgets.Display.readAndDispatch(Display.java:1650)\n        at org.eclipse.ui.internal.Workbench.runEventLoop(Workbench.java:1509)\n        at org.eclipse.ui.internal.Workbench.runUI(Workbench.java:1480)\n        at\norg.eclipse.ui.internal.Workbench.createAndRunWorkbench(Workbench.java:257)\n        at org.eclipse.ui.PlatformUI.createAndRunWorkbench(PlatformUI.java:139)\n        at org.eclipse.ui.internal.ide.IDEApplication.run(IDEApplication.java:48)\n        at\norg.eclipse.core.internal.runtime.PlatformActivator$1.run(PlatformActivator.java:260)\n        at\norg.eclipse.core.runtime.adaptor.EclipseStarter.run(EclipseStarter.java:173)\n        at\norg.eclipse.core.runtime.adaptor.EclipseStarter.run(EclipseStarter.java:106)\n        at sun.reflect.NativeMethodAccessorImpl.invoke0(Native Method)\n        at\nsun.reflect.NativeMethodAccessorImpl.invoke(NativeMethodAccessorImpl.java:39)\n        at\nsun.reflect.DelegatingMethodAccessorImpl.invoke(DelegatingMethodAccessorImpl.java:25)\n        at java.lang.reflect.Method.invoke(Method.java:324)\n        at org.eclipse.core.launcher.Main.basicRun(Main.java:305)\n        at org.eclipse.core.launcher.Main.run(Main.java:745)\n        at org.eclipse.core.launcher.Main.main(Main.java:713)",
    "\n\n*** This bug has been marked as a duplicate of 53633 ***"
  ],
  "commentCreationDates": [
    "2004-03-03T22:13:39+01:00",
    "2004-03-03T23:48:12+01:00"
  ],
  "traces": [
    {
      "exceptionType": "java.lang.ArithmeticException",
      "message": "/ by zero",
      "elements": [
        {
          "method": "org.eclipse.jface.text.contentassist.CompletionProposalPopup.verifyKey",
          "source": "CompletionProposalPopup.java:603"
        },
        {
          "method": "org.eclipse.jface.text.contentassist.ContentAssistant$InternalListener.verifyKey",
          "source": "ContentAssistant.java:624"
        },
        {
          "method": "org.eclipse.jface.text.TextViewer$VerifyKeyListenersManager.verifyKey",
          "source": "TextViewer.java:378"
        },
        {
          "method": "org.eclipse.swt.custom.StyledTextListener.handleEvent",
          "source": "StyledTextListener.java:55"
        },
        {
          "method": "org.eclipse.swt.widgets.EventTable.sendEvent",
          "source": "EventTable.java:82"
        },
        {
          "method": "org.eclipse.swt.widgets.Widget.sendEvent",
          "source": "Widget.java:956"
        },
        {
          "method": "org.eclipse.swt.widgets.Widget.sendEvent",
          "source": "Widget.java:980"
        },
        {
          "method": "org.eclipse.swt.widgets.Widget.sendEvent",
          "source": "Widget.java:965"
        },
        {
          "method": "org.eclipse.swt.widgets.Widget.notifyListeners",
          "source": "Widget.java:835"
        },
        {
          "method": "org.eclipse.swt.custom.StyledText.handleKeyDown",
          "source": "StyledText.java:5325"
        },
        {
          "method": "org.eclipse.swt.custom.StyledText$7.handleEvent",
          "source": "StyledText.java:5070"
        },
        {
          "method": "org.eclipse.swt.widgets.EventTable.sendEvent",
          "source": "EventTable.java:82"
        },
        {
          "method": "org.eclipse.swt.widgets.Widget.sendEvent",
          "source": "Widget.java:956"
        },
        {
          "method": "org.eclipse.swt.widgets.Widget.sendEvent",
          "source": "Widget.java:980"
        },
        {
          "method": "org.eclipse.swt.widgets.Widget.sendEvent",
          "source": "Widget.java:965"
        },
        {
          "method": "org.eclipse.swt.widgets.Control.sendKeyEvent",
          "source": "Control.java:2239"
        },
        {
          "method": "org.eclipse.swt.widgets.Control.gtk_key_press_event",
          "source": "Control.java:1751"
        },
        {
          "method": "org.eclipse.swt.widgets.Composite.gtk_key_press_event",
          "source": "Composite.java:441"
        },
        {
          "method": "org.eclipse.swt.widgets.Widget.windowProc",
          "source": "Widget.java:1217"
        },
        {
          "method": "org.eclipse.swt.widgets.Display.windowProc",
          "source": "Display.java:2362"
        },
        {
          "method": "org.eclipse.swt.internal.gtk.OS.gtk_main_do_event",
          "source": "Native Method"
        },
        {
          "method": "org.eclipse.swt.widgets.Display.eventProc",
          "source": "Display.java:728"
        },
        {
          "method": "org.eclipse.swt.internal.gtk.OS.gtk_main_iteration",
          "source": "Native Method"
        },
        {
          "method": "org.eclipse.swt.widgets.Display.readAndDispatch",
          "source": "Display.java:1650"
        },
        {
          "method": "org.eclipse.ui.internal.Workbench.runEventLoop",
          "source": "Workbench.java:1509"
        },
        {
          "method": "org.eclipse.ui.internal.Workbench.runUI",
          "source": "Workbench.java:1480"
        },
        {
          "method": "org.eclipse.ui.internal.Workbench.createAndRunWorkbench",
          "source": "Workbench.java:257"
        },
        {
          "method": "org.eclipse.ui.PlatformUI.createAndRunWorkbench",
          "source": "PlatformUI.java:139"
        },
        {
          "method": "org.eclipse.ui.internal.ide.IDEApplication.run",
          "source": "IDEApplication.java:48"
        },
        {
          "method": "org.eclipse.core.internal.runtime.PlatformActivator$1.run",
          "source": "PlatformActivator.java:260"
        },
        {
          "method": "org.eclipse.core.runtime.adaptor.EclipseStarter.run",
          "source": "EclipseStarter.java:173"
        },
        {
          "method": "org.eclipse.core.runtime.adaptor.EclipseStarter.run",
          "source": "EclipseStarter.java:106"
        },
        {
          "method": "sun.reflect.NativeMethodAccessorImpl.invoke0",
          "source": "Native Method"
        },
        {
          "method": "sun.reflect.NativeMethodAccessorImpl.invoke",
          "source": "NativeMethodAccessorImpl.java:39"
        },
        {
          "method": "sun.reflect.DelegatingMethodAccessorImpl.invoke",
          "source": "DelegatingMethodAccessorImpl.java:25"
        },
        {
          "method": "java.lang.reflect.Method.invoke",
          "source": "Method.java:324"
        },
        {
          "method": "org.eclipse.core.launcher.Main.basicRun",
          "source": "Main.java:305"
        },
        {
          "method": "org.eclipse.core.launcher.Main.run",
          "source": "Main.java:745"
        },
        {
          "method": "org.eclipse.core.launcher.Main.main",
          "source": "Main.java:713"
        }
      ],
      "number": 0,
      "commentIndex": 0,
      "bugId": "53682",
      "duplicateId": "53633",
      "date": "2004-03-03T22:13:39+01:00",
      "product": "Platform",
      "component": "UI",
      "severity": "normal"
    }
  ],
  "groupId": "38948",
  "bugId": "53682",
  "duplicateId": "53633",
  "date": "2004-03-03T22:13:39+01:00",
  "product": "Platform",
  "component": "UI",
  "severity": "normal"
}