{
  "comments": [
    "Build id: 200402250800\n\nSometimes I get a message box with an error about the AST not able to create\nanew element (see stacktrace from .log at the end).\nI got it reproducable with the test case below.\njust try to insert a new method manually befor the last existng method\n(   public S\n    ^^^^^^^^^)\nI don\u0027t know if the class SolarSystem matters, but it also produces the error\nwhen commenting out all the members in this class, so an empty class should do it.\n\n\n\npackage model;\n\npublic class Universe {\n\n    SolarSystem[][] fSystems;\n    SolarSystem fEmptySystem \u003d new SolarSystem();\n    \n    public Universe(int height, int width){\n        fSystems \u003d new SolarSystem[height][width];\n        initUnivers();\n    }\n\n        \n    private void initUnivers() {\n        for (int i \u003d 0; i \u003c fSystems.length; i++) {\n            for (int j \u003d 0; j \u003c fSystems[0].length; j++) {\n                fSystems[i][j]\u003dfEmptySystem;\n            }\n        }\n    }\n    \n   /* public SolarSystem getSystem(int index){\n        SolarSystem solarSystem \u003d new SolarSystem();\n        return null;\n    }*/\n\n    public S\n    ^^^^^^^^^\n\n    SolarSystem[][] getSystems(){\n        return fSystems;\n    }\n}\n\nENTRY org.eclipse.core.runtime 4 2 Mrz 08, 2004 18:57:55.514\n!MESSAGE An internal error occurred during: \"Java AST creation\".\n!STACK 0\njava.lang.IllegalArgumentException\n\tat org.eclipse.jdt.core.dom.ASTNode.setSourceRange(ASTNode.java:1796)\n\tat\norg.eclipse.jdt.core.dom.ASTConverter.updateInnerPositions(ASTConverter.java:2807)\n\tat org.eclipse.jdt.core.dom.ASTConverter.setTypeForField(ASTConverter.java:2791)\n\tat\norg.eclipse.jdt.core.dom.ASTConverter.convertToFieldDeclaration(ASTConverter.java:2725)\n\tat\norg.eclipse.jdt.core.dom.ASTConverter.checkAndAddMultipleFieldDeclaration(ASTConverter.java:359)\n\tat\norg.eclipse.jdt.core.dom.ASTConverter.buildBodyDeclarations(ASTConverter.java:319)\n\tat org.eclipse.jdt.core.dom.ASTConverter.convert(ASTConverter.java:263)\n\tat org.eclipse.jdt.core.dom.ASTConverter.convert(ASTConverter.java:142)\n\tat org.eclipse.jdt.core.dom.ASTParser.parseCompilationUnit(ASTParser.java:1091)\n\tat\norg.eclipse.jdt.core.dom.ASTParser.temporaryCreateASTDispatch(ASTParser.java:569)\n\tat org.eclipse.jdt.core.dom.ASTParser.createAST(ASTParser.java:542)\n\tat org.eclipse.jdt.core.dom.AST.parseCompilationUnit(AST.java:900)\n\tat\norg.eclipse.jdt.internal.ui.viewsupport.SelectionListenerWithASTManager$PartListenerGroup.computeAST(SelectionListenerWithASTManager.java:125)\n\tat\norg.eclipse.jdt.internal.ui.viewsupport.SelectionListenerWithASTManager$PartListenerGroup.calculateASTandInform(SelectionListenerWithASTManager.java:144)\n\tat\norg.eclipse.jdt.internal.ui.viewsupport.SelectionListenerWithASTManager$1.run(SelectionListenerWithASTManager.java:99)\n\tat org.eclipse.core.internal.jobs.Worker.run(Worker.java:62)",
    "I cannot reproduce using 0304. Could you please try again with that build and\ntell me if you can get it?\n\nThanks.",
    "Not reproduceable fro me on 0304. Closing. Will reopen if it happens again"
  ],
  "commentCreationDates": [
    "2004-03-08T18:17:30+01:00",
    "2004-03-09T14:29:01+01:00",
    "2004-03-09T20:01:05+01:00"
  ],
  "traces": [
    {
      "exceptionType": "java.lang.IllegalArgumentException",
      "elements": [
        {
          "method": "org.eclipse.jdt.core.dom.ASTNode.setSourceRange",
          "source": "ASTNode.java:1796"
        },
        {
          "method": "org.eclipse.jdt.core.dom.ASTConverter.updateInnerPositions",
          "source": "ASTConverter.java:2807"
        },
        {
          "method": "org.eclipse.jdt.core.dom.ASTConverter.setTypeForField",
          "source": "ASTConverter.java:2791"
        },
        {
          "method": "org.eclipse.jdt.core.dom.ASTConverter.convertToFieldDeclaration",
          "source": "ASTConverter.java:2725"
        },
        {
          "method": "org.eclipse.jdt.core.dom.ASTConverter.checkAndAddMultipleFieldDeclaration",
          "source": "ASTConverter.java:359"
        },
        {
          "method": "org.eclipse.jdt.core.dom.ASTConverter.buildBodyDeclarations",
          "source": "ASTConverter.java:319"
        },
        {
          "method": "org.eclipse.jdt.core.dom.ASTConverter.convert",
          "source": "ASTConverter.java:263"
        },
        {
          "method": "org.eclipse.jdt.core.dom.ASTConverter.convert",
          "source": "ASTConverter.java:142"
        },
        {
          "method": "org.eclipse.jdt.core.dom.ASTParser.parseCompilationUnit",
          "source": "ASTParser.java:1091"
        },
        {
          "method": "org.eclipse.jdt.core.dom.ASTParser.temporaryCreateASTDispatch",
          "source": "ASTParser.java:569"
        },
        {
          "method": "org.eclipse.jdt.core.dom.ASTParser.createAST",
          "source": "ASTParser.java:542"
        },
        {
          "method": "org.eclipse.jdt.core.dom.AST.parseCompilationUnit",
          "source": "AST.java:900"
        },
        {
          "method": "org.eclipse.jdt.internal.ui.viewsupport.SelectionListenerWithASTManager$PartListenerGroup.computeAST",
          "source": "SelectionListenerWithASTManager.java:125"
        },
        {
          "method": "org.eclipse.jdt.internal.ui.viewsupport.SelectionListenerWithASTManager$PartListenerGroup.calculateASTandInform",
          "source": "SelectionListenerWithASTManager.java:144"
        },
        {
          "method": "org.eclipse.jdt.internal.ui.viewsupport.SelectionListenerWithASTManager$1.run",
          "source": "SelectionListenerWithASTManager.java:99"
        },
        {
          "method": "org.eclipse.core.internal.jobs.Worker.run",
          "source": "Worker.java:62"
        }
      ],
      "number": 0,
      "commentIndex": 0,
      "bugId": "54061",
      "date": "2004-03-08T18:17:30+01:00",
      "product": "JDT",
      "component": "Core",
      "severity": "normal"
    }
  ],
  "groupId": "54061",
  "bugId": "54061",
  "date": "2004-03-08T18:17:30+01:00",
  "product": "JDT",
  "component": "Core",
  "severity": "normal"
}