{
  "comments": [
    "I20040309\n\nGot this when closing the workbench. Perhaps related to bug 53291, but not sure.\n\n\njava.lang.IllegalArgumentException: Index out of bounds\n        at java.lang.Throwable.\u003cinit\u003e(Throwable.java)\n        at java.lang.Throwable.\u003cinit\u003e(Throwable.java)\n        at org.eclipse.swt.SWT.error(SWT.java:2611)\n        at org.eclipse.swt.SWT.error(SWT.java:2555)\n        at org.eclipse.swt.widgets.Widget.error(Widget.java:373)\n        at org.eclipse.swt.widgets.Table.getItem(Table.java:899)\n        at\norg.eclipse.ui.dialogs.ResourceListSelectionDialog.updateItem(ResourceListSelectionDialog.java:764)\n        at\norg.eclipse.ui.dialogs.ResourceListSelectionDialog.access$2(ResourceListSelectionDialog.java:760)\n        at\norg.eclipse.ui.dialogs.ResourceListSelectionDialog$6.run(ResourceListSelectionDialog.java:234)\n        at org.eclipse.swt.widgets.RunnableLock.run(RunnableLock.java)\n        at org.eclipse.swt.widgets.Synchronizer.runAsyncMessages(Synchronizer.java)\n        at org.eclipse.swt.widgets.Display.runAsyncMessages(Display.java)\n        at org.eclipse.swt.widgets.Display.readAndDispatch(Display.java)\n        at org.eclipse.jface.window.Window.runEventLoop(Window.java:638)\n        at org.eclipse.jface.window.Window.open(Window.java:618)\n        at\norg.eclipse.ui.internal.ide.actions.OpenWorkspaceFileAction.queryFileResource(OpenWorkspaceFileAction.java:74)\n        at\norg.eclipse.ui.internal.ide.actions.OpenWorkspaceFileAction.run(OpenWorkspaceFileAction.java:89)\n        at org.eclipse.ui.internal.PluginAction.runWithEvent(PluginAction.java:273)\n        at\norg.eclipse.ui.internal.WWinPluginAction.runWithEvent(WWinPluginAction.java:207)\n        at org.eclipse.ui.commands.ActionHandler.execute(ActionHandler.java:68)\n        at org.eclipse.ui.internal.commands.Command.execute(Command.java:160)\n        at\norg.eclipse.ui.internal.keys.WorkbenchKeyboard.executeCommand(WorkbenchKeyboard.java:475)\n        at\norg.eclipse.ui.internal.keys.WorkbenchKeyboard.press(WorkbenchKeyboard.java)\n        at\norg.eclipse.ui.internal.keys.WorkbenchKeyboard.processKeyEvent(WorkbenchKeyboard.java:935)\n        at\norg.eclipse.ui.internal.keys.WorkbenchKeyboard.filterKeySequenceBindings(WorkbenchKeyboard.java)\n        at\norg.eclipse.ui.internal.keys.WorkbenchKeyboard.access$2(WorkbenchKeyboard.java)\n        at\norg.eclipse.ui.internal.keys.WorkbenchKeyboard$1.handleEvent(WorkbenchKeyboard.java)\n        at org.eclipse.swt.widgets.EventTable.sendEvent(EventTable.java)\n        at org.eclipse.swt.widgets.Display.filterEvent(Display.java)\n        at org.eclipse.swt.widgets.Widget.sendEvent(Widget.java)\n        at org.eclipse.swt.widgets.Widget.sendEvent(Widget.java)\n        at org.eclipse.swt.widgets.Widget.sendEvent(Widget.java)\n        at org.eclipse.swt.widgets.Control.sendKeyEvent(Control.java)\n        at org.eclipse.swt.widgets.Control.gtk_key_press_event(Control.java)\n        at org.eclipse.swt.widgets.Composite.gtk_key_press_event(Composite.java)\n        at org.eclipse.swt.widgets.Widget.windowProc(Widget.java)\n        at org.eclipse.swt.widgets.Display.windowProc(Display.java)\n        at org.eclipse.swt.internal.gtk.OS.gtk_main_do_event(Native Method)\n        at org.eclipse.swt.widgets.Display.eventProc(Display.java)\n        at org.eclipse.swt.internal.gtk.OS.gtk_main_iteration(Native Method)\n        at org.eclipse.swt.widgets.Display.readAndDispatch(Display.java)\n        at org.eclipse.ui.internal.Workbench.runEventLoop(Workbench.java:1451)\n        at org.eclipse.ui.internal.Workbench.runUI(Workbench.java:1422)\n        at\norg.eclipse.ui.internal.Workbench.createAndRunWorkbench(Workbench.java:258)\n        at org.eclipse.ui.PlatformUI.createAndRunWorkbench(PlatformUI.java:139)\n        at org.eclipse.ui.internal.ide.IDEApplication.run(IDEApplication.java:48)\n        at\norg.eclipse.core.internal.runtime.PlatformActivator$1.run(PlatformActivator.java:260)\n        at\norg.eclipse.core.runtime.adaptor.EclipseStarter.run(EclipseStarter.java:173)\n        at\norg.eclipse.core.runtime.adaptor.EclipseStarter.run(EclipseStarter.java:106)\n        at sun.reflect.NativeMethodAccessorImpl.invoke0(Native Method)\n        at\nsun.reflect.NativeMethodAccessorImpl.invoke(NativeMethodAccessorImpl.java:79)\n        at\nsun.reflect.DelegatingMethodAccessorImpl.invoke(DelegatingMethodAccessorImpl.java:41)\n        at java.lang.reflect.Method.invoke(Method.java:386)\n        at org.eclipse.core.launcher.Main.basicRun(Main.java:305)\n        at org.eclipse.core.launcher.Main.run(Main.java:745)\n        at org.eclipse.core.launcher.Main.main(Main.java:713)\nIndex out of bounds",
    "Tod, this does look very similar (but not quite the same) as bug 53291.  Can \nyou verify if this is a dup?",
    "\n\n*** This bug has been marked as a duplicate of 53291 ***",
    "This bug was marked as a duplicate of Bug 53291, but I have never seen the \nstack trace for Bug 53921.  I did, however, just see this exact same exception \non shutdown. \n \nI200406180010. \n \nRe-opening the bug.  If you still feel this bug is a duplicate of Bug 53291, \nplease re-open that bug and mark this as a duplicate of Bug 54257 again. ",
    "Created an attachment (id\u003d12501)\nLog File\n",
    "Oh, and GTK+ 2.4.1, KDE 3.2.2, Linux 2.6.4. ",
    "This dialog needs to also be migrated to the jobs mechanism in 3.1.",
    "Is this easily reproducable?",
    "I have not seen this problem since.  I believe that this problem just reflects \na lack of robustness in the code, rather than a real problem.  Fixing it might \nfit in the theme of \"built to last\".  :) ",
    "haven\u0027t seen this for some time",
    "I just saw this problem again.",
    "need a reproducable case here"
  ],
  "commentCreationDates": [
    "2004-03-10T10:05:11+01:00",
    "2004-03-10T16:30:21+01:00",
    "2004-03-10T16:35:57+01:00",
    "2004-06-18T19:44:42+02:00",
    "2004-06-18T19:45:22+02:00",
    "2004-06-18T19:45:52+02:00",
    "2004-06-18T19:52:41+02:00",
    "2004-07-21T21:40:42+02:00",
    "2004-07-22T00:49:22+02:00",
    "2004-07-22T09:52:22+02:00",
    "2005-06-17T20:15:04+02:00",
    "2006-04-21T21:32:33+02:00"
  ],
  "traces": [
    {
      "exceptionType": "java.lang.IllegalArgumentException",
      "message": "Index out of bounds",
      "elements": [
        {
          "method": "java.lang.Throwable.\u003cinit\u003e",
          "source": "Throwable.java"
        },
        {
          "method": "java.lang.Throwable.\u003cinit\u003e",
          "source": "Throwable.java"
        },
        {
          "method": "org.eclipse.swt.SWT.error",
          "source": "SWT.java:2611"
        },
        {
          "method": "org.eclipse.swt.SWT.error",
          "source": "SWT.java:2555"
        },
        {
          "method": "org.eclipse.swt.widgets.Widget.error",
          "source": "Widget.java:373"
        },
        {
          "method": "org.eclipse.swt.widgets.Table.getItem",
          "source": "Table.java:899"
        },
        {
          "method": "org.eclipse.ui.dialogs.ResourceListSelectionDialog.updateItem",
          "source": "ResourceListSelectionDialog.java:764"
        },
        {
          "method": "org.eclipse.ui.dialogs.ResourceListSelectionDialog.access$2",
          "source": "ResourceListSelectionDialog.java:760"
        },
        {
          "method": "org.eclipse.ui.dialogs.ResourceListSelectionDialog$6.run",
          "source": "ResourceListSelectionDialog.java:234"
        },
        {
          "method": "org.eclipse.swt.widgets.RunnableLock.run",
          "source": "RunnableLock.java"
        },
        {
          "method": "org.eclipse.swt.widgets.Synchronizer.runAsyncMessages",
          "source": "Synchronizer.java"
        },
        {
          "method": "org.eclipse.swt.widgets.Display.runAsyncMessages",
          "source": "Display.java"
        },
        {
          "method": "org.eclipse.swt.widgets.Display.readAndDispatch",
          "source": "Display.java"
        },
        {
          "method": "org.eclipse.jface.window.Window.runEventLoop",
          "source": "Window.java:638"
        },
        {
          "method": "org.eclipse.jface.window.Window.open",
          "source": "Window.java:618"
        },
        {
          "method": "org.eclipse.ui.internal.ide.actions.OpenWorkspaceFileAction.queryFileResource",
          "source": "OpenWorkspaceFileAction.java:74"
        },
        {
          "method": "org.eclipse.ui.internal.ide.actions.OpenWorkspaceFileAction.run",
          "source": "OpenWorkspaceFileAction.java:89"
        },
        {
          "method": "org.eclipse.ui.internal.PluginAction.runWithEvent",
          "source": "PluginAction.java:273"
        },
        {
          "method": "org.eclipse.ui.internal.WWinPluginAction.runWithEvent",
          "source": "WWinPluginAction.java:207"
        },
        {
          "method": "org.eclipse.ui.commands.ActionHandler.execute",
          "source": "ActionHandler.java:68"
        },
        {
          "method": "org.eclipse.ui.internal.commands.Command.execute",
          "source": "Command.java:160"
        },
        {
          "method": "org.eclipse.ui.internal.keys.WorkbenchKeyboard.executeCommand",
          "source": "WorkbenchKeyboard.java:475"
        },
        {
          "method": "org.eclipse.ui.internal.keys.WorkbenchKeyboard.press",
          "source": "WorkbenchKeyboard.java"
        },
        {
          "method": "org.eclipse.ui.internal.keys.WorkbenchKeyboard.processKeyEvent",
          "source": "WorkbenchKeyboard.java:935"
        },
        {
          "method": "org.eclipse.ui.internal.keys.WorkbenchKeyboard.filterKeySequenceBindings",
          "source": "WorkbenchKeyboard.java"
        },
        {
          "method": "org.eclipse.ui.internal.keys.WorkbenchKeyboard.access$2",
          "source": "WorkbenchKeyboard.java"
        },
        {
          "method": "org.eclipse.ui.internal.keys.WorkbenchKeyboard$1.handleEvent",
          "source": "WorkbenchKeyboard.java"
        },
        {
          "method": "org.eclipse.swt.widgets.EventTable.sendEvent",
          "source": "EventTable.java"
        },
        {
          "method": "org.eclipse.swt.widgets.Display.filterEvent",
          "source": "Display.java"
        },
        {
          "method": "org.eclipse.swt.widgets.Widget.sendEvent",
          "source": "Widget.java"
        },
        {
          "method": "org.eclipse.swt.widgets.Widget.sendEvent",
          "source": "Widget.java"
        },
        {
          "method": "org.eclipse.swt.widgets.Widget.sendEvent",
          "source": "Widget.java"
        },
        {
          "method": "org.eclipse.swt.widgets.Control.sendKeyEvent",
          "source": "Control.java"
        },
        {
          "method": "org.eclipse.swt.widgets.Control.gtk_key_press_event",
          "source": "Control.java"
        },
        {
          "method": "org.eclipse.swt.widgets.Composite.gtk_key_press_event",
          "source": "Composite.java"
        },
        {
          "method": "org.eclipse.swt.widgets.Widget.windowProc",
          "source": "Widget.java"
        },
        {
          "method": "org.eclipse.swt.widgets.Display.windowProc",
          "source": "Display.java"
        },
        {
          "method": "org.eclipse.swt.internal.gtk.OS.gtk_main_do_event",
          "source": "Native Method"
        },
        {
          "method": "org.eclipse.swt.widgets.Display.eventProc",
          "source": "Display.java"
        },
        {
          "method": "org.eclipse.swt.internal.gtk.OS.gtk_main_iteration",
          "source": "Native Method"
        },
        {
          "method": "org.eclipse.swt.widgets.Display.readAndDispatch",
          "source": "Display.java"
        },
        {
          "method": "org.eclipse.ui.internal.Workbench.runEventLoop",
          "source": "Workbench.java:1451"
        },
        {
          "method": "org.eclipse.ui.internal.Workbench.runUI",
          "source": "Workbench.java:1422"
        },
        {
          "method": "org.eclipse.ui.internal.Workbench.createAndRunWorkbench",
          "source": "Workbench.java:258"
        },
        {
          "method": "org.eclipse.ui.PlatformUI.createAndRunWorkbench",
          "source": "PlatformUI.java:139"
        },
        {
          "method": "org.eclipse.ui.internal.ide.IDEApplication.run",
          "source": "IDEApplication.java:48"
        },
        {
          "method": "org.eclipse.core.internal.runtime.PlatformActivator$1.run",
          "source": "PlatformActivator.java:260"
        },
        {
          "method": "org.eclipse.core.runtime.adaptor.EclipseStarter.run",
          "source": "EclipseStarter.java:173"
        },
        {
          "method": "org.eclipse.core.runtime.adaptor.EclipseStarter.run",
          "source": "EclipseStarter.java:106"
        },
        {
          "method": "sun.reflect.NativeMethodAccessorImpl.invoke0",
          "source": "Native Method"
        },
        {
          "method": "sun.reflect.NativeMethodAccessorImpl.invoke",
          "source": "NativeMethodAccessorImpl.java:79"
        },
        {
          "method": "sun.reflect.DelegatingMethodAccessorImpl.invoke",
          "source": "DelegatingMethodAccessorImpl.java:41"
        },
        {
          "method": "java.lang.reflect.Method.invoke",
          "source": "Method.java:386"
        },
        {
          "method": "org.eclipse.core.launcher.Main.basicRun",
          "source": "Main.java:305"
        },
        {
          "method": "org.eclipse.core.launcher.Main.run",
          "source": "Main.java:745"
        },
        {
          "method": "org.eclipse.core.launcher.Main.main",
          "source": "Main.java:713"
        }
      ],
      "number": 0,
      "commentIndex": 0,
      "bugId": "54257",
      "date": "2004-03-10T10:05:11+01:00",
      "product": "Platform",
      "component": "UI",
      "severity": "major"
    }
  ],
  "groupId": "54257",
  "bugId": "54257",
  "date": "2004-03-10T10:05:11+01:00",
  "product": "Platform",
  "component": "UI",
  "severity": "major"
}