{
  "comments": [
    "Pardon me as I try to muddle through the circumstances of this bug:\n\n1. I had a WSWB 3.0 build (I20040304) which worked fine on Linux\non a networked drive.\n2. Owing to some other network trouble, our NIS primary server\nwas taken off-line to be rebuilt.  This shouldn\u0027t be a show-stopper;\nother clients such as Emacs or mozilla manage to start and run fine\nin this environment.\n3. When I restart,  I get a dialog:\n\n\"Problems during startup.  Check the .log file in\nthe .metadata directory of your workspace\"\n\nThe stack trace in .metadata/.log file is at the bottom of this message.\n\nI tried cleaning my workspace and my .configuration without success.\nI asked another user to try my install and they got the same thing;\nthen they tried one of their own old installs (I20040216)\nand got the same thing.  I tried running with a workspace on a local\ndrive (\"-data /tmp/brent\"), and then I could get past this.\n\nI just tried on the latest (non-WSWB) Eclipse build (I20040310)\nand get a near-identical stack-trace although now I get a \"JVM\nterminated\" dialog.\n\nI do not know what Eclipse is attempting to do, but\nit is causing me trouble.  (Trouble which\nEmacs and VI don\u0027t have, when reading/writing networked files.)\n\n- Brent\n\n\n\n!SESSION Mar 11, 2004 14:24:39.333 ---------------------------------------------\njava.fullversion\u003dJ2RE 1.4.2 IBM build cxia32dev-20040128 (JIT enabled: jitc)\nBootLoader constants: OS\u003dlinux, ARCH\u003dx86, WS\u003dgtk, NL\u003den_US\nCommand-line arguments: -data work8\n!ENTRY reference:file:/home/bnicolle/cdt/linux_gtk/wswb-SDK-\nI20040304/eclipse/plugins/org.eclipse.core.runtime_3.0.0/ 0 0 Mar 11, 2004 \n14:24:39.334\n!MESSAGE FrameworkEvent.ERROR\n!STACK 0\norg.osgi.framework.BundleException: Exception in \norg.eclipse.core.internal.runtime.PlatformActivator.start()\n        at org.eclipse.osgi.framework.internal.core.BundleContext.startActivator\n(BundleContext.java:1010)\n        at org.eclipse.osgi.framework.internal.core.BundleContext.start\n(BundleContext.java:972)\n        at org.eclipse.osgi.framework.internal.core.BundleHost.startWorker\n(BundleHost.java:403)\n        at org.eclipse.osgi.framework.internal.core.Bundle.resume\n(Bundle.java:407)\n        at org.eclipse.osgi.framework.internal.core.Framework.resumeBundle\n(Framework.java:1018)\n        at org.eclipse.osgi.framework.internal.core.StartLevelImpl.resumeBundles\n(StartLevelImpl.java:565)\n        at org.eclipse.osgi.framework.internal.core.StartLevelImpl.incFWSL\n(StartLevelImpl.java:479)\n        at \norg.eclipse.osgi.framework.internal.core.StartLevelImpl.doSetStartLevel\n(StartLevelImpl.java:269)\n        at org.eclipse.osgi.framework.internal.core.StartLevelImpl.dispatchEvent\n(StartLevelImpl.java:439)\n        at org.eclipse.osgi.framework.eventmgr.ListenerList.dispatchEvent\n(ListenerList.java:135)\n        at \norg.eclipse.osgi.framework.eventmgr.EventThread$EventThreadItem.dispatchEvent\n(EventThread.java:59)\n        at org.eclipse.osgi.framework.eventmgr.EventThread.run\n(EventThread.java:118)\nNested exception:\njava.lang.IllegalStateException: Unable to create platform lock \nfile: /home/bnicolle/cdt/linux_gtk/wswb-SDK-\nI20040304/eclipse/work8/.metadata/.lock.\n        at org.eclipse.core.internal.runtime.InternalPlatform.getMetaArea\n(InternalPlatform.java:346)\n        at org.eclipse.core.internal.runtime.InternalPlatform.start\n(InternalPlatform.java:412)\n        at \norg.eclipse.core.internal.runtime.PlatformActivator.startInternalPlatform\n(PlatformActivator.java:171)\n        at org.eclipse.core.internal.runtime.PlatformActivator.start\n(PlatformActivator.java:53)\n        at org.eclipse.osgi.framework.internal.core.BundleContext$1.run\n(BundleContext.java:993)\n        at java.security.AccessController.doPrivileged1(Native Method)\n        at java.security.AccessController.doPrivileged\n(AccessController.java:350)\n        at org.eclipse.osgi.framework.internal.core.BundleContext.startActivator\n(BundleContext.java:989)\n        at org.eclipse.osgi.framework.internal.core.BundleContext.start\n(BundleContext.java:972)\n        at org.eclipse.osgi.framework.internal.core.BundleHost.startWorker\n(BundleHost.java:403)\n        at org.eclipse.osgi.framework.internal.core.Bundle.resume\n(Bundle.java:407)\n        at org.eclipse.osgi.framework.internal.core.Framework.resumeBundle\n(Framework.java:1018)\n        at org.eclipse.osgi.framework.internal.core.StartLevelImpl.resumeBundles\n(StartLevelImpl.java:565)\n        at org.eclipse.osgi.framework.internal.core.StartLevelImpl.incFWSL\n(StartLevelImpl.java:479)\n        at \norg.eclipse.osgi.framework.internal.core.StartLevelImpl.doSetStartLevel\n(StartLevelImpl.java:269)\n        at org.eclipse.osgi.framework.internal.core.StartLevelImpl.dispatchEvent\n(StartLevelImpl.java:439)\n        at org.eclipse.osgi.framework.eventmgr.ListenerList.dispatchEvent\n(ListenerList.java:135)\n        at \norg.eclipse.osgi.framework.eventmgr.EventThread$EventThreadItem.dispatchEvent\n(EventThread.java:59)\n        at org.eclipse.osgi.framework.eventmgr.EventThread.run\n(EventThread.java:118)\n!ENTRY reference:file:/home/bnicolle/cdt/linux_gtk/wswb-SDK-\nI20040304/eclipse/plugins/org.eclipse.update.configurator_3.0.0/ 0 0 Mar 11, \n2004 14:24:39.360\n!MESSAGE FrameworkEvent.ERROR\n!STACK 0\norg.osgi.framework.BundleException: Exception in \norg.eclipse.update.internal.configurator.ConfigurationActivator.start()\n        at org.eclipse.osgi.framework.internal.core.BundleContext.startActivator\n(BundleContext.java:1010)\n        at org.eclipse.osgi.framework.internal.core.BundleContext.start\n(BundleContext.java:972)\n        at org.eclipse.osgi.framework.internal.core.BundleHost.startWorker\n(BundleHost.java:403)\n        at org.eclipse.osgi.framework.internal.core.Bundle.resume\n(Bundle.java:407)\n        at org.eclipse.osgi.framework.internal.core.Framework.resumeBundle\n(Framework.java:1018)\n        at org.eclipse.osgi.framework.internal.core.StartLevelImpl.resumeBundles\n(StartLevelImpl.java:565)\n        at org.eclipse.osgi.framework.internal.core.StartLevelImpl.incFWSL\n(StartLevelImpl.java:479)\n        at \norg.eclipse.osgi.framework.internal.core.StartLevelImpl.doSetStartLevel\n(StartLevelImpl.java:269)\n        at org.eclipse.osgi.framework.internal.core.StartLevelImpl.dispatchEvent\n(StartLevelImpl.java:439)\n        at org.eclipse.osgi.framework.eventmgr.ListenerList.dispatchEvent\n(ListenerList.java:135)\n        at \norg.eclipse.osgi.framework.eventmgr.EventThread$EventThreadItem.dispatchEvent\n(EventThread.java:59)\n        at org.eclipse.osgi.framework.eventmgr.EventThread.run\n(EventThread.java:118)\nNested exception:\njava.lang.Exception: Can not start\n        at \norg.eclipse.update.internal.configurator.ConfigurationActivator.initialize\n(ConfigurationActivator.java:90)\n        at org.eclipse.update.internal.configurator.ConfigurationActivator.start\n(ConfigurationActivator.java:66)\n        at org.eclipse.osgi.framework.internal.core.BundleContext$1.run\n(BundleContext.java:993)\n        at java.security.AccessController.doPrivileged1(Native Method)\n        at java.security.AccessController.doPrivileged\n(AccessController.java:350)\n        at org.eclipse.osgi.framework.internal.core.BundleContext.startActivator\n(BundleContext.java:989)\n        at org.eclipse.osgi.framework.internal.core.BundleContext.start\n(BundleContext.java:972)\n        at org.eclipse.osgi.framework.internal.core.BundleHost.startWorker\n(BundleHost.java:403)\n        at org.eclipse.osgi.framework.internal.core.Bundle.resume\n(Bundle.java:407)\n        at org.eclipse.osgi.framework.internal.core.Framework.resumeBundle\n(Framework.java:1018)\n        at org.eclipse.osgi.framework.internal.core.StartLevelImpl.resumeBundles\n(StartLevelImpl.java:565)\n        at org.eclipse.osgi.framework.internal.core.StartLevelImpl.incFWSL\n(StartLevelImpl.java:479)\n        at \norg.eclipse.osgi.framework.internal.core.StartLevelImpl.doSetStartLevel\n(StartLevelImpl.java:269)\n        at org.eclipse.osgi.framework.internal.core.StartLevelImpl.dispatchEvent\n(StartLevelImpl.java:439)\n        at org.eclipse.osgi.framework.eventmgr.ListenerList.dispatchEvent\n(ListenerList.java:135)\n        at \norg.eclipse.osgi.framework.eventmgr.EventThread$EventThreadItem.dispatchEvent\n(EventThread.java:59)\n        at org.eclipse.osgi.framework.eventmgr.EventThread.run\n(EventThread.java:118)",
    "Eclipse acquires a lock in a special file in the workspace metadata during\nstartup. This lock is acquired to avoid two instances of Eclipse running against\nthe same workspace location simultaneously (what would cause data corruption). \n\nThe failure you got happened probably due to some interaction between your\nremote file system system (NFS?) locking mechanism and NIS.\n\nThe workaround when locking does not work in your setup is to disable it. You\nwill be able to start, but you will have protection from Eclipse for preventing\ntwo instances of Eclipse on the same workspace. For more info on how to disable\nthe metadata lock, please see bug 44735 comment 3.\n\nThe reason why you got the general \"JVM terminated\" error dialog is covered in\nbug 51537.\n\n*** This bug has been marked as a duplicate of 44735 ***",
    "I actually meant \"You will be able to start, but you will have *NO* protection\nfrom Eclipse for preventing two instances of Eclipse on the same workspace.\"",
    "The workaround provided gets me going again.\n\nIndeed my local lockd process looks suspicious:\n\n[158]~/cdt: ps -aux | grep lockd\nroot      4827  0.0  0.0     0    0 ?        SW   Feb13   0:00 [lockd]\nbnicolle 26848  0.0  0.0  3680  656 pts/1    S    18:09   0:00 grep lockd\n\nI would like to see a resolution which tells me more specifically\nwhy it can\u0027t start, or perhaps warns me that it is bypassing the lock daemon\nand continues in some kind of fall-back mode.\n"
  ],
  "commentCreationDates": [
    "2004-03-11T20:09:28+01:00",
    "2004-03-11T22:30:40+01:00",
    "2004-03-11T22:32:08+01:00",
    "2004-03-11T23:33:24+01:00"
  ],
  "traces": [
    {
      "exceptionType": "org.osgi.framework.BundleException",
      "message": "Exception in  org.eclipse.core.internal.runtime.PlatformActivator.start()",
      "elements": [
        {
          "method": "org.eclipse.osgi.framework.internal.core.BundleContext.startActivator",
          "source": "BundleContext.java:1010"
        },
        {
          "method": "org.eclipse.osgi.framework.internal.core.BundleContext.start",
          "source": "BundleContext.java:972"
        },
        {
          "method": "org.eclipse.osgi.framework.internal.core.BundleHost.startWorker",
          "source": "BundleHost.java:403"
        },
        {
          "method": "org.eclipse.osgi.framework.internal.core.Bundle.resume",
          "source": "Bundle.java:407"
        },
        {
          "method": "org.eclipse.osgi.framework.internal.core.Framework.resumeBundle",
          "source": "Framework.java:1018"
        },
        {
          "method": "org.eclipse.osgi.framework.internal.core.StartLevelImpl.resumeBundles",
          "source": "StartLevelImpl.java:565"
        },
        {
          "method": "org.eclipse.osgi.framework.internal.core.StartLevelImpl.incFWSL",
          "source": "StartLevelImpl.java:479"
        },
        {
          "method": "org.eclipse.osgi.framework.internal.core.StartLevelImpl.doSetStartLevel",
          "source": "StartLevelImpl.java:269"
        },
        {
          "method": "org.eclipse.osgi.framework.internal.core.StartLevelImpl.dispatchEvent",
          "source": "StartLevelImpl.java:439"
        },
        {
          "method": "org.eclipse.osgi.framework.eventmgr.ListenerList.dispatchEvent",
          "source": "ListenerList.java:135"
        },
        {
          "method": "org.eclipse.osgi.framework.eventmgr.EventThread$EventThreadItem.dispatchEvent",
          "source": "EventThread.java:59"
        },
        {
          "method": "org.eclipse.osgi.framework.eventmgr.EventThread.run",
          "source": "EventThread.java:118"
        }
      ],
      "number": 0,
      "commentIndex": 0,
      "bugId": "54526",
      "duplicateId": "44735",
      "date": "2004-03-11T20:09:28+01:00",
      "product": "Platform",
      "component": "Resources",
      "severity": "major"
    },
    {
      "exceptionType": "java.lang.IllegalStateException",
      "message": "Unable to create platform lock  file: /home/bnicolle/cdt/linux_gtk/wswb-SDK- I20040304/eclipse/work8/.metadata/.lock.",
      "elements": [
        {
          "method": "org.eclipse.core.internal.runtime.InternalPlatform.getMetaArea",
          "source": "InternalPlatform.java:346"
        },
        {
          "method": "org.eclipse.core.internal.runtime.InternalPlatform.start",
          "source": "InternalPlatform.java:412"
        },
        {
          "method": "org.eclipse.core.internal.runtime.PlatformActivator.startInternalPlatform",
          "source": "PlatformActivator.java:171"
        },
        {
          "method": "org.eclipse.core.internal.runtime.PlatformActivator.start",
          "source": "PlatformActivator.java:53"
        },
        {
          "method": "org.eclipse.osgi.framework.internal.core.BundleContext$1.run",
          "source": "BundleContext.java:993"
        },
        {
          "method": "java.security.AccessController.doPrivileged1",
          "source": "Native Method"
        },
        {
          "method": "java.security.AccessController.doPrivileged",
          "source": "AccessController.java:350"
        },
        {
          "method": "org.eclipse.osgi.framework.internal.core.BundleContext.startActivator",
          "source": "BundleContext.java:989"
        },
        {
          "method": "org.eclipse.osgi.framework.internal.core.BundleContext.start",
          "source": "BundleContext.java:972"
        },
        {
          "method": "org.eclipse.osgi.framework.internal.core.BundleHost.startWorker",
          "source": "BundleHost.java:403"
        },
        {
          "method": "org.eclipse.osgi.framework.internal.core.Bundle.resume",
          "source": "Bundle.java:407"
        },
        {
          "method": "org.eclipse.osgi.framework.internal.core.Framework.resumeBundle",
          "source": "Framework.java:1018"
        },
        {
          "method": "org.eclipse.osgi.framework.internal.core.StartLevelImpl.resumeBundles",
          "source": "StartLevelImpl.java:565"
        },
        {
          "method": "org.eclipse.osgi.framework.internal.core.StartLevelImpl.incFWSL",
          "source": "StartLevelImpl.java:479"
        },
        {
          "method": "org.eclipse.osgi.framework.internal.core.StartLevelImpl.doSetStartLevel",
          "source": "StartLevelImpl.java:269"
        },
        {
          "method": "org.eclipse.osgi.framework.internal.core.StartLevelImpl.dispatchEvent",
          "source": "StartLevelImpl.java:439"
        },
        {
          "method": "org.eclipse.osgi.framework.eventmgr.ListenerList.dispatchEvent",
          "source": "ListenerList.java:135"
        },
        {
          "method": "org.eclipse.osgi.framework.eventmgr.EventThread$EventThreadItem.dispatchEvent",
          "source": "EventThread.java:59"
        },
        {
          "method": "org.eclipse.osgi.framework.eventmgr.EventThread.run",
          "source": "EventThread.java:118"
        }
      ],
      "number": 1,
      "commentIndex": 0,
      "bugId": "54526",
      "duplicateId": "44735",
      "date": "2004-03-11T20:09:28+01:00",
      "product": "Platform",
      "component": "Resources",
      "severity": "major"
    },
    {
      "exceptionType": "org.osgi.framework.BundleException",
      "message": "Exception in  org.eclipse.update.internal.configurator.ConfigurationActivator.start()",
      "elements": [
        {
          "method": "org.eclipse.osgi.framework.internal.core.BundleContext.startActivator",
          "source": "BundleContext.java:1010"
        },
        {
          "method": "org.eclipse.osgi.framework.internal.core.BundleContext.start",
          "source": "BundleContext.java:972"
        },
        {
          "method": "org.eclipse.osgi.framework.internal.core.BundleHost.startWorker",
          "source": "BundleHost.java:403"
        },
        {
          "method": "org.eclipse.osgi.framework.internal.core.Bundle.resume",
          "source": "Bundle.java:407"
        },
        {
          "method": "org.eclipse.osgi.framework.internal.core.Framework.resumeBundle",
          "source": "Framework.java:1018"
        },
        {
          "method": "org.eclipse.osgi.framework.internal.core.StartLevelImpl.resumeBundles",
          "source": "StartLevelImpl.java:565"
        },
        {
          "method": "org.eclipse.osgi.framework.internal.core.StartLevelImpl.incFWSL",
          "source": "StartLevelImpl.java:479"
        },
        {
          "method": "org.eclipse.osgi.framework.internal.core.StartLevelImpl.doSetStartLevel",
          "source": "StartLevelImpl.java:269"
        },
        {
          "method": "org.eclipse.osgi.framework.internal.core.StartLevelImpl.dispatchEvent",
          "source": "StartLevelImpl.java:439"
        },
        {
          "method": "org.eclipse.osgi.framework.eventmgr.ListenerList.dispatchEvent",
          "source": "ListenerList.java:135"
        },
        {
          "method": "org.eclipse.osgi.framework.eventmgr.EventThread$EventThreadItem.dispatchEvent",
          "source": "EventThread.java:59"
        },
        {
          "method": "org.eclipse.osgi.framework.eventmgr.EventThread.run",
          "source": "EventThread.java:118"
        }
      ],
      "number": 2,
      "commentIndex": 0,
      "bugId": "54526",
      "duplicateId": "44735",
      "date": "2004-03-11T20:09:28+01:00",
      "product": "Platform",
      "component": "Resources",
      "severity": "major"
    },
    {
      "exceptionType": "java.lang.Exception",
      "message": "Can not start",
      "elements": [
        {
          "method": "org.eclipse.update.internal.configurator.ConfigurationActivator.initialize",
          "source": "ConfigurationActivator.java:90"
        },
        {
          "method": "org.eclipse.update.internal.configurator.ConfigurationActivator.start",
          "source": "ConfigurationActivator.java:66"
        },
        {
          "method": "org.eclipse.osgi.framework.internal.core.BundleContext$1.run",
          "source": "BundleContext.java:993"
        },
        {
          "method": "java.security.AccessController.doPrivileged1",
          "source": "Native Method"
        },
        {
          "method": "java.security.AccessController.doPrivileged",
          "source": "AccessController.java:350"
        },
        {
          "method": "org.eclipse.osgi.framework.internal.core.BundleContext.startActivator",
          "source": "BundleContext.java:989"
        },
        {
          "method": "org.eclipse.osgi.framework.internal.core.BundleContext.start",
          "source": "BundleContext.java:972"
        },
        {
          "method": "org.eclipse.osgi.framework.internal.core.BundleHost.startWorker",
          "source": "BundleHost.java:403"
        },
        {
          "method": "org.eclipse.osgi.framework.internal.core.Bundle.resume",
          "source": "Bundle.java:407"
        },
        {
          "method": "org.eclipse.osgi.framework.internal.core.Framework.resumeBundle",
          "source": "Framework.java:1018"
        },
        {
          "method": "org.eclipse.osgi.framework.internal.core.StartLevelImpl.resumeBundles",
          "source": "StartLevelImpl.java:565"
        },
        {
          "method": "org.eclipse.osgi.framework.internal.core.StartLevelImpl.incFWSL",
          "source": "StartLevelImpl.java:479"
        },
        {
          "method": "org.eclipse.osgi.framework.internal.core.StartLevelImpl.doSetStartLevel",
          "source": "StartLevelImpl.java:269"
        },
        {
          "method": "org.eclipse.osgi.framework.internal.core.StartLevelImpl.dispatchEvent",
          "source": "StartLevelImpl.java:439"
        },
        {
          "method": "org.eclipse.osgi.framework.eventmgr.ListenerList.dispatchEvent",
          "source": "ListenerList.java:135"
        },
        {
          "method": "org.eclipse.osgi.framework.eventmgr.EventThread$EventThreadItem.dispatchEvent",
          "source": "EventThread.java:59"
        },
        {
          "method": "org.eclipse.osgi.framework.eventmgr.EventThread.run",
          "source": "EventThread.java:118"
        }
      ],
      "number": 3,
      "commentIndex": 0,
      "bugId": "54526",
      "duplicateId": "44735",
      "date": "2004-03-11T20:09:28+01:00",
      "product": "Platform",
      "component": "Resources",
      "severity": "major"
    }
  ],
  "groupId": "44735",
  "bugId": "54526",
  "duplicateId": "44735",
  "date": "2004-03-11T20:09:28+01:00",
  "product": "Platform",
  "component": "Resources",
  "severity": "major"
}