{
  "comments": [
    "Build 207 \n\nSearching (from Java search page) declarations of method named \u0027close\u0027,\nraised a NullPointerException in match locator.\n\nLog: Mon Nov 05 12:57:24 CET 2001\n4 org.eclipse.jdt.ui 1 Internal Error\njava.lang.reflect.InvocationTargetException: java.lang.NullPointerException\n        at org.eclipse.jdt.internal.core.search.matching.PotentialMatch.locateMa\ntchesInClassFile(PotentialMatch.java:292)\n        at org.eclipse.jdt.internal.core.search.matching.PotentialMatch.locateMa\ntches(PotentialMatch.java:156)\n        at org.eclipse.jdt.internal.core.search.matching.MatchLocator.locateMatc\nhes(MatchLocator.java:899)\n        at org.eclipse.jdt.internal.core.search.matching.MatchLocator.locateMatc\nhes(MatchLocator.java:389)\n        at org.eclipse.jdt.core.search.SearchEngine.search(SearchEngine.java:339\n)\n        at org.eclipse.jdt.core.search.SearchEngine.search(SearchEngine.java:256\n)\n        at org.eclipse.jdt.internal.ui.search.JavaSearchOperation.execute(JavaSe\narchOperation.java:78)\n        at org.eclipse.ui.actions.WorkspaceModifyOperation$1.run(WorkspaceModify\nOperation.java:64)\n        at org.eclipse.core.internal.resources.Workspace.run(Workspace.java:1188\n)\n        at org.eclipse.ui.actions.WorkspaceModifyOperation.run(WorkspaceModifyOp\neration.java:78)\n        at org.eclipse.jface.operation.ModalContext$ModalContextThread.run(Modal\nContext.java:98)",
    "Posting workspace on n:/archive/workspaces/5526.zip",
    "Added a null check on the info, but still needs to understand why it didn\u0027t get \nproperly initialized (from classfile reader).",
    "Could not get the NullPointerException with workspace in \nn:/archive/workspaces/5526.zip, even with a plain 207 build."
  ],
  "commentCreationDates": [
    "2001-11-05T12:37:54+01:00",
    "2001-11-05T12:38:46+01:00",
    "2001-11-05T13:54:50+01:00",
    "2001-11-06T15:22:26+01:00"
  ],
  "traces": [
    {
      "exceptionType": "java.lang.NullPointerException",
      "elements": [
        {
          "method": "org.eclipse.jdt.internal.core.search.matching.PotentialMatch.locateMatchesInClassFile",
          "source": "PotentialMatch.java:292"
        },
        {
          "method": "org.eclipse.jdt.internal.core.search.matching.PotentialMatch.locateMatches",
          "source": "PotentialMatch.java:156"
        },
        {
          "method": "org.eclipse.jdt.internal.core.search.matching.MatchLocator.locateMatches",
          "source": "MatchLocator.java:899"
        },
        {
          "method": "org.eclipse.jdt.internal.core.search.matching.MatchLocator.locateMatches",
          "source": "MatchLocator.java:389"
        },
        {
          "method": "org.eclipse.jdt.core.search.SearchEngine.search",
          "source": "SearchEngine.java:339 "
        },
        {
          "method": "org.eclipse.jdt.core.search.SearchEngine.search",
          "source": "SearchEngine.java:256 "
        },
        {
          "method": "org.eclipse.jdt.internal.ui.search.JavaSearchOperation.execute",
          "source": "JavaSe archOperation.java:78"
        },
        {
          "method": "org.eclipse.ui.actions.WorkspaceModifyOperation$1.run",
          "source": "WorkspaceModify Operation.java:64"
        },
        {
          "method": "org.eclipse.core.internal.resources.Workspace.run",
          "source": "Workspace.java:1188 "
        },
        {
          "method": "org.eclipse.ui.actions.WorkspaceModifyOperation.run",
          "source": "WorkspaceModifyOp eration.java:78"
        },
        {
          "method": "org.eclipse.jface.operation.ModalContext$ModalContextThread.run",
          "source": "Modal Context.java:98"
        }
      ],
      "number": 0,
      "commentIndex": 0,
      "bugId": "5526",
      "date": "2001-11-05T12:37:54+01:00",
      "product": "JDT",
      "component": "Core",
      "severity": "normal"
    }
  ],
  "groupId": "5526",
  "bugId": "5526",
  "date": "2001-11-05T12:37:54+01:00",
  "product": "JDT",
  "component": "Core",
  "severity": "normal"
}