{
  "comments": [
    "build I20040318\n\nGot an unrelated error on startup (Sync view problems), which caused the\nWorkbench to shut down (another problem).  Noticed the following in the console.\nNo corresponding entry in the log.\n\njava.lang.NullPointerException\n        at\norg.eclipse.jdt.internal.core.search.indexing.IndexManager.rebuildIndex(IndexManager.java:325)\n        at\norg.eclipse.jdt.internal.core.search.indexing.IndexManager.getIndex(IndexManager.java:125)\n        at\norg.eclipse.jdt.internal.core.search.PatternSearchJob.getIndexes(PatternSearchJob.java:103)\n        at\norg.eclipse.jdt.internal.core.search.PatternSearchJob.execute(PatternSearchJob.java:65)\n        at\norg.eclipse.jdt.internal.core.search.processing.JobManager.performConcurrentJob(JobManager.java:261)\n        at\norg.eclipse.jdt.core.search.SearchEngine.searchAllTypeNames(SearchEngine.java:825)\n        at\norg.eclipse.jdt.internal.corext.util.AllTypesCache.search(AllTypesCache.java:440)\n        at\norg.eclipse.jdt.internal.corext.util.AllTypesCache$TypeCacher.doSearchTypes(AllTypesCache.java:129)\n        at\norg.eclipse.jdt.internal.corext.util.AllTypesCache$TypeCacher.run(AllTypesCache.java:98)",
    "Line 325 is:\n\t\trequest \u003d new AddJarFileToIndex((IFile) target, this);\n\nI don\u0027t see how you can get a NPE on that line. What VM are you using?",
    "You can probably ignore this.  I just realized I was accidentally running\nI20040219.  When I switched back to I20040318, I didn\u0027t see any problems.\nBut if you wanted to, you could see what line 325 was in I20040219.\n\n",
    "To clarify, I was running I20040219 on a workspace most recently saved with\nI20040318, so the index structure may have changed.\n",
    "We had thread issues with shutdown.\n\n*** This bug has been marked as a duplicate of 52619 ***"
  ],
  "commentCreationDates": [
    "2004-03-18T20:40:25+01:00",
    "2004-03-18T21:05:12+01:00",
    "2004-03-18T21:38:11+01:00",
    "2004-03-18T21:39:14+01:00",
    "2004-03-19T18:11:22+01:00"
  ],
  "traces": [
    {
      "exceptionType": "java.lang.NullPointerException",
      "elements": [
        {
          "method": "org.eclipse.jdt.internal.core.search.indexing.IndexManager.rebuildIndex",
          "source": "IndexManager.java:325"
        },
        {
          "method": "org.eclipse.jdt.internal.core.search.indexing.IndexManager.getIndex",
          "source": "IndexManager.java:125"
        },
        {
          "method": "org.eclipse.jdt.internal.core.search.PatternSearchJob.getIndexes",
          "source": "PatternSearchJob.java:103"
        },
        {
          "method": "org.eclipse.jdt.internal.core.search.PatternSearchJob.execute",
          "source": "PatternSearchJob.java:65"
        },
        {
          "method": "org.eclipse.jdt.internal.core.search.processing.JobManager.performConcurrentJob",
          "source": "JobManager.java:261"
        },
        {
          "method": "org.eclipse.jdt.core.search.SearchEngine.searchAllTypeNames",
          "source": "SearchEngine.java:825"
        },
        {
          "method": "org.eclipse.jdt.internal.corext.util.AllTypesCache.search",
          "source": "AllTypesCache.java:440"
        },
        {
          "method": "org.eclipse.jdt.internal.corext.util.AllTypesCache$TypeCacher.doSearchTypes",
          "source": "AllTypesCache.java:129"
        },
        {
          "method": "org.eclipse.jdt.internal.corext.util.AllTypesCache$TypeCacher.run",
          "source": "AllTypesCache.java:98"
        }
      ],
      "number": 0,
      "commentIndex": 0,
      "bugId": "55279",
      "duplicateId": "52619",
      "date": "2004-03-18T20:40:25+01:00",
      "product": "JDT",
      "component": "Core",
      "severity": "normal"
    }
  ],
  "groupId": "52619",
  "bugId": "55279",
  "duplicateId": "52619",
  "date": "2004-03-18T20:40:25+01:00",
  "product": "JDT",
  "component": "Core",
  "severity": "normal"
}