{
  "comments": [
    "Linux - GTK\nHyades 3.0\nNOTE: Only occurs on GTK, not in Motif.\n\nWhen I try to attach to a local agent for the first time, and hit OK on the \nLCD. The Profiling Monitor view does not get updated, and the following error \nappears:\n\norg.eclipse.swt.SWTException: Invalid thread access\n        at org.eclipse.swt.SWT.error(SWT.java:2625)\n        at org.eclipse.swt.SWT.error(SWT.java(Inlined Compiled Code))\n        at org.eclipse.swt.widgets.Widget.error(Widget.java(Inlined Compiled \nCode))\n        at org.eclipse.swt.widgets.Widget.checkWidget(Widget.java(Compiled \nCode))\n        at org.eclipse.swt.widgets.Tree.getSelection(Tree.java:553)\n        at org.eclipse.jface.viewers.TreeViewer.getSelection\n(TreeViewer.java:179)\n        at org.eclipse.jface.viewers.TreeViewer.setSelection\n(TreeViewer.java:233)\n        at org.eclipse.jface.viewers.AbstractTreeViewer.setSelectionToWidget\n(AbstractTreeViewer.java:1362)\n        at org.eclipse.jface.viewers.StructuredViewer.setSelectionToWidget\n(StructuredViewer.java:1068)\n        at org.eclipse.jface.viewers.StructuredViewer.preservingSelection\n(StructuredViewer.java:817)\n        at org.eclipse.jface.viewers.StructuredViewer.refresh\n(StructuredViewer.java:868)\n        at org.eclipse.jface.viewers.StructuredViewer.refresh\n(StructuredViewer.java:830)\n        at org.eclipse.hyades.trace.internal.ui.PDProjectViewer.selectObject\n(PDProjectViewer.java:180)\n        at \norg.eclipse.hyades.trace.internal.ui.PDProjectExplorer.handleProfileEvent\n(PDProjectExplorer.java:420)\n        at \norg.eclipse.hyades.trace.internal.ui.TraceUIManager.notifyProfileEventListener\n(TraceUIManager.java:465)\n        at org.eclipse.hyades.trace.ui.UIPlugin.notifyProfileEventListener\n(UIPlugin.java:433)\n        at org.eclipse.hyades.trace.ui.internal.util.PDCoreUtil.attach\n(PDCoreUtil.java:154)\n        at \norg.eclipse.hyades.trace.ui.internal.launcher.ProfileAttachDelegate.launch\n(ProfileAttachDelegate.java:47)\n        at org.eclipse.debug.internal.core.LaunchConfiguration.launch\n(LaunchConfiguration.java:171)\n        at org.eclipse.debug.internal.ui.DebugUIPlugin.buildAndLaunch\n(DebugUIPlugin.java:796)\n        at org.eclipse.debug.ui.DebugUITools.buildAndLaunch\n(DebugUITools.java:629)\n        at org.eclipse.debug.ui.DebugUITools$3.run(DebugUITools.java:585)\n        at org.eclipse.core.internal.jobs.Worker.run(Worker.java:62)\n\nNote: When I attach to another agent, then both of the agents appear in the \nProfling Montior. Seems this only happens the first time I try to attach.",
    "Take a look please",
    "Which Hyades build are you using?",
    "Does not occur in latest build 3.0_20040319_0934.",
    "Closing bug.",
    "house keeping"
  ],
  "commentCreationDates": [
    "2004-03-18T22:21:24+01:00",
    "2004-03-19T14:23:29+01:00",
    "2004-03-19T15:26:52+01:00",
    "2004-03-19T16:32:49+01:00",
    "2004-04-01T19:28:05+02:00",
    "2004-11-03T16:24:42+01:00"
  ],
  "traces": [
    {
      "exceptionType": "org.eclipse.swt.SWTException",
      "message": "Invalid thread access",
      "elements": [
        {
          "method": "org.eclipse.swt.SWT.error",
          "source": "SWT.java:2625"
        },
        {
          "method": "org.eclipse.swt.SWT.error",
          "source": "SWT.java(Inlined Compiled Code)"
        },
        {
          "method": "org.eclipse.swt.widgets.Widget.error",
          "source": "Widget.java(Inlined Compiled  Code)"
        },
        {
          "method": "org.eclipse.swt.widgets.Widget.checkWidget",
          "source": "Widget.java(Compiled  Code)"
        },
        {
          "method": "org.eclipse.swt.widgets.Tree.getSelection",
          "source": "Tree.java:553"
        },
        {
          "method": "org.eclipse.jface.viewers.TreeViewer.getSelection",
          "source": "TreeViewer.java:179"
        },
        {
          "method": "org.eclipse.jface.viewers.TreeViewer.setSelection",
          "source": "TreeViewer.java:233"
        },
        {
          "method": "org.eclipse.jface.viewers.AbstractTreeViewer.setSelectionToWidget",
          "source": "AbstractTreeViewer.java:1362"
        },
        {
          "method": "org.eclipse.jface.viewers.StructuredViewer.setSelectionToWidget",
          "source": "StructuredViewer.java:1068"
        },
        {
          "method": "org.eclipse.jface.viewers.StructuredViewer.preservingSelection",
          "source": "StructuredViewer.java:817"
        },
        {
          "method": "org.eclipse.jface.viewers.StructuredViewer.refresh",
          "source": "StructuredViewer.java:868"
        },
        {
          "method": "org.eclipse.jface.viewers.StructuredViewer.refresh",
          "source": "StructuredViewer.java:830"
        },
        {
          "method": "org.eclipse.hyades.trace.internal.ui.PDProjectViewer.selectObject",
          "source": "PDProjectViewer.java:180"
        },
        {
          "method": "org.eclipse.hyades.trace.internal.ui.PDProjectExplorer.handleProfileEvent",
          "source": "PDProjectExplorer.java:420"
        },
        {
          "method": "org.eclipse.hyades.trace.internal.ui.TraceUIManager.notifyProfileEventListener",
          "source": "TraceUIManager.java:465"
        },
        {
          "method": "org.eclipse.hyades.trace.ui.UIPlugin.notifyProfileEventListener",
          "source": "UIPlugin.java:433"
        },
        {
          "method": "org.eclipse.hyades.trace.ui.internal.util.PDCoreUtil.attach",
          "source": "PDCoreUtil.java:154"
        },
        {
          "method": "org.eclipse.hyades.trace.ui.internal.launcher.ProfileAttachDelegate.launch",
          "source": "ProfileAttachDelegate.java:47"
        },
        {
          "method": "org.eclipse.debug.internal.core.LaunchConfiguration.launch",
          "source": "LaunchConfiguration.java:171"
        },
        {
          "method": "org.eclipse.debug.internal.ui.DebugUIPlugin.buildAndLaunch",
          "source": "DebugUIPlugin.java:796"
        },
        {
          "method": "org.eclipse.debug.ui.DebugUITools.buildAndLaunch",
          "source": "DebugUITools.java:629"
        },
        {
          "method": "org.eclipse.debug.ui.DebugUITools$3.run",
          "source": "DebugUITools.java:585"
        },
        {
          "method": "org.eclipse.core.internal.jobs.Worker.run",
          "source": "Worker.java:62"
        }
      ],
      "number": 0,
      "commentIndex": 0,
      "bugId": "55304",
      "date": "2004-03-18T22:21:24+01:00",
      "product": "Hyades",
      "component": "UI",
      "severity": "normal"
    }
  ],
  "groupId": "55304",
  "bugId": "55304",
  "date": "2004-03-18T22:21:24+01:00",
  "product": "Hyades",
  "component": "UI",
  "severity": "normal"
}