{
  "comments": [
    "I20040318 + HEAD + JCore preview v413b\n\nI now crashes when the reconcile(true, ..., pm) is cancelled using\npm.setCancelled(true);\n\nTest Case: edit a large file, type a character (-\u003e start reconciling), type\nanother character shortly after (-\u003e stops previous reconcile and starts a new one).\n\n\norg.eclipse.core.runtime.OperationCanceledException\n        at\norg.eclipse.jdt.core.dom.ASTConverter.checkCanceled(ASTConverter.java:390)\n        at org.eclipse.jdt.core.dom.ASTConverter.convert(ASTConverter.java:243)\n        at org.eclipse.jdt.core.dom.ASTConverter.convert(ASTConverter.java:146)\n        at org.eclipse.jdt.core.dom.AST.convertCompilationUnit(AST.java:233)\n        at\norg.eclipse.jdt.internal.core.CompilationUnit.buildStructure(CompilationUnit.java:149)\n        at org.eclipse.jdt.internal.core.Openable.generateInfos(Openable.java:169)\n        at\norg.eclipse.jdt.internal.core.JavaElement.openWhenClosed(JavaElement.java:543)\n        at\norg.eclipse.jdt.internal.core.CompilationUnit.makeConsistent(CompilationUnit.java:938)\n        at\norg.eclipse.jdt.internal.core.ReconcileWorkingCopyOperation.executeOperation(ReconcileWorkingCopyOperation.java:56)\n        at\norg.eclipse.jdt.internal.core.JavaModelOperation.run(JavaModelOperation.java:700)\n        at\norg.eclipse.jdt.internal.core.JavaModelOperation.runOperation(JavaModelOperation.java:739)\n        at\norg.eclipse.jdt.internal.core.CompilationUnit.reconcile(CompilationUnit.java:1050)\n        at\norg.eclipse.jdt.internal.ui.text.java.JavaReconcilingStrategy.reconcile(JavaReconcilingStrategy.java:85)\n        at\norg.eclipse.jdt.internal.ui.text.java.JavaReconcilingStrategy.reconcile(JavaReconcilingStrategy.java:112)\n        at\norg.eclipse.jface.text.reconciler.CompositeReconcilingStrategy.reconcile(CompositeReconcilingStrategy.java:83)\n        at\norg.eclipse.jdt.internal.ui.text.JavaCompositeReconcilingStrategy.reconcile(JavaCompositeReconcilingStrategy.java:97)\n        at\norg.eclipse.jface.text.reconciler.MonoReconciler.process(MonoReconciler.java:76)\n        at\norg.eclipse.jface.text.reconciler.AbstractReconciler$BackgroundThread.run(AbstractReconciler.java:189)",
    "*** Bug 55339 has been marked as a duplicate of this bug. ***",
    "fixed."
  ],
  "commentCreationDates": [
    "2004-03-19T13:46:08+01:00",
    "2004-03-19T14:17:19+01:00",
    "2004-03-19T14:18:30+01:00"
  ],
  "traces": [
    {
      "exceptionType": "org.eclipse.core.runtime.OperationCanceledException",
      "elements": [
        {
          "method": "org.eclipse.jdt.core.dom.ASTConverter.checkCanceled",
          "source": "ASTConverter.java:390"
        },
        {
          "method": "org.eclipse.jdt.core.dom.ASTConverter.convert",
          "source": "ASTConverter.java:243"
        },
        {
          "method": "org.eclipse.jdt.core.dom.ASTConverter.convert",
          "source": "ASTConverter.java:146"
        },
        {
          "method": "org.eclipse.jdt.core.dom.AST.convertCompilationUnit",
          "source": "AST.java:233"
        },
        {
          "method": "org.eclipse.jdt.internal.core.CompilationUnit.buildStructure",
          "source": "CompilationUnit.java:149"
        },
        {
          "method": "org.eclipse.jdt.internal.core.Openable.generateInfos",
          "source": "Openable.java:169"
        },
        {
          "method": "org.eclipse.jdt.internal.core.JavaElement.openWhenClosed",
          "source": "JavaElement.java:543"
        },
        {
          "method": "org.eclipse.jdt.internal.core.CompilationUnit.makeConsistent",
          "source": "CompilationUnit.java:938"
        },
        {
          "method": "org.eclipse.jdt.internal.core.ReconcileWorkingCopyOperation.executeOperation",
          "source": "ReconcileWorkingCopyOperation.java:56"
        },
        {
          "method": "org.eclipse.jdt.internal.core.JavaModelOperation.run",
          "source": "JavaModelOperation.java:700"
        },
        {
          "method": "org.eclipse.jdt.internal.core.JavaModelOperation.runOperation",
          "source": "JavaModelOperation.java:739"
        },
        {
          "method": "org.eclipse.jdt.internal.core.CompilationUnit.reconcile",
          "source": "CompilationUnit.java:1050"
        },
        {
          "method": "org.eclipse.jdt.internal.ui.text.java.JavaReconcilingStrategy.reconcile",
          "source": "JavaReconcilingStrategy.java:85"
        },
        {
          "method": "org.eclipse.jdt.internal.ui.text.java.JavaReconcilingStrategy.reconcile",
          "source": "JavaReconcilingStrategy.java:112"
        },
        {
          "method": "org.eclipse.jface.text.reconciler.CompositeReconcilingStrategy.reconcile",
          "source": "CompositeReconcilingStrategy.java:83"
        },
        {
          "method": "org.eclipse.jdt.internal.ui.text.JavaCompositeReconcilingStrategy.reconcile",
          "source": "JavaCompositeReconcilingStrategy.java:97"
        },
        {
          "method": "org.eclipse.jface.text.reconciler.MonoReconciler.process",
          "source": "MonoReconciler.java:76"
        },
        {
          "method": "org.eclipse.jface.text.reconciler.AbstractReconciler$BackgroundThread.run",
          "source": "AbstractReconciler.java:189"
        }
      ],
      "number": 0,
      "commentIndex": 0,
      "bugId": "55362",
      "date": "2004-03-19T13:46:08+01:00",
      "product": "JDT",
      "component": "Text",
      "severity": "major"
    }
  ],
  "groupId": "55362",
  "bugId": "55362",
  "date": "2004-03-19T13:46:08+01:00",
  "product": "JDT",
  "component": "Text",
  "severity": "major"
}