{
  "comments": [
    "i20040318 + Rel.Eng release plug-in 3.0.3\n\nComparing with released causes the following error:\n\n!ENTRY org.eclipse.ui 4 0 Mar 21, 2004 23:17:23.179\n!MESSAGE org.eclipse.team.internal.ccvs.ui.subscriber.CompareParticipant.refresh\nWithRemote([Lorg/eclipse/core/resources/IResource;Z)V\n!STACK 0\njava.lang.NoSuchMethodError: org.eclipse.team.internal.ccvs.ui.subscriber.Compar\neParticipant.refreshWithRemote([Lorg/eclipse/core/resources/IResource;Z)V\n        at org.eclipse.releng.tools.CompareLocalToMap.execute(CompareLocalToMap.\njava:98)\n        at org.eclipse.team.internal.ccvs.ui.actions.CVSAction.run(CVSAction.jav\na:52)\n        at org.eclipse.ui.actions.ActionDelegate.runWithEvent(ActionDelegate.jav\na:71)\n        at org.eclipse.ui.internal.PluginAction.runWithEvent(PluginAction.java:2\n63)\n        at org.eclipse.jface.action.ActionContributionItem.handleWidgetSelection\n(ActionContributionItem.java:550)\n        at org.eclipse.jface.action.ActionContributionItem.access$2(ActionContri\nbutionItem.java:502)\n        at org.eclipse.jface.action.ActionContributionItem$5.handleEvent(ActionC\nontributionItem.java:435)\n        at org.eclipse.swt.widgets.EventTable.sendEvent(EventTable.java:82)\n        at org.eclipse.swt.widgets.Widget.sendEvent(Widget.java:810)\n        at org.eclipse.swt.widgets.Display.runDeferredEvents(Display.java:2424)\n        at org.eclipse.swt.widgets.Display.readAndDispatch(Display.java:2102)\n        at org.eclipse.ui.internal.Workbench.runEventLoop(Workbench.java:1448)\n        at org.eclipse.ui.internal.Workbench.runUI(Workbench.java:1419)\n        at org.eclipse.ui.internal.Workbench.createAndRunWorkbench(Workbench.jav\na:257)\n        at org.eclipse.ui.PlatformUI.createAndRunWorkbench(PlatformUI.java:139)\n        at org.eclipse.ui.internal.ide.IDEApplication.run(IDEApplication.java:90\n)\n        at org.eclipse.core.internal.runtime.PlatformActivator$1.run(PlatformAct\nivator.java:262)\n        at org.eclipse.core.runtime.adaptor.EclipseStarter.run(EclipseStarter.ja\nva:181)\n        at org.eclipse.core.runtime.adaptor.EclipseStarter.run(EclipseStarter.ja\nva:111)\n        at sun.reflect.NativeMethodAccessorImpl.invoke0(Native Method)\n        at sun.reflect.NativeMethodAccessorImpl.invoke(NativeMethodAccessorImpl.\njava:39)\n        at sun.reflect.DelegatingMethodAccessorImpl.invoke(DelegatingMethodAcces\nsorImpl.java:25)\n        at java.lang.reflect.Method.invoke(Method.java:324)\n        at org.eclipse.core.launcher.Main.basicRun(Main.java:305)\n        at org.eclipse.core.launcher.Main.run(Main.java:729)\n        at org.eclipse.core.launcher.Main.main(Main.java:713)\norg.eclipse.team.internal.ccvs.ui.subscriber.CompareParticipant.refreshWithRemot\ne([Lorg/eclipse/core/resources/IResource;Z)V",
    "Rafael, can you still reproduce the bug now? If so, could you please log the \nsteps you have taken? ",
    "With 3.0 M8 and the RelEng plug-in version 3.0.4, I could not reproduce the problem.\n\n(As a side note, when I tried executing the \"Compare with released\" action\nwithout having the map files loaded - no org.eclipse.releng project - it failed\nwith a NPE. I would expect it to show an error dialog telling me the reason it\nfailed, since is something you can easily ensure before trying the operation).",
    "This hasn\u0027t happened for me for ages. I believe it has been fixed a while ago.",
    "Yes, it was fixed a while ago"
  ],
  "commentCreationDates": [
    "2004-03-22T04:27:58+01:00",
    "2004-03-29T17:35:26+02:00",
    "2004-03-29T17:51:12+02:00",
    "2005-02-02T21:44:34+01:00",
    "2005-02-02T21:51:50+01:00"
  ],
  "traces": [
    {
      "exceptionType": "java.lang.NoSuchMethodError",
      "message": "org.eclipse.team.internal.ccvs.ui.subscriber.Compar eParticipant.refreshWithRemote([Lorg/eclipse/core/resources/IResource;Z)V",
      "elements": [
        {
          "method": "org.eclipse.releng.tools.CompareLocalToMap.execute",
          "source": "CompareLocalToMap. java:98"
        },
        {
          "method": "org.eclipse.team.internal.ccvs.ui.actions.CVSAction.run",
          "source": "CVSAction.jav a:52"
        },
        {
          "method": "org.eclipse.ui.actions.ActionDelegate.runWithEvent",
          "source": "ActionDelegate.jav a:71"
        },
        {
          "method": "org.eclipse.ui.internal.PluginAction.runWithEvent",
          "source": "PluginAction.java:2 63"
        },
        {
          "method": "org.eclipse.jface.action.ActionContributionItem.handleWidgetSelection",
          "source": "ActionContributionItem.java:550"
        },
        {
          "method": "org.eclipse.jface.action.ActionContributionItem.access$2",
          "source": "ActionContri butionItem.java:502"
        },
        {
          "method": "org.eclipse.jface.action.ActionContributionItem$5.handleEvent",
          "source": "ActionC ontributionItem.java:435"
        },
        {
          "method": "org.eclipse.swt.widgets.EventTable.sendEvent",
          "source": "EventTable.java:82"
        },
        {
          "method": "org.eclipse.swt.widgets.Widget.sendEvent",
          "source": "Widget.java:810"
        },
        {
          "method": "org.eclipse.swt.widgets.Display.runDeferredEvents",
          "source": "Display.java:2424"
        },
        {
          "method": "org.eclipse.swt.widgets.Display.readAndDispatch",
          "source": "Display.java:2102"
        },
        {
          "method": "org.eclipse.ui.internal.Workbench.runEventLoop",
          "source": "Workbench.java:1448"
        },
        {
          "method": "org.eclipse.ui.internal.Workbench.runUI",
          "source": "Workbench.java:1419"
        },
        {
          "method": "org.eclipse.ui.internal.Workbench.createAndRunWorkbench",
          "source": "Workbench.jav a:257"
        },
        {
          "method": "org.eclipse.ui.PlatformUI.createAndRunWorkbench",
          "source": "PlatformUI.java:139"
        },
        {
          "method": "org.eclipse.ui.internal.ide.IDEApplication.run",
          "source": "IDEApplication.java:90 "
        },
        {
          "method": "org.eclipse.core.internal.runtime.PlatformActivator$1.run",
          "source": "PlatformAct ivator.java:262"
        },
        {
          "method": "org.eclipse.core.runtime.adaptor.EclipseStarter.run",
          "source": "EclipseStarter.ja va:181"
        },
        {
          "method": "org.eclipse.core.runtime.adaptor.EclipseStarter.run",
          "source": "EclipseStarter.ja va:111"
        },
        {
          "method": "sun.reflect.NativeMethodAccessorImpl.invoke0",
          "source": "Native Method"
        },
        {
          "method": "sun.reflect.NativeMethodAccessorImpl.invoke",
          "source": "NativeMethodAccessorImpl. java:39"
        },
        {
          "method": "sun.reflect.DelegatingMethodAccessorImpl.invoke",
          "source": "DelegatingMethodAcces sorImpl.java:25"
        },
        {
          "method": "java.lang.reflect.Method.invoke",
          "source": "Method.java:324"
        },
        {
          "method": "org.eclipse.core.launcher.Main.basicRun",
          "source": "Main.java:305"
        },
        {
          "method": "org.eclipse.core.launcher.Main.run",
          "source": "Main.java:729"
        },
        {
          "method": "org.eclipse.core.launcher.Main.main",
          "source": "Main.java:713"
        }
      ],
      "number": 0,
      "commentIndex": 0,
      "bugId": "55490",
      "date": "2004-03-22T04:27:58+01:00",
      "product": "Platform",
      "component": "Releng",
      "severity": "normal"
    }
  ],
  "groupId": "55490",
  "bugId": "55490",
  "date": "2004-03-22T04:27:58+01:00",
  "product": "Platform",
  "component": "Releng",
  "severity": "normal"
}