{
  "comments": [
    "noticed this in my .log this afternoon. no other relevant entries in the .log.\nsorry, don\u0027t know what i was doing when it happened. using this morning\u0027s\nI-build. on GTK..\n\n!SESSION Mar 22, 2004 15:12:45.349 ---------------------------------------------\njava.version\u003d1.4.2_03\njava.vendor\u003dSun Microsystems Inc.\nBootLoader constants: OS\u003dlinux, ARCH\u003dx86, WS\u003dgtk, NL\u003den_US\nCommand-line arguments: -vmargs -cp /home/cmclaren/eclipse/./startup.jar org.ecl\nipse.core.launcher.Main\n!ENTRY org.eclipse.core.runtime 4 2 Mar 22, 2004 15:12:45.350\n!MESSAGE Problems occurred when invoking code from plug-in: \"org.eclipse.core.ru\nntime\".\n!STACK 0\njava.lang.NullPointerException\n        at org.eclipse.ui.texteditor.AbstractTextEditor.selectAndReveal(Abstract\nTextEditor.java:4134)\n        at org.eclipse.debug.internal.ui.views.launch.LaunchView.selectAndReveal\n(LaunchView.java:908)\n        at org.eclipse.debug.internal.ui.views.launch.LaunchView.openEditorForSt\nackFrame(LaunchView.java:830)\n        at org.eclipse.debug.internal.ui.views.launch.LaunchView.showEditorForCu\nrrentSelection(LaunchView.java:710)\n        at org.eclipse.debug.internal.ui.views.launch.LaunchView.selectionChange\nd(LaunchView.java:506)\n        at org.eclipse.jface.viewers.Viewer$2.run(Viewer.java:159)\n        at org.eclipse.core.internal.runtime.InternalPlatform.run(InternalPlatfo\nrm.java:610)\n        at org.eclipse.core.runtime.Platform.run(Platform.java:521)\n        at org.eclipse.jface.viewers.Viewer.fireSelectionChanged(Viewer.java:157\n)\n        at org.eclipse.jface.viewers.StructuredViewer.updateSelection(Structured\nViewer.java:1310)\n        at org.eclipse.jface.viewers.StructuredViewer.handleSelect(StructuredVie\nwer.java:666)\n        at org.eclipse.jface.viewers.StructuredViewer$4.widgetSelected(Structure\ndViewer.java:690)\n        at org.eclipse.jface.util.OpenStrategy.fireSelectionEvent(OpenStrategy.j\nava:178)\n        at org.eclipse.jface.util.OpenStrategy.access$3(OpenStrategy.java:173)\n        at org.eclipse.jface.util.OpenStrategy$1.handleEvent(OpenStrategy.java:3\n09)\n        at org.eclipse.swt.widgets.EventTable.sendEvent(EventTable.java:82)\n        at org.eclipse.swt.widgets.Widget.sendEvent(Widget.java:956)\n        at org.eclipse.swt.widgets.Display.runDeferredEvents(Display.java:1892)\n        at org.eclipse.swt.widgets.Display.readAndDispatch(Display.java:1667)\n        at org.eclipse.ui.internal.Workbench.runEventLoop(Workbench.java:1488)\n        at org.eclipse.ui.internal.Workbench.runUI(Workbench.java:1462)\n        at org.eclipse.ui.internal.Workbench.createAndRunWorkbench(Workbench.jav\na:259)\n        at org.eclipse.ui.PlatformUI.createAndRunWorkbench(PlatformUI.java:139)\n        at org.eclipse.ui.internal.ide.IDEApplication.run(IDEApplication.java:90\n)\n        at org.eclipse.core.internal.runtime.PlatformActivator$1.run(PlatformAct\nivator.java:262)\n        at org.eclipse.core.runtime.adaptor.EclipseStarter.run(EclipseStarter.ja\nva:213)\n        at org.eclipse.core.runtime.adaptor.EclipseStarter.run(EclipseStarter.ja\nva:115)\n        at sun.reflect.NativeMethodAccessorImpl.invoke0(Native Method)\n        at sun.reflect.NativeMethodAccessorImpl.invoke(NativeMethodAccessorImpl.\njava:39)\n        at sun.reflect.DelegatingMethodAccessorImpl.invoke(DelegatingMethodAcces\nsorImpl.java:25)\n        at java.lang.reflect.Method.invoke(Method.java:324)\n        at org.eclipse.core.launcher.Main.basicRun(Main.java:315)\n        at org.eclipse.core.launcher.Main.run(Main.java:740)\n        at org.eclipse.core.launcher.Main.main(Main.java:724)",
    "Looks like some other thread tears down the editor during selectAndReveal(...)",
    "looks very much like bug 60133, marking as dup of the newer since that contains\nthe discussion about the possible vm cause. Please reopen the other PR if you\nstill see this.\n\n*** This bug has been marked as a duplicate of 60133 ***"
  ],
  "commentCreationDates": [
    "2004-03-23T00:49:23+01:00",
    "2004-03-23T07:18:23+01:00",
    "2004-05-24T09:22:32+02:00"
  ],
  "traces": [
    {
      "exceptionType": "java.lang.NullPointerException",
      "elements": [
        {
          "method": "org.eclipse.ui.texteditor.AbstractTextEditor.selectAndReveal",
          "source": "Abstract TextEditor.java:4134"
        },
        {
          "method": "org.eclipse.debug.internal.ui.views.launch.LaunchView.selectAndReveal",
          "source": "LaunchView.java:908"
        },
        {
          "method": "org.eclipse.debug.internal.ui.views.launch.LaunchView.openEditorForStackFrame",
          "source": "LaunchView.java:830"
        },
        {
          "method": "org.eclipse.debug.internal.ui.views.launch.LaunchView.showEditorForCurrentSelection",
          "source": "LaunchView.java:710"
        },
        {
          "method": "org.eclipse.debug.internal.ui.views.launch.LaunchView.selectionChanged",
          "source": "LaunchView.java:506"
        },
        {
          "method": "org.eclipse.jface.viewers.Viewer$2.run",
          "source": "Viewer.java:159"
        },
        {
          "method": "org.eclipse.core.internal.runtime.InternalPlatform.run",
          "source": "InternalPlatfo rm.java:610"
        },
        {
          "method": "org.eclipse.core.runtime.Platform.run",
          "source": "Platform.java:521"
        },
        {
          "method": "org.eclipse.jface.viewers.Viewer.fireSelectionChanged",
          "source": "Viewer.java:157 "
        },
        {
          "method": "org.eclipse.jface.viewers.StructuredViewer.updateSelection",
          "source": "Structured Viewer.java:1310"
        },
        {
          "method": "org.eclipse.jface.viewers.StructuredViewer.handleSelect",
          "source": "StructuredVie wer.java:666"
        },
        {
          "method": "org.eclipse.jface.viewers.StructuredViewer$4.widgetSelected",
          "source": "Structure dViewer.java:690"
        },
        {
          "method": "org.eclipse.jface.util.OpenStrategy.fireSelectionEvent",
          "source": "OpenStrategy.j ava:178"
        },
        {
          "method": "org.eclipse.jface.util.OpenStrategy.access$3",
          "source": "OpenStrategy.java:173"
        },
        {
          "method": "org.eclipse.jface.util.OpenStrategy$1.handleEvent",
          "source": "OpenStrategy.java:3 09"
        },
        {
          "method": "org.eclipse.swt.widgets.EventTable.sendEvent",
          "source": "EventTable.java:82"
        },
        {
          "method": "org.eclipse.swt.widgets.Widget.sendEvent",
          "source": "Widget.java:956"
        },
        {
          "method": "org.eclipse.swt.widgets.Display.runDeferredEvents",
          "source": "Display.java:1892"
        },
        {
          "method": "org.eclipse.swt.widgets.Display.readAndDispatch",
          "source": "Display.java:1667"
        },
        {
          "method": "org.eclipse.ui.internal.Workbench.runEventLoop",
          "source": "Workbench.java:1488"
        },
        {
          "method": "org.eclipse.ui.internal.Workbench.runUI",
          "source": "Workbench.java:1462"
        },
        {
          "method": "org.eclipse.ui.internal.Workbench.createAndRunWorkbench",
          "source": "Workbench.jav a:259"
        },
        {
          "method": "org.eclipse.ui.PlatformUI.createAndRunWorkbench",
          "source": "PlatformUI.java:139"
        },
        {
          "method": "org.eclipse.ui.internal.ide.IDEApplication.run",
          "source": "IDEApplication.java:90 "
        },
        {
          "method": "org.eclipse.core.internal.runtime.PlatformActivator$1.run",
          "source": "PlatformAct ivator.java:262"
        },
        {
          "method": "org.eclipse.core.runtime.adaptor.EclipseStarter.run",
          "source": "EclipseStarter.ja va:213"
        },
        {
          "method": "org.eclipse.core.runtime.adaptor.EclipseStarter.run",
          "source": "EclipseStarter.ja va:115"
        },
        {
          "method": "sun.reflect.NativeMethodAccessorImpl.invoke0",
          "source": "Native Method"
        },
        {
          "method": "sun.reflect.NativeMethodAccessorImpl.invoke",
          "source": "NativeMethodAccessorImpl. java:39"
        },
        {
          "method": "sun.reflect.DelegatingMethodAccessorImpl.invoke",
          "source": "DelegatingMethodAcces sorImpl.java:25"
        },
        {
          "method": "java.lang.reflect.Method.invoke",
          "source": "Method.java:324"
        },
        {
          "method": "org.eclipse.core.launcher.Main.basicRun",
          "source": "Main.java:315"
        },
        {
          "method": "org.eclipse.core.launcher.Main.run",
          "source": "Main.java:740"
        },
        {
          "method": "org.eclipse.core.launcher.Main.main",
          "source": "Main.java:724"
        }
      ],
      "number": 0,
      "commentIndex": 0,
      "bugId": "55613",
      "duplicateId": "60133",
      "date": "2004-03-23T00:49:23+01:00",
      "product": "Platform",
      "component": "Text",
      "severity": "normal"
    }
  ],
  "groupId": "60133",
  "bugId": "55613",
  "duplicateId": "60133",
  "date": "2004-03-23T00:49:23+01:00",
  "product": "Platform",
  "component": "Text",
  "severity": "normal"
}