{
  "comments": [
    "I got the following stack trace in my log when trying to open the synch view. \nIt appears to work fine despite the error, however....\n\norg.osgi.framework.BundleException: The BundleActivator  is invalid\n        at org.eclipse.osgi.framework.internal.core.Bundle.loadBundleActivator(B\nundle.java:170)\n        at org.eclipse.osgi.framework.internal.core.BundleContext.start(BundleCo\nntext.java:967)\n        at org.eclipse.osgi.framework.internal.core.BundleHost.startWorker(Bundl\neHost.java:404)\n        at org.eclipse.osgi.framework.internal.core.Bundle.start(Bundle.java:304\n)\n        at org.eclipse.core.runtime.adaptor.EclipseClassLoader.findLocalClass(Ec\nlipseClassLoader.java:89)\n        at org.eclipse.osgi.framework.internal.core.BundleLoader.findLocalClass(\nBundleLoader.java:315)\n        at org.eclipse.osgi.framework.internal.core.BundleLoader.requireClass(Bu\nndleLoader.java:280)\n        at org.eclipse.osgi.framework.internal.core.BundleLoader.findRequiredCla\nss(BundleLoader.java:855)\n        at org.eclipse.osgi.framework.internal.core.BundleLoader.findClass(Bundl\neLoader.java:343)\n        at org.eclipse.osgi.framework.adaptor.core.AbstractClassLoader.loadClass\n(AbstractClassLoader.java:116)\n        at java.lang.ClassLoader.loadClass(ClassLoader.java:255)\n        at java.lang.ClassLoader.loadClassInternal(ClassLoader.java:315)\n        at org.eclipse.team.internal.ui.synchronize.SubscriberParticipantPage.cr\neateControl(SubscriberParticipantPage.java:94)\n        at org.eclipse.team.internal.ui.synchronize.SynchronizeView.doCreatePage\n(SynchronizeView.java:147)\n        at org.eclipse.ui.part.PageBookView.createPage(PageBookView.java:306)\n        at org.eclipse.ui.part.PageBookView.partActivated(PageBookView.java:563)\n\n        at org.eclipse.team.internal.ui.synchronize.SynchronizeView.display(Sync\nhronizeView.java:264)\n        at org.eclipse.team.internal.ui.synchronize.SynchronizeView.updateForExi\nstingParticipants(SynchronizeView.java:333)\n        at org.eclipse.team.internal.ui.synchronize.SynchronizeView.createPartCo\nntrol(SynchronizeView.java:306)\n        at org.eclipse.ui.internal.PartPane$1.run(PartPane.java:94)\n        at org.eclipse.core.internal.runtime.InternalPlatform.run(InternalPlatfo\nrm.java:610)\n        at org.eclipse.core.runtime.Platform.run(Platform.java:521)\n        at org.eclipse.ui.internal.PartPane.createChildControl(PartPane.java:90)\n\n        at org.eclipse.ui.internal.ViewPane.createChildControl(ViewPane.java:175\n)\n        at org.eclipse.ui.internal.PartPane.createControl(PartPane.java:154)\n        at org.eclipse.ui.internal.ViewPane.createControl(ViewPane.java:134)\n        at org.eclipse.ui.internal.PartTabFolder.showPart(PartTabFolder.java:886\n)\n        at org.eclipse.ui.internal.PartTabFolder.createControl(PartTabFolder.jav\na:317)\n        at org.eclipse.ui.internal.PartSashContainer.createControl(PartSashConta\niner.java:256)\n        at org.eclipse.ui.internal.PerspectivePresentation.activate(PerspectiveP\nresentation.java:148)\n        at org.eclipse.ui.internal.Perspective.onActivate(Perspective.java:630)\n        at org.eclipse.ui.internal.WorkbenchPage.setPerspective(WorkbenchPage.ja\nva:2674)\n        at org.eclipse.ui.internal.WorkbenchPage.busySetPerspective(WorkbenchPag\ne.java:694)\n        at org.eclipse.ui.internal.WorkbenchPage.access$8(WorkbenchPage.java:679\n)\n        at org.eclipse.ui.internal.WorkbenchPage$12.run(WorkbenchPage.java:2804)\n\n        at org.eclipse.swt.custom.BusyIndicator.showWhile(BusyIndicator.java:84)\n\n        at org.eclipse.ui.internal.WorkbenchPage.setPerspective(WorkbenchPage.ja\nva:2802)\n        at org.eclipse.ui.internal.PerspectiveBarContributionItem$2.widgetSelect\ned(PerspectiveBarContributionItem.java:89)\n        at org.eclipse.swt.widgets.TypedListener.handleEvent(TypedListener.java:\n89)\n        at org.eclipse.swt.widgets.EventTable.sendEvent(EventTable.java:82)\n        at org.eclipse.swt.widgets.Widget.sendEvent(Widget.java:769)\n        at org.eclipse.swt.widgets.Display.runDeferredEvents(Display.java:2584)\n        at org.eclipse.swt.widgets.Display.readAndDispatch(Display.java:2262)\n        at org.eclipse.ui.internal.Workbench.runEventLoop(Workbench.java:1488)\n        at org.eclipse.ui.internal.Workbench.runUI(Workbench.java:1462)\n        at org.eclipse.ui.internal.Workbench.createAndRunWorkbench(Workbench.jav\na:259)\n        at org.eclipse.ui.PlatformUI.createAndRunWorkbench(PlatformUI.java:139)\n        at org.eclipse.ui.internal.ide.IDEApplication.run(IDEApplication.java:90\n)\n        at org.eclipse.core.internal.runtime.PlatformActivator$1.run(PlatformAct\nivator.java:288)\n        at org.eclipse.core.runtime.adaptor.EclipseStarter.run(EclipseStarter.ja\nva:214)\n        at org.eclipse.core.runtime.adaptor.EclipseStarter.run(EclipseStarter.ja\nva:115)\n        at sun.reflect.NativeMethodAccessorImpl.invoke0(Native Method)\n        at sun.reflect.NativeMethodAccessorImpl.invoke(NativeMethodAccessorImpl.\njava:39)\n        at sun.reflect.DelegatingMethodAccessorImpl.invoke(DelegatingMethodAcces\nsorImpl.java:25)\n        at java.lang.reflect.Method.invoke(Method.java:324)\n        at org.eclipse.core.launcher.Main.basicRun(Main.java:315)\n        at org.eclipse.core.launcher.Main.run(Main.java:740)\n        at org.eclipse.core.launcher.Main.main(Main.java:724)\njava.lang.ClassNotFoundException:\n        at org.eclipse.osgi.framework.internal.core.BundleLoader.findClass(Bundl\neLoader.java:348)\n        at org.eclipse.osgi.framework.adaptor.core.AbstractClassLoader.loadClass\n(AbstractClassLoader.java:116)\n        at java.lang.ClassLoader.loadClass(ClassLoader.java:255)\n        at org.eclipse.osgi.framework.internal.core.BundleLoader.loadClass(Bundl\neLoader.java:251)\n        at org.eclipse.osgi.framework.internal.core.BundleHost.loadClass(BundleH\nost.java:332)\n        at org.eclipse.osgi.framework.internal.core.Bundle.loadBundleActivator(B\nundle.java:163)\n        at org.eclipse.osgi.framework.internal.core.BundleContext.start(BundleCo\nntext.java:967)\n        at org.eclipse.osgi.framework.internal.core.BundleHost.startWorker(Bundl\neHost.java:404)\n        at org.eclipse.osgi.framework.internal.core.Bundle.start(Bundle.java:304\n)\n        at org.eclipse.core.runtime.adaptor.EclipseClassLoader.findLocalClass(Ec\nlipseClassLoader.java:89)\n        at org.eclipse.osgi.framework.internal.core.BundleLoader.findLocalClass(\nBundleLoader.java:315)\n        at org.eclipse.osgi.framework.internal.core.BundleLoader.requireClass(Bu\nndleLoader.java:280)\n        at org.eclipse.osgi.framework.internal.core.BundleLoader.findRequiredCla\nss(BundleLoader.java:855)\n        at org.eclipse.osgi.framework.internal.core.BundleLoader.findClass(Bundl\neLoader.java:343)\n        at org.eclipse.osgi.framework.adaptor.core.AbstractClassLoader.loadClass\n(AbstractClassLoader.java:116)\n        at java.lang.ClassLoader.loadClass(ClassLoader.java:255)\n        at java.lang.ClassLoader.loadClassInternal(ClassLoader.java:315)\n        at org.eclipse.team.internal.ui.synchronize.SubscriberParticipantPage.cr\neateControl(SubscriberParticipantPage.java:94)\n        at org.eclipse.team.internal.ui.synchronize.SynchronizeView.doCreatePage\n(SynchronizeView.java:147)\n        at org.eclipse.ui.part.PageBookView.createPage(PageBookView.java:306)\n        at org.eclipse.ui.part.PageBookView.partActivated(PageBookView.java:563)\n\n        at org.eclipse.team.internal.ui.synchronize.SynchronizeView.display(Sync\nhronizeView.java:264)\n        at org.eclipse.team.internal.ui.synchronize.SynchronizeView.updateForExi\nstingParticipants(SynchronizeView.java:333)\n        at org.eclipse.team.internal.ui.synchronize.SynchronizeView.createPartCo\nntrol(SynchronizeView.java:306)\n        at org.eclipse.ui.internal.PartPane$1.run(PartPane.java:94)\n        at org.eclipse.core.internal.runtime.InternalPlatform.run(InternalPlatfo\nrm.java:610)\n        at org.eclipse.core.runtime.Platform.run(Platform.java:521)\n        at org.eclipse.ui.internal.PartPane.createChildControl(PartPane.java:90)\n\n        at org.eclipse.ui.internal.ViewPane.createChildControl(ViewPane.java:175\n)\n        at org.eclipse.ui.internal.PartPane.createControl(PartPane.java:154)\n        at org.eclipse.ui.internal.ViewPane.createControl(ViewPane.java:134)\n        at org.eclipse.ui.internal.PartTabFolder.showPart(PartTabFolder.java:886\n)\n        at org.eclipse.ui.internal.PartTabFolder.createControl(PartTabFolder.jav\na:317)\n        at org.eclipse.ui.internal.PartSashContainer.createControl(PartSashConta\niner.java:256)\n        at org.eclipse.ui.internal.PerspectivePresentation.activate(PerspectiveP\nresentation.java:148)\n        at org.eclipse.ui.internal.Perspective.onActivate(Perspective.java:630)\n        at org.eclipse.ui.internal.WorkbenchPage.setPerspective(WorkbenchPage.ja\nva:2674)\n        at org.eclipse.ui.internal.WorkbenchPage.busySetPerspective(WorkbenchPag\ne.java:694)\n        at org.eclipse.ui.internal.WorkbenchPage.access$8(WorkbenchPage.java:679\n)\n        at org.eclipse.ui.internal.WorkbenchPage$12.run(WorkbenchPage.java:2804)\n\n        at org.eclipse.swt.custom.BusyIndicator.showWhile(BusyIndicator.java:84)\n\n        at org.eclipse.ui.internal.WorkbenchPage.setPerspective(WorkbenchPage.ja\nva:2802)\n        at org.eclipse.ui.internal.PerspectiveBarContributionItem$2.widgetSelect\ned(PerspectiveBarContributionItem.java:89)\n        at org.eclipse.swt.widgets.TypedListener.handleEvent(TypedListener.java:\n89)\n        at org.eclipse.swt.widgets.EventTable.sendEvent(EventTable.java:82)\n        at org.eclipse.swt.widgets.Widget.sendEvent(Widget.java:769)\n        at org.eclipse.swt.widgets.Display.runDeferredEvents(Display.java:2584)\n        at org.eclipse.swt.widgets.Display.readAndDispatch(Display.java:2262)\n        at org.eclipse.ui.internal.Workbench.runEventLoop(Workbench.java:1488)\n        at org.eclipse.ui.internal.Workbench.runUI(Workbench.java:1462)\n        at org.eclipse.ui.internal.Workbench.createAndRunWorkbench(Workbench.jav\na:259)\n        at org.eclipse.ui.PlatformUI.createAndRunWorkbench(PlatformUI.java:139)\n        at org.eclipse.ui.internal.ide.IDEApplication.run(IDEApplication.java:90\n)\n        at org.eclipse.core.internal.runtime.PlatformActivator$1.run(PlatformAct\nivator.java:288)\n        at org.eclipse.core.runtime.adaptor.EclipseStarter.run(EclipseStarter.ja\nva:214)\n        at org.eclipse.core.runtime.adaptor.EclipseStarter.run(EclipseStarter.ja\nva:115)\n        at sun.reflect.NativeMethodAccessorImpl.invoke0(Native Method)\n        at sun.reflect.NativeMethodAccessorImpl.invoke(NativeMethodAccessorImpl.\njava:39)\n        at sun.reflect.DelegatingMethodAccessorImpl.invoke(DelegatingMethodAcces\nsorImpl.java:25)\n        at java.lang.reflect.Method.invoke(Method.java:324)\n        at org.eclipse.core.launcher.Main.basicRun(Main.java:315)\n        at org.eclipse.core.launcher.Main.run(Main.java:740)\n        at org.eclipse.core.launcher.Main.main(Main.java:724)",
    "\n\n*** This bug has been marked as a duplicate of 55397 ***"
  ],
  "commentCreationDates": [
    "2004-03-23T17:30:21+01:00",
    "2004-03-23T20:19:21+01:00"
  ],
  "traces": [
    {
      "exceptionType": "org.osgi.framework.BundleException",
      "message": "The BundleActivator  is invalid",
      "elements": [
        {
          "method": "org.eclipse.osgi.framework.internal.core.Bundle.loadBundleActivator",
          "source": "B undle.java:170"
        },
        {
          "method": "org.eclipse.osgi.framework.internal.core.BundleContext.start",
          "source": "BundleCo ntext.java:967"
        },
        {
          "method": "org.eclipse.osgi.framework.internal.core.BundleHost.startWorker",
          "source": "Bundl eHost.java:404"
        },
        {
          "method": "org.eclipse.osgi.framework.internal.core.Bundle.start",
          "source": "Bundle.java:304 "
        },
        {
          "method": "org.eclipse.core.runtime.adaptor.EclipseClassLoader.findLocalClass",
          "source": "Ec lipseClassLoader.java:89"
        },
        {
          "method": "org.eclipse.osgi.framework.internal.core.BundleLoader.findLocalClass",
          "source": " BundleLoader.java:315"
        },
        {
          "method": "org.eclipse.osgi.framework.internal.core.BundleLoader.requireClass",
          "source": "Bu ndleLoader.java:280"
        },
        {
          "method": "org.eclipse.osgi.framework.internal.core.BundleLoader.findRequiredClass",
          "source": "BundleLoader.java:855"
        },
        {
          "method": "org.eclipse.osgi.framework.internal.core.BundleLoader.findClass",
          "source": "Bundl eLoader.java:343"
        },
        {
          "method": "org.eclipse.osgi.framework.adaptor.core.AbstractClassLoader.loadClass",
          "source": "AbstractClassLoader.java:116"
        },
        {
          "method": "java.lang.ClassLoader.loadClass",
          "source": "ClassLoader.java:255"
        },
        {
          "method": "java.lang.ClassLoader.loadClassInternal",
          "source": "ClassLoader.java:315"
        },
        {
          "method": "org.eclipse.team.internal.ui.synchronize.SubscriberParticipantPage.createControl",
          "source": "SubscriberParticipantPage.java:94"
        },
        {
          "method": "org.eclipse.team.internal.ui.synchronize.SynchronizeView.doCreatePage",
          "source": "SynchronizeView.java:147"
        },
        {
          "method": "org.eclipse.ui.part.PageBookView.createPage",
          "source": "PageBookView.java:306"
        },
        {
          "method": "org.eclipse.ui.part.PageBookView.partActivated",
          "source": "PageBookView.java:563"
        },
        {
          "method": "org.eclipse.team.internal.ui.synchronize.SynchronizeView.display",
          "source": "Sync hronizeView.java:264"
        },
        {
          "method": "org.eclipse.team.internal.ui.synchronize.SynchronizeView.updateForExistingParticipants",
          "source": "SynchronizeView.java:333"
        },
        {
          "method": "org.eclipse.team.internal.ui.synchronize.SynchronizeView.createPartControl",
          "source": "SynchronizeView.java:306"
        },
        {
          "method": "org.eclipse.ui.internal.PartPane$1.run",
          "source": "PartPane.java:94"
        },
        {
          "method": "org.eclipse.core.internal.runtime.InternalPlatform.run",
          "source": "InternalPlatfo rm.java:610"
        },
        {
          "method": "org.eclipse.core.runtime.Platform.run",
          "source": "Platform.java:521"
        },
        {
          "method": "org.eclipse.ui.internal.PartPane.createChildControl",
          "source": "PartPane.java:90"
        },
        {
          "method": "org.eclipse.ui.internal.ViewPane.createChildControl",
          "source": "ViewPane.java:175 "
        },
        {
          "method": "org.eclipse.ui.internal.PartPane.createControl",
          "source": "PartPane.java:154"
        },
        {
          "method": "org.eclipse.ui.internal.ViewPane.createControl",
          "source": "ViewPane.java:134"
        },
        {
          "method": "org.eclipse.ui.internal.PartTabFolder.showPart",
          "source": "PartTabFolder.java:886 "
        },
        {
          "method": "org.eclipse.ui.internal.PartTabFolder.createControl",
          "source": "PartTabFolder.jav a:317"
        },
        {
          "method": "org.eclipse.ui.internal.PartSashContainer.createControl",
          "source": "PartSashConta iner.java:256"
        },
        {
          "method": "org.eclipse.ui.internal.PerspectivePresentation.activate",
          "source": "PerspectiveP resentation.java:148"
        },
        {
          "method": "org.eclipse.ui.internal.Perspective.onActivate",
          "source": "Perspective.java:630"
        },
        {
          "method": "org.eclipse.ui.internal.WorkbenchPage.setPerspective",
          "source": "WorkbenchPage.ja va:2674"
        },
        {
          "method": "org.eclipse.ui.internal.WorkbenchPage.busySetPerspective",
          "source": "WorkbenchPag e.java:694"
        },
        {
          "method": "org.eclipse.ui.internal.WorkbenchPage.access$8",
          "source": "WorkbenchPage.java:679 "
        },
        {
          "method": "org.eclipse.ui.internal.WorkbenchPage$12.run",
          "source": "WorkbenchPage.java:2804"
        },
        {
          "method": "org.eclipse.swt.custom.BusyIndicator.showWhile",
          "source": "BusyIndicator.java:84"
        },
        {
          "method": "org.eclipse.ui.internal.WorkbenchPage.setPerspective",
          "source": "WorkbenchPage.ja va:2802"
        },
        {
          "method": "org.eclipse.ui.internal.PerspectiveBarContributionItem$2.widgetSelected",
          "source": "PerspectiveBarContributionItem.java:89"
        },
        {
          "method": "org.eclipse.swt.widgets.TypedListener.handleEvent",
          "source": "TypedListener.java: 89"
        },
        {
          "method": "org.eclipse.swt.widgets.EventTable.sendEvent",
          "source": "EventTable.java:82"
        },
        {
          "method": "org.eclipse.swt.widgets.Widget.sendEvent",
          "source": "Widget.java:769"
        },
        {
          "method": "org.eclipse.swt.widgets.Display.runDeferredEvents",
          "source": "Display.java:2584"
        },
        {
          "method": "org.eclipse.swt.widgets.Display.readAndDispatch",
          "source": "Display.java:2262"
        },
        {
          "method": "org.eclipse.ui.internal.Workbench.runEventLoop",
          "source": "Workbench.java:1488"
        },
        {
          "method": "org.eclipse.ui.internal.Workbench.runUI",
          "source": "Workbench.java:1462"
        },
        {
          "method": "org.eclipse.ui.internal.Workbench.createAndRunWorkbench",
          "source": "Workbench.jav a:259"
        },
        {
          "method": "org.eclipse.ui.PlatformUI.createAndRunWorkbench",
          "source": "PlatformUI.java:139"
        },
        {
          "method": "org.eclipse.ui.internal.ide.IDEApplication.run",
          "source": "IDEApplication.java:90 "
        },
        {
          "method": "org.eclipse.core.internal.runtime.PlatformActivator$1.run",
          "source": "PlatformAct ivator.java:288"
        },
        {
          "method": "org.eclipse.core.runtime.adaptor.EclipseStarter.run",
          "source": "EclipseStarter.ja va:214"
        },
        {
          "method": "org.eclipse.core.runtime.adaptor.EclipseStarter.run",
          "source": "EclipseStarter.ja va:115"
        },
        {
          "method": "sun.reflect.NativeMethodAccessorImpl.invoke0",
          "source": "Native Method"
        },
        {
          "method": "sun.reflect.NativeMethodAccessorImpl.invoke",
          "source": "NativeMethodAccessorImpl. java:39"
        },
        {
          "method": "sun.reflect.DelegatingMethodAccessorImpl.invoke",
          "source": "DelegatingMethodAcces sorImpl.java:25"
        },
        {
          "method": "java.lang.reflect.Method.invoke",
          "source": "Method.java:324"
        },
        {
          "method": "org.eclipse.core.launcher.Main.basicRun",
          "source": "Main.java:315"
        },
        {
          "method": "org.eclipse.core.launcher.Main.run",
          "source": "Main.java:740"
        },
        {
          "method": "org.eclipse.core.launcher.Main.main",
          "source": "Main.java:724"
        }
      ],
      "number": 0,
      "commentIndex": 0,
      "bugId": "55715",
      "duplicateId": "55397",
      "date": "2004-03-23T17:30:21+01:00",
      "product": "Platform",
      "component": "Team",
      "severity": "normal"
    },
    {
      "exceptionType": "java.lang.ClassNotFoundException",
      "message": "",
      "elements": [
        {
          "method": "org.eclipse.osgi.framework.internal.core.BundleLoader.findClass",
          "source": "Bundl eLoader.java:348"
        },
        {
          "method": "org.eclipse.osgi.framework.adaptor.core.AbstractClassLoader.loadClass",
          "source": "AbstractClassLoader.java:116"
        },
        {
          "method": "java.lang.ClassLoader.loadClass",
          "source": "ClassLoader.java:255"
        },
        {
          "method": "org.eclipse.osgi.framework.internal.core.BundleLoader.loadClass",
          "source": "Bundl eLoader.java:251"
        },
        {
          "method": "org.eclipse.osgi.framework.internal.core.BundleHost.loadClass",
          "source": "BundleH ost.java:332"
        },
        {
          "method": "org.eclipse.osgi.framework.internal.core.Bundle.loadBundleActivator",
          "source": "B undle.java:163"
        },
        {
          "method": "org.eclipse.osgi.framework.internal.core.BundleContext.start",
          "source": "BundleCo ntext.java:967"
        },
        {
          "method": "org.eclipse.osgi.framework.internal.core.BundleHost.startWorker",
          "source": "Bundl eHost.java:404"
        },
        {
          "method": "org.eclipse.osgi.framework.internal.core.Bundle.start",
          "source": "Bundle.java:304 "
        },
        {
          "method": "org.eclipse.core.runtime.adaptor.EclipseClassLoader.findLocalClass",
          "source": "Ec lipseClassLoader.java:89"
        },
        {
          "method": "org.eclipse.osgi.framework.internal.core.BundleLoader.findLocalClass",
          "source": " BundleLoader.java:315"
        },
        {
          "method": "org.eclipse.osgi.framework.internal.core.BundleLoader.requireClass",
          "source": "Bu ndleLoader.java:280"
        },
        {
          "method": "org.eclipse.osgi.framework.internal.core.BundleLoader.findRequiredClass",
          "source": "BundleLoader.java:855"
        },
        {
          "method": "org.eclipse.osgi.framework.internal.core.BundleLoader.findClass",
          "source": "Bundl eLoader.java:343"
        },
        {
          "method": "org.eclipse.osgi.framework.adaptor.core.AbstractClassLoader.loadClass",
          "source": "AbstractClassLoader.java:116"
        },
        {
          "method": "java.lang.ClassLoader.loadClass",
          "source": "ClassLoader.java:255"
        },
        {
          "method": "java.lang.ClassLoader.loadClassInternal",
          "source": "ClassLoader.java:315"
        },
        {
          "method": "org.eclipse.team.internal.ui.synchronize.SubscriberParticipantPage.createControl",
          "source": "SubscriberParticipantPage.java:94"
        },
        {
          "method": "org.eclipse.team.internal.ui.synchronize.SynchronizeView.doCreatePage",
          "source": "SynchronizeView.java:147"
        },
        {
          "method": "org.eclipse.ui.part.PageBookView.createPage",
          "source": "PageBookView.java:306"
        },
        {
          "method": "org.eclipse.ui.part.PageBookView.partActivated",
          "source": "PageBookView.java:563"
        },
        {
          "method": "org.eclipse.team.internal.ui.synchronize.SynchronizeView.display",
          "source": "Sync hronizeView.java:264"
        },
        {
          "method": "org.eclipse.team.internal.ui.synchronize.SynchronizeView.updateForExistingParticipants",
          "source": "SynchronizeView.java:333"
        },
        {
          "method": "org.eclipse.team.internal.ui.synchronize.SynchronizeView.createPartControl",
          "source": "SynchronizeView.java:306"
        },
        {
          "method": "org.eclipse.ui.internal.PartPane$1.run",
          "source": "PartPane.java:94"
        },
        {
          "method": "org.eclipse.core.internal.runtime.InternalPlatform.run",
          "source": "InternalPlatfo rm.java:610"
        },
        {
          "method": "org.eclipse.core.runtime.Platform.run",
          "source": "Platform.java:521"
        },
        {
          "method": "org.eclipse.ui.internal.PartPane.createChildControl",
          "source": "PartPane.java:90"
        },
        {
          "method": "org.eclipse.ui.internal.ViewPane.createChildControl",
          "source": "ViewPane.java:175 "
        },
        {
          "method": "org.eclipse.ui.internal.PartPane.createControl",
          "source": "PartPane.java:154"
        },
        {
          "method": "org.eclipse.ui.internal.ViewPane.createControl",
          "source": "ViewPane.java:134"
        },
        {
          "method": "org.eclipse.ui.internal.PartTabFolder.showPart",
          "source": "PartTabFolder.java:886 "
        },
        {
          "method": "org.eclipse.ui.internal.PartTabFolder.createControl",
          "source": "PartTabFolder.jav a:317"
        },
        {
          "method": "org.eclipse.ui.internal.PartSashContainer.createControl",
          "source": "PartSashConta iner.java:256"
        },
        {
          "method": "org.eclipse.ui.internal.PerspectivePresentation.activate",
          "source": "PerspectiveP resentation.java:148"
        },
        {
          "method": "org.eclipse.ui.internal.Perspective.onActivate",
          "source": "Perspective.java:630"
        },
        {
          "method": "org.eclipse.ui.internal.WorkbenchPage.setPerspective",
          "source": "WorkbenchPage.ja va:2674"
        },
        {
          "method": "org.eclipse.ui.internal.WorkbenchPage.busySetPerspective",
          "source": "WorkbenchPag e.java:694"
        },
        {
          "method": "org.eclipse.ui.internal.WorkbenchPage.access$8",
          "source": "WorkbenchPage.java:679 "
        },
        {
          "method": "org.eclipse.ui.internal.WorkbenchPage$12.run",
          "source": "WorkbenchPage.java:2804"
        },
        {
          "method": "org.eclipse.swt.custom.BusyIndicator.showWhile",
          "source": "BusyIndicator.java:84"
        },
        {
          "method": "org.eclipse.ui.internal.WorkbenchPage.setPerspective",
          "source": "WorkbenchPage.ja va:2802"
        },
        {
          "method": "org.eclipse.ui.internal.PerspectiveBarContributionItem$2.widgetSelected",
          "source": "PerspectiveBarContributionItem.java:89"
        },
        {
          "method": "org.eclipse.swt.widgets.TypedListener.handleEvent",
          "source": "TypedListener.java: 89"
        },
        {
          "method": "org.eclipse.swt.widgets.EventTable.sendEvent",
          "source": "EventTable.java:82"
        },
        {
          "method": "org.eclipse.swt.widgets.Widget.sendEvent",
          "source": "Widget.java:769"
        },
        {
          "method": "org.eclipse.swt.widgets.Display.runDeferredEvents",
          "source": "Display.java:2584"
        },
        {
          "method": "org.eclipse.swt.widgets.Display.readAndDispatch",
          "source": "Display.java:2262"
        },
        {
          "method": "org.eclipse.ui.internal.Workbench.runEventLoop",
          "source": "Workbench.java:1488"
        },
        {
          "method": "org.eclipse.ui.internal.Workbench.runUI",
          "source": "Workbench.java:1462"
        },
        {
          "method": "org.eclipse.ui.internal.Workbench.createAndRunWorkbench",
          "source": "Workbench.jav a:259"
        },
        {
          "method": "org.eclipse.ui.PlatformUI.createAndRunWorkbench",
          "source": "PlatformUI.java:139"
        },
        {
          "method": "org.eclipse.ui.internal.ide.IDEApplication.run",
          "source": "IDEApplication.java:90 "
        },
        {
          "method": "org.eclipse.core.internal.runtime.PlatformActivator$1.run",
          "source": "PlatformAct ivator.java:288"
        },
        {
          "method": "org.eclipse.core.runtime.adaptor.EclipseStarter.run",
          "source": "EclipseStarter.ja va:214"
        },
        {
          "method": "org.eclipse.core.runtime.adaptor.EclipseStarter.run",
          "source": "EclipseStarter.ja va:115"
        },
        {
          "method": "sun.reflect.NativeMethodAccessorImpl.invoke0",
          "source": "Native Method"
        },
        {
          "method": "sun.reflect.NativeMethodAccessorImpl.invoke",
          "source": "NativeMethodAccessorImpl. java:39"
        },
        {
          "method": "sun.reflect.DelegatingMethodAccessorImpl.invoke",
          "source": "DelegatingMethodAcces sorImpl.java:25"
        },
        {
          "method": "java.lang.reflect.Method.invoke",
          "source": "Method.java:324"
        },
        {
          "method": "org.eclipse.core.launcher.Main.basicRun",
          "source": "Main.java:315"
        },
        {
          "method": "org.eclipse.core.launcher.Main.run",
          "source": "Main.java:740"
        },
        {
          "method": "org.eclipse.core.launcher.Main.main",
          "source": "Main.java:724"
        }
      ],
      "number": 1,
      "commentIndex": 0,
      "bugId": "55715",
      "duplicateId": "55397",
      "date": "2004-03-23T17:30:21+01:00",
      "product": "Platform",
      "component": "Team",
      "severity": "normal"
    }
  ],
  "groupId": "55657",
  "bugId": "55715",
  "duplicateId": "55397",
  "date": "2004-03-23T17:30:21+01:00",
  "product": "Platform",
  "component": "Team",
  "severity": "normal"
}