{
  "comments": [
    "I200403230800\n\nThis was written to the console when starting my dev workspace. It happens while\nactivating the sync view. Might be a Core problem.\n\n\norg.osgi.framework.BundleException: The BundleActivator  is invalid\n        at\norg.eclipse.osgi.framework.internal.core.Bundle.loadBundleActivator(Bundle.java:170)\n        at\norg.eclipse.osgi.framework.internal.core.BundleContext.start(BundleContext.java:967)\n        at\norg.eclipse.osgi.framework.internal.core.BundleHost.startWorker(BundleHost.java:404)\n        at org.eclipse.osgi.framework.internal.core.Bundle.start(Bundle.java:304)\n        at\norg.eclipse.core.runtime.adaptor.EclipseClassLoader.findLocalClass(EclipseClassLoader.java:89)\n        at\norg.eclipse.osgi.framework.internal.core.BundleLoader.findLocalClass(BundleLoader.java:315)\n        at\norg.eclipse.osgi.framework.internal.core.BundleLoader.requireClass(BundleLoader.java:280)\n        at\norg.eclipse.osgi.framework.internal.core.BundleLoader.findRequiredClass(BundleLoader.java:855)\n        at\norg.eclipse.osgi.framework.internal.core.BundleLoader.findClass(BundleLoader.java:343)\n        at\norg.eclipse.osgi.framework.adaptor.core.AbstractClassLoader.loadClass(AbstractClassLoader.java:116)\n        at java.lang.ClassLoader.loadClass(ClassLoader.java:235)\n        at java.lang.ClassLoader.loadClassInternal(ClassLoader.java:302)\n        at\norg.eclipse.team.internal.ui.synchronize.SubscriberParticipantPage.createControl(SubscriberParticipantPag\n        at\norg.eclipse.team.internal.ui.synchronize.SynchronizeView.doCreatePage(SynchronizeView.java:147)\n        at org.eclipse.ui.part.PageBookView.createPage(PageBookView.java:306)\n        at org.eclipse.ui.part.PageBookView.partActivated(PageBookView.java:563)\n        at\norg.eclipse.team.internal.ui.synchronize.SynchronizeView.display(SynchronizeView.java:264)\n        at\norg.eclipse.team.internal.ui.synchronize.SynchronizeView.updateForExistingParticipants(SynchronizeView.ja\n        at\norg.eclipse.team.internal.ui.synchronize.SynchronizeView.createPartControl(SynchronizeView.java:306)\n        at org.eclipse.ui.internal.PartPane$1.run(PartPane.java:94)\n        at\norg.eclipse.core.internal.runtime.InternalPlatform.run(InternalPlatform.java:610)\n        at org.eclipse.core.runtime.Platform.run(Platform.java:521)\n        at org.eclipse.ui.internal.PartPane.createChildControl(PartPane.java:90)\n        at org.eclipse.ui.internal.ViewPane.createChildControl(ViewPane.java:175)\n        at org.eclipse.ui.internal.PartPane.createControl(PartPane.java:154)\n        at org.eclipse.ui.internal.ViewPane.createControl(ViewPane.java:134)\n        at org.eclipse.ui.internal.PartTabFolder.showPart(PartTabFolder.java:886)\n        at\norg.eclipse.ui.internal.PartTabFolder.createControl(PartTabFolder.java:317)\n        at\norg.eclipse.ui.internal.PartSashContainer.createControl(PartSashContainer.java:256)\n        at\norg.eclipse.ui.internal.PerspectivePresentation.activate(PerspectivePresentation.java:148)\n        at org.eclipse.ui.internal.Perspective.onActivate(Perspective.java:630)\n        at org.eclipse.ui.internal.WorkbenchPage.onActivate(WorkbenchPage.java:1965)\n        at org.eclipse.ui.internal.WorkbenchWindow$6.run(WorkbenchWindow.java:1730)\n        at org.eclipse.swt.custom.BusyIndicator.showWhile(BusyIndicator.java:84)\n        at\norg.eclipse.ui.internal.WorkbenchWindow.setActivePage(WorkbenchWindow.java:1717)\n        at\norg.eclipse.ui.internal.WorkbenchWindow.restoreState(WorkbenchWindow.java:1304)\n        at org.eclipse.ui.internal.Workbench.restoreState(Workbench.java:1302)\n        at org.eclipse.ui.internal.Workbench.access$9(Workbench.java:1270)\n        at org.eclipse.ui.internal.Workbench$14.run(Workbench.java:1181)\n        at\norg.eclipse.core.internal.runtime.InternalPlatform.run(InternalPlatform.java:610)\n        at org.eclipse.core.runtime.Platform.run(Platform.java:521)\n        at org.eclipse.ui.internal.Workbench.restoreState(Workbench.java:1114)\n        at\norg.eclipse.ui.internal.WorkbenchConfigurer.restoreState(WorkbenchConfigurer.java:176)\n        at\norg.eclipse.ui.application.WorkbenchAdvisor.openWindows(WorkbenchAdvisor.java:613)\n        at org.eclipse.ui.internal.Workbench.init(Workbench.java:823)\n        at org.eclipse.ui.internal.Workbench.runUI(Workbench.java:1439)\n        at\norg.eclipse.ui.internal.Workbench.createAndRunWorkbench(Workbench.java:259)\n        at org.eclipse.ui.PlatformUI.createAndRunWorkbench(PlatformUI.java:139)\n        at org.eclipse.ui.internal.ide.IDEApplication.run(IDEApplication.java:90)\n        at\norg.eclipse.core.internal.runtime.PlatformActivator$1.run(PlatformActivator.java:288)\n        at\norg.eclipse.core.runtime.adaptor.EclipseStarter.run(EclipseStarter.java:214)\n        at\norg.eclipse.core.runtime.adaptor.EclipseStarter.run(EclipseStarter.java:115)\n        at sun.reflect.NativeMethodAccessorImpl.invoke0(Native Method)\n        at\nsun.reflect.NativeMethodAccessorImpl.invoke(NativeMethodAccessorImpl.java:39)\n        at\nsun.reflect.DelegatingMethodAccessorImpl.invoke(DelegatingMethodAccessorImpl.java:25)\n        at java.lang.reflect.Method.invoke(Method.java:324)\n        at org.eclipse.core.launcher.Main.basicRun(Main.java:315)\n        at org.eclipse.core.launcher.Main.run(Main.java:740)\n        at org.eclipse.core.launcher.Main.main(Main.java:724)\njava.lang.ClassNotFoundException:\n        at\norg.eclipse.osgi.framework.internal.core.BundleLoader.findClass(BundleLoader.java:348)\n        at\norg.eclipse.osgi.framework.adaptor.core.AbstractClassLoader.loadClass(AbstractClassLoader.java:116)\n        at java.lang.ClassLoader.loadClass(ClassLoader.java:235)\n        at\norg.eclipse.osgi.framework.internal.core.BundleLoader.loadClass(BundleLoader.java:251)\n        at\norg.eclipse.osgi.framework.internal.core.BundleHost.loadClass(BundleHost.java:332)\n        at\norg.eclipse.osgi.framework.internal.core.Bundle.loadBundleActivator(Bundle.java:163)\n        at\norg.eclipse.osgi.framework.internal.core.BundleContext.start(BundleContext.java:967)\n        at\norg.eclipse.osgi.framework.internal.core.BundleHost.startWorker(BundleHost.java:404)\n        at org.eclipse.osgi.framework.internal.core.Bundle.start(Bundle.java:304)\n        at\norg.eclipse.core.runtime.adaptor.EclipseClassLoader.findLocalClass(EclipseClassLoader.java:89)\n        at\norg.eclipse.osgi.framework.internal.core.BundleLoader.findLocalClass(BundleLoader.java:315)\n        at\norg.eclipse.osgi.framework.internal.core.BundleLoader.requireClass(BundleLoader.java:280)\n        at\norg.eclipse.osgi.framework.internal.core.BundleLoader.findRequiredClass(BundleLoader.java:855)\n        at\norg.eclipse.osgi.framework.internal.core.BundleLoader.findClass(BundleLoader.java:343)\n        at\norg.eclipse.osgi.framework.adaptor.core.AbstractClassLoader.loadClass(AbstractClassLoader.java:116)\n        at java.lang.ClassLoader.loadClass(ClassLoader.java:235)\n        at java.lang.ClassLoader.loadClassInternal(ClassLoader.java:302)\n        at\norg.eclipse.team.internal.ui.synchronize.SubscriberParticipantPage.createControl(SubscriberParticipantPag\n        at\norg.eclipse.team.internal.ui.synchronize.SynchronizeView.doCreatePage(SynchronizeView.java:147)\n        at org.eclipse.ui.part.PageBookView.createPage(PageBookView.java:306)\n        at org.eclipse.ui.part.PageBookView.partActivated(PageBookView.java:563)\n        at\norg.eclipse.team.internal.ui.synchronize.SynchronizeView.display(SynchronizeView.java:264)\n        at\norg.eclipse.team.internal.ui.synchronize.SynchronizeView.updateForExistingParticipants(SynchronizeView.ja\n        at\norg.eclipse.team.internal.ui.synchronize.SynchronizeView.createPartControl(SynchronizeView.java:306)\n        at org.eclipse.ui.internal.PartPane$1.run(PartPane.java:94)\n        at\norg.eclipse.core.internal.runtime.InternalPlatform.run(InternalPlatform.java:610)\n        at org.eclipse.core.runtime.Platform.run(Platform.java:521)\n        at org.eclipse.ui.internal.PartPane.createChildControl(PartPane.java:90)\n        at org.eclipse.ui.internal.ViewPane.createChildControl(ViewPane.java:175)\n        at org.eclipse.ui.internal.PartPane.createControl(PartPane.java:154)\n        at org.eclipse.ui.internal.ViewPane.createControl(ViewPane.java:134)\n        at org.eclipse.ui.internal.PartTabFolder.showPart(PartTabFolder.java:886)\n        at\norg.eclipse.ui.internal.PartTabFolder.createControl(PartTabFolder.java:317)\n        at\norg.eclipse.ui.internal.PartSashContainer.createControl(PartSashContainer.java:256)\n        at\norg.eclipse.ui.internal.PerspectivePresentation.activate(PerspectivePresentation.java:148)\n        at org.eclipse.ui.internal.Perspective.onActivate(Perspective.java:630)\n        at org.eclipse.ui.internal.WorkbenchPage.onActivate(WorkbenchPage.java:1965)\n        at org.eclipse.ui.internal.WorkbenchWindow$6.run(WorkbenchWindow.java:1730)\n        at org.eclipse.swt.custom.BusyIndicator.showWhile(BusyIndicator.java:84)\n        at\norg.eclipse.ui.internal.WorkbenchWindow.setActivePage(WorkbenchWindow.java:1717)\n        at\norg.eclipse.ui.internal.WorkbenchWindow.restoreState(WorkbenchWindow.java:1304)\n        at org.eclipse.ui.internal.Workbench.restoreState(Workbench.java:1302)\n        at org.eclipse.ui.internal.Workbench.access$9(Workbench.java:1270)\n        at org.eclipse.ui.internal.Workbench$14.run(Workbench.java:1181)\n        at\norg.eclipse.core.internal.runtime.InternalPlatform.run(InternalPlatform.java:610)\n        at org.eclipse.core.runtime.Platform.run(Platform.java:521)\n        at org.eclipse.ui.internal.Workbench.restoreState(Workbench.java:1114)\n        at\norg.eclipse.ui.internal.WorkbenchConfigurer.restoreState(WorkbenchConfigurer.java:176)\n        at\norg.eclipse.ui.application.WorkbenchAdvisor.openWindows(WorkbenchAdvisor.java:613)\n        at org.eclipse.ui.internal.Workbench.init(Workbench.java:823)\n        at org.eclipse.ui.internal.Workbench.runUI(Workbench.java:1439)\n        at\norg.eclipse.ui.internal.Workbench.createAndRunWorkbench(Workbench.java:259)\n        at org.eclipse.ui.PlatformUI.createAndRunWorkbench(PlatformUI.java:139)\n        at org.eclipse.ui.internal.ide.IDEApplication.run(IDEApplication.java:90)\n        at\norg.eclipse.core.internal.runtime.PlatformActivator$1.run(PlatformActivator.java:288)\n        at\norg.eclipse.core.runtime.adaptor.EclipseStarter.run(EclipseStarter.java:214)\n        at\norg.eclipse.core.runtime.adaptor.EclipseStarter.run(EclipseStarter.java:115)\n        at sun.reflect.NativeMethodAccessorImpl.invoke0(Native Method)\n        at\nsun.reflect.NativeMethodAccessorImpl.invoke(NativeMethodAccessorImpl.java:39)\n        at\nsun.reflect.DelegatingMethodAccessorImpl.invoke(DelegatingMethodAccessorImpl.java:25)\n        at java.lang.reflect.Method.invoke(Method.java:324)\n        at org.eclipse.core.launcher.Main.basicRun(Main.java:315)\n        at org.eclipse.core.launcher.Main.run(Main.java:740)\n        at org.eclipse.core.launcher.Main.main(Main.java:724)",
    "\n\n*** This bug has been marked as a duplicate of 55397 ***"
  ],
  "commentCreationDates": [
    "2004-03-23T19:55:40+01:00",
    "2004-03-23T20:19:40+01:00"
  ],
  "traces": [
    {
      "exceptionType": "org.osgi.framework.BundleException",
      "message": "The BundleActivator  is invalid",
      "elements": [
        {
          "method": "org.eclipse.osgi.framework.internal.core.Bundle.loadBundleActivator",
          "source": "Bundle.java:170"
        },
        {
          "method": "org.eclipse.osgi.framework.internal.core.BundleContext.start",
          "source": "BundleContext.java:967"
        },
        {
          "method": "org.eclipse.osgi.framework.internal.core.BundleHost.startWorker",
          "source": "BundleHost.java:404"
        },
        {
          "method": "org.eclipse.osgi.framework.internal.core.Bundle.start",
          "source": "Bundle.java:304"
        },
        {
          "method": "org.eclipse.core.runtime.adaptor.EclipseClassLoader.findLocalClass",
          "source": "EclipseClassLoader.java:89"
        },
        {
          "method": "org.eclipse.osgi.framework.internal.core.BundleLoader.findLocalClass",
          "source": "BundleLoader.java:315"
        },
        {
          "method": "org.eclipse.osgi.framework.internal.core.BundleLoader.requireClass",
          "source": "BundleLoader.java:280"
        },
        {
          "method": "org.eclipse.osgi.framework.internal.core.BundleLoader.findRequiredClass",
          "source": "BundleLoader.java:855"
        },
        {
          "method": "org.eclipse.osgi.framework.internal.core.BundleLoader.findClass",
          "source": "BundleLoader.java:343"
        },
        {
          "method": "org.eclipse.osgi.framework.adaptor.core.AbstractClassLoader.loadClass",
          "source": "AbstractClassLoader.java:116"
        },
        {
          "method": "java.lang.ClassLoader.loadClass",
          "source": "ClassLoader.java:235"
        },
        {
          "method": "java.lang.ClassLoader.loadClassInternal",
          "source": "ClassLoader.java:302"
        }
      ],
      "number": 0,
      "commentIndex": 0,
      "bugId": "55747",
      "duplicateId": "55397",
      "date": "2004-03-23T19:55:40+01:00",
      "product": "Platform",
      "component": "Team",
      "severity": "normal"
    },
    {
      "exceptionType": "java.lang.ClassNotFoundException",
      "message": "",
      "elements": [
        {
          "method": "org.eclipse.osgi.framework.internal.core.BundleLoader.findClass",
          "source": "BundleLoader.java:348"
        },
        {
          "method": "org.eclipse.osgi.framework.adaptor.core.AbstractClassLoader.loadClass",
          "source": "AbstractClassLoader.java:116"
        },
        {
          "method": "java.lang.ClassLoader.loadClass",
          "source": "ClassLoader.java:235"
        },
        {
          "method": "org.eclipse.osgi.framework.internal.core.BundleLoader.loadClass",
          "source": "BundleLoader.java:251"
        },
        {
          "method": "org.eclipse.osgi.framework.internal.core.BundleHost.loadClass",
          "source": "BundleHost.java:332"
        },
        {
          "method": "org.eclipse.osgi.framework.internal.core.Bundle.loadBundleActivator",
          "source": "Bundle.java:163"
        },
        {
          "method": "org.eclipse.osgi.framework.internal.core.BundleContext.start",
          "source": "BundleContext.java:967"
        },
        {
          "method": "org.eclipse.osgi.framework.internal.core.BundleHost.startWorker",
          "source": "BundleHost.java:404"
        },
        {
          "method": "org.eclipse.osgi.framework.internal.core.Bundle.start",
          "source": "Bundle.java:304"
        },
        {
          "method": "org.eclipse.core.runtime.adaptor.EclipseClassLoader.findLocalClass",
          "source": "EclipseClassLoader.java:89"
        },
        {
          "method": "org.eclipse.osgi.framework.internal.core.BundleLoader.findLocalClass",
          "source": "BundleLoader.java:315"
        },
        {
          "method": "org.eclipse.osgi.framework.internal.core.BundleLoader.requireClass",
          "source": "BundleLoader.java:280"
        },
        {
          "method": "org.eclipse.osgi.framework.internal.core.BundleLoader.findRequiredClass",
          "source": "BundleLoader.java:855"
        },
        {
          "method": "org.eclipse.osgi.framework.internal.core.BundleLoader.findClass",
          "source": "BundleLoader.java:343"
        },
        {
          "method": "org.eclipse.osgi.framework.adaptor.core.AbstractClassLoader.loadClass",
          "source": "AbstractClassLoader.java:116"
        },
        {
          "method": "java.lang.ClassLoader.loadClass",
          "source": "ClassLoader.java:235"
        },
        {
          "method": "java.lang.ClassLoader.loadClassInternal",
          "source": "ClassLoader.java:302"
        }
      ],
      "number": 1,
      "commentIndex": 0,
      "bugId": "55747",
      "duplicateId": "55397",
      "date": "2004-03-23T19:55:40+01:00",
      "product": "Platform",
      "component": "Team",
      "severity": "normal"
    }
  ],
  "groupId": "55657",
  "bugId": "55747",
  "duplicateId": "55397",
  "date": "2004-03-23T19:55:40+01:00",
  "product": "Platform",
  "component": "Team",
  "severity": "normal"
}