{
  "comments": [
    "Made a small textual change to a file. Erased the change. The \u0027Compare With Latest From HEAD\u0027 was \nstill showing that there was a difference, but then the difference was empty or was white space.\n\nSo, I selected \u0027Replace With... -\u003e Latest from HEAD\u0027.\n\nIt complained and then I no longer had the file in question. I was able to go to the project and do an \nUpdate at that level, and it brought back the file, but this will not be an acceptable work-around, in \ngeneral.\n\nOn Mac OS X 10.3.3 with Eclipse 3.0M7 (build id 200402122000).\n\nfrom console:\n\n!SESSION Mar 23, 2004 13:16:46.484 ---------------------------------------------\njava.version\u003d1.4.2_03\njava.vendor\u003dApple Computer, Inc.\nBootLoader constants: OS\u003dmacosx, ARCH\u003dppc, WS\u003dcarbon, NL\u003den_US\nCommand-line arguments: -keyring /Users/ray/.eclipse_keyring -showlocation -data workspace\n!ENTRY org.eclipse.team.cvs.core 2 -22 Mar 23, 2004 13:16:46.487\n!MESSAGE Unable to determine server version. Host \u0027woisme.apple.com\u0027 does not support the \u0027cvs \nversion\u0027 command. Although most functionality works, use version 1.11.1p1 or later for full support.\n!ENTRY org.eclipse.jdt.ui 4 10001 Mar 23, 2004 13:17:28.763\n!MESSAGE Internal Error\n!STACK 1\norg.eclipse.core.runtime.CoreException: The server reported an error while performing the \"cvs update\" \ncommand.\n\tat org.eclipse.team.internal.ui.sync.MergeResource.getLatestRevision(MergeResource.java:87)\n\tat org.eclipse.team.internal.ui.sync.TeamFile$2.createStream(TeamFile.java:89)\n\tat org.eclipse.compare.BufferedContent.getContents(BufferedContent.java:49)\n\tat org.eclipse.jdt.internal.ui.compare.JavaCompareUtilities.readString(JavaCompareUtilities.java:\n289)\n\tat org.eclipse.jdt.internal.ui.compare.JavaStructureCreator.getStructure(JavaStructureCreator.java:\n143)\n\tat \norg.eclipse.compare.structuremergeviewer.StructureDiffViewer.compareInputChanged(StructureDiffView\ner.java:215)\n\tat \norg.eclipse.jdt.internal.ui.compare.JavaStructureDiffViewer.compareInputChanged(JavaStructureDiffView\ner.java:86)\n\tat \norg.eclipse.compare.structuremergeviewer.StructureDiffViewer.inputChanged(StructureDiffViewer.java:\n146)\n\tat org.eclipse.jface.viewers.ContentViewer.setInput(ContentViewer.java:238)\n\tat org.eclipse.jface.viewers.StructuredViewer.setInput(StructuredViewer.java:1004)\n\tat org.eclipse.compare.CompareViewerSwitchingPane.setInput(CompareViewerSwitchingPane.java:\n302)\n\tat org.eclipse.compare.CompareEditorInput$12.run(CompareEditorInput.java:543)\n\tat org.eclipse.swt.custom.BusyIndicator.showWhile(BusyIndicator.java:84)\n\tat org.eclipse.compare.CompareEditorInput.feedDefault1(CompareEditorInput.java:539)\n\tat org.eclipse.compare.CompareEditorInput.access$2(CompareEditorInput.java:538)\n\tat org.eclipse.compare.CompareEditorInput$8.doubleClick(CompareEditorInput.java:473)\n\tat \norg.eclipse.compare.CompareViewerSwitchingPane.doubleClick(CompareViewerSwitchingPane.java:235)\n\tat org.eclipse.jface.viewers.StructuredViewer$1.run(StructuredViewer.java:381)\n\tat org.eclipse.core.internal.runtime.InternalPlatform.run(InternalPlatform.java:819)\n\tat org.eclipse.core.runtime.Platform.run(Platform.java:493)\n\tat org.eclipse.jface.viewers.StructuredViewer.fireDoubleClick(StructuredViewer.java:379)\n\tat org.eclipse.jface.viewers.StructuredViewer.handleDoubleSelect(StructuredViewer.java:598)\n\tat org.eclipse.jface.viewers.StructuredViewer$4.widgetDefaultSelected(StructuredViewer.java:693)\n\tat org.eclipse.jface.util.OpenStrategy.fireDefaultSelectionEvent(OpenStrategy.java:187)\n\tat org.eclipse.jface.util.OpenStrategy.access$0(OpenStrategy.java:184)\n\tat org.eclipse.jface.util.OpenStrategy$1.handleEvent(OpenStrategy.java:231)\n\tat org.eclipse.swt.widgets.EventTable.sendEvent(EventTable.java:82)\n\tat org.eclipse.swt.widgets.Widget.sendEvent(Widget.java:1179)\n\tat org.eclipse.swt.widgets.Widget.sendEvent(Widget.java:1203)\n\tat org.eclipse.swt.widgets.Widget.sendEvent(Widget.java:1188)\n\tat org.eclipse.swt.widgets.Widget.notifyListeners(Widget.java:1036)\n\tat org.eclipse.swt.widgets.Display.runDeferredEvents(Display.java:2209)\n\tat org.eclipse.swt.widgets.Display.readAndDispatch(Display.java:1921)\n\tat org.eclipse.ui.internal.Workbench.runEventLoop(Workbench.java:1550)\n\tat org.eclipse.ui.internal.Workbench.runUI(Workbench.java:1526)\n\tat org.eclipse.ui.internal.Workbench.createAndRunWorkbench(Workbench.java:265)\n\tat org.eclipse.ui.PlatformUI.createAndRunWorkbench(PlatformUI.java:139)\n\tat org.eclipse.ui.internal.ide.IDEApplication.run(IDEApplication.java:47)\n\tat org.eclipse.core.internal.runtime.PlatformActivator$1.run(PlatformActivator.java:257)\n\tat org.eclipse.core.runtime.adaptor.EclipseStarter.run(EclipseStarter.java:104)\n\tat sun.reflect.NativeMethodAccessorImpl.invoke0(Native Method)\n\tat sun.reflect.NativeMethodAccessorImpl.invoke(NativeMethodAccessorImpl.java:39)\n\tat sun.reflect.DelegatingMethodAccessorImpl.invoke(DelegatingMethodAccessorImpl.java:25)\n\tat java.lang.reflect.Method.invoke(Method.java:324)\n\tat org.eclipse.core.launcher.Main.basicRun(Main.java:279)\n\tat org.eclipse.core.launcher.Main.run(Main.java:742)\n\tat org.eclipse.core.launcher.Main.main(Main.java:581)\n!ENTRY org.eclipse.team.cvs.core 4 -10 Mar 23, 2004 13:17:28.769\n!MESSAGE The server reported an error while performing the \"cvs update\" command.\n!SUBENTRY 1 org.eclipse.team.cvs.core 4 -14 Mar 23, 2004 13:17:28.770\n!MESSAGE exc: cvs server: invalid option -- C\n!SUBENTRY 1 org.eclipse.team.cvs.core 4 -14 Mar 23, 2004 13:17:28.771\n!MESSAGE exc: Usage: cvs server [-APdflRp] [-k kopt] [-r rev|-D date] [-j rev]\n!SUBENTRY 1 org.eclipse.team.cvs.core 4 -14 Mar 23, 2004 13:17:28.772\n!MESSAGE exc:     [-I ign] [-W spec] [files...]\n!SUBENTRY 1 org.eclipse.team.cvs.core 4 -14 Mar 23, 2004 13:17:28.773\n!MESSAGE exc: \t-A\tReset any sticky tags/date/kopts.\n!SUBENTRY 1 org.eclipse.team.cvs.core 4 -14 Mar 23, 2004 13:17:28.774\n!MESSAGE exc: \t-P\tPrune empty directories.\n!SUBENTRY 1 org.eclipse.team.cvs.core 4 -14 Mar 23, 2004 13:17:28.775\n!MESSAGE exc: \t-d\tBuild directories, like checkout does.\n!SUBENTRY 1 org.eclipse.team.cvs.core 4 -14 Mar 23, 2004 13:17:28.776\n!MESSAGE exc: \t-f\tForce a head revision match if tag/date not found.\n!SUBENTRY 1 org.eclipse.team.cvs.core 4 -14 Mar 23, 2004 13:17:28.777\n!MESSAGE exc: \t-l\tLocal directory only, no recursion.\n!SUBENTRY 1 org.eclipse.team.cvs.core 4 -14 Mar 23, 2004 13:17:28.778\n!MESSAGE exc: \t-R\tProcess directories recursively.\n!SUBENTRY 1 org.eclipse.team.cvs.core 4 -14 Mar 23, 2004 13:17:28.779\n!MESSAGE exc: \t-p\tSend updates to standard output (avoids stickiness).\n!SUBENTRY 1 org.eclipse.team.cvs.core 4 -14 Mar 23, 2004 13:17:28.780\n!MESSAGE exc: \t-k kopt\tUse RCS kopt -k option on checkout.\n!SUBENTRY 1 org.eclipse.team.cvs.core 4 -14 Mar 23, 2004 13:17:28.781\n!MESSAGE exc: \t-r rev\tUpdate using specified revision/tag (is sticky).\n!SUBENTRY 1 org.eclipse.team.cvs.core 4 -14 Mar 23, 2004 13:17:28.781\n!MESSAGE exc: \t-D date\tSet date to update from (is sticky).\n!SUBENTRY 1 org.eclipse.team.cvs.core 4 -14 Mar 23, 2004 13:17:28.782\n!MESSAGE exc: \t-j rev\tMerge in changes made between current revision and rev.\n!SUBENTRY 1 org.eclipse.team.cvs.core 4 -14 Mar 23, 2004 13:17:28.783\n!MESSAGE exc: \t-I ign\tMore files to ignore (! to reset).\n!SUBENTRY 1 org.eclipse.team.cvs.core 4 -14 Mar 23, 2004 13:17:28.787\n!MESSAGE exc: \t-W spec\tWrappers specification line.\n!SUBENTRY 1 org.eclipse.team.cvs.core 4 -14 Mar 23, 2004 13:17:28.788\n!MESSAGE exc: (Specify the --help global option for a list of other help options)\n!ENTRY org.eclipse.team.cvs.core 4 -10 Mar 23, 2004 13:18:23.889\n!MESSAGE The server reported an error while performing the \"cvs update\" command.\n!SUBENTRY 1 org.eclipse.team.cvs.core 4 -14 Mar 23, 2004 13:18:23.891\n!MESSAGE exc: cvs server: invalid option -- C\n!SUBENTRY 1 org.eclipse.team.cvs.core 4 -14 Mar 23, 2004 13:18:23.892\n!MESSAGE exc: Usage: cvs server [-APdflRp] [-k kopt] [-r rev|-D date] [-j rev]\n!SUBENTRY 1 org.eclipse.team.cvs.core 4 -14 Mar 23, 2004 13:18:23.894\n!MESSAGE exc:     [-I ign] [-W spec] [files...]\n!SUBENTRY 1 org.eclipse.team.cvs.core 4 -14 Mar 23, 2004 13:18:23.896\n!MESSAGE exc: \t-A\tReset any sticky tags/date/kopts.\n!SUBENTRY 1 org.eclipse.team.cvs.core 4 -14 Mar 23, 2004 13:18:23.897\n!MESSAGE exc: \t-P\tPrune empty directories.\n!SUBENTRY 1 org.eclipse.team.cvs.core 4 -14 Mar 23, 2004 13:18:23.899\n!MESSAGE exc: \t-d\tBuild directories, like checkout does.\n!SUBENTRY 1 org.eclipse.team.cvs.core 4 -14 Mar 23, 2004 13:18:23.900\n!MESSAGE exc: \t-f\tForce a head revision match if tag/date not found.\n!SUBENTRY 1 org.eclipse.team.cvs.core 4 -14 Mar 23, 2004 13:18:23.903\n!MESSAGE exc: \t-l\tLocal directory only, no recursion.\n!SUBENTRY 1 org.eclipse.team.cvs.core 4 -14 Mar 23, 2004 13:18:23.905\n!MESSAGE exc: \t-R\tProcess directories recursively.\n!SUBENTRY 1 org.eclipse.team.cvs.core 4 -14 Mar 23, 2004 13:18:23.909\n!MESSAGE exc: \t-p\tSend updates to standard output (avoids stickiness).\n!SUBENTRY 1 org.eclipse.team.cvs.core 4 -14 Mar 23, 2004 13:18:23.911\n!MESSAGE exc: \t-k kopt\tUse RCS kopt -k option on checkout.\n!SUBENTRY 1 org.eclipse.team.cvs.core 4 -14 Mar 23, 2004 13:18:23.912\n!MESSAGE exc: \t-r rev\tUpdate using specified revision/tag (is sticky).\n!SUBENTRY 1 org.eclipse.team.cvs.core 4 -14 Mar 23, 2004 13:18:23.914\n!MESSAGE exc: \t-D date\tSet date to update from (is sticky).\n!SUBENTRY 1 org.eclipse.team.cvs.core 4 -14 Mar 23, 2004 13:18:23.915\n!MESSAGE exc: \t-j rev\tMerge in changes made between current revision and rev.\n!SUBENTRY 1 org.eclipse.team.cvs.core 4 -14 Mar 23, 2004 13:18:23.917\n!MESSAGE exc: \t-I ign\tMore files to ignore (! to reset).\n!SUBENTRY 1 org.eclipse.team.cvs.core 4 -14 Mar 23, 2004 13:18:23.919\n!MESSAGE exc: \t-W spec\tWrappers specification line.\n!SUBENTRY 1 org.eclipse.team.cvs.core 4 -14 Mar 23, 2004 13:18:23.925\n!MESSAGE exc: (Specify the --help global option for a list of other help options)",
    "The CVS server version you are using is not supported. You should upgrade to \n1.11.1p1 or later. (i.e. earlier version do not support replace using \"cvs \nupdate -C\").",
    "Works now. Not sure what happened. Probably pilot error."
  ],
  "commentCreationDates": [
    "2004-03-23T21:35:07+01:00",
    "2004-03-23T21:47:38+01:00",
    "2004-04-08T02:07:01+02:00"
  ],
  "traces": [
    {
      "exceptionType": "org.eclipse.core.runtime.CoreException",
      "message": "The server reported an error while performing the \"cvs update\"  command.",
      "elements": [
        {
          "method": "org.eclipse.team.internal.ui.sync.MergeResource.getLatestRevision",
          "source": "MergeResource.java:87"
        },
        {
          "method": "org.eclipse.team.internal.ui.sync.TeamFile$2.createStream",
          "source": "TeamFile.java:89"
        },
        {
          "method": "org.eclipse.compare.BufferedContent.getContents",
          "source": "BufferedContent.java:49"
        },
        {
          "method": "org.eclipse.jdt.internal.ui.compare.JavaCompareUtilities.readString",
          "source": "JavaCompareUtilities.java: 289"
        },
        {
          "method": "org.eclipse.jdt.internal.ui.compare.JavaStructureCreator.getStructure",
          "source": "JavaStructureCreator.java: 143"
        },
        {
          "method": "org.eclipse.compare.structuremergeviewer.StructureDiffViewer.compareInputChanged",
          "source": "StructureDiffView er.java:215"
        },
        {
          "method": "org.eclipse.jdt.internal.ui.compare.JavaStructureDiffViewer.compareInputChanged",
          "source": "JavaStructureDiffView er.java:86"
        },
        {
          "method": "org.eclipse.compare.structuremergeviewer.StructureDiffViewer.inputChanged",
          "source": "StructureDiffViewer.java: 146"
        },
        {
          "method": "org.eclipse.jface.viewers.ContentViewer.setInput",
          "source": "ContentViewer.java:238"
        },
        {
          "method": "org.eclipse.jface.viewers.StructuredViewer.setInput",
          "source": "StructuredViewer.java:1004"
        },
        {
          "method": "org.eclipse.compare.CompareViewerSwitchingPane.setInput",
          "source": "CompareViewerSwitchingPane.java: 302"
        },
        {
          "method": "org.eclipse.compare.CompareEditorInput$12.run",
          "source": "CompareEditorInput.java:543"
        },
        {
          "method": "org.eclipse.swt.custom.BusyIndicator.showWhile",
          "source": "BusyIndicator.java:84"
        },
        {
          "method": "org.eclipse.compare.CompareEditorInput.feedDefault1",
          "source": "CompareEditorInput.java:539"
        },
        {
          "method": "org.eclipse.compare.CompareEditorInput.access$2",
          "source": "CompareEditorInput.java:538"
        },
        {
          "method": "org.eclipse.compare.CompareEditorInput$8.doubleClick",
          "source": "CompareEditorInput.java:473"
        },
        {
          "method": "org.eclipse.compare.CompareViewerSwitchingPane.doubleClick",
          "source": "CompareViewerSwitchingPane.java:235"
        },
        {
          "method": "org.eclipse.jface.viewers.StructuredViewer$1.run",
          "source": "StructuredViewer.java:381"
        },
        {
          "method": "org.eclipse.core.internal.runtime.InternalPlatform.run",
          "source": "InternalPlatform.java:819"
        },
        {
          "method": "org.eclipse.core.runtime.Platform.run",
          "source": "Platform.java:493"
        },
        {
          "method": "org.eclipse.jface.viewers.StructuredViewer.fireDoubleClick",
          "source": "StructuredViewer.java:379"
        },
        {
          "method": "org.eclipse.jface.viewers.StructuredViewer.handleDoubleSelect",
          "source": "StructuredViewer.java:598"
        },
        {
          "method": "org.eclipse.jface.viewers.StructuredViewer$4.widgetDefaultSelected",
          "source": "StructuredViewer.java:693"
        },
        {
          "method": "org.eclipse.jface.util.OpenStrategy.fireDefaultSelectionEvent",
          "source": "OpenStrategy.java:187"
        },
        {
          "method": "org.eclipse.jface.util.OpenStrategy.access$0",
          "source": "OpenStrategy.java:184"
        },
        {
          "method": "org.eclipse.jface.util.OpenStrategy$1.handleEvent",
          "source": "OpenStrategy.java:231"
        },
        {
          "method": "org.eclipse.swt.widgets.EventTable.sendEvent",
          "source": "EventTable.java:82"
        },
        {
          "method": "org.eclipse.swt.widgets.Widget.sendEvent",
          "source": "Widget.java:1179"
        },
        {
          "method": "org.eclipse.swt.widgets.Widget.sendEvent",
          "source": "Widget.java:1203"
        },
        {
          "method": "org.eclipse.swt.widgets.Widget.sendEvent",
          "source": "Widget.java:1188"
        },
        {
          "method": "org.eclipse.swt.widgets.Widget.notifyListeners",
          "source": "Widget.java:1036"
        },
        {
          "method": "org.eclipse.swt.widgets.Display.runDeferredEvents",
          "source": "Display.java:2209"
        },
        {
          "method": "org.eclipse.swt.widgets.Display.readAndDispatch",
          "source": "Display.java:1921"
        },
        {
          "method": "org.eclipse.ui.internal.Workbench.runEventLoop",
          "source": "Workbench.java:1550"
        },
        {
          "method": "org.eclipse.ui.internal.Workbench.runUI",
          "source": "Workbench.java:1526"
        },
        {
          "method": "org.eclipse.ui.internal.Workbench.createAndRunWorkbench",
          "source": "Workbench.java:265"
        },
        {
          "method": "org.eclipse.ui.PlatformUI.createAndRunWorkbench",
          "source": "PlatformUI.java:139"
        },
        {
          "method": "org.eclipse.ui.internal.ide.IDEApplication.run",
          "source": "IDEApplication.java:47"
        },
        {
          "method": "org.eclipse.core.internal.runtime.PlatformActivator$1.run",
          "source": "PlatformActivator.java:257"
        },
        {
          "method": "org.eclipse.core.runtime.adaptor.EclipseStarter.run",
          "source": "EclipseStarter.java:104"
        },
        {
          "method": "sun.reflect.NativeMethodAccessorImpl.invoke0",
          "source": "Native Method"
        },
        {
          "method": "sun.reflect.NativeMethodAccessorImpl.invoke",
          "source": "NativeMethodAccessorImpl.java:39"
        },
        {
          "method": "sun.reflect.DelegatingMethodAccessorImpl.invoke",
          "source": "DelegatingMethodAccessorImpl.java:25"
        },
        {
          "method": "java.lang.reflect.Method.invoke",
          "source": "Method.java:324"
        },
        {
          "method": "org.eclipse.core.launcher.Main.basicRun",
          "source": "Main.java:279"
        },
        {
          "method": "org.eclipse.core.launcher.Main.run",
          "source": "Main.java:742"
        },
        {
          "method": "org.eclipse.core.launcher.Main.main",
          "source": "Main.java:581"
        }
      ],
      "number": 0,
      "commentIndex": 0,
      "bugId": "55780",
      "date": "2004-03-23T21:35:07+01:00",
      "product": "Platform",
      "component": "CVS",
      "severity": "normal"
    }
  ],
  "groupId": "55780",
  "bugId": "55780",
  "date": "2004-03-23T21:35:07+01:00",
  "product": "Platform",
  "component": "CVS",
  "severity": "normal"
}