{
  "comments": [
    "build i0324:0800, winxp, sunjdk1.4.2\n\n- downloaded build\n- started Eclipse\n- created new Java project (switched to Java perspective)\n- extracted the plug-in from bug 49879 comment 16 into workspace\n- in the Packages Explorer I selected the project and hit Refresh from the\ncontext menu\n- seemed to refresh ok but I get the following exception in the console\n\n\n\nosgi\u003e !SESSION Mar 24, 2004 11:57:10.668 ---------------------------------------\n------\njava.version\u003d1.4.2\njava.vendor\u003dSun Microsystems Inc.\nBootLoader constants: OS\u003dwin32, ARCH\u003dx86, WS\u003dwin32, NL\u003den_US\nCommand-line arguments: -showlocation -vmargs -cp C:\\eclipse\\dev\\i0324-0800\\ecli\npse\\startup.jar org.eclipse.core.launcher.Main\n!ENTRY org.eclipse.core.runtime 4 2 Mar 24, 2004 11:57:10.668\n!MESSAGE Problems occurred when invoking code from plug-in: \"org.eclipse.core.ru\nntime\".\n!STACK 0\norg.eclipse.swt.SWTException: Invalid thread access\n        at org.eclipse.swt.SWT.error(SWT.java:2625)\n        at org.eclipse.swt.SWT.error(SWT.java:2555)\n        at org.eclipse.swt.widgets.Widget.error(Widget.java:354)\n        at org.eclipse.swt.widgets.Widget.checkWidget(Widget.java:284)\n        at org.eclipse.swt.widgets.Menu.getItems(Menu.java:703)\n        at org.eclipse.jface.action.MenuManager.update(MenuManager.java:564)\n        at org.eclipse.jface.action.MenuManager.update(MenuManager.java:525)\n        at org.eclipse.ui.internal.activities.ws.WorkbenchActivitySupport$1.acti\nvityManagerChanged(WorkbenchActivitySupport.java:56)\n        at org.eclipse.ui.internal.activities.AbstractActivityManager.fireActivi\ntyManagerChanged(AbstractActivityManager.java:46)\n        at org.eclipse.ui.internal.activities.MutableActivityManager.setEnabledA\nctivityIds(MutableActivityManager.java:513)\n        at org.eclipse.ui.internal.activities.ws.WorkbenchActivitySupport.setEna\nbledActivityIds(WorkbenchActivitySupport.java:78)\n        at org.eclipse.ui.internal.ide.IDEWorkbenchActivityHelper.processProject\n(IDEWorkbenchActivityHelper.java:190)\n        at org.eclipse.ui.internal.ide.IDEWorkbenchActivityHelper$3.resourceChan\nged(IDEWorkbenchActivityHelper.java:152)\n        at org.eclipse.core.internal.events.NotificationManager$2.run(Notificati\nonManager.java:255)\n        at org.eclipse.core.internal.runtime.InternalPlatform.run(InternalPlatfo\nrm.java:610)\n        at org.eclipse.core.runtime.Platform.run(Platform.java:521)\n        at org.eclipse.core.internal.events.NotificationManager.notify(Notificat\nionManager.java:248)\n        at org.eclipse.core.internal.events.NotificationManager.broadcastChanges\n(NotificationManager.java:142)\n        at org.eclipse.core.internal.resources.Workspace.broadcastChanges(Worksp\nace.java:155)\n        at org.eclipse.core.internal.resources.Workspace.endOperation(Workspace.\njava:854)\n        at org.eclipse.core.internal.resources.Workspace.run(Workspace.java:1568\n)\n        at org.eclipse.jdt.core.JavaCore.run(JavaCore.java:3196)\n        at org.eclipse.jdt.core.JavaCore.run(JavaCore.java:3153)\n        at org.eclipse.jdt.internal.ui.actions.WorkbenchRunnableAdapter.run(Work\nbenchRunnableAdapter.java:50)\n        at org.eclipse.jface.operation.ModalContext$ModalContextThread.run(Modal\nContext.java:101)",
    "\n\n*** This bug has been marked as a duplicate of 55798 ***"
  ],
  "commentCreationDates": [
    "2004-03-24T17:03:53+01:00",
    "2004-03-24T18:20:19+01:00"
  ],
  "traces": [
    {
      "exceptionType": "org.eclipse.swt.SWTException",
      "message": "Invalid thread access",
      "elements": [
        {
          "method": "org.eclipse.swt.SWT.error",
          "source": "SWT.java:2625"
        },
        {
          "method": "org.eclipse.swt.SWT.error",
          "source": "SWT.java:2555"
        },
        {
          "method": "org.eclipse.swt.widgets.Widget.error",
          "source": "Widget.java:354"
        },
        {
          "method": "org.eclipse.swt.widgets.Widget.checkWidget",
          "source": "Widget.java:284"
        },
        {
          "method": "org.eclipse.swt.widgets.Menu.getItems",
          "source": "Menu.java:703"
        },
        {
          "method": "org.eclipse.jface.action.MenuManager.update",
          "source": "MenuManager.java:564"
        },
        {
          "method": "org.eclipse.jface.action.MenuManager.update",
          "source": "MenuManager.java:525"
        },
        {
          "method": "org.eclipse.ui.internal.activities.ws.WorkbenchActivitySupport$1.activityManagerChanged",
          "source": "WorkbenchActivitySupport.java:56"
        },
        {
          "method": "org.eclipse.ui.internal.activities.AbstractActivityManager.fireActivityManagerChanged",
          "source": "AbstractActivityManager.java:46"
        },
        {
          "method": "org.eclipse.ui.internal.activities.MutableActivityManager.setEnabledActivityIds",
          "source": "MutableActivityManager.java:513"
        },
        {
          "method": "org.eclipse.ui.internal.activities.ws.WorkbenchActivitySupport.setEnabledActivityIds",
          "source": "WorkbenchActivitySupport.java:78"
        },
        {
          "method": "org.eclipse.ui.internal.ide.IDEWorkbenchActivityHelper.processProject",
          "source": "IDEWorkbenchActivityHelper.java:190"
        },
        {
          "method": "org.eclipse.ui.internal.ide.IDEWorkbenchActivityHelper$3.resourceChanged",
          "source": "IDEWorkbenchActivityHelper.java:152"
        },
        {
          "method": "org.eclipse.core.internal.events.NotificationManager$2.run",
          "source": "Notificati onManager.java:255"
        },
        {
          "method": "org.eclipse.core.internal.runtime.InternalPlatform.run",
          "source": "InternalPlatfo rm.java:610"
        },
        {
          "method": "org.eclipse.core.runtime.Platform.run",
          "source": "Platform.java:521"
        },
        {
          "method": "org.eclipse.core.internal.events.NotificationManager.notify",
          "source": "Notificat ionManager.java:248"
        },
        {
          "method": "org.eclipse.core.internal.events.NotificationManager.broadcastChanges",
          "source": "NotificationManager.java:142"
        },
        {
          "method": "org.eclipse.core.internal.resources.Workspace.broadcastChanges",
          "source": "Worksp ace.java:155"
        },
        {
          "method": "org.eclipse.core.internal.resources.Workspace.endOperation",
          "source": "Workspace. java:854"
        },
        {
          "method": "org.eclipse.core.internal.resources.Workspace.run",
          "source": "Workspace.java:1568 "
        },
        {
          "method": "org.eclipse.jdt.core.JavaCore.run",
          "source": "JavaCore.java:3196"
        },
        {
          "method": "org.eclipse.jdt.core.JavaCore.run",
          "source": "JavaCore.java:3153"
        },
        {
          "method": "org.eclipse.jdt.internal.ui.actions.WorkbenchRunnableAdapter.run",
          "source": "Work benchRunnableAdapter.java:50"
        },
        {
          "method": "org.eclipse.jface.operation.ModalContext$ModalContextThread.run",
          "source": "Modal Context.java:101"
        }
      ],
      "number": 0,
      "commentIndex": 0,
      "bugId": "55936",
      "duplicateId": "55798",
      "date": "2004-03-24T17:03:53+01:00",
      "product": "Platform",
      "component": "UI",
      "severity": "normal"
    }
  ],
  "groupId": "55798",
  "bugId": "55936",
  "duplicateId": "55798",
  "date": "2004-03-24T17:03:53+01:00",
  "product": "Platform",
  "component": "UI",
  "severity": "normal"
}