{
  "comments": [
    "200403250800\n\nI found the following in my log file.  It didn\u0027t seem to cause any real harm...\n\njava.lang.IllegalArgumentException\n        at org.eclipse.jdt.core.dom.NumberLiteral.setToken(NumberLiteral.java:18\n4)\n        at org.eclipse.jdt.core.dom.AST.newNumberLiteral(AST.java:2709)\n        at org.eclipse.jdt.core.dom.ASTConverter.convert(ASTConverter.java:1369)\n\n        at org.eclipse.jdt.core.dom.ASTConverter.convert(ASTConverter.java:873)\n        at org.eclipse.jdt.core.dom.ASTConverter.convert(ASTConverter.java:947)\n        at org.eclipse.jdt.core.dom.ASTConverter.convert(ASTConverter.java:831)\n        at org.eclipse.jdt.core.dom.ASTConverter.convertToVariableDeclarationFra\ngment(ASTConverter.java:2683)\n        at org.eclipse.jdt.core.dom.ASTConverter.convertToFieldDeclaration(ASTCo\nnverter.java:2722)\n        at org.eclipse.jdt.core.dom.ASTConverter.checkAndAddMultipleFieldDeclara\ntion(ASTConverter.java:364)\n        at org.eclipse.jdt.core.dom.ASTConverter.buildBodyDeclarations(ASTConver\nter.java:324)\n        at org.eclipse.jdt.core.dom.ASTConverter.convert(ASTConverter.java:268)\n        at org.eclipse.jdt.core.dom.ASTConverter.convert(ASTConverter.java:146)\n        at org.eclipse.jdt.core.dom.AST.convertCompilationUnit(AST.java:265)\n        at org.eclipse.jdt.internal.core.ReconcileWorkingCopyOperation.executeOp\neration(ReconcileWorkingCopyOperation.java:79)\n        at org.eclipse.jdt.internal.core.JavaModelOperation.run(JavaModelOperati\non.java:700)\n        at org.eclipse.jdt.internal.core.JavaModelOperation.runOperation(JavaMod\nelOperation.java:739)\n        at org.eclipse.jdt.internal.core.CompilationUnit.reconcile(CompilationUn\nit.java:1051)\n        at org.eclipse.jdt.internal.ui.text.java.JavaReconcilingStrategy.reconci\nle(JavaReconcilingStrategy.java:85)\n        at org.eclipse.jdt.internal.ui.text.java.JavaReconcilingStrategy.initial\nReconcile(JavaReconcilingStrategy.java:143)\n        at org.eclipse.jface.text.reconciler.CompositeReconcilingStrategy.initia\nlReconcile(CompositeReconcilingStrategy.java:111)\n        at org.eclipse.jdt.internal.ui.text.JavaCompositeReconcilingStrategy.ini\ntialReconcile(JavaCompositeReconcilingStrategy.java:123)\n        at org.eclipse.jface.text.reconciler.MonoReconciler.initialProcess(MonoR\neconciler.java:104)\n        at org.eclipse.jdt.internal.ui.text.JavaReconciler.initialProcess(JavaRe\nconciler.java:280)\n        at org.eclipse.jface.text.reconciler.AbstractReconciler$BackgroundThread\n.run(AbstractReconciler.java:155)",
    "This is a dup of bug 55088.\nIf you have a test case, it would be very interesting.\n\n*** This bug has been marked as a duplicate of 55088 ***"
  ],
  "commentCreationDates": [
    "2004-03-25T19:49:53+01:00",
    "2004-03-25T20:21:02+01:00"
  ],
  "traces": [
    {
      "exceptionType": "java.lang.IllegalArgumentException",
      "elements": [
        {
          "method": "org.eclipse.jdt.core.dom.NumberLiteral.setToken",
          "source": "NumberLiteral.java:18 4"
        },
        {
          "method": "org.eclipse.jdt.core.dom.AST.newNumberLiteral",
          "source": "AST.java:2709"
        },
        {
          "method": "org.eclipse.jdt.core.dom.ASTConverter.convert",
          "source": "ASTConverter.java:1369"
        },
        {
          "method": "org.eclipse.jdt.core.dom.ASTConverter.convert",
          "source": "ASTConverter.java:873"
        },
        {
          "method": "org.eclipse.jdt.core.dom.ASTConverter.convert",
          "source": "ASTConverter.java:947"
        },
        {
          "method": "org.eclipse.jdt.core.dom.ASTConverter.convert",
          "source": "ASTConverter.java:831"
        },
        {
          "method": "org.eclipse.jdt.core.dom.ASTConverter.convertToVariableDeclarationFragment",
          "source": "ASTConverter.java:2683"
        },
        {
          "method": "org.eclipse.jdt.core.dom.ASTConverter.convertToFieldDeclaration",
          "source": "ASTCo nverter.java:2722"
        },
        {
          "method": "org.eclipse.jdt.core.dom.ASTConverter.checkAndAddMultipleFieldDeclaration",
          "source": "ASTConverter.java:364"
        },
        {
          "method": "org.eclipse.jdt.core.dom.ASTConverter.buildBodyDeclarations",
          "source": "ASTConver ter.java:324"
        },
        {
          "method": "org.eclipse.jdt.core.dom.ASTConverter.convert",
          "source": "ASTConverter.java:268"
        },
        {
          "method": "org.eclipse.jdt.core.dom.ASTConverter.convert",
          "source": "ASTConverter.java:146"
        },
        {
          "method": "org.eclipse.jdt.core.dom.AST.convertCompilationUnit",
          "source": "AST.java:265"
        },
        {
          "method": "org.eclipse.jdt.internal.core.ReconcileWorkingCopyOperation.executeOperation",
          "source": "ReconcileWorkingCopyOperation.java:79"
        },
        {
          "method": "org.eclipse.jdt.internal.core.JavaModelOperation.run",
          "source": "JavaModelOperati on.java:700"
        },
        {
          "method": "org.eclipse.jdt.internal.core.JavaModelOperation.runOperation",
          "source": "JavaMod elOperation.java:739"
        },
        {
          "method": "org.eclipse.jdt.internal.core.CompilationUnit.reconcile",
          "source": "CompilationUn it.java:1051"
        },
        {
          "method": "org.eclipse.jdt.internal.ui.text.java.JavaReconcilingStrategy.reconcile",
          "source": "JavaReconcilingStrategy.java:85"
        },
        {
          "method": "org.eclipse.jdt.internal.ui.text.java.JavaReconcilingStrategy.initialReconcile",
          "source": "JavaReconcilingStrategy.java:143"
        },
        {
          "method": "org.eclipse.jface.text.reconciler.CompositeReconcilingStrategy.initialReconcile",
          "source": "CompositeReconcilingStrategy.java:111"
        },
        {
          "method": "org.eclipse.jdt.internal.ui.text.JavaCompositeReconcilingStrategy.initialReconcile",
          "source": "JavaCompositeReconcilingStrategy.java:123"
        },
        {
          "method": "org.eclipse.jface.text.reconciler.MonoReconciler.initialProcess",
          "source": "MonoR econciler.java:104"
        },
        {
          "method": "org.eclipse.jdt.internal.ui.text.JavaReconciler.initialProcess",
          "source": "JavaRe conciler.java:280"
        },
        {
          "method": "org.eclipse.jface.text.reconciler.AbstractReconciler$BackgroundThread.run",
          "source": "AbstractReconciler.java:155"
        }
      ],
      "number": 0,
      "commentIndex": 0,
      "bugId": "56228",
      "duplicateId": "55088",
      "date": "2004-03-25T19:49:53+01:00",
      "product": "JDT",
      "component": "Core",
      "severity": "normal"
    }
  ],
  "groupId": "55088",
  "bugId": "56228",
  "duplicateId": "55088",
  "date": "2004-03-25T19:49:53+01:00",
  "product": "JDT",
  "component": "Core",
  "severity": "normal"
}