{
  "comments": [
    "The sorter for the breakpoint view doesn\u0027t handle well when multiple breakpoints\nare created/deleted programatically.\nIn the case of the watchpoint refactoring support for field rename, the\nfollowing error is logged :\n\norg.eclipse.core.internal.resources.ResourceException: Marker id: 18 not found.\n        at java.lang.Throwable.\u003cinit\u003e(Throwable.java:59)\n        at java.lang.Throwable.\u003cinit\u003e(Throwable.java:73)\n        at org.eclipse.core.runtime.CoreException.\u003cinit\u003e(CoreException.java:35)\n        at org.eclipse.core.internal.resources.Marker.checkInfo(Marker.java:55)\n        at org.eclipse.core.internal.resources.Marker.getType(Marker.java:179)\n        at\norg.eclipse.debug.internal.ui.views.breakpoints.BreakpointsSorter.compare(BreakpointsSorter.java:63)\n        at\norg.eclipse.jface.viewers.TableViewer.indexForElement(TableViewer.java:354)\n        at org.eclipse.jface.viewers.TableViewer.add(TableViewer.java:115)\n        at org.eclipse.jface.viewers.TableViewer.add(TableViewer.java:134)\n        at\norg.eclipse.debug.internal.ui.views.breakpoints.BreakpointsViewEventHandler$1.run(BreakpointsViewEventHandler.java:78)\n        at org.eclipse.swt.widgets.RunnableLock.run(RunnableLock.java:35)\n        at\norg.eclipse.swt.widgets.Synchronizer.runAsyncMessages(Synchronizer.java:106)\n        at org.eclipse.swt.widgets.Display.runAsyncMessages(Display.java:1930)\n        at org.eclipse.swt.widgets.Display.readAndDispatch(Display.java)\n        at org.eclipse.ui.internal.Workbench.runEventLoop(Workbench.java:1562)\n        at org.eclipse.ui.internal.Workbench.runUI(Workbench.java:1536)\n        at\norg.eclipse.ui.internal.Workbench.createAndRunWorkbench(Workbench.java:257)\n        at org.eclipse.ui.PlatformUI.createAndRunWorkbench(PlatformUI.java:139)\n        at org.eclipse.ui.internal.ide.IDEApplication.run(IDEApplication.java:90)\n        at\norg.eclipse.core.internal.runtime.PlatformActivator$1.run(PlatformActivator.java:277)\n        at\norg.eclipse.core.runtime.adaptor.EclipseStarter.run(EclipseStarter.java:239)\n        at\norg.eclipse.core.runtime.adaptor.EclipseStarter.run(EclipseStarter.java:117)\n        at sun.reflect.NativeMethodAccessorImpl.invoke0(Native Method)\n        at\nsun.reflect.NativeMethodAccessorImpl.invoke(NativeMethodAccessorImpl.java:79)\n        at\nsun.reflect.DelegatingMethodAccessorImpl.invoke(DelegatingMethodAccessorImpl.java:41)\n        at java.lang.reflect.Method.invoke(Method.java:386)\n        at org.eclipse.core.launcher.Main.basicRun(Main.java:267)\n        at org.eclipse.core.launcher.Main.run(Main.java:692)\n        at org.eclipse.core.launcher.Main.main(Main.java:676)\n!SUBENTRY 1 org.eclipse.core.resources 4 376 Mar 29, 2004 15:18:53.342\n!MESSAGE Marker id: 18 not found.",
    "Fixed in BreakpointSorter#compare(). Check that the markers exist before trying\nto get data from them.",
    "Please verify, Darin S.",
    "Verified."
  ],
  "commentCreationDates": [
    "2004-03-30T00:33:39+02:00",
    "2004-03-30T00:35:32+02:00",
    "2004-03-30T00:35:48+02:00",
    "2004-03-30T04:49:17+02:00"
  ],
  "traces": [
    {
      "exceptionType": "org.eclipse.core.internal.resources.ResourceException",
      "message": "Marker id: 18 not found.",
      "elements": [
        {
          "method": "java.lang.Throwable.\u003cinit\u003e",
          "source": "Throwable.java:59"
        },
        {
          "method": "java.lang.Throwable.\u003cinit\u003e",
          "source": "Throwable.java:73"
        },
        {
          "method": "org.eclipse.core.runtime.CoreException.\u003cinit\u003e",
          "source": "CoreException.java:35"
        },
        {
          "method": "org.eclipse.core.internal.resources.Marker.checkInfo",
          "source": "Marker.java:55"
        },
        {
          "method": "org.eclipse.core.internal.resources.Marker.getType",
          "source": "Marker.java:179"
        },
        {
          "method": "org.eclipse.debug.internal.ui.views.breakpoints.BreakpointsSorter.compare",
          "source": "BreakpointsSorter.java:63"
        },
        {
          "method": "org.eclipse.jface.viewers.TableViewer.indexForElement",
          "source": "TableViewer.java:354"
        },
        {
          "method": "org.eclipse.jface.viewers.TableViewer.add",
          "source": "TableViewer.java:115"
        },
        {
          "method": "org.eclipse.jface.viewers.TableViewer.add",
          "source": "TableViewer.java:134"
        },
        {
          "method": "org.eclipse.debug.internal.ui.views.breakpoints.BreakpointsViewEventHandler$1.run",
          "source": "BreakpointsViewEventHandler.java:78"
        },
        {
          "method": "org.eclipse.swt.widgets.RunnableLock.run",
          "source": "RunnableLock.java:35"
        },
        {
          "method": "org.eclipse.swt.widgets.Synchronizer.runAsyncMessages",
          "source": "Synchronizer.java:106"
        },
        {
          "method": "org.eclipse.swt.widgets.Display.runAsyncMessages",
          "source": "Display.java:1930"
        },
        {
          "method": "org.eclipse.swt.widgets.Display.readAndDispatch",
          "source": "Display.java"
        },
        {
          "method": "org.eclipse.ui.internal.Workbench.runEventLoop",
          "source": "Workbench.java:1562"
        },
        {
          "method": "org.eclipse.ui.internal.Workbench.runUI",
          "source": "Workbench.java:1536"
        },
        {
          "method": "org.eclipse.ui.internal.Workbench.createAndRunWorkbench",
          "source": "Workbench.java:257"
        },
        {
          "method": "org.eclipse.ui.PlatformUI.createAndRunWorkbench",
          "source": "PlatformUI.java:139"
        },
        {
          "method": "org.eclipse.ui.internal.ide.IDEApplication.run",
          "source": "IDEApplication.java:90"
        },
        {
          "method": "org.eclipse.core.internal.runtime.PlatformActivator$1.run",
          "source": "PlatformActivator.java:277"
        },
        {
          "method": "org.eclipse.core.runtime.adaptor.EclipseStarter.run",
          "source": "EclipseStarter.java:239"
        },
        {
          "method": "org.eclipse.core.runtime.adaptor.EclipseStarter.run",
          "source": "EclipseStarter.java:117"
        },
        {
          "method": "sun.reflect.NativeMethodAccessorImpl.invoke0",
          "source": "Native Method"
        },
        {
          "method": "sun.reflect.NativeMethodAccessorImpl.invoke",
          "source": "NativeMethodAccessorImpl.java:79"
        },
        {
          "method": "sun.reflect.DelegatingMethodAccessorImpl.invoke",
          "source": "DelegatingMethodAccessorImpl.java:41"
        },
        {
          "method": "java.lang.reflect.Method.invoke",
          "source": "Method.java:386"
        },
        {
          "method": "org.eclipse.core.launcher.Main.basicRun",
          "source": "Main.java:267"
        },
        {
          "method": "org.eclipse.core.launcher.Main.run",
          "source": "Main.java:692"
        },
        {
          "method": "org.eclipse.core.launcher.Main.main",
          "source": "Main.java:676"
        }
      ],
      "number": 0,
      "commentIndex": 0,
      "bugId": "56672",
      "date": "2004-03-30T00:33:39+02:00",
      "product": "Platform",
      "component": "Debug",
      "severity": "normal"
    }
  ],
  "groupId": "56672",
  "bugId": "56672",
  "date": "2004-03-30T00:33:39+02:00",
  "product": "Platform",
  "component": "Debug",
  "severity": "normal"
}