{
  "comments": [
    "i0324-0800, winxp, j9sc20040121\n\nI selected a project in the Navigator and chose Compare With -\u003e Released and\nnothing happened. Looking in my console, I found the following stack trace. Not\nsure if this is an Equinox thing or a Team/CVS thing....\n\nosgi\u003e !SESSION Mar 30, 2004 10:45:22.916 ---------------------------------------\n------\njava.fullversion\u003dJ2RE 1.4.1 IBM J9 build 20040121 (JIT enabled)\nBootLoader constants: OS\u003dwin32, ARCH\u003dx86, WS\u003dwin32, NL\u003den_US\nCommand-line arguments: -showlocation -vmargs -Xmx256M -Xj9 -cp C:\\eclipse\\dev\\i\n0324-0800\\eclipse\\startup.jar org.eclipse.core.launcher.Main\n!ENTRY org.eclipse.ui 4 4 Mar 30, 2004 10:45:22.926\n!MESSAGE Unhandled event loop exception\nUnhandled event loop exception\nReason:\n!ENTRY org.eclipse.ui 4 0 Mar 30, 2004 10:45:22.936\n!MESSAGE org.eclipse.team.ui.synchronize.subscriber.SubscriberParticipant\n!STACK 0\njava.lang.NoClassDefFoundError: org.eclipse.team.ui.synchronize.subscriber.Subsc\nriberParticipant\n        at java.lang.Throwable.\u003cinit\u003e(Throwable.java)\n        at java.lang.Throwable.\u003cinit\u003e(Throwable.java)\n        at java.lang.NoClassDefFoundError.\u003cinit\u003e(NoClassDefFoundError.java:52)\n        at org.eclipse.releng.tools.CompareLocalToMap.execute(CompareLocalToMap.\njava:92)\n        at org.eclipse.team.internal.ccvs.ui.actions.CVSAction.run(CVSAction.jav\na:52)\n        at org.eclipse.ui.actions.ActionDelegate.runWithEvent(ActionDelegate.jav\na:71)\n        at org.eclipse.ui.internal.PluginAction.runWithEvent(PluginAction.java:2\n59)\n        at org.eclipse.jface.action.ActionContributionItem.handleWidgetSelection\n(ActionContributionItem.java:550)\n        at org.eclipse.jface.action.ActionContributionItem.access$2(ActionContri\nbutionItem.java:502)\n        at org.eclipse.jface.action.ActionContributionItem$5.handleEvent(ActionC\nontributionItem.java:435)\n        at org.eclipse.swt.widgets.EventTable.sendEvent(EventTable.java)\n        at org.eclipse.swt.widgets.Widget.sendEvent(Widget.java)\n        at org.eclipse.swt.widgets.Display.runDeferredEvents(Display.java)\n        at org.eclipse.swt.widgets.Display.readAndDispatch(Display.java)\n        at org.eclipse.ui.internal.Workbench.runEventLoop(Workbench.java:1541)\n        at org.eclipse.ui.internal.Workbench.runUI(Workbench.java:1515)\n        at org.eclipse.ui.internal.Workbench.createAndRunWorkbench(Workbench.jav\na:257)\n        at org.eclipse.ui.PlatformUI.createAndRunWorkbench(PlatformUI.java:139)\n        at org.eclipse.ui.internal.ide.IDEApplication.run(IDEApplication.java:90\n)\n        at org.eclipse.core.internal.runtime.PlatformActivator$1.run(PlatformAct\nivator.java:288)\n        at org.eclipse.core.runtime.adaptor.EclipseStarter.run(EclipseStarter.ja\nva:232)\n        at org.eclipse.core.runtime.adaptor.EclipseStarter.run(EclipseStarter.ja\nva:116)\n        at sun.reflect.NativeMethodAccessorImpl.invoke0(Native Method)\n        at sun.reflect.NativeMethodAccessorImpl.invoke(NativeMethodAccessorImpl.\njava:79)\n        at sun.reflect.DelegatingMethodAccessorImpl.invoke(DelegatingMethodAcces\nsorImpl.java:41)\n        at java.lang.reflect.Method.invoke(Method.java:386)\n        at org.eclipse.core.launcher.Main.basicRun(Main.java:315)\n        at org.eclipse.core.launcher.Main.run(Main.java:740)\n        at org.eclipse.core.launcher.Main.main(Main.java:724)\norg.eclipse.team.ui.synchronize.subscriber.SubscriberParticipant",
    "Upgrade to version 3.04 of the release tool."
  ],
  "commentCreationDates": [
    "2004-03-30T17:03:39+02:00",
    "2004-03-30T17:12:59+02:00"
  ],
  "traces": [
    {
      "exceptionType": "java.lang.NoClassDefFoundError",
      "message": "org.eclipse.team.ui.synchronize.subscriber.Subsc riberParticipant",
      "elements": [
        {
          "method": "java.lang.Throwable.\u003cinit\u003e",
          "source": "Throwable.java"
        },
        {
          "method": "java.lang.Throwable.\u003cinit\u003e",
          "source": "Throwable.java"
        },
        {
          "method": "java.lang.NoClassDefFoundError.\u003cinit\u003e",
          "source": "NoClassDefFoundError.java:52"
        },
        {
          "method": "org.eclipse.releng.tools.CompareLocalToMap.execute",
          "source": "CompareLocalToMap. java:92"
        },
        {
          "method": "org.eclipse.team.internal.ccvs.ui.actions.CVSAction.run",
          "source": "CVSAction.jav a:52"
        },
        {
          "method": "org.eclipse.ui.actions.ActionDelegate.runWithEvent",
          "source": "ActionDelegate.jav a:71"
        },
        {
          "method": "org.eclipse.ui.internal.PluginAction.runWithEvent",
          "source": "PluginAction.java:2 59"
        },
        {
          "method": "org.eclipse.jface.action.ActionContributionItem.handleWidgetSelection",
          "source": "ActionContributionItem.java:550"
        },
        {
          "method": "org.eclipse.jface.action.ActionContributionItem.access$2",
          "source": "ActionContri butionItem.java:502"
        },
        {
          "method": "org.eclipse.jface.action.ActionContributionItem$5.handleEvent",
          "source": "ActionC ontributionItem.java:435"
        },
        {
          "method": "org.eclipse.swt.widgets.EventTable.sendEvent",
          "source": "EventTable.java"
        },
        {
          "method": "org.eclipse.swt.widgets.Widget.sendEvent",
          "source": "Widget.java"
        },
        {
          "method": "org.eclipse.swt.widgets.Display.runDeferredEvents",
          "source": "Display.java"
        },
        {
          "method": "org.eclipse.swt.widgets.Display.readAndDispatch",
          "source": "Display.java"
        },
        {
          "method": "org.eclipse.ui.internal.Workbench.runEventLoop",
          "source": "Workbench.java:1541"
        },
        {
          "method": "org.eclipse.ui.internal.Workbench.runUI",
          "source": "Workbench.java:1515"
        },
        {
          "method": "org.eclipse.ui.internal.Workbench.createAndRunWorkbench",
          "source": "Workbench.jav a:257"
        },
        {
          "method": "org.eclipse.ui.PlatformUI.createAndRunWorkbench",
          "source": "PlatformUI.java:139"
        },
        {
          "method": "org.eclipse.ui.internal.ide.IDEApplication.run",
          "source": "IDEApplication.java:90 "
        },
        {
          "method": "org.eclipse.core.internal.runtime.PlatformActivator$1.run",
          "source": "PlatformAct ivator.java:288"
        },
        {
          "method": "org.eclipse.core.runtime.adaptor.EclipseStarter.run",
          "source": "EclipseStarter.ja va:232"
        },
        {
          "method": "org.eclipse.core.runtime.adaptor.EclipseStarter.run",
          "source": "EclipseStarter.ja va:116"
        },
        {
          "method": "sun.reflect.NativeMethodAccessorImpl.invoke0",
          "source": "Native Method"
        },
        {
          "method": "sun.reflect.NativeMethodAccessorImpl.invoke",
          "source": "NativeMethodAccessorImpl. java:79"
        },
        {
          "method": "sun.reflect.DelegatingMethodAccessorImpl.invoke",
          "source": "DelegatingMethodAcces sorImpl.java:41"
        },
        {
          "method": "java.lang.reflect.Method.invoke",
          "source": "Method.java:386"
        },
        {
          "method": "org.eclipse.core.launcher.Main.basicRun",
          "source": "Main.java:315"
        },
        {
          "method": "org.eclipse.core.launcher.Main.run",
          "source": "Main.java:740"
        },
        {
          "method": "org.eclipse.core.launcher.Main.main",
          "source": "Main.java:724"
        }
      ],
      "number": 0,
      "commentIndex": 0,
      "bugId": "56757",
      "date": "2004-03-30T17:03:39+02:00",
      "product": "Platform",
      "component": "CVS",
      "severity": "normal"
    }
  ],
  "groupId": "56757",
  "bugId": "56757",
  "date": "2004-03-30T17:03:39+02:00",
  "product": "Platform",
  "component": "CVS",
  "severity": "normal"
}