{
  "comments": [
    "Build M8\n\n1) File\u003eOpen External File\n2) Select a Java file that is not in the workspace\n-\u003eNPE below\n\nMarked as major since this also happens when stepping in the debugger through \nexternal source.\n\n!SESSION Mar 31, 2004 14:36:32.469 --------------------------------------------\n-\n\njava.version\u003d1.4.2\njava.vendor\u003dSun Microsystems Inc.\nBootLoader constants: OS\u003dwin32, ARCH\u003dx86, WS\u003dwin32, NL\u003den_US\n!ENTRY org.eclipse.core.runtime 4 2 Mar 31, 2004 14:36:32.469\n!MESSAGE Problems occurred when invoking code from plug-\nin: \"org.eclipse.core.ru\nntime\".\n!STACK 0\njava.lang.NullPointerException\n        at \norg.eclipse.jdt.internal.ui.javaeditor.ASTProvider.activeJavaEditorCh\nanged(ASTProvider.java:210)\n        at org.eclipse.jdt.internal.ui.javaeditor.ASTProvider.access$0\n(ASTProvid\ner.java:199)\n        at \norg.eclipse.jdt.internal.ui.javaeditor.ASTProvider$ActivationListener\n.partOpened(ASTProvider.java:88)\n        at org.eclipse.ui.internal.PartListenerList2$5.run\n(PartListenerList2.jav\na:125)\n        at org.eclipse.core.internal.runtime.InternalPlatform.run\n(InternalPlatfo\nrm.java:610)\n        at org.eclipse.core.runtime.Platform.run(Platform.java:521)\n        at org.eclipse.ui.internal.PartListenerList2.firePartOpened\n(PartListener\nList2.java:123)\n        at org.eclipse.ui.internal.WWinPartService$1.partOpened\n(WWinPartService.\njava:62)\n        at org.eclipse.ui.internal.PartListenerList2$5.run\n(PartListenerList2.jav\na:125)\n        at org.eclipse.core.internal.runtime.InternalPlatform.run\n(InternalPlatfo\nrm.java:610)\n        at org.eclipse.core.runtime.Platform.run(Platform.java:521)\n        at org.eclipse.ui.internal.PartListenerList2.firePartOpened\n(PartListener\nList2.java:123)\n        at org.eclipse.ui.internal.WorkbenchPage.firePartOpened\n(WorkbenchPage.ja\nva:1356)\n        at org.eclipse.ui.internal.PartPane.createChildControl\n(PartPane.java:121\n)\n        at org.eclipse.ui.internal.PartPane.createControl(PartPane.java:154)\n        at org.eclipse.ui.internal.EditorWorkbook.showPart\n(EditorWorkbook.java:4\n70)\n        at org.eclipse.ui.internal.EditorWorkbook.add(EditorWorkbook.java:292)\n        at org.eclipse.ui.internal.EditorArea.addEditor(EditorArea.java:56)\n        at org.eclipse.ui.internal.EditorPresentation.openEditor\n(EditorPresentat\nion.java:225)\n        at org.eclipse.ui.internal.EditorManager$2.run(EditorManager.java:550)\n        at org.eclipse.swt.custom.BusyIndicator.showWhile\n(BusyIndicator.java:84)\n\n        at org.eclipse.ui.internal.EditorManager.createEditorTab\n(EditorManager.j\nava:539)\n        at org.eclipse.ui.internal.EditorManager.openInternalEditor\n(EditorManage\nr.java:635)\n        at org.eclipse.ui.internal.EditorManager.openEditorFromDescriptor\n(Editor\nManager.java:438)\n        at org.eclipse.ui.internal.EditorManager.openEditor\n(EditorManager.java:4\n26)\n        at org.eclipse.ui.internal.WorkbenchPage.busyOpenEditor\n(WorkbenchPage.ja\nva:2129)\n        at org.eclipse.ui.internal.WorkbenchPage.access$6\n(WorkbenchPage.java:207\n2)\n        at org.eclipse.ui.internal.WorkbenchPage$9.run(WorkbenchPage.java:2059)\n        at org.eclipse.swt.custom.BusyIndicator.showWhile\n(BusyIndicator.java:84)\n\n        at org.eclipse.ui.internal.WorkbenchPage.openEditor\n(WorkbenchPage.java:2\n054)\n        at org.eclipse.ui.internal.WorkbenchPage.openEditor\n(WorkbenchPage.java:2\n037)\n        at org.eclipse.ui.internal.editors.text.OpenExternalFileAction.run\n(OpenE\nxternalFileAction.java:115)\n        at org.eclipse.ui.internal.editors.text.OpenExternalFileAction.run\n(OpenE\nxternalFileAction.java:87)\n        at org.eclipse.ui.internal.PluginAction.runWithEvent\n(PluginAction.java:2\n69)\n        at org.eclipse.ui.internal.WWinPluginAction.runWithEvent\n(WWinPluginActio\nn.java:207)\n        at \norg.eclipse.jface.action.ActionContributionItem.handleWidgetSelection\n(ActionContributionItem.java:550)\n        at org.eclipse.jface.action.ActionContributionItem.access$2\n(ActionContri\nbutionItem.java:502)\n        at org.eclipse.jface.action.ActionContributionItem$5.handleEvent\n(ActionC\nontributionItem.java:435)\n        at org.eclipse.swt.widgets.EventTable.sendEvent(EventTable.java:82)\n        at org.eclipse.swt.widgets.Widget.sendEvent(Widget.java:769)\n        at org.eclipse.swt.widgets.Display.runDeferredEvents(Display.java:2578)\n        at org.eclipse.swt.widgets.Display.readAndDispatch(Display.java:2256)\n        at org.eclipse.ui.internal.Workbench.runEventLoop(Workbench.java:1562)\n        at org.eclipse.ui.internal.Workbench.runUI(Workbench.java:1536)\n        at org.eclipse.ui.internal.Workbench.createAndRunWorkbench\n(Workbench.jav\na:257)\n        at org.eclipse.ui.PlatformUI.createAndRunWorkbench(PlatformUI.java:139)\n        at org.eclipse.ui.internal.ide.IDEApplication.run\n(IDEApplication.java:90\n)\n        at org.eclipse.core.internal.runtime.PlatformActivator$1.run\n(PlatformAct\nivator.java:277)\n        at org.eclipse.core.runtime.adaptor.EclipseStarter.run\n(EclipseStarter.ja\nva:239)\n        at org.eclipse.core.runtime.adaptor.EclipseStarter.run\n(EclipseStarter.ja\nva:117)\n        at sun.reflect.NativeMethodAccessorImpl.invoke0(Native Method)\n        at sun.reflect.NativeMethodAccessorImpl.invoke\n(NativeMethodAccessorImpl.\njava:39)\n        at sun.reflect.DelegatingMethodAccessorImpl.invoke\n(DelegatingMethodAcces\nsorImpl.java:25)\n        at java.lang.reflect.Method.invoke(Method.java:324)\n        at org.eclipse.core.launcher.Main.basicRun(Main.java:316)\n        at org.eclipse.core.launcher.Main.run(Main.java:741)\n        at org.eclipse.core.launcher.Main.main(Main.java:725)",
    "ah, you\u0027re not using the plug-in export ;-)\n\n\n*** This bug has been marked as a duplicate of 56323 ***"
  ],
  "commentCreationDates": [
    "2004-03-31T13:44:05+02:00",
    "2004-03-31T13:51:01+02:00"
  ],
  "traces": [
    {
      "exceptionType": "java.lang.NullPointerException",
      "elements": [
        {
          "method": "org.eclipse.jdt.internal.ui.javaeditor.ASTProvider.activeJavaEditorChanged",
          "source": "ASTProvider.java:210"
        },
        {
          "method": "org.eclipse.jdt.internal.ui.javaeditor.ASTProvider.access$0",
          "source": "ASTProvid er.java:199"
        },
        {
          "method": "org.eclipse.jdt.internal.ui.javaeditor.ASTProvider$ActivationListener.partOpened",
          "source": "ASTProvider.java:88"
        },
        {
          "method": "org.eclipse.ui.internal.PartListenerList2$5.run",
          "source": "PartListenerList2.jav a:125"
        },
        {
          "method": "org.eclipse.core.internal.runtime.InternalPlatform.run",
          "source": "InternalPlatfo rm.java:610"
        },
        {
          "method": "org.eclipse.core.runtime.Platform.run",
          "source": "Platform.java:521"
        },
        {
          "method": "org.eclipse.ui.internal.PartListenerList2.firePartOpened",
          "source": "PartListener List2.java:123"
        },
        {
          "method": "org.eclipse.ui.internal.WWinPartService$1.partOpened",
          "source": "WWinPartService. java:62"
        },
        {
          "method": "org.eclipse.ui.internal.PartListenerList2$5.run",
          "source": "PartListenerList2.jav a:125"
        },
        {
          "method": "org.eclipse.core.internal.runtime.InternalPlatform.run",
          "source": "InternalPlatfo rm.java:610"
        },
        {
          "method": "org.eclipse.core.runtime.Platform.run",
          "source": "Platform.java:521"
        },
        {
          "method": "org.eclipse.ui.internal.PartListenerList2.firePartOpened",
          "source": "PartListener List2.java:123"
        },
        {
          "method": "org.eclipse.ui.internal.WorkbenchPage.firePartOpened",
          "source": "WorkbenchPage.ja va:1356"
        },
        {
          "method": "org.eclipse.ui.internal.PartPane.createChildControl",
          "source": "PartPane.java:121 "
        },
        {
          "method": "org.eclipse.ui.internal.PartPane.createControl",
          "source": "PartPane.java:154"
        },
        {
          "method": "org.eclipse.ui.internal.EditorWorkbook.showPart",
          "source": "EditorWorkbook.java:4 70"
        },
        {
          "method": "org.eclipse.ui.internal.EditorWorkbook.add",
          "source": "EditorWorkbook.java:292"
        },
        {
          "method": "org.eclipse.ui.internal.EditorArea.addEditor",
          "source": "EditorArea.java:56"
        },
        {
          "method": "org.eclipse.ui.internal.EditorPresentation.openEditor",
          "source": "EditorPresentat ion.java:225"
        },
        {
          "method": "org.eclipse.ui.internal.EditorManager$2.run",
          "source": "EditorManager.java:550"
        },
        {
          "method": "org.eclipse.swt.custom.BusyIndicator.showWhile",
          "source": "BusyIndicator.java:84"
        },
        {
          "method": "org.eclipse.ui.internal.EditorManager.createEditorTab",
          "source": "EditorManager.j ava:539"
        },
        {
          "method": "org.eclipse.ui.internal.EditorManager.openInternalEditor",
          "source": "EditorManage r.java:635"
        },
        {
          "method": "org.eclipse.ui.internal.EditorManager.openEditorFromDescriptor",
          "source": "Editor Manager.java:438"
        },
        {
          "method": "org.eclipse.ui.internal.EditorManager.openEditor",
          "source": "EditorManager.java:4 26"
        },
        {
          "method": "org.eclipse.ui.internal.WorkbenchPage.busyOpenEditor",
          "source": "WorkbenchPage.ja va:2129"
        },
        {
          "method": "org.eclipse.ui.internal.WorkbenchPage.access$6",
          "source": "WorkbenchPage.java:207 2"
        },
        {
          "method": "org.eclipse.ui.internal.WorkbenchPage$9.run",
          "source": "WorkbenchPage.java:2059"
        },
        {
          "method": "org.eclipse.swt.custom.BusyIndicator.showWhile",
          "source": "BusyIndicator.java:84"
        },
        {
          "method": "org.eclipse.ui.internal.WorkbenchPage.openEditor",
          "source": "WorkbenchPage.java:2 054"
        },
        {
          "method": "org.eclipse.ui.internal.WorkbenchPage.openEditor",
          "source": "WorkbenchPage.java:2 037"
        },
        {
          "method": "org.eclipse.ui.internal.editors.text.OpenExternalFileAction.run",
          "source": "OpenE xternalFileAction.java:115"
        },
        {
          "method": "org.eclipse.ui.internal.editors.text.OpenExternalFileAction.run",
          "source": "OpenE xternalFileAction.java:87"
        },
        {
          "method": "org.eclipse.ui.internal.PluginAction.runWithEvent",
          "source": "PluginAction.java:2 69"
        },
        {
          "method": "org.eclipse.ui.internal.WWinPluginAction.runWithEvent",
          "source": "WWinPluginActio n.java:207"
        },
        {
          "method": "org.eclipse.jface.action.ActionContributionItem.handleWidgetSelection",
          "source": "ActionContributionItem.java:550"
        },
        {
          "method": "org.eclipse.jface.action.ActionContributionItem.access$2",
          "source": "ActionContri butionItem.java:502"
        },
        {
          "method": "org.eclipse.jface.action.ActionContributionItem$5.handleEvent",
          "source": "ActionC ontributionItem.java:435"
        },
        {
          "method": "org.eclipse.swt.widgets.EventTable.sendEvent",
          "source": "EventTable.java:82"
        },
        {
          "method": "org.eclipse.swt.widgets.Widget.sendEvent",
          "source": "Widget.java:769"
        },
        {
          "method": "org.eclipse.swt.widgets.Display.runDeferredEvents",
          "source": "Display.java:2578"
        },
        {
          "method": "org.eclipse.swt.widgets.Display.readAndDispatch",
          "source": "Display.java:2256"
        },
        {
          "method": "org.eclipse.ui.internal.Workbench.runEventLoop",
          "source": "Workbench.java:1562"
        },
        {
          "method": "org.eclipse.ui.internal.Workbench.runUI",
          "source": "Workbench.java:1536"
        },
        {
          "method": "org.eclipse.ui.internal.Workbench.createAndRunWorkbench",
          "source": "Workbench.jav a:257"
        },
        {
          "method": "org.eclipse.ui.PlatformUI.createAndRunWorkbench",
          "source": "PlatformUI.java:139"
        },
        {
          "method": "org.eclipse.ui.internal.ide.IDEApplication.run",
          "source": "IDEApplication.java:90 "
        },
        {
          "method": "org.eclipse.core.internal.runtime.PlatformActivator$1.run",
          "source": "PlatformAct ivator.java:277"
        },
        {
          "method": "org.eclipse.core.runtime.adaptor.EclipseStarter.run",
          "source": "EclipseStarter.ja va:239"
        },
        {
          "method": "org.eclipse.core.runtime.adaptor.EclipseStarter.run",
          "source": "EclipseStarter.ja va:117"
        },
        {
          "method": "sun.reflect.NativeMethodAccessorImpl.invoke0",
          "source": "Native Method"
        },
        {
          "method": "sun.reflect.NativeMethodAccessorImpl.invoke",
          "source": "NativeMethodAccessorImpl. java:39"
        },
        {
          "method": "sun.reflect.DelegatingMethodAccessorImpl.invoke",
          "source": "DelegatingMethodAcces sorImpl.java:25"
        },
        {
          "method": "java.lang.reflect.Method.invoke",
          "source": "Method.java:324"
        },
        {
          "method": "org.eclipse.core.launcher.Main.basicRun",
          "source": "Main.java:316"
        },
        {
          "method": "org.eclipse.core.launcher.Main.run",
          "source": "Main.java:741"
        },
        {
          "method": "org.eclipse.core.launcher.Main.main",
          "source": "Main.java:725"
        }
      ],
      "number": 0,
      "commentIndex": 0,
      "bugId": "56898",
      "duplicateId": "56323",
      "date": "2004-03-31T13:44:05+02:00",
      "product": "JDT",
      "component": "Text",
      "severity": "major"
    }
  ],
  "groupId": "56323",
  "bugId": "56898",
  "duplicateId": "56323",
  "date": "2004-03-31T13:44:05+02:00",
  "product": "JDT",
  "component": "Text",
  "severity": "major"
}