{
  "comments": [
    "build: M8\n\nI am sorry but i don\u0027t know exactly when this happened. I was opening my \nworkspace and starting editing some code, tried to run an inner workbench and \nlooked at the console and found this exception:\n\nInstall location:\n    file:c:/eclipse/M8/eclipse/\nConfiguration file:\n    file:c:/eclipse/M8/eclipse/configuration/config.ini loaded\nConfiguration location:\n    file:c:/eclipse/M8/eclipse/configuration/\nFramework located:\n    file:c:/eclipse/M8/eclipse/plugins/org.eclipse.osgi_3.0.0/\nFramework classpath:\n    file:c:/eclipse/M8/eclipse/plugins/org.eclipse.osgi_3.0.0/core.jar\n    file:c:/eclipse/M8/eclipse/plugins/org.eclipse.osgi_3.0.0/console.jar\n    file:c:/eclipse/M8/eclipse/plugins/org.eclipse.osgi_3.0.0/osgi.jar\n    file:c:/eclipse/M8/eclipse/plugins/org.eclipse.osgi_3.0.0/resolver.jar\n    \nfile:c:/eclipse/M8/eclipse/plugins/org.eclipse.osgi_3.0.0/defaultAdaptor.jar\n\n    \nfile:c:/eclipse/M8/eclipse/plugins/org.eclipse.osgi_3.0.0/eclipseAdaptor.jar\n\nSplash location:\n    c:\\eclipse\\M8\\eclipse\\plugins\\org.eclipse.platform_3.0.0\\splash.bmp\nDebug-Options:\n    file:C:/eclipse/M8/eclipse/.options\nTime loadBundles in the framework: 90\njava.lang.ArrayIndexOutOfBoundsException\n        at java.lang.System.arraycopy(Native Method)\n        at org.eclipse.jdt.core.dom.ASTConverter.convert\n(ASTConverter.java:1424)\n\n        at org.eclipse.jdt.core.dom.ASTConverter.convert(ASTConverter.java:885)\n        at \norg.eclipse.jdt.core.dom.ASTConverter.convertToVariableDeclarationFra\ngment(ASTConverter.java:2683)\n        at org.eclipse.jdt.core.dom.ASTConverter.convertToFieldDeclaration\n(ASTCo\nnverter.java:2722)\n        at \norg.eclipse.jdt.core.dom.ASTConverter.checkAndAddMultipleFieldDeclara\ntion(ASTConverter.java:364)\n        at org.eclipse.jdt.core.dom.ASTConverter.buildBodyDeclarations\n(ASTConver\nter.java:324)\n        at org.eclipse.jdt.core.dom.ASTConverter.convert(ASTConverter.java:268)\n        at org.eclipse.jdt.core.dom.ASTConverter.convert(ASTConverter.java:146)\n        at org.eclipse.jdt.core.dom.AST.convertCompilationUnit(AST.java:265)\n        at \norg.eclipse.jdt.internal.core.ReconcileWorkingCopyOperation.executeOp\neration(ReconcileWorkingCopyOperation.java:79)\n        at org.eclipse.jdt.internal.core.JavaModelOperation.run\n(JavaModelOperati\non.java:700)\n        at org.eclipse.jdt.internal.core.JavaModelOperation.runOperation\n(JavaMod\nelOperation.java:739)\n        at org.eclipse.jdt.internal.core.CompilationUnit.reconcile\n(CompilationUn\nit.java:1051)\n        at \norg.eclipse.jdt.internal.ui.text.java.JavaReconcilingStrategy.reconci\nle(JavaReconcilingStrategy.java:85)\n        at \norg.eclipse.jdt.internal.ui.text.java.JavaReconcilingStrategy.reconci\nle(JavaReconcilingStrategy.java:118)\n        at \norg.eclipse.jface.text.reconciler.CompositeReconcilingStrategy.reconc\nile(CompositeReconcilingStrategy.java:83)\n        at \norg.eclipse.jdt.internal.ui.text.JavaCompositeReconcilingStrategy.rec\noncile(JavaCompositeReconcilingStrategy.java:97)\n        at org.eclipse.jface.text.reconciler.MonoReconciler.process\n(MonoReconcil\ner.java:76)\n        at \norg.eclipse.jface.text.reconciler.AbstractReconciler$BackgroundThread\n.run(AbstractReconciler.java:189)",
    "I think this is due to the same problem than bug 55088.",
    "This is not exactly the same stack trace, but it comes from the same bug.\n\n*** This bug has been marked as a duplicate of 55088 ***"
  ],
  "commentCreationDates": [
    "2004-03-31T15:24:10+02:00",
    "2004-03-31T19:59:36+02:00",
    "2004-03-31T23:56:27+02:00"
  ],
  "traces": [
    {
      "exceptionType": "java.lang.ArrayIndexOutOfBoundsException",
      "elements": [
        {
          "method": "java.lang.System.arraycopy",
          "source": "Native Method"
        },
        {
          "method": "org.eclipse.jdt.core.dom.ASTConverter.convert",
          "source": "ASTConverter.java:1424"
        },
        {
          "method": "org.eclipse.jdt.core.dom.ASTConverter.convert",
          "source": "ASTConverter.java:885"
        },
        {
          "method": "org.eclipse.jdt.core.dom.ASTConverter.convertToVariableDeclarationFragment",
          "source": "ASTConverter.java:2683"
        },
        {
          "method": "org.eclipse.jdt.core.dom.ASTConverter.convertToFieldDeclaration",
          "source": "ASTCo nverter.java:2722"
        },
        {
          "method": "org.eclipse.jdt.core.dom.ASTConverter.checkAndAddMultipleFieldDeclaration",
          "source": "ASTConverter.java:364"
        },
        {
          "method": "org.eclipse.jdt.core.dom.ASTConverter.buildBodyDeclarations",
          "source": "ASTConver ter.java:324"
        },
        {
          "method": "org.eclipse.jdt.core.dom.ASTConverter.convert",
          "source": "ASTConverter.java:268"
        },
        {
          "method": "org.eclipse.jdt.core.dom.ASTConverter.convert",
          "source": "ASTConverter.java:146"
        },
        {
          "method": "org.eclipse.jdt.core.dom.AST.convertCompilationUnit",
          "source": "AST.java:265"
        },
        {
          "method": "org.eclipse.jdt.internal.core.ReconcileWorkingCopyOperation.executeOperation",
          "source": "ReconcileWorkingCopyOperation.java:79"
        },
        {
          "method": "org.eclipse.jdt.internal.core.JavaModelOperation.run",
          "source": "JavaModelOperati on.java:700"
        },
        {
          "method": "org.eclipse.jdt.internal.core.JavaModelOperation.runOperation",
          "source": "JavaMod elOperation.java:739"
        },
        {
          "method": "org.eclipse.jdt.internal.core.CompilationUnit.reconcile",
          "source": "CompilationUn it.java:1051"
        },
        {
          "method": "org.eclipse.jdt.internal.ui.text.java.JavaReconcilingStrategy.reconcile",
          "source": "JavaReconcilingStrategy.java:85"
        },
        {
          "method": "org.eclipse.jdt.internal.ui.text.java.JavaReconcilingStrategy.reconcile",
          "source": "JavaReconcilingStrategy.java:118"
        },
        {
          "method": "org.eclipse.jface.text.reconciler.CompositeReconcilingStrategy.reconcile",
          "source": "CompositeReconcilingStrategy.java:83"
        },
        {
          "method": "org.eclipse.jdt.internal.ui.text.JavaCompositeReconcilingStrategy.reconcile",
          "source": "JavaCompositeReconcilingStrategy.java:97"
        },
        {
          "method": "org.eclipse.jface.text.reconciler.MonoReconciler.process",
          "source": "MonoReconcil er.java:76"
        },
        {
          "method": "org.eclipse.jface.text.reconciler.AbstractReconciler$BackgroundThread.run",
          "source": "AbstractReconciler.java:189"
        }
      ],
      "number": 0,
      "commentIndex": 0,
      "bugId": "56906",
      "duplicateId": "55088",
      "date": "2004-03-31T15:24:10+02:00",
      "product": "JDT",
      "component": "Core",
      "severity": "normal"
    }
  ],
  "groupId": "55088",
  "bugId": "56906",
  "duplicateId": "55088",
  "date": "2004-03-31T15:24:10+02:00",
  "product": "JDT",
  "component": "Core",
  "severity": "normal"
}