{
  "comments": [
    "Using I-20040330-linux-gtk\nMachine is running Gnome 2.5.91  (2.6 rc 1?), Sun jdk 1.4.2_02",
    "Do you see the menu items at all? Do you get any error message?\nIs it possible to append the .log file to this bug ?",
    "No warnings, no errors, a 1/4 spike to 33-50% CPU use\n",
    "Here is the appropriate log entry\n\n!ENTRY org.eclipse.ui 4 4 Mar 31, 2004 14:22:12.956\n!MESSAGE Unhandled event loop exception\n!ENTRY org.eclipse.ui 4 0 Mar 31, 2004 14:22:12.970\n!MESSAGE org/eclipse/update/internal/configurator/FeatureEntry\n!STACK 0\njava.lang.NoClassDefFoundError:\norg/eclipse/update/internal/configurator/FeatureEntry\n    at\norg.eclipse.update.internal.core.BaseSiteLocalFactory.createInstallConfigurationModel(BaseSiteLocalFactory.java:22)\n    at\norg.eclipse.update.internal.model.SiteLocalModel.processHistory(SiteLocalModel.java:250)\n    at\norg.eclipse.update.internal.model.SiteLocalModel.getConfigurationHistoryModel(SiteLocalModel.java:56)\n    at\norg.eclipse.update.internal.model.SiteLocalModel.resolve(SiteLocalModel.java:203)\n    at\norg.eclipse.update.internal.core.SiteLocal.internalGetLocalSite(SiteLocal.java:59)\n    at\norg.eclipse.update.internal.core.InternalSiteManager.internalGetLocalSite(InternalSiteManager.java:67)\n    at\norg.eclipse.update.internal.core.InternalSiteManager.getLocalSite(InternalSiteManager.java:52)\n    at org.eclipse.update.core.SiteManager.getLocalSite(SiteManager.java:126)\n    at\norg.eclipse.update.internal.ui.wizards.InstallWizard.addPages(InstallWizard.java:204)\n    at org.eclipse.jface.wizard.WizardDialog.createContents(WizardDialog.java:466)\n    at org.eclipse.jface.window.Window.create(Window.java:350)\n    at org.eclipse.jface.dialogs.Dialog.create(Dialog.java:859)\n    at\norg.eclipse.update.internal.ui.InstallWizardAction.openNewUpdatesWizard(InstallWizardAction.java:55)\n    at\norg.eclipse.update.internal.ui.InstallWizardAction.doRun(InstallWizardAction.java:49)\n    at\norg.eclipse.update.internal.ui.InstallWizardAction.access$0(InstallWizardAction.java:48)\n    at\norg.eclipse.update.internal.ui.InstallWizardAction$1.run(InstallWizardAction.java:43)\n    at org.eclipse.swt.custom.BusyIndicator.showWhile(BusyIndicator.java:84)\n    at\norg.eclipse.update.internal.ui.InstallWizardAction.run(InstallWizardAction.java:41)\n    at org.eclipse.ui.internal.PluginAction.runWithEvent(PluginAction.java:269)\n    at\norg.eclipse.ui.internal.WWinPluginAction.runWithEvent(WWinPluginAction.java:207)\n    at\norg.eclipse.jface.action.ActionContributionItem.handleWidgetSelection(ActionContributionItem.java:550)\n    at\norg.eclipse.jface.action.ActionContributionItem.access$2(ActionContributionItem.java:502)\n    at\norg.eclipse.jface.action.ActionContributionItem$5.handleEvent(ActionContributionItem.java:435)\n    at org.eclipse.swt.widgets.EventTable.sendEvent(EventTable.java:82)\n    at org.eclipse.swt.widgets.Widget.sendEvent(Widget.java:939)\n    at org.eclipse.swt.widgets.Display.runDeferredEvents(Display.java:1953)\n    at org.eclipse.swt.widgets.Display.readAndDispatch(Display.java:1726)\n    at org.eclipse.ui.internal.Workbench.runEventLoop(Workbench.java:1558)\n    at org.eclipse.ui.internal.Workbench.runUI(Workbench.java:1532)\n    at org.eclipse.ui.internal.Workbench.createAndRunWorkbench(Workbench.java:257)\n    at org.eclipse.ui.PlatformUI.createAndRunWorkbench(PlatformUI.java:139)\n    at org.eclipse.ui.internal.ide.IDEApplication.run(IDEApplication.java:90)\n    at\norg.eclipse.core.internal.runtime.PlatformActivator$1.run(PlatformActivator.java:277)\n    at org.eclipse.core.runtime.adaptor.EclipseStarter.run(EclipseStarter.java:241)\n    at org.eclipse.core.runtime.adaptor.EclipseStarter.run(EclipseStarter.java:117)\n    at sun.reflect.NativeMethodAccessorImpl.invoke0(Native Method)\n    at sun.reflect.NativeMethodAccessorImpl.invoke(NativeMethodAccessorImpl.java:39)\n    at\nsun.reflect.DelegatingMethodAccessorImpl.invoke(DelegatingMethodAccessorImpl.java:25)\n    at java.lang.reflect.Method.invoke(Method.java:494)\n    at org.eclipse.core.launcher.Main.basicRun(Main.java:267)\n    at org.eclipse.core.launcher.Main.run(Main.java:692)\n    at org.eclipse.core.launcher.Main.main(Main.java:676)\n!ENTRY org.eclipse.core.runtime 4 2 Mar 31, 2004 14:22:20.756\n!MESSAGE An internal error occurred during: \"Close floating window\".\n!STACK 0\njava.lang.NullPointerException\n    at org.eclipse.swt.widgets.Display.asyncExec(Display.java:483)\n    at org.eclipse.ui.progress.UIJob.run(UIJob.java:83)\n    at org.eclipse.core.internal.jobs.Worker.run(Worker.java:62)\n",
    "Oh yeah ... the menu items _are_ there.  Just apparently non-functional.",
    "Thanks for the log.\nIt appears that the org.eclipse.update.configurator is not exporting its \nclasses (FeatureEntry in this case). This seems odd, as things appear to be \nworking fine on Windows. \nCan you find any log entries that show some plugins have been \nuninstalled/disabled/etc. ?",
    "Here is the complete log of a session where I started eclipse, clicked on Manage\nConfiguration, and then shut down:\n\n\n!SESSION Apr 01, 2004 12:21:59.546 ---------------------------------------------\njava.version\u003d1.5.0-beta\njava.vendor\u003dSun Microsystems Inc.\nBootLoader constants: OS\u003dlinux, ARCH\u003dx86, WS\u003dgtk, NL\u003den_CA\n!ENTRY org.eclipse.osgi Apr 01, 2004 12:21:59.547\n!MESSAGE Bundle reference:file:/usr/local/eclipse/plugins/org.apache.ant_1.6.0/\n[37] was not resolved\n!ENTRY org.eclipse.osgi Apr 01, 2004 12:21:59.549\n!MESSAGE Bundle\nreference:file:/usr/local/eclipse/plugins/org.eclipse.tomcat_4.1.29/ [60] was\nnot resolved\n!ENTRY org.eclipse.ui 4 4 Apr 01, 2004 12:35:38.906\n!MESSAGE Unhandled event loop exception\n!ENTRY org.eclipse.ui 4 0 Apr 01, 2004 12:35:38.915\n!MESSAGE org/eclipse/update/internal/configurator/FeatureEntry\n!STACK 0\njava.lang.NoClassDefFoundError:\norg/eclipse/update/internal/configurator/FeatureEntry\n        at\norg.eclipse.update.internal.core.BaseSiteLocalFactory.createInstallConfigurationModel(BaseSiteLocalFactory.java:22)\n        at\norg.eclipse.update.internal.model.SiteLocalModel.processHistory(SiteLocalModel.java:250)\n        at\norg.eclipse.update.internal.model.SiteLocalModel.getConfigurationHistoryModel(SiteLocalModel.java:56)\n        at\norg.eclipse.update.internal.model.SiteLocalModel.resolve(SiteLocalModel.java:203)\n        at\norg.eclipse.update.internal.core.SiteLocal.internalGetLocalSite(SiteLocal.java:59)\n        at\norg.eclipse.update.internal.core.InternalSiteManager.internalGetLocalSite(InternalSiteManager.java:67)\n        at\norg.eclipse.update.internal.core.InternalSiteManager.getLocalSite(InternalSiteManager.java:52)\n        at org.eclipse.update.core.SiteManager.getLocalSite(SiteManager.java:126)\n        at\norg.eclipse.update.internal.ui.wizards.InstallWizard.addPages(InstallWizard.java:204)\n        at\norg.eclipse.jface.wizard.WizardDialog.createContents(WizardDialog.java:466)\n        at org.eclipse.jface.window.Window.create(Window.java:350)\n        at org.eclipse.jface.dialogs.Dialog.create(Dialog.java:859)\n        at\norg.eclipse.update.internal.ui.InstallWizardAction.openNewUpdatesWizard(InstallWizardAction.java:55)\n        at\norg.eclipse.update.internal.ui.InstallWizardAction.doRun(InstallWizardAction.java:49)\n        at\norg.eclipse.update.internal.ui.InstallWizardAction.access$0(InstallWizardAction.java:48)\n        at\norg.eclipse.update.internal.ui.InstallWizardAction$1.run(InstallWizardAction.java:43)\n        at org.eclipse.swt.custom.BusyIndicator.showWhile(BusyIndicator.java:84)\n        at\norg.eclipse.update.internal.ui.InstallWizardAction.run(InstallWizardAction.java:41)\n        at org.eclipse.ui.internal.PluginAction.runWithEvent(PluginAction.java:269)\n        at\norg.eclipse.ui.internal.WWinPluginAction.runWithEvent(WWinPluginAction.java:207)\n        at\norg.eclipse.jface.action.ActionContributionItem.handleWidgetSelection(ActionContributionItem.java:550)\n        at\norg.eclipse.jface.action.ActionContributionItem.access$2(ActionContributionItem.java:502)\n        at\norg.eclipse.jface.action.ActionContributionItem$5.handleEvent(ActionContributionItem.java:435)\n        at org.eclipse.swt.widgets.EventTable.sendEvent(EventTable.java:82)\n        at org.eclipse.swt.widgets.Widget.sendEvent(Widget.java:939)\n        at org.eclipse.swt.widgets.Display.runDeferredEvents(Display.java:1953)\n        at org.eclipse.swt.widgets.Display.readAndDispatch(Display.java:1726)\n        at org.eclipse.ui.internal.Workbench.runEventLoop(Workbench.java:1558)\n        at org.eclipse.ui.internal.Workbench.runUI(Workbench.java:1532)\n        at\norg.eclipse.ui.internal.Workbench.createAndRunWorkbench(Workbench.java:257)\n        at org.eclipse.ui.PlatformUI.createAndRunWorkbench(PlatformUI.java:139)\n        at org.eclipse.ui.internal.ide.IDEApplication.run(IDEApplication.java:90)\n        at\norg.eclipse.core.internal.runtime.PlatformActivator$1.run(PlatformActivator.java:277)\n        at\norg.eclipse.core.runtime.adaptor.EclipseStarter.run(EclipseStarter.java:241)\n        at\norg.eclipse.core.runtime.adaptor.EclipseStarter.run(EclipseStarter.java:117)\n        at sun.reflect.NativeMethodAccessorImpl.invoke0(Native Method)\n        at\nsun.reflect.NativeMethodAccessorImpl.invoke(NativeMethodAccessorImpl.java:39)\n        at\nsun.reflect.DelegatingMethodAccessorImpl.invoke(DelegatingMethodAccessorImpl.java:25)\n        at java.lang.reflect.Method.invoke(Method.java:494)\n        at org.eclipse.core.launcher.Main.basicRun(Main.java:267)\n        at org.eclipse.core.launcher.Main.run(Main.java:692)\n        at org.eclipse.core.launcher.Main.main(Main.java:676)\n!ENTRY\nreference:file:/usr/local/eclipse/plugins/org.eclipse.jdt.launching_3.0.0/ 0 0\nApr 01, 2004 12:35:53.991\n!MESSAGE FrameworkEvent.ERROR\n!STACK 0\norg.osgi.framework.BundleException: Exception in\n[Ljava.lang.Object;@1635aad.java.lang.NullPointerException() of bundle \u003cmissing\nargument\u003e.\n        at\norg.eclipse.osgi.framework.internal.core.BundleContext.stop(BundleContext.java:1044)\n        at\norg.eclipse.osgi.framework.internal.core.BundleHost.stopWorker(BundleHost.java:490)\n        at org.eclipse.osgi.framework.internal.core.Bundle.suspend(Bundle.java:546)\n        at\norg.eclipse.osgi.framework.internal.core.Framework.suspendBundle(Framework.java:1000)\n        at\norg.eclipse.osgi.framework.internal.core.StartLevelImpl.decFWSL(StartLevelImpl.java:626)\n        at\norg.eclipse.osgi.framework.internal.core.StartLevelImpl.doSetStartLevel(StartLevelImpl.java:277)\n        at\norg.eclipse.osgi.framework.internal.core.StartLevelImpl.shutdown(StartLevelImpl.java:250)\n        at\norg.eclipse.osgi.framework.internal.core.SystemBundle.suspend(SystemBundle.java:196)\n        at\norg.eclipse.osgi.framework.internal.core.Framework.shutdown(Framework.java:441)\n        at\norg.eclipse.osgi.framework.internal.core.SystemBundle$1.run(SystemBundle.java:181)\n        at java.lang.Thread.run(Thread.java:566)\n",
    "As an added note, I use the e-p-i-c perl editor, and it doesn\u0027t seem to be\npicking up features either ... is it possible that I am experiencing a problem\nwith the whole feature subsystem?",
    "It looks like a corrupted install to me, an you\u0027re running out of the cached \nplugins. \nTry installing it clean and see if that fixes the problem.",
    "Yup.  Invalid is so much more polite than \"The User Is An Idiot\".\nI can\u0027t believe that I forgot and also wasted your time.  Thanks.",
    ":-)",
    "*** Bug 58058 has been marked as a duplicate of this bug. ***"
  ],
  "commentCreationDates": [
    "2004-03-31T18:19:23+02:00",
    "2004-03-31T20:20:44+02:00",
    "2004-03-31T20:29:39+02:00",
    "2004-03-31T20:30:00+02:00",
    "2004-03-31T20:31:26+02:00",
    "2004-03-31T21:29:09+02:00",
    "2004-04-01T18:43:23+02:00",
    "2004-04-01T18:45:05+02:00",
    "2004-04-01T18:57:36+02:00",
    "2004-04-01T19:44:03+02:00",
    "2004-04-01T19:48:40+02:00",
    "2004-04-12T18:27:53+02:00"
  ],
  "traces": [
    {
      "exceptionType": "java.lang.NoClassDefFoundError",
      "message": "org/eclipse/update/internal/configurator/FeatureEntry",
      "elements": [
        {
          "method": "org.eclipse.update.internal.core.BaseSiteLocalFactory.createInstallConfigurationModel",
          "source": "BaseSiteLocalFactory.java:22"
        },
        {
          "method": "org.eclipse.update.internal.model.SiteLocalModel.processHistory",
          "source": "SiteLocalModel.java:250"
        },
        {
          "method": "org.eclipse.update.internal.model.SiteLocalModel.getConfigurationHistoryModel",
          "source": "SiteLocalModel.java:56"
        },
        {
          "method": "org.eclipse.update.internal.model.SiteLocalModel.resolve",
          "source": "SiteLocalModel.java:203"
        },
        {
          "method": "org.eclipse.update.internal.core.SiteLocal.internalGetLocalSite",
          "source": "SiteLocal.java:59"
        },
        {
          "method": "org.eclipse.update.internal.core.InternalSiteManager.internalGetLocalSite",
          "source": "InternalSiteManager.java:67"
        },
        {
          "method": "org.eclipse.update.internal.core.InternalSiteManager.getLocalSite",
          "source": "InternalSiteManager.java:52"
        },
        {
          "method": "org.eclipse.update.core.SiteManager.getLocalSite",
          "source": "SiteManager.java:126"
        },
        {
          "method": "org.eclipse.update.internal.ui.wizards.InstallWizard.addPages",
          "source": "InstallWizard.java:204"
        },
        {
          "method": "org.eclipse.jface.wizard.WizardDialog.createContents",
          "source": "WizardDialog.java:466"
        },
        {
          "method": "org.eclipse.jface.window.Window.create",
          "source": "Window.java:350"
        },
        {
          "method": "org.eclipse.jface.dialogs.Dialog.create",
          "source": "Dialog.java:859"
        },
        {
          "method": "org.eclipse.update.internal.ui.InstallWizardAction.openNewUpdatesWizard",
          "source": "InstallWizardAction.java:55"
        },
        {
          "method": "org.eclipse.update.internal.ui.InstallWizardAction.doRun",
          "source": "InstallWizardAction.java:49"
        },
        {
          "method": "org.eclipse.update.internal.ui.InstallWizardAction.access$0",
          "source": "InstallWizardAction.java:48"
        },
        {
          "method": "org.eclipse.update.internal.ui.InstallWizardAction$1.run",
          "source": "InstallWizardAction.java:43"
        },
        {
          "method": "org.eclipse.swt.custom.BusyIndicator.showWhile",
          "source": "BusyIndicator.java:84"
        },
        {
          "method": "org.eclipse.update.internal.ui.InstallWizardAction.run",
          "source": "InstallWizardAction.java:41"
        },
        {
          "method": "org.eclipse.ui.internal.PluginAction.runWithEvent",
          "source": "PluginAction.java:269"
        },
        {
          "method": "org.eclipse.ui.internal.WWinPluginAction.runWithEvent",
          "source": "WWinPluginAction.java:207"
        },
        {
          "method": "org.eclipse.jface.action.ActionContributionItem.handleWidgetSelection",
          "source": "ActionContributionItem.java:550"
        },
        {
          "method": "org.eclipse.jface.action.ActionContributionItem.access$2",
          "source": "ActionContributionItem.java:502"
        },
        {
          "method": "org.eclipse.jface.action.ActionContributionItem$5.handleEvent",
          "source": "ActionContributionItem.java:435"
        },
        {
          "method": "org.eclipse.swt.widgets.EventTable.sendEvent",
          "source": "EventTable.java:82"
        },
        {
          "method": "org.eclipse.swt.widgets.Widget.sendEvent",
          "source": "Widget.java:939"
        },
        {
          "method": "org.eclipse.swt.widgets.Display.runDeferredEvents",
          "source": "Display.java:1953"
        },
        {
          "method": "org.eclipse.swt.widgets.Display.readAndDispatch",
          "source": "Display.java:1726"
        },
        {
          "method": "org.eclipse.ui.internal.Workbench.runEventLoop",
          "source": "Workbench.java:1558"
        },
        {
          "method": "org.eclipse.ui.internal.Workbench.runUI",
          "source": "Workbench.java:1532"
        },
        {
          "method": "org.eclipse.ui.internal.Workbench.createAndRunWorkbench",
          "source": "Workbench.java:257"
        },
        {
          "method": "org.eclipse.ui.PlatformUI.createAndRunWorkbench",
          "source": "PlatformUI.java:139"
        },
        {
          "method": "org.eclipse.ui.internal.ide.IDEApplication.run",
          "source": "IDEApplication.java:90"
        },
        {
          "method": "org.eclipse.core.internal.runtime.PlatformActivator$1.run",
          "source": "PlatformActivator.java:277"
        },
        {
          "method": "org.eclipse.core.runtime.adaptor.EclipseStarter.run",
          "source": "EclipseStarter.java:241"
        },
        {
          "method": "org.eclipse.core.runtime.adaptor.EclipseStarter.run",
          "source": "EclipseStarter.java:117"
        },
        {
          "method": "sun.reflect.NativeMethodAccessorImpl.invoke0",
          "source": "Native Method"
        },
        {
          "method": "sun.reflect.NativeMethodAccessorImpl.invoke",
          "source": "NativeMethodAccessorImpl.java:39"
        },
        {
          "method": "sun.reflect.DelegatingMethodAccessorImpl.invoke",
          "source": "DelegatingMethodAccessorImpl.java:25"
        },
        {
          "method": "java.lang.reflect.Method.invoke",
          "source": "Method.java:494"
        },
        {
          "method": "org.eclipse.core.launcher.Main.basicRun",
          "source": "Main.java:267"
        },
        {
          "method": "org.eclipse.core.launcher.Main.run",
          "source": "Main.java:692"
        },
        {
          "method": "org.eclipse.core.launcher.Main.main",
          "source": "Main.java:676"
        }
      ],
      "number": 0,
      "commentIndex": 3,
      "bugId": "56937",
      "date": "2004-03-31T20:30:00+02:00",
      "product": "Platform",
      "component": "Update",
      "severity": "normal"
    },
    {
      "exceptionType": "java.lang.NullPointerException",
      "elements": [
        {
          "method": "org.eclipse.swt.widgets.Display.asyncExec",
          "source": "Display.java:483"
        },
        {
          "method": "org.eclipse.ui.progress.UIJob.run",
          "source": "UIJob.java:83"
        },
        {
          "method": "org.eclipse.core.internal.jobs.Worker.run",
          "source": "Worker.java:62"
        }
      ],
      "number": 1,
      "commentIndex": 3,
      "bugId": "56937",
      "date": "2004-03-31T20:30:00+02:00",
      "product": "Platform",
      "component": "Update",
      "severity": "normal"
    },
    {
      "exceptionType": "java.lang.NoClassDefFoundError",
      "message": "org/eclipse/update/internal/configurator/FeatureEntry",
      "elements": [
        {
          "method": "org.eclipse.update.internal.core.BaseSiteLocalFactory.createInstallConfigurationModel",
          "source": "BaseSiteLocalFactory.java:22"
        },
        {
          "method": "org.eclipse.update.internal.model.SiteLocalModel.processHistory",
          "source": "SiteLocalModel.java:250"
        },
        {
          "method": "org.eclipse.update.internal.model.SiteLocalModel.getConfigurationHistoryModel",
          "source": "SiteLocalModel.java:56"
        },
        {
          "method": "org.eclipse.update.internal.model.SiteLocalModel.resolve",
          "source": "SiteLocalModel.java:203"
        },
        {
          "method": "org.eclipse.update.internal.core.SiteLocal.internalGetLocalSite",
          "source": "SiteLocal.java:59"
        },
        {
          "method": "org.eclipse.update.internal.core.InternalSiteManager.internalGetLocalSite",
          "source": "InternalSiteManager.java:67"
        },
        {
          "method": "org.eclipse.update.internal.core.InternalSiteManager.getLocalSite",
          "source": "InternalSiteManager.java:52"
        },
        {
          "method": "org.eclipse.update.core.SiteManager.getLocalSite",
          "source": "SiteManager.java:126"
        },
        {
          "method": "org.eclipse.update.internal.ui.wizards.InstallWizard.addPages",
          "source": "InstallWizard.java:204"
        },
        {
          "method": "org.eclipse.jface.wizard.WizardDialog.createContents",
          "source": "WizardDialog.java:466"
        },
        {
          "method": "org.eclipse.jface.window.Window.create",
          "source": "Window.java:350"
        },
        {
          "method": "org.eclipse.jface.dialogs.Dialog.create",
          "source": "Dialog.java:859"
        },
        {
          "method": "org.eclipse.update.internal.ui.InstallWizardAction.openNewUpdatesWizard",
          "source": "InstallWizardAction.java:55"
        },
        {
          "method": "org.eclipse.update.internal.ui.InstallWizardAction.doRun",
          "source": "InstallWizardAction.java:49"
        },
        {
          "method": "org.eclipse.update.internal.ui.InstallWizardAction.access$0",
          "source": "InstallWizardAction.java:48"
        },
        {
          "method": "org.eclipse.update.internal.ui.InstallWizardAction$1.run",
          "source": "InstallWizardAction.java:43"
        },
        {
          "method": "org.eclipse.swt.custom.BusyIndicator.showWhile",
          "source": "BusyIndicator.java:84"
        },
        {
          "method": "org.eclipse.update.internal.ui.InstallWizardAction.run",
          "source": "InstallWizardAction.java:41"
        },
        {
          "method": "org.eclipse.ui.internal.PluginAction.runWithEvent",
          "source": "PluginAction.java:269"
        },
        {
          "method": "org.eclipse.ui.internal.WWinPluginAction.runWithEvent",
          "source": "WWinPluginAction.java:207"
        },
        {
          "method": "org.eclipse.jface.action.ActionContributionItem.handleWidgetSelection",
          "source": "ActionContributionItem.java:550"
        },
        {
          "method": "org.eclipse.jface.action.ActionContributionItem.access$2",
          "source": "ActionContributionItem.java:502"
        },
        {
          "method": "org.eclipse.jface.action.ActionContributionItem$5.handleEvent",
          "source": "ActionContributionItem.java:435"
        },
        {
          "method": "org.eclipse.swt.widgets.EventTable.sendEvent",
          "source": "EventTable.java:82"
        },
        {
          "method": "org.eclipse.swt.widgets.Widget.sendEvent",
          "source": "Widget.java:939"
        },
        {
          "method": "org.eclipse.swt.widgets.Display.runDeferredEvents",
          "source": "Display.java:1953"
        },
        {
          "method": "org.eclipse.swt.widgets.Display.readAndDispatch",
          "source": "Display.java:1726"
        },
        {
          "method": "org.eclipse.ui.internal.Workbench.runEventLoop",
          "source": "Workbench.java:1558"
        },
        {
          "method": "org.eclipse.ui.internal.Workbench.runUI",
          "source": "Workbench.java:1532"
        },
        {
          "method": "org.eclipse.ui.internal.Workbench.createAndRunWorkbench",
          "source": "Workbench.java:257"
        },
        {
          "method": "org.eclipse.ui.PlatformUI.createAndRunWorkbench",
          "source": "PlatformUI.java:139"
        },
        {
          "method": "org.eclipse.ui.internal.ide.IDEApplication.run",
          "source": "IDEApplication.java:90"
        },
        {
          "method": "org.eclipse.core.internal.runtime.PlatformActivator$1.run",
          "source": "PlatformActivator.java:277"
        },
        {
          "method": "org.eclipse.core.runtime.adaptor.EclipseStarter.run",
          "source": "EclipseStarter.java:241"
        },
        {
          "method": "org.eclipse.core.runtime.adaptor.EclipseStarter.run",
          "source": "EclipseStarter.java:117"
        },
        {
          "method": "sun.reflect.NativeMethodAccessorImpl.invoke0",
          "source": "Native Method"
        },
        {
          "method": "sun.reflect.NativeMethodAccessorImpl.invoke",
          "source": "NativeMethodAccessorImpl.java:39"
        },
        {
          "method": "sun.reflect.DelegatingMethodAccessorImpl.invoke",
          "source": "DelegatingMethodAccessorImpl.java:25"
        },
        {
          "method": "java.lang.reflect.Method.invoke",
          "source": "Method.java:494"
        },
        {
          "method": "org.eclipse.core.launcher.Main.basicRun",
          "source": "Main.java:267"
        },
        {
          "method": "org.eclipse.core.launcher.Main.run",
          "source": "Main.java:692"
        },
        {
          "method": "org.eclipse.core.launcher.Main.main",
          "source": "Main.java:676"
        }
      ],
      "number": 2,
      "commentIndex": 6,
      "bugId": "56937",
      "date": "2004-04-01T18:43:23+02:00",
      "product": "Platform",
      "component": "Update",
      "severity": "normal"
    },
    {
      "exceptionType": "org.osgi.framework.BundleException",
      "message": "Exception in [Ljava.lang.Object;@1635aad.java.lang.NullPointerException() of bundle \u003cmissing argument\u003e.",
      "elements": [
        {
          "method": "org.eclipse.osgi.framework.internal.core.BundleContext.stop",
          "source": "BundleContext.java:1044"
        },
        {
          "method": "org.eclipse.osgi.framework.internal.core.BundleHost.stopWorker",
          "source": "BundleHost.java:490"
        },
        {
          "method": "org.eclipse.osgi.framework.internal.core.Bundle.suspend",
          "source": "Bundle.java:546"
        },
        {
          "method": "org.eclipse.osgi.framework.internal.core.Framework.suspendBundle",
          "source": "Framework.java:1000"
        },
        {
          "method": "org.eclipse.osgi.framework.internal.core.StartLevelImpl.decFWSL",
          "source": "StartLevelImpl.java:626"
        },
        {
          "method": "org.eclipse.osgi.framework.internal.core.StartLevelImpl.doSetStartLevel",
          "source": "StartLevelImpl.java:277"
        },
        {
          "method": "org.eclipse.osgi.framework.internal.core.StartLevelImpl.shutdown",
          "source": "StartLevelImpl.java:250"
        },
        {
          "method": "org.eclipse.osgi.framework.internal.core.SystemBundle.suspend",
          "source": "SystemBundle.java:196"
        },
        {
          "method": "org.eclipse.osgi.framework.internal.core.Framework.shutdown",
          "source": "Framework.java:441"
        },
        {
          "method": "org.eclipse.osgi.framework.internal.core.SystemBundle$1.run",
          "source": "SystemBundle.java:181"
        },
        {
          "method": "java.lang.Thread.run",
          "source": "Thread.java:566"
        }
      ],
      "number": 3,
      "commentIndex": 6,
      "bugId": "56937",
      "date": "2004-04-01T18:43:23+02:00",
      "product": "Platform",
      "component": "Update",
      "severity": "normal"
    }
  ],
  "groupId": "56937",
  "bugId": "56937",
  "date": "2004-03-31T18:19:23+02:00",
  "product": "Platform",
  "component": "Update",
  "severity": "normal"
}