{
  "comments": [
    "build n0401, winxp, sun jdk 1.4.2\n\nNote that this is with the nightly build and most likely fixed in HEAD but I\nwanted to ensure that it was logged in case it has not been discovered yet.\n\n- download the nightly build\n- start eclipse\n- get the following stack trace in the console\n- all this is before the workspace launcher dialog is shown\n\n!SESSION Apr 01, 2004 14:04:44.787 ---------------------------------------------\n\njava.version\u003d1.4.2\njava.vendor\u003dSun Microsystems Inc.\nBootLoader constants: OS\u003dwin32, ARCH\u003dx86, WS\u003dwin32, NL\u003den_US\n!ENTRY org.eclipse.update.configurator Apr 01, 2004 14:04:44.787\n!MESSAGE Ignoring bundle at: reference:file:/c:/eclipse/dev/n0401/eclipse/plugin\ns/org.eclipse.core.runtime_3.0.0/\n!STACK 0\norg.osgi.framework.BundleException: A bundle with the unique ID and version is a\nlready installed: org.eclipse.core.runtime 3.0.0\n        at org.eclipse.osgi.framework.internal.core.Framework.installWorkerPrivi\nleged(Framework.java:736)\n        at org.eclipse.osgi.framework.internal.core.Framework$1.run(Framework.ja\nva:621)\n        at java.security.AccessController.doPrivileged(Native Method)\n        at org.eclipse.osgi.framework.internal.core.Framework.installWorker(Fram\nework.java:699)\n        at org.eclipse.osgi.framework.internal.core.Framework.installBundle(Fram\nework.java:616)\n        at org.eclipse.osgi.framework.internal.core.BundleContext.installBundle(\nBundleContext.java:207)\n        at org.eclipse.update.internal.configurator.ConfigurationActivator.insta\nllBundles(ConfigurationActivator.java:183)\n        at org.eclipse.update.internal.configurator.ConfigurationActivator.start\n(ConfigurationActivator.java:88)\n        at org.eclipse.osgi.framework.internal.core.BundleContext$1.run(BundleCo\nntext.java:992)\n        at java.security.AccessController.doPrivileged(Native Method)\n        at org.eclipse.osgi.framework.internal.core.BundleContext.startActivator\n(BundleContext.java:988)\n        at org.eclipse.osgi.framework.internal.core.BundleContext.start(BundleCo\nntext.java:971)\n        at org.eclipse.osgi.framework.internal.core.BundleHost.startWorker(Bundl\neHost.java:412)\n        at org.eclipse.osgi.framework.internal.core.Bundle.resume(Bundle.java:37\n7)\n        at org.eclipse.osgi.framework.internal.core.Framework.resumeBundle(Frame\nwork.java:980)\n        at org.eclipse.osgi.framework.internal.core.StartLevelImpl.resumeBundles\n(StartLevelImpl.java:565)\n        at org.eclipse.osgi.framework.internal.core.StartLevelImpl.incFWSL(Start\nLevelImpl.java:479)\n        at org.eclipse.osgi.framework.internal.core.StartLevelImpl.doSetStartLev\nel(StartLevelImpl.java:269)\n        at org.eclipse.osgi.framework.internal.core.StartLevelImpl.dispatchEvent\n(StartLevelImpl.java:439)\n        at org.eclipse.osgi.framework.eventmgr.ListenerList.dispatchEvent(Listen\nerList.java:135)\n        at org.eclipse.osgi.framework.eventmgr.EventThread$EventThreadItem.dispa\ntchEvent(EventThread.java:59)\n        at org.eclipse.osgi.framework.eventmgr.EventThread.run(EventThread.java:\n118)\n!ENTRY org.eclipse.update.configurator Apr 01, 2004 14:04:46.709\n!MESSAGE Ignoring bundle at: reference:file:/c:/eclipse/dev/n0401/eclipse/plugin\ns/org.eclipse.update.configurator_3.0.0/\n!STACK 0\norg.osgi.framework.BundleException: A bundle with the unique ID and version is a\nlready installed: org.eclipse.update.configurator 3.0.0\n        at org.eclipse.osgi.framework.internal.core.Framework.installWorkerPrivi\nleged(Framework.java:736)\n        at org.eclipse.osgi.framework.internal.core.Framework$1.run(Framework.ja\nva:621)\n        at java.security.AccessController.doPrivileged(Native Method)\n        at org.eclipse.osgi.framework.internal.core.Framework.installWorker(Fram\nework.java:699)\n        at org.eclipse.osgi.framework.internal.core.Framework.installBundle(Fram\nework.java:616)\n        at org.eclipse.osgi.framework.internal.core.BundleContext.installBundle(\nBundleContext.java:207)\n        at org.eclipse.update.internal.configurator.ConfigurationActivator.insta\nllBundles(ConfigurationActivator.java:183)\n        at org.eclipse.update.internal.configurator.ConfigurationActivator.start\n(ConfigurationActivator.java:88)\n        at org.eclipse.osgi.framework.internal.core.BundleContext$1.run(BundleCo\nntext.java:992)\n        at java.security.AccessController.doPrivileged(Native Method)\n        at org.eclipse.osgi.framework.internal.core.BundleContext.startActivator\n(BundleContext.java:988)\n        at org.eclipse.osgi.framework.internal.core.BundleContext.start(BundleCo\nntext.java:971)\n        at org.eclipse.osgi.framework.internal.core.BundleHost.startWorker(Bundl\neHost.java:412)\n        at org.eclipse.osgi.framework.internal.core.Bundle.resume(Bundle.java:37\n7)\n        at org.eclipse.osgi.framework.internal.core.Framework.resumeBundle(Frame\nwork.java:980)\n        at org.eclipse.osgi.framework.internal.core.StartLevelImpl.resumeBundles\n(StartLevelImpl.java:565)\n        at org.eclipse.osgi.framework.internal.core.StartLevelImpl.incFWSL(Start\nLevelImpl.java:479)\n        at org.eclipse.osgi.framework.internal.core.StartLevelImpl.doSetStartLev\nel(StartLevelImpl.java:269)\n        at org.eclipse.osgi.framework.internal.core.StartLevelImpl.dispatchEvent\n(StartLevelImpl.java:439)\n        at org.eclipse.osgi.framework.eventmgr.ListenerList.dispatchEvent(Listen\nerList.java:135)\n        at org.eclipse.osgi.framework.eventmgr.EventThread$EventThreadItem.dispa\ntchEvent(EventThread.java:59)\n        at org.eclipse.osgi.framework.eventmgr.EventThread.run(EventThread.java:\n118)",
    "I saw this too.  Although I was just running with the code from HEAD while self-\nhosting.  I think it is an update.configurator problem.  If I import \nupdate.configurator from the I-Build into my self-hosting environment then the \nproblem goes away.",
    "This means that Update is reinstalling runtime and update.configurator during\nthe first startup.\n\nMoving to Update for comments.",
    "This is caused by Core/Equinox bug 51165:\n\nThe update configurator has some workaround code in a few places, and can add \nsome more, but we should get the proper fix from the runtime.\n\nWhat happens is that the bundles that are automatically started based on \nosgi.bundles entry, have a url of the form\nreference:file:d:/some/path, but the bundles the configurator installs have \nthe form\nreference:file:/d:/some/path (note the leading / after file: )\nwhich is consistent with java.io.File.toURL().\nIt appears that Platform.asLocalURL() and some other places in the runtime \nmanually create these bundle url\u0027s as opposed to using the jdk to generate the \nurl.\nMoving to equinox for comments regarding the bundle url\u0027s.\n\n",
    "ultimately  both URLs are correct and valid and indicate the same location.  We \nare pretty much damned if we do, damned if we don\u0027t.  There are bug reports \nfloating around saying that we should NOT have the leading /.  here we are \ntalking about adding a leading /.  I honestly don\u0027t know what the right answer \nis.  Consistency will help but is bound to make someone unhappy.  Thoughts?\n",
    "moving this to update.  If update is going to test on location then it has to \nbe prepared to get equivalent URLs which take different forms.  For exmaple, \ncomparing file: URLs is best done by creating File objects and comparing them.\n",
    "I think this particular problem has been fixed recently, but the general issue \n(comparing File\u0027s) is still valid.",
    "Closing this, as we no longer log the install errors for automatically started \nbundles (such as osgi*, runtime, and update.configurator)"
  ],
  "commentCreationDates": [
    "2004-04-01T20:12:45+02:00",
    "2004-04-01T20:19:52+02:00",
    "2004-04-01T20:27:56+02:00",
    "2004-04-01T20:49:31+02:00",
    "2004-04-01T21:02:55+02:00",
    "2004-04-21T03:58:40+02:00",
    "2004-04-21T04:16:46+02:00",
    "2004-05-05T05:55:25+02:00"
  ],
  "traces": [
    {
      "exceptionType": "org.osgi.framework.BundleException",
      "message": "A bundle with the unique ID and version is a lready installed: org.eclipse.core.runtime 3.0.0",
      "elements": [
        {
          "method": "org.eclipse.osgi.framework.internal.core.Framework.installWorkerPrivileged",
          "source": "Framework.java:736"
        },
        {
          "method": "org.eclipse.osgi.framework.internal.core.Framework$1.run",
          "source": "Framework.ja va:621"
        },
        {
          "method": "java.security.AccessController.doPrivileged",
          "source": "Native Method"
        },
        {
          "method": "org.eclipse.osgi.framework.internal.core.Framework.installWorker",
          "source": "Fram ework.java:699"
        },
        {
          "method": "org.eclipse.osgi.framework.internal.core.Framework.installBundle",
          "source": "Fram ework.java:616"
        },
        {
          "method": "org.eclipse.osgi.framework.internal.core.BundleContext.installBundle",
          "source": " BundleContext.java:207"
        },
        {
          "method": "org.eclipse.update.internal.configurator.ConfigurationActivator.installBundles",
          "source": "ConfigurationActivator.java:183"
        },
        {
          "method": "org.eclipse.update.internal.configurator.ConfigurationActivator.start",
          "source": "ConfigurationActivator.java:88"
        },
        {
          "method": "org.eclipse.osgi.framework.internal.core.BundleContext$1.run",
          "source": "BundleCo ntext.java:992"
        },
        {
          "method": "java.security.AccessController.doPrivileged",
          "source": "Native Method"
        },
        {
          "method": "org.eclipse.osgi.framework.internal.core.BundleContext.startActivator",
          "source": "BundleContext.java:988"
        },
        {
          "method": "org.eclipse.osgi.framework.internal.core.BundleContext.start",
          "source": "BundleCo ntext.java:971"
        },
        {
          "method": "org.eclipse.osgi.framework.internal.core.BundleHost.startWorker",
          "source": "Bundl eHost.java:412"
        },
        {
          "method": "org.eclipse.osgi.framework.internal.core.Bundle.resume",
          "source": "Bundle.java:37 7"
        },
        {
          "method": "org.eclipse.osgi.framework.internal.core.Framework.resumeBundle",
          "source": "Frame work.java:980"
        },
        {
          "method": "org.eclipse.osgi.framework.internal.core.StartLevelImpl.resumeBundles",
          "source": "StartLevelImpl.java:565"
        },
        {
          "method": "org.eclipse.osgi.framework.internal.core.StartLevelImpl.incFWSL",
          "source": "Start LevelImpl.java:479"
        },
        {
          "method": "org.eclipse.osgi.framework.internal.core.StartLevelImpl.doSetStartLevel",
          "source": "StartLevelImpl.java:269"
        },
        {
          "method": "org.eclipse.osgi.framework.internal.core.StartLevelImpl.dispatchEvent",
          "source": "StartLevelImpl.java:439"
        },
        {
          "method": "org.eclipse.osgi.framework.eventmgr.ListenerList.dispatchEvent",
          "source": "Listen erList.java:135"
        },
        {
          "method": "org.eclipse.osgi.framework.eventmgr.EventThread$EventThreadItem.dispatchEvent",
          "source": "EventThread.java:59"
        },
        {
          "method": "org.eclipse.osgi.framework.eventmgr.EventThread.run",
          "source": "EventThread.java: 118"
        }
      ],
      "number": 0,
      "commentIndex": 0,
      "bugId": "57077",
      "date": "2004-04-01T20:12:45+02:00",
      "product": "Platform",
      "component": "Update",
      "severity": "normal"
    },
    {
      "exceptionType": "org.osgi.framework.BundleException",
      "message": "A bundle with the unique ID and version is a lready installed: org.eclipse.update.configurator 3.0.0",
      "elements": [
        {
          "method": "org.eclipse.osgi.framework.internal.core.Framework.installWorkerPrivileged",
          "source": "Framework.java:736"
        },
        {
          "method": "org.eclipse.osgi.framework.internal.core.Framework$1.run",
          "source": "Framework.ja va:621"
        },
        {
          "method": "java.security.AccessController.doPrivileged",
          "source": "Native Method"
        },
        {
          "method": "org.eclipse.osgi.framework.internal.core.Framework.installWorker",
          "source": "Fram ework.java:699"
        },
        {
          "method": "org.eclipse.osgi.framework.internal.core.Framework.installBundle",
          "source": "Fram ework.java:616"
        },
        {
          "method": "org.eclipse.osgi.framework.internal.core.BundleContext.installBundle",
          "source": " BundleContext.java:207"
        },
        {
          "method": "org.eclipse.update.internal.configurator.ConfigurationActivator.installBundles",
          "source": "ConfigurationActivator.java:183"
        },
        {
          "method": "org.eclipse.update.internal.configurator.ConfigurationActivator.start",
          "source": "ConfigurationActivator.java:88"
        },
        {
          "method": "org.eclipse.osgi.framework.internal.core.BundleContext$1.run",
          "source": "BundleCo ntext.java:992"
        },
        {
          "method": "java.security.AccessController.doPrivileged",
          "source": "Native Method"
        },
        {
          "method": "org.eclipse.osgi.framework.internal.core.BundleContext.startActivator",
          "source": "BundleContext.java:988"
        },
        {
          "method": "org.eclipse.osgi.framework.internal.core.BundleContext.start",
          "source": "BundleCo ntext.java:971"
        },
        {
          "method": "org.eclipse.osgi.framework.internal.core.BundleHost.startWorker",
          "source": "Bundl eHost.java:412"
        },
        {
          "method": "org.eclipse.osgi.framework.internal.core.Bundle.resume",
          "source": "Bundle.java:37 7"
        },
        {
          "method": "org.eclipse.osgi.framework.internal.core.Framework.resumeBundle",
          "source": "Frame work.java:980"
        },
        {
          "method": "org.eclipse.osgi.framework.internal.core.StartLevelImpl.resumeBundles",
          "source": "StartLevelImpl.java:565"
        },
        {
          "method": "org.eclipse.osgi.framework.internal.core.StartLevelImpl.incFWSL",
          "source": "Start LevelImpl.java:479"
        },
        {
          "method": "org.eclipse.osgi.framework.internal.core.StartLevelImpl.doSetStartLevel",
          "source": "StartLevelImpl.java:269"
        },
        {
          "method": "org.eclipse.osgi.framework.internal.core.StartLevelImpl.dispatchEvent",
          "source": "StartLevelImpl.java:439"
        },
        {
          "method": "org.eclipse.osgi.framework.eventmgr.ListenerList.dispatchEvent",
          "source": "Listen erList.java:135"
        },
        {
          "method": "org.eclipse.osgi.framework.eventmgr.EventThread$EventThreadItem.dispatchEvent",
          "source": "EventThread.java:59"
        },
        {
          "method": "org.eclipse.osgi.framework.eventmgr.EventThread.run",
          "source": "EventThread.java: 118"
        }
      ],
      "number": 1,
      "commentIndex": 0,
      "bugId": "57077",
      "date": "2004-04-01T20:12:45+02:00",
      "product": "Platform",
      "component": "Update",
      "severity": "normal"
    }
  ],
  "groupId": "57077",
  "bugId": "57077",
  "date": "2004-04-01T20:12:45+02:00",
  "product": "Platform",
  "component": "Update",
  "severity": "normal"
}