{
  "comments": [
    "I20030330\n\nI don\u0027t know what triggered the exception.\n\n!MESSAGE org/eclipse/debug/internal/ui/views/variables/VariablesView\nincompatible with org/eclipse/ui/IEditorPart\n!STACK 0\njava.lang.ClassCastException:\norg/eclipse/debug/internal/ui/views/variables/VariablesView incompatible with\norg/eclipse/ui/IEditorPart\n        at java.lang.Throwable.\u003cinit\u003e(Throwable.java)\n        at java.lang.Throwable.\u003cinit\u003e(Throwable.java)\n        at java.lang.ClassCastException.\u003cinit\u003e(ClassCastException.java:53)\n        at\norg.eclipse.jdt.internal.debug.ui.actions.ToggleBreakpointAdapter.toggleLineBreakpoints(ToggleBreakpointAdapter.java:131)\n        at\norg.eclipse.debug.internal.ui.actions.RetargetToggleLineBreakpointAction.performAction(RetargetToggleLineBreakpointAction.java:30)\n        at\norg.eclipse.debug.internal.ui.actions.RetargetAction.run(RetargetAction.java:96)\n        at org.eclipse.ui.internal.PluginAction.runWithEvent(PluginAction.java:269)\n        at\norg.eclipse.ui.internal.WWinPluginAction.runWithEvent(WWinPluginAction.java:207)\n        at\norg.eclipse.jface.action.ActionContributionItem.handleWidgetSelection(ActionContributionItem.java:550)\n        at\norg.eclipse.jface.action.ActionContributionItem.access$2(ActionContributionItem.java)\n        at\norg.eclipse.jface.action.ActionContributionItem$5.handleEvent(ActionContributionItem.java)\n        at org.eclipse.swt.widgets.EventTable.sendEvent(EventTable.java)\n        at org.eclipse.swt.widgets.Widget.sendEvent(Widget.java)\n        at org.eclipse.swt.widgets.Display.runDeferredEvents(Display.java)\n        at org.eclipse.swt.widgets.Display.readAndDispatch(Display.java)\n        at org.eclipse.ui.internal.Workbench.runEventLoop(Workbench.java:1558)\n        at org.eclipse.ui.internal.Workbench.runUI(Workbench.java:1532)\n        at\norg.eclipse.ui.internal.Workbench.createAndRunWorkbench(Workbench.java:257)\n        at org.eclipse.ui.PlatformUI.createAndRunWorkbench(PlatformUI.java:139)\n        at org.eclipse.ui.internal.ide.IDEApplication.run(IDEApplication.java:90)\n        at\norg.eclipse.core.internal.runtime.PlatformActivator$1.run(PlatformActivator.java:277)\n        at\norg.eclipse.core.runtime.adaptor.EclipseStarter.run(EclipseStarter.java:241)\n        at\norg.eclipse.core.runtime.adaptor.EclipseStarter.run(EclipseStarter.java:117)\n        at sun.reflect.NativeMethodAccessorImpl.invoke0(Native Method)\n        at\nsun.reflect.NativeMethodAccessorImpl.invoke(NativeMethodAccessorImpl.java:79)\n        at\nsun.reflect.DelegatingMethodAccessorImpl.invoke(DelegatingMethodAccessorImpl.java:41)\n        at java.lang.reflect.Method.invoke(Method.java:386)\n        at org.eclipse.core.launcher.Main.basicRun(Main.java:267)\n        at org.eclipse.core.launcher.Main.run(Main.java:692)\n        at org.eclipse.core.launcher.Main.main(Main.java:676)",
    "Unable to reproduce. Could have been related to key binding bugs."
  ],
  "commentCreationDates": [
    "2004-04-05T20:04:20+02:00",
    "2004-05-10T18:20:31+02:00"
  ],
  "traces": [
    {
      "exceptionType": "java.lang.ClassCastException",
      "message": "org/eclipse/debug/internal/ui/views/variables/VariablesView incompatible with org/eclipse/ui/IEditorPart",
      "elements": [
        {
          "method": "java.lang.Throwable.\u003cinit\u003e",
          "source": "Throwable.java"
        },
        {
          "method": "java.lang.Throwable.\u003cinit\u003e",
          "source": "Throwable.java"
        },
        {
          "method": "java.lang.ClassCastException.\u003cinit\u003e",
          "source": "ClassCastException.java:53"
        },
        {
          "method": "org.eclipse.jdt.internal.debug.ui.actions.ToggleBreakpointAdapter.toggleLineBreakpoints",
          "source": "ToggleBreakpointAdapter.java:131"
        },
        {
          "method": "org.eclipse.debug.internal.ui.actions.RetargetToggleLineBreakpointAction.performAction",
          "source": "RetargetToggleLineBreakpointAction.java:30"
        },
        {
          "method": "org.eclipse.debug.internal.ui.actions.RetargetAction.run",
          "source": "RetargetAction.java:96"
        },
        {
          "method": "org.eclipse.ui.internal.PluginAction.runWithEvent",
          "source": "PluginAction.java:269"
        },
        {
          "method": "org.eclipse.ui.internal.WWinPluginAction.runWithEvent",
          "source": "WWinPluginAction.java:207"
        },
        {
          "method": "org.eclipse.jface.action.ActionContributionItem.handleWidgetSelection",
          "source": "ActionContributionItem.java:550"
        },
        {
          "method": "org.eclipse.jface.action.ActionContributionItem.access$2",
          "source": "ActionContributionItem.java"
        },
        {
          "method": "org.eclipse.jface.action.ActionContributionItem$5.handleEvent",
          "source": "ActionContributionItem.java"
        },
        {
          "method": "org.eclipse.swt.widgets.EventTable.sendEvent",
          "source": "EventTable.java"
        },
        {
          "method": "org.eclipse.swt.widgets.Widget.sendEvent",
          "source": "Widget.java"
        },
        {
          "method": "org.eclipse.swt.widgets.Display.runDeferredEvents",
          "source": "Display.java"
        },
        {
          "method": "org.eclipse.swt.widgets.Display.readAndDispatch",
          "source": "Display.java"
        },
        {
          "method": "org.eclipse.ui.internal.Workbench.runEventLoop",
          "source": "Workbench.java:1558"
        },
        {
          "method": "org.eclipse.ui.internal.Workbench.runUI",
          "source": "Workbench.java:1532"
        },
        {
          "method": "org.eclipse.ui.internal.Workbench.createAndRunWorkbench",
          "source": "Workbench.java:257"
        },
        {
          "method": "org.eclipse.ui.PlatformUI.createAndRunWorkbench",
          "source": "PlatformUI.java:139"
        },
        {
          "method": "org.eclipse.ui.internal.ide.IDEApplication.run",
          "source": "IDEApplication.java:90"
        },
        {
          "method": "org.eclipse.core.internal.runtime.PlatformActivator$1.run",
          "source": "PlatformActivator.java:277"
        },
        {
          "method": "org.eclipse.core.runtime.adaptor.EclipseStarter.run",
          "source": "EclipseStarter.java:241"
        },
        {
          "method": "org.eclipse.core.runtime.adaptor.EclipseStarter.run",
          "source": "EclipseStarter.java:117"
        },
        {
          "method": "sun.reflect.NativeMethodAccessorImpl.invoke0",
          "source": "Native Method"
        },
        {
          "method": "sun.reflect.NativeMethodAccessorImpl.invoke",
          "source": "NativeMethodAccessorImpl.java:79"
        },
        {
          "method": "sun.reflect.DelegatingMethodAccessorImpl.invoke",
          "source": "DelegatingMethodAccessorImpl.java:41"
        },
        {
          "method": "java.lang.reflect.Method.invoke",
          "source": "Method.java:386"
        },
        {
          "method": "org.eclipse.core.launcher.Main.basicRun",
          "source": "Main.java:267"
        },
        {
          "method": "org.eclipse.core.launcher.Main.run",
          "source": "Main.java:692"
        },
        {
          "method": "org.eclipse.core.launcher.Main.main",
          "source": "Main.java:676"
        }
      ],
      "number": 0,
      "commentIndex": 0,
      "bugId": "57492",
      "date": "2004-04-05T20:04:20+02:00",
      "product": "JDT",
      "component": "Debug",
      "severity": "normal"
    }
  ],
  "groupId": "57492",
  "bugId": "57492",
  "date": "2004-04-05T20:04:20+02:00",
  "product": "JDT",
  "component": "Debug",
  "severity": "normal"
}