{
  "comments": [
    "Build 20040406 + fresh workspace\n\nTrying to open the update manager in help menu:\n\nUnhandled Exception\nReason:\nUnable to execute early startup code for a startup extension in plugin \norg.eclipse.update.scheduler\nUnhandled event loop exception\nReason:\norg/eclipse/update/operations/IOperationListener",
    "At what point did you see this error?\nThere has been a recent change in the automatic startup code for update, but \nthings seem to work fine on mu 0406 installation.\nCan you provide the exact steps to reproduce the problem? Thanks",
    "I expanded SDK, and launched it on new workspace \u0027workspace\u0027 located as a \nsibling of eclipse install folder.\n\nWith -consoleLog open, I got the following output:\n!SESSION Apr 06, 2004 21:48:01.638 ---------------------------------------------\njava.version\u003d1.4.2_02\njava.vendor\u003dSun Microsystems Inc.\nBootLoader constants: OS\u003dwin32, ARCH\u003dx86, WS\u003dwin32, NL\u003den_US\n!ENTRY org.eclipse.core.runtime 4 2 Apr 06, 2004 21:48:01.648\n!MESSAGE Problems occurred when invoking code from plug-\nin: \"org.eclipse.core.runtime\".\n!STACK 0\njava.lang.NoClassDefFoundError: \norg/eclipse/update/search/IUpdateSearchResultCollector\n        at java.lang.ClassLoader.defineClass0(Native Method)\n        at java.lang.ClassLoader.defineClass(ClassLoader.java:537)\n        at \norg.eclipse.osgi.framework.internal.defaultadaptor.DefaultClassLoader.defineClas\ns(DefaultClassLoader.java:309)\n        at org.eclipse.core.runtime.adaptor.EclipseClassLoader.defineClass\n(EclipseClassLoader.java:175)\n        at \norg.eclipse.osgi.framework.internal.defaultadaptor.DefaultClassLoader.findClassI\nmpl(DefaultClassLoader.java:298)\n        at \norg.eclipse.osgi.framework.internal.defaultadaptor.DefaultClassLoader.findClass\n(DefaultClassLoader.java:187)\n        at \norg.eclipse.osgi.framework.adaptor.core.AbstractClassLoader.findLocalClass\n(AbstractClassLoader.java:243)\n        at org.eclipse.core.runtime.adaptor.EclipseClassLoader.findLocalClass\n(EclipseClassLoader.java:104)\n        at org.eclipse.osgi.framework.internal.core.BundleLoader.findLocalClass\n(BundleLoader.java:370)\n        at org.eclipse.osgi.framework.internal.core.BundleLoader.findClass\n(BundleLoader.java:401)\n        at org.eclipse.osgi.framework.adaptor.core.AbstractClassLoader.loadClass\n(AbstractClassLoader.java:116)\n        at java.lang.ClassLoader.loadClass(ClassLoader.java:235)\n        at java.lang.ClassLoader.loadClassInternal(ClassLoader.java:302)\n        at java.lang.Class.getDeclaredConstructors0(Native Method)\n        at java.lang.Class.privateGetDeclaredConstructors(Class.java:1610)\n        at java.lang.Class.getConstructor0(Class.java:1922)\n        at java.lang.Class.newInstance0(Class.java:278)\n        at java.lang.Class.newInstance(Class.java:261)\n        at \norg.eclipse.core.internal.registry.ConfigurationElement.createExecutableExtensio\nn(ConfigurationElement.java:140)\n        at \norg.eclipse.core.internal.registry.ConfigurationElement.createExecutableExtensio\nn(ConfigurationElement.java:125)\n        at \norg.eclipse.core.internal.registry.ConfigurationElement.createExecutableExtensio\nn(ConfigurationElement.java:114)\n        at org.eclipse.ui.internal.WorkbenchPlugin$1.run\n(WorkbenchPlugin.java:188)\n        at org.eclipse.swt.custom.BusyIndicator.showWhile(BusyIndicator.java:51)\n        at org.eclipse.ui.internal.WorkbenchPlugin.createExtension\n(WorkbenchPlugin.java:185)\n        at \norg.eclipse.ui.internal.Workbench$EarlyStartupRunnable.getExecutableExtension\n(Workbench.java:1436)\n        at org.eclipse.ui.internal.Workbench$EarlyStartupRunnable.run\n(Workbench.java:1378)\n        at org.eclipse.core.internal.runtime.InternalPlatform.run\n(InternalPlatform.java:607)\n        at org.eclipse.core.runtime.Platform.run(Platform.java:524)\n        at org.eclipse.ui.internal.Workbench$16.run(Workbench.java:1350)\n        at java.lang.Thread.run(Thread.java:534)\n!ENTRY org.eclipse.ui 4 4 Apr 06, 2004 21:48:01.718\n!MESSAGE Unhandled Exception\nUnhandled Exception\nReason:\n!ENTRY org.eclipse.update.scheduler 4 0 Apr 06, 2004 21:48:01.738\n!MESSAGE Unable to execute early startup code for a startup extension in plugin \norg.eclipse.update.scheduler\n!STACK 0\njava.lang.NoClassDefFoundError: \norg/eclipse/update/search/IUpdateSearchResultCollector\n        at java.lang.ClassLoader.defineClass0(Native Method)\n        at java.lang.ClassLoader.defineClass(ClassLoader.java:537)\n        at \norg.eclipse.osgi.framework.internal.defaultadaptor.DefaultClassLoader.defineClas\ns(DefaultClassLoader.java:309)\n        at org.eclipse.core.runtime.adaptor.EclipseClassLoader.defineClass\n(EclipseClassLoader.java:175)\n        at \norg.eclipse.osgi.framework.internal.defaultadaptor.DefaultClassLoader.findClassI\nmpl(DefaultClassLoader.java:298)\n        at \norg.eclipse.osgi.framework.internal.defaultadaptor.DefaultClassLoader.findClass\n(DefaultClassLoader.java:187)\n        at \norg.eclipse.osgi.framework.adaptor.core.AbstractClassLoader.findLocalClass\n(AbstractClassLoader.java:243)\n        at org.eclipse.core.runtime.adaptor.EclipseClassLoader.findLocalClass\n(EclipseClassLoader.java:104)\n        at org.eclipse.osgi.framework.internal.core.BundleLoader.findLocalClass\n(BundleLoader.java:370)\n        at org.eclipse.osgi.framework.internal.core.BundleLoader.findClass\n(BundleLoader.java:401)\n        at org.eclipse.osgi.framework.adaptor.core.AbstractClassLoader.loadClass\n(AbstractClassLoader.java:116)\n        at java.lang.ClassLoader.loadClass(ClassLoader.java:235)\n        at java.lang.ClassLoader.loadClassInternal(ClassLoader.java:302)\n        at java.lang.Class.getDeclaredConstructors0(Native Method)\n        at java.lang.Class.privateGetDeclaredConstructors(Class.java:1610)\n        at java.lang.Class.getConstructor0(Class.java:1922)\n        at java.lang.Class.newInstance0(Class.java:278)\n        at java.lang.Class.newInstance(Class.java:261)\n        at \norg.eclipse.core.internal.registry.ConfigurationElement.createExecutableExtensio\nn(ConfigurationElement.java:140)\n        at \norg.eclipse.core.internal.registry.ConfigurationElement.createExecutableExtensio\nn(ConfigurationElement.java:125)\n        at \norg.eclipse.core.internal.registry.ConfigurationElement.createExecutableExtensio\nn(ConfigurationElement.java:114)\n        at org.eclipse.ui.internal.WorkbenchPlugin$1.run\n(WorkbenchPlugin.java:188)\n        at org.eclipse.swt.custom.BusyIndicator.showWhile(BusyIndicator.java:51)\n        at org.eclipse.ui.internal.WorkbenchPlugin.createExtension\n(WorkbenchPlugin.java:185)\n        at \norg.eclipse.ui.internal.Workbench$EarlyStartupRunnable.getExecutableExtension\n(Workbench.java:1436)\n        at org.eclipse.ui.internal.Workbench$EarlyStartupRunnable.run\n(Workbench.java:1378)\n        at org.eclipse.core.internal.runtime.InternalPlatform.run\n(InternalPlatform.java:607)\n        at org.eclipse.core.runtime.Platform.run(Platform.java:524)\n        at org.eclipse.ui.internal.Workbench$16.run(Workbench.java:1350)\n        at java.lang.Thread.run(Thread.java:534)\nUnable to execute early startup code for a startup extension in plugin \norg.eclipse.update.scheduler\n!ENTRY org.eclipse.ui 4 4 Apr 06, 2004 21:48:45.331\n!MESSAGE Unhandled event loop exception\nUnhandled event loop exception\nReason:\n!ENTRY org.eclipse.ui 4 0 Apr 06, 2004 21:48:45.341\n!MESSAGE org/eclipse/update/operations/IOperationListener\n!STACK 0\njava.lang.NoClassDefFoundError: org/eclipse/update/operations/IOperationListener\n        at java.lang.ClassLoader.defineClass0(Native Method)\n        at java.lang.ClassLoader.defineClass(ClassLoader.java:537)\n        at \norg.eclipse.osgi.framework.internal.defaultadaptor.DefaultClassLoader.defineClas\ns(DefaultClassLoader.java:309)\n        at org.eclipse.core.runtime.adaptor.EclipseClassLoader.defineClass\n(EclipseClassLoader.java:175)\n        at \norg.eclipse.osgi.framework.internal.defaultadaptor.DefaultClassLoader.findClassI\nmpl(DefaultClassLoader.java:298)\n        at \norg.eclipse.osgi.framework.internal.defaultadaptor.DefaultClassLoader.findClass\n(DefaultClassLoader.java:187)\n        at \norg.eclipse.osgi.framework.adaptor.core.AbstractClassLoader.findLocalClass\n(AbstractClassLoader.java:243)\n        at org.eclipse.core.runtime.adaptor.EclipseClassLoader.findLocalClass\n(EclipseClassLoader.java:104)\n        at org.eclipse.osgi.framework.internal.core.BundleLoader.findLocalClass\n(BundleLoader.java:370)\n        at org.eclipse.osgi.framework.internal.core.BundleLoader.findClass\n(BundleLoader.java:401)\n        at org.eclipse.osgi.framework.adaptor.core.AbstractClassLoader.loadClass\n(AbstractClassLoader.java:116)\n        at java.lang.ClassLoader.loadClass(ClassLoader.java:235)\n        at java.lang.ClassLoader.loadClassInternal(ClassLoader.java:302)\n        at \norg.eclipse.update.internal.ui.InstallWizardAction.openNewUpdatesWizard\n(InstallWizardAction.java:54)\n        at org.eclipse.update.internal.ui.InstallWizardAction.doRun\n(InstallWizardAction.java:50)\n        at org.eclipse.update.internal.ui.InstallWizardAction.access$0\n(InstallWizardAction.java:49)\n        at org.eclipse.update.internal.ui.InstallWizardAction$1.run\n(InstallWizardAction.java:44)\n        at org.eclipse.swt.custom.BusyIndicator.showWhile(BusyIndicator.java:84)\n        at org.eclipse.update.internal.ui.InstallWizardAction.run\n(InstallWizardAction.java:42)\n        at org.eclipse.ui.internal.PluginAction.runWithEvent\n(PluginAction.java:269)\n        at org.eclipse.ui.internal.WWinPluginAction.runWithEvent\n(WWinPluginAction.java:207)\n        at org.eclipse.jface.action.ActionContributionItem.handleWidgetSelection\n(ActionContributionItem.java:550)\n        at org.eclipse.jface.action.ActionContributionItem.access$2\n(ActionContributionItem.java:502)\n        at org.eclipse.jface.action.ActionContributionItem$5.handleEvent\n(ActionContributionItem.java:435)\n        at org.eclipse.swt.widgets.EventTable.sendEvent(EventTable.java:82)\n        at org.eclipse.swt.widgets.Widget.sendEvent(Widget.java:769)\n        at org.eclipse.swt.widgets.Display.runDeferredEvents(Display.java:2587)\n        at org.eclipse.swt.widgets.Display.readAndDispatch(Display.java:2265)\n        at org.eclipse.ui.internal.Workbench.runEventLoop(Workbench.java:1561)\n        at org.eclipse.ui.internal.Workbench.runUI(Workbench.java:1532)\n        at org.eclipse.ui.internal.Workbench.createAndRunWorkbench\n(Workbench.java:257)\n        at org.eclipse.ui.PlatformUI.createAndRunWorkbench(PlatformUI.java:140)\n        at org.eclipse.ui.internal.ide.IDEApplication.run\n(IDEApplication.java:90)\n        at org.eclipse.core.internal.runtime.PlatformActivator$1.run\n(PlatformActivator.java:279)\n        at org.eclipse.core.runtime.adaptor.EclipseStarter.run\n(EclipseStarter.java:241)\n        at org.eclipse.core.runtime.adaptor.EclipseStarter.run\n(EclipseStarter.java:117)\n        at sun.reflect.NativeMethodAccessorImpl.invoke0(Native Method)\n        at sun.reflect.NativeMethodAccessorImpl.invoke\n(NativeMethodAccessorImpl.java:39)\n        at sun.reflect.DelegatingMethodAccessorImpl.invoke\n(DelegatingMethodAccessorImpl.java:25)\n        at java.lang.reflect.Method.invoke(Method.java:324)\n        at org.eclipse.core.launcher.Main.basicRun(Main.java:267)\n        at org.eclipse.core.launcher.Main.run(Main.java:692)\n        at org.eclipse.core.launcher.Main.main(Main.java:676)\norg/eclipse/update/operations/IOperationListener\n\n\n",
    "Redownloaded integration build again. Installed and started it.\nGot the following during startup. Update manager is dead again.\n\n!SESSION Apr 06, 2004 23:45:29.752 ---------------------------------------------\njava.version\u003d1.4.2_02\njava.vendor\u003dSun Microsystems Inc.\nBootLoader constants: OS\u003dwin32, ARCH\u003dx86, WS\u003dwin32, NL\u003den_US\n!ENTRY org.eclipse.core.runtime 4 2 Apr 06, 2004 23:45:29.762\n!MESSAGE Problems occurred when invoking code from plug-\nin: \"org.eclipse.core.runtime\".\n!STACK 0\njava.lang.NoClassDefFoundError: \norg/eclipse/update/search/IUpdateSearchResultCollector\n        at java.lang.ClassLoader.defineClass0(Native Method)\n        at java.lang.ClassLoader.defineClass(ClassLoader.java:537)\n        at \norg.eclipse.osgi.framework.internal.defaultadaptor.DefaultClassLoader.defineClas\ns(DefaultClassLoader.java:309)\n        at org.eclipse.core.runtime.adaptor.EclipseClassLoader.defineClass\n(EclipseClassLoader.java:175)\n        at \norg.eclipse.osgi.framework.internal.defaultadaptor.DefaultClassLoader.findClassI\nmpl(DefaultClassLoader.java:298)\n        at \norg.eclipse.osgi.framework.internal.defaultadaptor.DefaultClassLoader.findClass\n(DefaultClassLoader.java:187)\n        at \norg.eclipse.osgi.framework.adaptor.core.AbstractClassLoader.findLocalClass\n(AbstractClassLoader.java:243)\n        at org.eclipse.core.runtime.adaptor.EclipseClassLoader.findLocalClass\n(EclipseClassLoader.java:104)\n        at org.eclipse.osgi.framework.internal.core.BundleLoader.findLocalClass\n(BundleLoader.java:370)\n        at org.eclipse.osgi.framework.internal.core.BundleLoader.findClass\n(BundleLoader.java:401)\n        at org.eclipse.osgi.framework.adaptor.core.AbstractClassLoader.loadClass\n(AbstractClassLoader.java:116)\n        at java.lang.ClassLoader.loadClass(ClassLoader.java:235)\n        at java.lang.ClassLoader.loadClassInternal(ClassLoader.java:302)\n        at java.lang.Class.getDeclaredConstructors0(Native Method)\n        at java.lang.Class.privateGetDeclaredConstructors(Class.java:1610)\n        at java.lang.Class.getConstructor0(Class.java:1922)\n        at java.lang.Class.newInstance0(Class.java:278)\n        at java.lang.Class.newInstance(Class.java:261)\n        at \norg.eclipse.core.internal.registry.ConfigurationElement.createExecutableExtensio\nn(ConfigurationElement.java:140)\n        at \norg.eclipse.core.internal.registry.ConfigurationElement.createExecutableExtensio\nn(ConfigurationElement.java:125)\n        at \norg.eclipse.core.internal.registry.ConfigurationElement.createExecutableExtensio\nn(ConfigurationElement.java:114)\n        at org.eclipse.ui.internal.WorkbenchPlugin$1.run\n(WorkbenchPlugin.java:188)\n        at org.eclipse.swt.custom.BusyIndicator.showWhile(BusyIndicator.java:51)\n        at org.eclipse.ui.internal.WorkbenchPlugin.createExtension\n(WorkbenchPlugin.java:185)\n        at \norg.eclipse.ui.internal.Workbench$EarlyStartupRunnable.getExecutableExtension\n(Workbench.java:1436)\n        at org.eclipse.ui.internal.Workbench$EarlyStartupRunnable.run\n(Workbench.java:1378)\n        at org.eclipse.core.internal.runtime.InternalPlatform.run\n(InternalPlatform.java:607)\n        at org.eclipse.core.runtime.Platform.run(Platform.java:524)\n        at org.eclipse.ui.internal.Workbench$16.run(Workbench.java:1350)\n        at java.lang.Thread.run(Thread.java:534)\n!ENTRY org.eclipse.ui 4 4 Apr 06, 2004 23:45:29.812\n!MESSAGE Unhandled Exception\nUnhandled Exception\nReason:\n!ENTRY org.eclipse.update.scheduler 4 0 Apr 06, 2004 23:45:29.822\n!MESSAGE Unable to execute early startup code for a startup extension in plugin \norg.eclipse.update.scheduler\n!STACK 0\njava.lang.NoClassDefFoundError: \norg/eclipse/update/search/IUpdateSearchResultCollector\n        at java.lang.ClassLoader.defineClass0(Native Method)\n        at java.lang.ClassLoader.defineClass(ClassLoader.java:537)\n        at \norg.eclipse.osgi.framework.internal.defaultadaptor.DefaultClassLoader.defineClas\ns(DefaultClassLoader.java:309)\n        at org.eclipse.core.runtime.adaptor.EclipseClassLoader.defineClass\n(EclipseClassLoader.java:175)\n        at \norg.eclipse.osgi.framework.internal.defaultadaptor.DefaultClassLoader.findClassI\nmpl(DefaultClassLoader.java:298)\n        at \norg.eclipse.osgi.framework.internal.defaultadaptor.DefaultClassLoader.findClass\n(DefaultClassLoader.java:187)\n        at \norg.eclipse.osgi.framework.adaptor.core.AbstractClassLoader.findLocalClass\n(AbstractClassLoader.java:243)\n        at org.eclipse.core.runtime.adaptor.EclipseClassLoader.findLocalClass\n(EclipseClassLoader.java:104)\n        at org.eclipse.osgi.framework.internal.core.BundleLoader.findLocalClass\n(BundleLoader.java:370)\n        at org.eclipse.osgi.framework.internal.core.BundleLoader.findClass\n(BundleLoader.java:401)\n        at org.eclipse.osgi.framework.adaptor.core.AbstractClassLoader.loadClass\n(AbstractClassLoader.java:116)\n        at java.lang.ClassLoader.loadClass(ClassLoader.java:235)\n        at java.lang.ClassLoader.loadClassInternal(ClassLoader.java:302)\n        at java.lang.Class.getDeclaredConstructors0(Native Method)\n        at java.lang.Class.privateGetDeclaredConstructors(Class.java:1610)\n        at java.lang.Class.getConstructor0(Class.java:1922)\n        at java.lang.Class.newInstance0(Class.java:278)\n        at java.lang.Class.newInstance(Class.java:261)\n        at \norg.eclipse.core.internal.registry.ConfigurationElement.createExecutableExtensio\nn(ConfigurationElement.java:140)\n        at \norg.eclipse.core.internal.registry.ConfigurationElement.createExecutableExtensio\nn(ConfigurationElement.java:125)\n        at \norg.eclipse.core.internal.registry.ConfigurationElement.createExecutableExtensio\nn(ConfigurationElement.java:114)\n        at org.eclipse.ui.internal.WorkbenchPlugin$1.run\n(WorkbenchPlugin.java:188)\n        at org.eclipse.swt.custom.BusyIndicator.showWhile(BusyIndicator.java:51)\n        at org.eclipse.ui.internal.WorkbenchPlugin.createExtension\n(WorkbenchPlugin.java:185)\n        at \norg.eclipse.ui.internal.Workbench$EarlyStartupRunnable.getExecutableExtension\n(Workbench.java:1436)\n        at org.eclipse.ui.internal.Workbench$EarlyStartupRunnable.run\n(Workbench.java:1378)\n        at org.eclipse.core.internal.runtime.InternalPlatform.run\n(InternalPlatform.java:607)\n        at org.eclipse.core.runtime.Platform.run(Platform.java:524)\n        at org.eclipse.ui.internal.Workbench$16.run(Workbench.java:1350)\n        at java.lang.Thread.run(Thread.java:534)\nUnable to execute early startup code for a startup extension in plugin \norg.eclipse.update.scheduler\n\n\n\n",
    "Got build all over again, and this time I can open the update manager ok. \nSuspecting corrupted JAR.",
    "closing as invalid"
  ],
  "commentCreationDates": [
    "2004-04-06T19:13:49+02:00",
    "2004-04-06T19:34:21+02:00",
    "2004-04-06T21:57:35+02:00",
    "2004-04-06T23:53:33+02:00",
    "2004-04-07T11:48:50+02:00",
    "2004-04-07T15:06:01+02:00"
  ],
  "traces": [
    {
      "exceptionType": "java.lang.NoClassDefFoundError",
      "message": "org/eclipse/update/search/IUpdateSearchResultCollector",
      "elements": [
        {
          "method": "java.lang.ClassLoader.defineClass0",
          "source": "Native Method"
        },
        {
          "method": "java.lang.ClassLoader.defineClass",
          "source": "ClassLoader.java:537"
        },
        {
          "method": "org.eclipse.osgi.framework.internal.defaultadaptor.DefaultClassLoader.defineClass",
          "source": "DefaultClassLoader.java:309"
        },
        {
          "method": "org.eclipse.core.runtime.adaptor.EclipseClassLoader.defineClass",
          "source": "EclipseClassLoader.java:175"
        },
        {
          "method": "org.eclipse.osgi.framework.internal.defaultadaptor.DefaultClassLoader.findClassImpl",
          "source": "DefaultClassLoader.java:298"
        },
        {
          "method": "org.eclipse.osgi.framework.internal.defaultadaptor.DefaultClassLoader.findClass",
          "source": "DefaultClassLoader.java:187"
        },
        {
          "method": "org.eclipse.osgi.framework.adaptor.core.AbstractClassLoader.findLocalClass",
          "source": "AbstractClassLoader.java:243"
        },
        {
          "method": "org.eclipse.core.runtime.adaptor.EclipseClassLoader.findLocalClass",
          "source": "EclipseClassLoader.java:104"
        },
        {
          "method": "org.eclipse.osgi.framework.internal.core.BundleLoader.findLocalClass",
          "source": "BundleLoader.java:370"
        },
        {
          "method": "org.eclipse.osgi.framework.internal.core.BundleLoader.findClass",
          "source": "BundleLoader.java:401"
        },
        {
          "method": "org.eclipse.osgi.framework.adaptor.core.AbstractClassLoader.loadClass",
          "source": "AbstractClassLoader.java:116"
        },
        {
          "method": "java.lang.ClassLoader.loadClass",
          "source": "ClassLoader.java:235"
        },
        {
          "method": "java.lang.ClassLoader.loadClassInternal",
          "source": "ClassLoader.java:302"
        },
        {
          "method": "java.lang.Class.getDeclaredConstructors0",
          "source": "Native Method"
        },
        {
          "method": "java.lang.Class.privateGetDeclaredConstructors",
          "source": "Class.java:1610"
        },
        {
          "method": "java.lang.Class.getConstructor0",
          "source": "Class.java:1922"
        },
        {
          "method": "java.lang.Class.newInstance0",
          "source": "Class.java:278"
        },
        {
          "method": "java.lang.Class.newInstance",
          "source": "Class.java:261"
        },
        {
          "method": "org.eclipse.core.internal.registry.ConfigurationElement.createExecutableExtension",
          "source": "ConfigurationElement.java:140"
        },
        {
          "method": "org.eclipse.core.internal.registry.ConfigurationElement.createExecutableExtension",
          "source": "ConfigurationElement.java:125"
        },
        {
          "method": "org.eclipse.core.internal.registry.ConfigurationElement.createExecutableExtension",
          "source": "ConfigurationElement.java:114"
        },
        {
          "method": "org.eclipse.ui.internal.WorkbenchPlugin$1.run",
          "source": "WorkbenchPlugin.java:188"
        },
        {
          "method": "org.eclipse.swt.custom.BusyIndicator.showWhile",
          "source": "BusyIndicator.java:51"
        },
        {
          "method": "org.eclipse.ui.internal.WorkbenchPlugin.createExtension",
          "source": "WorkbenchPlugin.java:185"
        },
        {
          "method": "org.eclipse.ui.internal.Workbench$EarlyStartupRunnable.getExecutableExtension",
          "source": "Workbench.java:1436"
        },
        {
          "method": "org.eclipse.ui.internal.Workbench$EarlyStartupRunnable.run",
          "source": "Workbench.java:1378"
        },
        {
          "method": "org.eclipse.core.internal.runtime.InternalPlatform.run",
          "source": "InternalPlatform.java:607"
        },
        {
          "method": "org.eclipse.core.runtime.Platform.run",
          "source": "Platform.java:524"
        },
        {
          "method": "org.eclipse.ui.internal.Workbench$16.run",
          "source": "Workbench.java:1350"
        },
        {
          "method": "java.lang.Thread.run",
          "source": "Thread.java:534"
        }
      ],
      "number": 0,
      "commentIndex": 2,
      "bugId": "57604",
      "date": "2004-04-06T21:57:35+02:00",
      "product": "Platform",
      "component": "Update",
      "severity": "major"
    },
    {
      "exceptionType": "java.lang.NoClassDefFoundError",
      "message": "org/eclipse/update/search/IUpdateSearchResultCollector",
      "elements": [
        {
          "method": "java.lang.ClassLoader.defineClass0",
          "source": "Native Method"
        },
        {
          "method": "java.lang.ClassLoader.defineClass",
          "source": "ClassLoader.java:537"
        },
        {
          "method": "org.eclipse.osgi.framework.internal.defaultadaptor.DefaultClassLoader.defineClass",
          "source": "DefaultClassLoader.java:309"
        },
        {
          "method": "org.eclipse.core.runtime.adaptor.EclipseClassLoader.defineClass",
          "source": "EclipseClassLoader.java:175"
        },
        {
          "method": "org.eclipse.osgi.framework.internal.defaultadaptor.DefaultClassLoader.findClassImpl",
          "source": "DefaultClassLoader.java:298"
        },
        {
          "method": "org.eclipse.osgi.framework.internal.defaultadaptor.DefaultClassLoader.findClass",
          "source": "DefaultClassLoader.java:187"
        },
        {
          "method": "org.eclipse.osgi.framework.adaptor.core.AbstractClassLoader.findLocalClass",
          "source": "AbstractClassLoader.java:243"
        },
        {
          "method": "org.eclipse.core.runtime.adaptor.EclipseClassLoader.findLocalClass",
          "source": "EclipseClassLoader.java:104"
        },
        {
          "method": "org.eclipse.osgi.framework.internal.core.BundleLoader.findLocalClass",
          "source": "BundleLoader.java:370"
        },
        {
          "method": "org.eclipse.osgi.framework.internal.core.BundleLoader.findClass",
          "source": "BundleLoader.java:401"
        },
        {
          "method": "org.eclipse.osgi.framework.adaptor.core.AbstractClassLoader.loadClass",
          "source": "AbstractClassLoader.java:116"
        },
        {
          "method": "java.lang.ClassLoader.loadClass",
          "source": "ClassLoader.java:235"
        },
        {
          "method": "java.lang.ClassLoader.loadClassInternal",
          "source": "ClassLoader.java:302"
        },
        {
          "method": "java.lang.Class.getDeclaredConstructors0",
          "source": "Native Method"
        },
        {
          "method": "java.lang.Class.privateGetDeclaredConstructors",
          "source": "Class.java:1610"
        },
        {
          "method": "java.lang.Class.getConstructor0",
          "source": "Class.java:1922"
        },
        {
          "method": "java.lang.Class.newInstance0",
          "source": "Class.java:278"
        },
        {
          "method": "java.lang.Class.newInstance",
          "source": "Class.java:261"
        },
        {
          "method": "org.eclipse.core.internal.registry.ConfigurationElement.createExecutableExtension",
          "source": "ConfigurationElement.java:140"
        },
        {
          "method": "org.eclipse.core.internal.registry.ConfigurationElement.createExecutableExtension",
          "source": "ConfigurationElement.java:125"
        },
        {
          "method": "org.eclipse.core.internal.registry.ConfigurationElement.createExecutableExtension",
          "source": "ConfigurationElement.java:114"
        },
        {
          "method": "org.eclipse.ui.internal.WorkbenchPlugin$1.run",
          "source": "WorkbenchPlugin.java:188"
        },
        {
          "method": "org.eclipse.swt.custom.BusyIndicator.showWhile",
          "source": "BusyIndicator.java:51"
        },
        {
          "method": "org.eclipse.ui.internal.WorkbenchPlugin.createExtension",
          "source": "WorkbenchPlugin.java:185"
        },
        {
          "method": "org.eclipse.ui.internal.Workbench$EarlyStartupRunnable.getExecutableExtension",
          "source": "Workbench.java:1436"
        },
        {
          "method": "org.eclipse.ui.internal.Workbench$EarlyStartupRunnable.run",
          "source": "Workbench.java:1378"
        },
        {
          "method": "org.eclipse.core.internal.runtime.InternalPlatform.run",
          "source": "InternalPlatform.java:607"
        },
        {
          "method": "org.eclipse.core.runtime.Platform.run",
          "source": "Platform.java:524"
        },
        {
          "method": "org.eclipse.ui.internal.Workbench$16.run",
          "source": "Workbench.java:1350"
        },
        {
          "method": "java.lang.Thread.run",
          "source": "Thread.java:534"
        }
      ],
      "number": 1,
      "commentIndex": 2,
      "bugId": "57604",
      "date": "2004-04-06T21:57:35+02:00",
      "product": "Platform",
      "component": "Update",
      "severity": "major"
    },
    {
      "exceptionType": "java.lang.NoClassDefFoundError",
      "message": "org/eclipse/update/operations/IOperationListener",
      "elements": [
        {
          "method": "java.lang.ClassLoader.defineClass0",
          "source": "Native Method"
        },
        {
          "method": "java.lang.ClassLoader.defineClass",
          "source": "ClassLoader.java:537"
        },
        {
          "method": "org.eclipse.osgi.framework.internal.defaultadaptor.DefaultClassLoader.defineClass",
          "source": "DefaultClassLoader.java:309"
        },
        {
          "method": "org.eclipse.core.runtime.adaptor.EclipseClassLoader.defineClass",
          "source": "EclipseClassLoader.java:175"
        },
        {
          "method": "org.eclipse.osgi.framework.internal.defaultadaptor.DefaultClassLoader.findClassImpl",
          "source": "DefaultClassLoader.java:298"
        },
        {
          "method": "org.eclipse.osgi.framework.internal.defaultadaptor.DefaultClassLoader.findClass",
          "source": "DefaultClassLoader.java:187"
        },
        {
          "method": "org.eclipse.osgi.framework.adaptor.core.AbstractClassLoader.findLocalClass",
          "source": "AbstractClassLoader.java:243"
        },
        {
          "method": "org.eclipse.core.runtime.adaptor.EclipseClassLoader.findLocalClass",
          "source": "EclipseClassLoader.java:104"
        },
        {
          "method": "org.eclipse.osgi.framework.internal.core.BundleLoader.findLocalClass",
          "source": "BundleLoader.java:370"
        },
        {
          "method": "org.eclipse.osgi.framework.internal.core.BundleLoader.findClass",
          "source": "BundleLoader.java:401"
        },
        {
          "method": "org.eclipse.osgi.framework.adaptor.core.AbstractClassLoader.loadClass",
          "source": "AbstractClassLoader.java:116"
        },
        {
          "method": "java.lang.ClassLoader.loadClass",
          "source": "ClassLoader.java:235"
        },
        {
          "method": "java.lang.ClassLoader.loadClassInternal",
          "source": "ClassLoader.java:302"
        },
        {
          "method": "org.eclipse.update.internal.ui.InstallWizardAction.openNewUpdatesWizard",
          "source": "InstallWizardAction.java:54"
        },
        {
          "method": "org.eclipse.update.internal.ui.InstallWizardAction.doRun",
          "source": "InstallWizardAction.java:50"
        },
        {
          "method": "org.eclipse.update.internal.ui.InstallWizardAction.access$0",
          "source": "InstallWizardAction.java:49"
        },
        {
          "method": "org.eclipse.update.internal.ui.InstallWizardAction$1.run",
          "source": "InstallWizardAction.java:44"
        },
        {
          "method": "org.eclipse.swt.custom.BusyIndicator.showWhile",
          "source": "BusyIndicator.java:84"
        },
        {
          "method": "org.eclipse.update.internal.ui.InstallWizardAction.run",
          "source": "InstallWizardAction.java:42"
        },
        {
          "method": "org.eclipse.ui.internal.PluginAction.runWithEvent",
          "source": "PluginAction.java:269"
        },
        {
          "method": "org.eclipse.ui.internal.WWinPluginAction.runWithEvent",
          "source": "WWinPluginAction.java:207"
        },
        {
          "method": "org.eclipse.jface.action.ActionContributionItem.handleWidgetSelection",
          "source": "ActionContributionItem.java:550"
        },
        {
          "method": "org.eclipse.jface.action.ActionContributionItem.access$2",
          "source": "ActionContributionItem.java:502"
        },
        {
          "method": "org.eclipse.jface.action.ActionContributionItem$5.handleEvent",
          "source": "ActionContributionItem.java:435"
        },
        {
          "method": "org.eclipse.swt.widgets.EventTable.sendEvent",
          "source": "EventTable.java:82"
        },
        {
          "method": "org.eclipse.swt.widgets.Widget.sendEvent",
          "source": "Widget.java:769"
        },
        {
          "method": "org.eclipse.swt.widgets.Display.runDeferredEvents",
          "source": "Display.java:2587"
        },
        {
          "method": "org.eclipse.swt.widgets.Display.readAndDispatch",
          "source": "Display.java:2265"
        },
        {
          "method": "org.eclipse.ui.internal.Workbench.runEventLoop",
          "source": "Workbench.java:1561"
        },
        {
          "method": "org.eclipse.ui.internal.Workbench.runUI",
          "source": "Workbench.java:1532"
        },
        {
          "method": "org.eclipse.ui.internal.Workbench.createAndRunWorkbench",
          "source": "Workbench.java:257"
        },
        {
          "method": "org.eclipse.ui.PlatformUI.createAndRunWorkbench",
          "source": "PlatformUI.java:140"
        },
        {
          "method": "org.eclipse.ui.internal.ide.IDEApplication.run",
          "source": "IDEApplication.java:90"
        },
        {
          "method": "org.eclipse.core.internal.runtime.PlatformActivator$1.run",
          "source": "PlatformActivator.java:279"
        },
        {
          "method": "org.eclipse.core.runtime.adaptor.EclipseStarter.run",
          "source": "EclipseStarter.java:241"
        },
        {
          "method": "org.eclipse.core.runtime.adaptor.EclipseStarter.run",
          "source": "EclipseStarter.java:117"
        },
        {
          "method": "sun.reflect.NativeMethodAccessorImpl.invoke0",
          "source": "Native Method"
        },
        {
          "method": "sun.reflect.NativeMethodAccessorImpl.invoke",
          "source": "NativeMethodAccessorImpl.java:39"
        },
        {
          "method": "sun.reflect.DelegatingMethodAccessorImpl.invoke",
          "source": "DelegatingMethodAccessorImpl.java:25"
        },
        {
          "method": "java.lang.reflect.Method.invoke",
          "source": "Method.java:324"
        },
        {
          "method": "org.eclipse.core.launcher.Main.basicRun",
          "source": "Main.java:267"
        },
        {
          "method": "org.eclipse.core.launcher.Main.run",
          "source": "Main.java:692"
        },
        {
          "method": "org.eclipse.core.launcher.Main.main",
          "source": "Main.java:676"
        }
      ],
      "number": 2,
      "commentIndex": 2,
      "bugId": "57604",
      "date": "2004-04-06T21:57:35+02:00",
      "product": "Platform",
      "component": "Update",
      "severity": "major"
    },
    {
      "exceptionType": "java.lang.NoClassDefFoundError",
      "message": "org/eclipse/update/search/IUpdateSearchResultCollector",
      "elements": [
        {
          "method": "java.lang.ClassLoader.defineClass0",
          "source": "Native Method"
        },
        {
          "method": "java.lang.ClassLoader.defineClass",
          "source": "ClassLoader.java:537"
        },
        {
          "method": "org.eclipse.osgi.framework.internal.defaultadaptor.DefaultClassLoader.defineClass",
          "source": "DefaultClassLoader.java:309"
        },
        {
          "method": "org.eclipse.core.runtime.adaptor.EclipseClassLoader.defineClass",
          "source": "EclipseClassLoader.java:175"
        },
        {
          "method": "org.eclipse.osgi.framework.internal.defaultadaptor.DefaultClassLoader.findClassImpl",
          "source": "DefaultClassLoader.java:298"
        },
        {
          "method": "org.eclipse.osgi.framework.internal.defaultadaptor.DefaultClassLoader.findClass",
          "source": "DefaultClassLoader.java:187"
        },
        {
          "method": "org.eclipse.osgi.framework.adaptor.core.AbstractClassLoader.findLocalClass",
          "source": "AbstractClassLoader.java:243"
        },
        {
          "method": "org.eclipse.core.runtime.adaptor.EclipseClassLoader.findLocalClass",
          "source": "EclipseClassLoader.java:104"
        },
        {
          "method": "org.eclipse.osgi.framework.internal.core.BundleLoader.findLocalClass",
          "source": "BundleLoader.java:370"
        },
        {
          "method": "org.eclipse.osgi.framework.internal.core.BundleLoader.findClass",
          "source": "BundleLoader.java:401"
        },
        {
          "method": "org.eclipse.osgi.framework.adaptor.core.AbstractClassLoader.loadClass",
          "source": "AbstractClassLoader.java:116"
        },
        {
          "method": "java.lang.ClassLoader.loadClass",
          "source": "ClassLoader.java:235"
        },
        {
          "method": "java.lang.ClassLoader.loadClassInternal",
          "source": "ClassLoader.java:302"
        },
        {
          "method": "java.lang.Class.getDeclaredConstructors0",
          "source": "Native Method"
        },
        {
          "method": "java.lang.Class.privateGetDeclaredConstructors",
          "source": "Class.java:1610"
        },
        {
          "method": "java.lang.Class.getConstructor0",
          "source": "Class.java:1922"
        },
        {
          "method": "java.lang.Class.newInstance0",
          "source": "Class.java:278"
        },
        {
          "method": "java.lang.Class.newInstance",
          "source": "Class.java:261"
        },
        {
          "method": "org.eclipse.core.internal.registry.ConfigurationElement.createExecutableExtension",
          "source": "ConfigurationElement.java:140"
        },
        {
          "method": "org.eclipse.core.internal.registry.ConfigurationElement.createExecutableExtension",
          "source": "ConfigurationElement.java:125"
        },
        {
          "method": "org.eclipse.core.internal.registry.ConfigurationElement.createExecutableExtension",
          "source": "ConfigurationElement.java:114"
        },
        {
          "method": "org.eclipse.ui.internal.WorkbenchPlugin$1.run",
          "source": "WorkbenchPlugin.java:188"
        },
        {
          "method": "org.eclipse.swt.custom.BusyIndicator.showWhile",
          "source": "BusyIndicator.java:51"
        },
        {
          "method": "org.eclipse.ui.internal.WorkbenchPlugin.createExtension",
          "source": "WorkbenchPlugin.java:185"
        },
        {
          "method": "org.eclipse.ui.internal.Workbench$EarlyStartupRunnable.getExecutableExtension",
          "source": "Workbench.java:1436"
        },
        {
          "method": "org.eclipse.ui.internal.Workbench$EarlyStartupRunnable.run",
          "source": "Workbench.java:1378"
        },
        {
          "method": "org.eclipse.core.internal.runtime.InternalPlatform.run",
          "source": "InternalPlatform.java:607"
        },
        {
          "method": "org.eclipse.core.runtime.Platform.run",
          "source": "Platform.java:524"
        },
        {
          "method": "org.eclipse.ui.internal.Workbench$16.run",
          "source": "Workbench.java:1350"
        },
        {
          "method": "java.lang.Thread.run",
          "source": "Thread.java:534"
        }
      ],
      "number": 3,
      "commentIndex": 3,
      "bugId": "57604",
      "date": "2004-04-06T23:53:33+02:00",
      "product": "Platform",
      "component": "Update",
      "severity": "major"
    },
    {
      "exceptionType": "java.lang.NoClassDefFoundError",
      "message": "org/eclipse/update/search/IUpdateSearchResultCollector",
      "elements": [
        {
          "method": "java.lang.ClassLoader.defineClass0",
          "source": "Native Method"
        },
        {
          "method": "java.lang.ClassLoader.defineClass",
          "source": "ClassLoader.java:537"
        },
        {
          "method": "org.eclipse.osgi.framework.internal.defaultadaptor.DefaultClassLoader.defineClass",
          "source": "DefaultClassLoader.java:309"
        },
        {
          "method": "org.eclipse.core.runtime.adaptor.EclipseClassLoader.defineClass",
          "source": "EclipseClassLoader.java:175"
        },
        {
          "method": "org.eclipse.osgi.framework.internal.defaultadaptor.DefaultClassLoader.findClassImpl",
          "source": "DefaultClassLoader.java:298"
        },
        {
          "method": "org.eclipse.osgi.framework.internal.defaultadaptor.DefaultClassLoader.findClass",
          "source": "DefaultClassLoader.java:187"
        },
        {
          "method": "org.eclipse.osgi.framework.adaptor.core.AbstractClassLoader.findLocalClass",
          "source": "AbstractClassLoader.java:243"
        },
        {
          "method": "org.eclipse.core.runtime.adaptor.EclipseClassLoader.findLocalClass",
          "source": "EclipseClassLoader.java:104"
        },
        {
          "method": "org.eclipse.osgi.framework.internal.core.BundleLoader.findLocalClass",
          "source": "BundleLoader.java:370"
        },
        {
          "method": "org.eclipse.osgi.framework.internal.core.BundleLoader.findClass",
          "source": "BundleLoader.java:401"
        },
        {
          "method": "org.eclipse.osgi.framework.adaptor.core.AbstractClassLoader.loadClass",
          "source": "AbstractClassLoader.java:116"
        },
        {
          "method": "java.lang.ClassLoader.loadClass",
          "source": "ClassLoader.java:235"
        },
        {
          "method": "java.lang.ClassLoader.loadClassInternal",
          "source": "ClassLoader.java:302"
        },
        {
          "method": "java.lang.Class.getDeclaredConstructors0",
          "source": "Native Method"
        },
        {
          "method": "java.lang.Class.privateGetDeclaredConstructors",
          "source": "Class.java:1610"
        },
        {
          "method": "java.lang.Class.getConstructor0",
          "source": "Class.java:1922"
        },
        {
          "method": "java.lang.Class.newInstance0",
          "source": "Class.java:278"
        },
        {
          "method": "java.lang.Class.newInstance",
          "source": "Class.java:261"
        },
        {
          "method": "org.eclipse.core.internal.registry.ConfigurationElement.createExecutableExtension",
          "source": "ConfigurationElement.java:140"
        },
        {
          "method": "org.eclipse.core.internal.registry.ConfigurationElement.createExecutableExtension",
          "source": "ConfigurationElement.java:125"
        },
        {
          "method": "org.eclipse.core.internal.registry.ConfigurationElement.createExecutableExtension",
          "source": "ConfigurationElement.java:114"
        },
        {
          "method": "org.eclipse.ui.internal.WorkbenchPlugin$1.run",
          "source": "WorkbenchPlugin.java:188"
        },
        {
          "method": "org.eclipse.swt.custom.BusyIndicator.showWhile",
          "source": "BusyIndicator.java:51"
        },
        {
          "method": "org.eclipse.ui.internal.WorkbenchPlugin.createExtension",
          "source": "WorkbenchPlugin.java:185"
        },
        {
          "method": "org.eclipse.ui.internal.Workbench$EarlyStartupRunnable.getExecutableExtension",
          "source": "Workbench.java:1436"
        },
        {
          "method": "org.eclipse.ui.internal.Workbench$EarlyStartupRunnable.run",
          "source": "Workbench.java:1378"
        },
        {
          "method": "org.eclipse.core.internal.runtime.InternalPlatform.run",
          "source": "InternalPlatform.java:607"
        },
        {
          "method": "org.eclipse.core.runtime.Platform.run",
          "source": "Platform.java:524"
        },
        {
          "method": "org.eclipse.ui.internal.Workbench$16.run",
          "source": "Workbench.java:1350"
        },
        {
          "method": "java.lang.Thread.run",
          "source": "Thread.java:534"
        }
      ],
      "number": 4,
      "commentIndex": 3,
      "bugId": "57604",
      "date": "2004-04-06T23:53:33+02:00",
      "product": "Platform",
      "component": "Update",
      "severity": "major"
    }
  ],
  "groupId": "57604",
  "bugId": "57604",
  "date": "2004-04-06T19:13:49+02:00",
  "product": "Platform",
  "component": "Update",
  "severity": "major"
}