{
  "comments": [
    "Build 20040406+Cheetah01\n\nCompiling JDT Core from sources in 1.5 mode, against 1.5 libs, got the \nfollowing internal error:\n\n!MESSAGE Errors during build.\n!SUBENTRY 2 org.eclipse.jdt.core 2 75 Apr 07, 2004 12:12:05.250\n!MESSAGE Errors running builder \"Java Builder\" on project org.eclipse.jdt.core.\n!SUBENTRY 2 org.eclipse.jdt.core 2 75 Apr 07, 2004 12:12:05.250\n!MESSAGE java.lang.NullPointerException encountered while running Java Builder.\n!STACK 0\njava.lang.NullPointerException\n        at java.util.Hashtable.get(Hashtable.java:333)\n        at \norg.eclipse.jdt.internal.compiler.lookup.SourceTypeBinding.getUpdatedFieldBindin\ng(SourceTypeBinding.java:622)\n        at \norg.eclipse.jdt.internal.compiler.ast.QualifiedNameReference.manageSyntheticAcce\nssIfNecessary(QualifiedNameReference.java:712)\n        at \norg.eclipse.jdt.internal.compiler.ast.QualifiedNameReference.analyseCode\n(QualifiedNameReference.java:231)\n        at \norg.eclipse.jdt.internal.compiler.ast.QualifiedNameReference.analyseCode\n(QualifiedNameReference.java:183)\n        at \norg.eclipse.jdt.internal.compiler.ast.QualifiedNameReference.analyseAssignment\n(QualifiedNameReference.java:140)\n        at org.eclipse.jdt.internal.compiler.ast.Assignment.analyseCode\n(Assignment.java:46)\n        at \norg.eclipse.jdt.internal.compiler.ast.QualifiedNameReference.analyseAssignment\n(QualifiedNameReference.java:140)\n        at org.eclipse.jdt.internal.compiler.ast.Assignment.analyseCode\n(Assignment.java:46)\n        at org.eclipse.jdt.internal.compiler.ast.MethodDeclaration.analyseCode\n(MethodDeclaration.java:70)\n        at \norg.eclipse.jdt.internal.compiler.ast.TypeDeclaration.internalAnalyseCode\n(TypeDeclaration.java:699)\n        at org.eclipse.jdt.internal.compiler.ast.TypeDeclaration.analyseCode\n(TypeDeclaration.java:262)\n        at \norg.eclipse.jdt.internal.compiler.ast.CompilationUnitDeclaration.analyseCode\n(CompilationUnitDeclaration.java:80)\n        at org.eclipse.jdt.internal.compiler.Compiler.process(Compiler.java:528)\n        at org.eclipse.jdt.internal.compiler.Compiler.compile(Compiler.java:333)\n        at org.eclipse.jdt.internal.core.builder.AbstractImageBuilder.compile\n(AbstractImageBuilder.java:209)\n        at org.eclipse.jdt.internal.core.builder.AbstractImageBuilder.compile\n(AbstractImageBuilder.java:159)\n        at org.eclipse.jdt.internal.core.builder.BatchImageBuilder.build\n(BatchImageBuilder.java:49)\n        at org.eclipse.jdt.internal.core.builder.JavaBuilder.buildAll\n(JavaBuilder.java:212)\n        at org.eclipse.jdt.internal.core.builder.JavaBuilder.build\n(JavaBuilder.java:135)\n        at org.eclipse.core.internal.events.BuildManager$2.run\n(BuildManager.java:514)\n        at org.eclipse.core.internal.runtime.InternalPlatform.run\n(InternalPlatform.java:607)\n        at org.eclipse.core.runtime.Platform.run(Platform.java:524)\n        at org.eclipse.core.internal.events.BuildManager.basicBuild\n(BuildManager.java:140)\n        at org.eclipse.core.internal.events.BuildManager.basicBuild\n(BuildManager.java:227)\n        at org.eclipse.core.internal.events.BuildManager.basicBuild\n(BuildManager.java:168)\n        at org.eclipse.core.internal.events.BuildManager$1.run\n(BuildManager.java:197)\n        at org.eclipse.core.internal.runtime.InternalPlatform.run\n(InternalPlatform.java:607)\n        at org.eclipse.core.runtime.Platform.run(Platform.java:524)\n        at org.eclipse.core.internal.events.BuildManager.basicBuild\n(BuildManager.java:200)\n        at org.eclipse.core.internal.events.BuildManager.basicBuildLoop\n(BuildManager.java:245)\n        at org.eclipse.core.internal.events.BuildManager.build\n(BuildManager.java:273)\n        at org.eclipse.core.internal.resources.Workspace.build\n(Workspace.java:175)\n        at org.eclipse.ui.actions.GlobalBuildAction$1.run\n(GlobalBuildAction.java:190)\n        at org.eclipse.core.internal.jobs.Worker.run(Worker.java:62)\n!ENTRY org.eclipse.jdt.core 4 4 Apr 07, 2004 12:18:56.672\n!MESSAGE Exception occurred during problem detection:\n!STACK 0\njava.lang.NullPointerException\n        at java.util.Hashtable.get(Hashtable.java:333)\n        at \norg.eclipse.jdt.internal.compiler.lookup.SourceTypeBinding.getUpdatedFieldBindin\ng(SourceTypeBinding.java:622)\n        at \norg.eclipse.jdt.internal.compiler.ast.QualifiedNameReference.manageSyntheticAcce\nssIfNecessary(QualifiedNameReference.java:712)\n        at \norg.eclipse.jdt.internal.compiler.ast.QualifiedNameReference.analyseCode\n(QualifiedNameReference.java:231)\n        at \norg.eclipse.jdt.internal.compiler.ast.QualifiedNameReference.analyseCode\n(QualifiedNameReference.java:183)\n        at \norg.eclipse.jdt.internal.compiler.ast.QualifiedNameReference.analyseAssignment\n(QualifiedNameReference.java:140)\n        at org.eclipse.jdt.internal.compiler.ast.Assignment.analyseCode\n(Assignment.java:46)\n        at \norg.eclipse.jdt.internal.compiler.ast.QualifiedNameReference.analyseAssignment\n(QualifiedNameReference.java:140)\n        at org.eclipse.jdt.internal.compiler.ast.Assignment.analyseCode\n(Assignment.java:46)\n        at org.eclipse.jdt.internal.compiler.ast.MethodDeclaration.analyseCode\n(MethodDeclaration.java:70)\n        at \norg.eclipse.jdt.internal.compiler.ast.TypeDeclaration.internalAnalyseCode\n(TypeDeclaration.java:699)\n        at org.eclipse.jdt.internal.compiler.ast.TypeDeclaration.analyseCode\n(TypeDeclaration.java:262)\n        at \norg.eclipse.jdt.internal.compiler.ast.CompilationUnitDeclaration.analyseCode\n(CompilationUnitDeclaration.java:80)\n        at org.eclipse.jdt.internal.compiler.Compiler.resolve(Compiler.java:584)\n        at org.eclipse.jdt.internal.compiler.Compiler.resolve(Compiler.java:620)\n        at org.eclipse.jdt.internal.core.CompilationUnitProblemFinder.process\n(CompilationUnitProblemFinder.java:165)\n        at org.eclipse.jdt.internal.core.CompilationUnitProblemFinder.process\n(CompilationUnitProblemFinder.java:205)\n        at \norg.eclipse.jdt.internal.core.ReconcileWorkingCopyOperation.executeOperation\n(ReconcileWorkingCopyOperation.java:74)\n        at org.eclipse.jdt.internal.core.JavaModelOperation.run\n(JavaModelOperation.java:700)\n        at org.eclipse.jdt.internal.core.JavaModelOperation.runOperation\n(JavaModelOperation.java:739)\n        at org.eclipse.jdt.internal.core.CompilationUnit.reconcile\n(CompilationUnit.java:1080)\n        at \norg.eclipse.jdt.internal.ui.text.java.JavaReconcilingStrategy.reconcile\n(JavaReconcilingStrategy.java:85)\n        at \norg.eclipse.jdt.internal.ui.text.java.JavaReconcilingStrategy.initialReconcile\n(JavaReconcilingStrategy.java:145)\n        at \norg.eclipse.jface.text.reconciler.CompositeReconcilingStrategy.initialReconcile\n(CompositeReconcilingStrategy.java:111)\n        at \norg.eclipse.jdt.internal.ui.text.JavaCompositeReconcilingStrategy.initialReconci\nle(JavaCompositeReconcilingStrategy.java:123)\n        at org.eclipse.jface.text.reconciler.MonoReconciler.initialProcess\n(MonoReconciler.java:104)\n        at org.eclipse.jdt.internal.ui.text.JavaReconciler.initialProcess\n(JavaReconciler.java:280)\n        at \norg.eclipse.jface.text.reconciler.AbstractReconciler$BackgroundThread.run\n(AbstractReconciler.java:155)",
    "\n\n*** This bug has been marked as a duplicate of 57718 ***",
    "This is not a dup, bogus submit.",
    "Offending unit was SelectionParser.",
    "Solved. Problem was due to incomplete copy of otherCodegenBindings when doing \nits lazy initialization (once needing an alternate codegen binding).\n\nFixed. Test case is to recompile the compiler with itself."
  ],
  "commentCreationDates": [
    "2004-04-07T12:38:25+02:00",
    "2004-04-07T13:01:00+02:00",
    "2004-04-07T13:02:48+02:00",
    "2004-04-07T19:13:19+02:00",
    "2004-04-08T23:05:35+02:00"
  ],
  "traces": [
    {
      "exceptionType": "java.lang.NullPointerException",
      "elements": [
        {
          "method": "java.util.Hashtable.get",
          "source": "Hashtable.java:333"
        },
        {
          "method": "org.eclipse.jdt.internal.compiler.lookup.SourceTypeBinding.getUpdatedFieldBinding",
          "source": "SourceTypeBinding.java:622"
        },
        {
          "method": "org.eclipse.jdt.internal.compiler.ast.QualifiedNameReference.manageSyntheticAccessIfNecessary",
          "source": "QualifiedNameReference.java:712"
        },
        {
          "method": "org.eclipse.jdt.internal.compiler.ast.QualifiedNameReference.analyseCode",
          "source": "QualifiedNameReference.java:231"
        },
        {
          "method": "org.eclipse.jdt.internal.compiler.ast.QualifiedNameReference.analyseCode",
          "source": "QualifiedNameReference.java:183"
        },
        {
          "method": "org.eclipse.jdt.internal.compiler.ast.QualifiedNameReference.analyseAssignment",
          "source": "QualifiedNameReference.java:140"
        },
        {
          "method": "org.eclipse.jdt.internal.compiler.ast.Assignment.analyseCode",
          "source": "Assignment.java:46"
        },
        {
          "method": "org.eclipse.jdt.internal.compiler.ast.QualifiedNameReference.analyseAssignment",
          "source": "QualifiedNameReference.java:140"
        },
        {
          "method": "org.eclipse.jdt.internal.compiler.ast.Assignment.analyseCode",
          "source": "Assignment.java:46"
        },
        {
          "method": "org.eclipse.jdt.internal.compiler.ast.MethodDeclaration.analyseCode",
          "source": "MethodDeclaration.java:70"
        },
        {
          "method": "org.eclipse.jdt.internal.compiler.ast.TypeDeclaration.internalAnalyseCode",
          "source": "TypeDeclaration.java:699"
        },
        {
          "method": "org.eclipse.jdt.internal.compiler.ast.TypeDeclaration.analyseCode",
          "source": "TypeDeclaration.java:262"
        },
        {
          "method": "org.eclipse.jdt.internal.compiler.ast.CompilationUnitDeclaration.analyseCode",
          "source": "CompilationUnitDeclaration.java:80"
        },
        {
          "method": "org.eclipse.jdt.internal.compiler.Compiler.process",
          "source": "Compiler.java:528"
        },
        {
          "method": "org.eclipse.jdt.internal.compiler.Compiler.compile",
          "source": "Compiler.java:333"
        },
        {
          "method": "org.eclipse.jdt.internal.core.builder.AbstractImageBuilder.compile",
          "source": "AbstractImageBuilder.java:209"
        },
        {
          "method": "org.eclipse.jdt.internal.core.builder.AbstractImageBuilder.compile",
          "source": "AbstractImageBuilder.java:159"
        },
        {
          "method": "org.eclipse.jdt.internal.core.builder.BatchImageBuilder.build",
          "source": "BatchImageBuilder.java:49"
        },
        {
          "method": "org.eclipse.jdt.internal.core.builder.JavaBuilder.buildAll",
          "source": "JavaBuilder.java:212"
        },
        {
          "method": "org.eclipse.jdt.internal.core.builder.JavaBuilder.build",
          "source": "JavaBuilder.java:135"
        },
        {
          "method": "org.eclipse.core.internal.events.BuildManager$2.run",
          "source": "BuildManager.java:514"
        },
        {
          "method": "org.eclipse.core.internal.runtime.InternalPlatform.run",
          "source": "InternalPlatform.java:607"
        },
        {
          "method": "org.eclipse.core.runtime.Platform.run",
          "source": "Platform.java:524"
        },
        {
          "method": "org.eclipse.core.internal.events.BuildManager.basicBuild",
          "source": "BuildManager.java:140"
        },
        {
          "method": "org.eclipse.core.internal.events.BuildManager.basicBuild",
          "source": "BuildManager.java:227"
        },
        {
          "method": "org.eclipse.core.internal.events.BuildManager.basicBuild",
          "source": "BuildManager.java:168"
        },
        {
          "method": "org.eclipse.core.internal.events.BuildManager$1.run",
          "source": "BuildManager.java:197"
        },
        {
          "method": "org.eclipse.core.internal.runtime.InternalPlatform.run",
          "source": "InternalPlatform.java:607"
        },
        {
          "method": "org.eclipse.core.runtime.Platform.run",
          "source": "Platform.java:524"
        },
        {
          "method": "org.eclipse.core.internal.events.BuildManager.basicBuild",
          "source": "BuildManager.java:200"
        },
        {
          "method": "org.eclipse.core.internal.events.BuildManager.basicBuildLoop",
          "source": "BuildManager.java:245"
        },
        {
          "method": "org.eclipse.core.internal.events.BuildManager.build",
          "source": "BuildManager.java:273"
        },
        {
          "method": "org.eclipse.core.internal.resources.Workspace.build",
          "source": "Workspace.java:175"
        },
        {
          "method": "org.eclipse.ui.actions.GlobalBuildAction$1.run",
          "source": "GlobalBuildAction.java:190"
        },
        {
          "method": "org.eclipse.core.internal.jobs.Worker.run",
          "source": "Worker.java:62"
        }
      ],
      "number": 0,
      "commentIndex": 0,
      "bugId": "57716",
      "date": "2004-04-07T12:38:25+02:00",
      "product": "JDT",
      "component": "Core",
      "severity": "normal"
    },
    {
      "exceptionType": "java.lang.NullPointerException",
      "elements": [
        {
          "method": "java.util.Hashtable.get",
          "source": "Hashtable.java:333"
        },
        {
          "method": "org.eclipse.jdt.internal.compiler.lookup.SourceTypeBinding.getUpdatedFieldBinding",
          "source": "SourceTypeBinding.java:622"
        },
        {
          "method": "org.eclipse.jdt.internal.compiler.ast.QualifiedNameReference.manageSyntheticAccessIfNecessary",
          "source": "QualifiedNameReference.java:712"
        },
        {
          "method": "org.eclipse.jdt.internal.compiler.ast.QualifiedNameReference.analyseCode",
          "source": "QualifiedNameReference.java:231"
        },
        {
          "method": "org.eclipse.jdt.internal.compiler.ast.QualifiedNameReference.analyseCode",
          "source": "QualifiedNameReference.java:183"
        },
        {
          "method": "org.eclipse.jdt.internal.compiler.ast.QualifiedNameReference.analyseAssignment",
          "source": "QualifiedNameReference.java:140"
        },
        {
          "method": "org.eclipse.jdt.internal.compiler.ast.Assignment.analyseCode",
          "source": "Assignment.java:46"
        },
        {
          "method": "org.eclipse.jdt.internal.compiler.ast.QualifiedNameReference.analyseAssignment",
          "source": "QualifiedNameReference.java:140"
        },
        {
          "method": "org.eclipse.jdt.internal.compiler.ast.Assignment.analyseCode",
          "source": "Assignment.java:46"
        },
        {
          "method": "org.eclipse.jdt.internal.compiler.ast.MethodDeclaration.analyseCode",
          "source": "MethodDeclaration.java:70"
        },
        {
          "method": "org.eclipse.jdt.internal.compiler.ast.TypeDeclaration.internalAnalyseCode",
          "source": "TypeDeclaration.java:699"
        },
        {
          "method": "org.eclipse.jdt.internal.compiler.ast.TypeDeclaration.analyseCode",
          "source": "TypeDeclaration.java:262"
        },
        {
          "method": "org.eclipse.jdt.internal.compiler.ast.CompilationUnitDeclaration.analyseCode",
          "source": "CompilationUnitDeclaration.java:80"
        },
        {
          "method": "org.eclipse.jdt.internal.compiler.Compiler.resolve",
          "source": "Compiler.java:584"
        },
        {
          "method": "org.eclipse.jdt.internal.compiler.Compiler.resolve",
          "source": "Compiler.java:620"
        },
        {
          "method": "org.eclipse.jdt.internal.core.CompilationUnitProblemFinder.process",
          "source": "CompilationUnitProblemFinder.java:165"
        },
        {
          "method": "org.eclipse.jdt.internal.core.CompilationUnitProblemFinder.process",
          "source": "CompilationUnitProblemFinder.java:205"
        },
        {
          "method": "org.eclipse.jdt.internal.core.ReconcileWorkingCopyOperation.executeOperation",
          "source": "ReconcileWorkingCopyOperation.java:74"
        },
        {
          "method": "org.eclipse.jdt.internal.core.JavaModelOperation.run",
          "source": "JavaModelOperation.java:700"
        },
        {
          "method": "org.eclipse.jdt.internal.core.JavaModelOperation.runOperation",
          "source": "JavaModelOperation.java:739"
        },
        {
          "method": "org.eclipse.jdt.internal.core.CompilationUnit.reconcile",
          "source": "CompilationUnit.java:1080"
        },
        {
          "method": "org.eclipse.jdt.internal.ui.text.java.JavaReconcilingStrategy.reconcile",
          "source": "JavaReconcilingStrategy.java:85"
        },
        {
          "method": "org.eclipse.jdt.internal.ui.text.java.JavaReconcilingStrategy.initialReconcile",
          "source": "JavaReconcilingStrategy.java:145"
        },
        {
          "method": "org.eclipse.jface.text.reconciler.CompositeReconcilingStrategy.initialReconcile",
          "source": "CompositeReconcilingStrategy.java:111"
        },
        {
          "method": "org.eclipse.jdt.internal.ui.text.JavaCompositeReconcilingStrategy.initialReconcile",
          "source": "JavaCompositeReconcilingStrategy.java:123"
        },
        {
          "method": "org.eclipse.jface.text.reconciler.MonoReconciler.initialProcess",
          "source": "MonoReconciler.java:104"
        },
        {
          "method": "org.eclipse.jdt.internal.ui.text.JavaReconciler.initialProcess",
          "source": "JavaReconciler.java:280"
        },
        {
          "method": "org.eclipse.jface.text.reconciler.AbstractReconciler$BackgroundThread.run",
          "source": "AbstractReconciler.java:155"
        }
      ],
      "number": 1,
      "commentIndex": 0,
      "bugId": "57716",
      "date": "2004-04-07T12:38:25+02:00",
      "product": "JDT",
      "component": "Core",
      "severity": "normal"
    }
  ],
  "groupId": "57716",
  "bugId": "57716",
  "date": "2004-04-07T12:38:25+02:00",
  "product": "JDT",
  "component": "Core",
  "severity": "normal"
}