{
  "comments": [
    "no reproducable steps, sorry\n\n\norg.eclipse.swt.SWTException: Invalid thread access\n        at org.eclipse.swt.SWT.error(SWT.java:2625)\n        at org.eclipse.swt.SWT.error(SWT.java:2555)\n        at org.eclipse.swt.widgets.Display.error(Display.java:701)\n        at org.eclipse.swt.widgets.Display.checkDevice(Display.java:526)\n        at org.eclipse.swt.widgets.Display.getActiveShell(Display.java:788)\n        at org.eclipse.ui.internal.Workbench.getActiveWorkbenchWindow\n(Workbench.\njava:587)\n        at org.eclipse.jdt.internal.ui.text.HTMLPrinter.insertPageProlog\n(HTMLPri\nnter.java:97)\n        at org.eclipse.jdt.internal.ui.text.HTMLPrinter.addPageProlog\n(HTMLPrinte\nr.java:110)\n        at \norg.eclipse.jdt.internal.ui.text.java.hover.AnnotationHover.formatMes\nsage(AnnotationHover.java:49)\n        at \norg.eclipse.jdt.internal.ui.text.java.hover.AnnotationHover.getHoverI\nnfo(AnnotationHover.java:90)\n        at \norg.eclipse.jdt.internal.ui.text.java.hover.JavaEditorTextHoverProxy.\ngetHoverInfo(JavaEditorTextHoverProxy.java:69)\n        at org.eclipse.jface.text.TextViewerHoverManager$4.run\n(TextViewerHoverMa\nnager.java:161)",
    "*** Bug 57985 has been marked as a duplicate of this bug. ***",
    "No action planned.",
    "The real cause for this is bug 57384 but I\u0027ve now changed the code since we run\ninto the null-case most of the time and hence the system color didn\u0027t get picked up.",
    "*** Bug 58431 has been marked as a duplicate of this bug. ***"
  ],
  "commentCreationDates": [
    "2004-04-08T15:57:52+02:00",
    "2004-04-13T12:32:47+02:00",
    "2004-04-13T12:51:00+02:00",
    "2004-04-14T12:35:06+02:00",
    "2004-04-14T12:35:23+02:00"
  ],
  "traces": [
    {
      "exceptionType": "org.eclipse.swt.SWTException",
      "message": "Invalid thread access",
      "elements": [
        {
          "method": "org.eclipse.swt.SWT.error",
          "source": "SWT.java:2625"
        },
        {
          "method": "org.eclipse.swt.SWT.error",
          "source": "SWT.java:2555"
        },
        {
          "method": "org.eclipse.swt.widgets.Display.error",
          "source": "Display.java:701"
        },
        {
          "method": "org.eclipse.swt.widgets.Display.checkDevice",
          "source": "Display.java:526"
        },
        {
          "method": "org.eclipse.swt.widgets.Display.getActiveShell",
          "source": "Display.java:788"
        },
        {
          "method": "org.eclipse.ui.internal.Workbench.getActiveWorkbenchWindow",
          "source": "Workbench. java:587"
        },
        {
          "method": "org.eclipse.jdt.internal.ui.text.HTMLPrinter.insertPageProlog",
          "source": "HTMLPri nter.java:97"
        },
        {
          "method": "org.eclipse.jdt.internal.ui.text.HTMLPrinter.addPageProlog",
          "source": "HTMLPrinte r.java:110"
        },
        {
          "method": "org.eclipse.jdt.internal.ui.text.java.hover.AnnotationHover.formatMessage",
          "source": "AnnotationHover.java:49"
        },
        {
          "method": "org.eclipse.jdt.internal.ui.text.java.hover.AnnotationHover.getHoverInfo",
          "source": "AnnotationHover.java:90"
        },
        {
          "method": "org.eclipse.jdt.internal.ui.text.java.hover.JavaEditorTextHoverProxy.getHoverInfo",
          "source": "JavaEditorTextHoverProxy.java:69"
        },
        {
          "method": "org.eclipse.jface.text.TextViewerHoverManager$4.run",
          "source": "TextViewerHoverMa nager.java:161"
        }
      ],
      "number": 0,
      "commentIndex": 0,
      "bugId": "57895",
      "date": "2004-04-08T15:57:52+02:00",
      "product": "JDT",
      "component": "Text",
      "severity": "normal"
    }
  ],
  "groupId": "57895",
  "bugId": "57895",
  "date": "2004-04-08T15:57:52+02:00",
  "product": "JDT",
  "component": "Text",
  "severity": "normal"
}