{
  "comments": [
    "I had a command prompt in the directory of the project I was refactoring.  It \ngave me an error popup telling me it couldn\u0027t complete which I would expect.  I \nhit undo but it seems to have done everything but remove the directory I had a \ncommand prompt in.  It also gave me the following exception:\n\norg.eclipse.core.internal.resources.ResourceException: Problems encountered whil\ne moving resources.\n        at java.lang.Throwable.\u003cinit\u003e(Throwable.java)\n        at java.lang.Throwable.\u003cinit\u003e(Throwable.java)\n        at org.eclipse.core.runtime.CoreException.\u003cinit\u003e(CoreException.java)\n        at org.eclipse.core.internal.resources.ResourceException.\u003cinit\u003e(Resource\nException.java:39)\n        at org.eclipse.core.internal.resources.Resource.move(Resource.java:1123)\n\n        at org.eclipse.jdt.internal.corext.refactoring.changes.RenameResourceCha\nnge.perform(RenameResourceChange.java:66)\n        at org.eclipse.jdt.internal.ui.refactoring.PerformChangeOperation$1.run(\nPerformChangeOperation.java:173)\n        at org.eclipse.jdt.internal.core.BatchOperation.executeOperation(BatchOp\neration.java:34)\n        at org.eclipse.jdt.internal.core.JavaModelOperation.execute(JavaModelOpe\nration.java:365)\n        at org.eclipse.jdt.internal.core.JavaModelOperation.run(JavaModelOperati\non.java)\n        at org.eclipse.core.internal.resources.Workspace.run(Workspace.java:1595\n)\n        at org.eclipse.jdt.core.JavaCore.run(JavaCore.java:2711)\n        at org.eclipse.jdt.internal.ui.refactoring.PerformChangeOperation.execut\neChange(PerformChangeOperation.java:183)\n        at org.eclipse.jdt.internal.ui.refactoring.PerformChangeOperation.run(Pe\nrformChangeOperation.java:145)\n        at org.eclipse.jface.operation.ModalContext.runInCurrentThread(ModalCont\next.java:302)\n        at org.eclipse.jface.operation.ModalContext.run(ModalContext.java:252)\n        at org.eclipse.jface.dialogs.ProgressMonitorDialog.run(ProgressMonitorDi\nalog.java:357)\n        at org.eclipse.jdt.internal.ui.refactoring.PerformRefactoringUtil.perfor\nmRefactoring(PerformRefactoringUtil.java:53)\n        at org.eclipse.jdt.internal.ui.refactoring.actions.RefactoringStarter.ac\ntivate(RefactoringStarter.java:109)\n        at org.eclipse.jdt.internal.ui.refactoring.RefactoringSupport$AbstractRe\nnameSupport.rename(RefactoringSupport.java:170)\n        at org.eclipse.jdt.internal.ui.refactoring.actions.RenameResourceAction.\nrun(RenameResourceAction.java:53)\n        at org.eclipse.jdt.internal.ui.refactoring.actions.RenameResourceAction.\nrun(RenameResourceAction.java:42)\n        at org.eclipse.jdt.ui.actions.RenameAction.run(RenameAction.java:118)\n        at org.eclipse.jdt.ui.actions.SelectionDispatchAction.dispatchRun(Select\nionDispatchAction.java:191)\n        at org.eclipse.jdt.ui.actions.SelectionDispatchAction.run(SelectionDispa\ntchAction.java:169)\n        at org.eclipse.jface.action.Action.runWithEvent(Action.java:842)\n        at org.eclipse.jface.action.ActionContributionItem.handleWidgetSelection\n(ActionContributionItem.java:456)\n        at org.eclipse.jface.action.ActionContributionItem.handleWidgetEvent(Act\nionContributionItem.java:403)\n        at org.eclipse.jface.action.ActionContributionItem.access$0(ActionContri\nbutionItem.java:397)\n        at org.eclipse.jface.action.ActionContributionItem$ActionListener.handle\nEvent(ActionContributionItem.java:72)\n        at org.eclipse.swt.widgets.EventTable.sendEvent(EventTable.java)\n        at org.eclipse.swt.widgets.Widget.sendEvent(Widget.java)\n        at org.eclipse.swt.widgets.Display.runDeferredEvents(Display.java)\n        at org.eclipse.swt.widgets.Display.readAndDispatch(Display.java)\n        at org.eclipse.ui.internal.Workbench.runEventLoop(Workbench.java:1402)\n        at org.eclipse.ui.internal.Workbench.run(Workbench.java:1385)\n        at org.eclipse.core.internal.boot.InternalBootLoader.run(InternalBootLoa\nder.java:858)\n        at org.eclipse.core.boot.BootLoader.run(BootLoader.java:461)\n        at java.lang.reflect.AccessibleObject.invokeL(AccessibleObject.java:207)\n\n        at java.lang.reflect.Method.invoke(Method.java:271)\n        at org.eclipse.core.launcher.Main.basicRun(Main.java:291)\n        at org.eclipse.core.launcher.Main.run(Main.java:747)\n        at org.eclipse.core.launcher.Main.main(Main.java:583)\n!ENTRY org.eclipse.core.resources 4 4 Apr 07, 2004 12:17:38.829\n!MESSAGE Problems encountered while moving resources.\n!SUBENTRY 1 org.eclipse.core.resources 4 273 Apr 07, 2004 12:17:38.829\n!MESSAGE Copy successful, but problems occurred removing old resources\n!SUBENTRY 2 org.eclipse.core.resources 4 273 Apr 07, 2004 12:17:38.829\n!MESSAGE Could not delete: D:\\workspaces\\ws_4_5_04\\WebSrv14AD.\n\n********************************************************************\nI went to move it back but the directory was still there, of course.  Again, it \ngave me an expected error but still gave the following stack trace:\n\n!ENTRY org.eclipse.jdt.ui 4 10001 Apr 07, 2004 12:18:28.781\n!MESSAGE Internal Error\n!STACK 1\norg.eclipse.core.internal.resources.ResourceException: Problems encountered whil\ne moving resources.\n        at java.lang.Throwable.\u003cinit\u003e(Throwable.java)\n        at java.lang.Throwable.\u003cinit\u003e(Throwable.java)\n        at org.eclipse.core.runtime.CoreException.\u003cinit\u003e(CoreException.java)\n        at org.eclipse.core.internal.resources.ResourceException.\u003cinit\u003e(Resource\nException.java:39)\n        at org.eclipse.core.internal.resources.Resource.move(Resource.java:1123)\n\n        at org.eclipse.jdt.internal.corext.refactoring.changes.RenameResourceCha\nnge.perform(RenameResourceChange.java:66)\n        at org.eclipse.jdt.internal.ui.refactoring.PerformChangeOperation$1.run(\nPerformChangeOperation.java:173)\n        at org.eclipse.jdt.internal.core.BatchOperation.executeOperation(BatchOp\neration.java:34)\n        at org.eclipse.jdt.internal.core.JavaModelOperation.execute(JavaModelOpe\nration.java:365)\n        at org.eclipse.jdt.internal.core.JavaModelOperation.run(JavaModelOperati\non.java)\n        at org.eclipse.core.internal.resources.Workspace.run(Workspace.java:1595\n)\n        at org.eclipse.jdt.core.JavaCore.run(JavaCore.java:2711)\n        at org.eclipse.jdt.internal.ui.refactoring.PerformChangeOperation.execut\neChange(PerformChangeOperation.java:183)\n        at org.eclipse.jdt.internal.ui.refactoring.PerformChangeOperation.run(Pe\nrformChangeOperation.java:145)\n        at org.eclipse.jface.operation.ModalContext.runInCurrentThread(ModalCont\next.java:302)\n        at org.eclipse.jface.operation.ModalContext.run(ModalContext.java:252)\n        at org.eclipse.jface.dialogs.ProgressMonitorDialog.run(ProgressMonitorDi\nalog.java:357)\n        at org.eclipse.jdt.internal.ui.refactoring.PerformRefactoringUtil.perfor\nmRefactoring(PerformRefactoringUtil.java:53)\n        at org.eclipse.jdt.internal.ui.refactoring.actions.RefactoringStarter.ac\ntivate(RefactoringStarter.java:109)\n        at org.eclipse.jdt.internal.ui.refactoring.RefactoringSupport$AbstractRe\nnameSupport.rename(RefactoringSupport.java:170)\n        at org.eclipse.jdt.internal.ui.refactoring.actions.RenameResourceAction.\nrun(RenameResourceAction.java:53)\n        at org.eclipse.jdt.internal.ui.refactoring.actions.RenameResourceAction.\nrun(RenameResourceAction.java:42)\n        at org.eclipse.jdt.ui.actions.RenameAction.run(RenameAction.java:118)\n        at org.eclipse.jdt.ui.actions.SelectionDispatchAction.dispatchRun(Select\nionDispatchAction.java:191)\n        at org.eclipse.jdt.ui.actions.SelectionDispatchAction.run(SelectionDispa\ntchAction.java:169)\n        at org.eclipse.jface.action.Action.runWithEvent(Action.java:842)\n        at org.eclipse.jface.action.ActionContributionItem.handleWidgetSelection\n(ActionContributionItem.java:456)\n        at org.eclipse.jface.action.ActionContributionItem.handleWidgetEvent(Act\nionContributionItem.java:403)\n        at org.eclipse.jface.action.ActionContributionItem.access$0(ActionContri\nbutionItem.java:397)\n        at org.eclipse.jface.action.ActionContributionItem$ActionListener.handle\nEvent(ActionContributionItem.java:72)\n        at org.eclipse.swt.widgets.EventTable.sendEvent(EventTable.java)\n        at org.eclipse.swt.widgets.Widget.sendEvent(Widget.java)\n        at org.eclipse.swt.widgets.Display.runDeferredEvents(Display.java)\n        at org.eclipse.swt.widgets.Display.readAndDispatch(Display.java)\n        at org.eclipse.ui.internal.Workbench.runEventLoop(Workbench.java:1402)\n        at org.eclipse.ui.internal.Workbench.run(Workbench.java:1385)\n        at org.eclipse.core.internal.boot.InternalBootLoader.run(InternalBootLoa\nder.java:858)\n        at org.eclipse.core.boot.BootLoader.run(BootLoader.java:461)\n        at java.lang.reflect.AccessibleObject.invokeL(AccessibleObject.java:207)\n\n        at java.lang.reflect.Method.invoke(Method.java:271)\n        at org.eclipse.core.launcher.Main.basicRun(Main.java:291)\n        at org.eclipse.core.launcher.Main.run(Main.java:747)\n        at org.eclipse.core.launcher.Main.main(Main.java:583)\n!ENTRY org.eclipse.core.resources 1 4 Apr 07, 2004 12:18:28.931\n!MESSAGE Problems encountered while moving resources.\n!SUBENTRY 1 org.eclipse.core.resources 1 4 Apr 07, 2004 12:18:28.931\n!MESSAGE Could not move: /WebSrv14AD_PI.\n!STACK 1\norg.eclipse.core.internal.resources.ResourceException: Resource already exists o\nn disk: D:\\workspaces\\ws_4_5_04\\WebSrv14AD.\n        at java.lang.Throwable.\u003cinit\u003e(Throwable.java)\n        at java.lang.Throwable.\u003cinit\u003e(Throwable.java)\n        at org.eclipse.core.runtime.CoreException.\u003cinit\u003e(CoreException.java)\n        at org.eclipse.core.internal.resources.ResourceException.\u003cinit\u003e(Resource\nException.java:30)\n        at org.eclipse.core.internal.localstore.FileSystemStore.move(FileSystemS\ntore.java:222)\n        at org.eclipse.core.internal.resources.ResourceTree.moveInFileSystem(Res\nourceTree.java:1113)\n        at org.eclipse.core.internal.resources.ResourceTree.moveProjectContent(R\nesourceTree.java:761)\n        at org.eclipse.core.internal.resources.ResourceTree.standardMoveProject(\nResourceTree.java:1077)\n        at org.eclipse.core.internal.resources.Resource.move(Resource.java:1111)\n\n        at org.eclipse.jdt.internal.corext.refactoring.changes.RenameResourceCha\nnge.perform(RenameResourceChange.java:66)\n        at org.eclipse.jdt.internal.ui.refactoring.PerformChangeOperation$1.run(\nPerformChangeOperation.java:173)\n        at org.eclipse.jdt.internal.core.BatchOperation.executeOperation(BatchOp\neration.java:34)\n        at org.eclipse.jdt.internal.core.JavaModelOperation.execute(JavaModelOpe\nration.java:365)\n        at org.eclipse.jdt.internal.core.JavaModelOperation.run(JavaModelOperati\non.java)\n        at org.eclipse.core.internal.resources.Workspace.run(Workspace.java:1595\n)\n        at org.eclipse.jdt.core.JavaCore.run(JavaCore.java:2711)\n        at org.eclipse.jdt.internal.ui.refactoring.PerformChangeOperation.execut\neChange(PerformChangeOperation.java:183)\n        at org.eclipse.jdt.internal.ui.refactoring.PerformChangeOperation.run(Pe\nrformChangeOperation.java:145)\n        at org.eclipse.jface.operation.ModalContext.runInCurrentThread(ModalCont\next.java:302)\n        at org.eclipse.jface.operation.ModalContext.run(ModalContext.java:252)\n        at org.eclipse.jface.dialogs.ProgressMonitorDialog.run(ProgressMonitorDi\nalog.java:357)\n        at org.eclipse.jdt.internal.ui.refactoring.PerformRefactoringUtil.perfor\nmRefactoring(PerformRefactoringUtil.java:53)\n        at org.eclipse.jdt.internal.ui.refactoring.actions.RefactoringStarter.ac\ntivate(RefactoringStarter.java:109)\n        at org.eclipse.jdt.internal.ui.refactoring.RefactoringSupport$AbstractRe\nnameSupport.rename(RefactoringSupport.java:170)\n        at org.eclipse.jdt.internal.ui.refactoring.actions.RenameResourceAction.\nrun(RenameResourceAction.java:53)\n        at org.eclipse.jdt.internal.ui.refactoring.actions.RenameResourceAction.\nrun(RenameResourceAction.java:42)\n        at org.eclipse.jdt.ui.actions.RenameAction.run(RenameAction.java:118)\n        at org.eclipse.jdt.ui.actions.SelectionDispatchAction.dispatchRun(Select\nionDispatchAction.java:191)\n        at org.eclipse.jdt.ui.actions.SelectionDispatchAction.run(SelectionDispa\ntchAction.java:169)\n        at org.eclipse.jface.action.Action.runWithEvent(Action.java:842)\n        at org.eclipse.jface.action.ActionContributionItem.handleWidgetSelection\n(ActionContributionItem.java:456)\n        at org.eclipse.jface.action.ActionContributionItem.handleWidgetEvent(Act\nionContributionItem.java:403)\n        at org.eclipse.jface.action.ActionContributionItem.access$0(ActionContri\nbutionItem.java:397)\n        at org.eclipse.jface.action.ActionContributionItem$ActionListener.handle\nEvent(ActionContributionItem.java:72)\n        at org.eclipse.swt.widgets.EventTable.sendEvent(EventTable.java)\n        at org.eclipse.swt.widgets.Widget.sendEvent(Widget.java)\n        at org.eclipse.swt.widgets.Display.runDeferredEvents(Display.java)\n        at org.eclipse.swt.widgets.Display.readAndDispatch(Display.java)\n        at org.eclipse.ui.internal.Workbench.runEventLoop(Workbench.java:1402)\n        at org.eclipse.ui.internal.Workbench.run(Workbench.java:1385)\n        at org.eclipse.core.internal.boot.InternalBootLoader.run(InternalBootLoa\nder.java:858)\n        at org.eclipse.core.boot.BootLoader.run(BootLoader.java:461)\n        at java.lang.reflect.AccessibleObject.invokeL(AccessibleObject.java:207)\n\n        at java.lang.reflect.Method.invoke(Method.java:271)\n        at org.eclipse.core.launcher.Main.basicRun(Main.java:291)\n        at org.eclipse.core.launcher.Main.run(Main.java:747)\n        at org.eclipse.core.launcher.Main.main(Main.java:583)",
    "Moving to JDT UI for comments",
    "RC2\n\nI found the same problem, slightly different scenario.  Open a file (in my \ncase, a PowerPoint presentation *.ppt) from the Package Explorer.  Modify it \noutside of Eclipse.  Keep PowerPoint open.  Now attempt to rename the file.  \nSee the error message displayed and a couple internal errors that are added to \nthe log.",
    "Created an attachment (id\u003d12523)\nError message\n",
    "Created an attachment (id\u003d12524)\nError Log exceptions\n",
    "There are three different issues:\n\n- the fact that the target directory is locked by an external command prompt.\n  There is no way how we can detect this in Eclipse, so the operation will\n  always fail. But I agree that the error message could be improved.\n\n- the fact that the file you want to rename is locked by an external program.\n  This can\u0027t be detected either using normal Eclipse/JDK API.\n\n- the fact that the resource is out of sync. This is clearly a bug and should\n  be addressed. I looked over the code and this only happens for resource in \n  the package explorer. Renaming Java element does treat this correctly.",
    "I agree with all your facts.  I don\u0027t think it is a good idea to log three \nerrors for what will be a common user mistake, that\u0027s all.  The platform \nshould catch them, inform the user, and move on.",
    "The initial defect I submitted here has been fixed.  I can\u0027t speak to cases 2\nand 3 from Dirk\u0027s comment.",
    "Seeting to won\u0027t fix. We shouldn\u0027t automatically refresh a file. Other funtionaly also doesn\u0027t do that."
  ],
  "commentCreationDates": [
    "2004-04-08T20:26:01+02:00",
    "2004-05-18T19:06:32+02:00",
    "2004-06-18T21:25:51+02:00",
    "2004-06-18T21:26:15+02:00",
    "2004-06-18T21:26:33+02:00",
    "2004-06-18T23:02:45+02:00",
    "2004-06-19T00:02:24+02:00",
    "2005-08-24T17:39:40+02:00",
    "2006-06-02T11:51:20+02:00"
  ],
  "traces": [
    {
      "exceptionType": "org.eclipse.core.internal.resources.ResourceException",
      "message": "Problems encountered whil e moving resources.",
      "elements": [
        {
          "method": "java.lang.Throwable.\u003cinit\u003e",
          "source": "Throwable.java"
        },
        {
          "method": "java.lang.Throwable.\u003cinit\u003e",
          "source": "Throwable.java"
        },
        {
          "method": "org.eclipse.core.runtime.CoreException.\u003cinit\u003e",
          "source": "CoreException.java"
        },
        {
          "method": "org.eclipse.core.internal.resources.ResourceException.\u003cinit\u003e",
          "source": "Resource Exception.java:39"
        },
        {
          "method": "org.eclipse.core.internal.resources.Resource.move",
          "source": "Resource.java:1123"
        },
        {
          "method": "org.eclipse.jdt.internal.corext.refactoring.changes.RenameResourceChange.perform",
          "source": "RenameResourceChange.java:66"
        },
        {
          "method": "org.eclipse.jdt.internal.ui.refactoring.PerformChangeOperation$1.run",
          "source": " PerformChangeOperation.java:173"
        },
        {
          "method": "org.eclipse.jdt.internal.core.BatchOperation.executeOperation",
          "source": "BatchOp eration.java:34"
        },
        {
          "method": "org.eclipse.jdt.internal.core.JavaModelOperation.execute",
          "source": "JavaModelOpe ration.java:365"
        },
        {
          "method": "org.eclipse.jdt.internal.core.JavaModelOperation.run",
          "source": "JavaModelOperati on.java"
        },
        {
          "method": "org.eclipse.core.internal.resources.Workspace.run",
          "source": "Workspace.java:1595 "
        },
        {
          "method": "org.eclipse.jdt.core.JavaCore.run",
          "source": "JavaCore.java:2711"
        },
        {
          "method": "org.eclipse.jdt.internal.ui.refactoring.PerformChangeOperation.executeChange",
          "source": "PerformChangeOperation.java:183"
        },
        {
          "method": "org.eclipse.jdt.internal.ui.refactoring.PerformChangeOperation.run",
          "source": "Pe rformChangeOperation.java:145"
        },
        {
          "method": "org.eclipse.jface.operation.ModalContext.runInCurrentThread",
          "source": "ModalCont ext.java:302"
        },
        {
          "method": "org.eclipse.jface.operation.ModalContext.run",
          "source": "ModalContext.java:252"
        },
        {
          "method": "org.eclipse.jface.dialogs.ProgressMonitorDialog.run",
          "source": "ProgressMonitorDi alog.java:357"
        },
        {
          "method": "org.eclipse.jdt.internal.ui.refactoring.PerformRefactoringUtil.performRefactoring",
          "source": "PerformRefactoringUtil.java:53"
        },
        {
          "method": "org.eclipse.jdt.internal.ui.refactoring.actions.RefactoringStarter.activate",
          "source": "RefactoringStarter.java:109"
        },
        {
          "method": "org.eclipse.jdt.internal.ui.refactoring.RefactoringSupport$AbstractRenameSupport.rename",
          "source": "RefactoringSupport.java:170"
        },
        {
          "method": "org.eclipse.jdt.internal.ui.refactoring.actions.RenameResourceAction.run",
          "source": "RenameResourceAction.java:53"
        },
        {
          "method": "org.eclipse.jdt.internal.ui.refactoring.actions.RenameResourceAction.run",
          "source": "RenameResourceAction.java:42"
        },
        {
          "method": "org.eclipse.jdt.ui.actions.RenameAction.run",
          "source": "RenameAction.java:118"
        },
        {
          "method": "org.eclipse.jdt.ui.actions.SelectionDispatchAction.dispatchRun",
          "source": "Select ionDispatchAction.java:191"
        },
        {
          "method": "org.eclipse.jdt.ui.actions.SelectionDispatchAction.run",
          "source": "SelectionDispa tchAction.java:169"
        },
        {
          "method": "org.eclipse.jface.action.Action.runWithEvent",
          "source": "Action.java:842"
        },
        {
          "method": "org.eclipse.jface.action.ActionContributionItem.handleWidgetSelection",
          "source": "ActionContributionItem.java:456"
        },
        {
          "method": "org.eclipse.jface.action.ActionContributionItem.handleWidgetEvent",
          "source": "Act ionContributionItem.java:403"
        },
        {
          "method": "org.eclipse.jface.action.ActionContributionItem.access$0",
          "source": "ActionContri butionItem.java:397"
        },
        {
          "method": "org.eclipse.jface.action.ActionContributionItem$ActionListener.handleEvent",
          "source": "ActionContributionItem.java:72"
        },
        {
          "method": "org.eclipse.swt.widgets.EventTable.sendEvent",
          "source": "EventTable.java"
        },
        {
          "method": "org.eclipse.swt.widgets.Widget.sendEvent",
          "source": "Widget.java"
        },
        {
          "method": "org.eclipse.swt.widgets.Display.runDeferredEvents",
          "source": "Display.java"
        },
        {
          "method": "org.eclipse.swt.widgets.Display.readAndDispatch",
          "source": "Display.java"
        },
        {
          "method": "org.eclipse.ui.internal.Workbench.runEventLoop",
          "source": "Workbench.java:1402"
        },
        {
          "method": "org.eclipse.ui.internal.Workbench.run",
          "source": "Workbench.java:1385"
        },
        {
          "method": "org.eclipse.core.internal.boot.InternalBootLoader.run",
          "source": "InternalBootLoa der.java:858"
        },
        {
          "method": "org.eclipse.core.boot.BootLoader.run",
          "source": "BootLoader.java:461"
        },
        {
          "method": "java.lang.reflect.AccessibleObject.invokeL",
          "source": "AccessibleObject.java:207"
        },
        {
          "method": "java.lang.reflect.Method.invoke",
          "source": "Method.java:271"
        },
        {
          "method": "org.eclipse.core.launcher.Main.basicRun",
          "source": "Main.java:291"
        },
        {
          "method": "org.eclipse.core.launcher.Main.run",
          "source": "Main.java:747"
        },
        {
          "method": "org.eclipse.core.launcher.Main.main",
          "source": "Main.java:583"
        }
      ],
      "number": 0,
      "commentIndex": 0,
      "bugId": "57951",
      "date": "2004-04-08T20:26:01+02:00",
      "product": "JDT",
      "component": "UI",
      "severity": "normal"
    },
    {
      "exceptionType": "org.eclipse.core.internal.resources.ResourceException",
      "message": "Problems encountered whil e moving resources.",
      "elements": [
        {
          "method": "java.lang.Throwable.\u003cinit\u003e",
          "source": "Throwable.java"
        },
        {
          "method": "java.lang.Throwable.\u003cinit\u003e",
          "source": "Throwable.java"
        },
        {
          "method": "org.eclipse.core.runtime.CoreException.\u003cinit\u003e",
          "source": "CoreException.java"
        },
        {
          "method": "org.eclipse.core.internal.resources.ResourceException.\u003cinit\u003e",
          "source": "Resource Exception.java:39"
        },
        {
          "method": "org.eclipse.core.internal.resources.Resource.move",
          "source": "Resource.java:1123"
        },
        {
          "method": "org.eclipse.jdt.internal.corext.refactoring.changes.RenameResourceChange.perform",
          "source": "RenameResourceChange.java:66"
        },
        {
          "method": "org.eclipse.jdt.internal.ui.refactoring.PerformChangeOperation$1.run",
          "source": " PerformChangeOperation.java:173"
        },
        {
          "method": "org.eclipse.jdt.internal.core.BatchOperation.executeOperation",
          "source": "BatchOp eration.java:34"
        },
        {
          "method": "org.eclipse.jdt.internal.core.JavaModelOperation.execute",
          "source": "JavaModelOpe ration.java:365"
        },
        {
          "method": "org.eclipse.jdt.internal.core.JavaModelOperation.run",
          "source": "JavaModelOperati on.java"
        },
        {
          "method": "org.eclipse.core.internal.resources.Workspace.run",
          "source": "Workspace.java:1595 "
        },
        {
          "method": "org.eclipse.jdt.core.JavaCore.run",
          "source": "JavaCore.java:2711"
        },
        {
          "method": "org.eclipse.jdt.internal.ui.refactoring.PerformChangeOperation.executeChange",
          "source": "PerformChangeOperation.java:183"
        },
        {
          "method": "org.eclipse.jdt.internal.ui.refactoring.PerformChangeOperation.run",
          "source": "Pe rformChangeOperation.java:145"
        },
        {
          "method": "org.eclipse.jface.operation.ModalContext.runInCurrentThread",
          "source": "ModalCont ext.java:302"
        },
        {
          "method": "org.eclipse.jface.operation.ModalContext.run",
          "source": "ModalContext.java:252"
        },
        {
          "method": "org.eclipse.jface.dialogs.ProgressMonitorDialog.run",
          "source": "ProgressMonitorDi alog.java:357"
        },
        {
          "method": "org.eclipse.jdt.internal.ui.refactoring.PerformRefactoringUtil.performRefactoring",
          "source": "PerformRefactoringUtil.java:53"
        },
        {
          "method": "org.eclipse.jdt.internal.ui.refactoring.actions.RefactoringStarter.activate",
          "source": "RefactoringStarter.java:109"
        },
        {
          "method": "org.eclipse.jdt.internal.ui.refactoring.RefactoringSupport$AbstractRenameSupport.rename",
          "source": "RefactoringSupport.java:170"
        },
        {
          "method": "org.eclipse.jdt.internal.ui.refactoring.actions.RenameResourceAction.run",
          "source": "RenameResourceAction.java:53"
        },
        {
          "method": "org.eclipse.jdt.internal.ui.refactoring.actions.RenameResourceAction.run",
          "source": "RenameResourceAction.java:42"
        },
        {
          "method": "org.eclipse.jdt.ui.actions.RenameAction.run",
          "source": "RenameAction.java:118"
        },
        {
          "method": "org.eclipse.jdt.ui.actions.SelectionDispatchAction.dispatchRun",
          "source": "Select ionDispatchAction.java:191"
        },
        {
          "method": "org.eclipse.jdt.ui.actions.SelectionDispatchAction.run",
          "source": "SelectionDispa tchAction.java:169"
        },
        {
          "method": "org.eclipse.jface.action.Action.runWithEvent",
          "source": "Action.java:842"
        },
        {
          "method": "org.eclipse.jface.action.ActionContributionItem.handleWidgetSelection",
          "source": "ActionContributionItem.java:456"
        },
        {
          "method": "org.eclipse.jface.action.ActionContributionItem.handleWidgetEvent",
          "source": "Act ionContributionItem.java:403"
        },
        {
          "method": "org.eclipse.jface.action.ActionContributionItem.access$0",
          "source": "ActionContri butionItem.java:397"
        },
        {
          "method": "org.eclipse.jface.action.ActionContributionItem$ActionListener.handleEvent",
          "source": "ActionContributionItem.java:72"
        },
        {
          "method": "org.eclipse.swt.widgets.EventTable.sendEvent",
          "source": "EventTable.java"
        },
        {
          "method": "org.eclipse.swt.widgets.Widget.sendEvent",
          "source": "Widget.java"
        },
        {
          "method": "org.eclipse.swt.widgets.Display.runDeferredEvents",
          "source": "Display.java"
        },
        {
          "method": "org.eclipse.swt.widgets.Display.readAndDispatch",
          "source": "Display.java"
        },
        {
          "method": "org.eclipse.ui.internal.Workbench.runEventLoop",
          "source": "Workbench.java:1402"
        },
        {
          "method": "org.eclipse.ui.internal.Workbench.run",
          "source": "Workbench.java:1385"
        },
        {
          "method": "org.eclipse.core.internal.boot.InternalBootLoader.run",
          "source": "InternalBootLoa der.java:858"
        },
        {
          "method": "org.eclipse.core.boot.BootLoader.run",
          "source": "BootLoader.java:461"
        },
        {
          "method": "java.lang.reflect.AccessibleObject.invokeL",
          "source": "AccessibleObject.java:207"
        },
        {
          "method": "java.lang.reflect.Method.invoke",
          "source": "Method.java:271"
        },
        {
          "method": "org.eclipse.core.launcher.Main.basicRun",
          "source": "Main.java:291"
        },
        {
          "method": "org.eclipse.core.launcher.Main.run",
          "source": "Main.java:747"
        },
        {
          "method": "org.eclipse.core.launcher.Main.main",
          "source": "Main.java:583"
        }
      ],
      "number": 1,
      "commentIndex": 0,
      "bugId": "57951",
      "date": "2004-04-08T20:26:01+02:00",
      "product": "JDT",
      "component": "UI",
      "severity": "normal"
    },
    {
      "exceptionType": "org.eclipse.core.internal.resources.ResourceException",
      "message": "Resource already exists o n disk: D:\\workspaces\\ws_4_5_04\\WebSrv14AD.",
      "elements": [
        {
          "method": "java.lang.Throwable.\u003cinit\u003e",
          "source": "Throwable.java"
        },
        {
          "method": "java.lang.Throwable.\u003cinit\u003e",
          "source": "Throwable.java"
        },
        {
          "method": "org.eclipse.core.runtime.CoreException.\u003cinit\u003e",
          "source": "CoreException.java"
        },
        {
          "method": "org.eclipse.core.internal.resources.ResourceException.\u003cinit\u003e",
          "source": "Resource Exception.java:30"
        },
        {
          "method": "org.eclipse.core.internal.localstore.FileSystemStore.move",
          "source": "FileSystemS tore.java:222"
        },
        {
          "method": "org.eclipse.core.internal.resources.ResourceTree.moveInFileSystem",
          "source": "Res ourceTree.java:1113"
        },
        {
          "method": "org.eclipse.core.internal.resources.ResourceTree.moveProjectContent",
          "source": "R esourceTree.java:761"
        },
        {
          "method": "org.eclipse.core.internal.resources.ResourceTree.standardMoveProject",
          "source": " ResourceTree.java:1077"
        },
        {
          "method": "org.eclipse.core.internal.resources.Resource.move",
          "source": "Resource.java:1111"
        },
        {
          "method": "org.eclipse.jdt.internal.corext.refactoring.changes.RenameResourceChange.perform",
          "source": "RenameResourceChange.java:66"
        },
        {
          "method": "org.eclipse.jdt.internal.ui.refactoring.PerformChangeOperation$1.run",
          "source": " PerformChangeOperation.java:173"
        },
        {
          "method": "org.eclipse.jdt.internal.core.BatchOperation.executeOperation",
          "source": "BatchOp eration.java:34"
        },
        {
          "method": "org.eclipse.jdt.internal.core.JavaModelOperation.execute",
          "source": "JavaModelOpe ration.java:365"
        },
        {
          "method": "org.eclipse.jdt.internal.core.JavaModelOperation.run",
          "source": "JavaModelOperati on.java"
        },
        {
          "method": "org.eclipse.core.internal.resources.Workspace.run",
          "source": "Workspace.java:1595 "
        },
        {
          "method": "org.eclipse.jdt.core.JavaCore.run",
          "source": "JavaCore.java:2711"
        },
        {
          "method": "org.eclipse.jdt.internal.ui.refactoring.PerformChangeOperation.executeChange",
          "source": "PerformChangeOperation.java:183"
        },
        {
          "method": "org.eclipse.jdt.internal.ui.refactoring.PerformChangeOperation.run",
          "source": "Pe rformChangeOperation.java:145"
        },
        {
          "method": "org.eclipse.jface.operation.ModalContext.runInCurrentThread",
          "source": "ModalCont ext.java:302"
        },
        {
          "method": "org.eclipse.jface.operation.ModalContext.run",
          "source": "ModalContext.java:252"
        },
        {
          "method": "org.eclipse.jface.dialogs.ProgressMonitorDialog.run",
          "source": "ProgressMonitorDi alog.java:357"
        },
        {
          "method": "org.eclipse.jdt.internal.ui.refactoring.PerformRefactoringUtil.performRefactoring",
          "source": "PerformRefactoringUtil.java:53"
        },
        {
          "method": "org.eclipse.jdt.internal.ui.refactoring.actions.RefactoringStarter.activate",
          "source": "RefactoringStarter.java:109"
        },
        {
          "method": "org.eclipse.jdt.internal.ui.refactoring.RefactoringSupport$AbstractRenameSupport.rename",
          "source": "RefactoringSupport.java:170"
        },
        {
          "method": "org.eclipse.jdt.internal.ui.refactoring.actions.RenameResourceAction.run",
          "source": "RenameResourceAction.java:53"
        },
        {
          "method": "org.eclipse.jdt.internal.ui.refactoring.actions.RenameResourceAction.run",
          "source": "RenameResourceAction.java:42"
        },
        {
          "method": "org.eclipse.jdt.ui.actions.RenameAction.run",
          "source": "RenameAction.java:118"
        },
        {
          "method": "org.eclipse.jdt.ui.actions.SelectionDispatchAction.dispatchRun",
          "source": "Select ionDispatchAction.java:191"
        },
        {
          "method": "org.eclipse.jdt.ui.actions.SelectionDispatchAction.run",
          "source": "SelectionDispa tchAction.java:169"
        },
        {
          "method": "org.eclipse.jface.action.Action.runWithEvent",
          "source": "Action.java:842"
        },
        {
          "method": "org.eclipse.jface.action.ActionContributionItem.handleWidgetSelection",
          "source": "ActionContributionItem.java:456"
        },
        {
          "method": "org.eclipse.jface.action.ActionContributionItem.handleWidgetEvent",
          "source": "Act ionContributionItem.java:403"
        },
        {
          "method": "org.eclipse.jface.action.ActionContributionItem.access$0",
          "source": "ActionContri butionItem.java:397"
        },
        {
          "method": "org.eclipse.jface.action.ActionContributionItem$ActionListener.handleEvent",
          "source": "ActionContributionItem.java:72"
        },
        {
          "method": "org.eclipse.swt.widgets.EventTable.sendEvent",
          "source": "EventTable.java"
        },
        {
          "method": "org.eclipse.swt.widgets.Widget.sendEvent",
          "source": "Widget.java"
        },
        {
          "method": "org.eclipse.swt.widgets.Display.runDeferredEvents",
          "source": "Display.java"
        },
        {
          "method": "org.eclipse.swt.widgets.Display.readAndDispatch",
          "source": "Display.java"
        },
        {
          "method": "org.eclipse.ui.internal.Workbench.runEventLoop",
          "source": "Workbench.java:1402"
        },
        {
          "method": "org.eclipse.ui.internal.Workbench.run",
          "source": "Workbench.java:1385"
        },
        {
          "method": "org.eclipse.core.internal.boot.InternalBootLoader.run",
          "source": "InternalBootLoa der.java:858"
        },
        {
          "method": "org.eclipse.core.boot.BootLoader.run",
          "source": "BootLoader.java:461"
        },
        {
          "method": "java.lang.reflect.AccessibleObject.invokeL",
          "source": "AccessibleObject.java:207"
        },
        {
          "method": "java.lang.reflect.Method.invoke",
          "source": "Method.java:271"
        },
        {
          "method": "org.eclipse.core.launcher.Main.basicRun",
          "source": "Main.java:291"
        },
        {
          "method": "org.eclipse.core.launcher.Main.run",
          "source": "Main.java:747"
        },
        {
          "method": "org.eclipse.core.launcher.Main.main",
          "source": "Main.java:583"
        }
      ],
      "number": 2,
      "commentIndex": 0,
      "bugId": "57951",
      "date": "2004-04-08T20:26:01+02:00",
      "product": "JDT",
      "component": "UI",
      "severity": "normal"
    }
  ],
  "groupId": "57951",
  "bugId": "57951",
  "date": "2004-04-08T20:26:01+02:00",
  "product": "JDT",
  "component": "UI",
  "severity": "normal"
}