{
  "comments": [
    "Reporter: Brook Zhang\nOS:  RHEL WS 3.0 -GTK \u0026 Windows 2003 Standard Edition\nLanguage: CHS/CHT/Korean\nBuild level: 200404071510(wswb-I20040407-200404121624)   \nJDK Version: IBM JDK 1.4.2 Beta\nTest case #:  CS18\nSummary: DBCS:Context search NLclass can\u0027t work well in C/C++ Search\n \nDescription:\nSteps to recreate problem:\n1-Create a Standard C/C++  project with \u003cNLprojectCPP\u003e name\n2-In the C/C++ Project View, right click on the \u003cNLprojectCPP\u003e,Select New--\n\u003eClass.\n3-Enter \u003cNLclass\u003e name with DBCS characters and check Inline and Include \nguard,and click Finish.\n4-Add a method \u003cNLmothod\u003e in \u003cNLclass\u003e.cpp and Select this method in Outline \nView.Then you can see the method is highlighted in \u003cNLclass\u003e.cpp\n5-Right click on the highlight and select Selection Search--\u003eReferences--\n\u003eWorkspace form the context menu.\n\n\u003c\u003cError\u003e\u003e   \n         DBCS:In the Search View,There are no found\n\u003c\u003cExpected Result\u003e\u003e\n         DBCS:Selected Search string show in search view correctly.",
    "for andrew ? bogdan ?",
    "Set dependency upon 58232 : once Bogdan investigates that I will triage these \nsimilar defects accordingly.  ",
    "Works for me with what is currently in CVS HEAD.  ",
    "I found that when Select \"Selection Search\"--\u003e\"References\"--\u003e\"Workspace\" form \nthe context menu.The old search view is poped up.But no item be found.The error \noccur in console :\n!MESSAGE Error\n!STACK 0\njava.lang.reflect.InvocationTargetException\n        at org.eclipse.jface.operation.ModalContext.run(ModalContext.java:283)\n        at org.eclipse.jface.dialogs.ProgressMonitorDialog.run\n(ProgressMonitorDialog.java:409)\n        at org.eclipse.cdt.internal.ui.search.actions.FindAction.performSearch\n(FindAction.java:254)\n        at org.eclipse.cdt.internal.ui.search.actions.FindAction.run\n(FindAction.java:205)\n        at org.eclipse.cdt.internal.ui.search.actions.FindAction.run\n(FindAction.java:149)\n        at org.eclipse.jface.action.Action.runWithEvent(Action.java:881)\n        at org.eclipse.jface.action.ActionContributionItem.handleWidgetSelection\n(ActionContributionItem.java:550)\n        at org.eclipse.jface.action.ActionContributionItem.access$2\n(ActionContributionItem.java:502)\n        at org.eclipse.jface.action.ActionContributionItem$5.handleEvent\n(ActionContributionItem.java:435)\n        at org.eclipse.swt.widgets.EventTable.sendEvent(EventTable.java\n(Compiled Code))\n        at org.eclipse.swt.widgets.Widget.sendEvent(Widget.java:939)\n        at org.eclipse.swt.widgets.Display.runDeferredEvents(Display.java:1953)\n        at org.eclipse.swt.widgets.Display.readAndDispatch(Display.java:1726)\n        at org.eclipse.ui.internal.Workbench.runEventLoop(Workbench.java:1436)\n        at org.eclipse.ui.internal.Workbench.runUI(Workbench.java:1407)\n        at org.eclipse.ui.internal.Workbench.createAndRunWorkbench\n(Workbench.java:244)\n        at org.eclipse.ui.PlatformUI.createAndRunWorkbench(PlatformUI.java:140)\n        at org.eclipse.ui.internal.ide.IDEApplication.run\n(IDEApplication.java:90)\n        at org.eclipse.core.internal.runtime.PlatformActivator$1.run\n(PlatformActivator.java:280)\n        at org.eclipse.core.runtime.adaptor.EclipseStarter.run\n(EclipseStarter.java:241)\n        at org.eclipse.core.runtime.adaptor.EclipseStarter.run\n(EclipseStarter.java:117)\n        at sun.reflect.NativeMethodAccessorImpl.invoke0(Native Method)\n        at sun.reflect.NativeMethodAccessorImpl.invoke\n(NativeMethodAccessorImpl.java:84)\n        at sun.reflect.NativeMethodAccessorImpl.invoke\n(NativeMethodAccessorImpl.java:57)\n        at sun.reflect.DelegatingMethodAccessorImpl.invoke\n(DelegatingMethodAccessorImpl.java:59)\n        at java.lang.reflect.Method.invoke(Method.java:389)\n        at org.eclipse.core.launcher.Main.basicRun(Main.java:267)\n        at org.eclipse.core.launcher.Main.run(Main.java:692)\n        at org.eclipse.core.launcher.Main.main(Main.java:676)\nCaused by: org.eclipse.swt.SWTException: Invalid thread access\n        at org.eclipse.swt.SWT.error(SWT.java:2659)\n        at org.eclipse.swt.SWT.error(SWT.java(Inlined Compiled Code))\n        at org.eclipse.swt.SWT.error(SWT.java(Inlined Compiled Code))\n        at org.eclipse.swt.widgets.Display.error(Display.java(Inlined Compiled \nCode))\n        at org.eclipse.swt.widgets.Display.checkDevice(Display.java(Inlined \nCompiled Code))\n        at org.eclipse.swt.widgets.Display.getActiveShell(Display.java(Compiled \nCode))\n        at org.eclipse.ui.internal.Workbench.getActiveWorkbenchWindow\n(Workbench.java:581)\n        at org.eclipse.search.internal.ui.SearchPlugin.getActiveWorkbenchWindow\n(SearchPlugin.java:101)\n        at org.eclipse.search.internal.ui.SearchPlugin.getActivePage\n(SearchPlugin.java:164)\n        at org.eclipse.search.internal.ui.SearchPlugin.getSearchResultView\n(SearchPlugin.java:213)\n        at org.eclipse.search.ui.SearchUI.getSearchResultView(SearchUI.java:121)\n        at \norg.eclipse.cdt.internal.ui.search.CSearchResultCollector.aboutToStart\n(CSearchResultCollector.java:63)\n        at org.eclipse.cdt.core.search.SearchEngine.search\n(SearchEngine.java:166)\n        at org.eclipse.cdt.internal.ui.search.CSearchOperation.run\n(CSearchOperation.java:80)\n        at org.eclipse.jface.operation.ModalContext$ModalContextThread.run\n(ModalContext.java:101)\n\n",
    "This defect is verified on new 200404190838(wswb-I20040422-\n200404231600),because the *.cpp can\u0027t open by C editor(see bug 59898),So the \nsearch don\u0027t work.Reopen it.  ",
    "Assigning to Kleo, rumour has it he\u0027s taking care of figuring out how to \ndeliver a workbench build where this is working.  ",
    "This defect also exist on build IES3.0-20040429(CDT 20040428).",
    "This is the same bug as 61570 reported from the BIDI testing - the issue is \nsearch not working for methods that contain NL characters.\n\n*** This bug has been marked as a duplicate of 61570 ***"
  ],
  "commentCreationDates": [
    "2004-04-13T07:56:50+02:00",
    "2004-04-13T21:45:48+02:00",
    "2004-04-14T15:49:37+02:00",
    "2004-04-20T20:18:36+02:00",
    "2004-04-21T10:14:08+02:00",
    "2004-04-26T12:26:42+02:00",
    "2004-04-26T17:46:23+02:00",
    "2004-04-30T08:27:10+02:00",
    "2004-05-18T16:20:50+02:00"
  ],
  "traces": [
    {
      "exceptionType": "java.lang.reflect.InvocationTargetException",
      "elements": [
        {
          "method": "org.eclipse.jface.operation.ModalContext.run",
          "source": "ModalContext.java:283"
        },
        {
          "method": "org.eclipse.jface.dialogs.ProgressMonitorDialog.run",
          "source": "ProgressMonitorDialog.java:409"
        },
        {
          "method": "org.eclipse.cdt.internal.ui.search.actions.FindAction.performSearch",
          "source": "FindAction.java:254"
        },
        {
          "method": "org.eclipse.cdt.internal.ui.search.actions.FindAction.run",
          "source": "FindAction.java:205"
        },
        {
          "method": "org.eclipse.cdt.internal.ui.search.actions.FindAction.run",
          "source": "FindAction.java:149"
        },
        {
          "method": "org.eclipse.jface.action.Action.runWithEvent",
          "source": "Action.java:881"
        },
        {
          "method": "org.eclipse.jface.action.ActionContributionItem.handleWidgetSelection",
          "source": "ActionContributionItem.java:550"
        },
        {
          "method": "org.eclipse.jface.action.ActionContributionItem.access$2",
          "source": "ActionContributionItem.java:502"
        },
        {
          "method": "org.eclipse.jface.action.ActionContributionItem$5.handleEvent",
          "source": "ActionContributionItem.java:435"
        },
        {
          "method": "org.eclipse.swt.widgets.EventTable.sendEvent",
          "source": "EventTable.java (Compiled Code)"
        },
        {
          "method": "org.eclipse.swt.widgets.Widget.sendEvent",
          "source": "Widget.java:939"
        },
        {
          "method": "org.eclipse.swt.widgets.Display.runDeferredEvents",
          "source": "Display.java:1953"
        },
        {
          "method": "org.eclipse.swt.widgets.Display.readAndDispatch",
          "source": "Display.java:1726"
        },
        {
          "method": "org.eclipse.ui.internal.Workbench.runEventLoop",
          "source": "Workbench.java:1436"
        },
        {
          "method": "org.eclipse.ui.internal.Workbench.runUI",
          "source": "Workbench.java:1407"
        },
        {
          "method": "org.eclipse.ui.internal.Workbench.createAndRunWorkbench",
          "source": "Workbench.java:244"
        },
        {
          "method": "org.eclipse.ui.PlatformUI.createAndRunWorkbench",
          "source": "PlatformUI.java:140"
        },
        {
          "method": "org.eclipse.ui.internal.ide.IDEApplication.run",
          "source": "IDEApplication.java:90"
        },
        {
          "method": "org.eclipse.core.internal.runtime.PlatformActivator$1.run",
          "source": "PlatformActivator.java:280"
        },
        {
          "method": "org.eclipse.core.runtime.adaptor.EclipseStarter.run",
          "source": "EclipseStarter.java:241"
        },
        {
          "method": "org.eclipse.core.runtime.adaptor.EclipseStarter.run",
          "source": "EclipseStarter.java:117"
        },
        {
          "method": "sun.reflect.NativeMethodAccessorImpl.invoke0",
          "source": "Native Method"
        },
        {
          "method": "sun.reflect.NativeMethodAccessorImpl.invoke",
          "source": "NativeMethodAccessorImpl.java:84"
        },
        {
          "method": "sun.reflect.NativeMethodAccessorImpl.invoke",
          "source": "NativeMethodAccessorImpl.java:57"
        },
        {
          "method": "sun.reflect.DelegatingMethodAccessorImpl.invoke",
          "source": "DelegatingMethodAccessorImpl.java:59"
        },
        {
          "method": "java.lang.reflect.Method.invoke",
          "source": "Method.java:389"
        },
        {
          "method": "org.eclipse.core.launcher.Main.basicRun",
          "source": "Main.java:267"
        },
        {
          "method": "org.eclipse.core.launcher.Main.run",
          "source": "Main.java:692"
        },
        {
          "method": "org.eclipse.core.launcher.Main.main",
          "source": "Main.java:676"
        }
      ],
      "causedBy": {
        "exceptionType": "org.eclipse.swt.SWTException",
        "message": "Invalid thread access",
        "elements": [
          {
            "method": "org.eclipse.swt.SWT.error",
            "source": "SWT.java:2659"
          },
          {
            "method": "org.eclipse.swt.SWT.error",
            "source": "SWT.java(Inlined Compiled Code)"
          },
          {
            "method": "org.eclipse.swt.SWT.error",
            "source": "SWT.java(Inlined Compiled Code)"
          },
          {
            "method": "org.eclipse.swt.widgets.Display.error",
            "source": "Display.java(Inlined Compiled  Code)"
          },
          {
            "method": "org.eclipse.swt.widgets.Display.checkDevice",
            "source": "Display.java(Inlined  Compiled Code)"
          },
          {
            "method": "org.eclipse.swt.widgets.Display.getActiveShell",
            "source": "Display.java(Compiled  Code)"
          },
          {
            "method": "org.eclipse.ui.internal.Workbench.getActiveWorkbenchWindow",
            "source": "Workbench.java:581"
          },
          {
            "method": "org.eclipse.search.internal.ui.SearchPlugin.getActiveWorkbenchWindow",
            "source": "SearchPlugin.java:101"
          },
          {
            "method": "org.eclipse.search.internal.ui.SearchPlugin.getActivePage",
            "source": "SearchPlugin.java:164"
          },
          {
            "method": "org.eclipse.search.internal.ui.SearchPlugin.getSearchResultView",
            "source": "SearchPlugin.java:213"
          },
          {
            "method": "org.eclipse.search.ui.SearchUI.getSearchResultView",
            "source": "SearchUI.java:121"
          },
          {
            "method": "org.eclipse.cdt.internal.ui.search.CSearchResultCollector.aboutToStart",
            "source": "CSearchResultCollector.java:63"
          },
          {
            "method": "org.eclipse.cdt.core.search.SearchEngine.search",
            "source": "SearchEngine.java:166"
          },
          {
            "method": "org.eclipse.cdt.internal.ui.search.CSearchOperation.run",
            "source": "CSearchOperation.java:80"
          },
          {
            "method": "org.eclipse.jface.operation.ModalContext$ModalContextThread.run",
            "source": "ModalContext.java:101"
          }
        ],
        "number": 0,
        "commentIndex": 0
      },
      "number": 0,
      "commentIndex": 4,
      "bugId": "58229",
      "duplicateId": "61570",
      "date": "2004-04-21T10:14:08+02:00",
      "product": "CDT",
      "component": "UI",
      "severity": "normal"
    }
  ],
  "groupId": "61570",
  "bugId": "58229",
  "duplicateId": "61570",
  "date": "2004-04-13T07:56:50+02:00",
  "product": "CDT",
  "component": "UI",
  "severity": "normal"
}