{
  "comments": [
    "Using jdtcore from HEAD content, I got the following stack trace when \nperforming a search action.\n\n\u003d\u003d\u003d\u003d\u003d\u003d\u003d\u003d\u003d\u003d\u003d\u003d\u003d\u003d\u003d\u003d\u003d\u003d\u003d\u003d\u003d\u003d\u003d\u003d\u003d\u003d\u003d\u003d\u003d\u003d\u003d\u003d\u003d\u003d\u003d\n4 org.eclipse.ui 0 java.lang.ArrayIndexOutOfBoundsException\njava.lang.ArrayIndexOutOfBoundsException\n        at org.eclipse.jdt.internal.core.index.impl.WordEntry.mapRefs(WordEntry.\njava:130)\n        at org.eclipse.jdt.internal.core.index.impl.MergeFactory.mergeReferences\n(MergeFactory.java:174)\n        at org.eclipse.jdt.internal.core.index.impl.MergeFactory.merge(MergeFact\nory.java:78)\n        at org.eclipse.jdt.internal.core.index.impl.Index.merge(Index.java:231)\n        at org.eclipse.jdt.internal.core.index.impl.Index.save(Index.java:340)\n        at org.eclipse.jdt.internal.core.search.PatternSearchJob.search(PatternS\nearchJob.java:115)\n        at org.eclipse.jdt.internal.core.search.PatternSearchJob.execute(Pattern\nSearchJob.java:81)\n        at org.eclipse.jdt.internal.core.search.processing.JobManager.performCon\ncurrentJob(JobManager.java:201)\n        at org.eclipse.jdt.core.search.SearchEngine.searchAllTypeNames(SearchEng\nine.java:445)\n        at org.eclipse.jdt.internal.ui.util.AllTypesSearchEngine.doSearchTypes(A\nllTypesSearchEngine.java:98)\n        at org.eclipse.jdt.internal.ui.util.AllTypesSearchEngine.searchTypes(All\nTypesSearchEngine.java:82)\n        at org.eclipse.jdt.internal.ui.util.AllTypesSearchEngine$1.run(AllTypesS\nearchEngine.java:51)\n        at org.eclipse.jface.operation.ModalContext$ModalContextThread.run(Modal\nContext.java:98)\njava.lang.ArrayIndexOutOfBoundsException",
    "Saved workspace for it.\n\nProblem occurred when doing an open type query. ",
    "Could not reproduce after reopening the same workspace. I guess the consistency check threw out the offending index.\n\n",
    "*** Bug 5890 has been marked as a duplicate of this bug. ***",
    "\n\n*** This bug has been marked as a duplicate of 5907 ***"
  ],
  "commentCreationDates": [
    "2001-11-13T13:48:12+01:00",
    "2001-11-13T15:28:08+01:00",
    "2001-11-13T21:58:49+01:00",
    "2001-11-14T15:31:00+01:00",
    "2001-11-29T16:18:07+01:00"
  ],
  "traces": [
    {
      "exceptionType": "java.lang.ArrayIndexOutOfBoundsException",
      "elements": [
        {
          "method": "org.eclipse.jdt.internal.core.index.impl.WordEntry.mapRefs",
          "source": "WordEntry. java:130"
        },
        {
          "method": "org.eclipse.jdt.internal.core.index.impl.MergeFactory.mergeReferences",
          "source": "MergeFactory.java:174"
        },
        {
          "method": "org.eclipse.jdt.internal.core.index.impl.MergeFactory.merge",
          "source": "MergeFact ory.java:78"
        },
        {
          "method": "org.eclipse.jdt.internal.core.index.impl.Index.merge",
          "source": "Index.java:231"
        },
        {
          "method": "org.eclipse.jdt.internal.core.index.impl.Index.save",
          "source": "Index.java:340"
        },
        {
          "method": "org.eclipse.jdt.internal.core.search.PatternSearchJob.search",
          "source": "PatternS earchJob.java:115"
        },
        {
          "method": "org.eclipse.jdt.internal.core.search.PatternSearchJob.execute",
          "source": "Pattern SearchJob.java:81"
        },
        {
          "method": "org.eclipse.jdt.internal.core.search.processing.JobManager.performConcurrentJob",
          "source": "JobManager.java:201"
        },
        {
          "method": "org.eclipse.jdt.core.search.SearchEngine.searchAllTypeNames",
          "source": "SearchEng ine.java:445"
        },
        {
          "method": "org.eclipse.jdt.internal.ui.util.AllTypesSearchEngine.doSearchTypes",
          "source": "A llTypesSearchEngine.java:98"
        },
        {
          "method": "org.eclipse.jdt.internal.ui.util.AllTypesSearchEngine.searchTypes",
          "source": "All TypesSearchEngine.java:82"
        },
        {
          "method": "org.eclipse.jdt.internal.ui.util.AllTypesSearchEngine$1.run",
          "source": "AllTypesS earchEngine.java:51"
        },
        {
          "method": "org.eclipse.jface.operation.ModalContext$ModalContextThread.run",
          "source": "Modal Context.java:98"
        }
      ],
      "number": 0,
      "commentIndex": 0,
      "bugId": "5837",
      "duplicateId": "5907",
      "date": "2001-11-13T13:48:12+01:00",
      "product": "JDT",
      "component": "Core",
      "severity": "normal"
    }
  ],
  "groupId": "5907",
  "bugId": "5837",
  "duplicateId": "5907",
  "date": "2001-11-13T13:48:12+01:00",
  "product": "JDT",
  "component": "Core",
  "severity": "normal"
}