{
  "comments": [
    "Build: 3.0 M8.\n\nIn another bug report (bug 57656), a user reported the following stack trace \nin the java console.  There were no consistent steps to reproduce.  See that \nbug for more info on his setup, VM, etc (nothing unusual that I can see).\n\njava.lang.IndexOutOfBoundsException: Index: 27, Size: 27\n        at java.util.ArrayList.RangeCheck(ArrayList.java:507)\n        at java.util.ArrayList.get(ArrayList.java:324)\n        at \norg.eclipse.jdt.internal.ui.javaeditor.CompilationUnitDocumentProvider$ReverseM\nap.get(CompilationUnitDocumentProvider.java:330)\n        at \norg.eclipse.jdt.internal.ui.javaeditor.CompilationUnitDocumentProvider$Compilat\nionUnitAnnotationModel.addAnnotation(CompilationUnitDocumentProvider.java:661)\n        at org.eclipse.jface.text.source.AnnotationModel.replaceAnnotations\n(AnnotationModel.java:190)\n        at org.eclipse.jface.text.source.AnnotationModel.replaceAnnotations\n(AnnotationModel.java:160)\n        at \norg.eclipse.jdt.internal.ui.javaeditor.OverrideIndicatorManager.updat\neAnnotations(OverrideIndicatorManager.java:227)\n        at \norg.eclipse.jdt.internal.ui.javaeditor.OverrideIndicatorManager.recon\nciled(OverrideIndicatorManager.java:271)\n        at \norg.eclipse.jdt.internal.ui.javaeditor.CompilationUnitEditor.reconcil\ned(CompilationUnitEditor.java:1669)\n        at \norg.eclipse.jdt.internal.ui.text.java.JavaReconcilingStrategy.reconci\nle(JavaReconcilingStrategy.java:107)\n        at \norg.eclipse.jdt.internal.ui.text.java.JavaReconcilingStrategy.reconci\nle(JavaReconcilingStrategy.java:118)\n        at \norg.eclipse.jface.text.reconciler.CompositeReconcilingStrategy.reconc\nile(CompositeReconcilingStrategy.java:83)\n        at \norg.eclipse.jdt.internal.ui.text.JavaCompositeReconcilingStrategy.rec\noncile(JavaCompositeReconcilingStrategy.java:97)\n        at org.eclipse.jface.text.reconciler.MonoReconciler.process\n(MonoReconciler.java:76)\n        at \norg.eclipse.jface.text.reconciler.AbstractReconciler$BackgroundThread\n.run(AbstractReconciler.java:189)",
    "For reference, this happened whilst running Eclipse with the -debug switch.\n\nIt just popped up during editing (ie typing, not saving/building)\n\nNothing of particular note was going on at the time - I was just half-way \nthrough typing in a line of code...",
    "we now synchronize on 1 lock object.\n\navailable in builds \u003e\u003d I20040427"
  ],
  "commentCreationDates": [
    "2004-04-14T05:21:21+02:00",
    "2004-04-14T11:30:53+02:00",
    "2004-04-27T11:04:36+02:00"
  ],
  "traces": [
    {
      "exceptionType": "java.lang.IndexOutOfBoundsException",
      "message": "Index: 27, Size: 27",
      "elements": [
        {
          "method": "java.util.ArrayList.RangeCheck",
          "source": "ArrayList.java:507"
        },
        {
          "method": "java.util.ArrayList.get",
          "source": "ArrayList.java:324"
        },
        {
          "method": "org.eclipse.jdt.internal.ui.javaeditor.CompilationUnitDocumentProvider$ReverseMap.get",
          "source": "CompilationUnitDocumentProvider.java:330"
        },
        {
          "method": "org.eclipse.jdt.internal.ui.javaeditor.CompilationUnitDocumentProvider$CompilationUnitAnnotationModel.addAnnotation",
          "source": "CompilationUnitDocumentProvider.java:661"
        },
        {
          "method": "org.eclipse.jface.text.source.AnnotationModel.replaceAnnotations",
          "source": "AnnotationModel.java:190"
        },
        {
          "method": "org.eclipse.jface.text.source.AnnotationModel.replaceAnnotations",
          "source": "AnnotationModel.java:160"
        },
        {
          "method": "org.eclipse.jdt.internal.ui.javaeditor.OverrideIndicatorManager.updateAnnotations",
          "source": "OverrideIndicatorManager.java:227"
        },
        {
          "method": "org.eclipse.jdt.internal.ui.javaeditor.OverrideIndicatorManager.reconciled",
          "source": "OverrideIndicatorManager.java:271"
        },
        {
          "method": "org.eclipse.jdt.internal.ui.javaeditor.CompilationUnitEditor.reconciled",
          "source": "CompilationUnitEditor.java:1669"
        },
        {
          "method": "org.eclipse.jdt.internal.ui.text.java.JavaReconcilingStrategy.reconcile",
          "source": "JavaReconcilingStrategy.java:107"
        },
        {
          "method": "org.eclipse.jdt.internal.ui.text.java.JavaReconcilingStrategy.reconcile",
          "source": "JavaReconcilingStrategy.java:118"
        },
        {
          "method": "org.eclipse.jface.text.reconciler.CompositeReconcilingStrategy.reconcile",
          "source": "CompositeReconcilingStrategy.java:83"
        },
        {
          "method": "org.eclipse.jdt.internal.ui.text.JavaCompositeReconcilingStrategy.reconcile",
          "source": "JavaCompositeReconcilingStrategy.java:97"
        },
        {
          "method": "org.eclipse.jface.text.reconciler.MonoReconciler.process",
          "source": "MonoReconciler.java:76"
        },
        {
          "method": "org.eclipse.jface.text.reconciler.AbstractReconciler$BackgroundThread.run",
          "source": "AbstractReconciler.java:189"
        }
      ],
      "number": 0,
      "commentIndex": 0,
      "bugId": "58407",
      "date": "2004-04-14T05:21:21+02:00",
      "product": "JDT",
      "component": "Text",
      "severity": "normal"
    }
  ],
  "groupId": "58407",
  "bugId": "58407",
  "date": "2004-04-14T05:21:21+02:00",
  "product": "JDT",
  "component": "Text",
  "severity": "normal"
}