{
  "comments": [
    "I200404131323\n\norg.eclipse.swt.SWTException: Invalid thread access\n        at org.eclipse.swt.SWT.error(SWT.java:2659)\n        at org.eclipse.swt.SWT.error(SWT.java:2584)\n        at org.eclipse.swt.SWT.error(SWT.java:2555)\n        at org.eclipse.swt.widgets.Display.error(Display.java:701)\n        at org.eclipse.swt.widgets.Display.checkDevice(Display.java:526)\n        at org.eclipse.swt.widgets.Display.getActiveShell(Display.java:788)\n        at org.eclipse.ui.internal.Workbench.getActiveWorkbenchWindow(Workbench.\njava:581)\n        at org.eclipse.jdt.internal.ui.text.HTMLPrinter.insertPageProlog(HTMLPri\nnter.java:97)\n        at org.eclipse.jdt.internal.ui.text.HTMLPrinter.addPageProlog(HTMLPrinte\nr.java:110)\n        at org.eclipse.jdt.internal.ui.text.java.hover.AnnotationHover.formatMes\nsage(AnnotationHover.java:49)\n        at org.eclipse.jdt.internal.ui.text.java.hover.AnnotationHover.getHoverI\nnfo(AnnotationHover.java:90)\n        at org.eclipse.jdt.internal.ui.text.java.hover.BestMatchHover.getHoverIn\nfo(BestMatchHover.java:102)\n        at org.eclipse.jdt.internal.ui.text.java.hover.JavaEditorTextHoverProxy.\ngetHoverInfo(JavaEditorTextHoverProxy.java:69)\n        at org.eclipse.jface.text.TextViewerHoverManager$4.run(TextViewerHoverMa\nnager.java:161)",
    "\n\n*** This bug has been marked as a duplicate of 57895 ***"
  ],
  "commentCreationDates": [
    "2004-04-14T10:40:43+02:00",
    "2004-04-14T12:35:21+02:00"
  ],
  "traces": [
    {
      "exceptionType": "org.eclipse.swt.SWTException",
      "message": "Invalid thread access",
      "elements": [
        {
          "method": "org.eclipse.swt.SWT.error",
          "source": "SWT.java:2659"
        },
        {
          "method": "org.eclipse.swt.SWT.error",
          "source": "SWT.java:2584"
        },
        {
          "method": "org.eclipse.swt.SWT.error",
          "source": "SWT.java:2555"
        },
        {
          "method": "org.eclipse.swt.widgets.Display.error",
          "source": "Display.java:701"
        },
        {
          "method": "org.eclipse.swt.widgets.Display.checkDevice",
          "source": "Display.java:526"
        },
        {
          "method": "org.eclipse.swt.widgets.Display.getActiveShell",
          "source": "Display.java:788"
        },
        {
          "method": "org.eclipse.ui.internal.Workbench.getActiveWorkbenchWindow",
          "source": "Workbench. java:581"
        },
        {
          "method": "org.eclipse.jdt.internal.ui.text.HTMLPrinter.insertPageProlog",
          "source": "HTMLPri nter.java:97"
        },
        {
          "method": "org.eclipse.jdt.internal.ui.text.HTMLPrinter.addPageProlog",
          "source": "HTMLPrinte r.java:110"
        },
        {
          "method": "org.eclipse.jdt.internal.ui.text.java.hover.AnnotationHover.formatMessage",
          "source": "AnnotationHover.java:49"
        },
        {
          "method": "org.eclipse.jdt.internal.ui.text.java.hover.AnnotationHover.getHoverInfo",
          "source": "AnnotationHover.java:90"
        },
        {
          "method": "org.eclipse.jdt.internal.ui.text.java.hover.BestMatchHover.getHoverInfo",
          "source": "BestMatchHover.java:102"
        },
        {
          "method": "org.eclipse.jdt.internal.ui.text.java.hover.JavaEditorTextHoverProxy.getHoverInfo",
          "source": "JavaEditorTextHoverProxy.java:69"
        },
        {
          "method": "org.eclipse.jface.text.TextViewerHoverManager$4.run",
          "source": "TextViewerHoverMa nager.java:161"
        }
      ],
      "number": 0,
      "commentIndex": 0,
      "bugId": "58431",
      "duplicateId": "57895",
      "date": "2004-04-14T10:40:43+02:00",
      "product": "JDT",
      "component": "Text",
      "severity": "normal"
    }
  ],
  "groupId": "57895",
  "bugId": "58431",
  "duplicateId": "57895",
  "date": "2004-04-14T10:40:43+02:00",
  "product": "JDT",
  "component": "Text",
  "severity": "normal"
}