{
  "comments": [
    "If you call Combo.select(index) with an index value out of range, it is supposed \nto ignore the call according to the javadoc.  However on Linux it throws a \nSWT.ERROR_INVALID_RANGE error.\n\nTo reproduce the bug, create a Combo widget and call select(0) before having any \nitems in it.  You\u0027ll get the following stack information:\njava.lang.IllegalArgumentException: Index out of bounds\n        at org.eclipse.swt.SWT.error(SWT.java:1687)\n        at org.eclipse.swt.SWT.error(SWT.java:1741)\n        at org.eclipse.swt.widgets.Widget.error(Widget.java:262)\n        at org.eclipse.swt.widgets.Combo.select(Combo.java:1049)\n\nThe javadoc for this method (and the deselect method) clearly says:\n    Indices that are out of range are ignored.\n\nThe reason this is \u0027major\u0027 is because of the impact to porting code written \noriginally for the Windows platform where this call is valid.  Now we get \ninternal errors and have to retrofit code to check the input range before making \nthese calls.",
    "Fixed.  Such cases are now silently ignored.\n",
    "*** Bug 9868 has been marked as a duplicate of this bug. ***"
  ],
  "commentCreationDates": [
    "2001-11-13T15:42:59+01:00",
    "2001-11-20T15:12:33+01:00",
    "2002-02-25T16:13:29+01:00"
  ],
  "traces": [
    {
      "exceptionType": "java.lang.IllegalArgumentException",
      "message": "Index out of bounds",
      "elements": [
        {
          "method": "org.eclipse.swt.SWT.error",
          "source": "SWT.java:1687"
        },
        {
          "method": "org.eclipse.swt.SWT.error",
          "source": "SWT.java:1741"
        },
        {
          "method": "org.eclipse.swt.widgets.Widget.error",
          "source": "Widget.java:262"
        },
        {
          "method": "org.eclipse.swt.widgets.Combo.select",
          "source": "Combo.java:1049"
        }
      ],
      "number": 0,
      "commentIndex": 0,
      "bugId": "5846",
      "date": "2001-11-13T15:42:59+01:00",
      "product": "Platform",
      "component": "SWT",
      "severity": "major"
    }
  ],
  "groupId": "5846",
  "bugId": "5846",
  "date": "2001-11-13T15:42:59+01:00",
  "product": "Platform",
  "component": "SWT",
  "severity": "major"
}