{
  "comments": [
    "Several people have been having problems running Eclipse because their Linux \nsystem has a color depth that we do not support. Specifically, getImageData \nfails for 15 bit color depth, and I believe it also fails for 32 bit color \ndepth. The fix is to look at the bits per pixel as well as the color depth, and \nscale up or down appropriately.\n\nHere is the information from an Eclipse Corner post, including the walkback and \nthe xdpyinfo:\n\nI am running Eclipse R1.0 and have attached a\ncopy of the output from xdpyinfo.  I am using RH 7.1 and Eclipse runs\nfine on the console.  I also have Cygwin/XFree86 running under Windows\n2000 and Eclipse  fails to start in this environment with the following\nexception.\n\norg.eclipse.swt.SWTException: Unsupported color depth\n  at org.eclipse.swt.SWT.error(SWT.java:1700)\n  at org.eclipse.swt.SWT.error(SWT.java:1741)\n  at org.eclipse.swt.graphics.Image.getImageData(Image.java:282)\n  at org.eclipse.swt.graphics.Image.\u003cinit\u003e(Image.java:926)\n  at org.eclipse.jface.action.ActionContributionItem$ImageCache.getGrayImage\n(ActionContributionItem.java:105)\n  at org.eclipse.jface.action.ActionContributionItem.updateImages\n(ActionContributionItem.java:452)\n  at org.eclipse.jface.action.ActionContributionItem.update\n(ActionContributionItem.java:518)\n  at org.eclipse.jface.action.ActionContributionItem.fill\n(ActionContributionItem.java:277)\n  at org.eclipse.jface.action.ToolBarManager.update(ToolBarManager.java:212)\n  at org.eclipse.ui.internal.WorkbenchWindow.addShortcut\n(WorkbenchWindow.java:224)\n  at org.eclipse.ui.internal.WorkbenchWindow.busyOpenPage\n(WorkbenchWindow.java:257)\n  at org.eclipse.ui.internal.WorkbenchWindow.access$6(WorkbenchWindow.java:248)\n  at org.eclipse.ui.internal.WorkbenchWindow$4.run(WorkbenchWindow.java:645)\n  at org.eclipse.swt.custom.BusyIndicator.showWhile(BusyIndicator.java:98)\n  at org.eclipse.ui.internal.WorkbenchWindow.openPage(WorkbenchWindow.java:642)\n  at org.eclipse.ui.internal.Workbench.openFirstTimeWindow(Workbench.java:465)\n  at org.eclipse.ui.internal.Workbench.openWindows(Workbench.java:541)\n  at org.eclipse.ui.internal.Workbench.init(Workbench.java:434)\n  at org.eclipse.ui.internal.Workbench.run(Workbench.java:672)\n  at org.eclipse.core.internal.boot.InternalBootLoader.run\n(InternalBootLoader.java:810)\n  at org.eclipse.core.boot.BootLoader.run(BootLoader.java:280)\n  at java.lang.reflect.Method.invoke(Native Method)\n  at org.eclipse.core.launcher.Main.basicRun(Main.java:151)\n  at org.eclipse.core.launcher.Main.run(Main.java:433)\n  at org.eclipse.core.launcher.Main.main(Main.java:306)\n\n\n--------------------------------------------------------------------------------\n\n\nname of display:    yang:0.0\nversion number:    11.0\nvendor string:    The XFree86 Project, Inc\nvendor release number:    40199001\nmaximum request size:  4194300 bytes\nmotion buffer size:  256\nbitmap unit, bit order, padding:    32, LSBFirst, 32\nimage byte order:    LSBFirst\nnumber of supported pixmap formats:    7\nsupported pixmap formats:\n    depth 1, bits_per_pixel 1, scanline_pad 32\n    depth 4, bits_per_pixel 8, scanline_pad 32\n    depth 8, bits_per_pixel 8, scanline_pad 32\n    depth 15, bits_per_pixel 16, scanline_pad 32\n    depth 16, bits_per_pixel 16, scanline_pad 32\n    depth 24, bits_per_pixel 24, scanline_pad 32\n    depth 32, bits_per_pixel 32, scanline_pad 32\nkeycode range:    minimum 8, maximum 255\nfocus:  window 0x140018a, revert to PointerRoot\nnumber of extensions:    20\n    BIG-REQUESTS\n    DOUBLE-BUFFER\n    Extended-Visual-Information\n    FontCache\n    GLX\n    LBX\n    MIT-SUNDRY-NONSTANDARD\n    RECORD\n    RENDER\n    SECURITY\n    SGI-GLX\n    SHAPE\n    SYNC\n    TOG-CUP\n    XC-APPGROUP\n    XC-MISC\n    XFree86-Bigfont\n    XKEYBOARD\n    XTEST\n    XVideo\ndefault screen number:    0\nnumber of screens:    1\n\nscreen #0:\n  dimensions:    1274x970 pixels (431x329 millimeters)\n  resolution:    75x75 dots per inch\n  depths (7):    32, 1, 4, 8, 15, 16, 24\n  root window id:    0x2e\n  depth of root window:    32 planes\n  number of colormaps:    minimum 1, maximum 1\n  default colormap:    0x20\n  default number of colormap cells:    2048\n  preallocated pixels:    black 0, white 16777215\n  options:    backing-store NO, save-unders NO\n  largest cursor:    1274x970\n  current input event mask:    0xf84033\n    KeyPressMask             KeyReleaseMask           EnterWindowMask          \n    LeaveWindowMask          KeymapStateMask          SubstructureNotifyMask   \n    SubstructureRedirectMask FocusChangeMask          PropertyChangeMask       \n    ColormapChangeMask       \n  number of visuals:    2\n  default visual id:  0x22\n  visual:\n    visual id:    0x22\n    class:    TrueColor\n    depth:    32 planes\n    available colormap entries:    2048 per subfield\n    red, green, blue masks:    0xff0000, 0xff00, 0xff\n    significant bits in color specification:    8 bits\n  visual:\n    visual id:    0x23\n    class:    TrueColor\n    depth:    32 planes\n    available colormap entries:    2048 per subfield\n    red, green, blue masks:    0xff0000, 0xff00, 0xff\n    significant bits in color specification:    8 bits",
    "I have added support for 15-bit and 32-bit screen\ndepth. The code has been released in 2.0 stream, but\nit needs testing. ",
    "Fixed.",
    "Customer has asked that this be reopened because they need a fix for the 1.0 \nstream.",
    "This is not the right place to ask for 1.0 fixes. Please close.",
    "Closed."
  ],
  "commentCreationDates": [
    "2001-11-13T18:27:05+01:00",
    "2001-11-14T02:17:07+01:00",
    "2001-12-06T14:50:51+01:00",
    "2002-01-24T20:14:18+01:00",
    "2002-01-28T21:43:16+01:00",
    "2002-01-28T21:47:27+01:00"
  ],
  "traces": [
    {
      "exceptionType": "org.eclipse.swt.SWTException",
      "message": "Unsupported color depth",
      "elements": [
        {
          "method": "org.eclipse.swt.SWT.error",
          "source": "SWT.java:1700"
        },
        {
          "method": "org.eclipse.swt.SWT.error",
          "source": "SWT.java:1741"
        },
        {
          "method": "org.eclipse.swt.graphics.Image.getImageData",
          "source": "Image.java:282"
        },
        {
          "method": "org.eclipse.swt.graphics.Image.\u003cinit\u003e",
          "source": "Image.java:926"
        },
        {
          "method": "org.eclipse.jface.action.ActionContributionItem$ImageCache.getGrayImage",
          "source": "ActionContributionItem.java:105"
        },
        {
          "method": "org.eclipse.jface.action.ActionContributionItem.updateImages",
          "source": "ActionContributionItem.java:452"
        },
        {
          "method": "org.eclipse.jface.action.ActionContributionItem.update",
          "source": "ActionContributionItem.java:518"
        },
        {
          "method": "org.eclipse.jface.action.ActionContributionItem.fill",
          "source": "ActionContributionItem.java:277"
        },
        {
          "method": "org.eclipse.jface.action.ToolBarManager.update",
          "source": "ToolBarManager.java:212"
        },
        {
          "method": "org.eclipse.ui.internal.WorkbenchWindow.addShortcut",
          "source": "WorkbenchWindow.java:224"
        },
        {
          "method": "org.eclipse.ui.internal.WorkbenchWindow.busyOpenPage",
          "source": "WorkbenchWindow.java:257"
        },
        {
          "method": "org.eclipse.ui.internal.WorkbenchWindow.access$6",
          "source": "WorkbenchWindow.java:248"
        },
        {
          "method": "org.eclipse.ui.internal.WorkbenchWindow$4.run",
          "source": "WorkbenchWindow.java:645"
        },
        {
          "method": "org.eclipse.swt.custom.BusyIndicator.showWhile",
          "source": "BusyIndicator.java:98"
        },
        {
          "method": "org.eclipse.ui.internal.WorkbenchWindow.openPage",
          "source": "WorkbenchWindow.java:642"
        },
        {
          "method": "org.eclipse.ui.internal.Workbench.openFirstTimeWindow",
          "source": "Workbench.java:465"
        },
        {
          "method": "org.eclipse.ui.internal.Workbench.openWindows",
          "source": "Workbench.java:541"
        },
        {
          "method": "org.eclipse.ui.internal.Workbench.init",
          "source": "Workbench.java:434"
        },
        {
          "method": "org.eclipse.ui.internal.Workbench.run",
          "source": "Workbench.java:672"
        },
        {
          "method": "org.eclipse.core.internal.boot.InternalBootLoader.run",
          "source": "InternalBootLoader.java:810"
        },
        {
          "method": "org.eclipse.core.boot.BootLoader.run",
          "source": "BootLoader.java:280"
        },
        {
          "method": "java.lang.reflect.Method.invoke",
          "source": "Native Method"
        },
        {
          "method": "org.eclipse.core.launcher.Main.basicRun",
          "source": "Main.java:151"
        },
        {
          "method": "org.eclipse.core.launcher.Main.run",
          "source": "Main.java:433"
        },
        {
          "method": "org.eclipse.core.launcher.Main.main",
          "source": "Main.java:306"
        }
      ],
      "number": 0,
      "commentIndex": 0,
      "bugId": "5857",
      "date": "2001-11-13T18:27:05+01:00",
      "product": "Platform",
      "component": "SWT",
      "severity": "normal"
    }
  ],
  "groupId": "5857",
  "bugId": "5857",
  "date": "2001-11-13T18:27:05+01:00",
  "product": "Platform",
  "component": "SWT",
  "severity": "normal"
}