{
  "comments": [
    "Build 20011107.\n\nI had placed a breakpoint at the beginning of a method (self-hosting\nworkspace, breakpoint at top of SetClasspathOperation#updateProjectReferences\n(...)). Then in a target workspace, perform a real change of the .classpath \n(reorder the classpath entries).\n\nGot the following stack dump, and debugger hanged.\n\n4 org.eclipse.ui 0 java.lang.NullPointerException\njava.lang.NullPointerException\n        at org.eclipse.jdt.internal.debug.core.JDIThread$StepHandler.step(JDIThr\nead.java:1477)\n        at org.eclipse.jdt.internal.debug.core.JDIThread.stepOver(JDIThread.java\n:1029)\n        at org.eclipse.debug.internal.ui.StepOverActionDelegate.stepAction(StepO\nverActionDelegate.java:26)\n        at org.eclipse.debug.internal.ui.StepActionDelegate.doAction(StepActionD\nelegate.java:22)\n        at org.eclipse.debug.internal.ui.ControlActionDelegate$1.run(ControlActi\nonDelegate.java:70)\n        at org.eclipse.swt.custom.BusyIndicator.showWhile(BusyIndicator.java:56)\n\n        at org.eclipse.debug.internal.ui.ControlActionDelegate.run(ControlAction\nDelegate.java:64)\n        at org.eclipse.debug.internal.ui.ControlAction.run(ControlAction.java:46\n)\n        at org.eclipse.jface.action.Action.runWithEvent(Action.java:453)\n        at org.eclipse.jface.action.ActionContributionItem.handleWidgetSelection\n(ActionContributionItem.java:407)\n        at org.eclipse.jface.action.ActionContributionItem.handleWidgetEvent(Act\nionContributionItem.java:361)\n        at org.eclipse.jface.action.ActionContributionItem.access$0(ActionContri\nbutionItem.java:352)\n        at org.eclipse.jface.action.ActionContributionItem$ActionListener.handle\nEvent(ActionContributionItem.java:47)\n        at org.eclipse.swt.widgets.EventTable.sendEvent(EventTable.java:54)\n        at org.eclipse.swt.widgets.Widget.notifyListeners(Widget.java:635)\n        at org.eclipse.swt.widgets.Display.runDeferredEvents(Display.java:1365)\n        at org.eclipse.swt.widgets.Display.readAndDispatch(Display.java:1167)\n        at org.eclipse.ui.internal.Workbench.runEventLoop(Workbench.java:727)\n        at org.eclipse.ui.internal.Workbench.run(Workbench.java:710)\n        at org.eclipse.core.internal.boot.InternalBootLoader.run(InternalBootLoa\nder.java:820)\n        at org.eclipse.core.boot.BootLoader.run(BootLoader.java:285)\n        at java.lang.reflect.Method.invoke(Native Method)\n        at org.eclipse.core.launcher.Main.basicRun(Main.java:151)\n        at org.eclipse.core.launcher.Main.run(Main.java:502)\n        at org.eclipse.core.launcher.UIMain.main(UIMain.java:52)\njava.lang.NullPointerException",
    "This looks suspiously like bug 5585",
    "The JDI crash only occurred when running on J9 (latest official drop).",
    "I never directly fixed this problem but we had many problems near this area \nthat have been fixed.  My intention is to closed this bug as I can no longer \nreproduce it.",
    "\n\n*** This bug has been marked as a duplicate of 6393 ***"
  ],
  "commentCreationDates": [
    "2001-11-13T18:34:04+01:00",
    "2001-11-13T18:39:25+01:00",
    "2001-11-13T18:49:10+01:00",
    "2001-11-27T18:23:53+01:00",
    "2001-11-29T18:47:01+01:00"
  ],
  "traces": [
    {
      "exceptionType": "java.lang.NullPointerException",
      "elements": [
        {
          "method": "org.eclipse.jdt.internal.debug.core.JDIThread$StepHandler.step",
          "source": "JDIThr ead.java:1477"
        },
        {
          "method": "org.eclipse.jdt.internal.debug.core.JDIThread.stepOver",
          "source": "JDIThread.java :1029"
        },
        {
          "method": "org.eclipse.debug.internal.ui.StepOverActionDelegate.stepAction",
          "source": "StepO verActionDelegate.java:26"
        },
        {
          "method": "org.eclipse.debug.internal.ui.StepActionDelegate.doAction",
          "source": "StepActionD elegate.java:22"
        },
        {
          "method": "org.eclipse.debug.internal.ui.ControlActionDelegate$1.run",
          "source": "ControlActi onDelegate.java:70"
        },
        {
          "method": "org.eclipse.swt.custom.BusyIndicator.showWhile",
          "source": "BusyIndicator.java:56"
        },
        {
          "method": "org.eclipse.debug.internal.ui.ControlActionDelegate.run",
          "source": "ControlAction Delegate.java:64"
        },
        {
          "method": "org.eclipse.debug.internal.ui.ControlAction.run",
          "source": "ControlAction.java:46 "
        },
        {
          "method": "org.eclipse.jface.action.Action.runWithEvent",
          "source": "Action.java:453"
        },
        {
          "method": "org.eclipse.jface.action.ActionContributionItem.handleWidgetSelection",
          "source": "ActionContributionItem.java:407"
        },
        {
          "method": "org.eclipse.jface.action.ActionContributionItem.handleWidgetEvent",
          "source": "Act ionContributionItem.java:361"
        },
        {
          "method": "org.eclipse.jface.action.ActionContributionItem.access$0",
          "source": "ActionContri butionItem.java:352"
        },
        {
          "method": "org.eclipse.jface.action.ActionContributionItem$ActionListener.handleEvent",
          "source": "ActionContributionItem.java:47"
        },
        {
          "method": "org.eclipse.swt.widgets.EventTable.sendEvent",
          "source": "EventTable.java:54"
        },
        {
          "method": "org.eclipse.swt.widgets.Widget.notifyListeners",
          "source": "Widget.java:635"
        },
        {
          "method": "org.eclipse.swt.widgets.Display.runDeferredEvents",
          "source": "Display.java:1365"
        },
        {
          "method": "org.eclipse.swt.widgets.Display.readAndDispatch",
          "source": "Display.java:1167"
        },
        {
          "method": "org.eclipse.ui.internal.Workbench.runEventLoop",
          "source": "Workbench.java:727"
        },
        {
          "method": "org.eclipse.ui.internal.Workbench.run",
          "source": "Workbench.java:710"
        },
        {
          "method": "org.eclipse.core.internal.boot.InternalBootLoader.run",
          "source": "InternalBootLoa der.java:820"
        },
        {
          "method": "org.eclipse.core.boot.BootLoader.run",
          "source": "BootLoader.java:285"
        },
        {
          "method": "java.lang.reflect.Method.invoke",
          "source": "Native Method"
        },
        {
          "method": "org.eclipse.core.launcher.Main.basicRun",
          "source": "Main.java:151"
        },
        {
          "method": "org.eclipse.core.launcher.Main.run",
          "source": "Main.java:502"
        },
        {
          "method": "org.eclipse.core.launcher.UIMain.main",
          "source": "UIMain.java:52"
        }
      ],
      "number": 0,
      "commentIndex": 0,
      "bugId": "5861",
      "duplicateId": "6393",
      "date": "2001-11-13T18:34:04+01:00",
      "product": "JDT",
      "component": "Debug",
      "severity": "critical"
    }
  ],
  "groupId": "6393",
  "bugId": "5861",
  "duplicateId": "6393",
  "date": "2001-11-13T18:34:04+01:00",
  "product": "JDT",
  "component": "Debug",
  "severity": "critical"
}