{
  "comments": [
    "I am using Eclipse 3.0 M8. \n\nCreate project in the Resource navigator. Close the project, open the project,\nyou should see the following exception: \n\norg.eclipse.swt.SWTException: Invalid thread access\n        at java.lang.Throwable.\u003cinit\u003e(Throwable.java)\n        at java.lang.Throwable.\u003cinit\u003e(Throwable.java)\n        at org.eclipse.swt.SWTException.\u003cinit\u003e(SWTException.java:73)\n        at org.eclipse.swt.SWTException.\u003cinit\u003e(SWTException.java:62)\n        at org.eclipse.swt.SWT.error(SWT.java:2625)\n        at org.eclipse.swt.SWT.error(SWT.java:2555)\n        at org.eclipse.swt.dnd.DND.error(DND.java:230)\n        at org.eclipse.swt.dnd.DND.error(DND.java:181)\n        at org.eclipse.swt.dnd.Clipboard.checkWidget(Clipboard.java:129)\n        at org.eclipse.swt.dnd.Clipboard.getAvailableTypes(Clipboard.java:444)\n        at org.eclipse.ui.views.navigator.PasteAction.updateSelection(PasteActio\nn.java:220)\n        at org.eclipse.ui.actions.BaseSelectionListenerAction.selectionChanged(B\naseSelectionListenerAction.java:102)\n        at org.eclipse.ui.views.navigator.RefactorActionGroup.updateActionBars(R\nefactorActionGroup.java:136)\n        at org.eclipse.ui.views.navigator.MainActionGroup.handleResourceChanged(\nMainActionGroup.java:109)\n        at org.eclipse.ui.views.navigator.MainActionGroup$1.resourceChanged(Main\nActionGroup.java:76)\n        at org.eclipse.core.internal.events.NotificationManager$2.run(Notificati\nonManager.java:255)\n        at org.eclipse.core.internal.runtime.InternalPlatform.run(InternalPlatfo\nrm.java)\n        at org.eclipse.core.runtime.Platform.run(Platform.java)\n        at org.eclipse.core.internal.events.NotificationManager.notify(Notificat\nionManager.java:248)\n        at org.eclipse.core.internal.events.NotificationManager.broadcastChanges\n(NotificationManager.java:142)\n        at org.eclipse.core.internal.resources.Workspace.broadcastChanges(Worksp\nace.java:155)\n        at org.eclipse.core.internal.resources.Workspace.endOperation(Workspace.\njava:854)\n        at org.eclipse.core.internal.resources.Workspace.run(Workspace.java:1568\n)\n        at org.eclipse.ui.actions.WorkspaceModifyOperation.run(WorkspaceModifyOp\neration.java:105)\n        at org.eclipse.jface.operation.ModalContext$ModalContextThread.run(Modal\nContext.java:101)",
    "Looks like a resource listener that is relying on being in the UI Thread.",
    "There has been interest expressed in this bug for 3.0.1, but I just tried it \non 3.0 GA and it appears to work.\n",
    "\nHmmm, I don\u0027t see the exception, here\u0027s the steps I used...\n\n1) Resource Perspective\n2) Create project (Java proj, did NOT switch to Java Perspective when asked)\n3) Close proj\n4) Open proj\n\nIs there anything else I should try?\n",
    "*** Bug 60074 has been marked as a duplicate of this bug. ***",
    "\nSeems to work now...\n"
  ],
  "commentCreationDates": [
    "2004-04-15T20:24:39+02:00",
    "2004-04-16T14:28:52+02:00",
    "2004-08-06T19:35:30+02:00",
    "2005-07-28T15:48:12+02:00",
    "2005-07-28T16:35:40+02:00",
    "2007-06-21T17:18:34+02:00"
  ],
  "traces": [
    {
      "exceptionType": "org.eclipse.swt.SWTException",
      "message": "Invalid thread access",
      "elements": [
        {
          "method": "java.lang.Throwable.\u003cinit\u003e",
          "source": "Throwable.java"
        },
        {
          "method": "java.lang.Throwable.\u003cinit\u003e",
          "source": "Throwable.java"
        },
        {
          "method": "org.eclipse.swt.SWTException.\u003cinit\u003e",
          "source": "SWTException.java:73"
        },
        {
          "method": "org.eclipse.swt.SWTException.\u003cinit\u003e",
          "source": "SWTException.java:62"
        },
        {
          "method": "org.eclipse.swt.SWT.error",
          "source": "SWT.java:2625"
        },
        {
          "method": "org.eclipse.swt.SWT.error",
          "source": "SWT.java:2555"
        },
        {
          "method": "org.eclipse.swt.dnd.DND.error",
          "source": "DND.java:230"
        },
        {
          "method": "org.eclipse.swt.dnd.DND.error",
          "source": "DND.java:181"
        },
        {
          "method": "org.eclipse.swt.dnd.Clipboard.checkWidget",
          "source": "Clipboard.java:129"
        },
        {
          "method": "org.eclipse.swt.dnd.Clipboard.getAvailableTypes",
          "source": "Clipboard.java:444"
        },
        {
          "method": "org.eclipse.ui.views.navigator.PasteAction.updateSelection",
          "source": "PasteActio n.java:220"
        },
        {
          "method": "org.eclipse.ui.actions.BaseSelectionListenerAction.selectionChanged",
          "source": "B aseSelectionListenerAction.java:102"
        },
        {
          "method": "org.eclipse.ui.views.navigator.RefactorActionGroup.updateActionBars",
          "source": "R efactorActionGroup.java:136"
        },
        {
          "method": "org.eclipse.ui.views.navigator.MainActionGroup.handleResourceChanged",
          "source": " MainActionGroup.java:109"
        },
        {
          "method": "org.eclipse.ui.views.navigator.MainActionGroup$1.resourceChanged",
          "source": "Main ActionGroup.java:76"
        },
        {
          "method": "org.eclipse.core.internal.events.NotificationManager$2.run",
          "source": "Notificati onManager.java:255"
        },
        {
          "method": "org.eclipse.core.internal.runtime.InternalPlatform.run",
          "source": "InternalPlatfo rm.java"
        },
        {
          "method": "org.eclipse.core.runtime.Platform.run",
          "source": "Platform.java"
        },
        {
          "method": "org.eclipse.core.internal.events.NotificationManager.notify",
          "source": "Notificat ionManager.java:248"
        },
        {
          "method": "org.eclipse.core.internal.events.NotificationManager.broadcastChanges",
          "source": "NotificationManager.java:142"
        },
        {
          "method": "org.eclipse.core.internal.resources.Workspace.broadcastChanges",
          "source": "Worksp ace.java:155"
        },
        {
          "method": "org.eclipse.core.internal.resources.Workspace.endOperation",
          "source": "Workspace. java:854"
        },
        {
          "method": "org.eclipse.core.internal.resources.Workspace.run",
          "source": "Workspace.java:1568 "
        },
        {
          "method": "org.eclipse.ui.actions.WorkspaceModifyOperation.run",
          "source": "WorkspaceModifyOp eration.java:105"
        },
        {
          "method": "org.eclipse.jface.operation.ModalContext$ModalContextThread.run",
          "source": "Modal Context.java:101"
        }
      ],
      "number": 0,
      "commentIndex": 0,
      "bugId": "58709",
      "date": "2004-04-15T20:24:39+02:00",
      "product": "Platform",
      "component": "UI",
      "severity": "normal"
    }
  ],
  "groupId": "58709",
  "bugId": "58709",
  "date": "2004-04-15T20:24:39+02:00",
  "product": "Platform",
  "component": "UI",
  "severity": "normal"
}