{
  "comments": [
    "I\u0027m using an M8 driver and have a multipage editor that has a source page as \none of its pages.  If I\u0027m on the source page an open another editor (any \neditor) and then close it so the focus jumps back to the source page of my \neditor, the following exception is logged:\n\n!MESSAGE Problems occurred when invoking code from plug-\nin: \"org.eclipse.core.runtime\".\n!STACK 0\njava.lang.NullPointerException\n        at org.eclipse.ui.texteditor.AbstractTextEditor.getCursorPosition\n(AbstractTextEditor.java:4513)\n        at org.eclipse.ui.texteditor.AbstractTextEditor.updateStatusField\n(AbstractTextEditor.java:4447)\n        at org.eclipse.ui.texteditor.StatusTextEditor.updateStatusField\n(StatusTextEditor.java:166)\n        at org.eclipse.ui.texteditor.AbstractTextEditor.setStatusField\n(AbstractTextEditor.java:4194)\n        at \norg.eclipse.ui.texteditor.BasicTextEditorActionContributor.doSetActiveEditor\n(BasicTextEditorActionContributor\n.java:215)\n        at \norg.eclipse.ui.texteditor.BasicTextEditorActionContributor.setActiveEditor\n(BasicTextEditorActionContributor.j\nava:229)\n        at com.ibm.sse.editor.ui.ActionContributor.setActiveEditor\n(ActionContributor.java:221)\n        at \ncom.ibm.sse.editor.xml.ui.actions.ActionContributorXML.setActiveEditor\n(ActionContributorXML.java:158)\n        at \ncom.ibm.etools.emf.workbench.ui.presentation.EditModelMultiPagePartActionBarCont\nributor.partClosed(EditModelM\nultiPagePartActionBarContributor.java:185)\n        at org.eclipse.ui.internal.PartListenerList$3.run\n(PartListenerList.java:89)\n        at org.eclipse.core.internal.runtime.InternalPlatform.run\n(InternalPlatform.java(Inlined Compiled Code))\n        at org.eclipse.core.runtime.Platform.run(Platform.java(Compiled Code))\n        at org.eclipse.ui.internal.PartListenerList.firePartClosed\n(PartListenerList.java:87)\n        at org.eclipse.ui.internal.WWinPartService$1.partClosed\n(WWinPartService.java:43)\n        at org.eclipse.ui.internal.PartListenerList2$3.run\n(PartListenerList2.java:85)\n        at org.eclipse.core.internal.runtime.InternalPlatform.run\n(InternalPlatform.java(Inlined Compiled Code))\n        at org.eclipse.core.runtime.Platform.run(Platform.java(Compiled Code))\n        at org.eclipse.ui.internal.PartListenerList2.firePartClosed\n(PartListenerList2.java:83)\n        at org.eclipse.ui.internal.WorkbenchPage.firePartClosed\n(WorkbenchPage.java:1329)\n        at org.eclipse.ui.internal.WorkbenchPage.closeEditor\n(WorkbenchPage.java:916)\n        at org.eclipse.ui.internal.WorkbenchPage.closeEditor\n(WorkbenchPage.java:881)\n        at org.eclipse.ui.internal.EditorPane.doHide(EditorPane.java:97)\n        at org.eclipse.ui.internal.EditorWorkbook.close(EditorWorkbook.java:235)\n        at org.eclipse.ui.internal.EditorWorkbook$1.close\n(EditorWorkbook.java:108)\n        at org.eclipse.ui.internal.presentations.BasicStackPresentation$6.close\n(BasicStackPresentation.java:182)\n        at org.eclipse.swt.custom.CTabFolder.onMouse(CTabFolder.java(Compiled \nCode))\n        at org.eclipse.swt.custom.CTabFolder$1.handleEvent(CTabFolder.java\n(Compiled Code))\n        at org.eclipse.swt.widgets.EventTable.sendEvent(EventTable.java\n(Compiled Code))\n        at org.eclipse.swt.widgets.Widget.sendEvent(Widget.java(Inlined \nCompiled Code))\n        at org.eclipse.swt.widgets.Display.runDeferredEvents(Display.java\n(Compiled Code))\n        at org.eclipse.swt.widgets.Display.readAndDispatch(Display.java\n(Compiled Code))\n        at org.eclipse.ui.internal.Workbench.runEventLoop(Workbench.java\n(Compiled Code))\n        at org.eclipse.ui.internal.Workbench.runUI(Workbench.java:1536)\n        at org.eclipse.ui.internal.Workbench.createAndRunWorkbench\n(Workbench.java:257)\n        at org.eclipse.ui.PlatformUI.createAndRunWorkbench(PlatformUI.java:139)\n        at org.eclipse.ui.internal.ide.IDEApplication.run\n(IDEApplication.java:90)\n        at org.eclipse.core.internal.runtime.PlatformActivator$1.run\n(PlatformActivator.java:277)\n        at org.eclipse.core.runtime.adaptor.EclipseStarter.run\n(EclipseStarter.java:239)\n        at org.eclipse.core.runtime.adaptor.EclipseStarter.run\n(EclipseStarter.java:117)\n        at sun.reflect.NativeMethodAccessorImpl.invoke0(Native Method)\n        at sun.reflect.NativeMethodAccessorImpl.invoke\n(NativeMethodAccessorImpl.java:84)\n        at sun.reflect.NativeMethodAccessorImpl.invoke\n(NativeMethodAccessorImpl.java:57)\n        at sun.reflect.DelegatingMethodAccessorImpl.invoke\n(DelegatingMethodAccessorImpl.java:59)\n        at java.lang.reflect.Method.invoke(Method.java:389)\n        at org.eclipse.core.launcher.Main.basicRun(Main.java:267)\n        at org.eclipse.core.launcher.Main.run(Main.java:692)\n        at org.eclipse.core.launcher.Main.main(Main.java:676)",
    "When I look at the corresponding source line in AbstractTextEditor.java rev.\n1.94 I see:\n\n\t\t\treturn fErrorLabel;\n\nwhich can\u0027t cause a NPE. So either it\u0027s a VM bug or the stack trace does not\ncorrespond to 3.0 M8 source.\n\nWe either need your code to reproduce the problem or a stack trace with\ncorresponding build id.",
    "Get rid of deprecated state.",
    "."
  ],
  "commentCreationDates": [
    "2004-04-16T00:31:23+02:00",
    "2004-04-20T12:12:27+02:00",
    "2007-06-22T15:59:08+02:00",
    "2007-06-22T16:04:26+02:00"
  ],
  "traces": [
    {
      "exceptionType": "java.lang.NullPointerException",
      "elements": [
        {
          "method": "org.eclipse.ui.texteditor.AbstractTextEditor.getCursorPosition",
          "source": "AbstractTextEditor.java:4513"
        },
        {
          "method": "org.eclipse.ui.texteditor.AbstractTextEditor.updateStatusField",
          "source": "AbstractTextEditor.java:4447"
        },
        {
          "method": "org.eclipse.ui.texteditor.StatusTextEditor.updateStatusField",
          "source": "StatusTextEditor.java:166"
        },
        {
          "method": "org.eclipse.ui.texteditor.AbstractTextEditor.setStatusField",
          "source": "AbstractTextEditor.java:4194"
        },
        {
          "method": "org.eclipse.ui.texteditor.BasicTextEditorActionContributor.doSetActiveEditor",
          "source": "BasicTextEditorActionContributor .java:215"
        },
        {
          "method": "org.eclipse.ui.texteditor.BasicTextEditorActionContributor.setActiveEditor",
          "source": "BasicTextEditorActionContributor.j ava:229"
        },
        {
          "method": "com.ibm.sse.editor.ui.ActionContributor.setActiveEditor",
          "source": "ActionContributor.java:221"
        },
        {
          "method": "com.ibm.sse.editor.xml.ui.actions.ActionContributorXML.setActiveEditor",
          "source": "ActionContributorXML.java:158"
        },
        {
          "method": "com.ibm.etools.emf.workbench.ui.presentation.EditModelMultiPagePartActionBarContributor.partClosed",
          "source": "EditModelM ultiPagePartActionBarContributor.java:185"
        },
        {
          "method": "org.eclipse.ui.internal.PartListenerList$3.run",
          "source": "PartListenerList.java:89"
        },
        {
          "method": "org.eclipse.core.internal.runtime.InternalPlatform.run",
          "source": "InternalPlatform.java(Inlined Compiled Code)"
        },
        {
          "method": "org.eclipse.core.runtime.Platform.run",
          "source": "Platform.java(Compiled Code)"
        },
        {
          "method": "org.eclipse.ui.internal.PartListenerList.firePartClosed",
          "source": "PartListenerList.java:87"
        },
        {
          "method": "org.eclipse.ui.internal.WWinPartService$1.partClosed",
          "source": "WWinPartService.java:43"
        },
        {
          "method": "org.eclipse.ui.internal.PartListenerList2$3.run",
          "source": "PartListenerList2.java:85"
        },
        {
          "method": "org.eclipse.core.internal.runtime.InternalPlatform.run",
          "source": "InternalPlatform.java(Inlined Compiled Code)"
        },
        {
          "method": "org.eclipse.core.runtime.Platform.run",
          "source": "Platform.java(Compiled Code)"
        },
        {
          "method": "org.eclipse.ui.internal.PartListenerList2.firePartClosed",
          "source": "PartListenerList2.java:83"
        },
        {
          "method": "org.eclipse.ui.internal.WorkbenchPage.firePartClosed",
          "source": "WorkbenchPage.java:1329"
        },
        {
          "method": "org.eclipse.ui.internal.WorkbenchPage.closeEditor",
          "source": "WorkbenchPage.java:916"
        },
        {
          "method": "org.eclipse.ui.internal.WorkbenchPage.closeEditor",
          "source": "WorkbenchPage.java:881"
        },
        {
          "method": "org.eclipse.ui.internal.EditorPane.doHide",
          "source": "EditorPane.java:97"
        },
        {
          "method": "org.eclipse.ui.internal.EditorWorkbook.close",
          "source": "EditorWorkbook.java:235"
        },
        {
          "method": "org.eclipse.ui.internal.EditorWorkbook$1.close",
          "source": "EditorWorkbook.java:108"
        },
        {
          "method": "org.eclipse.ui.internal.presentations.BasicStackPresentation$6.close",
          "source": "BasicStackPresentation.java:182"
        },
        {
          "method": "org.eclipse.swt.custom.CTabFolder.onMouse",
          "source": "CTabFolder.java(Compiled  Code)"
        },
        {
          "method": "org.eclipse.swt.custom.CTabFolder$1.handleEvent",
          "source": "CTabFolder.java (Compiled Code)"
        },
        {
          "method": "org.eclipse.swt.widgets.EventTable.sendEvent",
          "source": "EventTable.java (Compiled Code)"
        },
        {
          "method": "org.eclipse.swt.widgets.Widget.sendEvent",
          "source": "Widget.java(Inlined  Compiled Code)"
        },
        {
          "method": "org.eclipse.swt.widgets.Display.runDeferredEvents",
          "source": "Display.java (Compiled Code)"
        },
        {
          "method": "org.eclipse.swt.widgets.Display.readAndDispatch",
          "source": "Display.java (Compiled Code)"
        },
        {
          "method": "org.eclipse.ui.internal.Workbench.runEventLoop",
          "source": "Workbench.java (Compiled Code)"
        },
        {
          "method": "org.eclipse.ui.internal.Workbench.runUI",
          "source": "Workbench.java:1536"
        },
        {
          "method": "org.eclipse.ui.internal.Workbench.createAndRunWorkbench",
          "source": "Workbench.java:257"
        },
        {
          "method": "org.eclipse.ui.PlatformUI.createAndRunWorkbench",
          "source": "PlatformUI.java:139"
        },
        {
          "method": "org.eclipse.ui.internal.ide.IDEApplication.run",
          "source": "IDEApplication.java:90"
        },
        {
          "method": "org.eclipse.core.internal.runtime.PlatformActivator$1.run",
          "source": "PlatformActivator.java:277"
        },
        {
          "method": "org.eclipse.core.runtime.adaptor.EclipseStarter.run",
          "source": "EclipseStarter.java:239"
        },
        {
          "method": "org.eclipse.core.runtime.adaptor.EclipseStarter.run",
          "source": "EclipseStarter.java:117"
        },
        {
          "method": "sun.reflect.NativeMethodAccessorImpl.invoke0",
          "source": "Native Method"
        },
        {
          "method": "sun.reflect.NativeMethodAccessorImpl.invoke",
          "source": "NativeMethodAccessorImpl.java:84"
        },
        {
          "method": "sun.reflect.NativeMethodAccessorImpl.invoke",
          "source": "NativeMethodAccessorImpl.java:57"
        },
        {
          "method": "sun.reflect.DelegatingMethodAccessorImpl.invoke",
          "source": "DelegatingMethodAccessorImpl.java:59"
        },
        {
          "method": "java.lang.reflect.Method.invoke",
          "source": "Method.java:389"
        },
        {
          "method": "org.eclipse.core.launcher.Main.basicRun",
          "source": "Main.java:267"
        },
        {
          "method": "org.eclipse.core.launcher.Main.run",
          "source": "Main.java:692"
        },
        {
          "method": "org.eclipse.core.launcher.Main.main",
          "source": "Main.java:676"
        }
      ],
      "number": 0,
      "commentIndex": 0,
      "bugId": "58757",
      "date": "2004-04-16T00:31:23+02:00",
      "product": "Platform",
      "component": "Text",
      "severity": "normal"
    }
  ],
  "groupId": "58757",
  "bugId": "58757",
  "date": "2004-04-16T00:31:23+02:00",
  "product": "Platform",
  "component": "Text",
  "severity": "normal"
}