{
  "comments": [
    "I got the error bellow while typing the last \")\" in the text:\n\nCharRange CHAR_RANGE_1 \u003d new CharRange(0x0, 0xD7FF);\n\nThe class CharRange is not imported yet and underlined in red.\n\n!ENTRY org.eclipse.core.runtime 4 2 Apr 15, 2004 14:30:04.35\n!MESSAGE An internal error occurred during: \"Java AST creation\".\n!STACK 0\njava.lang.IllegalArgumentException\n        at org.eclipse.jdt.core.dom.ASTNode.setSourceRange(ASTNode.java:2592)\n        at\norg.eclipse.jdt.core.dom.ASTConverter.convertToVariableDeclarationFragment(ASTConverter.java:2677)\n        at\norg.eclipse.jdt.core.dom.ASTConverter.convertToFieldDeclaration(ASTConverter.java:2722)\n        at\norg.eclipse.jdt.core.dom.ASTConverter.checkAndAddMultipleFieldDeclaration(ASTConverter.java:364)\n        at\norg.eclipse.jdt.core.dom.ASTConverter.buildBodyDeclarations(ASTConverter.java:324)\n        at org.eclipse.jdt.core.dom.ASTConverter.convert(ASTConverter.java:268)\n        at org.eclipse.jdt.core.dom.ASTConverter.convert(ASTConverter.java:146)\n        at org.eclipse.jdt.core.dom.ASTParser.convert(ASTParser.java:697)\n        at org.eclipse.jdt.core.dom.ASTParser.internalCreateAST(ASTParser.java:667)\n        at org.eclipse.jdt.core.dom.ASTParser.createAST(ASTParser.java:563)\n        at\norg.eclipse.jdt.internal.ui.javaeditor.ASTProvider.createAST(ASTProvider.java:383)\n        at\norg.eclipse.jdt.internal.ui.javaeditor.ASTProvider.getAST(ASTProvider.java:344)\n        at\norg.eclipse.jdt.internal.ui.viewsupport.SelectionListenerWithASTManager$PartListenerGroup.calculateASTandInfo\nrm(SelectionListenerWithASTManager.java:123)\n        at\norg.eclipse.jdt.internal.ui.viewsupport.SelectionListenerWithASTManager$1.run(SelectionListenerWithASTManager\n.java:101)\n        at org.eclipse.core.internal.jobs.Worker.run(Worker.java:62)",
    "Version 3.0.m8",
    "Cannot reproduce trying to type the following code.\npackage p;\n\npublic class X {\n\t\n\tCharRange CHAR_RANGE_1 \u003d new CharRange(0x0, 0x7FF);\n\t\n\tpublic static void main(String[] args) {\n\t}\n}\n\nCould you please provide a complete test case or try to detail steps to\nreproduce if you get it often?\n\nThanks for your help.",
    "This has not happened since the first time I ran into it. Easy enough to watch\nfor of course, I\u0027ll report here if it happens again.",
    "Close as REMIND. Please reopen if it happens again.",
    "Closing as never reproduced in a long time"
  ],
  "commentCreationDates": [
    "2004-04-15T23:40:57+02:00",
    "2004-04-15T23:41:18+02:00",
    "2004-04-16T21:47:53+02:00",
    "2004-04-16T22:07:30+02:00",
    "2004-04-28T02:39:43+02:00",
    "2005-02-17T14:37:55+01:00"
  ],
  "traces": [
    {
      "exceptionType": "java.lang.IllegalArgumentException",
      "elements": [
        {
          "method": "org.eclipse.jdt.core.dom.ASTNode.setSourceRange",
          "source": "ASTNode.java:2592"
        },
        {
          "method": "org.eclipse.jdt.core.dom.ASTConverter.convertToVariableDeclarationFragment",
          "source": "ASTConverter.java:2677"
        },
        {
          "method": "org.eclipse.jdt.core.dom.ASTConverter.convertToFieldDeclaration",
          "source": "ASTConverter.java:2722"
        },
        {
          "method": "org.eclipse.jdt.core.dom.ASTConverter.checkAndAddMultipleFieldDeclaration",
          "source": "ASTConverter.java:364"
        },
        {
          "method": "org.eclipse.jdt.core.dom.ASTConverter.buildBodyDeclarations",
          "source": "ASTConverter.java:324"
        },
        {
          "method": "org.eclipse.jdt.core.dom.ASTConverter.convert",
          "source": "ASTConverter.java:268"
        },
        {
          "method": "org.eclipse.jdt.core.dom.ASTConverter.convert",
          "source": "ASTConverter.java:146"
        },
        {
          "method": "org.eclipse.jdt.core.dom.ASTParser.convert",
          "source": "ASTParser.java:697"
        },
        {
          "method": "org.eclipse.jdt.core.dom.ASTParser.internalCreateAST",
          "source": "ASTParser.java:667"
        },
        {
          "method": "org.eclipse.jdt.core.dom.ASTParser.createAST",
          "source": "ASTParser.java:563"
        },
        {
          "method": "org.eclipse.jdt.internal.ui.javaeditor.ASTProvider.createAST",
          "source": "ASTProvider.java:383"
        },
        {
          "method": "org.eclipse.jdt.internal.ui.javaeditor.ASTProvider.getAST",
          "source": "ASTProvider.java:344"
        },
        {
          "method": "org.eclipse.jdt.internal.ui.viewsupport.SelectionListenerWithASTManager$PartListenerGroup.calculateASTandInform",
          "source": "SelectionListenerWithASTManager.java:123"
        },
        {
          "method": "org.eclipse.jdt.internal.ui.viewsupport.SelectionListenerWithASTManager$1.run",
          "source": "SelectionListenerWithASTManager .java:101"
        },
        {
          "method": "org.eclipse.core.internal.jobs.Worker.run",
          "source": "Worker.java:62"
        }
      ],
      "number": 0,
      "commentIndex": 0,
      "bugId": "58751",
      "date": "2004-04-15T23:40:57+02:00",
      "product": "JDT",
      "component": "Core",
      "severity": "normal"
    }
  ],
  "groupId": "58751",
  "bugId": "58751",
  "date": "2004-04-15T23:40:57+02:00",
  "product": "JDT",
  "component": "Core",
  "severity": "normal"
}