{
  "comments": [
    "Log: Wed Nov 14 09:32:26 CET 2001\n1 org.eclipse.core.resources 4 Problems saving workspace\nProblems saving workspace\nReason:\nWhen performing a save of my workspace, I got some problems in the code saving \nJava variables, caused by an intempestive ResourceException raised when \naccessing the property store.\n\nWorkspace is available upon request.\n\n\nLog: Wed Nov 14 09:32:26 CET 2001\n2 org.eclipse.ui 1 Problems occurred while trying to save the state of the workb\nench.\n        1\u003d\u003d\u003d\u003d\u003d\u003d\u003d\u003d\u003d\u003d\u003d\u003d\u003d\u003cchildren\u003e\u003d\u003d\u003d\u003d\u003d\u003d\u003d\u003d\u003d\u003d\u003d\u003d\u003d\n        2 org.eclipse.core.resources 566 Problems occurred during save.\norg.eclipse.core.internal.resources.ResourceException: Property store is not ava\nilable for: /.\n        at org.eclipse.core.internal.properties.PropertyManager.getPropertyStore\n(PropertyManager.java:129)\n        at org.eclipse.core.internal.properties.PropertyManager.setProperty(Prop\nertyManager.java:146)\n        at org.eclipse.core.internal.resources.Resource.setPersistentProperty(Re\nsource.java:890)\n        at org.eclipse.jdt.internal.core.JavaModelManager.saveVariables(JavaMode\nlManager.java:976)\n        at org.eclipse.jdt.internal.core.JavaModelManager.saving(JavaModelManage\nr.java:987)\n        at org.eclipse.core.internal.resources.SaveManager.executeLifecycle(Save\nManager.java:244)\n        at org.eclipse.core.internal.resources.SaveManager$1.run(SaveManager.jav\na:87)\n        at org.eclipse.core.internal.runtime.InternalPlatform.run(InternalPlatfo\nrm.java:812)\n        at org.eclipse.core.runtime.Platform.run(Platform.java:395)\n        at org.eclipse.core.internal.resources.SaveManager.broadcastLifecycle(Sa\nveManager.java:98)\n        at org.eclipse.core.internal.resources.SaveManager.save(SaveManager.java\n:1073)\n        at org.eclipse.core.internal.resources.Workspace.save(Workspace.java:120\n7)\n        at org.eclipse.ui.internal.Workbench$4.run(Workbench.java:180)\n        at org.eclipse.jface.operation.ModalContext.runInCurrentThread(ModalCont\next.java:296)\n        at org.eclipse.jface.operation.ModalContext.run(ModalContext.java:249)\n        at org.eclipse.jface.dialogs.ProgressMonitorDialog.run(ProgressMonitorDi\nalog.java:335)\n        at org.eclipse.ui.internal.Workbench.disconnectFromWorkspace(Workbench.j\nava:187)\n        at org.eclipse.ui.internal.Workbench.busyClose(Workbench.java:109)\n        at org.eclipse.ui.internal.Workbench.access$4(Workbench.java:77)\n        at org.eclipse.ui.internal.Workbench$3.run(Workbench.java:159)\n        at org.eclipse.swt.custom.BusyIndicator.showWhile(BusyIndicator.java:56)\n\n        at org.eclipse.ui.internal.Workbench.close(Workbench.java:157)\n        at org.eclipse.ui.internal.QuitAction.run(QuitAction.java:31)\n        at org.eclipse.jface.action.Action.runWithEvent(Action.java:453)\n        at org.eclipse.jface.action.ActionContributionItem.handleWidgetSelection\n(ActionContributionItem.java:407)\n        at org.eclipse.jface.action.ActionContributionItem.handleWidgetEvent(Act\nionContributionItem.java:361)\n        at org.eclipse.jface.action.ActionContributionItem.access$0(ActionContri\nbutionItem.java:352)\n        at org.eclipse.jface.action.ActionContributionItem$ActionListener.handle\nEvent(ActionContributionItem.java:47)\n        at org.eclipse.swt.widgets.EventTable.sendEvent(EventTable.java:54)\n        at org.eclipse.swt.widgets.Widget.notifyListeners(Widget.java:635)\n        at org.eclipse.swt.widgets.Display.runDeferredEvents(Display.java:1365)\n        at org.eclipse.swt.widgets.Display.readAndDispatch(Display.java:1167)\n        at org.eclipse.ui.internal.Workbench.runEventLoop(Workbench.java:727)\n        at org.eclipse.ui.internal.Workbench.run(Workbench.java:710)\n        at org.eclipse.core.internal.boot.InternalBootLoader.run(InternalBootLoa\nder.java:820)\n        at org.eclipse.core.boot.BootLoader.run(BootLoader.java:285)\n        at java.lang.reflect.Method.invoke(Native Method)\n        at org.eclipse.core.launcher.Main.basicRun(Main.java:151)\n        at org.eclipse.core.launcher.Main.run(Main.java:502)\n        at org.eclipse.core.launcher.UIMain.main(UIMain.java:52)\n                4 org.eclipse.core.resources 271 Property store is not available\n for: /.\n        1\u003d\u003d\u003d\u003d\u003d\u003d\u003d\u003d\u003d\u003d\u003d\u003d\u003d\u003c/children\u003e\u003d\u003d\u003d\u003d\u003d\u003d\u003d\u003d\u003d\u003d\u003d\u003d\u003d\nProblems occurred while trying to save the state of the workbench.\n\nD:\\eclipse\\sdk\\eclipse\u003epause\nPress any key to continue . . .",
    "\n\n*** This bug has been marked as a duplicate of 5812 ***"
  ],
  "commentCreationDates": [
    "2001-11-14T09:18:44+01:00",
    "2001-11-14T16:05:18+01:00"
  ],
  "traces": [
    {
      "exceptionType": "org.eclipse.core.internal.resources.ResourceException",
      "message": "Property store is not ava ilable for: /.",
      "elements": [
        {
          "method": "org.eclipse.core.internal.properties.PropertyManager.getPropertyStore",
          "source": "PropertyManager.java:129"
        },
        {
          "method": "org.eclipse.core.internal.properties.PropertyManager.setProperty",
          "source": "Prop ertyManager.java:146"
        },
        {
          "method": "org.eclipse.core.internal.resources.Resource.setPersistentProperty",
          "source": "Re source.java:890"
        },
        {
          "method": "org.eclipse.jdt.internal.core.JavaModelManager.saveVariables",
          "source": "JavaMode lManager.java:976"
        },
        {
          "method": "org.eclipse.jdt.internal.core.JavaModelManager.saving",
          "source": "JavaModelManage r.java:987"
        },
        {
          "method": "org.eclipse.core.internal.resources.SaveManager.executeLifecycle",
          "source": "Save Manager.java:244"
        },
        {
          "method": "org.eclipse.core.internal.resources.SaveManager$1.run",
          "source": "SaveManager.jav a:87"
        },
        {
          "method": "org.eclipse.core.internal.runtime.InternalPlatform.run",
          "source": "InternalPlatfo rm.java:812"
        },
        {
          "method": "org.eclipse.core.runtime.Platform.run",
          "source": "Platform.java:395"
        },
        {
          "method": "org.eclipse.core.internal.resources.SaveManager.broadcastLifecycle",
          "source": "Sa veManager.java:98"
        },
        {
          "method": "org.eclipse.core.internal.resources.SaveManager.save",
          "source": "SaveManager.java :1073"
        },
        {
          "method": "org.eclipse.core.internal.resources.Workspace.save",
          "source": "Workspace.java:120 7"
        },
        {
          "method": "org.eclipse.ui.internal.Workbench$4.run",
          "source": "Workbench.java:180"
        },
        {
          "method": "org.eclipse.jface.operation.ModalContext.runInCurrentThread",
          "source": "ModalCont ext.java:296"
        },
        {
          "method": "org.eclipse.jface.operation.ModalContext.run",
          "source": "ModalContext.java:249"
        },
        {
          "method": "org.eclipse.jface.dialogs.ProgressMonitorDialog.run",
          "source": "ProgressMonitorDi alog.java:335"
        },
        {
          "method": "org.eclipse.ui.internal.Workbench.disconnectFromWorkspace",
          "source": "Workbench.j ava:187"
        },
        {
          "method": "org.eclipse.ui.internal.Workbench.busyClose",
          "source": "Workbench.java:109"
        },
        {
          "method": "org.eclipse.ui.internal.Workbench.access$4",
          "source": "Workbench.java:77"
        },
        {
          "method": "org.eclipse.ui.internal.Workbench$3.run",
          "source": "Workbench.java:159"
        },
        {
          "method": "org.eclipse.swt.custom.BusyIndicator.showWhile",
          "source": "BusyIndicator.java:56"
        },
        {
          "method": "org.eclipse.ui.internal.Workbench.close",
          "source": "Workbench.java:157"
        },
        {
          "method": "org.eclipse.ui.internal.QuitAction.run",
          "source": "QuitAction.java:31"
        },
        {
          "method": "org.eclipse.jface.action.Action.runWithEvent",
          "source": "Action.java:453"
        },
        {
          "method": "org.eclipse.jface.action.ActionContributionItem.handleWidgetSelection",
          "source": "ActionContributionItem.java:407"
        },
        {
          "method": "org.eclipse.jface.action.ActionContributionItem.handleWidgetEvent",
          "source": "Act ionContributionItem.java:361"
        },
        {
          "method": "org.eclipse.jface.action.ActionContributionItem.access$0",
          "source": "ActionContri butionItem.java:352"
        },
        {
          "method": "org.eclipse.jface.action.ActionContributionItem$ActionListener.handleEvent",
          "source": "ActionContributionItem.java:47"
        },
        {
          "method": "org.eclipse.swt.widgets.EventTable.sendEvent",
          "source": "EventTable.java:54"
        },
        {
          "method": "org.eclipse.swt.widgets.Widget.notifyListeners",
          "source": "Widget.java:635"
        },
        {
          "method": "org.eclipse.swt.widgets.Display.runDeferredEvents",
          "source": "Display.java:1365"
        },
        {
          "method": "org.eclipse.swt.widgets.Display.readAndDispatch",
          "source": "Display.java:1167"
        },
        {
          "method": "org.eclipse.ui.internal.Workbench.runEventLoop",
          "source": "Workbench.java:727"
        },
        {
          "method": "org.eclipse.ui.internal.Workbench.run",
          "source": "Workbench.java:710"
        },
        {
          "method": "org.eclipse.core.internal.boot.InternalBootLoader.run",
          "source": "InternalBootLoa der.java:820"
        },
        {
          "method": "org.eclipse.core.boot.BootLoader.run",
          "source": "BootLoader.java:285"
        },
        {
          "method": "java.lang.reflect.Method.invoke",
          "source": "Native Method"
        },
        {
          "method": "org.eclipse.core.launcher.Main.basicRun",
          "source": "Main.java:151"
        },
        {
          "method": "org.eclipse.core.launcher.Main.run",
          "source": "Main.java:502"
        },
        {
          "method": "org.eclipse.core.launcher.UIMain.main",
          "source": "UIMain.java:52"
        }
      ],
      "number": 0,
      "commentIndex": 0,
      "bugId": "5879",
      "duplicateId": "5812",
      "date": "2001-11-14T09:18:44+01:00",
      "product": "Platform",
      "component": "Resources",
      "severity": "normal"
    }
  ],
  "groupId": "5812",
  "bugId": "5879",
  "duplicateId": "5812",
  "date": "2001-11-14T09:18:44+01:00",
  "product": "Platform",
  "component": "Resources",
  "severity": "normal"
}