{
  "comments": [
    "If certain refactorings are attempted with a Cheetah-enabled 3.0M8 installation\non a source file with some of the new-style for loops, the following exception\nshows up and the dialog for configuring the refactoring does not:\n\njava.lang.IllegalArgumentException: Not yet implemented: convert(class\norg.eclipse.jdt.internal.compiler.ast.ForeachStatement)\n        at org.eclipse.jdt.core.dom.ASTConverter.convert(ASTConverter.java:1792)\n        at org.eclipse.jdt.core.dom.ASTConverter.convert(ASTConverter.java:398)\n        at\norg.eclipse.jdt.core.dom.ASTConverter.buildBodyDeclarations(ASTConverter.java:209)\n        at org.eclipse.jdt.core.dom.ASTConverter.convert(ASTConverter.java:1936)\n        at org.eclipse.jdt.core.dom.ASTConverter.convert(ASTConverter.java:931)\n        at org.eclipse.jdt.core.dom.AST.convertCompilationUnit(AST.java:239)\n        at\norg.eclipse.jdt.internal.core.ReconcileWorkingCopyOperation.executeOperation(ReconcileWorkingCopyOperation.java:81)\n        at\norg.eclipse.jdt.internal.core.JavaModelOperation.run(JavaModelOperation.java:700)\n        at\norg.eclipse.jdt.internal.core.JavaModelOperation.runOperation(JavaModelOperation.java:739)\n        at\norg.eclipse.jdt.internal.core.CompilationUnit.reconcile(CompilationUnit.java:1111)\n        at\norg.eclipse.jdt.internal.core.CompilationUnit.reconcile(CompilationUnit.java:1080)\n        at\norg.eclipse.jdt.internal.ui.text.java.JavaReconcilingStrategy.reconcile(JavaReconcilingStrategy.java:85)\n        at\norg.eclipse.jdt.internal.ui.text.java.JavaReconcilingStrategy.initialReconcile(JavaReconcilingStrategy.java:145)\n        at\norg.eclipse.jface.text.reconciler.CompositeReconcilingStrategy.initialReconcile(CompositeReconcilingStrategy.java:111)\n        at\norg.eclipse.jdt.internal.ui.text.JavaCompositeReconcilingStrategy.initialReconcile(JavaCompositeReconcilingStrategy.java:123)\n        at\norg.eclipse.jface.text.reconciler.MonoReconciler.initialProcess(MonoReconciler.java:104)\n        at\norg.eclipse.jdt.internal.ui.text.JavaReconciler.initialProcess(JavaReconciler.java:280)\n        at\norg.eclipse.jface.text.reconciler.AbstractReconciler$BackgroundThread.run(AbstractReconciler.java:155)\n\nCommenting out the foreach loops allows the refactoring to proceed.\n\nUsing JDT core 3.0.0.cheetah03 installed through the CVS checkout updater.",
    "Remember that tools outside compiler have not yet been leveraged to support \n1.5. Support will gradually come.",
    "The problem is that the reconciler is only using AST level 2.0 and to get the\n1.5 constructs it would need to use the AST level 3.0.\nThere is no much I can do about this.\n",
    "\n\n*** This bug has been marked as a duplicate of 59052 ***"
  ],
  "commentCreationDates": [
    "2004-04-19T06:03:59+02:00",
    "2004-04-19T11:31:01+02:00",
    "2004-04-19T16:19:37+02:00",
    "2004-04-19T16:43:07+02:00"
  ],
  "traces": [
    {
      "exceptionType": "java.lang.IllegalArgumentException",
      "message": "Not yet implemented: convert(class org.eclipse.jdt.internal.compiler.ast.ForeachStatement)",
      "elements": [
        {
          "method": "org.eclipse.jdt.core.dom.ASTConverter.convert",
          "source": "ASTConverter.java:1792"
        },
        {
          "method": "org.eclipse.jdt.core.dom.ASTConverter.convert",
          "source": "ASTConverter.java:398"
        },
        {
          "method": "org.eclipse.jdt.core.dom.ASTConverter.buildBodyDeclarations",
          "source": "ASTConverter.java:209"
        },
        {
          "method": "org.eclipse.jdt.core.dom.ASTConverter.convert",
          "source": "ASTConverter.java:1936"
        },
        {
          "method": "org.eclipse.jdt.core.dom.ASTConverter.convert",
          "source": "ASTConverter.java:931"
        },
        {
          "method": "org.eclipse.jdt.core.dom.AST.convertCompilationUnit",
          "source": "AST.java:239"
        },
        {
          "method": "org.eclipse.jdt.internal.core.ReconcileWorkingCopyOperation.executeOperation",
          "source": "ReconcileWorkingCopyOperation.java:81"
        },
        {
          "method": "org.eclipse.jdt.internal.core.JavaModelOperation.run",
          "source": "JavaModelOperation.java:700"
        },
        {
          "method": "org.eclipse.jdt.internal.core.JavaModelOperation.runOperation",
          "source": "JavaModelOperation.java:739"
        },
        {
          "method": "org.eclipse.jdt.internal.core.CompilationUnit.reconcile",
          "source": "CompilationUnit.java:1111"
        },
        {
          "method": "org.eclipse.jdt.internal.core.CompilationUnit.reconcile",
          "source": "CompilationUnit.java:1080"
        },
        {
          "method": "org.eclipse.jdt.internal.ui.text.java.JavaReconcilingStrategy.reconcile",
          "source": "JavaReconcilingStrategy.java:85"
        },
        {
          "method": "org.eclipse.jdt.internal.ui.text.java.JavaReconcilingStrategy.initialReconcile",
          "source": "JavaReconcilingStrategy.java:145"
        },
        {
          "method": "org.eclipse.jface.text.reconciler.CompositeReconcilingStrategy.initialReconcile",
          "source": "CompositeReconcilingStrategy.java:111"
        },
        {
          "method": "org.eclipse.jdt.internal.ui.text.JavaCompositeReconcilingStrategy.initialReconcile",
          "source": "JavaCompositeReconcilingStrategy.java:123"
        },
        {
          "method": "org.eclipse.jface.text.reconciler.MonoReconciler.initialProcess",
          "source": "MonoReconciler.java:104"
        },
        {
          "method": "org.eclipse.jdt.internal.ui.text.JavaReconciler.initialProcess",
          "source": "JavaReconciler.java:280"
        },
        {
          "method": "org.eclipse.jface.text.reconciler.AbstractReconciler$BackgroundThread.run",
          "source": "AbstractReconciler.java:155"
        }
      ],
      "number": 0,
      "commentIndex": 0,
      "bugId": "59023",
      "duplicateId": "59052",
      "date": "2004-04-19T06:03:59+02:00",
      "product": "JDT",
      "component": "Core",
      "severity": "normal"
    }
  ],
  "groupId": "59052",
  "bugId": "59023",
  "duplicateId": "59052",
  "date": "2004-04-19T06:03:59+02:00",
  "product": "JDT",
  "component": "Core",
  "severity": "normal"
}