{
  "comments": [
    "Found in Hyades 3.0 20040419_0915 driver.\n\nSteps to reproduce:\n-------------------\n1. Start Eclipse in a new workspace.\n2. Start a java process in the command line using -XrunpiAgent.\n3. Create a new Java-Attach configuration, attach to the java process, and \nprofile in some data. Then, terminate the process.\n4. The tooltip of the Profile button on the toolbar has now changed \nfrom \"Profile\" to \"Profile New_configuration\". Click on the button.\n\nYou will notice that nothing happens. This is because this configuration is \ndependent on attaching to a Java process. But since you\u0027ve killed that process, \nthis configuration can\u0027t attach to anything, so it does nothing.\n\nI think some info-message-popup should come up telling the user of this (in the \ndelegate?), and possibly provide a pop-up allowing the user to choose the new \nJava process to attach to.",
    "I\u0027ve also noticed a similar problem in another scenario...\n\n1. Create a new \"External Java App\" profile configuration, and specify \nnosuchhost as the host to use.\n2. Set some class, and some classpath, then Run.\n\nYou will see that the progress bar of the workbench starts going, and then \nstops. Nothing happens. I think there should be a msg telling the user that it \ncan\u0027t connect to \u0027nosuchhost\u0027, or something to that effect.\n\nI think these two problems are related, but let me know if you want this in a \nseparate bug - thanks. \u003d)",
    "I couldn\u0027t replicate the second scenario. I get an error pop-up stating that it \ncouldn\u0027t connect to the host. Are you able to reproduce this?",
    "Yup. I just reproduced the second one (i.e. External Java App + non-existent \nhost) again on the 20040419_0915 driver. I used \"nosuchhost:10002\", and after I \nclicked Run, nothing happened.\n\nNot sure what we\u0027re doing differently...",
    "\nI was using the latest code from CVS. I tested with the specified build and \nconfirmed, I get no pop-up. The exception printed to the console is:\n\norg.eclipse.swt.SWTException: Invalid thread access\n        at org.eclipse.swt.SWT.error(SWT.java:2659)\n        at org.eclipse.swt.SWT.error(SWT.java(Inlined Compiled Code))\n        at org.eclipse.swt.SWT.error(SWT.java(Inlined Compiled Code))\n        at org.eclipse.swt.widgets.Display.error(Display.java(Inlined Compiled \nCode))\n        at org.eclipse.swt.widgets.Display.checkDevice(Display.java(Compiled \nCode))\n        at org.eclipse.swt.widgets.Display.getActiveShell(Display.java:1026)\n        at org.eclipse.ui.internal.Workbench.getActiveWorkbenchWindow\n(Workbench.java:581)\n        at org.eclipse.hyades.security.util.ConnectUtil.getValidShell\n(ConnectUtil.java:570)\n        at org.eclipse.hyades.security.util.ConnectUtil.connect\n(ConnectUtil.java:142)\n        at org.eclipse.hyades.trace.ui.internal.util.PDCoreUtil.profileConnect\n(PDCoreUtil.java:999)\n        at org.eclipse.hyades.trace.ui.internal.util.PDCoreUtil.launchTrace\n(PDCoreUtil.java:661)\n        at \norg.eclipse.hyades.trace.ui.internal.launcher.ProfileJavaApplicationDelegate.lau\nnch(ProfileJavaApplicationDelegate.java:66)\n        at org.eclipse.debug.internal.core.LaunchConfiguration.launch\n(LaunchConfiguration.java:569)\n        at org.eclipse.debug.internal.core.LaunchConfiguration.launch\n(LaunchConfiguration.java:150)\n        at org.eclipse.debug.internal.ui.DebugUIPlugin.buildAndLaunch\n(DebugUIPlugin.java:774)\n        at org.eclipse.debug.ui.DebugUITools.buildAndLaunch\n(DebugUITools.java:629)\n        at org.eclipse.debug.ui.DebugUITools$3.run(DebugUITools.java:585)\n        at org.eclipse.core.internal.jobs.Worker.run(Worker.java:62)\n \n",
    "\nThis problem (the second scenario) was fixed in #59265. The fix will be \navailable in the next build. This isn\u0027t related to the first scenario. For the \nfirst one, the delegate wasn\u0027t checking for this error.",
    "\nFixed.",
    "Verified as fixed with Hyades 3.0 20040407_0845 driver during the second M9 \ntestpass.",
    "Closing bug."
  ],
  "commentCreationDates": [
    "2004-04-19T21:58:28+02:00",
    "2004-04-20T16:19:50+02:00",
    "2004-04-21T21:22:19+02:00",
    "2004-04-21T21:29:28+02:00",
    "2004-04-21T21:40:33+02:00",
    "2004-04-21T21:45:17+02:00",
    "2004-04-23T01:11:01+02:00",
    "2004-04-28T15:12:09+02:00",
    "2004-07-24T00:31:10+02:00"
  ],
  "traces": [
    {
      "exceptionType": "org.eclipse.swt.SWTException",
      "message": "Invalid thread access",
      "elements": [
        {
          "method": "org.eclipse.swt.SWT.error",
          "source": "SWT.java:2659"
        },
        {
          "method": "org.eclipse.swt.SWT.error",
          "source": "SWT.java(Inlined Compiled Code)"
        },
        {
          "method": "org.eclipse.swt.SWT.error",
          "source": "SWT.java(Inlined Compiled Code)"
        },
        {
          "method": "org.eclipse.swt.widgets.Display.error",
          "source": "Display.java(Inlined Compiled  Code)"
        },
        {
          "method": "org.eclipse.swt.widgets.Display.checkDevice",
          "source": "Display.java(Compiled  Code)"
        },
        {
          "method": "org.eclipse.swt.widgets.Display.getActiveShell",
          "source": "Display.java:1026"
        },
        {
          "method": "org.eclipse.ui.internal.Workbench.getActiveWorkbenchWindow",
          "source": "Workbench.java:581"
        },
        {
          "method": "org.eclipse.hyades.security.util.ConnectUtil.getValidShell",
          "source": "ConnectUtil.java:570"
        },
        {
          "method": "org.eclipse.hyades.security.util.ConnectUtil.connect",
          "source": "ConnectUtil.java:142"
        },
        {
          "method": "org.eclipse.hyades.trace.ui.internal.util.PDCoreUtil.profileConnect",
          "source": "PDCoreUtil.java:999"
        },
        {
          "method": "org.eclipse.hyades.trace.ui.internal.util.PDCoreUtil.launchTrace",
          "source": "PDCoreUtil.java:661"
        },
        {
          "method": "org.eclipse.hyades.trace.ui.internal.launcher.ProfileJavaApplicationDelegate.launch",
          "source": "ProfileJavaApplicationDelegate.java:66"
        },
        {
          "method": "org.eclipse.debug.internal.core.LaunchConfiguration.launch",
          "source": "LaunchConfiguration.java:569"
        },
        {
          "method": "org.eclipse.debug.internal.core.LaunchConfiguration.launch",
          "source": "LaunchConfiguration.java:150"
        },
        {
          "method": "org.eclipse.debug.internal.ui.DebugUIPlugin.buildAndLaunch",
          "source": "DebugUIPlugin.java:774"
        },
        {
          "method": "org.eclipse.debug.ui.DebugUITools.buildAndLaunch",
          "source": "DebugUITools.java:629"
        },
        {
          "method": "org.eclipse.debug.ui.DebugUITools$3.run",
          "source": "DebugUITools.java:585"
        },
        {
          "method": "org.eclipse.core.internal.jobs.Worker.run",
          "source": "Worker.java:62"
        }
      ],
      "number": 0,
      "commentIndex": 4,
      "bugId": "59138",
      "date": "2004-04-21T21:40:33+02:00",
      "product": "Hyades",
      "component": "UI",
      "severity": "normal"
    }
  ],
  "groupId": "59138",
  "bugId": "59138",
  "date": "2004-04-19T21:58:28+02:00",
  "product": "Hyades",
  "component": "UI",
  "severity": "normal"
}