{
  "comments": [
    "java.lang.NullPointerException\n        at org.eclipse.compare.internal.CompareUIPlugin$CompareRegistry.search(C\nompareUIPlugin.java:121)\n        at org.eclipse.compare.internal.CompareUIPlugin.findStructureViewer(Comp\nareUIPlugin.java:714)\n        at org.eclipse.compare.CompareEditorInput.findStructureViewer(CompareEdi\ntorInput.java:647)\n        at org.eclipse.compare.CompareEditorInput$3.getViewer(CompareEditorInput\n.java:429)\n        at org.eclipse.compare.CompareViewerSwitchingPane.setInput(CompareViewer\nSwitchingPane.java:291)\n        at org.eclipse.compare.CompareEditorInput.createContents(CompareEditorIn\nput.java:395)\n        at org.eclipse.compare.internal.CompareEditor.createPartControl(CompareE\nditor.java:160)\n        at org.eclipse.compare.internal.CompareEditor.doSetInput(CompareEditor.j\nava:137)\n        at org.eclipse.compare.internal.CompareEditor.setInput(CompareEditor.jav\na:103)\n        at org.eclipse.compare.internal.CompareUIPlugin.openCompareEditor(Compar\neUIPlugin.java:433)\n        at org.eclipse.compare.CompareUI.reuseCompareEditor(CompareUI.java:141)\n        at org.eclipse.team.internal.ui.synchronize.actions.OpenInCompareAction.\nopenCompareEditor(OpenInCompareAction.java:70)\n        at org.eclipse.team.internal.ui.synchronize.actions.OpenInCompareAction.\nrun(OpenInCompareAction.java:50)\n        at org.eclipse.team.internal.ui.synchronize.actions.OpenWithActionGroup.\nopenInCompareEditor(OpenWithActionGroup.java:104)\n        at org.eclipse.team.ui.synchronize.subscribers.SynchronizeViewerAdvisor.\nhandleOpen(SynchronizeViewerAdvisor.java:112)\n        at org.eclipse.team.ui.synchronize.subscribers.SynchronizeViewerAdvisor$\n3.open(SynchronizeViewerAdvisor.java:105)\n        at org.eclipse.jface.viewers.StructuredViewer$2.run(StructuredViewer.jav\na:406)\n        at org.eclipse.core.internal.runtime.InternalPlatform.run(InternalPlatfo\nrm.java:609)\n        at org.eclipse.core.runtime.Platform.run(Platform.java:541)\n        at org.eclipse.jface.viewers.StructuredViewer.fireOpen(StructuredViewer.\njava:404)\n        at org.eclipse.jface.viewers.StructuredViewer.handleOpen(StructuredViewe\nr.java:614)\n        at org.eclipse.jface.viewers.StructuredViewer$6.handleOpen(StructuredVie\nwer.java:703)\n        at org.eclipse.jface.util.OpenStrategy.fireOpenEvent(OpenStrategy.java:2\n09)\n        at org.eclipse.jface.util.OpenStrategy.access$2(OpenStrategy.java:204)\n        at org.eclipse.jface.util.OpenStrategy$1.mouseSelectItem(OpenStrategy.ja\nva:344)\n        at org.eclipse.jface.util.OpenStrategy$1.handleEvent(OpenStrategy.java:2\n89)\n        at org.eclipse.swt.widgets.EventTable.sendEvent(EventTable.java:82)\n        at org.eclipse.swt.widgets.Widget.sendEvent(Widget.java:769)\n        at org.eclipse.swt.widgets.Display.runDeferredEvents(Display.java:2592)\n        at org.eclipse.swt.widgets.Display.readAndDispatch(Display.java:2270)\n        at org.eclipse.ui.internal.Workbench.runEventLoop(Workbench.java:1437)\n        at org.eclipse.ui.internal.Workbench.runUI(Workbench.java:1408)\n        at org.eclipse.ui.internal.Workbench.createAndRunWorkbench(Workbench.jav\na:244)\n        at org.eclipse.ui.PlatformUI.createAndRunWorkbench(PlatformUI.java:140)\n        at org.eclipse.ui.internal.ide.IDEApplication.run(IDEApplication.java:90\n)\n        at org.eclipse.core.internal.runtime.PlatformActivator$1.run(PlatformAct\nivator.java:280)\n        at org.eclipse.core.runtime.adaptor.EclipseStarter.run(EclipseStarter.ja\nva:240)\n        at org.eclipse.core.runtime.adaptor.EclipseStarter.run(EclipseStarter.ja\nva:117)\n        at sun.reflect.NativeMethodAccessorImpl.invoke0(Native Method)\n        at sun.reflect.NativeMethodAccessorImpl.invoke(NativeMethodAccessorImpl.\njava:39)\n        at sun.reflect.DelegatingMethodAccessorImpl.invoke(DelegatingMethodAcces\nsorImpl.java:25)\n        at java.lang.reflect.Method.invoke(Method.java:324)\n        at org.eclipse.core.launcher.Main.basicRun(Main.java:267)\n        at org.eclipse.core.launcher.Main.run(Main.java:699)\n        at org.eclipse.core.launcher.Main.main(Main.java:683)",
    "Using N20040420.from20040420_0943\n",
    "Currently reproducible when opening the compare editor on a shared launch config\nwith conflicts in the Synchronize View.\n",
    "fixed for I20040420"
  ],
  "commentCreationDates": [
    "2004-04-20T10:49:48+02:00",
    "2004-04-20T10:50:38+02:00",
    "2004-04-20T10:52:51+02:00",
    "2004-04-20T11:33:33+02:00"
  ],
  "traces": [
    {
      "exceptionType": "java.lang.NullPointerException",
      "elements": [
        {
          "method": "org.eclipse.compare.internal.CompareUIPlugin$CompareRegistry.search",
          "source": "C ompareUIPlugin.java:121"
        },
        {
          "method": "org.eclipse.compare.internal.CompareUIPlugin.findStructureViewer",
          "source": "Comp areUIPlugin.java:714"
        },
        {
          "method": "org.eclipse.compare.CompareEditorInput.findStructureViewer",
          "source": "CompareEdi torInput.java:647"
        },
        {
          "method": "org.eclipse.compare.CompareEditorInput$3.getViewer",
          "source": "CompareEditorInput .java:429"
        },
        {
          "method": "org.eclipse.compare.CompareViewerSwitchingPane.setInput",
          "source": "CompareViewer SwitchingPane.java:291"
        },
        {
          "method": "org.eclipse.compare.CompareEditorInput.createContents",
          "source": "CompareEditorIn put.java:395"
        },
        {
          "method": "org.eclipse.compare.internal.CompareEditor.createPartControl",
          "source": "CompareE ditor.java:160"
        },
        {
          "method": "org.eclipse.compare.internal.CompareEditor.doSetInput",
          "source": "CompareEditor.j ava:137"
        },
        {
          "method": "org.eclipse.compare.internal.CompareEditor.setInput",
          "source": "CompareEditor.jav a:103"
        },
        {
          "method": "org.eclipse.compare.internal.CompareUIPlugin.openCompareEditor",
          "source": "Compar eUIPlugin.java:433"
        },
        {
          "method": "org.eclipse.compare.CompareUI.reuseCompareEditor",
          "source": "CompareUI.java:141"
        },
        {
          "method": "org.eclipse.team.internal.ui.synchronize.actions.OpenInCompareAction.openCompareEditor",
          "source": "OpenInCompareAction.java:70"
        },
        {
          "method": "org.eclipse.team.internal.ui.synchronize.actions.OpenInCompareAction.run",
          "source": "OpenInCompareAction.java:50"
        },
        {
          "method": "org.eclipse.team.internal.ui.synchronize.actions.OpenWithActionGroup.openInCompareEditor",
          "source": "OpenWithActionGroup.java:104"
        },
        {
          "method": "org.eclipse.team.ui.synchronize.subscribers.SynchronizeViewerAdvisor.handleOpen",
          "source": "SynchronizeViewerAdvisor.java:112"
        },
        {
          "method": "org.eclipse.team.ui.synchronize.subscribers.SynchronizeViewerAdvisor$3.open",
          "source": "SynchronizeViewerAdvisor.java:105"
        },
        {
          "method": "org.eclipse.jface.viewers.StructuredViewer$2.run",
          "source": "StructuredViewer.jav a:406"
        },
        {
          "method": "org.eclipse.core.internal.runtime.InternalPlatform.run",
          "source": "InternalPlatfo rm.java:609"
        },
        {
          "method": "org.eclipse.core.runtime.Platform.run",
          "source": "Platform.java:541"
        },
        {
          "method": "org.eclipse.jface.viewers.StructuredViewer.fireOpen",
          "source": "StructuredViewer. java:404"
        },
        {
          "method": "org.eclipse.jface.viewers.StructuredViewer.handleOpen",
          "source": "StructuredViewe r.java:614"
        },
        {
          "method": "org.eclipse.jface.viewers.StructuredViewer$6.handleOpen",
          "source": "StructuredVie wer.java:703"
        },
        {
          "method": "org.eclipse.jface.util.OpenStrategy.fireOpenEvent",
          "source": "OpenStrategy.java:2 09"
        },
        {
          "method": "org.eclipse.jface.util.OpenStrategy.access$2",
          "source": "OpenStrategy.java:204"
        },
        {
          "method": "org.eclipse.jface.util.OpenStrategy$1.mouseSelectItem",
          "source": "OpenStrategy.ja va:344"
        },
        {
          "method": "org.eclipse.jface.util.OpenStrategy$1.handleEvent",
          "source": "OpenStrategy.java:2 89"
        },
        {
          "method": "org.eclipse.swt.widgets.EventTable.sendEvent",
          "source": "EventTable.java:82"
        },
        {
          "method": "org.eclipse.swt.widgets.Widget.sendEvent",
          "source": "Widget.java:769"
        },
        {
          "method": "org.eclipse.swt.widgets.Display.runDeferredEvents",
          "source": "Display.java:2592"
        },
        {
          "method": "org.eclipse.swt.widgets.Display.readAndDispatch",
          "source": "Display.java:2270"
        },
        {
          "method": "org.eclipse.ui.internal.Workbench.runEventLoop",
          "source": "Workbench.java:1437"
        },
        {
          "method": "org.eclipse.ui.internal.Workbench.runUI",
          "source": "Workbench.java:1408"
        },
        {
          "method": "org.eclipse.ui.internal.Workbench.createAndRunWorkbench",
          "source": "Workbench.jav a:244"
        },
        {
          "method": "org.eclipse.ui.PlatformUI.createAndRunWorkbench",
          "source": "PlatformUI.java:140"
        },
        {
          "method": "org.eclipse.ui.internal.ide.IDEApplication.run",
          "source": "IDEApplication.java:90 "
        },
        {
          "method": "org.eclipse.core.internal.runtime.PlatformActivator$1.run",
          "source": "PlatformAct ivator.java:280"
        },
        {
          "method": "org.eclipse.core.runtime.adaptor.EclipseStarter.run",
          "source": "EclipseStarter.ja va:240"
        },
        {
          "method": "org.eclipse.core.runtime.adaptor.EclipseStarter.run",
          "source": "EclipseStarter.ja va:117"
        },
        {
          "method": "sun.reflect.NativeMethodAccessorImpl.invoke0",
          "source": "Native Method"
        },
        {
          "method": "sun.reflect.NativeMethodAccessorImpl.invoke",
          "source": "NativeMethodAccessorImpl. java:39"
        },
        {
          "method": "sun.reflect.DelegatingMethodAccessorImpl.invoke",
          "source": "DelegatingMethodAcces sorImpl.java:25"
        },
        {
          "method": "java.lang.reflect.Method.invoke",
          "source": "Method.java:324"
        },
        {
          "method": "org.eclipse.core.launcher.Main.basicRun",
          "source": "Main.java:267"
        },
        {
          "method": "org.eclipse.core.launcher.Main.run",
          "source": "Main.java:699"
        },
        {
          "method": "org.eclipse.core.launcher.Main.main",
          "source": "Main.java:683"
        }
      ],
      "number": 0,
      "commentIndex": 0,
      "bugId": "59204",
      "date": "2004-04-20T10:49:48+02:00",
      "product": "Platform",
      "component": "Compare",
      "severity": "normal"
    }
  ],
  "groupId": "59204",
  "bugId": "59204",
  "date": "2004-04-20T10:49:48+02:00",
  "product": "Platform",
  "component": "Compare",
  "severity": "normal"
}