{
  "comments": [
    "We are getting intermittent failures in the following test:\n\nDeadlockDetectionTest#testImplicitRules\n\nFailure - Timeout waiting for status to change from BLOCKED to WAIT_FOR_RUN \n                                            \njunit.framework.AssertionFailedError: Timeout waiting for status to change from \nBLOCKED to WAIT_FOR_RUN\n                                            at \norg.eclipse.core.tests.harness.TestBarrier.doWaitForStatus(TestBarrier.java:79)\n                                            at \norg.eclipse.core.tests.harness.TestBarrier.waitForStatus(TestBarrier.java:113)\n                                            at\n                                            \norg.eclipse.core.tests.runtime.jobs.DeadlockDetectionTest.testImplicitRules(Dead\nlockDetectionTest.java:779)\n                                            at \nsun.reflect.NativeMethodAccessorImpl.invoke0(Native Method)\n                                            at \nsun.reflect.NativeMethodAccessorImpl.invoke(NativeMethodAccessorImpl.java:39)\n                                            at \nsun.reflect.DelegatingMethodAccessorImpl.invoke(DelegatingMethodAccessorImpl.jav\na:25)\n                                            at \norg.eclipse.test.EclipseTestRunner.run(EclipseTestRunner.java:320)\n                                            at \norg.eclipse.test.EclipseTestRunner.run(EclipseTestRunner.java:199)\n                                            at \norg.eclipse.test.CoreTestApplication.runTests(CoreTestApplication.java:35)\n                                            at \norg.eclipse.test.CoreTestApplication.run(CoreTestApplication.java:31)\n                                            at \norg.eclipse.core.internal.runtime.PlatformActivator$1.run(PlatformActivator.java\n:280)\n                                            at \norg.eclipse.core.runtime.adaptor.EclipseStarter.run(EclipseStarter.java:240)\n                                            at \norg.eclipse.core.runtime.adaptor.EclipseStarter.run(EclipseStarter.java:117)\n                                            at \nsun.reflect.NativeMethodAccessorImpl.invoke0(Native Method)\n                                            at \nsun.reflect.NativeMethodAccessorImpl.invoke(NativeMethodAccessorImpl.java:39)\n                                            at \nsun.reflect.DelegatingMethodAccessorImpl.invoke(DelegatingMethodAccessorImpl.jav\na:25)\n                                            at \norg.eclipse.core.launcher.Main.basicRun(Main.java:267)\n                                            at \norg.eclipse.core.launcher.Main.run(Main.java:699)\n                                            at \norg.eclipse.core.launcher.Main.main(Main.java:683)",
    "This failed again today on WinXP.",
    "From I20040526:\n\njunit.framework.AssertionFailedError: Timeout waiting for job to end\nat\norg.eclipse.core.tests.runtime.jobs.DeadlockDetectionTest.testImplicitRules(DeadlockDetectionTest.java:801)\nat sun.reflect.NativeMethodAccessorImpl.invoke0(Native Method)\nat sun.reflect.NativeMethodAccessorImpl.invoke(NativeMethodAccessorImpl.java:39)\nat\nsun.reflect.DelegatingMethodAccessorImpl.invoke(DelegatingMethodAccessorImpl.java:25)\nat org.eclipse.test.EclipseTestRunner.run(EclipseTestRunner.java:322)\nat org.eclipse.test.EclipseTestRunner.run(EclipseTestRunner.java:198)\nat org.eclipse.test.CoreTestApplication.runTests(CoreTestApplication.java:35)\nat org.eclipse.test.CoreTestApplication.run(CoreTestApplication.java:31)\nat\norg.eclipse.core.internal.runtime.PlatformActivator$1.run(PlatformActivator.java:307)\nat org.eclipse.core.runtime.adaptor.EclipseStarter.run(EclipseStarter.java:256)\nat org.eclipse.core.runtime.adaptor.EclipseStarter.run(EclipseStarter.java:127)\nat sun.reflect.NativeMethodAccessorImpl.invoke0(Native Method)\nat sun.reflect.NativeMethodAccessorImpl.invoke(NativeMethodAccessorImpl.java:39)\nat\nsun.reflect.DelegatingMethodAccessorImpl.invoke(DelegatingMethodAccessorImpl.java:25)\nat org.eclipse.core.launcher.Main.basicRun(Main.java:185)\nat org.eclipse.core.launcher.Main.run(Main.java:638)\nat org.eclipse.core.launcher.Main.main(Main.java:622)",
    "In this last case, two jobs are failing to get past a barrier within ten\nseconds. The wait on the barrier is in 100 ms increments. Running this test on\nmy dual 3Ghz box, it takes from 200ms to 2.7 seconds to get past the barrier. It\nis likely that on a slow test machine it was jst exceeding the ten second limit.\nI have increased the limit to thirty seconds."
  ],
  "commentCreationDates": [
    "2004-04-20T23:56:48+02:00",
    "2004-04-29T16:03:55+02:00",
    "2004-05-26T16:38:08+02:00",
    "2004-05-27T23:38:05+02:00"
  ],
  "traces": [
    {
      "exceptionType": "junit.framework.AssertionFailedError",
      "message": "Timeout waiting for status to change from  BLOCKED to WAIT_FOR_RUN",
      "elements": [
        {
          "method": "org.eclipse.core.tests.harness.TestBarrier.doWaitForStatus",
          "source": "TestBarrier.java:79"
        },
        {
          "method": "org.eclipse.core.tests.harness.TestBarrier.waitForStatus",
          "source": "TestBarrier.java:113"
        },
        {
          "method": "org.eclipse.core.tests.runtime.jobs.DeadlockDetectionTest.testImplicitRules",
          "source": "Dead lockDetectionTest.java:779"
        },
        {
          "method": "sun.reflect.NativeMethodAccessorImpl.invoke0",
          "source": "Native Method"
        },
        {
          "method": "sun.reflect.NativeMethodAccessorImpl.invoke",
          "source": "NativeMethodAccessorImpl.java:39"
        },
        {
          "method": "sun.reflect.DelegatingMethodAccessorImpl.invoke",
          "source": "DelegatingMethodAccessorImpl.jav a:25"
        },
        {
          "method": "org.eclipse.test.EclipseTestRunner.run",
          "source": "EclipseTestRunner.java:320"
        },
        {
          "method": "org.eclipse.test.EclipseTestRunner.run",
          "source": "EclipseTestRunner.java:199"
        },
        {
          "method": "org.eclipse.test.CoreTestApplication.runTests",
          "source": "CoreTestApplication.java:35"
        },
        {
          "method": "org.eclipse.test.CoreTestApplication.run",
          "source": "CoreTestApplication.java:31"
        },
        {
          "method": "org.eclipse.core.internal.runtime.PlatformActivator$1.run",
          "source": "PlatformActivator.java :280"
        },
        {
          "method": "org.eclipse.core.runtime.adaptor.EclipseStarter.run",
          "source": "EclipseStarter.java:240"
        },
        {
          "method": "org.eclipse.core.runtime.adaptor.EclipseStarter.run",
          "source": "EclipseStarter.java:117"
        },
        {
          "method": "sun.reflect.NativeMethodAccessorImpl.invoke0",
          "source": "Native Method"
        },
        {
          "method": "sun.reflect.NativeMethodAccessorImpl.invoke",
          "source": "NativeMethodAccessorImpl.java:39"
        },
        {
          "method": "sun.reflect.DelegatingMethodAccessorImpl.invoke",
          "source": "DelegatingMethodAccessorImpl.jav a:25"
        },
        {
          "method": "org.eclipse.core.launcher.Main.basicRun",
          "source": "Main.java:267"
        },
        {
          "method": "org.eclipse.core.launcher.Main.run",
          "source": "Main.java:699"
        },
        {
          "method": "org.eclipse.core.launcher.Main.main",
          "source": "Main.java:683"
        }
      ],
      "number": 0,
      "commentIndex": 0,
      "bugId": "59357",
      "date": "2004-04-20T23:56:48+02:00",
      "product": "Platform",
      "component": "Resources",
      "severity": "normal"
    },
    {
      "exceptionType": "junit.framework.AssertionFailedError",
      "message": "Timeout waiting for job to end",
      "elements": [
        {
          "method": "org.eclipse.core.tests.runtime.jobs.DeadlockDetectionTest.testImplicitRules",
          "source": "DeadlockDetectionTest.java:801"
        },
        {
          "method": "sun.reflect.NativeMethodAccessorImpl.invoke0",
          "source": "Native Method"
        },
        {
          "method": "sun.reflect.NativeMethodAccessorImpl.invoke",
          "source": "NativeMethodAccessorImpl.java:39"
        },
        {
          "method": "sun.reflect.DelegatingMethodAccessorImpl.invoke",
          "source": "DelegatingMethodAccessorImpl.java:25"
        },
        {
          "method": "org.eclipse.test.EclipseTestRunner.run",
          "source": "EclipseTestRunner.java:322"
        },
        {
          "method": "org.eclipse.test.EclipseTestRunner.run",
          "source": "EclipseTestRunner.java:198"
        },
        {
          "method": "org.eclipse.test.CoreTestApplication.runTests",
          "source": "CoreTestApplication.java:35"
        },
        {
          "method": "org.eclipse.test.CoreTestApplication.run",
          "source": "CoreTestApplication.java:31"
        },
        {
          "method": "org.eclipse.core.internal.runtime.PlatformActivator$1.run",
          "source": "PlatformActivator.java:307"
        },
        {
          "method": "org.eclipse.core.runtime.adaptor.EclipseStarter.run",
          "source": "EclipseStarter.java:256"
        },
        {
          "method": "org.eclipse.core.runtime.adaptor.EclipseStarter.run",
          "source": "EclipseStarter.java:127"
        },
        {
          "method": "sun.reflect.NativeMethodAccessorImpl.invoke0",
          "source": "Native Method"
        },
        {
          "method": "sun.reflect.NativeMethodAccessorImpl.invoke",
          "source": "NativeMethodAccessorImpl.java:39"
        },
        {
          "method": "sun.reflect.DelegatingMethodAccessorImpl.invoke",
          "source": "DelegatingMethodAccessorImpl.java:25"
        },
        {
          "method": "org.eclipse.core.launcher.Main.basicRun",
          "source": "Main.java:185"
        },
        {
          "method": "org.eclipse.core.launcher.Main.run",
          "source": "Main.java:638"
        },
        {
          "method": "org.eclipse.core.launcher.Main.main",
          "source": "Main.java:622"
        }
      ],
      "number": 1,
      "commentIndex": 2,
      "bugId": "59357",
      "date": "2004-05-26T16:38:08+02:00",
      "product": "Platform",
      "component": "Resources",
      "severity": "normal"
    }
  ],
  "groupId": "59357",
  "bugId": "59357",
  "date": "2004-04-20T23:56:48+02:00",
  "product": "Platform",
  "component": "Resources",
  "severity": "normal"
}