{
  "comments": [
    "Build 20011114\n\nWhen switching over to use the latest build, I restarted my self-hosting \nworkspace, forced a refresh and triggered a full build, after what I noticed \nthe following stack dump in the console.\n\n: org.eclipse.core.resources.\njava.lang.NullPointerException\n        at org.eclipse.debug.internal.core.LaunchManager$LaunchManagerVisitor.vi\nsit(LaunchManager.java:578)\n        at org.eclipse.core.internal.events.ResourceDelta.accept(ResourceDelta.j\nava:52)\n        at org.eclipse.core.internal.events.ResourceDelta.accept(ResourceDelta.j\nava:56)\n        at org.eclipse.core.internal.events.ResourceDelta.accept(ResourceDelta.j\nava:56)\n        at org.eclipse.core.internal.events.ResourceDelta.accept(ResourceDelta.j\nava:56)\n        at org.eclipse.core.internal.events.ResourceDelta.accept(ResourceDelta.j\nava:56)\n        at org.eclipse.core.internal.events.ResourceDelta.accept(ResourceDelta.j\nava:43)\n        at org.eclipse.debug.internal.core.LaunchManager.resourceChanged(LaunchM\nanager.java:545)\n        at org.eclipse.core.internal.events.NotificationManager$1.run(Notificati\nonManager.java:125)\n        at org.eclipse.core.internal.runtime.InternalPlatform.run(InternalPlatfo\nrm.java:812)\n        at org.eclipse.core.runtime.Platform.run(Platform.java:395)\n        at org.eclipse.core.internal.events.NotificationManager.notify(Notificat\nionManager.java:140)\n        at org.eclipse.core.internal.events.NotificationManager.broadcastChanges\n(NotificationManager.java:43)\n        at org.eclipse.core.internal.events.NotificationManager.broadcastChanges\n(NotificationManager.java:64)\n        at org.eclipse.core.internal.resources.Workspace.broadcastChanges(Worksp\nace.java:110)\n        at org.eclipse.core.internal.resources.Workspace.endOperation(Workspace.\njava:698)\n        at org.eclipse.core.internal.resources.Workspace.run(Workspace.java:1191\n)\n        at com.oti.eclipsetools.internal.create.PluginImportWizard$1.run(PluginI\nmportWizard.java:74)\n        at org.eclipse.jface.operation.ModalContext$ModalContextThread.run(Modal\nContext.java:98)",
    "\n\n*** This bug has been marked as a duplicate of 5896 ***"
  ],
  "commentCreationDates": [
    "2001-11-15T11:44:49+01:00",
    "2001-11-15T13:56:31+01:00"
  ],
  "traces": [
    {
      "exceptionType": "java.lang.NullPointerException",
      "elements": [
        {
          "method": "org.eclipse.debug.internal.core.LaunchManager$LaunchManagerVisitor.visit",
          "source": "LaunchManager.java:578"
        },
        {
          "method": "org.eclipse.core.internal.events.ResourceDelta.accept",
          "source": "ResourceDelta.j ava:52"
        },
        {
          "method": "org.eclipse.core.internal.events.ResourceDelta.accept",
          "source": "ResourceDelta.j ava:56"
        },
        {
          "method": "org.eclipse.core.internal.events.ResourceDelta.accept",
          "source": "ResourceDelta.j ava:56"
        },
        {
          "method": "org.eclipse.core.internal.events.ResourceDelta.accept",
          "source": "ResourceDelta.j ava:56"
        },
        {
          "method": "org.eclipse.core.internal.events.ResourceDelta.accept",
          "source": "ResourceDelta.j ava:56"
        },
        {
          "method": "org.eclipse.core.internal.events.ResourceDelta.accept",
          "source": "ResourceDelta.j ava:43"
        },
        {
          "method": "org.eclipse.debug.internal.core.LaunchManager.resourceChanged",
          "source": "LaunchM anager.java:545"
        },
        {
          "method": "org.eclipse.core.internal.events.NotificationManager$1.run",
          "source": "Notificati onManager.java:125"
        },
        {
          "method": "org.eclipse.core.internal.runtime.InternalPlatform.run",
          "source": "InternalPlatfo rm.java:812"
        },
        {
          "method": "org.eclipse.core.runtime.Platform.run",
          "source": "Platform.java:395"
        },
        {
          "method": "org.eclipse.core.internal.events.NotificationManager.notify",
          "source": "Notificat ionManager.java:140"
        },
        {
          "method": "org.eclipse.core.internal.events.NotificationManager.broadcastChanges",
          "source": "NotificationManager.java:43"
        },
        {
          "method": "org.eclipse.core.internal.events.NotificationManager.broadcastChanges",
          "source": "NotificationManager.java:64"
        },
        {
          "method": "org.eclipse.core.internal.resources.Workspace.broadcastChanges",
          "source": "Worksp ace.java:110"
        },
        {
          "method": "org.eclipse.core.internal.resources.Workspace.endOperation",
          "source": "Workspace. java:698"
        },
        {
          "method": "org.eclipse.core.internal.resources.Workspace.run",
          "source": "Workspace.java:1191 "
        },
        {
          "method": "com.oti.eclipsetools.internal.create.PluginImportWizard$1.run",
          "source": "PluginI mportWizard.java:74"
        },
        {
          "method": "org.eclipse.jface.operation.ModalContext$ModalContextThread.run",
          "source": "Modal Context.java:98"
        }
      ],
      "number": 0,
      "commentIndex": 0,
      "bugId": "5946",
      "duplicateId": "5896",
      "date": "2001-11-15T11:44:49+01:00",
      "product": "Platform",
      "component": "Debug",
      "severity": "normal"
    }
  ],
  "groupId": "5896",
  "bugId": "5946",
  "duplicateId": "5896",
  "date": "2001-11-15T11:44:49+01:00",
  "product": "Platform",
  "component": "Debug",
  "severity": "normal"
}