{
  "comments": [
    "Build 20040422\n\nI was starting a workspace, when I realized I had forgotten some command line \narguments. When the first window came up, I exited through the file menu.\nGot the following exception:\n!ENTRY org.eclipse.core.runtime 4 2 Apr 23, 2004 11:17:39.510\n!MESSAGE Problems occurred when invoking code from plug-\nin: \"org.eclipse.core.runtime\".\n!STACK 0\njava.util.ConcurrentModificationException\n        at java.util.HashMap$HashIterator.nextEntry(HashMap.java:782)\n        at java.util.HashMap$KeyIterator.next(HashMap.java:818)\n        at org.eclipse.jdt.internal.core.JavaModelManager.saving\n(JavaModelManager.java:1410)\n        at org.eclipse.core.internal.resources.SaveManager.executeLifecycle\n(SaveManager.java:308)\n        at org.eclipse.core.internal.resources.SaveManager$1.run\n(SaveManager.java:129)\n        at org.eclipse.core.internal.runtime.InternalPlatform.run\n(InternalPlatform.java:609)\n        at org.eclipse.core.runtime.Platform.run(Platform.java:541)\n        at org.eclipse.core.internal.resources.SaveManager.broadcastLifecycle\n(SaveManager.java:141)\n        at org.eclipse.core.internal.resources.SaveManager.save\n(SaveManager.java:1323)\n        at org.eclipse.core.internal.resources.Workspace.save\n(Workspace.java:1674)\n        at org.eclipse.ui.internal.ide.IDEWorkbenchAdvisor$5.run\n(IDEWorkbenchAdvisor.java:440)\n        at org.eclipse.jface.operation.ModalContext.runInCurrentThread\n(ModalContext.java:302)\n        at org.eclipse.jface.operation.ModalContext.run(ModalContext.java:252)\n        at org.eclipse.jface.dialogs.ProgressMonitorDialog.run\n(ProgressMonitorDialog.java:429)\n        at \norg.eclipse.ui.internal.ide.IDEWorkbenchAdvisor.disconnectFromWorkspace\n(IDEWorkbenchAdvisor.java:447)\n        at org.eclipse.ui.internal.ide.IDEWorkbenchAdvisor.postShutdown\n(IDEWorkbenchAdvisor.java:212)\n        at org.eclipse.ui.internal.Workbench.shutdown(Workbench.java:1702)\n        at org.eclipse.ui.internal.Workbench.busyClose(Workbench.java:459)\n        at org.eclipse.ui.internal.Workbench.access$7(Workbench.java:390)\n        at org.eclipse.ui.internal.Workbench$12.run(Workbench.java:562)\n        at org.eclipse.swt.custom.BusyIndicator.showWhile(BusyIndicator.java:84)\n        at org.eclipse.ui.internal.Workbench.close(Workbench.java:560)\n        at org.eclipse.ui.internal.Workbench.close(Workbench.java:536)\n        at org.eclipse.ui.internal.QuitAction.run(QuitAction.java:55)\n        at org.eclipse.jface.action.Action.runWithEvent(Action.java:881)\n        at org.eclipse.jface.action.ActionContributionItem.handleWidgetSelection\n(ActionContributionItem.java:550)\n        at org.eclipse.jface.action.ActionContributionItem.access$2\n(ActionContributionItem.java:502)\n        at org.eclipse.jface.action.ActionContributionItem$5.handleEvent\n(ActionContributionItem.java:435)\n        at org.eclipse.swt.widgets.EventTable.sendEvent(EventTable.java:82)\n        at org.eclipse.swt.widgets.Widget.sendEvent(Widget.java:769)\n        at org.eclipse.swt.widgets.Display.runDeferredEvents(Display.java:2592)\n        at org.eclipse.swt.widgets.Display.readAndDispatch(Display.java:2270)\n        at org.eclipse.ui.internal.Workbench.runEventLoop(Workbench.java:1437)\n        at org.eclipse.ui.internal.Workbench.runUI(Workbench.java:1408)\n        at org.eclipse.ui.internal.Workbench.createAndRunWorkbench\n(Workbench.java:244)\n        at org.eclipse.ui.PlatformUI.createAndRunWorkbench(PlatformUI.java:140)\n        at org.eclipse.ui.internal.ide.IDEApplication.run\n(IDEApplication.java:90)\n        at org.eclipse.core.internal.runtime.PlatformActivator$1.run\n(PlatformActivator.java:280)\n        at org.eclipse.core.runtime.adaptor.EclipseStarter.run\n(EclipseStarter.java:240)\n        at org.eclipse.core.runtime.adaptor.EclipseStarter.run\n(EclipseStarter.java:117)\n        at sun.reflect.NativeMethodAccessorImpl.invoke0(Native Method)\n        at sun.reflect.NativeMethodAccessorImpl.invoke\n(NativeMethodAccessorImpl.java:39)\n        at sun.reflect.DelegatingMethodAccessorImpl.invoke\n(DelegatingMethodAccessorImpl.java:25)\n        at java.lang.reflect.Method.invoke(Method.java:324)\n        at org.eclipse.core.launcher.Main.basicRun(Main.java:267)\n        at org.eclipse.core.launcher.Main.run(Main.java:699)\n        at org.eclipse.core.launcher.Main.main(Main.java:683)",
    "I also get such exception with automatic snapshots (outside shutdown sequence).\n\n!ENTRY org.eclipse.core.runtime 4 2 Apr 23, 2004 12:12:15.583\n!MESSAGE Problems occurred when invoking code from plug-\nin: \"org.eclipse.core.runtime\".\n!STACK 0\njava.util.ConcurrentModificationException\n        at java.util.HashMap$HashIterator.nextEntry(HashMap.java:762)\n        at java.util.HashMap$KeyIterator.next(HashMap.java:798)\n        at org.eclipse.jdt.internal.core.JavaModelManager.saving\n(JavaModelManager.java:1410)\n        at org.eclipse.core.internal.resources.SaveManager.executeLifecycle\n(SaveManager.java:308)\n        at org.eclipse.core.internal.resources.SaveManager$1.run\n(SaveManager.java:129)\n        at org.eclipse.core.internal.runtime.InternalPlatform.run\n(InternalPlatform.java:609)\n        at org.eclipse.core.runtime.Platform.run(Platform.java:541)\n        at org.eclipse.core.internal.resources.SaveManager.broadcastLifecycle\n(SaveManager.java:141)\n        at org.eclipse.core.internal.resources.SaveManager.save\n(SaveManager.java:1323)\n        at org.eclipse.core.internal.resources.DelayedSnapshotJob.run\n(DelayedSnapshotJob.java:42)\n        at org.eclipse.core.internal.jobs.Worker.run(Worker.java:66)\n!ENTRY org.eclipse.core.resources 2 2 Apr 23, 2004 12:12:16.583\n!MESSAGE Save operation warnings.\n!SUBENTRY 1 org.eclipse.core.resources 2 566 Apr 23, 2004 12:12:16.583\n!MESSAGE Problems occurred during save.\n!STACK 0\njava.util.ConcurrentModificationException\n        at java.util.HashMap$HashIterator.nextEntry(HashMap.java:762)\n        at java.util.HashMap$KeyIterator.next(HashMap.java:798)\n        at org.eclipse.jdt.internal.core.JavaModelManager.saving\n(JavaModelManager.java:1410)\n        at org.eclipse.core.internal.resources.SaveManager.executeLifecycle\n(SaveManager.java:308)\n        at org.eclipse.core.internal.resources.SaveManager$1.run\n(SaveManager.java:129)\n        at org.eclipse.core.internal.runtime.InternalPlatform.run\n(InternalPlatform.java:609)\n        at org.eclipse.core.runtime.Platform.run(Platform.java:541)\n        at org.eclipse.core.internal.resources.SaveManager.broadcastLifecycle\n(SaveManager.java:141)\n        at org.eclipse.core.internal.resources.SaveManager.save\n(SaveManager.java:1323)\n        at org.eclipse.core.internal.resources.DelayedSnapshotJob.run\n(DelayedSnapshotJob.java:42)\n        at org.eclipse.core.internal.jobs.Worker.run(Worker.java:66)\n",
    "Exception is in JavaModelManager.",
    "\n\n*** This bug has been marked as a duplicate of 59638 ***"
  ],
  "commentCreationDates": [
    "2004-04-23T11:28:35+02:00",
    "2004-04-23T12:22:25+02:00",
    "2004-04-23T18:50:41+02:00",
    "2004-04-26T13:15:12+02:00"
  ],
  "traces": [
    {
      "exceptionType": "java.util.ConcurrentModificationException",
      "elements": [
        {
          "method": "java.util.HashMap$HashIterator.nextEntry",
          "source": "HashMap.java:782"
        },
        {
          "method": "java.util.HashMap$KeyIterator.next",
          "source": "HashMap.java:818"
        },
        {
          "method": "org.eclipse.jdt.internal.core.JavaModelManager.saving",
          "source": "JavaModelManager.java:1410"
        },
        {
          "method": "org.eclipse.core.internal.resources.SaveManager.executeLifecycle",
          "source": "SaveManager.java:308"
        },
        {
          "method": "org.eclipse.core.internal.resources.SaveManager$1.run",
          "source": "SaveManager.java:129"
        },
        {
          "method": "org.eclipse.core.internal.runtime.InternalPlatform.run",
          "source": "InternalPlatform.java:609"
        },
        {
          "method": "org.eclipse.core.runtime.Platform.run",
          "source": "Platform.java:541"
        },
        {
          "method": "org.eclipse.core.internal.resources.SaveManager.broadcastLifecycle",
          "source": "SaveManager.java:141"
        },
        {
          "method": "org.eclipse.core.internal.resources.SaveManager.save",
          "source": "SaveManager.java:1323"
        },
        {
          "method": "org.eclipse.core.internal.resources.Workspace.save",
          "source": "Workspace.java:1674"
        },
        {
          "method": "org.eclipse.ui.internal.ide.IDEWorkbenchAdvisor$5.run",
          "source": "IDEWorkbenchAdvisor.java:440"
        },
        {
          "method": "org.eclipse.jface.operation.ModalContext.runInCurrentThread",
          "source": "ModalContext.java:302"
        },
        {
          "method": "org.eclipse.jface.operation.ModalContext.run",
          "source": "ModalContext.java:252"
        },
        {
          "method": "org.eclipse.jface.dialogs.ProgressMonitorDialog.run",
          "source": "ProgressMonitorDialog.java:429"
        },
        {
          "method": "org.eclipse.ui.internal.ide.IDEWorkbenchAdvisor.disconnectFromWorkspace",
          "source": "IDEWorkbenchAdvisor.java:447"
        },
        {
          "method": "org.eclipse.ui.internal.ide.IDEWorkbenchAdvisor.postShutdown",
          "source": "IDEWorkbenchAdvisor.java:212"
        },
        {
          "method": "org.eclipse.ui.internal.Workbench.shutdown",
          "source": "Workbench.java:1702"
        },
        {
          "method": "org.eclipse.ui.internal.Workbench.busyClose",
          "source": "Workbench.java:459"
        },
        {
          "method": "org.eclipse.ui.internal.Workbench.access$7",
          "source": "Workbench.java:390"
        },
        {
          "method": "org.eclipse.ui.internal.Workbench$12.run",
          "source": "Workbench.java:562"
        },
        {
          "method": "org.eclipse.swt.custom.BusyIndicator.showWhile",
          "source": "BusyIndicator.java:84"
        },
        {
          "method": "org.eclipse.ui.internal.Workbench.close",
          "source": "Workbench.java:560"
        },
        {
          "method": "org.eclipse.ui.internal.Workbench.close",
          "source": "Workbench.java:536"
        },
        {
          "method": "org.eclipse.ui.internal.QuitAction.run",
          "source": "QuitAction.java:55"
        },
        {
          "method": "org.eclipse.jface.action.Action.runWithEvent",
          "source": "Action.java:881"
        },
        {
          "method": "org.eclipse.jface.action.ActionContributionItem.handleWidgetSelection",
          "source": "ActionContributionItem.java:550"
        },
        {
          "method": "org.eclipse.jface.action.ActionContributionItem.access$2",
          "source": "ActionContributionItem.java:502"
        },
        {
          "method": "org.eclipse.jface.action.ActionContributionItem$5.handleEvent",
          "source": "ActionContributionItem.java:435"
        },
        {
          "method": "org.eclipse.swt.widgets.EventTable.sendEvent",
          "source": "EventTable.java:82"
        },
        {
          "method": "org.eclipse.swt.widgets.Widget.sendEvent",
          "source": "Widget.java:769"
        },
        {
          "method": "org.eclipse.swt.widgets.Display.runDeferredEvents",
          "source": "Display.java:2592"
        },
        {
          "method": "org.eclipse.swt.widgets.Display.readAndDispatch",
          "source": "Display.java:2270"
        },
        {
          "method": "org.eclipse.ui.internal.Workbench.runEventLoop",
          "source": "Workbench.java:1437"
        },
        {
          "method": "org.eclipse.ui.internal.Workbench.runUI",
          "source": "Workbench.java:1408"
        },
        {
          "method": "org.eclipse.ui.internal.Workbench.createAndRunWorkbench",
          "source": "Workbench.java:244"
        },
        {
          "method": "org.eclipse.ui.PlatformUI.createAndRunWorkbench",
          "source": "PlatformUI.java:140"
        },
        {
          "method": "org.eclipse.ui.internal.ide.IDEApplication.run",
          "source": "IDEApplication.java:90"
        },
        {
          "method": "org.eclipse.core.internal.runtime.PlatformActivator$1.run",
          "source": "PlatformActivator.java:280"
        },
        {
          "method": "org.eclipse.core.runtime.adaptor.EclipseStarter.run",
          "source": "EclipseStarter.java:240"
        },
        {
          "method": "org.eclipse.core.runtime.adaptor.EclipseStarter.run",
          "source": "EclipseStarter.java:117"
        },
        {
          "method": "sun.reflect.NativeMethodAccessorImpl.invoke0",
          "source": "Native Method"
        },
        {
          "method": "sun.reflect.NativeMethodAccessorImpl.invoke",
          "source": "NativeMethodAccessorImpl.java:39"
        },
        {
          "method": "sun.reflect.DelegatingMethodAccessorImpl.invoke",
          "source": "DelegatingMethodAccessorImpl.java:25"
        },
        {
          "method": "java.lang.reflect.Method.invoke",
          "source": "Method.java:324"
        },
        {
          "method": "org.eclipse.core.launcher.Main.basicRun",
          "source": "Main.java:267"
        },
        {
          "method": "org.eclipse.core.launcher.Main.run",
          "source": "Main.java:699"
        },
        {
          "method": "org.eclipse.core.launcher.Main.main",
          "source": "Main.java:683"
        }
      ],
      "number": 0,
      "commentIndex": 0,
      "bugId": "59757",
      "duplicateId": "59638",
      "date": "2004-04-23T11:28:35+02:00",
      "product": "JDT",
      "component": "Core",
      "severity": "normal"
    },
    {
      "exceptionType": "java.util.ConcurrentModificationException",
      "elements": [
        {
          "method": "java.util.HashMap$HashIterator.nextEntry",
          "source": "HashMap.java:762"
        },
        {
          "method": "java.util.HashMap$KeyIterator.next",
          "source": "HashMap.java:798"
        },
        {
          "method": "org.eclipse.jdt.internal.core.JavaModelManager.saving",
          "source": "JavaModelManager.java:1410"
        },
        {
          "method": "org.eclipse.core.internal.resources.SaveManager.executeLifecycle",
          "source": "SaveManager.java:308"
        },
        {
          "method": "org.eclipse.core.internal.resources.SaveManager$1.run",
          "source": "SaveManager.java:129"
        },
        {
          "method": "org.eclipse.core.internal.runtime.InternalPlatform.run",
          "source": "InternalPlatform.java:609"
        },
        {
          "method": "org.eclipse.core.runtime.Platform.run",
          "source": "Platform.java:541"
        },
        {
          "method": "org.eclipse.core.internal.resources.SaveManager.broadcastLifecycle",
          "source": "SaveManager.java:141"
        },
        {
          "method": "org.eclipse.core.internal.resources.SaveManager.save",
          "source": "SaveManager.java:1323"
        },
        {
          "method": "org.eclipse.core.internal.resources.DelayedSnapshotJob.run",
          "source": "DelayedSnapshotJob.java:42"
        },
        {
          "method": "org.eclipse.core.internal.jobs.Worker.run",
          "source": "Worker.java:66"
        }
      ],
      "number": 1,
      "commentIndex": 1,
      "bugId": "59757",
      "duplicateId": "59638",
      "date": "2004-04-23T12:22:25+02:00",
      "product": "JDT",
      "component": "Core",
      "severity": "normal"
    },
    {
      "exceptionType": "java.util.ConcurrentModificationException",
      "elements": [
        {
          "method": "java.util.HashMap$HashIterator.nextEntry",
          "source": "HashMap.java:762"
        },
        {
          "method": "java.util.HashMap$KeyIterator.next",
          "source": "HashMap.java:798"
        },
        {
          "method": "org.eclipse.jdt.internal.core.JavaModelManager.saving",
          "source": "JavaModelManager.java:1410"
        },
        {
          "method": "org.eclipse.core.internal.resources.SaveManager.executeLifecycle",
          "source": "SaveManager.java:308"
        },
        {
          "method": "org.eclipse.core.internal.resources.SaveManager$1.run",
          "source": "SaveManager.java:129"
        },
        {
          "method": "org.eclipse.core.internal.runtime.InternalPlatform.run",
          "source": "InternalPlatform.java:609"
        },
        {
          "method": "org.eclipse.core.runtime.Platform.run",
          "source": "Platform.java:541"
        },
        {
          "method": "org.eclipse.core.internal.resources.SaveManager.broadcastLifecycle",
          "source": "SaveManager.java:141"
        },
        {
          "method": "org.eclipse.core.internal.resources.SaveManager.save",
          "source": "SaveManager.java:1323"
        },
        {
          "method": "org.eclipse.core.internal.resources.DelayedSnapshotJob.run",
          "source": "DelayedSnapshotJob.java:42"
        },
        {
          "method": "org.eclipse.core.internal.jobs.Worker.run",
          "source": "Worker.java:66"
        }
      ],
      "number": 2,
      "commentIndex": 1,
      "bugId": "59757",
      "duplicateId": "59638",
      "date": "2004-04-23T12:22:25+02:00",
      "product": "JDT",
      "component": "Core",
      "severity": "normal"
    }
  ],
  "groupId": "59638",
  "bugId": "59757",
  "duplicateId": "59638",
  "date": "2004-04-23T11:28:35+02:00",
  "product": "JDT",
  "component": "Core",
  "severity": "normal"
}