{
  "comments": [
    "In Eclipse 3.0M8 with FTP webdav plugin,\nwhen you open site explorer, click on the new site button and create a new FTP\nsite, there will be an error message popup which ask me to look at the log file.\nActually, the \"target site\" label is missing in 3.0M8 for team synchronization.\n\nBelow is the log message:\nBootLoader constants: OS\u003dwin32, ARCH\u003dx86, WS\u003dwin32, NL\u003den_GB\n!ENTRY org.eclipse.core.runtime 4 2 Apr 23, 2004 17:43:31.848\n!MESSAGE Problems occurred when invoking code from plug-in:\n\"org.eclipse.core.runtime\".\n!STACK 0\njava.lang.NoClassDefFoundError:\norg/eclipse/team/internal/ui/target/subscriber/SiteCreationPage\n        at java.lang.ClassLoader.defineClass0(Native Method)\n        at java.lang.ClassLoader.defineClass(ClassLoader.java:537)\n        at\norg.eclipse.osgi.framework.internal.defaultadaptor.DefaultClassLoader.defineClass(DefaultClassLoader.java:309)\n        at\norg.eclipse.core.runtime.adaptor.EclipseClassLoader.defineClass(EclipseClassLoader.java:175)\n        at\norg.eclipse.osgi.framework.internal.defaultadaptor.DefaultClassLoader.findClassImpl(DefaultClassLoader.java:298)\n        at\norg.eclipse.osgi.framework.internal.defaultadaptor.DefaultClassLoader.findClass(DefaultClassLoader.java:187)\n        at\norg.eclipse.osgi.framework.adaptor.core.AbstractClassLoader.findLocalClass(AbstractClassLoader.java:243)\n        at\norg.eclipse.core.runtime.adaptor.EclipseClassLoader.findLocalClass(EclipseClassLoader.java:104)\n        at\norg.eclipse.osgi.framework.internal.core.BundleLoader.findLocalClass(BundleLoader.java:315)\n        at\norg.eclipse.osgi.framework.internal.core.BundleLoader.findClass(BundleLoader.java:346)\n        at\norg.eclipse.osgi.framework.adaptor.core.AbstractClassLoader.loadClass(AbstractClassLoader.java:116)\n        at java.lang.ClassLoader.loadClass(ClassLoader.java:235)\n        at java.lang.ClassLoader.loadClassInternal(ClassLoader.java:302)\n        at\norg.eclipse.team.internal.ftp.ui.FTPConfigurationWizard.addPages(FTPConfigurationWizard.java:63)\n        at\norg.eclipse.team.internal.ui.wizards.ConfigureProjectWizardMainPage$1.selectionChanged(ConfigureProjectWizardMainPage.java:132)\n        at org.eclipse.jface.viewers.Viewer$2.run(Viewer.java:159)\n        at\norg.eclipse.core.internal.runtime.InternalPlatform.run(InternalPlatform.java:610)\n        at org.eclipse.core.runtime.Platform.run(Platform.java:521)\n        at org.eclipse.jface.viewers.Viewer.fireSelectionChanged(Viewer.java:157)\n        at\norg.eclipse.jface.viewers.StructuredViewer.updateSelection(StructuredViewer.java:1310)\n        at\norg.eclipse.jface.viewers.StructuredViewer.handleSelect(StructuredViewer.java:666)\n        at\norg.eclipse.jface.viewers.StructuredViewer$4.widgetSelected(StructuredViewer.java:690)\n        at\norg.eclipse.jface.util.OpenStrategy.fireSelectionEvent(OpenStrategy.java:178)\n        at org.eclipse.jface.util.OpenStrategy.access$3(OpenStrategy.java:173)\n        at org.eclipse.jface.util.OpenStrategy$1.handleEvent(OpenStrategy.java:309)\n        at org.eclipse.swt.widgets.EventTable.sendEvent(EventTable.java:82)\n        at org.eclipse.swt.widgets.Widget.sendEvent(Widget.java:769)\n        at org.eclipse.swt.widgets.Display.runDeferredEvents(Display.java:2578)\n        at org.eclipse.swt.widgets.Display.readAndDispatch(Display.java:2256)\n        at org.eclipse.jface.window.Window.runEventLoop(Window.java:670)\n        at org.eclipse.jface.window.Window.open(Window.java:650)\n        at\norg.eclipse.team.internal.ui.target.SiteExplorerView$8.run(SiteExplorerView.java:360)\n        at org.eclipse.jface.action.Action.runWithEvent(Action.java:881)\n        at\norg.eclipse.jface.action.ActionContributionItem.handleWidgetSelection(ActionContributionItem.java:550)\n        at\norg.eclipse.jface.action.ActionContributionItem.access$2(ActionContributionItem.java:502)\n        at\norg.eclipse.jface.action.ActionContributionItem$6.handleEvent(ActionContributionItem.java:474)\n        at org.eclipse.swt.widgets.EventTable.sendEvent(EventTable.java:82)\n        at org.eclipse.swt.widgets.Widget.sendEvent(Widget.java:769)\n        at org.eclipse.swt.widgets.Display.runDeferredEvents(Display.java:2578)\n        at org.eclipse.swt.widgets.Display.readAndDispatch(Display.java:2256)\n        at org.eclipse.ui.internal.Workbench.runEventLoop(Workbench.java:1562)\n        at org.eclipse.ui.internal.Workbench.runUI(Workbench.java:1536)\n        at\norg.eclipse.ui.internal.Workbench.createAndRunWorkbench(Workbench.java:257)\n        at org.eclipse.ui.PlatformUI.createAndRunWorkbench(PlatformUI.java:139)\n        at org.eclipse.ui.internal.ide.IDEApplication.run(IDEApplication.java:90)\n        at\norg.eclipse.core.internal.runtime.PlatformActivator$1.run(PlatformActivator.java:277)\n        at\norg.eclipse.core.runtime.adaptor.EclipseStarter.run(EclipseStarter.java:239)\n        at\norg.eclipse.core.runtime.adaptor.EclipseStarter.run(EclipseStarter.java:117)\n        at sun.reflect.NativeMethodAccessorImpl.invoke0(Native Method)\n        at\nsun.reflect.NativeMethodAccessorImpl.invoke(NativeMethodAccessorImpl.java:39)\n        at\nsun.reflect.DelegatingMethodAccessorImpl.invoke(DelegatingMethodAccessorImpl.java:25)\n        at java.lang.reflect.Method.invoke(Method.java:324)\n        at org.eclipse.core.launcher.Main.basicRun(Main.java:267)\n        at org.eclipse.core.launcher.Main.run(Main.java:692)\n        at org.eclipse.core.launcher.Main.main(Main.java:676)",
    "This was due to a classloading bug that has since been fixed"
  ],
  "commentCreationDates": [
    "2004-04-23T12:10:33+02:00",
    "2004-04-23T14:20:57+02:00"
  ],
  "traces": [
    {
      "exceptionType": "java.lang.NoClassDefFoundError",
      "message": "org/eclipse/team/internal/ui/target/subscriber/SiteCreationPage",
      "elements": [
        {
          "method": "java.lang.ClassLoader.defineClass0",
          "source": "Native Method"
        },
        {
          "method": "java.lang.ClassLoader.defineClass",
          "source": "ClassLoader.java:537"
        },
        {
          "method": "org.eclipse.osgi.framework.internal.defaultadaptor.DefaultClassLoader.defineClass",
          "source": "DefaultClassLoader.java:309"
        },
        {
          "method": "org.eclipse.core.runtime.adaptor.EclipseClassLoader.defineClass",
          "source": "EclipseClassLoader.java:175"
        },
        {
          "method": "org.eclipse.osgi.framework.internal.defaultadaptor.DefaultClassLoader.findClassImpl",
          "source": "DefaultClassLoader.java:298"
        },
        {
          "method": "org.eclipse.osgi.framework.internal.defaultadaptor.DefaultClassLoader.findClass",
          "source": "DefaultClassLoader.java:187"
        },
        {
          "method": "org.eclipse.osgi.framework.adaptor.core.AbstractClassLoader.findLocalClass",
          "source": "AbstractClassLoader.java:243"
        },
        {
          "method": "org.eclipse.core.runtime.adaptor.EclipseClassLoader.findLocalClass",
          "source": "EclipseClassLoader.java:104"
        },
        {
          "method": "org.eclipse.osgi.framework.internal.core.BundleLoader.findLocalClass",
          "source": "BundleLoader.java:315"
        },
        {
          "method": "org.eclipse.osgi.framework.internal.core.BundleLoader.findClass",
          "source": "BundleLoader.java:346"
        },
        {
          "method": "org.eclipse.osgi.framework.adaptor.core.AbstractClassLoader.loadClass",
          "source": "AbstractClassLoader.java:116"
        },
        {
          "method": "java.lang.ClassLoader.loadClass",
          "source": "ClassLoader.java:235"
        },
        {
          "method": "java.lang.ClassLoader.loadClassInternal",
          "source": "ClassLoader.java:302"
        },
        {
          "method": "org.eclipse.team.internal.ftp.ui.FTPConfigurationWizard.addPages",
          "source": "FTPConfigurationWizard.java:63"
        },
        {
          "method": "org.eclipse.team.internal.ui.wizards.ConfigureProjectWizardMainPage$1.selectionChanged",
          "source": "ConfigureProjectWizardMainPage.java:132"
        },
        {
          "method": "org.eclipse.jface.viewers.Viewer$2.run",
          "source": "Viewer.java:159"
        },
        {
          "method": "org.eclipse.core.internal.runtime.InternalPlatform.run",
          "source": "InternalPlatform.java:610"
        },
        {
          "method": "org.eclipse.core.runtime.Platform.run",
          "source": "Platform.java:521"
        },
        {
          "method": "org.eclipse.jface.viewers.Viewer.fireSelectionChanged",
          "source": "Viewer.java:157"
        },
        {
          "method": "org.eclipse.jface.viewers.StructuredViewer.updateSelection",
          "source": "StructuredViewer.java:1310"
        },
        {
          "method": "org.eclipse.jface.viewers.StructuredViewer.handleSelect",
          "source": "StructuredViewer.java:666"
        },
        {
          "method": "org.eclipse.jface.viewers.StructuredViewer$4.widgetSelected",
          "source": "StructuredViewer.java:690"
        },
        {
          "method": "org.eclipse.jface.util.OpenStrategy.fireSelectionEvent",
          "source": "OpenStrategy.java:178"
        },
        {
          "method": "org.eclipse.jface.util.OpenStrategy.access$3",
          "source": "OpenStrategy.java:173"
        },
        {
          "method": "org.eclipse.jface.util.OpenStrategy$1.handleEvent",
          "source": "OpenStrategy.java:309"
        },
        {
          "method": "org.eclipse.swt.widgets.EventTable.sendEvent",
          "source": "EventTable.java:82"
        },
        {
          "method": "org.eclipse.swt.widgets.Widget.sendEvent",
          "source": "Widget.java:769"
        },
        {
          "method": "org.eclipse.swt.widgets.Display.runDeferredEvents",
          "source": "Display.java:2578"
        },
        {
          "method": "org.eclipse.swt.widgets.Display.readAndDispatch",
          "source": "Display.java:2256"
        },
        {
          "method": "org.eclipse.jface.window.Window.runEventLoop",
          "source": "Window.java:670"
        },
        {
          "method": "org.eclipse.jface.window.Window.open",
          "source": "Window.java:650"
        },
        {
          "method": "org.eclipse.team.internal.ui.target.SiteExplorerView$8.run",
          "source": "SiteExplorerView.java:360"
        },
        {
          "method": "org.eclipse.jface.action.Action.runWithEvent",
          "source": "Action.java:881"
        },
        {
          "method": "org.eclipse.jface.action.ActionContributionItem.handleWidgetSelection",
          "source": "ActionContributionItem.java:550"
        },
        {
          "method": "org.eclipse.jface.action.ActionContributionItem.access$2",
          "source": "ActionContributionItem.java:502"
        },
        {
          "method": "org.eclipse.jface.action.ActionContributionItem$6.handleEvent",
          "source": "ActionContributionItem.java:474"
        },
        {
          "method": "org.eclipse.swt.widgets.EventTable.sendEvent",
          "source": "EventTable.java:82"
        },
        {
          "method": "org.eclipse.swt.widgets.Widget.sendEvent",
          "source": "Widget.java:769"
        },
        {
          "method": "org.eclipse.swt.widgets.Display.runDeferredEvents",
          "source": "Display.java:2578"
        },
        {
          "method": "org.eclipse.swt.widgets.Display.readAndDispatch",
          "source": "Display.java:2256"
        },
        {
          "method": "org.eclipse.ui.internal.Workbench.runEventLoop",
          "source": "Workbench.java:1562"
        },
        {
          "method": "org.eclipse.ui.internal.Workbench.runUI",
          "source": "Workbench.java:1536"
        },
        {
          "method": "org.eclipse.ui.internal.Workbench.createAndRunWorkbench",
          "source": "Workbench.java:257"
        },
        {
          "method": "org.eclipse.ui.PlatformUI.createAndRunWorkbench",
          "source": "PlatformUI.java:139"
        },
        {
          "method": "org.eclipse.ui.internal.ide.IDEApplication.run",
          "source": "IDEApplication.java:90"
        },
        {
          "method": "org.eclipse.core.internal.runtime.PlatformActivator$1.run",
          "source": "PlatformActivator.java:277"
        },
        {
          "method": "org.eclipse.core.runtime.adaptor.EclipseStarter.run",
          "source": "EclipseStarter.java:239"
        },
        {
          "method": "org.eclipse.core.runtime.adaptor.EclipseStarter.run",
          "source": "EclipseStarter.java:117"
        },
        {
          "method": "sun.reflect.NativeMethodAccessorImpl.invoke0",
          "source": "Native Method"
        },
        {
          "method": "sun.reflect.NativeMethodAccessorImpl.invoke",
          "source": "NativeMethodAccessorImpl.java:39"
        },
        {
          "method": "sun.reflect.DelegatingMethodAccessorImpl.invoke",
          "source": "DelegatingMethodAccessorImpl.java:25"
        },
        {
          "method": "java.lang.reflect.Method.invoke",
          "source": "Method.java:324"
        },
        {
          "method": "org.eclipse.core.launcher.Main.basicRun",
          "source": "Main.java:267"
        },
        {
          "method": "org.eclipse.core.launcher.Main.run",
          "source": "Main.java:692"
        },
        {
          "method": "org.eclipse.core.launcher.Main.main",
          "source": "Main.java:676"
        }
      ],
      "number": 0,
      "commentIndex": 0,
      "bugId": "59763",
      "date": "2004-04-23T12:10:33+02:00",
      "product": "Platform",
      "component": "Team",
      "severity": "major"
    }
  ],
  "groupId": "59763",
  "bugId": "59763",
  "date": "2004-04-23T12:10:33+02:00",
  "product": "Platform",
  "component": "Team",
  "severity": "major"
}