{
  "comments": [
    "java.lang.IllegalStateException\n        at org.eclipse.jface.text.projection.ProjectionMapping.findFragmentIndex\n(ProjectionMapping.java:166)\n        at org.eclipse.jface.text.projection.ProjectionMapping.findFragments(Pro\njectionMapping.java:198)\n        at org.eclipse.jface.text.projection.ProjectionMapping.toImageRegion(Pro\njectionMapping.java:226)\n        at org.eclipse.jface.text.projection.ProjectionMapping.toExactImageRegio\nn(ProjectionMapping.java:386)\n        at org.eclipse.jface.text.projection.ProjectionDocument.normalize(Projec\ntionDocument.java:518)\n        at org.eclipse.jface.text.projection.ProjectionDocument.masterDocumentAb\noutToBeChanged(ProjectionDocument.java:640)\n        at org.eclipse.jface.text.projection.ProjectionDocumentManager.fireDocum\nentEvent(ProjectionDocumentManager.java:119)\n        at org.eclipse.jface.text.projection.ProjectionDocumentManager.documentA\nboutToBeChanged(ProjectionDocumentManager.java:136)\n        at org.eclipse.jface.text.AbstractDocument.fireDocumentAboutToBeChanged(\nAbstractDocument.java:577)\n        at org.eclipse.jface.text.AbstractDocument.set(AbstractDocument.java:998\n)\n        at org.eclipse.jdt.internal.ui.javaeditor.PartiallySynchronizedDocument.\nset(PartiallySynchronizedDocument.java:101)\n        at org.eclipse.core.internal.filebuffers.ResourceTextFileBuffer.revert(R\nesourceTextFileBuffer.java:160)\n        at org.eclipse.ui.editors.text.TextFileDocumentProvider$1.execute(TextFi\nleDocumentProvider.java:581)\n        at org.eclipse.ui.editors.text.TextFileDocumentProvider$DocumentProvider\nOperation.run(TextFileDocumentProvider.java:96)\n        at org.eclipse.ui.actions.WorkspaceModifyDelegatingOperation.execute(Wor\nkspaceModifyDelegatingOperation.java:67)\n        at org.eclipse.ui.actions.WorkspaceModifyOperation$1.run(WorkspaceModify\nOperation.java:91)\n        at org.eclipse.core.internal.resources.Workspace.run(Workspace.java:1640\n)\n        at org.eclipse.ui.actions.WorkspaceModifyOperation.run(WorkspaceModifyOp\neration.java:105)\n        at org.eclipse.ui.internal.editors.text.WorkspaceOperationRunner.run(Wor\nkspaceOperationRunner.java:73)\n        at org.eclipse.ui.internal.editors.text.WorkspaceOperationRunner.run(Wor\nkspaceOperationRunner.java:63)\n        at org.eclipse.ui.editors.text.TextFileDocumentProvider.executeOperation\n(TextFileDocumentProvider.java:395)\n        at org.eclipse.ui.editors.text.TextFileDocumentProvider.resetDocument(Te\nxtFileDocumentProvider.java:599)\n        at org.eclipse.ui.texteditor.AbstractTextEditor.performRevert(AbstractTe\nxtEditor.java:3468)\n        at org.eclipse.ui.texteditor.AbstractTextEditor.doRevertToSaved(Abstract\nTextEditor.java:3451)\n        at org.eclipse.ui.texteditor.StatusTextEditor.doRevertToSaved(StatusText\nEditor.java:183)\n        at org.eclipse.ui.texteditor.RevertToSavedAction.run(RevertToSavedAction\n.java:47)\n        at org.eclipse.jface.action.Action.runWithEvent(Action.java:881)\n        at org.eclipse.ui.actions.RetargetAction.runWithEvent(RetargetAction.jav\na:212)\n        at org.eclipse.jface.action.ActionContributionItem.handleWidgetSelection\n(ActionContributionItem.java:550)\n        at org.eclipse.jface.action.ActionContributionItem.access$2(ActionContri\nbutionItem.java:502)\n        at org.eclipse.jface.action.ActionContributionItem$5.handleEvent(ActionC\nontributionItem.java:435)\n        at org.eclipse.swt.widgets.EventTable.sendEvent(EventTable.java:82)\n        at org.eclipse.swt.widgets.Widget.sendEvent(Widget.java:769)\n        at org.eclipse.swt.widgets.Display.runDeferredEvents(Display.java:2592)\n        at org.eclipse.swt.widgets.Display.readAndDispatch(Display.java:2270)\n        at org.eclipse.ui.internal.Workbench.runEventLoop(Workbench.java:1437)\n        at org.eclipse.ui.internal.Workbench.runUI(Workbench.java:1408)\n        at org.eclipse.ui.internal.Workbench.createAndRunWorkbench(Workbench.jav\na:244)\n        at org.eclipse.ui.PlatformUI.createAndRunWorkbench(PlatformUI.java:140)\n        at org.eclipse.ui.internal.ide.IDEApplication.run(IDEApplication.java:90\n)\n        at org.eclipse.core.internal.runtime.PlatformActivator$1.run(PlatformAct\nivator.java:280)\n        at org.eclipse.core.runtime.adaptor.EclipseStarter.run(EclipseStarter.ja\nva:240)\n        at org.eclipse.core.runtime.adaptor.EclipseStarter.run(EclipseStarter.ja\nva:117)\n        at sun.reflect.NativeMethodAccessorImpl.invoke0(Native Method)\n        at sun.reflect.NativeMethodAccessorImpl.invoke(NativeMethodAccessorImpl.\njava:39)\n        at sun.reflect.DelegatingMethodAccessorImpl.invoke(DelegatingMethodAcces\nsorImpl.java:25)\n        at java.lang.reflect.Method.invoke(Method.java:324)\n        at org.eclipse.core.launcher.Main.basicRun(Main.java:267)\n        at org.eclipse.core.launcher.Main.run(Main.java:699)\n        at org.eclipse.core.launcher.Main.main(Main.java:683)\njava.lang.IllegalStateException",
    "Using I200404220800.from20040423_1215",
    "Fixed in Head."
  ],
  "commentCreationDates": [
    "2004-04-23T17:22:12+02:00",
    "2004-04-23T17:22:49+02:00",
    "2004-04-23T17:51:38+02:00"
  ],
  "traces": [
    {
      "exceptionType": "java.lang.IllegalStateException",
      "elements": [
        {
          "method": "org.eclipse.jface.text.projection.ProjectionMapping.findFragmentIndex",
          "source": "ProjectionMapping.java:166"
        },
        {
          "method": "org.eclipse.jface.text.projection.ProjectionMapping.findFragments",
          "source": "Pro jectionMapping.java:198"
        },
        {
          "method": "org.eclipse.jface.text.projection.ProjectionMapping.toImageRegion",
          "source": "Pro jectionMapping.java:226"
        },
        {
          "method": "org.eclipse.jface.text.projection.ProjectionMapping.toExactImageRegion",
          "source": "ProjectionMapping.java:386"
        },
        {
          "method": "org.eclipse.jface.text.projection.ProjectionDocument.normalize",
          "source": "Projec tionDocument.java:518"
        },
        {
          "method": "org.eclipse.jface.text.projection.ProjectionDocument.masterDocumentAboutToBeChanged",
          "source": "ProjectionDocument.java:640"
        },
        {
          "method": "org.eclipse.jface.text.projection.ProjectionDocumentManager.fireDocumentEvent",
          "source": "ProjectionDocumentManager.java:119"
        },
        {
          "method": "org.eclipse.jface.text.projection.ProjectionDocumentManager.documentAboutToBeChanged",
          "source": "ProjectionDocumentManager.java:136"
        },
        {
          "method": "org.eclipse.jface.text.AbstractDocument.fireDocumentAboutToBeChanged",
          "source": " AbstractDocument.java:577"
        },
        {
          "method": "org.eclipse.jface.text.AbstractDocument.set",
          "source": "AbstractDocument.java:998 "
        },
        {
          "method": "org.eclipse.jdt.internal.ui.javaeditor.PartiallySynchronizedDocument.set",
          "source": "PartiallySynchronizedDocument.java:101"
        },
        {
          "method": "org.eclipse.core.internal.filebuffers.ResourceTextFileBuffer.revert",
          "source": "R esourceTextFileBuffer.java:160"
        },
        {
          "method": "org.eclipse.ui.editors.text.TextFileDocumentProvider$1.execute",
          "source": "TextFi leDocumentProvider.java:581"
        },
        {
          "method": "org.eclipse.ui.editors.text.TextFileDocumentProvider$DocumentProviderOperation.run",
          "source": "TextFileDocumentProvider.java:96"
        },
        {
          "method": "org.eclipse.ui.actions.WorkspaceModifyDelegatingOperation.execute",
          "source": "Wor kspaceModifyDelegatingOperation.java:67"
        },
        {
          "method": "org.eclipse.ui.actions.WorkspaceModifyOperation$1.run",
          "source": "WorkspaceModify Operation.java:91"
        },
        {
          "method": "org.eclipse.core.internal.resources.Workspace.run",
          "source": "Workspace.java:1640 "
        },
        {
          "method": "org.eclipse.ui.actions.WorkspaceModifyOperation.run",
          "source": "WorkspaceModifyOp eration.java:105"
        },
        {
          "method": "org.eclipse.ui.internal.editors.text.WorkspaceOperationRunner.run",
          "source": "Wor kspaceOperationRunner.java:73"
        },
        {
          "method": "org.eclipse.ui.internal.editors.text.WorkspaceOperationRunner.run",
          "source": "Wor kspaceOperationRunner.java:63"
        },
        {
          "method": "org.eclipse.ui.editors.text.TextFileDocumentProvider.executeOperation",
          "source": "TextFileDocumentProvider.java:395"
        },
        {
          "method": "org.eclipse.ui.editors.text.TextFileDocumentProvider.resetDocument",
          "source": "Te xtFileDocumentProvider.java:599"
        },
        {
          "method": "org.eclipse.ui.texteditor.AbstractTextEditor.performRevert",
          "source": "AbstractTe xtEditor.java:3468"
        },
        {
          "method": "org.eclipse.ui.texteditor.AbstractTextEditor.doRevertToSaved",
          "source": "Abstract TextEditor.java:3451"
        },
        {
          "method": "org.eclipse.ui.texteditor.StatusTextEditor.doRevertToSaved",
          "source": "StatusText Editor.java:183"
        },
        {
          "method": "org.eclipse.ui.texteditor.RevertToSavedAction.run",
          "source": "RevertToSavedAction .java:47"
        },
        {
          "method": "org.eclipse.jface.action.Action.runWithEvent",
          "source": "Action.java:881"
        },
        {
          "method": "org.eclipse.ui.actions.RetargetAction.runWithEvent",
          "source": "RetargetAction.jav a:212"
        },
        {
          "method": "org.eclipse.jface.action.ActionContributionItem.handleWidgetSelection",
          "source": "ActionContributionItem.java:550"
        },
        {
          "method": "org.eclipse.jface.action.ActionContributionItem.access$2",
          "source": "ActionContri butionItem.java:502"
        },
        {
          "method": "org.eclipse.jface.action.ActionContributionItem$5.handleEvent",
          "source": "ActionC ontributionItem.java:435"
        },
        {
          "method": "org.eclipse.swt.widgets.EventTable.sendEvent",
          "source": "EventTable.java:82"
        },
        {
          "method": "org.eclipse.swt.widgets.Widget.sendEvent",
          "source": "Widget.java:769"
        },
        {
          "method": "org.eclipse.swt.widgets.Display.runDeferredEvents",
          "source": "Display.java:2592"
        },
        {
          "method": "org.eclipse.swt.widgets.Display.readAndDispatch",
          "source": "Display.java:2270"
        },
        {
          "method": "org.eclipse.ui.internal.Workbench.runEventLoop",
          "source": "Workbench.java:1437"
        },
        {
          "method": "org.eclipse.ui.internal.Workbench.runUI",
          "source": "Workbench.java:1408"
        },
        {
          "method": "org.eclipse.ui.internal.Workbench.createAndRunWorkbench",
          "source": "Workbench.jav a:244"
        },
        {
          "method": "org.eclipse.ui.PlatformUI.createAndRunWorkbench",
          "source": "PlatformUI.java:140"
        },
        {
          "method": "org.eclipse.ui.internal.ide.IDEApplication.run",
          "source": "IDEApplication.java:90 "
        },
        {
          "method": "org.eclipse.core.internal.runtime.PlatformActivator$1.run",
          "source": "PlatformAct ivator.java:280"
        },
        {
          "method": "org.eclipse.core.runtime.adaptor.EclipseStarter.run",
          "source": "EclipseStarter.ja va:240"
        },
        {
          "method": "org.eclipse.core.runtime.adaptor.EclipseStarter.run",
          "source": "EclipseStarter.ja va:117"
        },
        {
          "method": "sun.reflect.NativeMethodAccessorImpl.invoke0",
          "source": "Native Method"
        },
        {
          "method": "sun.reflect.NativeMethodAccessorImpl.invoke",
          "source": "NativeMethodAccessorImpl. java:39"
        },
        {
          "method": "sun.reflect.DelegatingMethodAccessorImpl.invoke",
          "source": "DelegatingMethodAcces sorImpl.java:25"
        },
        {
          "method": "java.lang.reflect.Method.invoke",
          "source": "Method.java:324"
        },
        {
          "method": "org.eclipse.core.launcher.Main.basicRun",
          "source": "Main.java:267"
        },
        {
          "method": "org.eclipse.core.launcher.Main.run",
          "source": "Main.java:699"
        },
        {
          "method": "org.eclipse.core.launcher.Main.main",
          "source": "Main.java:683"
        }
      ],
      "number": 0,
      "commentIndex": 0,
      "bugId": "59796",
      "date": "2004-04-23T17:22:12+02:00",
      "product": "Platform",
      "component": "Text",
      "severity": "normal"
    }
  ],
  "groupId": "59796",
  "bugId": "59796",
  "date": "2004-04-23T17:22:12+02:00",
  "product": "Platform",
  "component": "Text",
  "severity": "normal"
}