{
  "comments": [
    "20011113\n\nUsing the source below:\n1. Set breakpoint where indicated\n2. Debug\n3. Breakpoint is hit, second thread continues running\n4. When second thread terminates, resume first thread.\n5. Notice following walkback:\njava.lang.UnsupportedOperationException\n\tat java.util.AbstractList.add(AbstractList.java:155)\n\tat java.util.AbstractList.add(AbstractList.java:93)\n\tat org.eclipse.jdt.internal.debug.core.JDIDebugTarget.createThread\n(JDIDebugTarget.java:335)\n\tat \norg.eclipse.jdt.internal.debug.core.JDIDebugTarget$ThreadStartHandler.handleEven\nt(JDIDebugTarget.java:1546)\n\tat org.eclipse.jdt.internal.debug.core.EventDispatcher.dispatch\n(EventDispatcher.java:109)\n\tat org.eclipse.jdt.internal.debug.core.EventDispatcher$1.run\n(EventDispatcher.java:143)\n\tat org.eclipse.core.internal.resources.Workspace.run\n(Workspace.java:1186)\n\tat org.eclipse.jdt.internal.debug.core.EventDispatcher.run\n(EventDispatcher.java:160)\n\tat java.lang.Thread.run(Thread.java:498)\n\n\n\n\npublic class MultiThreadedLooper {\n\n\tpublic static void main(String[] args) {\n\t\tMultiThreadedLooper mtl \u003d new MultiThreadedLooper();\n\t\tmtl.spawnSecondThread();\n\t\ttry {\n\t\t\tThread.sleep(2000);\n\t\t} catch (InterruptedException ie) {\n\t\t}\n\t\tmtl.go();\n\t}\n\t\n\tpublic void go() {\n\t\tSystem.out.println(\"Thread1: breakpoint here\");\n\t}\n\t\n\tpublic void spawnSecondThread() {\n\t\tThread secondThread \u003d new Thread(new Runnable() {\n\t\t\tpublic void run() {\n\t\t\t\tfor (int i \u003d 0; i \u003c 10; i++) {\n\t\t\t\t\tSystem.out.println(\"Thread2: looping \" \n+ i);\n\t\t\t\t\ttry {\n\t\t\t\t\t\tThread.sleep(1000);\n\t\t\t\t\t} catch (InterruptedException ie) {\t\n\t\t\t\t\t\n\t\t\t\t\t}\n\t\t\t\t}\n\t\t\t}\n\t\t});\n\t\tsecondThread.setName(\"Second thread\");\n\t\tsecondThread.start();\n\t}\n}",
    "\n\n*** This bug has been marked as a duplicate of 5963 ***"
  ],
  "commentCreationDates": [
    "2001-11-15T21:48:39+01:00",
    "2001-11-15T21:52:57+01:00"
  ],
  "traces": [
    {
      "exceptionType": "java.lang.UnsupportedOperationException",
      "elements": [
        {
          "method": "java.util.AbstractList.add",
          "source": "AbstractList.java:155"
        },
        {
          "method": "java.util.AbstractList.add",
          "source": "AbstractList.java:93"
        },
        {
          "method": "org.eclipse.jdt.internal.debug.core.JDIDebugTarget.createThread",
          "source": "JDIDebugTarget.java:335"
        },
        {
          "method": "org.eclipse.jdt.internal.debug.core.JDIDebugTarget$ThreadStartHandler.handleEvent",
          "source": "JDIDebugTarget.java:1546"
        },
        {
          "method": "org.eclipse.jdt.internal.debug.core.EventDispatcher.dispatch",
          "source": "EventDispatcher.java:109"
        },
        {
          "method": "org.eclipse.jdt.internal.debug.core.EventDispatcher$1.run",
          "source": "EventDispatcher.java:143"
        },
        {
          "method": "org.eclipse.core.internal.resources.Workspace.run",
          "source": "Workspace.java:1186"
        },
        {
          "method": "org.eclipse.jdt.internal.debug.core.EventDispatcher.run",
          "source": "EventDispatcher.java:160"
        },
        {
          "method": "java.lang.Thread.run",
          "source": "Thread.java:498"
        }
      ],
      "number": 0,
      "commentIndex": 0,
      "bugId": "5984",
      "duplicateId": "5963",
      "date": "2001-11-15T21:48:39+01:00",
      "product": "JDT",
      "component": "Debug",
      "severity": "normal"
    }
  ],
  "groupId": "5963",
  "bugId": "5984",
  "duplicateId": "5963",
  "date": "2001-11-15T21:48:39+01:00",
  "product": "JDT",
  "component": "Debug",
  "severity": "normal"
}