{
  "comments": [
    "build N20040423\n\nWhile looking into the JDT Debug test failures, I noticed the following in the \nconsole logs for this build.  I doubt this is the cause of the test failures.\n\neclipse-test:\n     [echo] Running org.eclipse.jdt.debug.tests.AutomatedSuite\n     [java] org.eclipse.swt.SWTException: Failed to execute runnable \n(java.lang.NullPointerException)\n     [java] \tat org.eclipse.swt.SWT.error(SWT.java:2659)\n     [java] \tat org.eclipse.swt.SWT.error(SWT.java:2584)\n     [java] \tat org.eclipse.swt.widgets.Synchronizer.runAsyncMessages\n(Synchronizer.java:109)\n     [java] \tat org.eclipse.swt.widgets.Display.runAsyncMessages\n(Display.java:2569)\n     [java] \tat org.eclipse.swt.widgets.Display.readAndDispatch\n(Display.java:2274)\n     [java] \tat org.eclipse.jdt.debug.tests.AutomatedSuite.run\n(AutomatedSuite.java:191)\n     [java] \tat org.eclipse.test.EclipseTestRunner.run\n(EclipseTestRunner.java:320)\n     [java] \tat org.eclipse.test.EclipseTestRunner.run\n(EclipseTestRunner.java:199)\n     [java] \tat org.eclipse.test.EclipseTestRunner.main\n(EclipseTestRunner.java:134)\n     [java] \tat org.eclipse.test.UITestApplication$3.run\n(UITestApplication.java:180)\n     [java] \tat org.eclipse.swt.widgets.RunnableLock.run\n(RunnableLock.java:35)\n     [java] \tat org.eclipse.swt.widgets.Synchronizer.runAsyncMessages\n(Synchronizer.java:106)\n     [java] \tat org.eclipse.swt.widgets.Display.runAsyncMessages\n(Display.java:2569)\n     [java] \tat org.eclipse.swt.widgets.Display.readAndDispatch\n(Display.java:2274)\n     [java] \tat org.eclipse.ui.internal.Workbench.runEventLoop\n(Workbench.java:1352)\n     [java] \tat org.eclipse.ui.internal.Workbench.runUI(Workbench.java:1323)\n     [java] \tat org.eclipse.ui.internal.Workbench.createAndRunWorkbench\n(Workbench.java:239)\n     [java] \tat org.eclipse.ui.PlatformUI.createAndRunWorkbench\n(PlatformUI.java:140)\n     [java] \tat org.eclipse.ui.internal.ide.IDEApplication.run\n(IDEApplication.java:90)\n     [java] \tat org.eclipse.test.UITestApplication.runApplication\n(UITestApplication.java:123)\n     [java] \tat org.eclipse.test.UITestApplication.run\n(UITestApplication.java:55)\n     [java] \tat org.eclipse.core.internal.runtime.PlatformActivator$1.run\n(PlatformActivator.java:283)\n     [java] \tat org.eclipse.core.runtime.adaptor.EclipseStarter.run\n(EclipseStarter.java:240)\n     [java] \tat org.eclipse.core.runtime.adaptor.EclipseStarter.run\n(EclipseStarter.java:117)\n     [java] \tat sun.reflect.NativeMethodAccessorImpl.invoke0(Native Method)\n     [java] \tat sun.reflect.NativeMethodAccessorImpl.invoke\n(NativeMethodAccessorImpl.java:39)\n     [java] \tat sun.reflect.DelegatingMethodAccessorImpl.invoke\n(DelegatingMethodAccessorImpl.java:25)\n     [java] \tat java.lang.reflect.Method.invoke(Method.java:324)\n     [java] \tat org.eclipse.core.launcher.Main.basicRun(Main.java:269)\n     [java] \tat org.eclipse.core.launcher.Main.run(Main.java:700)\n     [java] \tat org.eclipse.core.launcher.Main.main(Main.java:684)\n     [java] *** Stack trace of contained exception ***\n     [java] java.lang.NullPointerException\n     [java] \tat \norg.eclipse.jdt.internal.ui.text.SmartBackspaceManager.uninstall\n(SmartBackspaceManager.java:272)\n     [java] \tat \norg.eclipse.jdt.internal.ui.javaeditor.JavaSourceViewer.handleDispose\n(JavaSourceViewer.java:379)\n     [java] \tat org.eclipse.jface.text.TextViewer$1.widgetDisposed\n(TextViewer.java:1358)\n     [java] \tat org.eclipse.swt.widgets.TypedListener.handleEvent\n(TypedListener.java:100)\n     [java] \tat org.eclipse.swt.widgets.EventTable.sendEvent\n(EventTable.java:82)\n     [java] \tat org.eclipse.swt.widgets.Widget.sendEvent(Widget.java:796)\n     [java] \tat org.eclipse.swt.widgets.Widget.sendEvent(Widget.java:820)\n     [java] \tat org.eclipse.swt.widgets.Widget.sendEvent(Widget.java:805)\n     [java] \tat org.eclipse.swt.widgets.Widget.notifyListeners\n(Widget.java:613)\n     [java] \tat org.eclipse.swt.custom.StyledText.handleDispose\n(StyledText.java:4854)\n     [java] \tat org.eclipse.swt.custom.StyledText$7.handleEvent\n(StyledText.java:4725)\n     [java] \tat org.eclipse.swt.widgets.EventTable.sendEvent\n(EventTable.java:82)\n     [java] \tat org.eclipse.swt.widgets.Widget.sendEvent(Widget.java:796)\n     [java] \tat org.eclipse.swt.widgets.Widget.sendEvent(Widget.java:820)\n     [java] \tat org.eclipse.swt.widgets.Widget.sendEvent(Widget.java:801)\n     [java] \tat org.eclipse.swt.widgets.Widget.releaseWidget\n(Widget.java:708)\n     [java] \tat org.eclipse.swt.widgets.Control.releaseWidget\n(Control.java:1470)\n     [java] \tat org.eclipse.swt.widgets.Scrollable.releaseWidget\n(Scrollable.java:188)\n     [java] \tat org.eclipse.swt.widgets.Composite.releaseWidget\n(Composite.java:373)\n     [java] \tat org.eclipse.swt.widgets.Canvas.releaseWidget\n(Canvas.java:118)\n     [java] \tat org.eclipse.swt.widgets.Widget.releaseResources\n(Widget.java:673)\n     [java] \tat org.eclipse.swt.widgets.Composite.releaseChildren\n(Composite.java:367)\n     [java] \tat org.eclipse.swt.widgets.Composite.releaseWidget\n(Composite.java:372)\n     [java] \tat org.eclipse.swt.widgets.Canvas.releaseWidget\n(Canvas.java:118)\n     [java] \tat org.eclipse.swt.widgets.Widget.releaseResources\n(Widget.java:673)\n     [java] \tat org.eclipse.swt.widgets.Composite.releaseChildren\n(Composite.java:367)\n     [java] \tat org.eclipse.swt.widgets.Composite.releaseWidget\n(Composite.java:372)\n     [java] \tat org.eclipse.swt.widgets.Widget.releaseResources\n(Widget.java:673)\n     [java] \tat org.eclipse.swt.widgets.Composite.releaseChildren\n(Composite.java:367)\n     [java] \tat org.eclipse.swt.widgets.Composite.releaseWidget\n(Composite.java:372)\n     [java] \tat org.eclipse.swt.widgets.Widget.releaseResources\n(Widget.java:673)\n     [java] \tat org.eclipse.swt.widgets.Composite.releaseChildren\n(Composite.java:367)\n     [java] \tat org.eclipse.swt.widgets.Composite.releaseWidget\n(Composite.java:372)\n     [java] \tat org.eclipse.swt.widgets.Widget.releaseResources\n(Widget.java:673)\n     [java] \tat org.eclipse.swt.widgets.Composite.releaseChildren\n(Composite.java:367)\n     [java] \tat org.eclipse.swt.widgets.Composite.releaseWidget\n(Composite.java:372)\n     [java] \tat org.eclipse.swt.widgets.Widget.dispose(Widget.java:368)\n     [java] \tat org.eclipse.ui.internal.PartPane.dispose(PartPane.java:173)\n     [java] \tat org.eclipse.ui.internal.EditorPresentation.closeEditor\n(EditorPresentation.java:77)\n     [java] \tat org.eclipse.ui.internal.EditorPresentation.closeEditor\n(EditorPresentation.java:65)\n     [java] \tat org.eclipse.ui.internal.EditorManager.closeEditor\n(EditorManager.java:160)\n     [java] \tat org.eclipse.ui.internal.WorkbenchPage.closeEditor\n(WorkbenchPage.java:915)\n     [java] \tat org.eclipse.ui.texteditor.AbstractTextEditor$15.run\n(AbstractTextEditor.java:2743)\n     [java] \tat org.eclipse.swt.widgets.RunnableLock.run\n(RunnableLock.java:35)\n     [java] \tat org.eclipse.swt.widgets.Synchronizer.runAsyncMessages\n(Synchronizer.java:106)\n     [java] \tat org.eclipse.swt.widgets.Display.runAsyncMessages\n(Display.java:2569)\n     [java] \tat org.eclipse.swt.widgets.Display.readAndDispatch\n(Display.java:2274)\n     [java] \tat org.eclipse.jdt.debug.tests.AutomatedSuite.run\n(AutomatedSuite.java:191)\n     [java] \tat org.eclipse.test.EclipseTestRunner.run\n(EclipseTestRunner.java:320)\n     [java] \tat org.eclipse.test.EclipseTestRunner.run\n(EclipseTestRunner.java:199)\n     [java] \tat org.eclipse.test.EclipseTestRunner.main\n(EclipseTestRunner.java:134)\n     [java] \tat org.eclipse.test.UITestApplication$3.run\n(UITestApplication.java:180)\n     [java] \tat org.eclipse.swt.widgets.RunnableLock.run\n(RunnableLock.java:35)\n     [java] \tat org.eclipse.swt.widgets.Synchronizer.runAsyncMessages\n(Synchronizer.java:106)\n     [java] \tat org.eclipse.swt.widgets.Display.runAsyncMessages\n(Display.java:2569)\n     [java] \tat org.eclipse.swt.widgets.Display.readAndDispatch\n(Display.java:2274)\n     [java] \tat org.eclipse.ui.internal.Workbench.runEventLoop\n(Workbench.java:1352)\n     [java] \tat org.eclipse.ui.internal.Workbench.runUI(Workbench.java:1323)\n     [java] \tat org.eclipse.ui.internal.Workbench.createAndRunWorkbench\n(Workbench.java:239)\n     [java] \tat org.eclipse.ui.PlatformUI.createAndRunWorkbench\n(PlatformUI.java:140)\n     [java] \tat org.eclipse.ui.internal.ide.IDEApplication.run\n(IDEApplication.java:90)\n     [java] \tat org.eclipse.test.UITestApplication.runApplication\n(UITestApplication.java:123)\n     [java] \tat org.eclipse.test.UITestApplication.run\n(UITestApplication.java:55)\n     [java] \tat org.eclipse.core.internal.runtime.PlatformActivator$1.run\n(PlatformActivator.java:283)\n     [java] \tat org.eclipse.core.runtime.adaptor.EclipseStarter.run\n(EclipseStarter.java:240)\n     [java] \tat org.eclipse.core.runtime.adaptor.EclipseStarter.run\n(EclipseStarter.java:117)\n     [java] \tat sun.reflect.NativeMethodAccessorImpl.invoke0(Native Method)\n     [java] \tat sun.reflect.NativeMethodAccessorImpl.invoke\n(NativeMethodAccessorImpl.java:39)\n     [java] \tat sun.reflect.DelegatingMethodAccessorImpl.invoke\n(DelegatingMethodAccessorImpl.java:25)\n     [java] \tat java.lang.reflect.Method.invoke(Method.java:324)\n     [java] \tat org.eclipse.core.launcher.Main.basicRun(Main.java:269)\n     [java] \tat org.eclipse.core.launcher.Main.run(Main.java:700)\n     [java] \tat org.eclipse.core.launcher.Main.main(Main.java:684)\n     [java] org.eclipse.swt.SWTException: Failed to execute runnable \n(junit.framework.AssertionFailedError: BadLocationException occurred: \norg.eclipse.jface.text.BadLocationException)\n     [java] \tat org.eclipse.swt.SWT.error(SWT.java:2659)\n     [java] \tat org.eclipse.swt.SWT.error(SWT.java:2584)\n     [java] \tat org.eclipse.swt.widgets.Synchronizer.runAsyncMessages\n(Synchronizer.java:109)\n     [java] \tat org.eclipse.swt.widgets.Display.runAsyncMessages\n(Display.java:2569)\n     [java] \tat org.eclipse.swt.widgets.Display.readAndDispatch\n(Display.java:2274)\n     [java] \tat org.eclipse.jdt.debug.tests.AutomatedSuite.run\n(AutomatedSuite.java:191)\n     [java] \tat org.eclipse.test.EclipseTestRunner.run\n(EclipseTestRunner.java:320)\n     [java] \tat org.eclipse.test.EclipseTestRunner.run\n(EclipseTestRunner.java:199)\n     [java] \tat org.eclipse.test.EclipseTestRunner.main\n(EclipseTestRunner.java:134)\n     [java] \tat org.eclipse.test.UITestApplication$3.run\n(UITestApplication.java:180)\n     [java] \tat org.eclipse.swt.widgets.RunnableLock.run\n(RunnableLock.java:35)\n     [java] \tat org.eclipse.swt.widgets.Synchronizer.runAsyncMessages\n(Synchronizer.java:106)\n     [java] \tat org.eclipse.swt.widgets.Display.runAsyncMessages\n(Display.java:2569)\n     [java] \tat org.eclipse.swt.widgets.Display.readAndDispatch\n(Display.java:2274)\n     [java] \tat org.eclipse.ui.internal.Workbench.runEventLoop\n(Workbench.java:1352)\n     [java] \tat org.eclipse.ui.internal.Workbench.runUI(Workbench.java:1323)\n     [java] \tat org.eclipse.ui.internal.Workbench.createAndRunWorkbench\n(Workbench.java:239)\n     [java] \tat org.eclipse.ui.PlatformUI.createAndRunWorkbench\n(PlatformUI.java:140)\n     [java] \tat org.eclipse.ui.internal.ide.IDEApplication.run\n(IDEApplication.java:90)\n     [java] \tat org.eclipse.test.UITestApplication.runApplication\n(UITestApplication.java:123)\n     [java] \tat org.eclipse.test.UITestApplication.run\n(UITestApplication.java:55)\n     [java] \tat org.eclipse.core.internal.runtime.PlatformActivator$1.run\n(PlatformActivator.java:283)\n     [java] \tat org.eclipse.core.runtime.adaptor.EclipseStarter.run\n(EclipseStarter.java:240)\n     [java] \tat org.eclipse.core.runtime.adaptor.EclipseStarter.run\n(EclipseStarter.java:117)\n     [java] \tat sun.reflect.NativeMethodAccessorImpl.invoke0(Native Method)\n     [java] \tat sun.reflect.NativeMethodAccessorImpl.invoke\n(NativeMethodAccessorImpl.java:39)\n     [java] \tat sun.reflect.DelegatingMethodAccessorImpl.invoke\n(DelegatingMethodAccessorImpl.java:25)\n     [java] \tat java.lang.reflect.Method.invoke(Method.java:324)\n     [java] \tat org.eclipse.core.launcher.Main.basicRun(Main.java:269)\n     [java] \tat org.eclipse.core.launcher.Main.run(Main.java:700)\n     [java] \tat org.eclipse.core.launcher.Main.main(Main.java:684)\n     [java] *** Stack trace of contained exception ***\n     [java] junit.framework.AssertionFailedError: BadLocationException \noccurred: org.eclipse.jface.text.BadLocationException\n     [java] \tat junit.framework.Assert.fail(Assert.java:47)\n     [java] \tat junit.framework.Assert.assertTrue(Assert.java:20)\n     [java] \tat \norg.eclipse.jdt.debug.tests.core.LineTrackerTests.lineAppended\n(LineTrackerTests.java:164)\n     [java] \tat \norg.eclipse.jdt.debug.testplugin.ConsoleLineTracker.lineAppended\n(ConsoleLineTracker.java:66)\n     [java] \tat \norg.eclipse.debug.internal.ui.views.console.ConsoleLineNotifier.processNewLines\n(ConsoleLineNotifier.java:133)\n     [java] \tat \norg.eclipse.debug.internal.ui.views.console.ConsoleLineNotifier.streamsClosed\n(ConsoleLineNotifier.java:93)\n     [java] \tat \norg.eclipse.debug.internal.ui.views.console.ConsoleDocumentPartitioner$2.run\n(ConsoleDocumentPartitioner.java:642)\n     [java] \tat org.eclipse.swt.widgets.RunnableLock.run\n(RunnableLock.java:35)\n     [java] \tat org.eclipse.swt.widgets.Synchronizer.runAsyncMessages\n(Synchronizer.java:106)\n     [java] \tat org.eclipse.swt.widgets.Display.runAsyncMessages\n(Display.java:2569)\n     [java] \tat org.eclipse.swt.widgets.Display.readAndDispatch\n(Display.java:2274)\n     [java] \tat org.eclipse.jdt.debug.tests.AutomatedSuite.run\n(AutomatedSuite.java:191)\n     [java] \tat org.eclipse.test.EclipseTestRunner.run\n(EclipseTestRunner.java:320)\n     [java] \tat org.eclipse.test.EclipseTestRunner.run\n(EclipseTestRunner.java:199)\n     [java] \tat org.eclipse.test.EclipseTestRunner.main\n(EclipseTestRunner.java:134)\n     [java] \tat org.eclipse.test.UITestApplication$3.run\n(UITestApplication.java:180)\n     [java] \tat org.eclipse.swt.widgets.RunnableLock.run\n(RunnableLock.java:35)\n     [java] \tat org.eclipse.swt.widgets.Synchronizer.runAsyncMessages\n(Synchronizer.java:106)\n     [java] \tat org.eclipse.swt.widgets.Display.runAsyncMessages\n(Display.java:2569)\n     [java] \tat org.eclipse.swt.widgets.Display.readAndDispatch\n(Display.java:2274)\n     [java] \tat org.eclipse.ui.internal.Workbench.runEventLoop\n(Workbench.java:1352)\n     [java] \tat org.eclipse.ui.internal.Workbench.runUI(Workbench.java:1323)\n     [java] \tat org.eclipse.ui.internal.Workbench.createAndRunWorkbench\n(Workbench.java:239)\n     [java] \tat org.eclipse.ui.PlatformUI.createAndRunWorkbench\n(PlatformUI.java:140)\n     [java] \tat org.eclipse.ui.internal.ide.IDEApplication.run\n(IDEApplication.java:90)\n     [java] \tat org.eclipse.test.UITestApplication.runApplication\n(UITestApplication.java:123)\n     [java] \tat org.eclipse.test.UITestApplication.run\n(UITestApplication.java:55)\n     [java] \tat org.eclipse.core.internal.runtime.PlatformActivator$1.run\n(PlatformActivator.java:283)\n     [java] \tat org.eclipse.core.runtime.adaptor.EclipseStarter.run\n(EclipseStarter.java:240)\n     [java] \tat org.eclipse.core.runtime.adaptor.EclipseStarter.run\n(EclipseStarter.java:117)\n     [java] \tat sun.reflect.NativeMethodAccessorImpl.invoke0(Native Method)\n     [java] \tat sun.reflect.NativeMethodAccessorImpl.invoke\n(NativeMethodAccessorImpl.java:39)\n     [java] \tat sun.reflect.DelegatingMethodAccessorImpl.invoke\n(DelegatingMethodAccessorImpl.java:25)\n     [java] \tat java.lang.reflect.Method.invoke(Method.java:324)\n     [java] \tat org.eclipse.core.launcher.Main.basicRun(Main.java:269)\n     [java] \tat org.eclipse.core.launcher.Main.run(Main.java:700)\n     [java] \tat org.eclipse.core.launcher.Main.main(Main.java:684)",
    "\n\n*** This bug has been marked as a duplicate of 59785 ***"
  ],
  "commentCreationDates": [
    "2004-04-23T22:23:16+02:00",
    "2004-04-27T09:44:15+02:00"
  ],
  "traces": [
    {
      "exceptionType": "org.eclipse.swt.SWTException",
      "message": "Failed to execute runnable  (java.lang.NullPointerException)      [java]",
      "elements": [
        {
          "method": "org.eclipse.swt.SWT.error",
          "source": "SWT.java:2659"
        }
      ],
      "number": 0,
      "commentIndex": 0,
      "bugId": "59842",
      "duplicateId": "59785",
      "date": "2004-04-23T22:23:16+02:00",
      "product": "JDT",
      "component": "Text",
      "severity": "normal"
    },
    {
      "exceptionType": "junit.framework.AssertionFailedError",
      "message": "BadLocationException occurred:  org.eclipse.jface.text.BadLocationException)      [java]",
      "elements": [
        {
          "method": "org.eclipse.swt.SWT.error",
          "source": "SWT.java:2659"
        }
      ],
      "number": 1,
      "commentIndex": 0,
      "bugId": "59842",
      "duplicateId": "59785",
      "date": "2004-04-23T22:23:16+02:00",
      "product": "JDT",
      "component": "Text",
      "severity": "normal"
    },
    {
      "exceptionType": "junit.framework.AssertionFailedError",
      "message": "BadLocationException  occurred: org.eclipse.jface.text.BadLocationException      [java]",
      "elements": [
        {
          "method": "junit.framework.Assert.fail",
          "source": "Assert.java:47"
        }
      ],
      "number": 2,
      "commentIndex": 0,
      "bugId": "59842",
      "duplicateId": "59785",
      "date": "2004-04-23T22:23:16+02:00",
      "product": "JDT",
      "component": "Text",
      "severity": "normal"
    }
  ],
  "groupId": "59785",
  "bugId": "59842",
  "duplicateId": "59785",
  "date": "2004-04-23T22:23:16+02:00",
  "product": "JDT",
  "component": "Text",
  "severity": "normal"
}