{
  "comments": [
    "While running I200404270800 with GTK+ 2.4.0 on KDE 3.2.1. \n \n \n \n!ENTRY org.eclipse.ui 4 4 Apr 27, 2004 11:02:48.296 \n!MESSAGE Unhandled event loop exception \n!ENTRY org.eclipse.ui 4 0 Apr 27, 2004 11:02:48.297 \n!MESSAGE Widget is disposed \n!STACK 0 \norg.eclipse.swt.SWTException: Widget is disposed \n        at org.eclipse.swt.SWT.error(SWT.java:2680) \n        at org.eclipse.swt.SWT.error(SWT.java:2605) \n        at org.eclipse.swt.SWT.error(SWT.java:2576) \n        at org.eclipse.swt.widgets.Widget.error(Widget.java:373) \n        at org.eclipse.swt.widgets.Widget.checkWidget(Widget.java:309) \n        at org.eclipse.swt.widgets.TreeItem.getExpanded(TreeItem.java:281) \n        at \norg.eclipse.jface.viewers.TreeViewer.getExpanded(TreeViewer.java:149) \n        at \norg.eclipse.jface.viewers.AbstractTreeViewer.internalRemove(AbstractTreeViewer.java:1097) \n        at org.eclipse.jface.viewers.AbstractTreeViewer.access$1\n(AbstractTreeViewer.java:1076) \n        at \norg.eclipse.jface.viewers.AbstractTreeViewer$6.run(AbstractTreeViewer.java:1193) \n        at \norg.eclipse.jface.viewers.StructuredViewer.preservingSelection(StructuredViewer.java:810) \n        at \norg.eclipse.jface.viewers.AbstractTreeViewer.remove(AbstractTreeViewer.java:1191) \n        at \norg.eclipse.ui.internal.progress.ProgressTreeContentProvider.remove(ProgressTreeContentProvider.java:106) \n        at \norg.eclipse.ui.internal.progress.ProgressViewUpdater$1.runInUIThread(ProgressViewUpdater.java:244) \n        at org.eclipse.ui.progress.UIJob$1.run(UIJob.java:84) \n        at org.eclipse.swt.widgets.RunnableLock.run(RunnableLock.java:35) \n        at \norg.eclipse.swt.widgets.Synchronizer.runAsyncMessages(Synchronizer.java:106) \n        at org.eclipse.swt.widgets.Display.runAsyncMessages(Display.java:1996) \n        at org.eclipse.swt.widgets.Display.readAndDispatch(Display.java:1786) \n        at org.eclipse.ui.internal.Workbench.runEventLoop(Workbench.java:1353) \n        at org.eclipse.ui.internal.Workbench.runUI(Workbench.java:1324) \n        at \norg.eclipse.ui.internal.Workbench.createAndRunWorkbench(Workbench.java:240) \n        at org.eclipse.ui.PlatformUI.createAndRunWorkbench(PlatformUI.java:140) \n        at \norg.eclipse.ui.internal.ide.IDEApplication.run(IDEApplication.java:90) \n        at \norg.eclipse.core.internal.runtime.PlatformActivator$1.run(PlatformActivator.java:283) \n        at \norg.eclipse.core.runtime.adaptor.EclipseStarter.run(EclipseStarter.java:240) \n        at \norg.eclipse.core.runtime.adaptor.EclipseStarter.run(EclipseStarter.java:117) \n        at sun.reflect.NativeMethodAccessorImpl.invoke0(Native Method) \n        at \nsun.reflect.NativeMethodAccessorImpl.invoke(NativeMethodAccessorImpl.java:39) \n        at \nsun.reflect.DelegatingMethodAccessorImpl.invoke(DelegatingMethodAccessorImpl.java:25) \n        at java.lang.reflect.Method.invoke(Method.java:324) \n        at org.eclipse.core.launcher.Main.basicRun(Main.java:269) \n        at org.eclipse.core.launcher.Main.run(Main.java:700) \n        at org.eclipse.core.launcher.Main.main(Main.java:684)",
    "\n\n*** This bug has been marked as a duplicate of 58217 ***"
  ],
  "commentCreationDates": [
    "2004-04-27T17:34:05+02:00",
    "2004-04-27T21:33:17+02:00"
  ],
  "traces": [
    {
      "exceptionType": "org.eclipse.swt.SWTException",
      "message": "Widget is disposed",
      "elements": [
        {
          "method": "org.eclipse.swt.SWT.error",
          "source": "SWT.java:2680"
        },
        {
          "method": "org.eclipse.swt.SWT.error",
          "source": "SWT.java:2605"
        },
        {
          "method": "org.eclipse.swt.SWT.error",
          "source": "SWT.java:2576"
        },
        {
          "method": "org.eclipse.swt.widgets.Widget.error",
          "source": "Widget.java:373"
        },
        {
          "method": "org.eclipse.swt.widgets.Widget.checkWidget",
          "source": "Widget.java:309"
        },
        {
          "method": "org.eclipse.swt.widgets.TreeItem.getExpanded",
          "source": "TreeItem.java:281"
        },
        {
          "method": "org.eclipse.jface.viewers.TreeViewer.getExpanded",
          "source": "TreeViewer.java:149"
        },
        {
          "method": "org.eclipse.jface.viewers.AbstractTreeViewer.internalRemove",
          "source": "AbstractTreeViewer.java:1097"
        },
        {
          "method": "org.eclipse.jface.viewers.AbstractTreeViewer.access$1",
          "source": "AbstractTreeViewer.java:1076"
        },
        {
          "method": "org.eclipse.jface.viewers.AbstractTreeViewer$6.run",
          "source": "AbstractTreeViewer.java:1193"
        },
        {
          "method": "org.eclipse.jface.viewers.StructuredViewer.preservingSelection",
          "source": "StructuredViewer.java:810"
        },
        {
          "method": "org.eclipse.jface.viewers.AbstractTreeViewer.remove",
          "source": "AbstractTreeViewer.java:1191"
        },
        {
          "method": "org.eclipse.ui.internal.progress.ProgressTreeContentProvider.remove",
          "source": "ProgressTreeContentProvider.java:106"
        },
        {
          "method": "org.eclipse.ui.internal.progress.ProgressViewUpdater$1.runInUIThread",
          "source": "ProgressViewUpdater.java:244"
        },
        {
          "method": "org.eclipse.ui.progress.UIJob$1.run",
          "source": "UIJob.java:84"
        },
        {
          "method": "org.eclipse.swt.widgets.RunnableLock.run",
          "source": "RunnableLock.java:35"
        },
        {
          "method": "org.eclipse.swt.widgets.Synchronizer.runAsyncMessages",
          "source": "Synchronizer.java:106"
        },
        {
          "method": "org.eclipse.swt.widgets.Display.runAsyncMessages",
          "source": "Display.java:1996"
        },
        {
          "method": "org.eclipse.swt.widgets.Display.readAndDispatch",
          "source": "Display.java:1786"
        },
        {
          "method": "org.eclipse.ui.internal.Workbench.runEventLoop",
          "source": "Workbench.java:1353"
        },
        {
          "method": "org.eclipse.ui.internal.Workbench.runUI",
          "source": "Workbench.java:1324"
        },
        {
          "method": "org.eclipse.ui.internal.Workbench.createAndRunWorkbench",
          "source": "Workbench.java:240"
        },
        {
          "method": "org.eclipse.ui.PlatformUI.createAndRunWorkbench",
          "source": "PlatformUI.java:140"
        },
        {
          "method": "org.eclipse.ui.internal.ide.IDEApplication.run",
          "source": "IDEApplication.java:90"
        },
        {
          "method": "org.eclipse.core.internal.runtime.PlatformActivator$1.run",
          "source": "PlatformActivator.java:283"
        },
        {
          "method": "org.eclipse.core.runtime.adaptor.EclipseStarter.run",
          "source": "EclipseStarter.java:240"
        },
        {
          "method": "org.eclipse.core.runtime.adaptor.EclipseStarter.run",
          "source": "EclipseStarter.java:117"
        },
        {
          "method": "sun.reflect.NativeMethodAccessorImpl.invoke0",
          "source": "Native Method"
        },
        {
          "method": "sun.reflect.NativeMethodAccessorImpl.invoke",
          "source": "NativeMethodAccessorImpl.java:39"
        },
        {
          "method": "sun.reflect.DelegatingMethodAccessorImpl.invoke",
          "source": "DelegatingMethodAccessorImpl.java:25"
        },
        {
          "method": "java.lang.reflect.Method.invoke",
          "source": "Method.java:324"
        },
        {
          "method": "org.eclipse.core.launcher.Main.basicRun",
          "source": "Main.java:269"
        },
        {
          "method": "org.eclipse.core.launcher.Main.run",
          "source": "Main.java:700"
        },
        {
          "method": "org.eclipse.core.launcher.Main.main",
          "source": "Main.java:684"
        }
      ],
      "number": 0,
      "commentIndex": 0,
      "bugId": "60124",
      "duplicateId": "58217",
      "date": "2004-04-27T17:34:05+02:00",
      "product": "Platform",
      "component": "UI",
      "severity": "normal"
    }
  ],
  "groupId": "58217",
  "bugId": "60124",
  "duplicateId": "58217",
  "date": "2004-04-27T17:34:05+02:00",
  "product": "Platform",
  "component": "UI",
  "severity": "normal"
}