{
  "comments": [
    "In an attempt to work around defect 50347, I defined a project with linked \nsource folders.  Simply put, I got nowhere.\n\nSteps to reproduce:\n  1. create a new project in the workspace\n  2. add source folder\n     a. create new folder, link to external source folder\n\nDuring step 2.a, I get a dialog saying that the folder cannot be found, where \nthe folder path corresponds to the linked resource path, only it\u0027s missing the \ndrive specification (e.g. desired resource \u003d\u003d x:\\common\\src, path reported not \nfound \u003d\u003d common\\src).  After clicking out of the dialog, the source folder \nstill shows up in the project folder selection dialog.  I select it to \ncomplete the source folder definition.\n\nOnce the project is defined, it\u0027s useless.  The source folders are displayed, \nbut their contents are not loaded.  If I try to refresh the source/linked \nfolder, I get the Refresh Problems dialog, with the following \nmessage, \"Element not found: /common/src\".  I looked at the folder properties \n(via right-click), and I see that it is defined as a linked folder, pointing \nto the correct location (I\u0027ve confirmed this against the .project file as \nwell).",
    "While writing up the bug report, it occurred to me that perhaps the build spec \nsystem is assuming that folders are always relative to a single drive spec.  I \nrepeated the above test case, this time using a source folder located on a \nlocation on my c: drive, and I had no problems.",
    "I\u0027m back to this bug, as I\u0027ve encountered more broken behavior.\n\nI just created an empty Java project in the following location (i.e. not in \nthe default workspace) c:\\dev\\adv55\\eclipse\\testCommon\n\nI then added a source folder linked to a linked external resource.  The source \nfolder, was called commonSrc.  I defined the link using a linked resource \nvariable, extending it in the dialog itself.  The variable is called \"common\", \nand it is linked to c:\\dev\\adv55\\advcommon3x.  When I say that I extended the \nvariable, I mean that in the new source folder dialog, when I select to link \nto an external resource, I am given the choice to extend a linked resource \nvariable.  In this case, I extended it so that the full path is c:\\dev\\adv55\n\\advcommon3x.\n\nOk, now when I go back to my Java perspective, the source folder only contains \nthe resources in c:\\dev\\adv55\\advcommon3x\\src, but none of the resources in \nits subdirectories (i.e. all the packages contained therein).  \n\nAdditionally, I am continiously receiving the following Errors (i.e. these are \npoping up):\n\nError Aug 12, 2004 10:10:17.552 An internal error occurred during: \"Refreshing \nworkspace\".\njava.lang.IllegalArgumentException: Element not found: /advcommon3x/src/com.\n\tat org.eclipse.core.internal.watson.ElementTree.elementNotFound\n(ElementTree.java:377)\n\tat org.eclipse.core.internal.watson.ElementTree.createElement\n(ElementTree.java:286)\n\tat org.eclipse.core.internal.resources.Workspace.createResource\n(Workspace.java:711)\n\tat org.eclipse.core.internal.resources.Workspace.createResource\n(Workspace.java:681)\n\tat org.eclipse.core.internal.resources.Workspace.createResource\n(Workspace.java:745)\n\tat \norg.eclipse.core.internal.localstore.RefreshLocalVisitor.createResource\n(RefreshLocalVisitor.java:78)\n\tat \norg.eclipse.core.internal.localstore.RefreshLocalAliasVisitor.createResource\n(RefreshLocalAliasVisitor.java:34)\n\tat \norg.eclipse.core.internal.localstore.RefreshLocalVisitor.synchronizeExistence\n(RefreshLocalVisitor.java:202)\n\tat org.eclipse.core.internal.localstore.RefreshLocalVisitor.visit\n(RefreshLocalVisitor.java:278)\n\tat org.eclipse.core.internal.localstore.UnifiedTree.accept\n(UnifiedTree.java:75)\n\tat \norg.eclipse.core.internal.localstore.FileSystemResourceManager.refreshResource\n(FileSystemResourceManager.java:622)\n\tat \norg.eclipse.core.internal.localstore.FileSystemResourceManager.refresh\n(FileSystemResourceManager.java:609)\n\tat org.eclipse.core.internal.resources.Resource.refreshLocal\n(Resource.java:1222)\n\tat org.eclipse.core.internal.refresh.RefreshJob.runInWorkspace\n(RefreshJob.java:98)\n\tat org.eclipse.core.internal.resources.InternalWorkspaceJob.run\n(InternalWorkspaceJob.java:38)\n\tat org.eclipse.core.internal.jobs.Worker.run(Worker.java:66)\n\n\nHere\u0027s the session data:\n\neclipse.buildId\u003dI200406251208\njava.version\u003d1.4.2_03\njava.vendor\u003dSun Microsystems Inc.\nBootLoader constants: OS\u003dwin32, ARCH\u003dx86, WS\u003dwin32, NL\u003den_US\n",
    "Please forgive the confusion with this bug.  Apparently, I had it assigned to \nPlatform resources somehow.",
    "Platform / Resources is the right place to handle this problem.",
    "Cannot reproduce."
  ],
  "commentCreationDates": [
    "2004-04-27T20:50:33+02:00",
    "2004-04-27T20:58:23+02:00",
    "2004-08-12T19:22:58+02:00",
    "2004-08-12T19:25:47+02:00",
    "2004-08-16T16:53:05+02:00",
    "2005-02-15T19:47:52+01:00"
  ],
  "traces": [
    {
      "exceptionType": "java.lang.IllegalArgumentException",
      "message": "Element not found: /advcommon3x/src/com.",
      "elements": [
        {
          "method": "org.eclipse.core.internal.watson.ElementTree.elementNotFound",
          "source": "ElementTree.java:377"
        },
        {
          "method": "org.eclipse.core.internal.watson.ElementTree.createElement",
          "source": "ElementTree.java:286"
        },
        {
          "method": "org.eclipse.core.internal.resources.Workspace.createResource",
          "source": "Workspace.java:711"
        },
        {
          "method": "org.eclipse.core.internal.resources.Workspace.createResource",
          "source": "Workspace.java:681"
        },
        {
          "method": "org.eclipse.core.internal.resources.Workspace.createResource",
          "source": "Workspace.java:745"
        },
        {
          "method": "org.eclipse.core.internal.localstore.RefreshLocalVisitor.createResource",
          "source": "RefreshLocalVisitor.java:78"
        },
        {
          "method": "org.eclipse.core.internal.localstore.RefreshLocalAliasVisitor.createResource",
          "source": "RefreshLocalAliasVisitor.java:34"
        },
        {
          "method": "org.eclipse.core.internal.localstore.RefreshLocalVisitor.synchronizeExistence",
          "source": "RefreshLocalVisitor.java:202"
        },
        {
          "method": "org.eclipse.core.internal.localstore.RefreshLocalVisitor.visit",
          "source": "RefreshLocalVisitor.java:278"
        },
        {
          "method": "org.eclipse.core.internal.localstore.UnifiedTree.accept",
          "source": "UnifiedTree.java:75"
        },
        {
          "method": "org.eclipse.core.internal.localstore.FileSystemResourceManager.refreshResource",
          "source": "FileSystemResourceManager.java:622"
        },
        {
          "method": "org.eclipse.core.internal.localstore.FileSystemResourceManager.refresh",
          "source": "FileSystemResourceManager.java:609"
        },
        {
          "method": "org.eclipse.core.internal.resources.Resource.refreshLocal",
          "source": "Resource.java:1222"
        },
        {
          "method": "org.eclipse.core.internal.refresh.RefreshJob.runInWorkspace",
          "source": "RefreshJob.java:98"
        },
        {
          "method": "org.eclipse.core.internal.resources.InternalWorkspaceJob.run",
          "source": "InternalWorkspaceJob.java:38"
        },
        {
          "method": "org.eclipse.core.internal.jobs.Worker.run",
          "source": "Worker.java:66"
        }
      ],
      "number": 0,
      "commentIndex": 2,
      "bugId": "60165",
      "date": "2004-08-12T19:22:58+02:00",
      "product": "Platform",
      "component": "Resources",
      "severity": "major"
    }
  ],
  "groupId": "60165",
  "bugId": "60165",
  "date": "2004-04-27T20:50:33+02:00",
  "product": "Platform",
  "component": "Resources",
  "severity": "major"
}