{
  "comments": [
    "200404281424\n\nDoing a full build, the progress view (or the modal dialog that seems to use the\nsimilar widgets) is causing SWTExceptions: \"Graphic is disposed\" to happen:\n\nHere is one of the entries I got (and I got several of them if I had the dialog\nor the progress view open).\n\n!ENTRY org.eclipse.ui 4 4 Apr 29, 2004 11:23:40.07\n!MESSAGE Unhandled event loop exception\nUnhandled event loop exception\nReason:\n!ENTRY org.eclipse.ui 4 0 Apr 29, 2004 11:23:40.22\n!MESSAGE Graphic is disposed\n!STACK 0\norg.eclipse.swt.SWTException: Graphic is disposed\n        at org.eclipse.swt.SWT.error(SWT.java:2680)\n        at org.eclipse.swt.SWT.error(SWT.java:2605)\n        at org.eclipse.swt.SWT.error(SWT.java:2576)\n        at org.eclipse.swt.graphics.GC.drawText(GC.java:1363)\n        at org.eclipse.swt.graphics.GC.drawText(GC.java:1325)\n        at org.eclipse.ui.internal.progress.NewProgressViewer$Hyperlink.paint(Ne\nwProgressViewer.java:414)\n        at org.eclipse.ui.internal.progress.NewProgressViewer$Hyperlink.handleEv\nent(NewProgressViewer.java:307)\n        at org.eclipse.swt.widgets.EventTable.sendEvent(EventTable.java:82)\n        at org.eclipse.swt.widgets.Widget.sendEvent(Widget.java:796)\n        at org.eclipse.swt.widgets.Widget.sendEvent(Widget.java:820)\n        at org.eclipse.swt.widgets.Widget.sendEvent(Widget.java:805)\n        at org.eclipse.swt.widgets.Composite.WM_PAINT(Composite.java:795)\n        at org.eclipse.swt.widgets.Control.windowProc(Control.java:3002)\n        at org.eclipse.swt.widgets.Display.windowProc(Display.java:3158)\n        at org.eclipse.swt.internal.win32.OS.DispatchMessageW(Native Method)\n        at org.eclipse.swt.internal.win32.OS.DispatchMessage(OS.java:1459)\n        at org.eclipse.swt.widgets.Display.readAndDispatch(Display.java:2268)\n        at org.eclipse.ui.internal.Workbench.runEventLoop(Workbench.java:1353)\n        at org.eclipse.ui.internal.Workbench.runUI(Workbench.java:1324)\n        at org.eclipse.ui.internal.Workbench.createAndRunWorkbench(Workbench.jav\na:240)\n        at org.eclipse.ui.PlatformUI.createAndRunWorkbench(PlatformUI.java:140)\n        at org.eclipse.ui.internal.ide.IDEApplication.run(IDEApplication.java:90\n)\n        at org.eclipse.core.internal.runtime.PlatformActivator$1.run(PlatformAct\nivator.java:283)\n        at org.eclipse.core.runtime.adaptor.EclipseStarter.run(EclipseStarter.ja\nva:242)\n        at org.eclipse.core.runtime.adaptor.EclipseStarter.run(EclipseStarter.ja\nva:119)\n        at sun.reflect.NativeMethodAccessorImpl.invoke0(Native Method)\n        at sun.reflect.NativeMethodAccessorImpl.invoke(NativeMethodAccessorImpl.\njava:39)\n        at sun.reflect.DelegatingMethodAccessorImpl.invoke(DelegatingMethodAcces\nsorImpl.java:25)\n        at java.lang.reflect.Method.invoke(Method.java:324)\n        at org.eclipse.core.launcher.Main.basicRun(Main.java:269)\n        at org.eclipse.core.launcher.Main.run(Main.java:700)\n        at org.eclipse.core.launcher.Main.main(Main.java:684)",
    "fixed for N20040430"
  ],
  "commentCreationDates": [
    "2004-04-29T17:41:20+02:00",
    "2004-04-30T16:07:05+02:00"
  ],
  "traces": [
    {
      "exceptionType": "org.eclipse.swt.SWTException",
      "message": "Graphic is disposed",
      "elements": [
        {
          "method": "org.eclipse.swt.SWT.error",
          "source": "SWT.java:2680"
        },
        {
          "method": "org.eclipse.swt.SWT.error",
          "source": "SWT.java:2605"
        },
        {
          "method": "org.eclipse.swt.SWT.error",
          "source": "SWT.java:2576"
        },
        {
          "method": "org.eclipse.swt.graphics.GC.drawText",
          "source": "GC.java:1363"
        },
        {
          "method": "org.eclipse.swt.graphics.GC.drawText",
          "source": "GC.java:1325"
        },
        {
          "method": "org.eclipse.ui.internal.progress.NewProgressViewer$Hyperlink.paint",
          "source": "Ne wProgressViewer.java:414"
        },
        {
          "method": "org.eclipse.ui.internal.progress.NewProgressViewer$Hyperlink.handleEvent",
          "source": "NewProgressViewer.java:307"
        },
        {
          "method": "org.eclipse.swt.widgets.EventTable.sendEvent",
          "source": "EventTable.java:82"
        },
        {
          "method": "org.eclipse.swt.widgets.Widget.sendEvent",
          "source": "Widget.java:796"
        },
        {
          "method": "org.eclipse.swt.widgets.Widget.sendEvent",
          "source": "Widget.java:820"
        },
        {
          "method": "org.eclipse.swt.widgets.Widget.sendEvent",
          "source": "Widget.java:805"
        },
        {
          "method": "org.eclipse.swt.widgets.Composite.WM_PAINT",
          "source": "Composite.java:795"
        },
        {
          "method": "org.eclipse.swt.widgets.Control.windowProc",
          "source": "Control.java:3002"
        },
        {
          "method": "org.eclipse.swt.widgets.Display.windowProc",
          "source": "Display.java:3158"
        },
        {
          "method": "org.eclipse.swt.internal.win32.OS.DispatchMessageW",
          "source": "Native Method"
        },
        {
          "method": "org.eclipse.swt.internal.win32.OS.DispatchMessage",
          "source": "OS.java:1459"
        },
        {
          "method": "org.eclipse.swt.widgets.Display.readAndDispatch",
          "source": "Display.java:2268"
        },
        {
          "method": "org.eclipse.ui.internal.Workbench.runEventLoop",
          "source": "Workbench.java:1353"
        },
        {
          "method": "org.eclipse.ui.internal.Workbench.runUI",
          "source": "Workbench.java:1324"
        },
        {
          "method": "org.eclipse.ui.internal.Workbench.createAndRunWorkbench",
          "source": "Workbench.jav a:240"
        },
        {
          "method": "org.eclipse.ui.PlatformUI.createAndRunWorkbench",
          "source": "PlatformUI.java:140"
        },
        {
          "method": "org.eclipse.ui.internal.ide.IDEApplication.run",
          "source": "IDEApplication.java:90 "
        },
        {
          "method": "org.eclipse.core.internal.runtime.PlatformActivator$1.run",
          "source": "PlatformAct ivator.java:283"
        },
        {
          "method": "org.eclipse.core.runtime.adaptor.EclipseStarter.run",
          "source": "EclipseStarter.ja va:242"
        },
        {
          "method": "org.eclipse.core.runtime.adaptor.EclipseStarter.run",
          "source": "EclipseStarter.ja va:119"
        },
        {
          "method": "sun.reflect.NativeMethodAccessorImpl.invoke0",
          "source": "Native Method"
        },
        {
          "method": "sun.reflect.NativeMethodAccessorImpl.invoke",
          "source": "NativeMethodAccessorImpl. java:39"
        },
        {
          "method": "sun.reflect.DelegatingMethodAccessorImpl.invoke",
          "source": "DelegatingMethodAcces sorImpl.java:25"
        },
        {
          "method": "java.lang.reflect.Method.invoke",
          "source": "Method.java:324"
        },
        {
          "method": "org.eclipse.core.launcher.Main.basicRun",
          "source": "Main.java:269"
        },
        {
          "method": "org.eclipse.core.launcher.Main.run",
          "source": "Main.java:700"
        },
        {
          "method": "org.eclipse.core.launcher.Main.main",
          "source": "Main.java:684"
        }
      ],
      "number": 0,
      "commentIndex": 0,
      "bugId": "60444",
      "date": "2004-04-29T17:41:20+02:00",
      "product": "Platform",
      "component": "UI",
      "severity": "normal"
    }
  ],
  "groupId": "60444",
  "bugId": "60444",
  "date": "2004-04-29T17:41:20+02:00",
  "product": "Platform",
  "component": "UI",
  "severity": "normal"
}