{
  "comments": [
    "I20040428 + ZRH plugin-export from 200404029\n\n1. Synchronize view, open a file with a conflict\n2. In the compare editor, double click on a structure compare item\n-\u003e expected: only the selected element gets compared in the compare editors\n3. Got this:\n\norg.eclipse.jface.text.Assert$AssertionFailedException: Assertion failed:\n        at java.lang.Throwable.\u003cinit\u003e(Throwable.java)\n        at java.lang.Throwable.\u003cinit\u003e(Throwable.java)\n        at\norg.eclipse.jface.text.Assert$AssertionFailedException.\u003cinit\u003e(Assert.java:56)\n        at org.eclipse.jface.text.Assert.isTrue(Assert.java:177)\n        at org.eclipse.jface.text.Assert.isTrue(Assert.java)\n        at\norg.eclipse.jface.text.projection.ProjectionMapping.toImageRegion(ProjectionMapping.java)\n        at\norg.eclipse.jface.text.projection.ProjectionMapping.toImageRegion(ProjectionMapping.java)\n        at org.eclipse.jface.text.TextViewer.modelRange2WidgetRange(TextViewer.java)\n        at\norg.eclipse.jface.text.TextViewer.modelStyleRange2WidgetStyleRange(TextViewer.java)\n        at org.eclipse.jface.text.TextViewer.addPresentation(TextViewer.java)\n        at\norg.eclipse.jface.text.TextViewer.changeTextPresentation(TextViewer.java:4109)\n        at\norg.eclipse.jface.text.presentation.PresentationReconciler.applyTextRegionCollection(PresentationReconciler.java:568)\n        at\norg.eclipse.jface.text.presentation.PresentationReconciler.processDamage(PresentationReconciler.java:557)\n        at\norg.eclipse.jface.text.presentation.PresentationReconciler.access$3(PresentationReconciler.java:553)\n        at\norg.eclipse.jface.text.presentation.PresentationReconciler$InternalListener.textChanged(PresentationReconciler.java:222)\n        at\norg.eclipse.jface.text.TextViewer.updateTextListeners(TextViewer.java:2235)\n        at org.eclipse.jface.text.TextViewer.fireRedrawChanged(TextViewer.java:4265)\n        at org.eclipse.jface.text.TextViewer.enabledRedrawing(TextViewer.java:4319)\n        at org.eclipse.jface.text.TextViewer.setRedraw(TextViewer.java:4373)\n        at org.eclipse.jface.text.TextViewer.setVisibleRegion(TextViewer.java:3107)\n        at\norg.eclipse.compare.contentmergeviewer.TextMergeViewer.setDocument(TextMergeViewer.java:1938)\n        at\norg.eclipse.compare.contentmergeviewer.TextMergeViewer.updateContent(TextMergeViewer.java:1632)\n        at\norg.eclipse.compare.contentmergeviewer.ContentMergeViewer.internalRefresh(ContentMergeViewer.java:661)\n        at\norg.eclipse.compare.contentmergeviewer.ContentMergeViewer.inputChanged(ContentMergeViewer.java:558)\n        at org.eclipse.jface.viewers.ContentViewer.setInput(ContentViewer.java:238)\n        at\norg.eclipse.compare.CompareViewerSwitchingPane.setInput(CompareViewerSwitchingPane.java:302)\n        at\norg.eclipse.compare.CompareEditorInput$11.run(CompareEditorInput.java:526)\n        at org.eclipse.swt.custom.BusyIndicator.showWhile(BusyIndicator.java)\n        at org.eclipse.compare.CompareEditorInput.feed1(CompareEditorInput.java:516)\n        at\norg.eclipse.compare.CompareEditorInput.access$1(CompareEditorInput.java:515)\n        at\norg.eclipse.compare.CompareEditorInput$6.open(CompareEditorInput.java:457)\n        at\norg.eclipse.compare.CompareViewerSwitchingPane$1.open(CompareViewerSwitchingPane.java:55)\n        at\norg.eclipse.jface.viewers.StructuredViewer$2.run(StructuredViewer.java:406)\n        at\norg.eclipse.core.internal.runtime.InternalPlatform.run(InternalPlatform.java)\n        at org.eclipse.core.runtime.Platform.run(Platform.java)\n        at\norg.eclipse.jface.viewers.StructuredViewer.fireOpen(StructuredViewer.java:404)\n        at\norg.eclipse.jface.viewers.StructuredViewer.handleOpen(StructuredViewer.java:614)\n        at\norg.eclipse.jface.viewers.StructuredViewer$6.handleOpen(StructuredViewer.java:703)\n        at org.eclipse.jface.util.OpenStrategy.fireOpenEvent(OpenStrategy.java:209)\n        at org.eclipse.jface.util.OpenStrategy.access$2(OpenStrategy.java:204)\n        at org.eclipse.jface.util.OpenStrategy$1.handleEvent(OpenStrategy.java:233)\n        at org.eclipse.swt.widgets.EventTable.sendEvent(EventTable.java)\n        at org.eclipse.swt.widgets.Widget.sendEvent(Widget.java)\n        at org.eclipse.swt.widgets.Display.runDeferredEvents(Display.java)\n        at org.eclipse.swt.widgets.Display.readAndDispatch(Display.java)\n        at org.eclipse.ui.internal.Workbench.runEventLoop(Workbench.java:1353)\n        at org.eclipse.ui.internal.Workbench.runUI(Workbench.java:1324)\n        at\norg.eclipse.ui.internal.Workbench.createAndRunWorkbench(Workbench.java:240)\n        at org.eclipse.ui.PlatformUI.createAndRunWorkbench(PlatformUI.java:140)\n        at org.eclipse.ui.internal.ide.IDEApplication.run(IDEApplication.java:90)\n        at\norg.eclipse.core.internal.runtime.PlatformActivator$1.run(PlatformActivator.java:283)\n        at\norg.eclipse.core.runtime.adaptor.EclipseStarter.run(EclipseStarter.java:240)\n        at\norg.eclipse.core.runtime.adaptor.EclipseStarter.run(EclipseStarter.java:117)\n        at sun.reflect.NativeMethodAccessorImpl.invoke0(Native Method)\n        at\nsun.reflect.NativeMethodAccessorImpl.invoke(NativeMethodAccessorImpl.java:79)\n        at\nsun.reflect.DelegatingMethodAccessorImpl.invoke(DelegatingMethodAccessorImpl.java:41)\n        at java.lang.reflect.Method.invoke(Method.java:386)\n        at org.eclipse.core.launcher.Main.basicRun(Main.java:269)\n        at org.eclipse.core.launcher.Main.run(Main.java:700)\n        at org.eclipse.core.launcher.Main.main(Main.java:684)",
    "\n\n*** This bug has been marked as a duplicate of 55814 ***"
  ],
  "commentCreationDates": [
    "2004-04-30T10:58:14+02:00",
    "2004-04-30T14:38:49+02:00"
  ],
  "traces": [
    {
      "exceptionType": "org.eclipse.jface.text.Assert$AssertionFailedException",
      "message": "Assertion failed:",
      "elements": [
        {
          "method": "java.lang.Throwable.\u003cinit\u003e",
          "source": "Throwable.java"
        },
        {
          "method": "java.lang.Throwable.\u003cinit\u003e",
          "source": "Throwable.java"
        },
        {
          "method": "org.eclipse.jface.text.Assert$AssertionFailedException.\u003cinit\u003e",
          "source": "Assert.java:56"
        },
        {
          "method": "org.eclipse.jface.text.Assert.isTrue",
          "source": "Assert.java:177"
        },
        {
          "method": "org.eclipse.jface.text.Assert.isTrue",
          "source": "Assert.java"
        },
        {
          "method": "org.eclipse.jface.text.projection.ProjectionMapping.toImageRegion",
          "source": "ProjectionMapping.java"
        },
        {
          "method": "org.eclipse.jface.text.projection.ProjectionMapping.toImageRegion",
          "source": "ProjectionMapping.java"
        },
        {
          "method": "org.eclipse.jface.text.TextViewer.modelRange2WidgetRange",
          "source": "TextViewer.java"
        },
        {
          "method": "org.eclipse.jface.text.TextViewer.modelStyleRange2WidgetStyleRange",
          "source": "TextViewer.java"
        },
        {
          "method": "org.eclipse.jface.text.TextViewer.addPresentation",
          "source": "TextViewer.java"
        },
        {
          "method": "org.eclipse.jface.text.TextViewer.changeTextPresentation",
          "source": "TextViewer.java:4109"
        },
        {
          "method": "org.eclipse.jface.text.presentation.PresentationReconciler.applyTextRegionCollection",
          "source": "PresentationReconciler.java:568"
        },
        {
          "method": "org.eclipse.jface.text.presentation.PresentationReconciler.processDamage",
          "source": "PresentationReconciler.java:557"
        },
        {
          "method": "org.eclipse.jface.text.presentation.PresentationReconciler.access$3",
          "source": "PresentationReconciler.java:553"
        },
        {
          "method": "org.eclipse.jface.text.presentation.PresentationReconciler$InternalListener.textChanged",
          "source": "PresentationReconciler.java:222"
        },
        {
          "method": "org.eclipse.jface.text.TextViewer.updateTextListeners",
          "source": "TextViewer.java:2235"
        },
        {
          "method": "org.eclipse.jface.text.TextViewer.fireRedrawChanged",
          "source": "TextViewer.java:4265"
        },
        {
          "method": "org.eclipse.jface.text.TextViewer.enabledRedrawing",
          "source": "TextViewer.java:4319"
        },
        {
          "method": "org.eclipse.jface.text.TextViewer.setRedraw",
          "source": "TextViewer.java:4373"
        },
        {
          "method": "org.eclipse.jface.text.TextViewer.setVisibleRegion",
          "source": "TextViewer.java:3107"
        },
        {
          "method": "org.eclipse.compare.contentmergeviewer.TextMergeViewer.setDocument",
          "source": "TextMergeViewer.java:1938"
        },
        {
          "method": "org.eclipse.compare.contentmergeviewer.TextMergeViewer.updateContent",
          "source": "TextMergeViewer.java:1632"
        },
        {
          "method": "org.eclipse.compare.contentmergeviewer.ContentMergeViewer.internalRefresh",
          "source": "ContentMergeViewer.java:661"
        },
        {
          "method": "org.eclipse.compare.contentmergeviewer.ContentMergeViewer.inputChanged",
          "source": "ContentMergeViewer.java:558"
        },
        {
          "method": "org.eclipse.jface.viewers.ContentViewer.setInput",
          "source": "ContentViewer.java:238"
        },
        {
          "method": "org.eclipse.compare.CompareViewerSwitchingPane.setInput",
          "source": "CompareViewerSwitchingPane.java:302"
        },
        {
          "method": "org.eclipse.compare.CompareEditorInput$11.run",
          "source": "CompareEditorInput.java:526"
        },
        {
          "method": "org.eclipse.swt.custom.BusyIndicator.showWhile",
          "source": "BusyIndicator.java"
        },
        {
          "method": "org.eclipse.compare.CompareEditorInput.feed1",
          "source": "CompareEditorInput.java:516"
        },
        {
          "method": "org.eclipse.compare.CompareEditorInput.access$1",
          "source": "CompareEditorInput.java:515"
        },
        {
          "method": "org.eclipse.compare.CompareEditorInput$6.open",
          "source": "CompareEditorInput.java:457"
        },
        {
          "method": "org.eclipse.compare.CompareViewerSwitchingPane$1.open",
          "source": "CompareViewerSwitchingPane.java:55"
        },
        {
          "method": "org.eclipse.jface.viewers.StructuredViewer$2.run",
          "source": "StructuredViewer.java:406"
        },
        {
          "method": "org.eclipse.core.internal.runtime.InternalPlatform.run",
          "source": "InternalPlatform.java"
        },
        {
          "method": "org.eclipse.core.runtime.Platform.run",
          "source": "Platform.java"
        },
        {
          "method": "org.eclipse.jface.viewers.StructuredViewer.fireOpen",
          "source": "StructuredViewer.java:404"
        },
        {
          "method": "org.eclipse.jface.viewers.StructuredViewer.handleOpen",
          "source": "StructuredViewer.java:614"
        },
        {
          "method": "org.eclipse.jface.viewers.StructuredViewer$6.handleOpen",
          "source": "StructuredViewer.java:703"
        },
        {
          "method": "org.eclipse.jface.util.OpenStrategy.fireOpenEvent",
          "source": "OpenStrategy.java:209"
        },
        {
          "method": "org.eclipse.jface.util.OpenStrategy.access$2",
          "source": "OpenStrategy.java:204"
        },
        {
          "method": "org.eclipse.jface.util.OpenStrategy$1.handleEvent",
          "source": "OpenStrategy.java:233"
        },
        {
          "method": "org.eclipse.swt.widgets.EventTable.sendEvent",
          "source": "EventTable.java"
        },
        {
          "method": "org.eclipse.swt.widgets.Widget.sendEvent",
          "source": "Widget.java"
        },
        {
          "method": "org.eclipse.swt.widgets.Display.runDeferredEvents",
          "source": "Display.java"
        },
        {
          "method": "org.eclipse.swt.widgets.Display.readAndDispatch",
          "source": "Display.java"
        },
        {
          "method": "org.eclipse.ui.internal.Workbench.runEventLoop",
          "source": "Workbench.java:1353"
        },
        {
          "method": "org.eclipse.ui.internal.Workbench.runUI",
          "source": "Workbench.java:1324"
        },
        {
          "method": "org.eclipse.ui.internal.Workbench.createAndRunWorkbench",
          "source": "Workbench.java:240"
        },
        {
          "method": "org.eclipse.ui.PlatformUI.createAndRunWorkbench",
          "source": "PlatformUI.java:140"
        },
        {
          "method": "org.eclipse.ui.internal.ide.IDEApplication.run",
          "source": "IDEApplication.java:90"
        },
        {
          "method": "org.eclipse.core.internal.runtime.PlatformActivator$1.run",
          "source": "PlatformActivator.java:283"
        },
        {
          "method": "org.eclipse.core.runtime.adaptor.EclipseStarter.run",
          "source": "EclipseStarter.java:240"
        },
        {
          "method": "org.eclipse.core.runtime.adaptor.EclipseStarter.run",
          "source": "EclipseStarter.java:117"
        },
        {
          "method": "sun.reflect.NativeMethodAccessorImpl.invoke0",
          "source": "Native Method"
        },
        {
          "method": "sun.reflect.NativeMethodAccessorImpl.invoke",
          "source": "NativeMethodAccessorImpl.java:79"
        },
        {
          "method": "sun.reflect.DelegatingMethodAccessorImpl.invoke",
          "source": "DelegatingMethodAccessorImpl.java:41"
        },
        {
          "method": "java.lang.reflect.Method.invoke",
          "source": "Method.java:386"
        },
        {
          "method": "org.eclipse.core.launcher.Main.basicRun",
          "source": "Main.java:269"
        },
        {
          "method": "org.eclipse.core.launcher.Main.run",
          "source": "Main.java:700"
        },
        {
          "method": "org.eclipse.core.launcher.Main.main",
          "source": "Main.java:684"
        }
      ],
      "number": 0,
      "commentIndex": 0,
      "bugId": "60541",
      "duplicateId": "55814",
      "date": "2004-04-30T10:58:14+02:00",
      "product": "Platform",
      "component": "Text",
      "severity": "normal"
    }
  ],
  "groupId": "55814",
  "bugId": "60541",
  "duplicateId": "55814",
  "date": "2004-04-30T10:58:14+02:00",
  "product": "Platform",
  "component": "Text",
  "severity": "normal"
}