{
  "comments": [
    "build i0427-0800.\n\nGot this in my console. It shouldn\u0027t happen. Logging this bug report to keep a\nrecord....\n\n!ENTRY org.eclipse.core.runtime 4 2 Apr 30, 2004 16:13:40.449\n!MESSAGE Problems occurred when invoking code from plug-in: \"org.eclipse.core.ru\nntime\".\n!STACK 0\njava.lang.ClassCastException: org.eclipse.core.internal.resources.ResourceInfo\n        at org.eclipse.core.internal.resources.Project.internalGetDescription(Pr\noject.java:577)\n        at org.eclipse.core.internal.localstore.FileSystemResourceManager.locati\nonFor(FileSystemResourceManager.java:402)\n        at org.eclipse.core.internal.resources.Resource.getLocation(Resource.jav\na:873)\n        at org.eclipse.team.internal.ccvs.ui.CVSLightweightDecorator.decorateTex\ntLabel(CVSLightweightDecorator.java:257)\n        at org.eclipse.team.internal.ccvs.ui.CVSLightweightDecorator.decorate(CV\nSLightweightDecorator.java:235)\n        at org.eclipse.ui.internal.decorators.LightweightDecoratorDefinition.dec\norate(LightweightDecoratorDefinition.java:155)\n        at org.eclipse.ui.internal.decorators.LightweightDecoratorManager$Lightw\neightRunnable.run(LightweightDecoratorManager.java:60)\n        at org.eclipse.core.internal.runtime.InternalPlatform.run(InternalPlatfo\nrm.java:599)\n        at org.eclipse.core.runtime.Platform.run(Platform.java:543)\n        at org.eclipse.ui.internal.decorators.LightweightDecoratorManager.decora\nte(LightweightDecoratorManager.java:258)\n        at org.eclipse.ui.internal.decorators.LightweightDecoratorManager.getDec\norations(LightweightDecoratorManager.java:241)\n        at org.eclipse.ui.internal.decorators.DecorationScheduler$1.run(Decorati\nonScheduler.java:262)\n        at org.eclipse.core.internal.jobs.Worker.run(Worker.java:66)\n!ENTRY org.eclipse.ui 4 4 Apr 30, 2004 16:13:40.549\n!MESSAGE Exception in Decorator\nException in Decorator\nReason:\n!ENTRY org.eclipse.ui 4 4 Apr 30, 2004 16:13:40.559\n!MESSAGE org.eclipse.core.internal.resources.ResourceInfo\n!STACK 0\njava.lang.ClassCastException: org.eclipse.core.internal.resources.ResourceInfo\n        at org.eclipse.core.internal.resources.Project.internalGetDescription(Pr\noject.java:577)\n        at org.eclipse.core.internal.localstore.FileSystemResourceManager.locati\nonFor(FileSystemResourceManager.java:402)\n        at org.eclipse.core.internal.resources.Resource.getLocation(Resource.jav\na:873)\n        at org.eclipse.team.internal.ccvs.ui.CVSLightweightDecorator.decorateTex\ntLabel(CVSLightweightDecorator.java:257)\n        at org.eclipse.team.internal.ccvs.ui.CVSLightweightDecorator.decorate(CV\nSLightweightDecorator.java:235)\n        at org.eclipse.ui.internal.decorators.LightweightDecoratorDefinition.dec\norate(LightweightDecoratorDefinition.java:155)\n        at org.eclipse.ui.internal.decorators.LightweightDecoratorManager$Lightw\neightRunnable.run(LightweightDecoratorManager.java:60)\n        at org.eclipse.core.internal.runtime.InternalPlatform.run(InternalPlatfo\nrm.java:599)\n        at org.eclipse.core.runtime.Platform.run(Platform.java:543)\n        at org.eclipse.ui.internal.decorators.LightweightDecoratorManager.decora\nte(LightweightDecoratorManager.java:258)\n        at org.eclipse.ui.internal.decorators.LightweightDecoratorManager.getDec\norations(LightweightDecoratorManager.java:241)\n        at org.eclipse.ui.internal.decorators.DecorationScheduler$1.run(Decorati\nonScheduler.java:262)\n        at org.eclipse.core.internal.jobs.Worker.run(Worker.java:66)\norg.eclipse.core.internal.resources.ResourceInfo",
    "I believe it is a duplicate of bug 27844. ",
    "*** Bug 67430 has been marked as a duplicate of this bug. ***",
    "*** Bug 68536 has been marked as a duplicate of this bug. ***",
    "Closing - this hasn\u0027t been seen since 3.0 and a code review did not find the\ncause.  The code has changed since it was last reported so it\u0027s likely the\nproblem has gone away.  Will reopen if it is seen again."
  ],
  "commentCreationDates": [
    "2004-04-30T23:02:26+02:00",
    "2004-04-30T23:18:44+02:00",
    "2004-06-16T15:31:56+02:00",
    "2004-06-24T21:40:21+02:00",
    "2005-11-18T22:04:44+01:00"
  ],
  "traces": [
    {
      "exceptionType": "java.lang.ClassCastException",
      "message": "org.eclipse.core.internal.resources.ResourceInfo",
      "elements": [
        {
          "method": "org.eclipse.core.internal.resources.Project.internalGetDescription",
          "source": "Pr oject.java:577"
        },
        {
          "method": "org.eclipse.core.internal.localstore.FileSystemResourceManager.locationFor",
          "source": "FileSystemResourceManager.java:402"
        },
        {
          "method": "org.eclipse.core.internal.resources.Resource.getLocation",
          "source": "Resource.jav a:873"
        },
        {
          "method": "org.eclipse.team.internal.ccvs.ui.CVSLightweightDecorator.decorateTextLabel",
          "source": "CVSLightweightDecorator.java:257"
        },
        {
          "method": "org.eclipse.team.internal.ccvs.ui.CVSLightweightDecorator.decorate",
          "source": "CV SLightweightDecorator.java:235"
        },
        {
          "method": "org.eclipse.ui.internal.decorators.LightweightDecoratorDefinition.decorate",
          "source": "LightweightDecoratorDefinition.java:155"
        },
        {
          "method": "org.eclipse.ui.internal.decorators.LightweightDecoratorManager$LightweightRunnable.run",
          "source": "LightweightDecoratorManager.java:60"
        },
        {
          "method": "org.eclipse.core.internal.runtime.InternalPlatform.run",
          "source": "InternalPlatfo rm.java:599"
        },
        {
          "method": "org.eclipse.core.runtime.Platform.run",
          "source": "Platform.java:543"
        },
        {
          "method": "org.eclipse.ui.internal.decorators.LightweightDecoratorManager.decorate",
          "source": "LightweightDecoratorManager.java:258"
        },
        {
          "method": "org.eclipse.ui.internal.decorators.LightweightDecoratorManager.getDecorations",
          "source": "LightweightDecoratorManager.java:241"
        },
        {
          "method": "org.eclipse.ui.internal.decorators.DecorationScheduler$1.run",
          "source": "Decorati onScheduler.java:262"
        },
        {
          "method": "org.eclipse.core.internal.jobs.Worker.run",
          "source": "Worker.java:66"
        }
      ],
      "number": 0,
      "commentIndex": 0,
      "bugId": "60649",
      "date": "2004-04-30T23:02:26+02:00",
      "product": "Platform",
      "component": "Resources",
      "severity": "normal"
    },
    {
      "exceptionType": "java.lang.ClassCastException",
      "message": "org.eclipse.core.internal.resources.ResourceInfo",
      "elements": [
        {
          "method": "org.eclipse.core.internal.resources.Project.internalGetDescription",
          "source": "Pr oject.java:577"
        },
        {
          "method": "org.eclipse.core.internal.localstore.FileSystemResourceManager.locationFor",
          "source": "FileSystemResourceManager.java:402"
        },
        {
          "method": "org.eclipse.core.internal.resources.Resource.getLocation",
          "source": "Resource.jav a:873"
        },
        {
          "method": "org.eclipse.team.internal.ccvs.ui.CVSLightweightDecorator.decorateTextLabel",
          "source": "CVSLightweightDecorator.java:257"
        },
        {
          "method": "org.eclipse.team.internal.ccvs.ui.CVSLightweightDecorator.decorate",
          "source": "CV SLightweightDecorator.java:235"
        },
        {
          "method": "org.eclipse.ui.internal.decorators.LightweightDecoratorDefinition.decorate",
          "source": "LightweightDecoratorDefinition.java:155"
        },
        {
          "method": "org.eclipse.ui.internal.decorators.LightweightDecoratorManager$LightweightRunnable.run",
          "source": "LightweightDecoratorManager.java:60"
        },
        {
          "method": "org.eclipse.core.internal.runtime.InternalPlatform.run",
          "source": "InternalPlatfo rm.java:599"
        },
        {
          "method": "org.eclipse.core.runtime.Platform.run",
          "source": "Platform.java:543"
        },
        {
          "method": "org.eclipse.ui.internal.decorators.LightweightDecoratorManager.decorate",
          "source": "LightweightDecoratorManager.java:258"
        },
        {
          "method": "org.eclipse.ui.internal.decorators.LightweightDecoratorManager.getDecorations",
          "source": "LightweightDecoratorManager.java:241"
        },
        {
          "method": "org.eclipse.ui.internal.decorators.DecorationScheduler$1.run",
          "source": "Decorati onScheduler.java:262"
        },
        {
          "method": "org.eclipse.core.internal.jobs.Worker.run",
          "source": "Worker.java:66"
        }
      ],
      "number": 1,
      "commentIndex": 0,
      "bugId": "60649",
      "date": "2004-04-30T23:02:26+02:00",
      "product": "Platform",
      "component": "Resources",
      "severity": "normal"
    }
  ],
  "groupId": "60649",
  "bugId": "60649",
  "date": "2004-04-30T23:02:26+02:00",
  "product": "Platform",
  "component": "Resources",
  "severity": "normal"
}