{
  "comments": [
    "I20040504\n\nBootLoader constants: OS\u003dlinux, ARCH\u003damd64, WS\u003dgtk, NL\u003den_US\n!ENTRY org.eclipse.osgi May 04, 2004 10:25:30.557\n!MESSAGE Application error\n!STACK 1\njava.lang.NullPointerException\n        at org.eclipse.jface.action.StatusLine.handleDispose(StatusLine.java:314)\n        at org.eclipse.jface.action.StatusLine$1.widgetDisposed(StatusLine.java:197)\n        at org.eclipse.swt.widgets.TypedListener.handleEvent(TypedListener.java:100)\n        at org.eclipse.swt.widgets.EventTable.sendEvent(EventTable.java:82)\n        at org.eclipse.swt.widgets.Widget.sendEvent(Widget.java:939)\n        at org.eclipse.swt.widgets.Widget.sendEvent(Widget.java:963)\n        at org.eclipse.swt.widgets.Widget.sendEvent(Widget.java:944)\n        at org.eclipse.swt.widgets.Widget.releaseWidget(Widget.java:850)\n        at org.eclipse.swt.widgets.Control.releaseWidget(Control.java:2126)\n        at org.eclipse.swt.widgets.Scrollable.releaseWidget(Scrollable.java:255)\n       at org.eclipse.swt.widgets.Composite.releaseWidget(Composite.java:652)\n        at org.eclipse.swt.widgets.Widget.releaseResources(Widget.java:845)\n        at org.eclipse.swt.widgets.Composite.releaseChildren(Composite.java:646)\n       at org.eclipse.swt.widgets.Composite.releaseWidget(Composite.java:651)\n        at org.eclipse.swt.widgets.Canvas.releaseWidget(Canvas.java:132)\n        at org.eclipse.swt.widgets.Decorations.releaseWidget(Decorations.java:435)\n        at org.eclipse.swt.widgets.Shell.releaseWidget(Shell.java:1197)\n        at org.eclipse.swt.widgets.Widget.dispose(Widget.java:368)\n        at org.eclipse.swt.widgets.Shell.dispose(Shell.java:1139)\n        at org.eclipse.swt.widgets.Display.release(Display.java:1831)\n        at org.eclipse.swt.graphics.Device.dispose(Device.java:174)\n        at org.eclipse.ui.internal.ide.IDEApplication.run(IDEApplication.java:99)\n        at\norg.eclipse.core.internal.runtime.PlatformActivator$1.run(PlatformActivator.java:283)\n        at\norg.eclipse.core.runtime.adaptor.EclipseStarter.run(EclipseStarter.java:242)\n        at\norg.eclipse.core.runtime.adaptor.EclipseStarter.run(EclipseStarter.java:119)\n        at sun.reflect.NativeMethodAccessorImpl.invoke0(Native Method)\n        at\nsun.reflect.NativeMethodAccessorImpl.invoke(NativeMethodAccessorImpl.java:84)\n        at\nsun.reflect.NativeMethodAccessorImpl.invoke(NativeMethodAccessorImpl.java:57)\n        at\nsun.reflect.DelegatingMethodAccessorImpl.invoke(DelegatingMethodAccessorImpl.java:59)\n        at java.lang.reflect.Method.invoke(Method.java:390)\n        at org.eclipse.core.launcher.Main.basicRun(Main.java:269)\n        at org.eclipse.core.launcher.Main.run(Main.java:700)\n        at org.eclipse.core.launcher.Main.main(Main.java:684)",
    "N20040429 is OK. So is last week\u0027s integration build I20040428.\nThe bug first appeared in N20040430.",
    "fixed in head, v\u003e20040504\n"
  ],
  "commentCreationDates": [
    "2004-05-04T16:35:15+02:00",
    "2004-05-04T17:21:24+02:00",
    "2004-05-04T21:09:10+02:00"
  ],
  "traces": [
    {
      "exceptionType": "java.lang.NullPointerException",
      "elements": [
        {
          "method": "org.eclipse.jface.action.StatusLine.handleDispose",
          "source": "StatusLine.java:314"
        },
        {
          "method": "org.eclipse.jface.action.StatusLine$1.widgetDisposed",
          "source": "StatusLine.java:197"
        },
        {
          "method": "org.eclipse.swt.widgets.TypedListener.handleEvent",
          "source": "TypedListener.java:100"
        },
        {
          "method": "org.eclipse.swt.widgets.EventTable.sendEvent",
          "source": "EventTable.java:82"
        },
        {
          "method": "org.eclipse.swt.widgets.Widget.sendEvent",
          "source": "Widget.java:939"
        },
        {
          "method": "org.eclipse.swt.widgets.Widget.sendEvent",
          "source": "Widget.java:963"
        },
        {
          "method": "org.eclipse.swt.widgets.Widget.sendEvent",
          "source": "Widget.java:944"
        },
        {
          "method": "org.eclipse.swt.widgets.Widget.releaseWidget",
          "source": "Widget.java:850"
        },
        {
          "method": "org.eclipse.swt.widgets.Control.releaseWidget",
          "source": "Control.java:2126"
        },
        {
          "method": "org.eclipse.swt.widgets.Scrollable.releaseWidget",
          "source": "Scrollable.java:255"
        },
        {
          "method": "org.eclipse.swt.widgets.Composite.releaseWidget",
          "source": "Composite.java:652"
        },
        {
          "method": "org.eclipse.swt.widgets.Widget.releaseResources",
          "source": "Widget.java:845"
        },
        {
          "method": "org.eclipse.swt.widgets.Composite.releaseChildren",
          "source": "Composite.java:646"
        },
        {
          "method": "org.eclipse.swt.widgets.Composite.releaseWidget",
          "source": "Composite.java:651"
        },
        {
          "method": "org.eclipse.swt.widgets.Canvas.releaseWidget",
          "source": "Canvas.java:132"
        },
        {
          "method": "org.eclipse.swt.widgets.Decorations.releaseWidget",
          "source": "Decorations.java:435"
        },
        {
          "method": "org.eclipse.swt.widgets.Shell.releaseWidget",
          "source": "Shell.java:1197"
        },
        {
          "method": "org.eclipse.swt.widgets.Widget.dispose",
          "source": "Widget.java:368"
        },
        {
          "method": "org.eclipse.swt.widgets.Shell.dispose",
          "source": "Shell.java:1139"
        },
        {
          "method": "org.eclipse.swt.widgets.Display.release",
          "source": "Display.java:1831"
        },
        {
          "method": "org.eclipse.swt.graphics.Device.dispose",
          "source": "Device.java:174"
        },
        {
          "method": "org.eclipse.ui.internal.ide.IDEApplication.run",
          "source": "IDEApplication.java:99"
        },
        {
          "method": "org.eclipse.core.internal.runtime.PlatformActivator$1.run",
          "source": "PlatformActivator.java:283"
        },
        {
          "method": "org.eclipse.core.runtime.adaptor.EclipseStarter.run",
          "source": "EclipseStarter.java:242"
        },
        {
          "method": "org.eclipse.core.runtime.adaptor.EclipseStarter.run",
          "source": "EclipseStarter.java:119"
        },
        {
          "method": "sun.reflect.NativeMethodAccessorImpl.invoke0",
          "source": "Native Method"
        },
        {
          "method": "sun.reflect.NativeMethodAccessorImpl.invoke",
          "source": "NativeMethodAccessorImpl.java:84"
        },
        {
          "method": "sun.reflect.NativeMethodAccessorImpl.invoke",
          "source": "NativeMethodAccessorImpl.java:57"
        },
        {
          "method": "sun.reflect.DelegatingMethodAccessorImpl.invoke",
          "source": "DelegatingMethodAccessorImpl.java:59"
        },
        {
          "method": "java.lang.reflect.Method.invoke",
          "source": "Method.java:390"
        },
        {
          "method": "org.eclipse.core.launcher.Main.basicRun",
          "source": "Main.java:269"
        },
        {
          "method": "org.eclipse.core.launcher.Main.run",
          "source": "Main.java:700"
        },
        {
          "method": "org.eclipse.core.launcher.Main.main",
          "source": "Main.java:684"
        }
      ],
      "number": 0,
      "commentIndex": 0,
      "bugId": "60893",
      "date": "2004-05-04T16:35:15+02:00",
      "product": "Platform",
      "component": "SWT",
      "severity": "normal"
    }
  ],
  "groupId": "60893",
  "bugId": "60893",
  "date": "2004-05-04T16:35:15+02:00",
  "product": "Platform",
  "component": "SWT",
  "severity": "normal"
}