{
  "comments": [
    "build i0505-0200\n\nI got the following exceptions in my console when doing a scheduled synchronize\nwhen I first started this new build.\n\nI\u0027m not sure if the fragment project was sucessfully refreshed or not. Other\nprojects on that server (ottcvs1) seemed to complete ok. (although I don\u0027t have\nany incoming changes so I don\u0027t know for sure)\n\n!SESSION May 05, 2004 08:16:29.447 ---------------------------------------\n------\njava.version\u003d1.4.2\njava.vendor\u003dSun Microsystems Inc.\nBootLoader constants: OS\u003dwin32, ARCH\u003dx86, WS\u003dwin32, NL\u003den_US\nCommand-line arguments: -showlocation\n!ENTRY org.eclipse.team.core 4 -6 May 05, 2004 08:16:29.447\n!MESSAGE CVS Workspace\n!SUBENTRY 1 org.eclipse.team.core 4 0 May 05, 2004 08:16:29.457\n!MESSAGE An error occurred refreshing /org.eclipse.core.resources.spysupport: Au\nthentication error: com.jcraft.jsch.JSchException: Auth fail\n!STACK 1\norg.eclipse.team.internal.ccvs.core.connection.CVSAuthenticationException: Authe\nntication error: com.jcraft.jsch.JSchException: Auth fail\n        at org.eclipse.team.internal.ccvs.ssh2.CVSSSH2ServerConnection.open(CVSS\nSH2ServerConnection.java:133)\n        at org.eclipse.team.internal.ccvs.core.connection.Connection.open(Connec\ntion.java:127)\n        at org.eclipse.team.internal.ccvs.core.connection.CVSRepositoryLocation.\ncreateConnection(CVSRepositoryLocation.java:568)\n        at org.eclipse.team.internal.ccvs.core.connection.CVSRepositoryLocation.\nopenConnection(CVSRepositoryLocation.java:819)\n        at org.eclipse.team.internal.ccvs.core.client.Session.open(Session.java:\n142)\n        at org.eclipse.team.internal.ccvs.core.resources.RemoteFolderTreeBuilder\n.fetchDelta(RemoteFolderTreeBuilder.java:219)\n        at org.eclipse.team.internal.ccvs.core.resources.RemoteFolderTreeBuilder\n.buildTree(RemoteFolderTreeBuilder.java:187)\n        at org.eclipse.team.internal.ccvs.core.resources.RemoteFolderTreeBuilder\n.buildRemoteTree(RemoteFolderTreeBuilder.java:159)\n        at org.eclipse.team.internal.ccvs.core.resources.CVSWorkspaceRoot.getRem\noteTree(CVSWorkspaceRoot.java:230)\n        at org.eclipse.team.internal.ccvs.core.syncinfo.CVSResourceVariantTree.f\netchVariant(CVSResourceVariantTree.java:95)\n        at org.eclipse.team.core.variants.AbstractResourceVariantTree.refresh(Ab\nstractResourceVariantTree.java:107)\n        at org.eclipse.team.core.variants.AbstractResourceVariantTree.refresh(Ab\nstractResourceVariantTree.java:67)\n        at org.eclipse.team.core.variants.ResourceVariantTreeSubscriber.refresh(\nResourceVariantTreeSubscriber.java:157)\n        at org.eclipse.team.core.variants.ResourceVariantTreeSubscriber.refresh(\nResourceVariantTreeSubscriber.java:123)\n        at org.eclipse.team.internal.ui.synchronize.RefreshSubscriberJob.runInWo\nrkspace(RefreshSubscriberJob.java:207)\n        at org.eclipse.core.internal.resources.InternalWorkspaceJob.run(Internal\nWorkspaceJob.java:38)\n        at org.eclipse.core.internal.jobs.Worker.run(Worker.java:66)\n!SUBENTRY 2 org.eclipse.team.cvs.core 4 2 May 05, 2004 08:16:29.467\n!MESSAGE Authentication error: com.jcraft.jsch.JSchException: Auth fail",
    "\n\n*** This bug has been marked as a duplicate of 60104 ***"
  ],
  "commentCreationDates": [
    "2004-05-05T15:11:59+02:00",
    "2004-05-05T16:55:53+02:00"
  ],
  "traces": [
    {
      "exceptionType": "com.jcraft.jsch.JSchException",
      "message": "Auth fail",
      "elements": [
        {
          "method": "org.eclipse.team.internal.ccvs.ssh2.CVSSSH2ServerConnection.open",
          "source": "CVSS SH2ServerConnection.java:133"
        },
        {
          "method": "org.eclipse.team.internal.ccvs.core.connection.Connection.open",
          "source": "Connec tion.java:127"
        },
        {
          "method": "org.eclipse.team.internal.ccvs.core.connection.CVSRepositoryLocation.createConnection",
          "source": "CVSRepositoryLocation.java:568"
        },
        {
          "method": "org.eclipse.team.internal.ccvs.core.connection.CVSRepositoryLocation.openConnection",
          "source": "CVSRepositoryLocation.java:819"
        },
        {
          "method": "org.eclipse.team.internal.ccvs.core.client.Session.open",
          "source": "Session.java: 142"
        },
        {
          "method": "org.eclipse.team.internal.ccvs.core.resources.RemoteFolderTreeBuilder.fetchDelta",
          "source": "RemoteFolderTreeBuilder.java:219"
        },
        {
          "method": "org.eclipse.team.internal.ccvs.core.resources.RemoteFolderTreeBuilder.buildTree",
          "source": "RemoteFolderTreeBuilder.java:187"
        },
        {
          "method": "org.eclipse.team.internal.ccvs.core.resources.RemoteFolderTreeBuilder.buildRemoteTree",
          "source": "RemoteFolderTreeBuilder.java:159"
        },
        {
          "method": "org.eclipse.team.internal.ccvs.core.resources.CVSWorkspaceRoot.getRemoteTree",
          "source": "CVSWorkspaceRoot.java:230"
        },
        {
          "method": "org.eclipse.team.internal.ccvs.core.syncinfo.CVSResourceVariantTree.fetchVariant",
          "source": "CVSResourceVariantTree.java:95"
        },
        {
          "method": "org.eclipse.team.core.variants.AbstractResourceVariantTree.refresh",
          "source": "Ab stractResourceVariantTree.java:107"
        },
        {
          "method": "org.eclipse.team.core.variants.AbstractResourceVariantTree.refresh",
          "source": "Ab stractResourceVariantTree.java:67"
        },
        {
          "method": "org.eclipse.team.core.variants.ResourceVariantTreeSubscriber.refresh",
          "source": " ResourceVariantTreeSubscriber.java:157"
        },
        {
          "method": "org.eclipse.team.core.variants.ResourceVariantTreeSubscriber.refresh",
          "source": " ResourceVariantTreeSubscriber.java:123"
        },
        {
          "method": "org.eclipse.team.internal.ui.synchronize.RefreshSubscriberJob.runInWorkspace",
          "source": "RefreshSubscriberJob.java:207"
        },
        {
          "method": "org.eclipse.core.internal.resources.InternalWorkspaceJob.run",
          "source": "Internal WorkspaceJob.java:38"
        },
        {
          "method": "org.eclipse.core.internal.jobs.Worker.run",
          "source": "Worker.java:66"
        }
      ],
      "number": 0,
      "commentIndex": 0,
      "bugId": "61037",
      "duplicateId": "60104",
      "date": "2004-05-05T15:11:59+02:00",
      "product": "Platform",
      "component": "CVS",
      "severity": "normal"
    }
  ],
  "groupId": "60104",
  "bugId": "61037",
  "duplicateId": "60104",
  "date": "2004-05-05T15:11:59+02:00",
  "product": "Platform",
  "component": "CVS",
  "severity": "normal"
}