{
  "comments": [
    "build I20040427\n\nOK, this is a hard one to explain.\n- I set a breakpoint on MenuItem.setText\n- reactivated my target\n- the breakpoint was hit immediately\n- made it a conditional breakpoint with condition:\n  \"\".equals(string)\n- resumed\n- the workbench resumed (slowly -- the overhead for conditional breakpoints\nseems high)\n- popped up the context menu in a view\n- breakpoint was not hit\n- went back and forth a few times between host and target\n- breakpoint was not hit, but it was really slowing done the target (it updates\nmenus in response to window activation and deactivation)\n- double-clicked on breakpoint icon to remove it while the target was consuming CPU\n- the breakpoint was hit, but the Debug view did not show the stack\n- selecting the main thread showed Resume as enabled\n- closed and reopened the Debug view\n- it showed that the breakpoint had indeed been hit\n- the string argument was non-empty (\"Ex\u0026tract Interface...\") so the breakpoint\nshould not have been hit\n\nSo there seems to be two problems here:\n1. It seems like Debug removes the condition before removing the breakpoint, so\nit\u0027s possible for it to get hit in the interim.\n2. When this happens, the Debug view does not update properly.\n\n\nI also saw a few of these in my log:\norg.eclipse.debug.core.DebugException: Breakpoint does not have an associated\nmarker.\n\tat org.eclipse.debug.core.model.Breakpoint.ensureMarker(Breakpoint.java:264)\n\tat\norg.eclipse.jdt.internal.debug.core.breakpoints.JavaBreakpoint.getSuspendPolicy(JavaBreakpoint.java:859)\n\tat\norg.eclipse.jdt.internal.debug.core.model.JDIThread.handleSuspendForBreakpoint(JDIThread.java:1040)\n\tat\norg.eclipse.jdt.internal.debug.core.breakpoints.JavaBreakpoint.suspend(JavaBreakpoint.java:308)\n\tat\norg.eclipse.jdt.internal.debug.core.breakpoints.JavaLineBreakpoint.suspendForEvent(JavaLineBreakpoint.java:396)\n\tat\norg.eclipse.jdt.internal.debug.core.breakpoints.JavaLineBreakpoint$EvaluationListener.evaluationComplete(JavaLineBreakpoint.java:556)\n\tat\norg.eclipse.jdt.internal.debug.eval.ast.engine.ASTEvaluationEngine$EvalRunnable.evaluationFinished(ASTEvaluationEngine.java:381)\n\tat\norg.eclipse.jdt.internal.debug.eval.ast.engine.ASTEvaluationEngine$EvalRunnable.run(ASTEvaluationEngine.java:376)\n\tat\norg.eclipse.jdt.internal.debug.core.model.JDIThread$ThreadJob.run(JDIThread.java:2508)\n\tat org.eclipse.core.internal.jobs.Worker.run(Worker.java:66)",
    "Deferred"
  ],
  "commentCreationDates": [
    "2004-05-05T17:37:39+02:00",
    "2004-05-27T23:36:58+02:00"
  ],
  "traces": [
    {
      "exceptionType": "org.eclipse.debug.core.DebugException",
      "message": "Breakpoint does not have an associated marker.",
      "elements": [
        {
          "method": "org.eclipse.debug.core.model.Breakpoint.ensureMarker",
          "source": "Breakpoint.java:264"
        },
        {
          "method": "org.eclipse.jdt.internal.debug.core.breakpoints.JavaBreakpoint.getSuspendPolicy",
          "source": "JavaBreakpoint.java:859"
        },
        {
          "method": "org.eclipse.jdt.internal.debug.core.model.JDIThread.handleSuspendForBreakpoint",
          "source": "JDIThread.java:1040"
        },
        {
          "method": "org.eclipse.jdt.internal.debug.core.breakpoints.JavaBreakpoint.suspend",
          "source": "JavaBreakpoint.java:308"
        },
        {
          "method": "org.eclipse.jdt.internal.debug.core.breakpoints.JavaLineBreakpoint.suspendForEvent",
          "source": "JavaLineBreakpoint.java:396"
        },
        {
          "method": "org.eclipse.jdt.internal.debug.core.breakpoints.JavaLineBreakpoint$EvaluationListener.evaluationComplete",
          "source": "JavaLineBreakpoint.java:556"
        },
        {
          "method": "org.eclipse.jdt.internal.debug.eval.ast.engine.ASTEvaluationEngine$EvalRunnable.evaluationFinished",
          "source": "ASTEvaluationEngine.java:381"
        },
        {
          "method": "org.eclipse.jdt.internal.debug.eval.ast.engine.ASTEvaluationEngine$EvalRunnable.run",
          "source": "ASTEvaluationEngine.java:376"
        },
        {
          "method": "org.eclipse.jdt.internal.debug.core.model.JDIThread$ThreadJob.run",
          "source": "JDIThread.java:2508"
        },
        {
          "method": "org.eclipse.core.internal.jobs.Worker.run",
          "source": "Worker.java:66"
        }
      ],
      "number": 0,
      "commentIndex": 0,
      "bugId": "61071",
      "date": "2004-05-05T17:37:39+02:00",
      "product": "JDT",
      "component": "Debug",
      "severity": "normal"
    }
  ],
  "groupId": "61071",
  "bugId": "61071",
  "date": "2004-05-05T17:37:39+02:00",
  "product": "JDT",
  "component": "Debug",
  "severity": "normal"
}