{
  "comments": [
    "build i0505-1045\n\n- I have all of Core checked out from HEAD\n- I closed runtime and resources (and did stuff, then re-opened)\n- later on I noticed the following exception in my console\n\nCVSTeamProvider#isWatchEditEnabled() needs to check if the project is accessible\nbefore trying to access the persistent properties\n\nNote that there are 3 exceptions below. #1 and #3 are the same. Is #2 related?\n\nosgi\u003e !SESSION May 05, 2004 15:31:28.796 ---------------------------------------\n------\njava.version\u003d1.4.2\njava.vendor\u003dSun Microsystems Inc.\nBootLoader constants: OS\u003dwin32, ARCH\u003dx86, WS\u003dwin32, NL\u003den_US\nCommand-line arguments: -showlocation\n!ENTRY org.eclipse.team.cvs.core 4 0 May 05, 2004 15:31:29.447\n!MESSAGE Errors occured while applying CVS decorations to resources.\n!STACK 1\norg.eclipse.core.internal.resources.ResourceException: Resource /org.eclipse.cor\ne.resources is not open.\n        at org.eclipse.core.internal.resources.Project.checkAccessible(Project.j\nava:119)\n        at org.eclipse.core.internal.resources.Resource.getSessionProperty(Resou\nrce.java:978)\n        at org.eclipse.team.internal.ccvs.core.CVSTeamProvider.isWatchEditEnable\nd(CVSTeamProvider.java:1209)\n        at org.eclipse.team.internal.ccvs.ui.CVSLightweightDecorator.getOverlay(\nCVSLightweightDecorator.java:437)\n        at org.eclipse.team.internal.ccvs.ui.CVSLightweightDecorator.decorate(CV\nSLightweightDecorator.java:237)\n        at org.eclipse.ui.internal.decorators.LightweightDecoratorDefinition.dec\norate(LightweightDecoratorDefinition.java:155)\n        at org.eclipse.ui.internal.decorators.LightweightDecoratorManager$Lightw\neightRunnable.run(LightweightDecoratorManager.java:60)\n        at org.eclipse.core.internal.runtime.InternalPlatform.run(InternalPlatfo\nrm.java:604)\n        at org.eclipse.core.runtime.Platform.run(Platform.java:545)\n        at org.eclipse.ui.internal.decorators.LightweightDecoratorManager.decora\nte(LightweightDecoratorManager.java:258)\n        at org.eclipse.ui.internal.decorators.LightweightDecoratorManager.getDec\norations(LightweightDecoratorManager.java:241)\n        at org.eclipse.ui.internal.decorators.DecorationScheduler$1.run(Decorati\nonScheduler.java:262)\n        at org.eclipse.core.internal.jobs.Worker.run(Worker.java:66)\n!SUBENTRY 1 org.eclipse.core.resources 4 372 May 05, 2004 15:31:29.477\n!MESSAGE Resource /org.eclipse.core.resources is not open.\n!ENTRY org.eclipse.core.resources 4 368 May 05, 2004 15:40:37.365\n!MESSAGE Errors occured while applying CVS decorations to resources.\n!STACK 1\norg.eclipse.core.internal.resources.ResourceException: Resource /org.eclipse.cor\ne.runtime/src/org/eclipse/core/internal does not exist.\n        at org.eclipse.core.internal.resources.Resource.checkExists(Resource.jav\na:309)\n        at org.eclipse.core.internal.resources.Container.members(Container.java:\n174)\n        at org.eclipse.core.internal.resources.Container.members(Container.java:\n165)\n        at org.eclipse.team.internal.ccvs.core.resources.EclipseSynchronizer.mem\nbers(EclipseSynchronizer.java:469)\n        at org.eclipse.team.internal.ccvs.core.resources.EclipseFolder.members(E\nclipseFolder.java:40)\n        at org.eclipse.team.internal.ccvs.core.resources.EclipseFolder.calculate\nAndSaveChildModificationStates(EclipseFolder.java:347)\n        at org.eclipse.team.internal.ccvs.core.resources.EclipseFolder.isModifie\nd(EclipseFolder.java:317)\n        at org.eclipse.team.internal.ccvs.core.resources.EclipseFolder.calculate\nAndSaveChildModificationStates(EclipseFolder.java:351)\n        at org.eclipse.team.internal.ccvs.core.resources.EclipseFolder.isModifie\nd(EclipseFolder.java:317)\n        at org.eclipse.team.internal.ccvs.core.resources.EclipseFolder.calculate\nAndSaveChildModificationStates(EclipseFolder.java:351)\n        at org.eclipse.team.internal.ccvs.core.resources.EclipseFolder.isModifie\nd(EclipseFolder.java:317)\n        at org.eclipse.team.internal.ccvs.core.resources.EclipseFolder.calculate\nAndSaveChildModificationStates(EclipseFolder.java:351)\n        at org.eclipse.team.internal.ccvs.core.resources.EclipseFolder.isModifie\nd(EclipseFolder.java:317)\n        at org.eclipse.team.internal.ccvs.core.resources.EclipseFolder.calculate\nAndSaveChildModificationStates(EclipseFolder.java:351)\n        at org.eclipse.team.internal.ccvs.core.resources.EclipseFolder.isModifie\nd(EclipseFolder.java:317)\n        at org.eclipse.team.internal.ccvs.core.resources.EclipseFolder.calculate\nAndSaveChildModificationStates(EclipseFolder.java:351)\n        at org.eclipse.team.internal.ccvs.core.resources.EclipseFolder.isModifie\nd(EclipseFolder.java:317)\n        at org.eclipse.team.internal.ccvs.ui.CVSLightweightDecorator.isDirty(CVS\nLightweightDecorator.java:148)\n        at org.eclipse.team.internal.ccvs.ui.CVSLightweightDecorator.isDirty(CVS\nLightweightDecorator.java:161)\n        at org.eclipse.team.internal.ccvs.ui.CVSLightweightDecorator.decorate(CV\nSLightweightDecorator.java:232)\n        at org.eclipse.ui.internal.decorators.LightweightDecoratorDefinition.dec\norate(LightweightDecoratorDefinition.java:155)\n        at org.eclipse.ui.internal.decorators.LightweightDecoratorManager$Lightw\neightRunnable.run(LightweightDecoratorManager.java:60)\n        at org.eclipse.core.internal.runtime.InternalPlatform.run(InternalPlatfo\nrm.java:604)\n        at org.eclipse.core.runtime.Platform.run(Platform.java:545)\n        at org.eclipse.ui.internal.decorators.LightweightDecoratorManager.decora\nte(LightweightDecoratorManager.java:258)\n        at org.eclipse.ui.internal.decorators.LightweightDecoratorManager.getDec\norations(LightweightDecoratorManager.java:241)\n        at org.eclipse.ui.internal.decorators.DecorationScheduler$1.run(Decorati\nonScheduler.java:262)\n        at org.eclipse.core.internal.jobs.Worker.run(Worker.java:66)\n!SUBENTRY 1 org.eclipse.core.resources 4 368 May 05, 2004 15:40:37.415\n!MESSAGE Resource /org.eclipse.core.runtime/src/org/eclipse/core/internal does n\not exist.\n!ENTRY org.eclipse.team.cvs.core 4 0 May 05, 2004 15:40:37.425\n!MESSAGE Errors occured while applying CVS decorations to resources.\n!STACK 1\norg.eclipse.core.internal.resources.ResourceException: Resource /org.eclipse.cor\ne.runtime is not open.\n        at org.eclipse.core.internal.resources.Project.checkAccessible(Project.j\nava:119)\n        at org.eclipse.core.internal.resources.Resource.getSessionProperty(Resou\nrce.java:978)\n        at org.eclipse.team.internal.ccvs.core.CVSTeamProvider.isWatchEditEnable\nd(CVSTeamProvider.java:1209)\n        at org.eclipse.team.internal.ccvs.ui.CVSLightweightDecorator.getOverlay(\nCVSLightweightDecorator.java:437)\n        at org.eclipse.team.internal.ccvs.ui.CVSLightweightDecorator.decorate(CV\nSLightweightDecorator.java:237)\n        at org.eclipse.ui.internal.decorators.LightweightDecoratorDefinition.dec\norate(LightweightDecoratorDefinition.java:155)\n        at org.eclipse.ui.internal.decorators.LightweightDecoratorManager$Lightw\neightRunnable.run(LightweightDecoratorManager.java:60)\n        at org.eclipse.core.internal.runtime.InternalPlatform.run(InternalPlatfo\nrm.java:604)\n        at org.eclipse.core.runtime.Platform.run(Platform.java:545)\n        at org.eclipse.ui.internal.decorators.LightweightDecoratorManager.decora\nte(LightweightDecoratorManager.java:258)\n        at org.eclipse.ui.internal.decorators.LightweightDecoratorManager.getDec\norations(LightweightDecoratorManager.java:241)\n        at org.eclipse.ui.internal.decorators.DecorationScheduler$1.run(Decorati\nonScheduler.java:262)\n        at org.eclipse.core.internal.jobs.Worker.run(Worker.java:66)\n!SUBENTRY 1 org.eclipse.core.resources 4 372 May 05, 2004 15:40:37.435",
    "I just got this again (both exceptions). \n\n- all of Core loaded from HEAD\n- in the Navigator multi-select runtime and resources\n- context menu -\u003e Close\n- get the 2 exceptions\n\nOne interesting thing to note is that the decoration is still on one project but\nnot the other. (presumably because of the exception)",
    "I already fixed this case for non-existant projects so it will be easy to add \nthe opened check",
    "IResource#isAccessible will handle both cases for you. For a resource it makes\nsure it exists. For a project it makes sure it exists and is open.\n",
    "Fix to use isAccessible() released to HEAD."
  ],
  "commentCreationDates": [
    "2004-05-05T22:03:42+02:00",
    "2004-05-05T22:07:37+02:00",
    "2004-05-05T23:20:29+02:00",
    "2004-05-05T23:24:35+02:00",
    "2004-05-06T15:11:05+02:00"
  ],
  "traces": [
    {
      "exceptionType": "org.eclipse.core.internal.resources.ResourceException",
      "message": "Resource /org.eclipse.cor e.resources is not open.",
      "elements": [
        {
          "method": "org.eclipse.core.internal.resources.Project.checkAccessible",
          "source": "Project.j ava:119"
        },
        {
          "method": "org.eclipse.core.internal.resources.Resource.getSessionProperty",
          "source": "Resou rce.java:978"
        },
        {
          "method": "org.eclipse.team.internal.ccvs.core.CVSTeamProvider.isWatchEditEnabled",
          "source": "CVSTeamProvider.java:1209"
        },
        {
          "method": "org.eclipse.team.internal.ccvs.ui.CVSLightweightDecorator.getOverlay",
          "source": " CVSLightweightDecorator.java:437"
        },
        {
          "method": "org.eclipse.team.internal.ccvs.ui.CVSLightweightDecorator.decorate",
          "source": "CV SLightweightDecorator.java:237"
        },
        {
          "method": "org.eclipse.ui.internal.decorators.LightweightDecoratorDefinition.decorate",
          "source": "LightweightDecoratorDefinition.java:155"
        },
        {
          "method": "org.eclipse.ui.internal.decorators.LightweightDecoratorManager$LightweightRunnable.run",
          "source": "LightweightDecoratorManager.java:60"
        },
        {
          "method": "org.eclipse.core.internal.runtime.InternalPlatform.run",
          "source": "InternalPlatfo rm.java:604"
        },
        {
          "method": "org.eclipse.core.runtime.Platform.run",
          "source": "Platform.java:545"
        },
        {
          "method": "org.eclipse.ui.internal.decorators.LightweightDecoratorManager.decorate",
          "source": "LightweightDecoratorManager.java:258"
        },
        {
          "method": "org.eclipse.ui.internal.decorators.LightweightDecoratorManager.getDecorations",
          "source": "LightweightDecoratorManager.java:241"
        },
        {
          "method": "org.eclipse.ui.internal.decorators.DecorationScheduler$1.run",
          "source": "Decorati onScheduler.java:262"
        },
        {
          "method": "org.eclipse.core.internal.jobs.Worker.run",
          "source": "Worker.java:66"
        }
      ],
      "number": 0,
      "commentIndex": 0,
      "bugId": "61121",
      "date": "2004-05-05T22:03:42+02:00",
      "product": "Platform",
      "component": "CVS",
      "severity": "normal"
    },
    {
      "exceptionType": "org.eclipse.core.internal.resources.ResourceException",
      "message": "Resource /org.eclipse.cor e.runtime/src/org/eclipse/core/internal does not exist.",
      "elements": [
        {
          "method": "org.eclipse.core.internal.resources.Resource.checkExists",
          "source": "Resource.jav a:309"
        },
        {
          "method": "org.eclipse.core.internal.resources.Container.members",
          "source": "Container.java: 174"
        },
        {
          "method": "org.eclipse.core.internal.resources.Container.members",
          "source": "Container.java: 165"
        },
        {
          "method": "org.eclipse.team.internal.ccvs.core.resources.EclipseSynchronizer.members",
          "source": "EclipseSynchronizer.java:469"
        },
        {
          "method": "org.eclipse.team.internal.ccvs.core.resources.EclipseFolder.members",
          "source": "E clipseFolder.java:40"
        },
        {
          "method": "org.eclipse.team.internal.ccvs.core.resources.EclipseFolder.calculateAndSaveChildModificationStates",
          "source": "EclipseFolder.java:347"
        },
        {
          "method": "org.eclipse.team.internal.ccvs.core.resources.EclipseFolder.isModified",
          "source": "EclipseFolder.java:317"
        },
        {
          "method": "org.eclipse.team.internal.ccvs.core.resources.EclipseFolder.calculateAndSaveChildModificationStates",
          "source": "EclipseFolder.java:351"
        },
        {
          "method": "org.eclipse.team.internal.ccvs.core.resources.EclipseFolder.isModified",
          "source": "EclipseFolder.java:317"
        },
        {
          "method": "org.eclipse.team.internal.ccvs.core.resources.EclipseFolder.calculateAndSaveChildModificationStates",
          "source": "EclipseFolder.java:351"
        },
        {
          "method": "org.eclipse.team.internal.ccvs.core.resources.EclipseFolder.isModified",
          "source": "EclipseFolder.java:317"
        },
        {
          "method": "org.eclipse.team.internal.ccvs.core.resources.EclipseFolder.calculateAndSaveChildModificationStates",
          "source": "EclipseFolder.java:351"
        },
        {
          "method": "org.eclipse.team.internal.ccvs.core.resources.EclipseFolder.isModified",
          "source": "EclipseFolder.java:317"
        },
        {
          "method": "org.eclipse.team.internal.ccvs.core.resources.EclipseFolder.calculateAndSaveChildModificationStates",
          "source": "EclipseFolder.java:351"
        },
        {
          "method": "org.eclipse.team.internal.ccvs.core.resources.EclipseFolder.isModified",
          "source": "EclipseFolder.java:317"
        },
        {
          "method": "org.eclipse.team.internal.ccvs.core.resources.EclipseFolder.calculateAndSaveChildModificationStates",
          "source": "EclipseFolder.java:351"
        },
        {
          "method": "org.eclipse.team.internal.ccvs.core.resources.EclipseFolder.isModified",
          "source": "EclipseFolder.java:317"
        },
        {
          "method": "org.eclipse.team.internal.ccvs.ui.CVSLightweightDecorator.isDirty",
          "source": "CVS LightweightDecorator.java:148"
        },
        {
          "method": "org.eclipse.team.internal.ccvs.ui.CVSLightweightDecorator.isDirty",
          "source": "CVS LightweightDecorator.java:161"
        },
        {
          "method": "org.eclipse.team.internal.ccvs.ui.CVSLightweightDecorator.decorate",
          "source": "CV SLightweightDecorator.java:232"
        },
        {
          "method": "org.eclipse.ui.internal.decorators.LightweightDecoratorDefinition.decorate",
          "source": "LightweightDecoratorDefinition.java:155"
        },
        {
          "method": "org.eclipse.ui.internal.decorators.LightweightDecoratorManager$LightweightRunnable.run",
          "source": "LightweightDecoratorManager.java:60"
        },
        {
          "method": "org.eclipse.core.internal.runtime.InternalPlatform.run",
          "source": "InternalPlatfo rm.java:604"
        },
        {
          "method": "org.eclipse.core.runtime.Platform.run",
          "source": "Platform.java:545"
        },
        {
          "method": "org.eclipse.ui.internal.decorators.LightweightDecoratorManager.decorate",
          "source": "LightweightDecoratorManager.java:258"
        },
        {
          "method": "org.eclipse.ui.internal.decorators.LightweightDecoratorManager.getDecorations",
          "source": "LightweightDecoratorManager.java:241"
        },
        {
          "method": "org.eclipse.ui.internal.decorators.DecorationScheduler$1.run",
          "source": "Decorati onScheduler.java:262"
        },
        {
          "method": "org.eclipse.core.internal.jobs.Worker.run",
          "source": "Worker.java:66"
        }
      ],
      "number": 1,
      "commentIndex": 0,
      "bugId": "61121",
      "date": "2004-05-05T22:03:42+02:00",
      "product": "Platform",
      "component": "CVS",
      "severity": "normal"
    },
    {
      "exceptionType": "org.eclipse.core.internal.resources.ResourceException",
      "message": "Resource /org.eclipse.cor e.runtime is not open.",
      "elements": [
        {
          "method": "org.eclipse.core.internal.resources.Project.checkAccessible",
          "source": "Project.j ava:119"
        },
        {
          "method": "org.eclipse.core.internal.resources.Resource.getSessionProperty",
          "source": "Resou rce.java:978"
        },
        {
          "method": "org.eclipse.team.internal.ccvs.core.CVSTeamProvider.isWatchEditEnabled",
          "source": "CVSTeamProvider.java:1209"
        },
        {
          "method": "org.eclipse.team.internal.ccvs.ui.CVSLightweightDecorator.getOverlay",
          "source": " CVSLightweightDecorator.java:437"
        },
        {
          "method": "org.eclipse.team.internal.ccvs.ui.CVSLightweightDecorator.decorate",
          "source": "CV SLightweightDecorator.java:237"
        },
        {
          "method": "org.eclipse.ui.internal.decorators.LightweightDecoratorDefinition.decorate",
          "source": "LightweightDecoratorDefinition.java:155"
        },
        {
          "method": "org.eclipse.ui.internal.decorators.LightweightDecoratorManager$LightweightRunnable.run",
          "source": "LightweightDecoratorManager.java:60"
        },
        {
          "method": "org.eclipse.core.internal.runtime.InternalPlatform.run",
          "source": "InternalPlatfo rm.java:604"
        },
        {
          "method": "org.eclipse.core.runtime.Platform.run",
          "source": "Platform.java:545"
        },
        {
          "method": "org.eclipse.ui.internal.decorators.LightweightDecoratorManager.decorate",
          "source": "LightweightDecoratorManager.java:258"
        },
        {
          "method": "org.eclipse.ui.internal.decorators.LightweightDecoratorManager.getDecorations",
          "source": "LightweightDecoratorManager.java:241"
        },
        {
          "method": "org.eclipse.ui.internal.decorators.DecorationScheduler$1.run",
          "source": "Decorati onScheduler.java:262"
        },
        {
          "method": "org.eclipse.core.internal.jobs.Worker.run",
          "source": "Worker.java:66"
        }
      ],
      "number": 2,
      "commentIndex": 0,
      "bugId": "61121",
      "date": "2004-05-05T22:03:42+02:00",
      "product": "Platform",
      "component": "CVS",
      "severity": "normal"
    }
  ],
  "groupId": "61121",
  "bugId": "61121",
  "date": "2004-05-05T22:03:42+02:00",
  "product": "Platform",
  "component": "CVS",
  "severity": "normal"
}