{
  "comments": [
    "Build 20040506\n\nWhen restarting self-hosting workspace, I observed the following logging \nduring startup. I had successfully opened the same workspace with the same \nbuild before.\n\n!SESSION May 06, 2004 16:57:07.701 --------------------------------------------\n-\njava.version\u003d1.4.2_04\njava.vendor\u003dSun Microsystems Inc.\nBootLoader constants: OS\u003dwin32, ARCH\u003dx86, WS\u003dwin32, NL\u003den_US\nCommand-line arguments: -showlocation -refresh\n!ENTRY org.eclipse.update.configurator May 06, 2004 16:57:07.721\n!MESSAGE ConfigurationParser.parse() error:\n!STACK 0\njava.lang.IllegalArgumentException\n        at org.apache.crimson.parser.Parser2.parseInternal(Parser2.java:691)\n        at org.apache.crimson.parser.Parser2.parse(Parser2.java:337)\n        at org.apache.crimson.parser.XMLReaderImpl.parse\n(XMLReaderImpl.java:448)\n        at javax.xml.parsers.SAXParser.parse(SAXParser.java:345)\n        at org.eclipse.update.internal.configurator.ConfigurationParser.parse\n(ConfigurationParser.java:68)\n        at \norg.eclipse.update.internal.configurator.PlatformConfiguration.loadConfig\n(PlatformConfiguration.java:1140)\n        at \norg.eclipse.update.internal.configurator.PlatformConfiguration.initializeCurren\nt(PlatformConfiguration.java:701)\n        at \norg.eclipse.update.internal.configurator.PlatformConfiguration.\u003cinit\u003e\n(PlatformConfiguration.java:83)\n        at \norg.eclipse.update.internal.configurator.PlatformConfiguration.startup\n(PlatformConfiguration.java:642)\n        at \norg.eclipse.update.internal.configurator.ConfigurationActivator.getPlatformConf\niguration(ConfigurationActivator.java:296)\n        at \norg.eclipse.update.internal.configurator.ConfigurationActivator.initialize\n(ConfigurationActivator.java:114)\n        at \norg.eclipse.update.internal.configurator.ConfigurationActivator.start\n(ConfigurationActivator.java:68)\n        at org.eclipse.osgi.framework.internal.core.BundleContextImpl$1.run\n(BundleContextImpl.java:973)\n        at java.security.AccessController.doPrivileged(Native Method)\n        at \norg.eclipse.osgi.framework.internal.core.BundleContextImpl.startActivator\n(BundleContextImpl.java:969)\n        at org.eclipse.osgi.framework.internal.core.BundleContextImpl.start\n(BundleContextImpl.java:952)\n        at org.eclipse.osgi.framework.internal.core.BundleHost.startWorker\n(BundleHost.java:408)\n        at org.eclipse.osgi.framework.internal.core.AbstractBundle.resume\n(AbstractBundle.java:373)\n        at org.eclipse.osgi.framework.internal.core.Framework.resumeBundle\n(Framework.java:999)\n        at \norg.eclipse.osgi.framework.internal.core.StartLevelManager.resumeBundles\n(StartLevelManager.java:571)\n        at org.eclipse.osgi.framework.internal.core.StartLevelManager.incFWSL\n(StartLevelManager.java:482)\n        at \norg.eclipse.osgi.framework.internal.core.StartLevelManager.doSetStartLevel\n(StartLevelManager.java:272)\n        at \norg.eclipse.osgi.framework.internal.core.StartLevelManager.dispatchEvent\n(StartLevelManager.java:442)\n        at org.eclipse.osgi.framework.eventmgr.EventManager.dispatchEvent\n(EventManager.java:153)\n        at org.eclipse.osgi.framework.eventmgr.EventThread$Queued.dispatchEvent\n(EventThread.java:56)\n        at org.eclipse.osgi.framework.eventmgr.EventThread.run\n(EventThread.java:107)\n!ENTRY org.eclipse.update.configurator May 06, 2004 16:57:07.801\n!MESSAGE ConfigurationParser.parse() error:\n!STACK 0\njava.lang.IllegalArgumentException\n        at org.apache.crimson.parser.Parser2.parseInternal(Parser2.java:691)\n        at org.apache.crimson.parser.Parser2.parse(Parser2.java:337)\n        at org.apache.crimson.parser.XMLReaderImpl.parse\n(XMLReaderImpl.java:448)\n        at javax.xml.parsers.SAXParser.parse(SAXParser.java:345)\n        at org.eclipse.update.internal.configurator.ConfigurationParser.parse\n(ConfigurationParser.java:68)\n        at \norg.eclipse.update.internal.configurator.PlatformConfiguration.loadConfig\n(PlatformConfiguration.java:1166)\n        at \norg.eclipse.update.internal.configurator.PlatformConfiguration.initializeCurren\nt(PlatformConfiguration.java:701)\n        at \norg.eclipse.update.internal.configurator.PlatformConfiguration.\u003cinit\u003e\n(PlatformConfiguration.java:83)\n        at \norg.eclipse.update.internal.configurator.PlatformConfiguration.startup\n(PlatformConfiguration.java:642)\n        at \norg.eclipse.update.internal.configurator.ConfigurationActivator.getPlatformConf\niguration(ConfigurationActivator.java:296)\n        at \norg.eclipse.update.internal.configurator.ConfigurationActivator.initialize\n(ConfigurationActivator.java:114)\n        at \norg.eclipse.update.internal.configurator.ConfigurationActivator.start\n(ConfigurationActivator.java:68)\n        at org.eclipse.osgi.framework.internal.core.BundleContextImpl$1.run\n(BundleContextImpl.java:973)\n        at java.security.AccessController.doPrivileged(Native Method)\n        at \norg.eclipse.osgi.framework.internal.core.BundleContextImpl.startActivator\n(BundleContextImpl.java:969)\n        at org.eclipse.osgi.framework.internal.core.BundleContextImpl.start\n(BundleContextImpl.java:952)\n        at org.eclipse.osgi.framework.internal.core.BundleHost.startWorker\n(BundleHost.java:408)\n        at org.eclipse.osgi.framework.internal.core.AbstractBundle.resume\n(AbstractBundle.java:373)\n        at org.eclipse.osgi.framework.internal.core.Framework.resumeBundle\n(Framework.java:999)\n        at \norg.eclipse.osgi.framework.internal.core.StartLevelManager.resumeBundles\n(StartLevelManager.java:571)\n        at org.eclipse.osgi.framework.internal.core.StartLevelManager.incFWSL\n(StartLevelManager.java:482)\n        at \norg.eclipse.osgi.framework.internal.core.StartLevelManager.doSetStartLevel\n(StartLevelManager.java:272)\n        at \norg.eclipse.osgi.framework.internal.core.StartLevelManager.dispatchEvent\n(StartLevelManager.java:442)\n        at org.eclipse.osgi.framework.eventmgr.EventManager.dispatchEvent\n(EventManager.java:153)\n        at org.eclipse.osgi.framework.eventmgr.EventThread$Queued.dispatchEvent\n(EventThread.java:56)\n        at org.eclipse.osgi.framework.eventmgr.EventThread.run\n(EventThread.java:107)",
    "Possibly a mangled configuration file? ",
    "I put the trace last night, based on the traces you provided for the cheetah \nupdate problem. It looks like it worked :-)\nI will investigate.",
    "Philippe, were you running with an old configuration directory or was it just \ncreated? \nAre you running on NTFS or FAT(32) ?\n\nCan you clean the configuration folder, repeat the above and attach the \nconfiguration/org.eclipse.update folder here?\nThanks!",
    "I was reopening a self-hosting workspace (old) with latest SDK under WinXP.",
    "Filesystem is NTFS, and I reproduce it on each startup.\n",
    "Created an attachment (id\u003d10387)\nConfiguration folder\n",
    "Created an attachment (id\u003d10389)\nNew configuration after cleaning up first one\n",
    "Clarification. In between attachment 6 and 7, I did cleanup the old \nconfiguration as suggested by Dorian.\n\nFirst restart didn\u0027t issue any trace. Then exited and restarted, and got \nexceptions back.",
    "*** Bug 61359 has been marked as a duplicate of this bug. ***",
    "Thanks Philippe, this helped confirm my guess: it is the date attribute that \nis not correctly turned into a Date object.\nI will create another attribute instead, to store the long integer  for time, \nand create a Date object out of that one.",
    "Instead of using date as string, we will be using date as time (in ms) \n(Date.getTime()). That should fix these issues.\nI still write the date of the config as string inside a comment at the very \ntop of the file.\n\nPhilippe, I wonder if this has anything to do with the cheetah bug you were \nseeing, but I could never reproduce."
  ],
  "commentCreationDates": [
    "2004-05-06T17:11:35+02:00",
    "2004-05-06T17:35:58+02:00",
    "2004-05-06T19:08:01+02:00",
    "2004-05-06T21:55:38+02:00",
    "2004-05-06T22:12:14+02:00",
    "2004-05-07T13:15:36+02:00",
    "2004-05-07T13:16:16+02:00",
    "2004-05-07T13:20:54+02:00",
    "2004-05-07T13:22:02+02:00",
    "2004-05-07T15:57:51+02:00",
    "2004-05-07T16:06:09+02:00",
    "2004-05-07T23:36:14+02:00"
  ],
  "traces": [
    {
      "exceptionType": "java.lang.IllegalArgumentException",
      "elements": [
        {
          "method": "org.apache.crimson.parser.Parser2.parseInternal",
          "source": "Parser2.java:691"
        },
        {
          "method": "org.apache.crimson.parser.Parser2.parse",
          "source": "Parser2.java:337"
        },
        {
          "method": "org.apache.crimson.parser.XMLReaderImpl.parse",
          "source": "XMLReaderImpl.java:448"
        },
        {
          "method": "javax.xml.parsers.SAXParser.parse",
          "source": "SAXParser.java:345"
        },
        {
          "method": "org.eclipse.update.internal.configurator.ConfigurationParser.parse",
          "source": "ConfigurationParser.java:68"
        },
        {
          "method": "org.eclipse.update.internal.configurator.PlatformConfiguration.loadConfig",
          "source": "PlatformConfiguration.java:1140"
        },
        {
          "method": "org.eclipse.update.internal.configurator.PlatformConfiguration.initializeCurrent",
          "source": "PlatformConfiguration.java:701"
        },
        {
          "method": "org.eclipse.update.internal.configurator.PlatformConfiguration.\u003cinit\u003e",
          "source": "PlatformConfiguration.java:83"
        },
        {
          "method": "org.eclipse.update.internal.configurator.PlatformConfiguration.startup",
          "source": "PlatformConfiguration.java:642"
        },
        {
          "method": "org.eclipse.update.internal.configurator.ConfigurationActivator.getPlatformConfiguration",
          "source": "ConfigurationActivator.java:296"
        },
        {
          "method": "org.eclipse.update.internal.configurator.ConfigurationActivator.initialize",
          "source": "ConfigurationActivator.java:114"
        },
        {
          "method": "org.eclipse.update.internal.configurator.ConfigurationActivator.start",
          "source": "ConfigurationActivator.java:68"
        },
        {
          "method": "org.eclipse.osgi.framework.internal.core.BundleContextImpl$1.run",
          "source": "BundleContextImpl.java:973"
        },
        {
          "method": "java.security.AccessController.doPrivileged",
          "source": "Native Method"
        },
        {
          "method": "org.eclipse.osgi.framework.internal.core.BundleContextImpl.startActivator",
          "source": "BundleContextImpl.java:969"
        },
        {
          "method": "org.eclipse.osgi.framework.internal.core.BundleContextImpl.start",
          "source": "BundleContextImpl.java:952"
        },
        {
          "method": "org.eclipse.osgi.framework.internal.core.BundleHost.startWorker",
          "source": "BundleHost.java:408"
        },
        {
          "method": "org.eclipse.osgi.framework.internal.core.AbstractBundle.resume",
          "source": "AbstractBundle.java:373"
        },
        {
          "method": "org.eclipse.osgi.framework.internal.core.Framework.resumeBundle",
          "source": "Framework.java:999"
        },
        {
          "method": "org.eclipse.osgi.framework.internal.core.StartLevelManager.resumeBundles",
          "source": "StartLevelManager.java:571"
        },
        {
          "method": "org.eclipse.osgi.framework.internal.core.StartLevelManager.incFWSL",
          "source": "StartLevelManager.java:482"
        },
        {
          "method": "org.eclipse.osgi.framework.internal.core.StartLevelManager.doSetStartLevel",
          "source": "StartLevelManager.java:272"
        },
        {
          "method": "org.eclipse.osgi.framework.internal.core.StartLevelManager.dispatchEvent",
          "source": "StartLevelManager.java:442"
        },
        {
          "method": "org.eclipse.osgi.framework.eventmgr.EventManager.dispatchEvent",
          "source": "EventManager.java:153"
        },
        {
          "method": "org.eclipse.osgi.framework.eventmgr.EventThread$Queued.dispatchEvent",
          "source": "EventThread.java:56"
        },
        {
          "method": "org.eclipse.osgi.framework.eventmgr.EventThread.run",
          "source": "EventThread.java:107"
        }
      ],
      "number": 0,
      "commentIndex": 0,
      "bugId": "61224",
      "date": "2004-05-06T17:11:35+02:00",
      "product": "Platform",
      "component": "Update",
      "severity": "normal"
    },
    {
      "exceptionType": "java.lang.IllegalArgumentException",
      "elements": [
        {
          "method": "org.apache.crimson.parser.Parser2.parseInternal",
          "source": "Parser2.java:691"
        },
        {
          "method": "org.apache.crimson.parser.Parser2.parse",
          "source": "Parser2.java:337"
        },
        {
          "method": "org.apache.crimson.parser.XMLReaderImpl.parse",
          "source": "XMLReaderImpl.java:448"
        },
        {
          "method": "javax.xml.parsers.SAXParser.parse",
          "source": "SAXParser.java:345"
        },
        {
          "method": "org.eclipse.update.internal.configurator.ConfigurationParser.parse",
          "source": "ConfigurationParser.java:68"
        },
        {
          "method": "org.eclipse.update.internal.configurator.PlatformConfiguration.loadConfig",
          "source": "PlatformConfiguration.java:1166"
        },
        {
          "method": "org.eclipse.update.internal.configurator.PlatformConfiguration.initializeCurrent",
          "source": "PlatformConfiguration.java:701"
        },
        {
          "method": "org.eclipse.update.internal.configurator.PlatformConfiguration.\u003cinit\u003e",
          "source": "PlatformConfiguration.java:83"
        },
        {
          "method": "org.eclipse.update.internal.configurator.PlatformConfiguration.startup",
          "source": "PlatformConfiguration.java:642"
        },
        {
          "method": "org.eclipse.update.internal.configurator.ConfigurationActivator.getPlatformConfiguration",
          "source": "ConfigurationActivator.java:296"
        },
        {
          "method": "org.eclipse.update.internal.configurator.ConfigurationActivator.initialize",
          "source": "ConfigurationActivator.java:114"
        },
        {
          "method": "org.eclipse.update.internal.configurator.ConfigurationActivator.start",
          "source": "ConfigurationActivator.java:68"
        },
        {
          "method": "org.eclipse.osgi.framework.internal.core.BundleContextImpl$1.run",
          "source": "BundleContextImpl.java:973"
        },
        {
          "method": "java.security.AccessController.doPrivileged",
          "source": "Native Method"
        },
        {
          "method": "org.eclipse.osgi.framework.internal.core.BundleContextImpl.startActivator",
          "source": "BundleContextImpl.java:969"
        },
        {
          "method": "org.eclipse.osgi.framework.internal.core.BundleContextImpl.start",
          "source": "BundleContextImpl.java:952"
        },
        {
          "method": "org.eclipse.osgi.framework.internal.core.BundleHost.startWorker",
          "source": "BundleHost.java:408"
        },
        {
          "method": "org.eclipse.osgi.framework.internal.core.AbstractBundle.resume",
          "source": "AbstractBundle.java:373"
        },
        {
          "method": "org.eclipse.osgi.framework.internal.core.Framework.resumeBundle",
          "source": "Framework.java:999"
        },
        {
          "method": "org.eclipse.osgi.framework.internal.core.StartLevelManager.resumeBundles",
          "source": "StartLevelManager.java:571"
        },
        {
          "method": "org.eclipse.osgi.framework.internal.core.StartLevelManager.incFWSL",
          "source": "StartLevelManager.java:482"
        },
        {
          "method": "org.eclipse.osgi.framework.internal.core.StartLevelManager.doSetStartLevel",
          "source": "StartLevelManager.java:272"
        },
        {
          "method": "org.eclipse.osgi.framework.internal.core.StartLevelManager.dispatchEvent",
          "source": "StartLevelManager.java:442"
        },
        {
          "method": "org.eclipse.osgi.framework.eventmgr.EventManager.dispatchEvent",
          "source": "EventManager.java:153"
        },
        {
          "method": "org.eclipse.osgi.framework.eventmgr.EventThread$Queued.dispatchEvent",
          "source": "EventThread.java:56"
        },
        {
          "method": "org.eclipse.osgi.framework.eventmgr.EventThread.run",
          "source": "EventThread.java:107"
        }
      ],
      "number": 1,
      "commentIndex": 0,
      "bugId": "61224",
      "date": "2004-05-06T17:11:35+02:00",
      "product": "Platform",
      "component": "Update",
      "severity": "normal"
    }
  ],
  "groupId": "61224",
  "bugId": "61224",
  "date": "2004-05-06T17:11:35+02:00",
  "product": "Platform",
  "component": "Update",
  "severity": "normal"
}