{
  "comments": [
    "i get this stacktrace when starting the ibuild: 200405060200\n\njava.lang.IllegalArgumentException\n        at java.util.Date.parse(Date.java:587)\n        at java.util.Date.\u003cinit\u003e(Date.java:249)\n        at \norg.eclipse.update.internal.configurator.ConfigurationParser.processConfig\n(ConfigurationParser.java:277)\n        at \norg.eclipse.update.internal.configurator.ConfigurationParser.startElement\n(ConfigurationParser.java:102)\n        at \ncom.sun.org.apache.xerces.internal.parsers.AbstractSAXParser.startElement\n(AbstractSAXParser.java:478)\n        at \ncom.sun.org.apache.xerces.internal.xinclude.XIncludeHandler.startElement\n(XIncludeHandler.java:568)\n        at \ncom.sun.org.apache.xerces.internal.impl.XMLNSDocumentScannerImpl.scanStartElemen\nt(XMLNSDocumentScannerImpl.java:318)\n        at \ncom.sun.org.apache.xerces.internal.impl.XMLNSDocumentScannerImpl$NSContentDispat\ncher.scanRootElementHook(XMLNSDocumentScannerImpl.java:614)\n        at \ncom.sun.org.apache.xerces.internal.impl.XMLDocumentFragmentScannerImpl$FragmentC\nontentDispatcher.dispatch(XMLDocumentFragmentScannerImpl.java:1639)\n        at \ncom.sun.org.apache.xerces.internal.impl.XMLDocumentFragmentScannerImpl.scanDocum\nent(XMLDocumentFragmentScannerImpl.java:345)\n        at com.sun.org.apache.xerces.internal.parsers.XML11Configuration.parse\n(XML11Configuration.java:827)\n        at com.sun.org.apache.xerces.internal.parsers.XML11Configuration.parse\n(XML11Configuration.java:757)\n        at com.sun.org.apache.xerces.internal.parsers.XMLParser.parse\n(XMLParser.java:148)\n        at com.sun.org.apache.xerces.internal.parsers.AbstractSAXParser.parse\n(AbstractSAXParser.java:1169)\n        at javax.xml.parsers.SAXParser.parse(SAXParser.java:353)\n        at org.eclipse.update.internal.configurator.ConfigurationParser.parse\n(ConfigurationParser.java:68)\n        at \norg.eclipse.update.internal.configurator.PlatformConfiguration.loadConfig\n(PlatformConfiguration.java:1140)\n        at \norg.eclipse.update.internal.configurator.PlatformConfiguration.initializeCurrent\n(PlatformConfiguration.java:701)\n        at org.eclipse.update.internal.configurator.PlatformConfiguration.\u003cinit\u003e\n(PlatformConfiguration.java:83)\n        at \norg.eclipse.update.internal.configurator.PlatformConfiguration.startup\n(PlatformConfiguration.java:642)\n        at \norg.eclipse.update.internal.configurator.ConfigurationActivator.getPlatformConfi\nuration(ConfigurationActivator.java:296)\n        at \norg.eclipse.update.internal.configurator.ConfigurationActivator.initialize\n(ConfigurationActivator.java:114)\n        at org.eclipse.update.internal.configurator.ConfigurationActivator.start\n(ConfigurationActivator.java:68)\n        at org.eclipse.osgi.framework.internal.core.BundleContextImpl$1.run\n(BundleContextImpl.java:973)\n        at java.security.AccessController.doPrivileged(Native Method)\n        at \norg.eclipse.osgi.framework.internal.core.BundleContextImpl.startActivator\n(BundleContextImpl.java:969)\n        at org.eclipse.osgi.framework.internal.core.BundleContextImpl.start\n(BundleContextImpl.java:952)\n        at org.eclipse.osgi.framework.internal.core.BundleHost.startWorker\n(BundleHost.java:408)\n        at org.eclipse.osgi.framework.internal.core.AbstractBundle.resume\n(AbstractBundle.java:373)\n        at org.eclipse.osgi.framework.internal.core.Framework.resumeBundle\n(Framework.java:999)\n        at \norg.eclipse.osgi.framework.internal.core.StartLevelManager.resumeBundles\n(StartLevelManager.java:571)\n        at org.eclipse.osgi.framework.internal.core.StartLevelManager.incFWSL\n(StartLevelManager.java:482)\n        at \norg.eclipse.osgi.framework.internal.core.StartLevelManager.doSetStartLevel\n(StartLevelManager.java:272)\n        at \norg.eclipse.osgi.framework.internal.core.StartLevelManager.dispatchEvent\n(StartLevelManager.java:442)\n        at org.eclipse.osgi.framework.eventmgr.EventManager.dispatchEvent\n(EventManager.java:153)\n        at org.eclipse.osgi.framework.eventmgr.EventThread$Queued.dispatchEvent\n(EventThread.java:56)\n        at org.eclipse.osgi.framework.eventmgr.EventThread.run\n(EventThread.java:107)",
    "This looks like a duplicate of bug 61224.\nWhat locale is your machine ?",
    "locale: nl_NL",
    "fixed."
  ],
  "commentCreationDates": [
    "2004-05-06T22:52:06+02:00",
    "2004-05-07T00:53:13+02:00",
    "2004-05-07T07:45:41+02:00",
    "2004-05-11T05:57:17+02:00"
  ],
  "traces": [
    {
      "exceptionType": "java.lang.IllegalArgumentException",
      "elements": [
        {
          "method": "java.util.Date.parse",
          "source": "Date.java:587"
        },
        {
          "method": "java.util.Date.\u003cinit\u003e",
          "source": "Date.java:249"
        },
        {
          "method": "org.eclipse.update.internal.configurator.ConfigurationParser.processConfig",
          "source": "ConfigurationParser.java:277"
        },
        {
          "method": "org.eclipse.update.internal.configurator.ConfigurationParser.startElement",
          "source": "ConfigurationParser.java:102"
        },
        {
          "method": "com.sun.org.apache.xerces.internal.parsers.AbstractSAXParser.startElement",
          "source": "AbstractSAXParser.java:478"
        },
        {
          "method": "com.sun.org.apache.xerces.internal.xinclude.XIncludeHandler.startElement",
          "source": "XIncludeHandler.java:568"
        },
        {
          "method": "com.sun.org.apache.xerces.internal.impl.XMLNSDocumentScannerImpl.scanStartElement",
          "source": "XMLNSDocumentScannerImpl.java:318"
        },
        {
          "method": "com.sun.org.apache.xerces.internal.impl.XMLNSDocumentScannerImpl$NSContentDispatcher.scanRootElementHook",
          "source": "XMLNSDocumentScannerImpl.java:614"
        },
        {
          "method": "com.sun.org.apache.xerces.internal.impl.XMLDocumentFragmentScannerImpl$FragmentContentDispatcher.dispatch",
          "source": "XMLDocumentFragmentScannerImpl.java:1639"
        },
        {
          "method": "com.sun.org.apache.xerces.internal.impl.XMLDocumentFragmentScannerImpl.scanDocument",
          "source": "XMLDocumentFragmentScannerImpl.java:345"
        },
        {
          "method": "com.sun.org.apache.xerces.internal.parsers.XML11Configuration.parse",
          "source": "XML11Configuration.java:827"
        },
        {
          "method": "com.sun.org.apache.xerces.internal.parsers.XML11Configuration.parse",
          "source": "XML11Configuration.java:757"
        },
        {
          "method": "com.sun.org.apache.xerces.internal.parsers.XMLParser.parse",
          "source": "XMLParser.java:148"
        },
        {
          "method": "com.sun.org.apache.xerces.internal.parsers.AbstractSAXParser.parse",
          "source": "AbstractSAXParser.java:1169"
        },
        {
          "method": "javax.xml.parsers.SAXParser.parse",
          "source": "SAXParser.java:353"
        },
        {
          "method": "org.eclipse.update.internal.configurator.ConfigurationParser.parse",
          "source": "ConfigurationParser.java:68"
        },
        {
          "method": "org.eclipse.update.internal.configurator.PlatformConfiguration.loadConfig",
          "source": "PlatformConfiguration.java:1140"
        },
        {
          "method": "org.eclipse.update.internal.configurator.PlatformConfiguration.initializeCurrent",
          "source": "PlatformConfiguration.java:701"
        },
        {
          "method": "org.eclipse.update.internal.configurator.PlatformConfiguration.\u003cinit\u003e",
          "source": "PlatformConfiguration.java:83"
        },
        {
          "method": "org.eclipse.update.internal.configurator.PlatformConfiguration.startup",
          "source": "PlatformConfiguration.java:642"
        },
        {
          "method": "org.eclipse.update.internal.configurator.ConfigurationActivator.getPlatformConfiuration",
          "source": "ConfigurationActivator.java:296"
        },
        {
          "method": "org.eclipse.update.internal.configurator.ConfigurationActivator.initialize",
          "source": "ConfigurationActivator.java:114"
        },
        {
          "method": "org.eclipse.update.internal.configurator.ConfigurationActivator.start",
          "source": "ConfigurationActivator.java:68"
        },
        {
          "method": "org.eclipse.osgi.framework.internal.core.BundleContextImpl$1.run",
          "source": "BundleContextImpl.java:973"
        },
        {
          "method": "java.security.AccessController.doPrivileged",
          "source": "Native Method"
        },
        {
          "method": "org.eclipse.osgi.framework.internal.core.BundleContextImpl.startActivator",
          "source": "BundleContextImpl.java:969"
        },
        {
          "method": "org.eclipse.osgi.framework.internal.core.BundleContextImpl.start",
          "source": "BundleContextImpl.java:952"
        },
        {
          "method": "org.eclipse.osgi.framework.internal.core.BundleHost.startWorker",
          "source": "BundleHost.java:408"
        },
        {
          "method": "org.eclipse.osgi.framework.internal.core.AbstractBundle.resume",
          "source": "AbstractBundle.java:373"
        },
        {
          "method": "org.eclipse.osgi.framework.internal.core.Framework.resumeBundle",
          "source": "Framework.java:999"
        },
        {
          "method": "org.eclipse.osgi.framework.internal.core.StartLevelManager.resumeBundles",
          "source": "StartLevelManager.java:571"
        },
        {
          "method": "org.eclipse.osgi.framework.internal.core.StartLevelManager.incFWSL",
          "source": "StartLevelManager.java:482"
        },
        {
          "method": "org.eclipse.osgi.framework.internal.core.StartLevelManager.doSetStartLevel",
          "source": "StartLevelManager.java:272"
        },
        {
          "method": "org.eclipse.osgi.framework.internal.core.StartLevelManager.dispatchEvent",
          "source": "StartLevelManager.java:442"
        },
        {
          "method": "org.eclipse.osgi.framework.eventmgr.EventManager.dispatchEvent",
          "source": "EventManager.java:153"
        },
        {
          "method": "org.eclipse.osgi.framework.eventmgr.EventThread$Queued.dispatchEvent",
          "source": "EventThread.java:56"
        },
        {
          "method": "org.eclipse.osgi.framework.eventmgr.EventThread.run",
          "source": "EventThread.java:107"
        }
      ],
      "number": 0,
      "commentIndex": 0,
      "bugId": "61314",
      "date": "2004-05-06T22:52:06+02:00",
      "product": "Platform",
      "component": "Update",
      "severity": "normal"
    }
  ],
  "groupId": "61314",
  "bugId": "61314",
  "date": "2004-05-06T22:52:06+02:00",
  "product": "Platform",
  "component": "Update",
  "severity": "normal"
}