{
  "comments": [
    "I20040505\n\nOlivier got an incomplete classpath problem with I20040505. He was running \nwith JDT Core tracing on, and it looks like another case where \nModelEntry.updateUnknownClasspathContainer(...) is called:\n\njava.lang.Exception: \u003cFake exception\u003e\n        at org.eclipse.jdt.core.JavaCore.setClasspathContainer\n(JavaCore.java:3422)\n        at \norg.eclipse.pde.internal.core.ModelEntry.updateUnknownClasspathContainer\n(ModelEntry.java:152)\n        at org.eclipse.pde.internal.core.RequiredPluginsInitializer.initialize\n(RequiredPluginsInitializer.java:38)\n        at org.eclipse.jdt.core.JavaCore.getClasspathContainer\n(JavaCore.java:1215)\n        at org.eclipse.jdt.internal.core.JavaProject.getResolvedClasspath\n(JavaProject.java:1841)\n        at org.eclipse.jdt.internal.core.JavaProject.getResolvedClasspath\n(JavaProject.java:1755)\n        at org.eclipse.jdt.internal.core.JavaProject.getResolvedClasspath\n(JavaProject.java:1727)\n        at org.eclipse.jdt.internal.core.JavaProject.buildStructure\n(JavaProject.java:261)\n        at org.eclipse.jdt.internal.core.Openable.generateInfos\n(Openable.java:183)\n        at org.eclipse.jdt.internal.core.JavaElement.openWhenClosed\n(JavaElement.java:568)\n        at org.eclipse.jdt.internal.core.JavaElement.getElementInfo\n(JavaElement.java:305)\n        at org.eclipse.jdt.internal.core.JavaElement.getElementInfo\n(JavaElement.java:291)\n        at org.eclipse.jdt.internal.core.JavaElement.getChildren\n(JavaElement.java:246)\n        at org.eclipse.jdt.internal.core.JavaProject.getPackageFragmentRoots\n(JavaProject.java:1557)\n        at org.eclipse.jdt.ui.actions.OrganizeImportsAction.hasSourceFolders\n(OrganizeImportsAction.java:253)\n        at org.eclipse.jdt.ui.actions.OrganizeImportsAction.isEnabled\n(OrganizeImportsAction.java:239)\n        at org.eclipse.jdt.ui.actions.OrganizeImportsAction.selectionChanged\n(OrganizeImportsAction.java:152)\n        at \norg.eclipse.jdt.ui.actions.SelectionDispatchAction.dispatchSelectionChanged\n(SelectionDispatchAction.java:200)\n        at org.eclipse.jdt.ui.actions.SelectionDispatchAction.selectionChanged\n(SelectionDispatchAction.java:195)\n        at org.eclipse.jface.viewers.Viewer$2.run(Viewer.java:159)\n        at org.eclipse.core.internal.runtime.InternalPlatform.run\n(InternalPlatform.java:604)\n        at org.eclipse.core.runtime.Platform.run(Platform.java:545)\n        at org.eclipse.jface.viewers.Viewer.fireSelectionChanged\n(Viewer.java:157)\n        at org.eclipse.jface.viewers.StructuredViewer.updateSelection\n(StructuredViewer.java:1292)\n        at org.eclipse.jface.viewers.StructuredViewer.handleSelect\n(StructuredViewer.java:648)\n        at org.eclipse.jface.viewers.StructuredViewer$4.widgetSelected\n(StructuredViewer.java:672)\n        at org.eclipse.jface.util.OpenStrategy.fireSelectionEvent\n(OpenStrategy.java:180)\n        at org.eclipse.jface.util.OpenStrategy.access$3(OpenStrategy.java:175)\n        at org.eclipse.jface.util.OpenStrategy$1.handleEvent\n(OpenStrategy.java:324)\n        at org.eclipse.swt.widgets.EventTable.sendEvent(EventTable.java:82)\n        at org.eclipse.swt.widgets.Widget.sendEvent(Widget.java:796)\n        at org.eclipse.swt.widgets.Display.runDeferredEvents(Display.java:2594)\n        at org.eclipse.swt.widgets.Display.readAndDispatch(Display.java:2272)\n        at org.eclipse.ui.internal.Workbench.runEventLoop(Workbench.java:1353)\n        at org.eclipse.ui.internal.Workbench.runUI(Workbench.java:1324)\n        at org.eclipse.ui.internal.Workbench.createAndRunWorkbench\n(Workbench.java:243)\n        at org.eclipse.ui.PlatformUI.createAndRunWorkbench(PlatformUI.java:140)\n        at org.eclipse.ui.internal.ide.IDEApplication.run\n(IDEApplication.java:90)\n        at org.eclipse.core.internal.runtime.PlatformActivator$1.run\n(PlatformActivator.java:283)\n        at org.eclipse.core.runtime.adaptor.EclipseStarter.run\n(EclipseStarter.java:242)\n        at org.eclipse.core.runtime.adaptor.EclipseStarter.run\n(EclipseStarter.java:119)\n        at sun.reflect.NativeMethodAccessorImpl.invoke0(Native Method)\n        at sun.reflect.NativeMethodAccessorImpl.invoke\n(NativeMethodAccessorImpl.java:39)\n        at sun.reflect.DelegatingMethodAccessorImpl.invoke\n(DelegatingMethodAccessorImpl.java:25)\n        at java.lang.reflect.Method.invoke(Method.java:324)\n        at org.eclipse.core.launcher.Main.basicRun(Main.java:269)\n        at org.eclipse.core.launcher.Main.run(Main.java:700)\n        at org.eclipse.core.launcher.Main.main(Main.java:684)",
    "Created an attachment (id\u003d10385)\nJDT Core tracing log\n",
    "This would occur if scenario 1 in bug 60910 comment #5 took place.",
    "The only thing I have done is to restart an existing workspace.",
    "All these problems have officially been resolved as of the May 17 build."
  ],
  "commentCreationDates": [
    "2004-05-07T10:18:47+02:00",
    "2004-05-07T10:20:15+02:00",
    "2004-05-07T14:03:51+02:00",
    "2004-05-07T14:46:49+02:00",
    "2004-05-20T10:42:28+02:00"
  ],
  "traces": [
    {
      "exceptionType": "java.lang.Exception",
      "message": "\u003cFake exception\u003e",
      "elements": [
        {
          "method": "org.eclipse.jdt.core.JavaCore.setClasspathContainer",
          "source": "JavaCore.java:3422"
        },
        {
          "method": "org.eclipse.pde.internal.core.ModelEntry.updateUnknownClasspathContainer",
          "source": "ModelEntry.java:152"
        },
        {
          "method": "org.eclipse.pde.internal.core.RequiredPluginsInitializer.initialize",
          "source": "RequiredPluginsInitializer.java:38"
        },
        {
          "method": "org.eclipse.jdt.core.JavaCore.getClasspathContainer",
          "source": "JavaCore.java:1215"
        },
        {
          "method": "org.eclipse.jdt.internal.core.JavaProject.getResolvedClasspath",
          "source": "JavaProject.java:1841"
        },
        {
          "method": "org.eclipse.jdt.internal.core.JavaProject.getResolvedClasspath",
          "source": "JavaProject.java:1755"
        },
        {
          "method": "org.eclipse.jdt.internal.core.JavaProject.getResolvedClasspath",
          "source": "JavaProject.java:1727"
        },
        {
          "method": "org.eclipse.jdt.internal.core.JavaProject.buildStructure",
          "source": "JavaProject.java:261"
        },
        {
          "method": "org.eclipse.jdt.internal.core.Openable.generateInfos",
          "source": "Openable.java:183"
        },
        {
          "method": "org.eclipse.jdt.internal.core.JavaElement.openWhenClosed",
          "source": "JavaElement.java:568"
        },
        {
          "method": "org.eclipse.jdt.internal.core.JavaElement.getElementInfo",
          "source": "JavaElement.java:305"
        },
        {
          "method": "org.eclipse.jdt.internal.core.JavaElement.getElementInfo",
          "source": "JavaElement.java:291"
        },
        {
          "method": "org.eclipse.jdt.internal.core.JavaElement.getChildren",
          "source": "JavaElement.java:246"
        },
        {
          "method": "org.eclipse.jdt.internal.core.JavaProject.getPackageFragmentRoots",
          "source": "JavaProject.java:1557"
        },
        {
          "method": "org.eclipse.jdt.ui.actions.OrganizeImportsAction.hasSourceFolders",
          "source": "OrganizeImportsAction.java:253"
        },
        {
          "method": "org.eclipse.jdt.ui.actions.OrganizeImportsAction.isEnabled",
          "source": "OrganizeImportsAction.java:239"
        },
        {
          "method": "org.eclipse.jdt.ui.actions.OrganizeImportsAction.selectionChanged",
          "source": "OrganizeImportsAction.java:152"
        },
        {
          "method": "org.eclipse.jdt.ui.actions.SelectionDispatchAction.dispatchSelectionChanged",
          "source": "SelectionDispatchAction.java:200"
        },
        {
          "method": "org.eclipse.jdt.ui.actions.SelectionDispatchAction.selectionChanged",
          "source": "SelectionDispatchAction.java:195"
        },
        {
          "method": "org.eclipse.jface.viewers.Viewer$2.run",
          "source": "Viewer.java:159"
        },
        {
          "method": "org.eclipse.core.internal.runtime.InternalPlatform.run",
          "source": "InternalPlatform.java:604"
        },
        {
          "method": "org.eclipse.core.runtime.Platform.run",
          "source": "Platform.java:545"
        },
        {
          "method": "org.eclipse.jface.viewers.Viewer.fireSelectionChanged",
          "source": "Viewer.java:157"
        },
        {
          "method": "org.eclipse.jface.viewers.StructuredViewer.updateSelection",
          "source": "StructuredViewer.java:1292"
        },
        {
          "method": "org.eclipse.jface.viewers.StructuredViewer.handleSelect",
          "source": "StructuredViewer.java:648"
        },
        {
          "method": "org.eclipse.jface.viewers.StructuredViewer$4.widgetSelected",
          "source": "StructuredViewer.java:672"
        },
        {
          "method": "org.eclipse.jface.util.OpenStrategy.fireSelectionEvent",
          "source": "OpenStrategy.java:180"
        },
        {
          "method": "org.eclipse.jface.util.OpenStrategy.access$3",
          "source": "OpenStrategy.java:175"
        },
        {
          "method": "org.eclipse.jface.util.OpenStrategy$1.handleEvent",
          "source": "OpenStrategy.java:324"
        },
        {
          "method": "org.eclipse.swt.widgets.EventTable.sendEvent",
          "source": "EventTable.java:82"
        },
        {
          "method": "org.eclipse.swt.widgets.Widget.sendEvent",
          "source": "Widget.java:796"
        },
        {
          "method": "org.eclipse.swt.widgets.Display.runDeferredEvents",
          "source": "Display.java:2594"
        },
        {
          "method": "org.eclipse.swt.widgets.Display.readAndDispatch",
          "source": "Display.java:2272"
        },
        {
          "method": "org.eclipse.ui.internal.Workbench.runEventLoop",
          "source": "Workbench.java:1353"
        },
        {
          "method": "org.eclipse.ui.internal.Workbench.runUI",
          "source": "Workbench.java:1324"
        },
        {
          "method": "org.eclipse.ui.internal.Workbench.createAndRunWorkbench",
          "source": "Workbench.java:243"
        },
        {
          "method": "org.eclipse.ui.PlatformUI.createAndRunWorkbench",
          "source": "PlatformUI.java:140"
        },
        {
          "method": "org.eclipse.ui.internal.ide.IDEApplication.run",
          "source": "IDEApplication.java:90"
        },
        {
          "method": "org.eclipse.core.internal.runtime.PlatformActivator$1.run",
          "source": "PlatformActivator.java:283"
        },
        {
          "method": "org.eclipse.core.runtime.adaptor.EclipseStarter.run",
          "source": "EclipseStarter.java:242"
        },
        {
          "method": "org.eclipse.core.runtime.adaptor.EclipseStarter.run",
          "source": "EclipseStarter.java:119"
        },
        {
          "method": "sun.reflect.NativeMethodAccessorImpl.invoke0",
          "source": "Native Method"
        },
        {
          "method": "sun.reflect.NativeMethodAccessorImpl.invoke",
          "source": "NativeMethodAccessorImpl.java:39"
        },
        {
          "method": "sun.reflect.DelegatingMethodAccessorImpl.invoke",
          "source": "DelegatingMethodAccessorImpl.java:25"
        },
        {
          "method": "java.lang.reflect.Method.invoke",
          "source": "Method.java:324"
        },
        {
          "method": "org.eclipse.core.launcher.Main.basicRun",
          "source": "Main.java:269"
        },
        {
          "method": "org.eclipse.core.launcher.Main.run",
          "source": "Main.java:700"
        },
        {
          "method": "org.eclipse.core.launcher.Main.main",
          "source": "Main.java:684"
        }
      ],
      "number": 0,
      "commentIndex": 0,
      "bugId": "61365",
      "date": "2004-05-07T10:18:47+02:00",
      "product": "PDE",
      "component": "UI",
      "severity": "normal"
    }
  ],
  "groupId": "61365",
  "bugId": "61365",
  "date": "2004-05-07T10:18:47+02:00",
  "product": "PDE",
  "component": "UI",
  "severity": "normal"
}