{
  "comments": [
    "build i0506-0200\n\nUsing this build I am getting the following NPE in my console (nothing presented\nto the user) when trying to evaluate some code in my scrapbook page. Note that\nI\u0027m missing a quote for the \"value\" parm.\n\nActually when I add the missing quote I still get the same error. After getting\nthe error the status bar says \"Evaluating...\" and doesn\u0027t change. Also the\nExecute, Display, Inspect menu entries from the context menu are disabled. They\nare re-enabled if I close the scrapbook page and then re-open it.\n\nHere is the code: \n\njava.util.Properties properties \u003d new java.util.Properties();\nproperties.put(\"my:key\", \"value);\nproperties.store(System.out, null);\n\nHere is the stack:\n\n!ENTRY org.eclipse.ui 4 4 May 07, 2004 11:12:43.812\n!MESSAGE Unhandled event loop exception\nUnhandled event loop exception\nReason:\n!ENTRY org.eclipse.ui 4 0 May 07, 2004 11:12:43.822\n!MESSAGE java.lang.NullPointerException\n!STACK 0\njava.lang.NullPointerException\n        at org.eclipse.jdt.internal.debug.ui.snippeteditor.ScrapbookLauncher.doL\naunch(ScrapbookLauncher.java:223)\n        at org.eclipse.jdt.internal.debug.ui.snippeteditor.ScrapbookLauncher.lau\nnch(ScrapbookLauncher.java:143)\n        at org.eclipse.jdt.internal.debug.ui.snippeteditor.JavaSnippetEditor$16.\nrun(JavaSnippetEditor.java:1164)\n        at org.eclipse.swt.custom.BusyIndicator.showWhile(BusyIndicator.java:84)\n\n        at org.eclipse.jdt.internal.debug.ui.snippeteditor.JavaSnippetEditor.lau\nnchVM(JavaSnippetEditor.java:1167)\n        at org.eclipse.jdt.internal.debug.ui.snippeteditor.JavaSnippetEditor.bui\nldAndLaunch(JavaSnippetEditor.java:406)\n        at org.eclipse.jdt.internal.debug.ui.snippeteditor.JavaSnippetEditor.eva\nlSelection(JavaSnippetEditor.java:328)\n        at org.eclipse.jdt.internal.debug.ui.actions.ExecuteAction.run(ExecuteAc\ntion.java:49)\n        at org.eclipse.jdt.internal.debug.ui.actions.EvaluateAction.run(Evaluate\nAction.java:563)\n        at org.eclipse.ui.internal.PluginAction.runWithEvent(PluginAction.java:2\n76)\n        at org.eclipse.jface.action.ActionContributionItem.handleWidgetSelection\n(ActionContributionItem.java:612)\n        at org.eclipse.jface.action.ActionContributionItem.access$2(ActionContri\nbutionItem.java:563)\n        at org.eclipse.jface.action.ActionContributionItem$6.handleEvent(ActionC\nontributionItem.java:482)\n        at org.eclipse.swt.widgets.EventTable.sendEvent(EventTable.java:82)\n        at org.eclipse.swt.widgets.Widget.sendEvent(Widget.java:796)\n        at org.eclipse.swt.widgets.Display.runDeferredEvents(Display.java:2594)\n        at org.eclipse.swt.widgets.Display.readAndDispatch(Display.java:2272)\n        at org.eclipse.ui.internal.Workbench.runEventLoop(Workbench.java:1353)\n        at org.eclipse.ui.internal.Workbench.runUI(Workbench.java:1324)\n        at org.eclipse.ui.internal.Workbench.createAndRunWorkbench(Workbench.jav\na:243)\n        at org.eclipse.ui.PlatformUI.createAndRunWorkbench(PlatformUI.java:140)\n        at org.eclipse.ui.internal.ide.IDEApplication.run(IDEApplication.java:90\n)\n        at org.eclipse.core.internal.runtime.PlatformActivator$1.run(PlatformAct\nivator.java:283)\n        at org.eclipse.core.runtime.adaptor.EclipseStarter.run(EclipseStarter.ja\nva:242)\n        at org.eclipse.core.runtime.adaptor.EclipseStarter.run(EclipseStarter.ja\nva:119)\n        at sun.reflect.NativeMethodAccessorImpl.invoke0(Native Method)\n        at sun.reflect.NativeMethodAccessorImpl.invoke(NativeMethodAccessorImpl.\njava:39)\n        at sun.reflect.DelegatingMethodAccessorImpl.invoke(DelegatingMethodAcces\nsorImpl.java:25)\n        at java.lang.reflect.Method.invoke(Method.java:324)\n        at org.eclipse.core.launcher.Main.basicRun(Main.java:269)\n        at org.eclipse.core.launcher.Main.run(Main.java:700)\n        at org.eclipse.core.launcher.Main.main(Main.java:684)\njava.lang.NullPointerException",
    "\n\n*** This bug has been marked as a duplicate of 57763 ***",
    "*** Bug 61134 has been marked as a duplicate of this bug. ***"
  ],
  "commentCreationDates": [
    "2004-05-07T17:34:04+02:00",
    "2004-05-07T18:54:24+02:00",
    "2004-05-07T19:02:16+02:00"
  ],
  "traces": [
    {
      "exceptionType": "java.lang.NullPointerException",
      "elements": [
        {
          "method": "org.eclipse.jdt.internal.debug.ui.snippeteditor.ScrapbookLauncher.doLaunch",
          "source": "ScrapbookLauncher.java:223"
        },
        {
          "method": "org.eclipse.jdt.internal.debug.ui.snippeteditor.ScrapbookLauncher.launch",
          "source": "ScrapbookLauncher.java:143"
        },
        {
          "method": "org.eclipse.jdt.internal.debug.ui.snippeteditor.JavaSnippetEditor$16.run",
          "source": "JavaSnippetEditor.java:1164"
        },
        {
          "method": "org.eclipse.swt.custom.BusyIndicator.showWhile",
          "source": "BusyIndicator.java:84"
        },
        {
          "method": "org.eclipse.jdt.internal.debug.ui.snippeteditor.JavaSnippetEditor.launchVM",
          "source": "JavaSnippetEditor.java:1167"
        },
        {
          "method": "org.eclipse.jdt.internal.debug.ui.snippeteditor.JavaSnippetEditor.buildAndLaunch",
          "source": "JavaSnippetEditor.java:406"
        },
        {
          "method": "org.eclipse.jdt.internal.debug.ui.snippeteditor.JavaSnippetEditor.evalSelection",
          "source": "JavaSnippetEditor.java:328"
        },
        {
          "method": "org.eclipse.jdt.internal.debug.ui.actions.ExecuteAction.run",
          "source": "ExecuteAc tion.java:49"
        },
        {
          "method": "org.eclipse.jdt.internal.debug.ui.actions.EvaluateAction.run",
          "source": "Evaluate Action.java:563"
        },
        {
          "method": "org.eclipse.ui.internal.PluginAction.runWithEvent",
          "source": "PluginAction.java:2 76"
        },
        {
          "method": "org.eclipse.jface.action.ActionContributionItem.handleWidgetSelection",
          "source": "ActionContributionItem.java:612"
        },
        {
          "method": "org.eclipse.jface.action.ActionContributionItem.access$2",
          "source": "ActionContri butionItem.java:563"
        },
        {
          "method": "org.eclipse.jface.action.ActionContributionItem$6.handleEvent",
          "source": "ActionC ontributionItem.java:482"
        },
        {
          "method": "org.eclipse.swt.widgets.EventTable.sendEvent",
          "source": "EventTable.java:82"
        },
        {
          "method": "org.eclipse.swt.widgets.Widget.sendEvent",
          "source": "Widget.java:796"
        },
        {
          "method": "org.eclipse.swt.widgets.Display.runDeferredEvents",
          "source": "Display.java:2594"
        },
        {
          "method": "org.eclipse.swt.widgets.Display.readAndDispatch",
          "source": "Display.java:2272"
        },
        {
          "method": "org.eclipse.ui.internal.Workbench.runEventLoop",
          "source": "Workbench.java:1353"
        },
        {
          "method": "org.eclipse.ui.internal.Workbench.runUI",
          "source": "Workbench.java:1324"
        },
        {
          "method": "org.eclipse.ui.internal.Workbench.createAndRunWorkbench",
          "source": "Workbench.jav a:243"
        },
        {
          "method": "org.eclipse.ui.PlatformUI.createAndRunWorkbench",
          "source": "PlatformUI.java:140"
        },
        {
          "method": "org.eclipse.ui.internal.ide.IDEApplication.run",
          "source": "IDEApplication.java:90 "
        },
        {
          "method": "org.eclipse.core.internal.runtime.PlatformActivator$1.run",
          "source": "PlatformAct ivator.java:283"
        },
        {
          "method": "org.eclipse.core.runtime.adaptor.EclipseStarter.run",
          "source": "EclipseStarter.ja va:242"
        },
        {
          "method": "org.eclipse.core.runtime.adaptor.EclipseStarter.run",
          "source": "EclipseStarter.ja va:119"
        },
        {
          "method": "sun.reflect.NativeMethodAccessorImpl.invoke0",
          "source": "Native Method"
        },
        {
          "method": "sun.reflect.NativeMethodAccessorImpl.invoke",
          "source": "NativeMethodAccessorImpl. java:39"
        },
        {
          "method": "sun.reflect.DelegatingMethodAccessorImpl.invoke",
          "source": "DelegatingMethodAcces sorImpl.java:25"
        },
        {
          "method": "java.lang.reflect.Method.invoke",
          "source": "Method.java:324"
        },
        {
          "method": "org.eclipse.core.launcher.Main.basicRun",
          "source": "Main.java:269"
        },
        {
          "method": "org.eclipse.core.launcher.Main.run",
          "source": "Main.java:700"
        },
        {
          "method": "org.eclipse.core.launcher.Main.main",
          "source": "Main.java:684"
        }
      ],
      "number": 0,
      "commentIndex": 0,
      "bugId": "61405",
      "duplicateId": "57763",
      "date": "2004-05-07T17:34:04+02:00",
      "product": "JDT",
      "component": "Debug",
      "severity": "normal"
    }
  ],
  "groupId": "57763",
  "bugId": "61405",
  "duplicateId": "57763",
  "date": "2004-05-07T17:34:04+02:00",
  "product": "JDT",
  "component": "Debug",
  "severity": "normal"
}