{
  "comments": [
    "in i05051045\n\nI am trying to replace the string \"IPlatform.PI_RUNTIME\" \nwith \"Platform.PI_RUNTIME\".  I opened the searhc dialog using the toolbar \nbutton.  in the file tab entered the search string and then clicked Replace...  \nThis searched and found many entries and put them in the search view.  There \nwas no obvious way to specify the replacement string or get any action to \nhappen.  The search view context menu has Replace... and Replace Selection... \nentries but these did not seem to do anything.\n\nLooked in the log and found:\n!ENTRY org.eclipse.ui 4 4 May 07, 2004 17:17:17.168\n!MESSAGE Unhandled event loop exception\nUnhandled event loop exception\nReason:\n!ENTRY org.eclipse.ui 4 0 May 07, 2004 17:17:17.178\n!MESSAGE Failed to execute runnable (java.lang.NullPointerException)\n!STACK 0\norg.eclipse.swt.SWTException: Failed to execute runnable \n(java.lang.NullPointerException)\n        at org.eclipse.swt.SWT.error(SWT.java:2689)\n        at org.eclipse.swt.SWT.error(SWT.java:2614)\n        at org.eclipse.swt.widgets.Synchronizer.runAsyncMessages\n(Synchronizer.java:109)\n        at org.eclipse.swt.widgets.Display.runAsyncMessages(Display.java:2571)\n        at org.eclipse.swt.widgets.Display.readAndDispatch(Display.java:2276)\n        at org.eclipse.ui.internal.Workbench.runEventLoop(Workbench.java:1353)\n        at org.eclipse.ui.internal.Workbench.runUI(Workbench.java:1324)\n        at org.eclipse.ui.internal.Workbench.createAndRunWorkbench\n(Workbench.java:243)\n        at org.eclipse.ui.PlatformUI.createAndRunWorkbench(PlatformUI.java:140)\n        at org.eclipse.ui.internal.ide.IDEApplication.run\n(IDEApplication.java:90)\n        at org.eclipse.core.internal.runtime.PlatformActivator$1.run\n(PlatformActivator.java:283)\n        at org.eclipse.core.runtime.adaptor.EclipseStarter.run\n(EclipseStarter.java:243)\n        at org.eclipse.core.runtime.adaptor.EclipseStarter.run\n(EclipseStarter.java:120)\n        at sun.reflect.NativeMethodAccessorImpl.invoke0(Native Method)\n        at sun.reflect.NativeMethodAccessorImpl.invoke\n(NativeMethodAccessorImpl.java:39)\n        at sun.reflect.DelegatingMethodAccessorImpl.invoke\n(DelegatingMethodAccessorImpl.java:25)\n        at java.lang.reflect.Method.invoke(Method.java:324)\n        at org.eclipse.core.launcher.Main.basicRun(Main.java:269)\n        at org.eclipse.core.launcher.Main.run(Main.java:700)\n        at org.eclipse.core.launcher.Main.main(Main.java:684)\nFailed to execute runnable (java.lang.NullPointerException)\n!ENTRY org.eclipse.ui 4 4 May 07, 2004 17:17:17.188\n!MESSAGE *** SWT nested exception\n*** SWT nested exception\nReason:\n!ENTRY org.eclipse.ui 4 0 May 07, 2004 17:17:17.198\n!MESSAGE java.lang.NullPointerException\n!STACK 0\njava.lang.NullPointerException\n        at org.eclipse.search.internal.ui.text.ReplaceDialog2.\u003cinit\u003e\n(ReplaceDialog2.java:113)\n        at org.eclipse.search.internal.ui.text.ReplaceAction2.run\n(ReplaceAction2.java:151)\n        at org.eclipse.search.internal.ui.text.TextSearchPage$1.run\n(TextSearchPage.java:237)\n        at org.eclipse.swt.widgets.RunnableLock.run(RunnableLock.java:35)\n        at org.eclipse.swt.widgets.Synchronizer.runAsyncMessages\n(Synchronizer.java:106)\n        at org.eclipse.swt.widgets.Display.runAsyncMessages(Display.java:2571)\n        at org.eclipse.swt.widgets.Display.readAndDispatch(Display.java:2276)\n        at org.eclipse.ui.internal.Workbench.runEventLoop(Workbench.java:1353)\n        at org.eclipse.ui.internal.Workbench.runUI(Workbench.java:1324)\n        at org.eclipse.ui.internal.Workbench.createAndRunWorkbench\n(Workbench.java:243)\n        at org.eclipse.ui.PlatformUI.createAndRunWorkbench(PlatformUI.java:140)\n        at org.eclipse.ui.internal.ide.IDEApplication.run\n(IDEApplication.java:90)\n        at org.eclipse.core.internal.runtime.PlatformActivator$1.run\n(PlatformActivator.java:283)\n        at org.eclipse.core.runtime.adaptor.EclipseStarter.run\n(EclipseStarter.java:243)\n        at org.eclipse.core.runtime.adaptor.EclipseStarter.run\n(EclipseStarter.java:120)\n        at sun.reflect.NativeMethodAccessorImpl.invoke0(Native Method)\n        at sun.reflect.NativeMethodAccessorImpl.invoke\n(NativeMethodAccessorImpl.java:39)\n        at sun.reflect.DelegatingMethodAccessorImpl.invoke\n(DelegatingMethodAccessorImpl.java:25)\n        at java.lang.reflect.Method.invoke(Method.java:324)\n        at org.eclipse.core.launcher.Main.basicRun(Main.java:269)\n        at org.eclipse.core.launcher.Main.run(Main.java:700)\n        at org.eclipse.core.launcher.Main.main(Main.java:684)\njava.lang.NullPointerException",
    "Does this happen every time? Is it semi-repeateable?",
    "It happens every time in my i05051045 install.  I have not tried others.",
    "Aha, the trick is to have the search result view closed at the beginning.",
    "Nope the null pointer was selection related. I inspected the code of the\n2004-05-04 version of ReplaceDialog2 and found the following code at line 113 of\nReplaceDialog2:\n\n\nprotected ReplaceDialog2(Shell parentShell, IFile[] entries, FileSearchPage page) {\n\t\tsuper(parentShell);\n\t\tAssert.isNotNull(entries);\nhere \u003e\u003e\u003e\u003e\tAssert.isNotNull(fPage.getInput());\n\nNote that at the place of the assert, fPage hasn\u0027t been assigned yet. Duh! The\nproblem is already fixed, but it didn\u0027t make it into the I-build, it seems.\n"
  ],
  "commentCreationDates": [
    "2004-05-07T23:33:38+02:00",
    "2004-05-10T10:37:16+02:00",
    "2004-05-10T17:04:45+02:00",
    "2004-05-11T10:19:19+02:00",
    "2004-05-11T11:12:23+02:00"
  ],
  "traces": [
    {
      "exceptionType": "org.eclipse.swt.SWTException",
      "message": "Failed to execute runnable  (java.lang.NullPointerException)",
      "elements": [
        {
          "method": "org.eclipse.swt.SWT.error",
          "source": "SWT.java:2689"
        },
        {
          "method": "org.eclipse.swt.SWT.error",
          "source": "SWT.java:2614"
        },
        {
          "method": "org.eclipse.swt.widgets.Synchronizer.runAsyncMessages",
          "source": "Synchronizer.java:109"
        },
        {
          "method": "org.eclipse.swt.widgets.Display.runAsyncMessages",
          "source": "Display.java:2571"
        },
        {
          "method": "org.eclipse.swt.widgets.Display.readAndDispatch",
          "source": "Display.java:2276"
        },
        {
          "method": "org.eclipse.ui.internal.Workbench.runEventLoop",
          "source": "Workbench.java:1353"
        },
        {
          "method": "org.eclipse.ui.internal.Workbench.runUI",
          "source": "Workbench.java:1324"
        },
        {
          "method": "org.eclipse.ui.internal.Workbench.createAndRunWorkbench",
          "source": "Workbench.java:243"
        },
        {
          "method": "org.eclipse.ui.PlatformUI.createAndRunWorkbench",
          "source": "PlatformUI.java:140"
        },
        {
          "method": "org.eclipse.ui.internal.ide.IDEApplication.run",
          "source": "IDEApplication.java:90"
        },
        {
          "method": "org.eclipse.core.internal.runtime.PlatformActivator$1.run",
          "source": "PlatformActivator.java:283"
        },
        {
          "method": "org.eclipse.core.runtime.adaptor.EclipseStarter.run",
          "source": "EclipseStarter.java:243"
        },
        {
          "method": "org.eclipse.core.runtime.adaptor.EclipseStarter.run",
          "source": "EclipseStarter.java:120"
        },
        {
          "method": "sun.reflect.NativeMethodAccessorImpl.invoke0",
          "source": "Native Method"
        },
        {
          "method": "sun.reflect.NativeMethodAccessorImpl.invoke",
          "source": "NativeMethodAccessorImpl.java:39"
        },
        {
          "method": "sun.reflect.DelegatingMethodAccessorImpl.invoke",
          "source": "DelegatingMethodAccessorImpl.java:25"
        },
        {
          "method": "java.lang.reflect.Method.invoke",
          "source": "Method.java:324"
        },
        {
          "method": "org.eclipse.core.launcher.Main.basicRun",
          "source": "Main.java:269"
        },
        {
          "method": "org.eclipse.core.launcher.Main.run",
          "source": "Main.java:700"
        },
        {
          "method": "org.eclipse.core.launcher.Main.main",
          "source": "Main.java:684"
        }
      ],
      "number": 0,
      "commentIndex": 0,
      "bugId": "61463",
      "date": "2004-05-07T23:33:38+02:00",
      "product": "Platform",
      "component": "Search",
      "severity": "normal"
    },
    {
      "exceptionType": "java.lang.NullPointerException",
      "elements": [
        {
          "method": "org.eclipse.search.internal.ui.text.ReplaceDialog2.\u003cinit\u003e",
          "source": "ReplaceDialog2.java:113"
        },
        {
          "method": "org.eclipse.search.internal.ui.text.ReplaceAction2.run",
          "source": "ReplaceAction2.java:151"
        },
        {
          "method": "org.eclipse.search.internal.ui.text.TextSearchPage$1.run",
          "source": "TextSearchPage.java:237"
        },
        {
          "method": "org.eclipse.swt.widgets.RunnableLock.run",
          "source": "RunnableLock.java:35"
        },
        {
          "method": "org.eclipse.swt.widgets.Synchronizer.runAsyncMessages",
          "source": "Synchronizer.java:106"
        },
        {
          "method": "org.eclipse.swt.widgets.Display.runAsyncMessages",
          "source": "Display.java:2571"
        },
        {
          "method": "org.eclipse.swt.widgets.Display.readAndDispatch",
          "source": "Display.java:2276"
        },
        {
          "method": "org.eclipse.ui.internal.Workbench.runEventLoop",
          "source": "Workbench.java:1353"
        },
        {
          "method": "org.eclipse.ui.internal.Workbench.runUI",
          "source": "Workbench.java:1324"
        },
        {
          "method": "org.eclipse.ui.internal.Workbench.createAndRunWorkbench",
          "source": "Workbench.java:243"
        },
        {
          "method": "org.eclipse.ui.PlatformUI.createAndRunWorkbench",
          "source": "PlatformUI.java:140"
        },
        {
          "method": "org.eclipse.ui.internal.ide.IDEApplication.run",
          "source": "IDEApplication.java:90"
        },
        {
          "method": "org.eclipse.core.internal.runtime.PlatformActivator$1.run",
          "source": "PlatformActivator.java:283"
        },
        {
          "method": "org.eclipse.core.runtime.adaptor.EclipseStarter.run",
          "source": "EclipseStarter.java:243"
        },
        {
          "method": "org.eclipse.core.runtime.adaptor.EclipseStarter.run",
          "source": "EclipseStarter.java:120"
        },
        {
          "method": "sun.reflect.NativeMethodAccessorImpl.invoke0",
          "source": "Native Method"
        },
        {
          "method": "sun.reflect.NativeMethodAccessorImpl.invoke",
          "source": "NativeMethodAccessorImpl.java:39"
        },
        {
          "method": "sun.reflect.DelegatingMethodAccessorImpl.invoke",
          "source": "DelegatingMethodAccessorImpl.java:25"
        },
        {
          "method": "java.lang.reflect.Method.invoke",
          "source": "Method.java:324"
        },
        {
          "method": "org.eclipse.core.launcher.Main.basicRun",
          "source": "Main.java:269"
        },
        {
          "method": "org.eclipse.core.launcher.Main.run",
          "source": "Main.java:700"
        },
        {
          "method": "org.eclipse.core.launcher.Main.main",
          "source": "Main.java:684"
        }
      ],
      "number": 1,
      "commentIndex": 0,
      "bugId": "61463",
      "date": "2004-05-07T23:33:38+02:00",
      "product": "Platform",
      "component": "Search",
      "severity": "normal"
    }
  ],
  "groupId": "61463",
  "bugId": "61463",
  "date": "2004-05-07T23:33:38+02:00",
  "product": "Platform",
  "component": "Search",
  "severity": "normal"
}