{
  "comments": [
    "How to reproduce the problem : \n\n1. Eclipse 4/13 driver + additional plugins.\n2. File-\u003eImport -\u003e External Plug-ins and Fragments\n3. Edit one of the Java file. Make some dummy changes . For example type some\n   spaces. \n4. Save\n\n    Get the following in the console window.\n\norg.eclipse.swt.SWTException: Invalid thread access\n        at org.eclipse.swt.SWT.error(SWT.java:2659)\n        at org.eclipse.swt.SWT.error(SWT.java(Inlined Compiled Code))\n        at org.eclipse.swt.SWT.error(SWT.java(Inlined Compiled Code))\n        at org.eclipse.swt.widgets.Display.error(Display.java(Inlined Compiled C\node))\n        at org.eclipse.swt.widgets.Display.checkDevice(Display.java(Inlined Comp\niled Code))\n        at org.eclipse.swt.widgets.Display.getActiveShell(Display.java(Inlined C\nompiled Code))\n        at org.eclipse.ui.internal.Workbench.getActiveWorkbenchWindow(Workbench.\njava(Compiled Code))\n        at org.eclipse.jdt.internal.ui.text.HTMLPrinter.insertPageProlog(HTMLPri\nnter.java:97)\n        at org.eclipse.jdt.internal.ui.text.java.hover.JavadocHover.getHoverInfo\n(JavadocHover.java:74)\n        at org.eclipse.jdt.internal.ui.text.java.hover.AbstractJavaEditorTextHov\ner.getHoverInfo(AbstractJavaEditorTextHover.java:119)\n        at org.eclipse.jdt.internal.ui.text.java.hover.BestMatchHover.getHoverIn\nfo(BestMatchHover.java:102)\n        at org.eclipse.jdt.internal.ui.text.java.hover.JavaEditorTextHoverProxy.\ngetHoverInfo(JavaEditorTextHoverProxy.java:69)\n        at org.eclipse.jface.text.TextViewerHoverManager$4.run(TextViewerHoverMa\nnager.java:161)\norg.eclipse.swt.SWTException: Invalid thread access\n        at org.eclipse.swt.SWT.error(SWT.java:2659)\n        at org.eclipse.swt.SWT.error(SWT.java(Inlined Compiled Code))\n        at org.eclipse.swt.SWT.error(SWT.java(Inlined Compiled Code))\n        at org.eclipse.swt.widgets.Display.error(Display.java(Inlined Compiled C\node))\n        at org.eclipse.swt.widgets.Display.checkDevice(Display.java(Inlined Comp\niled Code))\n        at org.eclipse.swt.widgets.Display.getActiveShell(Display.java(Inlined C\nompiled Code))\n        at org.eclipse.ui.internal.Workbench.getActiveWorkbenchWindow(Workbench.\njava(Compiled Code))\n        at org.eclipse.jdt.internal.ui.text.HTMLPrinter.insertPageProlog(HTMLPri\nnter.java:97)\n        at org.eclipse.jdt.internal.ui.text.HTMLPrinter.addPageProlog(HTMLPrinte\nr.java:110)\n        at org.eclipse.jdt.internal.ui.text.java.hover.AnnotationHover.formatMes\nsage(AnnotationHover.java:49)\n        at org.eclipse.jdt.internal.ui.text.java.hover.AnnotationHover.getHoverI\nnfo(AnnotationHover.java:90)\n        at org.eclipse.jdt.internal.ui.text.java.hover.BestMatchHover.getHoverIn\nfo(BestMatchHover.java:102)\n        at org.eclipse.jdt.internal.ui.text.java.hover.JavaEditorTextHoverProxy.\ngetHoverInfo(JavaEditorTextHoverProxy.java:69)\n        at org.eclipse.jface.text.TextViewerHoverManager$4.run(TextViewerHoverMa\nnager.java:161)\norg.eclipse.swt.SWTException: Invalid thread access\n        at org.eclipse.swt.SWT.error(SWT.java:2659)\n        at org.eclipse.swt.SWT.error(SWT.java(Inlined Compiled Code))\n        at org.eclipse.swt.SWT.error(SWT.java(Inlined Compiled Code))\n        at org.eclipse.swt.widgets.Display.error(Display.java(Inlined Compiled C\node))\n        at org.eclipse.swt.widgets.Display.checkDevice(Display.java(Inlined Comp\niled Code))\n        at org.eclipse.swt.widgets.Display.getActiveShell(Display.java(Inlined C\nompiled Code))\n        at org.eclipse.ui.internal.Workbench.getActiveWorkbenchWindow(Workbench.\njava(Compiled Code))\n        at org.eclipse.jdt.internal.ui.text.HTMLPrinter.insertPageProlog(HTMLPri\nnter.java:97)\n        at org.eclipse.jdt.internal.ui.text.HTMLPrinter.addPageProlog(HTMLPrinte\nr.java:110)\n        at org.eclipse.jdt.internal.ui.text.java.hover.AnnotationHover.formatMes\nsage(AnnotationHover.java:49)\n        at org.eclipse.jdt.internal.ui.text.java.hover.AnnotationHover.getHoverI\nnfo(AnnotationHover.java:90)\n        at org.eclipse.jdt.internal.ui.text.java.hover.BestMatchHover.getHoverIn\nfo(BestMatchHover.java:102)\n        at org.eclipse.jdt.internal.ui.text.java.hover.JavaEditorTextHoverProxy.\ngetHoverInfo(JavaEditorTextHoverProxy.java:69)\n        at org.eclipse.jface.text.TextViewerHoverManager$4.run(TextViewerHoverMa\nnager.java:161)",
    "has been fixed a while ago"
  ],
  "commentCreationDates": [
    "2004-05-08T01:06:32+02:00",
    "2004-05-10T11:17:29+02:00"
  ],
  "traces": [
    {
      "exceptionType": "org.eclipse.swt.SWTException",
      "message": "Invalid thread access",
      "elements": [
        {
          "method": "org.eclipse.swt.SWT.error",
          "source": "SWT.java:2659"
        },
        {
          "method": "org.eclipse.swt.SWT.error",
          "source": "SWT.java(Inlined Compiled Code)"
        },
        {
          "method": "org.eclipse.swt.SWT.error",
          "source": "SWT.java(Inlined Compiled Code)"
        },
        {
          "method": "org.eclipse.swt.widgets.Display.error",
          "source": "Display.java(Inlined Compiled C ode)"
        },
        {
          "method": "org.eclipse.swt.widgets.Display.checkDevice",
          "source": "Display.java(Inlined Comp iled Code)"
        },
        {
          "method": "org.eclipse.swt.widgets.Display.getActiveShell",
          "source": "Display.java(Inlined C ompiled Code)"
        },
        {
          "method": "org.eclipse.ui.internal.Workbench.getActiveWorkbenchWindow",
          "source": "Workbench. java(Compiled Code)"
        },
        {
          "method": "org.eclipse.jdt.internal.ui.text.HTMLPrinter.insertPageProlog",
          "source": "HTMLPri nter.java:97"
        },
        {
          "method": "org.eclipse.jdt.internal.ui.text.java.hover.JavadocHover.getHoverInfo",
          "source": "JavadocHover.java:74"
        },
        {
          "method": "org.eclipse.jdt.internal.ui.text.java.hover.AbstractJavaEditorTextHover.getHoverInfo",
          "source": "AbstractJavaEditorTextHover.java:119"
        },
        {
          "method": "org.eclipse.jdt.internal.ui.text.java.hover.BestMatchHover.getHoverInfo",
          "source": "BestMatchHover.java:102"
        },
        {
          "method": "org.eclipse.jdt.internal.ui.text.java.hover.JavaEditorTextHoverProxy.getHoverInfo",
          "source": "JavaEditorTextHoverProxy.java:69"
        },
        {
          "method": "org.eclipse.jface.text.TextViewerHoverManager$4.run",
          "source": "TextViewerHoverMa nager.java:161"
        }
      ],
      "number": 0,
      "commentIndex": 0,
      "bugId": "61473",
      "date": "2004-05-08T01:06:32+02:00",
      "product": "JDT",
      "component": "Text",
      "severity": "normal"
    },
    {
      "exceptionType": "org.eclipse.swt.SWTException",
      "message": "Invalid thread access",
      "elements": [
        {
          "method": "org.eclipse.swt.SWT.error",
          "source": "SWT.java:2659"
        },
        {
          "method": "org.eclipse.swt.SWT.error",
          "source": "SWT.java(Inlined Compiled Code)"
        },
        {
          "method": "org.eclipse.swt.SWT.error",
          "source": "SWT.java(Inlined Compiled Code)"
        },
        {
          "method": "org.eclipse.swt.widgets.Display.error",
          "source": "Display.java(Inlined Compiled C ode)"
        },
        {
          "method": "org.eclipse.swt.widgets.Display.checkDevice",
          "source": "Display.java(Inlined Comp iled Code)"
        },
        {
          "method": "org.eclipse.swt.widgets.Display.getActiveShell",
          "source": "Display.java(Inlined C ompiled Code)"
        },
        {
          "method": "org.eclipse.ui.internal.Workbench.getActiveWorkbenchWindow",
          "source": "Workbench. java(Compiled Code)"
        },
        {
          "method": "org.eclipse.jdt.internal.ui.text.HTMLPrinter.insertPageProlog",
          "source": "HTMLPri nter.java:97"
        },
        {
          "method": "org.eclipse.jdt.internal.ui.text.HTMLPrinter.addPageProlog",
          "source": "HTMLPrinte r.java:110"
        },
        {
          "method": "org.eclipse.jdt.internal.ui.text.java.hover.AnnotationHover.formatMessage",
          "source": "AnnotationHover.java:49"
        },
        {
          "method": "org.eclipse.jdt.internal.ui.text.java.hover.AnnotationHover.getHoverInfo",
          "source": "AnnotationHover.java:90"
        },
        {
          "method": "org.eclipse.jdt.internal.ui.text.java.hover.BestMatchHover.getHoverInfo",
          "source": "BestMatchHover.java:102"
        },
        {
          "method": "org.eclipse.jdt.internal.ui.text.java.hover.JavaEditorTextHoverProxy.getHoverInfo",
          "source": "JavaEditorTextHoverProxy.java:69"
        },
        {
          "method": "org.eclipse.jface.text.TextViewerHoverManager$4.run",
          "source": "TextViewerHoverMa nager.java:161"
        }
      ],
      "number": 1,
      "commentIndex": 0,
      "bugId": "61473",
      "date": "2004-05-08T01:06:32+02:00",
      "product": "JDT",
      "component": "Text",
      "severity": "normal"
    },
    {
      "exceptionType": "org.eclipse.swt.SWTException",
      "message": "Invalid thread access",
      "elements": [
        {
          "method": "org.eclipse.swt.SWT.error",
          "source": "SWT.java:2659"
        },
        {
          "method": "org.eclipse.swt.SWT.error",
          "source": "SWT.java(Inlined Compiled Code)"
        },
        {
          "method": "org.eclipse.swt.SWT.error",
          "source": "SWT.java(Inlined Compiled Code)"
        },
        {
          "method": "org.eclipse.swt.widgets.Display.error",
          "source": "Display.java(Inlined Compiled C ode)"
        },
        {
          "method": "org.eclipse.swt.widgets.Display.checkDevice",
          "source": "Display.java(Inlined Comp iled Code)"
        },
        {
          "method": "org.eclipse.swt.widgets.Display.getActiveShell",
          "source": "Display.java(Inlined C ompiled Code)"
        },
        {
          "method": "org.eclipse.ui.internal.Workbench.getActiveWorkbenchWindow",
          "source": "Workbench. java(Compiled Code)"
        },
        {
          "method": "org.eclipse.jdt.internal.ui.text.HTMLPrinter.insertPageProlog",
          "source": "HTMLPri nter.java:97"
        },
        {
          "method": "org.eclipse.jdt.internal.ui.text.HTMLPrinter.addPageProlog",
          "source": "HTMLPrinte r.java:110"
        },
        {
          "method": "org.eclipse.jdt.internal.ui.text.java.hover.AnnotationHover.formatMessage",
          "source": "AnnotationHover.java:49"
        },
        {
          "method": "org.eclipse.jdt.internal.ui.text.java.hover.AnnotationHover.getHoverInfo",
          "source": "AnnotationHover.java:90"
        },
        {
          "method": "org.eclipse.jdt.internal.ui.text.java.hover.BestMatchHover.getHoverInfo",
          "source": "BestMatchHover.java:102"
        },
        {
          "method": "org.eclipse.jdt.internal.ui.text.java.hover.JavaEditorTextHoverProxy.getHoverInfo",
          "source": "JavaEditorTextHoverProxy.java:69"
        },
        {
          "method": "org.eclipse.jface.text.TextViewerHoverManager$4.run",
          "source": "TextViewerHoverMa nager.java:161"
        }
      ],
      "number": 2,
      "commentIndex": 0,
      "bugId": "61473",
      "date": "2004-05-08T01:06:32+02:00",
      "product": "JDT",
      "component": "Text",
      "severity": "normal"
    }
  ],
  "groupId": "61473",
  "bugId": "61473",
  "date": "2004-05-08T01:06:32+02:00",
  "product": "JDT",
  "component": "Text",
  "severity": "normal"
}