{
  "comments": [
    "To reproduce : \n\n1. Eclipse 04/13 + plugins\n2. Check-out a plugin from CVS\n3. Go to plug-in development perspective\n4. Edit one of the .java file\n5. Double-click on one of the methods from the Outline view\n6. Enter spaces.\n7. CTRL + S to save\n\n   See the following in the console : \n\n !ENTRY org.eclipse.jdt.core 4 4 May 07, 2004 16:45:09.09\n!MESSAGE Background Indexer Crash Recovery\n!STACK 0\njava.lang.IllegalArgumentException: Buffer size \u003c\u003d 0\n        at java.io.BufferedInputStream.\u003cinit\u003e(BufferedInputStream.java(Inlined C\nompiled Code))\n        at java.io.BufferedInputStream.\u003cinit\u003e(BufferedInputStream.java(Inlined C\nompiled Code))\n        at org.eclipse.jdt.internal.core.index.DiskIndex.readCategoryTable(DiskI\nndex.java(Compiled Code))\n        at org.eclipse.jdt.internal.core.index.DiskIndex.mergeCategory(DiskIndex\n.java:360)\n        at org.eclipse.jdt.internal.core.index.DiskIndex.mergeCategories(DiskInd\nex.java:352)\n        at org.eclipse.jdt.internal.core.index.DiskIndex.mergeWith(DiskIndex.jav\na(Compiled Code))\n        at org.eclipse.jdt.internal.core.index.Index.save(Index.java(Inlined Com\npiled Code))\n        at org.eclipse.jdt.internal.core.search.indexing.IndexManager.saveIndex(\nIndexManager.java(Compiled Code))\n        at org.eclipse.jdt.internal.core.search.indexing.SaveIndex.execute(SaveI\nndex.java:40)\n        at org.eclipse.jdt.internal.core.search.processing.JobManager.run(JobMan\nager.java:340)\n        at java.lang.Thread.run(Thread.java:566)\njava.lang.IllegalArgumentException: Buffer size \u003c\u003d 0\n        at java.io.BufferedInputStream.\u003cinit\u003e(BufferedInputStream.java(Inlined C\nompiled Code))\n        at java.io.BufferedInputStream.\u003cinit\u003e(BufferedInputStream.java(Inlined C\nompiled Code))\n        at org.eclipse.jdt.internal.core.index.DiskIndex.readCategoryTable(DiskI\nndex.java(Compiled Code))\n        at org.eclipse.jdt.internal.core.index.DiskIndex.mergeCategory(DiskIndex\n.java:360)\n        at org.eclipse.jdt.internal.core.index.DiskIndex.mergeCategories(DiskInd\nex.java:352)\n        at org.eclipse.jdt.internal.core.index.DiskIndex.mergeWith(DiskIndex.jav\na(Compiled Code))\n        at org.eclipse.jdt.internal.core.index.Index.save(Index.java(Inlined Com\npiled Code))\n        at org.eclipse.jdt.internal.core.search.indexing.IndexManager.saveIndex(\nIndexManager.java(Compiled Code))\n        at org.eclipse.jdt.internal.core.search.indexing.SaveIndex.execute(SaveI\nndex.java:40)\n        at org.eclipse.jdt.internal.core.search.processing.JobManager.run(JobMan\nager.java:340)\n        at java.lang.Thread.run(Thread.java:566)",
    "Which VM are you using?\n\nSuspect this is a duplicate of bug 57419 \u0026 bug 57861.",
    "\n\n*** This bug has been marked as a duplicate of 57419 ***"
  ],
  "commentCreationDates": [
    "2004-05-08T01:57:27+02:00",
    "2004-05-10T16:52:12+02:00",
    "2004-05-11T16:43:47+02:00"
  ],
  "traces": [
    {
      "exceptionType": "java.lang.IllegalArgumentException",
      "message": "Buffer size \u003c\u003d 0",
      "elements": [
        {
          "method": "java.io.BufferedInputStream.\u003cinit\u003e",
          "source": "BufferedInputStream.java(Inlined C ompiled Code)"
        },
        {
          "method": "java.io.BufferedInputStream.\u003cinit\u003e",
          "source": "BufferedInputStream.java(Inlined C ompiled Code)"
        },
        {
          "method": "org.eclipse.jdt.internal.core.index.DiskIndex.readCategoryTable",
          "source": "DiskI ndex.java(Compiled Code)"
        },
        {
          "method": "org.eclipse.jdt.internal.core.index.DiskIndex.mergeCategory",
          "source": "DiskIndex .java:360"
        },
        {
          "method": "org.eclipse.jdt.internal.core.index.DiskIndex.mergeCategories",
          "source": "DiskInd ex.java:352"
        },
        {
          "method": "org.eclipse.jdt.internal.core.index.DiskIndex.mergeWith",
          "source": "DiskIndex.jav a(Compiled Code)"
        },
        {
          "method": "org.eclipse.jdt.internal.core.index.Index.save",
          "source": "Index.java(Inlined Com piled Code)"
        },
        {
          "method": "org.eclipse.jdt.internal.core.search.indexing.IndexManager.saveIndex",
          "source": " IndexManager.java(Compiled Code)"
        },
        {
          "method": "org.eclipse.jdt.internal.core.search.indexing.SaveIndex.execute",
          "source": "SaveI ndex.java:40"
        },
        {
          "method": "org.eclipse.jdt.internal.core.search.processing.JobManager.run",
          "source": "JobMan ager.java:340"
        },
        {
          "method": "java.lang.Thread.run",
          "source": "Thread.java:566"
        }
      ],
      "number": 0,
      "commentIndex": 0,
      "bugId": "61481",
      "duplicateId": "57419",
      "date": "2004-05-08T01:57:27+02:00",
      "product": "JDT",
      "component": "Core",
      "severity": "normal"
    },
    {
      "exceptionType": "java.lang.IllegalArgumentException",
      "message": "Buffer size \u003c\u003d 0",
      "elements": [
        {
          "method": "java.io.BufferedInputStream.\u003cinit\u003e",
          "source": "BufferedInputStream.java(Inlined C ompiled Code)"
        },
        {
          "method": "java.io.BufferedInputStream.\u003cinit\u003e",
          "source": "BufferedInputStream.java(Inlined C ompiled Code)"
        },
        {
          "method": "org.eclipse.jdt.internal.core.index.DiskIndex.readCategoryTable",
          "source": "DiskI ndex.java(Compiled Code)"
        },
        {
          "method": "org.eclipse.jdt.internal.core.index.DiskIndex.mergeCategory",
          "source": "DiskIndex .java:360"
        },
        {
          "method": "org.eclipse.jdt.internal.core.index.DiskIndex.mergeCategories",
          "source": "DiskInd ex.java:352"
        },
        {
          "method": "org.eclipse.jdt.internal.core.index.DiskIndex.mergeWith",
          "source": "DiskIndex.jav a(Compiled Code)"
        },
        {
          "method": "org.eclipse.jdt.internal.core.index.Index.save",
          "source": "Index.java(Inlined Com piled Code)"
        },
        {
          "method": "org.eclipse.jdt.internal.core.search.indexing.IndexManager.saveIndex",
          "source": " IndexManager.java(Compiled Code)"
        },
        {
          "method": "org.eclipse.jdt.internal.core.search.indexing.SaveIndex.execute",
          "source": "SaveI ndex.java:40"
        },
        {
          "method": "org.eclipse.jdt.internal.core.search.processing.JobManager.run",
          "source": "JobMan ager.java:340"
        },
        {
          "method": "java.lang.Thread.run",
          "source": "Thread.java:566"
        }
      ],
      "number": 1,
      "commentIndex": 0,
      "bugId": "61481",
      "duplicateId": "57419",
      "date": "2004-05-08T01:57:27+02:00",
      "product": "JDT",
      "component": "Core",
      "severity": "normal"
    }
  ],
  "groupId": "57419",
  "bugId": "61481",
  "duplicateId": "57419",
  "date": "2004-05-08T01:57:27+02:00",
  "product": "JDT",
  "component": "Core",
  "severity": "normal"
}