{
  "comments": [
    "With build 2004-05-11, IBM J9SE VM (build 2.1, J2RE 1.4.1 IBM J9 build 20040121\n(JIT enabled))\n\n1) I changed two files in the org.eclipse.search project.\n2) Used team-synchronize from the package explorer (selection on the project).\n3) Selected the folder the two changed files are in\n4) Selected \"commit\" from the context menu.\n5) observe: I get an exception:\n\n!ENTRY org.eclipse.ui 4 0 May 11, 2004 10:24:26.70\n!MESSAGE java.lang.NullPointerException\n!STACK 0\njava.lang.NullPointerException\n        at java.lang.Throwable.\u003cinit\u003e(Throwable.java)\n        at java.lang.Throwable.\u003cinit\u003e(Throwable.java)\n        at java.lang.NullPointerException.\u003cinit\u003e(NullPointerException.java:60)\n        at org.eclipse.jface.resource.ImageRegistry.get(ImageRegistry.java)\n        at org.eclipse.team.internal.ui.dialogs.DetailsDialog.createDialogArea(D\netailsDialog.java:140)\n        at org.eclipse.jface.dialogs.Dialog.createContents(Dialog.java:631)\n        at org.eclipse.jface.window.Window.create(Window.java:348)\n        at org.eclipse.jface.dialogs.Dialog.create(Dialog.java:924)\n        at org.eclipse.jface.window.Window.open(Window.java:637)\n        at org.eclipse.team.internal.ccvs.ui.repo.RepositoryManager$2.run(Reposi\ntoryManager.java:552)\n        at org.eclipse.swt.widgets.Synchronizer.syncExec(Synchronizer.java:135)\n        at org.eclipse.ui.internal.UISynchronizer.syncExec(UISynchronizer.java)\n        at org.eclipse.swt.widgets.Display.syncExec(Display.java)\n        at org.eclipse.team.internal.ccvs.ui.repo.RepositoryManager.promptForCom\nment(RepositoryManager.java:550)\n        at org.eclipse.team.internal.ccvs.ui.subscriber.WorkspaceCommitOperation\n.promptForComment(WorkspaceCommitOperation.java:267)\n        at org.eclipse.team.internal.ccvs.ui.subscriber.WorkspaceCommitOperation\n.promptForUnaddedHandling(WorkspaceCommitOperation.java:284)\n        at org.eclipse.team.internal.ccvs.ui.subscriber.WorkspaceCommitOperation\n.getSyncInfoSet(WorkspaceCommitOperation.java:87)\n        at org.eclipse.team.internal.ccvs.ui.subscriber.WorkspaceCommitOperation\n.shouldRun(WorkspaceCommitOperation.java:72)\n        at org.eclipse.team.ui.TeamOperation.run(TeamOperation.java:92)\n        at org.eclipse.team.ui.synchronize.SynchronizeModelAction.run(Synchroniz\neModelAction.java:110)\n        at org.eclipse.jface.action.Action.runWithEvent(Action.java:881)\n        at org.eclipse.jface.action.ActionContributionItem.handleWidgetSelection\n(ActionContributionItem.java:891)\n        at org.eclipse.jface.action.ActionContributionItem.access$2(ActionContri\nbutionItem.java:842)\n        at org.eclipse.jface.action.ActionContributionItem$6.handleEvent(ActionC\nontributionItem.java:761)\n        at org.eclipse.swt.widgets.EventTable.sendEvent(EventTable.java)\n        at org.eclipse.swt.widgets.Widget.sendEvent(Widget.java)\n        at org.eclipse.swt.widgets.Display.runDeferredEvents(Display.java)\n        at org.eclipse.swt.widgets.Display.readAndDispatch(Display.java)\n        at org.eclipse.ui.internal.Workbench.runEventLoop(Workbench.java:1353)\n        at org.eclipse.ui.internal.Workbench.runUI(Workbench.java:1324)\n        at org.eclipse.ui.internal.Workbench.createAndRunWorkbench(Workbench.jav\na:243)\n        at org.eclipse.ui.PlatformUI.createAndRunWorkbench(PlatformUI.java:141)\n        at org.eclipse.ui.internal.ide.IDEApplication.run(IDEApplication.java:90\n)\n        at org.eclipse.core.internal.runtime.PlatformActivator$1.run(PlatformAct\nivator.java:298)\n        at org.eclipse.core.runtime.adaptor.EclipseStarter.run(EclipseStarter.ja\nva:249)\n        at org.eclipse.core.runtime.adaptor.EclipseStarter.run(EclipseStarter.ja\nva:126)\n        at sun.reflect.NativeMethodAccessorImpl.invoke0(Native Method)\n        at sun.reflect.NativeMethodAccessorImpl.invoke(NativeMethodAccessorImpl.\njava:79)\n        at sun.reflect.DelegatingMethodAccessorImpl.invoke(DelegatingMethodAcces\nsorImpl.java:41)\n        at java.lang.reflect.Method.invoke(Method.java:386)\n        at org.eclipse.core.launcher.Main.basicRun(Main.java:269)\n        at org.eclipse.core.launcher.Main.run(Main.java:722)\n        at org.eclipse.core.launcher.Main.main(Main.java:706)\njava.lang.NullPointerException\n\nI consider this a blocker, because it indeed \"blocks development or testing\".",
    "Nobody sets the imageKey on the ReleaseCommentDialog.",
    "Created an attachment (id\u003d10495)\nFixed jar for org.eclipse.team.ui plugin\n",
    "There was a change in behavior of the image registry which surfaced this bug. \nI have attached the fixed jar, released the changes to HEAD and tagged the map \nfor the next rebuild."
  ],
  "commentCreationDates": [
    "2004-05-11T10:45:09+02:00",
    "2004-05-11T11:34:44+02:00",
    "2004-05-11T15:53:01+02:00",
    "2004-05-11T15:54:05+02:00"
  ],
  "traces": [
    {
      "exceptionType": "java.lang.NullPointerException",
      "elements": [
        {
          "method": "java.lang.Throwable.\u003cinit\u003e",
          "source": "Throwable.java"
        },
        {
          "method": "java.lang.Throwable.\u003cinit\u003e",
          "source": "Throwable.java"
        },
        {
          "method": "java.lang.NullPointerException.\u003cinit\u003e",
          "source": "NullPointerException.java:60"
        },
        {
          "method": "org.eclipse.jface.resource.ImageRegistry.get",
          "source": "ImageRegistry.java"
        },
        {
          "method": "org.eclipse.team.internal.ui.dialogs.DetailsDialog.createDialogArea",
          "source": "D etailsDialog.java:140"
        },
        {
          "method": "org.eclipse.jface.dialogs.Dialog.createContents",
          "source": "Dialog.java:631"
        },
        {
          "method": "org.eclipse.jface.window.Window.create",
          "source": "Window.java:348"
        },
        {
          "method": "org.eclipse.jface.dialogs.Dialog.create",
          "source": "Dialog.java:924"
        },
        {
          "method": "org.eclipse.jface.window.Window.open",
          "source": "Window.java:637"
        },
        {
          "method": "org.eclipse.team.internal.ccvs.ui.repo.RepositoryManager$2.run",
          "source": "Reposi toryManager.java:552"
        },
        {
          "method": "org.eclipse.swt.widgets.Synchronizer.syncExec",
          "source": "Synchronizer.java:135"
        },
        {
          "method": "org.eclipse.ui.internal.UISynchronizer.syncExec",
          "source": "UISynchronizer.java"
        },
        {
          "method": "org.eclipse.swt.widgets.Display.syncExec",
          "source": "Display.java"
        },
        {
          "method": "org.eclipse.team.internal.ccvs.ui.repo.RepositoryManager.promptForComment",
          "source": "RepositoryManager.java:550"
        },
        {
          "method": "org.eclipse.team.internal.ccvs.ui.subscriber.WorkspaceCommitOperation.promptForComment",
          "source": "WorkspaceCommitOperation.java:267"
        },
        {
          "method": "org.eclipse.team.internal.ccvs.ui.subscriber.WorkspaceCommitOperation.promptForUnaddedHandling",
          "source": "WorkspaceCommitOperation.java:284"
        },
        {
          "method": "org.eclipse.team.internal.ccvs.ui.subscriber.WorkspaceCommitOperation.getSyncInfoSet",
          "source": "WorkspaceCommitOperation.java:87"
        },
        {
          "method": "org.eclipse.team.internal.ccvs.ui.subscriber.WorkspaceCommitOperation.shouldRun",
          "source": "WorkspaceCommitOperation.java:72"
        },
        {
          "method": "org.eclipse.team.ui.TeamOperation.run",
          "source": "TeamOperation.java:92"
        },
        {
          "method": "org.eclipse.team.ui.synchronize.SynchronizeModelAction.run",
          "source": "Synchroniz eModelAction.java:110"
        },
        {
          "method": "org.eclipse.jface.action.Action.runWithEvent",
          "source": "Action.java:881"
        },
        {
          "method": "org.eclipse.jface.action.ActionContributionItem.handleWidgetSelection",
          "source": "ActionContributionItem.java:891"
        },
        {
          "method": "org.eclipse.jface.action.ActionContributionItem.access$2",
          "source": "ActionContri butionItem.java:842"
        },
        {
          "method": "org.eclipse.jface.action.ActionContributionItem$6.handleEvent",
          "source": "ActionC ontributionItem.java:761"
        },
        {
          "method": "org.eclipse.swt.widgets.EventTable.sendEvent",
          "source": "EventTable.java"
        },
        {
          "method": "org.eclipse.swt.widgets.Widget.sendEvent",
          "source": "Widget.java"
        },
        {
          "method": "org.eclipse.swt.widgets.Display.runDeferredEvents",
          "source": "Display.java"
        },
        {
          "method": "org.eclipse.swt.widgets.Display.readAndDispatch",
          "source": "Display.java"
        },
        {
          "method": "org.eclipse.ui.internal.Workbench.runEventLoop",
          "source": "Workbench.java:1353"
        },
        {
          "method": "org.eclipse.ui.internal.Workbench.runUI",
          "source": "Workbench.java:1324"
        },
        {
          "method": "org.eclipse.ui.internal.Workbench.createAndRunWorkbench",
          "source": "Workbench.jav a:243"
        },
        {
          "method": "org.eclipse.ui.PlatformUI.createAndRunWorkbench",
          "source": "PlatformUI.java:141"
        },
        {
          "method": "org.eclipse.ui.internal.ide.IDEApplication.run",
          "source": "IDEApplication.java:90 "
        },
        {
          "method": "org.eclipse.core.internal.runtime.PlatformActivator$1.run",
          "source": "PlatformAct ivator.java:298"
        },
        {
          "method": "org.eclipse.core.runtime.adaptor.EclipseStarter.run",
          "source": "EclipseStarter.ja va:249"
        },
        {
          "method": "org.eclipse.core.runtime.adaptor.EclipseStarter.run",
          "source": "EclipseStarter.ja va:126"
        },
        {
          "method": "sun.reflect.NativeMethodAccessorImpl.invoke0",
          "source": "Native Method"
        },
        {
          "method": "sun.reflect.NativeMethodAccessorImpl.invoke",
          "source": "NativeMethodAccessorImpl. java:79"
        },
        {
          "method": "sun.reflect.DelegatingMethodAccessorImpl.invoke",
          "source": "DelegatingMethodAcces sorImpl.java:41"
        },
        {
          "method": "java.lang.reflect.Method.invoke",
          "source": "Method.java:386"
        },
        {
          "method": "org.eclipse.core.launcher.Main.basicRun",
          "source": "Main.java:269"
        },
        {
          "method": "org.eclipse.core.launcher.Main.run",
          "source": "Main.java:722"
        },
        {
          "method": "org.eclipse.core.launcher.Main.main",
          "source": "Main.java:706"
        }
      ],
      "number": 0,
      "commentIndex": 0,
      "bugId": "61697",
      "date": "2004-05-11T10:45:09+02:00",
      "product": "Platform",
      "component": "Team",
      "severity": "blocker"
    }
  ],
  "groupId": "61697",
  "bugId": "61697",
  "date": "2004-05-11T10:45:09+02:00",
  "product": "Platform",
  "component": "Team",
  "severity": "blocker"
}