{
  "comments": [
    "I had a number of editors open, \"linked\" to History View, and as I closed the \neditors, noticed these log messages being written to console. Didn\u0027t seem to \nhurt anything, just thought I\u0027d note them. This was on 05/06 build. \n\n\u003d \u003d \u003d \u003d \u003d\nFailed to execute runnable (org.eclipse.jface.util.\nAssert$AssertionFailedException: null argument;)\n!ENTRY org.eclipse.ui 4 4 May 11, 2004 07:25:28.936\n!MESSAGE *** SWT nested exception\n*** SWT nested exception\nReason:\n!ENTRY org.eclipse.ui 4 0 May 11, 2004 07:25:28.936\n!MESSAGE null argument;\n!STACK 0\norg.eclipse.jface.util.Assert$AssertionFailedException: null argument;\n        at org.eclipse.jface.util.Assert.isNotNull(Assert.java:139)\n        at org.eclipse.jface.util.Assert.isNotNull(Assert.java:116)\n        at org.eclipse.jface.viewers.StructuredViewer.\nassertElementsNotNull(StructuredViewer.java:217)\n        at org.eclipse.jface.viewers.TableViewer.add(TableViewer.java:111)\n        at org.eclipse.team.internal.ccvs.ui.HistoryView$3.run(HistoryView.java:\n206)\n        at org.eclipse.swt.widgets.RunnableLock.run(RunnableLock.java:35)\n        at org.eclipse.swt.widgets.Synchronizer.runAsyncMessages(Synchronizer.\njava:106)\n        at org.eclipse.swt.widgets.Display.runAsyncMessages(Display.java:2571)\n        at org.eclipse.swt.widgets.Display.readAndDispatch(Display.java:2276)\n        at org.eclipse.ui.internal.Workbench.runEventLoop(Workbench.java:1353)\n        at org.eclipse.ui.internal.Workbench.runUI(Workbench.java:1324)\n        at org.eclipse.ui.internal.Workbench.createAndRunWorkbench(Workbench.\njava:243)\n        at org.eclipse.ui.PlatformUI.createAndRunWorkbench(PlatformUI.java:140)\n        at org.eclipse.ui.internal.ide.IDEApplication.run(IDEApplication.java:\n90)\n        at org.eclipse.core.internal.runtime.PlatformActivator$1.\nrun(PlatformActivator.java:283)\n        at org.eclipse.core.runtime.adaptor.EclipseStarter.run(EclipseStarter.\njava:242)\n        at org.eclipse.core.runtime.adaptor.EclipseStarter.run(EclipseStarter.\njava:119)\n        at sun.reflect.NativeMethodAccessorImpl.invoke0(Native Method)\n        at sun.reflect.NativeMethodAccessorImpl.invoke(NativeMethodAccessorImpl.\njava:39)\n        at sun.reflect.DelegatingMethodAccessorImpl.\ninvoke(DelegatingMethodAccessorImpl.java:25)\n        at java.lang.reflect.Method.invoke(Method.java:324)\n        at org.eclipse.core.launcher.Main.basicRun(Main.java:269)\n        at org.eclipse.core.launcher.Main.run(Main.java:700)\n        at org.eclipse.core.launcher.Main.main(Main.java:684)\nnull argument;",
    "This is interesting because the line just before the viewer.add() performs a\nviewer.isDisposed() check. Not how the disposed viewer could add in this case\nthough.",
    "Fis released to HEAD. Problem was an instance variable that was set and then \naccessed from an asyncExec. The instance variable must have been nulled before \nthe async ran."
  ],
  "commentCreationDates": [
    "2004-05-11T13:44:43+02:00",
    "2004-05-11T20:56:53+02:00",
    "2004-05-11T21:13:19+02:00"
  ],
  "traces": [
    {
      "exceptionType": "org.eclipse.jface.util.Assert$AssertionFailedException",
      "message": "null argument;",
      "elements": [
        {
          "method": "org.eclipse.jface.util.Assert.isNotNull",
          "source": "Assert.java:139"
        },
        {
          "method": "org.eclipse.jface.util.Assert.isNotNull",
          "source": "Assert.java:116"
        },
        {
          "method": "org.eclipse.jface.viewers.StructuredViewer.assertElementsNotNull",
          "source": "StructuredViewer.java:217"
        },
        {
          "method": "org.eclipse.jface.viewers.TableViewer.add",
          "source": "TableViewer.java:111"
        },
        {
          "method": "org.eclipse.team.internal.ccvs.ui.HistoryView$3.run",
          "source": "HistoryView.java: 206"
        },
        {
          "method": "org.eclipse.swt.widgets.RunnableLock.run",
          "source": "RunnableLock.java:35"
        },
        {
          "method": "org.eclipse.swt.widgets.Synchronizer.runAsyncMessages",
          "source": "Synchronizer. java:106"
        },
        {
          "method": "org.eclipse.swt.widgets.Display.runAsyncMessages",
          "source": "Display.java:2571"
        },
        {
          "method": "org.eclipse.swt.widgets.Display.readAndDispatch",
          "source": "Display.java:2276"
        },
        {
          "method": "org.eclipse.ui.internal.Workbench.runEventLoop",
          "source": "Workbench.java:1353"
        },
        {
          "method": "org.eclipse.ui.internal.Workbench.runUI",
          "source": "Workbench.java:1324"
        },
        {
          "method": "org.eclipse.ui.internal.Workbench.createAndRunWorkbench",
          "source": "Workbench. java:243"
        },
        {
          "method": "org.eclipse.ui.PlatformUI.createAndRunWorkbench",
          "source": "PlatformUI.java:140"
        },
        {
          "method": "org.eclipse.ui.internal.ide.IDEApplication.run",
          "source": "IDEApplication.java: 90"
        },
        {
          "method": "org.eclipse.core.internal.runtime.PlatformActivator$1.run",
          "source": "PlatformActivator.java:283"
        },
        {
          "method": "org.eclipse.core.runtime.adaptor.EclipseStarter.run",
          "source": "EclipseStarter. java:242"
        },
        {
          "method": "org.eclipse.core.runtime.adaptor.EclipseStarter.run",
          "source": "EclipseStarter. java:119"
        },
        {
          "method": "sun.reflect.NativeMethodAccessorImpl.invoke0",
          "source": "Native Method"
        },
        {
          "method": "sun.reflect.NativeMethodAccessorImpl.invoke",
          "source": "NativeMethodAccessorImpl. java:39"
        },
        {
          "method": "sun.reflect.DelegatingMethodAccessorImpl.invoke",
          "source": "DelegatingMethodAccessorImpl.java:25"
        },
        {
          "method": "java.lang.reflect.Method.invoke",
          "source": "Method.java:324"
        },
        {
          "method": "org.eclipse.core.launcher.Main.basicRun",
          "source": "Main.java:269"
        },
        {
          "method": "org.eclipse.core.launcher.Main.run",
          "source": "Main.java:700"
        },
        {
          "method": "org.eclipse.core.launcher.Main.main",
          "source": "Main.java:684"
        }
      ],
      "number": 0,
      "commentIndex": 0,
      "bugId": "61710",
      "date": "2004-05-11T13:44:43+02:00",
      "product": "Platform",
      "component": "Team",
      "severity": "normal"
    }
  ],
  "groupId": "61710",
  "bugId": "61710",
  "date": "2004-05-11T13:44:43+02:00",
  "product": "Platform",
  "component": "Team",
  "severity": "normal"
}