{
  "comments": [
    "I found the following exception in my log.  I\u0027m using Linux-GTK I200405060200. \n \n \n!SESSION May 11, 2004 16:30:51.539 \n--------------------------------------------- \njava.version\u003d1.4.2_04 \njava.vendor\u003dSun Microsystems Inc. \nBootLoader constants: OS\u003dlinux, ARCH\u003dx86, WS\u003dgtk, NL\u003den_US \n!ENTRY org.eclipse.core.runtime 4 2 May 11, 2004 16:30:51.539 \n!MESSAGE Problems occurred when invoking code from plug-in: \n\"org.eclipse.core.runtime\". \n!STACK 0 \norg.eclipse.swt.SWTException: Invalid thread access \n        at org.eclipse.swt.SWT.error(SWT.java:2689) \n        at org.eclipse.swt.SWT.error(SWT.java:2614) \n        at org.eclipse.swt.SWT.error(SWT.java:2585) \n        at org.eclipse.swt.widgets.Widget.error(Widget.java:373) \n        at org.eclipse.swt.widgets.Widget.checkWidget(Widget.java:310) \n        at org.eclipse.swt.widgets.Widget.getData(Widget.java:399) \n        at \norg.eclipse.ui.part.MultiPageEditorPart.getEditor(MultiPageEditorPart.java:291) \n        at \norg.eclipse.ui.part.MultiPageEditorPart.removePage(MultiPageEditorPart.java:482) \n        at \norg.eclipse.pde.internal.ui.editor.MultiSourceEditor.removePage(MultiSourceEditor.java:42) \n        at \norg.eclipse.pde.internal.ui.editor.plugin.ManifestEditor.contextRemoved(ManifestEditor.java:116) \n        at \norg.eclipse.pde.internal.ui.editor.context.InputContextManager.fireContextChange(InputContextManager.java:212) \n        at \norg.eclipse.pde.internal.ui.editor.plugin.PluginInputContextManager.fireContextChange(PluginInputContextManager.java:43) \n        at \norg.eclipse.pde.internal.ui.editor.context.InputContextManager.removeContext(InputContextManager.java:191) \n        at \norg.eclipse.pde.internal.ui.editor.context.InputContextManager.structureChanged(InputContextManager.java:176) \n        at \norg.eclipse.pde.internal.ui.editor.context.InputContextManager.access$0\n(InputContextManager.java:166) \n        at \norg.eclipse.pde.internal.ui.editor.context.InputContextManager$1.visit(InputContextManager.java:155) \n        at \norg.eclipse.core.internal.events.ResourceDelta.accept(ResourceDelta.java:68) \n        at \norg.eclipse.core.internal.events.ResourceDelta.accept(ResourceDelta.java:77) \n        at \norg.eclipse.core.internal.events.ResourceDelta.accept(ResourceDelta.java:77) \n        at \norg.eclipse.core.internal.events.ResourceDelta.accept(ResourceDelta.java:49) \n        at \norg.eclipse.pde.internal.ui.editor.context.InputContextManager.resourceChanged(InputContextManager.java:147) \n        at \norg.eclipse.core.internal.events.NotificationManager$2.run(NotificationManager.java:268) \n        at \norg.eclipse.core.internal.runtime.InternalPlatform.run(InternalPlatform.java:604) \n        at org.eclipse.core.runtime.Platform.run(Platform.java:545) \n        at \norg.eclipse.core.internal.events.NotificationManager.notify(NotificationManager.java:260) \n        at \norg.eclipse.core.internal.events.NotificationManager.broadcastChanges(NotificationManager.java:148) \n        at \norg.eclipse.core.internal.resources.Workspace.broadcastChanges(Workspace.java:159) \n        at \norg.eclipse.core.internal.resources.Workspace.endOperation(Workspace.java:884) \n        at \norg.eclipse.core.internal.resources.Workspace.run(Workspace.java:1665) \n        at \norg.eclipse.ui.actions.WorkspaceModifyOperation.run(WorkspaceModifyOperation.java:105) \n        at \norg.eclipse.jface.operation.ModalContext$ModalContextThread.run(ModalContext.java:101)",
    "Fixed in 0511"
  ],
  "commentCreationDates": [
    "2004-05-11T23:13:30+02:00",
    "2004-05-11T23:46:57+02:00"
  ],
  "traces": [
    {
      "exceptionType": "org.eclipse.swt.SWTException",
      "message": "Invalid thread access",
      "elements": [
        {
          "method": "org.eclipse.swt.SWT.error",
          "source": "SWT.java:2689"
        },
        {
          "method": "org.eclipse.swt.SWT.error",
          "source": "SWT.java:2614"
        },
        {
          "method": "org.eclipse.swt.SWT.error",
          "source": "SWT.java:2585"
        },
        {
          "method": "org.eclipse.swt.widgets.Widget.error",
          "source": "Widget.java:373"
        },
        {
          "method": "org.eclipse.swt.widgets.Widget.checkWidget",
          "source": "Widget.java:310"
        },
        {
          "method": "org.eclipse.swt.widgets.Widget.getData",
          "source": "Widget.java:399"
        },
        {
          "method": "org.eclipse.ui.part.MultiPageEditorPart.getEditor",
          "source": "MultiPageEditorPart.java:291"
        },
        {
          "method": "org.eclipse.ui.part.MultiPageEditorPart.removePage",
          "source": "MultiPageEditorPart.java:482"
        },
        {
          "method": "org.eclipse.pde.internal.ui.editor.MultiSourceEditor.removePage",
          "source": "MultiSourceEditor.java:42"
        },
        {
          "method": "org.eclipse.pde.internal.ui.editor.plugin.ManifestEditor.contextRemoved",
          "source": "ManifestEditor.java:116"
        },
        {
          "method": "org.eclipse.pde.internal.ui.editor.context.InputContextManager.fireContextChange",
          "source": "InputContextManager.java:212"
        },
        {
          "method": "org.eclipse.pde.internal.ui.editor.plugin.PluginInputContextManager.fireContextChange",
          "source": "PluginInputContextManager.java:43"
        },
        {
          "method": "org.eclipse.pde.internal.ui.editor.context.InputContextManager.removeContext",
          "source": "InputContextManager.java:191"
        },
        {
          "method": "org.eclipse.pde.internal.ui.editor.context.InputContextManager.structureChanged",
          "source": "InputContextManager.java:176"
        },
        {
          "method": "org.eclipse.pde.internal.ui.editor.context.InputContextManager.access$0",
          "source": "InputContextManager.java:166"
        },
        {
          "method": "org.eclipse.pde.internal.ui.editor.context.InputContextManager$1.visit",
          "source": "InputContextManager.java:155"
        },
        {
          "method": "org.eclipse.core.internal.events.ResourceDelta.accept",
          "source": "ResourceDelta.java:68"
        },
        {
          "method": "org.eclipse.core.internal.events.ResourceDelta.accept",
          "source": "ResourceDelta.java:77"
        },
        {
          "method": "org.eclipse.core.internal.events.ResourceDelta.accept",
          "source": "ResourceDelta.java:77"
        },
        {
          "method": "org.eclipse.core.internal.events.ResourceDelta.accept",
          "source": "ResourceDelta.java:49"
        },
        {
          "method": "org.eclipse.pde.internal.ui.editor.context.InputContextManager.resourceChanged",
          "source": "InputContextManager.java:147"
        },
        {
          "method": "org.eclipse.core.internal.events.NotificationManager$2.run",
          "source": "NotificationManager.java:268"
        },
        {
          "method": "org.eclipse.core.internal.runtime.InternalPlatform.run",
          "source": "InternalPlatform.java:604"
        },
        {
          "method": "org.eclipse.core.runtime.Platform.run",
          "source": "Platform.java:545"
        },
        {
          "method": "org.eclipse.core.internal.events.NotificationManager.notify",
          "source": "NotificationManager.java:260"
        },
        {
          "method": "org.eclipse.core.internal.events.NotificationManager.broadcastChanges",
          "source": "NotificationManager.java:148"
        },
        {
          "method": "org.eclipse.core.internal.resources.Workspace.broadcastChanges",
          "source": "Workspace.java:159"
        },
        {
          "method": "org.eclipse.core.internal.resources.Workspace.endOperation",
          "source": "Workspace.java:884"
        },
        {
          "method": "org.eclipse.core.internal.resources.Workspace.run",
          "source": "Workspace.java:1665"
        },
        {
          "method": "org.eclipse.ui.actions.WorkspaceModifyOperation.run",
          "source": "WorkspaceModifyOperation.java:105"
        },
        {
          "method": "org.eclipse.jface.operation.ModalContext$ModalContextThread.run",
          "source": "ModalContext.java:101"
        }
      ],
      "number": 0,
      "commentIndex": 0,
      "bugId": "61807",
      "date": "2004-05-11T23:13:30+02:00",
      "product": "PDE",
      "component": "UI",
      "severity": "normal"
    }
  ],
  "groupId": "61807",
  "bugId": "61807",
  "date": "2004-05-11T23:13:30+02:00",
  "product": "PDE",
  "component": "UI",
  "severity": "normal"
}