{
  "comments": [
    "in i05111600\n\nI opened a Java perspective and clicked on the Javadoc tab and got the \nfollowing stack trace. Unfortunately, I don\u0027t have much to add as I really had \nnot done much.\n\n!ENTRY org.eclipse.core.runtime 4 2 May 12, 2004 15:25:40.900\n!MESSAGE Problems occurred when invoking code from plug-in: \"org.eclipse.core.ru\nntime\".\n!STACK 0\norg.eclipse.jface.util.Assert$AssertionFailedException: null argument;\n        at java.lang.Throwable.\u003cinit\u003e(Throwable.java)\n        at java.lang.Throwable.\u003cinit\u003e(Throwable.java)\n        at org.eclipse.jface.util.Assert$AssertionFailedException.\u003cinit\u003e(Assert.\njava:54)\n        at org.eclipse.jface.util.Assert.isNotNull(Assert.java:139)\n        at org.eclipse.jface.util.Assert.isNotNull(Assert.java)\n        at org.eclipse.jdt.internal.ui.infoviews.JavadocView$SelectionProvider.\u003c\ninit\u003e(JavadocView.java:159)\n        at org.eclipse.jdt.internal.ui.infoviews.JavadocView.internalCreatePartC\nontrol(JavadocView.java:255)\n        at org.eclipse.jdt.internal.ui.infoviews.AbstractInfoView.createPartCont\nrol(AbstractInfoView.java:163)\n        at org.eclipse.ui.internal.PartPane$1.run(PartPane.java:93)\n        at org.eclipse.core.internal.runtime.InternalPlatform.run(InternalPlatfo\nrm.java)\n        at org.eclipse.core.runtime.Platform.run(Platform.java)\n        at org.eclipse.ui.internal.PartPane.createChildControl(PartPane.java:89)\n\n        at org.eclipse.ui.internal.ViewPane.createChildControl(ViewPane.java:143\n)\n        at org.eclipse.ui.internal.ViewFactory$1.run(ViewFactory.java:276)\n        at org.eclipse.core.internal.runtime.InternalPlatform.run(InternalPlatfo\nrm.java)\n        at org.eclipse.core.runtime.Platform.run(Platform.java)\n        at org.eclipse.ui.internal.ViewFactory.busyRestoreView(ViewFactory.java:\n202)\n        at org.eclipse.ui.internal.ViewFactory$2.run(ViewFactory.java:454)\n        at org.eclipse.swt.custom.BusyIndicator.showWhile(BusyIndicator.java)\n        at org.eclipse.ui.internal.ViewFactory.restoreView(ViewFactory.java:452)\n\n        at org.eclipse.ui.internal.ViewFactory$ViewReference.getPart(ViewFactory\n.java:93)\n        at org.eclipse.ui.internal.WorkbenchPage$1.propertyChange(WorkbenchPage.\njava:130)\n        at org.eclipse.ui.internal.LayoutPart.setVisible(LayoutPart.java:248)\n        at org.eclipse.ui.internal.PartPane.setVisible(PartPane.java:259)\n        at org.eclipse.ui.internal.ViewPane.setVisible(ViewPane.java:625)\n        at org.eclipse.ui.internal.presentations.PresentableViewPart.setVisible(\nPresentableViewPart.java:114)\n        at org.eclipse.ui.internal.presentations.DefaultPartPresentation.selectP\nart(DefaultPartPresentation.java:777)\n        at org.eclipse.ui.internal.PartStack.refreshPresentationSelection(PartSt\nack.java:717)\n        at org.eclipse.ui.internal.PartStack.setSelection(PartStack.java:692)\n        at org.eclipse.ui.internal.PartStack.presentationSelectionChanged(PartSt\nack.java:497)\n        at org.eclipse.ui.internal.PartStack.access$0(PartStack.java:487)\n        at org.eclipse.ui.internal.PartStack$1.selectPart(PartStack.java:82)\n        at org.eclipse.ui.internal.presentations.DefaultPartPresentation$4.handl\neEvent(DefaultPartPresentation.java:155)\n        at org.eclipse.swt.widgets.EventTable.sendEvent(EventTable.java)\n        at org.eclipse.swt.widgets.Widget.sendEvent(Widget.java)\n        at org.eclipse.swt.widgets.Widget.sendEvent(Widget.java)\n        at org.eclipse.swt.widgets.Widget.sendEvent(Widget.java)\n        at org.eclipse.swt.widgets.Widget.notifyListeners(Widget.java)\n        at org.eclipse.swt.custom.CTabFolder.setSelection(CTabFolder.java:2916)\n        at org.eclipse.swt.custom.CTabFolder.onMouse(CTabFolder.java)\n        at org.eclipse.swt.custom.CTabFolder$1.handleEvent(CTabFolder.java)\n        at org.eclipse.swt.widgets.EventTable.sendEvent(EventTable.java)\n        at org.eclipse.swt.widgets.Widget.sendEvent(Widget.java)\n        at org.eclipse.swt.widgets.Display.runDeferredEvents(Display.java)\n        at org.eclipse.swt.widgets.Display.readAndDispatch(Display.java)\n        at org.eclipse.ui.internal.Workbench.runEventLoop(Workbench.java:1353)\n        at org.eclipse.ui.internal.Workbench.runUI(Workbench.java:1324)\n        at org.eclipse.ui.internal.Workbench.createAndRunWorkbench(Workbench.jav\na:243)\n        at org.eclipse.ui.PlatformUI.createAndRunWorkbench(PlatformUI.java:141)\n        at org.eclipse.ui.internal.ide.IDEApplication.run(IDEApplication.java:90\n)\n        at org.eclipse.core.internal.runtime.PlatformActivator$1.run(PlatformAct\nivator.java:298)\n        at org.eclipse.core.runtime.adaptor.EclipseStarter.run(EclipseStarter.ja\nva:249)\n        at org.eclipse.core.runtime.adaptor.EclipseStarter.run(EclipseStarter.ja\nva:126)\n        at sun.reflect.NativeMethodAccessorImpl.invoke0(Native Method)\n        at sun.reflect.NativeMethodAccessorImpl.invoke(NativeMethodAccessorImpl.\njava:84)\n        at sun.reflect.NativeMethodAccessorImpl.invoke(NativeMethodAccessorImpl.\njava:57)\n        at sun.reflect.DelegatingMethodAccessorImpl.invoke(DelegatingMethodAcces\nsorImpl.java:59)\n        at java.lang.reflect.Method.invoke(Method.java:390)\n        at org.eclipse.core.launcher.Main.basicRun(Main.java:269)\n        at org.eclipse.core.launcher.Main.run(Main.java:722)\n        at org.eclipse.core.launcher.Main.main(Main.java:706)",
    "fixed.\nis in I200405121600\n"
  ],
  "commentCreationDates": [
    "2004-05-12T21:40:55+02:00",
    "2004-05-13T11:51:35+02:00"
  ],
  "traces": [
    {
      "exceptionType": "org.eclipse.jface.util.Assert$AssertionFailedException",
      "message": "null argument;",
      "elements": [
        {
          "method": "java.lang.Throwable.\u003cinit\u003e",
          "source": "Throwable.java"
        },
        {
          "method": "java.lang.Throwable.\u003cinit\u003e",
          "source": "Throwable.java"
        },
        {
          "method": "org.eclipse.jface.util.Assert$AssertionFailedException.\u003cinit\u003e",
          "source": "Assert. java:54"
        },
        {
          "method": "org.eclipse.jface.util.Assert.isNotNull",
          "source": "Assert.java:139"
        },
        {
          "method": "org.eclipse.jface.util.Assert.isNotNull",
          "source": "Assert.java"
        },
        {
          "method": "org.eclipse.jdt.internal.ui.infoviews.JavadocView$SelectionProvider.\u003cinit\u003e",
          "source": "JavadocView.java:159"
        },
        {
          "method": "org.eclipse.jdt.internal.ui.infoviews.JavadocView.internalCreatePartControl",
          "source": "JavadocView.java:255"
        },
        {
          "method": "org.eclipse.jdt.internal.ui.infoviews.AbstractInfoView.createPartControl",
          "source": "AbstractInfoView.java:163"
        },
        {
          "method": "org.eclipse.ui.internal.PartPane$1.run",
          "source": "PartPane.java:93"
        },
        {
          "method": "org.eclipse.core.internal.runtime.InternalPlatform.run",
          "source": "InternalPlatfo rm.java"
        },
        {
          "method": "org.eclipse.core.runtime.Platform.run",
          "source": "Platform.java"
        },
        {
          "method": "org.eclipse.ui.internal.PartPane.createChildControl",
          "source": "PartPane.java:89"
        },
        {
          "method": "org.eclipse.ui.internal.ViewPane.createChildControl",
          "source": "ViewPane.java:143 "
        },
        {
          "method": "org.eclipse.ui.internal.ViewFactory$1.run",
          "source": "ViewFactory.java:276"
        },
        {
          "method": "org.eclipse.core.internal.runtime.InternalPlatform.run",
          "source": "InternalPlatfo rm.java"
        },
        {
          "method": "org.eclipse.core.runtime.Platform.run",
          "source": "Platform.java"
        },
        {
          "method": "org.eclipse.ui.internal.ViewFactory.busyRestoreView",
          "source": "ViewFactory.java: 202"
        },
        {
          "method": "org.eclipse.ui.internal.ViewFactory$2.run",
          "source": "ViewFactory.java:454"
        },
        {
          "method": "org.eclipse.swt.custom.BusyIndicator.showWhile",
          "source": "BusyIndicator.java"
        },
        {
          "method": "org.eclipse.ui.internal.ViewFactory.restoreView",
          "source": "ViewFactory.java:452"
        },
        {
          "method": "org.eclipse.ui.internal.ViewFactory$ViewReference.getPart",
          "source": "ViewFactory .java:93"
        },
        {
          "method": "org.eclipse.ui.internal.WorkbenchPage$1.propertyChange",
          "source": "WorkbenchPage. java:130"
        },
        {
          "method": "org.eclipse.ui.internal.LayoutPart.setVisible",
          "source": "LayoutPart.java:248"
        },
        {
          "method": "org.eclipse.ui.internal.PartPane.setVisible",
          "source": "PartPane.java:259"
        },
        {
          "method": "org.eclipse.ui.internal.ViewPane.setVisible",
          "source": "ViewPane.java:625"
        },
        {
          "method": "org.eclipse.ui.internal.presentations.PresentableViewPart.setVisible",
          "source": " PresentableViewPart.java:114"
        },
        {
          "method": "org.eclipse.ui.internal.presentations.DefaultPartPresentation.selectPart",
          "source": "DefaultPartPresentation.java:777"
        },
        {
          "method": "org.eclipse.ui.internal.PartStack.refreshPresentationSelection",
          "source": "PartSt ack.java:717"
        },
        {
          "method": "org.eclipse.ui.internal.PartStack.setSelection",
          "source": "PartStack.java:692"
        },
        {
          "method": "org.eclipse.ui.internal.PartStack.presentationSelectionChanged",
          "source": "PartSt ack.java:497"
        },
        {
          "method": "org.eclipse.ui.internal.PartStack.access$0",
          "source": "PartStack.java:487"
        },
        {
          "method": "org.eclipse.ui.internal.PartStack$1.selectPart",
          "source": "PartStack.java:82"
        },
        {
          "method": "org.eclipse.ui.internal.presentations.DefaultPartPresentation$4.handleEvent",
          "source": "DefaultPartPresentation.java:155"
        },
        {
          "method": "org.eclipse.swt.widgets.EventTable.sendEvent",
          "source": "EventTable.java"
        },
        {
          "method": "org.eclipse.swt.widgets.Widget.sendEvent",
          "source": "Widget.java"
        },
        {
          "method": "org.eclipse.swt.widgets.Widget.sendEvent",
          "source": "Widget.java"
        },
        {
          "method": "org.eclipse.swt.widgets.Widget.sendEvent",
          "source": "Widget.java"
        },
        {
          "method": "org.eclipse.swt.widgets.Widget.notifyListeners",
          "source": "Widget.java"
        },
        {
          "method": "org.eclipse.swt.custom.CTabFolder.setSelection",
          "source": "CTabFolder.java:2916"
        },
        {
          "method": "org.eclipse.swt.custom.CTabFolder.onMouse",
          "source": "CTabFolder.java"
        },
        {
          "method": "org.eclipse.swt.custom.CTabFolder$1.handleEvent",
          "source": "CTabFolder.java"
        },
        {
          "method": "org.eclipse.swt.widgets.EventTable.sendEvent",
          "source": "EventTable.java"
        },
        {
          "method": "org.eclipse.swt.widgets.Widget.sendEvent",
          "source": "Widget.java"
        },
        {
          "method": "org.eclipse.swt.widgets.Display.runDeferredEvents",
          "source": "Display.java"
        },
        {
          "method": "org.eclipse.swt.widgets.Display.readAndDispatch",
          "source": "Display.java"
        },
        {
          "method": "org.eclipse.ui.internal.Workbench.runEventLoop",
          "source": "Workbench.java:1353"
        },
        {
          "method": "org.eclipse.ui.internal.Workbench.runUI",
          "source": "Workbench.java:1324"
        },
        {
          "method": "org.eclipse.ui.internal.Workbench.createAndRunWorkbench",
          "source": "Workbench.jav a:243"
        },
        {
          "method": "org.eclipse.ui.PlatformUI.createAndRunWorkbench",
          "source": "PlatformUI.java:141"
        },
        {
          "method": "org.eclipse.ui.internal.ide.IDEApplication.run",
          "source": "IDEApplication.java:90 "
        },
        {
          "method": "org.eclipse.core.internal.runtime.PlatformActivator$1.run",
          "source": "PlatformAct ivator.java:298"
        },
        {
          "method": "org.eclipse.core.runtime.adaptor.EclipseStarter.run",
          "source": "EclipseStarter.ja va:249"
        },
        {
          "method": "org.eclipse.core.runtime.adaptor.EclipseStarter.run",
          "source": "EclipseStarter.ja va:126"
        },
        {
          "method": "sun.reflect.NativeMethodAccessorImpl.invoke0",
          "source": "Native Method"
        },
        {
          "method": "sun.reflect.NativeMethodAccessorImpl.invoke",
          "source": "NativeMethodAccessorImpl. java:84"
        },
        {
          "method": "sun.reflect.NativeMethodAccessorImpl.invoke",
          "source": "NativeMethodAccessorImpl. java:57"
        },
        {
          "method": "sun.reflect.DelegatingMethodAccessorImpl.invoke",
          "source": "DelegatingMethodAcces sorImpl.java:59"
        },
        {
          "method": "java.lang.reflect.Method.invoke",
          "source": "Method.java:390"
        },
        {
          "method": "org.eclipse.core.launcher.Main.basicRun",
          "source": "Main.java:269"
        },
        {
          "method": "org.eclipse.core.launcher.Main.run",
          "source": "Main.java:722"
        },
        {
          "method": "org.eclipse.core.launcher.Main.main",
          "source": "Main.java:706"
        }
      ],
      "number": 0,
      "commentIndex": 0,
      "bugId": "61990",
      "date": "2004-05-12T21:40:55+02:00",
      "product": "JDT",
      "component": "Text",
      "severity": "normal"
    }
  ],
  "groupId": "61990",
  "bugId": "61990",
  "date": "2004-05-12T21:40:55+02:00",
  "product": "JDT",
  "component": "Text",
  "severity": "normal"
}