{
  "comments": [
    "After renaming a .java file to some other type (for example, .dat) it is still \nbuilt as a Java compilation unit.",
    "Need to double check in 2.0 with new builder",
    "Kent - Please verify with new builder",
    "A.java \u0026 A.class are both removed when A.java is renamed.\n\nNote: You cannot rename the suffix of a .java file in the Java perspective, you \nhave to use a Resource perspective... but then when you return the Java \nperspective the file A.java is still visible. \u0027Refresh from local\u0027 does not \nremove it from the list.",
    "There would be a model refresh problem...",
    "The following exception in the delta processor prevents the java model from \nbeing refreshed:\njava.lang.IllegalArgumentException: Missing message: \nconvention.unit.notJavaName in: org.eclipse.jdt.internal.compiler.util.messages\n        at org.eclipse.jdt.internal.core.CompilationUnit.\u003cinit\u003e\n(CompilationUnit.java:41)\n        at org.eclipse.jdt.internal.core.PackageFragment.getCompilationUnit\n(PackageFragment.java:161)\n        at org.eclipse.jdt.internal.core.DeltaProcessor.createElement\n(DeltaProcessor.java:368)\n        at org.eclipse.jdt.internal.core.DeltaProcessor.elementRemoved\n(DeltaProcessor.java:558)\n        at \norg.eclipse.jdt.internal.core.DeltaProcessor.updateCurrentDeltaAndIndex\n(DeltaProcessor.java:809)\n        at org.eclipse.jdt.internal.core.DeltaProcessor.traverseDelta\n(DeltaProcessor.java:880)\n        at org.eclipse.jdt.internal.core.DeltaProcessor.traverseDelta\n(DeltaProcessor.java:943)\n        at org.eclipse.jdt.internal.core.DeltaProcessor.traverseDelta\n(DeltaProcessor.java:943)\n        at org.eclipse.jdt.internal.core.DeltaProcessor.processResourceDelta\n(DeltaProcessor.java:774)\n        at org.eclipse.jdt.internal.core.JavaModelManager.resourceChanged\n(JavaModelManager.java:1103)\n        at org.eclipse.core.internal.events.NotificationManager$1.run\n(NotificationManager.java:125)\n        at org.eclipse.core.internal.runtime.InternalPlatform.run\n(InternalPlatform.java:809)\n        at org.eclipse.core.runtime.Platform.run(Platform.java:395)\n        at org.eclipse.core.internal.events.NotificationManager.notify\n(NotificationManager.java:140)\n        at org.eclipse.core.internal.events.NotificationManager.broadcastChanges\n(NotificationManager.java:43)\n        at org.eclipse.core.internal.events.NotificationManager.broadcastChanges\n(NotificationManager.java:64)\n        at org.eclipse.core.internal.resources.Workspace.broadcastChanges\n(Workspace.java:121)\n        at org.eclipse.core.internal.resources.Workspace.endOperation\n(Workspace.java:709)\n        at org.eclipse.core.internal.resources.Workspace.run\n(Workspace.java:1237)\n        at org.eclipse.ui.actions.WorkspaceModifyOperation.run\n(WorkspaceModifyOperation.java:78)\n        at org.eclipse.jface.operation.ModalContext$ModalContextThread.run\n(ModalContext.java:98)",
    "When moving an element, we assumed that the new element type was the same as \nthe old one.\nFixed by always computing the new element type."
  ],
  "commentCreationDates": [
    "2001-11-22T17:39:55+01:00",
    "2001-11-27T08:11:05+01:00",
    "2002-01-29T23:33:49+01:00",
    "2002-01-30T15:51:39+01:00",
    "2002-02-11T09:35:38+01:00",
    "2002-02-11T10:42:17+01:00",
    "2002-02-11T12:35:46+01:00"
  ],
  "traces": [
    {
      "exceptionType": "java.lang.IllegalArgumentException",
      "message": "Missing message:  convention.unit.notJavaName in: org.eclipse.jdt.internal.compiler.util.messages",
      "elements": [
        {
          "method": "org.eclipse.jdt.internal.core.CompilationUnit.\u003cinit\u003e",
          "source": "CompilationUnit.java:41"
        },
        {
          "method": "org.eclipse.jdt.internal.core.PackageFragment.getCompilationUnit",
          "source": "PackageFragment.java:161"
        },
        {
          "method": "org.eclipse.jdt.internal.core.DeltaProcessor.createElement",
          "source": "DeltaProcessor.java:368"
        },
        {
          "method": "org.eclipse.jdt.internal.core.DeltaProcessor.elementRemoved",
          "source": "DeltaProcessor.java:558"
        },
        {
          "method": "org.eclipse.jdt.internal.core.DeltaProcessor.updateCurrentDeltaAndIndex",
          "source": "DeltaProcessor.java:809"
        },
        {
          "method": "org.eclipse.jdt.internal.core.DeltaProcessor.traverseDelta",
          "source": "DeltaProcessor.java:880"
        },
        {
          "method": "org.eclipse.jdt.internal.core.DeltaProcessor.traverseDelta",
          "source": "DeltaProcessor.java:943"
        },
        {
          "method": "org.eclipse.jdt.internal.core.DeltaProcessor.traverseDelta",
          "source": "DeltaProcessor.java:943"
        },
        {
          "method": "org.eclipse.jdt.internal.core.DeltaProcessor.processResourceDelta",
          "source": "DeltaProcessor.java:774"
        },
        {
          "method": "org.eclipse.jdt.internal.core.JavaModelManager.resourceChanged",
          "source": "JavaModelManager.java:1103"
        },
        {
          "method": "org.eclipse.core.internal.events.NotificationManager$1.run",
          "source": "NotificationManager.java:125"
        },
        {
          "method": "org.eclipse.core.internal.runtime.InternalPlatform.run",
          "source": "InternalPlatform.java:809"
        },
        {
          "method": "org.eclipse.core.runtime.Platform.run",
          "source": "Platform.java:395"
        },
        {
          "method": "org.eclipse.core.internal.events.NotificationManager.notify",
          "source": "NotificationManager.java:140"
        },
        {
          "method": "org.eclipse.core.internal.events.NotificationManager.broadcastChanges",
          "source": "NotificationManager.java:43"
        },
        {
          "method": "org.eclipse.core.internal.events.NotificationManager.broadcastChanges",
          "source": "NotificationManager.java:64"
        },
        {
          "method": "org.eclipse.core.internal.resources.Workspace.broadcastChanges",
          "source": "Workspace.java:121"
        },
        {
          "method": "org.eclipse.core.internal.resources.Workspace.endOperation",
          "source": "Workspace.java:709"
        },
        {
          "method": "org.eclipse.core.internal.resources.Workspace.run",
          "source": "Workspace.java:1237"
        },
        {
          "method": "org.eclipse.ui.actions.WorkspaceModifyOperation.run",
          "source": "WorkspaceModifyOperation.java:78"
        },
        {
          "method": "org.eclipse.jface.operation.ModalContext$ModalContextThread.run",
          "source": "ModalContext.java:98"
        }
      ],
      "number": 0,
      "commentIndex": 5,
      "bugId": "6236",
      "date": "2002-02-11T10:42:17+01:00",
      "product": "JDT",
      "component": "Core",
      "severity": "normal"
    }
  ],
  "groupId": "6236",
  "bugId": "6236",
  "date": "2001-11-22T17:39:55+01:00",
  "product": "JDT",
  "component": "Core",
  "severity": "normal"
}