{
  "comments": [
    "with the latest builds now using 200405140800 i get an Exception and a Dialog \nin eclipse that i should terminate eclipse because of a SWT error..\n\nIt seems that it does put the right data into the clipboard (or i can use the \nclipboard right after that pretty normally)\n\norg.eclipse.swt.SWTError: Cannot set data in clipboard\n        at org.eclipse.swt.dnd.DND.error(DND.java:225)\n        at org.eclipse.swt.dnd.DND.error(DND.java:181)\n        at org.eclipse.swt.dnd.Clipboard.setContents(Clipboard.java:267)\n        at org.eclipse.jdt.internal.ui.javaeditor.ClipboardOperationAction.doCut\nCopyWithImportsOperation(ClipboardOperationAction.java:304)\n        at org.eclipse.jdt.internal.ui.javaeditor.ClipboardOperationAction.inter\nnalDoOperation(ClipboardOperationAction.java:246)\n        at org.eclipse.jdt.internal.ui.javaeditor.ClipboardOperationAction$1.run\n(ClipboardOperationAction.java:224)\n        at org.eclipse.swt.custom.BusyIndicator.showWhile(BusyIndicator.java:69)\n\n        at org.eclipse.jdt.internal.ui.javaeditor.ClipboardOperationAction.run(C\nlipboardOperationAction.java:222)\n        at org.eclipse.jface.action.Action.runWithEvent(Action.java:881)\n        at org.eclipse.ui.commands.ActionHandler.execute(ActionHandler.java:141)\n\n        at org.eclipse.ui.internal.commands.Command.execute(Command.java:132)\n        at org.eclipse.ui.internal.keys.WorkbenchKeyboard.executeCommand(Workben\nchKeyboard.java:468)\n        at org.eclipse.ui.internal.keys.WorkbenchKeyboard.press(WorkbenchKeyboar\nd.java:886)\n        at org.eclipse.ui.internal.keys.WorkbenchKeyboard.processKeyEvent(Workbe\nnchKeyboard.java:927)\n        at org.eclipse.ui.internal.keys.WorkbenchKeyboard.filterKeySequenceBindi\nngs(WorkbenchKeyboard.java:545)\n        at org.eclipse.ui.internal.keys.WorkbenchKeyboard.access$2(WorkbenchKeyb\noard.java:493)\n        at org.eclipse.ui.internal.keys.WorkbenchKeyboard$1.handleEvent(Workbenc\nhKeyboard.java:258)\n        at org.eclipse.swt.widgets.EventTable.sendEvent(EventTable.java:82)\n        at org.eclipse.swt.widgets.Display.filterEvent(Display.java:712)\n        at org.eclipse.swt.widgets.Widget.sendEvent(Widget.java:795)\n        at org.eclipse.swt.widgets.Widget.sendEvent(Widget.java:820)\n        at org.eclipse.swt.widgets.Widget.sendEvent(Widget.java:805)\n        at org.eclipse.swt.widgets.Control.sendKeyEvent(Control.java:1724)\n        at org.eclipse.swt.widgets.Control.sendKeyEvent(Control.java:1720)\n        at org.eclipse.swt.widgets.Control.WM_CHAR(Control.java:3048)\n        at org.eclipse.swt.widgets.Control.windowProc(Control.java:2951)\n        at org.eclipse.swt.widgets.Display.windowProc(Display.java:3291)\n        at org.eclipse.swt.internal.win32.OS.CallWindowProcW(Native Method)\n        at org.eclipse.swt.internal.win32.OS.CallWindowProc(OS.java:1390)\n        at org.eclipse.swt.internal.BidiUtil.windowProc(BidiUtil.java:647)\n        at org.eclipse.swt.internal.win32.OS.DispatchMessageW(Native Method)\n        at org.eclipse.swt.internal.win32.OS.DispatchMessage(OS.java:1466)\n        at org.eclipse.swt.widgets.Display.readAndDispatch(Display.java:2388)\n        at org.eclipse.ui.internal.Workbench.runEventLoop(Workbench.java:1353)\n        at org.eclipse.ui.internal.Workbench.runUI(Workbench.java:1324)\n        at org.eclipse.ui.internal.Workbench.createAndRunWorkbench(Workbench.jav\na:243)\n        at org.eclipse.ui.PlatformUI.createAndRunWorkbench(PlatformUI.java:141)\n        at org.eclipse.ui.internal.ide.IDEApplication.run(IDEApplication.java:90\n)\n        at org.eclipse.core.internal.runtime.PlatformActivator$1.run(PlatformAct\nivator.java:298)\n        at org.eclipse.core.runtime.adaptor.EclipseStarter.run(EclipseStarter.ja\nva:249)\n        at org.eclipse.core.runtime.adaptor.EclipseStarter.run(EclipseStarter.ja\nva:126)\n        at sun.reflect.NativeMethodAccessorImpl.invoke0(Native Method)\n        at sun.reflect.NativeMethodAccessorImpl.invoke(NativeMethodAccessorImpl.\njava:39)\n        at sun.reflect.DelegatingMethodAccessorImpl.invoke(DelegatingMethodAcces\nsorImpl.java:25)\n        at java.lang.reflect.Method.invoke(Method.java:494)\n        at org.eclipse.core.launcher.Main.basicRun(Main.java:269)\n        at org.eclipse.core.launcher.Main.run(Main.java:722)\n        at org.eclipse.core.launcher.Main.main(Main.java:706)",
    "\n\n*** This bug has been marked as a duplicate of 61841 ***"
  ],
  "commentCreationDates": [
    "2004-05-16T11:33:44+02:00",
    "2004-05-17T19:34:34+02:00"
  ],
  "traces": [
    {
      "exceptionType": "org.eclipse.swt.SWTError",
      "message": "Cannot set data in clipboard",
      "elements": [
        {
          "method": "org.eclipse.swt.dnd.DND.error",
          "source": "DND.java:225"
        },
        {
          "method": "org.eclipse.swt.dnd.DND.error",
          "source": "DND.java:181"
        },
        {
          "method": "org.eclipse.swt.dnd.Clipboard.setContents",
          "source": "Clipboard.java:267"
        },
        {
          "method": "org.eclipse.jdt.internal.ui.javaeditor.ClipboardOperationAction.doCutCopyWithImportsOperation",
          "source": "ClipboardOperationAction.java:304"
        },
        {
          "method": "org.eclipse.jdt.internal.ui.javaeditor.ClipboardOperationAction.internalDoOperation",
          "source": "ClipboardOperationAction.java:246"
        },
        {
          "method": "org.eclipse.jdt.internal.ui.javaeditor.ClipboardOperationAction$1.run",
          "source": "ClipboardOperationAction.java:224"
        },
        {
          "method": "org.eclipse.swt.custom.BusyIndicator.showWhile",
          "source": "BusyIndicator.java:69"
        },
        {
          "method": "org.eclipse.jdt.internal.ui.javaeditor.ClipboardOperationAction.run",
          "source": "C lipboardOperationAction.java:222"
        },
        {
          "method": "org.eclipse.jface.action.Action.runWithEvent",
          "source": "Action.java:881"
        },
        {
          "method": "org.eclipse.ui.commands.ActionHandler.execute",
          "source": "ActionHandler.java:141"
        },
        {
          "method": "org.eclipse.ui.internal.commands.Command.execute",
          "source": "Command.java:132"
        },
        {
          "method": "org.eclipse.ui.internal.keys.WorkbenchKeyboard.executeCommand",
          "source": "Workben chKeyboard.java:468"
        },
        {
          "method": "org.eclipse.ui.internal.keys.WorkbenchKeyboard.press",
          "source": "WorkbenchKeyboar d.java:886"
        },
        {
          "method": "org.eclipse.ui.internal.keys.WorkbenchKeyboard.processKeyEvent",
          "source": "Workbe nchKeyboard.java:927"
        },
        {
          "method": "org.eclipse.ui.internal.keys.WorkbenchKeyboard.filterKeySequenceBindings",
          "source": "WorkbenchKeyboard.java:545"
        },
        {
          "method": "org.eclipse.ui.internal.keys.WorkbenchKeyboard.access$2",
          "source": "WorkbenchKeyb oard.java:493"
        },
        {
          "method": "org.eclipse.ui.internal.keys.WorkbenchKeyboard$1.handleEvent",
          "source": "Workbenc hKeyboard.java:258"
        },
        {
          "method": "org.eclipse.swt.widgets.EventTable.sendEvent",
          "source": "EventTable.java:82"
        },
        {
          "method": "org.eclipse.swt.widgets.Display.filterEvent",
          "source": "Display.java:712"
        },
        {
          "method": "org.eclipse.swt.widgets.Widget.sendEvent",
          "source": "Widget.java:795"
        },
        {
          "method": "org.eclipse.swt.widgets.Widget.sendEvent",
          "source": "Widget.java:820"
        },
        {
          "method": "org.eclipse.swt.widgets.Widget.sendEvent",
          "source": "Widget.java:805"
        },
        {
          "method": "org.eclipse.swt.widgets.Control.sendKeyEvent",
          "source": "Control.java:1724"
        },
        {
          "method": "org.eclipse.swt.widgets.Control.sendKeyEvent",
          "source": "Control.java:1720"
        },
        {
          "method": "org.eclipse.swt.widgets.Control.WM_CHAR",
          "source": "Control.java:3048"
        },
        {
          "method": "org.eclipse.swt.widgets.Control.windowProc",
          "source": "Control.java:2951"
        },
        {
          "method": "org.eclipse.swt.widgets.Display.windowProc",
          "source": "Display.java:3291"
        },
        {
          "method": "org.eclipse.swt.internal.win32.OS.CallWindowProcW",
          "source": "Native Method"
        },
        {
          "method": "org.eclipse.swt.internal.win32.OS.CallWindowProc",
          "source": "OS.java:1390"
        },
        {
          "method": "org.eclipse.swt.internal.BidiUtil.windowProc",
          "source": "BidiUtil.java:647"
        },
        {
          "method": "org.eclipse.swt.internal.win32.OS.DispatchMessageW",
          "source": "Native Method"
        },
        {
          "method": "org.eclipse.swt.internal.win32.OS.DispatchMessage",
          "source": "OS.java:1466"
        },
        {
          "method": "org.eclipse.swt.widgets.Display.readAndDispatch",
          "source": "Display.java:2388"
        },
        {
          "method": "org.eclipse.ui.internal.Workbench.runEventLoop",
          "source": "Workbench.java:1353"
        },
        {
          "method": "org.eclipse.ui.internal.Workbench.runUI",
          "source": "Workbench.java:1324"
        },
        {
          "method": "org.eclipse.ui.internal.Workbench.createAndRunWorkbench",
          "source": "Workbench.jav a:243"
        },
        {
          "method": "org.eclipse.ui.PlatformUI.createAndRunWorkbench",
          "source": "PlatformUI.java:141"
        },
        {
          "method": "org.eclipse.ui.internal.ide.IDEApplication.run",
          "source": "IDEApplication.java:90 "
        },
        {
          "method": "org.eclipse.core.internal.runtime.PlatformActivator$1.run",
          "source": "PlatformAct ivator.java:298"
        },
        {
          "method": "org.eclipse.core.runtime.adaptor.EclipseStarter.run",
          "source": "EclipseStarter.ja va:249"
        },
        {
          "method": "org.eclipse.core.runtime.adaptor.EclipseStarter.run",
          "source": "EclipseStarter.ja va:126"
        },
        {
          "method": "sun.reflect.NativeMethodAccessorImpl.invoke0",
          "source": "Native Method"
        },
        {
          "method": "sun.reflect.NativeMethodAccessorImpl.invoke",
          "source": "NativeMethodAccessorImpl. java:39"
        },
        {
          "method": "sun.reflect.DelegatingMethodAccessorImpl.invoke",
          "source": "DelegatingMethodAcces sorImpl.java:25"
        },
        {
          "method": "java.lang.reflect.Method.invoke",
          "source": "Method.java:494"
        },
        {
          "method": "org.eclipse.core.launcher.Main.basicRun",
          "source": "Main.java:269"
        },
        {
          "method": "org.eclipse.core.launcher.Main.run",
          "source": "Main.java:722"
        },
        {
          "method": "org.eclipse.core.launcher.Main.main",
          "source": "Main.java:706"
        }
      ],
      "number": 0,
      "commentIndex": 0,
      "bugId": "62418",
      "duplicateId": "61841",
      "date": "2004-05-16T11:33:44+02:00",
      "product": "Platform",
      "component": "SWT",
      "severity": "normal"
    }
  ],
  "groupId": "61841",
  "bugId": "62418",
  "duplicateId": "61841",
  "date": "2004-05-16T11:33:44+02:00",
  "product": "Platform",
  "component": "SWT",
  "severity": "normal"
}