{
  "comments": [
    "I\u0027m using nightly build N200405170010. I know it\u0027s a little it dangerous but I\nneed it...\n\nPerhaps it\u0027s a know problem but when I launch eclipse using this build, I always\nget following NPE:\n!ENTRY org.eclipse.core.runtime 4 2 May 17, 2004 11:00:08.268\n!MESSAGE Problems occurred when invoking code from plug-in:\n\"org.eclipse.core.runtime\".\n!STACK 0\njava.lang.NullPointerException\n        at\norg.eclipse.debug.internal.ui.views.launch.LaunchView.perspectiveChanged(LaunchView.java:614)\n        at\norg.eclipse.ui.internal.PerspectiveListenerListOld$2.run(PerspectiveListenerListOld.java:58)\n        at\norg.eclipse.core.internal.runtime.InternalPlatform.run(InternalPlatform.java:608)\n        at org.eclipse.core.runtime.Platform.run(Platform.java:668)\n        at\norg.eclipse.ui.internal.PerspectiveListenerListOld.firePerspectiveChanged(PerspectiveListenerListOld.java:56)\n        at\norg.eclipse.ui.internal.WorkbenchWindow.firePerspectiveChanged(WorkbenchWindow.java:913)\n        at\norg.eclipse.ui.internal.WorkbenchPage.showActionSet(WorkbenchPage.java:2918)\n        at\norg.eclipse.debug.internal.ui.views.launch.LaunchViewContextListener.showDebugActionSet(LaunchViewContextListener.java:821)\n        at\norg.eclipse.debug.internal.ui.views.launch.LaunchViewContextListener.\u003cinit\u003e(LaunchViewContextListener.java:135)\n        at\norg.eclipse.debug.internal.ui.views.launch.LaunchView.partOpened(LaunchView.java:656)\n        at org.eclipse.ui.internal.PartListenerList$5.run(PartListenerList.java:105)\n        at\norg.eclipse.core.internal.runtime.InternalPlatform.run(InternalPlatform.java:608)\n        at org.eclipse.core.runtime.Platform.run(Platform.java:668)\n        at\norg.eclipse.ui.internal.PartListenerList.firePartOpened(PartListenerList.java:103)\n        at\norg.eclipse.ui.internal.WorkbenchPage.firePartOpened(WorkbenchPage.java:1404)\n        at org.eclipse.ui.internal.PartPane.createChildControl(PartPane.java:138)\n        at org.eclipse.ui.internal.ViewPane.createChildControl(ViewPane.java:140)\n        at org.eclipse.ui.internal.PartPane.createControl(PartPane.java:170)\n        at org.eclipse.ui.internal.ViewPane.createControl(ViewPane.java:128)\n        at\norg.eclipse.ui.internal.PartStack.refreshPresentationSelection(PartStack.java:912)\n        at org.eclipse.ui.internal.PartStack.createControl(PartStack.java:463)\n        at org.eclipse.ui.internal.PartStack.createControl(PartStack.java:363)\n        at\norg.eclipse.ui.internal.PartSashContainer.createControl(PartSashContainer.java:427)\n        at\norg.eclipse.ui.internal.PerspectiveHelper.activate(PerspectiveHelper.java:156)\n        at org.eclipse.ui.internal.Perspective.onActivate(Perspective.java:718)\n        at org.eclipse.ui.internal.WorkbenchPage.onActivate(WorkbenchPage.java:1991)\n        at org.eclipse.ui.internal.WorkbenchWindow$7.run(WorkbenchWindow.java:1907)\n        at org.eclipse.swt.custom.BusyIndicator.showWhile(BusyIndicator.java:69)\n        at\norg.eclipse.ui.internal.WorkbenchWindow.setActivePage(WorkbenchWindow.java:1894)\n        at\norg.eclipse.ui.internal.WorkbenchWindow.restoreState(WorkbenchWindow.java:1462)\n        at org.eclipse.ui.internal.Workbench.restoreState(Workbench.java:1216)\n        at org.eclipse.ui.internal.Workbench.access$10(Workbench.java:1183)\n        at org.eclipse.ui.internal.Workbench$13.run(Workbench.java:1094)\n        at\norg.eclipse.core.internal.runtime.InternalPlatform.run(InternalPlatform.java:608)\n        at org.eclipse.core.runtime.Platform.run(Platform.java:668)\n        at org.eclipse.ui.internal.Workbench.restoreState(Workbench.java:1027)\n        at\norg.eclipse.ui.internal.WorkbenchConfigurer.restoreState(WorkbenchConfigurer.java:167)\n        at\norg.eclipse.ui.application.WorkbenchAdvisor.openWindows(WorkbenchAdvisor.java:652)\n        at org.eclipse.ui.internal.Workbench.init(Workbench.java:817)\n        at org.eclipse.ui.internal.Workbench.runUI(Workbench.java:1311)\n        at\norg.eclipse.ui.internal.Workbench.createAndRunWorkbench(Workbench.java:253)\n        at org.eclipse.ui.PlatformUI.createAndRunWorkbench(PlatformUI.java:141)\n        at org.eclipse.ui.internal.ide.IDEApplication.run(IDEApplication.java:97)\n        at\norg.eclipse.core.internal.runtime.PlatformActivator$1.run(PlatformActivator.java:299)\n        at\norg.eclipse.core.runtime.adaptor.EclipseStarter.run(EclipseStarter.java:256)\n        at\norg.eclipse.core.runtime.adaptor.EclipseStarter.run(EclipseStarter.java:127)\n        at sun.reflect.NativeMethodAccessorImpl.invoke0(Native Method)\n        at\nsun.reflect.NativeMethodAccessorImpl.invoke(NativeMethodAccessorImpl.java:39)\n        at\nsun.reflect.DelegatingMethodAccessorImpl.invoke(DelegatingMethodAccessorImpl.java:25)\n        at java.lang.reflect.Method.invoke(Method.java:324)\n        at org.eclipse.core.launcher.Main.basicRun(Main.java:184)\n        at org.eclipse.core.launcher.Main.run(Main.java:637)\n        at org.eclipse.core.launcher.Main.main(Main.java:621)\n\nNot usre if I should open it against debug-ui or core-ui, please reassign if\nnecessary or cancel if this is only a temporary issue...",
    "I think this is due to our fix for bug 61868, which needs to be reverted once \nbug 61937 is fixed.",
    "(But perhaps we can still protect against the problem with the current \nimplementation? I\u0027m seeing the problem too, running with the latest plugins).",
    "\n\n*** This bug has been marked as a duplicate of 60327 ***"
  ],
  "commentCreationDates": [
    "2004-05-17T11:16:32+02:00",
    "2004-05-17T17:05:15+02:00",
    "2004-05-17T17:06:15+02:00",
    "2004-05-17T17:11:33+02:00"
  ],
  "traces": [
    {
      "exceptionType": "java.lang.NullPointerException",
      "elements": [
        {
          "method": "org.eclipse.debug.internal.ui.views.launch.LaunchView.perspectiveChanged",
          "source": "LaunchView.java:614"
        },
        {
          "method": "org.eclipse.ui.internal.PerspectiveListenerListOld$2.run",
          "source": "PerspectiveListenerListOld.java:58"
        },
        {
          "method": "org.eclipse.core.internal.runtime.InternalPlatform.run",
          "source": "InternalPlatform.java:608"
        },
        {
          "method": "org.eclipse.core.runtime.Platform.run",
          "source": "Platform.java:668"
        },
        {
          "method": "org.eclipse.ui.internal.PerspectiveListenerListOld.firePerspectiveChanged",
          "source": "PerspectiveListenerListOld.java:56"
        },
        {
          "method": "org.eclipse.ui.internal.WorkbenchWindow.firePerspectiveChanged",
          "source": "WorkbenchWindow.java:913"
        },
        {
          "method": "org.eclipse.ui.internal.WorkbenchPage.showActionSet",
          "source": "WorkbenchPage.java:2918"
        },
        {
          "method": "org.eclipse.debug.internal.ui.views.launch.LaunchViewContextListener.showDebugActionSet",
          "source": "LaunchViewContextListener.java:821"
        },
        {
          "method": "org.eclipse.debug.internal.ui.views.launch.LaunchViewContextListener.\u003cinit\u003e",
          "source": "LaunchViewContextListener.java:135"
        },
        {
          "method": "org.eclipse.debug.internal.ui.views.launch.LaunchView.partOpened",
          "source": "LaunchView.java:656"
        },
        {
          "method": "org.eclipse.ui.internal.PartListenerList$5.run",
          "source": "PartListenerList.java:105"
        },
        {
          "method": "org.eclipse.core.internal.runtime.InternalPlatform.run",
          "source": "InternalPlatform.java:608"
        },
        {
          "method": "org.eclipse.core.runtime.Platform.run",
          "source": "Platform.java:668"
        },
        {
          "method": "org.eclipse.ui.internal.PartListenerList.firePartOpened",
          "source": "PartListenerList.java:103"
        },
        {
          "method": "org.eclipse.ui.internal.WorkbenchPage.firePartOpened",
          "source": "WorkbenchPage.java:1404"
        },
        {
          "method": "org.eclipse.ui.internal.PartPane.createChildControl",
          "source": "PartPane.java:138"
        },
        {
          "method": "org.eclipse.ui.internal.ViewPane.createChildControl",
          "source": "ViewPane.java:140"
        },
        {
          "method": "org.eclipse.ui.internal.PartPane.createControl",
          "source": "PartPane.java:170"
        },
        {
          "method": "org.eclipse.ui.internal.ViewPane.createControl",
          "source": "ViewPane.java:128"
        },
        {
          "method": "org.eclipse.ui.internal.PartStack.refreshPresentationSelection",
          "source": "PartStack.java:912"
        },
        {
          "method": "org.eclipse.ui.internal.PartStack.createControl",
          "source": "PartStack.java:463"
        },
        {
          "method": "org.eclipse.ui.internal.PartStack.createControl",
          "source": "PartStack.java:363"
        },
        {
          "method": "org.eclipse.ui.internal.PartSashContainer.createControl",
          "source": "PartSashContainer.java:427"
        },
        {
          "method": "org.eclipse.ui.internal.PerspectiveHelper.activate",
          "source": "PerspectiveHelper.java:156"
        },
        {
          "method": "org.eclipse.ui.internal.Perspective.onActivate",
          "source": "Perspective.java:718"
        },
        {
          "method": "org.eclipse.ui.internal.WorkbenchPage.onActivate",
          "source": "WorkbenchPage.java:1991"
        },
        {
          "method": "org.eclipse.ui.internal.WorkbenchWindow$7.run",
          "source": "WorkbenchWindow.java:1907"
        },
        {
          "method": "org.eclipse.swt.custom.BusyIndicator.showWhile",
          "source": "BusyIndicator.java:69"
        },
        {
          "method": "org.eclipse.ui.internal.WorkbenchWindow.setActivePage",
          "source": "WorkbenchWindow.java:1894"
        },
        {
          "method": "org.eclipse.ui.internal.WorkbenchWindow.restoreState",
          "source": "WorkbenchWindow.java:1462"
        },
        {
          "method": "org.eclipse.ui.internal.Workbench.restoreState",
          "source": "Workbench.java:1216"
        },
        {
          "method": "org.eclipse.ui.internal.Workbench.access$10",
          "source": "Workbench.java:1183"
        },
        {
          "method": "org.eclipse.ui.internal.Workbench$13.run",
          "source": "Workbench.java:1094"
        },
        {
          "method": "org.eclipse.core.internal.runtime.InternalPlatform.run",
          "source": "InternalPlatform.java:608"
        },
        {
          "method": "org.eclipse.core.runtime.Platform.run",
          "source": "Platform.java:668"
        },
        {
          "method": "org.eclipse.ui.internal.Workbench.restoreState",
          "source": "Workbench.java:1027"
        },
        {
          "method": "org.eclipse.ui.internal.WorkbenchConfigurer.restoreState",
          "source": "WorkbenchConfigurer.java:167"
        },
        {
          "method": "org.eclipse.ui.application.WorkbenchAdvisor.openWindows",
          "source": "WorkbenchAdvisor.java:652"
        },
        {
          "method": "org.eclipse.ui.internal.Workbench.init",
          "source": "Workbench.java:817"
        },
        {
          "method": "org.eclipse.ui.internal.Workbench.runUI",
          "source": "Workbench.java:1311"
        },
        {
          "method": "org.eclipse.ui.internal.Workbench.createAndRunWorkbench",
          "source": "Workbench.java:253"
        },
        {
          "method": "org.eclipse.ui.PlatformUI.createAndRunWorkbench",
          "source": "PlatformUI.java:141"
        },
        {
          "method": "org.eclipse.ui.internal.ide.IDEApplication.run",
          "source": "IDEApplication.java:97"
        },
        {
          "method": "org.eclipse.core.internal.runtime.PlatformActivator$1.run",
          "source": "PlatformActivator.java:299"
        },
        {
          "method": "org.eclipse.core.runtime.adaptor.EclipseStarter.run",
          "source": "EclipseStarter.java:256"
        },
        {
          "method": "org.eclipse.core.runtime.adaptor.EclipseStarter.run",
          "source": "EclipseStarter.java:127"
        },
        {
          "method": "sun.reflect.NativeMethodAccessorImpl.invoke0",
          "source": "Native Method"
        },
        {
          "method": "sun.reflect.NativeMethodAccessorImpl.invoke",
          "source": "NativeMethodAccessorImpl.java:39"
        },
        {
          "method": "sun.reflect.DelegatingMethodAccessorImpl.invoke",
          "source": "DelegatingMethodAccessorImpl.java:25"
        },
        {
          "method": "java.lang.reflect.Method.invoke",
          "source": "Method.java:324"
        },
        {
          "method": "org.eclipse.core.launcher.Main.basicRun",
          "source": "Main.java:184"
        },
        {
          "method": "org.eclipse.core.launcher.Main.run",
          "source": "Main.java:637"
        },
        {
          "method": "org.eclipse.core.launcher.Main.main",
          "source": "Main.java:621"
        }
      ],
      "number": 0,
      "commentIndex": 0,
      "bugId": "62448",
      "duplicateId": "60327",
      "date": "2004-05-17T11:16:32+02:00",
      "product": "Platform",
      "component": "Debug",
      "severity": "normal"
    }
  ],
  "groupId": "60327",
  "bugId": "62448",
  "duplicateId": "60327",
  "date": "2004-05-17T11:16:32+02:00",
  "product": "Platform",
  "component": "Debug",
  "severity": "normal"
}