{
  "comments": [
    "I was rearranging winodws in the Java perspective and got the following \nexception.\n\n\n!ENTRY org.eclipse.ui 4 0 May 17, 2004 10:14:12.311\n!MESSAGE Widget is disposed\n!STACK 0\norg.eclipse.swt.SWTException: Widget is disposed\n        at org.eclipse.swt.SWT.error(SWT.java:2689)\n        at org.eclipse.swt.SWT.error(SWT.java:2614)\n        at org.eclipse.swt.SWT.error(SWT.java:2585)\n        at org.eclipse.swt.widgets.Widget.error(Widget.java:381)\n        at org.eclipse.swt.widgets.Widget.checkWidget(Widget.java:283)\n        at org.eclipse.swt.widgets.Control.getParent(Control.java:885)\n        at org.eclipse.ui.internal.presentations.PaneFolder.layout\n(PaneFolder.ja\nva:327)\n        at org.eclipse.ui.internal.presentations.DefaultPartPresentation.layout\n(\nDefaultPartPresentation.java:660)\n        at \norg.eclipse.ui.internal.presentations.DefaultPartPresentation.setBoun\nds(DefaultPartPresentation.java:872)\n        at org.eclipse.ui.internal.PartStack.setBounds(PartStack.java:880)\n        at org.eclipse.ui.internal.LayoutTree.setBounds(LayoutTree.java:190)\n        at org.eclipse.ui.internal.LayoutTreeNode.setBounds\n(LayoutTreeNode.java:\n372)\n        at org.eclipse.ui.internal.LayoutTreeNode.setBounds\n(LayoutTreeNode.java:\n296)\n        at org.eclipse.ui.internal.PartSashContainer.resizeSashes\n(PartSashContai\nner.java:620)\n        at org.eclipse.ui.internal.PartSashContainer.addChild\n(PartSashContainer.\njava:332)\n        at org.eclipse.ui.internal.ViewSashContainer.addChild\n(ViewSashContainer.\njava:280)\n        at org.eclipse.ui.internal.PartSashContainer.add\n(PartSashContainer.java:\n928)\n        at org.eclipse.ui.internal.PartSashContainer.add\n(PartSashContainer.java:\n259)\n        at org.eclipse.ui.internal.PartSashContainer.addEnhanced\n(PartSashContain\ner.java:220)\n        at org.eclipse.ui.internal.PartSashContainer.add\n(PartSashContainer.java:\n192)\n        at org.eclipse.ui.internal.PerspectiveHelper.derefPart\n(PerspectiveHelper\n.java:537)\n        at org.eclipse.ui.internal.ViewSashContainer.derefPart\n(ViewSashContainer\n.java:262)\n        at org.eclipse.ui.internal.PartSashContainer.stack\n(PartSashContainer.jav\na:819)\n        at org.eclipse.ui.internal.PartSashContainer.dropObject\n(PartSashContaine\nr.java:796)\n        at \norg.eclipse.ui.internal.PartSashContainer$SashContainerDropTarget.dro\np(PartSashContainer.java:110)\n        at org.eclipse.ui.internal.dnd.DragUtil.performDrag(DragUtil.java:128)\n        at org.eclipse.ui.internal.PartStack.dragStart(PartStack.java:1116)\n        at org.eclipse.ui.internal.PartStack$1.dragStart(PartStack.java:78)\n        at \norg.eclipse.ui.internal.presentations.DefaultPartPresentation$10.hand\nleEvent(DefaultPartPresentation.java:308)\n        at org.eclipse.ui.presentations.PresentationUtil.handleMouseMove\n(Present\nationUtil.java:89)\n        at org.eclipse.ui.presentations.PresentationUtil.access$4\n(PresentationUt\nil.java:83)\n        at org.eclipse.ui.presentations.PresentationUtil$2.handleEvent\n(Presentat\nionUtil.java:55)\n        at org.eclipse.swt.widgets.EventTable.sendEvent(EventTable.java:82)\n        at org.eclipse.swt.widgets.Widget.sendEvent(Widget.java:796)\n        at org.eclipse.swt.widgets.Display.runDeferredEvents(Display.java:2716)\n        at org.eclipse.swt.widgets.Display.readAndDispatch(Display.java:2382)\n        at org.eclipse.ui.internal.Workbench.runEventLoop(Workbench.java:1363)\n        at org.eclipse.ui.internal.Workbench.runUI(Workbench.java:1334)\n        at org.eclipse.ui.internal.Workbench.createAndRunWorkbench\n(Workbench.jav\na:253)\n        at org.eclipse.ui.PlatformUI.createAndRunWorkbench(PlatformUI.java:141)\n        at org.eclipse.ui.internal.ide.IDEApplication.run\n(IDEApplication.java:97\n)\n        at org.eclipse.core.internal.runtime.PlatformActivator$1.run\n(PlatformAct\nivator.java:299)\n        at org.eclipse.core.runtime.adaptor.EclipseStarter.run\n(EclipseStarter.ja\nva:256)\n        at org.eclipse.core.runtime.adaptor.EclipseStarter.run\n(EclipseStarter.ja\nva:127)\n        at sun.reflect.NativeMethodAccessorImpl.invoke0(Native Method)\n        at sun.reflect.NativeMethodAccessorImpl.invoke\n(NativeMethodAccessorImpl.\njava:39)\n        at sun.reflect.DelegatingMethodAccessorImpl.invoke\n(DelegatingMethodAcces\nsorImpl.java:25)\n        at java.lang.reflect.Method.invoke(Method.java:324)\n        at org.eclipse.core.launcher.Main.basicRun(Main.java:184)\n        at org.eclipse.core.launcher.Main.run(Main.java:637)\n        at org.eclipse.core.launcher.Main.main(Main.java:621)\nWidget is disposed",
    "After this excpetion, the UI in the main window area stopped repainting but \nmenus could still be expanded.",
    "This occurred with build N20040517",
    "still happening with I20040518, quite critical.\n\nI had a stacktrace very similar to the one noted in comment 0, but it was\npreceded by a slightly different one which I will include:\n\n!STACK 0\norg.eclipse.swt.SWTException: Widget is disposed\n        at java.lang.Throwable.\u003cinit\u003e(Throwable.java)\n        at java.lang.Throwable.\u003cinit\u003e(Throwable.java)\n        at org.eclipse.swt.SWTException.\u003cinit\u003e(SWTException.java:73)\n        at org.eclipse.swt.SWT.error(SWT.java:2689)\n        at org.eclipse.swt.SWT.error(SWT.java:2614)\n        at org.eclipse.swt.SWT.error(SWT.java:2585)\n        at org.eclipse.swt.widgets.Widget.error(Widget.java:374)\n        at org.eclipse.swt.widgets.Widget.checkWidget(Widget.java)\n        at org.eclipse.swt.widgets.Control.getParent(Control.java:1560)\n        at\norg.eclipse.ui.internal.presentations.PaneFolder.layout(PaneFolder.java:327)\n        at\norg.eclipse.ui.internal.presentations.DefaultPartPresentation.layout(DefaultPartPresentation.java:660)\n        at\norg.eclipse.ui.internal.presentations.DefaultPartPresentation.setBounds(DefaultPartPresentation.java:872)\n        at org.eclipse.ui.internal.PartStack.setBounds(PartStack.java:879)\n        at org.eclipse.ui.internal.LayoutTree.setBounds(LayoutTree.java:190)\n        at org.eclipse.ui.internal.LayoutTreeNode.setBounds(LayoutTreeNode.java:373)\n        at\norg.eclipse.ui.internal.LayoutPartSash.widgetSelected(LayoutPartSash.java:191)\n        at org.eclipse.ui.internal.LayoutPartSash.access$1(LayoutPartSash.java:176)\n        at\norg.eclipse.ui.internal.LayoutPartSash$1.widgetSelected(LayoutPartSash.java:53)\n        at org.eclipse.swt.widgets.TypedListener.handleEvent(TypedListener.java)\n        at org.eclipse.swt.widgets.EventTable.sendEvent(EventTable.java)\n        at org.eclipse.swt.widgets.Widget.sendEvent(Widget.java)\n        at org.eclipse.swt.widgets.Widget.sendEvent(Widget.java)\n        at org.eclipse.swt.widgets.Widget.sendEvent(Widget.java)\n        at org.eclipse.swt.widgets.Sash.gtk_button_release_event(Sash.java:222)\n        at org.eclipse.swt.widgets.Widget.windowProc(Widget.java)\n        at org.eclipse.swt.widgets.Display.windowProc(Display.java)\n        at org.eclipse.swt.internal.gtk.OS.gtk_main_do_event(Native Method)\n        at org.eclipse.swt.widgets.Display.eventProc(Display.java)\n        at org.eclipse.swt.internal.gtk.OS.gtk_main_iteration(Native Method)\n        at org.eclipse.swt.widgets.Display.readAndDispatch(Display.java)\n        at org.eclipse.ui.internal.Workbench.runEventLoop(Workbench.java:1363)\n        at org.eclipse.ui.internal.Workbench.runUI(Workbench.java:1334)\n        at\norg.eclipse.ui.internal.Workbench.createAndRunWorkbench(Workbench.java:253)\n        at org.eclipse.ui.PlatformUI.createAndRunWorkbench(PlatformUI.java:141)\n        at org.eclipse.ui.internal.ide.IDEApplication.run(IDEApplication.java:97)\n        at\norg.eclipse.core.internal.runtime.PlatformActivator$1.run(PlatformActivator.java:299)\n        at\norg.eclipse.core.runtime.adaptor.EclipseStarter.run(EclipseStarter.java:256)\n        at\norg.eclipse.core.runtime.adaptor.EclipseStarter.run(EclipseStarter.java:127)\n        at sun.reflect.NativeMethodAccessorImpl.invoke0(Native Method)\n        at\nsun.reflect.NativeMethodAccessorImpl.invoke(NativeMethodAccessorImpl.java:79)\n        at\nsun.reflect.DelegatingMethodAccessorImpl.invoke(DelegatingMethodAccessorImpl.java:41)\n        at java.lang.reflect.Method.invoke(Method.java:386)\n        at org.eclipse.core.launcher.Main.basicRun(Main.java:184)\n        at org.eclipse.core.launcher.Main.run(Main.java:637)\n        at org.eclipse.core.launcher.Main.main(Main.java:621)\nWidget is disposed\n",
    "This happened when switching presentations. Result as described in comment 1.",
    "reducing severity, since I cannot reproduce consistently.",
    "*** Bug 62819 has been marked as a duplicate of this bug. ***",
    "I\u0027m getting this with the code in head on May 26, 2004.",
    "Fixed in head.\n\nThere were several problems here:\n1. When the current part is removed from a DefaultPartPresentation, it was not\nremoving the reference to the part\u0027s toolbar.\n\n2. PaneFolder was JavaDoc\u0027d to behave like an SWT control, but it could not\nhandle child widgets being disposed without warning (which is normal for SWT\ncomposites).\n\nBoth issues are fixed (although either fix would solve this problem)."
  ],
  "commentCreationDates": [
    "2004-05-17T16:29:05+02:00",
    "2004-05-17T16:29:54+02:00",
    "2004-05-17T16:30:14+02:00",
    "2004-05-18T17:09:22+02:00",
    "2004-05-18T17:12:12+02:00",
    "2004-05-18T17:44:11+02:00",
    "2004-05-19T16:48:17+02:00",
    "2004-05-27T02:50:43+02:00",
    "2004-05-27T18:19:35+02:00"
  ],
  "traces": [
    {
      "exceptionType": "org.eclipse.swt.SWTException",
      "message": "Widget is disposed",
      "elements": [
        {
          "method": "org.eclipse.swt.SWT.error",
          "source": "SWT.java:2689"
        },
        {
          "method": "org.eclipse.swt.SWT.error",
          "source": "SWT.java:2614"
        },
        {
          "method": "org.eclipse.swt.SWT.error",
          "source": "SWT.java:2585"
        },
        {
          "method": "org.eclipse.swt.widgets.Widget.error",
          "source": "Widget.java:381"
        },
        {
          "method": "org.eclipse.swt.widgets.Widget.checkWidget",
          "source": "Widget.java:283"
        },
        {
          "method": "org.eclipse.swt.widgets.Control.getParent",
          "source": "Control.java:885"
        },
        {
          "method": "org.eclipse.ui.internal.presentations.PaneFolder.layout",
          "source": "PaneFolder.ja va:327"
        },
        {
          "method": "org.eclipse.ui.internal.presentations.DefaultPartPresentation.layout",
          "source": " DefaultPartPresentation.java:660"
        },
        {
          "method": "org.eclipse.ui.internal.presentations.DefaultPartPresentation.setBounds",
          "source": "DefaultPartPresentation.java:872"
        },
        {
          "method": "org.eclipse.ui.internal.PartStack.setBounds",
          "source": "PartStack.java:880"
        },
        {
          "method": "org.eclipse.ui.internal.LayoutTree.setBounds",
          "source": "LayoutTree.java:190"
        },
        {
          "method": "org.eclipse.ui.internal.LayoutTreeNode.setBounds",
          "source": "LayoutTreeNode.java: 372"
        },
        {
          "method": "org.eclipse.ui.internal.LayoutTreeNode.setBounds",
          "source": "LayoutTreeNode.java: 296"
        },
        {
          "method": "org.eclipse.ui.internal.PartSashContainer.resizeSashes",
          "source": "PartSashContai ner.java:620"
        },
        {
          "method": "org.eclipse.ui.internal.PartSashContainer.addChild",
          "source": "PartSashContainer. java:332"
        },
        {
          "method": "org.eclipse.ui.internal.ViewSashContainer.addChild",
          "source": "ViewSashContainer. java:280"
        },
        {
          "method": "org.eclipse.ui.internal.PartSashContainer.add",
          "source": "PartSashContainer.java: 928"
        },
        {
          "method": "org.eclipse.ui.internal.PartSashContainer.add",
          "source": "PartSashContainer.java: 259"
        },
        {
          "method": "org.eclipse.ui.internal.PartSashContainer.addEnhanced",
          "source": "PartSashContain er.java:220"
        },
        {
          "method": "org.eclipse.ui.internal.PartSashContainer.add",
          "source": "PartSashContainer.java: 192"
        },
        {
          "method": "org.eclipse.ui.internal.PerspectiveHelper.derefPart",
          "source": "PerspectiveHelper .java:537"
        },
        {
          "method": "org.eclipse.ui.internal.ViewSashContainer.derefPart",
          "source": "ViewSashContainer .java:262"
        },
        {
          "method": "org.eclipse.ui.internal.PartSashContainer.stack",
          "source": "PartSashContainer.jav a:819"
        },
        {
          "method": "org.eclipse.ui.internal.PartSashContainer.dropObject",
          "source": "PartSashContaine r.java:796"
        },
        {
          "method": "org.eclipse.ui.internal.PartSashContainer$SashContainerDropTarget.drop",
          "source": "PartSashContainer.java:110"
        },
        {
          "method": "org.eclipse.ui.internal.dnd.DragUtil.performDrag",
          "source": "DragUtil.java:128"
        },
        {
          "method": "org.eclipse.ui.internal.PartStack.dragStart",
          "source": "PartStack.java:1116"
        },
        {
          "method": "org.eclipse.ui.internal.PartStack$1.dragStart",
          "source": "PartStack.java:78"
        },
        {
          "method": "org.eclipse.ui.internal.presentations.DefaultPartPresentation$10.handleEvent",
          "source": "DefaultPartPresentation.java:308"
        },
        {
          "method": "org.eclipse.ui.presentations.PresentationUtil.handleMouseMove",
          "source": "Present ationUtil.java:89"
        },
        {
          "method": "org.eclipse.ui.presentations.PresentationUtil.access$4",
          "source": "PresentationUt il.java:83"
        },
        {
          "method": "org.eclipse.ui.presentations.PresentationUtil$2.handleEvent",
          "source": "Presentat ionUtil.java:55"
        },
        {
          "method": "org.eclipse.swt.widgets.EventTable.sendEvent",
          "source": "EventTable.java:82"
        },
        {
          "method": "org.eclipse.swt.widgets.Widget.sendEvent",
          "source": "Widget.java:796"
        },
        {
          "method": "org.eclipse.swt.widgets.Display.runDeferredEvents",
          "source": "Display.java:2716"
        },
        {
          "method": "org.eclipse.swt.widgets.Display.readAndDispatch",
          "source": "Display.java:2382"
        },
        {
          "method": "org.eclipse.ui.internal.Workbench.runEventLoop",
          "source": "Workbench.java:1363"
        },
        {
          "method": "org.eclipse.ui.internal.Workbench.runUI",
          "source": "Workbench.java:1334"
        },
        {
          "method": "org.eclipse.ui.internal.Workbench.createAndRunWorkbench",
          "source": "Workbench.jav a:253"
        },
        {
          "method": "org.eclipse.ui.PlatformUI.createAndRunWorkbench",
          "source": "PlatformUI.java:141"
        },
        {
          "method": "org.eclipse.ui.internal.ide.IDEApplication.run",
          "source": "IDEApplication.java:97 "
        },
        {
          "method": "org.eclipse.core.internal.runtime.PlatformActivator$1.run",
          "source": "PlatformAct ivator.java:299"
        },
        {
          "method": "org.eclipse.core.runtime.adaptor.EclipseStarter.run",
          "source": "EclipseStarter.ja va:256"
        },
        {
          "method": "org.eclipse.core.runtime.adaptor.EclipseStarter.run",
          "source": "EclipseStarter.ja va:127"
        },
        {
          "method": "sun.reflect.NativeMethodAccessorImpl.invoke0",
          "source": "Native Method"
        },
        {
          "method": "sun.reflect.NativeMethodAccessorImpl.invoke",
          "source": "NativeMethodAccessorImpl. java:39"
        },
        {
          "method": "sun.reflect.DelegatingMethodAccessorImpl.invoke",
          "source": "DelegatingMethodAcces sorImpl.java:25"
        },
        {
          "method": "java.lang.reflect.Method.invoke",
          "source": "Method.java:324"
        },
        {
          "method": "org.eclipse.core.launcher.Main.basicRun",
          "source": "Main.java:184"
        },
        {
          "method": "org.eclipse.core.launcher.Main.run",
          "source": "Main.java:637"
        },
        {
          "method": "org.eclipse.core.launcher.Main.main",
          "source": "Main.java:621"
        }
      ],
      "number": 0,
      "commentIndex": 0,
      "bugId": "62482",
      "date": "2004-05-17T16:29:05+02:00",
      "product": "Platform",
      "component": "UI",
      "severity": "major"
    },
    {
      "exceptionType": "org.eclipse.swt.SWTException",
      "message": "Widget is disposed",
      "elements": [
        {
          "method": "java.lang.Throwable.\u003cinit\u003e",
          "source": "Throwable.java"
        },
        {
          "method": "java.lang.Throwable.\u003cinit\u003e",
          "source": "Throwable.java"
        },
        {
          "method": "org.eclipse.swt.SWTException.\u003cinit\u003e",
          "source": "SWTException.java:73"
        },
        {
          "method": "org.eclipse.swt.SWT.error",
          "source": "SWT.java:2689"
        },
        {
          "method": "org.eclipse.swt.SWT.error",
          "source": "SWT.java:2614"
        },
        {
          "method": "org.eclipse.swt.SWT.error",
          "source": "SWT.java:2585"
        },
        {
          "method": "org.eclipse.swt.widgets.Widget.error",
          "source": "Widget.java:374"
        },
        {
          "method": "org.eclipse.swt.widgets.Widget.checkWidget",
          "source": "Widget.java"
        },
        {
          "method": "org.eclipse.swt.widgets.Control.getParent",
          "source": "Control.java:1560"
        },
        {
          "method": "org.eclipse.ui.internal.presentations.PaneFolder.layout",
          "source": "PaneFolder.java:327"
        },
        {
          "method": "org.eclipse.ui.internal.presentations.DefaultPartPresentation.layout",
          "source": "DefaultPartPresentation.java:660"
        },
        {
          "method": "org.eclipse.ui.internal.presentations.DefaultPartPresentation.setBounds",
          "source": "DefaultPartPresentation.java:872"
        },
        {
          "method": "org.eclipse.ui.internal.PartStack.setBounds",
          "source": "PartStack.java:879"
        },
        {
          "method": "org.eclipse.ui.internal.LayoutTree.setBounds",
          "source": "LayoutTree.java:190"
        },
        {
          "method": "org.eclipse.ui.internal.LayoutTreeNode.setBounds",
          "source": "LayoutTreeNode.java:373"
        },
        {
          "method": "org.eclipse.ui.internal.LayoutPartSash.widgetSelected",
          "source": "LayoutPartSash.java:191"
        },
        {
          "method": "org.eclipse.ui.internal.LayoutPartSash.access$1",
          "source": "LayoutPartSash.java:176"
        },
        {
          "method": "org.eclipse.ui.internal.LayoutPartSash$1.widgetSelected",
          "source": "LayoutPartSash.java:53"
        },
        {
          "method": "org.eclipse.swt.widgets.TypedListener.handleEvent",
          "source": "TypedListener.java"
        },
        {
          "method": "org.eclipse.swt.widgets.EventTable.sendEvent",
          "source": "EventTable.java"
        },
        {
          "method": "org.eclipse.swt.widgets.Widget.sendEvent",
          "source": "Widget.java"
        },
        {
          "method": "org.eclipse.swt.widgets.Widget.sendEvent",
          "source": "Widget.java"
        },
        {
          "method": "org.eclipse.swt.widgets.Widget.sendEvent",
          "source": "Widget.java"
        },
        {
          "method": "org.eclipse.swt.widgets.Sash.gtk_button_release_event",
          "source": "Sash.java:222"
        },
        {
          "method": "org.eclipse.swt.widgets.Widget.windowProc",
          "source": "Widget.java"
        },
        {
          "method": "org.eclipse.swt.widgets.Display.windowProc",
          "source": "Display.java"
        },
        {
          "method": "org.eclipse.swt.internal.gtk.OS.gtk_main_do_event",
          "source": "Native Method"
        },
        {
          "method": "org.eclipse.swt.widgets.Display.eventProc",
          "source": "Display.java"
        },
        {
          "method": "org.eclipse.swt.internal.gtk.OS.gtk_main_iteration",
          "source": "Native Method"
        },
        {
          "method": "org.eclipse.swt.widgets.Display.readAndDispatch",
          "source": "Display.java"
        },
        {
          "method": "org.eclipse.ui.internal.Workbench.runEventLoop",
          "source": "Workbench.java:1363"
        },
        {
          "method": "org.eclipse.ui.internal.Workbench.runUI",
          "source": "Workbench.java:1334"
        },
        {
          "method": "org.eclipse.ui.internal.Workbench.createAndRunWorkbench",
          "source": "Workbench.java:253"
        },
        {
          "method": "org.eclipse.ui.PlatformUI.createAndRunWorkbench",
          "source": "PlatformUI.java:141"
        },
        {
          "method": "org.eclipse.ui.internal.ide.IDEApplication.run",
          "source": "IDEApplication.java:97"
        },
        {
          "method": "org.eclipse.core.internal.runtime.PlatformActivator$1.run",
          "source": "PlatformActivator.java:299"
        },
        {
          "method": "org.eclipse.core.runtime.adaptor.EclipseStarter.run",
          "source": "EclipseStarter.java:256"
        },
        {
          "method": "org.eclipse.core.runtime.adaptor.EclipseStarter.run",
          "source": "EclipseStarter.java:127"
        },
        {
          "method": "sun.reflect.NativeMethodAccessorImpl.invoke0",
          "source": "Native Method"
        },
        {
          "method": "sun.reflect.NativeMethodAccessorImpl.invoke",
          "source": "NativeMethodAccessorImpl.java:79"
        },
        {
          "method": "sun.reflect.DelegatingMethodAccessorImpl.invoke",
          "source": "DelegatingMethodAccessorImpl.java:41"
        },
        {
          "method": "java.lang.reflect.Method.invoke",
          "source": "Method.java:386"
        },
        {
          "method": "org.eclipse.core.launcher.Main.basicRun",
          "source": "Main.java:184"
        },
        {
          "method": "org.eclipse.core.launcher.Main.run",
          "source": "Main.java:637"
        },
        {
          "method": "org.eclipse.core.launcher.Main.main",
          "source": "Main.java:621"
        }
      ],
      "number": 1,
      "commentIndex": 3,
      "bugId": "62482",
      "date": "2004-05-18T17:09:22+02:00",
      "product": "Platform",
      "component": "UI",
      "severity": "major"
    }
  ],
  "groupId": "62482",
  "bugId": "62482",
  "date": "2004-05-17T16:29:05+02:00",
  "product": "Platform",
  "component": "UI",
  "severity": "major"
}