{
  "comments": [
    "Not sure whose this is....\n\nN20040517\n\nComparing previous versions of TableItem with the current version using \nCompare with version...  After comparing a couple of versions, I finally got \nthis.\n\njava.lang.NullPointerException\n        at java.lang.Throwable.\u003cinit\u003e(Throwable.java)\n        at java.lang.Throwable.\u003cinit\u003e(Throwable.java)\n        at java.lang.NullPointerException.\u003cinit\u003e(NullPointerException.java:60)\n        at org.eclipse.core.internal.content.ContentTypeManager.readBuffer\n(ContentTypeManager.java)\n        at \norg.eclipse.core.internal.content.ContentTypeManager.getDescriptionFor\n(ContentTypeManager.java)\n        at org.eclipse.team.internal.core.TeamPlugin.getContentDescription\n(TeamPlugin.java:143)\n        at org.eclipse.team.internal.core.TeamPlugin.getCharset\n(TeamPlugin.java:121)\n        at \norg.eclipse.team.core.variants.CachedResourceVariant$ResourceVariantStorage.get\nCharset(CachedResourceVariant.java:87)\n        at org.eclipse.team.internal.ccvs.ui.ResourceEditionNode.getCharset\n(ResourceEditionNode.java:156)\n        at org.eclipse.compare.contentmergeviewer.TextMergeViewer.getEncoding\n(TextMergeViewer.java:1670)\n        at org.eclipse.compare.contentmergeviewer.TextMergeViewer.updateContent\n(TextMergeViewer.java:1639)\n        at \norg.eclipse.compare.contentmergeviewer.ContentMergeViewer.internalRefresh\n(ContentMergeViewer.java:661)\n        at \norg.eclipse.compare.contentmergeviewer.ContentMergeViewer.inputChanged\n(ContentMergeViewer.java:558)\n        at org.eclipse.jface.viewers.ContentViewer.setInput(ContentViewer.java)\n        at org.eclipse.compare.CompareViewerSwitchingPane.setInput\n(CompareViewerSwitchingPane.java:302)\n        at org.eclipse.compare.CompareEditorInput$11.run\n(CompareEditorInput.java:526)\n        at org.eclipse.swt.custom.BusyIndicator.showWhile(BusyIndicator.java)\n        at org.eclipse.compare.CompareEditorInput.feed1\n(CompareEditorInput.java:516)\n        at org.eclipse.compare.CompareEditorInput.access$1\n(CompareEditorInput.java:515)\n        at org.eclipse.compare.CompareEditorInput$6.open\n(CompareEditorInput.java:457)\n        at org.eclipse.compare.CompareViewerSwitchingPane$1.open\n(CompareViewerSwitchingPane.java:55)\n        at org.eclipse.jface.viewers.StructuredViewer$2.run\n(StructuredViewer.java:396)\n        at org.eclipse.core.internal.runtime.InternalPlatform.run\n(InternalPlatform.java)\n        at org.eclipse.core.runtime.Platform.run(Platform.java)\n        at org.eclipse.jface.viewers.StructuredViewer.fireOpen\n(StructuredViewer.java:394)\n        at org.eclipse.jface.viewers.StructuredViewer.handleOpen\n(StructuredViewer.java:592)\n        at org.eclipse.jface.viewers.StructuredViewer$6.handleOpen\n(StructuredViewer.java:681)\n        at org.eclipse.jface.util.OpenStrategy.fireOpenEvent\n(OpenStrategy.java:211)\n        at org.eclipse.jface.util.OpenStrategy.access$2(OpenStrategy.java)\n        at org.eclipse.jface.util.OpenStrategy$1.handleEvent(OpenStrategy.java)\n        at org.eclipse.swt.widgets.EventTable.sendEvent(EventTable.java)\n        at org.eclipse.swt.widgets.Widget.sendEvent(Widget.java)\n        at org.eclipse.swt.widgets.Display.runDeferredEvents(Display.java)\n        at org.eclipse.swt.widgets.Display.readAndDispatch(Display.java)\n        at org.eclipse.ui.internal.Workbench.runEventLoop(Workbench.java:1363)\n        at org.eclipse.ui.internal.Workbench.runUI(Workbench.java:1334)\n        at org.eclipse.ui.internal.Workbench.createAndRunWorkbench\n(Workbench.java:253)\n        at org.eclipse.ui.PlatformUI.createAndRunWorkbench(PlatformUI.java:141)\n        at org.eclipse.ui.internal.ide.IDEApplication.run\n(IDEApplication.java:97)\n        at org.eclipse.core.internal.runtime.PlatformActivator$1.run\n(PlatformActivator.java:299)\n        at org.eclipse.core.runtime.adaptor.EclipseStarter.run\n(EclipseStarter.java:256)\n        at org.eclipse.core.runtime.adaptor.EclipseStarter.run\n(EclipseStarter.java:127)\n        at sun.reflect.NativeMethodAccessorImpl.invoke0(Native Method)\n        at sun.reflect.NativeMethodAccessorImpl.invoke\n(NativeMethodAccessorImpl.java:84)\n        at sun.reflect.NativeMethodAccessorImpl.invoke\n(NativeMethodAccessorImpl.java:57)\n        at sun.reflect.DelegatingMethodAccessorImpl.invoke\n(DelegatingMethodAccessorImpl.java:59)\n        at java.lang.reflect.Method.invoke(Method.java:390)\n        at org.eclipse.core.launcher.Main.basicRun(Main.java:184)\n        at org.eclipse.core.launcher.Main.run(Main.java:637)\n        at org.eclipse.core.launcher.Main.main(Main.java:621)",
    "It seems a null input stream is being passed to\nContentTypeManager.getDescriptionFor, and that is not allowed.",
    "This was fixed in I20040517"
  ],
  "commentCreationDates": [
    "2004-05-17T22:42:47+02:00",
    "2004-05-17T23:02:55+02:00",
    "2004-05-17T23:18:22+02:00"
  ],
  "traces": [
    {
      "exceptionType": "java.lang.NullPointerException",
      "elements": [
        {
          "method": "java.lang.Throwable.\u003cinit\u003e",
          "source": "Throwable.java"
        },
        {
          "method": "java.lang.Throwable.\u003cinit\u003e",
          "source": "Throwable.java"
        },
        {
          "method": "java.lang.NullPointerException.\u003cinit\u003e",
          "source": "NullPointerException.java:60"
        },
        {
          "method": "org.eclipse.core.internal.content.ContentTypeManager.readBuffer",
          "source": "ContentTypeManager.java"
        },
        {
          "method": "org.eclipse.core.internal.content.ContentTypeManager.getDescriptionFor",
          "source": "ContentTypeManager.java"
        },
        {
          "method": "org.eclipse.team.internal.core.TeamPlugin.getContentDescription",
          "source": "TeamPlugin.java:143"
        },
        {
          "method": "org.eclipse.team.internal.core.TeamPlugin.getCharset",
          "source": "TeamPlugin.java:121"
        },
        {
          "method": "org.eclipse.team.core.variants.CachedResourceVariant$ResourceVariantStorage.getCharset",
          "source": "CachedResourceVariant.java:87"
        },
        {
          "method": "org.eclipse.team.internal.ccvs.ui.ResourceEditionNode.getCharset",
          "source": "ResourceEditionNode.java:156"
        },
        {
          "method": "org.eclipse.compare.contentmergeviewer.TextMergeViewer.getEncoding",
          "source": "TextMergeViewer.java:1670"
        },
        {
          "method": "org.eclipse.compare.contentmergeviewer.TextMergeViewer.updateContent",
          "source": "TextMergeViewer.java:1639"
        },
        {
          "method": "org.eclipse.compare.contentmergeviewer.ContentMergeViewer.internalRefresh",
          "source": "ContentMergeViewer.java:661"
        },
        {
          "method": "org.eclipse.compare.contentmergeviewer.ContentMergeViewer.inputChanged",
          "source": "ContentMergeViewer.java:558"
        },
        {
          "method": "org.eclipse.jface.viewers.ContentViewer.setInput",
          "source": "ContentViewer.java"
        },
        {
          "method": "org.eclipse.compare.CompareViewerSwitchingPane.setInput",
          "source": "CompareViewerSwitchingPane.java:302"
        },
        {
          "method": "org.eclipse.compare.CompareEditorInput$11.run",
          "source": "CompareEditorInput.java:526"
        },
        {
          "method": "org.eclipse.swt.custom.BusyIndicator.showWhile",
          "source": "BusyIndicator.java"
        },
        {
          "method": "org.eclipse.compare.CompareEditorInput.feed1",
          "source": "CompareEditorInput.java:516"
        },
        {
          "method": "org.eclipse.compare.CompareEditorInput.access$1",
          "source": "CompareEditorInput.java:515"
        },
        {
          "method": "org.eclipse.compare.CompareEditorInput$6.open",
          "source": "CompareEditorInput.java:457"
        },
        {
          "method": "org.eclipse.compare.CompareViewerSwitchingPane$1.open",
          "source": "CompareViewerSwitchingPane.java:55"
        },
        {
          "method": "org.eclipse.jface.viewers.StructuredViewer$2.run",
          "source": "StructuredViewer.java:396"
        },
        {
          "method": "org.eclipse.core.internal.runtime.InternalPlatform.run",
          "source": "InternalPlatform.java"
        },
        {
          "method": "org.eclipse.core.runtime.Platform.run",
          "source": "Platform.java"
        },
        {
          "method": "org.eclipse.jface.viewers.StructuredViewer.fireOpen",
          "source": "StructuredViewer.java:394"
        },
        {
          "method": "org.eclipse.jface.viewers.StructuredViewer.handleOpen",
          "source": "StructuredViewer.java:592"
        },
        {
          "method": "org.eclipse.jface.viewers.StructuredViewer$6.handleOpen",
          "source": "StructuredViewer.java:681"
        },
        {
          "method": "org.eclipse.jface.util.OpenStrategy.fireOpenEvent",
          "source": "OpenStrategy.java:211"
        },
        {
          "method": "org.eclipse.jface.util.OpenStrategy.access$2",
          "source": "OpenStrategy.java"
        },
        {
          "method": "org.eclipse.jface.util.OpenStrategy$1.handleEvent",
          "source": "OpenStrategy.java"
        },
        {
          "method": "org.eclipse.swt.widgets.EventTable.sendEvent",
          "source": "EventTable.java"
        },
        {
          "method": "org.eclipse.swt.widgets.Widget.sendEvent",
          "source": "Widget.java"
        },
        {
          "method": "org.eclipse.swt.widgets.Display.runDeferredEvents",
          "source": "Display.java"
        },
        {
          "method": "org.eclipse.swt.widgets.Display.readAndDispatch",
          "source": "Display.java"
        },
        {
          "method": "org.eclipse.ui.internal.Workbench.runEventLoop",
          "source": "Workbench.java:1363"
        },
        {
          "method": "org.eclipse.ui.internal.Workbench.runUI",
          "source": "Workbench.java:1334"
        },
        {
          "method": "org.eclipse.ui.internal.Workbench.createAndRunWorkbench",
          "source": "Workbench.java:253"
        },
        {
          "method": "org.eclipse.ui.PlatformUI.createAndRunWorkbench",
          "source": "PlatformUI.java:141"
        },
        {
          "method": "org.eclipse.ui.internal.ide.IDEApplication.run",
          "source": "IDEApplication.java:97"
        },
        {
          "method": "org.eclipse.core.internal.runtime.PlatformActivator$1.run",
          "source": "PlatformActivator.java:299"
        },
        {
          "method": "org.eclipse.core.runtime.adaptor.EclipseStarter.run",
          "source": "EclipseStarter.java:256"
        },
        {
          "method": "org.eclipse.core.runtime.adaptor.EclipseStarter.run",
          "source": "EclipseStarter.java:127"
        },
        {
          "method": "sun.reflect.NativeMethodAccessorImpl.invoke0",
          "source": "Native Method"
        },
        {
          "method": "sun.reflect.NativeMethodAccessorImpl.invoke",
          "source": "NativeMethodAccessorImpl.java:84"
        },
        {
          "method": "sun.reflect.NativeMethodAccessorImpl.invoke",
          "source": "NativeMethodAccessorImpl.java:57"
        },
        {
          "method": "sun.reflect.DelegatingMethodAccessorImpl.invoke",
          "source": "DelegatingMethodAccessorImpl.java:59"
        },
        {
          "method": "java.lang.reflect.Method.invoke",
          "source": "Method.java:390"
        },
        {
          "method": "org.eclipse.core.launcher.Main.basicRun",
          "source": "Main.java:184"
        },
        {
          "method": "org.eclipse.core.launcher.Main.run",
          "source": "Main.java:637"
        },
        {
          "method": "org.eclipse.core.launcher.Main.main",
          "source": "Main.java:621"
        }
      ],
      "number": 0,
      "commentIndex": 0,
      "bugId": "62551",
      "date": "2004-05-17T22:42:47+02:00",
      "product": "Platform",
      "component": "CVS",
      "severity": "normal"
    }
  ],
  "groupId": "62551",
  "bugId": "62551",
  "date": "2004-05-17T22:42:47+02:00",
  "product": "Platform",
  "component": "CVS",
  "severity": "normal"
}