{
  "comments": [
    "I got i0517 and started it on my normal workspace.  On startup I got the \nfollowing log.  Note that this workspace has an open (customized) Debug \nperspective...\n\n!ENTRY org.eclipse.core.runtime 4 2 May 17, 2004 20:57:24.416\n!MESSAGE Problems occurred when invoking code from plug-\nin: \"org.eclipse.core.runtime\".\n!STACK 0\njava.lang.NullPointerException\n        at \norg.eclipse.debug.internal.ui.views.launch.LaunchView.perspectiveChanged\n(LaunchView.java:614)\n        at org.eclipse.ui.internal.PerspectiveListenerListOld$2.run\n(PerspectiveListenerListOld.java:58)\n        at org.eclipse.core.internal.runtime.InternalPlatform.run\n(InternalPlatform.java:608)\n        at org.eclipse.core.runtime.Platform.run(Platform.java:668)\n        at \norg.eclipse.ui.internal.PerspectiveListenerListOld.firePerspectiveChanged\n(PerspectiveListenerListOld.java:56)\n\n        at org.eclipse.ui.internal.WorkbenchWindow.firePerspectiveChanged\n(WorkbenchWindow.java:913)\n        at org.eclipse.ui.internal.WorkbenchPage.showActionSet\n(WorkbenchPage.java:2921)\n        at \norg.eclipse.debug.internal.ui.views.launch.LaunchViewContextListener.showDebugAc\ntionSet(LaunchViewContextList\nener.java:821)\n        at \norg.eclipse.debug.internal.ui.views.launch.LaunchViewContextListener.\u003cinit\u003e\n(LaunchViewContextListener.java:13\n5)\n        at org.eclipse.debug.internal.ui.views.launch.LaunchView.partOpened\n(LaunchView.java:656)\n        at org.eclipse.ui.internal.PartListenerList$5.run\n(PartListenerList.java:105)\n        at org.eclipse.core.internal.runtime.InternalPlatform.run\n(InternalPlatform.java:608)\n        at org.eclipse.core.runtime.Platform.run(Platform.java:668)\n        at org.eclipse.ui.internal.PartListenerList.firePartOpened\n(PartListenerList.java:103)\n        at org.eclipse.ui.internal.WorkbenchPage.firePartOpened\n(WorkbenchPage.java:1404)\n        at org.eclipse.ui.internal.PartPane.createChildControl\n(PartPane.java:138)\n        at org.eclipse.ui.internal.ViewPane.createChildControl\n(ViewPane.java:140)\n        at org.eclipse.ui.internal.ViewFactory$1.run(ViewFactory.java:276)\n        at org.eclipse.core.internal.runtime.InternalPlatform.run\n(InternalPlatform.java:608)\n        at org.eclipse.core.runtime.Platform.run(Platform.java:668)\n        at org.eclipse.ui.internal.ViewFactory.busyRestoreView\n(ViewFactory.java:202)\n        at org.eclipse.ui.internal.ViewFactory$2.run(ViewFactory.java:454)\n        at org.eclipse.swt.custom.BusyIndicator.showWhile(BusyIndicator.java:69)\n        at org.eclipse.ui.internal.ViewFactory.restoreView(ViewFactory.java:452)\n        at org.eclipse.ui.internal.ViewFactory$ViewReference.getPart\n(ViewFactory.java:93)\n        at org.eclipse.ui.internal.WorkbenchPage$1.propertyChange\n(WorkbenchPage.java:130)\n        at org.eclipse.ui.internal.LayoutPart.setVisible(LayoutPart.java:257)\n        at org.eclipse.ui.internal.PartPane.setVisible(PartPane.java:282)\n        at org.eclipse.ui.internal.ViewPane.setVisible(ViewPane.java:567)\n        at org.eclipse.ui.internal.presentations.PresentableViewPart.setVisible\n(PresentableViewPart.java:114)\n        at \norg.eclipse.ui.internal.presentations.DefaultPartPresentation.selectPart\n(DefaultPartPresentation.java:846)\n        at org.eclipse.ui.internal.PartStack.refreshPresentationSelection\n(PartStack.java:799)\n        at org.eclipse.ui.internal.PartStack.createControl(PartStack.java:347)\n        at org.eclipse.ui.internal.PartStack.createControl(PartStack.java:247)\n        at org.eclipse.ui.internal.PartSashContainer.createControl\n(PartSashContainer.java:427)\n        at org.eclipse.ui.internal.PerspectiveHelper.activate\n(PerspectiveHelper.java:156)\n        at org.eclipse.ui.internal.Perspective.onActivate(Perspective.java:718)\n        at org.eclipse.ui.internal.WorkbenchPage.onActivate\n(WorkbenchPage.java:1994)\n        at org.eclipse.ui.internal.WorkbenchWindow$7.run\n(WorkbenchWindow.java:1907)\n        at org.eclipse.swt.custom.BusyIndicator.showWhile(BusyIndicator.java:69)\n        at org.eclipse.ui.internal.WorkbenchWindow.setActivePage\n(WorkbenchWindow.java:1894)\n        at org.eclipse.ui.internal.WorkbenchWindow.restoreState\n(WorkbenchWindow.java:1462)\n        at org.eclipse.ui.internal.Workbench.restoreState(Workbench.java:1216)\n        at org.eclipse.ui.internal.Workbench.access$10(Workbench.java:1183)\n        at org.eclipse.ui.internal.Workbench$13.run(Workbench.java:1094)\n        at org.eclipse.core.internal.runtime.InternalPlatform.run\n(InternalPlatform.java:608)\n        at org.eclipse.core.runtime.Platform.run(Platform.java:668)\n        at org.eclipse.ui.internal.Workbench.restoreState(Workbench.java:1027)\n        at org.eclipse.ui.internal.WorkbenchConfigurer.restoreState\n(WorkbenchConfigurer.java:167)\n        at org.eclipse.ui.application.WorkbenchAdvisor.openWindows\n(WorkbenchAdvisor.java:652)\n        at org.eclipse.ui.internal.Workbench.init(Workbench.java:817)\n        at org.eclipse.ui.internal.Workbench.runUI(Workbench.java:1311)\n        at org.eclipse.ui.internal.Workbench.createAndRunWorkbench\n(Workbench.java:253)\n        at org.eclipse.ui.PlatformUI.createAndRunWorkbench(PlatformUI.java:141)\n        at org.eclipse.ui.internal.ide.IDEApplication.run\n(IDEApplication.java:97)\n        at org.eclipse.core.internal.runtime.PlatformActivator$1.run\n(PlatformActivator.java:299)\n        at org.eclipse.core.runtime.adaptor.EclipseStarter.run\n(EclipseStarter.java:256)\n        at org.eclipse.core.runtime.adaptor.EclipseStarter.run\n(EclipseStarter.java:127)\n        at sun.reflect.NativeMethodAccessorImpl.invoke0(Native Method)\n        at sun.reflect.NativeMethodAccessorImpl.invoke\n(NativeMethodAccessorImpl.java:39)\n        at sun.reflect.DelegatingMethodAccessorImpl.invoke\n(DelegatingMethodAccessorImpl.java:25)\n        at java.lang.reflect.Method.invoke(Method.java:324)\n        at org.eclipse.core.launcher.Main.basicRun(Main.java:184)\n        at org.eclipse.core.launcher.Main.run(Main.java:637)\n        at org.eclipse.core.launcher.Main.main(Main.java:621)\n!ENTRY org.eclipse.ui 4 4 May 17, 2004 20:57:25.128\n!MESSAGE Unable to find Action Set: org.eclipse.ui.Activities\nUnable to find Action Set: org.eclipse.ui.Activities",
    "\n\n*** This bug has been marked as a duplicate of 60327 ***"
  ],
  "commentCreationDates": [
    "2004-05-18T03:25:10+02:00",
    "2004-05-18T03:29:12+02:00"
  ],
  "traces": [
    {
      "exceptionType": "java.lang.NullPointerException",
      "elements": [
        {
          "method": "org.eclipse.debug.internal.ui.views.launch.LaunchView.perspectiveChanged",
          "source": "LaunchView.java:614"
        },
        {
          "method": "org.eclipse.ui.internal.PerspectiveListenerListOld$2.run",
          "source": "PerspectiveListenerListOld.java:58"
        },
        {
          "method": "org.eclipse.core.internal.runtime.InternalPlatform.run",
          "source": "InternalPlatform.java:608"
        },
        {
          "method": "org.eclipse.core.runtime.Platform.run",
          "source": "Platform.java:668"
        },
        {
          "method": "org.eclipse.ui.internal.PerspectiveListenerListOld.firePerspectiveChanged",
          "source": "PerspectiveListenerListOld.java:56"
        },
        {
          "method": "org.eclipse.ui.internal.WorkbenchWindow.firePerspectiveChanged",
          "source": "WorkbenchWindow.java:913"
        },
        {
          "method": "org.eclipse.ui.internal.WorkbenchPage.showActionSet",
          "source": "WorkbenchPage.java:2921"
        },
        {
          "method": "org.eclipse.debug.internal.ui.views.launch.LaunchViewContextListener.showDebugActionSet",
          "source": "LaunchViewContextList ener.java:821"
        },
        {
          "method": "org.eclipse.debug.internal.ui.views.launch.LaunchViewContextListener.\u003cinit\u003e",
          "source": "LaunchViewContextListener.java:13 5"
        },
        {
          "method": "org.eclipse.debug.internal.ui.views.launch.LaunchView.partOpened",
          "source": "LaunchView.java:656"
        },
        {
          "method": "org.eclipse.ui.internal.PartListenerList$5.run",
          "source": "PartListenerList.java:105"
        },
        {
          "method": "org.eclipse.core.internal.runtime.InternalPlatform.run",
          "source": "InternalPlatform.java:608"
        },
        {
          "method": "org.eclipse.core.runtime.Platform.run",
          "source": "Platform.java:668"
        },
        {
          "method": "org.eclipse.ui.internal.PartListenerList.firePartOpened",
          "source": "PartListenerList.java:103"
        },
        {
          "method": "org.eclipse.ui.internal.WorkbenchPage.firePartOpened",
          "source": "WorkbenchPage.java:1404"
        },
        {
          "method": "org.eclipse.ui.internal.PartPane.createChildControl",
          "source": "PartPane.java:138"
        },
        {
          "method": "org.eclipse.ui.internal.ViewPane.createChildControl",
          "source": "ViewPane.java:140"
        },
        {
          "method": "org.eclipse.ui.internal.ViewFactory$1.run",
          "source": "ViewFactory.java:276"
        },
        {
          "method": "org.eclipse.core.internal.runtime.InternalPlatform.run",
          "source": "InternalPlatform.java:608"
        },
        {
          "method": "org.eclipse.core.runtime.Platform.run",
          "source": "Platform.java:668"
        },
        {
          "method": "org.eclipse.ui.internal.ViewFactory.busyRestoreView",
          "source": "ViewFactory.java:202"
        },
        {
          "method": "org.eclipse.ui.internal.ViewFactory$2.run",
          "source": "ViewFactory.java:454"
        },
        {
          "method": "org.eclipse.swt.custom.BusyIndicator.showWhile",
          "source": "BusyIndicator.java:69"
        },
        {
          "method": "org.eclipse.ui.internal.ViewFactory.restoreView",
          "source": "ViewFactory.java:452"
        },
        {
          "method": "org.eclipse.ui.internal.ViewFactory$ViewReference.getPart",
          "source": "ViewFactory.java:93"
        },
        {
          "method": "org.eclipse.ui.internal.WorkbenchPage$1.propertyChange",
          "source": "WorkbenchPage.java:130"
        },
        {
          "method": "org.eclipse.ui.internal.LayoutPart.setVisible",
          "source": "LayoutPart.java:257"
        },
        {
          "method": "org.eclipse.ui.internal.PartPane.setVisible",
          "source": "PartPane.java:282"
        },
        {
          "method": "org.eclipse.ui.internal.ViewPane.setVisible",
          "source": "ViewPane.java:567"
        },
        {
          "method": "org.eclipse.ui.internal.presentations.PresentableViewPart.setVisible",
          "source": "PresentableViewPart.java:114"
        },
        {
          "method": "org.eclipse.ui.internal.presentations.DefaultPartPresentation.selectPart",
          "source": "DefaultPartPresentation.java:846"
        },
        {
          "method": "org.eclipse.ui.internal.PartStack.refreshPresentationSelection",
          "source": "PartStack.java:799"
        },
        {
          "method": "org.eclipse.ui.internal.PartStack.createControl",
          "source": "PartStack.java:347"
        },
        {
          "method": "org.eclipse.ui.internal.PartStack.createControl",
          "source": "PartStack.java:247"
        },
        {
          "method": "org.eclipse.ui.internal.PartSashContainer.createControl",
          "source": "PartSashContainer.java:427"
        },
        {
          "method": "org.eclipse.ui.internal.PerspectiveHelper.activate",
          "source": "PerspectiveHelper.java:156"
        },
        {
          "method": "org.eclipse.ui.internal.Perspective.onActivate",
          "source": "Perspective.java:718"
        },
        {
          "method": "org.eclipse.ui.internal.WorkbenchPage.onActivate",
          "source": "WorkbenchPage.java:1994"
        },
        {
          "method": "org.eclipse.ui.internal.WorkbenchWindow$7.run",
          "source": "WorkbenchWindow.java:1907"
        },
        {
          "method": "org.eclipse.swt.custom.BusyIndicator.showWhile",
          "source": "BusyIndicator.java:69"
        },
        {
          "method": "org.eclipse.ui.internal.WorkbenchWindow.setActivePage",
          "source": "WorkbenchWindow.java:1894"
        },
        {
          "method": "org.eclipse.ui.internal.WorkbenchWindow.restoreState",
          "source": "WorkbenchWindow.java:1462"
        },
        {
          "method": "org.eclipse.ui.internal.Workbench.restoreState",
          "source": "Workbench.java:1216"
        },
        {
          "method": "org.eclipse.ui.internal.Workbench.access$10",
          "source": "Workbench.java:1183"
        },
        {
          "method": "org.eclipse.ui.internal.Workbench$13.run",
          "source": "Workbench.java:1094"
        },
        {
          "method": "org.eclipse.core.internal.runtime.InternalPlatform.run",
          "source": "InternalPlatform.java:608"
        },
        {
          "method": "org.eclipse.core.runtime.Platform.run",
          "source": "Platform.java:668"
        },
        {
          "method": "org.eclipse.ui.internal.Workbench.restoreState",
          "source": "Workbench.java:1027"
        },
        {
          "method": "org.eclipse.ui.internal.WorkbenchConfigurer.restoreState",
          "source": "WorkbenchConfigurer.java:167"
        },
        {
          "method": "org.eclipse.ui.application.WorkbenchAdvisor.openWindows",
          "source": "WorkbenchAdvisor.java:652"
        },
        {
          "method": "org.eclipse.ui.internal.Workbench.init",
          "source": "Workbench.java:817"
        },
        {
          "method": "org.eclipse.ui.internal.Workbench.runUI",
          "source": "Workbench.java:1311"
        },
        {
          "method": "org.eclipse.ui.internal.Workbench.createAndRunWorkbench",
          "source": "Workbench.java:253"
        },
        {
          "method": "org.eclipse.ui.PlatformUI.createAndRunWorkbench",
          "source": "PlatformUI.java:141"
        },
        {
          "method": "org.eclipse.ui.internal.ide.IDEApplication.run",
          "source": "IDEApplication.java:97"
        },
        {
          "method": "org.eclipse.core.internal.runtime.PlatformActivator$1.run",
          "source": "PlatformActivator.java:299"
        },
        {
          "method": "org.eclipse.core.runtime.adaptor.EclipseStarter.run",
          "source": "EclipseStarter.java:256"
        },
        {
          "method": "org.eclipse.core.runtime.adaptor.EclipseStarter.run",
          "source": "EclipseStarter.java:127"
        },
        {
          "method": "sun.reflect.NativeMethodAccessorImpl.invoke0",
          "source": "Native Method"
        },
        {
          "method": "sun.reflect.NativeMethodAccessorImpl.invoke",
          "source": "NativeMethodAccessorImpl.java:39"
        },
        {
          "method": "sun.reflect.DelegatingMethodAccessorImpl.invoke",
          "source": "DelegatingMethodAccessorImpl.java:25"
        },
        {
          "method": "java.lang.reflect.Method.invoke",
          "source": "Method.java:324"
        },
        {
          "method": "org.eclipse.core.launcher.Main.basicRun",
          "source": "Main.java:184"
        },
        {
          "method": "org.eclipse.core.launcher.Main.run",
          "source": "Main.java:637"
        },
        {
          "method": "org.eclipse.core.launcher.Main.main",
          "source": "Main.java:621"
        }
      ],
      "number": 0,
      "commentIndex": 0,
      "bugId": "62579",
      "duplicateId": "60327",
      "date": "2004-05-18T03:25:10+02:00",
      "product": "Platform",
      "component": "Debug",
      "severity": "normal"
    }
  ],
  "groupId": "60327",
  "bugId": "62579",
  "duplicateId": "60327",
  "date": "2004-05-18T03:25:10+02:00",
  "product": "Platform",
  "component": "Debug",
  "severity": "normal"
}