{
  "comments": [
    "I200405171219 with ZRH plugin-export from 20040518_0827\n\nSteps to reproduce (not always):\n- start eclipse\n- open Java file 1\n- open Java file 2\n- drag tab of editor 2 to bottom, such that editor area is split horizontally\n- drag tab of editor 1 on tab of editor 2\n- close all\n-\u003e exception or sometimes a tab is left behind\n\norg.eclipse.swt.SWTException: Graphic is disposed\n        at org.eclipse.swt.SWT.error(SWT.java:2689)\n        at org.eclipse.swt.SWT.error(SWT.java:2614)\n        at org.eclipse.swt.SWT.error(SWT.java:2585)\n        at org.eclipse.swt.graphics.Image.getBounds(Image.java:950)\n        at org.eclipse.swt.custom.CTabItem.preferredWidth(CTabItem.java:601)\n        at org.eclipse.swt.custom.CTabFolder.setItemSize(CTabFolder.java:2693)\n        at org.eclipse.swt.custom.CTabFolder.updateItems(CTabFolder.java:3379)\n        at org.eclipse.swt.custom.CTabFolder.destroyItem(CTabFolder.java:640)\n        at org.eclipse.swt.custom.CTabItem.dispose(CTabItem.java:135)\n        at org.eclipse.ui.internal.presentations.DefaultPartPresentation.removeP\nart(DefaultPartPresentation.java:827)\n        at org.eclipse.ui.internal.PartStack.remove(PartStack.java:572)\n        at org.eclipse.ui.internal.EditorSashContainer.removeEditor(EditorSashCo\nntainer.java:193)\n        at org.eclipse.ui.internal.EditorAreaHelper.closeEditor(EditorAreaHelper\n.java:109)\n        at org.eclipse.ui.internal.EditorAreaHelper.closeEditor(EditorAreaHelper\n.java:99)\n        at org.eclipse.ui.internal.EditorManager.closeEditor(EditorManager.java:\n160)\n        at org.eclipse.ui.internal.WorkbenchPage.closeEditors(WorkbenchPage.java\n:906)\n        at org.eclipse.ui.internal.WorkbenchPage.closeAllEditors(WorkbenchPage.j\nava:853)\n        at org.eclipse.ui.internal.CloseAllAction.run(CloseAllAction.java:74)\n        at org.eclipse.jface.action.Action.runWithEvent(Action.java:881)\n        at org.eclipse.ui.commands.ActionHandler.execute(ActionHandler.java:141)\n\n        at org.eclipse.ui.internal.commands.Command.execute(Command.java:132)\n        at org.eclipse.ui.internal.keys.WorkbenchKeyboard.executeCommand(Workben\nchKeyboard.java:468)\n        at org.eclipse.ui.internal.keys.WorkbenchKeyboard.press(WorkbenchKeyboar\nd.java:886)\n        at org.eclipse.ui.internal.keys.WorkbenchKeyboard.processKeyEvent(Workbe\nnchKeyboard.java:927)\n        at org.eclipse.ui.internal.keys.WorkbenchKeyboard.filterKeySequenceBindi\nngs(WorkbenchKeyboard.java:545)\n        at org.eclipse.ui.internal.keys.WorkbenchKeyboard.access$2(WorkbenchKeyb\noard.java:493)\n        at org.eclipse.ui.internal.keys.WorkbenchKeyboard$1.handleEvent(Workbenc\nhKeyboard.java:258)\n        at org.eclipse.swt.widgets.EventTable.sendEvent(EventTable.java:82)\n        at org.eclipse.swt.widgets.Display.filterEvent(Display.java:712)\n        at org.eclipse.swt.widgets.Widget.sendEvent(Widget.java:795)\n        at org.eclipse.swt.widgets.Widget.sendEvent(Widget.java:820)\n        at org.eclipse.swt.widgets.Widget.sendEvent(Widget.java:805)\n        at org.eclipse.swt.widgets.Control.sendKeyEvent(Control.java:1724)\n        at org.eclipse.swt.widgets.Control.sendKeyEvent(Control.java:1720)\n        at org.eclipse.swt.widgets.Control.WM_KEYDOWN(Control.java:3499)\n        at org.eclipse.swt.widgets.Control.windowProc(Control.java:2978)\n        at org.eclipse.swt.widgets.Display.windowProc(Display.java:3291)\n        at org.eclipse.swt.internal.win32.OS.DispatchMessageW(Native Method)\n        at org.eclipse.swt.internal.win32.OS.DispatchMessage(OS.java:1466)\n        at org.eclipse.swt.widgets.Display.readAndDispatch(Display.java:2388)\n        at org.eclipse.ui.internal.Workbench.runEventLoop(Workbench.java:1363)\n        at org.eclipse.ui.internal.Workbench.runUI(Workbench.java:1334)\n        at org.eclipse.ui.internal.Workbench.createAndRunWorkbench(Workbench.jav\na:253)\n        at org.eclipse.ui.PlatformUI.createAndRunWorkbench(PlatformUI.java:141)\n        at org.eclipse.ui.internal.ide.IDEApplication.run(IDEApplication.java:97\n)\n        at org.eclipse.core.internal.runtime.PlatformActivator$1.run(PlatformAct\nivator.java:299)\n        at org.eclipse.core.runtime.adaptor.EclipseStarter.run(EclipseStarter.ja\nva:256)\n        at org.eclipse.core.runtime.adaptor.EclipseStarter.run(EclipseStarter.ja\nva:127)\n        at sun.reflect.NativeMethodAccessorImpl.invoke0(Native Method)\n        at sun.reflect.NativeMethodAccessorImpl.invoke(NativeMethodAccessorImpl.\njava:39)\n        at sun.reflect.DelegatingMethodAccessorImpl.invoke(DelegatingMethodAcces\nsorImpl.java:25)\n        at java.lang.reflect.Method.invoke(Method.java:324)\n        at org.eclipse.core.launcher.Main.basicRun(Main.java:184)\n        at org.eclipse.core.launcher.Main.run(Main.java:637)\n        at org.eclipse.core.launcher.Main.main(Main.java:621)\nGraphic is disposed",
    "I cannot reproduce this with this morning\u0027s integration build (0518).  Please \ntry this and follow up here whether it still happens for you or not, and if so \nthen the steps must be more specific than what were originally listed.\n",
    "I cannot reproduce on I200405180816 either. I\u0027d agree on closing then.",
    "closing\n"
  ],
  "commentCreationDates": [
    "2004-05-18T10:21:54+02:00",
    "2004-05-18T16:40:33+02:00",
    "2004-05-18T18:38:58+02:00",
    "2004-05-18T18:48:59+02:00"
  ],
  "traces": [
    {
      "exceptionType": "org.eclipse.swt.SWTException",
      "message": "Graphic is disposed",
      "elements": [
        {
          "method": "org.eclipse.swt.SWT.error",
          "source": "SWT.java:2689"
        },
        {
          "method": "org.eclipse.swt.SWT.error",
          "source": "SWT.java:2614"
        },
        {
          "method": "org.eclipse.swt.SWT.error",
          "source": "SWT.java:2585"
        },
        {
          "method": "org.eclipse.swt.graphics.Image.getBounds",
          "source": "Image.java:950"
        },
        {
          "method": "org.eclipse.swt.custom.CTabItem.preferredWidth",
          "source": "CTabItem.java:601"
        },
        {
          "method": "org.eclipse.swt.custom.CTabFolder.setItemSize",
          "source": "CTabFolder.java:2693"
        },
        {
          "method": "org.eclipse.swt.custom.CTabFolder.updateItems",
          "source": "CTabFolder.java:3379"
        },
        {
          "method": "org.eclipse.swt.custom.CTabFolder.destroyItem",
          "source": "CTabFolder.java:640"
        },
        {
          "method": "org.eclipse.swt.custom.CTabItem.dispose",
          "source": "CTabItem.java:135"
        },
        {
          "method": "org.eclipse.ui.internal.presentations.DefaultPartPresentation.removePart",
          "source": "DefaultPartPresentation.java:827"
        },
        {
          "method": "org.eclipse.ui.internal.PartStack.remove",
          "source": "PartStack.java:572"
        },
        {
          "method": "org.eclipse.ui.internal.EditorSashContainer.removeEditor",
          "source": "EditorSashCo ntainer.java:193"
        },
        {
          "method": "org.eclipse.ui.internal.EditorAreaHelper.closeEditor",
          "source": "EditorAreaHelper .java:109"
        },
        {
          "method": "org.eclipse.ui.internal.EditorAreaHelper.closeEditor",
          "source": "EditorAreaHelper .java:99"
        },
        {
          "method": "org.eclipse.ui.internal.EditorManager.closeEditor",
          "source": "EditorManager.java: 160"
        },
        {
          "method": "org.eclipse.ui.internal.WorkbenchPage.closeEditors",
          "source": "WorkbenchPage.java :906"
        },
        {
          "method": "org.eclipse.ui.internal.WorkbenchPage.closeAllEditors",
          "source": "WorkbenchPage.j ava:853"
        },
        {
          "method": "org.eclipse.ui.internal.CloseAllAction.run",
          "source": "CloseAllAction.java:74"
        },
        {
          "method": "org.eclipse.jface.action.Action.runWithEvent",
          "source": "Action.java:881"
        },
        {
          "method": "org.eclipse.ui.commands.ActionHandler.execute",
          "source": "ActionHandler.java:141"
        },
        {
          "method": "org.eclipse.ui.internal.commands.Command.execute",
          "source": "Command.java:132"
        },
        {
          "method": "org.eclipse.ui.internal.keys.WorkbenchKeyboard.executeCommand",
          "source": "Workben chKeyboard.java:468"
        },
        {
          "method": "org.eclipse.ui.internal.keys.WorkbenchKeyboard.press",
          "source": "WorkbenchKeyboar d.java:886"
        },
        {
          "method": "org.eclipse.ui.internal.keys.WorkbenchKeyboard.processKeyEvent",
          "source": "Workbe nchKeyboard.java:927"
        },
        {
          "method": "org.eclipse.ui.internal.keys.WorkbenchKeyboard.filterKeySequenceBindings",
          "source": "WorkbenchKeyboard.java:545"
        },
        {
          "method": "org.eclipse.ui.internal.keys.WorkbenchKeyboard.access$2",
          "source": "WorkbenchKeyb oard.java:493"
        },
        {
          "method": "org.eclipse.ui.internal.keys.WorkbenchKeyboard$1.handleEvent",
          "source": "Workbenc hKeyboard.java:258"
        },
        {
          "method": "org.eclipse.swt.widgets.EventTable.sendEvent",
          "source": "EventTable.java:82"
        },
        {
          "method": "org.eclipse.swt.widgets.Display.filterEvent",
          "source": "Display.java:712"
        },
        {
          "method": "org.eclipse.swt.widgets.Widget.sendEvent",
          "source": "Widget.java:795"
        },
        {
          "method": "org.eclipse.swt.widgets.Widget.sendEvent",
          "source": "Widget.java:820"
        },
        {
          "method": "org.eclipse.swt.widgets.Widget.sendEvent",
          "source": "Widget.java:805"
        },
        {
          "method": "org.eclipse.swt.widgets.Control.sendKeyEvent",
          "source": "Control.java:1724"
        },
        {
          "method": "org.eclipse.swt.widgets.Control.sendKeyEvent",
          "source": "Control.java:1720"
        },
        {
          "method": "org.eclipse.swt.widgets.Control.WM_KEYDOWN",
          "source": "Control.java:3499"
        },
        {
          "method": "org.eclipse.swt.widgets.Control.windowProc",
          "source": "Control.java:2978"
        },
        {
          "method": "org.eclipse.swt.widgets.Display.windowProc",
          "source": "Display.java:3291"
        },
        {
          "method": "org.eclipse.swt.internal.win32.OS.DispatchMessageW",
          "source": "Native Method"
        },
        {
          "method": "org.eclipse.swt.internal.win32.OS.DispatchMessage",
          "source": "OS.java:1466"
        },
        {
          "method": "org.eclipse.swt.widgets.Display.readAndDispatch",
          "source": "Display.java:2388"
        },
        {
          "method": "org.eclipse.ui.internal.Workbench.runEventLoop",
          "source": "Workbench.java:1363"
        },
        {
          "method": "org.eclipse.ui.internal.Workbench.runUI",
          "source": "Workbench.java:1334"
        },
        {
          "method": "org.eclipse.ui.internal.Workbench.createAndRunWorkbench",
          "source": "Workbench.jav a:253"
        },
        {
          "method": "org.eclipse.ui.PlatformUI.createAndRunWorkbench",
          "source": "PlatformUI.java:141"
        },
        {
          "method": "org.eclipse.ui.internal.ide.IDEApplication.run",
          "source": "IDEApplication.java:97 "
        },
        {
          "method": "org.eclipse.core.internal.runtime.PlatformActivator$1.run",
          "source": "PlatformAct ivator.java:299"
        },
        {
          "method": "org.eclipse.core.runtime.adaptor.EclipseStarter.run",
          "source": "EclipseStarter.ja va:256"
        },
        {
          "method": "org.eclipse.core.runtime.adaptor.EclipseStarter.run",
          "source": "EclipseStarter.ja va:127"
        },
        {
          "method": "sun.reflect.NativeMethodAccessorImpl.invoke0",
          "source": "Native Method"
        },
        {
          "method": "sun.reflect.NativeMethodAccessorImpl.invoke",
          "source": "NativeMethodAccessorImpl. java:39"
        },
        {
          "method": "sun.reflect.DelegatingMethodAccessorImpl.invoke",
          "source": "DelegatingMethodAcces sorImpl.java:25"
        },
        {
          "method": "java.lang.reflect.Method.invoke",
          "source": "Method.java:324"
        },
        {
          "method": "org.eclipse.core.launcher.Main.basicRun",
          "source": "Main.java:184"
        },
        {
          "method": "org.eclipse.core.launcher.Main.run",
          "source": "Main.java:637"
        },
        {
          "method": "org.eclipse.core.launcher.Main.main",
          "source": "Main.java:621"
        }
      ],
      "number": 0,
      "commentIndex": 0,
      "bugId": "62602",
      "date": "2004-05-18T10:21:54+02:00",
      "product": "Platform",
      "component": "SWT",
      "severity": "normal"
    }
  ],
  "groupId": "62602",
  "bugId": "62602",
  "date": "2004-05-18T10:21:54+02:00",
  "product": "Platform",
  "component": "SWT",
  "severity": "normal"
}