{
  "comments": [
    "I2004-04-17 + smoke test plugin export from 2004-04-18-11:15\n\n1) Setup like for a smoke test (i.e. import JUnit).\n2) Open a file with protected methods (I use TestCase.java as an example)\n3) hover over the method name of \n\nprotected void runTest() throws Throwable {\n\n4) observe: you get a hover\n5) make sure there is no selection in the editor, place the caret in the method\nname of the above method\n6) now hover over the \"protected\" keyword of the above method.\n7) observe: you get a NullPointerException:\n\n\njava.lang.NullPointerException\n        at java.lang.Throwable.\u003cinit\u003e(Throwable.java)\n        at org.eclipse.core.internal.preferences.EclipsePreferences.internalGet(\nEclipsePreferences.java)\n        at org.eclipse.core.internal.preferences.EclipsePreferences.get(EclipseP\nreferences.java)\n        at org.eclipse.core.internal.preferences.PreferenceForwarder.contains(Pr\neferenceForwarder.java)\n        at org.eclipse.ui.plugin.AbstractUIPlugin$CompatibilityPreferenceStore.c\nontains(AbstractUIPlugin.java)\n        at org.eclipse.ui.texteditor.ChainedPreferenceStore.getVisibleStore(Chai\nnedPreferenceStore.java)\n        at org.eclipse.ui.texteditor.ChainedPreferenceStore.getBoolean(ChainedPr\neferenceStore.java)\n        at org.eclipse.jdt.internal.ui.text.java.hover.AbstractAnnotationHover.g\netHoverInfo(AbstractAnnotationHover.java)\n        at org.eclipse.jdt.internal.ui.text.java.hover.BestMatchHover.getHoverIn\nfo(BestMatchHover.java)\n        at org.eclipse.jdt.internal.ui.text.java.hover.JavaEditorTextHoverProxy.\ngetHoverInfo(JavaEditorTextHoverProxy.java:69)\n        at org.eclipse.jface.text.TextViewerHoverManager$4.run(TextViewerHoverMa\nnager.java:161)",
    "\n\n*** This bug has been marked as a duplicate of 62612 ***"
  ],
  "commentCreationDates": [
    "2004-05-18T12:09:46+02:00",
    "2004-05-18T12:22:33+02:00"
  ],
  "traces": [
    {
      "exceptionType": "java.lang.NullPointerException",
      "elements": [
        {
          "method": "java.lang.Throwable.\u003cinit\u003e",
          "source": "Throwable.java"
        },
        {
          "method": "org.eclipse.core.internal.preferences.EclipsePreferences.internalGet",
          "source": " EclipsePreferences.java"
        },
        {
          "method": "org.eclipse.core.internal.preferences.EclipsePreferences.get",
          "source": "EclipseP references.java"
        },
        {
          "method": "org.eclipse.core.internal.preferences.PreferenceForwarder.contains",
          "source": "Pr eferenceForwarder.java"
        },
        {
          "method": "org.eclipse.ui.plugin.AbstractUIPlugin$CompatibilityPreferenceStore.contains",
          "source": "AbstractUIPlugin.java"
        },
        {
          "method": "org.eclipse.ui.texteditor.ChainedPreferenceStore.getVisibleStore",
          "source": "Chai nedPreferenceStore.java"
        },
        {
          "method": "org.eclipse.ui.texteditor.ChainedPreferenceStore.getBoolean",
          "source": "ChainedPr eferenceStore.java"
        },
        {
          "method": "org.eclipse.jdt.internal.ui.text.java.hover.AbstractAnnotationHover.getHoverInfo",
          "source": "AbstractAnnotationHover.java"
        },
        {
          "method": "org.eclipse.jdt.internal.ui.text.java.hover.BestMatchHover.getHoverInfo",
          "source": "BestMatchHover.java"
        },
        {
          "method": "org.eclipse.jdt.internal.ui.text.java.hover.JavaEditorTextHoverProxy.getHoverInfo",
          "source": "JavaEditorTextHoverProxy.java:69"
        },
        {
          "method": "org.eclipse.jface.text.TextViewerHoverManager$4.run",
          "source": "TextViewerHoverMa nager.java:161"
        }
      ],
      "number": 0,
      "commentIndex": 0,
      "bugId": "62615",
      "duplicateId": "62612",
      "date": "2004-05-18T12:09:46+02:00",
      "product": "JDT",
      "component": "Text",
      "severity": "normal"
    }
  ],
  "groupId": "62612",
  "bugId": "62615",
  "duplicateId": "62612",
  "date": "2004-05-18T12:09:46+02:00",
  "product": "JDT",
  "component": "Text",
  "severity": "normal"
}