{
  "comments": [
    "I200405180816.  Linux 2.6.4, GTK+ 2.4.0, KDE 3.2.1. \n \nWhen trying to run the UITestSuite with this morning\u0027s build, I get the \nfollowing exception in the log.  The process terminates with nothing appearing \nin the console view. \n \nI am not sure whether to consider this blocker or major.... \n \n \n!ENTRY org.eclipse.ui 4 4 May 18, 2004 12:08:23.722 \n!MESSAGE Unhandled event loop exception \n!ENTRY org.eclipse.ui 4 0 May 18, 2004 12:08:23.723 \n!MESSAGE Failed to execute runnable (java.lang.ClassCastException) \n!STACK 0 \norg.eclipse.swt.SWTException: Failed to execute runnable \n(java.lang.ClassCastException) \n        at org.eclipse.swt.SWT.error(SWT.java:2689) \n        at org.eclipse.swt.SWT.error(SWT.java:2614) \n        at \norg.eclipse.swt.widgets.Synchronizer.runAsyncMessages(Synchronizer.java:109) \n        at org.eclipse.swt.widgets.Display.runAsyncMessages(Display.java:2515) \n        at org.eclipse.swt.widgets.Display.readAndDispatch(Display.java:2252) \n        at org.eclipse.ui.internal.Workbench.runEventLoop(Workbench.java:1363) \n        at org.eclipse.ui.internal.Workbench.runUI(Workbench.java:1334) \n        at \norg.eclipse.ui.internal.Workbench.createAndRunWorkbench(Workbench.java:253) \n        at org.eclipse.ui.PlatformUI.createAndRunWorkbench(PlatformUI.java:141) \n        at \norg.eclipse.ui.internal.ide.IDEApplication.run(IDEApplication.java:97) \n        at \norg.eclipse.core.internal.runtime.PlatformActivator$1.run(PlatformActivator.java:299) \n        at \norg.eclipse.core.runtime.adaptor.EclipseStarter.run(EclipseStarter.java:256) \n        at \norg.eclipse.core.runtime.adaptor.EclipseStarter.run(EclipseStarter.java:127) \n        at sun.reflect.NativeMethodAccessorImpl.invoke0(Native Method) \n        at \nsun.reflect.NativeMethodAccessorImpl.invoke(NativeMethodAccessorImpl.java:39) \n        at \nsun.reflect.DelegatingMethodAccessorImpl.invoke(DelegatingMethodAccessorImpl.java:25) \n        at java.lang.reflect.Method.invoke(Method.java:324) \n        at org.eclipse.core.launcher.Main.basicRun(Main.java:184) \n        at org.eclipse.core.launcher.Main.run(Main.java:637) \n        at org.eclipse.core.launcher.Main.main(Main.java:621) \n!ENTRY org.eclipse.ui 4 4 May 18, 2004 12:08:23.725 \n!MESSAGE *** SWT nested exception \n!ENTRY org.eclipse.ui 4 0 May 18, 2004 12:08:23.726 \n!MESSAGE java.lang.ClassCastException \n!STACK 0 \njava.lang.ClassCastException \n        at \norg.eclipse.jdt.internal.junit.ui.JUnitPlugin.findTestRunnerViewPartInActivePage(JUnitPlugin.java:239) \n        at org.eclipse.jdt.internal.junit.ui.JUnitPlugin.access$0\n(JUnitPlugin.java:235) \n        at \norg.eclipse.jdt.internal.junit.ui.JUnitPlugin$1.run(JUnitPlugin.java:191) \n        at org.eclipse.swt.widgets.RunnableLock.run(RunnableLock.java:35) \n        at \norg.eclipse.swt.widgets.Synchronizer.runAsyncMessages(Synchronizer.java:106) \n        at org.eclipse.swt.widgets.Display.runAsyncMessages(Display.java:2515) \n        at org.eclipse.swt.widgets.Display.readAndDispatch(Display.java:2252) \n        at org.eclipse.ui.internal.Workbench.runEventLoop(Workbench.java:1363) \n        at org.eclipse.ui.internal.Workbench.runUI(Workbench.java:1334) \n        at \norg.eclipse.ui.internal.Workbench.createAndRunWorkbench(Workbench.java:253) \n        at org.eclipse.ui.PlatformUI.createAndRunWorkbench(PlatformUI.java:141) \n        at \norg.eclipse.ui.internal.ide.IDEApplication.run(IDEApplication.java:97) \n        at \norg.eclipse.core.internal.runtime.PlatformActivator$1.run(PlatformActivator.java:299) \n        at \norg.eclipse.core.runtime.adaptor.EclipseStarter.run(EclipseStarter.java:256) \n        at \norg.eclipse.core.runtime.adaptor.EclipseStarter.run(EclipseStarter.java:127) \n        at sun.reflect.NativeMethodAccessorImpl.invoke0(Native Method) \n        at \nsun.reflect.NativeMethodAccessorImpl.invoke(NativeMethodAccessorImpl.java:39) \n        at \nsun.reflect.DelegatingMethodAccessorImpl.invoke(DelegatingMethodAccessorImpl.java:25) \n        at java.lang.reflect.Method.invoke(Method.java:324) \n        at org.eclipse.core.launcher.Main.basicRun(Main.java:184) \n        at org.eclipse.core.launcher.Main.run(Main.java:637) \n        at org.eclipse.core.launcher.Main.main(Main.java:621)",
    "Doug can you reproduce this bug or does it always happen? I can successfully \nrun plug-in tests in 200405181200.\n\nIf the stacktrace is correct then this would indicate that \nIWorkbenchPage.findView returns an incorrect view:\n\u003e (TestRunnerViewPart) page.findView(TestRunnerViewPart.NAME)\n\n\n",
    "I can\u0027t reproduce this bug using the same workspace with I200405190010.  Okay \nto close as WORKSFORME, unless there is an obvious place where this could be \ngoing wrong.... ",
    "closing - noone else has reported this problem"
  ],
  "commentCreationDates": [
    "2004-05-18T18:31:03+02:00",
    "2004-05-19T10:51:32+02:00",
    "2004-05-19T19:33:47+02:00",
    "2004-05-19T21:51:43+02:00"
  ],
  "traces": [
    {
      "exceptionType": "org.eclipse.swt.SWTException",
      "message": "Failed to execute runnable  (java.lang.ClassCastException)",
      "elements": [
        {
          "method": "org.eclipse.swt.SWT.error",
          "source": "SWT.java:2689"
        },
        {
          "method": "org.eclipse.swt.SWT.error",
          "source": "SWT.java:2614"
        },
        {
          "method": "org.eclipse.swt.widgets.Synchronizer.runAsyncMessages",
          "source": "Synchronizer.java:109"
        },
        {
          "method": "org.eclipse.swt.widgets.Display.runAsyncMessages",
          "source": "Display.java:2515"
        },
        {
          "method": "org.eclipse.swt.widgets.Display.readAndDispatch",
          "source": "Display.java:2252"
        },
        {
          "method": "org.eclipse.ui.internal.Workbench.runEventLoop",
          "source": "Workbench.java:1363"
        },
        {
          "method": "org.eclipse.ui.internal.Workbench.runUI",
          "source": "Workbench.java:1334"
        },
        {
          "method": "org.eclipse.ui.internal.Workbench.createAndRunWorkbench",
          "source": "Workbench.java:253"
        },
        {
          "method": "org.eclipse.ui.PlatformUI.createAndRunWorkbench",
          "source": "PlatformUI.java:141"
        },
        {
          "method": "org.eclipse.ui.internal.ide.IDEApplication.run",
          "source": "IDEApplication.java:97"
        },
        {
          "method": "org.eclipse.core.internal.runtime.PlatformActivator$1.run",
          "source": "PlatformActivator.java:299"
        },
        {
          "method": "org.eclipse.core.runtime.adaptor.EclipseStarter.run",
          "source": "EclipseStarter.java:256"
        },
        {
          "method": "org.eclipse.core.runtime.adaptor.EclipseStarter.run",
          "source": "EclipseStarter.java:127"
        },
        {
          "method": "sun.reflect.NativeMethodAccessorImpl.invoke0",
          "source": "Native Method"
        },
        {
          "method": "sun.reflect.NativeMethodAccessorImpl.invoke",
          "source": "NativeMethodAccessorImpl.java:39"
        },
        {
          "method": "sun.reflect.DelegatingMethodAccessorImpl.invoke",
          "source": "DelegatingMethodAccessorImpl.java:25"
        },
        {
          "method": "java.lang.reflect.Method.invoke",
          "source": "Method.java:324"
        },
        {
          "method": "org.eclipse.core.launcher.Main.basicRun",
          "source": "Main.java:184"
        },
        {
          "method": "org.eclipse.core.launcher.Main.run",
          "source": "Main.java:637"
        },
        {
          "method": "org.eclipse.core.launcher.Main.main",
          "source": "Main.java:621"
        }
      ],
      "number": 0,
      "commentIndex": 0,
      "bugId": "62694",
      "date": "2004-05-18T18:31:03+02:00",
      "product": "JDT",
      "component": "UI",
      "severity": "blocker"
    },
    {
      "exceptionType": "java.lang.ClassCastException",
      "elements": [
        {
          "method": "org.eclipse.jdt.internal.junit.ui.JUnitPlugin.findTestRunnerViewPartInActivePage",
          "source": "JUnitPlugin.java:239"
        },
        {
          "method": "org.eclipse.jdt.internal.junit.ui.JUnitPlugin.access$0",
          "source": "JUnitPlugin.java:235"
        },
        {
          "method": "org.eclipse.jdt.internal.junit.ui.JUnitPlugin$1.run",
          "source": "JUnitPlugin.java:191"
        },
        {
          "method": "org.eclipse.swt.widgets.RunnableLock.run",
          "source": "RunnableLock.java:35"
        },
        {
          "method": "org.eclipse.swt.widgets.Synchronizer.runAsyncMessages",
          "source": "Synchronizer.java:106"
        },
        {
          "method": "org.eclipse.swt.widgets.Display.runAsyncMessages",
          "source": "Display.java:2515"
        },
        {
          "method": "org.eclipse.swt.widgets.Display.readAndDispatch",
          "source": "Display.java:2252"
        },
        {
          "method": "org.eclipse.ui.internal.Workbench.runEventLoop",
          "source": "Workbench.java:1363"
        },
        {
          "method": "org.eclipse.ui.internal.Workbench.runUI",
          "source": "Workbench.java:1334"
        },
        {
          "method": "org.eclipse.ui.internal.Workbench.createAndRunWorkbench",
          "source": "Workbench.java:253"
        },
        {
          "method": "org.eclipse.ui.PlatformUI.createAndRunWorkbench",
          "source": "PlatformUI.java:141"
        },
        {
          "method": "org.eclipse.ui.internal.ide.IDEApplication.run",
          "source": "IDEApplication.java:97"
        },
        {
          "method": "org.eclipse.core.internal.runtime.PlatformActivator$1.run",
          "source": "PlatformActivator.java:299"
        },
        {
          "method": "org.eclipse.core.runtime.adaptor.EclipseStarter.run",
          "source": "EclipseStarter.java:256"
        },
        {
          "method": "org.eclipse.core.runtime.adaptor.EclipseStarter.run",
          "source": "EclipseStarter.java:127"
        },
        {
          "method": "sun.reflect.NativeMethodAccessorImpl.invoke0",
          "source": "Native Method"
        },
        {
          "method": "sun.reflect.NativeMethodAccessorImpl.invoke",
          "source": "NativeMethodAccessorImpl.java:39"
        },
        {
          "method": "sun.reflect.DelegatingMethodAccessorImpl.invoke",
          "source": "DelegatingMethodAccessorImpl.java:25"
        },
        {
          "method": "java.lang.reflect.Method.invoke",
          "source": "Method.java:324"
        },
        {
          "method": "org.eclipse.core.launcher.Main.basicRun",
          "source": "Main.java:184"
        },
        {
          "method": "org.eclipse.core.launcher.Main.run",
          "source": "Main.java:637"
        },
        {
          "method": "org.eclipse.core.launcher.Main.main",
          "source": "Main.java:621"
        }
      ],
      "number": 1,
      "commentIndex": 0,
      "bugId": "62694",
      "date": "2004-05-18T18:31:03+02:00",
      "product": "JDT",
      "component": "UI",
      "severity": "blocker"
    }
  ],
  "groupId": "62694",
  "bugId": "62694",
  "date": "2004-05-18T18:31:03+02:00",
  "product": "JDT",
  "component": "UI",
  "severity": "blocker"
}