{
  "comments": [
    "I20040518-gtk M9 test pass\n\nReproducable steps:\n1. open eclipse on a fresh workspace\n2. on the intro page, choose \"what\u0027s new\"\n3. on the next page, choose \"go to workbench\"\n\n-\u003e got this in the log:\n\norg.eclipse.swt.SWTException: Widget is disposed\n        at java.lang.Throwable.\u003cinit\u003e(Throwable.java)\n        at java.lang.Throwable.\u003cinit\u003e(Throwable.java:73)\n        at org.eclipse.swt.SWTException.\u003cinit\u003e(SWTException.java:73)\n        at org.eclipse.swt.SWT.error(SWT.java:2689)\n        at org.eclipse.swt.SWT.error(SWT.java:2614)\n        at org.eclipse.swt.SWT.error(SWT.java:2585)\n        at org.eclipse.swt.widgets.Widget.error(Widget.java:374)\n        at org.eclipse.swt.widgets.Widget.checkWidget(Widget.java)\n        at org.eclipse.swt.widgets.Control.setRedraw(Control.java:2663)\n        at\norg.eclipse.ui.internal.intro.impl.model.IntroURL$1.run(IntroURL.java:104)\n        at org.eclipse.swt.custom.BusyIndicator.showWhile(BusyIndicator.java:69)\n        at\norg.eclipse.ui.internal.intro.impl.model.IntroURL.execute(IntroURL.java:92)\n        at\norg.eclipse.ui.internal.intro.impl.swt.PageForm$1.linkActivated(PageForm.java:51)\n        at\norg.eclipse.ui.forms.widgets.AbstractHyperlink.handleActivate(AbstractHyperlink.java:183)\n        at\norg.eclipse.ui.forms.widgets.ImageHyperlink.handleActivate(ImageHyperlink.java:137)\n        at\norg.eclipse.ui.forms.widgets.AbstractHyperlink.handleMouseUp(AbstractHyperlink.java:264)\n        at\norg.eclipse.ui.forms.widgets.AbstractHyperlink.access$1(AbstractHyperlink.java:248)\n        at\norg.eclipse.ui.forms.widgets.AbstractHyperlink$4.handleEvent(AbstractHyperlink.java:95)\n        at org.eclipse.swt.widgets.EventTable.sendEvent(EventTable.java)\n        at org.eclipse.swt.widgets.Widget.sendEvent(Widget.java:944)\n        at org.eclipse.swt.widgets.Display.runDeferredEvents(Display.java)\n        at org.eclipse.swt.widgets.Display.readAndDispatch(Display.java)\n        at org.eclipse.ui.internal.Workbench.runEventLoop(Workbench.java:1363)\n        at org.eclipse.ui.internal.Workbench.runUI(Workbench.java:1334)\n        at\norg.eclipse.ui.internal.Workbench.createAndRunWorkbench(Workbench.java:253)\n        at org.eclipse.ui.PlatformUI.createAndRunWorkbench(PlatformUI.java:141)\n        at org.eclipse.ui.internal.ide.IDEApplication.run(IDEApplication.java:97)\n        at\norg.eclipse.core.internal.runtime.PlatformActivator$1.run(PlatformActivator.java:299)\n        at\norg.eclipse.core.runtime.adaptor.EclipseStarter.run(EclipseStarter.java:256)\n        at\norg.eclipse.core.runtime.adaptor.EclipseStarter.run(EclipseStarter.java:127)\n        at sun.reflect.NativeMethodAccessorImpl.invoke0(Native Method)\n        at\nsun.reflect.NativeMethodAccessorImpl.invoke(NativeMethodAccessorImpl.java:79)\n        at\nsun.reflect.DelegatingMethodAccessorImpl.invoke(DelegatingMethodAccessorImpl.java:41)\n        at java.lang.reflect.Method.invoke(Method.java:386)\n        at org.eclipse.core.launcher.Main.basicRun(Main.java:184)\n        at org.eclipse.core.launcher.Main.run(Main.java:637)\n        at org.eclipse.core.launcher.Main.main(Main.java:621)\nWidget is disposed",
    "perhaps this is related to bug 62904",
    "this has been fixed for a while.\nPlease try it in later versions, and reopen if need be. \n\n\n\n*** This bug has been marked as a duplicate of 62904 ***"
  ],
  "commentCreationDates": [
    "2004-05-18T18:58:51+02:00",
    "2004-05-21T12:36:03+02:00",
    "2004-06-13T23:07:37+02:00"
  ],
  "traces": [
    {
      "exceptionType": "org.eclipse.swt.SWTException",
      "message": "Widget is disposed",
      "elements": [
        {
          "method": "java.lang.Throwable.\u003cinit\u003e",
          "source": "Throwable.java"
        },
        {
          "method": "java.lang.Throwable.\u003cinit\u003e",
          "source": "Throwable.java:73"
        },
        {
          "method": "org.eclipse.swt.SWTException.\u003cinit\u003e",
          "source": "SWTException.java:73"
        },
        {
          "method": "org.eclipse.swt.SWT.error",
          "source": "SWT.java:2689"
        },
        {
          "method": "org.eclipse.swt.SWT.error",
          "source": "SWT.java:2614"
        },
        {
          "method": "org.eclipse.swt.SWT.error",
          "source": "SWT.java:2585"
        },
        {
          "method": "org.eclipse.swt.widgets.Widget.error",
          "source": "Widget.java:374"
        },
        {
          "method": "org.eclipse.swt.widgets.Widget.checkWidget",
          "source": "Widget.java"
        },
        {
          "method": "org.eclipse.swt.widgets.Control.setRedraw",
          "source": "Control.java:2663"
        },
        {
          "method": "org.eclipse.ui.internal.intro.impl.model.IntroURL$1.run",
          "source": "IntroURL.java:104"
        },
        {
          "method": "org.eclipse.swt.custom.BusyIndicator.showWhile",
          "source": "BusyIndicator.java:69"
        },
        {
          "method": "org.eclipse.ui.internal.intro.impl.model.IntroURL.execute",
          "source": "IntroURL.java:92"
        },
        {
          "method": "org.eclipse.ui.internal.intro.impl.swt.PageForm$1.linkActivated",
          "source": "PageForm.java:51"
        },
        {
          "method": "org.eclipse.ui.forms.widgets.AbstractHyperlink.handleActivate",
          "source": "AbstractHyperlink.java:183"
        },
        {
          "method": "org.eclipse.ui.forms.widgets.ImageHyperlink.handleActivate",
          "source": "ImageHyperlink.java:137"
        },
        {
          "method": "org.eclipse.ui.forms.widgets.AbstractHyperlink.handleMouseUp",
          "source": "AbstractHyperlink.java:264"
        },
        {
          "method": "org.eclipse.ui.forms.widgets.AbstractHyperlink.access$1",
          "source": "AbstractHyperlink.java:248"
        },
        {
          "method": "org.eclipse.ui.forms.widgets.AbstractHyperlink$4.handleEvent",
          "source": "AbstractHyperlink.java:95"
        },
        {
          "method": "org.eclipse.swt.widgets.EventTable.sendEvent",
          "source": "EventTable.java"
        },
        {
          "method": "org.eclipse.swt.widgets.Widget.sendEvent",
          "source": "Widget.java:944"
        },
        {
          "method": "org.eclipse.swt.widgets.Display.runDeferredEvents",
          "source": "Display.java"
        },
        {
          "method": "org.eclipse.swt.widgets.Display.readAndDispatch",
          "source": "Display.java"
        },
        {
          "method": "org.eclipse.ui.internal.Workbench.runEventLoop",
          "source": "Workbench.java:1363"
        },
        {
          "method": "org.eclipse.ui.internal.Workbench.runUI",
          "source": "Workbench.java:1334"
        },
        {
          "method": "org.eclipse.ui.internal.Workbench.createAndRunWorkbench",
          "source": "Workbench.java:253"
        },
        {
          "method": "org.eclipse.ui.PlatformUI.createAndRunWorkbench",
          "source": "PlatformUI.java:141"
        },
        {
          "method": "org.eclipse.ui.internal.ide.IDEApplication.run",
          "source": "IDEApplication.java:97"
        },
        {
          "method": "org.eclipse.core.internal.runtime.PlatformActivator$1.run",
          "source": "PlatformActivator.java:299"
        },
        {
          "method": "org.eclipse.core.runtime.adaptor.EclipseStarter.run",
          "source": "EclipseStarter.java:256"
        },
        {
          "method": "org.eclipse.core.runtime.adaptor.EclipseStarter.run",
          "source": "EclipseStarter.java:127"
        },
        {
          "method": "sun.reflect.NativeMethodAccessorImpl.invoke0",
          "source": "Native Method"
        },
        {
          "method": "sun.reflect.NativeMethodAccessorImpl.invoke",
          "source": "NativeMethodAccessorImpl.java:79"
        },
        {
          "method": "sun.reflect.DelegatingMethodAccessorImpl.invoke",
          "source": "DelegatingMethodAccessorImpl.java:41"
        },
        {
          "method": "java.lang.reflect.Method.invoke",
          "source": "Method.java:386"
        },
        {
          "method": "org.eclipse.core.launcher.Main.basicRun",
          "source": "Main.java:184"
        },
        {
          "method": "org.eclipse.core.launcher.Main.run",
          "source": "Main.java:637"
        },
        {
          "method": "org.eclipse.core.launcher.Main.main",
          "source": "Main.java:621"
        }
      ],
      "number": 0,
      "commentIndex": 0,
      "bugId": "62705",
      "duplicateId": "62904",
      "date": "2004-05-18T18:58:51+02:00",
      "product": "Platform",
      "component": "User Assistance",
      "severity": "normal"
    }
  ],
  "groupId": "62904",
  "bugId": "62705",
  "duplicateId": "62904",
  "date": "2004-05-18T18:58:51+02:00",
  "product": "Platform",
  "component": "User Assistance",
  "severity": "normal"
}