{
  "comments": [
    "Build 20011120 + Jdtcore from HEAD (v_213)\n\nUnclear where the mouse cursor was located, but the hover-help did try to\nperform and failed for the reason below inside the test class (JavaSearchTests).\n\n1 org.eclipse.core.resources 4 Unhandled exception caught in event loop.\nUnhandled exception caught in event loop.\nReason:\nLog: Mon Nov 26 13:57:53 CET 2001\n4 org.eclipse.ui 0 Assertion failed; .\norg.eclipse.jdt.internal.core.Assert$AssertionFailedException: Assertion failed;\n .\n        at org.eclipse.jdt.internal.core.Assert.isTrue(Assert.java:82)\n        at org.eclipse.jdt.internal.core.Assert.isTrue(Assert.java:69)\n        at org.eclipse.jdt.internal.core.SourceType.\u003cinit\u003e(SourceType.java:34)\n        at org.eclipse.jdt.internal.core.CompilationUnit.getType(CompilationUnit\n.java:396)\n        at org.eclipse.jdt.internal.core.SelectionRequestor.resolveType(Selectio\nnRequestor.java:220)\n        at org.eclipse.jdt.internal.core.SelectionRequestor.acceptMethod(Selecti\nonRequestor.java:107)\n        at org.eclipse.jdt.internal.codeassist.SelectionEngine.selectFrom(Select\nionEngine.java:353)\n        at org.eclipse.jdt.internal.codeassist.SelectionEngine.select(SelectionE\nngine.java:306)\n        at org.eclipse.jdt.internal.core.Openable.codeSelect(Openable.java:147)\n        at org.eclipse.jdt.internal.core.Openable.codeSelect(Openable.java:120)\n        at org.eclipse.jdt.internal.core.CompilationUnit.codeSelect(CompilationU\nnit.java:69)\n        at org.eclipse.jdt.internal.ui.text.java.hover.JavaTypeHover.getHoverInf\no(JavaTypeHover.java:76)\n        at org.eclipse.jdt.internal.ui.text.java.hover.JavaTextHover.getInformat\nion(JavaTextHover.java:176)\n        at org.eclipse.jdt.internal.ui.text.java.hover.JavaTextHover.getHoverInf\no(JavaTextHover.java:153)\n        at org.eclipse.jface.text.TextViewerHoverManager.computeInformation(Text\nViewerHoverManager.java:56)\n        at org.eclipse.jface.text.AbstractInformationControlManager.showInformat\nion(AbstractInformationControlManager.java:523)\n        at org.eclipse.jface.text.AbstractHoverInformationControlManager$MouseTr\nacker.mouseHover(AbstractHoverInformationControlManager.java:201)\n        at org.eclipse.swt.widgets.TypedListener.handleEvent(TypedListener.java:\n207)\n        at org.eclipse.swt.widgets.EventTable.sendEvent(EventTable.java:54)\n        at org.eclipse.swt.widgets.Widget.notifyListeners(Widget.java:635)\n        at org.eclipse.swt.widgets.Display.runDeferredEvents(Display.java:1365)\n        at org.eclipse.swt.widgets.Display.readAndDispatch(Display.java:1167)\n        at org.eclipse.ui.internal.Workbench.runEventLoop(Workbench.java:729)\n        at org.eclipse.ui.internal.Workbench.run(Workbench.java:712)\n        at org.eclipse.core.internal.boot.InternalBootLoader.run(InternalBootLoa\nder.java:820)\n        at org.eclipse.core.boot.BootLoader.run(BootLoader.java:285)\n        at java.lang.reflect.Method.invoke(Native Method)\n        at org.eclipse.core.launcher.Main.basicRun(Main.java:151)\n        at org.eclipse.core.launcher.Main.run(Main.java:502)\n        at org.eclipse.core.launcher.UIMain.main(UIMain.java:52)\nAssertion failed; .",
    "The failure occurs any time hovering over a declaration (field/method) inside a \nworking copy.",
    "parameter of getType must be a simple name\n\nFixed",
    "*** Bug 6339 has been marked as a duplicate of this bug. ***"
  ],
  "commentCreationDates": [
    "2001-11-26T13:00:37+01:00",
    "2001-11-26T13:51:23+01:00",
    "2001-11-26T15:22:05+01:00",
    "2001-11-27T12:27:34+01:00"
  ],
  "traces": [
    {
      "exceptionType": "org.eclipse.jdt.internal.core.Assert$AssertionFailedException",
      "message": "Assertion failed;  .",
      "elements": [
        {
          "method": "org.eclipse.jdt.internal.core.Assert.isTrue",
          "source": "Assert.java:82"
        },
        {
          "method": "org.eclipse.jdt.internal.core.Assert.isTrue",
          "source": "Assert.java:69"
        },
        {
          "method": "org.eclipse.jdt.internal.core.SourceType.\u003cinit\u003e",
          "source": "SourceType.java:34"
        },
        {
          "method": "org.eclipse.jdt.internal.core.CompilationUnit.getType",
          "source": "CompilationUnit .java:396"
        },
        {
          "method": "org.eclipse.jdt.internal.core.SelectionRequestor.resolveType",
          "source": "Selectio nRequestor.java:220"
        },
        {
          "method": "org.eclipse.jdt.internal.core.SelectionRequestor.acceptMethod",
          "source": "Selecti onRequestor.java:107"
        },
        {
          "method": "org.eclipse.jdt.internal.codeassist.SelectionEngine.selectFrom",
          "source": "Select ionEngine.java:353"
        },
        {
          "method": "org.eclipse.jdt.internal.codeassist.SelectionEngine.select",
          "source": "SelectionE ngine.java:306"
        },
        {
          "method": "org.eclipse.jdt.internal.core.Openable.codeSelect",
          "source": "Openable.java:147"
        },
        {
          "method": "org.eclipse.jdt.internal.core.Openable.codeSelect",
          "source": "Openable.java:120"
        },
        {
          "method": "org.eclipse.jdt.internal.core.CompilationUnit.codeSelect",
          "source": "CompilationU nit.java:69"
        },
        {
          "method": "org.eclipse.jdt.internal.ui.text.java.hover.JavaTypeHover.getHoverInfo",
          "source": "JavaTypeHover.java:76"
        },
        {
          "method": "org.eclipse.jdt.internal.ui.text.java.hover.JavaTextHover.getInformation",
          "source": "JavaTextHover.java:176"
        },
        {
          "method": "org.eclipse.jdt.internal.ui.text.java.hover.JavaTextHover.getHoverInfo",
          "source": "JavaTextHover.java:153"
        },
        {
          "method": "org.eclipse.jface.text.TextViewerHoverManager.computeInformation",
          "source": "Text ViewerHoverManager.java:56"
        },
        {
          "method": "org.eclipse.jface.text.AbstractInformationControlManager.showInformation",
          "source": "AbstractInformationControlManager.java:523"
        },
        {
          "method": "org.eclipse.jface.text.AbstractHoverInformationControlManager$MouseTracker.mouseHover",
          "source": "AbstractHoverInformationControlManager.java:201"
        },
        {
          "method": "org.eclipse.swt.widgets.TypedListener.handleEvent",
          "source": "TypedListener.java: 207"
        },
        {
          "method": "org.eclipse.swt.widgets.EventTable.sendEvent",
          "source": "EventTable.java:54"
        },
        {
          "method": "org.eclipse.swt.widgets.Widget.notifyListeners",
          "source": "Widget.java:635"
        },
        {
          "method": "org.eclipse.swt.widgets.Display.runDeferredEvents",
          "source": "Display.java:1365"
        },
        {
          "method": "org.eclipse.swt.widgets.Display.readAndDispatch",
          "source": "Display.java:1167"
        },
        {
          "method": "org.eclipse.ui.internal.Workbench.runEventLoop",
          "source": "Workbench.java:729"
        },
        {
          "method": "org.eclipse.ui.internal.Workbench.run",
          "source": "Workbench.java:712"
        },
        {
          "method": "org.eclipse.core.internal.boot.InternalBootLoader.run",
          "source": "InternalBootLoa der.java:820"
        },
        {
          "method": "org.eclipse.core.boot.BootLoader.run",
          "source": "BootLoader.java:285"
        },
        {
          "method": "java.lang.reflect.Method.invoke",
          "source": "Native Method"
        },
        {
          "method": "org.eclipse.core.launcher.Main.basicRun",
          "source": "Main.java:151"
        },
        {
          "method": "org.eclipse.core.launcher.Main.run",
          "source": "Main.java:502"
        },
        {
          "method": "org.eclipse.core.launcher.UIMain.main",
          "source": "UIMain.java:52"
        }
      ],
      "number": 0,
      "commentIndex": 0,
      "bugId": "6302",
      "date": "2001-11-26T13:00:37+01:00",
      "product": "JDT",
      "component": "Core",
      "severity": "normal"
    }
  ],
  "groupId": "6302",
  "bugId": "6302",
  "date": "2001-11-26T13:00:37+01:00",
  "product": "JDT",
  "component": "Core",
  "severity": "normal"
}