{
  "comments": [
    "Eclipse build 200405190010\n\nI used an old workspace.\n\n!STACK 0\njava.lang.NoSuchMethodError:\norg.eclipse.jdt.internal.ui.wizards.dialogfields.ListDialogField.setElements(Ljava/util/List;)V\n        at\ncom.sysdeo.eclipse.tomcat.editors.ProjectListEditor.updateProjectsList(ProjectListEditor.java:65)\n        at\ncom.sysdeo.eclipse.tomcat.editors.ProjectListEditor.\u003cinit\u003e(ProjectListEditor.java:39)\n        at\ncom.sysdeo.eclipse.tomcat.TomcatPreferencePage.createContents(TomcatPreferencePage.java:123)\n        at\norg.eclipse.jface.preference.PreferencePage.createControl(PreferencePage.java:217)\n        at\norg.eclipse.jface.preference.PreferenceDialog$12.run(PreferenceDialog.java:1006)\n        at\norg.eclipse.core.internal.runtime.InternalPlatform.run(InternalPlatform.java:608)\n        at org.eclipse.core.runtime.Platform.run(Platform.java:758)\n        at\norg.eclipse.jface.preference.PreferenceDialog.showPage(PreferenceDialog.java:1001)\n        at\norg.eclipse.jface.preference.PreferenceDialog$8.selectionChanged(PreferenceDialog.java:528)\n        at\norg.eclipse.jface.viewers.StructuredViewer$3.run(StructuredViewer.java:452)\n        at\norg.eclipse.core.internal.runtime.InternalPlatform.run(InternalPlatform.java:608)\n        at org.eclipse.core.runtime.Platform.run(Platform.java:758)\n        at\norg.eclipse.jface.viewers.StructuredViewer.firePostSelectionChanged(StructuredViewer.java:450)\n        at\norg.eclipse.jface.viewers.StructuredViewer.handlePostSelect(StructuredViewer.java:710)\n        at\norg.eclipse.jface.viewers.StructuredViewer$5.widgetSelected(StructuredViewer.java:728)\n        at\norg.eclipse.jface.util.OpenStrategy.firePostSelectionEvent(OpenStrategy.java:200)\n        at org.eclipse.jface.util.OpenStrategy.access$4(OpenStrategy.java:195)\n        at org.eclipse.jface.util.OpenStrategy$3.run(OpenStrategy.java:349)\n        at org.eclipse.swt.widgets.RunnableLock.run(RunnableLock.java:35)\n        at\norg.eclipse.swt.widgets.Synchronizer.runAsyncMessages(Synchronizer.java:106)\n        at org.eclipse.swt.widgets.Display.runAsyncMessages(Display.java:2515)\n        at org.eclipse.swt.widgets.Display.readAndDispatch(Display.java:2252)\n        at org.eclipse.jface.window.Window.runEventLoop(Window.java:668)\n        at org.eclipse.jface.window.Window.open(Window.java:648)\n        at\norg.eclipse.ui.internal.OpenPreferencesAction.run(OpenPreferencesAction.java:72)\n        at org.eclipse.jface.action.Action.runWithEvent(Action.java:881)\n        at\norg.eclipse.jface.action.ActionContributionItem.handleWidgetSelection(ActionContributionItem.java:899)\n        at\norg.eclipse.jface.action.ActionContributionItem.access$2(ActionContributionItem.java:850)\n        at\norg.eclipse.jface.action.ActionContributionItem$7.handleEvent(ActionContributionItem.java:769)\n        at org.eclipse.swt.widgets.EventTable.sendEvent(EventTable.java:82)\n        at org.eclipse.swt.widgets.Widget.sendEvent(Widget.java:944)\n        at org.eclipse.swt.widgets.Display.runDeferredEvents(Display.java:2538)\n        at org.eclipse.swt.widgets.Display.readAndDispatch(Display.java:2249)\n        at org.eclipse.ui.internal.Workbench.runEventLoop(Workbench.java:1363)\n        at org.eclipse.ui.internal.Workbench.runUI(Workbench.java:1334)\n        at\norg.eclipse.ui.internal.Workbench.createAndRunWorkbench(Workbench.java:253)\n        at org.eclipse.ui.PlatformUI.createAndRunWorkbench(PlatformUI.java:141)\n        at org.eclipse.ui.internal.ide.IDEApplication.run(IDEApplication.java:97)\n        at\norg.eclipse.core.internal.runtime.PlatformActivator$1.run(PlatformActivator.java:305)\n        at\norg.eclipse.core.runtime.adaptor.EclipseStarter.run(EclipseStarter.java:256)\n        at\norg.eclipse.core.runtime.adaptor.EclipseStarter.run(EclipseStarter.java:127)\n        at sun.reflect.NativeMethodAccessorImpl.invoke0(Native Method)\n        at\nsun.reflect.NativeMethodAccessorImpl.invoke(NativeMethodAccessorImpl.java:39)\n        at\nsun.reflect.DelegatingMethodAccessorImpl.invoke(DelegatingMethodAccessorImpl.java:25)\n        at java.lang.reflect.Method.invoke(Method.java:324)\n        at org.eclipse.core.launcher.Main.basicRun(Main.java:184)\n        at org.eclipse.core.launcher.Main.run(Main.java:637)\n        at org.eclipse.core.launcher.Main.main(Main.java:621)\n!ENTRY org.eclipse.core.runtime 4 2 Mai 20, 2004 14:17:51.473\n!MESSAGE Problems occurred when invoking code from plug-in:\n\"org.eclipse.core.runtime\".\n!STACK 0\njava.lang.NoSuchMethodError:\norg.eclipse.jdt.internal.ui.wizards.dialogfields.ListDialogField.setElements(Ljava/util/List;)V\n        at\ncom.sysdeo.eclipse.tomcat.editors.ProjectListEditor.updateProjectsList(ProjectListEditor.java:65)\n        at\ncom.sysdeo.eclipse.tomcat.editors.ProjectListEditor.\u003cinit\u003e(ProjectListEditor.java:39)\n        at\ncom.sysdeo.eclipse.tomcat.TomcatSourcePathPreferencePage.createContents(TomcatSourcePathPreferencePage.java:36)\n        at\norg.eclipse.jface.preference.PreferencePage.createControl(PreferencePage.java:217)\n        at\norg.eclipse.jface.preference.PreferenceDialog$12.run(PreferenceDialog.java:1006)\n        at\norg.eclipse.core.internal.runtime.InternalPlatform.run(InternalPlatform.java:608)\n        at org.eclipse.core.runtime.Platform.run(Platform.java:758)\n        at\norg.eclipse.jface.preference.PreferenceDialog.showPage(PreferenceDialog.java:1001)\n        at\norg.eclipse.jface.preference.PreferenceDialog$8.selectionChanged(PreferenceDialog.java:528)\n        at\norg.eclipse.jface.viewers.StructuredViewer$3.run(StructuredViewer.java:452)\n        at\norg.eclipse.core.internal.runtime.InternalPlatform.run(InternalPlatform.java:608)\n        at org.eclipse.core.runtime.Platform.run(Platform.java:758)\n        at\norg.eclipse.jface.viewers.StructuredViewer.firePostSelectionChanged(StructuredViewer.java:450)\n        at\norg.eclipse.jface.viewers.StructuredViewer.handlePostSelect(StructuredViewer.java:710)\n        at\norg.eclipse.jface.viewers.StructuredViewer$5.widgetSelected(StructuredViewer.java:728)\n        at\norg.eclipse.jface.util.OpenStrategy.firePostSelectionEvent(OpenStrategy.java:200)\n        at org.eclipse.jface.util.OpenStrategy.access$4(OpenStrategy.java:195)\n        at org.eclipse.jface.util.OpenStrategy$3.run(OpenStrategy.java:349)\n        at org.eclipse.swt.widgets.RunnableLock.run(RunnableLock.java:35)\n        at\norg.eclipse.swt.widgets.Synchronizer.runAsyncMessages(Synchronizer.java:106)\n        at org.eclipse.swt.widgets.Display.runAsyncMessages(Display.java:2515)\n        at org.eclipse.swt.widgets.Display.readAndDispatch(Display.java:2252)\n        at org.eclipse.jface.window.Window.runEventLoop(Window.java:668)\n        at org.eclipse.jface.window.Window.open(Window.java:648)\n        at\norg.eclipse.ui.internal.OpenPreferencesAction.run(OpenPreferencesAction.java:72)\n        at org.eclipse.jface.action.Action.runWithEvent(Action.java:881)\n        at\norg.eclipse.jface.action.ActionContributionItem.handleWidgetSelection(ActionContributionItem.java:899)\n        at\norg.eclipse.jface.action.ActionContributionItem.access$2(ActionContributionItem.java:850)\n        at\norg.eclipse.jface.action.ActionContributionItem$7.handleEvent(ActionContributionItem.java:769)\n        at org.eclipse.swt.widgets.EventTable.sendEvent(EventTable.java:82)\n        at org.eclipse.swt.widgets.Widget.sendEvent(Widget.java:944)\n        at org.eclipse.swt.widgets.Display.runDeferredEvents(Display.java:2538)\n        at org.eclipse.swt.widgets.Display.readAndDispatch(Display.java:2249)\n        at org.eclipse.ui.internal.Workbench.runEventLoop(Workbench.java:1363)\n        at org.eclipse.ui.internal.Workbench.runUI(Workbench.java:1334)\n        at\norg.eclipse.ui.internal.Workbench.createAndRunWorkbench(Workbench.java:253)\n        at org.eclipse.ui.PlatformUI.createAndRunWorkbench(PlatformUI.java:141)\n        at org.eclipse.ui.internal.ide.IDEApplication.run(IDEApplication.java:97)\n        at\norg.eclipse.core.internal.runtime.PlatformActivator$1.run(PlatformActivator.java:305)\n        at\norg.eclipse.core.runtime.adaptor.EclipseStarter.run(EclipseStarter.java:256)\n        at\norg.eclipse.core.runtime.adaptor.EclipseStarter.run(EclipseStarter.java:127)\n        at sun.reflect.NativeMethodAccessorImpl.invoke0(Native Method)\n        at\nsun.reflect.NativeMethodAccessorImpl.invoke(NativeMethodAccessorImpl.java:39)\n        at\nsun.reflect.DelegatingMethodAccessorImpl.invoke(DelegatingMethodAccessorImpl.java:25)\n        at java.lang.reflect.Method.invoke(Method.java:324)\n        at org.eclipse.core.launcher.Main.basicRun(Main.java:184)\n        at org.eclipse.core.launcher.Main.run(Main.java:637)\n        at org.eclipse.core.launcher.Main.main(Main.java:621)",
    "The problem is the tomcat plugin which refers to internal API in jdt/UI which \nwe have changed. Please report the bug to the provider of the tomcat plug-in \n(Sysdeo)."
  ],
  "commentCreationDates": [
    "2004-05-20T19:46:00+02:00",
    "2004-05-21T11:11:40+02:00"
  ],
  "traces": [
    {
      "exceptionType": "java.lang.NoSuchMethodError",
      "message": "org.eclipse.jdt.internal.ui.wizards.dialogfields.ListDialogField.setElements(Ljava/util/List;)V",
      "elements": [
        {
          "method": "com.sysdeo.eclipse.tomcat.editors.ProjectListEditor.updateProjectsList",
          "source": "ProjectListEditor.java:65"
        },
        {
          "method": "com.sysdeo.eclipse.tomcat.editors.ProjectListEditor.\u003cinit\u003e",
          "source": "ProjectListEditor.java:39"
        },
        {
          "method": "com.sysdeo.eclipse.tomcat.TomcatPreferencePage.createContents",
          "source": "TomcatPreferencePage.java:123"
        },
        {
          "method": "org.eclipse.jface.preference.PreferencePage.createControl",
          "source": "PreferencePage.java:217"
        },
        {
          "method": "org.eclipse.jface.preference.PreferenceDialog$12.run",
          "source": "PreferenceDialog.java:1006"
        },
        {
          "method": "org.eclipse.core.internal.runtime.InternalPlatform.run",
          "source": "InternalPlatform.java:608"
        },
        {
          "method": "org.eclipse.core.runtime.Platform.run",
          "source": "Platform.java:758"
        },
        {
          "method": "org.eclipse.jface.preference.PreferenceDialog.showPage",
          "source": "PreferenceDialog.java:1001"
        },
        {
          "method": "org.eclipse.jface.preference.PreferenceDialog$8.selectionChanged",
          "source": "PreferenceDialog.java:528"
        },
        {
          "method": "org.eclipse.jface.viewers.StructuredViewer$3.run",
          "source": "StructuredViewer.java:452"
        },
        {
          "method": "org.eclipse.core.internal.runtime.InternalPlatform.run",
          "source": "InternalPlatform.java:608"
        },
        {
          "method": "org.eclipse.core.runtime.Platform.run",
          "source": "Platform.java:758"
        },
        {
          "method": "org.eclipse.jface.viewers.StructuredViewer.firePostSelectionChanged",
          "source": "StructuredViewer.java:450"
        },
        {
          "method": "org.eclipse.jface.viewers.StructuredViewer.handlePostSelect",
          "source": "StructuredViewer.java:710"
        },
        {
          "method": "org.eclipse.jface.viewers.StructuredViewer$5.widgetSelected",
          "source": "StructuredViewer.java:728"
        },
        {
          "method": "org.eclipse.jface.util.OpenStrategy.firePostSelectionEvent",
          "source": "OpenStrategy.java:200"
        },
        {
          "method": "org.eclipse.jface.util.OpenStrategy.access$4",
          "source": "OpenStrategy.java:195"
        },
        {
          "method": "org.eclipse.jface.util.OpenStrategy$3.run",
          "source": "OpenStrategy.java:349"
        },
        {
          "method": "org.eclipse.swt.widgets.RunnableLock.run",
          "source": "RunnableLock.java:35"
        },
        {
          "method": "org.eclipse.swt.widgets.Synchronizer.runAsyncMessages",
          "source": "Synchronizer.java:106"
        },
        {
          "method": "org.eclipse.swt.widgets.Display.runAsyncMessages",
          "source": "Display.java:2515"
        },
        {
          "method": "org.eclipse.swt.widgets.Display.readAndDispatch",
          "source": "Display.java:2252"
        },
        {
          "method": "org.eclipse.jface.window.Window.runEventLoop",
          "source": "Window.java:668"
        },
        {
          "method": "org.eclipse.jface.window.Window.open",
          "source": "Window.java:648"
        },
        {
          "method": "org.eclipse.ui.internal.OpenPreferencesAction.run",
          "source": "OpenPreferencesAction.java:72"
        },
        {
          "method": "org.eclipse.jface.action.Action.runWithEvent",
          "source": "Action.java:881"
        },
        {
          "method": "org.eclipse.jface.action.ActionContributionItem.handleWidgetSelection",
          "source": "ActionContributionItem.java:899"
        },
        {
          "method": "org.eclipse.jface.action.ActionContributionItem.access$2",
          "source": "ActionContributionItem.java:850"
        },
        {
          "method": "org.eclipse.jface.action.ActionContributionItem$7.handleEvent",
          "source": "ActionContributionItem.java:769"
        },
        {
          "method": "org.eclipse.swt.widgets.EventTable.sendEvent",
          "source": "EventTable.java:82"
        },
        {
          "method": "org.eclipse.swt.widgets.Widget.sendEvent",
          "source": "Widget.java:944"
        },
        {
          "method": "org.eclipse.swt.widgets.Display.runDeferredEvents",
          "source": "Display.java:2538"
        },
        {
          "method": "org.eclipse.swt.widgets.Display.readAndDispatch",
          "source": "Display.java:2249"
        },
        {
          "method": "org.eclipse.ui.internal.Workbench.runEventLoop",
          "source": "Workbench.java:1363"
        },
        {
          "method": "org.eclipse.ui.internal.Workbench.runUI",
          "source": "Workbench.java:1334"
        },
        {
          "method": "org.eclipse.ui.internal.Workbench.createAndRunWorkbench",
          "source": "Workbench.java:253"
        },
        {
          "method": "org.eclipse.ui.PlatformUI.createAndRunWorkbench",
          "source": "PlatformUI.java:141"
        },
        {
          "method": "org.eclipse.ui.internal.ide.IDEApplication.run",
          "source": "IDEApplication.java:97"
        },
        {
          "method": "org.eclipse.core.internal.runtime.PlatformActivator$1.run",
          "source": "PlatformActivator.java:305"
        },
        {
          "method": "org.eclipse.core.runtime.adaptor.EclipseStarter.run",
          "source": "EclipseStarter.java:256"
        },
        {
          "method": "org.eclipse.core.runtime.adaptor.EclipseStarter.run",
          "source": "EclipseStarter.java:127"
        },
        {
          "method": "sun.reflect.NativeMethodAccessorImpl.invoke0",
          "source": "Native Method"
        },
        {
          "method": "sun.reflect.NativeMethodAccessorImpl.invoke",
          "source": "NativeMethodAccessorImpl.java:39"
        },
        {
          "method": "sun.reflect.DelegatingMethodAccessorImpl.invoke",
          "source": "DelegatingMethodAccessorImpl.java:25"
        },
        {
          "method": "java.lang.reflect.Method.invoke",
          "source": "Method.java:324"
        },
        {
          "method": "org.eclipse.core.launcher.Main.basicRun",
          "source": "Main.java:184"
        },
        {
          "method": "org.eclipse.core.launcher.Main.run",
          "source": "Main.java:637"
        },
        {
          "method": "org.eclipse.core.launcher.Main.main",
          "source": "Main.java:621"
        }
      ],
      "number": 0,
      "commentIndex": 0,
      "bugId": "63262",
      "date": "2004-05-20T19:46:00+02:00",
      "product": "JDT",
      "component": "UI",
      "severity": "normal"
    },
    {
      "exceptionType": "java.lang.NoSuchMethodError",
      "message": "org.eclipse.jdt.internal.ui.wizards.dialogfields.ListDialogField.setElements(Ljava/util/List;)V",
      "elements": [
        {
          "method": "com.sysdeo.eclipse.tomcat.editors.ProjectListEditor.updateProjectsList",
          "source": "ProjectListEditor.java:65"
        },
        {
          "method": "com.sysdeo.eclipse.tomcat.editors.ProjectListEditor.\u003cinit\u003e",
          "source": "ProjectListEditor.java:39"
        },
        {
          "method": "com.sysdeo.eclipse.tomcat.TomcatSourcePathPreferencePage.createContents",
          "source": "TomcatSourcePathPreferencePage.java:36"
        },
        {
          "method": "org.eclipse.jface.preference.PreferencePage.createControl",
          "source": "PreferencePage.java:217"
        },
        {
          "method": "org.eclipse.jface.preference.PreferenceDialog$12.run",
          "source": "PreferenceDialog.java:1006"
        },
        {
          "method": "org.eclipse.core.internal.runtime.InternalPlatform.run",
          "source": "InternalPlatform.java:608"
        },
        {
          "method": "org.eclipse.core.runtime.Platform.run",
          "source": "Platform.java:758"
        },
        {
          "method": "org.eclipse.jface.preference.PreferenceDialog.showPage",
          "source": "PreferenceDialog.java:1001"
        },
        {
          "method": "org.eclipse.jface.preference.PreferenceDialog$8.selectionChanged",
          "source": "PreferenceDialog.java:528"
        },
        {
          "method": "org.eclipse.jface.viewers.StructuredViewer$3.run",
          "source": "StructuredViewer.java:452"
        },
        {
          "method": "org.eclipse.core.internal.runtime.InternalPlatform.run",
          "source": "InternalPlatform.java:608"
        },
        {
          "method": "org.eclipse.core.runtime.Platform.run",
          "source": "Platform.java:758"
        },
        {
          "method": "org.eclipse.jface.viewers.StructuredViewer.firePostSelectionChanged",
          "source": "StructuredViewer.java:450"
        },
        {
          "method": "org.eclipse.jface.viewers.StructuredViewer.handlePostSelect",
          "source": "StructuredViewer.java:710"
        },
        {
          "method": "org.eclipse.jface.viewers.StructuredViewer$5.widgetSelected",
          "source": "StructuredViewer.java:728"
        },
        {
          "method": "org.eclipse.jface.util.OpenStrategy.firePostSelectionEvent",
          "source": "OpenStrategy.java:200"
        },
        {
          "method": "org.eclipse.jface.util.OpenStrategy.access$4",
          "source": "OpenStrategy.java:195"
        },
        {
          "method": "org.eclipse.jface.util.OpenStrategy$3.run",
          "source": "OpenStrategy.java:349"
        },
        {
          "method": "org.eclipse.swt.widgets.RunnableLock.run",
          "source": "RunnableLock.java:35"
        },
        {
          "method": "org.eclipse.swt.widgets.Synchronizer.runAsyncMessages",
          "source": "Synchronizer.java:106"
        },
        {
          "method": "org.eclipse.swt.widgets.Display.runAsyncMessages",
          "source": "Display.java:2515"
        },
        {
          "method": "org.eclipse.swt.widgets.Display.readAndDispatch",
          "source": "Display.java:2252"
        },
        {
          "method": "org.eclipse.jface.window.Window.runEventLoop",
          "source": "Window.java:668"
        },
        {
          "method": "org.eclipse.jface.window.Window.open",
          "source": "Window.java:648"
        },
        {
          "method": "org.eclipse.ui.internal.OpenPreferencesAction.run",
          "source": "OpenPreferencesAction.java:72"
        },
        {
          "method": "org.eclipse.jface.action.Action.runWithEvent",
          "source": "Action.java:881"
        },
        {
          "method": "org.eclipse.jface.action.ActionContributionItem.handleWidgetSelection",
          "source": "ActionContributionItem.java:899"
        },
        {
          "method": "org.eclipse.jface.action.ActionContributionItem.access$2",
          "source": "ActionContributionItem.java:850"
        },
        {
          "method": "org.eclipse.jface.action.ActionContributionItem$7.handleEvent",
          "source": "ActionContributionItem.java:769"
        },
        {
          "method": "org.eclipse.swt.widgets.EventTable.sendEvent",
          "source": "EventTable.java:82"
        },
        {
          "method": "org.eclipse.swt.widgets.Widget.sendEvent",
          "source": "Widget.java:944"
        },
        {
          "method": "org.eclipse.swt.widgets.Display.runDeferredEvents",
          "source": "Display.java:2538"
        },
        {
          "method": "org.eclipse.swt.widgets.Display.readAndDispatch",
          "source": "Display.java:2249"
        },
        {
          "method": "org.eclipse.ui.internal.Workbench.runEventLoop",
          "source": "Workbench.java:1363"
        },
        {
          "method": "org.eclipse.ui.internal.Workbench.runUI",
          "source": "Workbench.java:1334"
        },
        {
          "method": "org.eclipse.ui.internal.Workbench.createAndRunWorkbench",
          "source": "Workbench.java:253"
        },
        {
          "method": "org.eclipse.ui.PlatformUI.createAndRunWorkbench",
          "source": "PlatformUI.java:141"
        },
        {
          "method": "org.eclipse.ui.internal.ide.IDEApplication.run",
          "source": "IDEApplication.java:97"
        },
        {
          "method": "org.eclipse.core.internal.runtime.PlatformActivator$1.run",
          "source": "PlatformActivator.java:305"
        },
        {
          "method": "org.eclipse.core.runtime.adaptor.EclipseStarter.run",
          "source": "EclipseStarter.java:256"
        },
        {
          "method": "org.eclipse.core.runtime.adaptor.EclipseStarter.run",
          "source": "EclipseStarter.java:127"
        },
        {
          "method": "sun.reflect.NativeMethodAccessorImpl.invoke0",
          "source": "Native Method"
        },
        {
          "method": "sun.reflect.NativeMethodAccessorImpl.invoke",
          "source": "NativeMethodAccessorImpl.java:39"
        },
        {
          "method": "sun.reflect.DelegatingMethodAccessorImpl.invoke",
          "source": "DelegatingMethodAccessorImpl.java:25"
        },
        {
          "method": "java.lang.reflect.Method.invoke",
          "source": "Method.java:324"
        },
        {
          "method": "org.eclipse.core.launcher.Main.basicRun",
          "source": "Main.java:184"
        },
        {
          "method": "org.eclipse.core.launcher.Main.run",
          "source": "Main.java:637"
        },
        {
          "method": "org.eclipse.core.launcher.Main.main",
          "source": "Main.java:621"
        }
      ],
      "number": 1,
      "commentIndex": 0,
      "bugId": "63262",
      "date": "2004-05-20T19:46:00+02:00",
      "product": "JDT",
      "component": "UI",
      "severity": "normal"
    }
  ],
  "groupId": "63262",
  "bugId": "63262",
  "date": "2004-05-20T19:46:00+02:00",
  "product": "JDT",
  "component": "UI",
  "severity": "normal"
}