{
  "comments": [
    "build i0521-0800\n\nI selected all the modules in CVS and checked them out. Autobuild was on. In the\nmiddle of the checkout I got the following error in my log file.\n\nosgi\u003e !SESSION May 21, 2004 11:20:02.387 ---------------------------------------\n------\neclipse.buildId\u003dI200405210800\njava.fullversion\u003dJ2RE 1.4.1 IBM J9 build 20040510 (JIT enabled)\nBootLoader constants: OS\u003dwin32, ARCH\u003dx86, WS\u003dwin32, NL\u003den_US\nCommand-line arguments: -showlocation\n!ENTRY org.eclipse.core.runtime 4 2 May 21, 2004 11:20:02.397\n!MESSAGE Problems occurred when invoking code from plug-in: \"org.eclipse.core.ru\nntime\".\n!STACK 0\njava.lang.NullPointerException\n        at java.lang.Throwable.\u003cinit\u003e(Throwable.java)\n        at java.lang.Throwable.\u003cinit\u003e(Throwable.java)\n        at java.lang.NullPointerException.\u003cinit\u003e(NullPointerException.java:60)\n        at org.eclipse.jdt.internal.core.DeltaProcessor.nonJavaResourcesChanged(\nDeltaProcessor.java:1543)\n        at org.eclipse.jdt.internal.core.DeltaProcessor.traverseDelta(DeltaProce\nssor.java)\n        at org.eclipse.jdt.internal.core.DeltaProcessor.traverseDelta(DeltaProce\nssor.java)\n        at org.eclipse.jdt.internal.core.DeltaProcessor.processResourceDelta(Del\ntaProcessor.java:1671)\n        at org.eclipse.jdt.internal.core.DeltaProcessor.resourceChanged(DeltaPro\ncessor.java)\n        at org.eclipse.jdt.internal.core.DeltaProcessingState.resourceChanged(De\nltaProcessingState.java:414)\n        at org.eclipse.core.internal.events.NotificationManager$2.run(Notificati\nonManager.java)\n        at org.eclipse.core.internal.runtime.InternalPlatform.run(InternalPlatfo\nrm.java)\n        at org.eclipse.core.runtime.Platform.run(Platform.java)\n        at org.eclipse.core.internal.events.NotificationManager.notify(Notificat\nionManager.java:277)\n        at org.eclipse.core.internal.events.NotificationManager.broadcastChanges\n(NotificationManager.java:151)\n        at org.eclipse.core.internal.resources.Workspace.broadcastChanges(Worksp\nace.java:172)\n        at org.eclipse.core.internal.resources.Workspace.endOperation(Workspace.\njava)\n        at org.eclipse.core.internal.resources.Workspace.run(Workspace.java)\n        at org.eclipse.core.internal.events.NotificationManager$NotifyJob.run(No\ntificationManager.java:38)\n        at org.eclipse.core.internal.jobs.Worker.run(Worker.java)",
    "Too late for M9.",
    "Could not reproduce. However JavaElementDelta.find(...) can return null. \nChanged JavaElementDelta.changed(...) to return the delta that it just \ncreated, and removed the call to JavaElementDelta.find(...).",
    "Could not reproduce.\nVerified in 200405281200 that the fix is in."
  ],
  "commentCreationDates": [
    "2004-05-21T17:34:31+02:00",
    "2004-05-21T19:27:30+02:00",
    "2004-05-25T16:37:30+02:00",
    "2004-05-28T21:40:17+02:00"
  ],
  "traces": [
    {
      "exceptionType": "java.lang.NullPointerException",
      "elements": [
        {
          "method": "java.lang.Throwable.\u003cinit\u003e",
          "source": "Throwable.java"
        },
        {
          "method": "java.lang.Throwable.\u003cinit\u003e",
          "source": "Throwable.java"
        },
        {
          "method": "java.lang.NullPointerException.\u003cinit\u003e",
          "source": "NullPointerException.java:60"
        },
        {
          "method": "org.eclipse.jdt.internal.core.DeltaProcessor.nonJavaResourcesChanged",
          "source": " DeltaProcessor.java:1543"
        },
        {
          "method": "org.eclipse.jdt.internal.core.DeltaProcessor.traverseDelta",
          "source": "DeltaProce ssor.java"
        },
        {
          "method": "org.eclipse.jdt.internal.core.DeltaProcessor.traverseDelta",
          "source": "DeltaProce ssor.java"
        },
        {
          "method": "org.eclipse.jdt.internal.core.DeltaProcessor.processResourceDelta",
          "source": "Del taProcessor.java:1671"
        },
        {
          "method": "org.eclipse.jdt.internal.core.DeltaProcessor.resourceChanged",
          "source": "DeltaPro cessor.java"
        },
        {
          "method": "org.eclipse.jdt.internal.core.DeltaProcessingState.resourceChanged",
          "source": "De ltaProcessingState.java:414"
        },
        {
          "method": "org.eclipse.core.internal.events.NotificationManager$2.run",
          "source": "Notificati onManager.java"
        },
        {
          "method": "org.eclipse.core.internal.runtime.InternalPlatform.run",
          "source": "InternalPlatfo rm.java"
        },
        {
          "method": "org.eclipse.core.runtime.Platform.run",
          "source": "Platform.java"
        },
        {
          "method": "org.eclipse.core.internal.events.NotificationManager.notify",
          "source": "Notificat ionManager.java:277"
        },
        {
          "method": "org.eclipse.core.internal.events.NotificationManager.broadcastChanges",
          "source": "NotificationManager.java:151"
        },
        {
          "method": "org.eclipse.core.internal.resources.Workspace.broadcastChanges",
          "source": "Worksp ace.java:172"
        },
        {
          "method": "org.eclipse.core.internal.resources.Workspace.endOperation",
          "source": "Workspace. java"
        },
        {
          "method": "org.eclipse.core.internal.resources.Workspace.run",
          "source": "Workspace.java"
        },
        {
          "method": "org.eclipse.core.internal.events.NotificationManager$NotifyJob.run",
          "source": "No tificationManager.java:38"
        },
        {
          "method": "org.eclipse.core.internal.jobs.Worker.run",
          "source": "Worker.java"
        }
      ],
      "number": 0,
      "commentIndex": 0,
      "bugId": "63434",
      "date": "2004-05-21T17:34:31+02:00",
      "product": "JDT",
      "component": "Core",
      "severity": "normal"
    }
  ],
  "groupId": "63434",
  "bugId": "63434",
  "date": "2004-05-21T17:34:31+02:00",
  "product": "JDT",
  "component": "Core",
  "severity": "normal"
}