{
  "comments": [
    "I20040521-1200 build on RedHat9.0\nI have checked out project from CVS, switched to java perspective, launched\nhelp, exited and found following in the log:\n\n!ENTRY org.eclipse.ui 4 4 May 21, 2004 13:21:33.938\n!MESSAGE Unhandled event loop exception\n!ENTRY org.eclipse.ui 4 0 May 21, 2004 13:21:33.939\n!MESSAGE Widget is disposed\n!STACK 0\norg.eclipse.swt.SWTException: Widget is disposed\n        at org.eclipse.swt.SWT.error(SWT.java:2689)\n        at org.eclipse.swt.SWT.error(SWT.java:2614)\n        at org.eclipse.swt.SWT.error(SWT.java:2585)\n        at org.eclipse.swt.widgets.Widget.error(Widget.java:374)\n        at org.eclipse.swt.widgets.Widget.checkWidget(Widget.java:310)\n        at org.eclipse.swt.widgets.Label.setImage(Label.java:474)\n        at org.eclipse.jface.dialogs.ProgressMonitorDialog.updateForClearBlocked\n(ProgressMonitorDialog.java:217)\n        at org.eclipse.jface.dialogs.ProgressMonitorDialog$ProgressMonitor.clear\nBlocked(ProgressMonitorDialog.java:200)\n        at org.eclipse.ui.internal.progress.ProgressMonitorFocusJobDialog$6.run(\nProgressMonitorFocusJobDialog.java:177)\n        at org.eclipse.swt.widgets.RunnableLock.run(RunnableLock.java:35)\n        at org.eclipse.swt.widgets.Synchronizer.runAsyncMessages(Synchronizer.ja\nva:106)\n        at org.eclipse.swt.widgets.Display.runAsyncMessages(Display.java:2519)\n        at org.eclipse.swt.widgets.Display.readAndDispatch(Display.java:2256)\n        at org.eclipse.ui.internal.Workbench.runEventLoop(Workbench.java:1363)\n        at org.eclipse.ui.internal.Workbench.runUI(Workbench.java:1334)\n        at org.eclipse.ui.internal.Workbench.createAndRunWorkbench(Workbench.jav\na:253)\n        at org.eclipse.ui.PlatformUI.createAndRunWorkbench(PlatformUI.java:141)\n        at org.eclipse.ui.internal.ide.IDEApplication.run(IDEApplication.java:97\n)\n        at org.eclipse.core.internal.runtime.PlatformActivator$1.run(PlatformAct\nivator.java:307)\n        at org.eclipse.core.runtime.adaptor.EclipseStarter.run(EclipseStarter.ja\nva:256)\n        at org.eclipse.core.runtime.adaptor.EclipseStarter.run(EclipseStarter.ja\nva:127)\n        at sun.reflect.NativeMethodAccessorImpl.invoke0(Native Method)\n        at sun.reflect.NativeMethodAccessorImpl.invoke(NativeMethodAccessorImpl.\njava:39)\n        at\nsun.reflect.DelegatingMethodAccessorImpl.invoke(DelegatingMethodAccessorImpl.java:25)\n        at java.lang.reflect.Method.invoke(Method.java:324)\n        at org.eclipse.core.launcher.Main.basicRun(Main.java:185)\n        at org.eclipse.core.launcher.Main.run(Main.java:638)\n        at org.eclipse.core.launcher.Main.main(Main.java:622)",
    "Thius is because the opening of this dialog is being blocked by the modal \ndialg and it is using the modal dialog as a potential parent. We need to \nreview the use of the isUser call and the grabbing of a shell.",
    "\n\n*** This bug has been marked as a duplicate of 64362 ***"
  ],
  "commentCreationDates": [
    "2004-05-21T19:52:18+02:00",
    "2004-05-27T14:29:00+02:00",
    "2004-05-27T18:23:14+02:00"
  ],
  "traces": [
    {
      "exceptionType": "org.eclipse.swt.SWTException",
      "message": "Widget is disposed",
      "elements": [
        {
          "method": "org.eclipse.swt.SWT.error",
          "source": "SWT.java:2689"
        },
        {
          "method": "org.eclipse.swt.SWT.error",
          "source": "SWT.java:2614"
        },
        {
          "method": "org.eclipse.swt.SWT.error",
          "source": "SWT.java:2585"
        },
        {
          "method": "org.eclipse.swt.widgets.Widget.error",
          "source": "Widget.java:374"
        },
        {
          "method": "org.eclipse.swt.widgets.Widget.checkWidget",
          "source": "Widget.java:310"
        },
        {
          "method": "org.eclipse.swt.widgets.Label.setImage",
          "source": "Label.java:474"
        },
        {
          "method": "org.eclipse.jface.dialogs.ProgressMonitorDialog.updateForClearBlocked",
          "source": "ProgressMonitorDialog.java:217"
        },
        {
          "method": "org.eclipse.jface.dialogs.ProgressMonitorDialog$ProgressMonitor.clearBlocked",
          "source": "ProgressMonitorDialog.java:200"
        },
        {
          "method": "org.eclipse.ui.internal.progress.ProgressMonitorFocusJobDialog$6.run",
          "source": " ProgressMonitorFocusJobDialog.java:177"
        },
        {
          "method": "org.eclipse.swt.widgets.RunnableLock.run",
          "source": "RunnableLock.java:35"
        },
        {
          "method": "org.eclipse.swt.widgets.Synchronizer.runAsyncMessages",
          "source": "Synchronizer.ja va:106"
        },
        {
          "method": "org.eclipse.swt.widgets.Display.runAsyncMessages",
          "source": "Display.java:2519"
        },
        {
          "method": "org.eclipse.swt.widgets.Display.readAndDispatch",
          "source": "Display.java:2256"
        },
        {
          "method": "org.eclipse.ui.internal.Workbench.runEventLoop",
          "source": "Workbench.java:1363"
        },
        {
          "method": "org.eclipse.ui.internal.Workbench.runUI",
          "source": "Workbench.java:1334"
        },
        {
          "method": "org.eclipse.ui.internal.Workbench.createAndRunWorkbench",
          "source": "Workbench.jav a:253"
        },
        {
          "method": "org.eclipse.ui.PlatformUI.createAndRunWorkbench",
          "source": "PlatformUI.java:141"
        },
        {
          "method": "org.eclipse.ui.internal.ide.IDEApplication.run",
          "source": "IDEApplication.java:97 "
        },
        {
          "method": "org.eclipse.core.internal.runtime.PlatformActivator$1.run",
          "source": "PlatformAct ivator.java:307"
        },
        {
          "method": "org.eclipse.core.runtime.adaptor.EclipseStarter.run",
          "source": "EclipseStarter.ja va:256"
        },
        {
          "method": "org.eclipse.core.runtime.adaptor.EclipseStarter.run",
          "source": "EclipseStarter.ja va:127"
        },
        {
          "method": "sun.reflect.NativeMethodAccessorImpl.invoke0",
          "source": "Native Method"
        },
        {
          "method": "sun.reflect.NativeMethodAccessorImpl.invoke",
          "source": "NativeMethodAccessorImpl. java:39"
        },
        {
          "method": "sun.reflect.DelegatingMethodAccessorImpl.invoke",
          "source": "DelegatingMethodAccessorImpl.java:25"
        },
        {
          "method": "java.lang.reflect.Method.invoke",
          "source": "Method.java:324"
        },
        {
          "method": "org.eclipse.core.launcher.Main.basicRun",
          "source": "Main.java:185"
        },
        {
          "method": "org.eclipse.core.launcher.Main.run",
          "source": "Main.java:638"
        },
        {
          "method": "org.eclipse.core.launcher.Main.main",
          "source": "Main.java:622"
        }
      ],
      "number": 0,
      "commentIndex": 0,
      "bugId": "63450",
      "duplicateId": "64362",
      "date": "2004-05-21T19:52:18+02:00",
      "product": "Platform",
      "component": "UI",
      "severity": "normal"
    }
  ],
  "groupId": "64362",
  "bugId": "63450",
  "duplicateId": "64362",
  "date": "2004-05-21T19:52:18+02:00",
  "product": "Platform",
  "component": "UI",
  "severity": "normal"
}