{
  "comments": [
    "I found this in my log but didn\u0027t notice anything wrong in the UI:\n!ENTRY org.eclipse.ui 4 0 May 21, 2004 13:52:49.970\n!MESSAGE java.lang.NullPointerException\n!STACK 0\njava.lang.NullPointerException\n        at\norg.eclipse.team.internal.ccvs.ui.subscriber.ChangeLogModelProvider.removeFromViewer(ChangeLogModelProvider.java:568)\n        at\norg.eclipse.team.internal.ccvs.ui.subscriber.ChangeLogModelProvider.handleResourceRemovals(ChangeLogModelProvider.java:554)\n        at\norg.eclipse.team.internal.ui.synchronize.SynchronizeModelProvider.handleChanges(SynchronizeModelProvider.java:303)\n        at\norg.eclipse.team.internal.ui.synchronize.SynchronizeModelProvider$4.run(SynchronizeModelProvider.java:254)\n        at org.eclipse.swt.custom.BusyIndicator.showWhile(BusyIndicator.java:69)\n        at\norg.eclipse.team.internal.ui.synchronize.SynchronizeModelProvider$3.run(SynchronizeModelProvider.java:252)\n        at\norg.eclipse.ui.internal.UILockListener.doPendingWork(UILockListener.java:107)\n        at org.eclipse.ui.internal.UISynchronizer$1.run(UISynchronizer.java:33)\n        at org.eclipse.swt.widgets.RunnableLock.run(RunnableLock.java:35)\n        at\norg.eclipse.swt.widgets.Synchronizer.runAsyncMessages(Synchronizer.java:106)\n        at org.eclipse.swt.widgets.Display.runAsyncMessages(Display.java:2693)\n        at org.eclipse.swt.widgets.Display.readAndDispatch(Display.java:2385)\n        at org.eclipse.ui.internal.Workbench.runEventLoop(Workbench.java:1363)\n        at org.eclipse.ui.internal.Workbench.runUI(Workbench.java:1334)\n        at\norg.eclipse.ui.internal.Workbench.createAndRunWorkbench(Workbench.java:253)\n        at org.eclipse.ui.PlatformUI.createAndRunWorkbench(PlatformUI.java:141)\n        at org.eclipse.ui.internal.ide.IDEApplication.run(IDEApplication.java:97)\n        at\norg.eclipse.core.internal.runtime.PlatformActivator$1.run(PlatformActivator.java:307)\n        at\norg.eclipse.core.runtime.adaptor.EclipseStarter.run(EclipseStarter.java:256)\n        at\norg.eclipse.core.runtime.adaptor.EclipseStarter.run(EclipseStarter.java:127)\n        at sun.reflect.NativeMethodAccessorImpl.invoke0(Native Method)\n        at\nsun.reflect.NativeMethodAccessorImpl.invoke(NativeMethodAccessorImpl.java:39)\n        at\nsun.reflect.DelegatingMethodAccessorImpl.invoke(DelegatingMethodAccessorImpl.java:25)\n        at java.lang.reflect.Method.invoke(Method.java:324)\n        at org.eclipse.core.launcher.Main.basicRun(Main.java:185)\n        at org.eclipse.core.launcher.Main.run(Main.java:638)\n        at org.eclipse.core.launcher.Main.main(Main.java:622)\njava.lang.NullPointerException",
    "fixed.",
    "*** Bug 64537 has been marked as a duplicate of this bug. ***"
  ],
  "commentCreationDates": [
    "2004-05-21T20:07:46+02:00",
    "2004-05-21T21:02:35+02:00",
    "2004-05-28T14:50:39+02:00"
  ],
  "traces": [
    {
      "exceptionType": "java.lang.NullPointerException",
      "elements": [
        {
          "method": "org.eclipse.team.internal.ccvs.ui.subscriber.ChangeLogModelProvider.removeFromViewer",
          "source": "ChangeLogModelProvider.java:568"
        },
        {
          "method": "org.eclipse.team.internal.ccvs.ui.subscriber.ChangeLogModelProvider.handleResourceRemovals",
          "source": "ChangeLogModelProvider.java:554"
        },
        {
          "method": "org.eclipse.team.internal.ui.synchronize.SynchronizeModelProvider.handleChanges",
          "source": "SynchronizeModelProvider.java:303"
        },
        {
          "method": "org.eclipse.team.internal.ui.synchronize.SynchronizeModelProvider$4.run",
          "source": "SynchronizeModelProvider.java:254"
        },
        {
          "method": "org.eclipse.swt.custom.BusyIndicator.showWhile",
          "source": "BusyIndicator.java:69"
        },
        {
          "method": "org.eclipse.team.internal.ui.synchronize.SynchronizeModelProvider$3.run",
          "source": "SynchronizeModelProvider.java:252"
        },
        {
          "method": "org.eclipse.ui.internal.UILockListener.doPendingWork",
          "source": "UILockListener.java:107"
        },
        {
          "method": "org.eclipse.ui.internal.UISynchronizer$1.run",
          "source": "UISynchronizer.java:33"
        },
        {
          "method": "org.eclipse.swt.widgets.RunnableLock.run",
          "source": "RunnableLock.java:35"
        },
        {
          "method": "org.eclipse.swt.widgets.Synchronizer.runAsyncMessages",
          "source": "Synchronizer.java:106"
        },
        {
          "method": "org.eclipse.swt.widgets.Display.runAsyncMessages",
          "source": "Display.java:2693"
        },
        {
          "method": "org.eclipse.swt.widgets.Display.readAndDispatch",
          "source": "Display.java:2385"
        },
        {
          "method": "org.eclipse.ui.internal.Workbench.runEventLoop",
          "source": "Workbench.java:1363"
        },
        {
          "method": "org.eclipse.ui.internal.Workbench.runUI",
          "source": "Workbench.java:1334"
        },
        {
          "method": "org.eclipse.ui.internal.Workbench.createAndRunWorkbench",
          "source": "Workbench.java:253"
        },
        {
          "method": "org.eclipse.ui.PlatformUI.createAndRunWorkbench",
          "source": "PlatformUI.java:141"
        },
        {
          "method": "org.eclipse.ui.internal.ide.IDEApplication.run",
          "source": "IDEApplication.java:97"
        },
        {
          "method": "org.eclipse.core.internal.runtime.PlatformActivator$1.run",
          "source": "PlatformActivator.java:307"
        },
        {
          "method": "org.eclipse.core.runtime.adaptor.EclipseStarter.run",
          "source": "EclipseStarter.java:256"
        },
        {
          "method": "org.eclipse.core.runtime.adaptor.EclipseStarter.run",
          "source": "EclipseStarter.java:127"
        },
        {
          "method": "sun.reflect.NativeMethodAccessorImpl.invoke0",
          "source": "Native Method"
        },
        {
          "method": "sun.reflect.NativeMethodAccessorImpl.invoke",
          "source": "NativeMethodAccessorImpl.java:39"
        },
        {
          "method": "sun.reflect.DelegatingMethodAccessorImpl.invoke",
          "source": "DelegatingMethodAccessorImpl.java:25"
        },
        {
          "method": "java.lang.reflect.Method.invoke",
          "source": "Method.java:324"
        },
        {
          "method": "org.eclipse.core.launcher.Main.basicRun",
          "source": "Main.java:185"
        },
        {
          "method": "org.eclipse.core.launcher.Main.run",
          "source": "Main.java:638"
        },
        {
          "method": "org.eclipse.core.launcher.Main.main",
          "source": "Main.java:622"
        }
      ],
      "number": 0,
      "commentIndex": 0,
      "bugId": "63456",
      "date": "2004-05-21T20:07:46+02:00",
      "product": "Platform",
      "component": "Team",
      "severity": "normal"
    }
  ],
  "groupId": "63456",
  "bugId": "63456",
  "date": "2004-05-21T20:07:46+02:00",
  "product": "Platform",
  "component": "Team",
  "severity": "normal"
}