{
  "comments": [
    "M9\n\nIn the Outgoing synchronize view, I chose Layout-\u003eCommit Sets and got this:\n\n!ENTRY org.eclipse.ui 4 0 May 24, 2004 11:42:00.603\n!MESSAGE java.lang.ArrayIndexOutOfBoundsException\n!STACK 0\njava.lang.ArrayIndexOutOfBoundsException\n        at java.lang.Throwable.\u003cinit\u003e(Throwable.java)\n        at java.lang.Throwable.\u003cinit\u003e(Throwable.java)\n        at\njava.lang.ArrayIndexOutOfBoundsException.\u003cinit\u003e(ArrayIndexOutOfBoundsException.java)\n        at org.eclipse.swt.widgets.Tree.getFocusItem(Tree.java:378)\n        at org.eclipse.swt.widgets.Tree.gtk_changed(Tree.java:635)\n        at org.eclipse.swt.widgets.Widget.windowProc(Widget.java:1161)\n        at org.eclipse.swt.widgets.Display.windowProc(Display.java)\n        at org.eclipse.swt.internal.gtk.OS.gtk_tree_store_clear(Native Method)\n        at org.eclipse.swt.widgets.Tree.removeAll(Tree.java:853)\n        at org.eclipse.jface.viewers.TreeViewer.removeAll(TreeViewer.java:223)\n        at\norg.eclipse.jface.viewers.AbstractTreeViewer$5.run(AbstractTreeViewer.java:780)\n        at\norg.eclipse.jface.viewers.StructuredViewer.preservingSelection(StructuredViewer.java)\n        at\norg.eclipse.jface.viewers.AbstractTreeViewer.inputChanged(AbstractTreeViewer.java:772)\n        at org.eclipse.jface.viewers.ContentViewer.setInput(ContentViewer.java:238)\n        at\norg.eclipse.jface.viewers.StructuredViewer.setInput(StructuredViewer.java:1058)\n        at\norg.eclipse.team.internal.ui.synchronize.StructuredViewerAdvisor.setInput(StructuredViewerAdvisor.java:354)\n        at\norg.eclipse.team.internal.ui.synchronize.SynchronizeModelManager.setInput(SynchronizeModelManager.java:201)\n        at\norg.eclipse.team.internal.ui.synchronize.SynchronizeModelManager$ToggleModelProviderAction.run(SynchronizeModelManager.java:60)\n        at org.eclipse.jface.action.Action.runWithEvent(Action.java:881)\n        at\norg.eclipse.jface.action.ActionContributionItem.handleWidgetSelection(ActionContributionItem.java:899)\n        at\norg.eclipse.jface.action.ActionContributionItem.access$2(ActionContributionItem.java:850)\n        at\norg.eclipse.jface.action.ActionContributionItem$7.handleEvent(ActionContributionItem.java:769)\n        at org.eclipse.swt.widgets.EventTable.sendEvent(EventTable.java)\n        at org.eclipse.swt.widgets.Widget.sendEvent(Widget.java)\n        at org.eclipse.swt.widgets.Display.runDeferredEvents(Display.java)\n        at org.eclipse.swt.widgets.Display.readAndDispatch(Display.java)\n        at org.eclipse.ui.internal.Workbench.runEventLoop(Workbench.java:1363)\n        at org.eclipse.ui.internal.Workbench.runUI(Workbench.java:1334)\n        at\norg.eclipse.ui.internal.Workbench.createAndRunWorkbench(Workbench.java:253)\n        at org.eclipse.ui.PlatformUI.createAndRunWorkbench(PlatformUI.java:141)\n        at org.eclipse.ui.internal.ide.IDEApplication.run(IDEApplication.java:97)\n        at\norg.eclipse.core.internal.runtime.PlatformActivator$1.run(PlatformActivator.java:307)\n        at\norg.eclipse.core.runtime.adaptor.EclipseStarter.run(EclipseStarter.java:256)\n        at\norg.eclipse.core.runtime.adaptor.EclipseStarter.run(EclipseStarter.java:127)\n        at sun.reflect.NativeMethodAccessorImpl.invoke0(Native Method)\n        at\nsun.reflect.NativeMethodAccessorImpl.invoke(NativeMethodAccessorImpl.java:79)\n        at\nsun.reflect.DelegatingMethodAccessorImpl.invoke(DelegatingMethodAccessorImpl.java:41)\n        at java.lang.reflect.Method.invoke(Method.java:386)\n        at org.eclipse.core.launcher.Main.basicRun(Main.java:185)\n        at org.eclipse.core.launcher.Main.run(Main.java:638)\n        at org.eclipse.core.launcher.Main.main(Main.java:622)\njava.lang.ArrayIndexOutOfBoundsException",
    "The synchronize view is unusable thereafter. Switching layout, closing, or\nreopening the view does not help. ",
    "This is happening on a removeAll from a Tree widget. Moving to SWT.",
    "\n\n*** This bug has been marked as a duplicate of 47896 ***"
  ],
  "commentCreationDates": [
    "2004-05-24T11:58:56+02:00",
    "2004-05-24T12:00:23+02:00",
    "2004-05-25T03:40:52+02:00",
    "2004-05-25T23:03:05+02:00"
  ],
  "traces": [
    {
      "exceptionType": "java.lang.ArrayIndexOutOfBoundsException",
      "elements": [
        {
          "method": "java.lang.Throwable.\u003cinit\u003e",
          "source": "Throwable.java"
        },
        {
          "method": "java.lang.Throwable.\u003cinit\u003e",
          "source": "Throwable.java"
        },
        {
          "method": "java.lang.ArrayIndexOutOfBoundsException.\u003cinit\u003e",
          "source": "ArrayIndexOutOfBoundsException.java"
        },
        {
          "method": "org.eclipse.swt.widgets.Tree.getFocusItem",
          "source": "Tree.java:378"
        },
        {
          "method": "org.eclipse.swt.widgets.Tree.gtk_changed",
          "source": "Tree.java:635"
        },
        {
          "method": "org.eclipse.swt.widgets.Widget.windowProc",
          "source": "Widget.java:1161"
        },
        {
          "method": "org.eclipse.swt.widgets.Display.windowProc",
          "source": "Display.java"
        },
        {
          "method": "org.eclipse.swt.internal.gtk.OS.gtk_tree_store_clear",
          "source": "Native Method"
        },
        {
          "method": "org.eclipse.swt.widgets.Tree.removeAll",
          "source": "Tree.java:853"
        },
        {
          "method": "org.eclipse.jface.viewers.TreeViewer.removeAll",
          "source": "TreeViewer.java:223"
        },
        {
          "method": "org.eclipse.jface.viewers.AbstractTreeViewer$5.run",
          "source": "AbstractTreeViewer.java:780"
        },
        {
          "method": "org.eclipse.jface.viewers.StructuredViewer.preservingSelection",
          "source": "StructuredViewer.java"
        },
        {
          "method": "org.eclipse.jface.viewers.AbstractTreeViewer.inputChanged",
          "source": "AbstractTreeViewer.java:772"
        },
        {
          "method": "org.eclipse.jface.viewers.ContentViewer.setInput",
          "source": "ContentViewer.java:238"
        },
        {
          "method": "org.eclipse.jface.viewers.StructuredViewer.setInput",
          "source": "StructuredViewer.java:1058"
        },
        {
          "method": "org.eclipse.team.internal.ui.synchronize.StructuredViewerAdvisor.setInput",
          "source": "StructuredViewerAdvisor.java:354"
        },
        {
          "method": "org.eclipse.team.internal.ui.synchronize.SynchronizeModelManager.setInput",
          "source": "SynchronizeModelManager.java:201"
        },
        {
          "method": "org.eclipse.team.internal.ui.synchronize.SynchronizeModelManager$ToggleModelProviderAction.run",
          "source": "SynchronizeModelManager.java:60"
        },
        {
          "method": "org.eclipse.jface.action.Action.runWithEvent",
          "source": "Action.java:881"
        },
        {
          "method": "org.eclipse.jface.action.ActionContributionItem.handleWidgetSelection",
          "source": "ActionContributionItem.java:899"
        },
        {
          "method": "org.eclipse.jface.action.ActionContributionItem.access$2",
          "source": "ActionContributionItem.java:850"
        },
        {
          "method": "org.eclipse.jface.action.ActionContributionItem$7.handleEvent",
          "source": "ActionContributionItem.java:769"
        },
        {
          "method": "org.eclipse.swt.widgets.EventTable.sendEvent",
          "source": "EventTable.java"
        },
        {
          "method": "org.eclipse.swt.widgets.Widget.sendEvent",
          "source": "Widget.java"
        },
        {
          "method": "org.eclipse.swt.widgets.Display.runDeferredEvents",
          "source": "Display.java"
        },
        {
          "method": "org.eclipse.swt.widgets.Display.readAndDispatch",
          "source": "Display.java"
        },
        {
          "method": "org.eclipse.ui.internal.Workbench.runEventLoop",
          "source": "Workbench.java:1363"
        },
        {
          "method": "org.eclipse.ui.internal.Workbench.runUI",
          "source": "Workbench.java:1334"
        },
        {
          "method": "org.eclipse.ui.internal.Workbench.createAndRunWorkbench",
          "source": "Workbench.java:253"
        },
        {
          "method": "org.eclipse.ui.PlatformUI.createAndRunWorkbench",
          "source": "PlatformUI.java:141"
        },
        {
          "method": "org.eclipse.ui.internal.ide.IDEApplication.run",
          "source": "IDEApplication.java:97"
        },
        {
          "method": "org.eclipse.core.internal.runtime.PlatformActivator$1.run",
          "source": "PlatformActivator.java:307"
        },
        {
          "method": "org.eclipse.core.runtime.adaptor.EclipseStarter.run",
          "source": "EclipseStarter.java:256"
        },
        {
          "method": "org.eclipse.core.runtime.adaptor.EclipseStarter.run",
          "source": "EclipseStarter.java:127"
        },
        {
          "method": "sun.reflect.NativeMethodAccessorImpl.invoke0",
          "source": "Native Method"
        },
        {
          "method": "sun.reflect.NativeMethodAccessorImpl.invoke",
          "source": "NativeMethodAccessorImpl.java:79"
        },
        {
          "method": "sun.reflect.DelegatingMethodAccessorImpl.invoke",
          "source": "DelegatingMethodAccessorImpl.java:41"
        },
        {
          "method": "java.lang.reflect.Method.invoke",
          "source": "Method.java:386"
        },
        {
          "method": "org.eclipse.core.launcher.Main.basicRun",
          "source": "Main.java:185"
        },
        {
          "method": "org.eclipse.core.launcher.Main.run",
          "source": "Main.java:638"
        },
        {
          "method": "org.eclipse.core.launcher.Main.main",
          "source": "Main.java:622"
        }
      ],
      "number": 0,
      "commentIndex": 0,
      "bugId": "63649",
      "duplicateId": "47896",
      "date": "2004-05-24T11:58:56+02:00",
      "product": "Platform",
      "component": "SWT",
      "severity": "normal"
    }
  ],
  "groupId": "66331",
  "bugId": "63649",
  "duplicateId": "47896",
  "date": "2004-05-24T11:58:56+02:00",
  "product": "Platform",
  "component": "SWT",
  "severity": "normal"
}