{
  "comments": [
    "3.0M9\n\norg.eclipse.swt.SWTException: Failed to execute runnable (java.lang.IllegalArgum\nentException)\n        at org.eclipse.swt.SWT.error(SWT.java:2689)\n        at org.eclipse.swt.SWT.error(SWT.java:2614)\n        at org.eclipse.swt.widgets.Synchronizer.runAsyncMessages(Synchronizer.ja\nva:109)\n        at org.eclipse.swt.widgets.Display.runAsyncMessages(Display.java:2693)\n        at org.eclipse.swt.widgets.Display.readAndDispatch(Display.java:2385)\n        at org.eclipse.ui.internal.Workbench.runEventLoop(Workbench.java:1363)\n        at org.eclipse.ui.internal.Workbench.runUI(Workbench.java:1334)\n        at org.eclipse.ui.internal.Workbench.createAndRunWorkbench(Workbench.jav\na:253)\n        at org.eclipse.ui.PlatformUI.createAndRunWorkbench(PlatformUI.java:141)\n        at org.eclipse.ui.internal.ide.IDEApplication.run(IDEApplication.java:97\n)\n        at org.eclipse.core.internal.runtime.PlatformActivator$1.run(PlatformAct\nivator.java:307)\n        at org.eclipse.core.runtime.adaptor.EclipseStarter.run(EclipseStarter.ja\nva:256)\n        at org.eclipse.core.runtime.adaptor.EclipseStarter.run(EclipseStarter.ja\nva:127)\n        at sun.reflect.NativeMethodAccessorImpl.invoke0(Native Method)\n        at sun.reflect.NativeMethodAccessorImpl.invoke(NativeMethodAccessorImpl.\njava:39)\n        at sun.reflect.DelegatingMethodAccessorImpl.invoke(DelegatingMethodAcces\nsorImpl.java:25)\n        at java.lang.reflect.Method.invoke(Method.java:324)\n        at org.eclipse.core.launcher.Main.basicRun(Main.java:185)\n        at org.eclipse.core.launcher.Main.run(Main.java:638)\n        at org.eclipse.core.launcher.Main.main(Main.java:622)\nFailed to execute runnable (java.lang.IllegalArgumentException)\n!ENTRY org.eclipse.ui 4 4 May 24, 2004 09:50:26.285\n!MESSAGE *** SWT nested exception\n*** SWT nested exception\nReason:\n!ENTRY org.eclipse.ui 4 0 May 24, 2004 09:50:26.295\n!MESSAGE java.lang.IllegalArgumentException\n!STACK 0\njava.lang.IllegalArgumentException\n        at org.eclipse.jface.text.source.projection.ProjectionViewer.catchupWith\nProjectionAnnotationModel(ProjectionViewer.java:769)\n        at org.eclipse.jface.text.source.projection.ProjectionViewer.access$7(Pr\nojectionViewer.java:731)\n        at org.eclipse.jface.text.source.projection.ProjectionViewer$1.run(Proje\nctionViewer.java:714)\n        at org.eclipse.swt.widgets.RunnableLock.run(RunnableLock.java:35)\n        at org.eclipse.swt.widgets.Synchronizer.runAsyncMessages(Synchronizer.ja\nva:106)\n        at org.eclipse.swt.widgets.Display.runAsyncMessages(Display.java:2693)\n        at org.eclipse.swt.widgets.Display.readAndDispatch(Display.java:2385)\n        at org.eclipse.ui.internal.Workbench.runEventLoop(Workbench.java:1363)\n        at org.eclipse.ui.internal.Workbench.runUI(Workbench.java:1334)\n        at org.eclipse.ui.internal.Workbench.createAndRunWorkbench(Workbench.jav\na:253)\n        at org.eclipse.ui.PlatformUI.createAndRunWorkbench(PlatformUI.java:141)\n        at org.eclipse.ui.internal.ide.IDEApplication.run(IDEApplication.java:97\n)\n        at org.eclipse.core.internal.runtime.PlatformActivator$1.run(PlatformAct\nivator.java:307)\n        at org.eclipse.core.runtime.adaptor.EclipseStarter.run(EclipseStarter.ja\nva:256)\n        at org.eclipse.core.runtime.adaptor.EclipseStarter.run(EclipseStarter.ja\nva:127)\n        at sun.reflect.NativeMethodAccessorImpl.invoke0(Native Method)\n        at sun.reflect.NativeMethodAccessorImpl.invoke(NativeMethodAccessorImpl.\njava:39)\n        at sun.reflect.DelegatingMethodAccessorImpl.invoke(DelegatingMethodAcces\nsorImpl.java:25)\n        at java.lang.reflect.Method.invoke(Method.java:324)\n        at org.eclipse.core.launcher.Main.basicRun(Main.java:185)\n        at org.eclipse.core.launcher.Main.run(Main.java:638)\n        at org.eclipse.core.launcher.Main.main(Main.java:622)\njava.lang.IllegalArgumentException",
    "Any additional info?",
    "Unfortunately not. I checked the log a few hours after the exception was thrown.",
    "+1\n\nnothing in .log\n\n!ENTRY org.eclipse.ui 4 4 Mai 24, 2004 14:34:24.943\n!MESSAGE Unhandled event loop exception\n!ENTRY org.eclipse.ui 4 0 Mai 24, 2004 14:34:24.953\n!MESSAGE Failed to execute runnable (java.lang.IllegalArgumentException)\n!STACK 0\norg.eclipse.swt.SWTException: Failed to execute runnable\n(java.lang.IllegalArgumentException)\n\tat org.eclipse.swt.SWT.error(SWT.java:2689)\n\tat org.eclipse.swt.SWT.error(SWT.java:2614)\n\tat org.eclipse.swt.widgets.Synchronizer.runAsyncMessages(Synchronizer.java:109)\n\tat org.eclipse.swt.widgets.Display.runAsyncMessages(Display.java:2693)\n\tat org.eclipse.swt.widgets.Display.readAndDispatch(Display.java:2385)\n\tat org.eclipse.ui.internal.Workbench.runEventLoop(Workbench.java:1363)\n\tat org.eclipse.ui.internal.Workbench.runUI(Workbench.java:1334)\n\tat org.eclipse.ui.internal.Workbench.createAndRunWorkbench(Workbench.java:253)\n\tat org.eclipse.ui.PlatformUI.createAndRunWorkbench(PlatformUI.java:141)\n\tat org.eclipse.ui.internal.ide.IDEApplication.run(IDEApplication.java:97)\n\tat\norg.eclipse.core.internal.runtime.PlatformActivator$1.run(PlatformActivator.java:307)\n\tat org.eclipse.core.runtime.adaptor.EclipseStarter.run(EclipseStarter.java:256)\n\tat org.eclipse.core.runtime.adaptor.EclipseStarter.run(EclipseStarter.java:127)\n\tat sun.reflect.NativeMethodAccessorImpl.invoke0(Native Method)\n\tat sun.reflect.NativeMethodAccessorImpl.invoke(NativeMethodAccessorImpl.java:39)\n\tat\nsun.reflect.DelegatingMethodAccessorImpl.invoke(DelegatingMethodAccessorImpl.java:25)\n\tat java.lang.reflect.Method.invoke(Method.java:324)\n\tat org.eclipse.core.launcher.Main.basicRun(Main.java:185)\n\tat org.eclipse.core.launcher.Main.run(Main.java:638)\n\tat org.eclipse.core.launcher.Main.main(Main.java:622)\n!ENTRY org.eclipse.ui 4 4 Mai 24, 2004 14:34:24.963\n!MESSAGE *** SWT nested exception\n!ENTRY org.eclipse.ui 4 0 Mai 24, 2004 14:34:24.973\n!MESSAGE java.lang.IllegalArgumentException\n!STACK 0\njava.lang.IllegalArgumentException\n\tat\norg.eclipse.jface.text.source.projection.ProjectionViewer.catchupWithProjectionAnnotationModel(ProjectionViewer.java:769)\n\tat\norg.eclipse.jface.text.source.projection.ProjectionViewer.access$7(ProjectionViewer.java:731)\n\tat\norg.eclipse.jface.text.source.projection.ProjectionViewer$1.run(ProjectionViewer.java:714)\n\tat org.eclipse.swt.widgets.RunnableLock.run(RunnableLock.java:35)\n\tat org.eclipse.swt.widgets.Synchronizer.runAsyncMessages(Synchronizer.java:106)\n\tat org.eclipse.swt.widgets.Display.runAsyncMessages(Display.java:2693)\n\tat org.eclipse.swt.widgets.Display.readAndDispatch(Display.java:2385)\n\tat org.eclipse.ui.internal.Workbench.runEventLoop(Workbench.java:1363)\n\tat org.eclipse.ui.internal.Workbench.runUI(Workbench.java:1334)\n\tat org.eclipse.ui.internal.Workbench.createAndRunWorkbench(Workbench.java:253)\n\tat org.eclipse.ui.PlatformUI.createAndRunWorkbench(PlatformUI.java:141)\n\tat org.eclipse.ui.internal.ide.IDEApplication.run(IDEApplication.java:97)\n\tat\norg.eclipse.core.internal.runtime.PlatformActivator$1.run(PlatformActivator.java:307)\n\tat org.eclipse.core.runtime.adaptor.EclipseStarter.run(EclipseStarter.java:256)\n\tat org.eclipse.core.runtime.adaptor.EclipseStarter.run(EclipseStarter.java:127)\n\tat sun.reflect.NativeMethodAccessorImpl.invoke0(Native Method)\n\tat sun.reflect.NativeMethodAccessorImpl.invoke(NativeMethodAccessorImpl.java:39)\n\tat\nsun.reflect.DelegatingMethodAccessorImpl.invoke(DelegatingMethodAccessorImpl.java:25)\n\tat java.lang.reflect.Method.invoke(Method.java:324)\n\tat org.eclipse.core.launcher.Main.basicRun(Main.java:185)\n\tat org.eclipse.core.launcher.Main.run(Main.java:638)\n\tat org.eclipse.core.launcher.Main.main(Main.java:622)\n",
    "Fixed in \u003e I200405251200.",
    "*** Bug 64009 has been marked as a duplicate of this bug. ***",
    "verifying...",
    "verified in code that catchupWithProjectionAnnotationModel does not throw IAEs\nany longer. Other methods may still throw IAEs.\n\nMarking as verfied as there is no reproducible case and we haven\u0027t see these\nexceptions since when it was fixed."
  ],
  "commentCreationDates": [
    "2004-05-24T13:02:42+02:00",
    "2004-05-24T13:09:02+02:00",
    "2004-05-24T14:34:23+02:00",
    "2004-05-24T16:46:12+02:00",
    "2004-05-25T15:35:03+02:00",
    "2004-05-26T10:10:41+02:00",
    "2004-06-11T19:28:24+02:00",
    "2004-06-11T19:37:37+02:00"
  ],
  "traces": [
    {
      "exceptionType": "org.eclipse.swt.SWTException",
      "message": "Failed to execute runnable (java.lang.IllegalArgum entException)",
      "elements": [
        {
          "method": "org.eclipse.swt.SWT.error",
          "source": "SWT.java:2689"
        },
        {
          "method": "org.eclipse.swt.SWT.error",
          "source": "SWT.java:2614"
        },
        {
          "method": "org.eclipse.swt.widgets.Synchronizer.runAsyncMessages",
          "source": "Synchronizer.ja va:109"
        },
        {
          "method": "org.eclipse.swt.widgets.Display.runAsyncMessages",
          "source": "Display.java:2693"
        },
        {
          "method": "org.eclipse.swt.widgets.Display.readAndDispatch",
          "source": "Display.java:2385"
        },
        {
          "method": "org.eclipse.ui.internal.Workbench.runEventLoop",
          "source": "Workbench.java:1363"
        },
        {
          "method": "org.eclipse.ui.internal.Workbench.runUI",
          "source": "Workbench.java:1334"
        },
        {
          "method": "org.eclipse.ui.internal.Workbench.createAndRunWorkbench",
          "source": "Workbench.jav a:253"
        },
        {
          "method": "org.eclipse.ui.PlatformUI.createAndRunWorkbench",
          "source": "PlatformUI.java:141"
        },
        {
          "method": "org.eclipse.ui.internal.ide.IDEApplication.run",
          "source": "IDEApplication.java:97 "
        },
        {
          "method": "org.eclipse.core.internal.runtime.PlatformActivator$1.run",
          "source": "PlatformAct ivator.java:307"
        },
        {
          "method": "org.eclipse.core.runtime.adaptor.EclipseStarter.run",
          "source": "EclipseStarter.ja va:256"
        },
        {
          "method": "org.eclipse.core.runtime.adaptor.EclipseStarter.run",
          "source": "EclipseStarter.ja va:127"
        },
        {
          "method": "sun.reflect.NativeMethodAccessorImpl.invoke0",
          "source": "Native Method"
        },
        {
          "method": "sun.reflect.NativeMethodAccessorImpl.invoke",
          "source": "NativeMethodAccessorImpl. java:39"
        },
        {
          "method": "sun.reflect.DelegatingMethodAccessorImpl.invoke",
          "source": "DelegatingMethodAcces sorImpl.java:25"
        },
        {
          "method": "java.lang.reflect.Method.invoke",
          "source": "Method.java:324"
        },
        {
          "method": "org.eclipse.core.launcher.Main.basicRun",
          "source": "Main.java:185"
        },
        {
          "method": "org.eclipse.core.launcher.Main.run",
          "source": "Main.java:638"
        },
        {
          "method": "org.eclipse.core.launcher.Main.main",
          "source": "Main.java:622"
        }
      ],
      "number": 0,
      "commentIndex": 0,
      "bugId": "63652",
      "date": "2004-05-24T13:02:42+02:00",
      "product": "Platform",
      "component": "Text",
      "severity": "normal"
    },
    {
      "exceptionType": "java.lang.IllegalArgumentException",
      "elements": [
        {
          "method": "org.eclipse.jface.text.source.projection.ProjectionViewer.catchupWithProjectionAnnotationModel",
          "source": "ProjectionViewer.java:769"
        },
        {
          "method": "org.eclipse.jface.text.source.projection.ProjectionViewer.access$7",
          "source": "Pr ojectionViewer.java:731"
        },
        {
          "method": "org.eclipse.jface.text.source.projection.ProjectionViewer$1.run",
          "source": "Proje ctionViewer.java:714"
        },
        {
          "method": "org.eclipse.swt.widgets.RunnableLock.run",
          "source": "RunnableLock.java:35"
        },
        {
          "method": "org.eclipse.swt.widgets.Synchronizer.runAsyncMessages",
          "source": "Synchronizer.ja va:106"
        },
        {
          "method": "org.eclipse.swt.widgets.Display.runAsyncMessages",
          "source": "Display.java:2693"
        },
        {
          "method": "org.eclipse.swt.widgets.Display.readAndDispatch",
          "source": "Display.java:2385"
        },
        {
          "method": "org.eclipse.ui.internal.Workbench.runEventLoop",
          "source": "Workbench.java:1363"
        },
        {
          "method": "org.eclipse.ui.internal.Workbench.runUI",
          "source": "Workbench.java:1334"
        },
        {
          "method": "org.eclipse.ui.internal.Workbench.createAndRunWorkbench",
          "source": "Workbench.jav a:253"
        },
        {
          "method": "org.eclipse.ui.PlatformUI.createAndRunWorkbench",
          "source": "PlatformUI.java:141"
        },
        {
          "method": "org.eclipse.ui.internal.ide.IDEApplication.run",
          "source": "IDEApplication.java:97 "
        },
        {
          "method": "org.eclipse.core.internal.runtime.PlatformActivator$1.run",
          "source": "PlatformAct ivator.java:307"
        },
        {
          "method": "org.eclipse.core.runtime.adaptor.EclipseStarter.run",
          "source": "EclipseStarter.ja va:256"
        },
        {
          "method": "org.eclipse.core.runtime.adaptor.EclipseStarter.run",
          "source": "EclipseStarter.ja va:127"
        },
        {
          "method": "sun.reflect.NativeMethodAccessorImpl.invoke0",
          "source": "Native Method"
        },
        {
          "method": "sun.reflect.NativeMethodAccessorImpl.invoke",
          "source": "NativeMethodAccessorImpl. java:39"
        },
        {
          "method": "sun.reflect.DelegatingMethodAccessorImpl.invoke",
          "source": "DelegatingMethodAcces sorImpl.java:25"
        },
        {
          "method": "java.lang.reflect.Method.invoke",
          "source": "Method.java:324"
        },
        {
          "method": "org.eclipse.core.launcher.Main.basicRun",
          "source": "Main.java:185"
        },
        {
          "method": "org.eclipse.core.launcher.Main.run",
          "source": "Main.java:638"
        },
        {
          "method": "org.eclipse.core.launcher.Main.main",
          "source": "Main.java:622"
        }
      ],
      "number": 1,
      "commentIndex": 0,
      "bugId": "63652",
      "date": "2004-05-24T13:02:42+02:00",
      "product": "Platform",
      "component": "Text",
      "severity": "normal"
    },
    {
      "exceptionType": "org.eclipse.swt.SWTException",
      "message": "Failed to execute runnable (java.lang.IllegalArgumentException)",
      "elements": [
        {
          "method": "org.eclipse.swt.SWT.error",
          "source": "SWT.java:2689"
        },
        {
          "method": "org.eclipse.swt.SWT.error",
          "source": "SWT.java:2614"
        },
        {
          "method": "org.eclipse.swt.widgets.Synchronizer.runAsyncMessages",
          "source": "Synchronizer.java:109"
        },
        {
          "method": "org.eclipse.swt.widgets.Display.runAsyncMessages",
          "source": "Display.java:2693"
        },
        {
          "method": "org.eclipse.swt.widgets.Display.readAndDispatch",
          "source": "Display.java:2385"
        },
        {
          "method": "org.eclipse.ui.internal.Workbench.runEventLoop",
          "source": "Workbench.java:1363"
        },
        {
          "method": "org.eclipse.ui.internal.Workbench.runUI",
          "source": "Workbench.java:1334"
        },
        {
          "method": "org.eclipse.ui.internal.Workbench.createAndRunWorkbench",
          "source": "Workbench.java:253"
        },
        {
          "method": "org.eclipse.ui.PlatformUI.createAndRunWorkbench",
          "source": "PlatformUI.java:141"
        },
        {
          "method": "org.eclipse.ui.internal.ide.IDEApplication.run",
          "source": "IDEApplication.java:97"
        },
        {
          "method": "org.eclipse.core.internal.runtime.PlatformActivator$1.run",
          "source": "PlatformActivator.java:307"
        },
        {
          "method": "org.eclipse.core.runtime.adaptor.EclipseStarter.run",
          "source": "EclipseStarter.java:256"
        },
        {
          "method": "org.eclipse.core.runtime.adaptor.EclipseStarter.run",
          "source": "EclipseStarter.java:127"
        },
        {
          "method": "sun.reflect.NativeMethodAccessorImpl.invoke0",
          "source": "Native Method"
        },
        {
          "method": "sun.reflect.NativeMethodAccessorImpl.invoke",
          "source": "NativeMethodAccessorImpl.java:39"
        },
        {
          "method": "sun.reflect.DelegatingMethodAccessorImpl.invoke",
          "source": "DelegatingMethodAccessorImpl.java:25"
        },
        {
          "method": "java.lang.reflect.Method.invoke",
          "source": "Method.java:324"
        },
        {
          "method": "org.eclipse.core.launcher.Main.basicRun",
          "source": "Main.java:185"
        },
        {
          "method": "org.eclipse.core.launcher.Main.run",
          "source": "Main.java:638"
        },
        {
          "method": "org.eclipse.core.launcher.Main.main",
          "source": "Main.java:622"
        }
      ],
      "number": 2,
      "commentIndex": 3,
      "bugId": "63652",
      "date": "2004-05-24T16:46:12+02:00",
      "product": "Platform",
      "component": "Text",
      "severity": "normal"
    },
    {
      "exceptionType": "java.lang.IllegalArgumentException",
      "elements": [
        {
          "method": "org.eclipse.jface.text.source.projection.ProjectionViewer.catchupWithProjectionAnnotationModel",
          "source": "ProjectionViewer.java:769"
        },
        {
          "method": "org.eclipse.jface.text.source.projection.ProjectionViewer.access$7",
          "source": "ProjectionViewer.java:731"
        },
        {
          "method": "org.eclipse.jface.text.source.projection.ProjectionViewer$1.run",
          "source": "ProjectionViewer.java:714"
        },
        {
          "method": "org.eclipse.swt.widgets.RunnableLock.run",
          "source": "RunnableLock.java:35"
        },
        {
          "method": "org.eclipse.swt.widgets.Synchronizer.runAsyncMessages",
          "source": "Synchronizer.java:106"
        },
        {
          "method": "org.eclipse.swt.widgets.Display.runAsyncMessages",
          "source": "Display.java:2693"
        },
        {
          "method": "org.eclipse.swt.widgets.Display.readAndDispatch",
          "source": "Display.java:2385"
        },
        {
          "method": "org.eclipse.ui.internal.Workbench.runEventLoop",
          "source": "Workbench.java:1363"
        },
        {
          "method": "org.eclipse.ui.internal.Workbench.runUI",
          "source": "Workbench.java:1334"
        },
        {
          "method": "org.eclipse.ui.internal.Workbench.createAndRunWorkbench",
          "source": "Workbench.java:253"
        },
        {
          "method": "org.eclipse.ui.PlatformUI.createAndRunWorkbench",
          "source": "PlatformUI.java:141"
        },
        {
          "method": "org.eclipse.ui.internal.ide.IDEApplication.run",
          "source": "IDEApplication.java:97"
        },
        {
          "method": "org.eclipse.core.internal.runtime.PlatformActivator$1.run",
          "source": "PlatformActivator.java:307"
        },
        {
          "method": "org.eclipse.core.runtime.adaptor.EclipseStarter.run",
          "source": "EclipseStarter.java:256"
        },
        {
          "method": "org.eclipse.core.runtime.adaptor.EclipseStarter.run",
          "source": "EclipseStarter.java:127"
        },
        {
          "method": "sun.reflect.NativeMethodAccessorImpl.invoke0",
          "source": "Native Method"
        },
        {
          "method": "sun.reflect.NativeMethodAccessorImpl.invoke",
          "source": "NativeMethodAccessorImpl.java:39"
        },
        {
          "method": "sun.reflect.DelegatingMethodAccessorImpl.invoke",
          "source": "DelegatingMethodAccessorImpl.java:25"
        },
        {
          "method": "java.lang.reflect.Method.invoke",
          "source": "Method.java:324"
        },
        {
          "method": "org.eclipse.core.launcher.Main.basicRun",
          "source": "Main.java:185"
        },
        {
          "method": "org.eclipse.core.launcher.Main.run",
          "source": "Main.java:638"
        },
        {
          "method": "org.eclipse.core.launcher.Main.main",
          "source": "Main.java:622"
        }
      ],
      "number": 3,
      "commentIndex": 3,
      "bugId": "63652",
      "date": "2004-05-24T16:46:12+02:00",
      "product": "Platform",
      "component": "Text",
      "severity": "normal"
    }
  ],
  "groupId": "63652",
  "bugId": "63652",
  "date": "2004-05-24T13:02:42+02:00",
  "product": "Platform",
  "component": "Text",
  "severity": "normal"
}