{
  "comments": [
    "Build M9\n\nTrying to perform a clean rebuild of the entire (source) self-hosting workspace \n(autobuild off), I observed that the build dialog refused to close and transfer \nto build progress. Found the following in the log after several attempts to \nclose it (it finally closed after hammering the close button a dozen times).\n\n!ENTRY org.eclipse.ui 4 4 May 25, 2004 16:34:30.411\n!MESSAGE Unhandled event loop exception\nUnhandled event loop exception\nReason:\n!ENTRY org.eclipse.ui 4 0 May 25, 2004 16:34:30.411\n!MESSAGE Widget is disposed\n!STACK 0\norg.eclipse.swt.SWTException: Widget is disposed\n        at org.eclipse.swt.SWT.error(SWT.java:2689)\n        at org.eclipse.swt.SWT.error(SWT.java:2614)\n        at org.eclipse.swt.SWT.error(SWT.java:2585)\n        at org.eclipse.swt.widgets.Widget.error(Widget.java:381)\n        at org.eclipse.swt.widgets.Widget.checkWidget(Widget.java:283)\n        at org.eclipse.swt.widgets.Button.getSelection(Button.java:311)\n        at org.eclipse.ui.internal.ide.dialogs.CleanDialog.buttonPressed\n(CleanDialog.java:99)\n        at org.eclipse.jface.dialogs.Dialog$2.widgetSelected(Dialog.java:505)\n        at org.eclipse.swt.widgets.TypedListener.handleEvent\n(TypedListener.java:89)\n        at org.eclipse.swt.widgets.EventTable.sendEvent(EventTable.java:82)\n        at org.eclipse.swt.widgets.Widget.sendEvent(Widget.java:796)\n        at org.eclipse.swt.widgets.Display.runDeferredEvents(Display.java:2716)\n        at org.eclipse.swt.widgets.Display.readAndDispatch(Display.java:2382)\n        at org.eclipse.jface.operation.ModalContext$ModalContextThread.block\n(ModalContext.java:136)\n        at org.eclipse.jface.operation.ModalContext.run(ModalContext.java:261)\n        at org.eclipse.jface.dialogs.ProgressMonitorDialog.run\n(ProgressMonitorDialog.java:397)\n        at org.eclipse.ui.internal.progress.ProgressMonitorJobsDialog.run\n(ProgressMonitorJobsDialog.java:238)\n        at org.eclipse.ui.internal.progress.ProgressManager$3.run\n(ProgressManager.java:778)\n        at org.eclipse.swt.custom.BusyIndicator.showWhile(BusyIndicator.java:69)\n        at org.eclipse.ui.internal.progress.ProgressManager.busyCursorWhile\n(ProgressManager.java:812)\n        at org.eclipse.ui.internal.progress.ProgressManager.busyCursorWhile\n(ProgressManager.java:787)\n        at org.eclipse.ui.internal.ide.dialogs.CleanDialog.buttonPressed\n(CleanDialog.java:92)\n        at org.eclipse.jface.dialogs.Dialog$2.widgetSelected(Dialog.java:505)\n        at org.eclipse.swt.widgets.TypedListener.handleEvent\n(TypedListener.java:89)\n        at org.eclipse.swt.widgets.EventTable.sendEvent(EventTable.java:82)\n        at org.eclipse.swt.widgets.Widget.sendEvent(Widget.java:796)\n        at org.eclipse.swt.widgets.Display.runDeferredEvents(Display.java:2716)\n        at org.eclipse.swt.widgets.Display.readAndDispatch(Display.java:2382)\n        at org.eclipse.jface.operation.ModalContext$ModalContextThread.block\n(ModalContext.java:136)\n        at org.eclipse.jface.operation.ModalContext.run(ModalContext.java:261)\n        at org.eclipse.jface.dialogs.ProgressMonitorDialog.run\n(ProgressMonitorDialog.java:397)\n        at org.eclipse.ui.internal.progress.ProgressMonitorJobsDialog.run\n(ProgressMonitorJobsDialog.java:238)\n        at org.eclipse.ui.internal.progress.ProgressManager$3.run\n(ProgressManager.java:778)\n        at org.eclipse.swt.custom.BusyIndicator.showWhile(BusyIndicator.java:69)\n        at org.eclipse.ui.internal.progress.ProgressManager.busyCursorWhile\n(ProgressManager.java:812)\n        at org.eclipse.ui.internal.progress.ProgressManager.busyCursorWhile\n(ProgressManager.java:787)\n        at org.eclipse.ui.internal.ide.dialogs.CleanDialog.buttonPressed\n(CleanDialog.java:92)\n        at org.eclipse.jface.dialogs.Dialog$2.widgetSelected(Dialog.java:505)\n        at org.eclipse.swt.widgets.TypedListener.handleEvent\n(TypedListener.java:89)\n        at org.eclipse.swt.widgets.EventTable.sendEvent(EventTable.java:82)\n        at org.eclipse.swt.widgets.Widget.sendEvent(Widget.java:796)\n        at org.eclipse.swt.widgets.Display.runDeferredEvents(Display.java:2716)\n        at org.eclipse.swt.widgets.Display.readAndDispatch(Display.java:2382)\n        at org.eclipse.jface.operation.ModalContext$ModalContextThread.block\n(ModalContext.java:136)\n        at org.eclipse.jface.operation.ModalContext.run(ModalContext.java:261)\n        at org.eclipse.jface.dialogs.ProgressMonitorDialog.run\n(ProgressMonitorDialog.java:397)\n        at org.eclipse.ui.internal.progress.ProgressMonitorJobsDialog.run\n(ProgressMonitorJobsDialog.java:238)\n        at org.eclipse.ui.internal.progress.ProgressManager$3.run\n(ProgressManager.java:778)\n        at org.eclipse.swt.custom.BusyIndicator.showWhile(BusyIndicator.java:69)\n        at org.eclipse.ui.internal.progress.ProgressManager.busyCursorWhile\n(ProgressManager.java:812)\n        at org.eclipse.ui.internal.progress.ProgressManager.busyCursorWhile\n(ProgressManager.java:787)\n        at org.eclipse.ui.internal.ide.dialogs.CleanDialog.buttonPressed\n(CleanDialog.java:92)\n        at org.eclipse.jface.dialogs.Dialog$2.widgetSelected(Dialog.java:505)\n        at org.eclipse.swt.widgets.TypedListener.handleEvent\n(TypedListener.java:89)\n        at org.eclipse.swt.widgets.EventTable.sendEvent(EventTable.java:82)\n        at org.eclipse.swt.widgets.Widget.sendEvent(Widget.java:796)\n        at org.eclipse.swt.widgets.Display.runDeferredEvents(Display.java:2716)\n        at org.eclipse.swt.widgets.Display.readAndDispatch(Display.java:2382)\n        at org.eclipse.jface.operation.ModalContext$ModalContextThread.block\n(ModalContext.java:136)\n        at org.eclipse.jface.operation.ModalContext.run(ModalContext.java:261)\n        at org.eclipse.jface.dialogs.ProgressMonitorDialog.run\n(ProgressMonitorDialog.java:397)\n        at org.eclipse.ui.internal.progress.ProgressMonitorJobsDialog.run\n(ProgressMonitorJobsDialog.java:238)\n        at org.eclipse.ui.internal.progress.ProgressManager$3.run\n(ProgressManager.java:778)\n        at org.eclipse.swt.custom.BusyIndicator.showWhile(BusyIndicator.java:69)\n        at org.eclipse.ui.internal.progress.ProgressManager.busyCursorWhile\n(ProgressManager.java:812)\n        at org.eclipse.ui.internal.progress.ProgressManager.busyCursorWhile\n(ProgressManager.java:787)\n        at org.eclipse.ui.internal.ide.dialogs.CleanDialog.buttonPressed\n(CleanDialog.java:92)\n        at org.eclipse.jface.dialogs.Dialog$2.widgetSelected(Dialog.java:505)\n        at org.eclipse.swt.widgets.TypedListener.handleEvent\n(TypedListener.java:89)\n        at org.eclipse.swt.widgets.EventTable.sendEvent(EventTable.java:82)\n        at org.eclipse.swt.widgets.Widget.sendEvent(Widget.java:796)\n        at org.eclipse.swt.widgets.Display.runDeferredEvents(Display.java:2716)\n        at org.eclipse.swt.widgets.Display.readAndDispatch(Display.java:2382)\n        at org.eclipse.jface.operation.ModalContext$ModalContextThread.block\n(ModalContext.java:136)\n        at org.eclipse.jface.operation.ModalContext.run(ModalContext.java:261)\n        at org.eclipse.jface.dialogs.ProgressMonitorDialog.run\n(ProgressMonitorDialog.java:397)\n        at org.eclipse.ui.internal.progress.ProgressMonitorJobsDialog.run\n(ProgressMonitorJobsDialog.java:238)\n        at org.eclipse.ui.internal.progress.ProgressManager$3.run\n(ProgressManager.java:778)\n        at org.eclipse.swt.custom.BusyIndicator.showWhile(BusyIndicator.java:69)\n        at org.eclipse.ui.internal.progress.ProgressManager.busyCursorWhile\n(ProgressManager.java:812)\n        at org.eclipse.ui.internal.progress.ProgressManager.busyCursorWhile\n(ProgressManager.java:787)\n        at org.eclipse.ui.internal.ide.dialogs.CleanDialog.buttonPressed\n(CleanDialog.java:92)\n        at org.eclipse.jface.dialogs.Dialog$2.widgetSelected(Dialog.java:505)\n        at org.eclipse.swt.widgets.TypedListener.handleEvent\n(TypedListener.java:89)\n        at org.eclipse.swt.widgets.EventTable.sendEvent(EventTable.java:82)\n        at org.eclipse.swt.widgets.Widget.sendEvent(Widget.java:796)\n        at org.eclipse.swt.widgets.Display.runDeferredEvents(Display.java:2716)\n        at org.eclipse.swt.widgets.Display.readAndDispatch(Display.java:2382)\n        at org.eclipse.jface.window.Window.runEventLoop(Window.java:668)\n        at org.eclipse.jface.window.Window.open(Window.java:648)\n        at org.eclipse.ui.internal.ide.actions.BuildCleanAction.run\n(BuildCleanAction.java:56)\n        at org.eclipse.jface.action.Action.runWithEvent(Action.java:881)\n        at org.eclipse.jface.action.ActionContributionItem.handleWidgetSelection\n(ActionContributionItem.java:899)\n        at org.eclipse.jface.action.ActionContributionItem.access$2\n(ActionContributionItem.java:850)\n        at org.eclipse.jface.action.ActionContributionItem$7.handleEvent\n(ActionContributionItem.java:769)\n        at org.eclipse.swt.widgets.EventTable.sendEvent(EventTable.java:82)\n        at org.eclipse.swt.widgets.Widget.sendEvent(Widget.java:796)\n        at org.eclipse.swt.widgets.Display.runDeferredEvents(Display.java:2716)\n        at org.eclipse.swt.widgets.Display.readAndDispatch(Display.java:2382)\n        at org.eclipse.ui.internal.Workbench.runEventLoop(Workbench.java:1363)\n        at org.eclipse.ui.internal.Workbench.runUI(Workbench.java:1334)\n        at org.eclipse.ui.internal.Workbench.createAndRunWorkbench\n(Workbench.java:253)\n        at org.eclipse.ui.PlatformUI.createAndRunWorkbench(PlatformUI.java:141)\n        at org.eclipse.ui.internal.ide.IDEApplication.run\n(IDEApplication.java:97)\n        at org.eclipse.core.internal.runtime.PlatformActivator$1.run\n(PlatformActivator.java:307)\n        at org.eclipse.core.runtime.adaptor.EclipseStarter.run\n(EclipseStarter.java:256)\n        at org.eclipse.core.runtime.adaptor.EclipseStarter.run\n(EclipseStarter.java:127)\n        at sun.reflect.NativeMethodAccessorImpl.invoke0(Native Method)\n        at sun.reflect.NativeMethodAccessorImpl.invoke\n(NativeMethodAccessorImpl.java:39)\n        at sun.reflect.DelegatingMethodAccessorImpl.invoke\n(DelegatingMethodAccessorImpl.java:25)\n        at java.lang.reflect.Method.invoke(Method.java:324)\n        at org.eclipse.core.launcher.Main.basicRun(Main.java:185)\n        at org.eclipse.core.launcher.Main.run(Main.java:638)\n        at org.eclipse.core.launcher.Main.main(Main.java:622)\nWidget is disposed",
    "Interestingly when the log entry got dumped in console (-consoleLog), an error \ndialog opened, reading something cryptic like: \"error open blocked dialog\" (but \nI did not notice it at this stage). The full build was running though in \nparallel, since in the meantime the build progress had appeared and I had sent \nit to the background (leaving the error dialog open).\n\nOnce build finished, I noticed the error dialog and close it. Another full \nbuild got triggered !?!",
    "busyCursorWhile was not locking out shells other than windows. Fixed in builds \n\u003e20040526",
    "*** Bug 63215 has been marked as a duplicate of this bug. ***",
    "Verified in 20040529"
  ],
  "commentCreationDates": [
    "2004-05-25T16:52:40+02:00",
    "2004-05-25T16:56:59+02:00",
    "2004-05-25T22:17:19+02:00",
    "2004-05-25T23:20:49+02:00",
    "2004-05-31T16:58:08+02:00"
  ],
  "traces": [
    {
      "exceptionType": "org.eclipse.swt.SWTException",
      "message": "Widget is disposed",
      "elements": [
        {
          "method": "org.eclipse.swt.SWT.error",
          "source": "SWT.java:2689"
        },
        {
          "method": "org.eclipse.swt.SWT.error",
          "source": "SWT.java:2614"
        },
        {
          "method": "org.eclipse.swt.SWT.error",
          "source": "SWT.java:2585"
        },
        {
          "method": "org.eclipse.swt.widgets.Widget.error",
          "source": "Widget.java:381"
        },
        {
          "method": "org.eclipse.swt.widgets.Widget.checkWidget",
          "source": "Widget.java:283"
        },
        {
          "method": "org.eclipse.swt.widgets.Button.getSelection",
          "source": "Button.java:311"
        },
        {
          "method": "org.eclipse.ui.internal.ide.dialogs.CleanDialog.buttonPressed",
          "source": "CleanDialog.java:99"
        },
        {
          "method": "org.eclipse.jface.dialogs.Dialog$2.widgetSelected",
          "source": "Dialog.java:505"
        },
        {
          "method": "org.eclipse.swt.widgets.TypedListener.handleEvent",
          "source": "TypedListener.java:89"
        },
        {
          "method": "org.eclipse.swt.widgets.EventTable.sendEvent",
          "source": "EventTable.java:82"
        },
        {
          "method": "org.eclipse.swt.widgets.Widget.sendEvent",
          "source": "Widget.java:796"
        },
        {
          "method": "org.eclipse.swt.widgets.Display.runDeferredEvents",
          "source": "Display.java:2716"
        },
        {
          "method": "org.eclipse.swt.widgets.Display.readAndDispatch",
          "source": "Display.java:2382"
        },
        {
          "method": "org.eclipse.jface.operation.ModalContext$ModalContextThread.block",
          "source": "ModalContext.java:136"
        },
        {
          "method": "org.eclipse.jface.operation.ModalContext.run",
          "source": "ModalContext.java:261"
        },
        {
          "method": "org.eclipse.jface.dialogs.ProgressMonitorDialog.run",
          "source": "ProgressMonitorDialog.java:397"
        },
        {
          "method": "org.eclipse.ui.internal.progress.ProgressMonitorJobsDialog.run",
          "source": "ProgressMonitorJobsDialog.java:238"
        },
        {
          "method": "org.eclipse.ui.internal.progress.ProgressManager$3.run",
          "source": "ProgressManager.java:778"
        },
        {
          "method": "org.eclipse.swt.custom.BusyIndicator.showWhile",
          "source": "BusyIndicator.java:69"
        },
        {
          "method": "org.eclipse.ui.internal.progress.ProgressManager.busyCursorWhile",
          "source": "ProgressManager.java:812"
        },
        {
          "method": "org.eclipse.ui.internal.progress.ProgressManager.busyCursorWhile",
          "source": "ProgressManager.java:787"
        },
        {
          "method": "org.eclipse.ui.internal.ide.dialogs.CleanDialog.buttonPressed",
          "source": "CleanDialog.java:92"
        },
        {
          "method": "org.eclipse.jface.dialogs.Dialog$2.widgetSelected",
          "source": "Dialog.java:505"
        },
        {
          "method": "org.eclipse.swt.widgets.TypedListener.handleEvent",
          "source": "TypedListener.java:89"
        },
        {
          "method": "org.eclipse.swt.widgets.EventTable.sendEvent",
          "source": "EventTable.java:82"
        },
        {
          "method": "org.eclipse.swt.widgets.Widget.sendEvent",
          "source": "Widget.java:796"
        },
        {
          "method": "org.eclipse.swt.widgets.Display.runDeferredEvents",
          "source": "Display.java:2716"
        },
        {
          "method": "org.eclipse.swt.widgets.Display.readAndDispatch",
          "source": "Display.java:2382"
        },
        {
          "method": "org.eclipse.jface.operation.ModalContext$ModalContextThread.block",
          "source": "ModalContext.java:136"
        },
        {
          "method": "org.eclipse.jface.operation.ModalContext.run",
          "source": "ModalContext.java:261"
        },
        {
          "method": "org.eclipse.jface.dialogs.ProgressMonitorDialog.run",
          "source": "ProgressMonitorDialog.java:397"
        },
        {
          "method": "org.eclipse.ui.internal.progress.ProgressMonitorJobsDialog.run",
          "source": "ProgressMonitorJobsDialog.java:238"
        },
        {
          "method": "org.eclipse.ui.internal.progress.ProgressManager$3.run",
          "source": "ProgressManager.java:778"
        },
        {
          "method": "org.eclipse.swt.custom.BusyIndicator.showWhile",
          "source": "BusyIndicator.java:69"
        },
        {
          "method": "org.eclipse.ui.internal.progress.ProgressManager.busyCursorWhile",
          "source": "ProgressManager.java:812"
        },
        {
          "method": "org.eclipse.ui.internal.progress.ProgressManager.busyCursorWhile",
          "source": "ProgressManager.java:787"
        },
        {
          "method": "org.eclipse.ui.internal.ide.dialogs.CleanDialog.buttonPressed",
          "source": "CleanDialog.java:92"
        },
        {
          "method": "org.eclipse.jface.dialogs.Dialog$2.widgetSelected",
          "source": "Dialog.java:505"
        },
        {
          "method": "org.eclipse.swt.widgets.TypedListener.handleEvent",
          "source": "TypedListener.java:89"
        },
        {
          "method": "org.eclipse.swt.widgets.EventTable.sendEvent",
          "source": "EventTable.java:82"
        },
        {
          "method": "org.eclipse.swt.widgets.Widget.sendEvent",
          "source": "Widget.java:796"
        },
        {
          "method": "org.eclipse.swt.widgets.Display.runDeferredEvents",
          "source": "Display.java:2716"
        },
        {
          "method": "org.eclipse.swt.widgets.Display.readAndDispatch",
          "source": "Display.java:2382"
        },
        {
          "method": "org.eclipse.jface.operation.ModalContext$ModalContextThread.block",
          "source": "ModalContext.java:136"
        },
        {
          "method": "org.eclipse.jface.operation.ModalContext.run",
          "source": "ModalContext.java:261"
        },
        {
          "method": "org.eclipse.jface.dialogs.ProgressMonitorDialog.run",
          "source": "ProgressMonitorDialog.java:397"
        },
        {
          "method": "org.eclipse.ui.internal.progress.ProgressMonitorJobsDialog.run",
          "source": "ProgressMonitorJobsDialog.java:238"
        },
        {
          "method": "org.eclipse.ui.internal.progress.ProgressManager$3.run",
          "source": "ProgressManager.java:778"
        },
        {
          "method": "org.eclipse.swt.custom.BusyIndicator.showWhile",
          "source": "BusyIndicator.java:69"
        },
        {
          "method": "org.eclipse.ui.internal.progress.ProgressManager.busyCursorWhile",
          "source": "ProgressManager.java:812"
        },
        {
          "method": "org.eclipse.ui.internal.progress.ProgressManager.busyCursorWhile",
          "source": "ProgressManager.java:787"
        },
        {
          "method": "org.eclipse.ui.internal.ide.dialogs.CleanDialog.buttonPressed",
          "source": "CleanDialog.java:92"
        },
        {
          "method": "org.eclipse.jface.dialogs.Dialog$2.widgetSelected",
          "source": "Dialog.java:505"
        },
        {
          "method": "org.eclipse.swt.widgets.TypedListener.handleEvent",
          "source": "TypedListener.java:89"
        },
        {
          "method": "org.eclipse.swt.widgets.EventTable.sendEvent",
          "source": "EventTable.java:82"
        },
        {
          "method": "org.eclipse.swt.widgets.Widget.sendEvent",
          "source": "Widget.java:796"
        },
        {
          "method": "org.eclipse.swt.widgets.Display.runDeferredEvents",
          "source": "Display.java:2716"
        },
        {
          "method": "org.eclipse.swt.widgets.Display.readAndDispatch",
          "source": "Display.java:2382"
        },
        {
          "method": "org.eclipse.jface.operation.ModalContext$ModalContextThread.block",
          "source": "ModalContext.java:136"
        },
        {
          "method": "org.eclipse.jface.operation.ModalContext.run",
          "source": "ModalContext.java:261"
        },
        {
          "method": "org.eclipse.jface.dialogs.ProgressMonitorDialog.run",
          "source": "ProgressMonitorDialog.java:397"
        },
        {
          "method": "org.eclipse.ui.internal.progress.ProgressMonitorJobsDialog.run",
          "source": "ProgressMonitorJobsDialog.java:238"
        },
        {
          "method": "org.eclipse.ui.internal.progress.ProgressManager$3.run",
          "source": "ProgressManager.java:778"
        },
        {
          "method": "org.eclipse.swt.custom.BusyIndicator.showWhile",
          "source": "BusyIndicator.java:69"
        },
        {
          "method": "org.eclipse.ui.internal.progress.ProgressManager.busyCursorWhile",
          "source": "ProgressManager.java:812"
        },
        {
          "method": "org.eclipse.ui.internal.progress.ProgressManager.busyCursorWhile",
          "source": "ProgressManager.java:787"
        },
        {
          "method": "org.eclipse.ui.internal.ide.dialogs.CleanDialog.buttonPressed",
          "source": "CleanDialog.java:92"
        },
        {
          "method": "org.eclipse.jface.dialogs.Dialog$2.widgetSelected",
          "source": "Dialog.java:505"
        },
        {
          "method": "org.eclipse.swt.widgets.TypedListener.handleEvent",
          "source": "TypedListener.java:89"
        },
        {
          "method": "org.eclipse.swt.widgets.EventTable.sendEvent",
          "source": "EventTable.java:82"
        },
        {
          "method": "org.eclipse.swt.widgets.Widget.sendEvent",
          "source": "Widget.java:796"
        },
        {
          "method": "org.eclipse.swt.widgets.Display.runDeferredEvents",
          "source": "Display.java:2716"
        },
        {
          "method": "org.eclipse.swt.widgets.Display.readAndDispatch",
          "source": "Display.java:2382"
        },
        {
          "method": "org.eclipse.jface.operation.ModalContext$ModalContextThread.block",
          "source": "ModalContext.java:136"
        },
        {
          "method": "org.eclipse.jface.operation.ModalContext.run",
          "source": "ModalContext.java:261"
        },
        {
          "method": "org.eclipse.jface.dialogs.ProgressMonitorDialog.run",
          "source": "ProgressMonitorDialog.java:397"
        },
        {
          "method": "org.eclipse.ui.internal.progress.ProgressMonitorJobsDialog.run",
          "source": "ProgressMonitorJobsDialog.java:238"
        },
        {
          "method": "org.eclipse.ui.internal.progress.ProgressManager$3.run",
          "source": "ProgressManager.java:778"
        },
        {
          "method": "org.eclipse.swt.custom.BusyIndicator.showWhile",
          "source": "BusyIndicator.java:69"
        },
        {
          "method": "org.eclipse.ui.internal.progress.ProgressManager.busyCursorWhile",
          "source": "ProgressManager.java:812"
        },
        {
          "method": "org.eclipse.ui.internal.progress.ProgressManager.busyCursorWhile",
          "source": "ProgressManager.java:787"
        },
        {
          "method": "org.eclipse.ui.internal.ide.dialogs.CleanDialog.buttonPressed",
          "source": "CleanDialog.java:92"
        },
        {
          "method": "org.eclipse.jface.dialogs.Dialog$2.widgetSelected",
          "source": "Dialog.java:505"
        },
        {
          "method": "org.eclipse.swt.widgets.TypedListener.handleEvent",
          "source": "TypedListener.java:89"
        },
        {
          "method": "org.eclipse.swt.widgets.EventTable.sendEvent",
          "source": "EventTable.java:82"
        },
        {
          "method": "org.eclipse.swt.widgets.Widget.sendEvent",
          "source": "Widget.java:796"
        },
        {
          "method": "org.eclipse.swt.widgets.Display.runDeferredEvents",
          "source": "Display.java:2716"
        },
        {
          "method": "org.eclipse.swt.widgets.Display.readAndDispatch",
          "source": "Display.java:2382"
        },
        {
          "method": "org.eclipse.jface.window.Window.runEventLoop",
          "source": "Window.java:668"
        },
        {
          "method": "org.eclipse.jface.window.Window.open",
          "source": "Window.java:648"
        },
        {
          "method": "org.eclipse.ui.internal.ide.actions.BuildCleanAction.run",
          "source": "BuildCleanAction.java:56"
        },
        {
          "method": "org.eclipse.jface.action.Action.runWithEvent",
          "source": "Action.java:881"
        },
        {
          "method": "org.eclipse.jface.action.ActionContributionItem.handleWidgetSelection",
          "source": "ActionContributionItem.java:899"
        },
        {
          "method": "org.eclipse.jface.action.ActionContributionItem.access$2",
          "source": "ActionContributionItem.java:850"
        },
        {
          "method": "org.eclipse.jface.action.ActionContributionItem$7.handleEvent",
          "source": "ActionContributionItem.java:769"
        },
        {
          "method": "org.eclipse.swt.widgets.EventTable.sendEvent",
          "source": "EventTable.java:82"
        },
        {
          "method": "org.eclipse.swt.widgets.Widget.sendEvent",
          "source": "Widget.java:796"
        },
        {
          "method": "org.eclipse.swt.widgets.Display.runDeferredEvents",
          "source": "Display.java:2716"
        },
        {
          "method": "org.eclipse.swt.widgets.Display.readAndDispatch",
          "source": "Display.java:2382"
        },
        {
          "method": "org.eclipse.ui.internal.Workbench.runEventLoop",
          "source": "Workbench.java:1363"
        },
        {
          "method": "org.eclipse.ui.internal.Workbench.runUI",
          "source": "Workbench.java:1334"
        },
        {
          "method": "org.eclipse.ui.internal.Workbench.createAndRunWorkbench",
          "source": "Workbench.java:253"
        },
        {
          "method": "org.eclipse.ui.PlatformUI.createAndRunWorkbench",
          "source": "PlatformUI.java:141"
        },
        {
          "method": "org.eclipse.ui.internal.ide.IDEApplication.run",
          "source": "IDEApplication.java:97"
        },
        {
          "method": "org.eclipse.core.internal.runtime.PlatformActivator$1.run",
          "source": "PlatformActivator.java:307"
        },
        {
          "method": "org.eclipse.core.runtime.adaptor.EclipseStarter.run",
          "source": "EclipseStarter.java:256"
        },
        {
          "method": "org.eclipse.core.runtime.adaptor.EclipseStarter.run",
          "source": "EclipseStarter.java:127"
        },
        {
          "method": "sun.reflect.NativeMethodAccessorImpl.invoke0",
          "source": "Native Method"
        },
        {
          "method": "sun.reflect.NativeMethodAccessorImpl.invoke",
          "source": "NativeMethodAccessorImpl.java:39"
        },
        {
          "method": "sun.reflect.DelegatingMethodAccessorImpl.invoke",
          "source": "DelegatingMethodAccessorImpl.java:25"
        },
        {
          "method": "java.lang.reflect.Method.invoke",
          "source": "Method.java:324"
        },
        {
          "method": "org.eclipse.core.launcher.Main.basicRun",
          "source": "Main.java:185"
        },
        {
          "method": "org.eclipse.core.launcher.Main.run",
          "source": "Main.java:638"
        },
        {
          "method": "org.eclipse.core.launcher.Main.main",
          "source": "Main.java:622"
        }
      ],
      "number": 0,
      "commentIndex": 0,
      "bugId": "63874",
      "date": "2004-05-25T16:52:40+02:00",
      "product": "Platform",
      "component": "UI",
      "severity": "normal"
    }
  ],
  "groupId": "63874",
  "bugId": "63874",
  "date": "2004-05-25T16:52:40+02:00",
  "product": "Platform",
  "component": "UI",
  "severity": "normal"
}