{
  "comments": [
    "I just updated from M7 to M9, and found that I was unable to launch any JUnit\ntests via Run, Run History or Run As. The stack trace is:\n\n!ENTRY org.eclipse.core.runtime 4 2 May 26, 2004 09:35:46.70\n!MESSAGE An internal error occurred during: \"Launching\".\n!STACK 0\njava.lang.UnsupportedOperationException\n        at java.util.AbstractList.remove(AbstractList.java:171)\n        at java.util.AbstractList$Itr.remove(AbstractList.java:436)\n        at\norg.eclipse.debug.core.model.LaunchConfigurationDelegate.computeBuildOrder(LaunchConfigurationDelegate.java:236)\n        at\norg.eclipse.debug.core.model.LaunchConfigurationDelegate.computeReferencedBuildOrder(LaunchConfigurationDelegate.java:189)\n        at\norg.eclipse.jdt.launching.AbstractJavaLaunchConfigurationDelegate.preLaunchCheck(AbstractJavaLaunchConfigurationDelegate.java:875)\n        at\norg.eclipse.debug.internal.core.LaunchConfiguration.launch(LaunchConfiguration.java:539)\n        at\norg.eclipse.debug.internal.core.LaunchConfiguration.launch(LaunchConfiguration.java:150)\n        at\norg.eclipse.debug.internal.ui.DebugUIPlugin.buildAndLaunch(DebugUIPlugin.java:796)\n        at org.eclipse.debug.internal.ui.DebugUIPlugin$6.run(DebugUIPlugin.java:959)\n        at org.eclipse.core.internal.jobs.Worker.run(Worker.java:66)\n\nI\u0027m running Version: 3.0.0\nBuild id: 200405211200\n\non SuSE Professional 8.2; session info is:\n\n!SESSION May 26, 2004 09:51:08.294 ---------------------------------------------\neclipse.buildId\u003dI200405211200\njava.version\u003d1.4.2_02\njava.vendor\u003dSun Microsystems Inc.\nBootLoader constants: OS\u003dlinux, ARCH\u003dx86, WS\u003dgtk, NL\u003den_US\n\nTried this several times with different test classes, always the same result.\nAlso tried closing and restarting the workbench.\n\nJUnit version is 3.8.1\n\nInstalled 3rd-party plugins are XML Buddy 2.0.5, DbEdit 1.0.0 and\norg.khataria.jsedit 1.0.1",
    "Created an attachment (id\u003d11125)\nDump of Help/About Eclipse Platform/Configuration Details\n",
    "Did some more testing, and found this also applies to trying to run a simple\njava application in the workbench. It must have something to do with my\nconfiguration/platform; I can\u0027t imagine that I\u0027d be the first one to discover it\notherwise.\n\nI attached my Eclipse config.\n\n",
    "\n\n*** This bug has been marked as a duplicate of 63533 ***"
  ],
  "commentCreationDates": [
    "2004-05-26T10:12:49+02:00",
    "2004-05-26T12:06:27+02:00",
    "2004-05-26T12:07:22+02:00",
    "2004-05-26T15:41:34+02:00"
  ],
  "traces": [
    {
      "exceptionType": "java.lang.UnsupportedOperationException",
      "elements": [
        {
          "method": "java.util.AbstractList.remove",
          "source": "AbstractList.java:171"
        },
        {
          "method": "java.util.AbstractList$Itr.remove",
          "source": "AbstractList.java:436"
        },
        {
          "method": "org.eclipse.debug.core.model.LaunchConfigurationDelegate.computeBuildOrder",
          "source": "LaunchConfigurationDelegate.java:236"
        },
        {
          "method": "org.eclipse.debug.core.model.LaunchConfigurationDelegate.computeReferencedBuildOrder",
          "source": "LaunchConfigurationDelegate.java:189"
        },
        {
          "method": "org.eclipse.jdt.launching.AbstractJavaLaunchConfigurationDelegate.preLaunchCheck",
          "source": "AbstractJavaLaunchConfigurationDelegate.java:875"
        },
        {
          "method": "org.eclipse.debug.internal.core.LaunchConfiguration.launch",
          "source": "LaunchConfiguration.java:539"
        },
        {
          "method": "org.eclipse.debug.internal.core.LaunchConfiguration.launch",
          "source": "LaunchConfiguration.java:150"
        },
        {
          "method": "org.eclipse.debug.internal.ui.DebugUIPlugin.buildAndLaunch",
          "source": "DebugUIPlugin.java:796"
        },
        {
          "method": "org.eclipse.debug.internal.ui.DebugUIPlugin$6.run",
          "source": "DebugUIPlugin.java:959"
        },
        {
          "method": "org.eclipse.core.internal.jobs.Worker.run",
          "source": "Worker.java:66"
        }
      ],
      "number": 0,
      "commentIndex": 0,
      "bugId": "64047",
      "duplicateId": "63533",
      "date": "2004-05-26T10:12:49+02:00",
      "product": "JDT",
      "component": "Debug",
      "severity": "major"
    }
  ],
  "groupId": "63533",
  "bugId": "64047",
  "duplicateId": "63533",
  "date": "2004-05-26T10:12:49+02:00",
  "product": "JDT",
  "component": "Debug",
  "severity": "major"
}