{
  "comments": [
    "VM: sun jdk 1.4.2_01\nCommand line arguments: -vmargs -mx256M\n\nSteps to reproduce:\n- Unzip a fresh 3.0M9 in an empty directory\n- Launch eclipse\n- Create a new java project with default settings\n- Create a new class with the class wizard. (com.test.Test)\n- Add a public constructor and a public method with javadoc and normal comments\nfor both\n- Add two import lines (I added java.applet.* and java.awt.*)\n- Close the editor\n- Go to the folding preferences (Windows-\u003ePreferences-\u003eJava-\u003eEditor-\u003eFolding)\n- Check all boxes on the tab. (there should be five of them).\n- Open the Test class.\n\nResult:\nThe import statements are collapsed, nothing else is.\n\nExpected result:\nImport statements, methods and comments should be collapsed.\n\nBuild id: 200405211200\n\nworkspace/.metadata/.log content:\n!SESSION mai 26, 2004 13:25:29.45 ----------------------------------------------\neclipse.buildId\u003dI200405211200\njava.version\u003d1.4.2_01\njava.vendor\u003dSun Microsystems Inc.\nBootLoader constants: OS\u003dlinux, ARCH\u003dx86, WS\u003dgtk, NL\u003dfr_FR\n!ENTRY org.eclipse.ui 4 4 mai 26, 2004 13:25:29.46\n!MESSAGE Unhandled event loop exception\n!ENTRY org.eclipse.ui 4 0 mai 26, 2004 13:25:29.48\n!MESSAGE Widget is disposed\n!STACK 0\norg.eclipse.swt.SWTException: Widget is disposed\n        at org.eclipse.swt.SWT.error(SWT.java:2689)\n        at org.eclipse.swt.SWT.error(SWT.java:2614)\n        at org.eclipse.swt.SWT.error(SWT.java:2585)\n        at org.eclipse.swt.widgets.Widget.error(Widget.java:374)\n        at org.eclipse.swt.widgets.Widget.checkWidget(Widget.java:310)\n        at org.eclipse.swt.widgets.Control.redraw(Control.java:2106)\n        at org.eclipse.ui.forms.widgets.ImageHyperlink.handleActivate(ImageHyper\nlink.java:139)\n        at org.eclipse.ui.forms.widgets.AbstractHyperlink.handleMouseUp(Abstract\nHyperlink.java:264)\n        at org.eclipse.ui.forms.widgets.AbstractHyperlink.access$1(AbstractHyper\nlink.java:248)\n        at org.eclipse.ui.forms.widgets.AbstractHyperlink$4.handleEvent(Abstract\nHyperlink.java:95)\n        at org.eclipse.swt.widgets.EventTable.sendEvent(EventTable.java:82)\n        at org.eclipse.swt.widgets.Widget.sendEvent(Widget.java:944)\n        at org.eclipse.swt.widgets.Display.runDeferredEvents(Display.java:2542)\n        at org.eclipse.swt.widgets.Display.readAndDispatch(Display.java:2253)\n        at org.eclipse.ui.internal.Workbench.runEventLoop(Workbench.java:1363)\n        at org.eclipse.ui.internal.Workbench.runUI(Workbench.java:1334)\n        at org.eclipse.ui.internal.Workbench.createAndRunWorkbench(Workbench.jav\na:253)\n        at org.eclipse.ui.PlatformUI.createAndRunWorkbench(PlatformUI.java:141)\n        at org.eclipse.ui.internal.ide.IDEApplication.run(IDEApplication.java:97\n)\n        at org.eclipse.core.internal.runtime.PlatformActivator$1.run(PlatformAct\nivator.java:307)\n        at org.eclipse.core.runtime.adaptor.EclipseStarter.run(EclipseStarter.ja\nva:256)\n        at org.eclipse.core.runtime.adaptor.EclipseStarter.run(EclipseStarter.ja\nva:127)\n        at sun.reflect.NativeMethodAccessorImpl.invoke0(Native Method)\n        at sun.reflect.NativeMethodAccessorImpl.invoke(NativeMethodAccessorImpl.\njava:39)\n        at sun.reflect.DelegatingMethodAccessorImpl.invoke(DelegatingMethodAcces\n        at org.eclipse.swt.widgets.Display.readAndDispatch(Display.java:2253)\n        at org.eclipse.ui.internal.Workbench.runEventLoop(Workbench.java:1363)\n        at org.eclipse.ui.internal.Workbench.runUI(Workbench.java:1334)\n        at org.eclipse.ui.internal.Workbench.createAndRunWorkbench(Workbench.jav\na:253)\n        at org.eclipse.ui.PlatformUI.createAndRunWorkbench(PlatformUI.java:141)\n        at org.eclipse.ui.internal.ide.IDEApplication.run(IDEApplication.java:97\n)\n        at org.eclipse.core.internal.runtime.PlatformActivator$1.run(PlatformAct\nivator.java:307)\n        at org.eclipse.core.runtime.adaptor.EclipseStarter.run(EclipseStarter.ja\nva:256)\n        at org.eclipse.core.runtime.adaptor.EclipseStarter.run(EclipseStarter.ja\nva:127)\n        at sun.reflect.NativeMethodAccessorImpl.invoke0(Native Method)\n        at sun.reflect.NativeMethodAccessorImpl.invoke(NativeMethodAccessorImpl.\njava:39)\n        at sun.reflect.DelegatingMethodAccessorImpl.invoke(DelegatingMethodAcces\nsorImpl.java:25)\n        at java.lang.reflect.Method.invoke(Method.java:324)\n        at org.eclipse.core.launcher.Main.basicRun(Main.java:185)\n        at org.eclipse.core.launcher.Main.run(Main.java:638)\n        at org.eclipse.core.launcher.Main.main(Main.java:622)\n\n\nThx in advance.",
    "\n\n*** This bug has been marked as a duplicate of 63178 ***"
  ],
  "commentCreationDates": [
    "2004-05-26T14:08:56+02:00",
    "2004-05-26T14:38:25+02:00"
  ],
  "traces": [
    {
      "exceptionType": "org.eclipse.swt.SWTException",
      "message": "Widget is disposed",
      "elements": [
        {
          "method": "org.eclipse.swt.SWT.error",
          "source": "SWT.java:2689"
        },
        {
          "method": "org.eclipse.swt.SWT.error",
          "source": "SWT.java:2614"
        },
        {
          "method": "org.eclipse.swt.SWT.error",
          "source": "SWT.java:2585"
        },
        {
          "method": "org.eclipse.swt.widgets.Widget.error",
          "source": "Widget.java:374"
        },
        {
          "method": "org.eclipse.swt.widgets.Widget.checkWidget",
          "source": "Widget.java:310"
        },
        {
          "method": "org.eclipse.swt.widgets.Control.redraw",
          "source": "Control.java:2106"
        },
        {
          "method": "org.eclipse.ui.forms.widgets.ImageHyperlink.handleActivate",
          "source": "ImageHyper link.java:139"
        },
        {
          "method": "org.eclipse.ui.forms.widgets.AbstractHyperlink.handleMouseUp",
          "source": "Abstract Hyperlink.java:264"
        },
        {
          "method": "org.eclipse.ui.forms.widgets.AbstractHyperlink.access$1",
          "source": "AbstractHyper link.java:248"
        },
        {
          "method": "org.eclipse.ui.forms.widgets.AbstractHyperlink$4.handleEvent",
          "source": "Abstract Hyperlink.java:95"
        },
        {
          "method": "org.eclipse.swt.widgets.EventTable.sendEvent",
          "source": "EventTable.java:82"
        },
        {
          "method": "org.eclipse.swt.widgets.Widget.sendEvent",
          "source": "Widget.java:944"
        },
        {
          "method": "org.eclipse.swt.widgets.Display.runDeferredEvents",
          "source": "Display.java:2542"
        },
        {
          "method": "org.eclipse.swt.widgets.Display.readAndDispatch",
          "source": "Display.java:2253"
        },
        {
          "method": "org.eclipse.ui.internal.Workbench.runEventLoop",
          "source": "Workbench.java:1363"
        },
        {
          "method": "org.eclipse.ui.internal.Workbench.runUI",
          "source": "Workbench.java:1334"
        },
        {
          "method": "org.eclipse.ui.internal.Workbench.createAndRunWorkbench",
          "source": "Workbench.jav a:253"
        },
        {
          "method": "org.eclipse.ui.PlatformUI.createAndRunWorkbench",
          "source": "PlatformUI.java:141"
        },
        {
          "method": "org.eclipse.ui.internal.ide.IDEApplication.run",
          "source": "IDEApplication.java:97 "
        },
        {
          "method": "org.eclipse.core.internal.runtime.PlatformActivator$1.run",
          "source": "PlatformAct ivator.java:307"
        },
        {
          "method": "org.eclipse.core.runtime.adaptor.EclipseStarter.run",
          "source": "EclipseStarter.ja va:256"
        },
        {
          "method": "org.eclipse.core.runtime.adaptor.EclipseStarter.run",
          "source": "EclipseStarter.ja va:127"
        },
        {
          "method": "sun.reflect.NativeMethodAccessorImpl.invoke0",
          "source": "Native Method"
        },
        {
          "method": "sun.reflect.NativeMethodAccessorImpl.invoke",
          "source": "NativeMethodAccessorImpl. java:39"
        }
      ],
      "number": 0,
      "commentIndex": 0,
      "bugId": "64080",
      "duplicateId": "63178",
      "date": "2004-05-26T14:08:56+02:00",
      "product": "JDT",
      "component": "Text",
      "severity": "normal"
    }
  ],
  "groupId": "63178",
  "bugId": "64080",
  "duplicateId": "63178",
  "date": "2004-05-26T14:08:56+02:00",
  "product": "JDT",
  "component": "Text",
  "severity": "normal"
}