{
  "comments": [
    "This problem only arrived with the M9 build (M8 was fine) so this could be with\nEclipse not Hyades, once I finish downloading the latest integration build I\u0027ll\ntest against that as well.  The problem can be reproduced by following the\nopening steps of \u003ca\nhref\u003d\"http://dev.eclipse.org/viewcvs/indextools.cgi/~checkout~/hyades-home/docs/profiling_applications.html\"\n\u003ethis tutorial\u003c/a\u003e up till step 3 where the M9 doesn\u0027t have the Build option\nhighlighted(differences between 2.1.3 and 3.0).  Now switch to profile and\nlogging perspective, in M8 all run options under both profile and just run are\navailable, however now there there are no run options under the \"Profile\nJCarModel\" button but there are run options under \"Run JCarModel\".  So run as\napplication and play around with it and quit.  Now observe under \"Profile\nJCarModel\" there are still no options under the \"Profile As\" button but now at\nthe top you see \"1 JCarModel\" suggesting a profile for a application.  Select\nthat option and when it tries to launch get this lovely traceback.\n\n java.lang.NoClassDefFoundError: org/apache/xerces/jaxp/SAXParserFactoryImpl\n        at\norg.eclipse.hyades.loaders.util.SAXFragmentHandler.makeParser(SAXFragmentHandler.java:172)\n        at\norg.eclipse.hyades.loaders.util.SAXFragmentHandler.setXMLLoader(SAXFragmentHandler.java:47)\n        at org.eclipse.hyades.loaders.util.XMLLoader.makeScanner(XMLLoader.java:452)\n        at org.eclipse.hyades.loaders.util.XMLLoader.\u003cinit\u003e(XMLLoader.java:59)\n        at\norg.eclipse.hyades.trace.ui.internal.piclient.XMLTraceDataProcessor.\u003cinit\u003e(XMLTraceDataProcessor.java:82)\n        at\norg.eclipse.hyades.trace.ui.internal.piclient.PIProcessListener.agentActive(PIProcessListener.java:144)\n        at\norg.eclipse.hyades.internal.execution.local.control.AgentImpl.handleCommand(AgentImpl.java:404)\n        at\norg.eclipse.hyades.internal.execution.local.control.ProcessImpl.handleCommand(ProcessImpl.java:552)\n        at\norg.eclipse.hyades.internal.execution.local.control.ProcessImpl$1.incommingCommand(ProcessImpl.java:130)\n        at\norg.eclipse.hyades.internal.execution.local.control.ConnectionImpl$1.incommingCommand(ConnectionImpl.java:177)\n        at\norg.eclipse.hyades.internal.execution.local.control.ConnectionImpl.processControlMessage(ConnectionImpl.java:393)\n        at\norg.eclipse.hyades.internal.execution.local.control.ConnectionImpl$SocketReaderThread.run(ConnectionImpl.java:484)",
    "Eugene,  I am punting this to you as you are the last entry on the satck (the \nloaders).  this is an issue with the fact Xerces was removed from M9.  The \nloaders should no longer be using xerces and I suspect they are not.  Please \nwork with Aaron to ensure his configuration is correct.",
    "Curtis, can you please work with Aaron on this problem. It seems like \nsomething\u0027s wrong with the JVM being used. Marius should be able to provide you \nwith more information about the loader.",
    "Do you remember which build you were using? I suspect this problem will \ndisappear in later builds.\n\nMarius, can you confirm that the loaders are no longer using Xerces? I did a \ntext search and found no instances of org.apache.xerces in our components.",
    "Yeah, I was using the M9, I finally got the I20040526 downloaded and installed\nand the bug appears to be fixed.",
    "Marking as fixed."
  ],
  "commentCreationDates": [
    "2004-05-26T17:05:40+02:00",
    "2004-05-26T19:05:42+02:00",
    "2004-05-26T19:13:04+02:00",
    "2004-05-26T19:34:17+02:00",
    "2004-05-26T20:11:04+02:00",
    "2004-05-26T20:54:05+02:00"
  ],
  "traces": [
    {
      "exceptionType": "java.lang.NoClassDefFoundError",
      "message": "org/apache/xerces/jaxp/SAXParserFactoryImpl",
      "elements": [
        {
          "method": "org.eclipse.hyades.loaders.util.SAXFragmentHandler.makeParser",
          "source": "SAXFragmentHandler.java:172"
        },
        {
          "method": "org.eclipse.hyades.loaders.util.SAXFragmentHandler.setXMLLoader",
          "source": "SAXFragmentHandler.java:47"
        },
        {
          "method": "org.eclipse.hyades.loaders.util.XMLLoader.makeScanner",
          "source": "XMLLoader.java:452"
        },
        {
          "method": "org.eclipse.hyades.loaders.util.XMLLoader.\u003cinit\u003e",
          "source": "XMLLoader.java:59"
        },
        {
          "method": "org.eclipse.hyades.trace.ui.internal.piclient.XMLTraceDataProcessor.\u003cinit\u003e",
          "source": "XMLTraceDataProcessor.java:82"
        },
        {
          "method": "org.eclipse.hyades.trace.ui.internal.piclient.PIProcessListener.agentActive",
          "source": "PIProcessListener.java:144"
        },
        {
          "method": "org.eclipse.hyades.internal.execution.local.control.AgentImpl.handleCommand",
          "source": "AgentImpl.java:404"
        },
        {
          "method": "org.eclipse.hyades.internal.execution.local.control.ProcessImpl.handleCommand",
          "source": "ProcessImpl.java:552"
        },
        {
          "method": "org.eclipse.hyades.internal.execution.local.control.ProcessImpl$1.incommingCommand",
          "source": "ProcessImpl.java:130"
        },
        {
          "method": "org.eclipse.hyades.internal.execution.local.control.ConnectionImpl$1.incommingCommand",
          "source": "ConnectionImpl.java:177"
        },
        {
          "method": "org.eclipse.hyades.internal.execution.local.control.ConnectionImpl.processControlMessage",
          "source": "ConnectionImpl.java:393"
        },
        {
          "method": "org.eclipse.hyades.internal.execution.local.control.ConnectionImpl$SocketReaderThread.run",
          "source": "ConnectionImpl.java:484"
        }
      ],
      "number": 0,
      "commentIndex": 0,
      "bugId": "64133",
      "date": "2004-05-26T17:05:40+02:00",
      "product": "Hyades",
      "component": "DataCollection\u0026Control",
      "severity": "normal"
    }
  ],
  "groupId": "64133",
  "bugId": "64133",
  "date": "2004-05-26T17:05:40+02:00",
  "product": "Hyades",
  "component": "DataCollection\u0026Control",
  "severity": "normal"
}