{
  "comments": [
    "I\u0027m using Eclipse 3.0M8 and CDT 3.0M8 on Slackware Linux 9.1 \n \nSometimes when I close eclipse after a work session the \"Saving Workspace\" \nprogress dialog just hang. It saves the workspace and the progress bar moves \nall the way to the right, but then it just sits there. I\u0027ve tried leaving it \nalone for up to 5 minutes but it doesn\u0027t seem to ever want to close - I have to \nmanually kill the PID of eclipse to get it to go away. \nI don\u0027t know if this is a CDT bug or a Eclipse bug, but when looking in my .log \nfile the last time this happened I saw this in the last entry: !MESSAGE Error \nwhile stopping \n\"reference:file:/home/juhl/eclipse/plugins/org.eclipse.cdt.core_2.0.0/ [97]\". \nwhich is why I\u0027m filing this as a cdt-core bug.  Below is the entire entry from \nthe .log file in case it is of any use : \n \n!SESSION May 31, 2004 23:30:40.404 \n--------------------------------------------- \njava.version\u003d1.4.2_01 \njava.vendor\u003dSun Microsystems Inc. \nBootLoader constants: OS\u003dlinux, ARCH\u003dx86, WS\u003dgtk, NL\u003den_US \n!ENTRY org.eclipse.osgi May 31, 2004 23:30:40.405 \n!MESSAGE Error while stopping \n\"reference:file:/home/juhl/eclipse/plugins/org.eclipse.cdt.core_2.0.0/ [97]\". \n!STACK 0 \norg.osgi.framework.BundleException: Exception in \norg.eclipse.core.internal.compatibility.PluginActivator.stop() \n        at \norg.eclipse.osgi.framework.internal.core.BundleContext.stop(BundleContext.java:1044) \n        at \norg.eclipse.osgi.framework.internal.core.BundleHost.stopWorker(BundleHost.java:482) \n        at \norg.eclipse.osgi.framework.internal.core.Bundle.stop(Bundle.java:447) \n        at \norg.eclipse.core.runtime.adaptor.BundleStopper.stopBundles(BundleStopper.java:54) \n        at \norg.eclipse.core.runtime.adaptor.BundleStopper.stopBundles(BundleStopper.java:47) \n        at \norg.eclipse.core.runtime.adaptor.EclipseAdaptor.frameworkStopping(EclipseAdaptor.java:472) \n        at \norg.eclipse.osgi.framework.internal.core.Framework.shutdown(Framework.java:431) \n        at \norg.eclipse.osgi.framework.internal.core.SystemBundle$1.run(SystemBundle.java:181) \n        at java.lang.Thread.run(Thread.java:534) \nNested exception: \njava.lang.NullPointerException \n        at org.eclipse.cdt.internal.core.CDescriptorManager.shutdown(Unknown \nSource) \n        at org.eclipse.cdt.core.CCorePlugin.shutdown(Unknown Source) \n        at \norg.eclipse.core.internal.compatibility.PluginActivator.stop(PluginActivator.java:66) \n        at \norg.eclipse.osgi.framework.internal.core.BundleContext$2.run(BundleContext.java:1028) \n        at java.security.AccessController.doPrivileged(Native Method) \n        at \norg.eclipse.osgi.framework.internal.core.BundleContext.stop(BundleContext.java:1024) \n        at \norg.eclipse.osgi.framework.internal.core.BundleHost.stopWorker(BundleHost.java:482) \n        at \norg.eclipse.osgi.framework.internal.core.Bundle.stop(Bundle.java:447) \n        at \norg.eclipse.core.runtime.adaptor.BundleStopper.stopBundles(BundleStopper.java:54) \n        at \norg.eclipse.core.runtime.adaptor.BundleStopper.stopBundles(BundleStopper.java:47) \n        at \norg.eclipse.core.runtime.adaptor.EclipseAdaptor.frameworkStopping(EclipseAdaptor.java:472) \n        at \norg.eclipse.osgi.framework.internal.core.Framework.shutdown(Framework.java:431) \n        at \norg.eclipse.osgi.framework.internal.core.SystemBundle$1.run(SystemBundle.java:181) \n        at java.lang.Thread.run(Thread.java:534) \n!ENTRY org.eclipse.osgi May 31, 2004 23:30:40.463 \n!MESSAGE Error while stopping \n\"reference:file:/home/juhl/eclipse/plugins/org.eclipse.cdt.ui_2.0.0/ [85]\". \n!STACK 0 \norg.osgi.framework.BundleException: Exception in \norg.eclipse.core.internal.compatibility.PluginActivator.stop() \n        at \norg.eclipse.osgi.framework.internal.core.BundleContext.stop(BundleContext.java:1044) \n        at \norg.eclipse.osgi.framework.internal.core.BundleHost.stopWorker(BundleHost.java:482) \n        at \norg.eclipse.osgi.framework.internal.core.Bundle.stop(Bundle.java:447) \n        at \norg.eclipse.core.runtime.adaptor.BundleStopper.stopBundles(BundleStopper.java:54) \n        at \norg.eclipse.core.runtime.adaptor.BundleStopper.stopBundles(BundleStopper.java:47) \n        at \norg.eclipse.core.runtime.adaptor.EclipseAdaptor.frameworkStopping(EclipseAdaptor.java:472) \n        at \norg.eclipse.osgi.framework.internal.core.Framework.shutdown(Framework.java:431) \n        at \norg.eclipse.osgi.framework.internal.core.SystemBundle$1.run(SystemBundle.java:181) \n        at java.lang.Thread.run(Thread.java:534) \nNested exception: \njava.lang.NullPointerException \n        at \norg.eclipse.cdt.internal.ui.buildconsole.BuildConsoleManager.shutdown(Unknown \nSource) \n        at org.eclipse.cdt.ui.CUIPlugin.shutdown(Unknown Source) \n        at \norg.eclipse.core.internal.compatibility.PluginActivator.stop(PluginActivator.java:66) \n        at \norg.eclipse.osgi.framework.internal.core.BundleContext$2.run(BundleContext.java:1028) \n        at java.security.AccessController.doPrivileged(Native Method) \n        at \norg.eclipse.osgi.framework.internal.core.BundleContext.stop(BundleContext.java:1024) \n        at \norg.eclipse.osgi.framework.internal.core.BundleHost.stopWorker(BundleHost.java:482) \n        at \norg.eclipse.osgi.framework.internal.core.Bundle.stop(Bundle.java:447) \n        at \norg.eclipse.core.runtime.adaptor.BundleStopper.stopBundles(BundleStopper.java:54) \n        at \norg.eclipse.core.runtime.adaptor.BundleStopper.stopBundles(BundleStopper.java:47) \n        at \norg.eclipse.core.runtime.adaptor.EclipseAdaptor.frameworkStopping(EclipseAdaptor.java:472) \n        at \norg.eclipse.osgi.framework.internal.core.Framework.shutdown(Framework.java:431) \n        at \norg.eclipse.osgi.framework.internal.core.SystemBundle$1.run(SystemBundle.java:181) \n        at java.lang.Thread.run(Thread.java:534) \n!ENTRY org.eclipse.osgi May 31, 2004 23:30:40.466 \n!MESSAGE Error while stopping \n\"reference:file:/home/juhl/eclipse/plugins/org.eclipse.cdt.debug.ui_2.0.0/ \n[88]\". \n!STACK 0 \norg.osgi.framework.BundleException: Exception in \norg.eclipse.core.internal.compatibility.PluginActivator.stop() \n        at \norg.eclipse.osgi.framework.internal.core.BundleContext.stop(BundleContext.java:1044) \n        at \norg.eclipse.osgi.framework.internal.core.BundleHost.stopWorker(BundleHost.java:482) \n        at \norg.eclipse.osgi.framework.internal.core.Bundle.stop(Bundle.java:447) \n        at \norg.eclipse.core.runtime.adaptor.BundleStopper.stopBundles(BundleStopper.java:54) \n        at \norg.eclipse.core.runtime.adaptor.BundleStopper.stopBundles(BundleStopper.java:47) \n        at \norg.eclipse.core.runtime.adaptor.EclipseAdaptor.frameworkStopping(EclipseAdaptor.java:472) \n        at \norg.eclipse.osgi.framework.internal.core.Framework.shutdown(Framework.java:431) \n        at \norg.eclipse.osgi.framework.internal.core.SystemBundle$1.run(SystemBundle.java:181) \n        at java.lang.Thread.run(Thread.java:534) \nNested exception: \njava.lang.NullPointerException \n        at org.eclipse.cdt.debug.ui.CDebugUIPlugin.shutdown(Unknown Source) \n        at \norg.eclipse.core.internal.compatibility.PluginActivator.stop(PluginActivator.java:66) \n        at \norg.eclipse.osgi.framework.internal.core.BundleContext$2.run(BundleContext.java:1028) \n        at java.security.AccessController.doPrivileged(Native Method) \n        at \norg.eclipse.osgi.framework.internal.core.BundleContext.stop(BundleContext.java:1024) \n        at \norg.eclipse.osgi.framework.internal.core.BundleHost.stopWorker(BundleHost.java:482) \n        at \norg.eclipse.osgi.framework.internal.core.Bundle.stop(Bundle.java:447) \n        at \norg.eclipse.core.runtime.adaptor.BundleStopper.stopBundles(BundleStopper.java:54) \n        at \norg.eclipse.core.runtime.adaptor.BundleStopper.stopBundles(BundleStopper.java:47) \n        at \norg.eclipse.core.runtime.adaptor.EclipseAdaptor.frameworkStopping(EclipseAdaptor.java:472) \n        at \norg.eclipse.osgi.framework.internal.core.Framework.shutdown(Framework.java:431) \n        at \norg.eclipse.osgi.framework.internal.core.SystemBundle$1.run(SystemBundle.java:181) \n        at java.lang.Thread.run(Thread.java:534) \n!ENTRY org.eclipse.osgi May 31, 2004 23:30:40.468 \n!MESSAGE Error while stopping \n\"reference:file:/home/juhl/eclipse/plugins/org.eclipse.cdt.debug.core_2.0.0/ \n[91]\". \n!STACK 0 \norg.osgi.framework.BundleException: Exception in \norg.eclipse.core.internal.compatibility.PluginActivator.stop() \n        at \norg.eclipse.osgi.framework.internal.core.BundleContext.stop(BundleContext.java:1044) \n        at \norg.eclipse.osgi.framework.internal.core.BundleHost.stopWorker(BundleHost.java:482) \n        at \norg.eclipse.osgi.framework.internal.core.Bundle.stop(Bundle.java:447) \n        at \norg.eclipse.core.runtime.adaptor.BundleStopper.stopBundles(BundleStopper.java:54) \n        at \norg.eclipse.core.runtime.adaptor.BundleStopper.stopBundles(BundleStopper.java:47) \n        at \norg.eclipse.core.runtime.adaptor.EclipseAdaptor.frameworkStopping(EclipseAdaptor.java:472) \n        at \norg.eclipse.osgi.framework.internal.core.Framework.shutdown(Framework.java:431) \n        at \norg.eclipse.osgi.framework.internal.core.SystemBundle$1.run(SystemBundle.java:181) \n        at java.lang.Thread.run(Thread.java:534) \nNested exception: \njava.lang.NullPointerException \n        at org.eclipse.cdt.debug.internal.core.SessionManager.dispose(Unknown \nSource) \n        at \norg.eclipse.cdt.debug.core.CDebugCorePlugin.setSessionManager(Unknown Source) \n        at org.eclipse.cdt.debug.core.CDebugCorePlugin.shutdown(Unknown Source) \n        at \norg.eclipse.core.internal.compatibility.PluginActivator.stop(PluginActivator.java:66) \n        at \norg.eclipse.osgi.framework.internal.core.BundleContext$2.run(BundleContext.java:1028) \n        at java.security.AccessController.doPrivileged(Native Method) \n        at \norg.eclipse.osgi.framework.internal.core.BundleContext.stop(BundleContext.java:1024) \n        at \norg.eclipse.osgi.framework.internal.core.BundleHost.stopWorker(BundleHost.java:482) \n        at \norg.eclipse.osgi.framework.internal.core.Bundle.stop(Bundle.java:447) \n        at \norg.eclipse.core.runtime.adaptor.BundleStopper.stopBundles(BundleStopper.java:54) \n        at \norg.eclipse.core.runtime.adaptor.BundleStopper.stopBundles(BundleStopper.java:47) \n        at \norg.eclipse.core.runtime.adaptor.EclipseAdaptor.frameworkStopping(EclipseAdaptor.java:472) \n        at \norg.eclipse.osgi.framework.internal.core.Framework.shutdown(Framework.java:431) \n        at \norg.eclipse.osgi.framework.internal.core.SystemBundle$1.run(SystemBundle.java:181) \n        at java.lang.Thread.run(Thread.java:534)",
    "The cdt.core plugin been move to use the Eclipes-3.0\nway OSGI bundle scheme.  We no longer use the Compatibiltiy\nplugin.\n\nNote:  We still use it for cdt.ui.\n\n",
    "Reopen the PR if you still see this.\n\nFlipping to Fix"
  ],
  "commentCreationDates": [
    "2004-05-31T23:42:30+02:00",
    "2004-06-01T22:41:05+02:00",
    "2004-06-01T22:41:33+02:00"
  ],
  "traces": [
    {
      "exceptionType": "org.osgi.framework.BundleException",
      "message": "Exception in  org.eclipse.core.internal.compatibility.PluginActivator.stop()",
      "elements": [
        {
          "method": "org.eclipse.osgi.framework.internal.core.BundleContext.stop",
          "source": "BundleContext.java:1044"
        },
        {
          "method": "org.eclipse.osgi.framework.internal.core.BundleHost.stopWorker",
          "source": "BundleHost.java:482"
        },
        {
          "method": "org.eclipse.osgi.framework.internal.core.Bundle.stop",
          "source": "Bundle.java:447"
        },
        {
          "method": "org.eclipse.core.runtime.adaptor.BundleStopper.stopBundles",
          "source": "BundleStopper.java:54"
        },
        {
          "method": "org.eclipse.core.runtime.adaptor.BundleStopper.stopBundles",
          "source": "BundleStopper.java:47"
        },
        {
          "method": "org.eclipse.core.runtime.adaptor.EclipseAdaptor.frameworkStopping",
          "source": "EclipseAdaptor.java:472"
        },
        {
          "method": "org.eclipse.osgi.framework.internal.core.Framework.shutdown",
          "source": "Framework.java:431"
        },
        {
          "method": "org.eclipse.osgi.framework.internal.core.SystemBundle$1.run",
          "source": "SystemBundle.java:181"
        },
        {
          "method": "java.lang.Thread.run",
          "source": "Thread.java:534"
        }
      ],
      "number": 0,
      "commentIndex": 0,
      "bugId": "64850",
      "date": "2004-05-31T23:42:30+02:00",
      "product": "CDT",
      "component": "cdt-core",
      "severity": "normal"
    },
    {
      "exceptionType": "java.lang.NullPointerException",
      "elements": [
        {
          "method": "org.eclipse.cdt.internal.core.CDescriptorManager.shutdown",
          "source": "Unknown  Source"
        },
        {
          "method": "org.eclipse.cdt.core.CCorePlugin.shutdown",
          "source": "Unknown Source"
        },
        {
          "method": "org.eclipse.core.internal.compatibility.PluginActivator.stop",
          "source": "PluginActivator.java:66"
        },
        {
          "method": "org.eclipse.osgi.framework.internal.core.BundleContext$2.run",
          "source": "BundleContext.java:1028"
        },
        {
          "method": "java.security.AccessController.doPrivileged",
          "source": "Native Method"
        },
        {
          "method": "org.eclipse.osgi.framework.internal.core.BundleContext.stop",
          "source": "BundleContext.java:1024"
        },
        {
          "method": "org.eclipse.osgi.framework.internal.core.BundleHost.stopWorker",
          "source": "BundleHost.java:482"
        },
        {
          "method": "org.eclipse.osgi.framework.internal.core.Bundle.stop",
          "source": "Bundle.java:447"
        },
        {
          "method": "org.eclipse.core.runtime.adaptor.BundleStopper.stopBundles",
          "source": "BundleStopper.java:54"
        },
        {
          "method": "org.eclipse.core.runtime.adaptor.BundleStopper.stopBundles",
          "source": "BundleStopper.java:47"
        },
        {
          "method": "org.eclipse.core.runtime.adaptor.EclipseAdaptor.frameworkStopping",
          "source": "EclipseAdaptor.java:472"
        },
        {
          "method": "org.eclipse.osgi.framework.internal.core.Framework.shutdown",
          "source": "Framework.java:431"
        },
        {
          "method": "org.eclipse.osgi.framework.internal.core.SystemBundle$1.run",
          "source": "SystemBundle.java:181"
        },
        {
          "method": "java.lang.Thread.run",
          "source": "Thread.java:534"
        }
      ],
      "number": 1,
      "commentIndex": 0,
      "bugId": "64850",
      "date": "2004-05-31T23:42:30+02:00",
      "product": "CDT",
      "component": "cdt-core",
      "severity": "normal"
    },
    {
      "exceptionType": "org.osgi.framework.BundleException",
      "message": "Exception in  org.eclipse.core.internal.compatibility.PluginActivator.stop()",
      "elements": [
        {
          "method": "org.eclipse.osgi.framework.internal.core.BundleContext.stop",
          "source": "BundleContext.java:1044"
        },
        {
          "method": "org.eclipse.osgi.framework.internal.core.BundleHost.stopWorker",
          "source": "BundleHost.java:482"
        },
        {
          "method": "org.eclipse.osgi.framework.internal.core.Bundle.stop",
          "source": "Bundle.java:447"
        },
        {
          "method": "org.eclipse.core.runtime.adaptor.BundleStopper.stopBundles",
          "source": "BundleStopper.java:54"
        },
        {
          "method": "org.eclipse.core.runtime.adaptor.BundleStopper.stopBundles",
          "source": "BundleStopper.java:47"
        },
        {
          "method": "org.eclipse.core.runtime.adaptor.EclipseAdaptor.frameworkStopping",
          "source": "EclipseAdaptor.java:472"
        },
        {
          "method": "org.eclipse.osgi.framework.internal.core.Framework.shutdown",
          "source": "Framework.java:431"
        },
        {
          "method": "org.eclipse.osgi.framework.internal.core.SystemBundle$1.run",
          "source": "SystemBundle.java:181"
        },
        {
          "method": "java.lang.Thread.run",
          "source": "Thread.java:534"
        }
      ],
      "number": 2,
      "commentIndex": 0,
      "bugId": "64850",
      "date": "2004-05-31T23:42:30+02:00",
      "product": "CDT",
      "component": "cdt-core",
      "severity": "normal"
    },
    {
      "exceptionType": "java.lang.NullPointerException",
      "elements": [
        {
          "method": "org.eclipse.cdt.internal.ui.buildconsole.BuildConsoleManager.shutdown",
          "source": "Unknown  Source"
        },
        {
          "method": "org.eclipse.cdt.ui.CUIPlugin.shutdown",
          "source": "Unknown Source"
        },
        {
          "method": "org.eclipse.core.internal.compatibility.PluginActivator.stop",
          "source": "PluginActivator.java:66"
        },
        {
          "method": "org.eclipse.osgi.framework.internal.core.BundleContext$2.run",
          "source": "BundleContext.java:1028"
        },
        {
          "method": "java.security.AccessController.doPrivileged",
          "source": "Native Method"
        },
        {
          "method": "org.eclipse.osgi.framework.internal.core.BundleContext.stop",
          "source": "BundleContext.java:1024"
        },
        {
          "method": "org.eclipse.osgi.framework.internal.core.BundleHost.stopWorker",
          "source": "BundleHost.java:482"
        },
        {
          "method": "org.eclipse.osgi.framework.internal.core.Bundle.stop",
          "source": "Bundle.java:447"
        },
        {
          "method": "org.eclipse.core.runtime.adaptor.BundleStopper.stopBundles",
          "source": "BundleStopper.java:54"
        },
        {
          "method": "org.eclipse.core.runtime.adaptor.BundleStopper.stopBundles",
          "source": "BundleStopper.java:47"
        },
        {
          "method": "org.eclipse.core.runtime.adaptor.EclipseAdaptor.frameworkStopping",
          "source": "EclipseAdaptor.java:472"
        },
        {
          "method": "org.eclipse.osgi.framework.internal.core.Framework.shutdown",
          "source": "Framework.java:431"
        },
        {
          "method": "org.eclipse.osgi.framework.internal.core.SystemBundle$1.run",
          "source": "SystemBundle.java:181"
        },
        {
          "method": "java.lang.Thread.run",
          "source": "Thread.java:534"
        }
      ],
      "number": 3,
      "commentIndex": 0,
      "bugId": "64850",
      "date": "2004-05-31T23:42:30+02:00",
      "product": "CDT",
      "component": "cdt-core",
      "severity": "normal"
    },
    {
      "exceptionType": "org.osgi.framework.BundleException",
      "message": "Exception in  org.eclipse.core.internal.compatibility.PluginActivator.stop()",
      "elements": [
        {
          "method": "org.eclipse.osgi.framework.internal.core.BundleContext.stop",
          "source": "BundleContext.java:1044"
        },
        {
          "method": "org.eclipse.osgi.framework.internal.core.BundleHost.stopWorker",
          "source": "BundleHost.java:482"
        },
        {
          "method": "org.eclipse.osgi.framework.internal.core.Bundle.stop",
          "source": "Bundle.java:447"
        },
        {
          "method": "org.eclipse.core.runtime.adaptor.BundleStopper.stopBundles",
          "source": "BundleStopper.java:54"
        },
        {
          "method": "org.eclipse.core.runtime.adaptor.BundleStopper.stopBundles",
          "source": "BundleStopper.java:47"
        },
        {
          "method": "org.eclipse.core.runtime.adaptor.EclipseAdaptor.frameworkStopping",
          "source": "EclipseAdaptor.java:472"
        },
        {
          "method": "org.eclipse.osgi.framework.internal.core.Framework.shutdown",
          "source": "Framework.java:431"
        },
        {
          "method": "org.eclipse.osgi.framework.internal.core.SystemBundle$1.run",
          "source": "SystemBundle.java:181"
        },
        {
          "method": "java.lang.Thread.run",
          "source": "Thread.java:534"
        }
      ],
      "number": 4,
      "commentIndex": 0,
      "bugId": "64850",
      "date": "2004-05-31T23:42:30+02:00",
      "product": "CDT",
      "component": "cdt-core",
      "severity": "normal"
    },
    {
      "exceptionType": "java.lang.NullPointerException",
      "elements": [
        {
          "method": "org.eclipse.cdt.debug.ui.CDebugUIPlugin.shutdown",
          "source": "Unknown Source"
        },
        {
          "method": "org.eclipse.core.internal.compatibility.PluginActivator.stop",
          "source": "PluginActivator.java:66"
        },
        {
          "method": "org.eclipse.osgi.framework.internal.core.BundleContext$2.run",
          "source": "BundleContext.java:1028"
        },
        {
          "method": "java.security.AccessController.doPrivileged",
          "source": "Native Method"
        },
        {
          "method": "org.eclipse.osgi.framework.internal.core.BundleContext.stop",
          "source": "BundleContext.java:1024"
        },
        {
          "method": "org.eclipse.osgi.framework.internal.core.BundleHost.stopWorker",
          "source": "BundleHost.java:482"
        },
        {
          "method": "org.eclipse.osgi.framework.internal.core.Bundle.stop",
          "source": "Bundle.java:447"
        },
        {
          "method": "org.eclipse.core.runtime.adaptor.BundleStopper.stopBundles",
          "source": "BundleStopper.java:54"
        },
        {
          "method": "org.eclipse.core.runtime.adaptor.BundleStopper.stopBundles",
          "source": "BundleStopper.java:47"
        },
        {
          "method": "org.eclipse.core.runtime.adaptor.EclipseAdaptor.frameworkStopping",
          "source": "EclipseAdaptor.java:472"
        },
        {
          "method": "org.eclipse.osgi.framework.internal.core.Framework.shutdown",
          "source": "Framework.java:431"
        },
        {
          "method": "org.eclipse.osgi.framework.internal.core.SystemBundle$1.run",
          "source": "SystemBundle.java:181"
        },
        {
          "method": "java.lang.Thread.run",
          "source": "Thread.java:534"
        }
      ],
      "number": 5,
      "commentIndex": 0,
      "bugId": "64850",
      "date": "2004-05-31T23:42:30+02:00",
      "product": "CDT",
      "component": "cdt-core",
      "severity": "normal"
    },
    {
      "exceptionType": "org.osgi.framework.BundleException",
      "message": "Exception in  org.eclipse.core.internal.compatibility.PluginActivator.stop()",
      "elements": [
        {
          "method": "org.eclipse.osgi.framework.internal.core.BundleContext.stop",
          "source": "BundleContext.java:1044"
        },
        {
          "method": "org.eclipse.osgi.framework.internal.core.BundleHost.stopWorker",
          "source": "BundleHost.java:482"
        },
        {
          "method": "org.eclipse.osgi.framework.internal.core.Bundle.stop",
          "source": "Bundle.java:447"
        },
        {
          "method": "org.eclipse.core.runtime.adaptor.BundleStopper.stopBundles",
          "source": "BundleStopper.java:54"
        },
        {
          "method": "org.eclipse.core.runtime.adaptor.BundleStopper.stopBundles",
          "source": "BundleStopper.java:47"
        },
        {
          "method": "org.eclipse.core.runtime.adaptor.EclipseAdaptor.frameworkStopping",
          "source": "EclipseAdaptor.java:472"
        },
        {
          "method": "org.eclipse.osgi.framework.internal.core.Framework.shutdown",
          "source": "Framework.java:431"
        },
        {
          "method": "org.eclipse.osgi.framework.internal.core.SystemBundle$1.run",
          "source": "SystemBundle.java:181"
        },
        {
          "method": "java.lang.Thread.run",
          "source": "Thread.java:534"
        }
      ],
      "number": 6,
      "commentIndex": 0,
      "bugId": "64850",
      "date": "2004-05-31T23:42:30+02:00",
      "product": "CDT",
      "component": "cdt-core",
      "severity": "normal"
    },
    {
      "exceptionType": "java.lang.NullPointerException",
      "elements": [
        {
          "method": "org.eclipse.cdt.debug.internal.core.SessionManager.dispose",
          "source": "Unknown  Source"
        },
        {
          "method": "org.eclipse.cdt.debug.core.CDebugCorePlugin.setSessionManager",
          "source": "Unknown Source"
        },
        {
          "method": "org.eclipse.cdt.debug.core.CDebugCorePlugin.shutdown",
          "source": "Unknown Source"
        },
        {
          "method": "org.eclipse.core.internal.compatibility.PluginActivator.stop",
          "source": "PluginActivator.java:66"
        },
        {
          "method": "org.eclipse.osgi.framework.internal.core.BundleContext$2.run",
          "source": "BundleContext.java:1028"
        },
        {
          "method": "java.security.AccessController.doPrivileged",
          "source": "Native Method"
        },
        {
          "method": "org.eclipse.osgi.framework.internal.core.BundleContext.stop",
          "source": "BundleContext.java:1024"
        },
        {
          "method": "org.eclipse.osgi.framework.internal.core.BundleHost.stopWorker",
          "source": "BundleHost.java:482"
        },
        {
          "method": "org.eclipse.osgi.framework.internal.core.Bundle.stop",
          "source": "Bundle.java:447"
        },
        {
          "method": "org.eclipse.core.runtime.adaptor.BundleStopper.stopBundles",
          "source": "BundleStopper.java:54"
        },
        {
          "method": "org.eclipse.core.runtime.adaptor.BundleStopper.stopBundles",
          "source": "BundleStopper.java:47"
        },
        {
          "method": "org.eclipse.core.runtime.adaptor.EclipseAdaptor.frameworkStopping",
          "source": "EclipseAdaptor.java:472"
        },
        {
          "method": "org.eclipse.osgi.framework.internal.core.Framework.shutdown",
          "source": "Framework.java:431"
        },
        {
          "method": "org.eclipse.osgi.framework.internal.core.SystemBundle$1.run",
          "source": "SystemBundle.java:181"
        },
        {
          "method": "java.lang.Thread.run",
          "source": "Thread.java:534"
        }
      ],
      "number": 7,
      "commentIndex": 0,
      "bugId": "64850",
      "date": "2004-05-31T23:42:30+02:00",
      "product": "CDT",
      "component": "cdt-core",
      "severity": "normal"
    }
  ],
  "groupId": "64850",
  "bugId": "64850",
  "date": "2004-05-31T23:42:30+02:00",
  "product": "CDT",
  "component": "cdt-core",
  "severity": "normal"
}