{
  "comments": [
    "3.0RC1\n\n- lock workspace by a job during the following steps (e.g., with the\norg.eclipse.ui.examples.job)\n- open a file\n- choose different encoding with Edit-\u003eEncoding\n-\u003e blocking dialog shows up\n- cancel user operation\n-\u003e file properties show the new encoding (unexpected)\n- change encoding in the file properties\n-\u003e no blocking dialog (unexpected)\n\nThis is inconsistent. \u0027Change Encoding\u0027 should probably aquire a lock on the\nfile (in both cases) and do nothing if it is canceled.",
    "Acctually, after the above step \"cancel user operation\" the following exception\nis thrown:\n\norg.eclipse.core.runtime.OperationCanceledException\n        at org.eclipse.core.internal.jobs.ThreadJob.joinRun(ThreadJob.java:147)\n        at org.eclipse.core.internal.jobs.ImplicitJobs.begin(ImplicitJobs.java:8\n7)\n        at org.eclipse.core.internal.jobs.JobManager.beginRule(JobManager.java:1\n70)\n        at org.eclipse.core.internal.resources.WorkManager.checkIn(WorkManager.j\nava:95)\n        at org.eclipse.core.internal.resources.Workspace.prepareOperation(Worksp\nace.java:1628)\n        at org.eclipse.core.internal.resources.File.create(File.java:105)\n        at org.eclipse.core.internal.resources.ProjectPreferences.save(ProjectPr\neferences.java:271)\n        at org.eclipse.core.internal.preferences.EclipsePreferences.flush(Eclips\nePreferences.java:337)\n        at org.eclipse.core.internal.preferences.EclipsePreferences.flush(Eclips\nePreferences.java:325)\n        at org.eclipse.core.internal.resources.CharsetManager.setCharsetFor(Char\nsetManager.java:174)\n        at org.eclipse.core.internal.resources.File.setCharset(File.java:377)\n        at org.eclipse.core.internal.filebuffers.ResourceTextFileBuffer.setEncod\ning(ResourceTextFileBuffer.java:146)\n        at org.eclipse.ui.editors.text.TextFileDocumentProvider.setEncoding(Text\nFileDocumentProvider.java:1027)\n        at org.eclipse.ui.editors.text.DefaultEncodingSupport.setEncoding(Defaul\ntEncodingSupport.java:113)\n        at org.eclipse.ui.editors.text.DefaultEncodingSupport.setEncoding(Defaul\ntEncodingSupport.java:136)\n        at org.eclipse.ui.editors.text.EncodingActionGroup$PredefinedEncodingAct\nion.run(EncodingActionGroup.java:116)\n        at org.eclipse.ui.texteditor.RetargetTextEditorAction.run(RetargetTextEd\nitorAction.java:240)\n        at org.eclipse.jface.action.Action.runWithEvent(Action.java:881)\n        at org.eclipse.jface.action.ActionContributionItem.handleWidgetSelection\n(ActionContributionItem.java:915)\n        at org.eclipse.jface.action.ActionContributionItem.access$2(ActionContri\nbutionItem.java:866)\n        at org.eclipse.jface.action.ActionContributionItem$7.handleEvent(ActionC\nontributionItem.java:785)\n        at org.eclipse.swt.widgets.EventTable.sendEvent(EventTable.java:82)\n        at org.eclipse.swt.widgets.Widget.sendEvent(Widget.java:796)\n        at org.eclipse.swt.widgets.Display.runDeferredEvents(Display.java:2716)\n        at org.eclipse.swt.widgets.Display.readAndDispatch(Display.java:2382)\n        at org.eclipse.ui.internal.Workbench.runEventLoop(Workbench.java:1363)\n        at org.eclipse.ui.internal.Workbench.runUI(Workbench.java:1334)\n        at org.eclipse.ui.internal.Workbench.createAndRunWorkbench(Workbench.jav\na:253)\n        at org.eclipse.ui.PlatformUI.createAndRunWorkbench(PlatformUI.java:141)\n        at org.eclipse.ui.internal.ide.IDEApplication.run(IDEApplication.java:96\n)\n        at org.eclipse.core.internal.runtime.PlatformActivator$1.run(PlatformAct\nivator.java:334)\n        at org.eclipse.core.runtime.adaptor.EclipseStarter.run(EclipseStarter.ja\nva:273)\n        at org.eclipse.core.runtime.adaptor.EclipseStarter.run(EclipseStarter.ja\nva:128)\n        at sun.reflect.NativeMethodAccessorImpl.invoke0(Native Method)\n        at sun.reflect.NativeMethodAccessorImpl.invoke(NativeMethodAccessorImpl.\njava:39)\n        at sun.reflect.DelegatingMethodAccessorImpl.invoke(DelegatingMethodAcces\nsorImpl.java:25)\n        at java.lang.reflect.Method.invoke(Method.java:324)\n        at org.eclipse.core.launcher.Main.basicRun(Main.java:185)\n        at org.eclipse.core.launcher.Main.run(Main.java:638)\n        at org.eclipse.core.launcher.Main.main(Main.java:622)\norg.eclipse.core.runtime.OperationCanceledException\n",
    "This is an issue with the different implementations and their result. Adding \nAndre."
  ],
  "commentCreationDates": [
    "2004-06-01T15:10:16+02:00",
    "2004-06-01T15:21:22+02:00",
    "2004-06-02T20:01:27+02:00"
  ],
  "traces": [
    {
      "exceptionType": "org.eclipse.core.runtime.OperationCanceledException",
      "elements": [
        {
          "method": "org.eclipse.core.internal.jobs.ThreadJob.joinRun",
          "source": "ThreadJob.java:147"
        },
        {
          "method": "org.eclipse.core.internal.jobs.ImplicitJobs.begin",
          "source": "ImplicitJobs.java:8 7"
        },
        {
          "method": "org.eclipse.core.internal.jobs.JobManager.beginRule",
          "source": "JobManager.java:1 70"
        },
        {
          "method": "org.eclipse.core.internal.resources.WorkManager.checkIn",
          "source": "WorkManager.j ava:95"
        },
        {
          "method": "org.eclipse.core.internal.resources.Workspace.prepareOperation",
          "source": "Worksp ace.java:1628"
        },
        {
          "method": "org.eclipse.core.internal.resources.File.create",
          "source": "File.java:105"
        },
        {
          "method": "org.eclipse.core.internal.resources.ProjectPreferences.save",
          "source": "ProjectPr eferences.java:271"
        },
        {
          "method": "org.eclipse.core.internal.preferences.EclipsePreferences.flush",
          "source": "Eclips ePreferences.java:337"
        },
        {
          "method": "org.eclipse.core.internal.preferences.EclipsePreferences.flush",
          "source": "Eclips ePreferences.java:325"
        },
        {
          "method": "org.eclipse.core.internal.resources.CharsetManager.setCharsetFor",
          "source": "Char setManager.java:174"
        },
        {
          "method": "org.eclipse.core.internal.resources.File.setCharset",
          "source": "File.java:377"
        },
        {
          "method": "org.eclipse.core.internal.filebuffers.ResourceTextFileBuffer.setEncoding",
          "source": "ResourceTextFileBuffer.java:146"
        },
        {
          "method": "org.eclipse.ui.editors.text.TextFileDocumentProvider.setEncoding",
          "source": "Text FileDocumentProvider.java:1027"
        },
        {
          "method": "org.eclipse.ui.editors.text.DefaultEncodingSupport.setEncoding",
          "source": "Defaul tEncodingSupport.java:113"
        },
        {
          "method": "org.eclipse.ui.editors.text.DefaultEncodingSupport.setEncoding",
          "source": "Defaul tEncodingSupport.java:136"
        },
        {
          "method": "org.eclipse.ui.editors.text.EncodingActionGroup$PredefinedEncodingAction.run",
          "source": "EncodingActionGroup.java:116"
        },
        {
          "method": "org.eclipse.ui.texteditor.RetargetTextEditorAction.run",
          "source": "RetargetTextEd itorAction.java:240"
        },
        {
          "method": "org.eclipse.jface.action.Action.runWithEvent",
          "source": "Action.java:881"
        },
        {
          "method": "org.eclipse.jface.action.ActionContributionItem.handleWidgetSelection",
          "source": "ActionContributionItem.java:915"
        },
        {
          "method": "org.eclipse.jface.action.ActionContributionItem.access$2",
          "source": "ActionContri butionItem.java:866"
        },
        {
          "method": "org.eclipse.jface.action.ActionContributionItem$7.handleEvent",
          "source": "ActionC ontributionItem.java:785"
        },
        {
          "method": "org.eclipse.swt.widgets.EventTable.sendEvent",
          "source": "EventTable.java:82"
        },
        {
          "method": "org.eclipse.swt.widgets.Widget.sendEvent",
          "source": "Widget.java:796"
        },
        {
          "method": "org.eclipse.swt.widgets.Display.runDeferredEvents",
          "source": "Display.java:2716"
        },
        {
          "method": "org.eclipse.swt.widgets.Display.readAndDispatch",
          "source": "Display.java:2382"
        },
        {
          "method": "org.eclipse.ui.internal.Workbench.runEventLoop",
          "source": "Workbench.java:1363"
        },
        {
          "method": "org.eclipse.ui.internal.Workbench.runUI",
          "source": "Workbench.java:1334"
        },
        {
          "method": "org.eclipse.ui.internal.Workbench.createAndRunWorkbench",
          "source": "Workbench.jav a:253"
        },
        {
          "method": "org.eclipse.ui.PlatformUI.createAndRunWorkbench",
          "source": "PlatformUI.java:141"
        },
        {
          "method": "org.eclipse.ui.internal.ide.IDEApplication.run",
          "source": "IDEApplication.java:96 "
        },
        {
          "method": "org.eclipse.core.internal.runtime.PlatformActivator$1.run",
          "source": "PlatformAct ivator.java:334"
        },
        {
          "method": "org.eclipse.core.runtime.adaptor.EclipseStarter.run",
          "source": "EclipseStarter.ja va:273"
        },
        {
          "method": "org.eclipse.core.runtime.adaptor.EclipseStarter.run",
          "source": "EclipseStarter.ja va:128"
        },
        {
          "method": "sun.reflect.NativeMethodAccessorImpl.invoke0",
          "source": "Native Method"
        },
        {
          "method": "sun.reflect.NativeMethodAccessorImpl.invoke",
          "source": "NativeMethodAccessorImpl. java:39"
        },
        {
          "method": "sun.reflect.DelegatingMethodAccessorImpl.invoke",
          "source": "DelegatingMethodAcces sorImpl.java:25"
        },
        {
          "method": "java.lang.reflect.Method.invoke",
          "source": "Method.java:324"
        },
        {
          "method": "org.eclipse.core.launcher.Main.basicRun",
          "source": "Main.java:185"
        },
        {
          "method": "org.eclipse.core.launcher.Main.run",
          "source": "Main.java:638"
        },
        {
          "method": "org.eclipse.core.launcher.Main.main",
          "source": "Main.java:622"
        }
      ],
      "number": 0,
      "commentIndex": 1,
      "bugId": "64933",
      "date": "2004-06-01T15:21:22+02:00",
      "product": "Platform",
      "component": "Text",
      "severity": "normal"
    }
  ],
  "groupId": "64933",
  "bugId": "64933",
  "date": "2004-06-01T15:10:16+02:00",
  "product": "Platform",
  "component": "Text",
  "severity": "normal"
}