{
  "comments": [
    "CDT 2.0.0.200405290301\nOn RedHat Linux EL3\n\nDuring a debug session, I open the Registers view\nand it is empty.\nI see a bunch of error messages on the Debugger Console:\nTarget request failed: No symbol \"eax\" (etc.) in current context",
    "The content of the Registers view is driven by the selection in the Debug view. \nThe registers are displayed only if a stack frame is selected. Make sure that \nyou have a stack frame selected in the Debug view.\nThe error messages in the debug console reflect are not bugs, they just reflect \nthe internal communication with gdb.",
    "Hmmm... thanks Mikhail.\n\nOkay, on Suse LES 9 beta 4, I see the registers view as you describe.\nI wasn\u0027t seeing *anything* before on RedHat, and will try to reproduce.\nIn the meantime,\n\nEXPECTED #1: If I have the wrong thing selected when the Registers View\nis visible, the Registers should not be blank but should say something\nlike \"Select a stack frame at a breakpoint to view registers\"\n\nEXPECTED #2: Don\u0027t clog up the Error Log with all these exceptions:\n\n!SUBENTRY 1 org.eclipse.cdt.debug.core 4 5010 Jun 02, 2004 09:47:19.941\n!MESSAGE Target request failed: No symbol \"fs\" in current context.\n!ENTRY org.eclipse.debug.ui 4 120 Jun 02, 2004 09:47:19.959\n!MESSAGE Error logged from Debug UI: \n!STACK 1\norg.eclipse.debug.core.DebugException: Target request failed: No symbol \"fs\" in \ncurrent context.\n        at \norg.eclipse.cdt.debug.internal.core.model.CDebugElement.throwDebugException\n(CDebugElement.java:297)\n        at org.eclipse.cdt.debug.internal.core.model.CDebugElement.requestFailed\n(CDebugElement.java:266)\n        at \norg.eclipse.cdt.debug.internal.core.model.CDebugElement.targetRequestFailed\n(CDebugElement.java:253)\n        at org.eclipse.cdt.debug.internal.core.model.CVariable.getCurrentValue\n(CVariable.java:549)\n        at org.eclipse.cdt.debug.internal.core.model.CGlobalVariable.getValue\n(CGlobalVariable.java:45)\n        at \norg.eclipse.debug.internal.ui.views.variables.VariablesViewContentProvider.hasCh\nildren(VariablesViewContentProvider.ja\nva:295)\n        at \norg.eclipse.debug.internal.ui.views.registers.RegistersViewContentProvider.hasCh\nildren(RegistersViewContentProvider.ja\nva:73)\n        at org.eclipse.jface.viewers.AbstractTreeViewer.isExpandable\n(AbstractTreeViewer.java:1153)\n        at org.eclipse.jface.viewers.AbstractTreeViewer.updatePlus\n(AbstractTreeViewer.java:1597)\n        at org.eclipse.jface.viewers.AbstractTreeViewer.createTreeItem\n(AbstractTreeViewer.java:377)\n        at org.eclipse.jface.viewers.AbstractTreeViewer$1.run\n(AbstractTreeViewer.java:356)\n        at org.eclipse.swt.custom.BusyIndicator.showWhile(BusyIndicator.java:69)\n",
    "\u003eEXPECTED #1: If I have the wrong thing selected when the Registers View\n\u003eis visible, the Registers should not be blank but should say something\n\u003elike \"Select a stack frame at a breakpoint to view registers\"\n\nThe whole Eclipse debug framework is driven by the item selected in the Debug \nview. The registers\u0027 value make sense only in the context of a stack frame. \nThat\u0027s the basics that should be described in the documentation. And the \nVariables view does exactly the same.\n\n\u003eEXPECTED #2: Don\u0027t clog up the Error Log with all these exceptions:\nAgreed.\n\nI have been able to reproduce this and I will submit the fix soon.\n",
    "I am not sure that it\u0027s the same problem, but if I open the Registers view when \nthe session is running, each register has the \"\u003cnot responding\u003e\" label.\nThe fix for this has been submitted.\n\n\u003eEXPECTED #2: Don\u0027t clog up the Error Log with all these exceptions:\nDone.\n",
    "Thanks Mikhail.\n\nI was unable to reproduce the original symptom on RedHat.\n\nVerified on 2.0.0.200406030301\n- No \u003cnot responding\u003e for local host\n- No error messages in log file\n\n",
    "*** Bug 66579 has been marked as a duplicate of this bug. ***"
  ],
  "commentCreationDates": [
    "2004-06-01T20:50:25+02:00",
    "2004-06-01T21:58:52+02:00",
    "2004-06-02T17:03:35+02:00",
    "2004-06-02T17:29:04+02:00",
    "2004-06-02T20:19:12+02:00",
    "2004-06-07T15:30:02+02:00",
    "2004-06-14T22:36:55+02:00"
  ],
  "traces": [
    {
      "exceptionType": "org.eclipse.debug.core.DebugException",
      "message": "Target request failed: No symbol \"fs\" in  current context.",
      "elements": [
        {
          "method": "org.eclipse.cdt.debug.internal.core.model.CDebugElement.throwDebugException",
          "source": "CDebugElement.java:297"
        },
        {
          "method": "org.eclipse.cdt.debug.internal.core.model.CDebugElement.requestFailed",
          "source": "CDebugElement.java:266"
        },
        {
          "method": "org.eclipse.cdt.debug.internal.core.model.CDebugElement.targetRequestFailed",
          "source": "CDebugElement.java:253"
        },
        {
          "method": "org.eclipse.cdt.debug.internal.core.model.CVariable.getCurrentValue",
          "source": "CVariable.java:549"
        },
        {
          "method": "org.eclipse.cdt.debug.internal.core.model.CGlobalVariable.getValue",
          "source": "CGlobalVariable.java:45"
        },
        {
          "method": "org.eclipse.debug.internal.ui.views.variables.VariablesViewContentProvider.hasChildren",
          "source": "VariablesViewContentProvider.ja va:295"
        },
        {
          "method": "org.eclipse.debug.internal.ui.views.registers.RegistersViewContentProvider.hasChildren",
          "source": "RegistersViewContentProvider.ja va:73"
        },
        {
          "method": "org.eclipse.jface.viewers.AbstractTreeViewer.isExpandable",
          "source": "AbstractTreeViewer.java:1153"
        },
        {
          "method": "org.eclipse.jface.viewers.AbstractTreeViewer.updatePlus",
          "source": "AbstractTreeViewer.java:1597"
        },
        {
          "method": "org.eclipse.jface.viewers.AbstractTreeViewer.createTreeItem",
          "source": "AbstractTreeViewer.java:377"
        },
        {
          "method": "org.eclipse.jface.viewers.AbstractTreeViewer$1.run",
          "source": "AbstractTreeViewer.java:356"
        },
        {
          "method": "org.eclipse.swt.custom.BusyIndicator.showWhile",
          "source": "BusyIndicator.java:69"
        }
      ],
      "number": 0,
      "commentIndex": 2,
      "bugId": "65112",
      "date": "2004-06-02T17:03:35+02:00",
      "product": "CDT",
      "component": "cdt-debug",
      "severity": "normal"
    }
  ],
  "groupId": "65112",
  "bugId": "65112",
  "date": "2004-06-01T20:50:25+02:00",
  "product": "CDT",
  "component": "cdt-debug",
  "severity": "normal"
}