{
  "comments": [
    "3.0RC1\n\nI pasted two lines of code at the end of a CU and the reverted to the saved\ncontent. The following excpetion was thrown, but I cannot reproduce anymore.\n\nMay be related to bug 64603 and/or bug 64898.\n\njava.lang.IllegalArgumentException: Index out of bounds\n        at org.eclipse.swt.SWT.error(SWT.java:2677)\n        at org.eclipse.swt.SWT.error(SWT.java:2616)\n        at org.eclipse.swt.SWT.error(SWT.java:2587)\n        at org.eclipse.swt.custom.StyledText.getLocationAtOffset(StyledText.java\n:3818)\n        at org.eclipse.jface.text.CursorLinePainter.drawHighlightLine(CursorLine\nPainter.java:173)\n        at org.eclipse.jface.text.CursorLinePainter.paint(CursorLinePainter.java\n:239)\n        at org.eclipse.jface.text.PaintManager.paint(PaintManager.java:296)\n        at org.eclipse.jface.text.PaintManager.selectionChanged(PaintManager.jav\na:335)\n        at org.eclipse.jface.viewers.Viewer$2.run(Viewer.java:159)\n        at org.eclipse.core.internal.runtime.InternalPlatform.run(InternalPlatfo\nrm.java:615)\n        at org.eclipse.core.runtime.Platform.run(Platform.java:758)\n        at org.eclipse.jface.viewers.Viewer.fireSelectionChanged(Viewer.java:157\n)\n        at org.eclipse.jface.text.TextViewer.fireSelectionChanged(TextViewer.jav\na:2145)\n        at org.eclipse.jface.text.TextViewer.selectionChanged(TextViewer.java:21\n28)\n        at org.eclipse.jface.text.TextViewer.setSelectedRange(TextViewer.java:19\n10)\n        at org.eclipse.jface.text.source.SourceViewer.setRangeIndication(SourceV\niewer.java:818)\n        at org.eclipse.jface.text.source.projection.ProjectionViewer.setRangeInd\nication(ProjectionViewer.java:1010)\n        at org.eclipse.ui.texteditor.AbstractTextEditor.setHighlightRange(Abstra\nctTextEditor.java:4320)\n        at org.eclipse.jdt.internal.ui.javaeditor.JavaEditor.setSelection(JavaEd\nitor.java:2596)\n        at org.eclipse.jdt.internal.ui.javaeditor.JavaEditor.setSelection(JavaEd\nitor.java:2674)\n        at org.eclipse.jdt.internal.ui.javaeditor.CompilationUnitEditor$Remember\nedSelection.restore(CompilationUnitEditor.java:843)\n        at org.eclipse.jdt.internal.ui.javaeditor.CompilationUnitEditor.restoreS\nelection(CompilationUnitEditor.java:1810)\n        at org.eclipse.ui.texteditor.AbstractTextEditor$4.run(AbstractTextEditor\n.java:317)\n        at org.eclipse.ui.texteditor.AbstractTextEditor$ElementStateListener.exe\ncute(AbstractTextEditor.java:404)\n        at org.eclipse.ui.texteditor.AbstractTextEditor$ElementStateListener.ele\nmentContentReplaced(AbstractTextEditor.java:321)\n        at org.eclipse.ui.editors.text.TextFileDocumentProvider$FileBufferListen\ner.bufferContentReplaced(TextFileDocumentProvider.java:226)\n        at org.eclipse.core.internal.filebuffers.TextFileBufferManager.fireBuffe\nrContentReplaced(TextFileBufferManager.java:256)\n        at org.eclipse.core.internal.filebuffers.ResourceTextFileBuffer.revert(R\nesourceTextFileBuffer.java:204)\n        at org.eclipse.ui.editors.text.TextFileDocumentProvider$1.execute(TextFi\nleDocumentProvider.java:589)\n        at org.eclipse.ui.editors.text.TextFileDocumentProvider$DocumentProvider\nOperation.run(TextFileDocumentProvider.java:105)\n        at org.eclipse.ui.actions.WorkspaceModifyDelegatingOperation.execute(Wor\nkspaceModifyDelegatingOperation.java:67)\n        at org.eclipse.ui.actions.WorkspaceModifyOperation$1.run(WorkspaceModify\nOperation.java:91)\n        at org.eclipse.core.internal.resources.Workspace.run(Workspace.java:1673\n)\n        at org.eclipse.ui.actions.WorkspaceModifyOperation.run(WorkspaceModifyOp\neration.java:105)\n        at org.eclipse.ui.internal.editors.text.WorkspaceOperationRunner.run(Wor\nkspaceOperationRunner.java:73)\n        at org.eclipse.ui.internal.editors.text.WorkspaceOperationRunner.run(Wor\nkspaceOperationRunner.java:63)\n        at org.eclipse.ui.editors.text.TextFileDocumentProvider.executeOperation\n(TextFileDocumentProvider.java:403)\n        at org.eclipse.ui.editors.text.TextFileDocumentProvider.resetDocument(Te\nxtFileDocumentProvider.java:607)\n        at org.eclipse.ui.texteditor.AbstractTextEditor.performRevert(AbstractTe\nxtEditor.java:3506)\n        at org.eclipse.ui.texteditor.AbstractTextEditor.doRevertToSaved(Abstract\nTextEditor.java:3489)\n        at org.eclipse.ui.texteditor.StatusTextEditor.doRevertToSaved(StatusText\nEditor.java:183)\n        at org.eclipse.ui.texteditor.RevertToSavedAction.run(RevertToSavedAction\n.java:47)\n        at org.eclipse.jface.action.Action.runWithEvent(Action.java:881)\n        at org.eclipse.ui.actions.RetargetAction.runWithEvent(RetargetAction.jav\na:212)\n        at org.eclipse.jface.action.ActionContributionItem.handleWidgetSelection\n(ActionContributionItem.java:915)\n        at org.eclipse.jface.action.ActionContributionItem.access$2(ActionContri\nbutionItem.java:866)\n        at org.eclipse.jface.action.ActionContributionItem$7.handleEvent(ActionC\nontributionItem.java:785)\n        at org.eclipse.swt.widgets.EventTable.sendEvent(EventTable.java:82)\n        at org.eclipse.swt.widgets.Widget.sendEvent(Widget.java:796)\n        at org.eclipse.swt.widgets.Display.runDeferredEvents(Display.java:2716)\n        at org.eclipse.swt.widgets.Display.readAndDispatch(Display.java:2382)\n        at org.eclipse.ui.internal.Workbench.runEventLoop(Workbench.java:1363)\n        at org.eclipse.ui.internal.Workbench.runUI(Workbench.java:1334)\n        at org.eclipse.ui.internal.Workbench.createAndRunWorkbench(Workbench.jav\na:253)\n        at org.eclipse.ui.PlatformUI.createAndRunWorkbench(PlatformUI.java:141)\n        at org.eclipse.ui.internal.ide.IDEApplication.run(IDEApplication.java:96\n)\n        at org.eclipse.core.internal.runtime.PlatformActivator$1.run(PlatformAct\nivator.java:334)\n        at org.eclipse.core.runtime.adaptor.EclipseStarter.run(EclipseStarter.ja\nva:273)\n        at org.eclipse.core.runtime.adaptor.EclipseStarter.run(EclipseStarter.ja\nva:128)\n        at sun.reflect.NativeMethodAccessorImpl.invoke0(Native Method)\n        at sun.reflect.NativeMethodAccessorImpl.invoke(NativeMethodAccessorImpl.\njava:39)\n        at sun.reflect.DelegatingMethodAccessorImpl.invoke(DelegatingMethodAcces\nsorImpl.java:25)\n        at java.lang.reflect.Method.invoke(Method.java:324)\n        at org.eclipse.core.launcher.Main.basicRun(Main.java:185)\n        at org.eclipse.core.launcher.Main.run(Main.java:638)\n        at org.eclipse.core.launcher.Main.main(Main.java:622)",
    "\n\n*** This bug has been marked as a duplicate of 64898 ***"
  ],
  "commentCreationDates": [
    "2004-06-02T11:32:24+02:00",
    "2004-06-02T19:54:38+02:00"
  ],
  "traces": [
    {
      "exceptionType": "java.lang.IllegalArgumentException",
      "message": "Index out of bounds",
      "elements": [
        {
          "method": "org.eclipse.swt.SWT.error",
          "source": "SWT.java:2677"
        },
        {
          "method": "org.eclipse.swt.SWT.error",
          "source": "SWT.java:2616"
        },
        {
          "method": "org.eclipse.swt.SWT.error",
          "source": "SWT.java:2587"
        },
        {
          "method": "org.eclipse.swt.custom.StyledText.getLocationAtOffset",
          "source": "StyledText.java :3818"
        },
        {
          "method": "org.eclipse.jface.text.CursorLinePainter.drawHighlightLine",
          "source": "CursorLine Painter.java:173"
        },
        {
          "method": "org.eclipse.jface.text.CursorLinePainter.paint",
          "source": "CursorLinePainter.java :239"
        },
        {
          "method": "org.eclipse.jface.text.PaintManager.paint",
          "source": "PaintManager.java:296"
        },
        {
          "method": "org.eclipse.jface.text.PaintManager.selectionChanged",
          "source": "PaintManager.jav a:335"
        },
        {
          "method": "org.eclipse.jface.viewers.Viewer$2.run",
          "source": "Viewer.java:159"
        },
        {
          "method": "org.eclipse.core.internal.runtime.InternalPlatform.run",
          "source": "InternalPlatfo rm.java:615"
        },
        {
          "method": "org.eclipse.core.runtime.Platform.run",
          "source": "Platform.java:758"
        },
        {
          "method": "org.eclipse.jface.viewers.Viewer.fireSelectionChanged",
          "source": "Viewer.java:157 "
        },
        {
          "method": "org.eclipse.jface.text.TextViewer.fireSelectionChanged",
          "source": "TextViewer.jav a:2145"
        },
        {
          "method": "org.eclipse.jface.text.TextViewer.selectionChanged",
          "source": "TextViewer.java:21 28"
        },
        {
          "method": "org.eclipse.jface.text.TextViewer.setSelectedRange",
          "source": "TextViewer.java:19 10"
        },
        {
          "method": "org.eclipse.jface.text.source.SourceViewer.setRangeIndication",
          "source": "SourceV iewer.java:818"
        },
        {
          "method": "org.eclipse.jface.text.source.projection.ProjectionViewer.setRangeIndication",
          "source": "ProjectionViewer.java:1010"
        },
        {
          "method": "org.eclipse.ui.texteditor.AbstractTextEditor.setHighlightRange",
          "source": "Abstra ctTextEditor.java:4320"
        },
        {
          "method": "org.eclipse.jdt.internal.ui.javaeditor.JavaEditor.setSelection",
          "source": "JavaEd itor.java:2596"
        },
        {
          "method": "org.eclipse.jdt.internal.ui.javaeditor.JavaEditor.setSelection",
          "source": "JavaEd itor.java:2674"
        },
        {
          "method": "org.eclipse.jdt.internal.ui.javaeditor.CompilationUnitEditor$RememberedSelection.restore",
          "source": "CompilationUnitEditor.java:843"
        },
        {
          "method": "org.eclipse.jdt.internal.ui.javaeditor.CompilationUnitEditor.restoreSelection",
          "source": "CompilationUnitEditor.java:1810"
        },
        {
          "method": "org.eclipse.ui.texteditor.AbstractTextEditor$4.run",
          "source": "AbstractTextEditor .java:317"
        },
        {
          "method": "org.eclipse.ui.texteditor.AbstractTextEditor$ElementStateListener.execute",
          "source": "AbstractTextEditor.java:404"
        },
        {
          "method": "org.eclipse.ui.texteditor.AbstractTextEditor$ElementStateListener.elementContentReplaced",
          "source": "AbstractTextEditor.java:321"
        },
        {
          "method": "org.eclipse.ui.editors.text.TextFileDocumentProvider$FileBufferListener.bufferContentReplaced",
          "source": "TextFileDocumentProvider.java:226"
        },
        {
          "method": "org.eclipse.core.internal.filebuffers.TextFileBufferManager.fireBufferContentReplaced",
          "source": "TextFileBufferManager.java:256"
        },
        {
          "method": "org.eclipse.core.internal.filebuffers.ResourceTextFileBuffer.revert",
          "source": "R esourceTextFileBuffer.java:204"
        },
        {
          "method": "org.eclipse.ui.editors.text.TextFileDocumentProvider$1.execute",
          "source": "TextFi leDocumentProvider.java:589"
        },
        {
          "method": "org.eclipse.ui.editors.text.TextFileDocumentProvider$DocumentProviderOperation.run",
          "source": "TextFileDocumentProvider.java:105"
        },
        {
          "method": "org.eclipse.ui.actions.WorkspaceModifyDelegatingOperation.execute",
          "source": "Wor kspaceModifyDelegatingOperation.java:67"
        },
        {
          "method": "org.eclipse.ui.actions.WorkspaceModifyOperation$1.run",
          "source": "WorkspaceModify Operation.java:91"
        },
        {
          "method": "org.eclipse.core.internal.resources.Workspace.run",
          "source": "Workspace.java:1673 "
        },
        {
          "method": "org.eclipse.ui.actions.WorkspaceModifyOperation.run",
          "source": "WorkspaceModifyOp eration.java:105"
        },
        {
          "method": "org.eclipse.ui.internal.editors.text.WorkspaceOperationRunner.run",
          "source": "Wor kspaceOperationRunner.java:73"
        },
        {
          "method": "org.eclipse.ui.internal.editors.text.WorkspaceOperationRunner.run",
          "source": "Wor kspaceOperationRunner.java:63"
        },
        {
          "method": "org.eclipse.ui.editors.text.TextFileDocumentProvider.executeOperation",
          "source": "TextFileDocumentProvider.java:403"
        },
        {
          "method": "org.eclipse.ui.editors.text.TextFileDocumentProvider.resetDocument",
          "source": "Te xtFileDocumentProvider.java:607"
        },
        {
          "method": "org.eclipse.ui.texteditor.AbstractTextEditor.performRevert",
          "source": "AbstractTe xtEditor.java:3506"
        },
        {
          "method": "org.eclipse.ui.texteditor.AbstractTextEditor.doRevertToSaved",
          "source": "Abstract TextEditor.java:3489"
        },
        {
          "method": "org.eclipse.ui.texteditor.StatusTextEditor.doRevertToSaved",
          "source": "StatusText Editor.java:183"
        },
        {
          "method": "org.eclipse.ui.texteditor.RevertToSavedAction.run",
          "source": "RevertToSavedAction .java:47"
        },
        {
          "method": "org.eclipse.jface.action.Action.runWithEvent",
          "source": "Action.java:881"
        },
        {
          "method": "org.eclipse.ui.actions.RetargetAction.runWithEvent",
          "source": "RetargetAction.jav a:212"
        },
        {
          "method": "org.eclipse.jface.action.ActionContributionItem.handleWidgetSelection",
          "source": "ActionContributionItem.java:915"
        },
        {
          "method": "org.eclipse.jface.action.ActionContributionItem.access$2",
          "source": "ActionContri butionItem.java:866"
        },
        {
          "method": "org.eclipse.jface.action.ActionContributionItem$7.handleEvent",
          "source": "ActionC ontributionItem.java:785"
        },
        {
          "method": "org.eclipse.swt.widgets.EventTable.sendEvent",
          "source": "EventTable.java:82"
        },
        {
          "method": "org.eclipse.swt.widgets.Widget.sendEvent",
          "source": "Widget.java:796"
        },
        {
          "method": "org.eclipse.swt.widgets.Display.runDeferredEvents",
          "source": "Display.java:2716"
        },
        {
          "method": "org.eclipse.swt.widgets.Display.readAndDispatch",
          "source": "Display.java:2382"
        },
        {
          "method": "org.eclipse.ui.internal.Workbench.runEventLoop",
          "source": "Workbench.java:1363"
        },
        {
          "method": "org.eclipse.ui.internal.Workbench.runUI",
          "source": "Workbench.java:1334"
        },
        {
          "method": "org.eclipse.ui.internal.Workbench.createAndRunWorkbench",
          "source": "Workbench.jav a:253"
        },
        {
          "method": "org.eclipse.ui.PlatformUI.createAndRunWorkbench",
          "source": "PlatformUI.java:141"
        },
        {
          "method": "org.eclipse.ui.internal.ide.IDEApplication.run",
          "source": "IDEApplication.java:96 "
        },
        {
          "method": "org.eclipse.core.internal.runtime.PlatformActivator$1.run",
          "source": "PlatformAct ivator.java:334"
        },
        {
          "method": "org.eclipse.core.runtime.adaptor.EclipseStarter.run",
          "source": "EclipseStarter.ja va:273"
        },
        {
          "method": "org.eclipse.core.runtime.adaptor.EclipseStarter.run",
          "source": "EclipseStarter.ja va:128"
        },
        {
          "method": "sun.reflect.NativeMethodAccessorImpl.invoke0",
          "source": "Native Method"
        },
        {
          "method": "sun.reflect.NativeMethodAccessorImpl.invoke",
          "source": "NativeMethodAccessorImpl. java:39"
        },
        {
          "method": "sun.reflect.DelegatingMethodAccessorImpl.invoke",
          "source": "DelegatingMethodAcces sorImpl.java:25"
        },
        {
          "method": "java.lang.reflect.Method.invoke",
          "source": "Method.java:324"
        },
        {
          "method": "org.eclipse.core.launcher.Main.basicRun",
          "source": "Main.java:185"
        },
        {
          "method": "org.eclipse.core.launcher.Main.run",
          "source": "Main.java:638"
        },
        {
          "method": "org.eclipse.core.launcher.Main.main",
          "source": "Main.java:622"
        }
      ],
      "number": 0,
      "commentIndex": 0,
      "bugId": "65244",
      "duplicateId": "64898",
      "date": "2004-06-02T11:32:24+02:00",
      "product": "JDT",
      "component": "Text",
      "severity": "normal"
    }
  ],
  "groupId": "64898",
  "bugId": "65244",
  "duplicateId": "64898",
  "date": "2004-06-02T11:32:24+02:00",
  "product": "JDT",
  "component": "Text",
  "severity": "normal"
}