{
  "comments": [
    "When attempting to install the latest EMF from the update site into a clean install of RC1, I get the \nfollowing error:\n\n!SUBENTRY 1 org.eclipse.update.core 4 0 Jun 04, 2004 08:10:44.927\n!MESSAGE The File \"/tmp/1896266879/eclipse/.update/1086353894707/1086353894708/\neclipse50944.tmp\" is not a valid JAR file. [invalid END header (bad central directory offset)]\n!STACK 0\njava.util.zip.ZipException: invalid END header (bad central directory offset)\n        at java.util.zip.ZipFile.open(Native Method)\n        at java.util.zip.ZipFile.\u003cinit\u003e(ZipFile.java:112)\n        at java.util.jar.JarFile.\u003cinit\u003e(JarFile.java:127)\n        at java.util.jar.JarFile.\u003cinit\u003e(JarFile.java:92)\n        at org.eclipse.update.internal.security.JarVerifier.init(JarVerifier.java:123)\n        at org.eclipse.update.internal.security.JarVerifier.verify(JarVerifier.java:229)\n        at org.eclipse.update.core.Feature.verifyReferences(Feature.java:933)\n        at org.eclipse.update.core.Feature.install(Feature.java:353)\n        at org.eclipse.update.internal.core.SiteFile.install(SiteFile.java:78)\n        at org.eclipse.update.internal.core.ConfiguredSite.install(ConfiguredSite.java:121)\n        at org.eclipse.update.internal.core.ConfiguredSite.install(ConfiguredSite.java:85)\n        at org.eclipse.update.internal.operations.InstallOperation.execute(InstallOperation.java:73)\n        at org.eclipse.update.internal.operations.BatchInstallOperation.execute(BatchInstallOperation.java:\n81)\n        at org.eclipse.update.internal.ui.wizards.InstallWizard$1.run(InstallWizard.java:144)\n        at org.eclipse.jface.operation.ModalContext$ModalContextThread.run(ModalContext.java:101)",
    "Per comments in EMF FAQ, there is currently no working UM site for EMF/SDO/XSD. \n\nhttp://dev.eclipse.org/viewcvs/indextools.cgi/~checkout~/emf-home/faq/index.html#dnl1\n\nIf you really want to install an old version of EMF (May 8, 2am), you can do so\nfrom here:\n\nhttp://download.eclipse.org/tools/emf/updates/\nhttp://fullmoon.torolab.ibm.com/tools/emf/updates/\n\nHowever, there\u0027s no guarantee this will be compatible/functional for the latest\nrelease of Eclipse.\n\nIn the event that an UM site becomes available with regular updates\n(2.0.0.yyyymmddhhmm releases), it will be added into the FAQ, the What\u0027s New,\nand the nav on the EMF/XSD sites. Until then, consider that there is no UM site\nfor EMF/XSD 2.0, for Eclipse 3.0. (There\u0027s an UM site for Eclipse 2.1, however,\nat http://update.eclipse.org/updates\n\nTicket closed. "
  ],
  "commentCreationDates": [
    "2004-06-04T15:13:11+02:00",
    "2004-06-04T19:16:08+02:00"
  ],
  "traces": [
    {
      "exceptionType": "java.util.zip.ZipException",
      "message": "invalid END header (bad central directory offset)",
      "elements": [
        {
          "method": "java.util.zip.ZipFile.open",
          "source": "Native Method"
        },
        {
          "method": "java.util.zip.ZipFile.\u003cinit\u003e",
          "source": "ZipFile.java:112"
        },
        {
          "method": "java.util.jar.JarFile.\u003cinit\u003e",
          "source": "JarFile.java:127"
        },
        {
          "method": "java.util.jar.JarFile.\u003cinit\u003e",
          "source": "JarFile.java:92"
        },
        {
          "method": "org.eclipse.update.internal.security.JarVerifier.init",
          "source": "JarVerifier.java:123"
        },
        {
          "method": "org.eclipse.update.internal.security.JarVerifier.verify",
          "source": "JarVerifier.java:229"
        },
        {
          "method": "org.eclipse.update.core.Feature.verifyReferences",
          "source": "Feature.java:933"
        },
        {
          "method": "org.eclipse.update.core.Feature.install",
          "source": "Feature.java:353"
        },
        {
          "method": "org.eclipse.update.internal.core.SiteFile.install",
          "source": "SiteFile.java:78"
        },
        {
          "method": "org.eclipse.update.internal.core.ConfiguredSite.install",
          "source": "ConfiguredSite.java:121"
        },
        {
          "method": "org.eclipse.update.internal.core.ConfiguredSite.install",
          "source": "ConfiguredSite.java:85"
        },
        {
          "method": "org.eclipse.update.internal.operations.InstallOperation.execute",
          "source": "InstallOperation.java:73"
        },
        {
          "method": "org.eclipse.update.internal.operations.BatchInstallOperation.execute",
          "source": "BatchInstallOperation.java: 81"
        },
        {
          "method": "org.eclipse.update.internal.ui.wizards.InstallWizard$1.run",
          "source": "InstallWizard.java:144"
        },
        {
          "method": "org.eclipse.jface.operation.ModalContext$ModalContextThread.run",
          "source": "ModalContext.java:101"
        }
      ],
      "number": 0,
      "commentIndex": 0,
      "bugId": "65709",
      "date": "2004-06-04T15:13:11+02:00",
      "product": "EMF",
      "component": "Core",
      "severity": "normal"
    }
  ],
  "groupId": "65709",
  "bugId": "65709",
  "date": "2004-06-04T15:13:11+02:00",
  "product": "EMF",
  "component": "Core",
  "severity": "normal"
}