{
  "comments": [
    "Smoke test input 2004-06-07, J9 2004-05-12\n\nDuring the smoke test I got this exception in the log:\n\n!ENTRY org.eclipse.core.runtime 4 2 Jun 07, 2004 16:19:25.823\n!MESSAGE Problems occurred when invoking code from plug-in: \"org.eclipse.core.ru\nntime\".\n!STACK 0\njava.lang.IllegalArgumentException: Index out of bounds\n        at java.lang.Throwable.\u003cinit\u003e(Throwable.java)\n        at java.lang.Throwable.\u003cinit\u003e(Throwable.java)\n        at org.eclipse.swt.SWT.error(SWT.java:2677)\n        at org.eclipse.swt.SWT.error(SWT.java)\n        at org.eclipse.swt.SWT.error(SWT.java)\n        at org.eclipse.swt.custom.StyledText.getLocationAtOffset(StyledText.java\n)\n        at org.eclipse.jface.text.CursorLinePainter.drawHighlightLine(CursorLine\nPainter.java:173)\n        at org.eclipse.jface.text.CursorLinePainter.paint(CursorLinePainter.java\n:239)\n        at org.eclipse.jface.text.PaintManager.paint(PaintManager.java)\n        at org.eclipse.jface.text.PaintManager.selectionChanged(PaintManager.jav\na:335)\n        at org.eclipse.jface.viewers.Viewer$2.run(Viewer.java)\n        at org.eclipse.core.internal.runtime.InternalPlatform.run(InternalPlatfo\nrm.java)\n        at org.eclipse.core.runtime.Platform.run(Platform.java)\n        at org.eclipse.jface.viewers.Viewer.fireSelectionChanged(Viewer.java)\n        at org.eclipse.jface.text.TextViewer.fireSelectionChanged(TextViewer.jav\na:2145)\n        at org.eclipse.jface.text.TextViewer.selectionChanged(TextViewer.java:21\n28)\n        at org.eclipse.jface.text.TextViewer.setSelectedRange(TextViewer.java:19\n10)\n        at org.eclipse.jface.text.DefaultUndoManager.selectAndReveal(DefaultUndo\nManager.java:832)\n        at org.eclipse.jface.text.DefaultUndoManager$TextCommand.undo(DefaultUnd\noManager.java:94)\n        at org.eclipse.jface.text.DefaultUndoManager.internalUndo(DefaultUndoMan\nager.java:556)\n        at org.eclipse.jface.text.DefaultUndoManager.undo(DefaultUndoManager.jav\na:821)\n        at org.eclipse.jface.text.TextViewer.doOperation(TextViewer.java:3358)\n        at org.eclipse.jface.text.source.SourceViewer.doOperation(SourceViewer.j\nava:744)\n        at org.eclipse.jface.text.source.projection.ProjectionViewer.doOperation\n(ProjectionViewer.java:1153)\n        at org.eclipse.jdt.internal.ui.javaeditor.JavaSourceViewer.doOperation(J\navaSourceViewer.java:151)\n        at org.eclipse.jdt.internal.ui.javaeditor.CompilationUnitEditor$AdaptedS\nourceViewer.doOperation(CompilationUnitEditor.java:188)\n        at org.eclipse.ui.texteditor.TextOperationAction$1.run(TextOperationActi\non.java:122)\n        at org.eclipse.swt.custom.BusyIndicator.showWhile(BusyIndicator.java)\n        at org.eclipse.ui.texteditor.TextOperationAction.run(TextOperationAction\n.java:120)\n        at org.eclipse.jface.action.Action.runWithEvent(Action.java:881)\n        at org.eclipse.ui.commands.ActionHandler.execute(ActionHandler.java:141)\n\n        at org.eclipse.ui.internal.commands.Command.execute(Command.java:132)\n        at org.eclipse.ui.internal.keys.WorkbenchKeyboard.executeCommand(Workben\nchKeyboard.java:469)\n        at org.eclipse.ui.internal.keys.WorkbenchKeyboard.press(WorkbenchKeyboar\nd.java)\n        at org.eclipse.ui.internal.keys.WorkbenchKeyboard.processKeyEvent(Workbe\nnchKeyboard.java:928)\n        at org.eclipse.ui.internal.keys.WorkbenchKeyboard.filterKeySequenceBindi\nngs(WorkbenchKeyboard.java:546)\n        at org.eclipse.ui.internal.keys.WorkbenchKeyboard.access$2(WorkbenchKeyb\noard.java:494)\n        at org.eclipse.ui.internal.keys.WorkbenchKeyboard$1.handleEvent(Workbenc\nhKeyboard.java:259)\n        at org.eclipse.swt.widgets.EventTable.sendEvent(EventTable.java)\n        at org.eclipse.swt.widgets.Display.filterEvent(Display.java)\n        at org.eclipse.swt.widgets.Widget.sendEvent(Widget.java)\n        at org.eclipse.swt.widgets.Widget.sendEvent(Widget.java)\n        at org.eclipse.swt.widgets.Widget.sendEvent(Widget.java)\n        at org.eclipse.swt.widgets.Control.sendKeyEvent(Control.java:1725)\n        at org.eclipse.swt.widgets.Control.sendKeyEvent(Control.java:1721)\n        at org.eclipse.swt.widgets.Control.WM_CHAR(Control.java:3049)\n        at org.eclipse.swt.widgets.Control.windowProc(Control.java)\n        at org.eclipse.swt.widgets.Display.windowProc(Display.java)\n        at org.eclipse.swt.internal.win32.OS.DispatchMessageW(Native Method)\n        at org.eclipse.swt.internal.win32.OS.DispatchMessage(OS.java)\n        at org.eclipse.swt.widgets.Display.readAndDispatch(Display.java)\n        at org.eclipse.ui.internal.Workbench.runEventLoop(Workbench.java:1363)\n        at org.eclipse.ui.internal.Workbench.runUI(Workbench.java:1334)\n        at org.eclipse.ui.internal.Workbench.createAndRunWorkbench(Workbench.jav\na:253)\n        at org.eclipse.ui.PlatformUI.createAndRunWorkbench(PlatformUI.java:141)\n        at org.eclipse.ui.internal.ide.IDEApplication.run(IDEApplication.java:96\n)\n        at org.eclipse.core.internal.runtime.PlatformActivator$1.run(PlatformAct\nivator.java:334)\n        at org.eclipse.core.runtime.adaptor.EclipseStarter.run(EclipseStarter.ja\nva:273)\n        at org.eclipse.core.runtime.adaptor.EclipseStarter.run(EclipseStarter.ja\nva:128)\n        at sun.reflect.NativeMethodAccessorImpl.invoke0(Native Method)\n        at sun.reflect.NativeMethodAccessorImpl.invoke(NativeMethodAccessorImpl.\njava:79)\n        at sun.reflect.DelegatingMethodAccessorImpl.invoke(DelegatingMethodAcces\nsorImpl.java:41)\n        at java.lang.reflect.Method.invoke(Method.java:386)\n        at org.eclipse.core.launcher.Main.basicRun(Main.java:185)\n        at org.eclipse.core.launcher.Main.run(Main.java:638)\n        at org.eclipse.core.launcher.Main.main(Main.java:622)\n\n\nUnfortunately, I didn\u0027t notice it right away, so I can\u0027t say what caused it. It\nmight have happened while I was undoing the generation of getters/setters while\nin segmented mode.",
    "\n\n*** This bug has been marked as a duplicate of 64898 ***"
  ],
  "commentCreationDates": [
    "2004-06-07T16:30:26+02:00",
    "2004-06-07T18:57:32+02:00"
  ],
  "traces": [
    {
      "exceptionType": "java.lang.IllegalArgumentException",
      "message": "Index out of bounds",
      "elements": [
        {
          "method": "java.lang.Throwable.\u003cinit\u003e",
          "source": "Throwable.java"
        },
        {
          "method": "java.lang.Throwable.\u003cinit\u003e",
          "source": "Throwable.java"
        },
        {
          "method": "org.eclipse.swt.SWT.error",
          "source": "SWT.java:2677"
        },
        {
          "method": "org.eclipse.swt.SWT.error",
          "source": "SWT.java"
        },
        {
          "method": "org.eclipse.swt.SWT.error",
          "source": "SWT.java"
        },
        {
          "method": "org.eclipse.swt.custom.StyledText.getLocationAtOffset",
          "source": "StyledText.java "
        },
        {
          "method": "org.eclipse.jface.text.CursorLinePainter.drawHighlightLine",
          "source": "CursorLine Painter.java:173"
        },
        {
          "method": "org.eclipse.jface.text.CursorLinePainter.paint",
          "source": "CursorLinePainter.java :239"
        },
        {
          "method": "org.eclipse.jface.text.PaintManager.paint",
          "source": "PaintManager.java"
        },
        {
          "method": "org.eclipse.jface.text.PaintManager.selectionChanged",
          "source": "PaintManager.jav a:335"
        },
        {
          "method": "org.eclipse.jface.viewers.Viewer$2.run",
          "source": "Viewer.java"
        },
        {
          "method": "org.eclipse.core.internal.runtime.InternalPlatform.run",
          "source": "InternalPlatfo rm.java"
        },
        {
          "method": "org.eclipse.core.runtime.Platform.run",
          "source": "Platform.java"
        },
        {
          "method": "org.eclipse.jface.viewers.Viewer.fireSelectionChanged",
          "source": "Viewer.java"
        },
        {
          "method": "org.eclipse.jface.text.TextViewer.fireSelectionChanged",
          "source": "TextViewer.jav a:2145"
        },
        {
          "method": "org.eclipse.jface.text.TextViewer.selectionChanged",
          "source": "TextViewer.java:21 28"
        },
        {
          "method": "org.eclipse.jface.text.TextViewer.setSelectedRange",
          "source": "TextViewer.java:19 10"
        },
        {
          "method": "org.eclipse.jface.text.DefaultUndoManager.selectAndReveal",
          "source": "DefaultUndo Manager.java:832"
        },
        {
          "method": "org.eclipse.jface.text.DefaultUndoManager$TextCommand.undo",
          "source": "DefaultUnd oManager.java:94"
        },
        {
          "method": "org.eclipse.jface.text.DefaultUndoManager.internalUndo",
          "source": "DefaultUndoMan ager.java:556"
        },
        {
          "method": "org.eclipse.jface.text.DefaultUndoManager.undo",
          "source": "DefaultUndoManager.jav a:821"
        },
        {
          "method": "org.eclipse.jface.text.TextViewer.doOperation",
          "source": "TextViewer.java:3358"
        },
        {
          "method": "org.eclipse.jface.text.source.SourceViewer.doOperation",
          "source": "SourceViewer.j ava:744"
        },
        {
          "method": "org.eclipse.jface.text.source.projection.ProjectionViewer.doOperation",
          "source": "ProjectionViewer.java:1153"
        },
        {
          "method": "org.eclipse.jdt.internal.ui.javaeditor.JavaSourceViewer.doOperation",
          "source": "J avaSourceViewer.java:151"
        },
        {
          "method": "org.eclipse.jdt.internal.ui.javaeditor.CompilationUnitEditor$AdaptedSourceViewer.doOperation",
          "source": "CompilationUnitEditor.java:188"
        },
        {
          "method": "org.eclipse.ui.texteditor.TextOperationAction$1.run",
          "source": "TextOperationActi on.java:122"
        },
        {
          "method": "org.eclipse.swt.custom.BusyIndicator.showWhile",
          "source": "BusyIndicator.java"
        },
        {
          "method": "org.eclipse.ui.texteditor.TextOperationAction.run",
          "source": "TextOperationAction .java:120"
        },
        {
          "method": "org.eclipse.jface.action.Action.runWithEvent",
          "source": "Action.java:881"
        },
        {
          "method": "org.eclipse.ui.commands.ActionHandler.execute",
          "source": "ActionHandler.java:141"
        },
        {
          "method": "org.eclipse.ui.internal.commands.Command.execute",
          "source": "Command.java:132"
        },
        {
          "method": "org.eclipse.ui.internal.keys.WorkbenchKeyboard.executeCommand",
          "source": "Workben chKeyboard.java:469"
        },
        {
          "method": "org.eclipse.ui.internal.keys.WorkbenchKeyboard.press",
          "source": "WorkbenchKeyboar d.java"
        },
        {
          "method": "org.eclipse.ui.internal.keys.WorkbenchKeyboard.processKeyEvent",
          "source": "Workbe nchKeyboard.java:928"
        },
        {
          "method": "org.eclipse.ui.internal.keys.WorkbenchKeyboard.filterKeySequenceBindings",
          "source": "WorkbenchKeyboard.java:546"
        },
        {
          "method": "org.eclipse.ui.internal.keys.WorkbenchKeyboard.access$2",
          "source": "WorkbenchKeyb oard.java:494"
        },
        {
          "method": "org.eclipse.ui.internal.keys.WorkbenchKeyboard$1.handleEvent",
          "source": "Workbenc hKeyboard.java:259"
        },
        {
          "method": "org.eclipse.swt.widgets.EventTable.sendEvent",
          "source": "EventTable.java"
        },
        {
          "method": "org.eclipse.swt.widgets.Display.filterEvent",
          "source": "Display.java"
        },
        {
          "method": "org.eclipse.swt.widgets.Widget.sendEvent",
          "source": "Widget.java"
        },
        {
          "method": "org.eclipse.swt.widgets.Widget.sendEvent",
          "source": "Widget.java"
        },
        {
          "method": "org.eclipse.swt.widgets.Widget.sendEvent",
          "source": "Widget.java"
        },
        {
          "method": "org.eclipse.swt.widgets.Control.sendKeyEvent",
          "source": "Control.java:1725"
        },
        {
          "method": "org.eclipse.swt.widgets.Control.sendKeyEvent",
          "source": "Control.java:1721"
        },
        {
          "method": "org.eclipse.swt.widgets.Control.WM_CHAR",
          "source": "Control.java:3049"
        },
        {
          "method": "org.eclipse.swt.widgets.Control.windowProc",
          "source": "Control.java"
        },
        {
          "method": "org.eclipse.swt.widgets.Display.windowProc",
          "source": "Display.java"
        },
        {
          "method": "org.eclipse.swt.internal.win32.OS.DispatchMessageW",
          "source": "Native Method"
        },
        {
          "method": "org.eclipse.swt.internal.win32.OS.DispatchMessage",
          "source": "OS.java"
        },
        {
          "method": "org.eclipse.swt.widgets.Display.readAndDispatch",
          "source": "Display.java"
        },
        {
          "method": "org.eclipse.ui.internal.Workbench.runEventLoop",
          "source": "Workbench.java:1363"
        },
        {
          "method": "org.eclipse.ui.internal.Workbench.runUI",
          "source": "Workbench.java:1334"
        },
        {
          "method": "org.eclipse.ui.internal.Workbench.createAndRunWorkbench",
          "source": "Workbench.jav a:253"
        },
        {
          "method": "org.eclipse.ui.PlatformUI.createAndRunWorkbench",
          "source": "PlatformUI.java:141"
        },
        {
          "method": "org.eclipse.ui.internal.ide.IDEApplication.run",
          "source": "IDEApplication.java:96 "
        },
        {
          "method": "org.eclipse.core.internal.runtime.PlatformActivator$1.run",
          "source": "PlatformAct ivator.java:334"
        },
        {
          "method": "org.eclipse.core.runtime.adaptor.EclipseStarter.run",
          "source": "EclipseStarter.ja va:273"
        },
        {
          "method": "org.eclipse.core.runtime.adaptor.EclipseStarter.run",
          "source": "EclipseStarter.ja va:128"
        },
        {
          "method": "sun.reflect.NativeMethodAccessorImpl.invoke0",
          "source": "Native Method"
        },
        {
          "method": "sun.reflect.NativeMethodAccessorImpl.invoke",
          "source": "NativeMethodAccessorImpl. java:79"
        },
        {
          "method": "sun.reflect.DelegatingMethodAccessorImpl.invoke",
          "source": "DelegatingMethodAcces sorImpl.java:41"
        },
        {
          "method": "java.lang.reflect.Method.invoke",
          "source": "Method.java:386"
        },
        {
          "method": "org.eclipse.core.launcher.Main.basicRun",
          "source": "Main.java:185"
        },
        {
          "method": "org.eclipse.core.launcher.Main.run",
          "source": "Main.java:638"
        },
        {
          "method": "org.eclipse.core.launcher.Main.main",
          "source": "Main.java:622"
        }
      ],
      "number": 0,
      "commentIndex": 0,
      "bugId": "65972",
      "duplicateId": "64898",
      "date": "2004-06-07T16:30:26+02:00",
      "product": "JDT",
      "component": "Text",
      "severity": "normal"
    }
  ],
  "groupId": "64898",
  "bugId": "65972",
  "duplicateId": "64898",
  "date": "2004-06-07T16:30:26+02:00",
  "product": "JDT",
  "component": "Text",
  "severity": "normal"
}