{
  "comments": [
    "3.0 20040608:08:00\n\nI have a bunch of these exceptions in my log today. I was editing plugin.xml\nfiles all morning, so it must be related. Also note that I do have the manifest\nbuilder enabled on these projects.\n\n!ENTRY org.eclipse.jdt.core 4 4 Jun 08, 2004 10:06:03.981\n!MESSAGE Exception occurred in listener of pre Java resource change notification\n!STACK 0\norg.eclipse.swt.SWTException: Invalid thread access\n        at org.eclipse.swt.SWT.error(SWT.java:2691)\n        at org.eclipse.swt.SWT.error(SWT.java:2616)\n        at org.eclipse.swt.SWT.error(SWT.java:2587)\n        at org.eclipse.swt.widgets.Widget.error(Widget.java:381)\n        at org.eclipse.swt.widgets.Widget.checkWidget(Widget.java:284)\n        at org.eclipse.swt.widgets.Table.setRedraw(Table.java:2260)\n        at org.eclipse.jface.viewers.TableViewer.inputChanged(TableViewer.java:413)\n        at org.eclipse.jface.viewers.ContentViewer.setInput(ContentViewer.java:238)\n        at\norg.eclipse.jface.viewers.StructuredViewer.setInput(StructuredViewer.java:1058)\n        at\norg.eclipse.pde.internal.ui.editor.feature.PluginSection.refresh(PluginSection.java:281)\n        at org.eclipse.ui.forms.ManagedForm.refresh(ManagedForm.java:159)\n        at\norg.eclipse.ui.forms.editor.FormPage$PageForm.staleStateChanged(FormPage.java:53)\n        at\norg.eclipse.ui.forms.AbstractFormPart.markStale(AbstractFormPart.java:116)\n        at\norg.eclipse.pde.internal.ui.editor.feature.PluginSection.modelsChanged(PluginSection.java:261)\n        at\norg.eclipse.pde.internal.core.WorkspaceModelManager.fireModelProviderEvent(WorkspaceModelManager.java:739)\n        at\norg.eclipse.pde.internal.core.WorkspaceModelManager.processModelChanges(WorkspaceModelManager.java:733)\n        at\norg.eclipse.pde.internal.core.WorkspaceModelManager.resourceChanged(WorkspaceModelManager.java:365)\n        at\norg.eclipse.jdt.internal.core.DeltaProcessingState$1.run(DeltaProcessingState.java:408)\n        at\norg.eclipse.core.internal.runtime.InternalPlatform.run(InternalPlatform.java:615)\n        at org.eclipse.core.runtime.Platform.run(Platform.java:758)\n        at\norg.eclipse.jdt.internal.core.DeltaProcessingState.resourceChanged(DeltaProcessingState.java:403)\n        at\norg.eclipse.core.internal.events.NotificationManager$2.run(NotificationManager.java:283)\n        at\norg.eclipse.core.internal.runtime.InternalPlatform.run(InternalPlatform.java:615)\n        at org.eclipse.core.runtime.Platform.run(Platform.java:758)\n        at\norg.eclipse.core.internal.events.NotificationManager.notify(NotificationManager.java:277)\n        at\norg.eclipse.core.internal.events.NotificationManager.broadcastChanges(NotificationManager.java:151)\n        at\norg.eclipse.core.internal.resources.Workspace.broadcastChanges(Workspace.java:172)\n        at\norg.eclipse.core.internal.resources.Workspace.endOperation(Workspace.java:900)\n        at org.eclipse.core.internal.resources.Workspace.run(Workspace.java:1682)\n        at\norg.eclipse.core.internal.events.NotificationManager$NotifyJob.run(NotificationManager.java:38)\n        at org.eclipse.core.internal.jobs.Worker.run(Worker.java:66)",
    "This has been fix a while ago in forms."
  ],
  "commentCreationDates": [
    "2004-06-08T16:53:38+02:00",
    "2005-05-19T18:19:42+02:00"
  ],
  "traces": [
    {
      "exceptionType": "org.eclipse.swt.SWTException",
      "message": "Invalid thread access",
      "elements": [
        {
          "method": "org.eclipse.swt.SWT.error",
          "source": "SWT.java:2691"
        },
        {
          "method": "org.eclipse.swt.SWT.error",
          "source": "SWT.java:2616"
        },
        {
          "method": "org.eclipse.swt.SWT.error",
          "source": "SWT.java:2587"
        },
        {
          "method": "org.eclipse.swt.widgets.Widget.error",
          "source": "Widget.java:381"
        },
        {
          "method": "org.eclipse.swt.widgets.Widget.checkWidget",
          "source": "Widget.java:284"
        },
        {
          "method": "org.eclipse.swt.widgets.Table.setRedraw",
          "source": "Table.java:2260"
        },
        {
          "method": "org.eclipse.jface.viewers.TableViewer.inputChanged",
          "source": "TableViewer.java:413"
        },
        {
          "method": "org.eclipse.jface.viewers.ContentViewer.setInput",
          "source": "ContentViewer.java:238"
        },
        {
          "method": "org.eclipse.jface.viewers.StructuredViewer.setInput",
          "source": "StructuredViewer.java:1058"
        },
        {
          "method": "org.eclipse.pde.internal.ui.editor.feature.PluginSection.refresh",
          "source": "PluginSection.java:281"
        },
        {
          "method": "org.eclipse.ui.forms.ManagedForm.refresh",
          "source": "ManagedForm.java:159"
        },
        {
          "method": "org.eclipse.ui.forms.editor.FormPage$PageForm.staleStateChanged",
          "source": "FormPage.java:53"
        },
        {
          "method": "org.eclipse.ui.forms.AbstractFormPart.markStale",
          "source": "AbstractFormPart.java:116"
        },
        {
          "method": "org.eclipse.pde.internal.ui.editor.feature.PluginSection.modelsChanged",
          "source": "PluginSection.java:261"
        },
        {
          "method": "org.eclipse.pde.internal.core.WorkspaceModelManager.fireModelProviderEvent",
          "source": "WorkspaceModelManager.java:739"
        },
        {
          "method": "org.eclipse.pde.internal.core.WorkspaceModelManager.processModelChanges",
          "source": "WorkspaceModelManager.java:733"
        },
        {
          "method": "org.eclipse.pde.internal.core.WorkspaceModelManager.resourceChanged",
          "source": "WorkspaceModelManager.java:365"
        },
        {
          "method": "org.eclipse.jdt.internal.core.DeltaProcessingState$1.run",
          "source": "DeltaProcessingState.java:408"
        },
        {
          "method": "org.eclipse.core.internal.runtime.InternalPlatform.run",
          "source": "InternalPlatform.java:615"
        },
        {
          "method": "org.eclipse.core.runtime.Platform.run",
          "source": "Platform.java:758"
        },
        {
          "method": "org.eclipse.jdt.internal.core.DeltaProcessingState.resourceChanged",
          "source": "DeltaProcessingState.java:403"
        },
        {
          "method": "org.eclipse.core.internal.events.NotificationManager$2.run",
          "source": "NotificationManager.java:283"
        },
        {
          "method": "org.eclipse.core.internal.runtime.InternalPlatform.run",
          "source": "InternalPlatform.java:615"
        },
        {
          "method": "org.eclipse.core.runtime.Platform.run",
          "source": "Platform.java:758"
        },
        {
          "method": "org.eclipse.core.internal.events.NotificationManager.notify",
          "source": "NotificationManager.java:277"
        },
        {
          "method": "org.eclipse.core.internal.events.NotificationManager.broadcastChanges",
          "source": "NotificationManager.java:151"
        },
        {
          "method": "org.eclipse.core.internal.resources.Workspace.broadcastChanges",
          "source": "Workspace.java:172"
        },
        {
          "method": "org.eclipse.core.internal.resources.Workspace.endOperation",
          "source": "Workspace.java:900"
        },
        {
          "method": "org.eclipse.core.internal.resources.Workspace.run",
          "source": "Workspace.java:1682"
        },
        {
          "method": "org.eclipse.core.internal.events.NotificationManager$NotifyJob.run",
          "source": "NotificationManager.java:38"
        },
        {
          "method": "org.eclipse.core.internal.jobs.Worker.run",
          "source": "Worker.java:66"
        }
      ],
      "number": 0,
      "commentIndex": 0,
      "bugId": "66148",
      "date": "2004-06-08T16:53:38+02:00",
      "product": "PDE",
      "component": "UI",
      "severity": "normal"
    }
  ],
  "groupId": "66148",
  "bugId": "66148",
  "date": "2004-06-08T16:53:38+02:00",
  "product": "PDE",
  "component": "UI",
  "severity": "normal"
}