{
  "comments": [
    "HI,\n\nI am excuting the ajc compiler (aspectj1.2) to weave EJB(1.2) with Aspect.\nI am getting following error,\n\nD:\\aspectj1.2\\bin\u003eajc -inpath D:\\bank-ejb.jar -aspectpath E:\\traceaspect.ja\nr -outjar traceable-bankejb.jar\nABORT\n\nException thrown from AspectJ 1.2\n\nThis might be logged as a bug already -- find current bugs at\n  http://bugs.eclipse.org/bugs/buglist.cgi?product\u003dAspectJ\u0026component\u003dCompiler\n\nBugs for exceptions thrown have titles File:line from the top stack,\ne.g., \"SomeFile.java:243\"\n\nIf you don\u0027t find the exception below in a bug, please add a new bug\nat http://bugs.eclipse.org/bugs/enter_bug.cgi?product\u003dAspectJ\nTo make the bug a priority, please include a test program\nthat can reproduce this exception.\nduplicate entry: META-INF/MANIFEST.MF\nduplicate entry: META-INF/MANIFEST.MF\njava.util.zip.ZipException: duplicate entry: META-INF/MANIFEST.MF\n        at java.util.zip.ZipOutputStream.putNextEntry(ZipOutputStream.java:163)\n        at java.util.jar.JarOutputStream.putNextEntry(JarOutputStream.java:90)\n        at org.aspectj.ajdt.internal.core.builder.AjBuildManager.writeResource\n(Aj\nBuildManager.java:345)\n        at \norg.aspectj.ajdt.internal.core.builder.AjBuildManager.copyResourcesFro\nmJarFile(AjBuildManager.java:289)\n        at \norg.aspectj.ajdt.internal.core.builder.AjBuildManager.copyResourcesToD\nestination(AjBuildManager.java:262)\n        at org.aspectj.ajdt.internal.core.builder.AjBuildManager.doBuild\n(AjBuildM\nanager.java:195)\n        at org.aspectj.ajdt.internal.core.builder.AjBuildManager.batchBuild\n(AjBui\nldManager.java:94)\n        at org.aspectj.ajdt.ajc.AjdtCommand.doCommand(AjdtCommand.java:102)\n        at org.aspectj.ajdt.ajc.AjdtCommand.runCommand(AjdtCommand.java:53)\n        at org.aspectj.tools.ajc.Main.run(Main.java:280)\n        at org.aspectj.tools.ajc.Main.runMain(Main.java:217)\n        at org.aspectj.tools.ajc.Main.main(Main.java:79)\n\n\n1 fail|abort",
    "Created an attachment (id\u003d11780)\nThis is samle ejb to be weaved.\n",
    "\n\n*** This bug has been marked as a duplicate of 57666 ***",
    "Fix released as part of AspectJ 1.2.1"
  ],
  "commentCreationDates": [
    "2004-06-09T12:33:06+02:00",
    "2004-06-09T12:36:58+02:00",
    "2004-07-30T15:08:49+02:00",
    "2004-10-21T10:32:51+02:00"
  ],
  "traces": [
    {
      "exceptionType": "java.util.zip.ZipException",
      "message": "duplicate entry: META-INF/MANIFEST.MF",
      "elements": [
        {
          "method": "java.util.zip.ZipOutputStream.putNextEntry",
          "source": "ZipOutputStream.java:163"
        },
        {
          "method": "java.util.jar.JarOutputStream.putNextEntry",
          "source": "JarOutputStream.java:90"
        },
        {
          "method": "org.aspectj.ajdt.internal.core.builder.AjBuildManager.writeResource",
          "source": "Aj BuildManager.java:345"
        },
        {
          "method": "org.aspectj.ajdt.internal.core.builder.AjBuildManager.copyResourcesFromJarFile",
          "source": "AjBuildManager.java:289"
        },
        {
          "method": "org.aspectj.ajdt.internal.core.builder.AjBuildManager.copyResourcesToDestination",
          "source": "AjBuildManager.java:262"
        },
        {
          "method": "org.aspectj.ajdt.internal.core.builder.AjBuildManager.doBuild",
          "source": "AjBuildM anager.java:195"
        },
        {
          "method": "org.aspectj.ajdt.internal.core.builder.AjBuildManager.batchBuild",
          "source": "AjBui ldManager.java:94"
        },
        {
          "method": "org.aspectj.ajdt.ajc.AjdtCommand.doCommand",
          "source": "AjdtCommand.java:102"
        },
        {
          "method": "org.aspectj.ajdt.ajc.AjdtCommand.runCommand",
          "source": "AjdtCommand.java:53"
        },
        {
          "method": "org.aspectj.tools.ajc.Main.run",
          "source": "Main.java:280"
        },
        {
          "method": "org.aspectj.tools.ajc.Main.runMain",
          "source": "Main.java:217"
        },
        {
          "method": "org.aspectj.tools.ajc.Main.main",
          "source": "Main.java:79"
        }
      ],
      "number": 0,
      "commentIndex": 0,
      "bugId": "66267",
      "duplicateId": "57666",
      "date": "2004-06-09T12:33:06+02:00",
      "product": "AspectJ",
      "component": "Compiler",
      "severity": "blocker"
    }
  ],
  "groupId": "57666",
  "bugId": "66267",
  "duplicateId": "57666",
  "date": "2004-06-09T12:33:06+02:00",
  "product": "AspectJ",
  "component": "Compiler",
  "severity": "blocker"
}