{
  "comments": [
    "I200406110010\n\nQuite often I find this NPE in the log:\n\n\n!ENTRY org.eclipse.ui 4 0 Jun 11, 2004 13:14:37.292\n!MESSAGE java.lang.NullPointerException\n!STACK 0\njava.lang.NullPointerException\n\tat org.eclipse.swt.widgets.Control.kEventControlSetFocusPart(Control.java:1369)\n\tat org.eclipse.swt.widgets.Composite.kEventControlSetFocusPart(Composite.java:352)\n\tat org.eclipse.swt.widgets.Widget.controlProc(Widget.java:317)\n\tat org.eclipse.swt.widgets.Display.controlProc(Display.java:743)\n\tat org.eclipse.swt.internal.carbon.OS.DisposeWindow(Native Method)\n\tat org.eclipse.swt.widgets.Shell.destroyWidget(Shell.java:488)\n\tat org.eclipse.swt.widgets.Widget.dispose(Widget.java:482)\n\tat org.eclipse.jface.window.Window.close(Window.java:253)\n\tat org.eclipse.jface.dialogs.Dialog.close(Dialog.java:826)\n\tat org.eclipse.jface.preference.PreferenceDialog.close(PreferenceDialog.java:253)\n\tat org.eclipse.jface.preference.PreferenceDialog.cancelPressed(PreferenceDialog.java:233)\n\tat org.eclipse.jface.preference.PreferenceDialog.buttonPressed(PreferenceDialog.java:203)\n\tat \norg.eclipse.ui.internal.dialogs.WorkbenchPreferenceDialog.buttonPressed(WorkbenchPreferenceDialog.j\nava:75)\n\tat org.eclipse.jface.dialogs.Dialog$2.widgetSelected(Dialog.java:506)\n\tat org.eclipse.swt.widgets.TypedListener.handleEvent(TypedListener.java:89)\n\tat org.eclipse.swt.widgets.EventTable.sendEvent(EventTable.java:82)\n\tat org.eclipse.swt.widgets.Widget.sendEvent(Widget.java:1196)\n\tat org.eclipse.swt.widgets.Widget.sendEvent(Widget.java:1220)\n\tat org.eclipse.swt.widgets.Widget.sendEvent(Widget.java:1205)\n\tat org.eclipse.swt.widgets.Widget.notifyListeners(Widget.java:1053)\n\tat org.eclipse.swt.widgets.Display.runDeferredEvents(Display.java:2868)\n\tat org.eclipse.swt.widgets.Display.readAndDispatch(Display.java:2538)\n\tat org.eclipse.jface.window.Window.runEventLoop(Window.java:668)\n\tat org.eclipse.jface.window.Window.open(Window.java:648)\n\tat org.eclipse.ui.internal.OpenPreferencesAction.run(OpenPreferencesAction.java:72)\n\tat org.eclipse.jface.action.Action.runWithEvent(Action.java:881)\n\tat \norg.eclipse.jface.action.ActionContributionItem.handleWidgetSelection(ActionContributionItem.java:\n915)\n\tat org.eclipse.jface.action.ActionContributionItem.access$2(ActionContributionItem.java:866)\n\tat org.eclipse.jface.action.ActionContributionItem$7.handleEvent(ActionContributionItem.java:\n785)\n\tat org.eclipse.swt.widgets.EventTable.sendEvent(EventTable.java:82)\n\tat org.eclipse.swt.widgets.Widget.sendEvent(Widget.java:1196)\n\tat org.eclipse.swt.widgets.Widget.sendEvent(Widget.java:1220)\n\tat org.eclipse.swt.widgets.Widget.sendEvent(Widget.java:1205)\n\tat org.eclipse.swt.widgets.Widget.notifyListeners(Widget.java:1053)\n\tat org.eclipse.swt.widgets.Display.runDeferredEvents(Display.java:2868)\n\tat org.eclipse.swt.widgets.Display.readAndDispatch(Display.java:2538)\n\tat org.eclipse.ui.internal.Workbench.runEventLoop(Workbench.java:1362)\n\tat org.eclipse.ui.internal.Workbench.runUI(Workbench.java:1333)\n\tat org.eclipse.ui.internal.Workbench.createAndRunWorkbench(Workbench.java:252)\n\tat org.eclipse.ui.PlatformUI.createAndRunWorkbench(PlatformUI.java:141)\n\tat org.eclipse.ui.internal.ide.IDEApplication.run(IDEApplication.java:96)\n\tat org.eclipse.core.internal.runtime.PlatformActivator$1.run(PlatformActivator.java:334)\n\tat org.eclipse.core.runtime.adaptor.EclipseStarter.run(EclipseStarter.java:272)\n\tat org.eclipse.core.runtime.adaptor.EclipseStarter.run(EclipseStarter.java:128)\n\tat sun.reflect.NativeMethodAccessorImpl.invoke0(Native Method)\n\tat sun.reflect.NativeMethodAccessorImpl.invoke(NativeMethodAccessorImpl.java:39)\n\tat sun.reflect.DelegatingMethodAccessorImpl.invoke(DelegatingMethodAccessorImpl.java:25)\n\tat java.lang.reflect.Method.invoke(Method.java:324)\n\tat org.eclipse.core.launcher.Main.basicRun(Main.java:185)\n\tat org.eclipse.core.launcher.Main.run(Main.java:638)\n\tat org.eclipse.core.launcher.Main.main(Main.java:622)\njava.lang.NullPointerException",
    "I am able to reproduce this bug using Build id: 200406110010 on Mac OS 10.3.3.\nThis doesn\u0027t seem to happen on windows, but happens on the Mac everytime I do\nthe following:\n\n- I happen to be running a fresh workspace (not sure if that matters or not)\n- Resource Perspective (default)\n- Go to \"File-\u003eImport-\u003eExternal Plugins and Fragments\"\n- Uncheck the \"Target Platform\" box\n- Select the plug-in location field and start typing random character\n- Hit \"Cancel\"\n- You will found the following in the log\n\n\n!SESSION Jun 11, 2004 09:19:07.34 ----------------------------------------------\neclipse.buildId\u003dI200406110010\njava.version\u003d1.4.2_03\njava.vendor\u003dApple Computer, Inc.\nBootLoader constants: OS\u003dmacosx, ARCH\u003dppc, WS\u003dcarbon, NL\u003den_US\nCommand-line arguments: -keyring /Users/ines/.eclipse_keyring -showlocation\n\n!ENTRY org.eclipse.ui 4 4 Jun 11, 2004 09:19:07.43\n!MESSAGE Unhandled event loop exception\n\n!ENTRY org.eclipse.ui 4 0 Jun 11, 2004 09:19:07.49\n!MESSAGE java.lang.NullPointerException\n!STACK 0\njava.lang.NullPointerException\n        at org.eclipse.swt.widgets.Control.kEventControlSetFocusPart(Control.jav\na:1369)\n        at org.eclipse.swt.widgets.Composite.kEventControlSetFocusPart(Composite\n.java:352)\n        at org.eclipse.swt.widgets.Widget.controlProc(Widget.java:317)\n        at org.eclipse.swt.widgets.Display.controlProc(Display.java:743)\n        at org.eclipse.swt.internal.carbon.OS.DisposeWindow(Native Method)\n        at org.eclipse.swt.widgets.Shell.destroyWidget(Shell.java:488)\n        at org.eclipse.swt.widgets.Widget.dispose(Widget.java:482)\n        at org.eclipse.jface.window.Window.close(Window.java:253)\n        at org.eclipse.jface.dialogs.Dialog.close(Dialog.java:826)\n        at org.eclipse.jface.wizard.WizardDialog.hardClose(WizardDialog.java:660\n)\n        at org.eclipse.jface.wizard.WizardDialog.close(WizardDialog.java:352)\n        at org.eclipse.jface.wizard.WizardDialog.cancelPressed(WizardDialog.java\n:341)\n        at org.eclipse.jface.wizard.WizardDialog$1.widgetSelected(WizardDialog.j\nava:227)\n        at org.eclipse.swt.widgets.TypedListener.handleEvent(TypedListener.java:\n89)\n        at org.eclipse.swt.widgets.EventTable.sendEvent(EventTable.java:82)\n        at org.eclipse.swt.widgets.Widget.sendEvent(Widget.java:1196)\n        at org.eclipse.swt.widgets.Widget.sendEvent(Widget.java:1220)\n        at org.eclipse.swt.widgets.Widget.sendEvent(Widget.java:1205)\n        at org.eclipse.swt.widgets.Widget.notifyListeners(Widget.java:1053)\n        at org.eclipse.swt.widgets.Display.runDeferredEvents(Display.java:2868)\n        at org.eclipse.swt.widgets.Display.readAndDispatch(Display.java:2538)\n        at org.eclipse.jface.window.Window.runEventLoop(Window.java:668)\n        at org.eclipse.jface.window.Window.open(Window.java:648)\n        at org.eclipse.ui.actions.ImportResourcesAction.run(ImportResourcesActio\nn.java:146)\n        at org.eclipse.ui.actions.BaseSelectionListenerAction.runWithEvent(BaseS\nelectionListenerAction.java:166)\n        at org.eclipse.jface.action.ActionContributionItem.handleWidgetSelection\n(ActionContributionItem.java:915)\n        at org.eclipse.jface.action.ActionContributionItem.access$2(ActionContri\nbutionItem.java:866)\n        at org.eclipse.jface.action.ActionContributionItem$7.handleEvent(ActionC\nontributionItem.java:785)\n        at org.eclipse.swt.widgets.EventTable.sendEvent(EventTable.java:82)\n        at org.eclipse.swt.widgets.Widget.sendEvent(Widget.java:1196)\n        at org.eclipse.swt.widgets.Widget.sendEvent(Widget.java:1220)\n        at org.eclipse.swt.widgets.Widget.sendEvent(Widget.java:1205)\n        at org.eclipse.swt.widgets.Widget.notifyListeners(Widget.java:1053)\n        at org.eclipse.swt.widgets.Display.runDeferredEvents(Display.java:2868)\n        at org.eclipse.swt.widgets.Display.readAndDispatch(Display.java:2538)\n        at org.eclipse.ui.internal.Workbench.runEventLoop(Workbench.java:1362)\n        at org.eclipse.ui.internal.Workbench.runUI(Workbench.java:1333)\n        at org.eclipse.ui.internal.Workbench.createAndRunWorkbench(Workbench.jav\na:252)\n        at org.eclipse.ui.PlatformUI.createAndRunWorkbench(PlatformUI.java:141)\n        at org.eclipse.ui.internal.ide.IDEApplication.run(IDEApplication.java:96\n)\n        at org.eclipse.core.internal.runtime.PlatformActivator$1.run(PlatformAct\nivator.java:334)\n        at org.eclipse.core.runtime.adaptor.EclipseStarter.run(EclipseStarter.ja\nva:272)\n        at org.eclipse.core.runtime.adaptor.EclipseStarter.run(EclipseStarter.ja\nva:128)\n        at sun.reflect.NativeMethodAccessorImpl.invoke0(Native Method)\n        at sun.reflect.NativeMethodAccessorImpl.invoke(NativeMethodAccessorImpl.\njava:39)\n        at sun.reflect.DelegatingMethodAccessorImpl.invoke(DelegatingMethodAcces\nsorImpl.java:25)\n        at java.lang.reflect.Method.invoke(Method.java:324)\n        at org.eclipse.core.launcher.Main.basicRun(Main.java:185)\n        at org.eclipse.core.launcher.Main.run(Main.java:638)",
    "(Grant on Silenio\u0027s machine)\n\nSSQ the following steps give a similar but not identical trace:\n- run the ControlExample, go to the Combo tab\n- click in the Combo to make its full contents show\n- press the SWT.DROP_DOWN radio, and the exception will occur\n",
    "Fixed \u003e 20040611. "
  ],
  "commentCreationDates": [
    "2004-06-11T14:10:46+02:00",
    "2004-06-11T15:35:14+02:00",
    "2004-06-11T17:09:18+02:00",
    "2004-06-11T17:32:10+02:00"
  ],
  "traces": [
    {
      "exceptionType": "java.lang.NullPointerException",
      "elements": [
        {
          "method": "org.eclipse.swt.widgets.Control.kEventControlSetFocusPart",
          "source": "Control.java:1369"
        },
        {
          "method": "org.eclipse.swt.widgets.Composite.kEventControlSetFocusPart",
          "source": "Composite.java:352"
        },
        {
          "method": "org.eclipse.swt.widgets.Widget.controlProc",
          "source": "Widget.java:317"
        },
        {
          "method": "org.eclipse.swt.widgets.Display.controlProc",
          "source": "Display.java:743"
        },
        {
          "method": "org.eclipse.swt.internal.carbon.OS.DisposeWindow",
          "source": "Native Method"
        },
        {
          "method": "org.eclipse.swt.widgets.Shell.destroyWidget",
          "source": "Shell.java:488"
        },
        {
          "method": "org.eclipse.swt.widgets.Widget.dispose",
          "source": "Widget.java:482"
        },
        {
          "method": "org.eclipse.jface.window.Window.close",
          "source": "Window.java:253"
        },
        {
          "method": "org.eclipse.jface.dialogs.Dialog.close",
          "source": "Dialog.java:826"
        },
        {
          "method": "org.eclipse.jface.preference.PreferenceDialog.close",
          "source": "PreferenceDialog.java:253"
        },
        {
          "method": "org.eclipse.jface.preference.PreferenceDialog.cancelPressed",
          "source": "PreferenceDialog.java:233"
        },
        {
          "method": "org.eclipse.jface.preference.PreferenceDialog.buttonPressed",
          "source": "PreferenceDialog.java:203"
        },
        {
          "method": "org.eclipse.ui.internal.dialogs.WorkbenchPreferenceDialog.buttonPressed",
          "source": "WorkbenchPreferenceDialog.j ava:75"
        },
        {
          "method": "org.eclipse.jface.dialogs.Dialog$2.widgetSelected",
          "source": "Dialog.java:506"
        },
        {
          "method": "org.eclipse.swt.widgets.TypedListener.handleEvent",
          "source": "TypedListener.java:89"
        },
        {
          "method": "org.eclipse.swt.widgets.EventTable.sendEvent",
          "source": "EventTable.java:82"
        },
        {
          "method": "org.eclipse.swt.widgets.Widget.sendEvent",
          "source": "Widget.java:1196"
        },
        {
          "method": "org.eclipse.swt.widgets.Widget.sendEvent",
          "source": "Widget.java:1220"
        },
        {
          "method": "org.eclipse.swt.widgets.Widget.sendEvent",
          "source": "Widget.java:1205"
        },
        {
          "method": "org.eclipse.swt.widgets.Widget.notifyListeners",
          "source": "Widget.java:1053"
        },
        {
          "method": "org.eclipse.swt.widgets.Display.runDeferredEvents",
          "source": "Display.java:2868"
        },
        {
          "method": "org.eclipse.swt.widgets.Display.readAndDispatch",
          "source": "Display.java:2538"
        },
        {
          "method": "org.eclipse.jface.window.Window.runEventLoop",
          "source": "Window.java:668"
        },
        {
          "method": "org.eclipse.jface.window.Window.open",
          "source": "Window.java:648"
        },
        {
          "method": "org.eclipse.ui.internal.OpenPreferencesAction.run",
          "source": "OpenPreferencesAction.java:72"
        },
        {
          "method": "org.eclipse.jface.action.Action.runWithEvent",
          "source": "Action.java:881"
        },
        {
          "method": "org.eclipse.jface.action.ActionContributionItem.handleWidgetSelection",
          "source": "ActionContributionItem.java: 915"
        },
        {
          "method": "org.eclipse.jface.action.ActionContributionItem.access$2",
          "source": "ActionContributionItem.java:866"
        },
        {
          "method": "org.eclipse.jface.action.ActionContributionItem$7.handleEvent",
          "source": "ActionContributionItem.java: 785"
        },
        {
          "method": "org.eclipse.swt.widgets.EventTable.sendEvent",
          "source": "EventTable.java:82"
        },
        {
          "method": "org.eclipse.swt.widgets.Widget.sendEvent",
          "source": "Widget.java:1196"
        },
        {
          "method": "org.eclipse.swt.widgets.Widget.sendEvent",
          "source": "Widget.java:1220"
        },
        {
          "method": "org.eclipse.swt.widgets.Widget.sendEvent",
          "source": "Widget.java:1205"
        },
        {
          "method": "org.eclipse.swt.widgets.Widget.notifyListeners",
          "source": "Widget.java:1053"
        },
        {
          "method": "org.eclipse.swt.widgets.Display.runDeferredEvents",
          "source": "Display.java:2868"
        },
        {
          "method": "org.eclipse.swt.widgets.Display.readAndDispatch",
          "source": "Display.java:2538"
        },
        {
          "method": "org.eclipse.ui.internal.Workbench.runEventLoop",
          "source": "Workbench.java:1362"
        },
        {
          "method": "org.eclipse.ui.internal.Workbench.runUI",
          "source": "Workbench.java:1333"
        },
        {
          "method": "org.eclipse.ui.internal.Workbench.createAndRunWorkbench",
          "source": "Workbench.java:252"
        },
        {
          "method": "org.eclipse.ui.PlatformUI.createAndRunWorkbench",
          "source": "PlatformUI.java:141"
        },
        {
          "method": "org.eclipse.ui.internal.ide.IDEApplication.run",
          "source": "IDEApplication.java:96"
        },
        {
          "method": "org.eclipse.core.internal.runtime.PlatformActivator$1.run",
          "source": "PlatformActivator.java:334"
        },
        {
          "method": "org.eclipse.core.runtime.adaptor.EclipseStarter.run",
          "source": "EclipseStarter.java:272"
        },
        {
          "method": "org.eclipse.core.runtime.adaptor.EclipseStarter.run",
          "source": "EclipseStarter.java:128"
        },
        {
          "method": "sun.reflect.NativeMethodAccessorImpl.invoke0",
          "source": "Native Method"
        },
        {
          "method": "sun.reflect.NativeMethodAccessorImpl.invoke",
          "source": "NativeMethodAccessorImpl.java:39"
        },
        {
          "method": "sun.reflect.DelegatingMethodAccessorImpl.invoke",
          "source": "DelegatingMethodAccessorImpl.java:25"
        },
        {
          "method": "java.lang.reflect.Method.invoke",
          "source": "Method.java:324"
        },
        {
          "method": "org.eclipse.core.launcher.Main.basicRun",
          "source": "Main.java:185"
        },
        {
          "method": "org.eclipse.core.launcher.Main.run",
          "source": "Main.java:638"
        },
        {
          "method": "org.eclipse.core.launcher.Main.main",
          "source": "Main.java:622"
        }
      ],
      "number": 0,
      "commentIndex": 0,
      "bugId": "66653",
      "date": "2004-06-11T14:10:46+02:00",
      "product": "Platform",
      "component": "SWT",
      "severity": "normal"
    },
    {
      "exceptionType": "java.lang.NullPointerException",
      "elements": [
        {
          "method": "org.eclipse.swt.widgets.Control.kEventControlSetFocusPart",
          "source": "Control.jav a:1369"
        },
        {
          "method": "org.eclipse.swt.widgets.Composite.kEventControlSetFocusPart",
          "source": "Composite .java:352"
        },
        {
          "method": "org.eclipse.swt.widgets.Widget.controlProc",
          "source": "Widget.java:317"
        },
        {
          "method": "org.eclipse.swt.widgets.Display.controlProc",
          "source": "Display.java:743"
        },
        {
          "method": "org.eclipse.swt.internal.carbon.OS.DisposeWindow",
          "source": "Native Method"
        },
        {
          "method": "org.eclipse.swt.widgets.Shell.destroyWidget",
          "source": "Shell.java:488"
        },
        {
          "method": "org.eclipse.swt.widgets.Widget.dispose",
          "source": "Widget.java:482"
        },
        {
          "method": "org.eclipse.jface.window.Window.close",
          "source": "Window.java:253"
        },
        {
          "method": "org.eclipse.jface.dialogs.Dialog.close",
          "source": "Dialog.java:826"
        },
        {
          "method": "org.eclipse.jface.wizard.WizardDialog.hardClose",
          "source": "WizardDialog.java:660 "
        },
        {
          "method": "org.eclipse.jface.wizard.WizardDialog.close",
          "source": "WizardDialog.java:352"
        },
        {
          "method": "org.eclipse.jface.wizard.WizardDialog.cancelPressed",
          "source": "WizardDialog.java :341"
        },
        {
          "method": "org.eclipse.jface.wizard.WizardDialog$1.widgetSelected",
          "source": "WizardDialog.j ava:227"
        },
        {
          "method": "org.eclipse.swt.widgets.TypedListener.handleEvent",
          "source": "TypedListener.java: 89"
        },
        {
          "method": "org.eclipse.swt.widgets.EventTable.sendEvent",
          "source": "EventTable.java:82"
        },
        {
          "method": "org.eclipse.swt.widgets.Widget.sendEvent",
          "source": "Widget.java:1196"
        },
        {
          "method": "org.eclipse.swt.widgets.Widget.sendEvent",
          "source": "Widget.java:1220"
        },
        {
          "method": "org.eclipse.swt.widgets.Widget.sendEvent",
          "source": "Widget.java:1205"
        },
        {
          "method": "org.eclipse.swt.widgets.Widget.notifyListeners",
          "source": "Widget.java:1053"
        },
        {
          "method": "org.eclipse.swt.widgets.Display.runDeferredEvents",
          "source": "Display.java:2868"
        },
        {
          "method": "org.eclipse.swt.widgets.Display.readAndDispatch",
          "source": "Display.java:2538"
        },
        {
          "method": "org.eclipse.jface.window.Window.runEventLoop",
          "source": "Window.java:668"
        },
        {
          "method": "org.eclipse.jface.window.Window.open",
          "source": "Window.java:648"
        },
        {
          "method": "org.eclipse.ui.actions.ImportResourcesAction.run",
          "source": "ImportResourcesActio n.java:146"
        },
        {
          "method": "org.eclipse.ui.actions.BaseSelectionListenerAction.runWithEvent",
          "source": "BaseS electionListenerAction.java:166"
        },
        {
          "method": "org.eclipse.jface.action.ActionContributionItem.handleWidgetSelection",
          "source": "ActionContributionItem.java:915"
        },
        {
          "method": "org.eclipse.jface.action.ActionContributionItem.access$2",
          "source": "ActionContri butionItem.java:866"
        },
        {
          "method": "org.eclipse.jface.action.ActionContributionItem$7.handleEvent",
          "source": "ActionC ontributionItem.java:785"
        },
        {
          "method": "org.eclipse.swt.widgets.EventTable.sendEvent",
          "source": "EventTable.java:82"
        },
        {
          "method": "org.eclipse.swt.widgets.Widget.sendEvent",
          "source": "Widget.java:1196"
        },
        {
          "method": "org.eclipse.swt.widgets.Widget.sendEvent",
          "source": "Widget.java:1220"
        },
        {
          "method": "org.eclipse.swt.widgets.Widget.sendEvent",
          "source": "Widget.java:1205"
        },
        {
          "method": "org.eclipse.swt.widgets.Widget.notifyListeners",
          "source": "Widget.java:1053"
        },
        {
          "method": "org.eclipse.swt.widgets.Display.runDeferredEvents",
          "source": "Display.java:2868"
        },
        {
          "method": "org.eclipse.swt.widgets.Display.readAndDispatch",
          "source": "Display.java:2538"
        },
        {
          "method": "org.eclipse.ui.internal.Workbench.runEventLoop",
          "source": "Workbench.java:1362"
        },
        {
          "method": "org.eclipse.ui.internal.Workbench.runUI",
          "source": "Workbench.java:1333"
        },
        {
          "method": "org.eclipse.ui.internal.Workbench.createAndRunWorkbench",
          "source": "Workbench.jav a:252"
        },
        {
          "method": "org.eclipse.ui.PlatformUI.createAndRunWorkbench",
          "source": "PlatformUI.java:141"
        },
        {
          "method": "org.eclipse.ui.internal.ide.IDEApplication.run",
          "source": "IDEApplication.java:96 "
        },
        {
          "method": "org.eclipse.core.internal.runtime.PlatformActivator$1.run",
          "source": "PlatformAct ivator.java:334"
        },
        {
          "method": "org.eclipse.core.runtime.adaptor.EclipseStarter.run",
          "source": "EclipseStarter.ja va:272"
        },
        {
          "method": "org.eclipse.core.runtime.adaptor.EclipseStarter.run",
          "source": "EclipseStarter.ja va:128"
        },
        {
          "method": "sun.reflect.NativeMethodAccessorImpl.invoke0",
          "source": "Native Method"
        },
        {
          "method": "sun.reflect.NativeMethodAccessorImpl.invoke",
          "source": "NativeMethodAccessorImpl. java:39"
        },
        {
          "method": "sun.reflect.DelegatingMethodAccessorImpl.invoke",
          "source": "DelegatingMethodAcces sorImpl.java:25"
        },
        {
          "method": "java.lang.reflect.Method.invoke",
          "source": "Method.java:324"
        },
        {
          "method": "org.eclipse.core.launcher.Main.basicRun",
          "source": "Main.java:185"
        },
        {
          "method": "org.eclipse.core.launcher.Main.run",
          "source": "Main.java:638"
        }
      ],
      "number": 1,
      "commentIndex": 1,
      "bugId": "66653",
      "date": "2004-06-11T15:35:14+02:00",
      "product": "Platform",
      "component": "SWT",
      "severity": "normal"
    }
  ],
  "groupId": "66653",
  "bugId": "66653",
  "date": "2004-06-11T14:10:46+02:00",
  "product": "Platform",
  "component": "SWT",
  "severity": "normal"
}