{
  "comments": [
    "In 0611\n\nWhen refreshing a window that has some detached views (that may or may not be \nrelevant) I get the following trace...\n\n!ENTRY org.eclipse.ui 4 0 Jun 11, 2004 11:44:13.877\n!MESSAGE java.lang.NullPointerException\n!STACK 0\njava.lang.NullPointerException\n        at java.lang.Throwable.\u003cinit\u003e(Throwable.java)\n        at java.lang.Throwable.\u003cinit\u003e(Throwable.java)\n        at java.lang.NullPointerException.\u003cinit\u003e(NullPointerException.java:60)\n        at org.eclipse.swt.widgets.MenuItem.widgetStyle(MenuItem.java)\n        at org.eclipse.swt.widgets.MenuItem.setText(MenuItem.java)\n        at org.eclipse.jface.action.ActionContributionItem.update\n(ActionContributionItem.java)\n        at org.eclipse.jface.action.ActionContributionItem$1.propertyChange\n(ActionContributionItem.java)\n        at org.eclipse.ui.internal.commands.ws.CommandCallback$1.commandChanged\n(CommandCallback.java)\n        at org.eclipse.ui.internal.commands.Command.fireCommandChanged\n(Command.java)\n        at org.eclipse.ui.internal.commands.MutableCommandManager.notifyCommands\n(MutableCommandManager.java)\n        at \norg.eclipse.ui.internal.commands.MutableCommandManager.setActiveContextIds\n(MutableCommandManager.java:580)\n        at \norg.eclipse.ui.internal.commands.ws.WorkbenchCommandSupport.setActiveContextIds\n(WorkbenchCommandSupport.java:\n512)\n        at org.eclipse.ui.internal.Workbench$2.contextManagerChanged\n(Workbench.java:1797)\n        at \norg.eclipse.ui.internal.contexts.AbstractContextManager.fireContextManagerChange\nd(AbstractContextManager.java\n)\n        at \norg.eclipse.ui.internal.contexts.ProxyContextManager$1.contextManagerChanged\n(ProxyContextManager.java:41)\n        at \norg.eclipse.ui.internal.contexts.AbstractContextManager.fireContextManagerChange\nd(AbstractContextManager.java\n)\n        at \norg.eclipse.ui.internal.contexts.MutableContextManager.setEnabledContextIds\n(MutableContextManager.java:260)\n        at \norg.eclipse.ui.internal.contexts.ws.WorkbenchContextSupport.processEnabledSubmis\nsions(WorkbenchContextSupport\n.java)\n        at \norg.eclipse.ui.internal.contexts.ws.WorkbenchContextSupport.checkWindowType\n(WorkbenchContextSupport.java)\n        at org.eclipse.ui.internal.contexts.ws.WorkbenchContextSupport.access$0\n(WorkbenchContextSupport.java)\n        at \norg.eclipse.ui.internal.contexts.ws.WorkbenchContextSupport$1.handleEvent\n(WorkbenchContextSupport.java)\n        at org.eclipse.swt.widgets.EventTable.sendEvent(EventTable.java)\n        at org.eclipse.swt.widgets.Display.filterEvent(Display.java)\n        at org.eclipse.swt.widgets.Widget.sendEvent(Widget.java)\n        at org.eclipse.swt.widgets.Widget.sendEvent(Widget.java)\n        at org.eclipse.swt.widgets.Widget.sendEvent(Widget.java)\n        at org.eclipse.swt.widgets.Shell.setActiveControl(Shell.java)\n        at org.eclipse.swt.widgets.Shell.WM_MOUSEACTIVATE(Shell.java:1450)\n        at org.eclipse.swt.widgets.Control.windowProc(Control.java)\n        at org.eclipse.swt.widgets.Decorations.windowProc(Decorations.java)\n        at org.eclipse.swt.widgets.Display.windowProc(Display.java)\n        at org.eclipse.swt.internal.win32.OS.DefWindowProcW(Native Method)\n        at org.eclipse.swt.internal.win32.OS.DefWindowProc(OS.java)\n        at org.eclipse.swt.widgets.Scrollable.callWindowProc(Scrollable.java)\n        at org.eclipse.swt.widgets.Control.windowProc(Control.java)\n        at org.eclipse.swt.widgets.Display.windowProc(Display.java)\n        at org.eclipse.swt.internal.win32.OS.DefWindowProcW(Native Method)\n        at org.eclipse.swt.internal.win32.OS.DefWindowProc(OS.java)\n        at org.eclipse.swt.widgets.Scrollable.callWindowProc(Scrollable.java)\n        at org.eclipse.swt.widgets.Control.windowProc(Control.java)\n        at org.eclipse.swt.widgets.Display.windowProc(Display.java)\n        at org.eclipse.swt.internal.win32.OS.DefWindowProcW(Native Method)\n        at org.eclipse.swt.internal.win32.OS.DefWindowProc(OS.java)\n        at org.eclipse.swt.widgets.Scrollable.callWindowProc(Scrollable.java)\n        at org.eclipse.swt.widgets.Control.windowProc(Control.java)\n        at org.eclipse.swt.widgets.Display.windowProc(Display.java)\n        at org.eclipse.swt.internal.win32.OS.DefWindowProcW(Native Method)\n        at org.eclipse.swt.internal.win32.OS.DefWindowProc(OS.java)\n        at org.eclipse.swt.widgets.Scrollable.callWindowProc(Scrollable.java)\n        at org.eclipse.swt.widgets.Control.windowProc(Control.java)\n        at org.eclipse.swt.widgets.Display.windowProc(Display.java)\n        at org.eclipse.swt.internal.win32.OS.DefWindowProcW(Native Method)\n        at org.eclipse.swt.internal.win32.OS.DefWindowProc(OS.java)\n        at org.eclipse.swt.widgets.Scrollable.callWindowProc(Scrollable.java)\n        at org.eclipse.swt.widgets.Control.windowProc(Control.java)\n        at org.eclipse.swt.widgets.Display.windowProc(Display.java)\n        at org.eclipse.swt.internal.win32.OS.DefWindowProcW(Native Method)\n        at org.eclipse.swt.internal.win32.OS.DefWindowProc(OS.java)\n        at org.eclipse.swt.widgets.Scrollable.callWindowProc(Scrollable.java)\n        at org.eclipse.swt.widgets.Control.windowProc(Control.java)\n        at org.eclipse.swt.widgets.Display.windowProc(Display.java)\n        at org.eclipse.swt.internal.win32.OS.DefWindowProcW(Native Method)\n        at org.eclipse.swt.internal.win32.OS.DefWindowProc(OS.java)\n        at org.eclipse.swt.widgets.Scrollable.callWindowProc(Scrollable.java)\n        at org.eclipse.swt.widgets.Control.windowProc(Control.java)\n        at org.eclipse.swt.widgets.Display.windowProc(Display.java)\n        at org.eclipse.swt.internal.win32.OS.DefWindowProcW(Native Method)\n        at org.eclipse.swt.internal.win32.OS.DefWindowProc(OS.java)\n        at org.eclipse.swt.widgets.Scrollable.callWindowProc(Scrollable.java)\n        at org.eclipse.swt.widgets.Control.windowProc(Control.java)\n        at org.eclipse.swt.widgets.Display.windowProc(Display.java)\n        at org.eclipse.swt.internal.win32.OS.DefWindowProcW(Native Method)\n        at org.eclipse.swt.internal.win32.OS.DefWindowProc(OS.java)\n        at org.eclipse.swt.widgets.Scrollable.callWindowProc(Scrollable.java)\n        at org.eclipse.swt.widgets.Control.windowProc(Control.java)\n        at org.eclipse.swt.widgets.Display.windowProc(Display.java)\n        at org.eclipse.swt.internal.win32.OS.PeekMessageW(Native Method)\n        at org.eclipse.swt.internal.win32.OS.PeekMessage(OS.java)\n        at org.eclipse.swt.widgets.Display.readAndDispatch(Display.java)\n        at org.eclipse.ui.internal.Workbench.runEventLoop(Workbench.java:1362)\n        at org.eclipse.ui.internal.Workbench.runUI(Workbench.java:1333)\n        at org.eclipse.ui.internal.Workbench.createAndRunWorkbench\n(Workbench.java:252)\n        at org.eclipse.ui.PlatformUI.createAndRunWorkbench(PlatformUI.java:141)\n        at org.eclipse.ui.internal.ide.IDEApplication.run\n(IDEApplication.java:96)\n        at org.eclipse.core.internal.runtime.PlatformActivator$1.run\n(PlatformActivator.java:334)\n        at org.eclipse.core.runtime.adaptor.EclipseStarter.run\n(EclipseStarter.java:272)\n        at org.eclipse.core.runtime.adaptor.EclipseStarter.run\n(EclipseStarter.java:128)\n        at sun.reflect.NativeMethodAccessorImpl.invoke0(Native Method)\n        at sun.reflect.NativeMethodAccessorImpl.invoke\n(NativeMethodAccessorImpl.java:84)\n        at sun.reflect.NativeMethodAccessorImpl.invoke\n(NativeMethodAccessorImpl.java:57)\n        at sun.reflect.DelegatingMethodAccessorImpl.invoke\n(DelegatingMethodAccessorImpl.java:59)\n        at java.lang.reflect.Method.invoke(Method.java:390)\n        at org.eclipse.core.launcher.Main.basicRun(Main.java:185)\n        at org.eclipse.core.launcher.Main.run(Main.java:638)\n        at org.eclipse.core.launcher.Main.main(Main.java:622)\njava.lang.NullPointerException",
    "This doesn\u0027t make any sense.  The NPE can only happen when the MenuItem has \nbeen disposed().  The first thing that MenuItem.setText() does is call \ncheckWidget() (which succeeds) and then eventually calls widgetStyle().  \nBetween the call to checkWidget() and widgetStyle(), there are no callbacks so \nno application code could run that disposed the MenuItem.\n\nSSQ, do you agree?\n\nJeff, could this be that class loader bug that turned NPE\u0027s into class not \nfound errors?\n",
    "I\u0027m marking this a dup of \"detached windows context menu\" bug.  If you see it \nagain, please reopen.\n\n*** This bug has been marked as a duplicate of 68096 ***"
  ],
  "commentCreationDates": [
    "2004-06-11T17:53:31+02:00",
    "2004-06-18T22:46:08+02:00",
    "2004-06-23T23:06:06+02:00"
  ],
  "traces": [
    {
      "exceptionType": "java.lang.NullPointerException",
      "elements": [
        {
          "method": "java.lang.Throwable.\u003cinit\u003e",
          "source": "Throwable.java"
        },
        {
          "method": "java.lang.Throwable.\u003cinit\u003e",
          "source": "Throwable.java"
        },
        {
          "method": "java.lang.NullPointerException.\u003cinit\u003e",
          "source": "NullPointerException.java:60"
        },
        {
          "method": "org.eclipse.swt.widgets.MenuItem.widgetStyle",
          "source": "MenuItem.java"
        },
        {
          "method": "org.eclipse.swt.widgets.MenuItem.setText",
          "source": "MenuItem.java"
        },
        {
          "method": "org.eclipse.jface.action.ActionContributionItem.update",
          "source": "ActionContributionItem.java"
        },
        {
          "method": "org.eclipse.jface.action.ActionContributionItem$1.propertyChange",
          "source": "ActionContributionItem.java"
        },
        {
          "method": "org.eclipse.ui.internal.commands.ws.CommandCallback$1.commandChanged",
          "source": "CommandCallback.java"
        },
        {
          "method": "org.eclipse.ui.internal.commands.Command.fireCommandChanged",
          "source": "Command.java"
        },
        {
          "method": "org.eclipse.ui.internal.commands.MutableCommandManager.notifyCommands",
          "source": "MutableCommandManager.java"
        },
        {
          "method": "org.eclipse.ui.internal.commands.MutableCommandManager.setActiveContextIds",
          "source": "MutableCommandManager.java:580"
        },
        {
          "method": "org.eclipse.ui.internal.commands.ws.WorkbenchCommandSupport.setActiveContextIds",
          "source": "WorkbenchCommandSupport.java: 512"
        },
        {
          "method": "org.eclipse.ui.internal.Workbench$2.contextManagerChanged",
          "source": "Workbench.java:1797"
        },
        {
          "method": "org.eclipse.ui.internal.contexts.AbstractContextManager.fireContextManagerChanged",
          "source": "AbstractContextManager.java "
        },
        {
          "method": "org.eclipse.ui.internal.contexts.ProxyContextManager$1.contextManagerChanged",
          "source": "ProxyContextManager.java:41"
        },
        {
          "method": "org.eclipse.ui.internal.contexts.AbstractContextManager.fireContextManagerChanged",
          "source": "AbstractContextManager.java "
        },
        {
          "method": "org.eclipse.ui.internal.contexts.MutableContextManager.setEnabledContextIds",
          "source": "MutableContextManager.java:260"
        },
        {
          "method": "org.eclipse.ui.internal.contexts.ws.WorkbenchContextSupport.processEnabledSubmissions",
          "source": "WorkbenchContextSupport .java"
        },
        {
          "method": "org.eclipse.ui.internal.contexts.ws.WorkbenchContextSupport.checkWindowType",
          "source": "WorkbenchContextSupport.java"
        },
        {
          "method": "org.eclipse.ui.internal.contexts.ws.WorkbenchContextSupport.access$0",
          "source": "WorkbenchContextSupport.java"
        },
        {
          "method": "org.eclipse.ui.internal.contexts.ws.WorkbenchContextSupport$1.handleEvent",
          "source": "WorkbenchContextSupport.java"
        },
        {
          "method": "org.eclipse.swt.widgets.EventTable.sendEvent",
          "source": "EventTable.java"
        },
        {
          "method": "org.eclipse.swt.widgets.Display.filterEvent",
          "source": "Display.java"
        },
        {
          "method": "org.eclipse.swt.widgets.Widget.sendEvent",
          "source": "Widget.java"
        },
        {
          "method": "org.eclipse.swt.widgets.Widget.sendEvent",
          "source": "Widget.java"
        },
        {
          "method": "org.eclipse.swt.widgets.Widget.sendEvent",
          "source": "Widget.java"
        },
        {
          "method": "org.eclipse.swt.widgets.Shell.setActiveControl",
          "source": "Shell.java"
        },
        {
          "method": "org.eclipse.swt.widgets.Shell.WM_MOUSEACTIVATE",
          "source": "Shell.java:1450"
        },
        {
          "method": "org.eclipse.swt.widgets.Control.windowProc",
          "source": "Control.java"
        },
        {
          "method": "org.eclipse.swt.widgets.Decorations.windowProc",
          "source": "Decorations.java"
        },
        {
          "method": "org.eclipse.swt.widgets.Display.windowProc",
          "source": "Display.java"
        },
        {
          "method": "org.eclipse.swt.internal.win32.OS.DefWindowProcW",
          "source": "Native Method"
        },
        {
          "method": "org.eclipse.swt.internal.win32.OS.DefWindowProc",
          "source": "OS.java"
        },
        {
          "method": "org.eclipse.swt.widgets.Scrollable.callWindowProc",
          "source": "Scrollable.java"
        },
        {
          "method": "org.eclipse.swt.widgets.Control.windowProc",
          "source": "Control.java"
        },
        {
          "method": "org.eclipse.swt.widgets.Display.windowProc",
          "source": "Display.java"
        },
        {
          "method": "org.eclipse.swt.internal.win32.OS.DefWindowProcW",
          "source": "Native Method"
        },
        {
          "method": "org.eclipse.swt.internal.win32.OS.DefWindowProc",
          "source": "OS.java"
        },
        {
          "method": "org.eclipse.swt.widgets.Scrollable.callWindowProc",
          "source": "Scrollable.java"
        },
        {
          "method": "org.eclipse.swt.widgets.Control.windowProc",
          "source": "Control.java"
        },
        {
          "method": "org.eclipse.swt.widgets.Display.windowProc",
          "source": "Display.java"
        },
        {
          "method": "org.eclipse.swt.internal.win32.OS.DefWindowProcW",
          "source": "Native Method"
        },
        {
          "method": "org.eclipse.swt.internal.win32.OS.DefWindowProc",
          "source": "OS.java"
        },
        {
          "method": "org.eclipse.swt.widgets.Scrollable.callWindowProc",
          "source": "Scrollable.java"
        },
        {
          "method": "org.eclipse.swt.widgets.Control.windowProc",
          "source": "Control.java"
        },
        {
          "method": "org.eclipse.swt.widgets.Display.windowProc",
          "source": "Display.java"
        },
        {
          "method": "org.eclipse.swt.internal.win32.OS.DefWindowProcW",
          "source": "Native Method"
        },
        {
          "method": "org.eclipse.swt.internal.win32.OS.DefWindowProc",
          "source": "OS.java"
        },
        {
          "method": "org.eclipse.swt.widgets.Scrollable.callWindowProc",
          "source": "Scrollable.java"
        },
        {
          "method": "org.eclipse.swt.widgets.Control.windowProc",
          "source": "Control.java"
        },
        {
          "method": "org.eclipse.swt.widgets.Display.windowProc",
          "source": "Display.java"
        },
        {
          "method": "org.eclipse.swt.internal.win32.OS.DefWindowProcW",
          "source": "Native Method"
        },
        {
          "method": "org.eclipse.swt.internal.win32.OS.DefWindowProc",
          "source": "OS.java"
        },
        {
          "method": "org.eclipse.swt.widgets.Scrollable.callWindowProc",
          "source": "Scrollable.java"
        },
        {
          "method": "org.eclipse.swt.widgets.Control.windowProc",
          "source": "Control.java"
        },
        {
          "method": "org.eclipse.swt.widgets.Display.windowProc",
          "source": "Display.java"
        },
        {
          "method": "org.eclipse.swt.internal.win32.OS.DefWindowProcW",
          "source": "Native Method"
        },
        {
          "method": "org.eclipse.swt.internal.win32.OS.DefWindowProc",
          "source": "OS.java"
        },
        {
          "method": "org.eclipse.swt.widgets.Scrollable.callWindowProc",
          "source": "Scrollable.java"
        },
        {
          "method": "org.eclipse.swt.widgets.Control.windowProc",
          "source": "Control.java"
        },
        {
          "method": "org.eclipse.swt.widgets.Display.windowProc",
          "source": "Display.java"
        },
        {
          "method": "org.eclipse.swt.internal.win32.OS.DefWindowProcW",
          "source": "Native Method"
        },
        {
          "method": "org.eclipse.swt.internal.win32.OS.DefWindowProc",
          "source": "OS.java"
        },
        {
          "method": "org.eclipse.swt.widgets.Scrollable.callWindowProc",
          "source": "Scrollable.java"
        },
        {
          "method": "org.eclipse.swt.widgets.Control.windowProc",
          "source": "Control.java"
        },
        {
          "method": "org.eclipse.swt.widgets.Display.windowProc",
          "source": "Display.java"
        },
        {
          "method": "org.eclipse.swt.internal.win32.OS.DefWindowProcW",
          "source": "Native Method"
        },
        {
          "method": "org.eclipse.swt.internal.win32.OS.DefWindowProc",
          "source": "OS.java"
        },
        {
          "method": "org.eclipse.swt.widgets.Scrollable.callWindowProc",
          "source": "Scrollable.java"
        },
        {
          "method": "org.eclipse.swt.widgets.Control.windowProc",
          "source": "Control.java"
        },
        {
          "method": "org.eclipse.swt.widgets.Display.windowProc",
          "source": "Display.java"
        },
        {
          "method": "org.eclipse.swt.internal.win32.OS.DefWindowProcW",
          "source": "Native Method"
        },
        {
          "method": "org.eclipse.swt.internal.win32.OS.DefWindowProc",
          "source": "OS.java"
        },
        {
          "method": "org.eclipse.swt.widgets.Scrollable.callWindowProc",
          "source": "Scrollable.java"
        },
        {
          "method": "org.eclipse.swt.widgets.Control.windowProc",
          "source": "Control.java"
        },
        {
          "method": "org.eclipse.swt.widgets.Display.windowProc",
          "source": "Display.java"
        },
        {
          "method": "org.eclipse.swt.internal.win32.OS.PeekMessageW",
          "source": "Native Method"
        },
        {
          "method": "org.eclipse.swt.internal.win32.OS.PeekMessage",
          "source": "OS.java"
        },
        {
          "method": "org.eclipse.swt.widgets.Display.readAndDispatch",
          "source": "Display.java"
        },
        {
          "method": "org.eclipse.ui.internal.Workbench.runEventLoop",
          "source": "Workbench.java:1362"
        },
        {
          "method": "org.eclipse.ui.internal.Workbench.runUI",
          "source": "Workbench.java:1333"
        },
        {
          "method": "org.eclipse.ui.internal.Workbench.createAndRunWorkbench",
          "source": "Workbench.java:252"
        },
        {
          "method": "org.eclipse.ui.PlatformUI.createAndRunWorkbench",
          "source": "PlatformUI.java:141"
        },
        {
          "method": "org.eclipse.ui.internal.ide.IDEApplication.run",
          "source": "IDEApplication.java:96"
        },
        {
          "method": "org.eclipse.core.internal.runtime.PlatformActivator$1.run",
          "source": "PlatformActivator.java:334"
        },
        {
          "method": "org.eclipse.core.runtime.adaptor.EclipseStarter.run",
          "source": "EclipseStarter.java:272"
        },
        {
          "method": "org.eclipse.core.runtime.adaptor.EclipseStarter.run",
          "source": "EclipseStarter.java:128"
        },
        {
          "method": "sun.reflect.NativeMethodAccessorImpl.invoke0",
          "source": "Native Method"
        },
        {
          "method": "sun.reflect.NativeMethodAccessorImpl.invoke",
          "source": "NativeMethodAccessorImpl.java:84"
        },
        {
          "method": "sun.reflect.NativeMethodAccessorImpl.invoke",
          "source": "NativeMethodAccessorImpl.java:57"
        },
        {
          "method": "sun.reflect.DelegatingMethodAccessorImpl.invoke",
          "source": "DelegatingMethodAccessorImpl.java:59"
        },
        {
          "method": "java.lang.reflect.Method.invoke",
          "source": "Method.java:390"
        },
        {
          "method": "org.eclipse.core.launcher.Main.basicRun",
          "source": "Main.java:185"
        },
        {
          "method": "org.eclipse.core.launcher.Main.run",
          "source": "Main.java:638"
        },
        {
          "method": "org.eclipse.core.launcher.Main.main",
          "source": "Main.java:622"
        }
      ],
      "number": 0,
      "commentIndex": 0,
      "bugId": "66716",
      "duplicateId": "68096",
      "date": "2004-06-11T17:53:31+02:00",
      "product": "Platform",
      "component": "SWT",
      "severity": "normal"
    }
  ],
  "groupId": "68096",
  "bugId": "66716",
  "duplicateId": "68096",
  "date": "2004-06-11T17:53:31+02:00",
  "product": "Platform",
  "component": "SWT",
  "severity": "normal"
}