{
  "comments": [
    "in 0611\n\nI had just pressed Alt-F4 (or ctrl-alt-f4 or alt-shft-f4)( was trying to close \nall the editors) and got the following stack dump.  Note that the perspective \nIwas in had several detached views.\n\n!ENTRY org.eclipse.ui 4 0 Jun 11, 2004 16:15:05.218\n!MESSAGE java.lang.NullPointerException\n!STACK 0\njava.lang.NullPointerException\n        at java.lang.Throwable.\u003cinit\u003e(Throwable.java)\n        at java.lang.Throwable.\u003cinit\u003e(Throwable.java)\n        at java.lang.NullPointerException.\u003cinit\u003e(NullPointerException.java:60)\n        at org.eclipse.swt.widgets.Menu.releaseWidget(Menu.java)\n        at org.eclipse.swt.widgets.Widget.dispose(Widget.java)\n        at org.eclipse.swt.widgets.Decorations.releaseWidget\n(Decorations.java:693)\n        at org.eclipse.swt.widgets.Shell.releaseWidget(Shell.java:791)\n        at org.eclipse.swt.widgets.Widget.dispose(Widget.java)\n        at org.eclipse.swt.widgets.Decorations.dispose(Decorations.java:371)\n        at org.eclipse.swt.widgets.Shell.dispose(Shell.java:487)\n        at org.eclipse.jface.window.Window.close(Window.java:253)\n        at org.eclipse.jface.window.ApplicationWindow.close\n(ApplicationWindow.java:272)\n        at org.eclipse.ui.internal.WorkbenchWindow.hardClose\n(WorkbenchWindow.java:1012)\n        at org.eclipse.ui.internal.WorkbenchWindow.busyClose\n(WorkbenchWindow.java:466)\n        at org.eclipse.ui.internal.WorkbenchWindow.access$0\n(WorkbenchWindow.java:448)\n        at org.eclipse.ui.internal.WorkbenchWindow$1.run\n(WorkbenchWindow.java:536)\n        at org.eclipse.swt.custom.BusyIndicator.showWhile(BusyIndicator.java)\n        at org.eclipse.ui.internal.WorkbenchWindow.close\n(WorkbenchWindow.java:534)\n        at org.eclipse.jface.window.Window.handleShellCloseEvent\n(Window.java:593)\n        at org.eclipse.jface.window.Window$2.shellClosed(Window.java:544)\n        at org.eclipse.swt.widgets.TypedListener.handleEvent(TypedListener.java)\n        at org.eclipse.swt.widgets.EventTable.sendEvent(EventTable.java)\n        at org.eclipse.swt.widgets.Widget.sendEvent(Widget.java)\n        at org.eclipse.swt.widgets.Widget.sendEvent(Widget.java)\n        at org.eclipse.swt.widgets.Widget.sendEvent(Widget.java)\n        at org.eclipse.swt.widgets.Decorations.WM_CLOSE(Decorations.java:1486)\n        at org.eclipse.swt.widgets.Control.windowProc(Control.java)\n        at org.eclipse.swt.widgets.Decorations.windowProc(Decorations.java)\n        at org.eclipse.swt.widgets.Display.windowProc(Display.java)\n        at org.eclipse.swt.internal.win32.OS.DefWindowProcW(Native Method)\n        at org.eclipse.swt.internal.win32.OS.DefWindowProc(OS.java)\n        at org.eclipse.swt.widgets.Shell.callWindowProc(Shell.java)\n        at org.eclipse.swt.widgets.Control.windowProc(Control.java)\n        at org.eclipse.swt.widgets.Decorations.windowProc(Decorations.java)\n        at org.eclipse.swt.widgets.Display.windowProc(Display.java)\n        at org.eclipse.swt.internal.win32.OS.DispatchMessageW(Native Method)\n        at org.eclipse.swt.internal.win32.OS.DispatchMessage(OS.java)\n        at org.eclipse.swt.widgets.Display.readAndDispatch(Display.java)\n        at org.eclipse.ui.internal.Workbench.runEventLoop(Workbench.java:1362)\n        at org.eclipse.ui.internal.Workbench.runUI(Workbench.java:1333)\n        at org.eclipse.ui.internal.Workbench.createAndRunWorkbench\n(Workbench.java:252)\n        at org.eclipse.ui.PlatformUI.createAndRunWorkbench(PlatformUI.java:141)\n        at org.eclipse.ui.internal.ide.IDEApplication.run\n(IDEApplication.java:96)\n        at org.eclipse.core.internal.runtime.PlatformActivator$1.run\n(PlatformActivator.java:334)\n        at org.eclipse.core.runtime.adaptor.EclipseStarter.run\n(EclipseStarter.java:272)\n        at org.eclipse.core.runtime.adaptor.EclipseStarter.run\n(EclipseStarter.java:128)\n        at sun.reflect.NativeMethodAccessorImpl.invoke0(Native Method)\n        at sun.reflect.NativeMethodAccessorImpl.invoke\n(NativeMethodAccessorImpl.java:84)\n        at sun.reflect.NativeMethodAccessorImpl.invoke\n(NativeMethodAccessorImpl.java:57)\n        at sun.reflect.DelegatingMethodAccessorImpl.invoke\n(DelegatingMethodAccessorImpl.java:59)\n        at java.lang.reflect.Method.invoke(Method.java:390)\n        at org.eclipse.core.launcher.Main.basicRun(Main.java:185)\n        at org.eclipse.core.launcher.Main.run(Main.java:638)\n        at org.eclipse.core.launcher.Main.main(Main.java:622)",
    "\n\n*** This bug has been marked as a duplicate of 67660 ***"
  ],
  "commentCreationDates": [
    "2004-06-11T22:32:10+02:00",
    "2004-06-18T20:52:42+02:00"
  ],
  "traces": [
    {
      "exceptionType": "java.lang.NullPointerException",
      "elements": [
        {
          "method": "java.lang.Throwable.\u003cinit\u003e",
          "source": "Throwable.java"
        },
        {
          "method": "java.lang.Throwable.\u003cinit\u003e",
          "source": "Throwable.java"
        },
        {
          "method": "java.lang.NullPointerException.\u003cinit\u003e",
          "source": "NullPointerException.java:60"
        },
        {
          "method": "org.eclipse.swt.widgets.Menu.releaseWidget",
          "source": "Menu.java"
        },
        {
          "method": "org.eclipse.swt.widgets.Widget.dispose",
          "source": "Widget.java"
        },
        {
          "method": "org.eclipse.swt.widgets.Decorations.releaseWidget",
          "source": "Decorations.java:693"
        },
        {
          "method": "org.eclipse.swt.widgets.Shell.releaseWidget",
          "source": "Shell.java:791"
        },
        {
          "method": "org.eclipse.swt.widgets.Widget.dispose",
          "source": "Widget.java"
        },
        {
          "method": "org.eclipse.swt.widgets.Decorations.dispose",
          "source": "Decorations.java:371"
        },
        {
          "method": "org.eclipse.swt.widgets.Shell.dispose",
          "source": "Shell.java:487"
        },
        {
          "method": "org.eclipse.jface.window.Window.close",
          "source": "Window.java:253"
        },
        {
          "method": "org.eclipse.jface.window.ApplicationWindow.close",
          "source": "ApplicationWindow.java:272"
        },
        {
          "method": "org.eclipse.ui.internal.WorkbenchWindow.hardClose",
          "source": "WorkbenchWindow.java:1012"
        },
        {
          "method": "org.eclipse.ui.internal.WorkbenchWindow.busyClose",
          "source": "WorkbenchWindow.java:466"
        },
        {
          "method": "org.eclipse.ui.internal.WorkbenchWindow.access$0",
          "source": "WorkbenchWindow.java:448"
        },
        {
          "method": "org.eclipse.ui.internal.WorkbenchWindow$1.run",
          "source": "WorkbenchWindow.java:536"
        },
        {
          "method": "org.eclipse.swt.custom.BusyIndicator.showWhile",
          "source": "BusyIndicator.java"
        },
        {
          "method": "org.eclipse.ui.internal.WorkbenchWindow.close",
          "source": "WorkbenchWindow.java:534"
        },
        {
          "method": "org.eclipse.jface.window.Window.handleShellCloseEvent",
          "source": "Window.java:593"
        },
        {
          "method": "org.eclipse.jface.window.Window$2.shellClosed",
          "source": "Window.java:544"
        },
        {
          "method": "org.eclipse.swt.widgets.TypedListener.handleEvent",
          "source": "TypedListener.java"
        },
        {
          "method": "org.eclipse.swt.widgets.EventTable.sendEvent",
          "source": "EventTable.java"
        },
        {
          "method": "org.eclipse.swt.widgets.Widget.sendEvent",
          "source": "Widget.java"
        },
        {
          "method": "org.eclipse.swt.widgets.Widget.sendEvent",
          "source": "Widget.java"
        },
        {
          "method": "org.eclipse.swt.widgets.Widget.sendEvent",
          "source": "Widget.java"
        },
        {
          "method": "org.eclipse.swt.widgets.Decorations.WM_CLOSE",
          "source": "Decorations.java:1486"
        },
        {
          "method": "org.eclipse.swt.widgets.Control.windowProc",
          "source": "Control.java"
        },
        {
          "method": "org.eclipse.swt.widgets.Decorations.windowProc",
          "source": "Decorations.java"
        },
        {
          "method": "org.eclipse.swt.widgets.Display.windowProc",
          "source": "Display.java"
        },
        {
          "method": "org.eclipse.swt.internal.win32.OS.DefWindowProcW",
          "source": "Native Method"
        },
        {
          "method": "org.eclipse.swt.internal.win32.OS.DefWindowProc",
          "source": "OS.java"
        },
        {
          "method": "org.eclipse.swt.widgets.Shell.callWindowProc",
          "source": "Shell.java"
        },
        {
          "method": "org.eclipse.swt.widgets.Control.windowProc",
          "source": "Control.java"
        },
        {
          "method": "org.eclipse.swt.widgets.Decorations.windowProc",
          "source": "Decorations.java"
        },
        {
          "method": "org.eclipse.swt.widgets.Display.windowProc",
          "source": "Display.java"
        },
        {
          "method": "org.eclipse.swt.internal.win32.OS.DispatchMessageW",
          "source": "Native Method"
        },
        {
          "method": "org.eclipse.swt.internal.win32.OS.DispatchMessage",
          "source": "OS.java"
        },
        {
          "method": "org.eclipse.swt.widgets.Display.readAndDispatch",
          "source": "Display.java"
        },
        {
          "method": "org.eclipse.ui.internal.Workbench.runEventLoop",
          "source": "Workbench.java:1362"
        },
        {
          "method": "org.eclipse.ui.internal.Workbench.runUI",
          "source": "Workbench.java:1333"
        },
        {
          "method": "org.eclipse.ui.internal.Workbench.createAndRunWorkbench",
          "source": "Workbench.java:252"
        },
        {
          "method": "org.eclipse.ui.PlatformUI.createAndRunWorkbench",
          "source": "PlatformUI.java:141"
        },
        {
          "method": "org.eclipse.ui.internal.ide.IDEApplication.run",
          "source": "IDEApplication.java:96"
        },
        {
          "method": "org.eclipse.core.internal.runtime.PlatformActivator$1.run",
          "source": "PlatformActivator.java:334"
        },
        {
          "method": "org.eclipse.core.runtime.adaptor.EclipseStarter.run",
          "source": "EclipseStarter.java:272"
        },
        {
          "method": "org.eclipse.core.runtime.adaptor.EclipseStarter.run",
          "source": "EclipseStarter.java:128"
        },
        {
          "method": "sun.reflect.NativeMethodAccessorImpl.invoke0",
          "source": "Native Method"
        },
        {
          "method": "sun.reflect.NativeMethodAccessorImpl.invoke",
          "source": "NativeMethodAccessorImpl.java:84"
        },
        {
          "method": "sun.reflect.NativeMethodAccessorImpl.invoke",
          "source": "NativeMethodAccessorImpl.java:57"
        },
        {
          "method": "sun.reflect.DelegatingMethodAccessorImpl.invoke",
          "source": "DelegatingMethodAccessorImpl.java:59"
        },
        {
          "method": "java.lang.reflect.Method.invoke",
          "source": "Method.java:390"
        },
        {
          "method": "org.eclipse.core.launcher.Main.basicRun",
          "source": "Main.java:185"
        },
        {
          "method": "org.eclipse.core.launcher.Main.run",
          "source": "Main.java:638"
        },
        {
          "method": "org.eclipse.core.launcher.Main.main",
          "source": "Main.java:622"
        }
      ],
      "number": 0,
      "commentIndex": 0,
      "bugId": "66784",
      "duplicateId": "67660",
      "date": "2004-06-11T22:32:10+02:00",
      "product": "Platform",
      "component": "SWT",
      "severity": "normal"
    }
  ],
  "groupId": "68096",
  "bugId": "66784",
  "duplicateId": "67660",
  "date": "2004-06-11T22:32:10+02:00",
  "product": "Platform",
  "component": "SWT",
  "severity": "normal"
}