{
  "comments": [
    "RC2\n\n- no steps, will try to reproduce\n- set-up:\n\nsrc // linked source folder\n|- encoding // package, UTF-8\n    |- LATIN1Class.java // ISO-8851-1\n\n- I played around with various encodings, suddenly got this:\n\n!ENTRY org.eclipse.ui 4 0 Jun 14, 2004 12:02:23.849\n!MESSAGE java.lang.NullPointerException\n!STACK 0\njava.lang.NullPointerException\n        at\norg.eclipse.ui.texteditor.AbstractTextEditor.getAction(AbstractTextEditor.java:3647)\n        at\norg.eclipse.ui.editors.text.EncodingActionGroup.update(EncodingActionGroup.java:430)\n        at\norg.eclipse.ui.editors.text.EncodingActionGroup$2.menuAboutToShow(EncodingActionGroup.java:357)\n        at\norg.eclipse.jface.action.MenuManager.fireAboutToShow(MenuManager.java:286)\n        at\norg.eclipse.jface.action.MenuManager.handleAboutToShow(MenuManager.java:370)\n        at org.eclipse.jface.action.MenuManager.access$0(MenuManager.java:367)\n        at org.eclipse.jface.action.MenuManager$2.menuShown(MenuManager.java:383)\n        at org.eclipse.swt.widgets.TypedListener.handleEvent(TypedListener.java:116)\n        at org.eclipse.swt.widgets.EventTable.sendEvent(EventTable.java:82)\n        at org.eclipse.swt.widgets.Widget.sendEvent(Widget.java:950)\n        at org.eclipse.swt.widgets.Widget.sendEvent(Widget.java:974)\n        at org.eclipse.swt.widgets.Widget.sendEvent(Widget.java:955)\n        at org.eclipse.swt.widgets.Menu.gtk_show(Menu.java:561)\n        at org.eclipse.swt.widgets.Widget.windowProc(Widget.java:1174)\n        at org.eclipse.swt.widgets.Display.windowProc(Display.java:3014)\n        at org.eclipse.swt.internal.gtk.OS.gtk_main_iteration(Native Method)\n        at org.eclipse.swt.widgets.Display.readAndDispatch(Display.java:2222)\n        at org.eclipse.ui.internal.Workbench.runEventLoop(Workbench.java:1362)\n        at org.eclipse.ui.internal.Workbench.runUI(Workbench.java:1333)\n        at\norg.eclipse.ui.internal.Workbench.createAndRunWorkbench(Workbench.java:252)\n        at org.eclipse.ui.PlatformUI.createAndRunWorkbench(PlatformUI.java:141)\n        at org.eclipse.ui.internal.ide.IDEApplication.run(IDEApplication.java:96)\n        at\norg.eclipse.core.internal.runtime.PlatformActivator$1.run(PlatformActivator.java:334)\n        at\norg.eclipse.core.runtime.adaptor.EclipseStarter.run(EclipseStarter.java:272)\n        at\norg.eclipse.core.runtime.adaptor.EclipseStarter.run(EclipseStarter.java:128)\n        at sun.reflect.NativeMethodAccessorImpl.invoke0(Native Method)\n        at\nsun.reflect.NativeMethodAccessorImpl.invoke(NativeMethodAccessorImpl.java:39)\n        at\nsun.reflect.DelegatingMethodAccessorImpl.invoke(DelegatingMethodAccessorImpl.java:25)\n        at java.lang.reflect.Method.invoke(Method.java:324)\n        at org.eclipse.core.launcher.Main.basicRun(Main.java:185)\n        at org.eclipse.core.launcher.Main.run(Main.java:638)\n        at org.eclipse.core.launcher.Main.main(Main.java:622)\njava.lang.NullPointerException",
    "This implies that the editor for which the menu is opened has already been \ndisposed.",
    "Any other dump in .log?\nThere\u0027s no posted code invoked here.\n",
    "No, in that case, this was the first exception in the log for that session.",
    "We can\u0027t reproduce. Tried again using N20050603-0010.",
    "Get rid of deprecated state.",
    "."
  ],
  "commentCreationDates": [
    "2004-06-14T12:19:04+02:00",
    "2004-06-16T15:18:39+02:00",
    "2004-06-16T15:55:03+02:00",
    "2004-06-16T16:19:21+02:00",
    "2005-06-04T17:10:30+02:00",
    "2007-06-22T15:58:47+02:00",
    "2007-06-22T16:04:13+02:00"
  ],
  "traces": [
    {
      "exceptionType": "java.lang.NullPointerException",
      "elements": [
        {
          "method": "org.eclipse.ui.texteditor.AbstractTextEditor.getAction",
          "source": "AbstractTextEditor.java:3647"
        },
        {
          "method": "org.eclipse.ui.editors.text.EncodingActionGroup.update",
          "source": "EncodingActionGroup.java:430"
        },
        {
          "method": "org.eclipse.ui.editors.text.EncodingActionGroup$2.menuAboutToShow",
          "source": "EncodingActionGroup.java:357"
        },
        {
          "method": "org.eclipse.jface.action.MenuManager.fireAboutToShow",
          "source": "MenuManager.java:286"
        },
        {
          "method": "org.eclipse.jface.action.MenuManager.handleAboutToShow",
          "source": "MenuManager.java:370"
        },
        {
          "method": "org.eclipse.jface.action.MenuManager.access$0",
          "source": "MenuManager.java:367"
        },
        {
          "method": "org.eclipse.jface.action.MenuManager$2.menuShown",
          "source": "MenuManager.java:383"
        },
        {
          "method": "org.eclipse.swt.widgets.TypedListener.handleEvent",
          "source": "TypedListener.java:116"
        },
        {
          "method": "org.eclipse.swt.widgets.EventTable.sendEvent",
          "source": "EventTable.java:82"
        },
        {
          "method": "org.eclipse.swt.widgets.Widget.sendEvent",
          "source": "Widget.java:950"
        },
        {
          "method": "org.eclipse.swt.widgets.Widget.sendEvent",
          "source": "Widget.java:974"
        },
        {
          "method": "org.eclipse.swt.widgets.Widget.sendEvent",
          "source": "Widget.java:955"
        },
        {
          "method": "org.eclipse.swt.widgets.Menu.gtk_show",
          "source": "Menu.java:561"
        },
        {
          "method": "org.eclipse.swt.widgets.Widget.windowProc",
          "source": "Widget.java:1174"
        },
        {
          "method": "org.eclipse.swt.widgets.Display.windowProc",
          "source": "Display.java:3014"
        },
        {
          "method": "org.eclipse.swt.internal.gtk.OS.gtk_main_iteration",
          "source": "Native Method"
        },
        {
          "method": "org.eclipse.swt.widgets.Display.readAndDispatch",
          "source": "Display.java:2222"
        },
        {
          "method": "org.eclipse.ui.internal.Workbench.runEventLoop",
          "source": "Workbench.java:1362"
        },
        {
          "method": "org.eclipse.ui.internal.Workbench.runUI",
          "source": "Workbench.java:1333"
        },
        {
          "method": "org.eclipse.ui.internal.Workbench.createAndRunWorkbench",
          "source": "Workbench.java:252"
        },
        {
          "method": "org.eclipse.ui.PlatformUI.createAndRunWorkbench",
          "source": "PlatformUI.java:141"
        },
        {
          "method": "org.eclipse.ui.internal.ide.IDEApplication.run",
          "source": "IDEApplication.java:96"
        },
        {
          "method": "org.eclipse.core.internal.runtime.PlatformActivator$1.run",
          "source": "PlatformActivator.java:334"
        },
        {
          "method": "org.eclipse.core.runtime.adaptor.EclipseStarter.run",
          "source": "EclipseStarter.java:272"
        },
        {
          "method": "org.eclipse.core.runtime.adaptor.EclipseStarter.run",
          "source": "EclipseStarter.java:128"
        },
        {
          "method": "sun.reflect.NativeMethodAccessorImpl.invoke0",
          "source": "Native Method"
        },
        {
          "method": "sun.reflect.NativeMethodAccessorImpl.invoke",
          "source": "NativeMethodAccessorImpl.java:39"
        },
        {
          "method": "sun.reflect.DelegatingMethodAccessorImpl.invoke",
          "source": "DelegatingMethodAccessorImpl.java:25"
        },
        {
          "method": "java.lang.reflect.Method.invoke",
          "source": "Method.java:324"
        },
        {
          "method": "org.eclipse.core.launcher.Main.basicRun",
          "source": "Main.java:185"
        },
        {
          "method": "org.eclipse.core.launcher.Main.run",
          "source": "Main.java:638"
        },
        {
          "method": "org.eclipse.core.launcher.Main.main",
          "source": "Main.java:622"
        }
      ],
      "number": 0,
      "commentIndex": 0,
      "bugId": "66900",
      "date": "2004-06-14T12:19:04+02:00",
      "product": "Platform",
      "component": "Text",
      "severity": "major"
    }
  ],
  "groupId": "66900",
  "bugId": "66900",
  "date": "2004-06-14T12:19:04+02:00",
  "product": "Platform",
  "component": "Text",
  "severity": "major"
}