{
  "comments": [
    "2 org.eclipse.core.resources 2 Problems occurred when invoking code from plug-\nin: org.eclipse.core.resources.\njava.lang.NullPointerException\n        at org.eclipse.jdt.internal.core.DeltaProcessor.initializeRoots\n(DeltaProcessor.java:588)\n        at org.eclipse.jdt.internal.core.DeltaProcessor.processResourceDelta\n(DeltaProcessor.java:717)\n        at org.eclipse.jdt.internal.core.JavaModelManager.resourceChanged\n(JavaModelManager.java:1131)\n        at org.eclipse.core.internal.events.NotificationManager$1.run\n(NotificationManager.java:125)\n        at org.eclipse.core.internal.runtime.InternalPlatform.run\n(InternalPlatform.java:818)\n        at org.eclipse.core.runtime.Platform.run(Platform.java:395)\n        at org.eclipse.core.internal.events.NotificationManager.notify\n(NotificationManager.java:140)\n        at org.eclipse.core.internal.events.NotificationManager.broadcastChanges\n(NotificationManager.java:43)\n        at org.eclipse.core.internal.events.NotificationManager.broadcastChanges\n(NotificationManager.java:64)\n        at org.eclipse.core.internal.resources.Workspace.broadcastChanges\n(Workspace.java:121)\n        at org.eclipse.core.internal.resources.Workspace.endOperation\n(Workspace.java:709)\n        at org.eclipse.core.internal.resources.Workspace.run\n(Workspace.java:1236)\n        at org.eclipse.ui.actions.WorkspaceModifyOperation.run\n(WorkspaceModifyOperation.java:78)\n        at org.eclipse.jface.operation.ModalContext$ModalContextThread.run\n(ModalContext.java:98)",
    "Seems a duplicate of 6621. Just to confirm did you notice the problem early \nafter startup ?",
    "\n\n*** This bug has been marked as a duplicate of 6586 ***"
  ],
  "commentCreationDates": [
    "2001-12-07T23:10:49+01:00",
    "2001-12-07T23:51:42+01:00",
    "2001-12-11T10:12:00+01:00"
  ],
  "traces": [
    {
      "exceptionType": "java.lang.NullPointerException",
      "elements": [
        {
          "method": "org.eclipse.jdt.internal.core.DeltaProcessor.initializeRoots",
          "source": "DeltaProcessor.java:588"
        },
        {
          "method": "org.eclipse.jdt.internal.core.DeltaProcessor.processResourceDelta",
          "source": "DeltaProcessor.java:717"
        },
        {
          "method": "org.eclipse.jdt.internal.core.JavaModelManager.resourceChanged",
          "source": "JavaModelManager.java:1131"
        },
        {
          "method": "org.eclipse.core.internal.events.NotificationManager$1.run",
          "source": "NotificationManager.java:125"
        },
        {
          "method": "org.eclipse.core.internal.runtime.InternalPlatform.run",
          "source": "InternalPlatform.java:818"
        },
        {
          "method": "org.eclipse.core.runtime.Platform.run",
          "source": "Platform.java:395"
        },
        {
          "method": "org.eclipse.core.internal.events.NotificationManager.notify",
          "source": "NotificationManager.java:140"
        },
        {
          "method": "org.eclipse.core.internal.events.NotificationManager.broadcastChanges",
          "source": "NotificationManager.java:43"
        },
        {
          "method": "org.eclipse.core.internal.events.NotificationManager.broadcastChanges",
          "source": "NotificationManager.java:64"
        },
        {
          "method": "org.eclipse.core.internal.resources.Workspace.broadcastChanges",
          "source": "Workspace.java:121"
        },
        {
          "method": "org.eclipse.core.internal.resources.Workspace.endOperation",
          "source": "Workspace.java:709"
        },
        {
          "method": "org.eclipse.core.internal.resources.Workspace.run",
          "source": "Workspace.java:1236"
        },
        {
          "method": "org.eclipse.ui.actions.WorkspaceModifyOperation.run",
          "source": "WorkspaceModifyOperation.java:78"
        },
        {
          "method": "org.eclipse.jface.operation.ModalContext$ModalContextThread.run",
          "source": "ModalContext.java:98"
        }
      ],
      "number": 0,
      "commentIndex": 0,
      "bugId": "6695",
      "duplicateId": "6586",
      "date": "2001-12-07T23:10:49+01:00",
      "product": "JDT",
      "component": "Core",
      "severity": "normal"
    }
  ],
  "groupId": "6586",
  "bugId": "6695",
  "duplicateId": "6586",
  "date": "2001-12-07T23:10:49+01:00",
  "product": "JDT",
  "component": "Core",
  "severity": "normal"
}