{
  "comments": [
    "I just got a NullPointerException - apparently in the CVS view (according to \nthe stacktrace) which caused another deadlock:\n\nthe stacktrace - from console (but .log shows exactly the same):\n!SESSION Jun 16, 2004 11:33:31.997 ---------------------------------------------\neclipse.buildId\u003dI200406110010\njava.version\u003d1.4.2_03\njava.vendor\u003dSun Microsystems Inc.\nBootLoader constants: OS\u003dwin32, ARCH\u003dx86, WS\u003dwin32, NL\u003dde_CH\n\n!ENTRY org.eclipse.ui 4 4 Jun 16, 2004 11:33:31.997\n!MESSAGE Unhandled event loop exception\nUnhandled event loop exception\nReason:\n\n!ENTRY org.eclipse.ui 4 0 Jun 16, 2004 11:33:32.07\n!MESSAGE java.lang.NullPointerException\n!STACK 0\njava.lang.NullPointerException\n        at org.eclipse.team.internal.ccvs.ui.actions.SyncAction$2.run\n(SyncAction.java:76)\n        at org.eclipse.swt.widgets.Synchronizer.syncExec(Synchronizer.java:135)\n        at org.eclipse.ui.internal.UISynchronizer.syncExec\n(UISynchronizer.java:25)\n        at org.eclipse.swt.widgets.Display.syncExec(Display.java:3056)\n        at \norg.eclipse.team.internal.ccvs.ui.actions.SyncAction.showSingleFileComparison\n(SyncAction.java:74)\n        at org.eclipse.team.internal.ccvs.ui.actions.SyncAction.execute\n(SyncAction.java:43)\n        at org.eclipse.team.internal.ccvs.ui.actions.CVSAction.run\n(CVSAction.java:70)\n        at org.eclipse.ui.actions.ActionDelegate.runWithEvent\n(ActionDelegate.java:71)\n        at org.eclipse.ui.internal.PluginAction.runWithEvent\n(PluginAction.java:266)\n        at org.eclipse.jface.action.ActionContributionItem.handleWidgetSelection\n(ActionContributionItem.java:915)\n        at org.eclipse.jface.action.ActionContributionItem.access$2\n(ActionContributionItem.java:866)\n        at org.eclipse.jface.action.ActionContributionItem$7.handleEvent\n(ActionContributionItem.java:785)\n        at org.eclipse.swt.widgets.EventTable.sendEvent(EventTable.java:82)\n        at org.eclipse.swt.widgets.Widget.sendEvent(Widget.java:796)\n        at org.eclipse.swt.widgets.Display.runDeferredEvents(Display.java:2732)\n        at org.eclipse.swt.widgets.Display.readAndDispatch(Display.java:2398)\n        at org.eclipse.ui.internal.Workbench.runEventLoop(Workbench.java:1362)\n        at org.eclipse.ui.internal.Workbench.runUI(Workbench.java:1333)\n        at org.eclipse.ui.internal.Workbench.createAndRunWorkbench\n(Workbench.java:252)\n        at org.eclipse.ui.PlatformUI.createAndRunWorkbench(PlatformUI.java:141)\n        at org.eclipse.ui.internal.ide.IDEApplication.run\n(IDEApplication.java:96)\n        at org.eclipse.core.internal.runtime.PlatformActivator$1.run\n(PlatformActivator.java:334)\n        at org.eclipse.core.runtime.adaptor.EclipseStarter.run\n(EclipseStarter.java:272)\n        at org.eclipse.core.runtime.adaptor.EclipseStarter.run\n(EclipseStarter.java:128)\n        at sun.reflect.NativeMethodAccessorImpl.invoke0(Native Method)\n        at sun.reflect.NativeMethodAccessorImpl.invoke(Unknown Source)\n        at sun.reflect.DelegatingMethodAccessorImpl.invoke(Unknown Source)\n        at java.lang.reflect.Method.invoke(Unknown Source)\n        at org.eclipse.core.launcher.Main.basicRun(Main.java:185)\n        at org.eclipse.core.launcher.Main.run(Main.java:638)\n        at org.eclipse.core.launcher.Main.main(Main.java:622)\njava.lang.NullPointerException\n\n!ENTRY org.eclipse.jdt.launching 4 150 Jun 16, 2004 11:34:01.520\n!MESSAGE The archive: /act/import/lib/commons-logging.jar which is referenced \nby the classpath, does not exist.\n\n\nThe corresponding thread-dump:\n-------------------------------------------------------------------\nFull thread dump Java HotSpot(TM) Client VM (1.4.2_03-b02 mixed mode):\n\n\"Worker-16\" prio\u003d5 tid\u003d0x02e65528 nid\u003d0xa14 in Object.wait() [3c9f000..3c9fd8c]\n        at java.lang.Object.wait(Native Method)\n        at org.eclipse.core.internal.jobs.WorkerPool.sleep(WorkerPool.java:166)\n        - locked \u003c0x11941488\u003e (a org.eclipse.core.internal.jobs.WorkerPool)\n        at org.eclipse.core.internal.jobs.WorkerPool.startJob\n(WorkerPool.java:193)\n        at org.eclipse.core.internal.jobs.Worker.run(Worker.java:59)\n\n\"Thread-758\" daemon prio\u003d7 tid\u003d0x0452eeb8 nid\u003d0x3c0 waiting for monitor entry \n[53bf000..53bfd8c]\n        at org.eclipse.jface.text.source.AnnotationMap.keySetIterator\n(AnnotationMap.java:73)\n        - waiting to lock \u003c0x15e81c80\u003e (a java.lang.Object)\n        at org.eclipse.jface.text.source.AnnotationModel.getAnnotationIterator\n(AnnotationModel.java:555)\n        at org.eclipse.jface.text.source.AnnotationModel.getAnnotationIterator\n(AnnotationModel.java:498)\n        at org.eclipse.jface.text.source.AnnotationModel.getAnnotationIterator\n(AnnotationModel.java:478)\n        at \norg.eclipse.jface.text.source.projection.ProjectionSummary.removeSummaries\n(ProjectionSummary.java:156)\n        at \norg.eclipse.jface.text.source.projection.ProjectionSummary.internalUpdateSummari\nes(ProjectionSummary.java:129)\n        at org.eclipse.jface.text.source.projection.ProjectionSummary.access$3\n(ProjectionSummary.java:111)\n        at \norg.eclipse.jface.text.source.projection.ProjectionSummary$Summarizer.run\n(ProjectionSummary.java:61)\n\n\"org.eclipse.jdt.internal.ui.text.JavaReconciler\" daemon prio\u003d2 tid\u003d0x0479bbb8 \nnid\u003d0x4b8 waiting for monitor entry [537f000..537fd8c\n]\n        at org.eclipse.jface.text.source.AnnotationPainter.modelChanged\n(AnnotationPainter.java:895)\n        - waiting to lock \u003c0x15eb50e8\u003e (a \norg.eclipse.jface.text.source.AnnotationPainter)\n        at org.eclipse.jface.text.source.AnnotationModel.fireModelChanged\n(AnnotationModel.java:401)\n        at org.eclipse.jface.text.source.AnnotationModel.fireModelChanged\n(AnnotationModel.java:367)\n        at org.eclipse.jface.text.source.AnnotationModel.replaceAnnotations\n(AnnotationModel.java:210)\n        at org.eclipse.jface.text.source.AnnotationModel.replaceAnnotations\n(AnnotationModel.java:175)\n        at \norg.eclipse.jdt.internal.ui.javaeditor.OverrideIndicatorManager.updateAnnotation\ns(OverrideIndicatorManager.java:262)\n        - locked \u003c0x15e81c80\u003e (a java.lang.Object)\n        at \norg.eclipse.jdt.internal.ui.javaeditor.OverrideIndicatorManager.reconciled\n(OverrideIndicatorManager.java:303)\n        at \norg.eclipse.jdt.internal.ui.javaeditor.CompilationUnitEditor.reconciled\n(CompilationUnitEditor.java:1743)\n        at \norg.eclipse.jdt.internal.ui.text.java.JavaReconcilingStrategy.reconcile\n(JavaReconcilingStrategy.java:117)\n        at \norg.eclipse.jdt.internal.ui.text.java.JavaReconcilingStrategy.initialReconcile\n(JavaReconcilingStrategy.java:156)\n        at \norg.eclipse.jdt.internal.ui.text.CompositeReconcilingStrategy.initialReconcile\n(CompositeReconcilingStrategy.java:114)\n        at \norg.eclipse.jdt.internal.ui.text.JavaCompositeReconcilingStrategy.initialReconci\nle(JavaCompositeReconcilingStrategy.java:\n122)\n        at org.eclipse.jface.text.reconciler.MonoReconciler.initialProcess\n(MonoReconciler.java:104)\n        at org.eclipse.jdt.internal.ui.text.JavaReconciler.initialProcess\n(JavaReconciler.java:304)\n        - locked \u003c0x15e80e78\u003e (a java.lang.Object)\n        at \norg.eclipse.jface.text.reconciler.AbstractReconciler$BackgroundThread.run\n(AbstractReconciler.java:169)\n\n\"org.eclipse.jdt.internal.ui.text.JavaReconciler\" daemon prio\u003d2 tid\u003d0x045b54a8 \nnid\u003d0x504 in Object.wait() [530f000..530fd8c]\n        at java.lang.Object.wait(Native Method)\n        at \norg.eclipse.jface.text.reconciler.AbstractReconciler$BackgroundThread.run\n(AbstractReconciler.java:175)\n        - locked \u003c0x15c2de60\u003e (a \norg.eclipse.jface.text.reconciler.DirtyRegionQueue)\n\n\"org.eclipse.jdt.internal.ui.text.JavaReconciler\" daemon prio\u003d2 tid\u003d0x046454e8 \nnid\u003d0xb34 in Object.wait() [52cf000..52cfd8c]\n        at java.lang.Object.wait(Native Method)\n        at \norg.eclipse.jface.text.reconciler.AbstractReconciler$BackgroundThread.run\n(AbstractReconciler.java:175)\n        - locked \u003c0x15ae17e8\u003e (a \norg.eclipse.jface.text.reconciler.DirtyRegionQueue)\n\n\"org.eclipse.jdt.internal.ui.text.JavaReconciler\" daemon prio\u003d2 tid\u003d0x04590b10 \nnid\u003d0xcb0 runnable [528f000..528fd8c]\n        at java.lang.Object.wait(Native Method)\n        at \norg.eclipse.jface.text.reconciler.AbstractReconciler$BackgroundThread.run\n(AbstractReconciler.java:175)\n        - locked \u003c0x15a3fd70\u003e (a \norg.eclipse.jface.text.reconciler.DirtyRegionQueue)\n\n\"org.eclipse.jdt.internal.ui.text.JavaReconciler\" daemon prio\u003d2 tid\u003d0x0458eb30 \nnid\u003d0x88c runnable [524f000..524fd8c]\n        at java.lang.Object.wait(Native Method)\n        at \norg.eclipse.jface.text.reconciler.AbstractReconciler$BackgroundThread.run\n(AbstractReconciler.java:175)\n        - locked \u003c0x15950560\u003e (a \norg.eclipse.jface.text.reconciler.DirtyRegionQueue)\n\n\"org.eclipse.jdt.internal.ui.text.JavaReconciler\" daemon prio\u003d2 tid\u003d0x047d2e10 \nnid\u003d0xd80 runnable [520f000..520fd8c]\n        at java.lang.Object.wait(Native Method)\n        at \norg.eclipse.jface.text.reconciler.AbstractReconciler$BackgroundThread.run\n(AbstractReconciler.java:175)\n        - locked \u003c0x1585fe50\u003e (a \norg.eclipse.jface.text.reconciler.DirtyRegionQueue)\n\n\"org.eclipse.jdt.internal.ui.text.JavaReconciler\" daemon prio\u003d2 tid\u003d0x046398c8 \nnid\u003d0xd48 runnable [51cf000..51cfd8c]\n        at java.lang.Object.wait(Native Method)\n        at \norg.eclipse.jface.text.reconciler.AbstractReconciler$BackgroundThread.run\n(AbstractReconciler.java:175)\n        - locked \u003c0x1574a120\u003e (a \norg.eclipse.jface.text.reconciler.DirtyRegionQueue)\n\n\"org.eclipse.jdt.internal.ui.text.JavaReconciler\" daemon prio\u003d2 tid\u003d0x04638788 \nnid\u003d0x310 runnable [516f000..516fd8c]\n        at java.lang.Object.wait(Native Method)\n        at \norg.eclipse.jface.text.reconciler.AbstractReconciler$BackgroundThread.run\n(AbstractReconciler.java:175)\n        - locked \u003c0x1564d2f8\u003e (a \norg.eclipse.jface.text.reconciler.DirtyRegionQueue)\n\n\"org.eclipse.jdt.internal.ui.text.JavaReconciler\" daemon prio\u003d2 tid\u003d0x0472d768 \nnid\u003d0x9fc runnable [506f000..506fd8c]\n        at java.lang.Object.wait(Native Method)\n        at \norg.eclipse.jface.text.reconciler.AbstractReconciler$BackgroundThread.run\n(AbstractReconciler.java:175)\n        - locked \u003c0x1556edb0\u003e (a \norg.eclipse.jface.text.reconciler.DirtyRegionQueue)\n\n\"org.eclipse.jdt.internal.ui.text.JavaReconciler\" daemon prio\u003d2 tid\u003d0x04526330 \nnid\u003d0xacc runnable [421f000..421fd8c]\n        at java.lang.Object.wait(Native Method)\n        at \norg.eclipse.jface.text.reconciler.AbstractReconciler$BackgroundThread.run\n(AbstractReconciler.java:175)\n        - locked \u003c0x153f3de8\u003e (a \norg.eclipse.jface.text.reconciler.DirtyRegionQueue)\n\n\"Worker-12\" prio\u003d5 tid\u003d0x046bf678 nid\u003d0x968 in Object.wait() [512f000..512fd8c]\n        at java.lang.Object.wait(Native Method)\n        at org.eclipse.core.internal.jobs.WorkerPool.sleep(WorkerPool.java:166)\n        - locked \u003c0x11941488\u003e (a org.eclipse.core.internal.jobs.WorkerPool)\n        at org.eclipse.core.internal.jobs.WorkerPool.startJob\n(WorkerPool.java:193)\n        at org.eclipse.core.internal.jobs.Worker.run(Worker.java:59)\n\n\"org.eclipse.jdt.internal.ui.text.JavaReconciler\" daemon prio\u003d2 tid\u003d0x0322ecb8 \nnid\u003d0x14c runnable [4e2f000..4e2fd8c]\n        at java.lang.Object.wait(Native Method)\n        at \norg.eclipse.jface.text.reconciler.AbstractReconciler$BackgroundThread.run\n(AbstractReconciler.java:175)\n        - locked \u003c0x13793d18\u003e (a \norg.eclipse.jface.text.reconciler.DirtyRegionQueue)\n\n\"org.eclipse.jdt.internal.ui.text.JavaReconciler\" daemon prio\u003d2 tid\u003d0x04403b20 \nnid\u003d0xb24 runnable [4c2f000..4c2fd8c]\n        at java.lang.Object.wait(Native Method)\n        - waiting on \u003c0x13597058\u003e (a \norg.eclipse.jface.text.reconciler.DirtyRegionQueue)\n        at \norg.eclipse.jface.text.reconciler.AbstractReconciler$BackgroundThread.run\n(AbstractReconciler.java:175)\n        - locked \u003c0x13597058\u003e (a \norg.eclipse.jface.text.reconciler.DirtyRegionQueue)\n\n\"org.eclipse.jdt.internal.ui.text.JavaReconciler\" daemon prio\u003d2 tid\u003d0x04381a68 \nnid\u003d0xee4 runnable [4bef000..4befd8c]\n        at java.lang.Object.wait(Native Method)\n        - waiting on \u003c0x13509ca0\u003e (a \norg.eclipse.jface.text.reconciler.DirtyRegionQueue)\n        at \norg.eclipse.jface.text.reconciler.AbstractReconciler$BackgroundThread.run\n(AbstractReconciler.java:175)\n        - locked \u003c0x13509ca0\u003e (a \norg.eclipse.jface.text.reconciler.DirtyRegionQueue)\n\n\"org.eclipse.jdt.internal.ui.text.JavaReconciler\" daemon prio\u003d2 tid\u003d0x042aaa50 \nnid\u003d0xdcc runnable [4aaf000..4aafd8c]\n        at java.lang.Object.wait(Native Method)\n        - waiting on \u003c0x13447660\u003e (a \norg.eclipse.jface.text.reconciler.DirtyRegionQueue)\n        at \norg.eclipse.jface.text.reconciler.AbstractReconciler$BackgroundThread.run\n(AbstractReconciler.java:175)\n        - locked \u003c0x13447660\u003e (a \norg.eclipse.jface.text.reconciler.DirtyRegionQueue)\n\n\"Java indexing\" daemon prio\u003d4 tid\u003d0x030b1ac0 nid\u003d0x6dc in Object.wait() \n[3fdf000..3fdfd8c]\n        at java.lang.Object.wait(Native Method)\n        - waiting on \u003c0x11c83a18\u003e (a \norg.eclipse.jdt.internal.core.search.indexing.IndexManager)\n        at java.lang.Object.wait(Unknown Source)\n        at org.eclipse.jdt.internal.core.search.processing.JobManager.run\n(JobManager.java:338)\n        - locked \u003c0x11c83a18\u003e (a \norg.eclipse.jdt.internal.core.search.indexing.IndexManager)\n        at java.lang.Thread.run(Unknown Source)\n\n\"Reference Cleaner - 2\" prio\u003d7 tid\u003d0x0308dba8 nid\u003d0xb1c in Object.wait() \n[3ecf000..3ecfd8c]\n        at java.lang.Object.wait(Native Method)\n        - waiting on \u003c0x11bf39d8\u003e (a java.lang.ref.ReferenceQueue$Lock)\n        at java.lang.ref.ReferenceQueue.remove(Unknown Source)\n        - locked \u003c0x11bf39d8\u003e (a java.lang.ref.ReferenceQueue$Lock)\n        at java.lang.ref.ReferenceQueue.remove(Unknown Source)\n        at \norg.eclipse.jface.action.ActionContributionItem$ImageCache$ReferenceCleanerThrea\nd.run(ActionContributionItem.java:207)\n\n\"Reference Cleaner - 1\" prio\u003d7 tid\u003d0x03065c58 nid\u003d0xbd4 in Object.wait() \n[3e8f000..3e8fd8c]\n        at java.lang.Object.wait(Native Method)\n        - waiting on \u003c0x11bf3a48\u003e (a java.lang.ref.ReferenceQueue$Lock)\n        at java.lang.ref.ReferenceQueue.remove(Unknown Source)\n        - locked \u003c0x11bf3a48\u003e (a java.lang.ref.ReferenceQueue$Lock)\n        at java.lang.ref.ReferenceQueue.remove(Unknown Source)\n        at \norg.eclipse.jface.action.ActionContributionItem$ImageCache$ReferenceCleanerThrea\nd.run(ActionContributionItem.java:207)\n\n\"Start Level Event Dispatcher\" daemon prio\u003d5 tid\u003d0x02ea88e0 nid\u003d0xf0c in \nObject.wait() [2fcf000..2fcfd8c]\n        at java.lang.Object.wait(Native Method)\n        - waiting on \u003c0x117c8f00\u003e (a \norg.eclipse.osgi.framework.eventmgr.EventThread)\n        at java.lang.Object.wait(Unknown Source)\n        at org.eclipse.osgi.framework.eventmgr.EventThread.getNextEvent\n(EventThread.java:162)\n        - locked \u003c0x117c8f00\u003e (a \norg.eclipse.osgi.framework.eventmgr.EventThread)\n        at org.eclipse.osgi.framework.eventmgr.EventThread.run\n(EventThread.java:100)\n\n\"Framework Event Dispatcher\" daemon prio\u003d5 tid\u003d0x009897a8 nid\u003d0x738 in \nObject.wait() [2f8f000..2f8fd8c]\n        at java.lang.Object.wait(Native Method)\n        - waiting on \u003c0x117b1438\u003e (a \norg.eclipse.osgi.framework.eventmgr.EventThread)\n        at java.lang.Object.wait(Unknown Source)\n        at org.eclipse.osgi.framework.eventmgr.EventThread.getNextEvent\n(EventThread.java:162)\n        - locked \u003c0x117b1438\u003e (a \norg.eclipse.osgi.framework.eventmgr.EventThread)\n        at org.eclipse.osgi.framework.eventmgr.EventThread.run\n(EventThread.java:100)\n\n\"Signal Dispatcher\" daemon prio\u003d10 tid\u003d0x008f62e0 nid\u003d0xcec waiting on \ncondition [0..0]\n\n\"Finalizer\" daemon prio\u003d9 tid\u003d0x008f34d8 nid\u003d0xaa0 in Object.wait() \n[2c2f000..2c2fd8c]\n        at java.lang.Object.wait(Native Method)\n        - waiting on \u003c0x1172a238\u003e (a java.lang.ref.ReferenceQueue$Lock)\n        at java.lang.ref.ReferenceQueue.remove(Unknown Source)\n        - locked \u003c0x1172a238\u003e (a java.lang.ref.ReferenceQueue$Lock)\n        at java.lang.ref.ReferenceQueue.remove(Unknown Source)\n        at java.lang.ref.Finalizer$FinalizerThread.run(Unknown Source)\n\n\"Reference Handler\" daemon prio\u003d10 tid\u003d0x008f20a8 nid\u003d0x9b8 in Object.wait() \n[2bef000..2befd8c]\n        at java.lang.Object.wait(Native Method)\n        - waiting on \u003c0x1172a2a0\u003e (a java.lang.ref.Reference$Lock)\n        at java.lang.Object.wait(Unknown Source)\n        at java.lang.ref.Reference$ReferenceHandler.run(Unknown Source)\n        - locked \u003c0x1172a2a0\u003e (a java.lang.ref.Reference$Lock)\n\n\"main\" prio\u003d5 tid\u003d0x00035c78 nid\u003d0x928 waiting for monitor entry [7e000..7fc3c]\n        at org.eclipse.jface.text.source.AnnotationMap.get\n(AnnotationMap.java:100)\n        - waiting to lock \u003c0x15e81c80\u003e (a java.lang.Object)\n        at org.eclipse.jface.text.source.AnnotationModel.getPosition\n(AnnotationModel.java:562)\n        at org.eclipse.jface.text.source.AnnotationPainter.getDecoration\n(AnnotationPainter.java:644)\n        at org.eclipse.jface.text.source.AnnotationPainter.catchupWithModel\n(AnnotationPainter.java:531)\n        at org.eclipse.jface.text.source.AnnotationPainter.updatePainting\n(AnnotationPainter.java:798)\n        at org.eclipse.jface.text.source.AnnotationPainter.modelChanged\n(AnnotationPainter.java:899)\n        - locked \u003c0x15eb50e8\u003e (a \norg.eclipse.jface.text.source.AnnotationPainter)\n        at org.eclipse.jface.text.source.AnnotationModel.fireModelChanged\n(AnnotationModel.java:401)\n        at org.eclipse.jface.text.source.AnnotationModel.fireModelChanged\n(AnnotationModel.java:367)\n        at org.eclipse.ui.texteditor.ResourceMarkerAnnotationModel.update\n(ResourceMarkerAnnotationModel.java:110)\n        at \norg.eclipse.ui.texteditor.ResourceMarkerAnnotationModel$ResourceChangeListener.r\nesourceChanged(ResourceMarkerAnnotationMo\ndel.java:53)\n        at org.eclipse.core.internal.events.NotificationManager$2.run\n(NotificationManager.java:283)\n        at org.eclipse.core.internal.runtime.InternalPlatform.run\n(InternalPlatform.java:615)\n        at org.eclipse.core.runtime.Platform.run(Platform.java:758)\n        at org.eclipse.core.internal.events.NotificationManager.notify\n(NotificationManager.java:277)\n        at org.eclipse.core.internal.events.NotificationManager.broadcastChanges\n(NotificationManager.java:151)\n        at org.eclipse.core.internal.resources.Workspace.broadcastChanges\n(Workspace.java:172)\n        at org.eclipse.core.internal.resources.Workspace.endOperation\n(Workspace.java:900)\n        at org.eclipse.core.internal.resources.Workspace.run\n(Workspace.java:1682)\n        at org.eclipse.core.internal.resources.Workspace.run\n(Workspace.java:1693)\n        at org.eclipse.ajdt.internal.ui.editor.AspectJEditor.addNewMarkers\n(AspectJEditor.java:509)\n        at org.eclipse.ajdt.internal.ui.editor.AspectJEditor$1.run\n(AspectJEditor.java:397)\n        at org.eclipse.swt.widgets.RunnableLock.run(RunnableLock.java:35)\n        at org.eclipse.swt.widgets.Synchronizer.runAsyncMessages\n(Synchronizer.java:106)\n        - locked \u003c0x15f089f0\u003e (a org.eclipse.swt.widgets.RunnableLock)\n        at org.eclipse.swt.widgets.Display.runAsyncMessages(Display.java:2709)\n        at org.eclipse.swt.widgets.Display.readAndDispatch(Display.java:2401)\n        at org.eclipse.ui.internal.Workbench.runEventLoop(Workbench.java:1362)\n        at org.eclipse.ui.internal.Workbench.runUI(Workbench.java:1333)\n        at org.eclipse.ui.internal.Workbench.createAndRunWorkbench\n(Workbench.java:252)\n        at org.eclipse.ui.PlatformUI.createAndRunWorkbench(PlatformUI.java:141)\n        at org.eclipse.ui.internal.ide.IDEApplication.run\n(IDEApplication.java:96)\n        at org.eclipse.core.internal.runtime.PlatformActivator$1.run\n(PlatformActivator.java:334)\n        at org.eclipse.core.runtime.adaptor.EclipseStarter.run\n(EclipseStarter.java:272)\n        at org.eclipse.core.runtime.adaptor.EclipseStarter.run\n(EclipseStarter.java:128)\n        at sun.reflect.NativeMethodAccessorImpl.invoke0(Native Method)\n        at sun.reflect.NativeMethodAccessorImpl.invoke(Unknown Source)\n        at sun.reflect.DelegatingMethodAccessorImpl.invoke(Unknown Source)\n        at java.lang.reflect.Method.invoke(Unknown Source)\n        at org.eclipse.core.launcher.Main.basicRun(Main.java:185)\n        at org.eclipse.core.launcher.Main.run(Main.java:638)\n        at org.eclipse.core.launcher.Main.main(Main.java:622)\n\n\"VM Thread\" prio\u003d5 tid\u003d0x009336b0 nid\u003d0x8e0 runnable\n\n\"VM Periodic Task Thread\" prio\u003d10 tid\u003d0x0094e1a8 nid\u003d0xb0 waiting on condition\n\"Suspend Checker Thread\" prio\u003d10 tid\u003d0x008f5558 nid\u003d0xc28 runnable\n\nFound one Java-level deadlock:\n\u003d\u003d\u003d\u003d\u003d\u003d\u003d\u003d\u003d\u003d\u003d\u003d\u003d\u003d\u003d\u003d\u003d\u003d\u003d\u003d\u003d\u003d\u003d\u003d\u003d\u003d\u003d\u003d\u003d\n\"org.eclipse.jdt.internal.ui.text.JavaReconciler\":\n  waiting to lock monitor 0x008f2db4 (object 0x15eb50e8, a \norg.eclipse.jface.text.source.AnnotationPainter),\n  which is held by \"main\"\n\"main\":\n  waiting to lock monitor 0x008f2d94 (object 0x15e81c80, a java.lang.Object),\n  which is held by \"org.eclipse.jdt.internal.ui.text.JavaReconciler\"\n\nJava stack information for the threads listed above:\n\u003d\u003d\u003d\u003d\u003d\u003d\u003d\u003d\u003d\u003d\u003d\u003d\u003d\u003d\u003d\u003d\u003d\u003d\u003d\u003d\u003d\u003d\u003d\u003d\u003d\u003d\u003d\u003d\u003d\u003d\u003d\u003d\u003d\u003d\u003d\u003d\u003d\u003d\u003d\u003d\u003d\u003d\u003d\u003d\u003d\u003d\u003d\u003d\u003d\u003d\u003d\n\"org.eclipse.jdt.internal.ui.text.JavaReconciler\":\n        at org.eclipse.jface.text.source.AnnotationPainter.modelChanged\n(AnnotationPainter.java:895)\n        - waiting to lock \u003c0x15eb50e8\u003e (a \norg.eclipse.jface.text.source.AnnotationPainter)\n        at org.eclipse.jface.text.source.AnnotationModel.fireModelChanged\n(AnnotationModel.java:401)\n        at org.eclipse.jface.text.source.AnnotationModel.fireModelChanged\n(AnnotationModel.java:367)\n        at org.eclipse.jface.text.source.AnnotationModel.replaceAnnotations\n(AnnotationModel.java:210)\n        at org.eclipse.jface.text.source.AnnotationModel.replaceAnnotations\n(AnnotationModel.java:175)\n        at \norg.eclipse.jdt.internal.ui.javaeditor.OverrideIndicatorManager.updateAnnotation\ns(OverrideIndicatorManager.java:262)\n        - locked \u003c0x15e81c80\u003e (a java.lang.Object)\n        at \norg.eclipse.jdt.internal.ui.javaeditor.OverrideIndicatorManager.reconciled\n(OverrideIndicatorManager.java:303)\n        at \norg.eclipse.jdt.internal.ui.javaeditor.CompilationUnitEditor.reconciled\n(CompilationUnitEditor.java:1743)\n        at \norg.eclipse.jdt.internal.ui.text.java.JavaReconcilingStrategy.reconcile\n(JavaReconcilingStrategy.java:117)\n        at \norg.eclipse.jdt.internal.ui.text.java.JavaReconcilingStrategy.initialReconcile\n(JavaReconcilingStrategy.java:156)\n        at \norg.eclipse.jdt.internal.ui.text.CompositeReconcilingStrategy.initialReconcile\n(CompositeReconcilingStrategy.java:114)\n        at \norg.eclipse.jdt.internal.ui.text.JavaCompositeReconcilingStrategy.initialReconci\nle(JavaCompositeReconcilingStrategy.java:\n122)\n        at org.eclipse.jface.text.reconciler.MonoReconciler.initialProcess\n(MonoReconciler.java:104)\n        at org.eclipse.jdt.internal.ui.text.JavaReconciler.initialProcess\n(JavaReconciler.java:304)\n        - locked \u003c0x15e80e78\u003e (a java.lang.Object)\n        at \norg.eclipse.jface.text.reconciler.AbstractReconciler$BackgroundThread.run\n(AbstractReconciler.java:169)\n\"main\":\n        at org.eclipse.jface.text.source.AnnotationMap.get\n(AnnotationMap.java:100)\n        - waiting to lock \u003c0x15e81c80\u003e (a java.lang.Object)\n        at org.eclipse.jface.text.source.AnnotationModel.getPosition\n(AnnotationModel.java:562)\n        at org.eclipse.jface.text.source.AnnotationPainter.getDecoration\n(AnnotationPainter.java:644)\n        at org.eclipse.jface.text.source.AnnotationPainter.catchupWithModel\n(AnnotationPainter.java:531)\n        at org.eclipse.jface.text.source.AnnotationPainter.updatePainting\n(AnnotationPainter.java:798)\n        at org.eclipse.jface.text.source.AnnotationPainter.modelChanged\n(AnnotationPainter.java:899)\n        - locked \u003c0x15eb50e8\u003e (a \norg.eclipse.jface.text.source.AnnotationPainter)\n        at org.eclipse.jface.text.source.AnnotationModel.fireModelChanged\n(AnnotationModel.java:401)\n        at org.eclipse.jface.text.source.AnnotationModel.fireModelChanged\n(AnnotationModel.java:367)\n        at org.eclipse.ui.texteditor.ResourceMarkerAnnotationModel.update\n(ResourceMarkerAnnotationModel.java:110)\n        at \norg.eclipse.ui.texteditor.ResourceMarkerAnnotationModel$ResourceChangeListener.r\nesourceChanged(ResourceMarkerAnnotationMo\ndel.java:53)\n        at org.eclipse.core.internal.events.NotificationManager$2.run\n(NotificationManager.java:283)\n        at org.eclipse.core.internal.runtime.InternalPlatform.run\n(InternalPlatform.java:615)\n        at org.eclipse.core.runtime.Platform.run(Platform.java:758)\n        at org.eclipse.core.internal.events.NotificationManager.notify\n(NotificationManager.java:277)\n        at org.eclipse.core.internal.events.NotificationManager.broadcastChanges\n(NotificationManager.java:151)\n        at org.eclipse.core.internal.resources.Workspace.broadcastChanges\n(Workspace.java:172)\n        at org.eclipse.core.internal.resources.Workspace.endOperation\n(Workspace.java:900)\n        at org.eclipse.core.internal.resources.Workspace.run\n(Workspace.java:1682)\n        at org.eclipse.core.internal.resources.Workspace.run\n(Workspace.java:1693)\n        at org.eclipse.ajdt.internal.ui.editor.AspectJEditor.addNewMarkers\n(AspectJEditor.java:509)\n        at org.eclipse.ajdt.internal.ui.editor.AspectJEditor$1.run\n(AspectJEditor.java:397)\n        at org.eclipse.swt.widgets.RunnableLock.run(RunnableLock.java:35)\n        at org.eclipse.swt.widgets.Synchronizer.runAsyncMessages\n(Synchronizer.java:106)\n        - locked \u003c0x15f089f0\u003e (a org.eclipse.swt.widgets.RunnableLock)\n        at org.eclipse.swt.widgets.Display.runAsyncMessages(Display.java:2709)\n        at org.eclipse.swt.widgets.Display.readAndDispatch(Display.java:2401)\n        at org.eclipse.ui.internal.Workbench.runEventLoop(Workbench.java:1362)\n        at org.eclipse.ui.internal.Workbench.runUI(Workbench.java:1333)\n        at org.eclipse.ui.internal.Workbench.createAndRunWorkbench\n(Workbench.java:252)\n        at org.eclipse.ui.PlatformUI.createAndRunWorkbench(PlatformUI.java:141)\n        at org.eclipse.ui.internal.ide.IDEApplication.run\n(IDEApplication.java:96)\n        at org.eclipse.core.internal.runtime.PlatformActivator$1.run\n(PlatformActivator.java:334)\n        at org.eclipse.core.runtime.adaptor.EclipseStarter.run\n(EclipseStarter.java:272)\n        at org.eclipse.core.runtime.adaptor.EclipseStarter.run\n(EclipseStarter.java:128)\n        at sun.reflect.NativeMethodAccessorImpl.invoke0(Native Method)\n        at sun.reflect.NativeMethodAccessorImpl.invoke(Unknown Source)\n        at sun.reflect.DelegatingMethodAccessorImpl.invoke(Unknown Source)\n        at java.lang.reflect.Method.invoke(Unknown Source)\n        at org.eclipse.core.launcher.Main.basicRun(Main.java:185)\n        at org.eclipse.core.launcher.Main.run(Main.java:638)\n        at org.eclipse.core.launcher.Main.main(Main.java:622)\n\nFound 1 deadlock.",
    "Move to Platform/CVS",
    "I have opened bug 67464 for the NPE and I\u0027m noving this bug to Platform Text \nto investigate the deadlock (I doubt that the NPE is related to the deadlock).",
    "+1 for RC3",
    "Reviewed by KUM.\nFixed in HEAD.\nWill be released into an upcoming build (\u003e I200406181200)\n\n\n",
    "Start verifying",
    "Verified by code inspection",
    "I just installed M3.0RC3 and got the following - I guess this is now working as \ndesigned. I just wanted to make sure...\nMichael\n\n!SESSION Jun 22, 2004 13:07:47.354 ---------------------------------------------\neclipse.buildId\u003dI200406192000\njava.version\u003d1.4.2_03\njava.vendor\u003dSun Microsystems Inc.\nBootLoader constants: OS\u003dwin32, ARCH\u003dx86, WS\u003dwin32, NL\u003dde_CH\n\n!ENTRY org.eclipse.osgi Jun 22, 2004 13:07:47.364\n!MESSAGE While loading \nclass \"org.eclipse.team.internal.ccvs.ui.console.ConsoleDocument$ConsoleLine\", \nthread \"main\" timed out waitin\ng (5000ms) for thread \"Worker-2\" to finish starting \nbundle \"org.eclipse.team.cvs.ui\". To avoid deadlock, thread \"main\" is proceeding\n but \"org.eclipse.team.internal.ccvs.ui.console.ConsoleDocument$ConsoleLine\" \nmay not be fully initialized.\n!STACK 0\njava.lang.Exception: Generated exception.\n        at org.eclipse.core.runtime.adaptor.EclipseClassLoader.findLocalClass\n(EclipseClassLoader.java:102)\n        at org.eclipse.osgi.framework.internal.core.BundleLoader.findLocalClass\n(BundleLoader.java:371)\n        at org.eclipse.osgi.framework.internal.core.BundleLoader.findClass\n(BundleLoader.java:402)\n        at org.eclipse.osgi.framework.adaptor.core.AbstractClassLoader.loadClass\n(AbstractClassLoader.java:93)\n        at java.lang.ClassLoader.loadClass(Unknown Source)\n        at java.lang.ClassLoader.loadClassInternal(Unknown Source)\n        at org.eclipse.team.internal.ccvs.ui.console.ConsoleDocument.getLines\n(ConsoleDocument.java:78)\n        at org.eclipse.team.internal.ccvs.ui.console.CVSOutputConsole.dump\n(CVSOutputConsole.java:140)\n        at org.eclipse.team.internal.ccvs.ui.console.CVSOutputConsole.access$1\n(CVSOutputConsole.java:137)\n        at org.eclipse.team.internal.ccvs.ui.console.CVSOutputConsole$1.run\n(CVSOutputConsole.java:108)\n        at org.eclipse.swt.widgets.RunnableLock.run(RunnableLock.java:35)\n        at org.eclipse.swt.widgets.Synchronizer.runAsyncMessages\n(Synchronizer.java:106)\n        at org.eclipse.swt.widgets.Display.runAsyncMessages(Display.java:2709)\n        at org.eclipse.swt.widgets.Display.readAndDispatch(Display.java:2401)\n        at org.eclipse.ui.internal.Workbench.runEventLoop(Workbench.java:1375)\n        at org.eclipse.ui.internal.Workbench.runUI(Workbench.java:1346)\n        at org.eclipse.ui.internal.Workbench.createAndRunWorkbench\n(Workbench.java:252)\n        at org.eclipse.ui.PlatformUI.createAndRunWorkbench(PlatformUI.java:141)\n        at org.eclipse.ui.internal.ide.IDEApplication.run\n(IDEApplication.java:96)\n        at org.eclipse.core.internal.runtime.PlatformActivator$1.run\n(PlatformActivator.java:335)\n        at org.eclipse.core.runtime.adaptor.EclipseStarter.run\n(EclipseStarter.java:272)\n        at org.eclipse.core.runtime.adaptor.EclipseStarter.run\n(EclipseStarter.java:128)\n        at sun.reflect.NativeMethodAccessorImpl.invoke0(Native Method)\n        at sun.reflect.NativeMethodAccessorImpl.invoke(Unknown Source)\n        at sun.reflect.DelegatingMethodAccessorImpl.invoke(Unknown Source)\n        at java.lang.reflect.Method.invoke(Unknown Source)\n        at org.eclipse.core.launcher.Main.basicRun(Main.java:186)\n        at org.eclipse.core.launcher.Main.run(Main.java:647)\n        at org.eclipse.core.launcher.Main.main(Main.java:631)\n",
    "Michael the last comment is unrelated to this bug and its fix. Please file a new\nbug to track this down."
  ],
  "commentCreationDates": [
    "2004-06-16T12:04:31+02:00",
    "2004-06-16T15:12:51+02:00",
    "2004-06-16T17:12:14+02:00",
    "2004-06-17T23:16:00+02:00",
    "2004-06-18T16:17:03+02:00",
    "2004-06-21T11:59:33+02:00",
    "2004-06-21T14:54:36+02:00",
    "2004-06-22T13:20:22+02:00",
    "2004-06-22T13:31:50+02:00"
  ],
  "traces": [
    {
      "exceptionType": "java.lang.NullPointerException",
      "elements": [
        {
          "method": "org.eclipse.team.internal.ccvs.ui.actions.SyncAction$2.run",
          "source": "SyncAction.java:76"
        },
        {
          "method": "org.eclipse.swt.widgets.Synchronizer.syncExec",
          "source": "Synchronizer.java:135"
        },
        {
          "method": "org.eclipse.ui.internal.UISynchronizer.syncExec",
          "source": "UISynchronizer.java:25"
        },
        {
          "method": "org.eclipse.swt.widgets.Display.syncExec",
          "source": "Display.java:3056"
        },
        {
          "method": "org.eclipse.team.internal.ccvs.ui.actions.SyncAction.showSingleFileComparison",
          "source": "SyncAction.java:74"
        },
        {
          "method": "org.eclipse.team.internal.ccvs.ui.actions.SyncAction.execute",
          "source": "SyncAction.java:43"
        },
        {
          "method": "org.eclipse.team.internal.ccvs.ui.actions.CVSAction.run",
          "source": "CVSAction.java:70"
        },
        {
          "method": "org.eclipse.ui.actions.ActionDelegate.runWithEvent",
          "source": "ActionDelegate.java:71"
        },
        {
          "method": "org.eclipse.ui.internal.PluginAction.runWithEvent",
          "source": "PluginAction.java:266"
        },
        {
          "method": "org.eclipse.jface.action.ActionContributionItem.handleWidgetSelection",
          "source": "ActionContributionItem.java:915"
        },
        {
          "method": "org.eclipse.jface.action.ActionContributionItem.access$2",
          "source": "ActionContributionItem.java:866"
        },
        {
          "method": "org.eclipse.jface.action.ActionContributionItem$7.handleEvent",
          "source": "ActionContributionItem.java:785"
        },
        {
          "method": "org.eclipse.swt.widgets.EventTable.sendEvent",
          "source": "EventTable.java:82"
        },
        {
          "method": "org.eclipse.swt.widgets.Widget.sendEvent",
          "source": "Widget.java:796"
        },
        {
          "method": "org.eclipse.swt.widgets.Display.runDeferredEvents",
          "source": "Display.java:2732"
        },
        {
          "method": "org.eclipse.swt.widgets.Display.readAndDispatch",
          "source": "Display.java:2398"
        },
        {
          "method": "org.eclipse.ui.internal.Workbench.runEventLoop",
          "source": "Workbench.java:1362"
        },
        {
          "method": "org.eclipse.ui.internal.Workbench.runUI",
          "source": "Workbench.java:1333"
        },
        {
          "method": "org.eclipse.ui.internal.Workbench.createAndRunWorkbench",
          "source": "Workbench.java:252"
        },
        {
          "method": "org.eclipse.ui.PlatformUI.createAndRunWorkbench",
          "source": "PlatformUI.java:141"
        },
        {
          "method": "org.eclipse.ui.internal.ide.IDEApplication.run",
          "source": "IDEApplication.java:96"
        },
        {
          "method": "org.eclipse.core.internal.runtime.PlatformActivator$1.run",
          "source": "PlatformActivator.java:334"
        },
        {
          "method": "org.eclipse.core.runtime.adaptor.EclipseStarter.run",
          "source": "EclipseStarter.java:272"
        },
        {
          "method": "org.eclipse.core.runtime.adaptor.EclipseStarter.run",
          "source": "EclipseStarter.java:128"
        },
        {
          "method": "sun.reflect.NativeMethodAccessorImpl.invoke0",
          "source": "Native Method"
        },
        {
          "method": "sun.reflect.NativeMethodAccessorImpl.invoke",
          "source": "Unknown Source"
        },
        {
          "method": "sun.reflect.DelegatingMethodAccessorImpl.invoke",
          "source": "Unknown Source"
        },
        {
          "method": "java.lang.reflect.Method.invoke",
          "source": "Unknown Source"
        },
        {
          "method": "org.eclipse.core.launcher.Main.basicRun",
          "source": "Main.java:185"
        },
        {
          "method": "org.eclipse.core.launcher.Main.run",
          "source": "Main.java:638"
        },
        {
          "method": "org.eclipse.core.launcher.Main.main",
          "source": "Main.java:622"
        }
      ],
      "number": 0,
      "commentIndex": 0,
      "bugId": "67424",
      "date": "2004-06-16T12:04:31+02:00",
      "product": "Platform",
      "component": "Text",
      "severity": "major"
    },
    {
      "exceptionType": "java.lang.Exception",
      "message": "Generated exception.",
      "elements": [
        {
          "method": "org.eclipse.core.runtime.adaptor.EclipseClassLoader.findLocalClass",
          "source": "EclipseClassLoader.java:102"
        },
        {
          "method": "org.eclipse.osgi.framework.internal.core.BundleLoader.findLocalClass",
          "source": "BundleLoader.java:371"
        },
        {
          "method": "org.eclipse.osgi.framework.internal.core.BundleLoader.findClass",
          "source": "BundleLoader.java:402"
        },
        {
          "method": "org.eclipse.osgi.framework.adaptor.core.AbstractClassLoader.loadClass",
          "source": "AbstractClassLoader.java:93"
        },
        {
          "method": "java.lang.ClassLoader.loadClass",
          "source": "Unknown Source"
        },
        {
          "method": "java.lang.ClassLoader.loadClassInternal",
          "source": "Unknown Source"
        },
        {
          "method": "org.eclipse.team.internal.ccvs.ui.console.ConsoleDocument.getLines",
          "source": "ConsoleDocument.java:78"
        },
        {
          "method": "org.eclipse.team.internal.ccvs.ui.console.CVSOutputConsole.dump",
          "source": "CVSOutputConsole.java:140"
        },
        {
          "method": "org.eclipse.team.internal.ccvs.ui.console.CVSOutputConsole.access$1",
          "source": "CVSOutputConsole.java:137"
        },
        {
          "method": "org.eclipse.team.internal.ccvs.ui.console.CVSOutputConsole$1.run",
          "source": "CVSOutputConsole.java:108"
        },
        {
          "method": "org.eclipse.swt.widgets.RunnableLock.run",
          "source": "RunnableLock.java:35"
        },
        {
          "method": "org.eclipse.swt.widgets.Synchronizer.runAsyncMessages",
          "source": "Synchronizer.java:106"
        },
        {
          "method": "org.eclipse.swt.widgets.Display.runAsyncMessages",
          "source": "Display.java:2709"
        },
        {
          "method": "org.eclipse.swt.widgets.Display.readAndDispatch",
          "source": "Display.java:2401"
        },
        {
          "method": "org.eclipse.ui.internal.Workbench.runEventLoop",
          "source": "Workbench.java:1375"
        },
        {
          "method": "org.eclipse.ui.internal.Workbench.runUI",
          "source": "Workbench.java:1346"
        },
        {
          "method": "org.eclipse.ui.internal.Workbench.createAndRunWorkbench",
          "source": "Workbench.java:252"
        },
        {
          "method": "org.eclipse.ui.PlatformUI.createAndRunWorkbench",
          "source": "PlatformUI.java:141"
        },
        {
          "method": "org.eclipse.ui.internal.ide.IDEApplication.run",
          "source": "IDEApplication.java:96"
        },
        {
          "method": "org.eclipse.core.internal.runtime.PlatformActivator$1.run",
          "source": "PlatformActivator.java:335"
        },
        {
          "method": "org.eclipse.core.runtime.adaptor.EclipseStarter.run",
          "source": "EclipseStarter.java:272"
        },
        {
          "method": "org.eclipse.core.runtime.adaptor.EclipseStarter.run",
          "source": "EclipseStarter.java:128"
        },
        {
          "method": "sun.reflect.NativeMethodAccessorImpl.invoke0",
          "source": "Native Method"
        },
        {
          "method": "sun.reflect.NativeMethodAccessorImpl.invoke",
          "source": "Unknown Source"
        },
        {
          "method": "sun.reflect.DelegatingMethodAccessorImpl.invoke",
          "source": "Unknown Source"
        },
        {
          "method": "java.lang.reflect.Method.invoke",
          "source": "Unknown Source"
        },
        {
          "method": "org.eclipse.core.launcher.Main.basicRun",
          "source": "Main.java:186"
        },
        {
          "method": "org.eclipse.core.launcher.Main.run",
          "source": "Main.java:647"
        },
        {
          "method": "org.eclipse.core.launcher.Main.main",
          "source": "Main.java:631"
        }
      ],
      "number": 1,
      "commentIndex": 7,
      "bugId": "67424",
      "date": "2004-06-22T13:20:22+02:00",
      "product": "Platform",
      "component": "Text",
      "severity": "major"
    }
  ],
  "groupId": "67424",
  "bugId": "67424",
  "date": "2004-06-16T12:04:31+02:00",
  "product": "Platform",
  "component": "Text",
  "severity": "major"
}