{
  "comments": [
    "Two problesm:\n\nWhen just one .java file is dirtied, Save All doesn\u0027t become enabled.\n\nWhen Save All is enabled and is then selected it doesn\u0027t become disabled.",
    "Was not able to recreate can you describe the steps you used?\n\nWere you using the latest 3.0 build? ",
    "I am using RC2 which was first available on Monday (not, as the web site \nindicates, on Friday).\n\nBTW 1, I\u0027m getting a lot of the following e.g. if I open Eclipse in a terminal \nI see it and at other times such as when inserting a breakpoint (a dialog pops \nup):\n\njava.lang.NoClassDefFoundError\n        at org.eclipse.jdt.core.dom.AST.newTryStatement(AST.java:1960)\n        at org.eclipse.jdt.core.dom.ASTConverter.convert(ASTConverter.java:2114)\n        at org.eclipse.jdt.core.dom.ASTConverter.convert(ASTConverter.java:1855)\n        at org.eclipse.jdt.core.dom.ASTConverter.convert(ASTConverter.java:1910)\n        at org.eclipse.jdt.core.dom.ASTConverter.convert(ASTConverter.java:1813)\n        at org.eclipse.jdt.core.dom.ASTConverter.convert(ASTConverter.java:2055)\n        at org.eclipse.jdt.core.dom.ASTConverter.convert(ASTConverter.java:1837)\n        at org.eclipse.jdt.core.dom.ASTConverter.convert(ASTConverter.java:770)\n        at org.eclipse.jdt.core.dom.ASTConverter.buildBodyDeclarations\n(ASTConverter.java:336)\n        at org.eclipse.jdt.core.dom.ASTConverter.convert(ASTConverter.java:274)\n        at org.eclipse.jdt.core.dom.ASTConverter.convert(ASTConverter.java:152)\n        at org.eclipse.jdt.core.dom.AST.convertCompilationUnit(AST.java:253)\n        at \norg.eclipse.jdt.internal.core.ReconcileWorkingCopyOperation.executeOperation\n(ReconcileWorkingCopyOperation.java:81)\n        at org.eclipse.jdt.internal.core.JavaModelOperation.run\n(JavaModelOperation.java:700)\n        at org.eclipse.jdt.internal.core.JavaModelOperation.runOperation\n(JavaModelOperation.java:739)\n        at org.eclipse.jdt.internal.core.CompilationUnit.reconcile\n(CompilationUnit.java:1098)\n        at \norg.eclipse.jdt.internal.ui.text.java.JavaReconcilingStrategy.reconcile\n(JavaReconcilingStrategy.java:88)\n        at \norg.eclipse.jdt.internal.ui.text.java.JavaReconcilingStrategy.initialReconcile\n(JavaReconcilingStrategy.java:156)\n        at \norg.eclipse.jdt.internal.ui.text.CompositeReconcilingStrategy.initialReconcile\n(CompositeReconcilingStrategy.java:114)\n        at \norg.eclipse.jdt.internal.ui.text.JavaCompositeReconcilingStrategy.initialReconci\nle(JavaCompositeReconcilingStrategy.java:122)\n        at org.eclipse.jface.text.reconciler.MonoReconciler.initialProcess\n(MonoReconciler.java:104)\n        at org.eclipse.jdt.internal.ui.text.JavaReconciler.initialProcess\n(JavaReconciler.java:304)\n        at \norg.eclipse.jface.text.reconciler.AbstractReconciler$BackgroundThread.run\n(AbstractReconciler.java:169)\nUnhandled event loop exception\nReason:\njava.lang.NoClassDefFoundError\n\n\n\nBTW 2, the Find/Replace dialog plus cut/copy is totally screwed in RC2 (rather \nthan being just regular screwed prior to RC2). I don\u0027t know if this is related, \ni.e. something in the core creating havoc in several places. (I\u0027ve reported \nthis as BUG 67369.)\n\nBTW 3: I have the latest integration builds of VE, EMF and GEF installed but I \ndon\u0027t think they are causing the problems.\n\n",
    "The noclassdef found error is suspicious. We really need to have reproducable \nsteps in order to fix the bug. \n",
    "I\u0027m not saying that the noclassdef is the source of the Save All bug, its just \nthat it happens a lot on my installation of RC2. In fact, upon further \ninvestigation I reckon it\u0027s _not_ associated with this Save All bug.\n\n\nI can now characterise the Save All bug better: it happens only for large \nfiles, e.g. non-trivial source code with \u003e 1000 lines. Small files don\u0027t cause \nthe problem but large files do every time. So, it\u0027s not so much that \u003e 1 files \nneed to be dirtied for Save All to become enabled but that a \u0027small\u0027 file needs \nto be dirtied.\n",
    "I cannot reproduce your bug.  Passing to JDT Core for comment about the \nexceptions in the log. ",
    "We have now a specific bug for the NoClassDefFoundError error: bug 67969, please\nuse it to follow this error (I will add reporter as CC of this bug...).\nI put back this bug in JDT/UI land to let them decide to resolve it as\nworksforme for the Save All menu item issue...\n\n",
    "\n\n*** This bug has been marked as a duplicate of 67590 ***"
  ],
  "commentCreationDates": [
    "2004-06-16T17:21:36+02:00",
    "2004-06-16T20:48:27+02:00",
    "2004-06-16T22:02:59+02:00",
    "2004-06-16T22:17:53+02:00",
    "2004-06-16T23:16:53+02:00",
    "2004-06-17T03:11:57+02:00",
    "2004-06-21T13:30:53+02:00",
    "2004-07-13T11:11:19+02:00"
  ],
  "traces": [
    {
      "exceptionType": "java.lang.NoClassDefFoundError",
      "elements": [
        {
          "method": "org.eclipse.jdt.core.dom.AST.newTryStatement",
          "source": "AST.java:1960"
        },
        {
          "method": "org.eclipse.jdt.core.dom.ASTConverter.convert",
          "source": "ASTConverter.java:2114"
        },
        {
          "method": "org.eclipse.jdt.core.dom.ASTConverter.convert",
          "source": "ASTConverter.java:1855"
        },
        {
          "method": "org.eclipse.jdt.core.dom.ASTConverter.convert",
          "source": "ASTConverter.java:1910"
        },
        {
          "method": "org.eclipse.jdt.core.dom.ASTConverter.convert",
          "source": "ASTConverter.java:1813"
        },
        {
          "method": "org.eclipse.jdt.core.dom.ASTConverter.convert",
          "source": "ASTConverter.java:2055"
        },
        {
          "method": "org.eclipse.jdt.core.dom.ASTConverter.convert",
          "source": "ASTConverter.java:1837"
        },
        {
          "method": "org.eclipse.jdt.core.dom.ASTConverter.convert",
          "source": "ASTConverter.java:770"
        },
        {
          "method": "org.eclipse.jdt.core.dom.ASTConverter.buildBodyDeclarations",
          "source": "ASTConverter.java:336"
        },
        {
          "method": "org.eclipse.jdt.core.dom.ASTConverter.convert",
          "source": "ASTConverter.java:274"
        },
        {
          "method": "org.eclipse.jdt.core.dom.ASTConverter.convert",
          "source": "ASTConverter.java:152"
        },
        {
          "method": "org.eclipse.jdt.core.dom.AST.convertCompilationUnit",
          "source": "AST.java:253"
        },
        {
          "method": "org.eclipse.jdt.internal.core.ReconcileWorkingCopyOperation.executeOperation",
          "source": "ReconcileWorkingCopyOperation.java:81"
        },
        {
          "method": "org.eclipse.jdt.internal.core.JavaModelOperation.run",
          "source": "JavaModelOperation.java:700"
        },
        {
          "method": "org.eclipse.jdt.internal.core.JavaModelOperation.runOperation",
          "source": "JavaModelOperation.java:739"
        },
        {
          "method": "org.eclipse.jdt.internal.core.CompilationUnit.reconcile",
          "source": "CompilationUnit.java:1098"
        },
        {
          "method": "org.eclipse.jdt.internal.ui.text.java.JavaReconcilingStrategy.reconcile",
          "source": "JavaReconcilingStrategy.java:88"
        },
        {
          "method": "org.eclipse.jdt.internal.ui.text.java.JavaReconcilingStrategy.initialReconcile",
          "source": "JavaReconcilingStrategy.java:156"
        },
        {
          "method": "org.eclipse.jdt.internal.ui.text.CompositeReconcilingStrategy.initialReconcile",
          "source": "CompositeReconcilingStrategy.java:114"
        },
        {
          "method": "org.eclipse.jdt.internal.ui.text.JavaCompositeReconcilingStrategy.initialReconcile",
          "source": "JavaCompositeReconcilingStrategy.java:122"
        },
        {
          "method": "org.eclipse.jface.text.reconciler.MonoReconciler.initialProcess",
          "source": "MonoReconciler.java:104"
        },
        {
          "method": "org.eclipse.jdt.internal.ui.text.JavaReconciler.initialProcess",
          "source": "JavaReconciler.java:304"
        },
        {
          "method": "org.eclipse.jface.text.reconciler.AbstractReconciler$BackgroundThread.run",
          "source": "AbstractReconciler.java:169"
        }
      ],
      "number": 0,
      "commentIndex": 2,
      "bugId": "67469",
      "duplicateId": "67590",
      "date": "2004-06-16T22:02:59+02:00",
      "product": "JDT",
      "component": "Text",
      "severity": "normal"
    }
  ],
  "groupId": "67590",
  "bugId": "67469",
  "duplicateId": "67590",
  "date": "2004-06-16T17:21:36+02:00",
  "product": "JDT",
  "component": "Text",
  "severity": "normal"
}