{
  "comments": [
    "3.0RC2 (Build id: 200406111814)\nTo duplicate, check out the org.eclipse.ui.tutorials.rcp.part1 project from \nCVS. Create a new Debug launch configuration for it. Set the application name \nto org.eclipse.ui.tutorials.rcp.part1.RcpApplication . Add the -consoleLog \noption. In the Configurations tab turn off Use the the default list. Turn on \nClean the configuration area before launching. Delete the entry for \norg.eclipse.update.configurator. In the Plug-ins tab select Choose plug-ins \nand fragments to launch from the list. Click Deselect All. Put a check next to \norg.eclipse.ui.tutorials.rcp.part1. Click Add Required Plug-ins. Click Debug \nto launch the program. \n\nThe following errors will be sent to the console window and a strange looking \nworkbench window will come up. In bug 66726, Wassimm says this should work. If \nyou change nothing else but turn back on the option to Use the default list in \nthe Configurations tab it will work perfectly. The browser example works fine \ntoo, either way.\n\n!SESSION Jun 16, 2004 15:47:09.971 --------------------------------------------\n-\neclipse.buildId\u003dunknown\njava.version\u003d1.4.2_04\njava.vendor\u003dSun Microsystems Inc.\nBootLoader constants: OS\u003dwin32, ARCH\u003dx86, WS\u003dwin32, NL\u003den_US\nCommand-line arguments: -application \norg.eclipse.ui.tutorials.rcp.part1.RcpApplication\n\n!ENTRY initial@reference:file:C:/Program \nFiles/eclipse/plugins/org.eclipse.ui.workbench_3.0.0/ 0 0 Jun 16, 2004 \n15:47:09.971\n!MESSAGE FrameworkEvent.ERROR\n!STACK 0\norg.osgi.framework.BundleException: Fragment bundle \"update@/c:/Program \nFiles/eclipse/plugins/org.eclipse.ui.workbench.compatibility_3.0.0/\" attempted \nto require additional bundle \"org.eclipse.core.resources\".  Try refreshing the \nhost bundle \"initial@reference:file:C:/Program \nFiles/eclipse/plugins/org.eclipse.ui.workbench_3.0.0/\".\n\tat \norg.eclipse.osgi.framework.internal.core.BundleLoader.initializeFragment\n(BundleLoader.java:236)\n\tat org.eclipse.osgi.framework.internal.core.BundleLoader.attachFragment\n(BundleLoader.java:1146)\n\tat org.eclipse.osgi.framework.internal.core.BundleHost.attachFragment\n(BundleHost.java:622)\n\tat org.eclipse.osgi.framework.internal.core.BundleFragment.setHost\n(BundleFragment.java:392)\n\tat \norg.eclipse.osgi.framework.internal.core.PackageAdminImpl.processDelta\n(PackageAdminImpl.java:470)\n\tat \norg.eclipse.osgi.framework.internal.core.PackageAdminImpl.refreshPackages\n(PackageAdminImpl.java:352)\n\tat org.eclipse.osgi.framework.internal.core.PackageAdminImpl$1.run\n(PackageAdminImpl.java:321)\n\tat java.lang.Thread.run(Thread.java:534)\n\n!ENTRY org.eclipse.ui 4 4 Jun 16, 2004 15:47:15.892\n!MESSAGE Invalid Menu Extension (Path is invalid): \norg.eclipse.ui.cheatsheets.actions.CheatSheetHelpMenuAction\nInvalid Menu Extension (Path is invalid): \norg.eclipse.ui.cheatsheets.actions.CheatSheetHelpMenuAction\n\n!ENTRY org.eclipse.ui 4 4 Jun 16, 2004 15:47:15.892\n!MESSAGE Invalid Menu Extension (Path is invalid): \norg.eclipse.ui.edit.text.openExternalFile\nInvalid Menu Extension (Path is invalid): \norg.eclipse.ui.edit.text.openExternalFile\nInvalid Menu Extension (Path is invalid): \norg.eclipse.ui.edit.text.gotoLastEditPosition\n\n!ENTRY org.eclipse.ui 4 4 Jun 16, 2004 15:47:15.908\n!MESSAGE Invalid Menu Extension (Path is invalid): \norg.eclipse.ui.edit.text.gotoLastEditPosition\nInvalid Menu Extension (Path is invalid): org_eclipse_ui_examples_readmetool\n\n!ENTRY org.eclipse.ui 4 4 Jun 16, 2004 15:47:15.908\n!MESSAGE Invalid Menu Extension (Path is invalid): \norg_eclipse_ui_examples_readmetool\nInvalid Menu Extension (Path is invalid): \norg_eclipse_ui_examples_readmetool_readmeAction\nInvalid Menu Extension (Path is invalid): \norg_eclipse_ui_examples_readmetool_readmeRetargetAction\nInvalid Menu Extension (Path is invalid): \norg_eclipse_ui_examples_readmetool_readmeRelabelRetargetAction\n\n!ENTRY org.eclipse.ui 4 4 Jun 16, 2004 15:47:15.908\n!MESSAGE Invalid Menu Extension (Path is invalid): \norg_eclipse_ui_examples_readmetool_readmeAction\n\n!ENTRY org.eclipse.ui 4 4 Jun 16, 2004 15:47:15.924\n!MESSAGE Invalid Menu Extension (Path is invalid): \norg_eclipse_ui_examples_readmetool_readmeRetargetAction\n\n!ENTRY org.eclipse.ui 4 4 Jun 16, 2004 15:47:15.924\n!MESSAGE Invalid Menu Extension (Path is invalid): \norg_eclipse_ui_examples_readmetool_readmeRelabelRetargetAction\n\n!ENTRY org.eclipse.ui 4 4Invalid Menu Extension (Path is invalid): \norg.eclipse.update.ui.updateMenu\n Jun 16, 2004 15:47:15.939\n!MESSAGE Invalid Menu Extension (Path is invalid): \norg.eclipse.update.ui.updateMenu\n\n!ENTRY org.eclipse.ui 4 4 Jun 16, 2004 15:47:15.939\n!MESSAGE Invalid Menu Extension (Path is invalid): \norg.eclipse.update.ui.configManager\nInvalid Menu Extension (Path is invalid): org.eclipse.update.ui.configManager\n\n!ENTRY org.eclipse.ui 4 4 Jun 16, 2004 15:47:15.939\n!MESSAGE Invalid Menu Extension (Path is invalid): \norg.eclipse.update.ui.newUpdates\nInvalid Menu Extension (Path is invalid): org.eclipse.update.ui.newUpdates\n\n!ENTRY org.eclipse.ui 4 4 Jun 16, 2004 15:47:15.955\n!MESSAGE Invalid Menu Extension (Path is invalid): goToResource\nInvalid Menu Extension (Path is invalid): goToResource\n\n!ENTRY org.eclipse.ui 4 4 Jun 16, 2004 15:47:15.955\n!MESSAGE Invalid Menu Extension (Path is invalid): \norg.eclipse.ui.OpenWorkspaceFile\nInvalid Menu Extension (Path is invalid): org.eclipse.ui.OpenWorkspaceFile",
    "although not technically a dup of bug 66726, the fix and cleanup for bug 66726 \nalso addressed this bug as well.\n\nThe problem here was that your tutorials, unlike the rcp examples, do require \nupdate.configurator.  Even when update.configurator was removed from the \nautostart list, just by its virtue of being in the list of plugins to launch, \nit gets started by the runtime.  \nBecause said plugin was not among the autostart, PDE was not generating a \nplatform.xml for it, so Update started doing its own thing upon startup and \ngenerating its own platform.xml causing all those problems.\n\nThis is all fixed up now.\n\n*** This bug has been marked as a duplicate of 66726 ***"
  ],
  "commentCreationDates": [
    "2004-06-16T22:00:39+02:00",
    "2004-06-17T05:51:22+02:00"
  ],
  "traces": [
    {
      "exceptionType": "org.osgi.framework.BundleException",
      "message": "Fragment bundle \"update@/c:/Program  Files/eclipse/plugins/org.eclipse.ui.workbench.compatibility_3.0.0/\" attempted  to require additional bundle \"org.eclipse.core.resources\".  Try refreshing the  host bundle \"initial@reference:file:C:/Program  Files/eclipse/plugins/org.eclipse.ui.workbench_3.0.0/\".",
      "elements": [
        {
          "method": "org.eclipse.osgi.framework.internal.core.BundleLoader.initializeFragment",
          "source": "BundleLoader.java:236"
        },
        {
          "method": "org.eclipse.osgi.framework.internal.core.BundleLoader.attachFragment",
          "source": "BundleLoader.java:1146"
        },
        {
          "method": "org.eclipse.osgi.framework.internal.core.BundleHost.attachFragment",
          "source": "BundleHost.java:622"
        },
        {
          "method": "org.eclipse.osgi.framework.internal.core.BundleFragment.setHost",
          "source": "BundleFragment.java:392"
        },
        {
          "method": "org.eclipse.osgi.framework.internal.core.PackageAdminImpl.processDelta",
          "source": "PackageAdminImpl.java:470"
        },
        {
          "method": "org.eclipse.osgi.framework.internal.core.PackageAdminImpl.refreshPackages",
          "source": "PackageAdminImpl.java:352"
        },
        {
          "method": "org.eclipse.osgi.framework.internal.core.PackageAdminImpl$1.run",
          "source": "PackageAdminImpl.java:321"
        },
        {
          "method": "java.lang.Thread.run",
          "source": "Thread.java:534"
        }
      ],
      "number": 0,
      "commentIndex": 0,
      "bugId": "67524",
      "duplicateId": "66726",
      "date": "2004-06-16T22:00:39+02:00",
      "product": "PDE",
      "component": "UI",
      "severity": "normal"
    }
  ],
  "groupId": "66726",
  "bugId": "67524",
  "duplicateId": "66726",
  "date": "2004-06-16T22:00:39+02:00",
  "product": "PDE",
  "component": "UI",
  "severity": "normal"
}