{
  "comments": [
    "I200406162000\n\nUnfortunately I don\u0027t remember the expression.\n\njava.lang.NullPointerException\n        at org.eclipse.jdt.internal.debug.eval.ast.engine.ASTInstructionCompiler\n.containsALocalType(ASTInstructionCompiler.java:331)\n        at org.eclipse.jdt.internal.debug.eval.ast.engine.ASTInstructionCompiler\n.visit(ASTInstructionCompiler.java:2075)\n        at org.eclipse.jdt.core.dom.MethodInvocation.accept0(MethodInvocation.ja\nva:234)\n        at org.eclipse.jdt.core.dom.ASTNode.accept(ASTNode.java:2454)\n        at org.eclipse.jdt.core.dom.ASTNode.acceptChild(ASTNode.java:2501)\n        at org.eclipse.jdt.core.dom.ReturnStatement.accept0(ReturnStatement.java\n:133)\n        at org.eclipse.jdt.core.dom.ASTNode.accept(ASTNode.java:2454)\n        at org.eclipse.jdt.core.dom.ASTNode.acceptChildren(ASTNode.java:2524)\n        at org.eclipse.jdt.core.dom.Block.accept0(Block.java:133)\n        at org.eclipse.jdt.core.dom.ASTNode.accept(ASTNode.java:2454)\n        at org.eclipse.jdt.core.dom.ASTNode.acceptChild(ASTNode.java:2501)\n        at org.eclipse.jdt.core.dom.MethodDeclaration.accept0(MethodDeclaration.\njava:499)\n        at org.eclipse.jdt.core.dom.ASTNode.accept(ASTNode.java:2454)\n        at org.eclipse.jdt.core.dom.ASTNode.acceptChildren(ASTNode.java:2524)\n        at org.eclipse.jdt.core.dom.TypeDeclaration.accept0(TypeDeclaration.java\n:474)\n        at org.eclipse.jdt.core.dom.ASTNode.accept(ASTNode.java:2454)\n        at org.eclipse.jdt.core.dom.ASTNode.acceptChildren(ASTNode.java:2524)\n        at org.eclipse.jdt.core.dom.CompilationUnit.accept0(CompilationUnit.java\n:290)\n        at org.eclipse.jdt.core.dom.ASTNode.accept(ASTNode.java:2454)\n        at org.eclipse.jdt.internal.debug.eval.ast.engine.ASTEvaluationEngine.cr\neateExpressionFromAST(ASTEvaluationEngine.java:251)\n        at org.eclipse.jdt.internal.debug.eval.ast.engine.ASTEvaluationEngine.ge\ntCompiledExpression(ASTEvaluationEngine.java:156)\n        at org.eclipse.jdt.internal.debug.eval.ast.engine.ASTEvaluationEngine.ev\naluate(ASTEvaluationEngine.java:73)\n        at org.eclipse.jdt.internal.debug.ui.JavaWatchExpressionDelegate$Evaluat\nionRunnable.run(JavaWatchExpressionDelegate.java:144)\n        at org.eclipse.jdt.internal.debug.core.model.JDIThread$ThreadJob.run(JDI\nThread.java:2516)\n        at org.eclipse.core.internal.jobs.Worker.run(Worker.java:66)",
    "\n\n*** This bug has been marked as a duplicate of 67395 ***"
  ],
  "commentCreationDates": [
    "2004-06-17T18:18:04+02:00",
    "2004-06-17T18:26:25+02:00"
  ],
  "traces": [
    {
      "exceptionType": "java.lang.NullPointerException",
      "elements": [
        {
          "method": "org.eclipse.jdt.internal.debug.eval.ast.engine.ASTInstructionCompiler.containsALocalType",
          "source": "ASTInstructionCompiler.java:331"
        },
        {
          "method": "org.eclipse.jdt.internal.debug.eval.ast.engine.ASTInstructionCompiler.visit",
          "source": "ASTInstructionCompiler.java:2075"
        },
        {
          "method": "org.eclipse.jdt.core.dom.MethodInvocation.accept0",
          "source": "MethodInvocation.ja va:234"
        },
        {
          "method": "org.eclipse.jdt.core.dom.ASTNode.accept",
          "source": "ASTNode.java:2454"
        },
        {
          "method": "org.eclipse.jdt.core.dom.ASTNode.acceptChild",
          "source": "ASTNode.java:2501"
        },
        {
          "method": "org.eclipse.jdt.core.dom.ReturnStatement.accept0",
          "source": "ReturnStatement.java :133"
        },
        {
          "method": "org.eclipse.jdt.core.dom.ASTNode.accept",
          "source": "ASTNode.java:2454"
        },
        {
          "method": "org.eclipse.jdt.core.dom.ASTNode.acceptChildren",
          "source": "ASTNode.java:2524"
        },
        {
          "method": "org.eclipse.jdt.core.dom.Block.accept0",
          "source": "Block.java:133"
        },
        {
          "method": "org.eclipse.jdt.core.dom.ASTNode.accept",
          "source": "ASTNode.java:2454"
        },
        {
          "method": "org.eclipse.jdt.core.dom.ASTNode.acceptChild",
          "source": "ASTNode.java:2501"
        },
        {
          "method": "org.eclipse.jdt.core.dom.MethodDeclaration.accept0",
          "source": "MethodDeclaration. java:499"
        },
        {
          "method": "org.eclipse.jdt.core.dom.ASTNode.accept",
          "source": "ASTNode.java:2454"
        },
        {
          "method": "org.eclipse.jdt.core.dom.ASTNode.acceptChildren",
          "source": "ASTNode.java:2524"
        },
        {
          "method": "org.eclipse.jdt.core.dom.TypeDeclaration.accept0",
          "source": "TypeDeclaration.java :474"
        },
        {
          "method": "org.eclipse.jdt.core.dom.ASTNode.accept",
          "source": "ASTNode.java:2454"
        },
        {
          "method": "org.eclipse.jdt.core.dom.ASTNode.acceptChildren",
          "source": "ASTNode.java:2524"
        },
        {
          "method": "org.eclipse.jdt.core.dom.CompilationUnit.accept0",
          "source": "CompilationUnit.java :290"
        },
        {
          "method": "org.eclipse.jdt.core.dom.ASTNode.accept",
          "source": "ASTNode.java:2454"
        },
        {
          "method": "org.eclipse.jdt.internal.debug.eval.ast.engine.ASTEvaluationEngine.createExpressionFromAST",
          "source": "ASTEvaluationEngine.java:251"
        },
        {
          "method": "org.eclipse.jdt.internal.debug.eval.ast.engine.ASTEvaluationEngine.getCompiledExpression",
          "source": "ASTEvaluationEngine.java:156"
        },
        {
          "method": "org.eclipse.jdt.internal.debug.eval.ast.engine.ASTEvaluationEngine.evaluate",
          "source": "ASTEvaluationEngine.java:73"
        },
        {
          "method": "org.eclipse.jdt.internal.debug.ui.JavaWatchExpressionDelegate$EvaluationRunnable.run",
          "source": "JavaWatchExpressionDelegate.java:144"
        },
        {
          "method": "org.eclipse.jdt.internal.debug.core.model.JDIThread$ThreadJob.run",
          "source": "JDI Thread.java:2516"
        },
        {
          "method": "org.eclipse.core.internal.jobs.Worker.run",
          "source": "Worker.java:66"
        }
      ],
      "number": 0,
      "commentIndex": 0,
      "bugId": "67664",
      "duplicateId": "67395",
      "date": "2004-06-17T18:18:04+02:00",
      "product": "JDT",
      "component": "Debug",
      "severity": "normal"
    }
  ],
  "groupId": "67395",
  "bugId": "67664",
  "duplicateId": "67395",
  "date": "2004-06-17T18:18:04+02:00",
  "product": "JDT",
  "component": "Debug",
  "severity": "normal"
}