{
  "comments": [
    "It seems that there is some faulty regular expression handeling of the CVS\ncommit message from the server.\n\nThis has been happening since M9, but I hadn\u0027t found the log until now.\n\nNo error is overtly displayed, but after I type in my own commit message, and\nhit ok, nothing happens as this exception is thrown and logged.  I am unable to\ncommit to my repository.\n\n-JJ\n\n\n!SESSION Jun 17, 2004 13:17:12.796 ---------------------------------------------\neclipse.buildId\u003dI200406111814\njava.version\u003d1.4.2_04\njava.vendor\u003dSun Microsystems Inc.\nBootLoader constants: OS\u003dwin32, ARCH\u003dx86, WS\u003dwin32, NL\u003den_US\n\n!ENTRY org.eclipse.ui 4 4 Jun 17, 2004 13:17:12.796\n!MESSAGE Unhandled event loop exception\n\n!ENTRY org.eclipse.ui 4 0 Jun 17, 2004 13:17:12.812\n!MESSAGE Unclosed group near index 149\n@contract \n\nCVS: Enter contract number above in the format Contract#-Task#\nCVS: (that\u0027s contract number, then dash, then task number, no spaces.\n\n                                                                               \n                                                                     ^\n!STACK 0\njava.util.regex.PatternSyntaxException: Unclosed group near index 149\n@contract \n\nCVS: Enter contract number above in the format Contract#-Task#\nCVS: (that\u0027s contract number, then dash, then task number, no spaces.\n\n                                                                               \n                                                                     ^\n\tat java.util.regex.Pattern.error(Unknown Source)\n\tat java.util.regex.Pattern.accept(Unknown Source)\n\tat java.util.regex.Pattern.group0(Unknown Source)\n\tat java.util.regex.Pattern.sequence(Unknown Source)\n\tat java.util.regex.Pattern.expr(Unknown Source)\n\tat java.util.regex.Pattern.compile(Unknown Source)\n\tat java.util.regex.Pattern.\u003cinit\u003e(Unknown Source)\n\tat java.util.regex.Pattern.compile(Unknown Source)\n\tat java.lang.String.replaceAll(Unknown Source)\n\tat\norg.eclipse.team.internal.ccvs.ui.CommitCommentArea.finished(CommitCommentArea.java:187)\n\tat\norg.eclipse.team.internal.ccvs.ui.CommitCommentArea.getComment(CommitCommentArea.java:172)\n\tat\norg.eclipse.team.internal.ccvs.ui.ReleaseCommentDialog.getComment(ReleaseCommentDialog.java:121)\n\tat\norg.eclipse.team.internal.ccvs.ui.repo.RepositoryManager.promptForComment(RepositoryManager.java:557)\n\tat\norg.eclipse.team.internal.ccvs.ui.operations.CommitOperation.promptForComment(CommitOperation.java:167)\n\tat\norg.eclipse.team.internal.ccvs.ui.operations.CommitOperation.performPrompting(CommitOperation.java:46)\n\tat\norg.eclipse.team.internal.ccvs.ui.actions.CommitAction$1.run(CommitAction.java:37)\n\tat\norg.eclipse.team.internal.ccvs.ui.repo.RepositoryManager.run(RepositoryManager.java:664)\n\tat org.eclipse.team.internal.ccvs.ui.actions.CVSAction$1.run(CVSAction.java:243)\n\tat org.eclipse.team.internal.ccvs.ui.actions.CVSAction$2.run(CVSAction.java:252)\n\tat org.eclipse.swt.custom.BusyIndicator.showWhile(BusyIndicator.java:69)\n\tat org.eclipse.team.internal.ccvs.ui.actions.CVSAction.run(CVSAction.java:249)\n\tat\norg.eclipse.team.internal.ccvs.ui.actions.CommitAction.execute(CommitAction.java:34)\n\tat org.eclipse.team.internal.ccvs.ui.actions.CVSAction.run(CVSAction.java:70)\n\tat org.eclipse.ui.actions.ActionDelegate.runWithEvent(ActionDelegate.java:71)\n\tat org.eclipse.ui.internal.PluginAction.runWithEvent(PluginAction.java:266)\n\tat\norg.eclipse.jface.action.ActionContributionItem.handleWidgetSelection(ActionContributionItem.java:915)\n\tat\norg.eclipse.jface.action.ActionContributionItem.access$2(ActionContributionItem.java:866)\n\tat\norg.eclipse.jface.action.ActionContributionItem$7.handleEvent(ActionContributionItem.java:785)\n\tat org.eclipse.swt.widgets.EventTable.sendEvent(EventTable.java:82)\n\tat org.eclipse.swt.widgets.Widget.sendEvent(Widget.java:796)\n\tat org.eclipse.swt.widgets.Display.runDeferredEvents(Display.java:2732)\n\tat org.eclipse.swt.widgets.Display.readAndDispatch(Display.java:2398)\n\tat org.eclipse.ui.internal.Workbench.runEventLoop(Workbench.java:1362)\n\tat org.eclipse.ui.internal.Workbench.runUI(Workbench.java:1333)\n\tat org.eclipse.ui.internal.Workbench.createAndRunWorkbench(Workbench.java:252)\n\tat org.eclipse.ui.PlatformUI.createAndRunWorkbench(PlatformUI.java:141)\n\tat org.eclipse.ui.internal.ide.IDEApplication.run(IDEApplication.java:96)\n\tat\norg.eclipse.core.internal.runtime.PlatformActivator$1.run(PlatformActivator.java:334)\n\tat org.eclipse.core.runtime.adaptor.EclipseStarter.run(EclipseStarter.java:272)\n\tat org.eclipse.core.runtime.adaptor.EclipseStarter.run(EclipseStarter.java:128)\n\tat sun.reflect.NativeMethodAccessorImpl.invoke0(Native Method)\n\tat sun.reflect.NativeMethodAccessorImpl.invoke(Unknown Source)\n\tat sun.reflect.DelegatingMethodAccessorImpl.invoke(Unknown Source)\n\tat java.lang.reflect.Method.invoke(Unknown Source)\n\tat org.eclipse.core.launcher.Main.basicRun(Main.java:185)\n\tat org.eclipse.core.launcher.Main.run(Main.java:638)\n\tat org.eclipse.core.launcher.Main.main(Main.java:622)",
    "Yes, I see how this could happen. String#replaceAll is speced to accept a \nregular expression. The commit template of your server must have something in \nit that is interpreted as a regular expression. This is an easy fix. I will \nsee if we can get approval for 3.0.",
    "It turns out that the replaceAll is speced to throw a runtime exception \ninstead of a regular exception so the community memeber who cntributed the \ncode didn\u0027t catch it and continue. We should also consider using startsWith \nand endsWith instead of replaceAll. These are both easy safe fixes.",
    "I have a patch ready which uses startsWith and endsWith to strip unmodified \ntemplate contents. Now all I need is 2 component leads to approve the fix. (DJ \nand JM, will you both approve this for inclusion in RC3?).",
    "+1",
    "+1",
    "Fix released to 4 p.m. build"
  ],
  "commentCreationDates": [
    "2004-06-17T19:36:27+02:00",
    "2004-06-17T19:50:34+02:00",
    "2004-06-17T19:56:22+02:00",
    "2004-06-17T20:08:02+02:00",
    "2004-06-17T21:23:05+02:00",
    "2004-06-17T21:42:39+02:00",
    "2004-06-17T22:13:03+02:00"
  ],
  "traces": [
    {
      "exceptionType": "java.util.regex.PatternSyntaxException",
      "message": "Unclosed group near index 149 @contract   CVS: Enter contract number above in the format Contract#-Task# CVS: (that\u0027s contract number, then dash, then task number, no spaces.                                                                                                                                                       ^",
      "elements": [
        {
          "method": "java.util.regex.Pattern.error",
          "source": "Unknown Source"
        },
        {
          "method": "java.util.regex.Pattern.accept",
          "source": "Unknown Source"
        },
        {
          "method": "java.util.regex.Pattern.group0",
          "source": "Unknown Source"
        },
        {
          "method": "java.util.regex.Pattern.sequence",
          "source": "Unknown Source"
        },
        {
          "method": "java.util.regex.Pattern.expr",
          "source": "Unknown Source"
        },
        {
          "method": "java.util.regex.Pattern.compile",
          "source": "Unknown Source"
        },
        {
          "method": "java.util.regex.Pattern.\u003cinit\u003e",
          "source": "Unknown Source"
        },
        {
          "method": "java.util.regex.Pattern.compile",
          "source": "Unknown Source"
        },
        {
          "method": "java.lang.String.replaceAll",
          "source": "Unknown Source"
        },
        {
          "method": "org.eclipse.team.internal.ccvs.ui.CommitCommentArea.finished",
          "source": "CommitCommentArea.java:187"
        },
        {
          "method": "org.eclipse.team.internal.ccvs.ui.CommitCommentArea.getComment",
          "source": "CommitCommentArea.java:172"
        },
        {
          "method": "org.eclipse.team.internal.ccvs.ui.ReleaseCommentDialog.getComment",
          "source": "ReleaseCommentDialog.java:121"
        },
        {
          "method": "org.eclipse.team.internal.ccvs.ui.repo.RepositoryManager.promptForComment",
          "source": "RepositoryManager.java:557"
        },
        {
          "method": "org.eclipse.team.internal.ccvs.ui.operations.CommitOperation.promptForComment",
          "source": "CommitOperation.java:167"
        },
        {
          "method": "org.eclipse.team.internal.ccvs.ui.operations.CommitOperation.performPrompting",
          "source": "CommitOperation.java:46"
        },
        {
          "method": "org.eclipse.team.internal.ccvs.ui.actions.CommitAction$1.run",
          "source": "CommitAction.java:37"
        },
        {
          "method": "org.eclipse.team.internal.ccvs.ui.repo.RepositoryManager.run",
          "source": "RepositoryManager.java:664"
        },
        {
          "method": "org.eclipse.team.internal.ccvs.ui.actions.CVSAction$1.run",
          "source": "CVSAction.java:243"
        },
        {
          "method": "org.eclipse.team.internal.ccvs.ui.actions.CVSAction$2.run",
          "source": "CVSAction.java:252"
        },
        {
          "method": "org.eclipse.swt.custom.BusyIndicator.showWhile",
          "source": "BusyIndicator.java:69"
        },
        {
          "method": "org.eclipse.team.internal.ccvs.ui.actions.CVSAction.run",
          "source": "CVSAction.java:249"
        },
        {
          "method": "org.eclipse.team.internal.ccvs.ui.actions.CommitAction.execute",
          "source": "CommitAction.java:34"
        },
        {
          "method": "org.eclipse.team.internal.ccvs.ui.actions.CVSAction.run",
          "source": "CVSAction.java:70"
        },
        {
          "method": "org.eclipse.ui.actions.ActionDelegate.runWithEvent",
          "source": "ActionDelegate.java:71"
        },
        {
          "method": "org.eclipse.ui.internal.PluginAction.runWithEvent",
          "source": "PluginAction.java:266"
        },
        {
          "method": "org.eclipse.jface.action.ActionContributionItem.handleWidgetSelection",
          "source": "ActionContributionItem.java:915"
        },
        {
          "method": "org.eclipse.jface.action.ActionContributionItem.access$2",
          "source": "ActionContributionItem.java:866"
        },
        {
          "method": "org.eclipse.jface.action.ActionContributionItem$7.handleEvent",
          "source": "ActionContributionItem.java:785"
        },
        {
          "method": "org.eclipse.swt.widgets.EventTable.sendEvent",
          "source": "EventTable.java:82"
        },
        {
          "method": "org.eclipse.swt.widgets.Widget.sendEvent",
          "source": "Widget.java:796"
        },
        {
          "method": "org.eclipse.swt.widgets.Display.runDeferredEvents",
          "source": "Display.java:2732"
        },
        {
          "method": "org.eclipse.swt.widgets.Display.readAndDispatch",
          "source": "Display.java:2398"
        },
        {
          "method": "org.eclipse.ui.internal.Workbench.runEventLoop",
          "source": "Workbench.java:1362"
        },
        {
          "method": "org.eclipse.ui.internal.Workbench.runUI",
          "source": "Workbench.java:1333"
        },
        {
          "method": "org.eclipse.ui.internal.Workbench.createAndRunWorkbench",
          "source": "Workbench.java:252"
        },
        {
          "method": "org.eclipse.ui.PlatformUI.createAndRunWorkbench",
          "source": "PlatformUI.java:141"
        },
        {
          "method": "org.eclipse.ui.internal.ide.IDEApplication.run",
          "source": "IDEApplication.java:96"
        },
        {
          "method": "org.eclipse.core.internal.runtime.PlatformActivator$1.run",
          "source": "PlatformActivator.java:334"
        },
        {
          "method": "org.eclipse.core.runtime.adaptor.EclipseStarter.run",
          "source": "EclipseStarter.java:272"
        },
        {
          "method": "org.eclipse.core.runtime.adaptor.EclipseStarter.run",
          "source": "EclipseStarter.java:128"
        },
        {
          "method": "sun.reflect.NativeMethodAccessorImpl.invoke0",
          "source": "Native Method"
        },
        {
          "method": "sun.reflect.NativeMethodAccessorImpl.invoke",
          "source": "Unknown Source"
        },
        {
          "method": "sun.reflect.DelegatingMethodAccessorImpl.invoke",
          "source": "Unknown Source"
        },
        {
          "method": "java.lang.reflect.Method.invoke",
          "source": "Unknown Source"
        },
        {
          "method": "org.eclipse.core.launcher.Main.basicRun",
          "source": "Main.java:185"
        },
        {
          "method": "org.eclipse.core.launcher.Main.run",
          "source": "Main.java:638"
        },
        {
          "method": "org.eclipse.core.launcher.Main.main",
          "source": "Main.java:622"
        }
      ],
      "number": 0,
      "commentIndex": 0,
      "bugId": "67674",
      "date": "2004-06-17T19:36:27+02:00",
      "product": "Platform",
      "component": "CVS",
      "severity": "normal"
    }
  ],
  "groupId": "67674",
  "bugId": "67674",
  "date": "2004-06-17T19:36:27+02:00",
  "product": "Platform",
  "component": "CVS",
  "severity": "normal"
}