{
  "comments": [
    "I have had to Force Quit Eclipse due to it hanging.  When I try to relaunch, I get a \nNoClassDefFoundError.\nThis time is is from org.eclipse.ui.workbench.  It appears that something gets hosed when\nforce quitting - although I have been able to quit Eclipse on Windows, and can restart without\nlosing anything (other than perhaps the last thing i was editing).  I have to totally reconstruct\na new .metadata, and recheck out all my projects, etc., copy over any changed files, and this\ntakes alot of time and is prone to errors.\n\n!SESSION Jun 21, 2004 15:10:06.577 ---------------------------------------------\njava.version\u003d1.3.1\njava.vendor\u003dApple Computer, Inc.\nBootLoader constants: OS\u003dmacosx, ARCH\u003dppc, WS\u003dcarbon, NL\u003den_US\nCommand-line arguments: -noupdate -consoleLog -showlocation -os macosx -ws carbon -install file:\n/Developer/eclipse2.1.3/\n!ENTRY org.eclipse.ui.workbench 4 2 Jun 21, 2004 15:10:06.578\n!MESSAGE Problems occurred when invoking code from plug-in: \"org.eclipse.ui.workbench\".\n!STACK 0\njava.lang.NoClassDefFoundError: ??~A\n        at \norg.eclipse.team.internal.ccvs.core.resources.CVSWorkspaceRoot.getCVSFolderFor(CVSWorkspaceRoot.j\nava:528)\n        at \norg.eclipse.team.internal.ccvs.core.resources.CVSWorkspaceRoot.\u003cinit\u003e(CVSWorkspaceRoot.java:69)\n        at org.eclipse.team.internal.ccvs.core.CVSTeamProvider.setProject(CVSTeamProvider.java:188)\n        at org.eclipse.team.core.RepositoryProvider.mapNewProvider(RepositoryProvider.java:174)\n        at org.eclipse.team.core.RepositoryProvider.getProvider(RepositoryProvider.java:418)\n        at \norg.eclipse.team.internal.ccvs.ui.CVSLightweightDecorator.getCVSProviderFor(CVSLightweightDecorator.\njava:131)\n        at \norg.eclipse.team.internal.ccvs.ui.CVSLightweightDecorator.decorate(CVSLightweightDecorator.java:173)\n        at \norg.eclipse.ui.internal.decorators.LightweightDecoratorDefinition.decorate(LightweightDecoratorDefiniti\non.java:158)\n        at \norg.eclipse.ui.internal.decorators.LightweightDecoratorManager$LightweightRunnable.run(LightweightD\necoratorManager.java:54)\n        at org.eclipse.core.internal.runtime.InternalPlatform.run(InternalPlatform.java:1006)\n        at org.eclipse.core.runtime.Platform.run(Platform.java:413)\n        at \norg.eclipse.ui.internal.decorators.LightweightDecoratorManager.decorate(LightweightDecoratorManager\n.java:203)\n        at \norg.eclipse.ui.internal.decorators.LightweightDecoratorManager.getDecorations(LightweightDecoratorM\nanager.java:184)\n        at org.eclipse.ui.internal.decorators.DecorationScheduler$2.run(DecorationScheduler.java:293)\n        at java.lang.Thread.run(Thread.java:491)\n\nMac OS X (10.3.4)\ndual-proc G5\n1GB memory",
    "*** Bug 68100 has been marked as a duplicate of this bug. ***",
    "Can you still reproduce?\n",
    "(In reply to comment #2)\n\u003e Can you still reproduce?\n\u003e \nI am now using Eclipse 3.0.1 build 200409161125 and have not reproduced this error.  I have had \nEclipse hang when trying a new plugin (due to bug 67384), but was able to remove the plugin and \nrestart Eclipse with no errors.\n\nKL",
    "Closing.  No longer reproducible."
  ],
  "commentCreationDates": [
    "2004-06-21T22:23:01+02:00",
    "2004-06-21T22:53:14+02:00",
    "2005-04-12T14:55:21+02:00",
    "2005-04-12T16:21:05+02:00",
    "2005-04-13T20:26:25+02:00"
  ],
  "traces": [
    {
      "exceptionType": "java.lang.NoClassDefFoundError",
      "message": "??~A",
      "elements": [
        {
          "method": "org.eclipse.team.internal.ccvs.core.resources.CVSWorkspaceRoot.getCVSFolderFor",
          "source": "CVSWorkspaceRoot.j ava:528"
        },
        {
          "method": "org.eclipse.team.internal.ccvs.core.resources.CVSWorkspaceRoot.\u003cinit\u003e",
          "source": "CVSWorkspaceRoot.java:69"
        },
        {
          "method": "org.eclipse.team.internal.ccvs.core.CVSTeamProvider.setProject",
          "source": "CVSTeamProvider.java:188"
        },
        {
          "method": "org.eclipse.team.core.RepositoryProvider.mapNewProvider",
          "source": "RepositoryProvider.java:174"
        },
        {
          "method": "org.eclipse.team.core.RepositoryProvider.getProvider",
          "source": "RepositoryProvider.java:418"
        },
        {
          "method": "org.eclipse.team.internal.ccvs.ui.CVSLightweightDecorator.getCVSProviderFor",
          "source": "CVSLightweightDecorator. java:131"
        },
        {
          "method": "org.eclipse.team.internal.ccvs.ui.CVSLightweightDecorator.decorate",
          "source": "CVSLightweightDecorator.java:173"
        },
        {
          "method": "org.eclipse.ui.internal.decorators.LightweightDecoratorDefinition.decorate",
          "source": "LightweightDecoratorDefiniti on.java:158"
        },
        {
          "method": "org.eclipse.ui.internal.decorators.LightweightDecoratorManager$LightweightRunnable.run",
          "source": "LightweightD ecoratorManager.java:54"
        },
        {
          "method": "org.eclipse.core.internal.runtime.InternalPlatform.run",
          "source": "InternalPlatform.java:1006"
        },
        {
          "method": "org.eclipse.core.runtime.Platform.run",
          "source": "Platform.java:413"
        },
        {
          "method": "org.eclipse.ui.internal.decorators.LightweightDecoratorManager.decorate",
          "source": "LightweightDecoratorManager .java:203"
        },
        {
          "method": "org.eclipse.ui.internal.decorators.LightweightDecoratorManager.getDecorations",
          "source": "LightweightDecoratorM anager.java:184"
        },
        {
          "method": "org.eclipse.ui.internal.decorators.DecorationScheduler$2.run",
          "source": "DecorationScheduler.java:293"
        },
        {
          "method": "java.lang.Thread.run",
          "source": "Thread.java:491"
        }
      ],
      "number": 0,
      "commentIndex": 0,
      "bugId": "68095",
      "date": "2004-06-21T22:23:01+02:00",
      "product": "Platform",
      "component": "Runtime",
      "severity": "major"
    }
  ],
  "groupId": "68095",
  "bugId": "68095",
  "date": "2004-06-21T22:23:01+02:00",
  "product": "Platform",
  "component": "Runtime",
  "severity": "major"
}