{
  "comments": [
    "You get this NPE in the latest EMF build...\n\n*** ERROR ***: Tue Jun 22 14:26:40 EDT 2004    java.lang.NullPointerException\n    \t\t at java.util.TreeMap.compare(TreeMap.java:1093)\n    \t\t at java.util.TreeMap.put(TreeMap.java:471)\n    \t\t at org.eclipse.emf.ecore.xmi.impl.XMLHelperImpl.packages\n(XMLHelperImpl.java:676)\n    \t\t at \ncom.ibm.wtp.internal.emf.xmi.helpers.CompatibilityXMISaveImpl.addNamespaceDecla\nr\nations(CompatibilityXMISaveImpl.java:52)\n    \t\t at org.eclipse.emf.ecore.xmi.impl.XMLSaveImpl.traverse\n(XMLSaveImpl.java:334)\n    \t\t at org.eclipse.emf.ecore.xmi.impl.XMLSaveImpl.save\n(XMLSaveImpl.java:138)\n    \t\t at org.eclipse.emf.ecore.xmi.impl.XMLResourceImpl.doSave\n(XMLResourceImpl.java:167)\n    \t\t at \ncom.ibm.wtp.emf.resource.CompatibilityXMIResourceImpl.doSave\n(CompatibilityXMIResourceImpl.java:117)\n    \t\t at org.eclipse.emf.ecore.resource.impl.ResourceImpl.save\n(ResourceImpl.java:785)\n    \t\t at org.eclipse.emf.ecore.resource.impl.ResourceImpl.save\n(ResourceImpl.java:722)\n    \t\t at com.ibm.wtp.emf.resource.ReferencedXMIResourceImpl.save",
    "The fix is committed to CVS.",
    "The fix is available in the latest driver.",
    "OK"
  ],
  "commentCreationDates": [
    "2004-06-23T01:52:20+02:00",
    "2004-06-23T14:42:11+02:00",
    "2004-06-23T22:55:40+02:00",
    "2005-03-01T19:31:50+01:00"
  ],
  "traces": [
    {
      "exceptionType": "java.lang.NullPointerException",
      "elements": [
        {
          "method": "java.util.TreeMap.compare",
          "source": "TreeMap.java:1093"
        },
        {
          "method": "java.util.TreeMap.put",
          "source": "TreeMap.java:471"
        },
        {
          "method": "org.eclipse.emf.ecore.xmi.impl.XMLHelperImpl.packages",
          "source": "XMLHelperImpl.java:676"
        },
        {
          "method": "com.ibm.wtp.internal.emf.xmi.helpers.CompatibilityXMISaveImpl.addNamespaceDeclarations",
          "source": "CompatibilityXMISaveImpl.java:52"
        },
        {
          "method": "org.eclipse.emf.ecore.xmi.impl.XMLSaveImpl.traverse",
          "source": "XMLSaveImpl.java:334"
        },
        {
          "method": "org.eclipse.emf.ecore.xmi.impl.XMLSaveImpl.save",
          "source": "XMLSaveImpl.java:138"
        },
        {
          "method": "org.eclipse.emf.ecore.xmi.impl.XMLResourceImpl.doSave",
          "source": "XMLResourceImpl.java:167"
        },
        {
          "method": "com.ibm.wtp.emf.resource.CompatibilityXMIResourceImpl.doSave",
          "source": "CompatibilityXMIResourceImpl.java:117"
        },
        {
          "method": "org.eclipse.emf.ecore.resource.impl.ResourceImpl.save",
          "source": "ResourceImpl.java:785"
        },
        {
          "method": "org.eclipse.emf.ecore.resource.impl.ResourceImpl.save",
          "source": "ResourceImpl.java:722"
        }
      ],
      "number": 0,
      "commentIndex": 0,
      "bugId": "68256",
      "date": "2004-06-23T01:52:20+02:00",
      "product": "EMF",
      "component": "Core",
      "severity": "normal"
    }
  ],
  "groupId": "68256",
  "bugId": "68256",
  "date": "2004-06-23T01:52:20+02:00",
  "product": "EMF",
  "component": "Core",
  "severity": "normal"
}