{
  "comments": [
    "I got this printed on my console when trying to use open type.\n\nThere was a Progress Information dialog open which never made any progress.\n\njava.lang.IllegalMonitorStateException: JVMLK002: current thread not owner\n        at org.eclipse.jdt.internal.core.index.Index.query(Index.java(Compiled\nCode))\n        at\norg.eclipse.jdt.internal.core.search.matching.TypeDeclarationPattern.queryIn(TypeDeclarationPattern.java:189)\n        at\norg.eclipse.jdt.internal.core.search.matching.InternalSearchPattern.findIndexMatches(InternalSearchPattern.java(Compi\nled Code))\n        at\norg.eclipse.jdt.internal.core.search.matching.MatchLocator.findIndexMatches(MatchLocator.java:266)\n        at\norg.eclipse.jdt.internal.core.search.PatternSearchJob.search(PatternSearchJob.java:109)\n        at\norg.eclipse.jdt.internal.core.search.PatternSearchJob.execute(PatternSearchJob.java:64)\n        at\norg.eclipse.jdt.internal.core.search.processing.JobManager.performConcurrentJob(JobManager.java:253)\n        at\norg.eclipse.jdt.core.search.SearchEngine.searchAllTypeNames(SearchEngine.java:866)\n        at\norg.eclipse.jdt.internal.corext.util.AllTypesCache.search(AllTypesCache.java:526)\n        at\norg.eclipse.jdt.internal.corext.util.AllTypesCache$TypeCacher.doSearchTypes(AllTypesCache.java:197)\n        at\norg.eclipse.jdt.internal.corext.util.AllTypesCache$TypeCacher.run(AllTypesCache.java:166)\njava.lang.IllegalMonitorStateException: JVMLK002: current thread not owner\n        at org.eclipse.jdt.internal.core.index.Index.query(Index.java(Compiled\nCode))\n        at\norg.eclipse.jdt.internal.core.search.matching.TypeDeclarationPattern.queryIn(TypeDeclarationPattern.java:189)\n        at\norg.eclipse.jdt.internal.core.search.matching.InternalSearchPattern.findIndexMatches(InternalSearchPattern.java(Compi\nled Code))\n        at\norg.eclipse.jdt.internal.core.search.matching.MatchLocator.findIndexMatches(MatchLocator.java:266)\n        at\norg.eclipse.jdt.internal.core.search.PatternSearchJob.search(PatternSearchJob.java:109)\n        at\norg.eclipse.jdt.internal.core.search.PatternSearchJob.execute(PatternSearchJob.java:64)\n        at\norg.eclipse.jdt.internal.core.search.processing.JobManager.performConcurrentJob(JobManager.java:253)\n        at\norg.eclipse.jdt.core.search.SearchEngine.searchAllTypeNames(SearchEngine.java:866)\n        at\norg.eclipse.jdt.internal.corext.util.AllTypesCache.search(AllTypesCache.java:526)\n        at\norg.eclipse.jdt.internal.corext.util.AllTypesCache$TypeCacher.doSearchTypes(AllTypesCache.java:197)\n        at\norg.eclipse.jdt.internal.corext.util.AllTypesCache$TypeCacher.run(AllTypesCache.java:166)\nUnhandled event loop exception\n\n-------------------------------------------------------------\n\nHere\u0027s a thread dump of what was happening at the time:\n\n2XMFULLTHDDUMP Full thread dump Classic VM (J2RE 1.4.1 IBM Windows 32 build\ncn1411-20040301a, native threads):\n3XMTHREADINFO      \"ModalContext\" (TID:0xB5F360, sys_thread_t:0x1CF4EC50,\nstate:CW, native ID:0xC74) prio\u003d6\n4XESTACKTRACE          at java.lang.Object.wait(Native Method)\n4XESTACKTRACE          at\norg.eclipse.jdt.internal.corext.util.AllTypesCache.getAllTypes(AllTypesCache.java:303)\n4XESTACKTRACE          at\norg.eclipse.jdt.internal.corext.util.AllTypesCache.getTypes(AllTypesCache.java:240)\n4XESTACKTRACE          at\norg.eclipse.jdt.internal.ui.dialogs.TypeSelectionDialog$1.run(TypeSelectionDialog.java:189)\n4XESTACKTRACE          at\norg.eclipse.jface.operation.ModalContext$ModalContextThread.run(ModalContext.java:101)\n3XMTHREADINFO      \"Worker-18\" (TID:0xB43538, sys_thread_t:0x1CED81C0, state:CW,\nnative ID:0x8C0) prio\u003d5\n4XESTACKTRACE          at java.lang.Object.wait(Native Method)\n4XESTACKTRACE          at\norg.eclipse.core.internal.jobs.WorkerPool.sleep(WorkerPool.java(Compiled Code))\n4XESTACKTRACE          at\norg.eclipse.core.internal.jobs.WorkerPool.startJob(WorkerPool.java(Compiled Code))\n4XESTACKTRACE          at org.eclipse.core.internal.jobs.Worker.run(Worker.java:59)\n3XMTHREADINFO      \"org.eclipse.jdt.internal.ui.text.JavaReconciler\"\n(TID:0x1994700, sys_thread_t:0x1CDD80D8, state:CW, native ID:0xCC8) prio\u003d1\n4XESTACKTRACE          at java.lang.Object.wait(Native Method)\n4XESTACKTRACE          at\norg.eclipse.jface.text.reconciler.AbstractReconciler$BackgroundThread.run(AbstractReconciler.java(Compiled\nCode))\n3XMTHREADINFO      \"org.eclipse.jdt.internal.ui.text.JavaReconciler\"\n(TID:0x18435B8, sys_thread_t:0x1CDE0520, state:CW, native ID:0xC60) prio\u003d1\n4XESTACKTRACE          at java.lang.Object.wait(Native Method)\n4XESTACKTRACE          at\norg.eclipse.jface.text.reconciler.AbstractReconciler$BackgroundThread.run(AbstractReconciler.java(Compiled\nCode))\n3XMTHREADINFO      \"org.eclipse.jdt.internal.ui.text.JavaReconciler\"\n(TID:0x164EFB8, sys_thread_t:0x1D7112E0, state:CW, native ID:0xC08) prio\u003d1\n4XESTACKTRACE          at java.lang.Object.wait(Native Method)\n4XESTACKTRACE          at\norg.eclipse.jface.text.reconciler.AbstractReconciler$BackgroundThread.run(AbstractReconciler.java(Compiled\nCode))\n3XMTHREADINFO      \"org.eclipse.jdt.internal.ui.text.JavaReconciler\"\n(TID:0x15977B0, sys_thread_t:0x1D532940, state:CW, native ID:0xA10) prio\u003d1\n4XESTACKTRACE          at java.lang.Object.wait(Native Method)\n4XESTACKTRACE          at\norg.eclipse.jface.text.reconciler.AbstractReconciler$BackgroundThread.run(AbstractReconciler.java(Compiled\nCode))\n3XMTHREADINFO      \"Java indexing\" (TID:0x13BD100, sys_thread_t:0x1B350440,\nstate:CW, native ID:0x824) prio\u003d4\n4XESTACKTRACE          at java.lang.Object.wait(Native Method)\n4XESTACKTRACE          at java.lang.Object.wait(Object.java:438)\n4XESTACKTRACE          at\norg.eclipse.jdt.internal.core.search.processing.JobManager.run(JobManager.java:338)\n4XESTACKTRACE          at java.lang.Thread.run(Thread.java:568)\n3XMTHREADINFO      \"Reference Cleaner - 2\" (TID:0xA05BB0,\nsys_thread_t:0x1B1331E8, state:CW, native ID:0x2D4) prio\u003d6\n4XESTACKTRACE          at java.lang.Object.wait(Native Method)\n4XESTACKTRACE          at\njava.lang.ref.ReferenceQueue.remove(ReferenceQueue.java:143)\n4XESTACKTRACE          at\njava.lang.ref.ReferenceQueue.remove(ReferenceQueue.java:159)\n4XESTACKTRACE          at\norg.eclipse.jface.action.ActionContributionItem$ImageCache$ReferenceCleanerThread.run(ActionContributionItem.java:207)\n3XMTHREADINFO      \"Reference Cleaner - 1\" (TID:0xA05C18,\nsys_thread_t:0x1B1342F8, state:CW, native ID:0x404) prio\u003d6\n4XESTACKTRACE          at java.lang.Object.wait(Native Method)\n4XESTACKTRACE          at\njava.lang.ref.ReferenceQueue.remove(ReferenceQueue.java:143)\n4XESTACKTRACE          at\njava.lang.ref.ReferenceQueue.remove(ReferenceQueue.java:159)\n4XESTACKTRACE          at\norg.eclipse.jface.action.ActionContributionItem$ImageCache$ReferenceCleanerThread.run(ActionContributionItem.java:207)\n3XMTHREADINFO      \"Start Level Event Dispatcher\" (TID:0xA0B540,\nsys_thread_t:0x1AB59850, state:CW, native ID:0x994) prio\u003d5\n4XESTACKTRACE          at java.lang.Object.wait(Native Method)\n4XESTACKTRACE          at java.lang.Object.wait(Object.java:438)\n4XESTACKTRACE          at\norg.eclipse.osgi.framework.eventmgr.EventThread.getNextEvent(EventThread.java:162)\n4XESTACKTRACE          at\norg.eclipse.osgi.framework.eventmgr.EventThread.run(EventThread.java:100)\n3XMTHREADINFO      \"Framework Event Dispatcher\" (TID:0xA0B5A8,\nsys_thread_t:0x1A9B67D8, state:CW, native ID:0x814) prio\u003d5\n4XESTACKTRACE          at java.lang.Object.wait(Native Method)\n4XESTACKTRACE          at java.lang.Object.wait(Object.java:438)\n4XESTACKTRACE          at\norg.eclipse.osgi.framework.eventmgr.EventThread.getNextEvent(EventThread.java:162)\n4XESTACKTRACE          at\norg.eclipse.osgi.framework.eventmgr.EventThread.run(EventThread.java:100)\n3XMTHREADINFO      \"Finalizer\" (TID:0xA0B8B0, sys_thread_t:0x1A247E80, state:CW,\nnative ID:0x658) prio\u003d8\n4XESTACKTRACE          at java.lang.Object.wait(Native Method)\n4XESTACKTRACE          at\njava.lang.ref.ReferenceQueue.remove(ReferenceQueue.java:143)\n4XESTACKTRACE          at\njava.lang.ref.ReferenceQueue.remove(ReferenceQueue.java(Compiled Code))\n4XESTACKTRACE          at\njava.lang.ref.Finalizer$FinalizerThread.run(Finalizer.java(Compiled Code))\n3XMTHREADINFO      \"Reference Handler\" (TID:0xA0B908, sys_thread_t:0x1A2AC978,\nstate:CW, native ID:0x340) prio\u003d10\n4XESTACKTRACE          at java.lang.ref.Reference.process(Native Method)\n4XESTACKTRACE          at java.lang.ref.Reference.access$300(Reference.java:36)\n4XESTACKTRACE          at\njava.lang.ref.Reference$ReferenceHandler.run(Reference.java:116)\n3XMTHREADINFO      \"Signal dispatcher\" (TID:0xA0B960, sys_thread_t:0x1A2AC240,\nstate:R, native ID:0x7B4) prio\u003d5\n3XMTHREADINFO      \"main\" (TID:0xA0B9B8, sys_thread_t:0x353C8, state:R, native\nID:0x748) prio\u003d6\n4XESTACKTRACE          at org.eclipse.swt.internal.win32.OS.WaitMessage(Native\nMethod)\n4XESTACKTRACE          at\norg.eclipse.swt.widgets.Display.sleep(Display.java(Compiled Code))\n4XESTACKTRACE          at\norg.eclipse.jface.operation.ModalContext$ModalContextThread.block(ModalContext.java(Compiled\nCode))\n4XESTACKTRACE          at\norg.eclipse.jface.operation.ModalContext.run(ModalContext.java:262)\n4XESTACKTRACE          at\norg.eclipse.jface.dialogs.ProgressMonitorDialog.run(ProgressMonitorDialog.java:397)\n4XESTACKTRACE          at\norg.eclipse.ui.internal.progress.ProgressMonitorJobsDialog.run(ProgressMonitorJobsDialog.java:251)\n4XESTACKTRACE          at\norg.eclipse.ui.internal.progress.ProgressManager$3.run(ProgressManager.java:778)\n4XESTACKTRACE          at\norg.eclipse.swt.custom.BusyIndicator.showWhile(BusyIndicator.java:69)\n4XESTACKTRACE          at\norg.eclipse.ui.internal.progress.ProgressManager.busyCursorWhile(ProgressManager.java:812)\n4XESTACKTRACE          at\norg.eclipse.ui.internal.progress.ProgressManager.busyCursorWhile(ProgressManager.java:789)\n4XESTACKTRACE          at\norg.eclipse.ui.internal.progress.ProgressManager.run(ProgressManager.java:973)\n4XESTACKTRACE          at\norg.eclipse.jdt.internal.ui.dialogs.TypeSelectionDialog.open(TypeSelectionDialog.java:195)\n4XESTACKTRACE          at\norg.eclipse.jdt.internal.ui.actions.OpenTypeAction.run(OpenTypeAction.java:68)\n4XESTACKTRACE          at\norg.eclipse.jdt.internal.ui.actions.OpenTypeAction.run(OpenTypeAction.java:89)\n4XESTACKTRACE          at\norg.eclipse.ui.internal.PluginAction.runWithEvent(PluginAction.java:276)\n4XESTACKTRACE          at\norg.eclipse.ui.internal.WWinPluginAction.runWithEvent(WWinPluginAction.java:206)\n4XESTACKTRACE          at\norg.eclipse.ui.commands.ActionHandler.execute(ActionHandler.java:141)\n4XESTACKTRACE          at\norg.eclipse.ui.internal.commands.Command.execute(Command.java:132)\n4XESTACKTRACE          at\norg.eclipse.ui.internal.keys.WorkbenchKeyboard.executeCommand(WorkbenchKeyboard.java:469)\n4XESTACKTRACE          at\norg.eclipse.ui.internal.keys.WorkbenchKeyboard.press(WorkbenchKeyboard.java:887)\n4XESTACKTRACE          at\norg.eclipse.ui.internal.keys.WorkbenchKeyboard.processKeyEvent(WorkbenchKeyboard.java:928)\n4XESTACKTRACE          at\norg.eclipse.ui.internal.keys.WorkbenchKeyboard.filterKeySequenceBindings(WorkbenchKeyboard.java:546)\n4XESTACKTRACE          at\norg.eclipse.ui.internal.keys.WorkbenchKeyboard.access$2(WorkbenchKeyboard.java:494)\n4XESTACKTRACE          at\norg.eclipse.ui.internal.keys.WorkbenchKeyboard$1.handleEvent(WorkbenchKeyboard.java:259)\n4XESTACKTRACE          at\norg.eclipse.swt.widgets.EventTable.sendEvent(EventTable.java(Compiled Code))\n4XESTACKTRACE          at\norg.eclipse.swt.widgets.Display.filterEvent(Display.java(Compiled Code))\n4XESTACKTRACE          at\norg.eclipse.swt.widgets.Widget.sendEvent(Widget.java(Compiled Code))\n4XESTACKTRACE          at\norg.eclipse.swt.widgets.Widget.sendEvent(Widget.java(Compiled Code))\n4XESTACKTRACE          at\norg.eclipse.swt.widgets.Widget.sendEvent(Widget.java(Compiled Code))\n4XESTACKTRACE          at\norg.eclipse.swt.widgets.Control.sendKeyEvent(Control.java:1734)\n4XESTACKTRACE          at\norg.eclipse.swt.widgets.Control.sendKeyEvent(Control.java:1730)\n4XESTACKTRACE          at org.eclipse.swt.widgets.Control.WM_CHAR(Control.java:3067)\n4XESTACKTRACE          at\norg.eclipse.swt.widgets.Control.windowProc(Control.java(Compiled Code))\n4XESTACKTRACE          at\norg.eclipse.swt.widgets.Display.windowProc(Display.java(Compiled Code))\n4XESTACKTRACE          at\norg.eclipse.swt.internal.win32.OS.DispatchMessageW(Native Method)\n4XESTACKTRACE          at\norg.eclipse.swt.internal.win32.OS.DispatchMessage(OS.java(Compiled Code))\n4XESTACKTRACE          at\norg.eclipse.swt.widgets.Display.readAndDispatch(Display.java(Compiled Code))\n4XESTACKTRACE          at\norg.eclipse.ui.internal.Workbench.runEventLoop(Workbench.java(Compiled Code))\n4XESTACKTRACE          at\norg.eclipse.ui.internal.Workbench.runUI(Workbench.java:1346)\n4XESTACKTRACE          at\norg.eclipse.ui.internal.Workbench.createAndRunWorkbench(Workbench.java:252)\n4XESTACKTRACE          at\norg.eclipse.ui.PlatformUI.createAndRunWorkbench(PlatformUI.java:141)\n4XESTACKTRACE          at\norg.eclipse.ui.internal.ide.IDEApplication.run(IDEApplication.java:96)\n4XESTACKTRACE          at\norg.eclipse.core.internal.runtime.PlatformActivator$1.run(PlatformActivator.java:335)\n4XESTACKTRACE          at\norg.eclipse.core.runtime.adaptor.EclipseStarter.run(EclipseStarter.java:272)\n4XESTACKTRACE          at\norg.eclipse.core.runtime.adaptor.EclipseStarter.run(EclipseStarter.java:128)\n4XESTACKTRACE          at sun.reflect.NativeMethodAccessorImpl.invoke0(Native\nMethod)\n4XESTACKTRACE          at\nsun.reflect.NativeMethodAccessorImpl.invoke(NativeMethodAccessorImpl.java:79)\n4XESTACKTRACE          at\nsun.reflect.DelegatingMethodAccessorImpl.invoke(DelegatingMethodAccessorImpl.java:41)\n4XESTACKTRACE          at java.lang.reflect.Method.invoke(Method.java:386)\n4XESTACKTRACE          at org.eclipse.core.launcher.Main.basicRun(Main.java:186)\n4XESTACKTRACE          at org.eclipse.core.launcher.Main.run(Main.java:647)\n4XESTACKTRACE          at org.eclipse.core.launcher.Main.main(Main.java:631)\n\n\n---------------------------------------------------------\n\nHere\u0027s my configuration info:\n\n*** Date: 6/23/04 2:06 PM\n\n*** Platform Details:\n\n*** System properties:\nawt.toolkit\u003dsun.awt.windows.WToolkit\nconsole.encoding\u003dCp437\neclipse.application\u003dorg.eclipse.ui.ide.workbench\neclipse.buildId\u003dI200406192000\neclipse.commands\u003d-os\nwin32\n-ws\nwin32\n-arch\nx86\n-showsplash\nD:\\Program Files\\eclipse\\eclipse.exe -showsplash 600\n-exitdata\nD:\\Program Files\\eclipse\\eclipse.exe -exitdata 9e4_38\n-debug\n-data\nD:\\workspaces\\head_workspace\n-Xmx512\n-vm\nC:\\WINDOWS\\system32\\java.exe\n\neclipse.product\u003dorg.eclipse.platform\neclipse.startTime\u003d1088010203375\neclipse.vm\u003dC:\\WINDOWS\\system32\\java.exe\neclipse.vmargs\u003d-Xj9\n-cp\nD:\\Program Files\\eclipse\\startup.jar\norg.eclipse.core.launcher.Main\n\neof\u003deof\nfile.encoding\u003dCp1252\nfile.encoding.pkg\u003dsun.io\nfile.separator\u003d\\\nibm.system.encoding\u003dCp1252\ninvokedviajava\u003d\njava.assistive\u003dON\njava.awt.fonts\u003d\njava.awt.graphicsenv\u003dsun.awt.Win32GraphicsEnvironment\njava.awt.printerjob\u003dsun.awt.windows.WPrinterJob\njava.class.path\u003dD:\\Program Files\\eclipse\\startup.jar\njava.class.version\u003d48.0\njava.compiler\u003djitc\njava.endorsed.dirs\u003dD:\\Program Files\\IBM\\Java141\\jre\\lib\\endorsed\njava.ext.dirs\u003dD:\\Program Files\\IBM\\Java141\\jre\\lib\\ext\njava.fullversion\u003dJ2RE 1.4.1 IBM Windows 32 build cn1411-20040301a (JIT enabled:\njitc)\njava.home\u003dD:\\Program Files\\IBM\\Java141\\jre\njava.io.tmpdir\u003dC:\\DOCUME~1\\Sxenos\\LOCALS~1\\Temp\\\njava.library.path\u003dC:\\WINDOWS\\system32;.;C:\\WINDOWS\\System32;C:\\WINDOWS;C:\\WINDOWS\\system32;C:\\WINDOWS;C:\\WINDOWS\\System32\\Wbem;C:\\WINDOWS\\system32\\nls;C:\\WINDOWS\\system32\\nls\\ENGLISH;C:\\Program\nFiles\\Eps10\\bin;D:\\Program\nFiles\\jdk-1_4_1_01-fcs-bin-windows-i586-30_sep_2002-cleaned\\jdk1.4.1_01\\bin;C:\\Nokia\\Tools\\Nokia_Developers_Suite_for_J2ME\\bin;C:\\Nokia\\Update_Manager\\bin;C:\\Optimizeit\\OptimizeitSuite60\\lib;X:.;Z:.;Y:.\njava.runtime.name\u003dJava(TM) 2 Runtime Environment, Standard Edition\njava.runtime.version\u003d1.4.1\njava.specification.name\u003dJava Platform API Specification\njava.specification.vendor\u003dSun Microsystems Inc.\njava.specification.version\u003d1.4\njava.util.prefs.PreferencesFactory\u003djava.util.prefs.WindowsPreferencesFactory\njava.vendor\u003dIBM Corporation\njava.vendor.url\u003dhttp://www.ibm.com/\njava.vendor.url.bug\u003d\njava.version\u003d1.4.1\njava.vm.info\u003dJ2RE 1.4.1 IBM Windows 32 build cn1411-20040301a (JIT enabled: jitc)\njava.vm.name\u003dClassic VM\njava.vm.specification.name\u003dJava Virtual Machine Specification\njava.vm.specification.vendor\u003dSun Microsystems Inc.\njava.vm.specification.version\u003d1.0\njava.vm.vendor\u003dIBM Corporation\njava.vm.version\u003d1.4.1\nline.separator\u003d",
    "*** Bug 68520 has been marked as a duplicate of this bug. ***",
    "Not reproduceable on Sun 1.4.2 - highly suspect its a VM bug with J2RE 1.4.1 \nIBM Windows 32 build cn1411-20040301a.\n\nNewer versions of this VM are available so we\u0027ll close this bug \u0026 reopen if \nthe problem is reproduceable on the newer versions... at that time we\u0027ll look \nfor a workaround."
  ],
  "commentCreationDates": [
    "2004-06-23T20:11:44+02:00",
    "2004-06-25T17:57:55+02:00",
    "2004-06-25T19:39:22+02:00"
  ],
  "traces": [
    {
      "exceptionType": "java.lang.IllegalMonitorStateException",
      "message": "JVMLK002: current thread not owner",
      "elements": [
        {
          "method": "org.eclipse.jdt.internal.core.index.Index.query",
          "source": "Index.java(Compiled Code)"
        },
        {
          "method": "org.eclipse.jdt.internal.core.search.matching.TypeDeclarationPattern.queryIn",
          "source": "TypeDeclarationPattern.java:189"
        },
        {
          "method": "org.eclipse.jdt.internal.core.search.matching.InternalSearchPattern.findIndexMatches",
          "source": "InternalSearchPattern.java(Compi led Code)"
        },
        {
          "method": "org.eclipse.jdt.internal.core.search.matching.MatchLocator.findIndexMatches",
          "source": "MatchLocator.java:266"
        },
        {
          "method": "org.eclipse.jdt.internal.core.search.PatternSearchJob.search",
          "source": "PatternSearchJob.java:109"
        },
        {
          "method": "org.eclipse.jdt.internal.core.search.PatternSearchJob.execute",
          "source": "PatternSearchJob.java:64"
        },
        {
          "method": "org.eclipse.jdt.internal.core.search.processing.JobManager.performConcurrentJob",
          "source": "JobManager.java:253"
        },
        {
          "method": "org.eclipse.jdt.core.search.SearchEngine.searchAllTypeNames",
          "source": "SearchEngine.java:866"
        },
        {
          "method": "org.eclipse.jdt.internal.corext.util.AllTypesCache.search",
          "source": "AllTypesCache.java:526"
        },
        {
          "method": "org.eclipse.jdt.internal.corext.util.AllTypesCache$TypeCacher.doSearchTypes",
          "source": "AllTypesCache.java:197"
        },
        {
          "method": "org.eclipse.jdt.internal.corext.util.AllTypesCache$TypeCacher.run",
          "source": "AllTypesCache.java:166"
        }
      ],
      "number": 0,
      "commentIndex": 0,
      "bugId": "68348",
      "date": "2004-06-23T20:11:44+02:00",
      "product": "JDT",
      "component": "Core",
      "severity": "normal"
    },
    {
      "exceptionType": "java.lang.IllegalMonitorStateException",
      "message": "JVMLK002: current thread not owner",
      "elements": [
        {
          "method": "org.eclipse.jdt.internal.core.index.Index.query",
          "source": "Index.java(Compiled Code)"
        },
        {
          "method": "org.eclipse.jdt.internal.core.search.matching.TypeDeclarationPattern.queryIn",
          "source": "TypeDeclarationPattern.java:189"
        },
        {
          "method": "org.eclipse.jdt.internal.core.search.matching.InternalSearchPattern.findIndexMatches",
          "source": "InternalSearchPattern.java(Compi led Code)"
        },
        {
          "method": "org.eclipse.jdt.internal.core.search.matching.MatchLocator.findIndexMatches",
          "source": "MatchLocator.java:266"
        },
        {
          "method": "org.eclipse.jdt.internal.core.search.PatternSearchJob.search",
          "source": "PatternSearchJob.java:109"
        },
        {
          "method": "org.eclipse.jdt.internal.core.search.PatternSearchJob.execute",
          "source": "PatternSearchJob.java:64"
        },
        {
          "method": "org.eclipse.jdt.internal.core.search.processing.JobManager.performConcurrentJob",
          "source": "JobManager.java:253"
        },
        {
          "method": "org.eclipse.jdt.core.search.SearchEngine.searchAllTypeNames",
          "source": "SearchEngine.java:866"
        },
        {
          "method": "org.eclipse.jdt.internal.corext.util.AllTypesCache.search",
          "source": "AllTypesCache.java:526"
        },
        {
          "method": "org.eclipse.jdt.internal.corext.util.AllTypesCache$TypeCacher.doSearchTypes",
          "source": "AllTypesCache.java:197"
        },
        {
          "method": "org.eclipse.jdt.internal.corext.util.AllTypesCache$TypeCacher.run",
          "source": "AllTypesCache.java:166"
        }
      ],
      "number": 1,
      "commentIndex": 0,
      "bugId": "68348",
      "date": "2004-06-23T20:11:44+02:00",
      "product": "JDT",
      "component": "Core",
      "severity": "normal"
    }
  ],
  "groupId": "68348",
  "bugId": "68348",
  "date": "2004-06-23T20:11:44+02:00",
  "product": "JDT",
  "component": "Core",
  "severity": "normal"
}