{
  "comments": [
    "Potential SWT issue, but I\u0027ll start with CDT first.\nCDT 2.0.0.200406230\nEclipse 3.0RC3\n\n1. Create a Std Make C++ project\n2. Create a subdir within that project\n3. Project \u003e Properties \u003e C/C++ Project Paths \u003e Source tab.\n4. Click the Add Folder... button\nThe Source Folder Selection (SFS) dialog appears.\n5. Move the SFS dialog.\n6. Cancel the SFS dialog, or close it using the X control.\n7. OK (not Cancel) to dismiss the Properties dialog.\nThe following appears on the console which started Eclipse:\nUnhandled event loop exception\nReason:\nWidget is disposed\n\nThe following appears in the .log file:\n\n!ENTRY org.eclipse.ui 4 4 Jun 24, 2004 11:03:22.242\n!MESSAGE Unhandled event loop exception\n\n!ENTRY org.eclipse.ui 4 0 Jun 24, 2004 11:03:22.243\n!MESSAGE Widget is disposed\n!STACK 0\norg.eclipse.swt.SWTException: Widget is disposed\n        at org.eclipse.swt.SWT.error(SWT.java:2691)\n        at org.eclipse.swt.SWT.error(SWT.java(Inlined Compiled Code))\n        at org.eclipse.swt.SWT.error(SWT.java(Inlined Compiled Code))\n        at org.eclipse.swt.widgets.Widget.error(Widget.java(Inlined Compiled \nCode))\n        at org.eclipse.swt.widgets.Widget.checkWidget(Widget.java(Compiled \nCode))\n        at org.eclipse.swt.widgets.Control.setVisible(Control.java:2847)\n        at org.eclipse.jface.dialogs.DialogMessageArea.restoreTitle\n(DialogMessageArea.java:125)\n        at org.eclipse.jface.dialogs.DialogMessageArea.updateText\n(DialogMessageArea.java:147)\n        at org.eclipse.jface.preference.PreferenceDialog.updateMessage\n(PreferenceDialog.java:1136)\n        at org.eclipse.jface.preference.PreferencePage.setMessage\n(PreferencePage.java:464)\n        at org.eclipse.cdt.internal.ui.dialogs.StatusUtil.applyToStatusLine\n(StatusUtil.java:55)\n        at \norg.eclipse.cdt.internal.ui.dialogs.cpaths.CPathPropertyPage.statusChanged\n(CPathPropertyPage.java:214)\n        at \norg.eclipse.cdt.internal.ui.dialogs.cpaths.AbstractPathOptionBlock.doStatusLineU\npdate(AbstractPathOptionBlock.java:195)\n        at \norg.eclipse.cdt.internal.ui.dialogs.cpaths.CPathTabBlock.buildPathDialogFieldCha\nnged(CPathTabBlock.java:48)\n        at \norg.eclipse.cdt.internal.ui.dialogs.cpaths.CPathTabBlock$BuildPathAdapter.dialog\nFieldChanged(CPathTabBlock.java:40)\n        at \norg.eclipse.cdt.internal.ui.wizards.dialogfields.DialogField.dialogFieldChanged\n(DialogField.java:52)\n        at \norg.eclipse.cdt.internal.ui.wizards.dialogfields.ListDialogField.dialogFieldChan\nged(ListDialogField.java:470)\n        at \norg.eclipse.cdt.internal.ui.wizards.dialogfields.ListDialogField.setElements\n(ListDialogField.java:546)\n        at org.eclipse.cdt.internal.ui.dialogs.cpaths.CPathTabBlock.initialize\n(CPathTabBlock.java:103)\n        at \norg.eclipse.cdt.internal.ui.dialogs.cpaths.AbstractPathOptionBlock.init\n(AbstractPathOptionBlock.java:117)\n        at org.eclipse.cdt.internal.ui.dialogs.cpaths.CPathPropertyPage$2.run\n(CPathPropertyPage.java:244)\n        at org.eclipse.swt.widgets.RunnableLock.run(RunnableLock.java:35)\n        at org.eclipse.swt.widgets.Synchronizer.runAsyncMessages\n(Synchronizer.java:106)\n        at org.eclipse.swt.widgets.Display.runAsyncMessages(Display.java:2558)\n        at org.eclipse.swt.widgets.Display.readAndDispatch(Display.java:2291)\n        at org.eclipse.ui.internal.Workbench.runEventLoop(Workbench.java:1375)\n        at org.eclipse.ui.internal.Workbench.runUI(Workbench.java:1346)\n        at org.eclipse.ui.internal.Workbench.createAndRunWorkbench\n(Workbench.java:252)\n        at org.eclipse.ui.PlatformUI.createAndRunWorkbench(PlatformUI.java:141)\n        at org.eclipse.ui.internal.ide.IDEApplication.run\n(IDEApplication.java:96)\n        at org.eclipse.core.internal.runtime.PlatformActivator$1.run\n(PlatformActivator.java:335)\n        at org.eclipse.core.runtime.adaptor.EclipseStarter.run\n(EclipseStarter.java:272)\n        at org.eclipse.core.runtime.adaptor.EclipseStarter.run\n(EclipseStarter.java:128)\n        at sun.reflect.NativeMethodAccessorImpl.invoke0(Native Method)\n        at sun.reflect.NativeMethodAccessorImpl.invoke\n(NativeMethodAccessorImpl.java:85)\n        at sun.reflect.NativeMethodAccessorImpl.invoke\n(NativeMethodAccessorImpl.java:58)\n        at sun.reflect.DelegatingMethodAccessorImpl.invoke\n(DelegatingMethodAccessorImpl.java:60)\n        at java.lang.reflect.Method.invoke(Method.java:391)\n        at org.eclipse.core.launcher.Main.basicRun(Main.java:186)\n        at org.eclipse.core.launcher.Main.run(Main.java:647)\n        at org.eclipse.core.launcher.Main.main(Main.java:631)",
    "Oh yeah, and this is on Linux (RedHat EL3).\nDoes not occur on Windows.\n",
    "Assigning to Hoda for investigation.",
    "\u003e Assigning to Hoda for investigation.\n\nLet Dave handle it, he may already have a fix.\n\nThanks Hoda.",
    "Ok, I\u0027ve added some more isDisposed checks in the async display calls, I don\u0027t\nhave linux so could you hammer on these pages to see if it still happens.\n\nThanks"
  ],
  "commentCreationDates": [
    "2004-06-24T17:19:50+02:00",
    "2004-06-24T19:03:59+02:00",
    "2004-06-25T16:27:29+02:00",
    "2004-06-25T20:19:02+02:00",
    "2004-06-25T22:27:08+02:00"
  ],
  "traces": [
    {
      "exceptionType": "org.eclipse.swt.SWTException",
      "message": "Widget is disposed",
      "elements": [
        {
          "method": "org.eclipse.swt.SWT.error",
          "source": "SWT.java:2691"
        },
        {
          "method": "org.eclipse.swt.SWT.error",
          "source": "SWT.java(Inlined Compiled Code)"
        },
        {
          "method": "org.eclipse.swt.SWT.error",
          "source": "SWT.java(Inlined Compiled Code)"
        },
        {
          "method": "org.eclipse.swt.widgets.Widget.error",
          "source": "Widget.java(Inlined Compiled  Code)"
        },
        {
          "method": "org.eclipse.swt.widgets.Widget.checkWidget",
          "source": "Widget.java(Compiled  Code)"
        },
        {
          "method": "org.eclipse.swt.widgets.Control.setVisible",
          "source": "Control.java:2847"
        },
        {
          "method": "org.eclipse.jface.dialogs.DialogMessageArea.restoreTitle",
          "source": "DialogMessageArea.java:125"
        },
        {
          "method": "org.eclipse.jface.dialogs.DialogMessageArea.updateText",
          "source": "DialogMessageArea.java:147"
        },
        {
          "method": "org.eclipse.jface.preference.PreferenceDialog.updateMessage",
          "source": "PreferenceDialog.java:1136"
        },
        {
          "method": "org.eclipse.jface.preference.PreferencePage.setMessage",
          "source": "PreferencePage.java:464"
        },
        {
          "method": "org.eclipse.cdt.internal.ui.dialogs.StatusUtil.applyToStatusLine",
          "source": "StatusUtil.java:55"
        },
        {
          "method": "org.eclipse.cdt.internal.ui.dialogs.cpaths.CPathPropertyPage.statusChanged",
          "source": "CPathPropertyPage.java:214"
        },
        {
          "method": "org.eclipse.cdt.internal.ui.dialogs.cpaths.AbstractPathOptionBlock.doStatusLineUpdate",
          "source": "AbstractPathOptionBlock.java:195"
        },
        {
          "method": "org.eclipse.cdt.internal.ui.dialogs.cpaths.CPathTabBlock.buildPathDialogFieldChanged",
          "source": "CPathTabBlock.java:48"
        },
        {
          "method": "org.eclipse.cdt.internal.ui.dialogs.cpaths.CPathTabBlock$BuildPathAdapter.dialogFieldChanged",
          "source": "CPathTabBlock.java:40"
        },
        {
          "method": "org.eclipse.cdt.internal.ui.wizards.dialogfields.DialogField.dialogFieldChanged",
          "source": "DialogField.java:52"
        },
        {
          "method": "org.eclipse.cdt.internal.ui.wizards.dialogfields.ListDialogField.dialogFieldChanged",
          "source": "ListDialogField.java:470"
        },
        {
          "method": "org.eclipse.cdt.internal.ui.wizards.dialogfields.ListDialogField.setElements",
          "source": "ListDialogField.java:546"
        },
        {
          "method": "org.eclipse.cdt.internal.ui.dialogs.cpaths.CPathTabBlock.initialize",
          "source": "CPathTabBlock.java:103"
        },
        {
          "method": "org.eclipse.cdt.internal.ui.dialogs.cpaths.AbstractPathOptionBlock.init",
          "source": "AbstractPathOptionBlock.java:117"
        },
        {
          "method": "org.eclipse.cdt.internal.ui.dialogs.cpaths.CPathPropertyPage$2.run",
          "source": "CPathPropertyPage.java:244"
        },
        {
          "method": "org.eclipse.swt.widgets.RunnableLock.run",
          "source": "RunnableLock.java:35"
        },
        {
          "method": "org.eclipse.swt.widgets.Synchronizer.runAsyncMessages",
          "source": "Synchronizer.java:106"
        },
        {
          "method": "org.eclipse.swt.widgets.Display.runAsyncMessages",
          "source": "Display.java:2558"
        },
        {
          "method": "org.eclipse.swt.widgets.Display.readAndDispatch",
          "source": "Display.java:2291"
        },
        {
          "method": "org.eclipse.ui.internal.Workbench.runEventLoop",
          "source": "Workbench.java:1375"
        },
        {
          "method": "org.eclipse.ui.internal.Workbench.runUI",
          "source": "Workbench.java:1346"
        },
        {
          "method": "org.eclipse.ui.internal.Workbench.createAndRunWorkbench",
          "source": "Workbench.java:252"
        },
        {
          "method": "org.eclipse.ui.PlatformUI.createAndRunWorkbench",
          "source": "PlatformUI.java:141"
        },
        {
          "method": "org.eclipse.ui.internal.ide.IDEApplication.run",
          "source": "IDEApplication.java:96"
        },
        {
          "method": "org.eclipse.core.internal.runtime.PlatformActivator$1.run",
          "source": "PlatformActivator.java:335"
        },
        {
          "method": "org.eclipse.core.runtime.adaptor.EclipseStarter.run",
          "source": "EclipseStarter.java:272"
        },
        {
          "method": "org.eclipse.core.runtime.adaptor.EclipseStarter.run",
          "source": "EclipseStarter.java:128"
        },
        {
          "method": "sun.reflect.NativeMethodAccessorImpl.invoke0",
          "source": "Native Method"
        },
        {
          "method": "sun.reflect.NativeMethodAccessorImpl.invoke",
          "source": "NativeMethodAccessorImpl.java:85"
        },
        {
          "method": "sun.reflect.NativeMethodAccessorImpl.invoke",
          "source": "NativeMethodAccessorImpl.java:58"
        },
        {
          "method": "sun.reflect.DelegatingMethodAccessorImpl.invoke",
          "source": "DelegatingMethodAccessorImpl.java:60"
        },
        {
          "method": "java.lang.reflect.Method.invoke",
          "source": "Method.java:391"
        },
        {
          "method": "org.eclipse.core.launcher.Main.basicRun",
          "source": "Main.java:186"
        },
        {
          "method": "org.eclipse.core.launcher.Main.run",
          "source": "Main.java:647"
        },
        {
          "method": "org.eclipse.core.launcher.Main.main",
          "source": "Main.java:631"
        }
      ],
      "number": 0,
      "commentIndex": 0,
      "bugId": "68486",
      "date": "2004-06-24T17:19:50+02:00",
      "product": "CDT",
      "component": "cdt-core",
      "severity": "major"
    }
  ],
  "groupId": "68486",
  "bugId": "68486",
  "date": "2004-06-24T17:19:50+02:00",
  "product": "CDT",
  "component": "cdt-core",
  "severity": "major"
}