{
  "comments": [
    "This might be related to bug 68348\n\nI was running a long checkout from CVS in the background, and tried to hit\nctrl-shift-T. The progress dialog never closed, and I found the following\nexceptions written to my console:\n\n\njava.lang.NullPointerException\n        at java.lang.SecurityManager.checkRead(SecurityManager.java:900)\n        at java.io.FileInputStream.\u003cinit\u003e(FileInputStream.java(Inlined Compiled\nCode))\n        at\norg.eclipse.jdt.internal.core.index.DiskIndex.readCategoryTable(DiskIndex.java(Compiled\nCode))\n        at\norg.eclipse.jdt.internal.core.index.DiskIndex.mergeCategory(DiskIndex.java:360)\n        at\norg.eclipse.jdt.internal.core.index.DiskIndex.mergeCategories(DiskIndex.java:352)\n        at\norg.eclipse.jdt.internal.core.index.DiskIndex.mergeWith(DiskIndex.java:444)\n        at org.eclipse.jdt.internal.core.index.Index.save(Index.java:171)\n        at\norg.eclipse.jdt.internal.core.search.indexing.IndexManager.saveIndex(IndexManager.java:506)\n        at\norg.eclipse.jdt.internal.core.search.indexing.IndexManager.saveIndexes(IndexManager.java:548)\n        at\norg.eclipse.jdt.internal.core.search.indexing.IndexManager.notifyIdle(IndexManager.java:369)\n        at\norg.eclipse.jdt.internal.core.search.processing.JobManager.run(JobManager.java:344)\n        at java.lang.Thread.run(Thread.java:568)\njava.lang.NullPointerException\n        at java.lang.SecurityManager.checkRead(SecurityManager.java:900)\n        at java.io.FileInputStream.\u003cinit\u003e(FileInputStream.java(Inlined Compiled\nCode))\n        at\norg.eclipse.jdt.internal.core.index.DiskIndex.readCategoryTable(DiskIndex.java(Compiled\nCode))\n        at\norg.eclipse.jdt.internal.core.index.DiskIndex.mergeCategory(DiskIndex.java:360)\n        at\norg.eclipse.jdt.internal.core.index.DiskIndex.mergeCategories(DiskIndex.java:352)\n        at\norg.eclipse.jdt.internal.core.index.DiskIndex.mergeWith(DiskIndex.java:444)\n        at org.eclipse.jdt.internal.core.index.Index.save(Index.java:171)\n        at\norg.eclipse.jdt.internal.core.search.indexing.IndexManager.saveIndex(IndexManager.java:506)\n        at\norg.eclipse.jdt.internal.core.search.indexing.SaveIndex.execute(SaveIndex.java:40)\n        at\norg.eclipse.jdt.internal.core.search.processing.JobManager.run(JobManager.java:361)\n        at java.lang.Thread.run(Thread.java:568)\njava.lang.NullPointerException\n        at\norg.eclipse.jdt.internal.core.search.indexing.IndexManager.getIndex(IndexManager.java(Compiled\nCode))\n        at\norg.eclipse.jdt.internal.core.search.PatternSearchJob.getIndexes(PatternSearchJob.java(Compiled\nCode))\n        at\norg.eclipse.jdt.internal.core.search.PatternSearchJob.execute(PatternSearchJob.java(Compiled\nCode))\n        at\norg.eclipse.jdt.internal.core.search.processing.JobManager.performConcurrentJob(JobManager.java:253)\n        at\norg.eclipse.jdt.core.search.SearchEngine.searchAllTypeNames(SearchEngine.java:866)\n        at\norg.eclipse.jdt.internal.corext.util.AllTypesCache.search(AllTypesCache.java:526)\n        at\norg.eclipse.jdt.internal.corext.util.AllTypesCache$TypeCacher.doSearchTypes(AllTypesCache.java:197)\n        at\norg.eclipse.jdt.internal.corext.util.AllTypesCache$TypeCacher.run(AllTypesCache.java:166)\njava.lang.NullPointerException: name can\u0027t be null\n        at java.io.FilePermission.init(FilePermission.java:180)\n        at java.io.FilePermission.\u003cinit\u003e(FilePermission.java:253)\n        at java.lang.SecurityManager.checkRead(SecurityManager.java:899)\n        at java.io.FileInputStream.\u003cinit\u003e(FileInputStream.java(Inlined Compiled\nCode))\n        at\norg.eclipse.jdt.internal.core.index.DiskIndex.readCategoryTable(DiskIndex.java(Compiled\nCode))\n        at\norg.eclipse.jdt.internal.core.index.DiskIndex.mergeCategory(DiskIndex.java:360)\n        at\norg.eclipse.jdt.internal.core.index.DiskIndex.mergeCategories(DiskIndex.java:352)\n        at\norg.eclipse.jdt.internal.core.index.DiskIndex.mergeWith(DiskIndex.java(Compiled\nCode))\n        at org.eclipse.jdt.internal.core.index.Index.save(Index.java:171)\n        at\norg.eclipse.jdt.internal.core.search.indexing.IndexManager.saveIndex(IndexManager.java:506)\n        at\norg.eclipse.jdt.internal.core.search.indexing.IndexManager.saveIndexes(IndexManager.java:548)\n        at\norg.eclipse.jdt.internal.core.search.indexing.IndexManager.notifyIdle(IndexManager.java:369)\n        at\norg.eclipse.jdt.internal.core.search.processing.JobManager.run(JobManager.java:344)\n        at java.lang.Thread.run(Thread.java:568)",
    "This was caused by a VM bug with IBM build cxia321411-20040301 (JIT enabled: \njitc). There are newer versions of this VM available - you should switch.\n\n*** This bug has been marked as a duplicate of 66836 ***"
  ],
  "commentCreationDates": [
    "2004-06-24T19:42:22+02:00",
    "2004-09-02T18:59:42+02:00"
  ],
  "traces": [
    {
      "exceptionType": "java.lang.NullPointerException",
      "elements": [
        {
          "method": "java.lang.SecurityManager.checkRead",
          "source": "SecurityManager.java:900"
        },
        {
          "method": "java.io.FileInputStream.\u003cinit\u003e",
          "source": "FileInputStream.java(Inlined Compiled Code)"
        },
        {
          "method": "org.eclipse.jdt.internal.core.index.DiskIndex.readCategoryTable",
          "source": "DiskIndex.java(Compiled Code)"
        },
        {
          "method": "org.eclipse.jdt.internal.core.index.DiskIndex.mergeCategory",
          "source": "DiskIndex.java:360"
        },
        {
          "method": "org.eclipse.jdt.internal.core.index.DiskIndex.mergeCategories",
          "source": "DiskIndex.java:352"
        },
        {
          "method": "org.eclipse.jdt.internal.core.index.DiskIndex.mergeWith",
          "source": "DiskIndex.java:444"
        },
        {
          "method": "org.eclipse.jdt.internal.core.index.Index.save",
          "source": "Index.java:171"
        },
        {
          "method": "org.eclipse.jdt.internal.core.search.indexing.IndexManager.saveIndex",
          "source": "IndexManager.java:506"
        },
        {
          "method": "org.eclipse.jdt.internal.core.search.indexing.IndexManager.saveIndexes",
          "source": "IndexManager.java:548"
        },
        {
          "method": "org.eclipse.jdt.internal.core.search.indexing.IndexManager.notifyIdle",
          "source": "IndexManager.java:369"
        },
        {
          "method": "org.eclipse.jdt.internal.core.search.processing.JobManager.run",
          "source": "JobManager.java:344"
        },
        {
          "method": "java.lang.Thread.run",
          "source": "Thread.java:568"
        }
      ],
      "number": 0,
      "commentIndex": 0,
      "bugId": "68510",
      "duplicateId": "66836",
      "date": "2004-06-24T19:42:22+02:00",
      "product": "JDT",
      "component": "Core",
      "severity": "normal"
    },
    {
      "exceptionType": "java.lang.NullPointerException",
      "elements": [
        {
          "method": "java.lang.SecurityManager.checkRead",
          "source": "SecurityManager.java:900"
        },
        {
          "method": "java.io.FileInputStream.\u003cinit\u003e",
          "source": "FileInputStream.java(Inlined Compiled Code)"
        },
        {
          "method": "org.eclipse.jdt.internal.core.index.DiskIndex.readCategoryTable",
          "source": "DiskIndex.java(Compiled Code)"
        },
        {
          "method": "org.eclipse.jdt.internal.core.index.DiskIndex.mergeCategory",
          "source": "DiskIndex.java:360"
        },
        {
          "method": "org.eclipse.jdt.internal.core.index.DiskIndex.mergeCategories",
          "source": "DiskIndex.java:352"
        },
        {
          "method": "org.eclipse.jdt.internal.core.index.DiskIndex.mergeWith",
          "source": "DiskIndex.java:444"
        },
        {
          "method": "org.eclipse.jdt.internal.core.index.Index.save",
          "source": "Index.java:171"
        },
        {
          "method": "org.eclipse.jdt.internal.core.search.indexing.IndexManager.saveIndex",
          "source": "IndexManager.java:506"
        },
        {
          "method": "org.eclipse.jdt.internal.core.search.indexing.SaveIndex.execute",
          "source": "SaveIndex.java:40"
        },
        {
          "method": "org.eclipse.jdt.internal.core.search.processing.JobManager.run",
          "source": "JobManager.java:361"
        },
        {
          "method": "java.lang.Thread.run",
          "source": "Thread.java:568"
        }
      ],
      "number": 1,
      "commentIndex": 0,
      "bugId": "68510",
      "duplicateId": "66836",
      "date": "2004-06-24T19:42:22+02:00",
      "product": "JDT",
      "component": "Core",
      "severity": "normal"
    },
    {
      "exceptionType": "java.lang.NullPointerException",
      "elements": [
        {
          "method": "org.eclipse.jdt.internal.core.search.indexing.IndexManager.getIndex",
          "source": "IndexManager.java(Compiled Code)"
        },
        {
          "method": "org.eclipse.jdt.internal.core.search.PatternSearchJob.getIndexes",
          "source": "PatternSearchJob.java(Compiled Code)"
        },
        {
          "method": "org.eclipse.jdt.internal.core.search.PatternSearchJob.execute",
          "source": "PatternSearchJob.java(Compiled Code)"
        },
        {
          "method": "org.eclipse.jdt.internal.core.search.processing.JobManager.performConcurrentJob",
          "source": "JobManager.java:253"
        },
        {
          "method": "org.eclipse.jdt.core.search.SearchEngine.searchAllTypeNames",
          "source": "SearchEngine.java:866"
        },
        {
          "method": "org.eclipse.jdt.internal.corext.util.AllTypesCache.search",
          "source": "AllTypesCache.java:526"
        },
        {
          "method": "org.eclipse.jdt.internal.corext.util.AllTypesCache$TypeCacher.doSearchTypes",
          "source": "AllTypesCache.java:197"
        },
        {
          "method": "org.eclipse.jdt.internal.corext.util.AllTypesCache$TypeCacher.run",
          "source": "AllTypesCache.java:166"
        }
      ],
      "number": 2,
      "commentIndex": 0,
      "bugId": "68510",
      "duplicateId": "66836",
      "date": "2004-06-24T19:42:22+02:00",
      "product": "JDT",
      "component": "Core",
      "severity": "normal"
    },
    {
      "exceptionType": "java.lang.NullPointerException",
      "message": "name can\u0027t be null",
      "elements": [
        {
          "method": "java.io.FilePermission.init",
          "source": "FilePermission.java:180"
        },
        {
          "method": "java.io.FilePermission.\u003cinit\u003e",
          "source": "FilePermission.java:253"
        },
        {
          "method": "java.lang.SecurityManager.checkRead",
          "source": "SecurityManager.java:899"
        },
        {
          "method": "java.io.FileInputStream.\u003cinit\u003e",
          "source": "FileInputStream.java(Inlined Compiled Code)"
        },
        {
          "method": "org.eclipse.jdt.internal.core.index.DiskIndex.readCategoryTable",
          "source": "DiskIndex.java(Compiled Code)"
        },
        {
          "method": "org.eclipse.jdt.internal.core.index.DiskIndex.mergeCategory",
          "source": "DiskIndex.java:360"
        },
        {
          "method": "org.eclipse.jdt.internal.core.index.DiskIndex.mergeCategories",
          "source": "DiskIndex.java:352"
        },
        {
          "method": "org.eclipse.jdt.internal.core.index.DiskIndex.mergeWith",
          "source": "DiskIndex.java(Compiled Code)"
        },
        {
          "method": "org.eclipse.jdt.internal.core.index.Index.save",
          "source": "Index.java:171"
        },
        {
          "method": "org.eclipse.jdt.internal.core.search.indexing.IndexManager.saveIndex",
          "source": "IndexManager.java:506"
        },
        {
          "method": "org.eclipse.jdt.internal.core.search.indexing.IndexManager.saveIndexes",
          "source": "IndexManager.java:548"
        },
        {
          "method": "org.eclipse.jdt.internal.core.search.indexing.IndexManager.notifyIdle",
          "source": "IndexManager.java:369"
        },
        {
          "method": "org.eclipse.jdt.internal.core.search.processing.JobManager.run",
          "source": "JobManager.java:344"
        },
        {
          "method": "java.lang.Thread.run",
          "source": "Thread.java:568"
        }
      ],
      "number": 3,
      "commentIndex": 0,
      "bugId": "68510",
      "duplicateId": "66836",
      "date": "2004-06-24T19:42:22+02:00",
      "product": "JDT",
      "component": "Core",
      "severity": "normal"
    }
  ],
  "groupId": "66836",
  "bugId": "68510",
  "duplicateId": "66836",
  "date": "2004-06-24T19:42:22+02:00",
  "product": "JDT",
  "component": "Core",
  "severity": "normal"
}