{
  "comments": [
    "I200406250010\n\n- use file with two \u0027a\u0027 and a line delimiter as its content:\n\"aa\n\"\n- find regular expression: a[^b]\n- set cursor at offset 0 and press find -\u003e OK\n- set cursor at offset 1 and press find -\u003e IAE\n\njava.lang.IllegalArgumentException: Argument not valid\n        at org.eclipse.swt.SWT.error(SWT.java:2677)\n        at org.eclipse.swt.SWT.error(SWT.java:2616)\n        at org.eclipse.swt.SWT.error(SWT.java:2587)\n        at org.eclipse.swt.custom.StyledText.setSelectionRange(StyledText.java:7\n196)\n        at org.eclipse.jface.text.TextViewer.findAndSelect(TextViewer.java:3929)\n\n        at org.eclipse.jface.text.TextViewer$FindReplaceTarget.findAndSelect(Tex\ntViewer.java:787)\n        at org.eclipse.ui.texteditor.FindReplaceTarget.findAndSelect(FindReplace\nTarget.java:88)\n        at org.eclipse.ui.texteditor.FindReplaceDialog.findAndSelect(FindReplace\nDialog.java:861)\n        at org.eclipse.ui.texteditor.FindReplaceDialog.findIndex(FindReplaceDial\nog.java:829)\n        at org.eclipse.ui.texteditor.FindReplaceDialog.findNext(FindReplaceDialo\ng.java:920)\n        at org.eclipse.ui.texteditor.FindReplaceDialog.performSearch(FindReplace\nDialog.java:1404)\n        at org.eclipse.ui.texteditor.FindReplaceDialog.performSearch(FindReplace\nDialog.java:1385)\n        at org.eclipse.ui.texteditor.FindReplaceDialog.access$28(FindReplaceDial\nog.java:1384)\n        at org.eclipse.ui.texteditor.FindReplaceDialog$1.widgetSelected(FindRepl\naceDialog.java:366)\n        at org.eclipse.swt.widgets.TypedListener.handleEvent(TypedListener.java:\n89)\n        at org.eclipse.swt.widgets.EventTable.sendEvent(EventTable.java:82)\n        at org.eclipse.swt.widgets.Widget.sendEvent(Widget.java:796)\n        at org.eclipse.swt.widgets.Display.runDeferredEvents(Display.java:2772)\n        at org.eclipse.swt.widgets.Display.readAndDispatch(Display.java:2431)\n        at org.eclipse.ui.internal.Workbench.runEventLoop(Workbench.java:1377)\n        at org.eclipse.ui.internal.Workbench.runUI(Workbench.java:1348)\n        at org.eclipse.ui.internal.Workbench.createAndRunWorkbench(Workbench.jav\na:254)\n        at org.eclipse.ui.PlatformUI.createAndRunWorkbench(PlatformUI.java:141)\n        at org.eclipse.ui.internal.ide.IDEApplication.run(IDEApplication.java:96\n)\n        at org.eclipse.core.internal.runtime.PlatformActivator$1.run(PlatformAct\nivator.java:335)\n        at org.eclipse.core.runtime.adaptor.EclipseStarter.run(EclipseStarter.ja\nva:273)\n        at org.eclipse.core.runtime.adaptor.EclipseStarter.run(EclipseStarter.ja\nva:129)\n        at sun.reflect.NativeMethodAccessorImpl.invoke0(Native Method)\n        at sun.reflect.NativeMethodAccessorImpl.invoke(NativeMethodAccessorImpl.\njava:39)\n        at sun.reflect.DelegatingMethodAccessorImpl.invoke(DelegatingMethodAcces\nsorImpl.java:25)\n        at java.lang.reflect.Method.invoke(Method.java:324)\n        at org.eclipse.core.launcher.Main.basicRun(Main.java:183)\n        at org.eclipse.core.launcher.Main.run(Main.java:644)\n        at org.eclipse.core.launcher.Main.main(Main.java:628)",
    "I can reproduce and continue work normally without restart and without loss of data.\n",
    "I20041207-0800\n\nAnother way to reproduce: regex search for \"\\s\" in text file\n\"testing\ntesting\n\"\n\nThe problem only appears with a Windows (\\r\\n line delimiters) document. Not\nreproducible with Unix nor MacOS 9 line delimiters. In contrast to the\nFind/Replace dialog, File Search does not produce an exception.",
    "Even if it depends on bug 44766 we should at least fix the IAE.",
    "Fixed in HEAD.\nAvailable in builds \u003e 20050114",
    "Verified in I20050217-2000 with test cases from comment 0 and comment 2."
  ],
  "commentCreationDates": [
    "2004-06-25T11:00:49+02:00",
    "2004-06-25T11:12:04+02:00",
    "2004-12-09T23:19:00+01:00",
    "2004-12-10T07:49:50+01:00",
    "2005-01-14T16:50:09+01:00",
    "2005-02-18T11:06:37+01:00"
  ],
  "traces": [
    {
      "exceptionType": "java.lang.IllegalArgumentException",
      "message": "Argument not valid",
      "elements": [
        {
          "method": "org.eclipse.swt.SWT.error",
          "source": "SWT.java:2677"
        },
        {
          "method": "org.eclipse.swt.SWT.error",
          "source": "SWT.java:2616"
        },
        {
          "method": "org.eclipse.swt.SWT.error",
          "source": "SWT.java:2587"
        },
        {
          "method": "org.eclipse.swt.custom.StyledText.setSelectionRange",
          "source": "StyledText.java:7 196"
        },
        {
          "method": "org.eclipse.jface.text.TextViewer.findAndSelect",
          "source": "TextViewer.java:3929"
        },
        {
          "method": "org.eclipse.jface.text.TextViewer$FindReplaceTarget.findAndSelect",
          "source": "Tex tViewer.java:787"
        },
        {
          "method": "org.eclipse.ui.texteditor.FindReplaceTarget.findAndSelect",
          "source": "FindReplace Target.java:88"
        },
        {
          "method": "org.eclipse.ui.texteditor.FindReplaceDialog.findAndSelect",
          "source": "FindReplace Dialog.java:861"
        },
        {
          "method": "org.eclipse.ui.texteditor.FindReplaceDialog.findIndex",
          "source": "FindReplaceDial og.java:829"
        },
        {
          "method": "org.eclipse.ui.texteditor.FindReplaceDialog.findNext",
          "source": "FindReplaceDialo g.java:920"
        },
        {
          "method": "org.eclipse.ui.texteditor.FindReplaceDialog.performSearch",
          "source": "FindReplace Dialog.java:1404"
        },
        {
          "method": "org.eclipse.ui.texteditor.FindReplaceDialog.performSearch",
          "source": "FindReplace Dialog.java:1385"
        },
        {
          "method": "org.eclipse.ui.texteditor.FindReplaceDialog.access$28",
          "source": "FindReplaceDial og.java:1384"
        },
        {
          "method": "org.eclipse.ui.texteditor.FindReplaceDialog$1.widgetSelected",
          "source": "FindRepl aceDialog.java:366"
        },
        {
          "method": "org.eclipse.swt.widgets.TypedListener.handleEvent",
          "source": "TypedListener.java: 89"
        },
        {
          "method": "org.eclipse.swt.widgets.EventTable.sendEvent",
          "source": "EventTable.java:82"
        },
        {
          "method": "org.eclipse.swt.widgets.Widget.sendEvent",
          "source": "Widget.java:796"
        },
        {
          "method": "org.eclipse.swt.widgets.Display.runDeferredEvents",
          "source": "Display.java:2772"
        },
        {
          "method": "org.eclipse.swt.widgets.Display.readAndDispatch",
          "source": "Display.java:2431"
        },
        {
          "method": "org.eclipse.ui.internal.Workbench.runEventLoop",
          "source": "Workbench.java:1377"
        },
        {
          "method": "org.eclipse.ui.internal.Workbench.runUI",
          "source": "Workbench.java:1348"
        },
        {
          "method": "org.eclipse.ui.internal.Workbench.createAndRunWorkbench",
          "source": "Workbench.jav a:254"
        },
        {
          "method": "org.eclipse.ui.PlatformUI.createAndRunWorkbench",
          "source": "PlatformUI.java:141"
        },
        {
          "method": "org.eclipse.ui.internal.ide.IDEApplication.run",
          "source": "IDEApplication.java:96 "
        },
        {
          "method": "org.eclipse.core.internal.runtime.PlatformActivator$1.run",
          "source": "PlatformAct ivator.java:335"
        },
        {
          "method": "org.eclipse.core.runtime.adaptor.EclipseStarter.run",
          "source": "EclipseStarter.ja va:273"
        },
        {
          "method": "org.eclipse.core.runtime.adaptor.EclipseStarter.run",
          "source": "EclipseStarter.ja va:129"
        },
        {
          "method": "sun.reflect.NativeMethodAccessorImpl.invoke0",
          "source": "Native Method"
        },
        {
          "method": "sun.reflect.NativeMethodAccessorImpl.invoke",
          "source": "NativeMethodAccessorImpl. java:39"
        },
        {
          "method": "sun.reflect.DelegatingMethodAccessorImpl.invoke",
          "source": "DelegatingMethodAcces sorImpl.java:25"
        },
        {
          "method": "java.lang.reflect.Method.invoke",
          "source": "Method.java:324"
        },
        {
          "method": "org.eclipse.core.launcher.Main.basicRun",
          "source": "Main.java:183"
        },
        {
          "method": "org.eclipse.core.launcher.Main.run",
          "source": "Main.java:644"
        },
        {
          "method": "org.eclipse.core.launcher.Main.main",
          "source": "Main.java:628"
        }
      ],
      "number": 0,
      "commentIndex": 0,
      "bugId": "68580",
      "date": "2004-06-25T11:00:49+02:00",
      "product": "Platform",
      "component": "Text",
      "severity": "normal"
    }
  ],
  "groupId": "68580",
  "bugId": "68580",
  "date": "2004-06-25T11:00:49+02:00",
  "product": "Platform",
  "component": "Text",
  "severity": "normal"
}