{
  "comments": [
    "20040625\n\nTypeDeclarationStatement fail to translate with an 3.0 AST.\n(ScopeAnalyzerTest.createAST creates a 3.0 AST of the type created by:\n\t\tbuf.append(\"package test1.ae;\\n\");\n\t\tbuf.append(\"public class E {\\n\");\n\t\tbuf.append(\"    public static class A {\\n\");\n\t\tbuf.append(\"        public class A1 {\\n\");\n\t\tbuf.append(\"            public int foo() {\\n\");\n\t\tbuf.append(\"                return 1;\\n\");\t\t\n\t\tbuf.append(\"            }\\n\");\t\t\t\n\t\tbuf.append(\"        }\\n\");\n\t\tbuf.append(\"        public class A2 {\\n\");\n\t\tbuf.append(\"        }\\n\");\t\t\n\t\tbuf.append(\"        public int foo() {\\n\");\n\t\tbuf.append(\"            return 2;\\n\");\t\t\n\t\tbuf.append(\"        }\\n\");\n\t\tbuf.append(\"    }\\n\");\n\t\tbuf.append(\"}\\n\");\t\t\n\t\tbuf.append(\"class F {\\n\");\n\t\tbuf.append(\"    public int goo(int param0) {\\n\");\n\t\tbuf.append(\"        class C extends E.A {\\n\");\n\t\tbuf.append(\"            A1 b;\\n\");\n\t\tbuf.append(\"            public int foo() {\\n\");\n\t\tbuf.append(\"                return 3;\\n\");\t\t\n\t\tbuf.append(\"            }\\n\");\n\t\tbuf.append(\"        }\\n\");\t\t\n\t\tbuf.append(\"        return 4;\\n\");\n\t\tbuf.append(\"    }\\n\");\t\t\t\n\t\tbuf.append(\"}\\n\");\n\njava.lang.UnsupportedOperationException: Operation only supported in JLS2 AST\n\tat java.lang.Throwable.\u003cinit\u003e(Throwable.java)\n\tat java.lang.Throwable.\u003cinit\u003e(Throwable.java:73)\n\tat org.eclipse.jdt.core.dom.ASTNode.supportedOnlyIn2(ASTNode.java:1775)\n\tat\norg.eclipse.jdt.core.dom.TypeDeclarationStatement.getTypeDeclaration(TypeDeclarationStatement.java:247)\n\tat org.eclipse.jdt.core.dom.ASTConverter.convert(ASTConverter.java:2328)\n\tat org.eclipse.jdt.core.dom.ASTConverter.convert(ASTConverter.java:626)\n\tat\norg.eclipse.jdt.core.dom.ASTConverter.buildBodyDeclarations(ASTConverter.java:436)\n\tat org.eclipse.jdt.core.dom.ASTConverter.convert(ASTConverter.java:2519)\n\tat org.eclipse.jdt.core.dom.ASTConverter.convert(ASTConverter.java:1280)\n\tat org.eclipse.jdt.core.dom.ASTParser.convert(ASTParser.java:710)\n\tat org.eclipse.jdt.core.dom.ASTParser.internalCreateAST(ASTParser.java:681)\n\tat org.eclipse.jdt.core.dom.ASTParser.createAST(ASTParser.java:574)\n\tat\norg.eclipse.jdt.ui.tests.core.ScopeAnalyzerTest.createAST(ScopeAnalyzerTest.java:769)\n\tat\norg.eclipse.jdt.ui.tests.core.ScopeAnalyzerTest.testTypeDeclarations1(ScopeAnalyzerTest.java)\n\tat sun.reflect.NativeMethodAccessorImpl.invoke0(Native Method)\n\tat sun.reflect.NativeMethodAccessorImpl.invoke(NativeMethodAccessorImpl.java:79)\n\tat\nsun.reflect.DelegatingMethodAccessorImpl.invoke(DelegatingMethodAccessorImpl.java:41)\n\tat java.lang.reflect.Method.invoke(Method.java:386)\n\tat junit.framework.TestCase.runTest(TestCase.java:154)\n\tat junit.framework.TestCase.runBare(TestCase.java:127)\n\tat junit.framework.TestResult$1.protect(TestResult.java:106)\n\tat junit.framework.TestResult.runProtected(TestResult.java:124)\n\tat junit.framework.TestResult.run(TestResult.java:109)\n\tat junit.framework.TestCase.run(TestCase.java:118)\n\tat junit.framework.TestSuite.runTest(TestSuite.java:208)\n\tat junit.framework.TestSuite.run(TestSuite.java:203)\n\tat junit.extensions.TestDecorator.basicRun(TestDecorator.java:22)\n\tat junit.extensions.TestSetup$1.protect(TestSetup.java:19)\n\tat junit.framework.TestResult.runProtected(TestResult.java:124)\n\tat junit.extensions.TestSetup.run(TestSetup.java:23)\n\tat\norg.eclipse.jdt.internal.junit.runner.RemoteTestRunner.runTests(RemoteTestRunner.java:421)\n\tat\norg.eclipse.jdt.internal.junit.runner.RemoteTestRunner.run(RemoteTestRunner.java:305)\n\tat\norg.eclipse.pde.internal.junit.runtime.RemotePluginTestRunner.main(RemotePluginTestRunner.java:30)\n\tat\norg.eclipse.pde.internal.junit.runtime.UITestApplication$1.run(UITestApplication.java:92)\n\tat org.eclipse.swt.widgets.RunnableLock.run(RunnableLock.java:35)\n\tat org.eclipse.swt.widgets.Synchronizer.runAsyncMessages(Synchronizer.java:106)\n\tat org.eclipse.swt.widgets.Display.runAsyncMessages(Display.java:2749)\n\tat org.eclipse.swt.widgets.Display.readAndDispatch(Display.java:2434)\n\tat org.eclipse.ui.internal.Workbench.runEventLoop(Workbench.java:1377)\n\tat org.eclipse.ui.internal.Workbench.runUI(Workbench.java:1348)\n\tat org.eclipse.ui.internal.Workbench.createAndRunWorkbench(Workbench.java:254)\n\tat org.eclipse.ui.PlatformUI.createAndRunWorkbench(PlatformUI.java:141)\n\tat org.eclipse.ui.internal.ide.IDEApplication.run(IDEApplication.java:96)\n\tat\norg.eclipse.pde.internal.junit.runtime.UITestApplication.run(UITestApplication.java:33)\n\tat\norg.eclipse.core.internal.runtime.PlatformActivator$1.run(PlatformActivator.java:335)\n\tat org.eclipse.core.runtime.adaptor.EclipseStarter.run(EclipseStarter.java:273)\n\tat org.eclipse.core.runtime.adaptor.EclipseStarter.run(EclipseStarter.java:129)\n\tat sun.reflect.NativeMethodAccessorImpl.invoke0(Native Method)\n\tat sun.reflect.NativeMethodAccessorImpl.invoke(NativeMethodAccessorImpl.java:79)\n\tat\nsun.reflect.DelegatingMethodAccessorImpl.invoke(DelegatingMethodAccessorImpl.java:41)\n\tat java.lang.reflect.Method.invoke(Method.java:386)\n\tat org.eclipse.core.launcher.Main.basicRun(Main.java:183)\n\tat org.eclipse.core.launcher.Main.run(Main.java:644)\n\tat org.eclipse.core.launcher.Main.main(Main.java:628)",
    "Fixed and released in stream 1.5.\nRegression test added."
  ],
  "commentCreationDates": [
    "2004-06-25T15:23:42+02:00",
    "2004-06-29T04:43:16+02:00"
  ],
  "traces": [
    {
      "exceptionType": "java.lang.UnsupportedOperationException",
      "message": "Operation only supported in JLS2 AST",
      "elements": [
        {
          "method": "java.lang.Throwable.\u003cinit\u003e",
          "source": "Throwable.java"
        },
        {
          "method": "java.lang.Throwable.\u003cinit\u003e",
          "source": "Throwable.java:73"
        },
        {
          "method": "org.eclipse.jdt.core.dom.ASTNode.supportedOnlyIn2",
          "source": "ASTNode.java:1775"
        },
        {
          "method": "org.eclipse.jdt.core.dom.TypeDeclarationStatement.getTypeDeclaration",
          "source": "TypeDeclarationStatement.java:247"
        },
        {
          "method": "org.eclipse.jdt.core.dom.ASTConverter.convert",
          "source": "ASTConverter.java:2328"
        },
        {
          "method": "org.eclipse.jdt.core.dom.ASTConverter.convert",
          "source": "ASTConverter.java:626"
        },
        {
          "method": "org.eclipse.jdt.core.dom.ASTConverter.buildBodyDeclarations",
          "source": "ASTConverter.java:436"
        },
        {
          "method": "org.eclipse.jdt.core.dom.ASTConverter.convert",
          "source": "ASTConverter.java:2519"
        },
        {
          "method": "org.eclipse.jdt.core.dom.ASTConverter.convert",
          "source": "ASTConverter.java:1280"
        },
        {
          "method": "org.eclipse.jdt.core.dom.ASTParser.convert",
          "source": "ASTParser.java:710"
        },
        {
          "method": "org.eclipse.jdt.core.dom.ASTParser.internalCreateAST",
          "source": "ASTParser.java:681"
        },
        {
          "method": "org.eclipse.jdt.core.dom.ASTParser.createAST",
          "source": "ASTParser.java:574"
        },
        {
          "method": "org.eclipse.jdt.ui.tests.core.ScopeAnalyzerTest.createAST",
          "source": "ScopeAnalyzerTest.java:769"
        },
        {
          "method": "org.eclipse.jdt.ui.tests.core.ScopeAnalyzerTest.testTypeDeclarations1",
          "source": "ScopeAnalyzerTest.java"
        },
        {
          "method": "sun.reflect.NativeMethodAccessorImpl.invoke0",
          "source": "Native Method"
        },
        {
          "method": "sun.reflect.NativeMethodAccessorImpl.invoke",
          "source": "NativeMethodAccessorImpl.java:79"
        },
        {
          "method": "sun.reflect.DelegatingMethodAccessorImpl.invoke",
          "source": "DelegatingMethodAccessorImpl.java:41"
        },
        {
          "method": "java.lang.reflect.Method.invoke",
          "source": "Method.java:386"
        },
        {
          "method": "junit.framework.TestCase.runTest",
          "source": "TestCase.java:154"
        },
        {
          "method": "junit.framework.TestCase.runBare",
          "source": "TestCase.java:127"
        },
        {
          "method": "junit.framework.TestResult$1.protect",
          "source": "TestResult.java:106"
        },
        {
          "method": "junit.framework.TestResult.runProtected",
          "source": "TestResult.java:124"
        },
        {
          "method": "junit.framework.TestResult.run",
          "source": "TestResult.java:109"
        },
        {
          "method": "junit.framework.TestCase.run",
          "source": "TestCase.java:118"
        },
        {
          "method": "junit.framework.TestSuite.runTest",
          "source": "TestSuite.java:208"
        },
        {
          "method": "junit.framework.TestSuite.run",
          "source": "TestSuite.java:203"
        },
        {
          "method": "junit.extensions.TestDecorator.basicRun",
          "source": "TestDecorator.java:22"
        },
        {
          "method": "junit.extensions.TestSetup$1.protect",
          "source": "TestSetup.java:19"
        },
        {
          "method": "junit.framework.TestResult.runProtected",
          "source": "TestResult.java:124"
        },
        {
          "method": "junit.extensions.TestSetup.run",
          "source": "TestSetup.java:23"
        },
        {
          "method": "org.eclipse.jdt.internal.junit.runner.RemoteTestRunner.runTests",
          "source": "RemoteTestRunner.java:421"
        },
        {
          "method": "org.eclipse.jdt.internal.junit.runner.RemoteTestRunner.run",
          "source": "RemoteTestRunner.java:305"
        },
        {
          "method": "org.eclipse.pde.internal.junit.runtime.RemotePluginTestRunner.main",
          "source": "RemotePluginTestRunner.java:30"
        },
        {
          "method": "org.eclipse.pde.internal.junit.runtime.UITestApplication$1.run",
          "source": "UITestApplication.java:92"
        },
        {
          "method": "org.eclipse.swt.widgets.RunnableLock.run",
          "source": "RunnableLock.java:35"
        },
        {
          "method": "org.eclipse.swt.widgets.Synchronizer.runAsyncMessages",
          "source": "Synchronizer.java:106"
        },
        {
          "method": "org.eclipse.swt.widgets.Display.runAsyncMessages",
          "source": "Display.java:2749"
        },
        {
          "method": "org.eclipse.swt.widgets.Display.readAndDispatch",
          "source": "Display.java:2434"
        },
        {
          "method": "org.eclipse.ui.internal.Workbench.runEventLoop",
          "source": "Workbench.java:1377"
        },
        {
          "method": "org.eclipse.ui.internal.Workbench.runUI",
          "source": "Workbench.java:1348"
        },
        {
          "method": "org.eclipse.ui.internal.Workbench.createAndRunWorkbench",
          "source": "Workbench.java:254"
        },
        {
          "method": "org.eclipse.ui.PlatformUI.createAndRunWorkbench",
          "source": "PlatformUI.java:141"
        },
        {
          "method": "org.eclipse.ui.internal.ide.IDEApplication.run",
          "source": "IDEApplication.java:96"
        },
        {
          "method": "org.eclipse.pde.internal.junit.runtime.UITestApplication.run",
          "source": "UITestApplication.java:33"
        },
        {
          "method": "org.eclipse.core.internal.runtime.PlatformActivator$1.run",
          "source": "PlatformActivator.java:335"
        },
        {
          "method": "org.eclipse.core.runtime.adaptor.EclipseStarter.run",
          "source": "EclipseStarter.java:273"
        },
        {
          "method": "org.eclipse.core.runtime.adaptor.EclipseStarter.run",
          "source": "EclipseStarter.java:129"
        },
        {
          "method": "sun.reflect.NativeMethodAccessorImpl.invoke0",
          "source": "Native Method"
        },
        {
          "method": "sun.reflect.NativeMethodAccessorImpl.invoke",
          "source": "NativeMethodAccessorImpl.java:79"
        },
        {
          "method": "sun.reflect.DelegatingMethodAccessorImpl.invoke",
          "source": "DelegatingMethodAccessorImpl.java:41"
        },
        {
          "method": "java.lang.reflect.Method.invoke",
          "source": "Method.java:386"
        },
        {
          "method": "org.eclipse.core.launcher.Main.basicRun",
          "source": "Main.java:183"
        },
        {
          "method": "org.eclipse.core.launcher.Main.run",
          "source": "Main.java:644"
        },
        {
          "method": "org.eclipse.core.launcher.Main.main",
          "source": "Main.java:628"
        }
      ],
      "number": 0,
      "commentIndex": 0,
      "bugId": "68602",
      "date": "2004-06-25T15:23:42+02:00",
      "product": "JDT",
      "component": "Core",
      "severity": "normal"
    }
  ],
  "groupId": "68602",
  "bugId": "68602",
  "date": "2004-06-25T15:23:42+02:00",
  "product": "JDT",
  "component": "Core",
  "severity": "normal"
}