{
  "comments": [
    "R3.0 + Cheetah06\n\n1. Import org.eclipse.jdt.core as source\n2. Open JavaElement.java\n3. Select getSchedulingRule()\n4. Press Mark Occurences\n5. Put cursor on return type \u0027ISchedulingRule\u0027\nObserve: You get the following error:\n!ENTRY org.eclipse.core.runtime 4 2 Jun 30, 2004 15:20:22.680\n!MESSAGE An internal error occurred during: \"Java AST creation\".\n!STACK 0\njava.lang.UnsupportedOperationException: Operation only supported in JLS2 AST\n        at org.eclipse.jdt.core.dom.ASTNode.supportedOnlyIn2(ASTNode.java:1775)\n        at org.eclipse.jdt.core.dom.MethodDeclaration.getReturnType\n(MethodDeclaration.java:669)\n        at \norg.eclipse.jdt.internal.corext.refactoring.code.flow.FlowAnalyzer.endVisit\n(FlowAnalyzer.java:591)\n        at \norg.eclipse.jdt.internal.corext.refactoring.code.flow.InOutFlowAnalyzer.endVisi\nt(InOutFlowAnalyzer.java:71)\n        at org.eclipse.jdt.core.dom.MethodDeclaration.accept0\n(MethodDeclaration.java:501)\n        at org.eclipse.jdt.core.dom.ASTNode.accept(ASTNode.java:2454)\n        at org.eclipse.jdt.core.dom.ASTNode.acceptChildren(ASTNode.java:2524)\n        at org.eclipse.jdt.core.dom.TypeDeclaration.accept0\n(TypeDeclaration.java:483)\n        at org.eclipse.jdt.core.dom.ASTNode.accept(ASTNode.java:2454)\n        at org.eclipse.jdt.core.dom.ASTNode.acceptChild(ASTNode.java:2501)\n        at org.eclipse.jdt.core.dom.TypeDeclarationStatement.accept0\n(TypeDeclarationStatement.java:186)\n        at org.eclipse.jdt.core.dom.ASTNode.accept(ASTNode.java:2454)\n        at org.eclipse.jdt.core.dom.ASTNode.acceptChildren(ASTNode.java:2524)\n        at org.eclipse.jdt.core.dom.Block.accept0(Block.java:133)\n        at org.eclipse.jdt.core.dom.ASTNode.accept(ASTNode.java:2454)\n        at org.eclipse.jdt.core.dom.ASTNode.acceptChild(ASTNode.java:2501)\n        at org.eclipse.jdt.core.dom.IfStatement.accept0(IfStatement.java:187)\n        at org.eclipse.jdt.core.dom.ASTNode.accept(ASTNode.java:2454)\n        at \norg.eclipse.jdt.internal.corext.refactoring.code.flow.InOutFlowAnalyzer.perform\n(InOutFlowAnalyzer.java:39)\n        at org.eclipse.jdt.internal.ui.search.MethodExitsFinder.markReferences\n(MethodExitsFinder.java:100)\n        at org.eclipse.jdt.internal.ui.search.MethodExitsFinder.perform\n(MethodExitsFinder.java:80)\n        at \norg.eclipse.jdt.internal.ui.javaeditor.JavaEditor.updateOccurrenceAnnotations\n(JavaEditor.java:3605)\n        at org.eclipse.jdt.internal.ui.javaeditor.JavaEditor$7.selectionChanged\n(JavaEditor.java:3661)\n        at \norg.eclipse.jdt.internal.ui.viewsupport.SelectionListenerWithASTManager$PartLis\ntenerGroup.calculateASTandInform(SelectionListenerWithASTManager.java:164)\n        at \norg.eclipse.jdt.internal.ui.viewsupport.SelectionListenerWithASTManager$3.run\n(SelectionListenerWithASTManager.java:136)\n        at org.eclipse.core.internal.jobs.Worker.run(Worker.java:66)",
    "getReturnType2() should be used in JLS3 mode.",
    "Got addressed in HEAD and will be in next I-Build.",
    "Verified in I200408101200."
  ],
  "commentCreationDates": [
    "2004-06-30T15:30:47+02:00",
    "2004-06-30T15:31:52+02:00",
    "2004-07-26T16:39:13+02:00",
    "2004-08-11T19:25:18+02:00"
  ],
  "traces": [
    {
      "exceptionType": "java.lang.UnsupportedOperationException",
      "message": "Operation only supported in JLS2 AST",
      "elements": [
        {
          "method": "org.eclipse.jdt.core.dom.ASTNode.supportedOnlyIn2",
          "source": "ASTNode.java:1775"
        },
        {
          "method": "org.eclipse.jdt.core.dom.MethodDeclaration.getReturnType",
          "source": "MethodDeclaration.java:669"
        },
        {
          "method": "org.eclipse.jdt.internal.corext.refactoring.code.flow.FlowAnalyzer.endVisit",
          "source": "FlowAnalyzer.java:591"
        },
        {
          "method": "org.eclipse.jdt.internal.corext.refactoring.code.flow.InOutFlowAnalyzer.endVisit",
          "source": "InOutFlowAnalyzer.java:71"
        },
        {
          "method": "org.eclipse.jdt.core.dom.MethodDeclaration.accept0",
          "source": "MethodDeclaration.java:501"
        },
        {
          "method": "org.eclipse.jdt.core.dom.ASTNode.accept",
          "source": "ASTNode.java:2454"
        },
        {
          "method": "org.eclipse.jdt.core.dom.ASTNode.acceptChildren",
          "source": "ASTNode.java:2524"
        },
        {
          "method": "org.eclipse.jdt.core.dom.TypeDeclaration.accept0",
          "source": "TypeDeclaration.java:483"
        },
        {
          "method": "org.eclipse.jdt.core.dom.ASTNode.accept",
          "source": "ASTNode.java:2454"
        },
        {
          "method": "org.eclipse.jdt.core.dom.ASTNode.acceptChild",
          "source": "ASTNode.java:2501"
        },
        {
          "method": "org.eclipse.jdt.core.dom.TypeDeclarationStatement.accept0",
          "source": "TypeDeclarationStatement.java:186"
        },
        {
          "method": "org.eclipse.jdt.core.dom.ASTNode.accept",
          "source": "ASTNode.java:2454"
        },
        {
          "method": "org.eclipse.jdt.core.dom.ASTNode.acceptChildren",
          "source": "ASTNode.java:2524"
        },
        {
          "method": "org.eclipse.jdt.core.dom.Block.accept0",
          "source": "Block.java:133"
        },
        {
          "method": "org.eclipse.jdt.core.dom.ASTNode.accept",
          "source": "ASTNode.java:2454"
        },
        {
          "method": "org.eclipse.jdt.core.dom.ASTNode.acceptChild",
          "source": "ASTNode.java:2501"
        },
        {
          "method": "org.eclipse.jdt.core.dom.IfStatement.accept0",
          "source": "IfStatement.java:187"
        },
        {
          "method": "org.eclipse.jdt.core.dom.ASTNode.accept",
          "source": "ASTNode.java:2454"
        },
        {
          "method": "org.eclipse.jdt.internal.corext.refactoring.code.flow.InOutFlowAnalyzer.perform",
          "source": "InOutFlowAnalyzer.java:39"
        },
        {
          "method": "org.eclipse.jdt.internal.ui.search.MethodExitsFinder.markReferences",
          "source": "MethodExitsFinder.java:100"
        },
        {
          "method": "org.eclipse.jdt.internal.ui.search.MethodExitsFinder.perform",
          "source": "MethodExitsFinder.java:80"
        },
        {
          "method": "org.eclipse.jdt.internal.ui.javaeditor.JavaEditor.updateOccurrenceAnnotations",
          "source": "JavaEditor.java:3605"
        },
        {
          "method": "org.eclipse.jdt.internal.ui.javaeditor.JavaEditor$7.selectionChanged",
          "source": "JavaEditor.java:3661"
        },
        {
          "method": "org.eclipse.jdt.internal.ui.viewsupport.SelectionListenerWithASTManager$PartListenerGroup.calculateASTandInform",
          "source": "SelectionListenerWithASTManager.java:164"
        },
        {
          "method": "org.eclipse.jdt.internal.ui.viewsupport.SelectionListenerWithASTManager$3.run",
          "source": "SelectionListenerWithASTManager.java:136"
        },
        {
          "method": "org.eclipse.core.internal.jobs.Worker.run",
          "source": "Worker.java:66"
        }
      ],
      "number": 0,
      "commentIndex": 0,
      "bugId": "69004",
      "date": "2004-06-30T15:30:47+02:00",
      "product": "JDT",
      "component": "UI",
      "severity": "normal"
    }
  ],
  "groupId": "69004",
  "bugId": "69004",
  "date": "2004-06-30T15:30:47+02:00",
  "product": "JDT",
  "component": "UI",
  "severity": "normal"
}