{
  "comments": [
    "When trying to document classes that are in the default package, the following \nerror occurs:\n\n\u003e Calling ajc...\n\u003e Building signature files...\n\u003e Calling javadoc...\nLoading source file C:\\eclipse_RC3\\eclipse\\ajdocworkingdir\\A.java...\nC:\\eclipse_RC3\\eclipse\\ajdocworkingdir\\A.java:1: \u003cidentifier\u003e expected\npackage ;\n        ^\n1 error\n\u003e Decorating html files...\n\u003e Decorating C:\\doc\\classX.html...\nAn internal error occured in ajdoc\nPlease copy the following text into an email message and send it,\nalong with any additional information you can add to:            \n                                                                 \n       aspectj-dev@eclipse.org                           \n                                                                 \n\njava.io.FileNotFoundException: C:\\doc\\classX.html (The system cannot find the \nfile specified)\njava.io.FileNotFoundException: C:\\doc\\classX.html (The system cannot find the \nfile specified)\n\tat java.io.FileInputStream.open(Native Method)\n\tat java.io.FileInputStream.\u003cinit\u003e(FileInputStream.java:106)\n\tat java.io.FileReader.\u003cinit\u003e(FileReader.java:55)\n\tat org.aspectj.tools.ajdoc.HtmlDecorator.decorateHTMLFile\n(HtmlDecorator.java:142)\n\tat org.aspectj.tools.ajdoc.HtmlDecorator.decorateHTMLFromDecl\n(HtmlDecorator.java:115)\n\tat org.aspectj.tools.ajdoc.HtmlDecorator.decorateHTMLFromDecls\n(HtmlDecorator.java:54)\n\tat org.aspectj.tools.ajdoc.HtmlDecorator.decorateHTMLFromInputFiles\n(HtmlDecorator.java:43)\n\tat org.aspectj.tools.ajdoc.Main.main(Main.java:210)",
    "Fixed.  The problem was in the generation of the stub files, which created an \nimproper package declaration for compilation units in the default package.\n\norg.aspectj.tools.ajdoc/CoverageTestCase.java has been expanded to test for \nthis.\n",
    "Fix released as part of AspectJ 1.2.1"
  ],
  "commentCreationDates": [
    "2004-06-30T16:22:51+02:00",
    "2004-07-05T20:16:48+02:00",
    "2004-10-21T10:31:15+02:00"
  ],
  "traces": [
    {
      "exceptionType": "java.io.FileNotFoundException",
      "message": "C:\\doc\\classX.html (The system cannot find the  file specified)",
      "elements": [
        {
          "method": "java.io.FileInputStream.open",
          "source": "Native Method"
        },
        {
          "method": "java.io.FileInputStream.\u003cinit\u003e",
          "source": "FileInputStream.java:106"
        },
        {
          "method": "java.io.FileReader.\u003cinit\u003e",
          "source": "FileReader.java:55"
        },
        {
          "method": "org.aspectj.tools.ajdoc.HtmlDecorator.decorateHTMLFile",
          "source": "HtmlDecorator.java:142"
        },
        {
          "method": "org.aspectj.tools.ajdoc.HtmlDecorator.decorateHTMLFromDecl",
          "source": "HtmlDecorator.java:115"
        },
        {
          "method": "org.aspectj.tools.ajdoc.HtmlDecorator.decorateHTMLFromDecls",
          "source": "HtmlDecorator.java:54"
        },
        {
          "method": "org.aspectj.tools.ajdoc.HtmlDecorator.decorateHTMLFromInputFiles",
          "source": "HtmlDecorator.java:43"
        },
        {
          "method": "org.aspectj.tools.ajdoc.Main.main",
          "source": "Main.java:210"
        }
      ],
      "number": 0,
      "commentIndex": 0,
      "bugId": "69011",
      "date": "2004-06-30T16:22:51+02:00",
      "product": "AspectJ",
      "component": "AJDoc",
      "severity": "minor"
    }
  ],
  "groupId": "69011",
  "bugId": "69011",
  "date": "2004-06-30T16:22:51+02:00",
  "product": "AspectJ",
  "component": "AJDoc",
  "severity": "minor"
}