{
  "comments": [
    "When trying to build a midsized project in eclipse 3.0 release I am always \ngetting an OutOfMemoryError. Increasing the heap size does not change the \nsituation. The project compiles without trouble when using eclipse 2.1.\n\nVM: Sun 1.4.1_02\n\nMy command line ist:\njava -classpath startup.jar org.eclipse.core.launcher.Main -os win32 -ws win32 -\narch x86 -showsplash -debug -dev -Xmx384m\n\nThe error message is as follows:\n\nUnhandled event loop exception\nReason:\njava.lang.OutOfMemoryError\njava.lang.OutOfMemoryError\njava.lang.NullPointerException\n        at org.eclipse.jdt.internal.core.search.indexing.IndexManager.getIndex\n(IndexManager.java:183)\n        at org.eclipse.jdt.internal.core.search.PatternSearchJob.getIndexes\n(PatternSearchJob.java:90)\n        at org.eclipse.jdt.internal.core.search.PatternSearchJob.execute\n(PatternSearchJob.java:58)\n        at \norg.eclipse.jdt.internal.core.search.processing.JobManager.performConcurrentJob\n(JobManager.java:253)\n        at org.eclipse.jdt.core.search.SearchEngine.searchAllTypeNames\n(SearchEngine.java:866)\n        at org.eclipse.jdt.internal.corext.util.AllTypesCache.search\n(AllTypesCache.java:526)\n        at \norg.eclipse.jdt.internal.corext.util.AllTypesCache$TypeCacher.doSearchTypes\n(AllTypesCache.java:197)\n        at org.eclipse.jdt.internal.corext.util.AllTypesCache$TypeCacher.run\n(AllTypesCache.java:166)",
    "So do you still see this problem?\n\nIs repeatable everytime? Does it happen on every project or just a few?\n\nCan you send us your workspace if its not too large?",
    "Same NPE as bug 71281.\n\nPlease provide steps to reproduce, then reopen.\n\n*** This bug has been marked as a duplicate of 71281 ***"
  ],
  "commentCreationDates": [
    "2004-07-01T15:29:31+02:00",
    "2004-08-09T18:40:22+02:00",
    "2004-08-10T21:37:29+02:00"
  ],
  "traces": [
    {
      "exceptionType": "java.lang.NullPointerException",
      "elements": [
        {
          "method": "org.eclipse.jdt.internal.core.search.indexing.IndexManager.getIndex",
          "source": "IndexManager.java:183"
        },
        {
          "method": "org.eclipse.jdt.internal.core.search.PatternSearchJob.getIndexes",
          "source": "PatternSearchJob.java:90"
        },
        {
          "method": "org.eclipse.jdt.internal.core.search.PatternSearchJob.execute",
          "source": "PatternSearchJob.java:58"
        },
        {
          "method": "org.eclipse.jdt.internal.core.search.processing.JobManager.performConcurrentJob",
          "source": "JobManager.java:253"
        },
        {
          "method": "org.eclipse.jdt.core.search.SearchEngine.searchAllTypeNames",
          "source": "SearchEngine.java:866"
        },
        {
          "method": "org.eclipse.jdt.internal.corext.util.AllTypesCache.search",
          "source": "AllTypesCache.java:526"
        },
        {
          "method": "org.eclipse.jdt.internal.corext.util.AllTypesCache$TypeCacher.doSearchTypes",
          "source": "AllTypesCache.java:197"
        },
        {
          "method": "org.eclipse.jdt.internal.corext.util.AllTypesCache$TypeCacher.run",
          "source": "AllTypesCache.java:166"
        }
      ],
      "number": 0,
      "commentIndex": 0,
      "bugId": "69132",
      "duplicateId": "71281",
      "date": "2004-07-01T15:29:31+02:00",
      "product": "JDT",
      "component": "Core",
      "severity": "blocker"
    }
  ],
  "groupId": "71281",
  "bugId": "69132",
  "duplicateId": "71281",
  "date": "2004-07-01T15:29:31+02:00",
  "product": "JDT",
  "component": "Core",
  "severity": "blocker"
}