{
  "comments": [
    "CDT 2.0 GA\nLinux RH EL3.\n\n1. Build automatically is turned on.\n2. I import a large PSF file (of 4 projects) which turns out to produce\nmany messages from CVS (regarding invalid line ending; one shown below).\nThese messages are shown in the Task list.\n3. As an import completes, the build starts and yields a message on the\nTask List, I think, producing a CME.\n\nSee Log file below.\nReproducible, although the stack trace varies.\n\n!ENTRY org.eclipse.team.cvs.core 2 0 Jun 30, 2004 15:28:29.332\n!MESSAGE CVS file /Sort/QuickSort/M4/SD_45.h either contains invalid line \nendings on the server (CR/LF instead of just LF) or is a binary file that is \nnot marked as -\nkb.\n\n!ENTRY org.eclipse.ui 4 4 Jun 30, 2004 15:28:30.433\n!MESSAGE Unhandled event loop exception\n\n!ENTRY org.eclipse.ui 4 0 Jun 30, 2004 15:28:30.436\n!MESSAGE Failed to execute runnable (java.util.ConcurrentModificationException)\n!STACK 0\norg.eclipse.swt.SWTException: Failed to execute runnable \n(java.util.ConcurrentModificationException)\n        at org.eclipse.swt.SWT.error(SWT.java:2691)\n        at org.eclipse.swt.SWT.error(SWT.java:2616)\n        at org.eclipse.swt.widgets.Synchronizer.runAsyncMessages\n(Synchronizer.java:109)\n        at org.eclipse.swt.widgets.Display.runAsyncMessages(Display.java:2572)\n        at org.eclipse.swt.widgets.Display.readAndDispatch(Display.java:2301)\n        at org.eclipse.jface.operation.ModalContext$ModalContextThread.block\n(ModalContext.java:136)\n        at org.eclipse.jface.operation.ModalContext.run(ModalContext.java:262)\n        at org.eclipse.jface.wizard.WizardDialog.run(WizardDialog.java:752)\n        at \norg.eclipse.team.internal.ui.wizards.ProjectSetImportWizard.performFinish\n(ProjectSetImportWizard.java:59)\n        at org.eclipse.jface.wizard.WizardDialog.finishPressed\n(WizardDialog.java:609)\n        at org.eclipse.jface.wizard.WizardDialog.buttonPressed\n(WizardDialog.java:305)\n        at org.eclipse.jface.dialogs.Dialog$2.widgetSelected(Dialog.java:506)\n        at org.eclipse.swt.widgets.TypedListener.handleEvent\n(TypedListener.java:89)\n        at org.eclipse.swt.widgets.EventTable.sendEvent(EventTable.java:82)\n        at org.eclipse.swt.widgets.Widget.sendEvent(Widget.java:954)\n        at org.eclipse.swt.widgets.Display.runDeferredEvents(Display.java:2595)\n        at org.eclipse.swt.widgets.Display.readAndDispatch(Display.java:2298)\n        at org.eclipse.jface.window.Window.runEventLoop(Window.java:668)\n        at org.eclipse.jface.window.Window.open(Window.java:648)\n        at org.eclipse.ui.actions.ImportResourcesAction.run\n(ImportResourcesAction.java:145)\n        at org.eclipse.ui.actions.BaseSelectionListenerAction.runWithEvent\n(BaseSelectionListenerAction.java:166)\n        at org.eclipse.jface.action.ActionContributionItem.handleWidgetSelection\n(ActionContributionItem.java:915)\n        at org.eclipse.jface.action.ActionContributionItem.access$2\n(ActionContributionItem.java:866)\n        at org.eclipse.jface.action.ActionContributionItem$7.handleEvent\n(ActionContributionItem.java:785)\n        at org.eclipse.swt.widgets.EventTable.sendEvent(EventTable.java:82)\n        at org.eclipse.swt.widgets.Widget.sendEvent(Widget.java:954)\n        at org.eclipse.swt.widgets.Display.runDeferredEvents(Display.java:2595)\n        at org.eclipse.swt.widgets.Display.readAndDispatch(Display.java:2298)\n        at org.eclipse.ui.internal.Workbench.runEventLoop(Workbench.java:1377)\n        at org.eclipse.ui.internal.Workbench.runUI(Workbench.java:1348)\n        at org.eclipse.ui.internal.Workbench.createAndRunWorkbench\n(Workbench.java:254)\n        at org.eclipse.ui.PlatformUI.createAndRunWorkbench(PlatformUI.java:141)\n        at org.eclipse.ui.internal.ide.IDEApplication.run\n(IDEApplication.java:96)\n        at org.eclipse.core.internal.runtime.PlatformActivator$1.run\n(PlatformActivator.java:335)\n        at org.eclipse.core.runtime.adaptor.EclipseStarter.run\n(EclipseStarter.java:273)\n        at org.eclipse.core.runtime.adaptor.EclipseStarter.run\n(EclipseStarter.java:129)\n        at sun.reflect.NativeMethodAccessorImpl.invoke0(Native Method)\n        at sun.reflect.NativeMethodAccessorImpl.invoke(Unknown Source)\n        at sun.reflect.DelegatingMethodAccessorImpl.invoke(Unknown Source)\n        at java.lang.reflect.Method.invoke(Unknown Source)\n        at org.eclipse.core.launcher.Main.basicRun(Main.java:183)\n        at org.eclipse.core.launcher.Main.run(Main.java:644)\n        at org.eclipse.core.launcher.Main.main(Main.java:628)\n\n!ENTRY org.eclipse.ui 4 4 Jun 30, 2004 15:28:30.458\n!MESSAGE *** SWT nested exception\n!ENTRY org.eclipse.ui 4 0 Jun 30, 2004 15:28:30.474\n!MESSAGE java.util.ConcurrentModificationException\n!STACK 0\njava.util.ConcurrentModificationException\n        at java.util.HashMap$HashIterator.nextEntry(Unknown Source)\n        at java.util.HashMap$KeyIterator.next(Unknown Source)\n        at org.eclipse.cdt.internal.ui.util.ProblemItemMapper.iterateItems\n(ProblemItemMapper.java:84)\n        at org.eclipse.cdt.internal.ui.util.ProblemItemMapper.problemsChanged\n(ProblemItemMapper.java:59)\n        at org.eclipse.cdt.internal.ui.util.ProblemTreeViewer$1.run\n(ProblemTreeViewer.java:68)\n        at org.eclipse.swt.widgets.RunnableLock.run(RunnableLock.java:35)\n        at org.eclipse.swt.widgets.Synchronizer.runAsyncMessages\n(Synchronizer.java:106)\n        at org.eclipse.swt.widgets.Display.runAsyncMessages(Display.java:2572)\n        at org.eclipse.swt.widgets.Display.readAndDispatch(Display.java:2301)\n        at org.eclipse.jface.operation.ModalContext$ModalContextThread.block\n(ModalContext.java:136)\n        at org.eclipse.jface.operation.ModalContext.run(ModalContext.java:262)\n        at org.eclipse.jface.wizard.WizardDialog.run(WizardDialog.java:752)\n        at \norg.eclipse.team.internal.ui.wizards.ProjectSetImportWizard.performFinish\n(ProjectSetImportWizard.java:59)\n        at org.eclipse.jface.wizard.WizardDialog.finishPressed\n(WizardDialog.java:609)\n        at org.eclipse.jface.wizard.WizardDialog.buttonPressed\n(WizardDialog.java:305)\n        at org.eclipse.jface.dialogs.Dialog$2.widgetSelected(Dialog.java:506)\n        at org.eclipse.swt.widgets.TypedListener.handleEvent\n(TypedListener.java:89)\n        at org.eclipse.swt.widgets.EventTable.sendEvent(EventTable.java:82)\n        at org.eclipse.swt.widgets.Widget.sendEvent(Widget.java:954)\n        at org.eclipse.swt.widgets.Display.runDeferredEvents(Display.java:2595)\n        at org.eclipse.swt.widgets.Display.readAndDispatch(Display.java:2298)\n        at org.eclipse.jface.window.Window.runEventLoop(Window.java:668)\n        at org.eclipse.jface.window.Window.open(Window.java:648)\n        at org.eclipse.ui.actions.ImportResourcesAction.run\n(ImportResourcesAction.java:145)\n        at org.eclipse.ui.actions.BaseSelectionListenerAction.runWithEvent\n(BaseSelectionListenerAction.java:166)\n        at org.eclipse.jface.action.ActionContributionItem.handleWidgetSelection\n(ActionContributionItem.java:915)\n        at org.eclipse.jface.action.ActionContributionItem.access$2\n(ActionContributionItem.java:866)\n        at org.eclipse.jface.action.ActionContributionItem$7.handleEvent\n(ActionContributionItem.java:785)\n        at org.eclipse.swt.widgets.EventTable.sendEvent(EventTable.java:82)\n        at org.eclipse.swt.widgets.Widget.sendEvent(Widget.java:954)\n        at org.eclipse.swt.widgets.Display.runDeferredEvents(Display.java:2595)\n        at org.eclipse.swt.widgets.Display.readAndDispatch(Display.java:2298)\n        at org.eclipse.ui.internal.Workbench.runEventLoop(Workbench.java:1377)\n        at org.eclipse.ui.internal.Workbench.runUI(Workbench.java:1348)\n        at org.eclipse.ui.internal.Workbench.createAndRunWorkbench\n(Workbench.java:254)\n        at org.eclipse.ui.PlatformUI.createAndRunWorkbench(PlatformUI.java:141)\n        at org.eclipse.ui.internal.ide.IDEApplication.run\n(IDEApplication.java:96)\n        at org.eclipse.core.internal.runtime.PlatformActivator$1.run\n(PlatformActivator.java:335)\n        at org.eclipse.core.runtime.adaptor.EclipseStarter.run\n(EclipseStarter.java:273)\n        at org.eclipse.core.runtime.adaptor.EclipseStarter.run\n(EclipseStarter.java:129)\n        at sun.reflect.NativeMethodAccessorImpl.invoke0(Native Method)\n        at sun.reflect.NativeMethodAccessorImpl.invoke(Unknown Source)\n        at sun.reflect.DelegatingMethodAccessorImpl.invoke(Unknown Source)\n        at java.lang.reflect.Method.invoke(Unknown Source)\n        at org.eclipse.core.launcher.Main.basicRun(Main.java:183)\n        at org.eclipse.core.launcher.Main.run(Main.java:644)\n        at org.eclipse.core.launcher.Main.main(Main.java:628)",
    "PR was not targeted to any particular release. Changing target milestone to 2.1",
    "Changes from David, make this obsolete, the CView uses the LabelDecorator."
  ],
  "commentCreationDates": [
    "2004-07-06T18:13:16+02:00",
    "2004-07-07T22:56:07+02:00",
    "2004-11-25T00:30:04+01:00"
  ],
  "traces": [
    {
      "exceptionType": "org.eclipse.swt.SWTException",
      "message": "Failed to execute runnable  (java.util.ConcurrentModificationException)",
      "elements": [
        {
          "method": "org.eclipse.swt.SWT.error",
          "source": "SWT.java:2691"
        },
        {
          "method": "org.eclipse.swt.SWT.error",
          "source": "SWT.java:2616"
        },
        {
          "method": "org.eclipse.swt.widgets.Synchronizer.runAsyncMessages",
          "source": "Synchronizer.java:109"
        },
        {
          "method": "org.eclipse.swt.widgets.Display.runAsyncMessages",
          "source": "Display.java:2572"
        },
        {
          "method": "org.eclipse.swt.widgets.Display.readAndDispatch",
          "source": "Display.java:2301"
        },
        {
          "method": "org.eclipse.jface.operation.ModalContext$ModalContextThread.block",
          "source": "ModalContext.java:136"
        },
        {
          "method": "org.eclipse.jface.operation.ModalContext.run",
          "source": "ModalContext.java:262"
        },
        {
          "method": "org.eclipse.jface.wizard.WizardDialog.run",
          "source": "WizardDialog.java:752"
        },
        {
          "method": "org.eclipse.team.internal.ui.wizards.ProjectSetImportWizard.performFinish",
          "source": "ProjectSetImportWizard.java:59"
        },
        {
          "method": "org.eclipse.jface.wizard.WizardDialog.finishPressed",
          "source": "WizardDialog.java:609"
        },
        {
          "method": "org.eclipse.jface.wizard.WizardDialog.buttonPressed",
          "source": "WizardDialog.java:305"
        },
        {
          "method": "org.eclipse.jface.dialogs.Dialog$2.widgetSelected",
          "source": "Dialog.java:506"
        },
        {
          "method": "org.eclipse.swt.widgets.TypedListener.handleEvent",
          "source": "TypedListener.java:89"
        },
        {
          "method": "org.eclipse.swt.widgets.EventTable.sendEvent",
          "source": "EventTable.java:82"
        },
        {
          "method": "org.eclipse.swt.widgets.Widget.sendEvent",
          "source": "Widget.java:954"
        },
        {
          "method": "org.eclipse.swt.widgets.Display.runDeferredEvents",
          "source": "Display.java:2595"
        },
        {
          "method": "org.eclipse.swt.widgets.Display.readAndDispatch",
          "source": "Display.java:2298"
        },
        {
          "method": "org.eclipse.jface.window.Window.runEventLoop",
          "source": "Window.java:668"
        },
        {
          "method": "org.eclipse.jface.window.Window.open",
          "source": "Window.java:648"
        },
        {
          "method": "org.eclipse.ui.actions.ImportResourcesAction.run",
          "source": "ImportResourcesAction.java:145"
        },
        {
          "method": "org.eclipse.ui.actions.BaseSelectionListenerAction.runWithEvent",
          "source": "BaseSelectionListenerAction.java:166"
        },
        {
          "method": "org.eclipse.jface.action.ActionContributionItem.handleWidgetSelection",
          "source": "ActionContributionItem.java:915"
        },
        {
          "method": "org.eclipse.jface.action.ActionContributionItem.access$2",
          "source": "ActionContributionItem.java:866"
        },
        {
          "method": "org.eclipse.jface.action.ActionContributionItem$7.handleEvent",
          "source": "ActionContributionItem.java:785"
        },
        {
          "method": "org.eclipse.swt.widgets.EventTable.sendEvent",
          "source": "EventTable.java:82"
        },
        {
          "method": "org.eclipse.swt.widgets.Widget.sendEvent",
          "source": "Widget.java:954"
        },
        {
          "method": "org.eclipse.swt.widgets.Display.runDeferredEvents",
          "source": "Display.java:2595"
        },
        {
          "method": "org.eclipse.swt.widgets.Display.readAndDispatch",
          "source": "Display.java:2298"
        },
        {
          "method": "org.eclipse.ui.internal.Workbench.runEventLoop",
          "source": "Workbench.java:1377"
        },
        {
          "method": "org.eclipse.ui.internal.Workbench.runUI",
          "source": "Workbench.java:1348"
        },
        {
          "method": "org.eclipse.ui.internal.Workbench.createAndRunWorkbench",
          "source": "Workbench.java:254"
        },
        {
          "method": "org.eclipse.ui.PlatformUI.createAndRunWorkbench",
          "source": "PlatformUI.java:141"
        },
        {
          "method": "org.eclipse.ui.internal.ide.IDEApplication.run",
          "source": "IDEApplication.java:96"
        },
        {
          "method": "org.eclipse.core.internal.runtime.PlatformActivator$1.run",
          "source": "PlatformActivator.java:335"
        },
        {
          "method": "org.eclipse.core.runtime.adaptor.EclipseStarter.run",
          "source": "EclipseStarter.java:273"
        },
        {
          "method": "org.eclipse.core.runtime.adaptor.EclipseStarter.run",
          "source": "EclipseStarter.java:129"
        },
        {
          "method": "sun.reflect.NativeMethodAccessorImpl.invoke0",
          "source": "Native Method"
        },
        {
          "method": "sun.reflect.NativeMethodAccessorImpl.invoke",
          "source": "Unknown Source"
        },
        {
          "method": "sun.reflect.DelegatingMethodAccessorImpl.invoke",
          "source": "Unknown Source"
        },
        {
          "method": "java.lang.reflect.Method.invoke",
          "source": "Unknown Source"
        },
        {
          "method": "org.eclipse.core.launcher.Main.basicRun",
          "source": "Main.java:183"
        },
        {
          "method": "org.eclipse.core.launcher.Main.run",
          "source": "Main.java:644"
        },
        {
          "method": "org.eclipse.core.launcher.Main.main",
          "source": "Main.java:628"
        }
      ],
      "number": 0,
      "commentIndex": 0,
      "bugId": "69390",
      "date": "2004-07-06T18:13:16+02:00",
      "product": "CDT",
      "component": "cdt-core",
      "severity": "major"
    },
    {
      "exceptionType": "java.util.ConcurrentModificationException",
      "elements": [
        {
          "method": "java.util.HashMap$HashIterator.nextEntry",
          "source": "Unknown Source"
        },
        {
          "method": "java.util.HashMap$KeyIterator.next",
          "source": "Unknown Source"
        },
        {
          "method": "org.eclipse.cdt.internal.ui.util.ProblemItemMapper.iterateItems",
          "source": "ProblemItemMapper.java:84"
        },
        {
          "method": "org.eclipse.cdt.internal.ui.util.ProblemItemMapper.problemsChanged",
          "source": "ProblemItemMapper.java:59"
        },
        {
          "method": "org.eclipse.cdt.internal.ui.util.ProblemTreeViewer$1.run",
          "source": "ProblemTreeViewer.java:68"
        },
        {
          "method": "org.eclipse.swt.widgets.RunnableLock.run",
          "source": "RunnableLock.java:35"
        },
        {
          "method": "org.eclipse.swt.widgets.Synchronizer.runAsyncMessages",
          "source": "Synchronizer.java:106"
        },
        {
          "method": "org.eclipse.swt.widgets.Display.runAsyncMessages",
          "source": "Display.java:2572"
        },
        {
          "method": "org.eclipse.swt.widgets.Display.readAndDispatch",
          "source": "Display.java:2301"
        },
        {
          "method": "org.eclipse.jface.operation.ModalContext$ModalContextThread.block",
          "source": "ModalContext.java:136"
        },
        {
          "method": "org.eclipse.jface.operation.ModalContext.run",
          "source": "ModalContext.java:262"
        },
        {
          "method": "org.eclipse.jface.wizard.WizardDialog.run",
          "source": "WizardDialog.java:752"
        },
        {
          "method": "org.eclipse.team.internal.ui.wizards.ProjectSetImportWizard.performFinish",
          "source": "ProjectSetImportWizard.java:59"
        },
        {
          "method": "org.eclipse.jface.wizard.WizardDialog.finishPressed",
          "source": "WizardDialog.java:609"
        },
        {
          "method": "org.eclipse.jface.wizard.WizardDialog.buttonPressed",
          "source": "WizardDialog.java:305"
        },
        {
          "method": "org.eclipse.jface.dialogs.Dialog$2.widgetSelected",
          "source": "Dialog.java:506"
        },
        {
          "method": "org.eclipse.swt.widgets.TypedListener.handleEvent",
          "source": "TypedListener.java:89"
        },
        {
          "method": "org.eclipse.swt.widgets.EventTable.sendEvent",
          "source": "EventTable.java:82"
        },
        {
          "method": "org.eclipse.swt.widgets.Widget.sendEvent",
          "source": "Widget.java:954"
        },
        {
          "method": "org.eclipse.swt.widgets.Display.runDeferredEvents",
          "source": "Display.java:2595"
        },
        {
          "method": "org.eclipse.swt.widgets.Display.readAndDispatch",
          "source": "Display.java:2298"
        },
        {
          "method": "org.eclipse.jface.window.Window.runEventLoop",
          "source": "Window.java:668"
        },
        {
          "method": "org.eclipse.jface.window.Window.open",
          "source": "Window.java:648"
        },
        {
          "method": "org.eclipse.ui.actions.ImportResourcesAction.run",
          "source": "ImportResourcesAction.java:145"
        },
        {
          "method": "org.eclipse.ui.actions.BaseSelectionListenerAction.runWithEvent",
          "source": "BaseSelectionListenerAction.java:166"
        },
        {
          "method": "org.eclipse.jface.action.ActionContributionItem.handleWidgetSelection",
          "source": "ActionContributionItem.java:915"
        },
        {
          "method": "org.eclipse.jface.action.ActionContributionItem.access$2",
          "source": "ActionContributionItem.java:866"
        },
        {
          "method": "org.eclipse.jface.action.ActionContributionItem$7.handleEvent",
          "source": "ActionContributionItem.java:785"
        },
        {
          "method": "org.eclipse.swt.widgets.EventTable.sendEvent",
          "source": "EventTable.java:82"
        },
        {
          "method": "org.eclipse.swt.widgets.Widget.sendEvent",
          "source": "Widget.java:954"
        },
        {
          "method": "org.eclipse.swt.widgets.Display.runDeferredEvents",
          "source": "Display.java:2595"
        },
        {
          "method": "org.eclipse.swt.widgets.Display.readAndDispatch",
          "source": "Display.java:2298"
        },
        {
          "method": "org.eclipse.ui.internal.Workbench.runEventLoop",
          "source": "Workbench.java:1377"
        },
        {
          "method": "org.eclipse.ui.internal.Workbench.runUI",
          "source": "Workbench.java:1348"
        },
        {
          "method": "org.eclipse.ui.internal.Workbench.createAndRunWorkbench",
          "source": "Workbench.java:254"
        },
        {
          "method": "org.eclipse.ui.PlatformUI.createAndRunWorkbench",
          "source": "PlatformUI.java:141"
        },
        {
          "method": "org.eclipse.ui.internal.ide.IDEApplication.run",
          "source": "IDEApplication.java:96"
        },
        {
          "method": "org.eclipse.core.internal.runtime.PlatformActivator$1.run",
          "source": "PlatformActivator.java:335"
        },
        {
          "method": "org.eclipse.core.runtime.adaptor.EclipseStarter.run",
          "source": "EclipseStarter.java:273"
        },
        {
          "method": "org.eclipse.core.runtime.adaptor.EclipseStarter.run",
          "source": "EclipseStarter.java:129"
        },
        {
          "method": "sun.reflect.NativeMethodAccessorImpl.invoke0",
          "source": "Native Method"
        },
        {
          "method": "sun.reflect.NativeMethodAccessorImpl.invoke",
          "source": "Unknown Source"
        },
        {
          "method": "sun.reflect.DelegatingMethodAccessorImpl.invoke",
          "source": "Unknown Source"
        },
        {
          "method": "java.lang.reflect.Method.invoke",
          "source": "Unknown Source"
        },
        {
          "method": "org.eclipse.core.launcher.Main.basicRun",
          "source": "Main.java:183"
        },
        {
          "method": "org.eclipse.core.launcher.Main.run",
          "source": "Main.java:644"
        },
        {
          "method": "org.eclipse.core.launcher.Main.main",
          "source": "Main.java:628"
        }
      ],
      "number": 1,
      "commentIndex": 0,
      "bugId": "69390",
      "date": "2004-07-06T18:13:16+02:00",
      "product": "CDT",
      "component": "cdt-core",
      "severity": "major"
    }
  ],
  "groupId": "69390",
  "bugId": "69390",
  "date": "2004-07-06T18:13:16+02:00",
  "product": "CDT",
  "component": "cdt-core",
  "severity": "major"
}