{
  "comments": [
    "Eclipse 3.0 GTK version crashes on startup. \n\nI\u0027m using SuSE Linux 8.0 and gtk-1.2.10-284\n\nHere\u0027s the log message:\n\n!SESSION Jul 10, 2004 22:34:35.94 ----------------------------------------------\neclipse.buildId\u003dI200406251208\njava.version\u003d1.4.2_05\njava.vendor\u003dSun Microsystems Inc.\nBootLoader constants: OS\u003dlinux, ARCH\u003dx86, WS\u003dgtk, NL\u003den_US\n\n!ENTRY org.eclipse.osgi Jul 10, 2004 22:34:35.95\n!MESSAGE Application error\n!STACK 1\njava.lang.UnsatisfiedLinkError: /home/akaranta/downloaded/java/eclipse/eclipse/p\nlugins/org.eclipse.swt.gtk_3.0.0/os/linux/x86/libswt-pi-gtk-3062.so: /usr/lib/li\nbpangoxft-1.0.so.0: undefined symbol: FT_Stream_GetShort\n        at java.lang.ClassLoader$NativeLibrary.load(Native Method)\n        at java.lang.ClassLoader.loadLibrary0(ClassLoader.java:1586)\n        at java.lang.ClassLoader.loadLibrary(ClassLoader.java:1495)\n        at java.lang.Runtime.loadLibrary0(Runtime.java:788)\n        at java.lang.System.loadLibrary(System.java:834)\n        at org.eclipse.swt.internal.Library.loadLibrary(Library.java:100)\n        at org.eclipse.swt.internal.gtk.OS.\u003cclinit\u003e(OS.java:19)\n        at org.eclipse.swt.internal.Converter.wcsToMbcs(Converter.java:63)\n        at org.eclipse.swt.internal.Converter.wcsToMbcs(Converter.java:54)\n        at org.eclipse.swt.widgets.Display.\u003cclinit\u003e(Display.java:118)\n        at org.eclipse.ui.internal.Workbench.createDisplay(Workbench.java:268)\n        at org.eclipse.ui.PlatformUI.createDisplay(PlatformUI.java:153)\n        at org.eclipse.ui.internal.ide.IDEApplication.createDisplay(IDEApplicati\non.java:122)\n        at org.eclipse.ui.internal.ide.IDEApplication.run(IDEApplication.java:72\n)\n        at org.eclipse.core.internal.runtime.PlatformActivator$1.run(PlatformAct\nivator.java:335)\n        at org.eclipse.core.runtime.adaptor.EclipseStarter.run(EclipseStarter.ja\nva:273)\n        at org.eclipse.core.runtime.adaptor.EclipseStarter.run(EclipseStarter.ja\nva:129)\n        at sun.reflect.NativeMethodAccessorImpl.invoke0(Native Method)\n        at sun.reflect.NativeMethodAccessorImpl.invoke(NativeMethodAccessorImpl.\njava:39)\n        at sun.reflect.DelegatingMethodAccessorImpl.invoke(DelegatingMethodAcces\nsorImpl.java:25)\n        at java.lang.reflect.Method.invoke(Method.java:324)\n        at org.eclipse.core.launcher.Main.basicRun(Main.java:183)\n        at org.eclipse.core.launcher.Main.run(Main.java:644)\n        at org.eclipse.core.launcher.Main.main(Main.java:628)",
    "It seems that SuSE 8.0 does not ship with GTK+-2.2 which is the minimum \nrequired by SWT.\n\nCan you post the output of \u0027rpm -qa | grep -i gtk\u0027 ?",
    "I think this problem is related to Bug68732, if we were not hard linking to \npangoxft (or pangoft2 ?) this would probably not be happening.\n\nSuSE 8.0 is probably to old to run eclipse 3.0, but in this case a new version \nof the package freetype would do (me thinks).\n\nAntti, would you be able to compile swt libraries ? would you be able to \nupdate freetype ?",
    "Felipe, I\u0027m unsure.  It\u0027s clear that libpangoxft exists on this users\u0027 system...\n I bet upgrading GTK+ would solve it.",
    "Yeap, I knew I\u0027ve seem this before: old version of freetype.\nPlease, reopen this problem report if updating freetype does not solve the \nproblem for you.\n\n*** This bug has been marked as a duplicate of 25367 ***"
  ],
  "commentCreationDates": [
    "2004-07-11T09:35:27+02:00",
    "2004-07-11T15:11:59+02:00",
    "2004-07-12T23:44:38+02:00",
    "2004-07-12T23:49:32+02:00",
    "2004-07-12T23:58:21+02:00"
  ],
  "traces": [
    {
      "exceptionType": "java.lang.UnsatisfiedLinkError",
      "message": "/home/akaranta/downloaded/java/eclipse/eclipse/p lugins/org.eclipse.swt.gtk_3.0.0/os/linux/x86/libswt-pi-gtk-3062.so: /usr/lib/li bpangoxft-1.0.so.0: undefined symbol: FT_Stream_GetShort",
      "elements": [
        {
          "method": "java.lang.ClassLoader$NativeLibrary.load",
          "source": "Native Method"
        },
        {
          "method": "java.lang.ClassLoader.loadLibrary0",
          "source": "ClassLoader.java:1586"
        },
        {
          "method": "java.lang.ClassLoader.loadLibrary",
          "source": "ClassLoader.java:1495"
        },
        {
          "method": "java.lang.Runtime.loadLibrary0",
          "source": "Runtime.java:788"
        },
        {
          "method": "java.lang.System.loadLibrary",
          "source": "System.java:834"
        },
        {
          "method": "org.eclipse.swt.internal.Library.loadLibrary",
          "source": "Library.java:100"
        },
        {
          "method": "org.eclipse.swt.internal.gtk.OS.\u003cclinit\u003e",
          "source": "OS.java:19"
        },
        {
          "method": "org.eclipse.swt.internal.Converter.wcsToMbcs",
          "source": "Converter.java:63"
        },
        {
          "method": "org.eclipse.swt.internal.Converter.wcsToMbcs",
          "source": "Converter.java:54"
        },
        {
          "method": "org.eclipse.swt.widgets.Display.\u003cclinit\u003e",
          "source": "Display.java:118"
        },
        {
          "method": "org.eclipse.ui.internal.Workbench.createDisplay",
          "source": "Workbench.java:268"
        },
        {
          "method": "org.eclipse.ui.PlatformUI.createDisplay",
          "source": "PlatformUI.java:153"
        },
        {
          "method": "org.eclipse.ui.internal.ide.IDEApplication.createDisplay",
          "source": "IDEApplicati on.java:122"
        },
        {
          "method": "org.eclipse.ui.internal.ide.IDEApplication.run",
          "source": "IDEApplication.java:72 "
        },
        {
          "method": "org.eclipse.core.internal.runtime.PlatformActivator$1.run",
          "source": "PlatformAct ivator.java:335"
        },
        {
          "method": "org.eclipse.core.runtime.adaptor.EclipseStarter.run",
          "source": "EclipseStarter.ja va:273"
        },
        {
          "method": "org.eclipse.core.runtime.adaptor.EclipseStarter.run",
          "source": "EclipseStarter.ja va:129"
        },
        {
          "method": "sun.reflect.NativeMethodAccessorImpl.invoke0",
          "source": "Native Method"
        },
        {
          "method": "sun.reflect.NativeMethodAccessorImpl.invoke",
          "source": "NativeMethodAccessorImpl. java:39"
        },
        {
          "method": "sun.reflect.DelegatingMethodAccessorImpl.invoke",
          "source": "DelegatingMethodAcces sorImpl.java:25"
        },
        {
          "method": "java.lang.reflect.Method.invoke",
          "source": "Method.java:324"
        },
        {
          "method": "org.eclipse.core.launcher.Main.basicRun",
          "source": "Main.java:183"
        },
        {
          "method": "org.eclipse.core.launcher.Main.run",
          "source": "Main.java:644"
        },
        {
          "method": "org.eclipse.core.launcher.Main.main",
          "source": "Main.java:628"
        }
      ],
      "number": 0,
      "commentIndex": 0,
      "bugId": "69790",
      "duplicateId": "25367",
      "date": "2004-07-11T09:35:27+02:00",
      "product": "Platform",
      "component": "SWT",
      "severity": "normal"
    }
  ],
  "groupId": "25367",
  "bugId": "69790",
  "duplicateId": "25367",
  "date": "2004-07-11T09:35:27+02:00",
  "product": "Platform",
  "component": "SWT",
  "severity": "normal"
}