{
  "comments": [
    "Hi,\n\nI upgraded from 3.0RC2 to 3.0 release.\n\nNow when I try to start eclipse the splash screen comes up, and then an error \nmessage appears referring me to the log file.\n\nI had installed the AJDT for AspectJ and was able to run it, prior to copying \nthe latest release of Eclipse (unzipped the file into the correct directories).\n\nThe contents of the log file are :\n\n!SESSION Jul 13, 2004 12:06:52.249 ---------------------------------------------\neclipse.buildId\u003dI200406251208\njava.version\u003d1.4.2\njava.vendor\u003dSun Microsystems Inc.\nBootLoader constants: OS\u003dwin32, ARCH\u003dx86, WS\u003dwin32, NL\u003den_IE\n\n!ENTRY org.eclipse.osgi Jul 13, 2004 12:06:52.249\n!MESSAGE Application error\n!STACK 1\njava.lang.RuntimeException: No application id has been found.\n\tat org.eclipse.core.internal.runtime.PlatformActivator$1.run\n(PlatformActivator.java:313)\n\tat org.eclipse.core.runtime.adaptor.EclipseStarter.run\n(EclipseStarter.java:273)\n\tat org.eclipse.core.runtime.adaptor.EclipseStarter.run\n(EclipseStarter.java:129)\n\tat sun.reflect.NativeMethodAccessorImpl.invoke0(Native Method)\n\tat sun.reflect.NativeMethodAccessorImpl.invoke\n(NativeMethodAccessorImpl.java:39)\n\tat sun.reflect.DelegatingMethodAccessorImpl.invoke\n(DelegatingMethodAccessorImpl.java:25)\n\tat java.lang.reflect.Method.invoke(Method.java:324)\n\tat org.eclipse.core.launcher.Main.basicRun(Main.java:183)\n\tat org.eclipse.core.launcher.Main.run(Main.java:644)\n\tat org.eclipse.core.launcher.Main.main(Main.java:628)\n\n!ENTRY org.eclipse.osgi Jul 13, 2004 12:06:52.264\n!MESSAGE Bundle update@/c:/eclipse/plugins/org.apache.ant_1.5.4/ [4] was not \nresolved.\n!SUBENTRY 1 org.eclipse.osgi Jul 13, 2004 12:06:52.264\n!MESSAGE Bundle update@/c:/eclipse/plugins/org.apache.ant_1.6.1/ was picked \ninstead.\n\n!ENTRY org.eclipse.osgi Jul 13, 2004 12:06:52.264\n!MESSAGE Bundle update@/c:/eclipse/plugins/org.apache.lucene_1.3.0/ [6] was not \nresolved.\n!SUBENTRY 1 org.eclipse.osgi Jul 13, 2004 12:06:52.264\n!MESSAGE Bundle update@/c:/eclipse/plugins/org.apache.lucene_1.3.0.RC2/ was \npicked instead.\n\n!ENTRY org.eclipse.osgi Jul 13, 2004 12:06:52.280\n!MESSAGE Bundle update@/c:/eclipse/plugins/org.eclipse.tomcat_4.1.29/ [71] was \nnot resolved.\n!SUBENTRY 1 org.eclipse.osgi Jul 13, 2004 12:06:52.280\n!MESSAGE Bundle update@/c:/eclipse/plugins/org.eclipse.tomcat_4.1.30/ was \npicked instead.",
    "I needed to uninstall and re-install AJDT.  Everything works OK now"
  ],
  "commentCreationDates": [
    "2004-07-13T13:33:00+02:00",
    "2004-07-14T10:33:59+02:00"
  ],
  "traces": [
    {
      "exceptionType": "java.lang.RuntimeException",
      "message": "No application id has been found.",
      "elements": [
        {
          "method": "org.eclipse.core.internal.runtime.PlatformActivator$1.run",
          "source": "PlatformActivator.java:313"
        },
        {
          "method": "org.eclipse.core.runtime.adaptor.EclipseStarter.run",
          "source": "EclipseStarter.java:273"
        },
        {
          "method": "org.eclipse.core.runtime.adaptor.EclipseStarter.run",
          "source": "EclipseStarter.java:129"
        },
        {
          "method": "sun.reflect.NativeMethodAccessorImpl.invoke0",
          "source": "Native Method"
        },
        {
          "method": "sun.reflect.NativeMethodAccessorImpl.invoke",
          "source": "NativeMethodAccessorImpl.java:39"
        },
        {
          "method": "sun.reflect.DelegatingMethodAccessorImpl.invoke",
          "source": "DelegatingMethodAccessorImpl.java:25"
        },
        {
          "method": "java.lang.reflect.Method.invoke",
          "source": "Method.java:324"
        },
        {
          "method": "org.eclipse.core.launcher.Main.basicRun",
          "source": "Main.java:183"
        },
        {
          "method": "org.eclipse.core.launcher.Main.run",
          "source": "Main.java:644"
        },
        {
          "method": "org.eclipse.core.launcher.Main.main",
          "source": "Main.java:628"
        }
      ],
      "number": 0,
      "commentIndex": 0,
      "bugId": "69905",
      "date": "2004-07-13T13:33:00+02:00",
      "product": "Platform",
      "component": "User Assistance",
      "severity": "blocker"
    }
  ],
  "groupId": "69905",
  "bugId": "69905",
  "date": "2004-07-13T13:33:00+02:00",
  "product": "Platform",
  "component": "User Assistance",
  "severity": "blocker"
}