{
  "comments": [
    "Using the spacewar example, the following works fine:\n    ajdoc -private -d doc spacewar coordination\nbut the following breaks:\n    ajdoc -public -d doc spacewar coordination\n\nThe end of the failing output is below. Display.html and\nDisplay.DisplayAspect.html were not generated as the types are not public, so\npresumably the decorator shouldn\u0027t be looking for them in this case.\n\n\u003e Decorating html files...\n\u003e Decorating C:\\aspectj1.2\\doc\\examples\\doc\\spacewar\\Debug.html...\n\u003e Decorating C:\\aspectj1.2\\doc\\examples\\doc\\spacewar\\Display.DisplayAspect.html.\n..\nAn internal error occured in ajdoc\nPlease copy the following text into an email message and send it,\nalong with any additional information you can add to:\n\n       aspectj-dev@eclipse.org\n\n\njava.io.FileNotFoundException: C:\\aspectj1.2\\doc\\examples\\doc\\spacewar\\Display.D\nisplayAspect.html (The system cannot find the file specified)\njava.io.FileNotFoundException: C:\\aspectj1.2\\doc\\examples\\doc\\spacewar\\Display.D\nisplayAspect.html (The system cannot find the file specified)\n        at java.io.FileInputStream.open(Native Method)\n        at java.io.FileInputStream.\u003cinit\u003e(FileInputStream.java:106)\n        at java.io.FileReader.\u003cinit\u003e(FileReader.java:55)\n        at org.aspectj.tools.ajdoc.HtmlDecorator.decorateHTMLFile(HtmlDecorator.\njava:142)\n        at org.aspectj.tools.ajdoc.HtmlDecorator.decorateHTMLFromDecl(HtmlDecora\ntor.java:115)\n        at org.aspectj.tools.ajdoc.HtmlDecorator.decorateHTMLFromDecls(HtmlDecor\nator.java:54)\n        at org.aspectj.tools.ajdoc.HtmlDecorator.decorateHTMLFromInputFiles(Html\nDecorator.java:43)\n        at org.aspectj.tools.ajdoc.Main.main(Main.java:210)",
    "Fixed.\n\nThis turned out to be a trickier problem, and I expanded the CoverageTestCase \nand SpacewarTestCase tests to cover it more thoroughly.  In a nutshell, the \ncompiler\u0027s AST makes any nested aspect \"public\" accessiblity, whether it is \ndeclared \"package\" or \"private\" visibility.  This results in a mismmatch \nbetween the structure model and the source code.\n\nI was tempted to fix this by making the structure model treat those aspects as \nprivate.  However, this would be a somewhat time consuming operation since it \nwould need to parse the original source code rather than relying on the AST.  \nSo instead I made ajdoc treat this case correctly.\n\nPLEASE NOTE THE SIDE-EFFECT of keeping this behavior: the outline view will \ncontinue to show private/package nested aspects as public, sine that\u0027s what\u0027s \nin the bytecode.\n",
    "Matt - I\u0027ve just checked in a new org.aspectj.ajde with Miks fix in it - can you\ntest it?",
    "I\u0027ve verified the fix from AJDT. Thanks guys.",
    "Fix released as part of AspectJ 1.2.1"
  ],
  "commentCreationDates": [
    "2004-07-14T13:16:55+02:00",
    "2004-07-14T22:14:32+02:00",
    "2004-07-15T10:38:49+02:00",
    "2004-07-15T10:58:59+02:00",
    "2004-10-21T10:30:48+02:00"
  ],
  "traces": [
    {
      "exceptionType": "java.io.FileNotFoundException",
      "message": "C:\\aspectj1.2\\doc\\examples\\doc\\spacewar\\Display.D isplayAspect.html (The system cannot find the file specified)",
      "elements": [
        {
          "method": "java.io.FileInputStream.open",
          "source": "Native Method"
        },
        {
          "method": "java.io.FileInputStream.\u003cinit\u003e",
          "source": "FileInputStream.java:106"
        },
        {
          "method": "java.io.FileReader.\u003cinit\u003e",
          "source": "FileReader.java:55"
        },
        {
          "method": "org.aspectj.tools.ajdoc.HtmlDecorator.decorateHTMLFile",
          "source": "HtmlDecorator. java:142"
        },
        {
          "method": "org.aspectj.tools.ajdoc.HtmlDecorator.decorateHTMLFromDecl",
          "source": "HtmlDecora tor.java:115"
        },
        {
          "method": "org.aspectj.tools.ajdoc.HtmlDecorator.decorateHTMLFromDecls",
          "source": "HtmlDecor ator.java:54"
        },
        {
          "method": "org.aspectj.tools.ajdoc.HtmlDecorator.decorateHTMLFromInputFiles",
          "source": "Html Decorator.java:43"
        },
        {
          "method": "org.aspectj.tools.ajdoc.Main.main",
          "source": "Main.java:210"
        }
      ],
      "number": 0,
      "commentIndex": 0,
      "bugId": "70008",
      "date": "2004-07-14T13:16:55+02:00",
      "product": "AspectJ",
      "component": "AJDoc",
      "severity": "normal"
    }
  ],
  "groupId": "70008",
  "bugId": "70008",
  "date": "2004-07-14T13:16:55+02:00",
  "product": "AspectJ",
  "component": "AJDoc",
  "severity": "normal"
}