{
  "comments": [
    "Hi guys!\n\n  I have a problem with JUnit framework. Each time i try to launch a class as a \nJUnit task I\u0027ve got exception:\n\njava.lang.NoSuchMethodError: junit.framework.TestCase.getName()\nLjava/lang/String;\n\tat org.eclipse.jdt.internal.junit.runner.RemoteTestRunner.getTestName\n(RemoteTestRunner.java:616)\n\tat org.eclipse.jdt.internal.junit.runner.RemoteTestRunner.sendTree\n(RemoteTestRunner.java:589)\n\tat org.eclipse.jdt.internal.junit.runner.RemoteTestRunner.sendTree\n(RemoteTestRunner.java:585)\n\tat org.eclipse.jdt.internal.junit.runner.RemoteTestRunner.runTests\n(RemoteTestRunner.java:414)\n\tat org.eclipse.jdt.internal.junit.runner.RemoteTestRunner.run\n(RemoteTestRunner.java:305)\n\tat org.eclipse.jdt.internal.junit.runner.RemoteTestRunner.main\n(RemoteTestRunner.java:186)\n\n  Class example is below:\n\npackage com.classic.xyz;\n\nimport org.apache.log4j.Logger;\n\nimport junit.framework.*;\n\npublic class MainTest extends TestCase {\n\tprivate static Logger log \u003d Logger.getLogger(MainTest.class);\n\n\tpublic MainTest(String testName) {\n\t\tsuper(testName);\n\t}\n\t\n\tpublic static TestSuite suite(){\n\t\tTestSuite suite \u003d new TestSuite();\n\t\tsuite.addTest(new MainTest(\"testCalculator\"));\n\t\treturn suite;\n\t}\n\t\n\tpublic void testCalculator()\n\tthrows Exception {\n\t\tString logStr \u003d \"testCalculator() : \";\n\t\tlog.debug(logStr + \"start\");\n\t\t\n\t\tlog.debug(logStr + \"end\");\n\t}\n\n}\n\nCheers, Andrei",
    "Move to JDT/UI",
    "works for me - I suspect you are using a very old JUnit version in your \nworkspace."
  ],
  "commentCreationDates": [
    "2004-07-19T09:32:42+02:00",
    "2004-07-19T17:28:53+02:00",
    "2004-09-07T14:47:33+02:00"
  ],
  "traces": [
    {
      "exceptionType": "java.lang.NoSuchMethodError",
      "message": "junit.framework.TestCase.getName() Ljava/lang/String;",
      "elements": [
        {
          "method": "org.eclipse.jdt.internal.junit.runner.RemoteTestRunner.getTestName",
          "source": "RemoteTestRunner.java:616"
        },
        {
          "method": "org.eclipse.jdt.internal.junit.runner.RemoteTestRunner.sendTree",
          "source": "RemoteTestRunner.java:589"
        },
        {
          "method": "org.eclipse.jdt.internal.junit.runner.RemoteTestRunner.sendTree",
          "source": "RemoteTestRunner.java:585"
        },
        {
          "method": "org.eclipse.jdt.internal.junit.runner.RemoteTestRunner.runTests",
          "source": "RemoteTestRunner.java:414"
        },
        {
          "method": "org.eclipse.jdt.internal.junit.runner.RemoteTestRunner.run",
          "source": "RemoteTestRunner.java:305"
        },
        {
          "method": "org.eclipse.jdt.internal.junit.runner.RemoteTestRunner.main",
          "source": "RemoteTestRunner.java:186"
        }
      ],
      "number": 0,
      "commentIndex": 0,
      "bugId": "70309",
      "date": "2004-07-19T09:32:42+02:00",
      "product": "JDT",
      "component": "UI",
      "severity": "normal"
    }
  ],
  "groupId": "70309",
  "bugId": "70309",
  "date": "2004-07-19T09:32:42+02:00",
  "product": "JDT",
  "component": "UI",
  "severity": "normal"
}