{
  "comments": [
    "When trying to open a .class file through the Open External File dialog, I get\nthe following error spewed to my Terminal window:\n\norg.eclipse.ui.PartInitException: Class File Viewer\n        at\norg.eclipse.ui.texteditor.AbstractTextEditor.internalInit(AbstractTextEditor.java:2251)\n        at\norg.eclipse.ui.texteditor.AbstractTextEditor.init(AbstractTextEditor.java:2264)\n        at org.eclipse.ui.internal.EditorManager.createSite(EditorManager.java:721)\n        at\norg.eclipse.ui.internal.EditorManager.openInternalEditor(EditorManager.java:780)\n        at\norg.eclipse.ui.internal.EditorManager.openEditorFromDescriptor(EditorManager.java:585)\n        at org.eclipse.ui.internal.EditorManager.openEditor(EditorManager.java:573)\n        at\norg.eclipse.ui.internal.WorkbenchPage.busyOpenEditorBatched(WorkbenchPage.java:2201)\n        at\norg.eclipse.ui.internal.WorkbenchPage.busyOpenEditor(WorkbenchPage.java:2134)\n        at org.eclipse.ui.internal.WorkbenchPage.access$6(WorkbenchPage.java:2126)\n        at org.eclipse.ui.internal.WorkbenchPage$9.run(WorkbenchPage.java:2113)\n        at org.eclipse.swt.custom.BusyIndicator.showWhile(BusyIndicator.java:69)\n        at org.eclipse.ui.internal.WorkbenchPage.openEditor(WorkbenchPage.java:2108)\n        at org.eclipse.ui.internal.WorkbenchPage.openEditor(WorkbenchPage.java:2091)\n        at\norg.eclipse.ui.internal.editors.text.OpenExternalFileAction.run(OpenExternalFileAction.java:115)\n        at\norg.eclipse.ui.internal.editors.text.OpenExternalFileAction.run(OpenExternalFileAction.java:87)\n        at org.eclipse.ui.internal.PluginAction.runWithEvent(PluginAction.java:276)\n        at\norg.eclipse.ui.internal.WWinPluginAction.runWithEvent(WWinPluginAction.java:206)\n        at\norg.eclipse.jface.action.ActionContributionItem.handleWidgetSelection(ActionContributionItem.java:915)\n        at\norg.eclipse.jface.action.ActionContributionItem.access$2(ActionContributionItem.java:866)\n        at\norg.eclipse.jface.action.ActionContributionItem$7.handleEvent(ActionContributionItem.java:785)\n        at org.eclipse.swt.widgets.EventTable.sendEvent(EventTable.java:82)\n        at org.eclipse.swt.widgets.Widget.sendEvent(Widget.java:731)\n        at org.eclipse.swt.widgets.Display.runDeferredEvents(Display.java:2938)\n        at org.eclipse.swt.widgets.Display.readAndDispatch(Display.java:2642)\n        at org.eclipse.ui.internal.Workbench.runEventLoop(Workbench.java:1377)\n        at org.eclipse.ui.internal.Workbench.runUI(Workbench.java:1348)\n        at\norg.eclipse.ui.internal.Workbench.createAndRunWorkbench(Workbench.java:254)\n        at org.eclipse.ui.PlatformUI.createAndRunWorkbench(PlatformUI.java:141)\n        at org.eclipse.ui.internal.ide.IDEApplication.run(IDEApplication.java:96)\n        at\norg.eclipse.core.internal.runtime.PlatformActivator$1.run(PlatformActivator.java:335)\n        at\norg.eclipse.core.runtime.adaptor.EclipseStarter.run(EclipseStarter.java:273)\n        at\norg.eclipse.core.runtime.adaptor.EclipseStarter.run(EclipseStarter.java:129)\n        at sun.reflect.NativeMethodAccessorImpl.invoke0(Native Method)\n        at sun.reflect.NativeMethodAccessorImpl.invoke(Unknown Source)\n        at sun.reflect.DelegatingMethodAccessorImpl.invoke(Unknown Source)\n        at java.lang.reflect.Method.invoke(Unknown Source)\n        at org.eclipse.core.launcher.Main.basicRun(Main.java:183)\n        at org.eclipse.core.launcher.Main.run(Main.java:644)\n        at org.eclipse.core.launcher.Main.main(Main.java:628)",
    "Cannot reproduce using R3.0. What I see is that nothing happens (see bug 58179)\ni.e. no editor is opened, nothing in .log and nothing in .console.\n\n\n*** This bug has been marked as a duplicate of 58179 ***",
    "Not a duplicate since the real problem here is the Java Model not supporting the\nexternal files.",
    "*** Bug 111049 has been marked as a duplicate of this bug. ***",
    "There would now be a dialog but this is currently not working due to bug 112277.",
    "*** Bug 112681 has been marked as a duplicate of this bug. ***"
  ],
  "commentCreationDates": [
    "2004-07-19T16:58:47+02:00",
    "2004-07-19T17:22:57+02:00",
    "2005-09-22T16:24:16+02:00",
    "2005-10-03T14:45:04+02:00",
    "2005-10-17T10:16:56+02:00",
    "2005-10-17T10:17:00+02:00"
  ],
  "traces": [
    {
      "exceptionType": "org.eclipse.ui.PartInitException",
      "message": "Class File Viewer",
      "elements": [
        {
          "method": "org.eclipse.ui.texteditor.AbstractTextEditor.internalInit",
          "source": "AbstractTextEditor.java:2251"
        },
        {
          "method": "org.eclipse.ui.texteditor.AbstractTextEditor.init",
          "source": "AbstractTextEditor.java:2264"
        },
        {
          "method": "org.eclipse.ui.internal.EditorManager.createSite",
          "source": "EditorManager.java:721"
        },
        {
          "method": "org.eclipse.ui.internal.EditorManager.openInternalEditor",
          "source": "EditorManager.java:780"
        },
        {
          "method": "org.eclipse.ui.internal.EditorManager.openEditorFromDescriptor",
          "source": "EditorManager.java:585"
        },
        {
          "method": "org.eclipse.ui.internal.EditorManager.openEditor",
          "source": "EditorManager.java:573"
        },
        {
          "method": "org.eclipse.ui.internal.WorkbenchPage.busyOpenEditorBatched",
          "source": "WorkbenchPage.java:2201"
        },
        {
          "method": "org.eclipse.ui.internal.WorkbenchPage.busyOpenEditor",
          "source": "WorkbenchPage.java:2134"
        },
        {
          "method": "org.eclipse.ui.internal.WorkbenchPage.access$6",
          "source": "WorkbenchPage.java:2126"
        },
        {
          "method": "org.eclipse.ui.internal.WorkbenchPage$9.run",
          "source": "WorkbenchPage.java:2113"
        },
        {
          "method": "org.eclipse.swt.custom.BusyIndicator.showWhile",
          "source": "BusyIndicator.java:69"
        },
        {
          "method": "org.eclipse.ui.internal.WorkbenchPage.openEditor",
          "source": "WorkbenchPage.java:2108"
        },
        {
          "method": "org.eclipse.ui.internal.WorkbenchPage.openEditor",
          "source": "WorkbenchPage.java:2091"
        },
        {
          "method": "org.eclipse.ui.internal.editors.text.OpenExternalFileAction.run",
          "source": "OpenExternalFileAction.java:115"
        },
        {
          "method": "org.eclipse.ui.internal.editors.text.OpenExternalFileAction.run",
          "source": "OpenExternalFileAction.java:87"
        },
        {
          "method": "org.eclipse.ui.internal.PluginAction.runWithEvent",
          "source": "PluginAction.java:276"
        },
        {
          "method": "org.eclipse.ui.internal.WWinPluginAction.runWithEvent",
          "source": "WWinPluginAction.java:206"
        },
        {
          "method": "org.eclipse.jface.action.ActionContributionItem.handleWidgetSelection",
          "source": "ActionContributionItem.java:915"
        },
        {
          "method": "org.eclipse.jface.action.ActionContributionItem.access$2",
          "source": "ActionContributionItem.java:866"
        },
        {
          "method": "org.eclipse.jface.action.ActionContributionItem$7.handleEvent",
          "source": "ActionContributionItem.java:785"
        },
        {
          "method": "org.eclipse.swt.widgets.EventTable.sendEvent",
          "source": "EventTable.java:82"
        },
        {
          "method": "org.eclipse.swt.widgets.Widget.sendEvent",
          "source": "Widget.java:731"
        },
        {
          "method": "org.eclipse.swt.widgets.Display.runDeferredEvents",
          "source": "Display.java:2938"
        },
        {
          "method": "org.eclipse.swt.widgets.Display.readAndDispatch",
          "source": "Display.java:2642"
        },
        {
          "method": "org.eclipse.ui.internal.Workbench.runEventLoop",
          "source": "Workbench.java:1377"
        },
        {
          "method": "org.eclipse.ui.internal.Workbench.runUI",
          "source": "Workbench.java:1348"
        },
        {
          "method": "org.eclipse.ui.internal.Workbench.createAndRunWorkbench",
          "source": "Workbench.java:254"
        },
        {
          "method": "org.eclipse.ui.PlatformUI.createAndRunWorkbench",
          "source": "PlatformUI.java:141"
        },
        {
          "method": "org.eclipse.ui.internal.ide.IDEApplication.run",
          "source": "IDEApplication.java:96"
        },
        {
          "method": "org.eclipse.core.internal.runtime.PlatformActivator$1.run",
          "source": "PlatformActivator.java:335"
        },
        {
          "method": "org.eclipse.core.runtime.adaptor.EclipseStarter.run",
          "source": "EclipseStarter.java:273"
        },
        {
          "method": "org.eclipse.core.runtime.adaptor.EclipseStarter.run",
          "source": "EclipseStarter.java:129"
        },
        {
          "method": "sun.reflect.NativeMethodAccessorImpl.invoke0",
          "source": "Native Method"
        },
        {
          "method": "sun.reflect.NativeMethodAccessorImpl.invoke",
          "source": "Unknown Source"
        },
        {
          "method": "sun.reflect.DelegatingMethodAccessorImpl.invoke",
          "source": "Unknown Source"
        },
        {
          "method": "java.lang.reflect.Method.invoke",
          "source": "Unknown Source"
        },
        {
          "method": "org.eclipse.core.launcher.Main.basicRun",
          "source": "Main.java:183"
        },
        {
          "method": "org.eclipse.core.launcher.Main.run",
          "source": "Main.java:644"
        },
        {
          "method": "org.eclipse.core.launcher.Main.main",
          "source": "Main.java:628"
        }
      ],
      "number": 0,
      "commentIndex": 0,
      "bugId": "70347",
      "date": "2004-07-19T16:58:47+02:00",
      "product": "Platform",
      "component": "Text",
      "severity": "minor"
    }
  ],
  "groupId": "70347",
  "bugId": "70347",
  "date": "2004-07-19T16:58:47+02:00",
  "product": "Platform",
  "component": "Text",
  "severity": "minor"
}