{
  "comments": [
    "In the 20011217 build, if you attempt to rename a java source, you get the \nfollowing exception:\n\norg.eclipse.jface.util.Assert$AssertionFailedException: null argument;Must \ncall initializeDialogUnits before calling this method\n        at org.eclipse.jface.util.Assert.isNotNull(Assert.java:133)\n        at org.eclipse.jface.dialogs.DialogPage.convertWidthInCharsToPixels\n(DialogPage.java:157)\n        at \norg.eclipse.jdt.internal.ui.refactoring.ErrorWizardPage.createTableViewer\n(ErrorWizardPage.java:226)\n        at \norg.eclipse.jdt.internal.ui.refactoring.ErrorWizardPage.createControl\n(ErrorWizardPage.java:203)\n        at org.eclipse.jface.wizard.Wizard.createPageControls(Wizard.java:164)\n        at org.eclipse.jface.wizard.WizardDialog.createPageControls\n(WizardDialog.java:504)\n        at org.eclipse.jface.wizard.WizardDialog.createContents\n(WizardDialog.java:455)\n        at org.eclipse.jface.window.Window.create(Window.java:237)\n        at org.eclipse.jface.window.Window.open(Window.java:510)\n        at \norg.eclipse.jdt.internal.ui.refactoring.actions.RefactoringAction.activateRefac\ntoringWizard(RefactoringAction.java:111)\n        at \norg.eclipse.jdt.internal.ui.reorg.RefactoringSupportFactory$RenameSupport.renam\ne(RefactoringSupportFactory.java:57)\n        at org.eclipse.jdt.internal.ui.reorg.RenameAction.run\n(RenameAction.java:36)\n        at org.eclipse.jface.action.Action.runWithEvent(Action.java:452)\n        at \norg.eclipse.jface.action.ActionContributionItem.handleWidgetSelection\n(ActionContributionItem.java:407)\n        at org.eclipse.jface.action.ActionContributionItem.handleWidgetEvent\n(ActionContributionItem.java:361)\n        at org.eclipse.jface.action.ActionContributionItem.access$0\n(ActionContributionItem.java:352)\n        at \norg.eclipse.jface.action.ActionContributionItem$ActionListener.handleEvent\n(ActionContributionItem.java:47)\n        at org.eclipse.swt.widgets.EventTable.sendEvent(EventTable.java\n(Compiled Code))\n        at org.eclipse.swt.widgets.Widget.notifyListeners(Widget.java(Compiled \nCode))\n        at org.eclipse.swt.widgets.Display.runDeferredEvents(Display.java\n(Compiled Code))\n        at org.eclipse.swt.widgets.Display.readAndDispatch(Display.java\n(Compiled Code))\n        at org.eclipse.ui.internal.Workbench.runEventLoop(Workbench.java\n(Compiled Code))\n        at org.eclipse.ui.internal.Workbench.run(Workbench.java:762)\n        at org.eclipse.core.internal.boot.InternalBootLoader.run\n(InternalBootLoader.java:820)\n        at org.eclipse.core.boot.BootLoader.run(BootLoader.java:285)\n        at java.lang.reflect.Method.invoke(Native Method)\n        at org.eclipse.core.launcher.Main.basicRun(Main.java:151)\n        at org.eclipse.core.launcher.Main.run(Main.java:502)\n        at org.eclipse.core.launcher.Main.main(Main.java:362)",
    "pls see: 7039. The assertion will be removed for the 20011217 integration build.\nHowever, should adapt our code to make it conform to the wizard API spec.",
    "Added call initializeDialogUnits to conform to new API."
  ],
  "commentCreationDates": [
    "2001-12-18T15:17:11+01:00",
    "2001-12-18T16:07:11+01:00",
    "2002-01-17T17:08:47+01:00"
  ],
  "traces": [
    {
      "exceptionType": "org.eclipse.jface.util.Assert$AssertionFailedException",
      "message": "null argument;Must  call initializeDialogUnits before calling this method",
      "elements": [
        {
          "method": "org.eclipse.jface.util.Assert.isNotNull",
          "source": "Assert.java:133"
        },
        {
          "method": "org.eclipse.jface.dialogs.DialogPage.convertWidthInCharsToPixels",
          "source": "DialogPage.java:157"
        },
        {
          "method": "org.eclipse.jdt.internal.ui.refactoring.ErrorWizardPage.createTableViewer",
          "source": "ErrorWizardPage.java:226"
        },
        {
          "method": "org.eclipse.jdt.internal.ui.refactoring.ErrorWizardPage.createControl",
          "source": "ErrorWizardPage.java:203"
        },
        {
          "method": "org.eclipse.jface.wizard.Wizard.createPageControls",
          "source": "Wizard.java:164"
        },
        {
          "method": "org.eclipse.jface.wizard.WizardDialog.createPageControls",
          "source": "WizardDialog.java:504"
        },
        {
          "method": "org.eclipse.jface.wizard.WizardDialog.createContents",
          "source": "WizardDialog.java:455"
        },
        {
          "method": "org.eclipse.jface.window.Window.create",
          "source": "Window.java:237"
        },
        {
          "method": "org.eclipse.jface.window.Window.open",
          "source": "Window.java:510"
        },
        {
          "method": "org.eclipse.jdt.internal.ui.refactoring.actions.RefactoringAction.activateRefactoringWizard",
          "source": "RefactoringAction.java:111"
        },
        {
          "method": "org.eclipse.jdt.internal.ui.reorg.RefactoringSupportFactory$RenameSupport.rename",
          "source": "RefactoringSupportFactory.java:57"
        },
        {
          "method": "org.eclipse.jdt.internal.ui.reorg.RenameAction.run",
          "source": "RenameAction.java:36"
        },
        {
          "method": "org.eclipse.jface.action.Action.runWithEvent",
          "source": "Action.java:452"
        },
        {
          "method": "org.eclipse.jface.action.ActionContributionItem.handleWidgetSelection",
          "source": "ActionContributionItem.java:407"
        },
        {
          "method": "org.eclipse.jface.action.ActionContributionItem.handleWidgetEvent",
          "source": "ActionContributionItem.java:361"
        },
        {
          "method": "org.eclipse.jface.action.ActionContributionItem.access$0",
          "source": "ActionContributionItem.java:352"
        },
        {
          "method": "org.eclipse.jface.action.ActionContributionItem$ActionListener.handleEvent",
          "source": "ActionContributionItem.java:47"
        },
        {
          "method": "org.eclipse.swt.widgets.EventTable.sendEvent",
          "source": "EventTable.java (Compiled Code)"
        },
        {
          "method": "org.eclipse.swt.widgets.Widget.notifyListeners",
          "source": "Widget.java(Compiled  Code)"
        },
        {
          "method": "org.eclipse.swt.widgets.Display.runDeferredEvents",
          "source": "Display.java (Compiled Code)"
        },
        {
          "method": "org.eclipse.swt.widgets.Display.readAndDispatch",
          "source": "Display.java (Compiled Code)"
        },
        {
          "method": "org.eclipse.ui.internal.Workbench.runEventLoop",
          "source": "Workbench.java (Compiled Code)"
        },
        {
          "method": "org.eclipse.ui.internal.Workbench.run",
          "source": "Workbench.java:762"
        },
        {
          "method": "org.eclipse.core.internal.boot.InternalBootLoader.run",
          "source": "InternalBootLoader.java:820"
        },
        {
          "method": "org.eclipse.core.boot.BootLoader.run",
          "source": "BootLoader.java:285"
        },
        {
          "method": "java.lang.reflect.Method.invoke",
          "source": "Native Method"
        },
        {
          "method": "org.eclipse.core.launcher.Main.basicRun",
          "source": "Main.java:151"
        },
        {
          "method": "org.eclipse.core.launcher.Main.run",
          "source": "Main.java:502"
        },
        {
          "method": "org.eclipse.core.launcher.Main.main",
          "source": "Main.java:362"
        }
      ],
      "number": 0,
      "commentIndex": 0,
      "bugId": "7041",
      "date": "2001-12-18T15:17:11+01:00",
      "product": "JDT",
      "component": "UI",
      "severity": "normal"
    }
  ],
  "groupId": "7041",
  "bugId": "7041",
  "date": "2001-12-18T15:17:11+01:00",
  "product": "JDT",
  "component": "UI",
  "severity": "normal"
}