{
  "comments": [
    "It seems to load the library fine, and mozilla itself runs fine as well, but \nwhen using the browser widget I get the error below. Even worse is that \nEclipse doesn\u0027t start up if a view in the default perspective is causing this \nerror; it seems like it is never caught and causes the whole application not \nto start up.. \n \n \norg.eclipse.swt.SWTError: No more handles [Unknown mozilla path] \n        at org.eclipse.swt.SWT.error(SWT.java:2717) \n        at org.eclipse.swt.browser.Browser.\u003cinit\u003e(Browser.java:128) \n        at \ncom.lombardisoftware.client.ae.forms.bpd.simulation.views.SimulationAnalysisView.createPartControl(SimulationAnalysisView.java:85) \n        at org.eclipse.ui.internal.PartPane$2.run(PartPane.java:137) \n        at \norg.eclipse.core.internal.runtime.InternalPlatform.run(InternalPlatform.java:615) \n        at org.eclipse.core.runtime.Platform.run(Platform.java:747) \n        at \norg.eclipse.ui.internal.PartPane.createChildControl(PartPane.java:133) \n        at \norg.eclipse.ui.internal.ViewPane.createChildControl(ViewPane.java:131) \n        at org.eclipse.ui.internal.ViewFactory$1.run(ViewFactory.java:337) \n        at \norg.eclipse.core.internal.runtime.InternalPlatform.run(InternalPlatform.java:615) \n        at org.eclipse.core.runtime.Platform.run(Platform.java:747) \n        at \norg.eclipse.ui.internal.ViewFactory.busyRestoreView(ViewFactory.java:259) \n        at org.eclipse.ui.internal.ViewFactory$2.run(ViewFactory.java:516) \n        at \norg.eclipse.swt.custom.BusyIndicator.showWhile(BusyIndicator.java:69) \n        at \norg.eclipse.ui.internal.ViewFactory.restoreView(ViewFactory.java:514) \n        at \norg.eclipse.ui.internal.ViewFactory$ViewReference.getPart(ViewFactory.java:102) \n        at \norg.eclipse.ui.internal.WorkbenchPage$1.propertyChange(WorkbenchPage.java:132) \n        at org.eclipse.ui.internal.LayoutPart.setVisible(LayoutPart.java:268)",
    "It failed because the location of the Mozilla distribution was not found. I \nhave some questions for you below.\n\nSome general info first: the SWT FAQ contains info regarding this kind of \nissue:\n\n- What do I need to run the SWT Browser inside Eclipse on Linux GTK or Linux \nMotif?\nhttp://dev.eclipse.org/viewcvs/index.cgi/%7Echeckout%7E/platform-swt-\nhome/faq.html#browserlinux\n\n- What do I need to run the SWT Browser in a standalone application on Linux \nGTK or Linux Motif?\nhttp://dev.eclipse.org/viewcvs/index.cgi/%7Echeckout%7E/platform-swt-\nhome/faq.html#browserlinuxrcp\n\nNow let\u0027s see.\n\n1. Which Linux distribution are you using?\n2. Do you start Eclipse through the eclipse launcher or through the java \ncommand line?\n3. How and where did you install Mozilla 1.6?\n\nIf your Mozilla 1.6 is installed in /usr/lib/mozilla-1.6, you can try the \nfollowing:\n- open a terminal\n- setenv MOZILLA_FIVE_HOME /usr/lib/mozilla-1.6  (for cshell users)\n- eclipse\n\nYou should go further. Please let us know about 1. 2. and 3. to help us \nunderstand what is happening.",
    "MOZILLA_FIVE_HOME did the trick. I\u0027ve just never had to-do that step before. \n \nThe problem occured when installing SuSE 9.1. It worked fine with both RedHat \n9 and SuSe 9.0 without setting any additional parameters. But I probably \ninstalled an RPM of Mozilla which set that up, and I couldn\u0027t use the SuSE 9.1 \nRPM because the version number was too high (they ship with Mozilla 1.7 which \nSWT also didn\u0027t like).... \n \n ",
    "RH9 and Suse9 both come with a supported version of Mozilla (1.4GTK2). In \naddition, these 2 platforms set a config file /etc/gre.conf that specify the \nlocation of Mozilla. This file is found by the eclipse launcher to \nautomatically set MOZILLA_FIVE_HOME and LD_LIBRARY_PATH correctly. So that\u0027s \nwhy it was working before. When this file is not there - or to override it - \nMOZILLA_FIVE_HOME must be set.\n\nFor Mozilla 1.7, you can monitor bug 61384 for updates.\n\nCan you confirm Suse 9.1 comes with Mozilla 1.7? Thanks!\n\n"
  ],
  "commentCreationDates": [
    "2004-07-24T18:48:20+02:00",
    "2004-08-05T17:56:42+02:00",
    "2004-08-20T17:42:31+02:00",
    "2004-08-23T18:16:48+02:00"
  ],
  "traces": [
    {
      "exceptionType": "org.eclipse.swt.SWTError",
      "message": "No more handles [Unknown mozilla path]",
      "elements": [
        {
          "method": "org.eclipse.swt.SWT.error",
          "source": "SWT.java:2717"
        },
        {
          "method": "org.eclipse.swt.browser.Browser.\u003cinit\u003e",
          "source": "Browser.java:128"
        },
        {
          "method": "com.lombardisoftware.client.ae.forms.bpd.simulation.views.SimulationAnalysisView.createPartControl",
          "source": "SimulationAnalysisView.java:85"
        },
        {
          "method": "org.eclipse.ui.internal.PartPane$2.run",
          "source": "PartPane.java:137"
        },
        {
          "method": "org.eclipse.core.internal.runtime.InternalPlatform.run",
          "source": "InternalPlatform.java:615"
        },
        {
          "method": "org.eclipse.core.runtime.Platform.run",
          "source": "Platform.java:747"
        },
        {
          "method": "org.eclipse.ui.internal.PartPane.createChildControl",
          "source": "PartPane.java:133"
        },
        {
          "method": "org.eclipse.ui.internal.ViewPane.createChildControl",
          "source": "ViewPane.java:131"
        },
        {
          "method": "org.eclipse.ui.internal.ViewFactory$1.run",
          "source": "ViewFactory.java:337"
        },
        {
          "method": "org.eclipse.core.internal.runtime.InternalPlatform.run",
          "source": "InternalPlatform.java:615"
        },
        {
          "method": "org.eclipse.core.runtime.Platform.run",
          "source": "Platform.java:747"
        },
        {
          "method": "org.eclipse.ui.internal.ViewFactory.busyRestoreView",
          "source": "ViewFactory.java:259"
        },
        {
          "method": "org.eclipse.ui.internal.ViewFactory$2.run",
          "source": "ViewFactory.java:516"
        },
        {
          "method": "org.eclipse.swt.custom.BusyIndicator.showWhile",
          "source": "BusyIndicator.java:69"
        },
        {
          "method": "org.eclipse.ui.internal.ViewFactory.restoreView",
          "source": "ViewFactory.java:514"
        },
        {
          "method": "org.eclipse.ui.internal.ViewFactory$ViewReference.getPart",
          "source": "ViewFactory.java:102"
        },
        {
          "method": "org.eclipse.ui.internal.WorkbenchPage$1.propertyChange",
          "source": "WorkbenchPage.java:132"
        },
        {
          "method": "org.eclipse.ui.internal.LayoutPart.setVisible",
          "source": "LayoutPart.java:268"
        }
      ],
      "number": 0,
      "commentIndex": 0,
      "bugId": "70779",
      "date": "2004-07-24T18:48:20+02:00",
      "product": "Platform",
      "component": "SWT",
      "severity": "major"
    }
  ],
  "groupId": "70779",
  "bugId": "70779",
  "date": "2004-07-24T18:48:20+02:00",
  "product": "Platform",
  "component": "SWT",
  "severity": "major"
}