{
  "comments": [
    "20011218\n\nTry to format my java source:\njava.lang.Error: Unresolved compilation problem: \n        The method format() in the type \norg.eclipse.jdt.internal.formatter.CodeFormatter is not applicable for the \narguments (java.lang.String, int, int[])\n\n        at java.lang.reflect.Constructor.newInstance(Native Method)\n        at org.eclipse.jdt.internal.ui.text.java.JavaFormattingStrategy.format\n(JavaFormattingStrategy.java:54)\n        at org.eclipse.jface.text.formatter.ContentFormatter.format\n(ContentFormatter.java:425)\n        at org.eclipse.jface.text.formatter.ContentFormatter.formatRegion\n(ContentFormatter.java:336)\n        at org.eclipse.jface.text.formatter.ContentFormatter.format\n(ContentFormatter.java:300)\n        at org.eclipse.jface.text.source.SourceViewer.doOperation\n(SourceViewer.java:385)\n        at org.eclipse.ui.texteditor.TextOperationAction.run\n(TextOperationAction.java:61)\n        at org.eclipse.jface.action.Action.runWithEvent(Action.java:452)\n        at \norg.eclipse.jface.action.ActionContributionItem.handleWidgetSelection\n(ActionContributionItem.java:407)\n        at org.eclipse.jface.action.ActionContributionItem.handleWidgetEvent\n(ActionContributionItem.java:361)\n        at org.eclipse.jface.action.ActionContributionItem.access$0\n(ActionContributionItem.java:352)\n        at \norg.eclipse.jface.action.ActionContributionItem$ActionListener.handleEvent\n(ActionContributionItem.java:47)\n        at org.eclipse.swt.widgets.EventTable.sendEvent(EventTable.java\n(Compiled Code))\n        at org.eclipse.swt.widgets.Widget.notifyListeners(Widget.java(Compiled \nCode))\n        at org.eclipse.swt.widgets.Display.runDeferredEvents(Display.java\n(Compiled Code))\n        at org.eclipse.swt.widgets.Display.readAndDispatch(Display.java\n(Compiled Code))\n        at org.eclipse.ui.internal.Workbench.runEventLoop(Workbench.java\n(Compiled Code))\n        at org.eclipse.ui.internal.Workbench.run(Workbench.java:798)\n        at org.eclipse.core.internal.boot.InternalBootLoader.run\n(InternalBootLoader.java:821)\n        at org.eclipse.core.boot.BootLoader.run(BootLoader.java:285)\n        at java.lang.reflect.Method.invoke(Native Method)\n        at org.eclipse.core.launcher.Main.basicRun(Main.java:151)\n        at org.eclipse.core.launcher.Main.run(Main.java:502)\n        at org.eclipse.core.launcher.Main.main(Main.java:362)",
    "Formatter belongs to Java Core. Moving",
    "Do you still have the problem with latest stable? I don\u0027t think so. If not, I will close this one.\n",
    "haven\u0027t seen the problem since.",
    "Closed.",
    "Changing Milestone."
  ],
  "commentCreationDates": [
    "2001-12-19T03:47:20+01:00",
    "2002-01-10T13:45:53+01:00",
    "2002-03-25T22:26:16+01:00",
    "2002-03-25T22:53:08+01:00",
    "2002-03-26T16:21:49+01:00",
    "2002-03-27T21:41:22+01:00"
  ],
  "traces": [
    {
      "exceptionType": "java.lang.Error",
      "message": "Unresolved compilation problem:          The method format() in the type  org.eclipse.jdt.internal.formatter.CodeFormatter is not applicable for the  arguments (java.lang.String, int, int[])",
      "elements": [
        {
          "method": "java.lang.reflect.Constructor.newInstance",
          "source": "Native Method"
        },
        {
          "method": "org.eclipse.jdt.internal.ui.text.java.JavaFormattingStrategy.format",
          "source": "JavaFormattingStrategy.java:54"
        },
        {
          "method": "org.eclipse.jface.text.formatter.ContentFormatter.format",
          "source": "ContentFormatter.java:425"
        },
        {
          "method": "org.eclipse.jface.text.formatter.ContentFormatter.formatRegion",
          "source": "ContentFormatter.java:336"
        },
        {
          "method": "org.eclipse.jface.text.formatter.ContentFormatter.format",
          "source": "ContentFormatter.java:300"
        },
        {
          "method": "org.eclipse.jface.text.source.SourceViewer.doOperation",
          "source": "SourceViewer.java:385"
        },
        {
          "method": "org.eclipse.ui.texteditor.TextOperationAction.run",
          "source": "TextOperationAction.java:61"
        },
        {
          "method": "org.eclipse.jface.action.Action.runWithEvent",
          "source": "Action.java:452"
        },
        {
          "method": "org.eclipse.jface.action.ActionContributionItem.handleWidgetSelection",
          "source": "ActionContributionItem.java:407"
        },
        {
          "method": "org.eclipse.jface.action.ActionContributionItem.handleWidgetEvent",
          "source": "ActionContributionItem.java:361"
        },
        {
          "method": "org.eclipse.jface.action.ActionContributionItem.access$0",
          "source": "ActionContributionItem.java:352"
        },
        {
          "method": "org.eclipse.jface.action.ActionContributionItem$ActionListener.handleEvent",
          "source": "ActionContributionItem.java:47"
        },
        {
          "method": "org.eclipse.swt.widgets.EventTable.sendEvent",
          "source": "EventTable.java (Compiled Code)"
        },
        {
          "method": "org.eclipse.swt.widgets.Widget.notifyListeners",
          "source": "Widget.java(Compiled  Code)"
        },
        {
          "method": "org.eclipse.swt.widgets.Display.runDeferredEvents",
          "source": "Display.java (Compiled Code)"
        },
        {
          "method": "org.eclipse.swt.widgets.Display.readAndDispatch",
          "source": "Display.java (Compiled Code)"
        },
        {
          "method": "org.eclipse.ui.internal.Workbench.runEventLoop",
          "source": "Workbench.java (Compiled Code)"
        },
        {
          "method": "org.eclipse.ui.internal.Workbench.run",
          "source": "Workbench.java:798"
        },
        {
          "method": "org.eclipse.core.internal.boot.InternalBootLoader.run",
          "source": "InternalBootLoader.java:821"
        },
        {
          "method": "org.eclipse.core.boot.BootLoader.run",
          "source": "BootLoader.java:285"
        },
        {
          "method": "java.lang.reflect.Method.invoke",
          "source": "Native Method"
        },
        {
          "method": "org.eclipse.core.launcher.Main.basicRun",
          "source": "Main.java:151"
        },
        {
          "method": "org.eclipse.core.launcher.Main.run",
          "source": "Main.java:502"
        },
        {
          "method": "org.eclipse.core.launcher.Main.main",
          "source": "Main.java:362"
        }
      ],
      "number": 0,
      "commentIndex": 0,
      "bugId": "7079",
      "date": "2001-12-19T03:47:20+01:00",
      "product": "JDT",
      "component": "UI",
      "severity": "normal"
    }
  ],
  "groupId": "7079",
  "bugId": "7079",
  "date": "2001-12-19T03:47:20+01:00",
  "product": "JDT",
  "component": "UI",
  "severity": "normal"
}