{
  "comments": [
    "Eclipse: 20040728\nLinux: fedora-core-1\n\nThe stack below is produced every time I open a closed project.\n\n\n!ENTRY org.eclipse.ui 4 4 Aug 03, 2004 16:03:17.82\n!MESSAGE Unhandled event loop exception\n\n!ENTRY org.eclipse.ui 4 0 Aug 03, 2004 16:03:17.82\n!MESSAGE java.lang.OutOfMemoryError\n!STACK 0\njava.lang.OutOfMemoryError\n\n!ENTRY org.eclipse.osgi Aug 03, 2004 16:03:36.482\n!MESSAGE Error while stopping \"org.eclipse.jdt.core_3.0.1\".\n!STACK 0\norg.osgi.framework.BundleException: Exception in\norg.eclipse.jdt.core.JavaCore.stop() of bundle org.eclipse.jdt.core.\n        at\norg.eclipse.osgi.framework.internal.core.BundleContextImpl.stop(BundleContextImpl.java:1010)\n        at\norg.eclipse.osgi.framework.internal.core.BundleHost.stopWorker(BundleHost.java:502)\n        at\norg.eclipse.osgi.framework.internal.core.AbstractBundle.stop(AbstractBundle.java:437)\n        at\norg.eclipse.core.runtime.adaptor.BundleStopper.basicStopBundles(BundleStopper.java:75)\n        at\norg.eclipse.core.runtime.adaptor.BundleStopper.stopBundles(BundleStopper.java:62)\n        at\norg.eclipse.core.runtime.adaptor.EclipseAdaptor.frameworkStopping(EclipseAdaptor.java:551)\n        at\norg.eclipse.osgi.framework.internal.core.Framework.shutdown(Framework.java:457)\n        at\norg.eclipse.osgi.framework.internal.core.SystemBundle$1.run(SystemBundle.java:182)\n        at java.lang.Thread.run(Thread.java:534)\nCaused by: java.lang.NullPointerException\n        at\norg.eclipse.jdt.internal.core.search.processing.JobManager.discardJobs(JobManager.java:110)\n        at\norg.eclipse.jdt.internal.core.search.processing.JobManager.shutdown(JobManager.java:407)\n        at\norg.eclipse.jdt.internal.core.JavaModelManager.shutdown(JavaModelManager.java:1833)\n        at org.eclipse.jdt.core.JavaCore.stop(JavaCore.java:3601)\n        at\norg.eclipse.osgi.framework.internal.core.BundleContextImpl$2.run(BundleContextImpl.java:994)\n        at java.security.AccessController.doPrivileged(Native Method)\n        at\norg.eclipse.osgi.framework.internal.core.BundleContextImpl.stop(BundleContextImpl.java:990)\n        ... 8 more\nRoot exception:\njava.lang.NullPointerException\n        at\norg.eclipse.jdt.internal.core.search.processing.JobManager.discardJobs(JobManager.java:110)\n        at\norg.eclipse.jdt.internal.core.search.processing.JobManager.shutdown(JobManager.java:407)\n        at\norg.eclipse.jdt.internal.core.JavaModelManager.shutdown(JavaModelManager.java:1833)\n        at org.eclipse.jdt.core.JavaCore.stop(JavaCore.java:3601)\n        at\norg.eclipse.osgi.framework.internal.core.BundleContextImpl$2.run(BundleContextImpl.java:994)\n        at java.security.AccessController.doPrivileged(Native Method)\n        at\norg.eclipse.osgi.framework.internal.core.BundleContextImpl.stop(BundleContextImpl.java:990)\n        at\norg.eclipse.osgi.framework.internal.core.BundleHost.stopWorker(BundleHost.java:502)\n        at\norg.eclipse.osgi.framework.internal.core.AbstractBundle.stop(AbstractBundle.java:437)\n        at\norg.eclipse.core.runtime.adaptor.BundleStopper.basicStopBundles(BundleStopper.java:75)\n        at\norg.eclipse.core.runtime.adaptor.BundleStopper.stopBundles(BundleStopper.java:62)\n        at\norg.eclipse.core.runtime.adaptor.EclipseAdaptor.frameworkStopping(EclipseAdaptor.java:551)\n        at\norg.eclipse.osgi.framework.internal.core.Framework.shutdown(Framework.java:457)\n        at\norg.eclipse.osgi.framework.internal.core.SystemBundle$1.run(SystemBundle.java:182)\n        at java.lang.Thread.run(Thread.java:534)\n~",
    "The stack trace is from shutting down eclipse... are you sure its \nreproduceable when you open a closed project?\n\nWhat command line do you use to start eclipse? Do you increase the VM memory \nargs?",
    "I start eclipse with -Xmx256m -Xms64m\n\nI reopened the offending project this morning and looked at the progress view\ndetails. I saw that the Java indexing service is where it spends a great deal of\ntime, indexing about 1 file / second (and apparently getting slower over time).\nWhen that completes it moves to \u0027Building workspace\u0027 which gives no indication\nof how long it will take. The whole process took about 15 minutes to open the\nproject and compile 2000 classes.\n\nHowever, the project finally opened ok. So I closed and reopened it again and\neclipse froze - no UI updates, no logs. I had to kill it :-(",
    "The files being indexed are more than likely jar files so they can take a few \nseconds depending on their size (some are 2-5Mb). This should be a one time \nhit.\n\nCan you start eclipse using a command line like:\n\neclipse.exe -data \\your_workspace -vm \\jdk1.4.2\\bin\\java.exe -vmargs -Xmx256M\n\nThen hit break inside the console window to get a stack dump when the \nworkbench appears frozen. Please paste in the trace \u0026 check to see if its the \nsame after 10-20 seconds.",
    "HI,\nI\u0027m having trouble reproducing this particular problem today (lots of out of\nmemory errors on linux in general though which I\u0027m trying to find repeatable use\ncases for).\n\nI\u0027ll keep trying and get back when I have something.\n\nChanning",
    "Please provide steps to reproduce, then reopen.\n\nNote: Added protection to JobManager to guard against NPE in discardJobs.",
    "Channing,\n\nYou can also verify that the VM is picking up your VM args by running with:\n\n-verbose:gc\n\nThis should give you some GC info (too much, but its better than nothing).\n\nPlease paste the last part of the trace once you \u0027run out of memory\u0027.",
    "\u003e You can also verify that the VM is picking up your VM args\n\nThey are being picked up. I am going to try with M20040811 ...",
    "Closing as never reproduced in a long time"
  ],
  "commentCreationDates": [
    "2004-08-03T17:18:29+02:00",
    "2004-08-04T19:05:24+02:00",
    "2004-08-05T11:32:35+02:00",
    "2004-08-05T16:39:57+02:00",
    "2004-08-06T21:47:52+02:00",
    "2004-08-10T20:48:32+02:00",
    "2004-08-11T17:37:20+02:00",
    "2004-08-16T11:00:51+02:00",
    "2005-02-17T14:57:25+01:00"
  ],
  "traces": [
    {
      "exceptionType": "org.osgi.framework.BundleException",
      "message": "Exception in org.eclipse.jdt.core.JavaCore.stop() of bundle org.eclipse.jdt.core.",
      "elements": [
        {
          "method": "org.eclipse.osgi.framework.internal.core.BundleContextImpl.stop",
          "source": "BundleContextImpl.java:1010"
        },
        {
          "method": "org.eclipse.osgi.framework.internal.core.BundleHost.stopWorker",
          "source": "BundleHost.java:502"
        },
        {
          "method": "org.eclipse.osgi.framework.internal.core.AbstractBundle.stop",
          "source": "AbstractBundle.java:437"
        },
        {
          "method": "org.eclipse.core.runtime.adaptor.BundleStopper.basicStopBundles",
          "source": "BundleStopper.java:75"
        },
        {
          "method": "org.eclipse.core.runtime.adaptor.BundleStopper.stopBundles",
          "source": "BundleStopper.java:62"
        },
        {
          "method": "org.eclipse.core.runtime.adaptor.EclipseAdaptor.frameworkStopping",
          "source": "EclipseAdaptor.java:551"
        },
        {
          "method": "org.eclipse.osgi.framework.internal.core.Framework.shutdown",
          "source": "Framework.java:457"
        },
        {
          "method": "org.eclipse.osgi.framework.internal.core.SystemBundle$1.run",
          "source": "SystemBundle.java:182"
        },
        {
          "method": "java.lang.Thread.run",
          "source": "Thread.java:534"
        }
      ],
      "causedBy": {
        "exceptionType": "java.lang.NullPointerException",
        "elements": [
          {
            "method": "org.eclipse.jdt.internal.core.search.processing.JobManager.discardJobs",
            "source": "JobManager.java:110"
          },
          {
            "method": "org.eclipse.jdt.internal.core.search.processing.JobManager.shutdown",
            "source": "JobManager.java:407"
          },
          {
            "method": "org.eclipse.jdt.internal.core.JavaModelManager.shutdown",
            "source": "JavaModelManager.java:1833"
          },
          {
            "method": "org.eclipse.jdt.core.JavaCore.stop",
            "source": "JavaCore.java:3601"
          },
          {
            "method": "org.eclipse.osgi.framework.internal.core.BundleContextImpl$2.run",
            "source": "BundleContextImpl.java:994"
          },
          {
            "method": "java.security.AccessController.doPrivileged",
            "source": "Native Method"
          },
          {
            "method": "org.eclipse.osgi.framework.internal.core.BundleContextImpl.stop",
            "source": "BundleContextImpl.java:990"
          }
        ],
        "number": 0,
        "commentIndex": 0
      },
      "number": 0,
      "commentIndex": 0,
      "bugId": "71293",
      "date": "2004-08-03T17:18:29+02:00",
      "product": "JDT",
      "component": "Core",
      "severity": "normal"
    },
    {
      "exceptionType": "java.lang.NullPointerException",
      "elements": [
        {
          "method": "org.eclipse.jdt.internal.core.search.processing.JobManager.discardJobs",
          "source": "JobManager.java:110"
        },
        {
          "method": "org.eclipse.jdt.internal.core.search.processing.JobManager.shutdown",
          "source": "JobManager.java:407"
        },
        {
          "method": "org.eclipse.jdt.internal.core.JavaModelManager.shutdown",
          "source": "JavaModelManager.java:1833"
        },
        {
          "method": "org.eclipse.jdt.core.JavaCore.stop",
          "source": "JavaCore.java:3601"
        },
        {
          "method": "org.eclipse.osgi.framework.internal.core.BundleContextImpl$2.run",
          "source": "BundleContextImpl.java:994"
        },
        {
          "method": "java.security.AccessController.doPrivileged",
          "source": "Native Method"
        },
        {
          "method": "org.eclipse.osgi.framework.internal.core.BundleContextImpl.stop",
          "source": "BundleContextImpl.java:990"
        },
        {
          "method": "org.eclipse.osgi.framework.internal.core.BundleHost.stopWorker",
          "source": "BundleHost.java:502"
        },
        {
          "method": "org.eclipse.osgi.framework.internal.core.AbstractBundle.stop",
          "source": "AbstractBundle.java:437"
        },
        {
          "method": "org.eclipse.core.runtime.adaptor.BundleStopper.basicStopBundles",
          "source": "BundleStopper.java:75"
        },
        {
          "method": "org.eclipse.core.runtime.adaptor.BundleStopper.stopBundles",
          "source": "BundleStopper.java:62"
        },
        {
          "method": "org.eclipse.core.runtime.adaptor.EclipseAdaptor.frameworkStopping",
          "source": "EclipseAdaptor.java:551"
        },
        {
          "method": "org.eclipse.osgi.framework.internal.core.Framework.shutdown",
          "source": "Framework.java:457"
        },
        {
          "method": "org.eclipse.osgi.framework.internal.core.SystemBundle$1.run",
          "source": "SystemBundle.java:182"
        },
        {
          "method": "java.lang.Thread.run",
          "source": "Thread.java:534"
        }
      ],
      "number": 1,
      "commentIndex": 0,
      "bugId": "71293",
      "date": "2004-08-03T17:18:29+02:00",
      "product": "JDT",
      "component": "Core",
      "severity": "normal"
    }
  ],
  "groupId": "71293",
  "bugId": "71293",
  "date": "2004-08-03T17:18:29+02:00",
  "product": "JDT",
  "component": "Core",
  "severity": "normal"
}