{
  "comments": [
    " ",
    "Oops, sorry, here\u0027s the description:\n\nWhen you select the previous queries and do not click on the arrow that opens\nthe small panel to select a previous query but click on the icon to open a\nwindow to select a query, you get one error per already executed query. The\nexception in .metadata/.log is below:\n\n\n!ENTRY org.eclipse.core.runtime 4 2 Aug 03, 2004 17:41:31.851\n!MESSAGE Problems occurred when invoking code from plug-in:\n\"org.eclipse.core.runtime\".\n!STACK 0\njava.lang.IllegalArgumentException: Argument not valid\n        at org.eclipse.swt.SWT.error(SWT.java:2677)\n        at org.eclipse.swt.SWT.error(SWT.java:2616)\n        at org.eclipse.swt.SWT.error(SWT.java:2587)\n        at org.eclipse.swt.widgets.Widget.error(Widget.java:376)\n        at org.eclipse.swt.widgets.TableItem.setImage(TableItem.java:850)\n        at org.eclipse.jface.viewers.TableViewer.doUpdateItem(TableViewer.java:221)\n        at\norg.eclipse.jface.viewers.StructuredViewer$UpdateItemSafeRunnable.run(StructuredViewer.java:128)\n        at\norg.eclipse.core.internal.runtime.InternalPlatform.run(InternalPlatform.java:615)\n        at org.eclipse.core.runtime.Platform.run(Platform.java:747)\n        at\norg.eclipse.jface.viewers.StructuredViewer.updateItem(StructuredViewer.java:1374)\n        at\norg.eclipse.jface.viewers.TableViewer.internalRefresh(TableViewer.java:514)\n        at\norg.eclipse.jface.viewers.TableViewer.internalRefresh(TableViewer.java:449)\n        at\norg.eclipse.jface.viewers.StructuredViewer$7.run(StructuredViewer.java:924)\n        at\norg.eclipse.jface.viewers.StructuredViewer.preservingSelection(StructuredViewer.java:862)\n        at\norg.eclipse.jface.viewers.StructuredViewer.refresh(StructuredViewer.java:922)\n        at\norg.eclipse.jface.viewers.StructuredViewer.refresh(StructuredViewer.java:881)\n        at org.eclipse.jface.viewers.TableViewer.inputChanged(TableViewer.java:416)\n        at org.eclipse.jface.viewers.ContentViewer.setInput(ContentViewer.java:238)\n        at\norg.eclipse.jface.viewers.StructuredViewer.setInput(StructuredViewer.java:1059)\n        at\norg.eclipse.cme.ui.search.dialogs.SearchHistoryDialog.createDialogArea(SearchHistoryDialog.java:102)\n        at org.eclipse.jface.dialogs.Dialog.createContents(Dialog.java:632)\n        at org.eclipse.jface.window.Window.create(Window.java:348)\n        at org.eclipse.jface.dialogs.Dialog.create(Dialog.java:925)\n        at org.eclipse.jface.window.Window.open(Window.java:637)\n        at\norg.eclipse.cme.ui.search.SearchHistoryDialogAction.run(SearchHistoryDialogAction.java:126)\n        at\norg.eclipse.cme.ui.search.SearchHistoryDropDownAction.run(SearchHistoryDropDownAction.java:98)\n        at org.eclipse.jface.action.Action.runWithEvent(Action.java:881)\n        at\norg.eclipse.jface.action.ActionContributionItem.handleWidgetSelection(ActionContributionItem.java:915)\n        at\norg.eclipse.jface.action.ActionContributionItem.access$2(ActionContributionItem.java:866)\n        at\norg.eclipse.jface.action.ActionContributionItem$8.handleEvent(ActionContributionItem.java:824)\n        at org.eclipse.swt.widgets.EventTable.sendEvent(EventTable.java:82)\n        at org.eclipse.swt.widgets.Widget.sendEvent(Widget.java:954)\n        at org.eclipse.swt.widgets.Display.runDeferredEvents(Display.java:2595)\n        at org.eclipse.swt.widgets.Display.readAndDispatch(Display.java:2298)\n        at org.eclipse.ui.internal.Workbench.runEventLoop(Workbench.java:1377)\n        at org.eclipse.ui.internal.Workbench.runUI(Workbench.java:1348)\n        at\norg.eclipse.ui.internal.Workbench.createAndRunWorkbench(Workbench.java:254)\n        at org.eclipse.ui.PlatformUI.createAndRunWorkbench(PlatformUI.java:141)\n        at org.eclipse.ui.internal.ide.IDEApplication.run(IDEApplication.java:96)\n        at\norg.eclipse.core.internal.runtime.PlatformActivator$1.run(PlatformActivator.java:335)\n        at\norg.eclipse.core.runtime.adaptor.EclipseStarter.run(EclipseStarter.java:273)\n        at\norg.eclipse.core.runtime.adaptor.EclipseStarter.run(EclipseStarter.java:129)\n        at sun.reflect.NativeMethodAccessorImpl.invoke0(Native Method)\n        at\nsun.reflect.NativeMethodAccessorImpl.invoke(NativeMethodAccessorImpl.java:39)\n        at\nsun.reflect.DelegatingMethodAccessorImpl.invoke(DelegatingMethodAccessorImpl.java:25)\n        at java.lang.reflect.Method.invoke(Method.java:324)\n        at org.eclipse.core.launcher.Main.basicRun(Main.java:183)\n        at org.eclipse.core.launcher.Main.run(Main.java:644)\n        at org.eclipse.core.launcher.Main.main(Main.java:628)\n",
    "Fixed in latest CVS release and will be included in the 0.1.3 release"
  ],
  "commentCreationDates": [
    "2004-08-03T17:50:31+02:00",
    "2004-08-03T17:54:27+02:00",
    "2004-08-25T16:02:13+02:00"
  ],
  "traces": [
    {
      "exceptionType": "java.lang.IllegalArgumentException",
      "message": "Argument not valid",
      "elements": [
        {
          "method": "org.eclipse.swt.SWT.error",
          "source": "SWT.java:2677"
        },
        {
          "method": "org.eclipse.swt.SWT.error",
          "source": "SWT.java:2616"
        },
        {
          "method": "org.eclipse.swt.SWT.error",
          "source": "SWT.java:2587"
        },
        {
          "method": "org.eclipse.swt.widgets.Widget.error",
          "source": "Widget.java:376"
        },
        {
          "method": "org.eclipse.swt.widgets.TableItem.setImage",
          "source": "TableItem.java:850"
        },
        {
          "method": "org.eclipse.jface.viewers.TableViewer.doUpdateItem",
          "source": "TableViewer.java:221"
        },
        {
          "method": "org.eclipse.jface.viewers.StructuredViewer$UpdateItemSafeRunnable.run",
          "source": "StructuredViewer.java:128"
        },
        {
          "method": "org.eclipse.core.internal.runtime.InternalPlatform.run",
          "source": "InternalPlatform.java:615"
        },
        {
          "method": "org.eclipse.core.runtime.Platform.run",
          "source": "Platform.java:747"
        },
        {
          "method": "org.eclipse.jface.viewers.StructuredViewer.updateItem",
          "source": "StructuredViewer.java:1374"
        },
        {
          "method": "org.eclipse.jface.viewers.TableViewer.internalRefresh",
          "source": "TableViewer.java:514"
        },
        {
          "method": "org.eclipse.jface.viewers.TableViewer.internalRefresh",
          "source": "TableViewer.java:449"
        },
        {
          "method": "org.eclipse.jface.viewers.StructuredViewer$7.run",
          "source": "StructuredViewer.java:924"
        },
        {
          "method": "org.eclipse.jface.viewers.StructuredViewer.preservingSelection",
          "source": "StructuredViewer.java:862"
        },
        {
          "method": "org.eclipse.jface.viewers.StructuredViewer.refresh",
          "source": "StructuredViewer.java:922"
        },
        {
          "method": "org.eclipse.jface.viewers.StructuredViewer.refresh",
          "source": "StructuredViewer.java:881"
        },
        {
          "method": "org.eclipse.jface.viewers.TableViewer.inputChanged",
          "source": "TableViewer.java:416"
        },
        {
          "method": "org.eclipse.jface.viewers.ContentViewer.setInput",
          "source": "ContentViewer.java:238"
        },
        {
          "method": "org.eclipse.jface.viewers.StructuredViewer.setInput",
          "source": "StructuredViewer.java:1059"
        },
        {
          "method": "org.eclipse.cme.ui.search.dialogs.SearchHistoryDialog.createDialogArea",
          "source": "SearchHistoryDialog.java:102"
        },
        {
          "method": "org.eclipse.jface.dialogs.Dialog.createContents",
          "source": "Dialog.java:632"
        },
        {
          "method": "org.eclipse.jface.window.Window.create",
          "source": "Window.java:348"
        },
        {
          "method": "org.eclipse.jface.dialogs.Dialog.create",
          "source": "Dialog.java:925"
        },
        {
          "method": "org.eclipse.jface.window.Window.open",
          "source": "Window.java:637"
        },
        {
          "method": "org.eclipse.cme.ui.search.SearchHistoryDialogAction.run",
          "source": "SearchHistoryDialogAction.java:126"
        },
        {
          "method": "org.eclipse.cme.ui.search.SearchHistoryDropDownAction.run",
          "source": "SearchHistoryDropDownAction.java:98"
        },
        {
          "method": "org.eclipse.jface.action.Action.runWithEvent",
          "source": "Action.java:881"
        },
        {
          "method": "org.eclipse.jface.action.ActionContributionItem.handleWidgetSelection",
          "source": "ActionContributionItem.java:915"
        },
        {
          "method": "org.eclipse.jface.action.ActionContributionItem.access$2",
          "source": "ActionContributionItem.java:866"
        },
        {
          "method": "org.eclipse.jface.action.ActionContributionItem$8.handleEvent",
          "source": "ActionContributionItem.java:824"
        },
        {
          "method": "org.eclipse.swt.widgets.EventTable.sendEvent",
          "source": "EventTable.java:82"
        },
        {
          "method": "org.eclipse.swt.widgets.Widget.sendEvent",
          "source": "Widget.java:954"
        },
        {
          "method": "org.eclipse.swt.widgets.Display.runDeferredEvents",
          "source": "Display.java:2595"
        },
        {
          "method": "org.eclipse.swt.widgets.Display.readAndDispatch",
          "source": "Display.java:2298"
        },
        {
          "method": "org.eclipse.ui.internal.Workbench.runEventLoop",
          "source": "Workbench.java:1377"
        },
        {
          "method": "org.eclipse.ui.internal.Workbench.runUI",
          "source": "Workbench.java:1348"
        },
        {
          "method": "org.eclipse.ui.internal.Workbench.createAndRunWorkbench",
          "source": "Workbench.java:254"
        },
        {
          "method": "org.eclipse.ui.PlatformUI.createAndRunWorkbench",
          "source": "PlatformUI.java:141"
        },
        {
          "method": "org.eclipse.ui.internal.ide.IDEApplication.run",
          "source": "IDEApplication.java:96"
        },
        {
          "method": "org.eclipse.core.internal.runtime.PlatformActivator$1.run",
          "source": "PlatformActivator.java:335"
        },
        {
          "method": "org.eclipse.core.runtime.adaptor.EclipseStarter.run",
          "source": "EclipseStarter.java:273"
        },
        {
          "method": "org.eclipse.core.runtime.adaptor.EclipseStarter.run",
          "source": "EclipseStarter.java:129"
        },
        {
          "method": "sun.reflect.NativeMethodAccessorImpl.invoke0",
          "source": "Native Method"
        },
        {
          "method": "sun.reflect.NativeMethodAccessorImpl.invoke",
          "source": "NativeMethodAccessorImpl.java:39"
        },
        {
          "method": "sun.reflect.DelegatingMethodAccessorImpl.invoke",
          "source": "DelegatingMethodAccessorImpl.java:25"
        },
        {
          "method": "java.lang.reflect.Method.invoke",
          "source": "Method.java:324"
        },
        {
          "method": "org.eclipse.core.launcher.Main.basicRun",
          "source": "Main.java:183"
        },
        {
          "method": "org.eclipse.core.launcher.Main.run",
          "source": "Main.java:644"
        },
        {
          "method": "org.eclipse.core.launcher.Main.main",
          "source": "Main.java:628"
        }
      ],
      "number": 0,
      "commentIndex": 1,
      "bugId": "71297",
      "date": "2004-08-03T17:54:27+02:00",
      "product": "z_Archived",
      "component": "CME",
      "severity": "normal"
    }
  ],
  "groupId": "71297",
  "bugId": "71297",
  "date": "2004-08-03T17:50:31+02:00",
  "product": "z_Archived",
  "component": "CME",
  "severity": "normal"
}