{
  "comments": [
    "I200408101200\n\nNot sure when this happened.\n\njava.lang.ClassCastException\n        at org.eclipse.jdt.internal.core.util.HandleFactory.createElement(Handle\nFactory.java:310)\n        at org.eclipse.jdt.internal.core.util.HandleFactory.createElement(Handle\nFactory.java:300)\n        at org.eclipse.jdt.internal.core.SelectionRequestor.acceptLocalVariable(\nSelectionRequestor.java:220)\n        at org.eclipse.jdt.internal.codeassist.SelectionEngine.selectFrom(Select\nionEngine.java:720)\n        at org.eclipse.jdt.internal.codeassist.SelectionEngine.select(SelectionE\nngine.java:533)\n        at org.eclipse.jdt.internal.core.Openable.codeSelect(Openable.java:143)\n        at org.eclipse.jdt.internal.core.CompilationUnit.codeSelect(CompilationU\nnit.java:303)\n        at org.eclipse.jdt.internal.core.CompilationUnit.codeSelect(CompilationU\nnit.java:297)\n        at org.eclipse.jdt.internal.ui.infoviews.TextSelectionConverter.codeReso\nlve(TextSelectionConverter.java:90)\n        at org.eclipse.jdt.internal.ui.infoviews.TextSelectionConverter.codeReso\nlve(TextSelectionConverter.java:52)\n        at org.eclipse.jdt.internal.ui.infoviews.AbstractInfoView.findSelectedJa\nvaElement(AbstractInfoView.java:333)\n        at org.eclipse.jdt.internal.ui.infoviews.JavadocView.findSelectedJavaEle\nment(JavadocView.java:500)\n        at org.eclipse.jdt.internal.ui.infoviews.AbstractInfoView$2.run(Abstract\nInfoView.java:448)\njava.lang.ClassCastException\n        at org.eclipse.jdt.internal.core.util.HandleFactory.createElement(Handle\nFactory.java:310)\n        at org.eclipse.jdt.internal.core.util.HandleFactory.createElement(Handle\nFactory.java:300)\n        at org.eclipse.jdt.internal.core.SelectionRequestor.acceptLocalVariable(\nSelectionRequestor.java:220)\n        at org.eclipse.jdt.internal.codeassist.SelectionEngine.selectFrom(Select\nionEngine.java:720)\n        at org.eclipse.jdt.internal.codeassist.SelectionEngine.select(SelectionE\nngine.java:533)\n        at org.eclipse.jdt.internal.core.Openable.codeSelect(Openable.java:143)\n        at org.eclipse.jdt.internal.core.CompilationUnit.codeSelect(CompilationU\nnit.java:303)\n        at org.eclipse.jdt.internal.core.CompilationUnit.codeSelect(CompilationU\nnit.java:297)\n        at org.eclipse.jdt.internal.ui.infoviews.TextSelectionConverter.codeReso\nlve(TextSelectionConverter.java:90)\n        at org.eclipse.jdt.internal.ui.infoviews.TextSelectionConverter.codeReso\nlve(TextSelectionConverter.java:52)\n        at org.eclipse.jdt.internal.ui.infoviews.AbstractInfoView.findSelectedJa\nvaElement(AbstractInfoView.java:333)\n        at org.eclipse.jdt.internal.ui.infoviews.AbstractInfoView$2.run(Abstract\nInfoView.java:448)",
    "I can reproduce the stack trace with the following test case\n\n1) create a new java project\n2) set compiler compliance level to 1.5 (Properties\u003eJava Compiler\u003eCompliance \nand Classfiles\u003eCompiler compliance level)\n3) create X.java\n/**\n */\npublic enum X {;\n  void foo() {\n    int var;\n    var \u003d 0;\n  }\n\n}\n4) select \"var\" inside \"var \u003d 0;\"\nThe ClassCastException occurs\n\nChristof - Did you write similar Java code to cause the ClassCastException ?",
    "Yes, I experimented with an enum and members therein. I\u0027m not sure if the\nexception was thrown when I did so, but it\u0027s plausible.",
    "HandleFactory#createElement(...) use an ASTVisitor but does not visit the \nEnumDeclaration node.\n\nFixed ( visit() and endVisit() methods added).\nTest added (ResolveTest_1_5#test0015())"
  ],
  "commentCreationDates": [
    "2004-08-12T11:29:02+02:00",
    "2004-08-12T18:19:15+02:00",
    "2004-08-12T20:45:13+02:00",
    "2004-08-16T12:35:50+02:00"
  ],
  "traces": [
    {
      "exceptionType": "java.lang.ClassCastException",
      "elements": [
        {
          "method": "org.eclipse.jdt.internal.core.util.HandleFactory.createElement",
          "source": "Handle Factory.java:310"
        },
        {
          "method": "org.eclipse.jdt.internal.core.util.HandleFactory.createElement",
          "source": "Handle Factory.java:300"
        },
        {
          "method": "org.eclipse.jdt.internal.core.SelectionRequestor.acceptLocalVariable",
          "source": " SelectionRequestor.java:220"
        },
        {
          "method": "org.eclipse.jdt.internal.codeassist.SelectionEngine.selectFrom",
          "source": "Select ionEngine.java:720"
        },
        {
          "method": "org.eclipse.jdt.internal.codeassist.SelectionEngine.select",
          "source": "SelectionE ngine.java:533"
        },
        {
          "method": "org.eclipse.jdt.internal.core.Openable.codeSelect",
          "source": "Openable.java:143"
        },
        {
          "method": "org.eclipse.jdt.internal.core.CompilationUnit.codeSelect",
          "source": "CompilationU nit.java:303"
        },
        {
          "method": "org.eclipse.jdt.internal.core.CompilationUnit.codeSelect",
          "source": "CompilationU nit.java:297"
        },
        {
          "method": "org.eclipse.jdt.internal.ui.infoviews.TextSelectionConverter.codeResolve",
          "source": "TextSelectionConverter.java:90"
        },
        {
          "method": "org.eclipse.jdt.internal.ui.infoviews.TextSelectionConverter.codeResolve",
          "source": "TextSelectionConverter.java:52"
        },
        {
          "method": "org.eclipse.jdt.internal.ui.infoviews.AbstractInfoView.findSelectedJavaElement",
          "source": "AbstractInfoView.java:333"
        },
        {
          "method": "org.eclipse.jdt.internal.ui.infoviews.JavadocView.findSelectedJavaElement",
          "source": "JavadocView.java:500"
        },
        {
          "method": "org.eclipse.jdt.internal.ui.infoviews.AbstractInfoView$2.run",
          "source": "Abstract InfoView.java:448"
        }
      ],
      "number": 0,
      "commentIndex": 0,
      "bugId": "71852",
      "date": "2004-08-12T11:29:02+02:00",
      "product": "JDT",
      "component": "Core",
      "severity": "normal"
    },
    {
      "exceptionType": "java.lang.ClassCastException",
      "elements": [
        {
          "method": "org.eclipse.jdt.internal.core.util.HandleFactory.createElement",
          "source": "Handle Factory.java:310"
        },
        {
          "method": "org.eclipse.jdt.internal.core.util.HandleFactory.createElement",
          "source": "Handle Factory.java:300"
        },
        {
          "method": "org.eclipse.jdt.internal.core.SelectionRequestor.acceptLocalVariable",
          "source": " SelectionRequestor.java:220"
        },
        {
          "method": "org.eclipse.jdt.internal.codeassist.SelectionEngine.selectFrom",
          "source": "Select ionEngine.java:720"
        },
        {
          "method": "org.eclipse.jdt.internal.codeassist.SelectionEngine.select",
          "source": "SelectionE ngine.java:533"
        },
        {
          "method": "org.eclipse.jdt.internal.core.Openable.codeSelect",
          "source": "Openable.java:143"
        },
        {
          "method": "org.eclipse.jdt.internal.core.CompilationUnit.codeSelect",
          "source": "CompilationU nit.java:303"
        },
        {
          "method": "org.eclipse.jdt.internal.core.CompilationUnit.codeSelect",
          "source": "CompilationU nit.java:297"
        },
        {
          "method": "org.eclipse.jdt.internal.ui.infoviews.TextSelectionConverter.codeResolve",
          "source": "TextSelectionConverter.java:90"
        },
        {
          "method": "org.eclipse.jdt.internal.ui.infoviews.TextSelectionConverter.codeResolve",
          "source": "TextSelectionConverter.java:52"
        },
        {
          "method": "org.eclipse.jdt.internal.ui.infoviews.AbstractInfoView.findSelectedJavaElement",
          "source": "AbstractInfoView.java:333"
        },
        {
          "method": "org.eclipse.jdt.internal.ui.infoviews.AbstractInfoView$2.run",
          "source": "Abstract InfoView.java:448"
        }
      ],
      "number": 1,
      "commentIndex": 0,
      "bugId": "71852",
      "date": "2004-08-12T11:29:02+02:00",
      "product": "JDT",
      "component": "Core",
      "severity": "normal"
    }
  ],
  "groupId": "71852",
  "bugId": "71852",
  "date": "2004-08-12T11:29:02+02:00",
  "product": "JDT",
  "component": "Core",
  "severity": "normal"
}