{
  "comments": [
    "I200408120010\n\nNot sure when this happend.\n\njava.lang.NullPointerException\n        at org.eclipse.jdt.internal.debug.eval.ast.engine.ASTInstructionCompiler\n.containsALocalType(ASTInstructionCompiler.java:331)\n        at org.eclipse.jdt.internal.debug.eval.ast.engine.ASTInstructionCompiler\n.visit(ASTInstructionCompiler.java:2075)\n        at org.eclipse.jdt.core.dom.MethodInvocation.accept0(MethodInvocation.ja\nva:237)\n        at org.eclipse.jdt.core.dom.ASTNode.accept(ASTNode.java:2450)\n        at org.eclipse.jdt.core.dom.ASTNode.acceptChild(ASTNode.java:2497)\n        at org.eclipse.jdt.core.dom.ReturnStatement.accept0(ReturnStatement.java\n:135)\n        at org.eclipse.jdt.core.dom.ASTNode.accept(ASTNode.java:2450)\n        at org.eclipse.jdt.core.dom.ASTNode.acceptChildren(ASTNode.java:2520)\n        at org.eclipse.jdt.core.dom.Block.accept0(Block.java:135)\n        at org.eclipse.jdt.core.dom.ASTNode.accept(ASTNode.java:2450)\n        at org.eclipse.jdt.core.dom.ASTNode.acceptChild(ASTNode.java:2497)\n        at org.eclipse.jdt.core.dom.MethodDeclaration.accept0(MethodDeclaration.\njava:504)\n        at org.eclipse.jdt.core.dom.ASTNode.accept(ASTNode.java:2450)\n        at org.eclipse.jdt.core.dom.ASTNode.acceptChildren(ASTNode.java:2520)\n        at org.eclipse.jdt.core.dom.TypeDeclaration.accept0(TypeDeclaration.java\n:477)\n        at org.eclipse.jdt.core.dom.ASTNode.accept(ASTNode.java:2450)\n        at org.eclipse.jdt.core.dom.ASTNode.acceptChildren(ASTNode.java:2520)\n        at org.eclipse.jdt.core.dom.CompilationUnit.accept0(CompilationUnit.java\n:292)\n        at org.eclipse.jdt.core.dom.ASTNode.accept(ASTNode.java:2450)\n        at org.eclipse.jdt.internal.debug.eval.ast.engine.ASTEvaluationEngine.cr\neateExpressionFromAST(ASTEvaluationEngine.java:251)\n        at org.eclipse.jdt.internal.debug.eval.ast.engine.ASTEvaluationEngine.ge\ntCompiledExpression(ASTEvaluationEngine.java:156)\n        at org.eclipse.jdt.internal.debug.eval.ast.engine.ASTEvaluationEngine.ev\naluate(ASTEvaluationEngine.java:73)\n        at org.eclipse.jdt.internal.debug.ui.JavaWatchExpressionDelegate$Evaluat\nionRunnable.run(JavaWatchExpressionDelegate.java:144)\n        at org.eclipse.jdt.internal.debug.core.model.JDIThread$ThreadJob.run(JDI\nThread.java:2511)\n        at org.eclipse.core.internal.jobs.Worker.run(Worker.java:66)",
    "\n\n*** This bug has been marked as a duplicate of 67395 ***"
  ],
  "commentCreationDates": [
    "2004-08-12T11:26:39+02:00",
    "2004-08-12T15:26:06+02:00"
  ],
  "traces": [
    {
      "exceptionType": "java.lang.NullPointerException",
      "elements": [
        {
          "method": "org.eclipse.jdt.internal.debug.eval.ast.engine.ASTInstructionCompiler.containsALocalType",
          "source": "ASTInstructionCompiler.java:331"
        },
        {
          "method": "org.eclipse.jdt.internal.debug.eval.ast.engine.ASTInstructionCompiler.visit",
          "source": "ASTInstructionCompiler.java:2075"
        },
        {
          "method": "org.eclipse.jdt.core.dom.MethodInvocation.accept0",
          "source": "MethodInvocation.ja va:237"
        },
        {
          "method": "org.eclipse.jdt.core.dom.ASTNode.accept",
          "source": "ASTNode.java:2450"
        },
        {
          "method": "org.eclipse.jdt.core.dom.ASTNode.acceptChild",
          "source": "ASTNode.java:2497"
        },
        {
          "method": "org.eclipse.jdt.core.dom.ReturnStatement.accept0",
          "source": "ReturnStatement.java :135"
        },
        {
          "method": "org.eclipse.jdt.core.dom.ASTNode.accept",
          "source": "ASTNode.java:2450"
        },
        {
          "method": "org.eclipse.jdt.core.dom.ASTNode.acceptChildren",
          "source": "ASTNode.java:2520"
        },
        {
          "method": "org.eclipse.jdt.core.dom.Block.accept0",
          "source": "Block.java:135"
        },
        {
          "method": "org.eclipse.jdt.core.dom.ASTNode.accept",
          "source": "ASTNode.java:2450"
        },
        {
          "method": "org.eclipse.jdt.core.dom.ASTNode.acceptChild",
          "source": "ASTNode.java:2497"
        },
        {
          "method": "org.eclipse.jdt.core.dom.MethodDeclaration.accept0",
          "source": "MethodDeclaration. java:504"
        },
        {
          "method": "org.eclipse.jdt.core.dom.ASTNode.accept",
          "source": "ASTNode.java:2450"
        },
        {
          "method": "org.eclipse.jdt.core.dom.ASTNode.acceptChildren",
          "source": "ASTNode.java:2520"
        },
        {
          "method": "org.eclipse.jdt.core.dom.TypeDeclaration.accept0",
          "source": "TypeDeclaration.java :477"
        },
        {
          "method": "org.eclipse.jdt.core.dom.ASTNode.accept",
          "source": "ASTNode.java:2450"
        },
        {
          "method": "org.eclipse.jdt.core.dom.ASTNode.acceptChildren",
          "source": "ASTNode.java:2520"
        },
        {
          "method": "org.eclipse.jdt.core.dom.CompilationUnit.accept0",
          "source": "CompilationUnit.java :292"
        },
        {
          "method": "org.eclipse.jdt.core.dom.ASTNode.accept",
          "source": "ASTNode.java:2450"
        },
        {
          "method": "org.eclipse.jdt.internal.debug.eval.ast.engine.ASTEvaluationEngine.createExpressionFromAST",
          "source": "ASTEvaluationEngine.java:251"
        },
        {
          "method": "org.eclipse.jdt.internal.debug.eval.ast.engine.ASTEvaluationEngine.getCompiledExpression",
          "source": "ASTEvaluationEngine.java:156"
        },
        {
          "method": "org.eclipse.jdt.internal.debug.eval.ast.engine.ASTEvaluationEngine.evaluate",
          "source": "ASTEvaluationEngine.java:73"
        },
        {
          "method": "org.eclipse.jdt.internal.debug.ui.JavaWatchExpressionDelegate$EvaluationRunnable.run",
          "source": "JavaWatchExpressionDelegate.java:144"
        },
        {
          "method": "org.eclipse.jdt.internal.debug.core.model.JDIThread$ThreadJob.run",
          "source": "JDI Thread.java:2511"
        },
        {
          "method": "org.eclipse.core.internal.jobs.Worker.run",
          "source": "Worker.java:66"
        }
      ],
      "number": 0,
      "commentIndex": 0,
      "bugId": "71851",
      "duplicateId": "67395",
      "date": "2004-08-12T11:26:39+02:00",
      "product": "JDT",
      "component": "Debug",
      "severity": "normal"
    }
  ],
  "groupId": "67395",
  "bugId": "71851",
  "duplicateId": "67395",
  "date": "2004-08-12T11:26:39+02:00",
  "product": "JDT",
  "component": "Debug",
  "severity": "normal"
}