{
  "comments": [
    "From the newsgroup:\n\nWe create a swt browser and launch it in our perspectives view and I see the\nfollowing problem. ( Note everything works fine under Windows XP SWT. )\n\nHeres the info in the console window I see\n\n\u003e\u003eUnhandled event loop exception\n\u003e\u003eReason:\n\u003e\u003eNo more handles [NS_InitEmbedding\n/usr/lib/mozilla-1.4:/usr/lib/mozilla-1.4\n\u003e\u003eerro r -2147221164]\n\nin the .log file in the workspace I see:\n\n!ENTRY org.eclipse.ui 4 0 Aug 13, 2004 10:54:53.945\n!MESSAGE No more handles [NS_InitEmbedding\n/usr/lib/mozilla-1.4:/usr/lib/mozilla-1.4 error -2147221164]\n!STACK 0\norg.eclipse.swt.SWTError: No more handles [NS_InitEmbedding\n/usr/lib/mozilla-1.4:/usr/lib/mozilla-1.4 error -2147221164]\n\tat org.eclipse.swt.SWT.error(SWT.java:2717)\n\tat org.eclipse.swt.browser.Browser.\u003cinit\u003e(Browser.java:158)\nat\ncom.xxxx.internal.BrowserEditor.createBrowser(BrowserEditor.java:152)\n\tat\ncom.xxxx.internal.BrowserEditor.createPartControl(BrowserEditor.java:62)\n\tat org.eclipse.ui.internal.PartPane$2.run(PartPane.java:137)\n\tat\norg.eclipse.core.internal.runtime.InternalPlatform.run(InternalPlatform.java\n:615)\n\tat org.eclipse.core.runtime.Platform.run(Platform.java:747)\n\tat org.eclipse.ui.internal.PartPane.createChildControl\n(PartPane.java:133)\n\tat org.eclipse.ui.internal.PartPane.createControl(PartPane.java:205)\n\tat\norg.eclipse.ui.internal.PartStack.refreshPresentationSelection(PartStack.jav\na:939)\n\tat org.eclipse.ui.internal.PartStack.setSelection(PartStack.java:921)\n\tat\norg.eclipse.ui.internal.EditorStack.setVisibleEditor(EditorStack.java:170)\n\tat........\n\n\nthe browser is created like the following (from the stack above\nBrowserEditor.java:152)\n\nfinal Browser browser \u003d new Browser(parent, SWT.NONE);\n\nwhere parent is a Composite.\n\neverything works fine under windows. But when we try to open the browser\nunder linux we immediately get the No More Handles Error from SWT error\ndialog.\n\nany ideas?",
    "Mike: for some reason the MOZILLA_FIVE_HOME environment is set \nto /usr/lib/mozilla-1.4:/usr/lib/mozilla-1.4\ninstead of simply\n/usr/lib/mozilla-1.4\n\nA few questions to understand why this is happening.\n\nCan you paste the content of the file /etc/gre.conf ?\nCan you try the following\n1. Open a terminal\n2. setenv MOZILLA_FIVE_HOME /usr/lib/mozilla-1.4     (cshell users)\n3. eclipse    (start eclipse)\nDo you have a different message?\n\n",
    "My conf file looks correct per whats mentioned in the FAQs, environment\nvariables are set up, in my shell script file, so I think thats why its in there\ntwice.",
    "note I have tried setting the MOZILLA_FIVE_HOME variable. our application won\u0027t\nstart with out it set. Note I\u0027m taking this off line and directly to Chris for now",
    "Marking as INVALID. Following up through email directly."
  ],
  "commentCreationDates": [
    "2004-08-17T00:50:31+02:00",
    "2004-08-17T01:00:14+02:00",
    "2004-08-17T20:27:52+02:00",
    "2004-08-17T20:29:28+02:00",
    "2004-08-17T20:58:59+02:00"
  ],
  "traces": [
    {
      "exceptionType": "org.eclipse.swt.SWTError",
      "message": "No more handles [NS_InitEmbedding /usr/lib/mozilla-1.4:/usr/lib/mozilla-1.4 error -2147221164]",
      "elements": [
        {
          "method": "org.eclipse.swt.SWT.error",
          "source": "SWT.java:2717"
        },
        {
          "method": "org.eclipse.swt.browser.Browser.\u003cinit\u003e",
          "source": "Browser.java:158"
        },
        {
          "method": "com.xxxx.internal.BrowserEditor.createBrowser",
          "source": "BrowserEditor.java:152"
        },
        {
          "method": "com.xxxx.internal.BrowserEditor.createPartControl",
          "source": "BrowserEditor.java:62"
        },
        {
          "method": "org.eclipse.ui.internal.PartPane$2.run",
          "source": "PartPane.java:137"
        },
        {
          "method": "org.eclipse.core.internal.runtime.InternalPlatform.run",
          "source": "InternalPlatform.java :615"
        },
        {
          "method": "org.eclipse.core.runtime.Platform.run",
          "source": "Platform.java:747"
        },
        {
          "method": "org.eclipse.ui.internal.PartPane.createChildControl",
          "source": "PartPane.java:133"
        },
        {
          "method": "org.eclipse.ui.internal.PartPane.createControl",
          "source": "PartPane.java:205"
        },
        {
          "method": "org.eclipse.ui.internal.PartStack.refreshPresentationSelection",
          "source": "PartStack.jav a:939"
        },
        {
          "method": "org.eclipse.ui.internal.PartStack.setSelection",
          "source": "PartStack.java:921"
        },
        {
          "method": "org.eclipse.ui.internal.EditorStack.setVisibleEditor",
          "source": "EditorStack.java:170"
        }
      ],
      "number": 0,
      "commentIndex": 0,
      "bugId": "72070",
      "date": "2004-08-17T00:50:31+02:00",
      "product": "Platform",
      "component": "SWT",
      "severity": "normal"
    }
  ],
  "groupId": "72070",
  "bugId": "72070",
  "date": "2004-08-17T00:50:31+02:00",
  "product": "Platform",
  "component": "SWT",
  "severity": "normal"
}