{
  "comments": [
    "Enviroment:\nEclipse 3.0 + CDT 2.0 build 20040816\nUsing standard make project.\n\nSteps to reproduce:\n1. open Project Properties-\u003eBuilders and uncheck CDT Makefile builder check-box\n2. goto Project Properties-\u003eC/C++ Make Project and press Apply button\n\nProblem:\nError is shown: \"Missing Builder: org.eclipse.cdt.make.core.makeBuilder\"\nThought i don\u0027t want to use default CDT makefile builder. i\u0027m using external.\n\nFrom the .log:\norg.eclipse.core.runtime.CoreException: Missing Builder: \norg.eclipse.cdt.make.core.makeBuilder\n        at \norg.eclipse.cdt.make.internal.core.BuildInfoFactory$BuildProperty.\u003cinit\u003e\n(BuildInfoFactory.java:322)\n        at org.eclipse.cdt.make.internal.core.BuildInfoFactory.create\n(BuildInfoFactory.java:377)\n        at org.eclipse.cdt.make.core.MakeCorePlugin.createBuildInfo\n(MakeCorePlugin.java:110)\n        at org.eclipse.cdt.make.ui.dialogs.SettingsBlock$8.run\n(SettingsBlock.java:376)\n        at org.eclipse.core.internal.resources.Workspace.run\n(Workspace.java:1673)\n        at org.eclipse.core.internal.resources.Workspace.run\n(Workspace.java:1693)\n        at org.eclipse.cdt.make.ui.dialogs.SettingsBlock.performApply\n(SettingsBlock.java:419)\n        at org.eclipse.cdt.ui.dialogs.TabFolderOptionBlock.performApply\n(TabFolderOptionBlock.java:162)\n        at org.eclipse.cdt.make.internal.ui.properties.MakePropertyPage$1.run\n(MakePropertyPage.java:78)\n        at org.eclipse.jface.operation.ModalContext.runInCurrentThread\n(ModalContext.java:303)\n        at org.eclipse.jface.operation.ModalContext.run(ModalContext.java:253)\n        at org.eclipse.jface.dialogs.ProgressMonitorDialog.run\n(ProgressMonitorDialog.java:397)\n        at org.eclipse.ui.internal.progress.ProgressMonitorJobsDialog.run\n(ProgressMonitorJobsDialog.java:251)\n        at org.eclipse.ui.internal.progress.ProgressManager.run\n(ProgressManager.java:969)\n        at org.eclipse.ui.internal.progress.ProgressManager$5.run\n(ProgressManager.java:991)\n        at org.eclipse.swt.custom.BusyIndicator.showWhile(BusyIndicator.java:69)\n        at org.eclipse.ui.internal.progress.ProgressManager.runInUI\n(ProgressManager.java:987)\n        at \norg.eclipse.cdt.make.internal.ui.properties.MakePropertyPage.performOk\n(MakePropertyPage.java:82)\n        at org.eclipse.jface.preference.PreferencePage.performApply\n(PreferencePage.java:409)\n        at org.eclipse.jface.preference.PreferencePage$2.widgetSelected\n(PreferencePage.java:272)\n        at org.eclipse.swt.widgets.TypedListener.handleEvent\n(TypedListener.java:89)\n        at org.eclipse.swt.widgets.EventTable.sendEvent(EventTable.java:82)\n        at org.eclipse.swt.widgets.Widget.sendEvent(Widget.java:796)\n        at org.eclipse.swt.widgets.Display.runDeferredEvents(Display.java:2772)\n        at org.eclipse.swt.widgets.Display.readAndDispatch(Display.java:2431)\n        at org.eclipse.jface.window.Window.runEventLoop(Window.java:668)\n        at org.eclipse.jface.window.Window.open(Window.java:648)\n        at org.eclipse.ui.dialogs.PropertyDialogAction.run\n(PropertyDialogAction.java:177)\n        at org.eclipse.ui.internal.ide.actions.ProjectPropertyDialogAction.run\n(ProjectPropertyDialogAction.java:69)\n        at org.eclipse.jface.action.Action.runWithEvent(Action.java:881)\n        at org.eclipse.jface.action.ActionContributionItem.handleWidgetSelection\n(ActionContributionItem.java:915)\n        at org.eclipse.jface.action.ActionContributionItem.access$2\n(ActionContributionItem.java:866)\n        at org.eclipse.jface.action.ActionContributionItem$7.handleEvent\n(ActionContributionItem.java:785)\n        at org.eclipse.swt.widgets.EventTable.sendEvent(EventTable.java:82)\n        at org.eclipse.swt.widgets.Widget.sendEvent(Widget.java:796)\n        at org.eclipse.swt.widgets.Display.runDeferredEvents(Display.java:2772)\n        at org.eclipse.swt.widgets.Display.readAndDispatch(Display.java:2431)\n        at org.eclipse.ui.internal.Workbench.runEventLoop(Workbench.java:1377)\n        at org.eclipse.ui.internal.Workbench.runUI(Workbench.java:1348)\n        at org.eclipse.ui.internal.Workbench.createAndRunWorkbench\n(Workbench.java:254)\n        at org.eclipse.ui.PlatformUI.createAndRunWorkbench(PlatformUI.java:141)\n        at org.eclipse.ui.internal.ide.IDEApplication.run\n(IDEApplication.java:96)\n        at org.eclipse.core.internal.runtime.PlatformActivator$1.run\n(PlatformActivator.java:335)\n        at org.eclipse.core.runtime.adaptor.EclipseStarter.run\n(EclipseStarter.java:273)\n        at org.eclipse.core.runtime.adaptor.EclipseStarter.run\n(EclipseStarter.java:129)\n        at sun.reflect.NativeMethodAccessorImpl.invoke0(Native Method)\n        at sun.reflect.NativeMethodAccessorImpl.invoke(Unknown Source)\n        at sun.reflect.DelegatingMethodAccessorImpl.invoke(Unknown Source)\n        at java.lang.reflect.Method.invoke(Unknown Source)\n        at org.eclipse.core.launcher.Main.basicRun(Main.java:183)\n        at org.eclipse.core.launcher.Main.run(Main.java:644)\n        at org.eclipse.core.launcher.Main.main(Main.java:628)\n!SUBENTRY 1 org.eclipse.cdt.make.core 4 -1 Rgp 19, 2004 10:23:36.734\n!MESSAGE Missing Builder: org.eclipse.cdt.make.core.makeBuilder",
    "fixed in both 2.0.1 and HEAD",
    "*** Bug 71089 has been marked as a duplicate of this bug. ***"
  ],
  "commentCreationDates": [
    "2004-08-19T09:28:53+02:00",
    "2004-08-19T17:34:54+02:00",
    "2004-08-31T22:09:21+02:00"
  ],
  "traces": [
    {
      "exceptionType": "org.eclipse.core.runtime.CoreException",
      "message": "Missing Builder:  org.eclipse.cdt.make.core.makeBuilder",
      "elements": [
        {
          "method": "org.eclipse.cdt.make.internal.core.BuildInfoFactory$BuildProperty.\u003cinit\u003e",
          "source": "BuildInfoFactory.java:322"
        },
        {
          "method": "org.eclipse.cdt.make.internal.core.BuildInfoFactory.create",
          "source": "BuildInfoFactory.java:377"
        },
        {
          "method": "org.eclipse.cdt.make.core.MakeCorePlugin.createBuildInfo",
          "source": "MakeCorePlugin.java:110"
        },
        {
          "method": "org.eclipse.cdt.make.ui.dialogs.SettingsBlock$8.run",
          "source": "SettingsBlock.java:376"
        },
        {
          "method": "org.eclipse.core.internal.resources.Workspace.run",
          "source": "Workspace.java:1673"
        },
        {
          "method": "org.eclipse.core.internal.resources.Workspace.run",
          "source": "Workspace.java:1693"
        },
        {
          "method": "org.eclipse.cdt.make.ui.dialogs.SettingsBlock.performApply",
          "source": "SettingsBlock.java:419"
        },
        {
          "method": "org.eclipse.cdt.ui.dialogs.TabFolderOptionBlock.performApply",
          "source": "TabFolderOptionBlock.java:162"
        },
        {
          "method": "org.eclipse.cdt.make.internal.ui.properties.MakePropertyPage$1.run",
          "source": "MakePropertyPage.java:78"
        },
        {
          "method": "org.eclipse.jface.operation.ModalContext.runInCurrentThread",
          "source": "ModalContext.java:303"
        },
        {
          "method": "org.eclipse.jface.operation.ModalContext.run",
          "source": "ModalContext.java:253"
        },
        {
          "method": "org.eclipse.jface.dialogs.ProgressMonitorDialog.run",
          "source": "ProgressMonitorDialog.java:397"
        },
        {
          "method": "org.eclipse.ui.internal.progress.ProgressMonitorJobsDialog.run",
          "source": "ProgressMonitorJobsDialog.java:251"
        },
        {
          "method": "org.eclipse.ui.internal.progress.ProgressManager.run",
          "source": "ProgressManager.java:969"
        },
        {
          "method": "org.eclipse.ui.internal.progress.ProgressManager$5.run",
          "source": "ProgressManager.java:991"
        },
        {
          "method": "org.eclipse.swt.custom.BusyIndicator.showWhile",
          "source": "BusyIndicator.java:69"
        },
        {
          "method": "org.eclipse.ui.internal.progress.ProgressManager.runInUI",
          "source": "ProgressManager.java:987"
        },
        {
          "method": "org.eclipse.cdt.make.internal.ui.properties.MakePropertyPage.performOk",
          "source": "MakePropertyPage.java:82"
        },
        {
          "method": "org.eclipse.jface.preference.PreferencePage.performApply",
          "source": "PreferencePage.java:409"
        },
        {
          "method": "org.eclipse.jface.preference.PreferencePage$2.widgetSelected",
          "source": "PreferencePage.java:272"
        },
        {
          "method": "org.eclipse.swt.widgets.TypedListener.handleEvent",
          "source": "TypedListener.java:89"
        },
        {
          "method": "org.eclipse.swt.widgets.EventTable.sendEvent",
          "source": "EventTable.java:82"
        },
        {
          "method": "org.eclipse.swt.widgets.Widget.sendEvent",
          "source": "Widget.java:796"
        },
        {
          "method": "org.eclipse.swt.widgets.Display.runDeferredEvents",
          "source": "Display.java:2772"
        },
        {
          "method": "org.eclipse.swt.widgets.Display.readAndDispatch",
          "source": "Display.java:2431"
        },
        {
          "method": "org.eclipse.jface.window.Window.runEventLoop",
          "source": "Window.java:668"
        },
        {
          "method": "org.eclipse.jface.window.Window.open",
          "source": "Window.java:648"
        },
        {
          "method": "org.eclipse.ui.dialogs.PropertyDialogAction.run",
          "source": "PropertyDialogAction.java:177"
        },
        {
          "method": "org.eclipse.ui.internal.ide.actions.ProjectPropertyDialogAction.run",
          "source": "ProjectPropertyDialogAction.java:69"
        },
        {
          "method": "org.eclipse.jface.action.Action.runWithEvent",
          "source": "Action.java:881"
        },
        {
          "method": "org.eclipse.jface.action.ActionContributionItem.handleWidgetSelection",
          "source": "ActionContributionItem.java:915"
        },
        {
          "method": "org.eclipse.jface.action.ActionContributionItem.access$2",
          "source": "ActionContributionItem.java:866"
        },
        {
          "method": "org.eclipse.jface.action.ActionContributionItem$7.handleEvent",
          "source": "ActionContributionItem.java:785"
        },
        {
          "method": "org.eclipse.swt.widgets.EventTable.sendEvent",
          "source": "EventTable.java:82"
        },
        {
          "method": "org.eclipse.swt.widgets.Widget.sendEvent",
          "source": "Widget.java:796"
        },
        {
          "method": "org.eclipse.swt.widgets.Display.runDeferredEvents",
          "source": "Display.java:2772"
        },
        {
          "method": "org.eclipse.swt.widgets.Display.readAndDispatch",
          "source": "Display.java:2431"
        },
        {
          "method": "org.eclipse.ui.internal.Workbench.runEventLoop",
          "source": "Workbench.java:1377"
        },
        {
          "method": "org.eclipse.ui.internal.Workbench.runUI",
          "source": "Workbench.java:1348"
        },
        {
          "method": "org.eclipse.ui.internal.Workbench.createAndRunWorkbench",
          "source": "Workbench.java:254"
        },
        {
          "method": "org.eclipse.ui.PlatformUI.createAndRunWorkbench",
          "source": "PlatformUI.java:141"
        },
        {
          "method": "org.eclipse.ui.internal.ide.IDEApplication.run",
          "source": "IDEApplication.java:96"
        },
        {
          "method": "org.eclipse.core.internal.runtime.PlatformActivator$1.run",
          "source": "PlatformActivator.java:335"
        },
        {
          "method": "org.eclipse.core.runtime.adaptor.EclipseStarter.run",
          "source": "EclipseStarter.java:273"
        },
        {
          "method": "org.eclipse.core.runtime.adaptor.EclipseStarter.run",
          "source": "EclipseStarter.java:129"
        },
        {
          "method": "sun.reflect.NativeMethodAccessorImpl.invoke0",
          "source": "Native Method"
        },
        {
          "method": "sun.reflect.NativeMethodAccessorImpl.invoke",
          "source": "Unknown Source"
        },
        {
          "method": "sun.reflect.DelegatingMethodAccessorImpl.invoke",
          "source": "Unknown Source"
        },
        {
          "method": "java.lang.reflect.Method.invoke",
          "source": "Unknown Source"
        },
        {
          "method": "org.eclipse.core.launcher.Main.basicRun",
          "source": "Main.java:183"
        },
        {
          "method": "org.eclipse.core.launcher.Main.run",
          "source": "Main.java:644"
        },
        {
          "method": "org.eclipse.core.launcher.Main.main",
          "source": "Main.java:628"
        }
      ],
      "number": 0,
      "commentIndex": 0,
      "bugId": "72228",
      "date": "2004-08-19T09:28:53+02:00",
      "product": "CDT",
      "component": "cdt-core",
      "severity": "normal"
    }
  ],
  "groupId": "72228",
  "bugId": "72228",
  "date": "2004-08-19T09:28:53+02:00",
  "product": "CDT",
  "component": "cdt-core",
  "severity": "normal"
}