{
  "comments": [
    "In the properties pane, I hit the down arrow on the objectClass for an \nObjectContributor for a PopupMenu.\nThe Java Attribute Page appears and when you hit Browse... the following \nexception occurs:\njava.lang.IllegalArgumentException: Argument cannot be null\n        at org.eclipse.swt.SWT.error(SWT.java:1873)\n        at org.eclipse.swt.SWT.error(SWT.java:1819)\n        at org.eclipse.swt.widgets.Widget.error(Widget.java:366)\n        at org.eclipse.swt.widgets.Label.setText(Label.java(Compiled Code))\n        at org.eclipse.ui.dialogs.SelectionDialog.createMessageArea\n(SelectionDialog.java:80)\n        at \norg.eclipse.jdt.internal.ui.dialogs.AbstractElementListSelectionDialog.createMe\nssageArea(AbstractElementListSelectionDialog.java:240)\n        at \norg.eclipse.jdt.internal.ui.dialogs.TwoPaneElementSelector.createDialogArea\n(TwoPaneElementSelector.java:91)\n        at org.eclipse.jface.dialogs.Dialog.createContents(Dialog.java:434)\n        at org.eclipse.jface.window.Window.create(Window.java:237)\n        at org.eclipse.jdt.internal.ui.dialogs.SelectionStatusDialog.create\n(SelectionStatusDialog.java:132)\n        at \norg.eclipse.jdt.internal.ui.dialogs.AbstractElementListSelectionDialog.create\n(AbstractElementListSelectionDialog.java:407)\n        at org.eclipse.jdt.internal.ui.dialogs.TypeSelectionDialog.create\n(TypeSelectionDialog.java:131)\n        at org.eclipse.jface.window.Window.open(Window.java:510)\n        at \norg.eclipse.jdt.internal.ui.dialogs.AbstractElementListSelectionDialog.access$s\nuperOpen(AbstractElementListSelectionDialog.java:400)\n        at \norg.eclipse.jdt.internal.ui.dialogs.AbstractElementListSelectionDialog.access$2\n(AbstractElementListSelectionDialog.java:399)\n        at \norg.eclipse.jdt.internal.ui.dialogs.AbstractElementListSelectionDialog$4.run\n(AbstractElementListSelectionDialog.java:393)\n        at org.eclipse.swt.custom.BusyIndicator.showWhile\n(BusyIndicator.java:56)\n        at \norg.eclipse.jdt.internal.ui.dialogs.AbstractElementListSelectionDialog.open\n(AbstractElementListSelectionDialog.java:391)\n        at org.eclipse.jdt.internal.ui.dialogs.TypeSelectionDialog.open\n(TypeSelectionDialog.java(Compiled Code))\n        at \norg.eclipse.pde.internal.editor.manifest.JavaAttributeWizardPage.handleFindType\n(JavaAttributeWizardPage.java:369)\n        at \norg.eclipse.pde.internal.editor.manifest.JavaAttributeWizardPage.access$9\n(JavaAttributeWizardPage.java:360)\n        at \norg.eclipse.pde.internal.editor.manifest.JavaAttributeWizardPage$6.widgetSelect\ned(JavaAttributeWizardPage.java:237)\n        at org.eclipse.swt.widgets.TypedListener.handleEvent(TypedListener.java\n(Compiled Code))\n        at org.eclipse.swt.widgets.EventTable.sendEvent(EventTable.java\n(Compiled Code))\n        at org.eclipse.swt.widgets.Widget.notifyListeners(Widget.java(Compiled \nCode))\n        at org.eclipse.swt.widgets.Display.runDeferredEvents(Display.java\n(Compiled Code))\n        at org.eclipse.swt.widgets.Display.readAndDispatch(Display.java\n(Compiled Code))\n        at org.eclipse.jface.window.Window.runEventLoop(Window.java(Compiled \nCode))\n        at org.eclipse.jface.window.Window.open(Window.java:523)\n        at \norg.eclipse.pde.internal.editor.manifest.JavaAttributeCellEditor.openDialogBox\n(JavaAttributeCellEditor.java:40)\n        at org.eclipse.jface.viewers.DialogCellEditor$2.widgetSelected\n(DialogCellEditor.java:154)\n        at org.eclipse.swt.widgets.TypedListener.handleEvent(TypedListener.java\n(Compiled Code))\n        at org.eclipse.swt.widgets.EventTable.sendEvent(EventTable.java\n(Compiled Code))\n        at org.eclipse.swt.widgets.Widget.notifyListeners(Widget.java(Compiled \nCode))\n        at org.eclipse.swt.widgets.Display.runDeferredEvents(Display.java\n(Compiled Code))\n        at org.eclipse.swt.widgets.Display.readAndDispatch(Display.java\n(Compiled Code))\n        at org.eclipse.ui.internal.Workbench.runEventLoop(Workbench.java\n(Compiled Code))\n        at org.eclipse.ui.internal.Workbench.run(Workbench.java:798)\n        at org.eclipse.core.internal.boot.InternalBootLoader.run\n(InternalBootLoader.java:821)\n        at org.eclipse.core.boot.BootLoader.run(BootLoader.java:285)\n        at java.lang.reflect.Method.invoke(Native Method)\n        at org.eclipse.core.launcher.Main.basicRun(Main.java:151)\n        at org.eclipse.core.launcher.Main.run(Main.java:502)\n        at org.eclipse.core.launcher.Main.main(Main.java:362)",
    "Fixed in build 20020122"
  ],
  "commentCreationDates": [
    "2002-01-03T16:17:33+01:00",
    "2002-01-22T19:06:41+01:00"
  ],
  "traces": [
    {
      "exceptionType": "java.lang.IllegalArgumentException",
      "message": "Argument cannot be null",
      "elements": [
        {
          "method": "org.eclipse.swt.SWT.error",
          "source": "SWT.java:1873"
        },
        {
          "method": "org.eclipse.swt.SWT.error",
          "source": "SWT.java:1819"
        },
        {
          "method": "org.eclipse.swt.widgets.Widget.error",
          "source": "Widget.java:366"
        },
        {
          "method": "org.eclipse.swt.widgets.Label.setText",
          "source": "Label.java(Compiled Code)"
        },
        {
          "method": "org.eclipse.ui.dialogs.SelectionDialog.createMessageArea",
          "source": "SelectionDialog.java:80"
        },
        {
          "method": "org.eclipse.jdt.internal.ui.dialogs.AbstractElementListSelectionDialog.createMessageArea",
          "source": "AbstractElementListSelectionDialog.java:240"
        },
        {
          "method": "org.eclipse.jdt.internal.ui.dialogs.TwoPaneElementSelector.createDialogArea",
          "source": "TwoPaneElementSelector.java:91"
        },
        {
          "method": "org.eclipse.jface.dialogs.Dialog.createContents",
          "source": "Dialog.java:434"
        },
        {
          "method": "org.eclipse.jface.window.Window.create",
          "source": "Window.java:237"
        },
        {
          "method": "org.eclipse.jdt.internal.ui.dialogs.SelectionStatusDialog.create",
          "source": "SelectionStatusDialog.java:132"
        },
        {
          "method": "org.eclipse.jdt.internal.ui.dialogs.AbstractElementListSelectionDialog.create",
          "source": "AbstractElementListSelectionDialog.java:407"
        },
        {
          "method": "org.eclipse.jdt.internal.ui.dialogs.TypeSelectionDialog.create",
          "source": "TypeSelectionDialog.java:131"
        },
        {
          "method": "org.eclipse.jface.window.Window.open",
          "source": "Window.java:510"
        },
        {
          "method": "org.eclipse.jdt.internal.ui.dialogs.AbstractElementListSelectionDialog.access$superOpen",
          "source": "AbstractElementListSelectionDialog.java:400"
        },
        {
          "method": "org.eclipse.jdt.internal.ui.dialogs.AbstractElementListSelectionDialog.access$2",
          "source": "AbstractElementListSelectionDialog.java:399"
        },
        {
          "method": "org.eclipse.jdt.internal.ui.dialogs.AbstractElementListSelectionDialog$4.run",
          "source": "AbstractElementListSelectionDialog.java:393"
        },
        {
          "method": "org.eclipse.swt.custom.BusyIndicator.showWhile",
          "source": "BusyIndicator.java:56"
        },
        {
          "method": "org.eclipse.jdt.internal.ui.dialogs.AbstractElementListSelectionDialog.open",
          "source": "AbstractElementListSelectionDialog.java:391"
        },
        {
          "method": "org.eclipse.jdt.internal.ui.dialogs.TypeSelectionDialog.open",
          "source": "TypeSelectionDialog.java(Compiled Code)"
        },
        {
          "method": "org.eclipse.pde.internal.editor.manifest.JavaAttributeWizardPage.handleFindType",
          "source": "JavaAttributeWizardPage.java:369"
        },
        {
          "method": "org.eclipse.pde.internal.editor.manifest.JavaAttributeWizardPage.access$9",
          "source": "JavaAttributeWizardPage.java:360"
        },
        {
          "method": "org.eclipse.pde.internal.editor.manifest.JavaAttributeWizardPage$6.widgetSelected",
          "source": "JavaAttributeWizardPage.java:237"
        },
        {
          "method": "org.eclipse.swt.widgets.TypedListener.handleEvent",
          "source": "TypedListener.java (Compiled Code)"
        },
        {
          "method": "org.eclipse.swt.widgets.EventTable.sendEvent",
          "source": "EventTable.java (Compiled Code)"
        },
        {
          "method": "org.eclipse.swt.widgets.Widget.notifyListeners",
          "source": "Widget.java(Compiled  Code)"
        },
        {
          "method": "org.eclipse.swt.widgets.Display.runDeferredEvents",
          "source": "Display.java (Compiled Code)"
        },
        {
          "method": "org.eclipse.swt.widgets.Display.readAndDispatch",
          "source": "Display.java (Compiled Code)"
        },
        {
          "method": "org.eclipse.jface.window.Window.runEventLoop",
          "source": "Window.java(Compiled  Code)"
        },
        {
          "method": "org.eclipse.jface.window.Window.open",
          "source": "Window.java:523"
        },
        {
          "method": "org.eclipse.pde.internal.editor.manifest.JavaAttributeCellEditor.openDialogBox",
          "source": "JavaAttributeCellEditor.java:40"
        },
        {
          "method": "org.eclipse.jface.viewers.DialogCellEditor$2.widgetSelected",
          "source": "DialogCellEditor.java:154"
        },
        {
          "method": "org.eclipse.swt.widgets.TypedListener.handleEvent",
          "source": "TypedListener.java (Compiled Code)"
        },
        {
          "method": "org.eclipse.swt.widgets.EventTable.sendEvent",
          "source": "EventTable.java (Compiled Code)"
        },
        {
          "method": "org.eclipse.swt.widgets.Widget.notifyListeners",
          "source": "Widget.java(Compiled  Code)"
        },
        {
          "method": "org.eclipse.swt.widgets.Display.runDeferredEvents",
          "source": "Display.java (Compiled Code)"
        },
        {
          "method": "org.eclipse.swt.widgets.Display.readAndDispatch",
          "source": "Display.java (Compiled Code)"
        },
        {
          "method": "org.eclipse.ui.internal.Workbench.runEventLoop",
          "source": "Workbench.java (Compiled Code)"
        },
        {
          "method": "org.eclipse.ui.internal.Workbench.run",
          "source": "Workbench.java:798"
        },
        {
          "method": "org.eclipse.core.internal.boot.InternalBootLoader.run",
          "source": "InternalBootLoader.java:821"
        },
        {
          "method": "org.eclipse.core.boot.BootLoader.run",
          "source": "BootLoader.java:285"
        },
        {
          "method": "java.lang.reflect.Method.invoke",
          "source": "Native Method"
        },
        {
          "method": "org.eclipse.core.launcher.Main.basicRun",
          "source": "Main.java:151"
        },
        {
          "method": "org.eclipse.core.launcher.Main.run",
          "source": "Main.java:502"
        },
        {
          "method": "org.eclipse.core.launcher.Main.main",
          "source": "Main.java:362"
        }
      ],
      "number": 0,
      "commentIndex": 0,
      "bugId": "7236",
      "date": "2002-01-03T16:17:33+01:00",
      "product": "PDE",
      "component": "UI",
      "severity": "normal"
    }
  ],
  "groupId": "7236",
  "bugId": "7236",
  "date": "2002-01-03T16:17:33+01:00",
  "product": "PDE",
  "component": "UI",
  "severity": "normal"
}