{
  "comments": [
    "I don\u0027t know what the right component is - I\u0027m sorry if compiler is wrong.\n\nFor some reason I get this error every time I include\n/opt/aspectj1.2/lib/aspectjtools.jar \nin the classpath for the java runtime. The some code\nexecutes fine when I don\u0027t include the jar. \naspectjrt.jar is not giving me any problems.\n\nAny clues? Perhaps some type of conflict?\nThe java runtime is from Sun\u0027s JDK 1.4. \nXerces-j is installed, and this is Fedora Core Rawhide.\n\nException in thread \"main\" javax.xml.parsers.FactoryConfigurationError: Provider\norg.apache.xerces.jaxp.DocumentBuilderFactoryImpl not found\n        at\njavax.xml.parsers.DocumentBuilderFactory.newInstance(DocumentBuilderFactory.java:99)\n        at java.util.prefs.XmlSupport.load(XmlSupport.java:210)\n        at java.util.prefs.XmlSupport.importMap(XmlSupport.java:318)\n        at\njava.util.prefs.FileSystemPreferences$8.run(FileSystemPreferences.java:561)\n        at java.security.AccessController.doPrivileged(Native Method)\n        at\njava.util.prefs.FileSystemPreferences.loadCache(FileSystemPreferences.java:554)\n        at\njava.util.prefs.FileSystemPreferences.initCacheIfNecessary(FileSystemPreferences.java:537)\n        at\njava.util.prefs.FileSystemPreferences.getSpi(FileSystemPreferences.java:514)\n        at java.util.prefs.AbstractPreferences.get(AbstractPreferences.java:270)\n        at\njava.util.prefs.AbstractPreferences.getBoolean(AbstractPreferences.java:481)\n        at edu.cornell.cs.sam.ui.SamGUI.reorderComponents(SamGUI.java:214)\n        at edu.cornell.cs.sam.ui.SamGUI.createComponents(SamGUI.java:206)\n        at edu.cornell.cs.sam.ui.SamGUI.\u003cinit\u003e(SamGUI.java:162)\n        at edu.cornell.cs.sam.ui.SamGUI.startUI(SamGUI.java:1326)\n        at edu.cornell.cs.sam.ui.SamUI.startSaM(SamUI.java:112)\n        at edu.cornell.cs.sam.ui.SamUI.startSaM(SamUI.java:147)\n        at edu.cornell.cs.sam.ui.SamGUI.main(SamGUI.java:1351)",
    "aspectjtools.jar seems to have picked up some unwanted classes during the build \nand packaging process - there are one or two javax.xml..* classes in there that \nshouldn\u0027t be. Suspect these are incompatible with the versions you have \nelsewhere on your classpath. \n\nThis needs to be fixed in 1.2.1. I\u0027ll post to this bug report as soon as a fix \nis available from the aspectj download page.",
    "I believe this bug has already been fixed in the 1.2.1 stream.  With the rebuild\nof the jdt dependencies for the compiler move we have lost the rogue javax.xml\nstuff that shouldn\u0027t be in there.  When the next build succeeds (which includes\na whole bunch of package renames) I\u0027ll verify that...",
    "I checked and we aren\u0027t including javax.xml classes but after some further\ninvestigation I have also removed:\n\norg/eclipse/jface/*  \norg/eclipse/text/* \norg/eclipse/osgi/* \n\nI have left in:\n\norg/osgi/*\norg/eclipse/core/*\n\nfix checked in, waiting for build.",
    "Fix available:\n\nBUILD COMPLETE -  build.373\nDate of build: 09/07/2004 19:06:28\nTime to build: 99 minutes 10 seconds\nLast changed: 09/07/2004 16:35:51\nLatest good AspectJ jar available at:\ndownload.eclipse.org/technology/ajdt/dev/aspectj-DEVELOPMENT.jar",
    "Fix released as part of AspectJ 1.2.1"
  ],
  "commentCreationDates": [
    "2004-08-23T04:17:54+02:00",
    "2004-08-25T09:14:19+02:00",
    "2004-09-07T12:51:59+02:00",
    "2004-09-07T18:04:39+02:00",
    "2004-09-08T09:49:45+02:00",
    "2004-10-21T10:32:06+02:00"
  ],
  "traces": [
    {
      "exceptionType": "javax.xml.parsers.FactoryConfigurationError",
      "message": "Provider org.apache.xerces.jaxp.DocumentBuilderFactoryImpl not found",
      "elements": [
        {
          "method": "javax.xml.parsers.DocumentBuilderFactory.newInstance",
          "source": "DocumentBuilderFactory.java:99"
        },
        {
          "method": "java.util.prefs.XmlSupport.load",
          "source": "XmlSupport.java:210"
        },
        {
          "method": "java.util.prefs.XmlSupport.importMap",
          "source": "XmlSupport.java:318"
        },
        {
          "method": "java.util.prefs.FileSystemPreferences$8.run",
          "source": "FileSystemPreferences.java:561"
        },
        {
          "method": "java.security.AccessController.doPrivileged",
          "source": "Native Method"
        },
        {
          "method": "java.util.prefs.FileSystemPreferences.loadCache",
          "source": "FileSystemPreferences.java:554"
        },
        {
          "method": "java.util.prefs.FileSystemPreferences.initCacheIfNecessary",
          "source": "FileSystemPreferences.java:537"
        },
        {
          "method": "java.util.prefs.FileSystemPreferences.getSpi",
          "source": "FileSystemPreferences.java:514"
        },
        {
          "method": "java.util.prefs.AbstractPreferences.get",
          "source": "AbstractPreferences.java:270"
        },
        {
          "method": "java.util.prefs.AbstractPreferences.getBoolean",
          "source": "AbstractPreferences.java:481"
        },
        {
          "method": "edu.cornell.cs.sam.ui.SamGUI.reorderComponents",
          "source": "SamGUI.java:214"
        },
        {
          "method": "edu.cornell.cs.sam.ui.SamGUI.createComponents",
          "source": "SamGUI.java:206"
        },
        {
          "method": "edu.cornell.cs.sam.ui.SamGUI.\u003cinit\u003e",
          "source": "SamGUI.java:162"
        },
        {
          "method": "edu.cornell.cs.sam.ui.SamGUI.startUI",
          "source": "SamGUI.java:1326"
        },
        {
          "method": "edu.cornell.cs.sam.ui.SamUI.startSaM",
          "source": "SamUI.java:112"
        },
        {
          "method": "edu.cornell.cs.sam.ui.SamUI.startSaM",
          "source": "SamUI.java:147"
        },
        {
          "method": "edu.cornell.cs.sam.ui.SamGUI.main",
          "source": "SamGUI.java:1351"
        }
      ],
      "number": 0,
      "commentIndex": 0,
      "bugId": "72409",
      "date": "2004-08-23T04:17:54+02:00",
      "product": "AspectJ",
      "component": "Compiler",
      "severity": "normal"
    }
  ],
  "groupId": "72409",
  "bugId": "72409",
  "date": "2004-08-23T04:17:54+02:00",
  "product": "AspectJ",
  "component": "Compiler",
  "severity": "normal"
}