{
  "comments": [
    "The XSDParser (part of the XSD support shipped with Ecore/SDO) does\nsome work with classloaders in its constructor. In some contexts thi results \nin a security exception.\n\njava.security.AccessControlException: access denied \n(java.lang.RuntimePermission setContextClassLoader)\n       at java.security.AccessControlContext.checkPermission\n(AccessControlContext.java(Compiled Code))\n       at java.security.AccessController.checkPermission(AccessController.java\n(Compiled Code))\n       at java.lang.SecurityManager.checkPermission(SecurityManager.java\n(Compiled Code))\n       at com.ibm.ws.security.core.SecurityManager.checkPermission\n(SecurityManager.java(Compiled Code))\n       at java.lang.Thread.setContextClassLoader(Thread.java:1249)\n       at org.eclipse.xsd.util.XSDParser.\u003cinit\u003e(XSDParser.java:174)\n       at org.eclipse.xsd.util.XSDResourceImpl.doLoad(XSDResourceImpl.java:384)\n       at org.eclipse.emf.ecore.resource.impl.ResourceImpl.load\n(ResourceImpl.java:867)\n       at com.ibm.ws.sib.mfp.sdo.repository.XSDResourceLoader.loadSchema\n(XSDResourceLoader.java:176)\n       at \ncom.ibm.ws.sib.mfp.sdo.repository.SdoRepositoryCache.loadSchemaResource\n(SdoRepositoryCache.java:474)\n       at com.ibm.ws.sib.mfp.sdo.repository.SdoRepositoryCache.loadResource\n(SdoRepositoryCache.java:456)\n       at com.ibm.ws.sib.mfp.sdo.repository.SdoRepositoryCache.getEcoreModel\n(SdoRepositoryCache.java:261)\n\n\nCan this constructor be changed so that it doesn\u0027t need to fiddle with the \nclassloader?",
    "The fix to remove the unnecessary code has been committed to CVS.",
    "The fix is available in the M200408260844 build."
  ],
  "commentCreationDates": [
    "2004-08-24T20:47:14+02:00",
    "2004-08-24T20:59:13+02:00",
    "2004-08-26T16:00:25+02:00"
  ],
  "traces": [
    {
      "exceptionType": "java.security.AccessControlException",
      "message": "access denied  (java.lang.RuntimePermission setContextClassLoader)",
      "elements": [
        {
          "method": "java.security.AccessControlContext.checkPermission",
          "source": "AccessControlContext.java(Compiled Code)"
        },
        {
          "method": "java.security.AccessController.checkPermission",
          "source": "AccessController.java (Compiled Code)"
        },
        {
          "method": "java.lang.SecurityManager.checkPermission",
          "source": "SecurityManager.java (Compiled Code)"
        },
        {
          "method": "com.ibm.ws.security.core.SecurityManager.checkPermission",
          "source": "SecurityManager.java(Compiled Code)"
        },
        {
          "method": "java.lang.Thread.setContextClassLoader",
          "source": "Thread.java:1249"
        },
        {
          "method": "org.eclipse.xsd.util.XSDParser.\u003cinit\u003e",
          "source": "XSDParser.java:174"
        },
        {
          "method": "org.eclipse.xsd.util.XSDResourceImpl.doLoad",
          "source": "XSDResourceImpl.java:384"
        },
        {
          "method": "org.eclipse.emf.ecore.resource.impl.ResourceImpl.load",
          "source": "ResourceImpl.java:867"
        },
        {
          "method": "com.ibm.ws.sib.mfp.sdo.repository.XSDResourceLoader.loadSchema",
          "source": "XSDResourceLoader.java:176"
        },
        {
          "method": "com.ibm.ws.sib.mfp.sdo.repository.SdoRepositoryCache.loadSchemaResource",
          "source": "SdoRepositoryCache.java:474"
        },
        {
          "method": "com.ibm.ws.sib.mfp.sdo.repository.SdoRepositoryCache.loadResource",
          "source": "SdoRepositoryCache.java:456"
        },
        {
          "method": "com.ibm.ws.sib.mfp.sdo.repository.SdoRepositoryCache.getEcoreModel",
          "source": "SdoRepositoryCache.java:261"
        }
      ],
      "number": 0,
      "commentIndex": 0,
      "bugId": "72532",
      "date": "2004-08-24T20:47:14+02:00",
      "product": "EMF",
      "component": "Core",
      "severity": "normal"
    }
  ],
  "groupId": "72532",
  "bugId": "72532",
  "date": "2004-08-24T20:47:14+02:00",
  "product": "EMF",
  "component": "Core",
  "severity": "normal"
}