{
  "comments": [
    "When I was searching (file search) I got an error message\nsaying an SWT error had occured and I should close the application. \n\nI closed, and when I try to startup again I now keep getting the error\nwidget is disposed.  It seems there was some inconsistent state\nleft in the workspace, because when I remove the workspace I can\nstartup with no problem.\n\nI don\u0027t have the log file from the original error any more, but here is\nthe stack trace that prevents startup.  This is on FreeBSD with\nEclipse 3.0 compiled from source based on the Linux source, with\nminor modifications in the native part to make it compile (mostly changes\nof paths in the Makefiles).  JRE is SUN JDK 1.4.2, also compiled from\nsource (FreeBSD port).\n\n-----------------------------------------\n!ENTRY org.eclipse.osgi Aug 25, 2004 10:03:41.04\n!MESSAGE Application error\n!STACK 1\norg.eclipse.swt.SWTException: Widget is disposed\n        at org.eclipse.swt.SWT.error(SWT.java:2691)\n        at org.eclipse.swt.SWT.error(SWT.java:2616)\n        at org.eclipse.swt.SWT.error(SWT.java:2587)\n        at org.eclipse.swt.widgets.Widget.error(Widget.java:376)\n        at org.eclipse.swt.widgets.Widget.checkWidget(Widget.java:312)\n        at org.eclipse.swt.widgets.Control.getParent(Control.java:1582)\n        at org.eclipse.swt.widgets.Shell.getShells(Shell.java:706)\n        at org.eclipse.swt.widgets.Shell.releaseShells(Shell.java:1343)\n        at org.eclipse.swt.widgets.Shell.releaseWidget(Shell.java:1351)\n        at org.eclipse.swt.widgets.Widget.dispose(Widget.java:371)\n        at org.eclipse.swt.widgets.Shell.dispose(Shell.java:1295)\n        at org.eclipse.jface.window.Window.close(Window.java:253)\n        at org.eclipse.jface.dialogs.Dialog.close(Dialog.java:826)\n        at\norg.eclipse.jface.dialogs.ProgressMonitorDialog.close(ProgressMonitorDialog.java:283)\n        at\norg.eclipse.jface.dialogs.ProgressMonitorDialog.finishedRun(ProgressMonitorDialog.java:477)\n        at\norg.eclipse.jface.dialogs.ProgressMonitorDialog.run(ProgressMonitorDialog.java:400)\n        at\norg.eclipse.ui.internal.activities.ws.WorkbenchActivitySupport$4.run(WorkbenchActivitySupport.java:199)\n        at org.eclipse.swt.custom.BusyIndicator.showWhile(BusyIndicator.java:69)\n       at\norg.eclipse.ui.internal.activities.ws.WorkbenchActivitySupport$3.run(WorkbenchActivitySupport.java:192)\n        at org.eclipse.swt.widgets.RunnableLock.run(RunnableLock.java:35)\n        at\norg.eclipse.swt.widgets.Synchronizer.runAsyncMessages(Synchronizer.java:106)\n        at org.eclipse.swt.widgets.Display.runAsyncMessages(Display.java:2572)\n        at org.eclipse.swt.widgets.Display.readAndDispatch(Display.java:2301)\n        at org.eclipse.swt.widgets.Display.release(Display.java:2350)\n        at org.eclipse.swt.graphics.Device.dispose(Device.java:174)\n        at org.eclipse.ui.internal.ide.IDEApplication.run(IDEApplication.java:112)\n        at\norg.eclipse.core.internal.runtime.PlatformActivator$1.run(PlatformActivator.java:335)\n        at\norg.eclipse.core.runtime.adaptor.EclipseStarter.run(EclipseStarter.java:273)\n        at\norg.eclipse.core.runtime.adaptor.EclipseStarter.run(EclipseStarter.java:129)\n        at sun.reflect.NativeMethodAccessorImpl.invoke0(Native Method)\n        at\nsun.reflect.NativeMethodAccessorImpl.invoke(NativeMethodAccessorImpl.java:39)\n        at\nsun.reflect.DelegatingMethodAccessorImpl.invoke(DelegatingMethodAccessorImpl.java:25)\n        at java.lang.reflect.Method.invoke(Method.java:324)\n        at org.eclipse.core.launcher.Main.basicRun(Main.java:183)\n        at org.eclipse.core.launcher.Main.run(Main.java:644)\n        at org.eclipse.core.launcher.Main.main(Main.java:628)\n(",
    "What eclipse build are you using?",
    "I used Eclipse 3.0 compiled from source, i.e. the final release. That would be\neclipse-sourceBuild-srcIncluded-3.0.zip.  I don\u0027t know what build that\ncorresponds to.",
    "Can you please elaborate on \"minor modifications in the native part\" and give \ninformation about what version of GTK+ you are running on your FreeBSD machine.",
    "Well, \"modifications\" might not be the best term.  I patched it to get it to\ncompile, e.g. added #includes.  I\u0027m uploading the complete diff here.\n\nhunter[35]$ pkg-config --modversion gtk+-2.0\n2.4.0\nhunter[36]$\n\nLet me add that this version is otherwise very stable on my system.  My colleagues\non Linux complain about crashes every couple hours, for me it runs w/o any\nincident many days, and only very rarely gets minor hickups.  Thanks for a great\nproduct.",
    "Created an attachment (id\u003d14280)\nmy patches to get the native part to compile on FreeBSD\n\nPls note that this is for compiling a FreeBSD version, despite the fact that\nI patch the linux tree.  I was too lazy to clone the tree first.",
    "Georg, the workspace that fails around ? Could you be able to share it (zip it \nand attach it in this PR) ? I hope the workspace it not very large (\u003c5Mb).\n",
    "I meant to say:\nGeorg, do you still have the workspace that fails around ?",
    "sorry I don\u0027t have the workspace any more.",
    "I checked the code and there is nothing wrong with it and I can\u0027t reproduce \nthis problem.\nTherefore, I\u0027m closing this as worksforme. Please reopen this bug if you have \nmore information or a workspace which could help me to reproduce this problem.",
    "closing."
  ],
  "commentCreationDates": [
    "2004-08-25T10:20:15+02:00",
    "2004-08-26T18:59:56+02:00",
    "2004-08-27T10:12:59+02:00",
    "2004-08-30T19:17:57+02:00",
    "2004-08-31T11:09:13+02:00",
    "2004-08-31T11:12:45+02:00",
    "2004-09-10T20:12:19+02:00",
    "2004-09-10T20:12:57+02:00",
    "2004-09-12T00:32:50+02:00",
    "2004-09-13T17:06:26+02:00",
    "2004-09-13T17:06:45+02:00"
  ],
  "traces": [
    {
      "exceptionType": "org.eclipse.swt.SWTException",
      "message": "Widget is disposed",
      "elements": [
        {
          "method": "org.eclipse.swt.SWT.error",
          "source": "SWT.java:2691"
        },
        {
          "method": "org.eclipse.swt.SWT.error",
          "source": "SWT.java:2616"
        },
        {
          "method": "org.eclipse.swt.SWT.error",
          "source": "SWT.java:2587"
        },
        {
          "method": "org.eclipse.swt.widgets.Widget.error",
          "source": "Widget.java:376"
        },
        {
          "method": "org.eclipse.swt.widgets.Widget.checkWidget",
          "source": "Widget.java:312"
        },
        {
          "method": "org.eclipse.swt.widgets.Control.getParent",
          "source": "Control.java:1582"
        },
        {
          "method": "org.eclipse.swt.widgets.Shell.getShells",
          "source": "Shell.java:706"
        },
        {
          "method": "org.eclipse.swt.widgets.Shell.releaseShells",
          "source": "Shell.java:1343"
        },
        {
          "method": "org.eclipse.swt.widgets.Shell.releaseWidget",
          "source": "Shell.java:1351"
        },
        {
          "method": "org.eclipse.swt.widgets.Widget.dispose",
          "source": "Widget.java:371"
        },
        {
          "method": "org.eclipse.swt.widgets.Shell.dispose",
          "source": "Shell.java:1295"
        },
        {
          "method": "org.eclipse.jface.window.Window.close",
          "source": "Window.java:253"
        },
        {
          "method": "org.eclipse.jface.dialogs.Dialog.close",
          "source": "Dialog.java:826"
        },
        {
          "method": "org.eclipse.jface.dialogs.ProgressMonitorDialog.close",
          "source": "ProgressMonitorDialog.java:283"
        },
        {
          "method": "org.eclipse.jface.dialogs.ProgressMonitorDialog.finishedRun",
          "source": "ProgressMonitorDialog.java:477"
        },
        {
          "method": "org.eclipse.jface.dialogs.ProgressMonitorDialog.run",
          "source": "ProgressMonitorDialog.java:400"
        },
        {
          "method": "org.eclipse.ui.internal.activities.ws.WorkbenchActivitySupport$4.run",
          "source": "WorkbenchActivitySupport.java:199"
        },
        {
          "method": "org.eclipse.swt.custom.BusyIndicator.showWhile",
          "source": "BusyIndicator.java:69"
        },
        {
          "method": "org.eclipse.ui.internal.activities.ws.WorkbenchActivitySupport$3.run",
          "source": "WorkbenchActivitySupport.java:192"
        },
        {
          "method": "org.eclipse.swt.widgets.RunnableLock.run",
          "source": "RunnableLock.java:35"
        },
        {
          "method": "org.eclipse.swt.widgets.Synchronizer.runAsyncMessages",
          "source": "Synchronizer.java:106"
        },
        {
          "method": "org.eclipse.swt.widgets.Display.runAsyncMessages",
          "source": "Display.java:2572"
        },
        {
          "method": "org.eclipse.swt.widgets.Display.readAndDispatch",
          "source": "Display.java:2301"
        },
        {
          "method": "org.eclipse.swt.widgets.Display.release",
          "source": "Display.java:2350"
        },
        {
          "method": "org.eclipse.swt.graphics.Device.dispose",
          "source": "Device.java:174"
        },
        {
          "method": "org.eclipse.ui.internal.ide.IDEApplication.run",
          "source": "IDEApplication.java:112"
        },
        {
          "method": "org.eclipse.core.internal.runtime.PlatformActivator$1.run",
          "source": "PlatformActivator.java:335"
        },
        {
          "method": "org.eclipse.core.runtime.adaptor.EclipseStarter.run",
          "source": "EclipseStarter.java:273"
        },
        {
          "method": "org.eclipse.core.runtime.adaptor.EclipseStarter.run",
          "source": "EclipseStarter.java:129"
        },
        {
          "method": "sun.reflect.NativeMethodAccessorImpl.invoke0",
          "source": "Native Method"
        },
        {
          "method": "sun.reflect.NativeMethodAccessorImpl.invoke",
          "source": "NativeMethodAccessorImpl.java:39"
        },
        {
          "method": "sun.reflect.DelegatingMethodAccessorImpl.invoke",
          "source": "DelegatingMethodAccessorImpl.java:25"
        },
        {
          "method": "java.lang.reflect.Method.invoke",
          "source": "Method.java:324"
        },
        {
          "method": "org.eclipse.core.launcher.Main.basicRun",
          "source": "Main.java:183"
        },
        {
          "method": "org.eclipse.core.launcher.Main.run",
          "source": "Main.java:644"
        },
        {
          "method": "org.eclipse.core.launcher.Main.main",
          "source": "Main.java:628"
        }
      ],
      "number": 0,
      "commentIndex": 0,
      "bugId": "72578",
      "date": "2004-08-25T10:20:15+02:00",
      "product": "Platform",
      "component": "SWT",
      "severity": "normal"
    }
  ],
  "groupId": "72578",
  "bugId": "72578",
  "date": "2004-08-25T10:20:15+02:00",
  "product": "Platform",
  "component": "SWT",
  "severity": "normal"
}