{
  "comments": [
    "EClassImpl has the following problem with multi threaded read access \n\njava.lang.UnsupportedOperationException\n        at\norg.eclipse.emf.common.util.BasicEList$UnmodifiableEList.shrink(BasicEList.java:1668)\n        at\norg.eclipse.emf.ecore.impl.EClassImpl.getEAllReferences(EClassImpl.java:262)\n        at\norg.eclipse.emf.ecore.impl.EClassImpl.getEAllReferences(EClassImpl.java:251)\n        at\norg.eclipse.emf.ecore.impl.EClassImpl.getEAllContainments(EClassImpl.java:572)\n        at\norg.eclipse.hyades.logging.events.cbe.util.EventValidation.validateRequiredProperties(EventValidation.java:75)\n        at\norg.eclipse.hyades.logging.events.cbe.impl.SituationTypeImpl.validate(SituationTypeImpl.java:199)\n        at\norg.eclipse.hyades.logging.events.cbe.impl.ReportSituationImpl.validate(ReportSituationImpl.java:202)\n        at\norg.eclipse.hyades.logging.events.cbe.impl.SituationImpl.validate(SituationImpl.java:477)\n        at\norg.eclipse.hyades.logging.events.cbe.impl.CommonBaseEventImpl.validate(CommonBaseEventImpl.java:2144)\n        at Worker.run(Worker.java:33)\n\nEObject eObject \u003d .....\nEClass eClass \u003d elementInstance.eClass(); \nList containments \u003d eClass.getEAllContainments();",
    "The fix is committed to CVS.",
    "The fix is available in the M200408260844 build."
  ],
  "commentCreationDates": [
    "2004-08-26T13:20:31+02:00",
    "2004-08-26T14:12:42+02:00",
    "2004-08-26T16:00:23+02:00"
  ],
  "traces": [
    {
      "exceptionType": "java.lang.UnsupportedOperationException",
      "elements": [
        {
          "method": "org.eclipse.emf.common.util.BasicEList$UnmodifiableEList.shrink",
          "source": "BasicEList.java:1668"
        },
        {
          "method": "org.eclipse.emf.ecore.impl.EClassImpl.getEAllReferences",
          "source": "EClassImpl.java:262"
        },
        {
          "method": "org.eclipse.emf.ecore.impl.EClassImpl.getEAllReferences",
          "source": "EClassImpl.java:251"
        },
        {
          "method": "org.eclipse.emf.ecore.impl.EClassImpl.getEAllContainments",
          "source": "EClassImpl.java:572"
        },
        {
          "method": "org.eclipse.hyades.logging.events.cbe.util.EventValidation.validateRequiredProperties",
          "source": "EventValidation.java:75"
        },
        {
          "method": "org.eclipse.hyades.logging.events.cbe.impl.SituationTypeImpl.validate",
          "source": "SituationTypeImpl.java:199"
        },
        {
          "method": "org.eclipse.hyades.logging.events.cbe.impl.ReportSituationImpl.validate",
          "source": "ReportSituationImpl.java:202"
        },
        {
          "method": "org.eclipse.hyades.logging.events.cbe.impl.SituationImpl.validate",
          "source": "SituationImpl.java:477"
        },
        {
          "method": "org.eclipse.hyades.logging.events.cbe.impl.CommonBaseEventImpl.validate",
          "source": "CommonBaseEventImpl.java:2144"
        },
        {
          "method": "Worker.run",
          "source": "Worker.java:33"
        }
      ],
      "number": 0,
      "commentIndex": 0,
      "bugId": "72675",
      "date": "2004-08-26T13:20:31+02:00",
      "product": "EMF",
      "component": "Core",
      "severity": "normal"
    }
  ],
  "groupId": "72675",
  "bugId": "72675",
  "date": "2004-08-26T13:20:31+02:00",
  "product": "EMF",
  "component": "Core",
  "severity": "normal"
}