{
  "comments": [
    "I got the following NPE running the test suite:\n\n!ENTRY org.eclipse.core.runtime 4 2 Aug 27, 2004 10:10:31.843\n!MESSAGE An internal error occurred during: \"Debug\".\n!STACK 0\njava.lang.NullPointerException\n\tat \norg.eclipse.jdt.internal.debug.core.model.JDIDebugTarget.isOutOfSynch\n(JDIDebugTarget.java:733)\n\tat org.eclipse.jdt.internal.debug.ui.JDIModelPresentation.getText\n(JDIModelPresentation.java:234)\n\tat org.eclipse.debug.internal.ui.LazyModelPresentation.getText\n(LazyModelPresentation.java:101)\n\tat org.eclipse.debug.internal.ui.DelegatingModelPresentation.getText\n(DelegatingModelPresentation.java:158)\n\tat \norg.eclipse.debug.internal.ui.views.DebugViewLabelDecorator$LabelJob.run\n(DebugViewLabelDecorator.java:326)\n\tat org.eclipse.core.internal.jobs.Worker.run(Worker.java:66)\n\nIt looks like the UI was trying to render a debug target that was in the \nprocess of terminating/cleaning up. The method JDIDebugTarget.removeAllThreads\n() does not obtain a lock on the thread list before clearing it, and thus, \nanyone else building a thread iterator can get null entries - i.e. the list \ncan be in the process of being cleared while buiding the thread iterator.\n\nTo make the code more readable, I removed the gettor for #getThreadList(). \nThe \"clear\" operation now obtains the lock on the thread list before clearing.",
    "Fixed in JDIDebugTarget.",
    "Please verify, Kevin.",
    "verified"
  ],
  "commentCreationDates": [
    "2004-08-27T17:43:24+02:00",
    "2004-08-27T17:53:59+02:00",
    "2004-08-27T17:54:12+02:00",
    "2004-09-01T21:11:37+02:00"
  ],
  "traces": [
    {
      "exceptionType": "java.lang.NullPointerException",
      "elements": [
        {
          "method": "org.eclipse.jdt.internal.debug.core.model.JDIDebugTarget.isOutOfSynch",
          "source": "JDIDebugTarget.java:733"
        },
        {
          "method": "org.eclipse.jdt.internal.debug.ui.JDIModelPresentation.getText",
          "source": "JDIModelPresentation.java:234"
        },
        {
          "method": "org.eclipse.debug.internal.ui.LazyModelPresentation.getText",
          "source": "LazyModelPresentation.java:101"
        },
        {
          "method": "org.eclipse.debug.internal.ui.DelegatingModelPresentation.getText",
          "source": "DelegatingModelPresentation.java:158"
        },
        {
          "method": "org.eclipse.debug.internal.ui.views.DebugViewLabelDecorator$LabelJob.run",
          "source": "DebugViewLabelDecorator.java:326"
        },
        {
          "method": "org.eclipse.core.internal.jobs.Worker.run",
          "source": "Worker.java:66"
        }
      ],
      "number": 0,
      "commentIndex": 0,
      "bugId": "72792",
      "date": "2004-08-27T17:43:24+02:00",
      "product": "JDT",
      "component": "Debug",
      "severity": "normal"
    }
  ],
  "groupId": "72792",
  "bugId": "72792",
  "date": "2004-08-27T17:43:24+02:00",
  "product": "JDT",
  "component": "Debug",
  "severity": "normal"
}