{
  "comments": [
    "If the Clipboard object is called in several thread, not in parallel, for more \nthan one time, the follwing exception will rise:\n\norg.eclipse.swt.SWTError: Cannot set data in clipboard\n                 at org.eclipse.swt.dnd.DND.error(DND.java:225)\n                 at org.eclipse.swt.dnd.DND.error(DND.java:181)\n                 at \norg.eclipse.swt.dnd.Clipboard.setContents(Clipboard.java:290)\n                 at\nde.powerisdnmonitor.ui.swt.controls.CallerEditorControl$6.run(CallerEditorCo\nntrol.java:200)\n                 at \norg.eclipse.swt.widgets.RunnableLock.run(RunnableLock.java:35)\n                 at\norg.eclipse.swt.widgets.Synchronizer.runAsyncMessages(Synchronizer.java:106)\n                 at \norg.eclipse.swt.widgets.Display.runAsyncMessages(Display.java:2749)\n                 at \norg.eclipse.swt.widgets.Display.readAndDispatch(Display.java:2434)\n                 at\nde.powerisdnmonitor.ui.swt.AbstractBaseComponent.show(AbstractBaseComponent.\njava:118)\n                 at\nde.powerisdnmonitor.ui.swt.AbstractCommandApplicationComponent.execute(Abstr\nactCommandApplicationComponent.java:17)\n                 at\nde.powerisdnmonitor.service.trayicon.TrayIcon$ActionHandler$HandlerThread.ru\nn(TrayIcon.java:104)\n\nThe code which caused the problem:\n\nClipboard cb \u003d new Clipboard(Display.getCurrent());\nString textData \u003d \"Hello World !\";\nTextTransfer textTransfer \u003d TextTransfer.getInstance();\ncb.setContents(new Object[]{textData}, new \nTransfer[]{textTransfer});\ncb.dispose();\n\nThe exception will occur if the code is run multiple times.",
    "Fixed for 3.1 in HEAD \u003e Oct 6, 2004"
  ],
  "commentCreationDates": [
    "2004-09-01T15:52:43+02:00",
    "2004-10-06T23:19:40+02:00"
  ],
  "traces": [
    {
      "exceptionType": "org.eclipse.swt.SWTError",
      "message": "Cannot set data in clipboard",
      "elements": [
        {
          "method": "org.eclipse.swt.dnd.DND.error",
          "source": "DND.java:225"
        },
        {
          "method": "org.eclipse.swt.dnd.DND.error",
          "source": "DND.java:181"
        },
        {
          "method": "org.eclipse.swt.dnd.Clipboard.setContents",
          "source": "Clipboard.java:290"
        },
        {
          "method": "de.powerisdnmonitor.ui.swt.controls.CallerEditorControl$6.run",
          "source": "CallerEditorCo ntrol.java:200"
        },
        {
          "method": "org.eclipse.swt.widgets.RunnableLock.run",
          "source": "RunnableLock.java:35"
        },
        {
          "method": "org.eclipse.swt.widgets.Synchronizer.runAsyncMessages",
          "source": "Synchronizer.java:106"
        },
        {
          "method": "org.eclipse.swt.widgets.Display.runAsyncMessages",
          "source": "Display.java:2749"
        },
        {
          "method": "org.eclipse.swt.widgets.Display.readAndDispatch",
          "source": "Display.java:2434"
        },
        {
          "method": "de.powerisdnmonitor.ui.swt.AbstractBaseComponent.show",
          "source": "AbstractBaseComponent. java:118"
        },
        {
          "method": "de.powerisdnmonitor.ui.swt.AbstractCommandApplicationComponent.execute",
          "source": "Abstr actCommandApplicationComponent.java:17"
        },
        {
          "method": "de.powerisdnmonitor.service.trayicon.TrayIcon$ActionHandler$HandlerThread.run",
          "source": "TrayIcon.java:104"
        }
      ],
      "number": 0,
      "commentIndex": 0,
      "bugId": "73052",
      "date": "2004-09-01T15:52:43+02:00",
      "product": "Platform",
      "component": "SWT",
      "severity": "normal"
    }
  ],
  "groupId": "73052",
  "bugId": "73052",
  "date": "2004-09-01T15:52:43+02:00",
  "product": "Platform",
  "component": "SWT",
  "severity": "normal"
}