{
  "comments": [
    "Stable Build 20011219\n\nFirst attempt to debug some code (with one breakpoint hit), the debugger almost \nfreezes, dumping the following exceptions in the console (with a long delay).\n\njava.lang.NullPointerException\n        at org.eclipse.jdt.internal.debug.ui.Timer.dispose(Timer.java:112)\n        at \norg.eclipse.jdt.internal.debug.ui.JDIModelPresentation$DefaultJavaValueDetailPro\nvider.timeout(JDIModelPresentation.java:1302)\n        at org.eclipse.jdt.internal.debug.ui.Timer$1.run(Timer.java:62)\n        at java.lang.Thread.run(Thread.java:539)\njava.lang.NullPointerException\n        at org.eclipse.jdt.internal.debug.ui.Timer.dispose(Timer.java:112)\n        at org.eclipse.jdt.internal.debug.ui.JDIModelPresentation$1.run\n(JDIModelPresentation.java:1337)\n        at java.lang.Thread.run(Thread.java:539)\nLog: Mon Jan 07 16:42:24 CET 2002\n4 org.eclipse.jdt.launching 4 org.eclipse.jdi.TimeoutException occurred \nretrieving source name debug attribute.\norg.eclipse.debug.core.DebugException[5010]: org.eclipse.jdi.TimeoutException\n        at org.eclipse.jdi.internal.connect.PacketReceiveManager.getReply\n(PacketReceiveManager.java:120)\n        at org.eclipse.jdi.internal.connect.PacketReceiveManager.getReply\n(PacketReceiveManager.java:130)\n        at org.eclipse.jdi.internal.MirrorImpl.requestVM(MirrorImpl.java:155)\n        at org.eclipse.jdi.internal.MirrorImpl.requestVM(MirrorImpl.java:173)\n        at org.eclipse.jdi.internal.MethodImpl.isObsolete(MethodImpl.java:654)\n        at org.eclipse.jdi.internal.MethodImpl.getLineTable(MethodImpl.java:110)\n        at org.eclipse.jdi.internal.MethodImpl.location(MethodImpl.java:502)\n        at org.eclipse.jdt.internal.debug.core.JDIStackFrame.getSourceName\n(JDIStackFrame.java:775)\n        at org.eclipse.jdt.launching.ProjectSourceLocator.getSourceElement\n(ProjectSourceLocator.java:138)\n        at \norg.eclipse.jdt.internal.debug.ui.launcher.JavaUISourceLocator.getSourceElement\n(JavaUISourceLocator.java:43)\n        at org.eclipse.debug.internal.ui.DebugView.showMarkerForCurrentSelection\n(DebugView.java:228)\n        at org.eclipse.debug.internal.ui.DebugView.selectionChanged\n(DebugView.java:191)\n        at org.eclipse.jface.viewers.Viewer.fireSelectionChanged\n(Viewer.java:147)\n        at org.eclipse.jface.viewers.StructuredViewer.updateSelection\n(StructuredViewer.java:978)\n        at org.eclipse.jface.viewers.StructuredViewer.handleSelect\n(StructuredViewer.java:465)\n        at org.eclipse.jface.viewers.AbstractTreeViewer$1.widgetSelected\n(AbstractTreeViewer.java:624)\n        at org.eclipse.swt.widgets.TypedListener.handleEvent\n(TypedListener.java:85)\n        at org.eclipse.swt.widgets.EventTable.sendEvent(EventTable.java:74)\n        at org.eclipse.swt.widgets.Widget.notifyListeners(Widget.java:635)\n        at org.eclipse.swt.widgets.Display.runDeferredEvents(Display.java:1408)\n        at org.eclipse.swt.widgets.Display.readAndDispatch(Display.java:1200)\n        at org.eclipse.ui.internal.Workbench.runEventLoop(Workbench.java:815)\n        at org.eclipse.ui.internal.Workbench.run(Workbench.java:798)\n        at org.eclipse.core.internal.boot.InternalBootLoader.run\n(InternalBootLoader.java:821)\n        at org.eclipse.core.boot.BootLoader.run(BootLoader.java:285)\n        at sun.reflect.NativeMethodAccessorImpl.invoke0(Native Method)\n        at sun.reflect.NativeMethodAccessorImpl.invoke\n(NativeMethodAccessorImpl.java:42)\n        at sun.reflect.DelegatingMethodAccessorImpl.invoke\n(DelegatingMethodAccessorImpl.java:28)\n        at java.lang.reflect.Method.invoke(Method.java:327)\n        at org.eclipse.core.launcher.Main.basicRun(Main.java:151)\n        at org.eclipse.core.launcher.Main.run(Main.java:502)\n        at org.eclipse.core.launcher.UIMain.main(UIMain.java:52)\n        4 org.eclipse.jdt.debug 5010 org.eclipse.jdi.TimeoutException occurred \nretrieving source name debug attribute.",
    "Forgot to mention I was running a JDK1.4beta3 VM.\nTried again with J9 and it did behave ok.",
    "Fixed. There were two calls to Timer.dispose(), and the timer did not protect \nitself from a double-dispose.",
    "Please verify.",
    "Verified."
  ],
  "commentCreationDates": [
    "2002-01-07T15:32:31+01:00",
    "2002-01-07T15:34:19+01:00",
    "2002-01-21T16:48:42+01:00",
    "2002-01-21T16:50:52+01:00",
    "2002-01-21T16:58:05+01:00"
  ],
  "traces": [
    {
      "exceptionType": "java.lang.NullPointerException",
      "elements": [
        {
          "method": "org.eclipse.jdt.internal.debug.ui.Timer.dispose",
          "source": "Timer.java:112"
        },
        {
          "method": "org.eclipse.jdt.internal.debug.ui.JDIModelPresentation$DefaultJavaValueDetailProvider.timeout",
          "source": "JDIModelPresentation.java:1302"
        },
        {
          "method": "org.eclipse.jdt.internal.debug.ui.Timer$1.run",
          "source": "Timer.java:62"
        },
        {
          "method": "java.lang.Thread.run",
          "source": "Thread.java:539"
        }
      ],
      "number": 0,
      "commentIndex": 0,
      "bugId": "7310",
      "date": "2002-01-07T15:32:31+01:00",
      "product": "JDT",
      "component": "Debug",
      "severity": "normal"
    },
    {
      "exceptionType": "java.lang.NullPointerException",
      "elements": [
        {
          "method": "org.eclipse.jdt.internal.debug.ui.Timer.dispose",
          "source": "Timer.java:112"
        },
        {
          "method": "org.eclipse.jdt.internal.debug.ui.JDIModelPresentation$1.run",
          "source": "JDIModelPresentation.java:1337"
        },
        {
          "method": "java.lang.Thread.run",
          "source": "Thread.java:539"
        }
      ],
      "number": 1,
      "commentIndex": 0,
      "bugId": "7310",
      "date": "2002-01-07T15:32:31+01:00",
      "product": "JDT",
      "component": "Debug",
      "severity": "normal"
    },
    {
      "exceptionType": "org.eclipse.jdi.TimeoutException",
      "elements": [
        {
          "method": "org.eclipse.jdi.internal.connect.PacketReceiveManager.getReply",
          "source": "PacketReceiveManager.java:120"
        },
        {
          "method": "org.eclipse.jdi.internal.connect.PacketReceiveManager.getReply",
          "source": "PacketReceiveManager.java:130"
        },
        {
          "method": "org.eclipse.jdi.internal.MirrorImpl.requestVM",
          "source": "MirrorImpl.java:155"
        },
        {
          "method": "org.eclipse.jdi.internal.MirrorImpl.requestVM",
          "source": "MirrorImpl.java:173"
        },
        {
          "method": "org.eclipse.jdi.internal.MethodImpl.isObsolete",
          "source": "MethodImpl.java:654"
        },
        {
          "method": "org.eclipse.jdi.internal.MethodImpl.getLineTable",
          "source": "MethodImpl.java:110"
        },
        {
          "method": "org.eclipse.jdi.internal.MethodImpl.location",
          "source": "MethodImpl.java:502"
        },
        {
          "method": "org.eclipse.jdt.internal.debug.core.JDIStackFrame.getSourceName",
          "source": "JDIStackFrame.java:775"
        },
        {
          "method": "org.eclipse.jdt.launching.ProjectSourceLocator.getSourceElement",
          "source": "ProjectSourceLocator.java:138"
        },
        {
          "method": "org.eclipse.jdt.internal.debug.ui.launcher.JavaUISourceLocator.getSourceElement",
          "source": "JavaUISourceLocator.java:43"
        },
        {
          "method": "org.eclipse.debug.internal.ui.DebugView.showMarkerForCurrentSelection",
          "source": "DebugView.java:228"
        },
        {
          "method": "org.eclipse.debug.internal.ui.DebugView.selectionChanged",
          "source": "DebugView.java:191"
        },
        {
          "method": "org.eclipse.jface.viewers.Viewer.fireSelectionChanged",
          "source": "Viewer.java:147"
        },
        {
          "method": "org.eclipse.jface.viewers.StructuredViewer.updateSelection",
          "source": "StructuredViewer.java:978"
        },
        {
          "method": "org.eclipse.jface.viewers.StructuredViewer.handleSelect",
          "source": "StructuredViewer.java:465"
        },
        {
          "method": "org.eclipse.jface.viewers.AbstractTreeViewer$1.widgetSelected",
          "source": "AbstractTreeViewer.java:624"
        },
        {
          "method": "org.eclipse.swt.widgets.TypedListener.handleEvent",
          "source": "TypedListener.java:85"
        },
        {
          "method": "org.eclipse.swt.widgets.EventTable.sendEvent",
          "source": "EventTable.java:74"
        },
        {
          "method": "org.eclipse.swt.widgets.Widget.notifyListeners",
          "source": "Widget.java:635"
        },
        {
          "method": "org.eclipse.swt.widgets.Display.runDeferredEvents",
          "source": "Display.java:1408"
        },
        {
          "method": "org.eclipse.swt.widgets.Display.readAndDispatch",
          "source": "Display.java:1200"
        },
        {
          "method": "org.eclipse.ui.internal.Workbench.runEventLoop",
          "source": "Workbench.java:815"
        },
        {
          "method": "org.eclipse.ui.internal.Workbench.run",
          "source": "Workbench.java:798"
        },
        {
          "method": "org.eclipse.core.internal.boot.InternalBootLoader.run",
          "source": "InternalBootLoader.java:821"
        },
        {
          "method": "org.eclipse.core.boot.BootLoader.run",
          "source": "BootLoader.java:285"
        },
        {
          "method": "sun.reflect.NativeMethodAccessorImpl.invoke0",
          "source": "Native Method"
        },
        {
          "method": "sun.reflect.NativeMethodAccessorImpl.invoke",
          "source": "NativeMethodAccessorImpl.java:42"
        },
        {
          "method": "sun.reflect.DelegatingMethodAccessorImpl.invoke",
          "source": "DelegatingMethodAccessorImpl.java:28"
        },
        {
          "method": "java.lang.reflect.Method.invoke",
          "source": "Method.java:327"
        },
        {
          "method": "org.eclipse.core.launcher.Main.basicRun",
          "source": "Main.java:151"
        },
        {
          "method": "org.eclipse.core.launcher.Main.run",
          "source": "Main.java:502"
        },
        {
          "method": "org.eclipse.core.launcher.UIMain.main",
          "source": "UIMain.java:52"
        }
      ],
      "number": 2,
      "commentIndex": 0,
      "bugId": "7310",
      "date": "2002-01-07T15:32:31+01:00",
      "product": "JDT",
      "component": "Debug",
      "severity": "normal"
    }
  ],
  "groupId": "7310",
  "bugId": "7310",
  "date": "2002-01-07T15:32:31+01:00",
  "product": "JDT",
  "component": "Debug",
  "severity": "normal"
}