{
  "comments": [
    "I am developing plugins for various IDEs. We recently switched from Swing to \nSWT. Now I am trying to embedd our products (SWT components) in various IDEs\n(Swing components).\n\nEmbedding of SWT in Swing is working fine in stand alone application. But when \nI deploy my plugin in IDE eg IntelliJ IDEA, following error is thrown\n\norg.eclipse.swt.SWTError: No more handles\n        at org.eclipse.swt.SWT.error(SWT.java:2717)\n        at org.eclipse.swt.SWT.error(SWT.java:2616)\n        at org.eclipse.swt.SWT.error(SWT.java:2587)\n        at org.eclipse.swt.widgets.Widget.error(Widget.java:381)\n        at org.eclipse.swt.widgets.Control.createHandle(Control.java:462)\n        at org.eclipse.swt.widgets.Composite.createHandle(Composite.java:173)\n        at org.eclipse.swt.widgets.Decorations.createHandle(Decorations.java:320\n)\n        at org.eclipse.swt.widgets.Shell.createHandle(Shell.java:436)\n        at org.eclipse.swt.widgets.Control.createWidget(Control.java:477)\n        at org.eclipse.swt.widgets.Scrollable.createWidget(Scrollable.java:129)\n        at org.eclipse.swt.widgets.Decorations.createWidget(Decorations.java:327\n)\n        at org.eclipse.swt.widgets.Shell.\u003cinit\u003e(Shell.java:251)\n        at org.eclipse.swt.widgets.Shell.win32_new(Shell.java:341)\n        at org.eclipse.swt.awt.SWT_AWT.new_Shell(SWT_AWT.java:269)\n\nI am getting the same exception in JBuilder and NetBeans also. I watched the \nprocesses in TaskManager, Handle count keeps changing for this processes even \nafter I get this error. That means Windows or process has not reached limit (if \nthere is any).\n\nI am not able to figure out the reason :(\nI might be able to fix it if I find the reason.\n\n-Sudhan.",
    "You\u0027ll need to provide some code (preferrably small) that shows the problem \nhappening; the stack trace alone does not provide enough context information to \nfigure this out.\n",
    "\n\n*** This bug has been marked as a duplicate of 69381 ***"
  ],
  "commentCreationDates": [
    "2004-09-02T06:43:52+02:00",
    "2004-09-02T15:26:07+02:00",
    "2004-09-02T18:08:24+02:00"
  ],
  "traces": [
    {
      "exceptionType": "org.eclipse.swt.SWTError",
      "message": "No more handles",
      "elements": [
        {
          "method": "org.eclipse.swt.SWT.error",
          "source": "SWT.java:2717"
        },
        {
          "method": "org.eclipse.swt.SWT.error",
          "source": "SWT.java:2616"
        },
        {
          "method": "org.eclipse.swt.SWT.error",
          "source": "SWT.java:2587"
        },
        {
          "method": "org.eclipse.swt.widgets.Widget.error",
          "source": "Widget.java:381"
        },
        {
          "method": "org.eclipse.swt.widgets.Control.createHandle",
          "source": "Control.java:462"
        },
        {
          "method": "org.eclipse.swt.widgets.Composite.createHandle",
          "source": "Composite.java:173"
        },
        {
          "method": "org.eclipse.swt.widgets.Decorations.createHandle",
          "source": "Decorations.java:320 "
        },
        {
          "method": "org.eclipse.swt.widgets.Shell.createHandle",
          "source": "Shell.java:436"
        },
        {
          "method": "org.eclipse.swt.widgets.Control.createWidget",
          "source": "Control.java:477"
        },
        {
          "method": "org.eclipse.swt.widgets.Scrollable.createWidget",
          "source": "Scrollable.java:129"
        },
        {
          "method": "org.eclipse.swt.widgets.Decorations.createWidget",
          "source": "Decorations.java:327 "
        },
        {
          "method": "org.eclipse.swt.widgets.Shell.\u003cinit\u003e",
          "source": "Shell.java:251"
        },
        {
          "method": "org.eclipse.swt.widgets.Shell.win32_new",
          "source": "Shell.java:341"
        },
        {
          "method": "org.eclipse.swt.awt.SWT_AWT.new_Shell",
          "source": "SWT_AWT.java:269"
        }
      ],
      "number": 0,
      "commentIndex": 0,
      "bugId": "73124",
      "duplicateId": "69381",
      "date": "2004-09-02T06:43:52+02:00",
      "product": "Platform",
      "component": "SWT",
      "severity": "blocker"
    }
  ],
  "groupId": "69381",
  "bugId": "73124",
  "duplicateId": "69381",
  "date": "2004-09-02T06:43:52+02:00",
  "product": "Platform",
  "component": "SWT",
  "severity": "blocker"
}