{
  "comments": [
    "The testcase testSimpleHcr is failing (infact it\u0027s an error) with a Null \nPointer Exception on both Linux and HP-UX PA_RISC.\n\nFollowing is the exception when ran as automated test suite.\ntestSimpleHcr Error N/A \n\njava.lang.NullPointerException\nat org.eclipse.jdt.debug.tests.core.HcrTests.testSimpleHcr(HcrTests.java:72)\nat sun.reflect.NativeMethodAccessorImpl.invoke0(Native Method)\nat sun.reflect.NativeMethodAccessorImpl.invoke(NativeMethodAccessorImpl.java:39)\nat sun.reflect.DelegatingMethodAccessorImpl.invoke\n(DelegatingMethodAccessorImpl.java:25)\nat org.eclipse.jdt.debug.tests.AutomatedSuite$1.run(AutomatedSuite.java:178)\nat java.lang.Thread.run(Thread.java:534) \n\nWhen the test case is ran as jUnit Plug-in test from Eclipse it is failing with \nthe message \"Program didnot suspend, launch terminated\".\n \nI have drilled down the problem to DebugEventWaiter.java where \"fEvent\" is not \ninitalized. In the method waitForEvent, there is a if condition which checks \nfor the value of fEvent. Since this variable is getting null and this is \nreturned to the variable suspendee in AbstractDebugTest.java.\nI am sure that the variable fEvent is not initialized in some other code \nfragment in the test plug-in.\n\n-Ragavendran.",
    "What VM are you testing on? Does it support HCR? Does HCR work when you try it \nmanually?",
    "Closing without more info."
  ],
  "commentCreationDates": [
    "2004-09-02T15:30:26+02:00",
    "2004-09-02T16:53:48+02:00",
    "2004-09-10T17:32:36+02:00"
  ],
  "traces": [
    {
      "exceptionType": "java.lang.NullPointerException",
      "elements": [
        {
          "method": "org.eclipse.jdt.debug.tests.core.HcrTests.testSimpleHcr",
          "source": "HcrTests.java:72"
        },
        {
          "method": "sun.reflect.NativeMethodAccessorImpl.invoke0",
          "source": "Native Method"
        },
        {
          "method": "sun.reflect.NativeMethodAccessorImpl.invoke",
          "source": "NativeMethodAccessorImpl.java:39"
        },
        {
          "method": "sun.reflect.DelegatingMethodAccessorImpl.invoke",
          "source": "DelegatingMethodAccessorImpl.java:25"
        },
        {
          "method": "org.eclipse.jdt.debug.tests.AutomatedSuite$1.run",
          "source": "AutomatedSuite.java:178"
        },
        {
          "method": "java.lang.Thread.run",
          "source": "Thread.java:534"
        }
      ],
      "number": 0,
      "commentIndex": 0,
      "bugId": "73149",
      "date": "2004-09-02T15:30:26+02:00",
      "product": "JDT",
      "component": "Debug",
      "severity": "major"
    }
  ],
  "groupId": "73149",
  "bugId": "73149",
  "date": "2004-09-02T15:30:26+02:00",
  "product": "JDT",
  "component": "Debug",
  "severity": "major"
}