{
  "comments": [
    "I200409011200 + plugin-export from 20040902_1026\n\nI don\u0027t have a reproducible case and I don\u0027t remember what I was working on:\n\n!MESSAGE Failed to execute runnable (java.lang.ArrayIndexOutOfBoundsException: 3\n)\n!STACK 0\norg.eclipse.swt.SWTException: Failed to execute runnable (java.lang.ArrayIndexOu\ntOfBoundsException: 3)\n        at org.eclipse.swt.SWT.error(SWT.java:2691)\n        at org.eclipse.swt.SWT.error(SWT.java:2616)\n        at org.eclipse.swt.widgets.Synchronizer.runAsyncMessages(Synchronizer.ja\nva:109)\n        at org.eclipse.swt.widgets.Display.runAsyncMessages(Display.java:2760)\n        at org.eclipse.swt.widgets.Display.readAndDispatch(Display.java:2445)\n        at org.eclipse.ui.internal.Workbench.runEventLoop(Workbench.java:1435)\n        at org.eclipse.ui.internal.Workbench.runUI(Workbench.java:1406)\n        at org.eclipse.ui.internal.Workbench.createAndRunWorkbench(Workbench.jav\na:263)\n        at org.eclipse.ui.PlatformUI.createAndRunWorkbench(PlatformUI.java:144)\n        at org.eclipse.ui.internal.ide.IDEApplication.run(IDEApplication.java:10\n2)\n        at org.eclipse.core.internal.runtime.PlatformActivator$1.run(PlatformAct\nivator.java:335)\n        at org.eclipse.core.runtime.adaptor.EclipseStarter.run(EclipseStarter.ja\nva:273)\n        at org.eclipse.core.runtime.adaptor.EclipseStarter.run(EclipseStarter.ja\nva:129)\n        at sun.reflect.NativeMethodAccessorImpl.invoke0(Native Method)\n        at sun.reflect.NativeMethodAccessorImpl.invoke(NativeMethodAccessorImpl.\njava:39)\n        at sun.reflect.DelegatingMethodAccessorImpl.invoke(DelegatingMethodAcces\nsorImpl.java:25)\n        at java.lang.reflect.Method.invoke(Method.java:324)\n        at org.eclipse.core.launcher.Main.basicRun(Main.java:183)\n        at org.eclipse.core.launcher.Main.run(Main.java:644)\n        at org.eclipse.core.launcher.Main.main(Main.java:628)\nFailed to execute runnable (java.lang.ArrayIndexOutOfBoundsException: 3)\n\n!ENTRY org.eclipse.ui 4 4 Sep 06, 2004 10:13:52.966\n!MESSAGE *** SWT nested exception\n*** SWT nested exception\nReason:\n\n!ENTRY org.eclipse.ui 4 0 Sep 06, 2004 10:13:52.976\n!MESSAGE 3\n!STACK 0\njava.lang.ArrayIndexOutOfBoundsException: 3\n        at org.eclipse.jface.text.source.LineNumberRulerColumn.doPaint1(LineNumb\nerRulerColumn.java:786)\n        at org.eclipse.jface.text.source.LineNumberRulerColumn.doubleBufferPaint\n(LineNumberRulerColumn.java:617)\n        at org.eclipse.jface.text.source.LineNumberRulerColumn.redraw(LineNumber\nRulerColumn.java:863)\n        at org.eclipse.jface.text.source.LineNumberRulerColumn$1.run(LineNumberR\nulerColumn.java:360)\n        at org.eclipse.swt.widgets.RunnableLock.run(RunnableLock.java:35)\n        at org.eclipse.swt.widgets.Synchronizer.runAsyncMessages(Synchronizer.ja\nva:106)\n        at org.eclipse.swt.widgets.Display.runAsyncMessages(Display.java:2760)\n        at org.eclipse.swt.widgets.Display.readAndDispatch(Display.java:2445)\n        at org.eclipse.ui.internal.Workbench.runEventLoop(Workbench.java:1435)\n        at org.eclipse.ui.internal.Workbench.runUI(Workbench.java:1406)\n        at org.eclipse.ui.internal.Workbench.createAndRunWorkbench(Workbench.jav\na:263)\n        at org.eclipse.ui.PlatformUI.createAndRunWorkbench(PlatformUI.java:144)\n        at org.eclipse.ui.internal.ide.IDEApplication.run(IDEApplication.java:10\n2)\n        at org.eclipse.core.internal.runtime.PlatformActivator$1.run(PlatformAct\nivator.java:335)\n        at org.eclipse.core.runtime.adaptor.EclipseStarter.run(EclipseStarter.ja\nva:273)\n        at org.eclipse.core.runtime.adaptor.EclipseStarter.run(EclipseStarter.ja\nva:129)\n        at sun.reflect.NativeMethodAccessorImpl.invoke0(Native Method)\n        at sun.reflect.NativeMethodAccessorImpl.invoke(NativeMethodAccessorImpl.\njava:39)\n        at sun.reflect.DelegatingMethodAccessorImpl.invoke(DelegatingMethodAcces\nsorImpl.java:25)\n        at java.lang.reflect.Method.invoke(Method.java:324)\n        at org.eclipse.core.launcher.Main.basicRun(Main.java:183)\n        at org.eclipse.core.launcher.Main.run(Main.java:644)\n        at org.eclipse.core.launcher.Main.main(Main.java:628)",
    "Might be related to bug 66763.\nAny idea which editor you used? If Java editor, was folding enabled?\n\n\n",
    "I don\u0027t remember having used anything else than the Java editor at that time,\nbut am not sure. Yes, I have folding enabled.\n",
    "3.3M1\n\nStill there, but extremely rare, I didn\u0027t remember having seen this.\n\nCaused by: java.lang.ArrayIndexOutOfBoundsException: 3\n        at org.eclipse.jface.text.source.LineNumberRulerColumn.paintLine(LineNum\nberRulerColumn.java:724)\n        at org.eclipse.jface.text.source.LineNumberRulerColumn.doPaint(LineNumbe\nrRulerColumn.java:659)\n        at org.eclipse.jface.text.source.LineNumberChangeRulerColumn.doPaint(Lin\neNumberChangeRulerColumn.java:183)\n        at org.eclipse.jface.text.source.LineNumberRulerColumn.doubleBufferPaint\n(LineNumberRulerColumn.java:609)\n        at org.eclipse.jface.text.source.LineNumberRulerColumn.redraw(LineNumber\nRulerColumn.java:760)\n        at org.eclipse.jface.internal.text.source.DiffPainter.redraw(DiffPainter\n.java:385)\n        at org.eclipse.jface.internal.text.source.DiffPainter.access$2(DiffPaint\ner.java:384)\n        at org.eclipse.jface.internal.text.source.DiffPainter$2.run(DiffPainter.\njava:374)\n        at org.eclipse.swt.widgets.RunnableLock.run(RunnableLock.java:35)\n        at org.eclipse.swt.widgets.Synchronizer.runAsyncMessages(Synchronizer.ja\nva:123)\n        ... 20 more"
  ],
  "commentCreationDates": [
    "2004-09-06T16:45:17+02:00",
    "2004-09-07T16:37:20+02:00",
    "2004-09-07T17:11:52+02:00",
    "2006-09-05T10:49:53+02:00"
  ],
  "traces": [
    {
      "exceptionType": "tOfBoundsException",
      "message": "3)",
      "elements": [
        {
          "method": "org.eclipse.swt.SWT.error",
          "source": "SWT.java:2691"
        },
        {
          "method": "org.eclipse.swt.SWT.error",
          "source": "SWT.java:2616"
        },
        {
          "method": "org.eclipse.swt.widgets.Synchronizer.runAsyncMessages",
          "source": "Synchronizer.ja va:109"
        },
        {
          "method": "org.eclipse.swt.widgets.Display.runAsyncMessages",
          "source": "Display.java:2760"
        },
        {
          "method": "org.eclipse.swt.widgets.Display.readAndDispatch",
          "source": "Display.java:2445"
        },
        {
          "method": "org.eclipse.ui.internal.Workbench.runEventLoop",
          "source": "Workbench.java:1435"
        },
        {
          "method": "org.eclipse.ui.internal.Workbench.runUI",
          "source": "Workbench.java:1406"
        },
        {
          "method": "org.eclipse.ui.internal.Workbench.createAndRunWorkbench",
          "source": "Workbench.jav a:263"
        },
        {
          "method": "org.eclipse.ui.PlatformUI.createAndRunWorkbench",
          "source": "PlatformUI.java:144"
        },
        {
          "method": "org.eclipse.ui.internal.ide.IDEApplication.run",
          "source": "IDEApplication.java:10 2"
        },
        {
          "method": "org.eclipse.core.internal.runtime.PlatformActivator$1.run",
          "source": "PlatformAct ivator.java:335"
        },
        {
          "method": "org.eclipse.core.runtime.adaptor.EclipseStarter.run",
          "source": "EclipseStarter.ja va:273"
        },
        {
          "method": "org.eclipse.core.runtime.adaptor.EclipseStarter.run",
          "source": "EclipseStarter.ja va:129"
        },
        {
          "method": "sun.reflect.NativeMethodAccessorImpl.invoke0",
          "source": "Native Method"
        },
        {
          "method": "sun.reflect.NativeMethodAccessorImpl.invoke",
          "source": "NativeMethodAccessorImpl. java:39"
        },
        {
          "method": "sun.reflect.DelegatingMethodAccessorImpl.invoke",
          "source": "DelegatingMethodAcces sorImpl.java:25"
        },
        {
          "method": "java.lang.reflect.Method.invoke",
          "source": "Method.java:324"
        },
        {
          "method": "org.eclipse.core.launcher.Main.basicRun",
          "source": "Main.java:183"
        },
        {
          "method": "org.eclipse.core.launcher.Main.run",
          "source": "Main.java:644"
        },
        {
          "method": "org.eclipse.core.launcher.Main.main",
          "source": "Main.java:628"
        }
      ],
      "number": 0,
      "commentIndex": 0,
      "bugId": "73329",
      "date": "2004-09-06T16:45:17+02:00",
      "product": "Platform",
      "component": "Text",
      "severity": "normal"
    },
    {
      "exceptionType": "java.lang.ArrayIndexOutOfBoundsException",
      "message": "3",
      "elements": [
        {
          "method": "org.eclipse.jface.text.source.LineNumberRulerColumn.doPaint1",
          "source": "LineNumb erRulerColumn.java:786"
        },
        {
          "method": "org.eclipse.jface.text.source.LineNumberRulerColumn.doubleBufferPaint",
          "source": "LineNumberRulerColumn.java:617"
        },
        {
          "method": "org.eclipse.jface.text.source.LineNumberRulerColumn.redraw",
          "source": "LineNumber RulerColumn.java:863"
        },
        {
          "method": "org.eclipse.jface.text.source.LineNumberRulerColumn$1.run",
          "source": "LineNumberR ulerColumn.java:360"
        },
        {
          "method": "org.eclipse.swt.widgets.RunnableLock.run",
          "source": "RunnableLock.java:35"
        },
        {
          "method": "org.eclipse.swt.widgets.Synchronizer.runAsyncMessages",
          "source": "Synchronizer.ja va:106"
        },
        {
          "method": "org.eclipse.swt.widgets.Display.runAsyncMessages",
          "source": "Display.java:2760"
        },
        {
          "method": "org.eclipse.swt.widgets.Display.readAndDispatch",
          "source": "Display.java:2445"
        },
        {
          "method": "org.eclipse.ui.internal.Workbench.runEventLoop",
          "source": "Workbench.java:1435"
        },
        {
          "method": "org.eclipse.ui.internal.Workbench.runUI",
          "source": "Workbench.java:1406"
        },
        {
          "method": "org.eclipse.ui.internal.Workbench.createAndRunWorkbench",
          "source": "Workbench.jav a:263"
        },
        {
          "method": "org.eclipse.ui.PlatformUI.createAndRunWorkbench",
          "source": "PlatformUI.java:144"
        },
        {
          "method": "org.eclipse.ui.internal.ide.IDEApplication.run",
          "source": "IDEApplication.java:10 2"
        },
        {
          "method": "org.eclipse.core.internal.runtime.PlatformActivator$1.run",
          "source": "PlatformAct ivator.java:335"
        },
        {
          "method": "org.eclipse.core.runtime.adaptor.EclipseStarter.run",
          "source": "EclipseStarter.ja va:273"
        },
        {
          "method": "org.eclipse.core.runtime.adaptor.EclipseStarter.run",
          "source": "EclipseStarter.ja va:129"
        },
        {
          "method": "sun.reflect.NativeMethodAccessorImpl.invoke0",
          "source": "Native Method"
        },
        {
          "method": "sun.reflect.NativeMethodAccessorImpl.invoke",
          "source": "NativeMethodAccessorImpl. java:39"
        },
        {
          "method": "sun.reflect.DelegatingMethodAccessorImpl.invoke",
          "source": "DelegatingMethodAcces sorImpl.java:25"
        },
        {
          "method": "java.lang.reflect.Method.invoke",
          "source": "Method.java:324"
        },
        {
          "method": "org.eclipse.core.launcher.Main.basicRun",
          "source": "Main.java:183"
        },
        {
          "method": "org.eclipse.core.launcher.Main.run",
          "source": "Main.java:644"
        },
        {
          "method": "org.eclipse.core.launcher.Main.main",
          "source": "Main.java:628"
        }
      ],
      "number": 1,
      "commentIndex": 0,
      "bugId": "73329",
      "date": "2004-09-06T16:45:17+02:00",
      "product": "Platform",
      "component": "Text",
      "severity": "normal"
    },
    {
      "exceptionType": "java.lang.ArrayIndexOutOfBoundsException",
      "message": "3",
      "elements": [
        {
          "method": "org.eclipse.jface.text.source.LineNumberRulerColumn.paintLine",
          "source": "LineNum berRulerColumn.java:724"
        },
        {
          "method": "org.eclipse.jface.text.source.LineNumberRulerColumn.doPaint",
          "source": "LineNumbe rRulerColumn.java:659"
        },
        {
          "method": "org.eclipse.jface.text.source.LineNumberChangeRulerColumn.doPaint",
          "source": "Lin eNumberChangeRulerColumn.java:183"
        },
        {
          "method": "org.eclipse.jface.text.source.LineNumberRulerColumn.doubleBufferPaint",
          "source": "LineNumberRulerColumn.java:609"
        },
        {
          "method": "org.eclipse.jface.text.source.LineNumberRulerColumn.redraw",
          "source": "LineNumber RulerColumn.java:760"
        },
        {
          "method": "org.eclipse.jface.internal.text.source.DiffPainter.redraw",
          "source": "DiffPainter .java:385"
        },
        {
          "method": "org.eclipse.jface.internal.text.source.DiffPainter.access$2",
          "source": "DiffPaint er.java:384"
        },
        {
          "method": "org.eclipse.jface.internal.text.source.DiffPainter$2.run",
          "source": "DiffPainter. java:374"
        },
        {
          "method": "org.eclipse.swt.widgets.RunnableLock.run",
          "source": "RunnableLock.java:35"
        },
        {
          "method": "org.eclipse.swt.widgets.Synchronizer.runAsyncMessages",
          "source": "Synchronizer.ja va:123"
        }
      ],
      "number": 2,
      "commentIndex": 3,
      "bugId": "73329",
      "date": "2006-09-05T10:49:53+02:00",
      "product": "Platform",
      "component": "Text",
      "severity": "normal"
    }
  ],
  "groupId": "73329",
  "bugId": "73329",
  "date": "2004-09-06T16:45:17+02:00",
  "product": "Platform",
  "component": "Text",
  "severity": "normal"
}