{
  "comments": [
    "I200409011200 + plugin-export from 20040902_1026\n\nNot reproducible, but I remember the steps:\n- cursor was after \u0027r\u0027 of \u0027for\u0027 in the code below\n- invoke content assist\n- choose \u0027for - iterate over collection\u0027\n- wait until preview shows up (shows code for iteration over \u0027positions\u0027)\n- hit enter\n-\u003e the exception below\n\n\tpublic void testDeprecatedMemberHighlighting() {\n\t\tSemanticHighlightingManager manager\u003d (SemanticHighlightingManager) new\nAccessor(fEditor).get(\"fSemanticManager\");\n\t\tSemanticHighlightingPresenter presenter\u003d (SemanticHighlightingPresenter) new\nAccessor(manager).get(\"fPresenter\");\n\t\tList positions\u003d new ArrayList();\n\t\tpresenter.addAllPositions(positions);\n\t\tfor\n\t}\n\norg.eclipse.jface.text.BadLocationException\n        at org.eclipse.jface.text.AbstractDocument.replace(AbstractDocument.java\n:990)\n        at org.eclipse.jdt.internal.ui.javaeditor.PartiallySynchronizedDocument.\nreplace(PartiallySynchronizedDocument.java:92)\n        at org.eclipse.jdt.internal.ui.text.template.contentassist.TemplatePropo\nsal.apply(TemplateProposal.java:144)\n        at org.eclipse.jface.text.contentassist.CompletionProposalPopup.insertPr\noposal(CompletionProposalPopup.java:391)\n        at org.eclipse.jface.text.contentassist.CompletionProposalPopup.selectPr\noposalWithMask(CompletionProposalPopup.java:359)\n        at org.eclipse.jface.text.contentassist.CompletionProposalPopup.verifyKe\ny(CompletionProposalPopup.java:686)\n        at org.eclipse.jface.text.contentassist.ContentAssistant$InternalListene\nr.verifyKey(ContentAssistant.java:622)\n        at org.eclipse.jface.text.TextViewer$VerifyKeyListenersManager.verifyKey\n(TextViewer.java:403)\n        at org.eclipse.swt.custom.StyledTextListener.handleEvent(StyledTextListe\nner.java:55)\n        at org.eclipse.swt.widgets.EventTable.sendEvent(EventTable.java:82)\n        at org.eclipse.swt.widgets.Widget.sendEvent(Widget.java:796)\n        at org.eclipse.swt.widgets.Widget.sendEvent(Widget.java:820)\n        at org.eclipse.swt.widgets.Widget.sendEvent(Widget.java:805)\n        at org.eclipse.swt.widgets.Widget.notifyListeners(Widget.java:613)\n        at org.eclipse.swt.custom.StyledText.handleKeyDown(StyledText.java:5000)\n\n        at org.eclipse.swt.custom.StyledText$7.handleEvent(StyledText.java:4747)\n\n        at org.eclipse.swt.widgets.EventTable.sendEvent(EventTable.java:82)\n        at org.eclipse.swt.widgets.Widget.sendEvent(Widget.java:796)\n        at org.eclipse.swt.widgets.Widget.sendEvent(Widget.java:820)\n        at org.eclipse.swt.widgets.Widget.sendEvent(Widget.java:805)\n        at org.eclipse.swt.widgets.Control.sendKeyEvent(Control.java:1735)\n        at org.eclipse.swt.widgets.Control.sendKeyEvent(Control.java:1731)\n        at org.eclipse.swt.widgets.Control.WM_CHAR(Control.java:3072)\n        at org.eclipse.swt.widgets.Control.windowProc(Control.java:2974)\n        at org.eclipse.swt.widgets.Display.windowProc(Display.java:3349)\n        at org.eclipse.swt.internal.win32.OS.DispatchMessageW(Native Method)\n        at org.eclipse.swt.internal.win32.OS.DispatchMessage(OS.java:1472)\n        at org.eclipse.swt.widgets.Display.readAndDispatch(Display.java:2440)\n        at org.eclipse.ui.internal.Workbench.runEventLoop(Workbench.java:1435)\n        at org.eclipse.ui.internal.Workbench.runUI(Workbench.java:1406)\n        at org.eclipse.ui.internal.Workbench.createAndRunWorkbench(Workbench.jav\na:263)\n        at org.eclipse.ui.PlatformUI.createAndRunWorkbench(PlatformUI.java:144)\n        at org.eclipse.ui.internal.ide.IDEApplication.run(IDEApplication.java:10\n2)\n        at org.eclipse.core.internal.runtime.PlatformActivator$1.run(PlatformAct\nivator.java:335)\n        at org.eclipse.core.runtime.adaptor.EclipseStarter.run(EclipseStarter.ja\nva:273)\n        at org.eclipse.core.runtime.adaptor.EclipseStarter.run(EclipseStarter.ja\nva:129)\n        at sun.reflect.NativeMethodAccessorImpl.invoke0(Native Method)\n        at sun.reflect.NativeMethodAccessorImpl.invoke(NativeMethodAccessorImpl.\njava:39)\n        at sun.reflect.DelegatingMethodAccessorImpl.invoke(DelegatingMethodAcces\nsorImpl.java:25)\n        at java.lang.reflect.Method.invoke(Method.java:324)\n        at org.eclipse.core.launcher.Main.basicRun(Main.java:183)\n        at org.eclipse.core.launcher.Main.run(Main.java:644)\n        at org.eclipse.core.launcher.Main.main(Main.java:628)",
    "Test case:\n1. add \"for\"\n2. ctrl+space\n3. select \"for - iterate over collection\"\n4. enter\n\u003d\u003d\u003e empty error dialog and BLE in .log\n\nWorks in 3.0 and 3.0.1.\nWorks with other for templates.\n\n\n",
    "Works for me using N20050616-0010"
  ],
  "commentCreationDates": [
    "2004-09-06T16:57:49+02:00",
    "2004-09-07T16:00:40+02:00",
    "2005-06-16T12:08:47+02:00"
  ],
  "traces": [
    {
      "exceptionType": "org.eclipse.jface.text.BadLocationException",
      "elements": [
        {
          "method": "org.eclipse.jface.text.AbstractDocument.replace",
          "source": "AbstractDocument.java :990"
        },
        {
          "method": "org.eclipse.jdt.internal.ui.javaeditor.PartiallySynchronizedDocument.replace",
          "source": "PartiallySynchronizedDocument.java:92"
        },
        {
          "method": "org.eclipse.jdt.internal.ui.text.template.contentassist.TemplateProposal.apply",
          "source": "TemplateProposal.java:144"
        },
        {
          "method": "org.eclipse.jface.text.contentassist.CompletionProposalPopup.insertProposal",
          "source": "CompletionProposalPopup.java:391"
        },
        {
          "method": "org.eclipse.jface.text.contentassist.CompletionProposalPopup.selectProposalWithMask",
          "source": "CompletionProposalPopup.java:359"
        },
        {
          "method": "org.eclipse.jface.text.contentassist.CompletionProposalPopup.verifyKey",
          "source": "CompletionProposalPopup.java:686"
        },
        {
          "method": "org.eclipse.jface.text.contentassist.ContentAssistant$InternalListener.verifyKey",
          "source": "ContentAssistant.java:622"
        },
        {
          "method": "org.eclipse.jface.text.TextViewer$VerifyKeyListenersManager.verifyKey",
          "source": "TextViewer.java:403"
        },
        {
          "method": "org.eclipse.swt.custom.StyledTextListener.handleEvent",
          "source": "StyledTextListe ner.java:55"
        },
        {
          "method": "org.eclipse.swt.widgets.EventTable.sendEvent",
          "source": "EventTable.java:82"
        },
        {
          "method": "org.eclipse.swt.widgets.Widget.sendEvent",
          "source": "Widget.java:796"
        },
        {
          "method": "org.eclipse.swt.widgets.Widget.sendEvent",
          "source": "Widget.java:820"
        },
        {
          "method": "org.eclipse.swt.widgets.Widget.sendEvent",
          "source": "Widget.java:805"
        },
        {
          "method": "org.eclipse.swt.widgets.Widget.notifyListeners",
          "source": "Widget.java:613"
        },
        {
          "method": "org.eclipse.swt.custom.StyledText.handleKeyDown",
          "source": "StyledText.java:5000"
        },
        {
          "method": "org.eclipse.swt.custom.StyledText$7.handleEvent",
          "source": "StyledText.java:4747"
        },
        {
          "method": "org.eclipse.swt.widgets.EventTable.sendEvent",
          "source": "EventTable.java:82"
        },
        {
          "method": "org.eclipse.swt.widgets.Widget.sendEvent",
          "source": "Widget.java:796"
        },
        {
          "method": "org.eclipse.swt.widgets.Widget.sendEvent",
          "source": "Widget.java:820"
        },
        {
          "method": "org.eclipse.swt.widgets.Widget.sendEvent",
          "source": "Widget.java:805"
        },
        {
          "method": "org.eclipse.swt.widgets.Control.sendKeyEvent",
          "source": "Control.java:1735"
        },
        {
          "method": "org.eclipse.swt.widgets.Control.sendKeyEvent",
          "source": "Control.java:1731"
        },
        {
          "method": "org.eclipse.swt.widgets.Control.WM_CHAR",
          "source": "Control.java:3072"
        },
        {
          "method": "org.eclipse.swt.widgets.Control.windowProc",
          "source": "Control.java:2974"
        },
        {
          "method": "org.eclipse.swt.widgets.Display.windowProc",
          "source": "Display.java:3349"
        },
        {
          "method": "org.eclipse.swt.internal.win32.OS.DispatchMessageW",
          "source": "Native Method"
        },
        {
          "method": "org.eclipse.swt.internal.win32.OS.DispatchMessage",
          "source": "OS.java:1472"
        },
        {
          "method": "org.eclipse.swt.widgets.Display.readAndDispatch",
          "source": "Display.java:2440"
        },
        {
          "method": "org.eclipse.ui.internal.Workbench.runEventLoop",
          "source": "Workbench.java:1435"
        },
        {
          "method": "org.eclipse.ui.internal.Workbench.runUI",
          "source": "Workbench.java:1406"
        },
        {
          "method": "org.eclipse.ui.internal.Workbench.createAndRunWorkbench",
          "source": "Workbench.jav a:263"
        },
        {
          "method": "org.eclipse.ui.PlatformUI.createAndRunWorkbench",
          "source": "PlatformUI.java:144"
        },
        {
          "method": "org.eclipse.ui.internal.ide.IDEApplication.run",
          "source": "IDEApplication.java:10 2"
        },
        {
          "method": "org.eclipse.core.internal.runtime.PlatformActivator$1.run",
          "source": "PlatformAct ivator.java:335"
        },
        {
          "method": "org.eclipse.core.runtime.adaptor.EclipseStarter.run",
          "source": "EclipseStarter.ja va:273"
        },
        {
          "method": "org.eclipse.core.runtime.adaptor.EclipseStarter.run",
          "source": "EclipseStarter.ja va:129"
        },
        {
          "method": "sun.reflect.NativeMethodAccessorImpl.invoke0",
          "source": "Native Method"
        },
        {
          "method": "sun.reflect.NativeMethodAccessorImpl.invoke",
          "source": "NativeMethodAccessorImpl. java:39"
        },
        {
          "method": "sun.reflect.DelegatingMethodAccessorImpl.invoke",
          "source": "DelegatingMethodAcces sorImpl.java:25"
        },
        {
          "method": "java.lang.reflect.Method.invoke",
          "source": "Method.java:324"
        },
        {
          "method": "org.eclipse.core.launcher.Main.basicRun",
          "source": "Main.java:183"
        },
        {
          "method": "org.eclipse.core.launcher.Main.run",
          "source": "Main.java:644"
        },
        {
          "method": "org.eclipse.core.launcher.Main.main",
          "source": "Main.java:628"
        }
      ],
      "number": 0,
      "commentIndex": 0,
      "bugId": "73331",
      "date": "2004-09-06T16:57:49+02:00",
      "product": "JDT",
      "component": "Text",
      "severity": "major"
    }
  ],
  "groupId": "73331",
  "bugId": "73331",
  "date": "2004-09-06T16:57:49+02:00",
  "product": "JDT",
  "component": "Text",
  "severity": "major"
}