{
  "comments": [
    "I\u0027m running Eclipse 3.0 on Fermilab Scientific Linux (Based on RH Enterprise\nLinux 3.0) with the following parameters:\n\neclipse -vmargs -Xmx768M -Xms512M\n\nI use the Java VM from Sun j2sdk1.4.2_04 and I have 1GB RAM.\n\nI happens often that Eclipse crashes when trying to opening a file for editing.\n \nThe error reported on the .metadata/.log file is:\n\njava.version\u003d1.4.2_04\njava.vendor\u003dSun Microsystems Inc.\nBootLoader constants: OS\u003dlinux, ARCH\u003dx86, WS\u003dgtk, NL\u003den_US\n                                                                                \n!ENTRY org.eclipse.ui 4 4 Sep 07, 2004 10:03:32.475\n!MESSAGE Unhandled event loop exception\n                                                                                \n!ENTRY org.eclipse.ui 4 0 Sep 07, 2004 10:03:32.475\n!MESSAGE java.lang.OutOfMemoryError\n!STACK 0\njava.lang.OutOfMemoryError\n                                                                                \n!ENTRY org.eclipse.ui 4 4 Sep 07, 2004 10:03:34.579\n!MESSAGE Unhandled event loop exception\n                                                                                \n!ENTRY org.eclipse.ui 4 0 Sep 07, 2004 10:03:34.580\n!MESSAGE java.lang.OutOfMemoryError\n!STACK 0\njava.lang.OutOfMemoryError\n                                                                                \n!ENTRY org.eclipse.osgi Sep 07, 2004 10:03:44.593\n!MESSAGE Error while stopping \"org.eclipse.cdt.debug.ui_2.0.0\".\n!STACK 0\norg.osgi.framework.BundleException: Exception in\norg.eclipse.cdt.debug.ui.CDebugUIPlugin.stop() of bundle org.eclipse.cdt.debug.ui.\n        at\norg.eclipse.osgi.framework.internal.core.BundleContextImpl.stop(BundleContextImpl.java:1010)\n        at\norg.eclipse.osgi.framework.internal.core.BundleHost.stopWorker(BundleHost.java:502)\n        at\norg.eclipse.osgi.framework.internal.core.AbstractBundle.stop(AbstractBundle.java:437)\nat\norg.eclipse.core.runtime.adaptor.BundleStopper.basicStopBundles(BundleStopper.java:75)\n        at\norg.eclipse.core.runtime.adaptor.BundleStopper.stopBundles(BundleStopper.java:62)\n        at\norg.eclipse.core.runtime.adaptor.EclipseAdaptor.frameworkStopping(EclipseAdaptor.java:551)\n        at\norg.eclipse.osgi.framework.internal.core.Framework.shutdown(Framework.java:457)\n        at\norg.eclipse.osgi.framework.internal.core.SystemBundle$1.run(SystemBundle.java:182)\n        at java.lang.Thread.run(Thread.java:534)\nCaused by: org.eclipse.swt.SWTException: Device is disposed\n        at org.eclipse.swt.SWT.error(SWT.java:2691)\n        at org.eclipse.swt.SWT.error(SWT.java:2616)\n        at org.eclipse.swt.SWT.error(SWT.java:2587)\n        at org.eclipse.swt.widgets.Display.error(Display.java:828)\n        at org.eclipse.swt.widgets.Display.asyncExec(Display.java:554)\n        at\norg.eclipse.cdt.debug.ui.CDebugUIPlugin.listenSelection(CDebugUIPlugin.java:345)\n        at org.eclipse.cdt.debug.ui.CDebugUIPlugin.stop(CDebugUIPlugin.java:325)\n       at\norg.eclipse.osgi.framework.internal.core.BundleContextImpl$2.run(BundleContextImpl.java:994)\n        at java.security.AccessController.doPrivileged(Native Method)\n        at\norg.eclipse.osgi.framework.internal.core.BundleContextImpl.stop(BundleContextImpl.java:990)\n        ... 8 more\nRoot exception:\norg.eclipse.swt.SWTException: Device is disposed\n        at org.eclipse.swt.SWT.error(SWT.java:2691)\n        at org.eclipse.swt.SWT.error(SWT.java:2616)\n        at org.eclipse.swt.SWT.error(SWT.java:2587)\n        at org.eclipse.swt.widgets.Display.error(Display.java:828)\n        at org.eclipse.swt.widgets.Display.asyncExec(Display.java:554)\n        at\norg.eclipse.cdt.debug.ui.CDebugUIPlugin.listenSelection(CDebugUIPlugin.java:345)\n        at org.eclipse.cdt.debug.ui.CDebugUIPlugin.stop(CDebugUIPlugin.java:325)\n       at\norg.eclipse.osgi.framework.internal.core.BundleContextImpl$2.run(BundleContextImpl.java:994)\n        at java.security.AccessController.doPrivileged(Native Method)\n        at\norg.eclipse.osgi.framework.internal.core.BundleContextImpl.stop(BundleContextImpl.java:990)\n        at\norg.eclipse.osgi.framework.internal.core.BundleHost.stopWorker(BundleHost.java:502)\nat\norg.eclipse.osgi.framework.internal.core.AbstractBundle.stop(AbstractBundle.java:437)\n        at\norg.eclipse.core.runtime.adaptor.BundleStopper.basicStopBundles(BundleStopper.java:75)\n        at\norg.eclipse.core.runtime.adaptor.BundleStopper.stopBundles(BundleStopper.java:62)\n        at\norg.eclipse.core.runtime.adaptor.EclipseAdaptor.frameworkStopping(EclipseAdaptor.java:551)\n        at\norg.eclipse.osgi.framework.internal.core.Framework.shutdown(Framework.java:457)\n        at\norg.eclipse.osgi.framework.internal.core.SystemBundle$1.run(SystemBundle.java:182)\n        at java.lang.Thread.run(Thread.java:534)",
    "The \"OutOfMemoryError\" exception has nothing to do with the exceptions in the \nlog. These exceptions are thrown when Eclipse is being closed and they have no \neffect on memory consumption.\nChanging severity to normal.",
    "The problem that caused these exceptions has been fixed in the head. I can\u0027t \nreproduce the crash. If it is still reproducible, it should be submitted as a \nseparate bug to the platform.\nMarking as FIXED."
  ],
  "commentCreationDates": [
    "2004-09-07T10:28:20+02:00",
    "2004-09-07T16:44:52+02:00",
    "2004-11-11T21:11:50+01:00"
  ],
  "traces": [
    {
      "exceptionType": "org.osgi.framework.BundleException",
      "message": "Exception in org.eclipse.cdt.debug.ui.CDebugUIPlugin.stop() of bundle org.eclipse.cdt.debug.ui.",
      "elements": [
        {
          "method": "org.eclipse.osgi.framework.internal.core.BundleContextImpl.stop",
          "source": "BundleContextImpl.java:1010"
        },
        {
          "method": "org.eclipse.osgi.framework.internal.core.BundleHost.stopWorker",
          "source": "BundleHost.java:502"
        },
        {
          "method": "org.eclipse.osgi.framework.internal.core.AbstractBundle.stop",
          "source": "AbstractBundle.java:437"
        },
        {
          "method": "org.eclipse.core.runtime.adaptor.BundleStopper.basicStopBundles",
          "source": "BundleStopper.java:75"
        },
        {
          "method": "org.eclipse.core.runtime.adaptor.BundleStopper.stopBundles",
          "source": "BundleStopper.java:62"
        },
        {
          "method": "org.eclipse.core.runtime.adaptor.EclipseAdaptor.frameworkStopping",
          "source": "EclipseAdaptor.java:551"
        },
        {
          "method": "org.eclipse.osgi.framework.internal.core.Framework.shutdown",
          "source": "Framework.java:457"
        },
        {
          "method": "org.eclipse.osgi.framework.internal.core.SystemBundle$1.run",
          "source": "SystemBundle.java:182"
        },
        {
          "method": "java.lang.Thread.run",
          "source": "Thread.java:534"
        }
      ],
      "causedBy": {
        "exceptionType": "org.eclipse.swt.SWTException",
        "message": "Device is disposed",
        "elements": [
          {
            "method": "org.eclipse.swt.SWT.error",
            "source": "SWT.java:2691"
          },
          {
            "method": "org.eclipse.swt.SWT.error",
            "source": "SWT.java:2616"
          },
          {
            "method": "org.eclipse.swt.SWT.error",
            "source": "SWT.java:2587"
          },
          {
            "method": "org.eclipse.swt.widgets.Display.error",
            "source": "Display.java:828"
          },
          {
            "method": "org.eclipse.swt.widgets.Display.asyncExec",
            "source": "Display.java:554"
          },
          {
            "method": "org.eclipse.cdt.debug.ui.CDebugUIPlugin.listenSelection",
            "source": "CDebugUIPlugin.java:345"
          },
          {
            "method": "org.eclipse.cdt.debug.ui.CDebugUIPlugin.stop",
            "source": "CDebugUIPlugin.java:325"
          },
          {
            "method": "org.eclipse.osgi.framework.internal.core.BundleContextImpl$2.run",
            "source": "BundleContextImpl.java:994"
          },
          {
            "method": "java.security.AccessController.doPrivileged",
            "source": "Native Method"
          },
          {
            "method": "org.eclipse.osgi.framework.internal.core.BundleContextImpl.stop",
            "source": "BundleContextImpl.java:990"
          }
        ],
        "number": 0,
        "commentIndex": 0
      },
      "number": 0,
      "commentIndex": 0,
      "bugId": "73351",
      "date": "2004-09-07T10:28:20+02:00",
      "product": "CDT",
      "component": "cdt-debug",
      "severity": "normal"
    },
    {
      "exceptionType": "org.eclipse.swt.SWTException",
      "message": "Device is disposed",
      "elements": [
        {
          "method": "org.eclipse.swt.SWT.error",
          "source": "SWT.java:2691"
        },
        {
          "method": "org.eclipse.swt.SWT.error",
          "source": "SWT.java:2616"
        },
        {
          "method": "org.eclipse.swt.SWT.error",
          "source": "SWT.java:2587"
        },
        {
          "method": "org.eclipse.swt.widgets.Display.error",
          "source": "Display.java:828"
        },
        {
          "method": "org.eclipse.swt.widgets.Display.asyncExec",
          "source": "Display.java:554"
        },
        {
          "method": "org.eclipse.cdt.debug.ui.CDebugUIPlugin.listenSelection",
          "source": "CDebugUIPlugin.java:345"
        },
        {
          "method": "org.eclipse.cdt.debug.ui.CDebugUIPlugin.stop",
          "source": "CDebugUIPlugin.java:325"
        },
        {
          "method": "org.eclipse.osgi.framework.internal.core.BundleContextImpl$2.run",
          "source": "BundleContextImpl.java:994"
        },
        {
          "method": "java.security.AccessController.doPrivileged",
          "source": "Native Method"
        },
        {
          "method": "org.eclipse.osgi.framework.internal.core.BundleContextImpl.stop",
          "source": "BundleContextImpl.java:990"
        },
        {
          "method": "org.eclipse.osgi.framework.internal.core.BundleHost.stopWorker",
          "source": "BundleHost.java:502"
        },
        {
          "method": "org.eclipse.osgi.framework.internal.core.AbstractBundle.stop",
          "source": "AbstractBundle.java:437"
        },
        {
          "method": "org.eclipse.core.runtime.adaptor.BundleStopper.basicStopBundles",
          "source": "BundleStopper.java:75"
        },
        {
          "method": "org.eclipse.core.runtime.adaptor.BundleStopper.stopBundles",
          "source": "BundleStopper.java:62"
        },
        {
          "method": "org.eclipse.core.runtime.adaptor.EclipseAdaptor.frameworkStopping",
          "source": "EclipseAdaptor.java:551"
        },
        {
          "method": "org.eclipse.osgi.framework.internal.core.Framework.shutdown",
          "source": "Framework.java:457"
        },
        {
          "method": "org.eclipse.osgi.framework.internal.core.SystemBundle$1.run",
          "source": "SystemBundle.java:182"
        },
        {
          "method": "java.lang.Thread.run",
          "source": "Thread.java:534"
        }
      ],
      "number": 1,
      "commentIndex": 0,
      "bugId": "73351",
      "date": "2004-09-07T10:28:20+02:00",
      "product": "CDT",
      "component": "cdt-debug",
      "severity": "normal"
    }
  ],
  "groupId": "73351",
  "bugId": "73351",
  "date": "2004-09-07T10:28:20+02:00",
  "product": "CDT",
  "component": "cdt-debug",
  "severity": "normal"
}