{
  "comments": [
    "I have tried to run \"eclipse-SDK-3.0-aix-motif.zip\" as well as\n\"eclipse-SDK-3.1M1-aix-motif.zip\" on an AIX 5.2 machine. But both do not get\nfurther than the splash screen.\n\nWe have a 64bit AIX PPC machine. I first tried with the 64bit Java JREs from\nIBM. Then I also tried the 32bit version, both failed, with different errors.\n\nuname -a:\n  AIX \u003csomename\u003e 2 5 000692084C00\noslevel -r:\n  5200-03\n\nIn the download for Eclipse the following is mentioned:\n\"AIX Version 5.2: For fileset X11.motif.lib: If service level \u003e 5.2.0.0, you\nmust apply APAR IY41944\"\n\nI tried to verify this and it seems OK (our installed AIX already seems to\ncomprise APAR IY41944). But I am not 100% sure about it.\n\nI have no admin privileges on this machine. JRE and Eclipse are installed\nprivately. But I can use Java without problems otherwise, so I do not think that\nthis causes the errors.\n\nHere are the errors from the Eclipse logfiles.\n\n\neclipse-SDK-3.0-aix-motif.zip\n\u003d\u003d\u003d\u003d\u003d\u003d\u003d\u003d\u003d\u003d\u003d\u003d\u003d\u003d\u003d\u003d\u003d\u003d\u003d\u003d\u003d\u003d\u003d\u003d\u003d\u003d\u003d\u003d\u003d\n\nWith 64-bit JRE\n---------------\n!SESSION Sep 07, 2004 10:54:46.334 ---------------------------------------------\neclipse.buildId\u003dI200406251208\njava.fullversion\u003dJ2RE 1.4.2 IBM AIX 5L for PowerPC (64 bit JVM) build\ncaix641420-20040626 (JIT enabled: jitc)\nBootLoader constants: OS\u003daix, ARCH\u003dppc, WS\u003dmotif, NL\u003den_US\n\n!ENTRY org.eclipse.osgi Sep 07, 2004 10:54:46.342\n!MESSAGE Application error\n!STACK 1\njava.lang.UnsatisfiedLinkError:\n/home/user/tgdkabe9/eclipse/plugins/org.eclipse.swt.motif_3.0.0/os/aix/ppc/libswt-motif-3062.a:\n load ENOEXEC on shared library(s) /home/user/tgdkabe9/ecli\npse/plugins/org.eclipse.swt.motif_3.0.0/os/aix/ppc/libswt-motif-3062.a\n        at java.lang.ClassLoader$NativeLibrary.load(Native Method)\n        at java.lang.ClassLoader.loadLibrary0(ClassLoader.java:2120)\n        at java.lang.ClassLoader.loadLibrary(ClassLoader.java:1968)\n        at java.lang.Runtime.loadLibrary0(Runtime.java:824)\n        at java.lang.System.loadLibrary(System.java:908)\n        at org.eclipse.swt.internal.Library.loadLibrary(Library.java:100)\n        at org.eclipse.swt.internal.motif.OS.\u003cclinit\u003e(OS.java:20)\n        at org.eclipse.swt.graphics.Device.\u003cclinit\u003e(Device.java:89)\n        at org.eclipse.ui.internal.Workbench.createDisplay(Workbench.java:268)\n        at org.eclipse.ui.PlatformUI.createDisplay(PlatformUI.java:153)\n        at\norg.eclipse.ui.internal.ide.IDEApplication.createDisplay(IDEApplication.java:122)\n        at org.eclipse.ui.internal.ide.IDEApplication.run(IDEApplication.java:72)\n        at\norg.eclipse.core.internal.runtime.PlatformActivator$1.run(PlatformActivator.java:335)\n        at\norg.eclipse.core.runtime.adaptor.EclipseStarter.run(EclipseStarter.java:273)\n        at\norg.eclipse.core.runtime.adaptor.EclipseStarter.run(EclipseStarter.java:129)\n        at sun.reflect.NativeMethodAccessorImpl.invoke0(Native Method)\n        at\nsun.reflect.NativeMethodAccessorImpl.invoke(NativeMethodAccessorImpl.java:85)\n        at\nsun.reflect.NativeMethodAccessorImpl.invoke(NativeMethodAccessorImpl.java:58)\n        at\nsun.reflect.DelegatingMethodAccessorImpl.invoke(DelegatingMethodAccessorImpl.java:60)\n        at java.lang.reflect.Method.invoke(Method.java:391)\n        at org.eclipse.core.launcher.Main.basicRun(Main.java:183)\n        at org.eclipse.core.launcher.Main.run(Main.java:644)\n        at org.eclipse.core.launcher.Main.main(Main.java:628)\n\n\nWith 32-bit JRE\n---------------\n!SESSION Sep 07, 2004 10:52:17.842 ---------------------------------------------\neclipse.buildId\u003dI200406251208\njava.fullversion\u003dJ2RE 1.4.2 IBM AIX build ca1420-20040626 (JIT enabled: jitc)\nBootLoader constants: OS\u003daix, ARCH\u003dppc, WS\u003dmotif, NL\u003den_US\n\n!ENTRY org.eclipse.osgi Sep 07, 2004 10:52:17.847\n!MESSAGE Application error\n!STACK 1\njava.lang.IllegalArgumentException: Argument cannot be null\n        at org.eclipse.swt.SWT.error(SWT.java:2677)\n        at org.eclipse.swt.SWT.error(SWT.java:2616)\n        at org.eclipse.swt.SWT.error(SWT.java:2587)\n        at org.eclipse.swt.graphics.Font.\u003cinit\u003e(Font.java:106)\n        at\norg.eclipse.jface.resource.FontRegistry.calculateDefaultFont(FontRegistry.java:412)\n        at\norg.eclipse.jface.resource.FontRegistry.defaultFontRecord(FontRegistry.java:430)\n        at\norg.eclipse.jface.resource.FontRegistry.getFontRecord(FontRegistry.java:519)\n        at org.eclipse.jface.resource.FontRegistry.get(FontRegistry.java:472)\n        at\norg.eclipse.jface.resource.JFaceResources.getDialogFont(JFaceResources.java:182)\n        at org.eclipse.jface.dialogs.Dialog.initializeDialogUnits(Dialog.java:778)\n        at\norg.eclipse.jface.dialogs.TitleAreaDialog.createContents(TitleAreaDialog.java:93)\n        at org.eclipse.jface.window.Window.create(Window.java:348)\n        at org.eclipse.jface.dialogs.Dialog.create(Dialog.java:925)\n        at org.eclipse.jface.window.Window.open(Window.java:637)\n        at\norg.eclipse.ui.internal.ide.ChooseWorkspaceDialog.prompt(ChooseWorkspaceDialog.java:65)\n        at\norg.eclipse.ui.internal.ide.IDEApplication.promptForWorkspace(IDEApplication.java:314)\n        at\norg.eclipse.ui.internal.ide.IDEApplication.checkInstanceLocation(IDEApplication.java:219)\n        at org.eclipse.ui.internal.ide.IDEApplication.run(IDEApplication.java:83)\n        at\norg.eclipse.core.internal.runtime.PlatformActivator$1.run(PlatformActivator.java:335)\n        at\norg.eclipse.core.runtime.adaptor.EclipseStarter.run(EclipseStarter.java:273)\n        at\norg.eclipse.core.runtime.adaptor.EclipseStarter.run(EclipseStarter.java:129)\n        at sun.reflect.NativeMethodAccessorImpl.invoke0(Native Method)\n        at\nsun.reflect.NativeMethodAccessorImpl.invoke(NativeMethodAccessorImpl.java:85)\n        at\nsun.reflect.NativeMethodAccessorImpl.invoke(NativeMethodAccessorImpl.java:58)\n        at\nsun.reflect.DelegatingMethodAccessorImpl.invoke(DelegatingMethodAccessorImpl.java:60)\n        at java.lang.reflect.Method.invoke(Method.java:391)\n        at org.eclipse.core.launcher.Main.basicRun(Main.java:183)\n        at org.eclipse.core.launcher.Main.run(Main.java:644)\n        at org.eclipse.core.launcher.Main.main(Main.java:628)\n\n\neclipse-SDK-3.1M1-aix-motif.zip\n\u003d\u003d\u003d\u003d\u003d\u003d\u003d\u003d\u003d\u003d\u003d\u003d\u003d\u003d\u003d\u003d\u003d\u003d\u003d\u003d\u003d\u003d\u003d\u003d\u003d\u003d\u003d\u003d\u003d\u003d\u003d\n\nWith 64-bit JRE\n---------------\n!SESSION Sep 07, 2004 11:05:47.835 ---------------------------------------------\neclipse.buildId\u003dI200408122000\njava.fullversion\u003dJ2RE 1.4.2 IBM AIX 5L for PowerPC (64 bit JVM) build\ncaix641420-20040626 (JIT enabled: jitc)\nBootLoader constants: OS\u003daix, ARCH\u003dppc, WS\u003dmotif, NL\u003den_US\n\n!ENTRY org.eclipse.osgi Sep 07, 2004 11:05:47.840\n!MESSAGE Application error\n!STACK 1\njava.lang.UnsatisfiedLinkError:\n/home/user/tgdkabe9/eclipse/plugins/org.eclipse.swt.motif_3.1.0/os/aix/ppc/libswt-motif-3101.a:\n load ENOEXEC on shared library(s) /home/user/tgdkabe9/ecli\npse/plugins/org.eclipse.swt.motif_3.1.0/os/aix/ppc/libswt-motif-3101.a\n        at java.lang.ClassLoader$NativeLibrary.load(Native Method)\n        at java.lang.ClassLoader.loadLibrary0(ClassLoader.java:2120)\n        at java.lang.ClassLoader.loadLibrary(ClassLoader.java:1968)\n        at java.lang.Runtime.loadLibrary0(Runtime.java:824)\n        at java.lang.System.loadLibrary(System.java:908)\n        at org.eclipse.swt.internal.Library.loadLibrary(Library.java:100)\n        at org.eclipse.swt.internal.motif.OS.\u003cclinit\u003e(OS.java:20)\n        at org.eclipse.swt.graphics.Device.\u003cclinit\u003e(Device.java:89)\n        at org.eclipse.ui.internal.Workbench.createDisplay(Workbench.java:277)\n        at org.eclipse.ui.PlatformUI.createDisplay(PlatformUI.java:156)\n        at\norg.eclipse.ui.internal.ide.IDEApplication.createDisplay(IDEApplication.java:127)\n        at org.eclipse.ui.internal.ide.IDEApplication.run(IDEApplication.java:78)\n        at\norg.eclipse.core.internal.runtime.PlatformActivator$1.run(PlatformActivator.java:335)\n        at\norg.eclipse.core.runtime.adaptor.EclipseStarter.run(EclipseStarter.java:273)\n        at\norg.eclipse.core.runtime.adaptor.EclipseStarter.run(EclipseStarter.java:129)\n        at sun.reflect.NativeMethodAccessorImpl.invoke0(Native Method)\n        at\nsun.reflect.NativeMethodAccessorImpl.invoke(NativeMethodAccessorImpl.java:85)\n        at\nsun.reflect.NativeMethodAccessorImpl.invoke(NativeMethodAccessorImpl.java:58)\n        at\nsun.reflect.DelegatingMethodAccessorImpl.invoke(DelegatingMethodAccessorImpl.java:60)\n        at java.lang.reflect.Method.invoke(Method.java:391)\n        at org.eclipse.core.launcher.Main.basicRun(Main.java:183)\n        at org.eclipse.core.launcher.Main.run(Main.java:644)\n        at org.eclipse.core.launcher.Main.main(Main.java:628)\n\nWith 32-bit JRE\n---------------\n!SESSION Sep 07, 2004 11:07:57.901 ---------------------------------------------\neclipse.buildId\u003dI200408122000\njava.fullversion\u003dJ2RE 1.4.2 IBM AIX build ca1420-20040626 (JIT enabled: jitc)\nBootLoader constants: OS\u003daix, ARCH\u003dppc, WS\u003dmotif, NL\u003den_US\n\n!ENTRY org.eclipse.osgi Sep 07, 2004 11:07:57.908\n!MESSAGE Application error\n!STACK 1\njava.lang.IllegalArgumentException: Argument cannot be null\n        at org.eclipse.swt.SWT.error(SWT.java:2677)\n        at org.eclipse.swt.SWT.error(SWT.java:2616)\n        at org.eclipse.swt.SWT.error(SWT.java:2587)\n        at org.eclipse.swt.graphics.Font.\u003cinit\u003e(Font.java:106)\n        at\norg.eclipse.jface.resource.FontRegistry.calculateDefaultFont(FontRegistry.java:418)\n        at\norg.eclipse.jface.resource.FontRegistry.defaultFontRecord(FontRegistry.java:437)\n        at\norg.eclipse.jface.resource.FontRegistry.getFontRecord(FontRegistry.java:527)\n        at org.eclipse.jface.resource.FontRegistry.get(FontRegistry.java:480)\n        at\norg.eclipse.jface.resource.JFaceResources.getDialogFont(JFaceResources.java:183)\n        at org.eclipse.jface.dialogs.Dialog.initializeDialogUnits(Dialog.java:822)\n        at\norg.eclipse.jface.dialogs.TitleAreaDialog.createContents(TitleAreaDialog.java:136)\n        at org.eclipse.jface.window.Window.create(Window.java:356)\n        at org.eclipse.jface.dialogs.Dialog.create(Dialog.java:979)\n        at org.eclipse.jface.window.Window.open(Window.java:661)\n        at\norg.eclipse.ui.internal.ide.ChooseWorkspaceDialog.prompt(ChooseWorkspaceDialog.java:70)\n        at\norg.eclipse.ui.internal.ide.IDEApplication.promptForWorkspace(IDEApplication.java:322)\n        at\norg.eclipse.ui.internal.ide.IDEApplication.checkInstanceLocation(IDEApplication.java:226)\n        at org.eclipse.ui.internal.ide.IDEApplication.run(IDEApplication.java:89)\n        at\norg.eclipse.core.internal.runtime.PlatformActivator$1.run(PlatformActivator.java:335)\n        at\norg.eclipse.core.runtime.adaptor.EclipseStarter.run(EclipseStarter.java:273)\n        at\norg.eclipse.core.runtime.adaptor.EclipseStarter.run(EclipseStarter.java:129)\n        at sun.reflect.NativeMethodAccessorImpl.invoke0(Native Method)\n        at\nsun.reflect.NativeMethodAccessorImpl.invoke(NativeMethodAccessorImpl.java:85)\n        at\nsun.reflect.NativeMethodAccessorImpl.invoke(NativeMethodAccessorImpl.java:58)\n        at\nsun.reflect.DelegatingMethodAccessorImpl.invoke(DelegatingMethodAccessorImpl.java:60)\n        at java.lang.reflect.Method.invoke(Method.java:391)\n        at org.eclipse.core.launcher.Main.basicRun(Main.java:183)\n        at org.eclipse.core.launcher.Main.run(Main.java:644)\n        at org.eclipse.core.launcher.Main.main(Main.java:628)",
    "This does not seem to be a problem of Eclipse or SWT. I was trying to run\nEclipse on an AIX server and my DISPLAY was set to a Windows XP machine running\n\"Reflection X\", an X Server for Windows or X emulation. The errors described\noccurred with that configuration (on AIX!).\n\nNow I got my Linux box and tried to direct the DISPLAY there. Amazingly enough\nit works now, at least when I use the 32-bit JRE on AIX. There is still an error\nwhen I use the 64-bit JRE, but then again I am not absolutely sure if this is\nreally a 64-bit CPU as I was told.\n\nSo essentially it works and the errors could have been caused by timing problems\nor weird incompatiblities with \"Reflection X\", not really SWT or Eclipse."
  ],
  "commentCreationDates": [
    "2004-09-07T12:00:44+02:00",
    "2004-09-15T15:59:42+02:00"
  ],
  "traces": [
    {
      "exceptionType": "java.lang.UnsatisfiedLinkError",
      "message": "/home/user/tgdkabe9/eclipse/plugins/org.eclipse.swt.motif_3.0.0/os/aix/ppc/libswt-motif-3062.a:  load ENOEXEC on shared library(s) /home/user/tgdkabe9/ecli pse/plugins/org.eclipse.swt.motif_3.0.0/os/aix/ppc/libswt-motif-3062.a",
      "elements": [
        {
          "method": "java.lang.ClassLoader$NativeLibrary.load",
          "source": "Native Method"
        },
        {
          "method": "java.lang.ClassLoader.loadLibrary0",
          "source": "ClassLoader.java:2120"
        },
        {
          "method": "java.lang.ClassLoader.loadLibrary",
          "source": "ClassLoader.java:1968"
        },
        {
          "method": "java.lang.Runtime.loadLibrary0",
          "source": "Runtime.java:824"
        },
        {
          "method": "java.lang.System.loadLibrary",
          "source": "System.java:908"
        },
        {
          "method": "org.eclipse.swt.internal.Library.loadLibrary",
          "source": "Library.java:100"
        },
        {
          "method": "org.eclipse.swt.internal.motif.OS.\u003cclinit\u003e",
          "source": "OS.java:20"
        },
        {
          "method": "org.eclipse.swt.graphics.Device.\u003cclinit\u003e",
          "source": "Device.java:89"
        },
        {
          "method": "org.eclipse.ui.internal.Workbench.createDisplay",
          "source": "Workbench.java:268"
        },
        {
          "method": "org.eclipse.ui.PlatformUI.createDisplay",
          "source": "PlatformUI.java:153"
        },
        {
          "method": "org.eclipse.ui.internal.ide.IDEApplication.createDisplay",
          "source": "IDEApplication.java:122"
        },
        {
          "method": "org.eclipse.ui.internal.ide.IDEApplication.run",
          "source": "IDEApplication.java:72"
        },
        {
          "method": "org.eclipse.core.internal.runtime.PlatformActivator$1.run",
          "source": "PlatformActivator.java:335"
        },
        {
          "method": "org.eclipse.core.runtime.adaptor.EclipseStarter.run",
          "source": "EclipseStarter.java:273"
        },
        {
          "method": "org.eclipse.core.runtime.adaptor.EclipseStarter.run",
          "source": "EclipseStarter.java:129"
        },
        {
          "method": "sun.reflect.NativeMethodAccessorImpl.invoke0",
          "source": "Native Method"
        },
        {
          "method": "sun.reflect.NativeMethodAccessorImpl.invoke",
          "source": "NativeMethodAccessorImpl.java:85"
        },
        {
          "method": "sun.reflect.NativeMethodAccessorImpl.invoke",
          "source": "NativeMethodAccessorImpl.java:58"
        },
        {
          "method": "sun.reflect.DelegatingMethodAccessorImpl.invoke",
          "source": "DelegatingMethodAccessorImpl.java:60"
        },
        {
          "method": "java.lang.reflect.Method.invoke",
          "source": "Method.java:391"
        },
        {
          "method": "org.eclipse.core.launcher.Main.basicRun",
          "source": "Main.java:183"
        },
        {
          "method": "org.eclipse.core.launcher.Main.run",
          "source": "Main.java:644"
        },
        {
          "method": "org.eclipse.core.launcher.Main.main",
          "source": "Main.java:628"
        }
      ],
      "number": 0,
      "commentIndex": 0,
      "bugId": "73355",
      "date": "2004-09-07T12:00:44+02:00",
      "product": "Platform",
      "component": "SWT",
      "severity": "minor"
    },
    {
      "exceptionType": "java.lang.IllegalArgumentException",
      "message": "Argument cannot be null",
      "elements": [
        {
          "method": "org.eclipse.swt.SWT.error",
          "source": "SWT.java:2677"
        },
        {
          "method": "org.eclipse.swt.SWT.error",
          "source": "SWT.java:2616"
        },
        {
          "method": "org.eclipse.swt.SWT.error",
          "source": "SWT.java:2587"
        },
        {
          "method": "org.eclipse.swt.graphics.Font.\u003cinit\u003e",
          "source": "Font.java:106"
        },
        {
          "method": "org.eclipse.jface.resource.FontRegistry.calculateDefaultFont",
          "source": "FontRegistry.java:412"
        },
        {
          "method": "org.eclipse.jface.resource.FontRegistry.defaultFontRecord",
          "source": "FontRegistry.java:430"
        },
        {
          "method": "org.eclipse.jface.resource.FontRegistry.getFontRecord",
          "source": "FontRegistry.java:519"
        },
        {
          "method": "org.eclipse.jface.resource.FontRegistry.get",
          "source": "FontRegistry.java:472"
        },
        {
          "method": "org.eclipse.jface.resource.JFaceResources.getDialogFont",
          "source": "JFaceResources.java:182"
        },
        {
          "method": "org.eclipse.jface.dialogs.Dialog.initializeDialogUnits",
          "source": "Dialog.java:778"
        },
        {
          "method": "org.eclipse.jface.dialogs.TitleAreaDialog.createContents",
          "source": "TitleAreaDialog.java:93"
        },
        {
          "method": "org.eclipse.jface.window.Window.create",
          "source": "Window.java:348"
        },
        {
          "method": "org.eclipse.jface.dialogs.Dialog.create",
          "source": "Dialog.java:925"
        },
        {
          "method": "org.eclipse.jface.window.Window.open",
          "source": "Window.java:637"
        },
        {
          "method": "org.eclipse.ui.internal.ide.ChooseWorkspaceDialog.prompt",
          "source": "ChooseWorkspaceDialog.java:65"
        },
        {
          "method": "org.eclipse.ui.internal.ide.IDEApplication.promptForWorkspace",
          "source": "IDEApplication.java:314"
        },
        {
          "method": "org.eclipse.ui.internal.ide.IDEApplication.checkInstanceLocation",
          "source": "IDEApplication.java:219"
        },
        {
          "method": "org.eclipse.ui.internal.ide.IDEApplication.run",
          "source": "IDEApplication.java:83"
        },
        {
          "method": "org.eclipse.core.internal.runtime.PlatformActivator$1.run",
          "source": "PlatformActivator.java:335"
        },
        {
          "method": "org.eclipse.core.runtime.adaptor.EclipseStarter.run",
          "source": "EclipseStarter.java:273"
        },
        {
          "method": "org.eclipse.core.runtime.adaptor.EclipseStarter.run",
          "source": "EclipseStarter.java:129"
        },
        {
          "method": "sun.reflect.NativeMethodAccessorImpl.invoke0",
          "source": "Native Method"
        },
        {
          "method": "sun.reflect.NativeMethodAccessorImpl.invoke",
          "source": "NativeMethodAccessorImpl.java:85"
        },
        {
          "method": "sun.reflect.NativeMethodAccessorImpl.invoke",
          "source": "NativeMethodAccessorImpl.java:58"
        },
        {
          "method": "sun.reflect.DelegatingMethodAccessorImpl.invoke",
          "source": "DelegatingMethodAccessorImpl.java:60"
        },
        {
          "method": "java.lang.reflect.Method.invoke",
          "source": "Method.java:391"
        },
        {
          "method": "org.eclipse.core.launcher.Main.basicRun",
          "source": "Main.java:183"
        },
        {
          "method": "org.eclipse.core.launcher.Main.run",
          "source": "Main.java:644"
        },
        {
          "method": "org.eclipse.core.launcher.Main.main",
          "source": "Main.java:628"
        }
      ],
      "number": 1,
      "commentIndex": 0,
      "bugId": "73355",
      "date": "2004-09-07T12:00:44+02:00",
      "product": "Platform",
      "component": "SWT",
      "severity": "minor"
    },
    {
      "exceptionType": "java.lang.UnsatisfiedLinkError",
      "message": "/home/user/tgdkabe9/eclipse/plugins/org.eclipse.swt.motif_3.1.0/os/aix/ppc/libswt-motif-3101.a:  load ENOEXEC on shared library(s) /home/user/tgdkabe9/ecli pse/plugins/org.eclipse.swt.motif_3.1.0/os/aix/ppc/libswt-motif-3101.a",
      "elements": [
        {
          "method": "java.lang.ClassLoader$NativeLibrary.load",
          "source": "Native Method"
        },
        {
          "method": "java.lang.ClassLoader.loadLibrary0",
          "source": "ClassLoader.java:2120"
        },
        {
          "method": "java.lang.ClassLoader.loadLibrary",
          "source": "ClassLoader.java:1968"
        },
        {
          "method": "java.lang.Runtime.loadLibrary0",
          "source": "Runtime.java:824"
        },
        {
          "method": "java.lang.System.loadLibrary",
          "source": "System.java:908"
        },
        {
          "method": "org.eclipse.swt.internal.Library.loadLibrary",
          "source": "Library.java:100"
        },
        {
          "method": "org.eclipse.swt.internal.motif.OS.\u003cclinit\u003e",
          "source": "OS.java:20"
        },
        {
          "method": "org.eclipse.swt.graphics.Device.\u003cclinit\u003e",
          "source": "Device.java:89"
        },
        {
          "method": "org.eclipse.ui.internal.Workbench.createDisplay",
          "source": "Workbench.java:277"
        },
        {
          "method": "org.eclipse.ui.PlatformUI.createDisplay",
          "source": "PlatformUI.java:156"
        },
        {
          "method": "org.eclipse.ui.internal.ide.IDEApplication.createDisplay",
          "source": "IDEApplication.java:127"
        },
        {
          "method": "org.eclipse.ui.internal.ide.IDEApplication.run",
          "source": "IDEApplication.java:78"
        },
        {
          "method": "org.eclipse.core.internal.runtime.PlatformActivator$1.run",
          "source": "PlatformActivator.java:335"
        },
        {
          "method": "org.eclipse.core.runtime.adaptor.EclipseStarter.run",
          "source": "EclipseStarter.java:273"
        },
        {
          "method": "org.eclipse.core.runtime.adaptor.EclipseStarter.run",
          "source": "EclipseStarter.java:129"
        },
        {
          "method": "sun.reflect.NativeMethodAccessorImpl.invoke0",
          "source": "Native Method"
        },
        {
          "method": "sun.reflect.NativeMethodAccessorImpl.invoke",
          "source": "NativeMethodAccessorImpl.java:85"
        },
        {
          "method": "sun.reflect.NativeMethodAccessorImpl.invoke",
          "source": "NativeMethodAccessorImpl.java:58"
        },
        {
          "method": "sun.reflect.DelegatingMethodAccessorImpl.invoke",
          "source": "DelegatingMethodAccessorImpl.java:60"
        },
        {
          "method": "java.lang.reflect.Method.invoke",
          "source": "Method.java:391"
        },
        {
          "method": "org.eclipse.core.launcher.Main.basicRun",
          "source": "Main.java:183"
        },
        {
          "method": "org.eclipse.core.launcher.Main.run",
          "source": "Main.java:644"
        },
        {
          "method": "org.eclipse.core.launcher.Main.main",
          "source": "Main.java:628"
        }
      ],
      "number": 2,
      "commentIndex": 0,
      "bugId": "73355",
      "date": "2004-09-07T12:00:44+02:00",
      "product": "Platform",
      "component": "SWT",
      "severity": "minor"
    },
    {
      "exceptionType": "java.lang.IllegalArgumentException",
      "message": "Argument cannot be null",
      "elements": [
        {
          "method": "org.eclipse.swt.SWT.error",
          "source": "SWT.java:2677"
        },
        {
          "method": "org.eclipse.swt.SWT.error",
          "source": "SWT.java:2616"
        },
        {
          "method": "org.eclipse.swt.SWT.error",
          "source": "SWT.java:2587"
        },
        {
          "method": "org.eclipse.swt.graphics.Font.\u003cinit\u003e",
          "source": "Font.java:106"
        },
        {
          "method": "org.eclipse.jface.resource.FontRegistry.calculateDefaultFont",
          "source": "FontRegistry.java:418"
        },
        {
          "method": "org.eclipse.jface.resource.FontRegistry.defaultFontRecord",
          "source": "FontRegistry.java:437"
        },
        {
          "method": "org.eclipse.jface.resource.FontRegistry.getFontRecord",
          "source": "FontRegistry.java:527"
        },
        {
          "method": "org.eclipse.jface.resource.FontRegistry.get",
          "source": "FontRegistry.java:480"
        },
        {
          "method": "org.eclipse.jface.resource.JFaceResources.getDialogFont",
          "source": "JFaceResources.java:183"
        },
        {
          "method": "org.eclipse.jface.dialogs.Dialog.initializeDialogUnits",
          "source": "Dialog.java:822"
        },
        {
          "method": "org.eclipse.jface.dialogs.TitleAreaDialog.createContents",
          "source": "TitleAreaDialog.java:136"
        },
        {
          "method": "org.eclipse.jface.window.Window.create",
          "source": "Window.java:356"
        },
        {
          "method": "org.eclipse.jface.dialogs.Dialog.create",
          "source": "Dialog.java:979"
        },
        {
          "method": "org.eclipse.jface.window.Window.open",
          "source": "Window.java:661"
        },
        {
          "method": "org.eclipse.ui.internal.ide.ChooseWorkspaceDialog.prompt",
          "source": "ChooseWorkspaceDialog.java:70"
        },
        {
          "method": "org.eclipse.ui.internal.ide.IDEApplication.promptForWorkspace",
          "source": "IDEApplication.java:322"
        },
        {
          "method": "org.eclipse.ui.internal.ide.IDEApplication.checkInstanceLocation",
          "source": "IDEApplication.java:226"
        },
        {
          "method": "org.eclipse.ui.internal.ide.IDEApplication.run",
          "source": "IDEApplication.java:89"
        },
        {
          "method": "org.eclipse.core.internal.runtime.PlatformActivator$1.run",
          "source": "PlatformActivator.java:335"
        },
        {
          "method": "org.eclipse.core.runtime.adaptor.EclipseStarter.run",
          "source": "EclipseStarter.java:273"
        },
        {
          "method": "org.eclipse.core.runtime.adaptor.EclipseStarter.run",
          "source": "EclipseStarter.java:129"
        },
        {
          "method": "sun.reflect.NativeMethodAccessorImpl.invoke0",
          "source": "Native Method"
        },
        {
          "method": "sun.reflect.NativeMethodAccessorImpl.invoke",
          "source": "NativeMethodAccessorImpl.java:85"
        },
        {
          "method": "sun.reflect.NativeMethodAccessorImpl.invoke",
          "source": "NativeMethodAccessorImpl.java:58"
        },
        {
          "method": "sun.reflect.DelegatingMethodAccessorImpl.invoke",
          "source": "DelegatingMethodAccessorImpl.java:60"
        },
        {
          "method": "java.lang.reflect.Method.invoke",
          "source": "Method.java:391"
        },
        {
          "method": "org.eclipse.core.launcher.Main.basicRun",
          "source": "Main.java:183"
        },
        {
          "method": "org.eclipse.core.launcher.Main.run",
          "source": "Main.java:644"
        },
        {
          "method": "org.eclipse.core.launcher.Main.main",
          "source": "Main.java:628"
        }
      ],
      "number": 3,
      "commentIndex": 0,
      "bugId": "73355",
      "date": "2004-09-07T12:00:44+02:00",
      "product": "Platform",
      "component": "SWT",
      "severity": "minor"
    }
  ],
  "groupId": "73355",
  "bugId": "73355",
  "date": "2004-09-07T12:00:44+02:00",
  "product": "Platform",
  "component": "SWT",
  "severity": "minor"
}