{
  "comments": [
    "The following npe occurs, when I try to create a new profile launch configuration. \n(Eclipse 3.0.1, EMF 2.0.1, Hyades 3.0.1, XSD 2.0.1) \n \n!ENTRY org.eclipse.core.runtime 4 2 Sep 07, 2004 17:17:20.817 \n!MESSAGE Problems occurred when invoking code from plug-in: \n\"org.eclipse.core.runtime\". \n!STACK 0 \njava.lang.NullPointerException \nat \norg.eclipse.hyades.trace.ui.internal.launcher.ProfilingSetsManager.readFilters(ProfilingSetsManager.java) \n        at \norg.eclipse.hyades.trace.ui.internal.launcher.ProfilingSetsManager.initializeProfilingFilters(ProfilingSetsManager.java) \n        at \norg.eclipse.hyades.trace.ui.internal.launcher.ProfilingSetsManager.initialize(ProfilingSetsManager.java) \n        at \norg.eclipse.hyades.trace.ui.launcher.ProfilingSetsManagerCopy.\u003cinit\u003e(ProfilingSetsManagerCopy.java) \n        at \norg.eclipse.hyades.trace.ui.internal.core.TraceProfileOverviewUI.getManagerCopy(TraceProfileOverviewUI.java) \n        at \norg.eclipse.hyades.trace.ui.internal.core.TraceProfileOverviewUI.createProfilingSetTable(TraceProfileOverviewUI.java) \n        at \norg.eclipse.hyades.trace.ui.internal.core.TraceProfileOverviewUI.createControl(TraceProfileOverviewUI.java) \n        at \norg.eclipse.hyades.trace.ui.internal.launcher.ProfileOverviewTab.createControl(ProfileOverviewTab.java) \n        at \norg.eclipse.hyades.trace.ui.internal.core.TraceProfileUI.createControl(TraceProfileUI.java) \n        at \norg.eclipse.hyades.trace.ui.internal.launcher.ProfileTab.createControl(ProfileTab.java) \n        at \norg.eclipse.debug.internal.ui.launchConfigurations.LaunchConfigurationTabGroupViewer.showTabsFor(LaunchConfigurationTabGroupViewer.java:705) \n        at \norg.eclipse.debug.internal.ui.launchConfigurations.LaunchConfigurationTabGroupViewer.showInstanceTabsFor(LaunchConfigurationTabGroupViewer.java:630) \n        at \norg.eclipse.debug.internal.ui.launchConfigurations.LaunchConfigurationTabGroupViewer.displayInstanceTabs(LaunchConfigurationTabGroupViewer.java:516) \n        at \norg.eclipse.debug.internal.ui.launchConfigurations.LaunchConfigurationTabGroupViewer$5.run(LaunchConfigurationTabGroupViewer.java:473) \n        at org.eclipse.swt.custom.BusyIndicator.showWhile(BusyIndicator.java:69) \n        at \norg.eclipse.debug.internal.ui.launchConfigurations.LaunchConfigurationTabGroupViewer.inputChanged(LaunchConfigurationTabGroupViewer.java:490) \n        at \norg.eclipse.debug.internal.ui.launchConfigurations.LaunchConfigurationTabGroupViewer.setInput(LaunchConfigurationTabGroupViewer.java:454) \n        at \norg.eclipse.debug.internal.ui.launchConfigurations.LaunchConfigurationsDialog.handleLaunchConfigurationSelectionChanged(LaunchConfigurationsDialog.java:775 \n) \n        at \norg.eclipse.debug.internal.ui.launchConfigurations.LaunchConfigurationsDialog$3.selectionChanged(LaunchConfigurationsDialog.java:585) \n        at org.eclipse.jface.viewers.Viewer$2.run(Viewer.java:159) \n        at org.eclipse.core.internal.runtime.InternalPlatform.run(InternalPlatform.java:615) \n        at org.eclipse.core.runtime.Platform.run(Platform.java:747) \n        at org.eclipse.jface.viewers.Viewer.fireSelectionChanged(Viewer.java:157) \n        at \norg.eclipse.jface.viewers.StructuredViewer.updateSelection(StructuredViewer.java:1394) \n        at \norg.eclipse.jface.viewers.StructuredViewer.setSelection(StructuredViewer.java:1093) \n        at org.eclipse.jface.viewers.Viewer.setSelection(Viewer.java:356) \n        at \norg.eclipse.debug.internal.ui.launchConfigurations.LaunchConfigurationsDialog.doInitialTreeSelection(LaunchConfigurationsDialog.java:368) \n        at \norg.eclipse.debug.internal.ui.launchConfigurations.LaunchConfigurationsDialog.initializeContent(LaunchConfigurationsDialog.java:309) \n        at \norg.eclipse.debug.internal.ui.launchConfigurations.LaunchConfigurationsDialog.createContents(LaunchConfigurationsDialog.java:304) \n        at org.eclipse.jface.window.Window.create(Window.java:348) \n        at org.eclipse.jface.dialogs.Dialog.create(Dialog.java:925) \n        at \norg.eclipse.debug.internal.ui.launchConfigurations.LaunchConfigurationsDialog.create(LaunchConfigurationsDialog.java:1596) \n        at org.eclipse.jface.window.Window.open(Window.java:637) \n        at \norg.eclipse.debug.internal.ui.launchConfigurations.LaunchConfigurationsDialog.open(LaunchConfigurationsDialog.java:419) \n        at org.eclipse.debug.ui.DebugUITools$1.run(DebugUITools.java:381) \n        at org.eclipse.swt.custom.BusyIndicator.showWhile(BusyIndicator.java:69) \n        at \norg.eclipse.debug.ui.DebugUITools.openLaunchConfigurationDialogOnGroup(DebugUITools.java:385) \n        at \norg.eclipse.debug.ui.DebugUITools.openLaunchConfigurationDialogOnGroup(DebugUITools.java:327) \n        at \norg.eclipse.debug.ui.actions.OpenLaunchDialogAction.run(OpenLaunchDialogAction.java:80) \n        at org.eclipse.jface.action.Action.runWithEvent(Action.java:881) \n        at \norg.eclipse.jface.action.ActionContributionItem.handleWidgetSelection(ActionContributionItem.java:915) \n        at org.eclipse.jface.action.ActionContributionItem.access$2\n(ActionContributionItem.java:866)",
    "Created an attachment (id\u003d14428)\nComplete Log-File\n",
    "Ok, after some hours I found out, that importing the preferences from an older \ninstallation causes the problems. Setting up a complete new version of Eclipse and \nconfiguring all preferences manually :-( was the way to get it working. \n \nHolger "
  ],
  "commentCreationDates": [
    "2004-09-07T17:30:26+02:00",
    "2004-09-07T17:32:31+02:00",
    "2004-09-10T10:12:46+02:00"
  ],
  "traces": [
    {
      "exceptionType": "java.lang.NullPointerException",
      "elements": [
        {
          "method": "org.eclipse.hyades.trace.ui.internal.launcher.ProfilingSetsManager.readFilters",
          "source": "ProfilingSetsManager.java"
        },
        {
          "method": "org.eclipse.hyades.trace.ui.internal.launcher.ProfilingSetsManager.initializeProfilingFilters",
          "source": "ProfilingSetsManager.java"
        },
        {
          "method": "org.eclipse.hyades.trace.ui.internal.launcher.ProfilingSetsManager.initialize",
          "source": "ProfilingSetsManager.java"
        },
        {
          "method": "org.eclipse.hyades.trace.ui.launcher.ProfilingSetsManagerCopy.\u003cinit\u003e",
          "source": "ProfilingSetsManagerCopy.java"
        },
        {
          "method": "org.eclipse.hyades.trace.ui.internal.core.TraceProfileOverviewUI.getManagerCopy",
          "source": "TraceProfileOverviewUI.java"
        },
        {
          "method": "org.eclipse.hyades.trace.ui.internal.core.TraceProfileOverviewUI.createProfilingSetTable",
          "source": "TraceProfileOverviewUI.java"
        },
        {
          "method": "org.eclipse.hyades.trace.ui.internal.core.TraceProfileOverviewUI.createControl",
          "source": "TraceProfileOverviewUI.java"
        },
        {
          "method": "org.eclipse.hyades.trace.ui.internal.launcher.ProfileOverviewTab.createControl",
          "source": "ProfileOverviewTab.java"
        },
        {
          "method": "org.eclipse.hyades.trace.ui.internal.core.TraceProfileUI.createControl",
          "source": "TraceProfileUI.java"
        },
        {
          "method": "org.eclipse.hyades.trace.ui.internal.launcher.ProfileTab.createControl",
          "source": "ProfileTab.java"
        },
        {
          "method": "org.eclipse.debug.internal.ui.launchConfigurations.LaunchConfigurationTabGroupViewer.showTabsFor",
          "source": "LaunchConfigurationTabGroupViewer.java:705"
        },
        {
          "method": "org.eclipse.debug.internal.ui.launchConfigurations.LaunchConfigurationTabGroupViewer.showInstanceTabsFor",
          "source": "LaunchConfigurationTabGroupViewer.java:630"
        },
        {
          "method": "org.eclipse.debug.internal.ui.launchConfigurations.LaunchConfigurationTabGroupViewer.displayInstanceTabs",
          "source": "LaunchConfigurationTabGroupViewer.java:516"
        },
        {
          "method": "org.eclipse.debug.internal.ui.launchConfigurations.LaunchConfigurationTabGroupViewer$5.run",
          "source": "LaunchConfigurationTabGroupViewer.java:473"
        },
        {
          "method": "org.eclipse.swt.custom.BusyIndicator.showWhile",
          "source": "BusyIndicator.java:69"
        },
        {
          "method": "org.eclipse.debug.internal.ui.launchConfigurations.LaunchConfigurationTabGroupViewer.inputChanged",
          "source": "LaunchConfigurationTabGroupViewer.java:490"
        },
        {
          "method": "org.eclipse.debug.internal.ui.launchConfigurations.LaunchConfigurationTabGroupViewer.setInput",
          "source": "LaunchConfigurationTabGroupViewer.java:454"
        },
        {
          "method": "org.eclipse.debug.internal.ui.launchConfigurations.LaunchConfigurationsDialog.handleLaunchConfigurationSelectionChanged",
          "source": "LaunchConfigurationsDialog.java:775  "
        },
        {
          "method": "org.eclipse.debug.internal.ui.launchConfigurations.LaunchConfigurationsDialog$3.selectionChanged",
          "source": "LaunchConfigurationsDialog.java:585"
        },
        {
          "method": "org.eclipse.jface.viewers.Viewer$2.run",
          "source": "Viewer.java:159"
        },
        {
          "method": "org.eclipse.core.internal.runtime.InternalPlatform.run",
          "source": "InternalPlatform.java:615"
        },
        {
          "method": "org.eclipse.core.runtime.Platform.run",
          "source": "Platform.java:747"
        },
        {
          "method": "org.eclipse.jface.viewers.Viewer.fireSelectionChanged",
          "source": "Viewer.java:157"
        },
        {
          "method": "org.eclipse.jface.viewers.StructuredViewer.updateSelection",
          "source": "StructuredViewer.java:1394"
        },
        {
          "method": "org.eclipse.jface.viewers.StructuredViewer.setSelection",
          "source": "StructuredViewer.java:1093"
        },
        {
          "method": "org.eclipse.jface.viewers.Viewer.setSelection",
          "source": "Viewer.java:356"
        },
        {
          "method": "org.eclipse.debug.internal.ui.launchConfigurations.LaunchConfigurationsDialog.doInitialTreeSelection",
          "source": "LaunchConfigurationsDialog.java:368"
        },
        {
          "method": "org.eclipse.debug.internal.ui.launchConfigurations.LaunchConfigurationsDialog.initializeContent",
          "source": "LaunchConfigurationsDialog.java:309"
        },
        {
          "method": "org.eclipse.debug.internal.ui.launchConfigurations.LaunchConfigurationsDialog.createContents",
          "source": "LaunchConfigurationsDialog.java:304"
        },
        {
          "method": "org.eclipse.jface.window.Window.create",
          "source": "Window.java:348"
        },
        {
          "method": "org.eclipse.jface.dialogs.Dialog.create",
          "source": "Dialog.java:925"
        },
        {
          "method": "org.eclipse.debug.internal.ui.launchConfigurations.LaunchConfigurationsDialog.create",
          "source": "LaunchConfigurationsDialog.java:1596"
        },
        {
          "method": "org.eclipse.jface.window.Window.open",
          "source": "Window.java:637"
        },
        {
          "method": "org.eclipse.debug.internal.ui.launchConfigurations.LaunchConfigurationsDialog.open",
          "source": "LaunchConfigurationsDialog.java:419"
        },
        {
          "method": "org.eclipse.debug.ui.DebugUITools$1.run",
          "source": "DebugUITools.java:381"
        },
        {
          "method": "org.eclipse.swt.custom.BusyIndicator.showWhile",
          "source": "BusyIndicator.java:69"
        },
        {
          "method": "org.eclipse.debug.ui.DebugUITools.openLaunchConfigurationDialogOnGroup",
          "source": "DebugUITools.java:385"
        },
        {
          "method": "org.eclipse.debug.ui.DebugUITools.openLaunchConfigurationDialogOnGroup",
          "source": "DebugUITools.java:327"
        },
        {
          "method": "org.eclipse.debug.ui.actions.OpenLaunchDialogAction.run",
          "source": "OpenLaunchDialogAction.java:80"
        },
        {
          "method": "org.eclipse.jface.action.Action.runWithEvent",
          "source": "Action.java:881"
        },
        {
          "method": "org.eclipse.jface.action.ActionContributionItem.handleWidgetSelection",
          "source": "ActionContributionItem.java:915"
        },
        {
          "method": "org.eclipse.jface.action.ActionContributionItem.access$2",
          "source": "ActionContributionItem.java:866"
        }
      ],
      "number": 0,
      "commentIndex": 0,
      "bugId": "73377",
      "date": "2004-09-07T17:30:26+02:00",
      "product": "Hyades",
      "component": "Hyades",
      "severity": "major"
    }
  ],
  "groupId": "73377",
  "bugId": "73377",
  "date": "2004-09-07T17:30:26+02:00",
  "product": "Hyades",
  "component": "Hyades",
  "severity": "major"
}