{
  "comments": [
    "Version: WSWB 1.0 + wswb rollup 1 \nPlatform: Windows 2000 (have not tested on Linux) \nSeverity: Stop ship \nProduct: WSDD \n\nWhen you try to use the software update mechanism with rollup 1, it does not \nstart up, instead you get an internal error. \nThis is very severe for WSDD as we are using the software update as a basis of \nour product. This is currently a stop ship item for us. \n\nSteps to recreate: \n1) Install and start WSWB 1.0 \n2) Activate the Software Updates menu item \n        - Perspective -\u003e Customize... \n        - expand Other \n        - select Software Updates \n3) Select Help -\u003e Software Updates \n        - the Software Updates window comes up fine \n4) Close WSWB and install rollup 1 \n5) Start WSWB \n6) Select Help -\u003e Software Updates \n        - you get an error dialog \n9) dismiss dialog and try the Software updates again \n        - you get a different error dialog \n\nHere is the output from the log: \n\nLog: Tue Jan 08 18:00:07 EST 2002 \n1 org.eclipse.core.resources 4 Unhandled exception caught in event loop. \nLog: Tue Jan 08 18:00:07 EST 2002 \n4 org.eclipse.ui 0 java.lang.ExceptionInInitializerError \njava.lang.ExceptionInInitializerError: java.util.MissingResourceException: Can\u0027t \nfind bundle for base name org.eclipse.core.internal.boot.messages, locale en_US \n        at \njava.util.ResourceBundle.throwMissingResourceException(ResourceBundle.java:695) \n        at java.util.ResourceBundle.getBundleImpl(ResourceBundle.java:667) \n        at java.util.ResourceBundle.getBundle(ResourceBundle.java:547) \n        at org.eclipse.core.internal.boot.Policy.relocalize(Policy.java:87) \n        at org.eclipse.core.internal.boot.Policy.\u003cclinit\u003e(Policy.java:15) \n        at \norg.eclipse.core.internal.boot.update.NLResourceHelper.getResourceBundle(NLResou\nrceHelper.java:48) \n        at \norg.eclipse.core.internal.boot.update.NLResourceHelper.getResourceBundle(NLResou\nrceHelper.java:38) \n        at \norg.eclipse.core.internal.boot.update.NLResourceHelper.getResourceString(NLResou\nrceHelper.java:73) \n        at \norg.eclipse.core.internal.boot.update.ProductDescriptor.getLabel(ProductDescript\nor.java:226) \n        at \norg.eclipse.update.internal.ui.UMDialog.initializeContent(UMDialog.java:505) \n        at \norg.eclipse.update.internal.ui.UMDialog.createDialogArea(UMDialog.java:323) \n        at org.eclipse.jface.dialogs.Dialog.createContents(Dialog.java:301) \n        at org.eclipse.jface.window.Window.create(Window.java:237) \n        at org.eclipse.jface.window.Window.open(Window.java:510) \n        at \norg.eclipse.update.internal.ui.UMDialogAction.run(UMDialogAction.java:34) \n        at org.eclipse.ui.internal.PluginAction.run(PluginAction.java:125) \n        at \norg.eclipse.jface.action.ActionContributionItem.handleWidgetSelection(ActionCont\nributionItem.java:407) \n        at \norg.eclipse.jface.action.ActionContributionItem.handleWidgetEvent(ActionContribu\ntionItem.java:361) \n        at \norg.eclipse.jface.action.ActionContributionItem.access$0(ActionContributionItem.\njava:352) \n        at \norg.eclipse.jface.action.ActionContributionItem$ActionListener.handleEvent(Actio\nnContributionItem.java:47) \n        at org.eclipse.swt.widgets.EventTable.sendEvent(EventTable.java(Compiled \nCode)) \n        at org.eclipse.swt.widgets.Widget.notifyListeners(Widget.java:634) \n        at org.eclipse.swt.widgets.Display.runDeferredEvents(Display.java:1282) \n        at org.eclipse.swt.widgets.Display.readAndDispatch(Display.java:1092) \n        at org.eclipse.ui.internal.Workbench.runEventLoop(Workbench.java:673) \n        at org.eclipse.ui.internal.Workbench.run(Workbench.java:656) \n        at \norg.eclipse.core.internal.boot.InternalBootLoader.run(InternalBootLoader.java:81\n5) \n        at org.eclipse.core.boot.BootLoader.run(BootLoader.java:285) \n        at java.lang.reflect.Method.invoke(Native Method) \n        at org.eclipse.core.launcher.Main.basicRun(Main.java:151) \n        at org.eclipse.core.launcher.Main.run(Main.java:437) \n        at org.eclipse.core.launcher.Main.main(Main.java:310) \nLog: Tue Jan 08 18:00:25 EST 2002 \n1 org.eclipse.core.resources 4 Unhandled exception caught in event loop. \nLog: Tue Jan 08 18:00:25 EST 2002 \n4 org.eclipse.ui 0 org/eclipse/core/internal/boot/Policy \njava.lang.NoClassDefFoundError: org/eclipse/core/internal/boot/Policy \n        at \norg.eclipse.core.internal.boot.update.NLResourceHelper.getResourceBundle(NLResou\nrceHelper.java:48) \n        at \norg.eclipse.core.internal.boot.update.NLResourceHelper.getResourceBundle(NLResou\nrceHelper.java:38) \n        at \norg.eclipse.core.internal.boot.update.NLResourceHelper.getResourceString(NLResou\nrceHelper.java:73) \n        at \norg.eclipse.core.internal.boot.update.ProductDescriptor.getLabel(ProductDescript\nor.java:226) \n        at \norg.eclipse.update.internal.ui.UMDialog.initializeContent(UMDialog.java:505) \n        at \norg.eclipse.update.internal.ui.UMDialog.createDialogArea(UMDialog.java:323) \n        at org.eclipse.jface.dialogs.Dialog.createContents(Dialog.java:301) \n        at org.eclipse.jface.window.Window.create(Window.java:237) \n        at org.eclipse.jface.window.Window.open(Window.java:510) \n        at \norg.eclipse.update.internal.ui.UMDialogAction.run(UMDialogAction.java:34) \n        at org.eclipse.ui.internal.PluginAction.run(PluginAction.java:125) \n        at \norg.eclipse.jface.action.ActionContributionItem.handleWidgetSelection(ActionCont\nributionItem.java:407) \n        at \norg.eclipse.jface.action.ActionContributionItem.handleWidgetEvent(ActionContribu\ntionItem.java:361) \n        at \norg.eclipse.jface.action.ActionContributionItem.access$0(ActionContributionItem.\njava:352) \n        at \norg.eclipse.jface.action.ActionContributionItem$ActionListener.handleEvent(Actio\nnContributionItem.java:47) \n        at org.eclipse.swt.widgets.EventTable.sendEvent(EventTable.java(Compiled \nCode)) \n        at org.eclipse.swt.widgets.Widget.notifyListeners(Widget.java:634) \n        at org.eclipse.swt.widgets.Display.runDeferredEvents(Display.java:1282) \n        at org.eclipse.swt.widgets.Display.readAndDispatch(Display.java:1092) \n        at org.eclipse.ui.internal.Workbench.runEventLoop(Workbench.java:673) \n        at org.eclipse.ui.internal.Workbench.run(Workbench.java:656) \n        at \norg.eclipse.core.internal.boot.InternalBootLoader.run(InternalBootLoader.java:81\n5) \n        at org.eclipse.core.boot.BootLoader.run(BootLoader.java:285) \n        at java.lang.reflect.Method.invoke(Native Method) \n        at org.eclipse.core.launcher.Main.basicRun(Main.java:151) \n        at org.eclipse.core.launcher.Main.run(Main.java:437) \n        at org.eclipse.core.launcher.Main.main(Main.java:310)",
    "This is a build problem in org.eclipse.core.boot plugin. The boot.jar is \nmissing org.eclipse.core.internal.boot.messages.properties file. ",
    "Fixed in Rollup 2.\nPR Closed.\n"
  ],
  "commentCreationDates": [
    "2002-01-09T01:15:54+01:00",
    "2002-01-16T23:04:51+01:00",
    "2002-02-15T20:45:53+01:00"
  ],
  "traces": [
    {
      "exceptionType": "java.util.MissingResourceException",
      "message": "Can\u0027t  find bundle for base name org.eclipse.core.internal.boot.messages, locale en_US",
      "elements": [
        {
          "method": "java.util.ResourceBundle.throwMissingResourceException",
          "source": "ResourceBundle.java:695"
        },
        {
          "method": "java.util.ResourceBundle.getBundleImpl",
          "source": "ResourceBundle.java:667"
        },
        {
          "method": "java.util.ResourceBundle.getBundle",
          "source": "ResourceBundle.java:547"
        },
        {
          "method": "org.eclipse.core.internal.boot.Policy.relocalize",
          "source": "Policy.java:87"
        },
        {
          "method": "org.eclipse.core.internal.boot.Policy.\u003cclinit\u003e",
          "source": "Policy.java:15"
        },
        {
          "method": "org.eclipse.core.internal.boot.update.NLResourceHelper.getResourceBundle",
          "source": "NLResou rceHelper.java:48"
        },
        {
          "method": "org.eclipse.core.internal.boot.update.NLResourceHelper.getResourceBundle",
          "source": "NLResou rceHelper.java:38"
        },
        {
          "method": "org.eclipse.core.internal.boot.update.NLResourceHelper.getResourceString",
          "source": "NLResou rceHelper.java:73"
        },
        {
          "method": "org.eclipse.core.internal.boot.update.ProductDescriptor.getLabel",
          "source": "ProductDescript or.java:226"
        },
        {
          "method": "org.eclipse.update.internal.ui.UMDialog.initializeContent",
          "source": "UMDialog.java:505"
        },
        {
          "method": "org.eclipse.update.internal.ui.UMDialog.createDialogArea",
          "source": "UMDialog.java:323"
        },
        {
          "method": "org.eclipse.jface.dialogs.Dialog.createContents",
          "source": "Dialog.java:301"
        },
        {
          "method": "org.eclipse.jface.window.Window.create",
          "source": "Window.java:237"
        },
        {
          "method": "org.eclipse.jface.window.Window.open",
          "source": "Window.java:510"
        },
        {
          "method": "org.eclipse.update.internal.ui.UMDialogAction.run",
          "source": "UMDialogAction.java:34"
        },
        {
          "method": "org.eclipse.ui.internal.PluginAction.run",
          "source": "PluginAction.java:125"
        },
        {
          "method": "org.eclipse.jface.action.ActionContributionItem.handleWidgetSelection",
          "source": "ActionCont ributionItem.java:407"
        },
        {
          "method": "org.eclipse.jface.action.ActionContributionItem.handleWidgetEvent",
          "source": "ActionContribu tionItem.java:361"
        },
        {
          "method": "org.eclipse.jface.action.ActionContributionItem.access$0",
          "source": "ActionContributionItem. java:352"
        },
        {
          "method": "org.eclipse.jface.action.ActionContributionItem$ActionListener.handleEvent",
          "source": "Actio nContributionItem.java:47"
        },
        {
          "method": "org.eclipse.swt.widgets.EventTable.sendEvent",
          "source": "EventTable.java(Compiled  Code)"
        },
        {
          "method": "org.eclipse.swt.widgets.Widget.notifyListeners",
          "source": "Widget.java:634"
        },
        {
          "method": "org.eclipse.swt.widgets.Display.runDeferredEvents",
          "source": "Display.java:1282"
        },
        {
          "method": "org.eclipse.swt.widgets.Display.readAndDispatch",
          "source": "Display.java:1092"
        },
        {
          "method": "org.eclipse.ui.internal.Workbench.runEventLoop",
          "source": "Workbench.java:673"
        },
        {
          "method": "org.eclipse.ui.internal.Workbench.run",
          "source": "Workbench.java:656"
        },
        {
          "method": "org.eclipse.core.internal.boot.InternalBootLoader.run",
          "source": "InternalBootLoader.java:81 5"
        },
        {
          "method": "org.eclipse.core.boot.BootLoader.run",
          "source": "BootLoader.java:285"
        },
        {
          "method": "java.lang.reflect.Method.invoke",
          "source": "Native Method"
        },
        {
          "method": "org.eclipse.core.launcher.Main.basicRun",
          "source": "Main.java:151"
        },
        {
          "method": "org.eclipse.core.launcher.Main.run",
          "source": "Main.java:437"
        },
        {
          "method": "org.eclipse.core.launcher.Main.main",
          "source": "Main.java:310"
        }
      ],
      "number": 0,
      "commentIndex": 0,
      "bugId": "7371",
      "date": "2002-01-09T01:15:54+01:00",
      "product": "Platform",
      "component": "Resources",
      "severity": "blocker"
    },
    {
      "exceptionType": "java.lang.NoClassDefFoundError",
      "message": "org/eclipse/core/internal/boot/Policy",
      "elements": [
        {
          "method": "org.eclipse.core.internal.boot.update.NLResourceHelper.getResourceBundle",
          "source": "NLResou rceHelper.java:48"
        },
        {
          "method": "org.eclipse.core.internal.boot.update.NLResourceHelper.getResourceBundle",
          "source": "NLResou rceHelper.java:38"
        },
        {
          "method": "org.eclipse.core.internal.boot.update.NLResourceHelper.getResourceString",
          "source": "NLResou rceHelper.java:73"
        },
        {
          "method": "org.eclipse.core.internal.boot.update.ProductDescriptor.getLabel",
          "source": "ProductDescript or.java:226"
        },
        {
          "method": "org.eclipse.update.internal.ui.UMDialog.initializeContent",
          "source": "UMDialog.java:505"
        },
        {
          "method": "org.eclipse.update.internal.ui.UMDialog.createDialogArea",
          "source": "UMDialog.java:323"
        },
        {
          "method": "org.eclipse.jface.dialogs.Dialog.createContents",
          "source": "Dialog.java:301"
        },
        {
          "method": "org.eclipse.jface.window.Window.create",
          "source": "Window.java:237"
        },
        {
          "method": "org.eclipse.jface.window.Window.open",
          "source": "Window.java:510"
        },
        {
          "method": "org.eclipse.update.internal.ui.UMDialogAction.run",
          "source": "UMDialogAction.java:34"
        },
        {
          "method": "org.eclipse.ui.internal.PluginAction.run",
          "source": "PluginAction.java:125"
        },
        {
          "method": "org.eclipse.jface.action.ActionContributionItem.handleWidgetSelection",
          "source": "ActionCont ributionItem.java:407"
        },
        {
          "method": "org.eclipse.jface.action.ActionContributionItem.handleWidgetEvent",
          "source": "ActionContribu tionItem.java:361"
        },
        {
          "method": "org.eclipse.jface.action.ActionContributionItem.access$0",
          "source": "ActionContributionItem. java:352"
        },
        {
          "method": "org.eclipse.jface.action.ActionContributionItem$ActionListener.handleEvent",
          "source": "Actio nContributionItem.java:47"
        },
        {
          "method": "org.eclipse.swt.widgets.EventTable.sendEvent",
          "source": "EventTable.java(Compiled  Code)"
        },
        {
          "method": "org.eclipse.swt.widgets.Widget.notifyListeners",
          "source": "Widget.java:634"
        },
        {
          "method": "org.eclipse.swt.widgets.Display.runDeferredEvents",
          "source": "Display.java:1282"
        },
        {
          "method": "org.eclipse.swt.widgets.Display.readAndDispatch",
          "source": "Display.java:1092"
        },
        {
          "method": "org.eclipse.ui.internal.Workbench.runEventLoop",
          "source": "Workbench.java:673"
        },
        {
          "method": "org.eclipse.ui.internal.Workbench.run",
          "source": "Workbench.java:656"
        },
        {
          "method": "org.eclipse.core.internal.boot.InternalBootLoader.run",
          "source": "InternalBootLoader.java:81 5"
        },
        {
          "method": "org.eclipse.core.boot.BootLoader.run",
          "source": "BootLoader.java:285"
        },
        {
          "method": "java.lang.reflect.Method.invoke",
          "source": "Native Method"
        },
        {
          "method": "org.eclipse.core.launcher.Main.basicRun",
          "source": "Main.java:151"
        },
        {
          "method": "org.eclipse.core.launcher.Main.run",
          "source": "Main.java:437"
        },
        {
          "method": "org.eclipse.core.launcher.Main.main",
          "source": "Main.java:310"
        }
      ],
      "number": 1,
      "commentIndex": 0,
      "bugId": "7371",
      "date": "2002-01-09T01:15:54+01:00",
      "product": "Platform",
      "component": "Resources",
      "severity": "blocker"
    }
  ],
  "groupId": "7371",
  "bugId": "7371",
  "date": "2002-01-09T01:15:54+01:00",
  "product": "Platform",
  "component": "Resources",
  "severity": "blocker"
}