{
  "comments": [
    "Actually I don\u0027t know what\u0027s going wrong. I do an install of eclipse to /opt/\n_eclipse and add the TruStudio Plugin from Xored. I can\u0027t enable the php editor \nand I can\u0027t adjust preferences for the module PHP or Python either. Because of \nthe output in .log I think it\u0027s more of a fundamental failure, then actually \nwith Xored.\n\nLog follows:\n\n~/workspace/.metadata% cat .log\n!SESSION Sep 14, 2004 16:35:38.703 ---------------------------------------------\njava.version\u003d1.4.2_03\njava.vendor\u003dSun Microsystems Inc.\nBootLoader constants: OS\u003dlinux, ARCH\u003dx86, WS\u003dgtk, NL\u003den_US\n!ENTRY org.eclipse.core.runtime 4 2 Sep 14, 2004 16:35:38.705\n!MESSAGE Problems occurred when invoking code from plug-in: \"org.eclipse.core.\nruntime\".\n!STACK 0\njava.lang.NoClassDefFoundError: org/eclipse/jface/text/templates/persistence/\nTemplateStore\n        at java.lang.Class.getDeclaredConstructors0(Native Method)\n        at java.lang.Class.privateGetDeclaredConstructors(Unknown Source)\n        at java.lang.Class.getConstructor0(Unknown Source)\n        at java.lang.Class.newInstance0(Unknown Source)\n        at java.lang.Class.newInstance(Unknown Source)\n[...]\n!ENTRY org.eclipse.core.runtime 4 2 Sep 14, 2004 16:55:13.899\n!MESSAGE Problems occurred when invoking code from plug-in: \"org.eclipse.core.\nruntime\".\n!STACK 0\njava.lang.NoClassDefFoundError: org/eclipse/ui/texteditor/\nAbstractDecoratedTextEditor\n        at java.lang.ClassLoader.defineClass0(Native Method)\n        at java.lang.ClassLoader.defineClass(Unknown Source)\n[...]\n\nenvironment is as follows:\n\nCLASSPATH\u003d/opt/_j2re/lib/rt.jar\nJAVA_HOME\u003d/opt/_j2re\nPATH\u003d/home/thomas/local/bin:/opt/_j2re/bin:[...]",
    "Could you please attach a full .log file containing only this problem?\n",
    "Please re-open with more details."
  ],
  "commentCreationDates": [
    "2004-09-14T17:03:42+02:00",
    "2004-09-14T19:27:23+02:00",
    "2004-10-14T21:52:52+02:00"
  ],
  "traces": [
    {
      "exceptionType": "java.lang.NoClassDefFoundError",
      "message": "org/eclipse/jface/text/templates/persistence/ TemplateStore",
      "elements": [
        {
          "method": "java.lang.Class.getDeclaredConstructors0",
          "source": "Native Method"
        },
        {
          "method": "java.lang.Class.privateGetDeclaredConstructors",
          "source": "Unknown Source"
        },
        {
          "method": "java.lang.Class.getConstructor0",
          "source": "Unknown Source"
        },
        {
          "method": "java.lang.Class.newInstance0",
          "source": "Unknown Source"
        },
        {
          "method": "java.lang.Class.newInstance",
          "source": "Unknown Source"
        }
      ],
      "number": 0,
      "commentIndex": 0,
      "bugId": "73879",
      "date": "2004-09-14T17:03:42+02:00",
      "product": "Platform",
      "component": "Runtime",
      "severity": "normal"
    },
    {
      "exceptionType": "java.lang.NoClassDefFoundError",
      "message": "org/eclipse/ui/texteditor/ AbstractDecoratedTextEditor",
      "elements": [
        {
          "method": "java.lang.ClassLoader.defineClass0",
          "source": "Native Method"
        },
        {
          "method": "java.lang.ClassLoader.defineClass",
          "source": "Unknown Source"
        }
      ],
      "number": 1,
      "commentIndex": 0,
      "bugId": "73879",
      "date": "2004-09-14T17:03:42+02:00",
      "product": "Platform",
      "component": "Runtime",
      "severity": "normal"
    }
  ],
  "groupId": "73879",
  "bugId": "73879",
  "date": "2004-09-14T17:03:42+02:00",
  "product": "Platform",
  "component": "Runtime",
  "severity": "normal"
}