{
  "comments": [
    "Problem is that RulerProvider.getAttachedEditParts(...) does not check that edit\npart for the returned model element is registered in viewer registry.\n\n!MESSAGE java.lang.NullPointerException\n!STACK 0\njava.lang.NullPointerException\n        at org.eclipse.gef.internal.ui.rulers.DragGuidePolicy.showAttachedPartsF\needback(DragGuidePolicy.java:197)\n        at org.eclipse.gef.internal.ui.rulers.DragGuidePolicy.showSourceFeedback\n(DragGuidePolicy.java:239)\n        at org.eclipse.gef.editparts.AbstractEditPart.showSourceFeedback(Abstrac\ntEditPart.java:979)\n        at org.eclipse.gef.tools.DragEditPartsTracker.showSourceFeedback(DragEdi\ntPartsTracker.java:502)\n        at org.eclipse.gef.tools.DragEditPartsTracker.handleDragInProgress(DragE\nditPartsTracker.java:320)\n        at org.eclipse.gef.tools.AbstractTool.mouseDrag(AbstractTool.java:982)\n        at org.eclipse.gef.tools.SelectionTool.mouseDrag(SelectionTool.java:502)\n\n        at org.eclipse.gef.EditDomain.mouseDrag(EditDomain.java:208)\n        at org.eclipse.gef.ui.parts.DomainEventDispatcher.dispatchMouseMoved(Dom\nainEventDispatcher.java:327)\n        at org.eclipse.draw2d.LightweightSystem$EventHandler.mouseMove(Lightweig\nhtSystem.java:511)\n        at org.eclipse.swt.widgets.TypedListener.handleEvent(TypedListener.java:\n144)\n        at org.eclipse.swt.widgets.EventTable.sendEvent(EventTable.java:82)\n        at org.eclipse.swt.widgets.Widget.sendEvent(Widget.java:796)\n        at org.eclipse.swt.widgets.Display.runDeferredEvents(Display.java:2772)\n        at org.eclipse.swt.widgets.Display.readAndDispatch(Display.java:2431)\n        at org.eclipse.ui.internal.Workbench.runEventLoop(Workbench.java:1377)\n        at org.eclipse.ui.internal.Workbench.runUI(Workbench.java:1348)\n        at org.eclipse.ui.internal.Workbench.createAndRunWorkbench(Workbench.jav\na:254)\n        at org.eclipse.ui.PlatformUI.createAndRunWorkbench(PlatformUI.java:141)\n        at org.eclipse.ui.internal.ide.IDEApplication.run(IDEApplication.java:96\n)\n        at org.eclipse.core.internal.runtime.PlatformActivator$1.run(PlatformAct\nivator.java:335)\n        at org.eclipse.core.runtime.adaptor.EclipseStarter.run(EclipseStarter.ja\nva:273)\n        at org.eclipse.core.runtime.adaptor.EclipseStarter.run(EclipseStarter.ja\nva:129)\n        at sun.reflect.NativeMethodAccessorImpl.invoke0(Native Method)\n        at sun.reflect.NativeMethodAccessorImpl.invoke(NativeMethodAccessorImpl.\njava:39)\n        at sun.reflect.DelegatingMethodAccessorImpl.invoke(DelegatingMethodAcces\nsorImpl.java:25)\n        at java.lang.reflect.Method.invoke(Method.java:324)\n        at org.eclipse.core.launcher.Main.basicRun(Main.java:183)\n        at org.eclipse.core.launcher.Main.run(Main.java:644)\n        at org.eclipse.core.launcher.Main.main(Main.java:628)\njava.lang.NullPointerException",
    "So, you want hidden editparts to move with the guides they are attached to?\n\nI\u0027ve fixed this and released to HEAD.  It should be in tonight\u0027s build.",
    "*** Bug 83144 has been marked as a duplicate of this bug. ***"
  ],
  "commentCreationDates": [
    "2004-09-14T18:36:42+02:00",
    "2004-09-23T00:51:12+02:00",
    "2005-01-19T22:21:42+01:00"
  ],
  "traces": [
    {
      "exceptionType": "java.lang.NullPointerException",
      "elements": [
        {
          "method": "org.eclipse.gef.internal.ui.rulers.DragGuidePolicy.showAttachedPartsFeedback",
          "source": "DragGuidePolicy.java:197"
        },
        {
          "method": "org.eclipse.gef.internal.ui.rulers.DragGuidePolicy.showSourceFeedback",
          "source": "DragGuidePolicy.java:239"
        },
        {
          "method": "org.eclipse.gef.editparts.AbstractEditPart.showSourceFeedback",
          "source": "Abstrac tEditPart.java:979"
        },
        {
          "method": "org.eclipse.gef.tools.DragEditPartsTracker.showSourceFeedback",
          "source": "DragEdi tPartsTracker.java:502"
        },
        {
          "method": "org.eclipse.gef.tools.DragEditPartsTracker.handleDragInProgress",
          "source": "DragE ditPartsTracker.java:320"
        },
        {
          "method": "org.eclipse.gef.tools.AbstractTool.mouseDrag",
          "source": "AbstractTool.java:982"
        },
        {
          "method": "org.eclipse.gef.tools.SelectionTool.mouseDrag",
          "source": "SelectionTool.java:502"
        },
        {
          "method": "org.eclipse.gef.EditDomain.mouseDrag",
          "source": "EditDomain.java:208"
        },
        {
          "method": "org.eclipse.gef.ui.parts.DomainEventDispatcher.dispatchMouseMoved",
          "source": "Dom ainEventDispatcher.java:327"
        },
        {
          "method": "org.eclipse.draw2d.LightweightSystem$EventHandler.mouseMove",
          "source": "Lightweig htSystem.java:511"
        },
        {
          "method": "org.eclipse.swt.widgets.TypedListener.handleEvent",
          "source": "TypedListener.java: 144"
        },
        {
          "method": "org.eclipse.swt.widgets.EventTable.sendEvent",
          "source": "EventTable.java:82"
        },
        {
          "method": "org.eclipse.swt.widgets.Widget.sendEvent",
          "source": "Widget.java:796"
        },
        {
          "method": "org.eclipse.swt.widgets.Display.runDeferredEvents",
          "source": "Display.java:2772"
        },
        {
          "method": "org.eclipse.swt.widgets.Display.readAndDispatch",
          "source": "Display.java:2431"
        },
        {
          "method": "org.eclipse.ui.internal.Workbench.runEventLoop",
          "source": "Workbench.java:1377"
        },
        {
          "method": "org.eclipse.ui.internal.Workbench.runUI",
          "source": "Workbench.java:1348"
        },
        {
          "method": "org.eclipse.ui.internal.Workbench.createAndRunWorkbench",
          "source": "Workbench.jav a:254"
        },
        {
          "method": "org.eclipse.ui.PlatformUI.createAndRunWorkbench",
          "source": "PlatformUI.java:141"
        },
        {
          "method": "org.eclipse.ui.internal.ide.IDEApplication.run",
          "source": "IDEApplication.java:96 "
        },
        {
          "method": "org.eclipse.core.internal.runtime.PlatformActivator$1.run",
          "source": "PlatformAct ivator.java:335"
        },
        {
          "method": "org.eclipse.core.runtime.adaptor.EclipseStarter.run",
          "source": "EclipseStarter.ja va:273"
        },
        {
          "method": "org.eclipse.core.runtime.adaptor.EclipseStarter.run",
          "source": "EclipseStarter.ja va:129"
        },
        {
          "method": "sun.reflect.NativeMethodAccessorImpl.invoke0",
          "source": "Native Method"
        },
        {
          "method": "sun.reflect.NativeMethodAccessorImpl.invoke",
          "source": "NativeMethodAccessorImpl. java:39"
        },
        {
          "method": "sun.reflect.DelegatingMethodAccessorImpl.invoke",
          "source": "DelegatingMethodAcces sorImpl.java:25"
        },
        {
          "method": "java.lang.reflect.Method.invoke",
          "source": "Method.java:324"
        },
        {
          "method": "org.eclipse.core.launcher.Main.basicRun",
          "source": "Main.java:183"
        },
        {
          "method": "org.eclipse.core.launcher.Main.run",
          "source": "Main.java:644"
        },
        {
          "method": "org.eclipse.core.launcher.Main.main",
          "source": "Main.java:628"
        }
      ],
      "number": 0,
      "commentIndex": 0,
      "bugId": "73892",
      "date": "2004-09-14T18:36:42+02:00",
      "product": "GEF",
      "component": "GEF",
      "severity": "normal"
    }
  ],
  "groupId": "73892",
  "bugId": "73892",
  "date": "2004-09-14T18:36:42+02:00",
  "product": "GEF",
  "component": "GEF",
  "severity": "normal"
}