{
  "comments": [
    "build i0920\n\nI get the following exception in my .log file when I try and close a project\n(via the Navigator view).\n\n!ENTRY org.eclipse.core.runtime 4 2 Sep 20, 2004 14:49:02.563\n!MESSAGE Problems occurred when invoking code from plug-in:\n\"org.eclipse.core.runtime\".\n!STACK 0\njava.lang.NullPointerException\n        at\norg.eclipse.core.internal.filebuffers.ResourceFileBuffer$FileSynchronizer.resourceChanged(ResourceFileBuffer.java:118)\n        at\norg.eclipse.core.internal.events.NotificationManager$2.run(NotificationManager.java:283)\n        at\norg.eclipse.core.internal.runtime.InternalPlatform.run(InternalPlatform.java:615)\n        at org.eclipse.core.runtime.Platform.run(Platform.java:747)\n        at\norg.eclipse.core.internal.events.NotificationManager.notify(NotificationManager.java:277)\n        at\norg.eclipse.core.internal.events.NotificationManager.handleEvent(NotificationManager.java:249)\n        at\norg.eclipse.core.internal.resources.Workspace.broadcastEvent(Workspace.java:182)\n        at org.eclipse.core.internal.resources.Project.close(Project.java:170)\n        at\norg.eclipse.ui.actions.CloseResourceAction.invokeOperation(CloseResourceAction.java:175)\n        at org.eclipse.ui.actions.WorkspaceAction.execute(WorkspaceAction.java:136)\n        at\norg.eclipse.ui.actions.WorkspaceAction$1.execute(WorkspaceAction.java:305)\n        at\norg.eclipse.ui.actions.WorkspaceModifyOperation$1.run(WorkspaceModifyOperation.java:98)\n        at org.eclipse.core.internal.resources.Workspace.run(Workspace.java:1674)\n        at\norg.eclipse.ui.actions.WorkspaceModifyOperation.run(WorkspaceModifyOperation.java:110)\n        at\norg.eclipse.jface.operation.ModalContext$ModalContextThread.run(ModalContext.java:105)",
    "Fixed. Build 200409210800",
    "I am still getting this in build 0921-0800.",
    "Sorry, we did not contribute to I200409210800. The fix is in builds \u003e\u003d I200409211600",
    "*** Bug 74464 has been marked as a duplicate of this bug. ***"
  ],
  "commentCreationDates": [
    "2004-09-20T20:56:58+02:00",
    "2004-09-21T10:17:32+02:00",
    "2004-09-22T00:17:55+02:00",
    "2004-09-22T08:46:51+02:00",
    "2004-09-22T08:47:37+02:00"
  ],
  "traces": [
    {
      "exceptionType": "java.lang.NullPointerException",
      "elements": [
        {
          "method": "org.eclipse.core.internal.filebuffers.ResourceFileBuffer$FileSynchronizer.resourceChanged",
          "source": "ResourceFileBuffer.java:118"
        },
        {
          "method": "org.eclipse.core.internal.events.NotificationManager$2.run",
          "source": "NotificationManager.java:283"
        },
        {
          "method": "org.eclipse.core.internal.runtime.InternalPlatform.run",
          "source": "InternalPlatform.java:615"
        },
        {
          "method": "org.eclipse.core.runtime.Platform.run",
          "source": "Platform.java:747"
        },
        {
          "method": "org.eclipse.core.internal.events.NotificationManager.notify",
          "source": "NotificationManager.java:277"
        },
        {
          "method": "org.eclipse.core.internal.events.NotificationManager.handleEvent",
          "source": "NotificationManager.java:249"
        },
        {
          "method": "org.eclipse.core.internal.resources.Workspace.broadcastEvent",
          "source": "Workspace.java:182"
        },
        {
          "method": "org.eclipse.core.internal.resources.Project.close",
          "source": "Project.java:170"
        },
        {
          "method": "org.eclipse.ui.actions.CloseResourceAction.invokeOperation",
          "source": "CloseResourceAction.java:175"
        },
        {
          "method": "org.eclipse.ui.actions.WorkspaceAction.execute",
          "source": "WorkspaceAction.java:136"
        },
        {
          "method": "org.eclipse.ui.actions.WorkspaceAction$1.execute",
          "source": "WorkspaceAction.java:305"
        },
        {
          "method": "org.eclipse.ui.actions.WorkspaceModifyOperation$1.run",
          "source": "WorkspaceModifyOperation.java:98"
        },
        {
          "method": "org.eclipse.core.internal.resources.Workspace.run",
          "source": "Workspace.java:1674"
        },
        {
          "method": "org.eclipse.ui.actions.WorkspaceModifyOperation.run",
          "source": "WorkspaceModifyOperation.java:110"
        },
        {
          "method": "org.eclipse.jface.operation.ModalContext$ModalContextThread.run",
          "source": "ModalContext.java:105"
        }
      ],
      "number": 0,
      "commentIndex": 0,
      "bugId": "74344",
      "date": "2004-09-20T20:56:58+02:00",
      "product": "Platform",
      "component": "Text",
      "severity": "normal"
    }
  ],
  "groupId": "74344",
  "bugId": "74344",
  "date": "2004-09-20T20:56:58+02:00",
  "product": "Platform",
  "component": "Text",
  "severity": "normal"
}