{
  "comments": [
    "I had a fresh installed Eclipse 3.0 with some small plugins, nothing special and\nupdated to 3.0.1 using the integrated update of Eclipse.\nAll stuff (bin+conf+workspace) are located in \"C:\\Program Files\\Eclipse3\"\n\nAfter successful (?) update I get the error message:\n An error has occurred. See the log file\n c:\\Progam\n\nThe log file only shows as error:\n!ENTRY org.eclipse.osgi Sep 21, 2004 13:35:29.492\n!MESSAGE Application error\n!STACK 1\njava.lang.RuntimeException: No application id has been found.\n\tat\norg.eclipse.core.internal.runtime.PlatformActivator$1.run(PlatformActivator.java:313)\n\tat org.eclipse.core.runtime.adaptor.EclipseStarter.run(EclipseStarter.java:273)\n\tat org.eclipse.core.runtime.adaptor.EclipseStarter.run(EclipseStarter.java:129)\n\tat sun.reflect.NativeMethodAccessorImpl.invoke0(Native Method)\n\tat sun.reflect.NativeMethodAccessorImpl.invoke(Unknown Source)\n\tat sun.reflect.DelegatingMethodAccessorImpl.invoke(Unknown Source)\n\tat java.lang.reflect.Method.invoke(Unknown Source)\n\tat org.eclipse.core.launcher.Main.basicRun(Main.java:183)\n\tat org.eclipse.core.launcher.Main.run(Main.java:644)\n\tat org.eclipse.core.launcher.Main.main(Main.java:628)\n\nWhat do I need to do to recover my installation?\nIt seems to be broken due to the automatic update.",
    "Looks like bug #74377.",
    "Nope, I do not agree. I have a different message.\nI played around with the installed files (after archiving them...) - The IDE now\nis able to come up if \nconfiguration\\org.eclipse.update\\platform.xml\nis erased from disk prior starting.\nThen a lot of other thisng do not work - but it look like the application fails\ndue some kind of update hook?",
    "\n\n*** This bug has been marked as a duplicate of 74377 ***"
  ],
  "commentCreationDates": [
    "2004-09-21T13:56:02+02:00",
    "2004-09-21T14:41:49+02:00",
    "2004-09-21T14:45:53+02:00",
    "2004-09-22T20:19:11+02:00"
  ],
  "traces": [
    {
      "exceptionType": "java.lang.RuntimeException",
      "message": "No application id has been found.",
      "elements": [
        {
          "method": "org.eclipse.core.internal.runtime.PlatformActivator$1.run",
          "source": "PlatformActivator.java:313"
        },
        {
          "method": "org.eclipse.core.runtime.adaptor.EclipseStarter.run",
          "source": "EclipseStarter.java:273"
        },
        {
          "method": "org.eclipse.core.runtime.adaptor.EclipseStarter.run",
          "source": "EclipseStarter.java:129"
        },
        {
          "method": "sun.reflect.NativeMethodAccessorImpl.invoke0",
          "source": "Native Method"
        },
        {
          "method": "sun.reflect.NativeMethodAccessorImpl.invoke",
          "source": "Unknown Source"
        },
        {
          "method": "sun.reflect.DelegatingMethodAccessorImpl.invoke",
          "source": "Unknown Source"
        },
        {
          "method": "java.lang.reflect.Method.invoke",
          "source": "Unknown Source"
        },
        {
          "method": "org.eclipse.core.launcher.Main.basicRun",
          "source": "Main.java:183"
        },
        {
          "method": "org.eclipse.core.launcher.Main.run",
          "source": "Main.java:644"
        },
        {
          "method": "org.eclipse.core.launcher.Main.main",
          "source": "Main.java:628"
        }
      ],
      "number": 0,
      "commentIndex": 0,
      "bugId": "74412",
      "duplicateId": "74377",
      "date": "2004-09-21T13:56:02+02:00",
      "product": "Platform",
      "component": "Runtime",
      "severity": "critical"
    }
  ],
  "groupId": "74624",
  "bugId": "74412",
  "duplicateId": "74377",
  "date": "2004-09-21T13:56:02+02:00",
  "product": "Platform",
  "component": "Runtime",
  "severity": "critical"
}