{
  "comments": [
    "build i0923-0800\n\nSorry, no reproducable steps. I just noticed this in my log file after doing a\nbunch of Java searches.\n\n!ENTRY org.eclipse.jdt.ui 4 10001 Sep 23, 2004 12:02:13.593\n!MESSAGE Internal Error\n!STACK 0\njava.lang.IllegalMonitorStateException\n        at java.lang.Object.notifyAll(Native Method)\n        at\norg.eclipse.jdt.internal.core.search.indexing.ReadWriteMonitor.exitRead(ReadWriteMonitor.java:58)\n        at\norg.eclipse.jdt.internal.core.search.PatternSearchJob.search(PatternSearchJob.java:119)\n        at\norg.eclipse.jdt.internal.core.search.PatternSearchJob.execute(PatternSearchJob.java:64)\n        at\norg.eclipse.jdt.internal.core.search.processing.JobManager.performConcurrentJob(JobManager.java:260)\n        at\norg.eclipse.jdt.core.search.SearchEngine.searchAllTypeNames(SearchEngine.java:870)\n        at\norg.eclipse.jdt.internal.corext.util.AllTypesCache.search(AllTypesCache.java:539)\n        at\norg.eclipse.jdt.internal.corext.util.AllTypesCache$TypeCacher.doSearchTypes(AllTypesCache.java:204)\n        at\norg.eclipse.jdt.internal.corext.util.AllTypesCache$TypeCacher.run(AllTypesCache.java:169)",
    "\n\n*** This bug has been marked as a duplicate of 73226 ***"
  ],
  "commentCreationDates": [
    "2004-09-23T18:10:44+02:00",
    "2004-09-23T19:41:59+02:00"
  ],
  "traces": [
    {
      "exceptionType": "java.lang.IllegalMonitorStateException",
      "elements": [
        {
          "method": "java.lang.Object.notifyAll",
          "source": "Native Method"
        },
        {
          "method": "org.eclipse.jdt.internal.core.search.indexing.ReadWriteMonitor.exitRead",
          "source": "ReadWriteMonitor.java:58"
        },
        {
          "method": "org.eclipse.jdt.internal.core.search.PatternSearchJob.search",
          "source": "PatternSearchJob.java:119"
        },
        {
          "method": "org.eclipse.jdt.internal.core.search.PatternSearchJob.execute",
          "source": "PatternSearchJob.java:64"
        },
        {
          "method": "org.eclipse.jdt.internal.core.search.processing.JobManager.performConcurrentJob",
          "source": "JobManager.java:260"
        },
        {
          "method": "org.eclipse.jdt.core.search.SearchEngine.searchAllTypeNames",
          "source": "SearchEngine.java:870"
        },
        {
          "method": "org.eclipse.jdt.internal.corext.util.AllTypesCache.search",
          "source": "AllTypesCache.java:539"
        },
        {
          "method": "org.eclipse.jdt.internal.corext.util.AllTypesCache$TypeCacher.doSearchTypes",
          "source": "AllTypesCache.java:204"
        },
        {
          "method": "org.eclipse.jdt.internal.corext.util.AllTypesCache$TypeCacher.run",
          "source": "AllTypesCache.java:169"
        }
      ],
      "number": 0,
      "commentIndex": 0,
      "bugId": "74794",
      "duplicateId": "73226",
      "date": "2004-09-23T18:10:44+02:00",
      "product": "JDT",
      "component": "Core",
      "severity": "normal"
    }
  ],
  "groupId": "73226",
  "bugId": "74794",
  "duplicateId": "73226",
  "date": "2004-09-23T18:10:44+02:00",
  "product": "JDT",
  "component": "Core",
  "severity": "normal"
}