{
  "comments": [
    "In our use of CVS we use taginfo to check the validity of a tag. If the tag is \ninvalid then the script executed exits with an exit code of 1, otherwise it \nexits with an exit code of 0. \n\nThe non-zero exit code from taginfo results in an \"internal error\" being \nreturned and the relevant message from our taginfo script, which would tell the \nuser why the tag was invalid, is never displayed.\n\nAs a point of comparison the above scenario works perfectly from a commitinfo \nscript. It either completes successfully or reports an error which is visible \nin Eclipse. \n\nWhen I posted the above question on the newsgroup Michael suggested I log this \nas a bug and directed me to get the debug info pasted below. I have pasted the \noutput from a successful and unsuccessful tag command.\n\nThanks\n\nGavin\n\n++++++++++++++++++\n\n+++++++++++++++++++++++++++++++++++++++++++++++++++++++++++++++\nThe output from a failed cvs tag command\n+++++++++++++++++++++++++++++++++++++++++++++++++++++++++++++++\n***\ncvs version\n    Concurrent Versions System (CVS) 1.11.2 (client/server)\nok (took 0:00.234)\n***\n\n***\ncvs tag \"/testing/this_is_an_invalid_tag\" \"/testing/HelloWorld.java\"\nfailed due to an internal error (took 0:00.390)\n***\n\nInstall location:\n    file:/c:/eclipse/\nConfiguration file:\n    file:/c:/eclipse/configuration/config.ini loaded\nConfiguration location:\n    file:/c:/eclipse/configuration/\nConfiguration file:\n    file:/c:/eclipse/configuration/config.ini loaded\nFramework located:\n    file:/c:/eclipse/plugins/org.eclipse.osgi_3.0.0/\nLoading framework classpath from:\n    file:/c:/eclipse/plugins/org.eclipse.osgi_3.0.0/eclipse.properties\nFramework classpath:\n    file:/c:/eclipse/plugins/org.eclipse.osgi_3.0.0/core.jar\n    file:/c:/eclipse/plugins/org.eclipse.osgi_3.0.0/console.jar\n    file:/c:/eclipse/plugins/org.eclipse.osgi_3.0.0/osgi.jar\n    file:/c:/eclipse/plugins/org.eclipse.osgi_3.0.0/resolver.jar\n    file:/c:/eclipse/plugins/org.eclipse.osgi_3.0.0/defaultAdaptor.jar\n    file:/c:/eclipse/plugins/org.eclipse.osgi_3.0.0/eclipseAdaptor.jar\nDebug options:\n    file:/C:/Documents/Java/Eclipse/.options not found\nTime to load bundles: 47\n!SESSION Sep 27, 2004 15:50:18.918 ---------------------------------------------\neclipse.buildId\u003dI200406192000\njava.version\u003d1.4.2\njava.vendor\u003dSun Microsystems Inc.\nBootLoader constants: OS\u003dwin32, ARCH\u003dx86, WS\u003dwin32, NL\u003den_ZA\n\n!ENTRY org.eclipse.osgi Sep 27, 2004 15:50:18.933\n!MESSAGE Bundle update@/c:/eclipse/plugins/org.apache.ant_1.5.4/ [9] was not \nresolved.\n!SUBENTRY 1 org.eclipse.osgi Sep 27, 2004 15:50:18.933\n!MESSAGE Bundle update@/c:/eclipse/plugins/org.apache.ant_1.6.1/ was picked \ninstead.\n\n!ENTRY org.eclipse.osgi Sep 27, 2004 15:50:18.949\n!MESSAGE Bundle update@/c:/eclipse/plugins/org.apache.lucene_1.3.0/ [11] was \nnot resolved.\n!SUBENTRY 1 org.eclipse.osgi Sep 27, 2004 15:50:18.949\n!MESSAGE Bundle update@/c:/eclipse/plugins/org.apache.lucene_1.3.0.RC2/ was \npicked instead.\n\n!ENTRY org.eclipse.osgi Sep 27, 2004 15:50:18.964\n!MESSAGE Bundle update@/c:/eclipse/plugins/org.eclipse.tomcat_4.1.29/ [75] was \nnot resolved.\n!SUBENTRY 1 org.eclipse.osgi Sep 27, 2004 15:50:18.964\n!MESSAGE Bundle update@/c:/eclipse/plugins/org.eclipse.tomcat_4.1.30/ was \npicked instead.\n\n!ENTRY org.eclipse.osgi Sep 27, 2004 15:50:18.980\n!MESSAGE Bundle update@/c:/eclipse/plugins/org.apache.ant_1.6.0/ [98] was not \nresolved.\n!SUBENTRY 1 org.eclipse.osgi Sep 27, 2004 15:50:18.996\n!MESSAGE Bundle update@/c:/eclipse/plugins/org.apache.ant_1.6.1/ was picked \ninstead.\nStarting application: 1797\n\n!ENTRY org.eclipse.osgi Sep 27, 2004 15:50:42.121\n!MESSAGE While loading \nclass \"org.eclipse.team.internal.ccvs.ui.console.ConsoleDocument$ConsoleLine\"\n, thread \"main\" timed out waiting (5000ms) for thread \"Worker-1\" to finish \nstarting bundle \"org.ecli\npse.team.cvs.ui\". To avoid deadlock, thread \"main\" is proceeding \nbut \"org.eclipse.team.internal.ccvs\n.ui.console.ConsoleDocument$ConsoleLine\" may not be fully initialized.\n!STACK 0\njava.lang.Exception: Generated exception.\n        at org.eclipse.core.runtime.adaptor.EclipseClassLoader.findLocalClass\n(EclipseClassLoader.jav\na:102)\n        at org.eclipse.osgi.framework.internal.core.BundleLoader.findLocalClass\n(BundleLoader.java:37\n1)\n        at org.eclipse.osgi.framework.internal.core.BundleLoader.findClass\n(BundleLoader.java:402)\n        at org.eclipse.osgi.framework.adaptor.core.AbstractClassLoader.loadClass\n(AbstractClassLoader\n.java:93)\n        at java.lang.ClassLoader.loadClass(ClassLoader.java:235)\n        at java.lang.ClassLoader.loadClassInternal(ClassLoader.java:302)\n        at org.eclipse.team.internal.ccvs.ui.console.ConsoleDocument.getLines\n(ConsoleDocument.java:7\n8)\n        at org.eclipse.team.internal.ccvs.ui.console.CVSOutputConsole.dump\n(CVSOutputConsole.java:140\n)\n        at org.eclipse.team.internal.ccvs.ui.console.CVSOutputConsole.access$1\n(CVSOutputConsole.java\n:137)\n        at org.eclipse.team.internal.ccvs.ui.console.CVSOutputConsole$1.run\n(CVSOutputConsole.java:10\n8)\n        at org.eclipse.swt.widgets.RunnableLock.run(RunnableLock.java:35)\n        at org.eclipse.swt.widgets.Synchronizer.runAsyncMessages\n(Synchronizer.java:106)\n        at org.eclipse.swt.widgets.Display.runAsyncMessages(Display.java:2709)\n        at org.eclipse.swt.widgets.Display.readAndDispatch(Display.java:2401)\n        at org.eclipse.ui.internal.Workbench.runEventLoop(Workbench.java:1375)\n        at org.eclipse.ui.internal.Workbench.runUI(Workbench.java:1346)\n        at org.eclipse.ui.internal.Workbench.createAndRunWorkbench\n(Workbench.java:252)\n        at org.eclipse.ui.PlatformUI.createAndRunWorkbench(PlatformUI.java:141)\n        at org.eclipse.ui.internal.ide.IDEApplication.run\n(IDEApplication.java:96)\n        at org.eclipse.core.internal.runtime.PlatformActivator$1.run\n(PlatformActivator.java:335)\n        at org.eclipse.core.runtime.adaptor.EclipseStarter.run\n(EclipseStarter.java:272)\n        at org.eclipse.core.runtime.adaptor.EclipseStarter.run\n(EclipseStarter.java:128)\n        at sun.reflect.NativeMethodAccessorImpl.invoke0(Native Method)\n        at sun.reflect.NativeMethodAccessorImpl.invoke\n(NativeMethodAccessorImpl.java:39)\n        at sun.reflect.DelegatingMethodAccessorImpl.invoke\n(DelegatingMethodAccessorImpl.java:25)\n        at java.lang.reflect.Method.invoke(Method.java:324)\n        at org.eclipse.core.launcher.Main.basicRun(Main.java:186)\n        at org.eclipse.core.launcher.Main.run(Main.java:647)\n        at org.eclipse.core.launcher.Main.main(Main.java:631)\nI HATE YOU\nI LOVE YOU\nValid-responses ok error M E Checked-in Valid-requests Template Set-sticky MT \nClear-static-directory\n Module-expansion Set-static-directory Clear-sticky New-entry Merged Removed \nUpdated Remove-entry Up\ndate-existing Copy-file Created Notified Mod-time\nvalid-requests\nValid-requests Root Valid-responses valid-requests Repository Directory Max-\ndotdot Static-directory\nSticky Checkin-prog Update-prog Entry Kopt Checkin-time Modified Is-modified \nUseUnchanged Unchanged\nNotify Questionable Case Argument Argumentx Global_option Gzip-stream wrapper-\nsendme-rcsOptions Set\nGssapi-authenticate expand-modules ci co update diff log rlog add remove update-\npatches gzip-file-co\nntents status rdiff tag rtag import admin export history release watch-on watch-\noff watch-add watch-\nremove watchers editors init annotate rannotate noop version\nok\nRoot /usr/local/pnp/cvsroot\nCMD\u003e cvs version\nversion\nM Concurrent Versions System (CVS) 1.11.2 (client/server)\nok\nRESULT\u003e Status OK: org.eclipse.team.cvs.core code\u003d0 ok null\nCMD\u003e cvs tag \"/testing/this_is_an_invalid_tag\" \"/testing/HelloWorld.java\"\nDirectory .\n/usr/local/pnp/cvsroot/testing\nEntry /HelloWorld.java/1.17///\nUnchanged HelloWorld.java\nArgument this_is_an_invalid_tag\nArgument HelloWorld.java\nDirectory .\n/usr/local/pnp/cvsroot/testing\ntag\nM\nRESULT\u003e java.lang.StringIndexOutOfBoundsException: String index out of range: 0\n\n!ENTRY org.eclipse.core.runtime 4 2 Sep 27, 2004 15:52:35.589\n!MESSAGE An internal error occurred during: \"Tagging from workspace\".\n!STACK 0\njava.lang.StringIndexOutOfBoundsException: String index out of range: 0\n        at java.lang.String.charAt(String.java:444)\n        at \norg.eclipse.team.internal.ccvs.core.client.listeners.TagListener.messageLine\n(TagListener.\njava:35)\n        at org.eclipse.team.internal.ccvs.core.client.Request.executeRequest\n(Request.java:215)\n        at org.eclipse.team.internal.ccvs.core.client.Command.doExecute\n(Command.java:421)\n        at org.eclipse.team.internal.ccvs.core.client.Command$1.run\n(Command.java:337)\n        at org.eclipse.team.internal.ccvs.core.resources.EclipseSynchronizer.run\n(EclipseSynchronizer\n.java:1408)\n        at org.eclipse.team.internal.ccvs.core.resources.EclipseResource$2.run\n(EclipseResource.java:\n268)\n        at org.eclipse.core.internal.resources.Workspace.run\n(Workspace.java:1673)\n        at org.eclipse.team.internal.ccvs.core.resources.EclipseResource.run\n(EclipseResource.java:26\n5)\n        at org.eclipse.team.internal.ccvs.core.client.Command.execute\n(Command.java:349)\n        at org.eclipse.team.internal.ccvs.core.client.Tag.execute(Tag.java:79)\n        at org.eclipse.team.internal.ccvs.ui.operations.TagOperation.tag\n(TagOperation.java:107)\n        at org.eclipse.team.internal.ccvs.ui.operations.TagOperation.execute\n(TagOperation.java:58)\n        at \norg.eclipse.team.internal.ccvs.ui.operations.RepositoryProviderOperation.execute\n(Reposito\nryProviderOperation.java:59)\n        at org.eclipse.team.internal.ccvs.ui.operations.TagOperation.execute\n(TagOperation.java:153)\n        at org.eclipse.team.internal.ccvs.ui.operations.CVSOperation.run\n(CVSOperation.java:84)\n        at org.eclipse.team.internal.ui.actions.JobRunnableContext.run\n(JobRunnableContext.java:159)\n        at \norg.eclipse.team.internal.ui.actions.JobRunnableContext$3.runInWorkspace\n(JobRunnableConte\nxt.java:179)\n        at org.eclipse.core.internal.resources.InternalWorkspaceJob.run\n(InternalWorkspaceJob.java:38\n)\n        at org.eclipse.core.internal.jobs.Worker.run(Worker.java:66)\n\n+++++++++++++++++++++++++++++++++++++++++++++++++++++++++++++++\nThe output from a successful tag command\n+++++++++++++++++++++++++++++++++++++++++++++++++++++++++++++++\n***\ncvs version\n    Concurrent Versions System (CVS) 1.11.2 (client/server)\nok (took 0:00.140)\n***\n\n***\ncvs tag \"/testing/M_006790_DEV\" \"/testing/HelloWorld.java\"\n    Authorisation   : ggoldsmith granted...\n    Message         : Its okay to add M_006790_DEV...\n    T HelloWorld.java\nok (took 0:00.563)\n***\n\nInstall location:\n    file:/c:/eclipse/\nConfiguration file:\n    file:/c:/eclipse/configuration/config.ini loaded\nConfiguration location:\n    file:/c:/eclipse/configuration/\nConfiguration file:\n    file:/c:/eclipse/configuration/config.ini loaded\nFramework located:\n    file:/c:/eclipse/plugins/org.eclipse.osgi_3.0.0/\nLoading framework classpath from:\n    file:/c:/eclipse/plugins/org.eclipse.osgi_3.0.0/eclipse.properties\nFramework classpath:\n    file:/c:/eclipse/plugins/org.eclipse.osgi_3.0.0/core.jar\n    file:/c:/eclipse/plugins/org.eclipse.osgi_3.0.0/console.jar\n    file:/c:/eclipse/plugins/org.eclipse.osgi_3.0.0/osgi.jar\n    file:/c:/eclipse/plugins/org.eclipse.osgi_3.0.0/resolver.jar\n    file:/c:/eclipse/plugins/org.eclipse.osgi_3.0.0/defaultAdaptor.jar\n    file:/c:/eclipse/plugins/org.eclipse.osgi_3.0.0/eclipseAdaptor.jar\nDebug options:\n    file:/C:/Documents/Java/Eclipse/.options not found\nTime to load bundles: 47\n!SESSION Sep 27, 2004 16:01:00.984 ---------------------------------------------\neclipse.buildId\u003dI200406192000\njava.version\u003d1.4.2\njava.vendor\u003dSun Microsystems Inc.\nBootLoader constants: OS\u003dwin32, ARCH\u003dx86, WS\u003dwin32, NL\u003den_ZA\n\n!ENTRY org.eclipse.osgi Sep 27, 2004 16:01:00.999\n!MESSAGE Bundle update@/c:/eclipse/plugins/org.apache.ant_1.5.4/ [9] was not \nresolved.\n!SUBENTRY 1 org.eclipse.osgi Sep 27, 2004 16:01:01.15\n!MESSAGE Bundle update@/c:/eclipse/plugins/org.apache.ant_1.6.1/ was picked \ninstead.\n\n!ENTRY org.eclipse.osgi Sep 27, 2004 16:01:01.15\n!MESSAGE Bundle update@/c:/eclipse/plugins/org.apache.lucene_1.3.0/ [11] was \nnot resolved.\n!SUBENTRY 1 org.eclipse.osgi Sep 27, 2004 16:01:01.15\n!MESSAGE Bundle update@/c:/eclipse/plugins/org.apache.lucene_1.3.0.RC2/ was \npicked instead.\n\n!ENTRY org.eclipse.osgi Sep 27, 2004 16:01:01.31\n!MESSAGE Bundle update@/c:/eclipse/plugins/org.eclipse.tomcat_4.1.29/ [75] was \nnot resolved.\n!SUBENTRY 1 org.eclipse.osgi Sep 27, 2004 16:01:01.31\n!MESSAGE Bundle update@/c:/eclipse/plugins/org.eclipse.tomcat_4.1.30/ was \npicked instead.\n\n!ENTRY org.eclipse.osgi Sep 27, 2004 16:01:01.46\n!MESSAGE Bundle update@/c:/eclipse/plugins/org.apache.ant_1.6.0/ [98] was not \nresolved.\n!SUBENTRY 1 org.eclipse.osgi Sep 27, 2004 16:01:01.62\n!MESSAGE Bundle update@/c:/eclipse/plugins/org.apache.ant_1.6.1/ was picked \ninstead.\nStarting application: 1750\n\n!ENTRY org.eclipse.osgi Sep 27, 2004 16:01:24.640\n!MESSAGE While loading \nclass \"org.eclipse.team.internal.ccvs.ui.console.ConsoleDocument$ConsoleLine\"\n, thread \"main\" timed out waiting (5000ms) for thread \"Worker-0\" to finish \nstarting bundle \"org.ecli\npse.team.cvs.ui\". To avoid deadlock, thread \"main\" is proceeding \nbut \"org.eclipse.team.internal.ccvs\n.ui.console.ConsoleDocument$ConsoleLine\" may not be fully initialized.\n!STACK 0\njava.lang.Exception: Generated exception.\n        at org.eclipse.core.runtime.adaptor.EclipseClassLoader.findLocalClass\n(EclipseClassLoader.jav\na:102)\n        at org.eclipse.osgi.framework.internal.core.BundleLoader.findLocalClass\n(BundleLoader.java:37\n1)\n        at org.eclipse.osgi.framework.internal.core.BundleLoader.findClass\n(BundleLoader.java:402)\n        at org.eclipse.osgi.framework.adaptor.core.AbstractClassLoader.loadClass\n(AbstractClassLoader\n.java:93)\n        at java.lang.ClassLoader.loadClass(ClassLoader.java:235)\n        at java.lang.ClassLoader.loadClassInternal(ClassLoader.java:302)\n        at org.eclipse.team.internal.ccvs.ui.console.ConsoleDocument.getLines\n(ConsoleDocument.java:7\n8)\n        at org.eclipse.team.internal.ccvs.ui.console.CVSOutputConsole.dump\n(CVSOutputConsole.java:140\n)\n        at org.eclipse.team.internal.ccvs.ui.console.CVSOutputConsole.access$1\n(CVSOutputConsole.java\n:137)\n        at org.eclipse.team.internal.ccvs.ui.console.CVSOutputConsole$1.run\n(CVSOutputConsole.java:10\n8)\n        at org.eclipse.swt.widgets.RunnableLock.run(RunnableLock.java:35)\n        at org.eclipse.swt.widgets.Synchronizer.runAsyncMessages\n(Synchronizer.java:106)\n        at org.eclipse.swt.widgets.Display.runAsyncMessages(Display.java:2709)\n        at org.eclipse.swt.widgets.Display.readAndDispatch(Display.java:2401)\n        at org.eclipse.ui.internal.Workbench.runEventLoop(Workbench.java:1375)\n        at org.eclipse.ui.internal.Workbench.runUI(Workbench.java:1346)\n        at org.eclipse.ui.internal.Workbench.createAndRunWorkbench\n(Workbench.java:252)\n        at org.eclipse.ui.PlatformUI.createAndRunWorkbench(PlatformUI.java:141)\n        at org.eclipse.ui.internal.ide.IDEApplication.run\n(IDEApplication.java:96)\n        at org.eclipse.core.internal.runtime.PlatformActivator$1.run\n(PlatformActivator.java:335)\n        at org.eclipse.core.runtime.adaptor.EclipseStarter.run\n(EclipseStarter.java:272)\n        at org.eclipse.core.runtime.adaptor.EclipseStarter.run\n(EclipseStarter.java:128)\n        at sun.reflect.NativeMethodAccessorImpl.invoke0(Native Method)\n        at sun.reflect.NativeMethodAccessorImpl.invoke\n(NativeMethodAccessorImpl.java:39)\n        at sun.reflect.DelegatingMethodAccessorImpl.invoke\n(DelegatingMethodAccessorImpl.java:25)\n        at java.lang.reflect.Method.invoke(Method.java:324)\n        at org.eclipse.core.launcher.Main.basicRun(Main.java:186)\n        at org.eclipse.core.launcher.Main.run(Main.java:647)\n        at org.eclipse.core.launcher.Main.main(Main.java:631)\nI HATE YOU\nI LOVE YOU\nValid-responses ok error M E Checked-in Valid-requests Template Set-sticky MT \nClear-static-directory\n Module-expansion Set-static-directory Clear-sticky New-entry Merged Removed \nUpdated Remove-entry Up\ndate-existing Copy-file Created Notified Mod-time\nvalid-requests\nValid-requests Root Valid-responses valid-requests Repository Directory Max-\ndotdot Static-directory\nSticky Checkin-prog Update-prog Entry Kopt Checkin-time Modified Is-modified \nUseUnchanged Unchanged\nNotify Questionable Case Argument Argumentx Global_option Gzip-stream wrapper-\nsendme-rcsOptions Set\nGssapi-authenticate expand-modules ci co update diff log rlog add remove update-\npatches gzip-file-co\nntents status rdiff tag rtag import admin export history release watch-on watch-\noff watch-add watch-\nremove watchers editors init annotate rannotate noop version\nok\nRoot /usr/local/pnp/cvsroot\nCMD\u003e cvs version\nversion\nM Concurrent Versions System (CVS) 1.11.2 (client/server)\nok\nRESULT\u003e Status OK: org.eclipse.team.cvs.core code\u003d0 ok null\nCMD\u003e cvs tag \"/testing/M_006790_DEV\" \"/testing/HelloWorld.java\"\nDirectory .\n/usr/local/pnp/cvsroot/testing\nEntry /HelloWorld.java/1.17///\nUnchanged HelloWorld.java\nArgument M_006790_DEV\nArgument HelloWorld.java\nDirectory .\n/usr/local/pnp/cvsroot/testing\ntag\nM Authorisation   : ggoldsmith granted...\nM Message         : Its okay to add M_006790_DEV...\nM T HelloWorld.java\nok\nRESULT\u003e Status OK: org.eclipse.team.cvs.core code\u003d0 ok null",
    "Ah, I see the problem. Our custom Tag listener is expecting all message lines \nto have contents but it seems that there is a case where the message is empty. \nThansk for the info.",
    "Fix released to HEAD"
  ],
  "commentCreationDates": [
    "2004-09-27T17:13:41+02:00",
    "2004-09-27T20:48:47+02:00",
    "2004-10-04T17:19:54+02:00"
  ],
  "traces": [
    {
      "exceptionType": "java.lang.Exception",
      "message": "Generated exception.",
      "elements": [
        {
          "method": "org.eclipse.core.runtime.adaptor.EclipseClassLoader.findLocalClass",
          "source": "EclipseClassLoader.jav a:102"
        },
        {
          "method": "org.eclipse.osgi.framework.internal.core.BundleLoader.findLocalClass",
          "source": "BundleLoader.java:37 1"
        },
        {
          "method": "org.eclipse.osgi.framework.internal.core.BundleLoader.findClass",
          "source": "BundleLoader.java:402"
        },
        {
          "method": "org.eclipse.osgi.framework.adaptor.core.AbstractClassLoader.loadClass",
          "source": "AbstractClassLoader .java:93"
        },
        {
          "method": "java.lang.ClassLoader.loadClass",
          "source": "ClassLoader.java:235"
        },
        {
          "method": "java.lang.ClassLoader.loadClassInternal",
          "source": "ClassLoader.java:302"
        },
        {
          "method": "org.eclipse.team.internal.ccvs.ui.console.ConsoleDocument.getLines",
          "source": "ConsoleDocument.java:7 8"
        },
        {
          "method": "org.eclipse.team.internal.ccvs.ui.console.CVSOutputConsole.dump",
          "source": "CVSOutputConsole.java:140 "
        },
        {
          "method": "org.eclipse.team.internal.ccvs.ui.console.CVSOutputConsole.access$1",
          "source": "CVSOutputConsole.java :137"
        },
        {
          "method": "org.eclipse.team.internal.ccvs.ui.console.CVSOutputConsole$1.run",
          "source": "CVSOutputConsole.java:10 8"
        },
        {
          "method": "org.eclipse.swt.widgets.RunnableLock.run",
          "source": "RunnableLock.java:35"
        },
        {
          "method": "org.eclipse.swt.widgets.Synchronizer.runAsyncMessages",
          "source": "Synchronizer.java:106"
        },
        {
          "method": "org.eclipse.swt.widgets.Display.runAsyncMessages",
          "source": "Display.java:2709"
        },
        {
          "method": "org.eclipse.swt.widgets.Display.readAndDispatch",
          "source": "Display.java:2401"
        },
        {
          "method": "org.eclipse.ui.internal.Workbench.runEventLoop",
          "source": "Workbench.java:1375"
        },
        {
          "method": "org.eclipse.ui.internal.Workbench.runUI",
          "source": "Workbench.java:1346"
        },
        {
          "method": "org.eclipse.ui.internal.Workbench.createAndRunWorkbench",
          "source": "Workbench.java:252"
        },
        {
          "method": "org.eclipse.ui.PlatformUI.createAndRunWorkbench",
          "source": "PlatformUI.java:141"
        },
        {
          "method": "org.eclipse.ui.internal.ide.IDEApplication.run",
          "source": "IDEApplication.java:96"
        },
        {
          "method": "org.eclipse.core.internal.runtime.PlatformActivator$1.run",
          "source": "PlatformActivator.java:335"
        },
        {
          "method": "org.eclipse.core.runtime.adaptor.EclipseStarter.run",
          "source": "EclipseStarter.java:272"
        },
        {
          "method": "org.eclipse.core.runtime.adaptor.EclipseStarter.run",
          "source": "EclipseStarter.java:128"
        },
        {
          "method": "sun.reflect.NativeMethodAccessorImpl.invoke0",
          "source": "Native Method"
        },
        {
          "method": "sun.reflect.NativeMethodAccessorImpl.invoke",
          "source": "NativeMethodAccessorImpl.java:39"
        },
        {
          "method": "sun.reflect.DelegatingMethodAccessorImpl.invoke",
          "source": "DelegatingMethodAccessorImpl.java:25"
        },
        {
          "method": "java.lang.reflect.Method.invoke",
          "source": "Method.java:324"
        },
        {
          "method": "org.eclipse.core.launcher.Main.basicRun",
          "source": "Main.java:186"
        },
        {
          "method": "org.eclipse.core.launcher.Main.run",
          "source": "Main.java:647"
        },
        {
          "method": "org.eclipse.core.launcher.Main.main",
          "source": "Main.java:631"
        }
      ],
      "number": 0,
      "commentIndex": 0,
      "bugId": "75091",
      "date": "2004-09-27T17:13:41+02:00",
      "product": "Platform",
      "component": "CVS",
      "severity": "normal"
    },
    {
      "exceptionType": "java.lang.StringIndexOutOfBoundsException",
      "message": "String index out of range: 0",
      "elements": [
        {
          "method": "java.lang.String.charAt",
          "source": "String.java:444"
        },
        {
          "method": "org.eclipse.team.internal.ccvs.core.client.listeners.TagListener.messageLine",
          "source": "TagListener. java:35"
        },
        {
          "method": "org.eclipse.team.internal.ccvs.core.client.Request.executeRequest",
          "source": "Request.java:215"
        },
        {
          "method": "org.eclipse.team.internal.ccvs.core.client.Command.doExecute",
          "source": "Command.java:421"
        },
        {
          "method": "org.eclipse.team.internal.ccvs.core.client.Command$1.run",
          "source": "Command.java:337"
        },
        {
          "method": "org.eclipse.team.internal.ccvs.core.resources.EclipseSynchronizer.run",
          "source": "EclipseSynchronizer .java:1408"
        },
        {
          "method": "org.eclipse.team.internal.ccvs.core.resources.EclipseResource$2.run",
          "source": "EclipseResource.java: 268"
        },
        {
          "method": "org.eclipse.core.internal.resources.Workspace.run",
          "source": "Workspace.java:1673"
        },
        {
          "method": "org.eclipse.team.internal.ccvs.core.resources.EclipseResource.run",
          "source": "EclipseResource.java:26 5"
        },
        {
          "method": "org.eclipse.team.internal.ccvs.core.client.Command.execute",
          "source": "Command.java:349"
        },
        {
          "method": "org.eclipse.team.internal.ccvs.core.client.Tag.execute",
          "source": "Tag.java:79"
        },
        {
          "method": "org.eclipse.team.internal.ccvs.ui.operations.TagOperation.tag",
          "source": "TagOperation.java:107"
        },
        {
          "method": "org.eclipse.team.internal.ccvs.ui.operations.TagOperation.execute",
          "source": "TagOperation.java:58"
        },
        {
          "method": "org.eclipse.team.internal.ccvs.ui.operations.RepositoryProviderOperation.execute",
          "source": "Reposito ryProviderOperation.java:59"
        },
        {
          "method": "org.eclipse.team.internal.ccvs.ui.operations.TagOperation.execute",
          "source": "TagOperation.java:153"
        },
        {
          "method": "org.eclipse.team.internal.ccvs.ui.operations.CVSOperation.run",
          "source": "CVSOperation.java:84"
        },
        {
          "method": "org.eclipse.team.internal.ui.actions.JobRunnableContext.run",
          "source": "JobRunnableContext.java:159"
        },
        {
          "method": "org.eclipse.team.internal.ui.actions.JobRunnableContext$3.runInWorkspace",
          "source": "JobRunnableConte xt.java:179"
        },
        {
          "method": "org.eclipse.core.internal.resources.InternalWorkspaceJob.run",
          "source": "InternalWorkspaceJob.java:38 "
        },
        {
          "method": "org.eclipse.core.internal.jobs.Worker.run",
          "source": "Worker.java:66"
        }
      ],
      "number": 1,
      "commentIndex": 0,
      "bugId": "75091",
      "date": "2004-09-27T17:13:41+02:00",
      "product": "Platform",
      "component": "CVS",
      "severity": "normal"
    },
    {
      "exceptionType": "java.lang.Exception",
      "message": "Generated exception.",
      "elements": [
        {
          "method": "org.eclipse.core.runtime.adaptor.EclipseClassLoader.findLocalClass",
          "source": "EclipseClassLoader.jav a:102"
        },
        {
          "method": "org.eclipse.osgi.framework.internal.core.BundleLoader.findLocalClass",
          "source": "BundleLoader.java:37 1"
        },
        {
          "method": "org.eclipse.osgi.framework.internal.core.BundleLoader.findClass",
          "source": "BundleLoader.java:402"
        },
        {
          "method": "org.eclipse.osgi.framework.adaptor.core.AbstractClassLoader.loadClass",
          "source": "AbstractClassLoader .java:93"
        },
        {
          "method": "java.lang.ClassLoader.loadClass",
          "source": "ClassLoader.java:235"
        },
        {
          "method": "java.lang.ClassLoader.loadClassInternal",
          "source": "ClassLoader.java:302"
        },
        {
          "method": "org.eclipse.team.internal.ccvs.ui.console.ConsoleDocument.getLines",
          "source": "ConsoleDocument.java:7 8"
        },
        {
          "method": "org.eclipse.team.internal.ccvs.ui.console.CVSOutputConsole.dump",
          "source": "CVSOutputConsole.java:140 "
        },
        {
          "method": "org.eclipse.team.internal.ccvs.ui.console.CVSOutputConsole.access$1",
          "source": "CVSOutputConsole.java :137"
        },
        {
          "method": "org.eclipse.team.internal.ccvs.ui.console.CVSOutputConsole$1.run",
          "source": "CVSOutputConsole.java:10 8"
        },
        {
          "method": "org.eclipse.swt.widgets.RunnableLock.run",
          "source": "RunnableLock.java:35"
        },
        {
          "method": "org.eclipse.swt.widgets.Synchronizer.runAsyncMessages",
          "source": "Synchronizer.java:106"
        },
        {
          "method": "org.eclipse.swt.widgets.Display.runAsyncMessages",
          "source": "Display.java:2709"
        },
        {
          "method": "org.eclipse.swt.widgets.Display.readAndDispatch",
          "source": "Display.java:2401"
        },
        {
          "method": "org.eclipse.ui.internal.Workbench.runEventLoop",
          "source": "Workbench.java:1375"
        },
        {
          "method": "org.eclipse.ui.internal.Workbench.runUI",
          "source": "Workbench.java:1346"
        },
        {
          "method": "org.eclipse.ui.internal.Workbench.createAndRunWorkbench",
          "source": "Workbench.java:252"
        },
        {
          "method": "org.eclipse.ui.PlatformUI.createAndRunWorkbench",
          "source": "PlatformUI.java:141"
        },
        {
          "method": "org.eclipse.ui.internal.ide.IDEApplication.run",
          "source": "IDEApplication.java:96"
        },
        {
          "method": "org.eclipse.core.internal.runtime.PlatformActivator$1.run",
          "source": "PlatformActivator.java:335"
        },
        {
          "method": "org.eclipse.core.runtime.adaptor.EclipseStarter.run",
          "source": "EclipseStarter.java:272"
        },
        {
          "method": "org.eclipse.core.runtime.adaptor.EclipseStarter.run",
          "source": "EclipseStarter.java:128"
        },
        {
          "method": "sun.reflect.NativeMethodAccessorImpl.invoke0",
          "source": "Native Method"
        },
        {
          "method": "sun.reflect.NativeMethodAccessorImpl.invoke",
          "source": "NativeMethodAccessorImpl.java:39"
        },
        {
          "method": "sun.reflect.DelegatingMethodAccessorImpl.invoke",
          "source": "DelegatingMethodAccessorImpl.java:25"
        },
        {
          "method": "java.lang.reflect.Method.invoke",
          "source": "Method.java:324"
        },
        {
          "method": "org.eclipse.core.launcher.Main.basicRun",
          "source": "Main.java:186"
        },
        {
          "method": "org.eclipse.core.launcher.Main.run",
          "source": "Main.java:647"
        },
        {
          "method": "org.eclipse.core.launcher.Main.main",
          "source": "Main.java:631"
        }
      ],
      "number": 2,
      "commentIndex": 0,
      "bugId": "75091",
      "date": "2004-09-27T17:13:41+02:00",
      "product": "Platform",
      "component": "CVS",
      "severity": "normal"
    }
  ],
  "groupId": "75091",
  "bugId": "75091",
  "date": "2004-09-27T17:13:41+02:00",
  "product": "Platform",
  "component": "CVS",
  "severity": "normal"
}