{
  "comments": [
    "This is using the 0109 integration build.\n\njava.lang.NullPointerException\n        at org.eclipse.jdt.internal.compiler.lookup.Scope.findField\n(Scope.java:179)\n        at org.eclipse.jdt.internal.compiler.lookup.BlockScope.getField\n(BlockScope.java:1113)\n        at \norg.eclipse.jdt.internal.eval.CodeSnippetSingleNameReference.reportError\n(CodeSnippetSingleNameReference.java:559)\n        at \norg.eclipse.jdt.internal.compiler.ast.SingleNameReference.resolveType\n(SingleNameReference.java:645)\n        at org.eclipse.jdt.internal.eval.CodeSnippetReturnStatement.resolve\n(CodeSnippetReturnStatement.java:91)\n        at org.eclipse.jdt.internal.compiler.ast.Block.resolveUsing\n(Block.java:91)\n        at org.eclipse.jdt.internal.compiler.ast.TryStatement.resolve\n(TryStatement.java:358)\n        at \norg.eclipse.jdt.internal.compiler.ast.AbstractMethodDeclaration.resolve\n(AbstractMethodDeclaration.java:269)\n        at org.eclipse.jdt.internal.compiler.ast.MethodDeclaration.resolve\n(MethodDeclaration.java:66)\n        at org.eclipse.jdt.internal.compiler.ast.TypeDeclaration.resolve\n(TypeDeclaration.java:726)\n        at org.eclipse.jdt.internal.compiler.ast.TypeDeclaration.resolve\n(TypeDeclaration.java:754)\n        at \norg.eclipse.jdt.internal.compiler.ast.CompilationUnitDeclaration.resolve\n(CompilationUnitDeclaration.java:188)\n        at org.eclipse.jdt.internal.compiler.Compiler.process\n(Compiler.java:453)\n        at org.eclipse.jdt.internal.compiler.Compiler.compile\n(Compiler.java:261)\n        at org.eclipse.jdt.internal.eval.Evaluator.getClasses\n(Evaluator.java:113)\n        at org.eclipse.jdt.internal.eval.EvaluationContext.evaluate\n(EvaluationContext.java:213)\n        at \norg.eclipse.jdt.internal.core.eval.EvaluationContextWrapper.evaluateCodeSnippet\n(EvaluationContextWrapper.java:169)\n        at org.eclipse.jdt.internal.debug.eval.LocalEvaluationEngine$2.run\n(LocalEvaluationEngine.java:472)\n        at java.lang.Thread.run(Thread.java:512)",
    "Can you provide a test case that resulted in this NPE?  \n\nFrom the trace it looks like you were attempting to evaluate a code snippet?\n\nIf this is true and it was in remote debug target, we currently do not support \nremote evaluation. Please see bug 1526 Remote Evaulation (AST evaluation) for \nmore details.  \n\nOr was the evaluation attempting to start the remote target?  If so the code \nevaluated would help in finding the problem.\n\nEither way, more details would be appreciated.",
    "Increased priority due to NPE, but more details are required.",
    "I have been trying to recreate this problem.  I am not sure how I did it.  All \nI know is that I was just trying to start to debug.\n\nWe may just need to close this bug report and I will open a new one if I can \nfind a reproducible scenario.",
    "Agreed. Marking as \"WORKSFORME\"."
  ],
  "commentCreationDates": [
    "2002-01-12T22:30:48+01:00",
    "2002-01-13T04:14:33+01:00",
    "2002-01-16T17:51:06+01:00",
    "2002-01-16T19:32:18+01:00",
    "2002-01-16T19:47:46+01:00"
  ],
  "traces": [
    {
      "exceptionType": "java.lang.NullPointerException",
      "elements": [
        {
          "method": "org.eclipse.jdt.internal.compiler.lookup.Scope.findField",
          "source": "Scope.java:179"
        },
        {
          "method": "org.eclipse.jdt.internal.compiler.lookup.BlockScope.getField",
          "source": "BlockScope.java:1113"
        },
        {
          "method": "org.eclipse.jdt.internal.eval.CodeSnippetSingleNameReference.reportError",
          "source": "CodeSnippetSingleNameReference.java:559"
        },
        {
          "method": "org.eclipse.jdt.internal.compiler.ast.SingleNameReference.resolveType",
          "source": "SingleNameReference.java:645"
        },
        {
          "method": "org.eclipse.jdt.internal.eval.CodeSnippetReturnStatement.resolve",
          "source": "CodeSnippetReturnStatement.java:91"
        },
        {
          "method": "org.eclipse.jdt.internal.compiler.ast.Block.resolveUsing",
          "source": "Block.java:91"
        },
        {
          "method": "org.eclipse.jdt.internal.compiler.ast.TryStatement.resolve",
          "source": "TryStatement.java:358"
        },
        {
          "method": "org.eclipse.jdt.internal.compiler.ast.AbstractMethodDeclaration.resolve",
          "source": "AbstractMethodDeclaration.java:269"
        },
        {
          "method": "org.eclipse.jdt.internal.compiler.ast.MethodDeclaration.resolve",
          "source": "MethodDeclaration.java:66"
        },
        {
          "method": "org.eclipse.jdt.internal.compiler.ast.TypeDeclaration.resolve",
          "source": "TypeDeclaration.java:726"
        },
        {
          "method": "org.eclipse.jdt.internal.compiler.ast.TypeDeclaration.resolve",
          "source": "TypeDeclaration.java:754"
        },
        {
          "method": "org.eclipse.jdt.internal.compiler.ast.CompilationUnitDeclaration.resolve",
          "source": "CompilationUnitDeclaration.java:188"
        },
        {
          "method": "org.eclipse.jdt.internal.compiler.Compiler.process",
          "source": "Compiler.java:453"
        },
        {
          "method": "org.eclipse.jdt.internal.compiler.Compiler.compile",
          "source": "Compiler.java:261"
        },
        {
          "method": "org.eclipse.jdt.internal.eval.Evaluator.getClasses",
          "source": "Evaluator.java:113"
        },
        {
          "method": "org.eclipse.jdt.internal.eval.EvaluationContext.evaluate",
          "source": "EvaluationContext.java:213"
        },
        {
          "method": "org.eclipse.jdt.internal.core.eval.EvaluationContextWrapper.evaluateCodeSnippet",
          "source": "EvaluationContextWrapper.java:169"
        },
        {
          "method": "org.eclipse.jdt.internal.debug.eval.LocalEvaluationEngine$2.run",
          "source": "LocalEvaluationEngine.java:472"
        },
        {
          "method": "java.lang.Thread.run",
          "source": "Thread.java:512"
        }
      ],
      "number": 0,
      "commentIndex": 0,
      "bugId": "7516",
      "date": "2002-01-12T22:30:48+01:00",
      "product": "JDT",
      "component": "Debug",
      "severity": "normal"
    }
  ],
  "groupId": "7516",
  "bugId": "7516",
  "date": "2002-01-12T22:30:48+01:00",
  "product": "JDT",
  "component": "Debug",
  "severity": "normal"
}