{
  "comments": [
    "I changed compiler preferences for handling of unused method parameters from\nwarn to ignore and while compiling Eclipse (3.0.1) crashed with the following\nException:\n\n!ENTRY org.eclipse.core.runtime 4 2 Sep 28, 2004 17:38:58.156\n!MESSAGE Problems occurred when invoking code from plug-in:\n\"org.eclipse.core.runtime\".\n!STACK 0\norg.eclipse.swt.SWTException: Widget is disposed\n        at org.eclipse.swt.SWT.error(SWT.java:2691)\n        at org.eclipse.swt.SWT.error(SWT.java:2616)\n        at org.eclipse.swt.SWT.error(SWT.java:2587)\n        at org.eclipse.swt.widgets.Widget.error(Widget.java:381)\n        at org.eclipse.swt.widgets.Widget.checkWidget(Widget.java:283)\n        at org.eclipse.swt.widgets.Control.setVisible(Control.java:2371)\n        at org.eclipse.jface.dialogs.DialogPage.setVisible(DialogPage.java:418)\n        at\norg.eclipse.jface.preference.PreferenceDialog.selectCurrentPageAgain(PreferenceDialog.java:793)\n        at\norg.eclipse.jface.preference.PreferenceDialog$8.handleError(PreferenceDialog.java:518)\n        at\norg.eclipse.jface.preference.PreferenceDialog$8.selectionChanged(PreferenceDialog.java:531)\n        at\norg.eclipse.jface.viewers.StructuredViewer$3.run(StructuredViewer.java:450)\n        at\norg.eclipse.core.internal.runtime.InternalPlatform.run(InternalPlatform.java:616)\n        at org.eclipse.core.runtime.Platform.run(Platform.java:747)\n        at\norg.eclipse.jface.viewers.StructuredViewer.firePostSelectionChanged(StructuredViewer.java:448)\n        at\norg.eclipse.jface.viewers.StructuredViewer.handlePostSelect(StructuredViewer.java:708)\n        at\norg.eclipse.jface.viewers.StructuredViewer$5.widgetSelected(StructuredViewer.java:726)\n        at\norg.eclipse.jface.util.OpenStrategy.firePostSelectionEvent(OpenStrategy.java:200)\n        at org.eclipse.jface.util.OpenStrategy.access$4(OpenStrategy.java:195)\n        at org.eclipse.jface.util.OpenStrategy$3.run(OpenStrategy.java:349)\n        at org.eclipse.swt.widgets.RunnableLock.run(RunnableLock.java:35)\n        at\norg.eclipse.swt.widgets.Synchronizer.runAsyncMessages(Synchronizer.java:106)\n        at org.eclipse.swt.widgets.Display.runAsyncMessages(Display.java:2749)\n        at org.eclipse.swt.widgets.Display.readAndDispatch(Display.java:2434)\n        at org.eclipse.jface.window.Window.runEventLoop(Window.java:668)\n        at org.eclipse.jface.window.Window.open(Window.java:648)\n        at\norg.eclipse.ui.dialogs.PropertyDialogAction.run(PropertyDialogAction.java:177)\n        at\norg.eclipse.ui.internal.ide.actions.ProjectPropertyDialogAction.run(ProjectPropertyDialogAction.java:69)\n        at org.eclipse.jface.action.Action.runWithEvent(Action.java:881)\n        at\norg.eclipse.jface.action.ActionContributionItem.handleWidgetSelection(ActionContributionItem.java:915)\n        at\norg.eclipse.jface.action.ActionContributionItem.access$2(ActionContributionItem.java:866)\n        at\norg.eclipse.jface.action.ActionContributionItem$7.handleEvent(ActionContributionItem.java:785)\n        at org.eclipse.swt.widgets.EventTable.sendEvent(EventTable.java:82)\n        at org.eclipse.swt.widgets.Widget.sendEvent(Widget.java:796)\n        at org.eclipse.swt.widgets.Display.runDeferredEvents(Display.java:2772)\n        at org.eclipse.swt.widgets.Display.readAndDispatch(Display.java:2431)\n        at org.eclipse.ui.internal.Workbench.runEventLoop(Workbench.java:1377)\n        at org.eclipse.ui.internal.Workbench.runUI(Workbench.java:1348)\n        at\norg.eclipse.ui.internal.Workbench.createAndRunWorkbench(Workbench.java:254)\n        at org.eclipse.ui.PlatformUI.createAndRunWorkbench(PlatformUI.java:141)\n        at org.eclipse.ui.internal.ide.IDEApplication.run(IDEApplication.java:96)\n        at\norg.eclipse.core.internal.runtime.PlatformActivator$1.run(PlatformActivator.java:335)\n        at\norg.eclipse.core.runtime.adaptor.EclipseStarter.run(EclipseStarter.java:273)\n        at\norg.eclipse.core.runtime.adaptor.EclipseStarter.run(EclipseStarter.java:129)\n        at sun.reflect.NativeMethodAccessorImpl.invoke0(Native Method)\n        at\nsun.reflect.NativeMethodAccessorImpl.invoke(NativeMethodAccessorImpl.java:39)\n        at\nsun.reflect.DelegatingMethodAccessorImpl.invoke(DelegatingMethodAccessorImpl.java:25)\n        at java.lang.reflect.Method.invoke(Method.java:324)\n        at org.eclipse.core.launcher.Main.basicRun(Main.java:183)\n        at org.eclipse.core.launcher.Main.run(Main.java:644)\n        at org.eclipse.core.launcher.Main.main(Main.java:628)",
    "The exception above was generated when you were interacting with the UI, not\nduring rebuild. Didn\u0027t you get a VM dump (a hs_err_pid\u003cnumber\u003e.log on a Sun VM)\nin the current directory?\n\nHow did the crash happen? Any messages presented?",
    "No evidence of a crash here. Please provide a Java core dump file if available.\nI will forward this to the UI team to look at this widget disposed error. Can\nyou reproduce this?",
    "This just looks like a simple problem with error handling in the preference \ndailog - I don\u0027t think there is anything for Core to do here.",
    "Were you making this change using the project preferences or the main \npreferences? I am having trouble replicating this right now as I suspect it is \nthe side effect of a bug that is currently fixed.",
    "The bug occured while changing the main preferences\nI got no hs_err_pid... file during this crash",
    "Can\u0027t replicate in 3.1 M4. Please reopen if you have replicatable steps."
  ],
  "commentCreationDates": [
    "2004-09-28T18:12:34+02:00",
    "2004-09-28T18:57:09+02:00",
    "2004-09-28T23:56:45+02:00",
    "2004-09-29T15:55:19+02:00",
    "2004-09-30T18:58:40+02:00",
    "2004-09-30T23:10:35+02:00",
    "2005-01-05T20:16:16+01:00"
  ],
  "traces": [
    {
      "exceptionType": "org.eclipse.swt.SWTException",
      "message": "Widget is disposed",
      "elements": [
        {
          "method": "org.eclipse.swt.SWT.error",
          "source": "SWT.java:2691"
        },
        {
          "method": "org.eclipse.swt.SWT.error",
          "source": "SWT.java:2616"
        },
        {
          "method": "org.eclipse.swt.SWT.error",
          "source": "SWT.java:2587"
        },
        {
          "method": "org.eclipse.swt.widgets.Widget.error",
          "source": "Widget.java:381"
        },
        {
          "method": "org.eclipse.swt.widgets.Widget.checkWidget",
          "source": "Widget.java:283"
        },
        {
          "method": "org.eclipse.swt.widgets.Control.setVisible",
          "source": "Control.java:2371"
        },
        {
          "method": "org.eclipse.jface.dialogs.DialogPage.setVisible",
          "source": "DialogPage.java:418"
        },
        {
          "method": "org.eclipse.jface.preference.PreferenceDialog.selectCurrentPageAgain",
          "source": "PreferenceDialog.java:793"
        },
        {
          "method": "org.eclipse.jface.preference.PreferenceDialog$8.handleError",
          "source": "PreferenceDialog.java:518"
        },
        {
          "method": "org.eclipse.jface.preference.PreferenceDialog$8.selectionChanged",
          "source": "PreferenceDialog.java:531"
        },
        {
          "method": "org.eclipse.jface.viewers.StructuredViewer$3.run",
          "source": "StructuredViewer.java:450"
        },
        {
          "method": "org.eclipse.core.internal.runtime.InternalPlatform.run",
          "source": "InternalPlatform.java:616"
        },
        {
          "method": "org.eclipse.core.runtime.Platform.run",
          "source": "Platform.java:747"
        },
        {
          "method": "org.eclipse.jface.viewers.StructuredViewer.firePostSelectionChanged",
          "source": "StructuredViewer.java:448"
        },
        {
          "method": "org.eclipse.jface.viewers.StructuredViewer.handlePostSelect",
          "source": "StructuredViewer.java:708"
        },
        {
          "method": "org.eclipse.jface.viewers.StructuredViewer$5.widgetSelected",
          "source": "StructuredViewer.java:726"
        },
        {
          "method": "org.eclipse.jface.util.OpenStrategy.firePostSelectionEvent",
          "source": "OpenStrategy.java:200"
        },
        {
          "method": "org.eclipse.jface.util.OpenStrategy.access$4",
          "source": "OpenStrategy.java:195"
        },
        {
          "method": "org.eclipse.jface.util.OpenStrategy$3.run",
          "source": "OpenStrategy.java:349"
        },
        {
          "method": "org.eclipse.swt.widgets.RunnableLock.run",
          "source": "RunnableLock.java:35"
        },
        {
          "method": "org.eclipse.swt.widgets.Synchronizer.runAsyncMessages",
          "source": "Synchronizer.java:106"
        },
        {
          "method": "org.eclipse.swt.widgets.Display.runAsyncMessages",
          "source": "Display.java:2749"
        },
        {
          "method": "org.eclipse.swt.widgets.Display.readAndDispatch",
          "source": "Display.java:2434"
        },
        {
          "method": "org.eclipse.jface.window.Window.runEventLoop",
          "source": "Window.java:668"
        },
        {
          "method": "org.eclipse.jface.window.Window.open",
          "source": "Window.java:648"
        },
        {
          "method": "org.eclipse.ui.dialogs.PropertyDialogAction.run",
          "source": "PropertyDialogAction.java:177"
        },
        {
          "method": "org.eclipse.ui.internal.ide.actions.ProjectPropertyDialogAction.run",
          "source": "ProjectPropertyDialogAction.java:69"
        },
        {
          "method": "org.eclipse.jface.action.Action.runWithEvent",
          "source": "Action.java:881"
        },
        {
          "method": "org.eclipse.jface.action.ActionContributionItem.handleWidgetSelection",
          "source": "ActionContributionItem.java:915"
        },
        {
          "method": "org.eclipse.jface.action.ActionContributionItem.access$2",
          "source": "ActionContributionItem.java:866"
        },
        {
          "method": "org.eclipse.jface.action.ActionContributionItem$7.handleEvent",
          "source": "ActionContributionItem.java:785"
        },
        {
          "method": "org.eclipse.swt.widgets.EventTable.sendEvent",
          "source": "EventTable.java:82"
        },
        {
          "method": "org.eclipse.swt.widgets.Widget.sendEvent",
          "source": "Widget.java:796"
        },
        {
          "method": "org.eclipse.swt.widgets.Display.runDeferredEvents",
          "source": "Display.java:2772"
        },
        {
          "method": "org.eclipse.swt.widgets.Display.readAndDispatch",
          "source": "Display.java:2431"
        },
        {
          "method": "org.eclipse.ui.internal.Workbench.runEventLoop",
          "source": "Workbench.java:1377"
        },
        {
          "method": "org.eclipse.ui.internal.Workbench.runUI",
          "source": "Workbench.java:1348"
        },
        {
          "method": "org.eclipse.ui.internal.Workbench.createAndRunWorkbench",
          "source": "Workbench.java:254"
        },
        {
          "method": "org.eclipse.ui.PlatformUI.createAndRunWorkbench",
          "source": "PlatformUI.java:141"
        },
        {
          "method": "org.eclipse.ui.internal.ide.IDEApplication.run",
          "source": "IDEApplication.java:96"
        },
        {
          "method": "org.eclipse.core.internal.runtime.PlatformActivator$1.run",
          "source": "PlatformActivator.java:335"
        },
        {
          "method": "org.eclipse.core.runtime.adaptor.EclipseStarter.run",
          "source": "EclipseStarter.java:273"
        },
        {
          "method": "org.eclipse.core.runtime.adaptor.EclipseStarter.run",
          "source": "EclipseStarter.java:129"
        },
        {
          "method": "sun.reflect.NativeMethodAccessorImpl.invoke0",
          "source": "Native Method"
        },
        {
          "method": "sun.reflect.NativeMethodAccessorImpl.invoke",
          "source": "NativeMethodAccessorImpl.java:39"
        },
        {
          "method": "sun.reflect.DelegatingMethodAccessorImpl.invoke",
          "source": "DelegatingMethodAccessorImpl.java:25"
        },
        {
          "method": "java.lang.reflect.Method.invoke",
          "source": "Method.java:324"
        },
        {
          "method": "org.eclipse.core.launcher.Main.basicRun",
          "source": "Main.java:183"
        },
        {
          "method": "org.eclipse.core.launcher.Main.run",
          "source": "Main.java:644"
        },
        {
          "method": "org.eclipse.core.launcher.Main.main",
          "source": "Main.java:628"
        }
      ],
      "number": 0,
      "commentIndex": 0,
      "bugId": "75186",
      "date": "2004-09-28T18:12:34+02:00",
      "product": "Platform",
      "component": "UI",
      "severity": "normal"
    }
  ],
  "groupId": "75186",
  "bugId": "75186",
  "date": "2004-09-28T18:12:34+02:00",
  "product": "Platform",
  "component": "UI",
  "severity": "normal"
}