{
  "comments": [
    "I get an IllegalArgumentException setting the Run/Debug console size from\n200,000 to 400,000 chars. \n\nVersion 3.1.m2.\n\n!ENTRY org.eclipse.core.runtime 4 2 Sep 28, 2004 16:32:40.912\n!MESSAGE Problems occurred when invoking code from plug-in:\n\"org.eclipse.core.runtime\".\n!STACK 0\njava.lang.IllegalArgumentException: High water mark must be greater than low\nwater mark\n        at org.eclipse.ui.console.IOConsole.setWaterMarks(IOConsole.java:288)\n        at\norg.eclipse.debug.internal.ui.views.console.ProcessConsole.propertyChange(ProcessConsole.java:177)\n        at org.eclipse.ui.plugin.AbstractUIPlugin$2.run(AbstractUIPlugin.java:278)\n        at\norg.eclipse.core.internal.runtime.InternalPlatform.run(InternalPlatform.java:616)\n        at org.eclipse.core.runtime.Platform.run(Platform.java:747)\n        at\norg.eclipse.ui.plugin.AbstractUIPlugin$CompatibilityPreferenceStore.firePropertyChangeEvent(AbstractUIPlugin.\njava:275)\n        at\norg.eclipse.ui.plugin.AbstractUIPlugin$1.propertyChange(AbstractUIPlugin.java:218)\n        at\norg.eclipse.core.internal.preferences.PreferenceForwarder.preferenceChange(PreferenceForwarder.java:114)\n        at\norg.eclipse.core.internal.preferences.EclipsePreferences$4.run(EclipsePreferences.java:743)\n        at\norg.eclipse.core.internal.runtime.InternalPlatform.run(InternalPlatform.java:616)\n        at org.eclipse.core.runtime.Platform.run(Platform.java:747)\n        at\norg.eclipse.core.internal.preferences.EclipsePreferences.preferenceChanged(EclipsePreferences.java:746)\n        at\norg.eclipse.core.internal.preferences.EclipsePreferences.putInt(EclipsePreferences.java:835)\n        at\norg.eclipse.core.internal.preferences.PreferenceForwarder.setValue(PreferenceForwarder.java:456)\n        at\norg.eclipse.ui.plugin.AbstractUIPlugin$CompatibilityPreferenceStore.setValue(AbstractUIPlugin.java:470)\n        at\norg.eclipse.jface.preference.IntegerFieldEditor.doStore(IntegerFieldEditor.java:132)\n        at org.eclipse.jface.preference.FieldEditor.store(FieldEditor.java:636)\n        at\norg.eclipse.jface.preference.FieldEditorPreferencePage.performOk(FieldEditorPreferencePage.java:334)\n        at\norg.eclipse.debug.internal.ui.preferences.ConsolePreferencePage.performOk(ConsolePreferencePage.java:157)\n        at\norg.eclipse.jface.preference.PreferencePage.performApply(PreferencePage.java:422)\n        at\norg.eclipse.jface.preference.PreferencePage$2.widgetSelected(PreferencePage.java:277)\n        at org.eclipse.swt.widgets.TypedListener.handleEvent(TypedListener.java:89)\n        at org.eclipse.swt.widgets.EventTable.sendEvent(EventTable.java:82)\n        at org.eclipse.swt.widgets.Widget.sendEvent(Widget.java:796)\n        at org.eclipse.swt.widgets.Display.runDeferredEvents(Display.java:2783)\n        at org.eclipse.swt.widgets.Display.readAndDispatch(Display.java:2442)\n        at org.eclipse.jface.window.Window.runEventLoop(Window.java:706)\n        at org.eclipse.jface.window.Window.open(Window.java:684)\n        at\norg.eclipse.ui.internal.OpenPreferencesAction.run(OpenPreferencesAction.java:75)\n        at org.eclipse.jface.action.Action.runWithEvent(Action.java:988)\n        at\norg.eclipse.jface.action.ActionContributionItem.handleWidgetSelection(ActionContributionItem.java:555)\n        at\norg.eclipse.jface.action.ActionContributionItem.access$2(ActionContributionItem.java:505)\n        at\norg.eclipse.jface.action.ActionContributionItem$6.handleEvent(ActionContributionItem.java:419)\n        at org.eclipse.swt.widgets.EventTable.sendEvent(EventTable.java:82)\n        at org.eclipse.swt.widgets.Widget.sendEvent(Widget.java:796)\n        at org.eclipse.swt.widgets.Display.runDeferredEvents(Display.java:2783)\n        at org.eclipse.swt.widgets.Display.readAndDispatch(Display.java:2442)\n        at org.eclipse.ui.internal.Workbench.runEventLoop(Workbench.java:1443)\n        at org.eclipse.ui.internal.Workbench.runUI(Workbench.java:1414)\n        at\norg.eclipse.ui.internal.Workbench.createAndRunWorkbench(Workbench.java:271)\n        at org.eclipse.ui.PlatformUI.createAndRunWorkbench(PlatformUI.java:144)\n        at org.eclipse.ui.internal.ide.IDEApplication.run(IDEApplication.java:102)\n        at\norg.eclipse.core.internal.runtime.PlatformActivator$1.run(PlatformActivator.java:335)\n        at\norg.eclipse.core.runtime.adaptor.EclipseStarter.run(EclipseStarter.java:273)\n        at\norg.eclipse.core.runtime.adaptor.EclipseStarter.run(EclipseStarter.java:129)\n        at sun.reflect.NativeMethodAccessorImpl.invoke0(Native Method)\n        at\nsun.reflect.NativeMethodAccessorImpl.invoke(NativeMethodAccessorImpl.java:39)\n        at\nsun.reflect.DelegatingMethodAccessorImpl.invoke(DelegatingMethodAccessorImpl.java:25)\n        at java.lang.reflect.Method.invoke(Method.java:324)\n        at org.eclipse.core.launcher.Main.basicRun(Main.java:185)\n        at org.eclipse.core.launcher.Main.run(Main.java:704)\n        at org.eclipse.core.launcher.Main.main(Main.java:688)",
    "Then if I try to turn off setting a limit by un-checking the box, I get:\n\n!ENTRY org.eclipse.core.runtime 4 2 Sep 28, 2004 16:34:49.310\n!MESSAGE Problems occurred when invoking code from plug-in:\n\"org.eclipse.core.runtime\".\n!STACK 0\njava.lang.IllegalArgumentException: High water mark must be greater than low\nwater mark\n        at org.eclipse.ui.console.IOConsole.setWaterMarks(IOConsole.java:288)\n        at\norg.eclipse.debug.internal.ui.views.console.ProcessConsole.propertyChange(ProcessConsole.java:179)\n        at org.eclipse.ui.plugin.AbstractUIPlugin$2.run(AbstractUIPlugin.java:278)\n        at\norg.eclipse.core.internal.runtime.InternalPlatform.run(InternalPlatform.java:616)\n        at org.eclipse.core.runtime.Platform.run(Platform.java:747)\n        at\norg.eclipse.ui.plugin.AbstractUIPlugin$CompatibilityPreferenceStore.firePropertyChangeEvent(AbstractUIPlugin.\njava:275)\n        at\norg.eclipse.ui.plugin.AbstractUIPlugin$1.propertyChange(AbstractUIPlugin.java:218)\n        at\norg.eclipse.core.internal.preferences.PreferenceForwarder.preferenceChange(PreferenceForwarder.java:114)\n        at\norg.eclipse.core.internal.preferences.EclipsePreferences$4.run(EclipsePreferences.java:743)\n        at\norg.eclipse.core.internal.runtime.InternalPlatform.run(InternalPlatform.java:616)\n        at org.eclipse.core.runtime.Platform.run(Platform.java:747)\n        at\norg.eclipse.core.internal.preferences.EclipsePreferences.preferenceChanged(EclipsePreferences.java:746)\n        at\norg.eclipse.core.internal.preferences.EclipsePreferences.putBoolean(EclipsePreferences.java:769)\n        at\norg.eclipse.core.internal.preferences.PreferenceForwarder.setValue(PreferenceForwarder.java:225)\n        at\norg.eclipse.ui.plugin.AbstractUIPlugin$CompatibilityPreferenceStore.setValue(AbstractUIPlugin.java:491)\n        at\norg.eclipse.jface.preference.BooleanFieldEditor.doStore(BooleanFieldEditor.java:154)\n        at org.eclipse.jface.preference.FieldEditor.store(FieldEditor.java:636)\n        at\norg.eclipse.jface.preference.FieldEditorPreferencePage.performOk(FieldEditorPreferencePage.java:334)\n        at\norg.eclipse.debug.internal.ui.preferences.ConsolePreferencePage.performOk(ConsolePreferencePage.java:157)\n        at\norg.eclipse.jface.preference.PreferencePage.performApply(PreferencePage.java:422)\n        at\norg.eclipse.jface.preference.PreferencePage$2.widgetSelected(PreferencePage.java:277)\n        at org.eclipse.swt.widgets.TypedListener.handleEvent(TypedListener.java:89)\n        at org.eclipse.swt.widgets.EventTable.sendEvent(EventTable.java:82)\n        at org.eclipse.swt.widgets.Widget.sendEvent(Widget.java:796)\n        at org.eclipse.swt.widgets.Display.runDeferredEvents(Display.java:2783)\n        at org.eclipse.swt.widgets.Display.readAndDispatch(Display.java:2442)\n        at org.eclipse.jface.window.Window.runEventLoop(Window.java:706)\n        at org.eclipse.jface.window.Window.open(Window.java:684)\n        at\norg.eclipse.ui.internal.OpenPreferencesAction.run(OpenPreferencesAction.java:75)\n        at org.eclipse.jface.action.Action.runWithEvent(Action.java:988)\n        at\norg.eclipse.jface.action.ActionContributionItem.handleWidgetSelection(ActionContributionItem.java:555)\n        at\norg.eclipse.jface.action.ActionContributionItem.access$2(ActionContributionItem.java:505)\n        at\norg.eclipse.jface.action.ActionContributionItem$6.handleEvent(ActionContributionItem.java:419)\n        at org.eclipse.swt.widgets.EventTable.sendEvent(EventTable.java:82)\n        at org.eclipse.swt.widgets.Widget.sendEvent(Widget.java:796)\n        at org.eclipse.swt.widgets.Display.runDeferredEvents(Display.java:2783)\n        at org.eclipse.swt.widgets.Display.readAndDispatch(Display.java:2442)\n        at org.eclipse.ui.internal.Workbench.runEventLoop(Workbench.java:1443)\n        at org.eclipse.ui.internal.Workbench.runUI(Workbench.java:1414)\n        at\norg.eclipse.ui.internal.Workbench.createAndRunWorkbench(Workbench.java:271)\n        at org.eclipse.ui.PlatformUI.createAndRunWorkbench(PlatformUI.java:144)\n        at org.eclipse.ui.internal.ide.IDEApplication.run(IDEApplication.java:102)\n        at\norg.eclipse.core.internal.runtime.PlatformActivator$1.run(PlatformActivator.java:335)\n        at\norg.eclipse.core.runtime.adaptor.EclipseStarter.run(EclipseStarter.java:273)\n        at\norg.eclipse.core.runtime.adaptor.EclipseStarter.run(EclipseStarter.java:129)\n        at sun.reflect.NativeMethodAccessorImpl.invoke0(Native Method)\n        at\nsun.reflect.NativeMethodAccessorImpl.invoke(NativeMethodAccessorImpl.java:39)\n        at\nsun.reflect.DelegatingMethodAccessorImpl.invoke(DelegatingMethodAccessorImpl.java:25)\n        at java.lang.reflect.Method.invoke(Method.java:324)\n        at org.eclipse.core.launcher.Main.basicRun(Main.java:185)\n        at org.eclipse.core.launcher.Main.run(Main.java:704)\n        at org.eclipse.core.launcher.Main.main(Main.java:688)",
    "\n\n*** This bug has been marked as a duplicate of 75177 ***",
    "The second stack trace is a dup of 75177, but the first is not. setWaterMarks(..) is getting called before \nthe high water mark preference is set.",
    "Fixed in ProcessConsole. We receive the low water mark change event before the high water mark. Only \nupdate the consoles if low \u003c high.",
    "please verify",
    "Verified."
  ],
  "commentCreationDates": [
    "2004-09-29T01:42:36+02:00",
    "2004-09-29T01:43:34+02:00",
    "2004-09-29T15:38:24+02:00",
    "2004-09-29T15:41:52+02:00",
    "2004-09-29T16:21:29+02:00",
    "2004-09-29T16:21:57+02:00",
    "2004-10-04T17:09:14+02:00"
  ],
  "traces": [
    {
      "exceptionType": "java.lang.IllegalArgumentException",
      "message": "High water mark must be greater than low water mark",
      "elements": [
        {
          "method": "org.eclipse.ui.console.IOConsole.setWaterMarks",
          "source": "IOConsole.java:288"
        },
        {
          "method": "org.eclipse.debug.internal.ui.views.console.ProcessConsole.propertyChange",
          "source": "ProcessConsole.java:177"
        },
        {
          "method": "org.eclipse.ui.plugin.AbstractUIPlugin$2.run",
          "source": "AbstractUIPlugin.java:278"
        },
        {
          "method": "org.eclipse.core.internal.runtime.InternalPlatform.run",
          "source": "InternalPlatform.java:616"
        },
        {
          "method": "org.eclipse.core.runtime.Platform.run",
          "source": "Platform.java:747"
        },
        {
          "method": "org.eclipse.ui.plugin.AbstractUIPlugin$CompatibilityPreferenceStore.firePropertyChangeEvent",
          "source": "AbstractUIPlugin. java:275"
        },
        {
          "method": "org.eclipse.ui.plugin.AbstractUIPlugin$1.propertyChange",
          "source": "AbstractUIPlugin.java:218"
        },
        {
          "method": "org.eclipse.core.internal.preferences.PreferenceForwarder.preferenceChange",
          "source": "PreferenceForwarder.java:114"
        },
        {
          "method": "org.eclipse.core.internal.preferences.EclipsePreferences$4.run",
          "source": "EclipsePreferences.java:743"
        },
        {
          "method": "org.eclipse.core.internal.runtime.InternalPlatform.run",
          "source": "InternalPlatform.java:616"
        },
        {
          "method": "org.eclipse.core.runtime.Platform.run",
          "source": "Platform.java:747"
        },
        {
          "method": "org.eclipse.core.internal.preferences.EclipsePreferences.preferenceChanged",
          "source": "EclipsePreferences.java:746"
        },
        {
          "method": "org.eclipse.core.internal.preferences.EclipsePreferences.putInt",
          "source": "EclipsePreferences.java:835"
        },
        {
          "method": "org.eclipse.core.internal.preferences.PreferenceForwarder.setValue",
          "source": "PreferenceForwarder.java:456"
        },
        {
          "method": "org.eclipse.ui.plugin.AbstractUIPlugin$CompatibilityPreferenceStore.setValue",
          "source": "AbstractUIPlugin.java:470"
        },
        {
          "method": "org.eclipse.jface.preference.IntegerFieldEditor.doStore",
          "source": "IntegerFieldEditor.java:132"
        },
        {
          "method": "org.eclipse.jface.preference.FieldEditor.store",
          "source": "FieldEditor.java:636"
        },
        {
          "method": "org.eclipse.jface.preference.FieldEditorPreferencePage.performOk",
          "source": "FieldEditorPreferencePage.java:334"
        },
        {
          "method": "org.eclipse.debug.internal.ui.preferences.ConsolePreferencePage.performOk",
          "source": "ConsolePreferencePage.java:157"
        },
        {
          "method": "org.eclipse.jface.preference.PreferencePage.performApply",
          "source": "PreferencePage.java:422"
        },
        {
          "method": "org.eclipse.jface.preference.PreferencePage$2.widgetSelected",
          "source": "PreferencePage.java:277"
        },
        {
          "method": "org.eclipse.swt.widgets.TypedListener.handleEvent",
          "source": "TypedListener.java:89"
        },
        {
          "method": "org.eclipse.swt.widgets.EventTable.sendEvent",
          "source": "EventTable.java:82"
        },
        {
          "method": "org.eclipse.swt.widgets.Widget.sendEvent",
          "source": "Widget.java:796"
        },
        {
          "method": "org.eclipse.swt.widgets.Display.runDeferredEvents",
          "source": "Display.java:2783"
        },
        {
          "method": "org.eclipse.swt.widgets.Display.readAndDispatch",
          "source": "Display.java:2442"
        },
        {
          "method": "org.eclipse.jface.window.Window.runEventLoop",
          "source": "Window.java:706"
        },
        {
          "method": "org.eclipse.jface.window.Window.open",
          "source": "Window.java:684"
        },
        {
          "method": "org.eclipse.ui.internal.OpenPreferencesAction.run",
          "source": "OpenPreferencesAction.java:75"
        },
        {
          "method": "org.eclipse.jface.action.Action.runWithEvent",
          "source": "Action.java:988"
        },
        {
          "method": "org.eclipse.jface.action.ActionContributionItem.handleWidgetSelection",
          "source": "ActionContributionItem.java:555"
        },
        {
          "method": "org.eclipse.jface.action.ActionContributionItem.access$2",
          "source": "ActionContributionItem.java:505"
        },
        {
          "method": "org.eclipse.jface.action.ActionContributionItem$6.handleEvent",
          "source": "ActionContributionItem.java:419"
        },
        {
          "method": "org.eclipse.swt.widgets.EventTable.sendEvent",
          "source": "EventTable.java:82"
        },
        {
          "method": "org.eclipse.swt.widgets.Widget.sendEvent",
          "source": "Widget.java:796"
        },
        {
          "method": "org.eclipse.swt.widgets.Display.runDeferredEvents",
          "source": "Display.java:2783"
        },
        {
          "method": "org.eclipse.swt.widgets.Display.readAndDispatch",
          "source": "Display.java:2442"
        },
        {
          "method": "org.eclipse.ui.internal.Workbench.runEventLoop",
          "source": "Workbench.java:1443"
        },
        {
          "method": "org.eclipse.ui.internal.Workbench.runUI",
          "source": "Workbench.java:1414"
        },
        {
          "method": "org.eclipse.ui.internal.Workbench.createAndRunWorkbench",
          "source": "Workbench.java:271"
        },
        {
          "method": "org.eclipse.ui.PlatformUI.createAndRunWorkbench",
          "source": "PlatformUI.java:144"
        },
        {
          "method": "org.eclipse.ui.internal.ide.IDEApplication.run",
          "source": "IDEApplication.java:102"
        },
        {
          "method": "org.eclipse.core.internal.runtime.PlatformActivator$1.run",
          "source": "PlatformActivator.java:335"
        },
        {
          "method": "org.eclipse.core.runtime.adaptor.EclipseStarter.run",
          "source": "EclipseStarter.java:273"
        },
        {
          "method": "org.eclipse.core.runtime.adaptor.EclipseStarter.run",
          "source": "EclipseStarter.java:129"
        },
        {
          "method": "sun.reflect.NativeMethodAccessorImpl.invoke0",
          "source": "Native Method"
        },
        {
          "method": "sun.reflect.NativeMethodAccessorImpl.invoke",
          "source": "NativeMethodAccessorImpl.java:39"
        },
        {
          "method": "sun.reflect.DelegatingMethodAccessorImpl.invoke",
          "source": "DelegatingMethodAccessorImpl.java:25"
        },
        {
          "method": "java.lang.reflect.Method.invoke",
          "source": "Method.java:324"
        },
        {
          "method": "org.eclipse.core.launcher.Main.basicRun",
          "source": "Main.java:185"
        },
        {
          "method": "org.eclipse.core.launcher.Main.run",
          "source": "Main.java:704"
        },
        {
          "method": "org.eclipse.core.launcher.Main.main",
          "source": "Main.java:688"
        }
      ],
      "number": 0,
      "commentIndex": 0,
      "bugId": "75226",
      "date": "2004-09-29T01:42:36+02:00",
      "product": "JDT",
      "component": "Debug",
      "severity": "normal"
    },
    {
      "exceptionType": "java.lang.IllegalArgumentException",
      "message": "High water mark must be greater than low water mark",
      "elements": [
        {
          "method": "org.eclipse.ui.console.IOConsole.setWaterMarks",
          "source": "IOConsole.java:288"
        },
        {
          "method": "org.eclipse.debug.internal.ui.views.console.ProcessConsole.propertyChange",
          "source": "ProcessConsole.java:179"
        },
        {
          "method": "org.eclipse.ui.plugin.AbstractUIPlugin$2.run",
          "source": "AbstractUIPlugin.java:278"
        },
        {
          "method": "org.eclipse.core.internal.runtime.InternalPlatform.run",
          "source": "InternalPlatform.java:616"
        },
        {
          "method": "org.eclipse.core.runtime.Platform.run",
          "source": "Platform.java:747"
        },
        {
          "method": "org.eclipse.ui.plugin.AbstractUIPlugin$CompatibilityPreferenceStore.firePropertyChangeEvent",
          "source": "AbstractUIPlugin. java:275"
        },
        {
          "method": "org.eclipse.ui.plugin.AbstractUIPlugin$1.propertyChange",
          "source": "AbstractUIPlugin.java:218"
        },
        {
          "method": "org.eclipse.core.internal.preferences.PreferenceForwarder.preferenceChange",
          "source": "PreferenceForwarder.java:114"
        },
        {
          "method": "org.eclipse.core.internal.preferences.EclipsePreferences$4.run",
          "source": "EclipsePreferences.java:743"
        },
        {
          "method": "org.eclipse.core.internal.runtime.InternalPlatform.run",
          "source": "InternalPlatform.java:616"
        },
        {
          "method": "org.eclipse.core.runtime.Platform.run",
          "source": "Platform.java:747"
        },
        {
          "method": "org.eclipse.core.internal.preferences.EclipsePreferences.preferenceChanged",
          "source": "EclipsePreferences.java:746"
        },
        {
          "method": "org.eclipse.core.internal.preferences.EclipsePreferences.putBoolean",
          "source": "EclipsePreferences.java:769"
        },
        {
          "method": "org.eclipse.core.internal.preferences.PreferenceForwarder.setValue",
          "source": "PreferenceForwarder.java:225"
        },
        {
          "method": "org.eclipse.ui.plugin.AbstractUIPlugin$CompatibilityPreferenceStore.setValue",
          "source": "AbstractUIPlugin.java:491"
        },
        {
          "method": "org.eclipse.jface.preference.BooleanFieldEditor.doStore",
          "source": "BooleanFieldEditor.java:154"
        },
        {
          "method": "org.eclipse.jface.preference.FieldEditor.store",
          "source": "FieldEditor.java:636"
        },
        {
          "method": "org.eclipse.jface.preference.FieldEditorPreferencePage.performOk",
          "source": "FieldEditorPreferencePage.java:334"
        },
        {
          "method": "org.eclipse.debug.internal.ui.preferences.ConsolePreferencePage.performOk",
          "source": "ConsolePreferencePage.java:157"
        },
        {
          "method": "org.eclipse.jface.preference.PreferencePage.performApply",
          "source": "PreferencePage.java:422"
        },
        {
          "method": "org.eclipse.jface.preference.PreferencePage$2.widgetSelected",
          "source": "PreferencePage.java:277"
        },
        {
          "method": "org.eclipse.swt.widgets.TypedListener.handleEvent",
          "source": "TypedListener.java:89"
        },
        {
          "method": "org.eclipse.swt.widgets.EventTable.sendEvent",
          "source": "EventTable.java:82"
        },
        {
          "method": "org.eclipse.swt.widgets.Widget.sendEvent",
          "source": "Widget.java:796"
        },
        {
          "method": "org.eclipse.swt.widgets.Display.runDeferredEvents",
          "source": "Display.java:2783"
        },
        {
          "method": "org.eclipse.swt.widgets.Display.readAndDispatch",
          "source": "Display.java:2442"
        },
        {
          "method": "org.eclipse.jface.window.Window.runEventLoop",
          "source": "Window.java:706"
        },
        {
          "method": "org.eclipse.jface.window.Window.open",
          "source": "Window.java:684"
        },
        {
          "method": "org.eclipse.ui.internal.OpenPreferencesAction.run",
          "source": "OpenPreferencesAction.java:75"
        },
        {
          "method": "org.eclipse.jface.action.Action.runWithEvent",
          "source": "Action.java:988"
        },
        {
          "method": "org.eclipse.jface.action.ActionContributionItem.handleWidgetSelection",
          "source": "ActionContributionItem.java:555"
        },
        {
          "method": "org.eclipse.jface.action.ActionContributionItem.access$2",
          "source": "ActionContributionItem.java:505"
        },
        {
          "method": "org.eclipse.jface.action.ActionContributionItem$6.handleEvent",
          "source": "ActionContributionItem.java:419"
        },
        {
          "method": "org.eclipse.swt.widgets.EventTable.sendEvent",
          "source": "EventTable.java:82"
        },
        {
          "method": "org.eclipse.swt.widgets.Widget.sendEvent",
          "source": "Widget.java:796"
        },
        {
          "method": "org.eclipse.swt.widgets.Display.runDeferredEvents",
          "source": "Display.java:2783"
        },
        {
          "method": "org.eclipse.swt.widgets.Display.readAndDispatch",
          "source": "Display.java:2442"
        },
        {
          "method": "org.eclipse.ui.internal.Workbench.runEventLoop",
          "source": "Workbench.java:1443"
        },
        {
          "method": "org.eclipse.ui.internal.Workbench.runUI",
          "source": "Workbench.java:1414"
        },
        {
          "method": "org.eclipse.ui.internal.Workbench.createAndRunWorkbench",
          "source": "Workbench.java:271"
        },
        {
          "method": "org.eclipse.ui.PlatformUI.createAndRunWorkbench",
          "source": "PlatformUI.java:144"
        },
        {
          "method": "org.eclipse.ui.internal.ide.IDEApplication.run",
          "source": "IDEApplication.java:102"
        },
        {
          "method": "org.eclipse.core.internal.runtime.PlatformActivator$1.run",
          "source": "PlatformActivator.java:335"
        },
        {
          "method": "org.eclipse.core.runtime.adaptor.EclipseStarter.run",
          "source": "EclipseStarter.java:273"
        },
        {
          "method": "org.eclipse.core.runtime.adaptor.EclipseStarter.run",
          "source": "EclipseStarter.java:129"
        },
        {
          "method": "sun.reflect.NativeMethodAccessorImpl.invoke0",
          "source": "Native Method"
        },
        {
          "method": "sun.reflect.NativeMethodAccessorImpl.invoke",
          "source": "NativeMethodAccessorImpl.java:39"
        },
        {
          "method": "sun.reflect.DelegatingMethodAccessorImpl.invoke",
          "source": "DelegatingMethodAccessorImpl.java:25"
        },
        {
          "method": "java.lang.reflect.Method.invoke",
          "source": "Method.java:324"
        },
        {
          "method": "org.eclipse.core.launcher.Main.basicRun",
          "source": "Main.java:185"
        },
        {
          "method": "org.eclipse.core.launcher.Main.run",
          "source": "Main.java:704"
        },
        {
          "method": "org.eclipse.core.launcher.Main.main",
          "source": "Main.java:688"
        }
      ],
      "number": 1,
      "commentIndex": 1,
      "bugId": "75226",
      "date": "2004-09-29T01:43:34+02:00",
      "product": "JDT",
      "component": "Debug",
      "severity": "normal"
    }
  ],
  "groupId": "75226",
  "bugId": "75226",
  "date": "2004-09-29T01:42:36+02:00",
  "product": "JDT",
  "component": "Debug",
  "severity": "normal"
}