{
  "comments": [
    "First an important note - I have the Cheetah (1.5) plugin installed.  Cheetah\ncontributes to the preferences page in question, so it may be to blame.  I can\nreliably reproduce this bug on both RedHat Linux 9 and Windows XP.\n\nTo reproduce this error, follow these steps:\n\n1.  Right click on a java or plugin project and select \"Properties\".\n2.  Select the \"Java Compiler\" preference page\n3.  Click \"Use project settings\" and click OK.  \n4.  Eclipse will inform you of the need to do a full project build.  Click \"Yes\".\n5.  The properties dialog will close.  Right click on the project again and\nselect \"Properties\" and return to the \"Java Compiler\" page.\n6.  Click \"Use workspace settings\" and click OK.\n7.  Eclipse will inform you again of the need to do a full project build.  Click\n\"Yes\".\n8.  The properties dialog will close again. \n9.  Right click on the project A THIRD TIME (stay with me here!)  Eclipse will\nopen an error dialog with the title \"Could Not Accept Changes\" and the message\n\"The currently displayed page contains invalid values\".  The Java Compiler page\nwill not be visible.  You\u0027ll also get the following stack trace:\n\njava.lang.IllegalStateException: Preference node \"org.eclipse.jdt.core\" has been\nremoved.\n        at\norg.eclipse.core.internal.preferences.EclipsePreferences.checkRemoved(EclipsePreferences.java:142)\n        at\norg.eclipse.core.internal.preferences.EclipsePreferences.keys(EclipsePreferences.java:575)\n        at\norg.eclipse.jdt.internal.core.JavaProject.getOptions(JavaProject.java:1438)\n        at\norg.eclipse.jdt.internal.core.CompilationUnitProblemFinder.process(CompilationUnitProblemFinder.java:151)\n        at\norg.eclipse.jdt.internal.core.CompilationUnitProblemFinder.process(CompilationUnitProblemFinder.java:206)\n        at\norg.eclipse.jdt.internal.core.ReconcileWorkingCopyOperation.executeOperation(ReconcileWorkingCopyOperation.java:76)\n        at\norg.eclipse.jdt.internal.core.JavaModelOperation.run(JavaModelOperation.java:700)\n        at\norg.eclipse.jdt.internal.core.JavaModelOperation.runOperation(JavaModelOperation.java:739)\n        at\norg.eclipse.jdt.internal.core.CompilationUnit.reconcile(CompilationUnit.java:1097)\n        at\norg.eclipse.jdt.internal.ui.text.java.JavaReconcilingStrategy.reconcile(JavaReconcilingStrategy.java:88)\n        at\norg.eclipse.jdt.internal.ui.text.java.JavaReconcilingStrategy.reconcile(JavaReconcilingStrategy.java:129)\n        at\norg.eclipse.jdt.internal.ui.text.CompositeReconcilingStrategy.reconcile(CompositeReconcilingStrategy.java:86)\n        at\norg.eclipse.jdt.internal.ui.text.JavaCompositeReconcilingStrategy.reconcile(JavaCompositeReconcilingStrategy.java:96)\n        at\norg.eclipse.jface.text.reconciler.MonoReconciler.process(MonoReconciler.java:75)\n        at\norg.eclipse.jdt.internal.ui.text.JavaReconciler.process(JavaReconciler.java:315)\n        at\norg.eclipse.jface.text.reconciler.AbstractReconciler$BackgroundThread.run(AbstractReconciler.java:204)",
    "Please install 3.1 M2 which fixes this problem.\nNote that now Cheetah plugin is no longer available.\nTo get 1.5 features latest implementation, you have to get 3.1 milestone or\nintegration builds.\n\n\n*** This bug has been marked as a duplicate of 68993 ***"
  ],
  "commentCreationDates": [
    "2004-09-29T02:42:48+02:00",
    "2004-09-29T09:24:23+02:00"
  ],
  "traces": [
    {
      "exceptionType": "java.lang.IllegalStateException",
      "message": "Preference node \"org.eclipse.jdt.core\" has been removed.",
      "elements": [
        {
          "method": "org.eclipse.core.internal.preferences.EclipsePreferences.checkRemoved",
          "source": "EclipsePreferences.java:142"
        },
        {
          "method": "org.eclipse.core.internal.preferences.EclipsePreferences.keys",
          "source": "EclipsePreferences.java:575"
        },
        {
          "method": "org.eclipse.jdt.internal.core.JavaProject.getOptions",
          "source": "JavaProject.java:1438"
        },
        {
          "method": "org.eclipse.jdt.internal.core.CompilationUnitProblemFinder.process",
          "source": "CompilationUnitProblemFinder.java:151"
        },
        {
          "method": "org.eclipse.jdt.internal.core.CompilationUnitProblemFinder.process",
          "source": "CompilationUnitProblemFinder.java:206"
        },
        {
          "method": "org.eclipse.jdt.internal.core.ReconcileWorkingCopyOperation.executeOperation",
          "source": "ReconcileWorkingCopyOperation.java:76"
        },
        {
          "method": "org.eclipse.jdt.internal.core.JavaModelOperation.run",
          "source": "JavaModelOperation.java:700"
        },
        {
          "method": "org.eclipse.jdt.internal.core.JavaModelOperation.runOperation",
          "source": "JavaModelOperation.java:739"
        },
        {
          "method": "org.eclipse.jdt.internal.core.CompilationUnit.reconcile",
          "source": "CompilationUnit.java:1097"
        },
        {
          "method": "org.eclipse.jdt.internal.ui.text.java.JavaReconcilingStrategy.reconcile",
          "source": "JavaReconcilingStrategy.java:88"
        },
        {
          "method": "org.eclipse.jdt.internal.ui.text.java.JavaReconcilingStrategy.reconcile",
          "source": "JavaReconcilingStrategy.java:129"
        },
        {
          "method": "org.eclipse.jdt.internal.ui.text.CompositeReconcilingStrategy.reconcile",
          "source": "CompositeReconcilingStrategy.java:86"
        },
        {
          "method": "org.eclipse.jdt.internal.ui.text.JavaCompositeReconcilingStrategy.reconcile",
          "source": "JavaCompositeReconcilingStrategy.java:96"
        },
        {
          "method": "org.eclipse.jface.text.reconciler.MonoReconciler.process",
          "source": "MonoReconciler.java:75"
        },
        {
          "method": "org.eclipse.jdt.internal.ui.text.JavaReconciler.process",
          "source": "JavaReconciler.java:315"
        },
        {
          "method": "org.eclipse.jface.text.reconciler.AbstractReconciler$BackgroundThread.run",
          "source": "AbstractReconciler.java:204"
        }
      ],
      "number": 0,
      "commentIndex": 0,
      "bugId": "75230",
      "duplicateId": "68993",
      "date": "2004-09-29T02:42:48+02:00",
      "product": "JDT",
      "component": "Core",
      "severity": "normal"
    }
  ],
  "groupId": "68993",
  "bugId": "75230",
  "duplicateId": "68993",
  "date": "2004-09-29T02:42:48+02:00",
  "product": "JDT",
  "component": "Core",
  "severity": "normal"
}