{
  "comments": [
    "I got following exception when trying to synchronize a workspace I didn\u0027t work\non for a long time.\nUnfortunately I can be more precise on how long the time is, but I would say it\nwas a workspace I worked with 3.1 M1 build...\nHope it will be enough to reproduce...\n\nHere\u0027s the log of the exeception:\n!ENTRY org.eclipse.core.runtime 4 2 Sep 29, 2004 19:01:12.424\n!MESSAGE An internal error occurred during: \"Synchronizing\".\n!STACK 0\njava.lang.IllegalMonitorStateException\n        at java.text.SimpleDateFormat.parse(SimpleDateFormat.java:1249)\n        at java.text.DateFormat.parse(DateFormat.java:345)\n        at\norg.eclipse.team.internal.ccvs.core.util.CVSDateFormatter.entryLineToDate(DateFormat.java)\n        at\norg.eclipse.team.internal.ccvs.core.syncinfo.ResourceSyncInfo.setEntryLine(DateFormat.java)\n        at\norg.eclipse.team.internal.ccvs.core.syncinfo.ResourceSyncInfo.\u003cinit\u003e(Unknown Source)\n        at\norg.eclipse.team.internal.ccvs.core.syncinfo.ResourceSyncInfo.\u003cinit\u003e(Unknown Source)\n        at\norg.eclipse.team.internal.ccvs.core.resources.RemoteFile.getSyncInfo(Unknown Source)\n        at\norg.eclipse.team.internal.ccvs.core.resources.RemoteFile.getTimeStamp(Unknown\nSource)\n        at\norg.eclipse.team.internal.ccvs.core.client.AbstractStructureVisitor.sendEntryLineToServer(Unknown\nSource)\n        at\norg.eclipse.team.internal.ccvs.core.client.AbstractStructureVisitor.sendFile(Unknown\nSource)\n        at\norg.eclipse.team.internal.ccvs.core.client.FileStructureVisitor.visitFile(Unknown\nSource)\n        at\norg.eclipse.team.internal.ccvs.core.resources.RemoteFile.accept(Unknown Source)\n        at\norg.eclipse.team.internal.ccvs.core.client.AbstractStructureVisitor.visit(Unknown\nSource)\n        at\norg.eclipse.team.internal.ccvs.core.client.AbstractMessageCommand.sendLocalResourceState(Unknown\nSource)\n        at org.eclipse.team.internal.ccvs.core.client.Command.doExecute(Unknown\nSource)\n        at org.eclipse.team.internal.ccvs.core.client.Command$1.run(Unknown Source)\n        at\norg.eclipse.team.internal.ccvs.core.resources.RemoteFolder.run(Unknown Source)\n        at org.eclipse.team.internal.ccvs.core.client.Command.execute(Unknown\nSource)\n        at\norg.eclipse.team.internal.ccvs.core.resources.RemoteFolderTreeBuilder.fetchFileRevisions(Unknown\nSource)\n        at\norg.eclipse.team.internal.ccvs.core.resources.RemoteFolderTreeBuilder.fetchFileRevisions(Unknown\nSource)\n        at\norg.eclipse.team.internal.ccvs.core.resources.RemoteFolderTreeBuilder.buildTree(Unknown\nSource)\n        at\norg.eclipse.team.internal.ccvs.core.resources.RemoteFolderTreeBuilder.buildRemoteTree(Unknown\nSource)\n        at\norg.eclipse.team.internal.ccvs.core.resources.CVSWorkspaceRoot.getRemoteTree(Unknown\nSource)\n        at\norg.eclipse.team.internal.ccvs.core.syncinfo.CVSResourceVariantTree.fetchVariant(Unknown\nSource)\n        at\norg.eclipse.team.core.variants.AbstractResourceVariantTree.refresh(Unknown Source)\n        at\norg.eclipse.team.internal.ccvs.core.syncinfo.CVSResourceVariantTree.refresh(Unknown\nSource)\n        at\norg.eclipse.team.core.variants.AbstractResourceVariantTree.refresh(Unknown Source)\n        at\norg.eclipse.team.core.variants.ResourceVariantTreeSubscriber.refresh(Unknown Source)\n        at\norg.eclipse.team.core.variants.ResourceVariantTreeSubscriber.refresh(Unknown Source)\n        at\norg.eclipse.team.internal.ui.synchronize.RefreshSubscriberJob.run(Unknown Source)\n        at org.eclipse.core.internal.jobs.Worker.run(Unknown Source)\n\nSet as major as the only workaround is to delete project and check-out it\nagain... (which is really painful for big workspaces).",
    "This appears to be an issue with the IBM VM or class libraries and is not a \nproblem in the CVS code (i.e. access to the date formatter is synchronized).\n\n*** This bug has been marked as a duplicate of 73603 ***",
    "*** Bug 88173 has been marked as a duplicate of this bug. ***"
  ],
  "commentCreationDates": [
    "2004-09-29T19:16:49+02:00",
    "2004-09-29T19:46:05+02:00",
    "2005-03-16T14:48:03+01:00"
  ],
  "traces": [
    {
      "exceptionType": "java.lang.IllegalMonitorStateException",
      "elements": [
        {
          "method": "java.text.SimpleDateFormat.parse",
          "source": "SimpleDateFormat.java:1249"
        },
        {
          "method": "java.text.DateFormat.parse",
          "source": "DateFormat.java:345"
        },
        {
          "method": "org.eclipse.team.internal.ccvs.core.util.CVSDateFormatter.entryLineToDate",
          "source": "DateFormat.java"
        },
        {
          "method": "org.eclipse.team.internal.ccvs.core.syncinfo.ResourceSyncInfo.setEntryLine",
          "source": "DateFormat.java"
        },
        {
          "method": "org.eclipse.team.internal.ccvs.core.syncinfo.ResourceSyncInfo.\u003cinit\u003e",
          "source": "Unknown Source"
        },
        {
          "method": "org.eclipse.team.internal.ccvs.core.syncinfo.ResourceSyncInfo.\u003cinit\u003e",
          "source": "Unknown Source"
        },
        {
          "method": "org.eclipse.team.internal.ccvs.core.resources.RemoteFile.getSyncInfo",
          "source": "Unknown Source"
        },
        {
          "method": "org.eclipse.team.internal.ccvs.core.resources.RemoteFile.getTimeStamp",
          "source": "Unknown Source"
        },
        {
          "method": "org.eclipse.team.internal.ccvs.core.client.AbstractStructureVisitor.sendEntryLineToServer",
          "source": "Unknown Source"
        },
        {
          "method": "org.eclipse.team.internal.ccvs.core.client.AbstractStructureVisitor.sendFile",
          "source": "Unknown Source"
        },
        {
          "method": "org.eclipse.team.internal.ccvs.core.client.FileStructureVisitor.visitFile",
          "source": "Unknown Source"
        },
        {
          "method": "org.eclipse.team.internal.ccvs.core.resources.RemoteFile.accept",
          "source": "Unknown Source"
        },
        {
          "method": "org.eclipse.team.internal.ccvs.core.client.AbstractStructureVisitor.visit",
          "source": "Unknown Source"
        },
        {
          "method": "org.eclipse.team.internal.ccvs.core.client.AbstractMessageCommand.sendLocalResourceState",
          "source": "Unknown Source"
        },
        {
          "method": "org.eclipse.team.internal.ccvs.core.client.Command.doExecute",
          "source": "Unknown Source"
        },
        {
          "method": "org.eclipse.team.internal.ccvs.core.client.Command$1.run",
          "source": "Unknown Source"
        },
        {
          "method": "org.eclipse.team.internal.ccvs.core.resources.RemoteFolder.run",
          "source": "Unknown Source"
        },
        {
          "method": "org.eclipse.team.internal.ccvs.core.client.Command.execute",
          "source": "Unknown Source"
        },
        {
          "method": "org.eclipse.team.internal.ccvs.core.resources.RemoteFolderTreeBuilder.fetchFileRevisions",
          "source": "Unknown Source"
        },
        {
          "method": "org.eclipse.team.internal.ccvs.core.resources.RemoteFolderTreeBuilder.fetchFileRevisions",
          "source": "Unknown Source"
        },
        {
          "method": "org.eclipse.team.internal.ccvs.core.resources.RemoteFolderTreeBuilder.buildTree",
          "source": "Unknown Source"
        },
        {
          "method": "org.eclipse.team.internal.ccvs.core.resources.RemoteFolderTreeBuilder.buildRemoteTree",
          "source": "Unknown Source"
        },
        {
          "method": "org.eclipse.team.internal.ccvs.core.resources.CVSWorkspaceRoot.getRemoteTree",
          "source": "Unknown Source"
        },
        {
          "method": "org.eclipse.team.internal.ccvs.core.syncinfo.CVSResourceVariantTree.fetchVariant",
          "source": "Unknown Source"
        },
        {
          "method": "org.eclipse.team.core.variants.AbstractResourceVariantTree.refresh",
          "source": "Unknown Source"
        },
        {
          "method": "org.eclipse.team.internal.ccvs.core.syncinfo.CVSResourceVariantTree.refresh",
          "source": "Unknown Source"
        },
        {
          "method": "org.eclipse.team.core.variants.AbstractResourceVariantTree.refresh",
          "source": "Unknown Source"
        },
        {
          "method": "org.eclipse.team.core.variants.ResourceVariantTreeSubscriber.refresh",
          "source": "Unknown Source"
        },
        {
          "method": "org.eclipse.team.core.variants.ResourceVariantTreeSubscriber.refresh",
          "source": "Unknown Source"
        },
        {
          "method": "org.eclipse.team.internal.ui.synchronize.RefreshSubscriberJob.run",
          "source": "Unknown Source"
        },
        {
          "method": "org.eclipse.core.internal.jobs.Worker.run",
          "source": "Unknown Source"
        }
      ],
      "number": 0,
      "commentIndex": 0,
      "bugId": "75321",
      "duplicateId": "73603",
      "date": "2004-09-29T19:16:49+02:00",
      "product": "Platform",
      "component": "CVS",
      "severity": "major"
    }
  ],
  "groupId": "73603",
  "bugId": "75321",
  "duplicateId": "73603",
  "date": "2004-09-29T19:16:49+02:00",
  "product": "Platform",
  "component": "CVS",
  "severity": "major"
}