{
  "comments": [
    "3.1.0 M2\n\nWas editing a plugin.xml file and consistently started to get internal errors.\nSeveral of the following exceptions were in the log. Closing and re-opening the\neditor fixed the problem.\n\n\n!ENTRY org.eclipse.core.runtime 4 2 Oct 03, 2004 15:55:12.960\n!MESSAGE Problems occurred when invoking code from plug-in:\n\"org.eclipse.core.runtime\".\n!STACK 0\norg.eclipse.swt.SWTException: Widget is disposed\n        at org.eclipse.swt.SWT.error(SWT.java:2691)\n        at org.eclipse.swt.SWT.error(SWT.java:2616)\n        at org.eclipse.swt.SWT.error(SWT.java:2587)\n        at org.eclipse.swt.widgets.Widget.error(Widget.java:381)\n        at org.eclipse.swt.widgets.Widget.checkWidget(Widget.java:283)\n        at org.eclipse.swt.widgets.Widget.checkParent(Widget.java:223)\n        at org.eclipse.swt.widgets.Widget.\u003cinit\u003e(Widget.java:111)\n        at org.eclipse.swt.widgets.Control.\u003cinit\u003e(Control.java:89)\n        at org.eclipse.swt.widgets.Scrollable.\u003cinit\u003e(Scrollable.java:72)\n        at org.eclipse.swt.widgets.Composite.\u003cinit\u003e(Composite.java:86)\n        at org.eclipse.swt.custom.TableTree.\u003cinit\u003e(TableTree.java:94)\n        at\norg.eclipse.ui.views.properties.PropertySheetViewer.\u003cinit\u003e(PropertySheetViewer.java:119)\n        at\norg.eclipse.ui.views.properties.PropertySheetPage.createControl(PropertySheetPage.java:120)\n        at\norg.eclipse.pde.internal.ui.editor.schema.SchemaPropertySheet.createControl(SchemaPropertySheet.java:34)\n        at\norg.eclipse.pde.internal.ui.editor.PDEMultiPagePropertySheet.getPageControl(PDEMultiPagePropertySheet.java:89)\n        at\norg.eclipse.pde.internal.ui.editor.PDEMultiPagePropertySheet.createPageRec(PDEMultiPagePropertySheet.java:58)\n        at\norg.eclipse.pde.internal.ui.editor.PDEMultiPagePropertySheet.setPageActive(PDEMultiPagePropertySheet.java:137)\n        at\norg.eclipse.pde.internal.ui.editor.PDEFormEditor.updatePropertySheet(PDEFormEditor.java:502)\n        at\norg.eclipse.pde.internal.ui.editor.PropertiesAction.run(PropertiesAction.java:29)\n        at\norg.eclipse.pde.internal.ui.editor.schema.ElementSection.handleDoubleClick(ElementSection.java:418)\n        at\norg.eclipse.pde.internal.ui.editor.TreeSection$PartAdapter.handleDoubleClick(TreeSection.java:33)\n        at\norg.eclipse.pde.internal.ui.parts.TreePart$2.doubleClick(TreePart.java:54)\n        at\norg.eclipse.jface.viewers.StructuredViewer$1.run(StructuredViewer.java:427)\n        at\norg.eclipse.core.internal.runtime.InternalPlatform.run(InternalPlatform.java:616)\n        at org.eclipse.core.runtime.Platform.run(Platform.java:747)\n        at\norg.eclipse.jface.viewers.StructuredViewer.fireDoubleClick(StructuredViewer.java:425)\n        at\norg.eclipse.jface.viewers.StructuredViewer.handleDoubleSelect(StructuredViewer.java:647)\n        at\norg.eclipse.jface.viewers.StructuredViewer$4.widgetDefaultSelected(StructuredViewer.java:757)\n        at\norg.eclipse.jface.util.OpenStrategy.fireDefaultSelectionEvent(OpenStrategy.java:219)\n        at org.eclipse.jface.util.OpenStrategy.access$0(OpenStrategy.java:216)\n        at org.eclipse.jface.util.OpenStrategy$1.handleEvent(OpenStrategy.java:275)\n        at org.eclipse.swt.widgets.EventTable.sendEvent(EventTable.java:82)\n        at org.eclipse.swt.widgets.Widget.sendEvent(Widget.java:796)\n        at org.eclipse.swt.widgets.Display.runDeferredEvents(Display.java:2783)\n        at org.eclipse.swt.widgets.Display.readAndDispatch(Display.java:2442)\n        at org.eclipse.ui.internal.Workbench.runEventLoop(Workbench.java:1443)\n        at org.eclipse.ui.internal.Workbench.runUI(Workbench.java:1414)\n        at\norg.eclipse.ui.internal.Workbench.createAndRunWorkbench(Workbench.java:271)\n        at org.eclipse.ui.PlatformUI.createAndRunWorkbench(PlatformUI.java:144)\n        at org.eclipse.ui.internal.ide.IDEApplication.run(IDEApplication.java:102)\n        at\norg.eclipse.core.internal.runtime.PlatformActivator$1.run(PlatformActivator.java:335)\n        at\norg.eclipse.core.runtime.adaptor.EclipseStarter.run(EclipseStarter.java:273)\n        at\norg.eclipse.core.runtime.adaptor.EclipseStarter.run(EclipseStarter.java:129)\n        at sun.reflect.NativeMethodAccessorImpl.invoke0(Native Method)\n        at sun.reflect.NativeMethodAccessorImpl.invoke(Unknown Source)\n        at sun.reflect.DelegatingMethodAccessorImpl.invoke(Unknown Source)\n        at java.lang.reflect.Method.invoke(Unknown Source)\n        at org.eclipse.core.launcher.Main.basicRun(Main.java:185)\n        at org.eclipse.core.launcher.Main.run(Main.java:704)\n        at org.eclipse.core.launcher.Main.main(Main.java:688)",
    "was it a plugin.xml or a schema file?",
    "plugin.xml",
    "then you must have pasted the wrong log entry.",
    "I got it today trying to add the translatable property. I won\u0027t do it. I move\nback to previous usable build.\nWhen this is fixed, I will do it.",
    "\n\n*** This bug has been marked as a duplicate of 78602 ***"
  ],
  "commentCreationDates": [
    "2004-10-04T02:44:02+02:00",
    "2004-10-04T02:45:29+02:00",
    "2004-10-04T15:19:47+02:00",
    "2004-10-04T16:19:09+02:00",
    "2004-11-22T16:18:25+01:00",
    "2004-11-23T08:17:07+01:00"
  ],
  "traces": [
    {
      "exceptionType": "org.eclipse.swt.SWTException",
      "message": "Widget is disposed",
      "elements": [
        {
          "method": "org.eclipse.swt.SWT.error",
          "source": "SWT.java:2691"
        },
        {
          "method": "org.eclipse.swt.SWT.error",
          "source": "SWT.java:2616"
        },
        {
          "method": "org.eclipse.swt.SWT.error",
          "source": "SWT.java:2587"
        },
        {
          "method": "org.eclipse.swt.widgets.Widget.error",
          "source": "Widget.java:381"
        },
        {
          "method": "org.eclipse.swt.widgets.Widget.checkWidget",
          "source": "Widget.java:283"
        },
        {
          "method": "org.eclipse.swt.widgets.Widget.checkParent",
          "source": "Widget.java:223"
        },
        {
          "method": "org.eclipse.swt.widgets.Widget.\u003cinit\u003e",
          "source": "Widget.java:111"
        },
        {
          "method": "org.eclipse.swt.widgets.Control.\u003cinit\u003e",
          "source": "Control.java:89"
        },
        {
          "method": "org.eclipse.swt.widgets.Scrollable.\u003cinit\u003e",
          "source": "Scrollable.java:72"
        },
        {
          "method": "org.eclipse.swt.widgets.Composite.\u003cinit\u003e",
          "source": "Composite.java:86"
        },
        {
          "method": "org.eclipse.swt.custom.TableTree.\u003cinit\u003e",
          "source": "TableTree.java:94"
        },
        {
          "method": "org.eclipse.ui.views.properties.PropertySheetViewer.\u003cinit\u003e",
          "source": "PropertySheetViewer.java:119"
        },
        {
          "method": "org.eclipse.ui.views.properties.PropertySheetPage.createControl",
          "source": "PropertySheetPage.java:120"
        },
        {
          "method": "org.eclipse.pde.internal.ui.editor.schema.SchemaPropertySheet.createControl",
          "source": "SchemaPropertySheet.java:34"
        },
        {
          "method": "org.eclipse.pde.internal.ui.editor.PDEMultiPagePropertySheet.getPageControl",
          "source": "PDEMultiPagePropertySheet.java:89"
        },
        {
          "method": "org.eclipse.pde.internal.ui.editor.PDEMultiPagePropertySheet.createPageRec",
          "source": "PDEMultiPagePropertySheet.java:58"
        },
        {
          "method": "org.eclipse.pde.internal.ui.editor.PDEMultiPagePropertySheet.setPageActive",
          "source": "PDEMultiPagePropertySheet.java:137"
        },
        {
          "method": "org.eclipse.pde.internal.ui.editor.PDEFormEditor.updatePropertySheet",
          "source": "PDEFormEditor.java:502"
        },
        {
          "method": "org.eclipse.pde.internal.ui.editor.PropertiesAction.run",
          "source": "PropertiesAction.java:29"
        },
        {
          "method": "org.eclipse.pde.internal.ui.editor.schema.ElementSection.handleDoubleClick",
          "source": "ElementSection.java:418"
        },
        {
          "method": "org.eclipse.pde.internal.ui.editor.TreeSection$PartAdapter.handleDoubleClick",
          "source": "TreeSection.java:33"
        },
        {
          "method": "org.eclipse.pde.internal.ui.parts.TreePart$2.doubleClick",
          "source": "TreePart.java:54"
        },
        {
          "method": "org.eclipse.jface.viewers.StructuredViewer$1.run",
          "source": "StructuredViewer.java:427"
        },
        {
          "method": "org.eclipse.core.internal.runtime.InternalPlatform.run",
          "source": "InternalPlatform.java:616"
        },
        {
          "method": "org.eclipse.core.runtime.Platform.run",
          "source": "Platform.java:747"
        },
        {
          "method": "org.eclipse.jface.viewers.StructuredViewer.fireDoubleClick",
          "source": "StructuredViewer.java:425"
        },
        {
          "method": "org.eclipse.jface.viewers.StructuredViewer.handleDoubleSelect",
          "source": "StructuredViewer.java:647"
        },
        {
          "method": "org.eclipse.jface.viewers.StructuredViewer$4.widgetDefaultSelected",
          "source": "StructuredViewer.java:757"
        },
        {
          "method": "org.eclipse.jface.util.OpenStrategy.fireDefaultSelectionEvent",
          "source": "OpenStrategy.java:219"
        },
        {
          "method": "org.eclipse.jface.util.OpenStrategy.access$0",
          "source": "OpenStrategy.java:216"
        },
        {
          "method": "org.eclipse.jface.util.OpenStrategy$1.handleEvent",
          "source": "OpenStrategy.java:275"
        },
        {
          "method": "org.eclipse.swt.widgets.EventTable.sendEvent",
          "source": "EventTable.java:82"
        },
        {
          "method": "org.eclipse.swt.widgets.Widget.sendEvent",
          "source": "Widget.java:796"
        },
        {
          "method": "org.eclipse.swt.widgets.Display.runDeferredEvents",
          "source": "Display.java:2783"
        },
        {
          "method": "org.eclipse.swt.widgets.Display.readAndDispatch",
          "source": "Display.java:2442"
        },
        {
          "method": "org.eclipse.ui.internal.Workbench.runEventLoop",
          "source": "Workbench.java:1443"
        },
        {
          "method": "org.eclipse.ui.internal.Workbench.runUI",
          "source": "Workbench.java:1414"
        },
        {
          "method": "org.eclipse.ui.internal.Workbench.createAndRunWorkbench",
          "source": "Workbench.java:271"
        },
        {
          "method": "org.eclipse.ui.PlatformUI.createAndRunWorkbench",
          "source": "PlatformUI.java:144"
        },
        {
          "method": "org.eclipse.ui.internal.ide.IDEApplication.run",
          "source": "IDEApplication.java:102"
        },
        {
          "method": "org.eclipse.core.internal.runtime.PlatformActivator$1.run",
          "source": "PlatformActivator.java:335"
        },
        {
          "method": "org.eclipse.core.runtime.adaptor.EclipseStarter.run",
          "source": "EclipseStarter.java:273"
        },
        {
          "method": "org.eclipse.core.runtime.adaptor.EclipseStarter.run",
          "source": "EclipseStarter.java:129"
        },
        {
          "method": "sun.reflect.NativeMethodAccessorImpl.invoke0",
          "source": "Native Method"
        },
        {
          "method": "sun.reflect.NativeMethodAccessorImpl.invoke",
          "source": "Unknown Source"
        },
        {
          "method": "sun.reflect.DelegatingMethodAccessorImpl.invoke",
          "source": "Unknown Source"
        },
        {
          "method": "java.lang.reflect.Method.invoke",
          "source": "Unknown Source"
        },
        {
          "method": "org.eclipse.core.launcher.Main.basicRun",
          "source": "Main.java:185"
        },
        {
          "method": "org.eclipse.core.launcher.Main.run",
          "source": "Main.java:704"
        },
        {
          "method": "org.eclipse.core.launcher.Main.main",
          "source": "Main.java:688"
        }
      ],
      "number": 0,
      "commentIndex": 0,
      "bugId": "75553",
      "duplicateId": "78602",
      "date": "2004-10-04T02:44:02+02:00",
      "product": "PDE",
      "component": "UI",
      "severity": "normal"
    }
  ],
  "groupId": "78602",
  "bugId": "75553",
  "duplicateId": "78602",
  "date": "2004-10-04T02:44:02+02:00",
  "product": "PDE",
  "component": "UI",
  "severity": "normal"
}