{
  "comments": [
    "I\u0027ve enabled word wrap for debug console to 81 characters. As a result my error\nlog is filled with the following exceptions:\n\n\n!ENTRY org.eclipse.ui 4 0 Oct 04, 2004 13:25:50.957\n!MESSAGE 4\n!STACK 0\njava.lang.ArrayIndexOutOfBoundsException: 4\n        at\norg.eclipse.swt.custom.StyledText$ContentWidthCache.textChanged(StyledText.java:1407)\n        at org.eclipse.swt.custom.StyledText.handleTextChanged(StyledText.java:5129)\n        at org.eclipse.swt.custom.StyledText$6.textChanged(StyledText.java:4709)\n        at\norg.eclipse.ui.internal.console.IOConsoleDocumentAdapter.documentChanged(IOConsoleDocumentAdapter.java:306)\n        at\norg.eclipse.jface.text.AbstractDocument.doFireDocumentChanged2(AbstractDocument.java:682)\n        at\norg.eclipse.jface.text.AbstractDocument.doFireDocumentChanged(AbstractDocument.java:645)\n        at\norg.eclipse.jface.text.AbstractDocument.doFireDocumentChanged(AbstractDocument.java:630)\n        at\norg.eclipse.jface.text.AbstractDocument.fireDocumentChanged(AbstractDocument.java:707)\n        at\norg.eclipse.jface.text.AbstractDocument.replace(AbstractDocument.java:998)\n        at\norg.eclipse.ui.internal.console.IOConsoleDocument.replace(IOConsoleDocument.java:83)\n        at\norg.eclipse.ui.internal.console.IOConsolePartitioner$1.run(IOConsolePartitioner.java:525)\n        at org.eclipse.swt.widgets.RunnableLock.run(RunnableLock.java:35)\n        at\norg.eclipse.swt.widgets.Synchronizer.runAsyncMessages(Synchronizer.java:106)\n        at org.eclipse.swt.widgets.Display.runAsyncMessages(Display.java:2760)\n        at org.eclipse.swt.widgets.Display.readAndDispatch(Display.java:2445)\n        at org.eclipse.ui.internal.Workbench.runEventLoop(Workbench.java:1443)\n        at org.eclipse.ui.internal.Workbench.runUI(Workbench.java:1414)\n        at\norg.eclipse.ui.internal.Workbench.createAndRunWorkbench(Workbench.java:271)\n        at org.eclipse.ui.PlatformUI.createAndRunWorkbench(PlatformUI.java:144)\n        at org.eclipse.ui.internal.ide.IDEApplication.run(IDEApplication.java:102)\n        at\norg.eclipse.core.internal.runtime.PlatformActivator$1.run(PlatformActivator.java:335)\n        at\norg.eclipse.core.runtime.adaptor.EclipseStarter.run(EclipseStarter.java:273)\n        at\norg.eclipse.core.runtime.adaptor.EclipseStarter.run(EclipseStarter.java:129)\n        at sun.reflect.NativeMethodAccessorImpl.invoke0(Native Method)\n        at sun.reflect.NativeMethodAccessorImpl.invoke(Unknown Source)\n        at sun.reflect.DelegatingMethodAccessorImpl.invoke(Unknown Source)\n        at java.lang.reflect.Method.invoke(Unknown Source)\n        at org.eclipse.core.launcher.Main.basicRun(Main.java:185)\n        at org.eclipse.core.launcher.Main.run(Main.java:704)\n        at org.eclipse.core.launcher.Main.main(Main.java:688)",
    "\n\n*** This bug has been marked as a duplicate of 75111 ***"
  ],
  "commentCreationDates": [
    "2004-10-04T19:40:52+02:00",
    "2004-10-04T19:46:59+02:00"
  ],
  "traces": [
    {
      "exceptionType": "java.lang.ArrayIndexOutOfBoundsException",
      "message": "4",
      "elements": [
        {
          "method": "org.eclipse.swt.custom.StyledText$ContentWidthCache.textChanged",
          "source": "StyledText.java:1407"
        },
        {
          "method": "org.eclipse.swt.custom.StyledText.handleTextChanged",
          "source": "StyledText.java:5129"
        },
        {
          "method": "org.eclipse.swt.custom.StyledText$6.textChanged",
          "source": "StyledText.java:4709"
        },
        {
          "method": "org.eclipse.ui.internal.console.IOConsoleDocumentAdapter.documentChanged",
          "source": "IOConsoleDocumentAdapter.java:306"
        },
        {
          "method": "org.eclipse.jface.text.AbstractDocument.doFireDocumentChanged2",
          "source": "AbstractDocument.java:682"
        },
        {
          "method": "org.eclipse.jface.text.AbstractDocument.doFireDocumentChanged",
          "source": "AbstractDocument.java:645"
        },
        {
          "method": "org.eclipse.jface.text.AbstractDocument.doFireDocumentChanged",
          "source": "AbstractDocument.java:630"
        },
        {
          "method": "org.eclipse.jface.text.AbstractDocument.fireDocumentChanged",
          "source": "AbstractDocument.java:707"
        },
        {
          "method": "org.eclipse.jface.text.AbstractDocument.replace",
          "source": "AbstractDocument.java:998"
        },
        {
          "method": "org.eclipse.ui.internal.console.IOConsoleDocument.replace",
          "source": "IOConsoleDocument.java:83"
        },
        {
          "method": "org.eclipse.ui.internal.console.IOConsolePartitioner$1.run",
          "source": "IOConsolePartitioner.java:525"
        },
        {
          "method": "org.eclipse.swt.widgets.RunnableLock.run",
          "source": "RunnableLock.java:35"
        },
        {
          "method": "org.eclipse.swt.widgets.Synchronizer.runAsyncMessages",
          "source": "Synchronizer.java:106"
        },
        {
          "method": "org.eclipse.swt.widgets.Display.runAsyncMessages",
          "source": "Display.java:2760"
        },
        {
          "method": "org.eclipse.swt.widgets.Display.readAndDispatch",
          "source": "Display.java:2445"
        },
        {
          "method": "org.eclipse.ui.internal.Workbench.runEventLoop",
          "source": "Workbench.java:1443"
        },
        {
          "method": "org.eclipse.ui.internal.Workbench.runUI",
          "source": "Workbench.java:1414"
        },
        {
          "method": "org.eclipse.ui.internal.Workbench.createAndRunWorkbench",
          "source": "Workbench.java:271"
        },
        {
          "method": "org.eclipse.ui.PlatformUI.createAndRunWorkbench",
          "source": "PlatformUI.java:144"
        },
        {
          "method": "org.eclipse.ui.internal.ide.IDEApplication.run",
          "source": "IDEApplication.java:102"
        },
        {
          "method": "org.eclipse.core.internal.runtime.PlatformActivator$1.run",
          "source": "PlatformActivator.java:335"
        },
        {
          "method": "org.eclipse.core.runtime.adaptor.EclipseStarter.run",
          "source": "EclipseStarter.java:273"
        },
        {
          "method": "org.eclipse.core.runtime.adaptor.EclipseStarter.run",
          "source": "EclipseStarter.java:129"
        },
        {
          "method": "sun.reflect.NativeMethodAccessorImpl.invoke0",
          "source": "Native Method"
        },
        {
          "method": "sun.reflect.NativeMethodAccessorImpl.invoke",
          "source": "Unknown Source"
        },
        {
          "method": "sun.reflect.DelegatingMethodAccessorImpl.invoke",
          "source": "Unknown Source"
        },
        {
          "method": "java.lang.reflect.Method.invoke",
          "source": "Unknown Source"
        },
        {
          "method": "org.eclipse.core.launcher.Main.basicRun",
          "source": "Main.java:185"
        },
        {
          "method": "org.eclipse.core.launcher.Main.run",
          "source": "Main.java:704"
        },
        {
          "method": "org.eclipse.core.launcher.Main.main",
          "source": "Main.java:688"
        }
      ],
      "number": 0,
      "commentIndex": 0,
      "bugId": "75583",
      "duplicateId": "75111",
      "date": "2004-10-04T19:40:52+02:00",
      "product": "Platform",
      "component": "Debug",
      "severity": "normal"
    }
  ],
  "groupId": "75111",
  "bugId": "75583",
  "duplicateId": "75111",
  "date": "2004-10-04T19:40:52+02:00",
  "product": "Platform",
  "component": "Debug",
  "severity": "normal"
}