{
  "comments": [
    "Steps to reproduce:\n\n- create new project\n- put attached file into test/ directory\n- open it in Eclipse\n- rename class name to Rand\n- save\n- rename file to Rand.java\n- position cursor on Random class name in file\n- hit Ctrl+Shift+M (automatic import)\n\nAfter performing these steps following exception is thrown and Eclipse needs to\nbe killed using external tool. What\u0027s interesting that after Eclipse is\nrestarted it\u0027s still impossible to auto-import Random class. Typing import\nstatement manually works fine.\n\n3.1M2/Linux GTK\n\n\n\nException in thread \"All Types Caching\" org.eclipse.swt.SWTException: Invalid\nthread access\n        at org.eclipse.swt.SWT.error(SWT.java:2691)\n        at org.eclipse.swt.SWT.error(SWT.java:2616)\n        at org.eclipse.swt.SWT.error(SWT.java:2587)\n        at org.eclipse.swt.widgets.Widget.error(Widget.java:379)\n        at org.eclipse.swt.widgets.Widget.checkWidget(Widget.java:316)\n        at org.eclipse.swt.widgets.Control.internal_new_GC(Control.java:1993)\n        at org.eclipse.swt.graphics.GC.\u003cinit\u003e(GC.java:115)\n        at org.eclipse.swt.graphics.GC.\u003cinit\u003e(GC.java:82)\n        at org.eclipse.jface.dialogs.Dialog.shortenText(Dialog.java:290)\n        at\norg.eclipse.jface.dialogs.ProgressMonitorDialog$ProgressMonitor.subTask(ProgressMonitorDialog.java:216)\n        at\norg.eclipse.ui.internal.progress.ProgressMonitorJobsDialog$3.subTask(ProgressMonitorJobsDialog.java:402)\n        at\norg.eclipse.core.runtime.ProgressMonitorWrapper.subTask(ProgressMonitorWrapper.java:156)\n        at\norg.eclipse.core.runtime.SubProgressMonitor.subTask(SubProgressMonitor.java:166)\n        at\norg.eclipse.core.runtime.ProgressMonitorWrapper.subTask(ProgressMonitorWrapper.java:156)\n        at\norg.eclipse.core.runtime.SubProgressMonitor.subTask(SubProgressMonitor.java:166)\n        at\norg.eclipse.core.runtime.ProgressMonitorWrapper.subTask(ProgressMonitorWrapper.java:156)\n        at\norg.eclipse.core.runtime.SubProgressMonitor.subTask(SubProgressMonitor.java:166)\n        at\norg.eclipse.jdt.internal.corext.util.AllTypesCache$DelegatedProgressMonitor.subTask(AllTypesCache.java:101)\n        at\norg.eclipse.core.runtime.ProgressMonitorWrapper.subTask(ProgressMonitorWrapper.java:156)\n        at\norg.eclipse.core.runtime.SubProgressMonitor.subTask(SubProgressMonitor.java:166)\n        at\norg.eclipse.core.runtime.ProgressMonitorWrapper.subTask(ProgressMonitorWrapper.java:156)\n        at\norg.eclipse.core.runtime.SubProgressMonitor.subTask(SubProgressMonitor.java:166)\n        at\norg.eclipse.core.runtime.SubProgressMonitor.done(SubProgressMonitor.java:133)\n        at\norg.eclipse.jdt.internal.core.search.PatternSearchJob.execute(PatternSearchJob.java:75)\n        at\norg.eclipse.jdt.internal.core.search.processing.JobManager.performConcurrentJob(JobManager.java:260)\n        at\norg.eclipse.jdt.core.search.SearchEngine.searchAllTypeNames(SearchEngine.java:870)\n        at\norg.eclipse.jdt.internal.corext.util.AllTypesCache.search(AllTypesCache.java:539)\n        at\norg.eclipse.jdt.internal.corext.util.AllTypesCache$TypeCacher.doSearchTypes(AllTypesCache.java:204)\n        at\norg.eclipse.jdt.internal.corext.util.AllTypesCache$TypeCacher.run(AllTypesCache.java:169)",
    "Created an attachment (id\u003d14988)\nTest case\n",
    "Auto-importing the Rand class from other classes in the project doesn\u0027t work\n(nothing happens, no entries in error log).",
    "Move to JDT/UI",
    "Andre, can you please comment. This got fixed. Right ?",
    "Yes, should have be fixed in M3,"
  ],
  "commentCreationDates": [
    "2004-10-04T23:36:21+02:00",
    "2004-10-04T23:37:37+02:00",
    "2004-10-04T23:44:57+02:00",
    "2004-10-05T00:08:46+02:00",
    "2004-11-17T09:53:21+01:00",
    "2004-11-17T12:00:16+01:00"
  ],
  "traces": [
    {
      "exceptionType": "org.eclipse.swt.SWTException",
      "message": "Invalid thread access",
      "elements": [
        {
          "method": "org.eclipse.swt.SWT.error",
          "source": "SWT.java:2691"
        },
        {
          "method": "org.eclipse.swt.SWT.error",
          "source": "SWT.java:2616"
        },
        {
          "method": "org.eclipse.swt.SWT.error",
          "source": "SWT.java:2587"
        },
        {
          "method": "org.eclipse.swt.widgets.Widget.error",
          "source": "Widget.java:379"
        },
        {
          "method": "org.eclipse.swt.widgets.Widget.checkWidget",
          "source": "Widget.java:316"
        },
        {
          "method": "org.eclipse.swt.widgets.Control.internal_new_GC",
          "source": "Control.java:1993"
        },
        {
          "method": "org.eclipse.swt.graphics.GC.\u003cinit\u003e",
          "source": "GC.java:115"
        },
        {
          "method": "org.eclipse.swt.graphics.GC.\u003cinit\u003e",
          "source": "GC.java:82"
        },
        {
          "method": "org.eclipse.jface.dialogs.Dialog.shortenText",
          "source": "Dialog.java:290"
        },
        {
          "method": "org.eclipse.jface.dialogs.ProgressMonitorDialog$ProgressMonitor.subTask",
          "source": "ProgressMonitorDialog.java:216"
        },
        {
          "method": "org.eclipse.ui.internal.progress.ProgressMonitorJobsDialog$3.subTask",
          "source": "ProgressMonitorJobsDialog.java:402"
        },
        {
          "method": "org.eclipse.core.runtime.ProgressMonitorWrapper.subTask",
          "source": "ProgressMonitorWrapper.java:156"
        },
        {
          "method": "org.eclipse.core.runtime.SubProgressMonitor.subTask",
          "source": "SubProgressMonitor.java:166"
        },
        {
          "method": "org.eclipse.core.runtime.ProgressMonitorWrapper.subTask",
          "source": "ProgressMonitorWrapper.java:156"
        },
        {
          "method": "org.eclipse.core.runtime.SubProgressMonitor.subTask",
          "source": "SubProgressMonitor.java:166"
        },
        {
          "method": "org.eclipse.core.runtime.ProgressMonitorWrapper.subTask",
          "source": "ProgressMonitorWrapper.java:156"
        },
        {
          "method": "org.eclipse.core.runtime.SubProgressMonitor.subTask",
          "source": "SubProgressMonitor.java:166"
        },
        {
          "method": "org.eclipse.jdt.internal.corext.util.AllTypesCache$DelegatedProgressMonitor.subTask",
          "source": "AllTypesCache.java:101"
        },
        {
          "method": "org.eclipse.core.runtime.ProgressMonitorWrapper.subTask",
          "source": "ProgressMonitorWrapper.java:156"
        },
        {
          "method": "org.eclipse.core.runtime.SubProgressMonitor.subTask",
          "source": "SubProgressMonitor.java:166"
        },
        {
          "method": "org.eclipse.core.runtime.ProgressMonitorWrapper.subTask",
          "source": "ProgressMonitorWrapper.java:156"
        },
        {
          "method": "org.eclipse.core.runtime.SubProgressMonitor.subTask",
          "source": "SubProgressMonitor.java:166"
        },
        {
          "method": "org.eclipse.core.runtime.SubProgressMonitor.done",
          "source": "SubProgressMonitor.java:133"
        },
        {
          "method": "org.eclipse.jdt.internal.core.search.PatternSearchJob.execute",
          "source": "PatternSearchJob.java:75"
        },
        {
          "method": "org.eclipse.jdt.internal.core.search.processing.JobManager.performConcurrentJob",
          "source": "JobManager.java:260"
        },
        {
          "method": "org.eclipse.jdt.core.search.SearchEngine.searchAllTypeNames",
          "source": "SearchEngine.java:870"
        },
        {
          "method": "org.eclipse.jdt.internal.corext.util.AllTypesCache.search",
          "source": "AllTypesCache.java:539"
        },
        {
          "method": "org.eclipse.jdt.internal.corext.util.AllTypesCache$TypeCacher.doSearchTypes",
          "source": "AllTypesCache.java:204"
        },
        {
          "method": "org.eclipse.jdt.internal.corext.util.AllTypesCache$TypeCacher.run",
          "source": "AllTypesCache.java:169"
        }
      ],
      "number": 0,
      "commentIndex": 0,
      "bugId": "75608",
      "date": "2004-10-04T23:36:21+02:00",
      "product": "JDT",
      "component": "UI",
      "severity": "major"
    }
  ],
  "groupId": "75608",
  "bugId": "75608",
  "date": "2004-10-04T23:36:21+02:00",
  "product": "JDT",
  "component": "UI",
  "severity": "major"
}