{
  "comments": [
    "I have installed eclipse on my red hat linux 9.0. When I tried ./eclipse I got\nthe following error. \n\n!SESSION Oct 06, 2004 16:52:17.229 ---------------------------------------------\neclipse.buildId\u003dI200406251208\njava.version\u003d1.4.2_02\njava.vendor\u003dSun Microsystems Inc.\nBootLoader constants: OS\u003dlinux, ARCH\u003dx86, WS\u003dgtk, NL\u003den_US\n\n!ENTRY org.eclipse.osgi Oct 06, 2004 16:52:17.230\n!MESSAGE Application error\n!STACK 1\njava.lang.RuntimeException: Application \"org.eclipse.ui.ide.workbench\" could not\nbe found in the registry. The\n applications available are: org.eclipse.ant.core.antRunner,\norg.eclipse.pde.build.BuildScriptGenerator, org.e\nclipse.pde.build.FetchScriptGenerator, org.eclipse.update.core.standaloneUpdate,\norg.eclipse.pde.junit.runtime\n.uitestapplication, org.eclipse.pde.junit.runtime.legacyUItestapplication,\norg.eclipse.pde.junit.runtime.coret\nestapplication.\n        at\norg.eclipse.core.internal.runtime.PlatformActivator$1.run(PlatformActivator.java:325)\n        at\norg.eclipse.core.runtime.adaptor.EclipseStarter.run(EclipseStarter.java:273)\n        at\norg.eclipse.core.runtime.adaptor.EclipseStarter.run(EclipseStarter.java:129)\n        at sun.reflect.NativeMethodAccessorImpl.invoke0(Native Method)\n        at\nsun.reflect.NativeMethodAccessorImpl.invoke(NativeMethodAccessorImpl.java:39)\n        at\nsun.reflect.DelegatingMethodAccessorImpl.invoke(DelegatingMethodAccessorImpl.java:25)\n        at java.lang.reflect.Method.invoke(Method.java:324)\n        at org.eclipse.core.launcher.Main.basicRun(Main.java:183)\n        at org.eclipse.core.launcher.Main.run(Main.java:644)\n        at org.eclipse.core.launcher.Main.main(Main.java:628)\n\n!ENTRY org.eclipse.osgi Oct 06, 2004 16:52:17.241\n!MESSAGE Bundle\nupdate@/home/mvelope/eclipse/plugins/org.eclipse.update.scheduler_3.0.0/ [3] was\nnot resolved.\n!SUBENTRY 1 org.eclipse.osgi Oct 06, 2004 16:52:17.241\n!MESSAGE Missing optionally required bundle org.eclipse.ui.ide_0.0.0.\n!SUBENTRY 1 org.eclipse.osgi Oct 06, 2004 16:52:17.241\n!MESSAGE Missing optionally required bundle org.eclipse.ui.views_0.0.0.\n!SUBENTRY 1 org.eclipse.osgi Oct 06, 2004 16:52:17.241\n!MESSAGE Missing optionally required bundle\norg.eclipse.ui.workbench.texteditor_0.0.0.\n!SUBENTRY 1 org.eclipse.osgi Oct 06, 2004 16:52:17.241\n!MESSAGE Missing optionally required bundle org.eclipse.ui.editors_0.0.0.\n\n!ENTRY org.eclipse.osgi Oct 06, 2004 16:52:17.246\n!MESSAGE Bundle update@/home/mvelope/eclipse/plugins/org.eclipse.ui.intro_3.0.0/\n[8] was not resolved.\n!SUBENTRY 1 org.eclipse.osgi Oct 06, 2004 16:52:17.246\n!MESSAGE Missing required bundle org.eclipse.ui_0.0.0.\n!SUBENTRY 1 org.eclipse.osgi Oct 06, 2004 16:52:17.246\n!MESSAGE Missing required bundle org.eclipse.help_0.0.0.\n!SUBENTRY 1 org.eclipse.osgi Oct 06, 2004 16:52:17.247\n!MESSAGE Missing required bundle org.eclipse.ui.forms_0.0.0.\n\n!ENTRY org.eclipse.osgi Oct 06, 2004 16:52:17.248\n!MESSAGE Bundle\nupdate@/home/mvelope/eclipse/plugins/org.eclipse.jdt.debug.ui_3.0.0/ [9] was not\nresolved.\n!SUBENTRY 1 org.eclipse.osgi Oct 06, 2004 16:52:17.248\n!MESSAGE Missing required bundle org.eclipse.ui.ide_0.0.0.\n!SUBENTRY 1 org.eclipse.osgi Oct 06, 2004 16:52:17.248\n!MESSAGE Missing required bundle org.eclipse.ui.workbench.texteditor_0.0.0.\n\n!SUBENTRY 1 org.eclipse.osgi Oct 06, 2004 16:52:17.249\n!MESSAGE Missing required bundle org.eclipse.ui.editors_0.0.0.\n!SUBENTRY 1 org.eclipse.osgi Oct 06, 2004 16:52:17.249\n!MESSAGE Missing required bundle org.eclipse.ui_0.0.0.\n!SUBENTRY 1 org.eclipse.osgi Oct 06, 2004 16:52:17.249\n!MESSAGE Missing required bundle org.eclipse.debug.ui_0.0.0.\n!SUBENTRY 1 org.eclipse.osgi Oct 06, 2004 16:52:17.249\n!MESSAGE Missing required bundle org.eclipse.jdt.ui_0.0.0.\n\n!ENTRY org.eclipse.osgi Oct 06, 2004 16:52:17.250\n!MESSAGE Bundle\nupdate@/home/mvelope/eclipse/plugins/org.eclipse.help.base_3.0.0/ [10] was not\nresolved.\n!SUBENTRY 1 org.eclipse.osgi Oct 06, 2004 16:52:17.250\n!MESSAGE Missing required bundle org.eclipse.help_0.0.0.\n\n!ENTRY org.eclipse.osgi Oct 06, 2004 16:52:17.250\n!MESSAGE Bundle update@/home/mvelope/eclipse/plugins/org.eclipse.sdk_3.0.0/ [14]\nwas not resolved.\n!SUBENTRY 1 org.eclipse.osgi Oct 06, 2004 16:52:17.250\n!MESSAGE Missing required bundle org.eclipse.ui_0.0.0.\n\n!ENTRY org.eclipse.osgi Oct 06, 2004 16:52:17.251\n!MESSAGE Bundle update@/home/mvelope/eclipse/plugins/org.eclipse.jdt.ui_3.0.0/\n[15] was not resolved.\n!SUBENTRY 1 org.eclipse.osgi Oct 06, 2004 16:52:17.251\n!MESSAGE Missing required bundle org.eclipse.ui_0.0.0.\n!SUBENTRY 1 org.eclipse.osgi Oct 06, 2004 16:52:17.251\n!MESSAGE Missing required bundle org.eclipse.ui.console_0.0.0.\n!SUBENTRY 1 org.eclipse.osgi Oct 06, 2004 16:52:17.252\n!MESSAGE Missing required bundle org.eclipse.help_0.0.0.\n!SUBENTRY 1 org.eclipse.osgi Oct 06, 2004 16:52:17.252\n!MESSAGE Missing required bundle org.eclipse.search_0.0.0.\n!SUBENTRY 1 org.eclipse.osgi Oct 06, 2004 16:52:17.252\n!MESSAGE Missing required bundle org.eclipse.debug.ui_0.0.0.\n!SUBENTRY 1 org.eclipse.osgi Oct 06, 2004 16:52:17.252\n!MESSAGE Missing required bundle org.eclipse.compare_0.0.0.\n!SUBENTRY 1 org.eclipse.osgi Oct 06, 2004 16:52:17.252\n!MESSAGE Missing required bundle org.eclipse.ui.workbench.texteditor_0.0.0.\n\n!SUBENTRY 1 org.eclipse.osgi Oct 06, 2004 16:52:17.252\n!MESSAGE Missing required bundle org.eclipse.ui.ide_0.0.0.\n!SUBENTRY 1 org.eclipse.osgi Oct 06, 2004 16:52:17.252\n!MESSAGE Missing required bundle org.eclipse.ui.views_0.0.0.\n!SUBENTRY 1 org.eclipse.osgi Oct 06, 2004 16:52:17.253\n!MESSAGE Missing required bundle org.eclipse.ui.editors_0.0.0.\n!SUBENTRY 1 org.eclipse.osgi Oct 06, 2004 16:52:17.253\n!MESSAGE Missing required bundle org.eclipse.ltk.ui.refactoring_0.0.0.\n\n!ENTRY org.eclipse.osgi Oct 06, 2004 16:52:17.253\n!MESSAGE Bundle\nupdate@/home/mvelope/eclipse/plugins/org.eclipse.ui.workbench_3.0.0/ [19] was\nnot resolved.\n!SUBENTRY 1 org.eclipse.osgi Oct 06, 2004 16:52:17.253\n!MESSAGE Missing required bundle org.eclipse.help_0.0.0.\n\n!ENTRY org.eclipse.osgi Oct 06, 2004 16:52:17.254\n!MESSAGE Bundle update@/home/mvelope/eclipse/plugins/org.eclipse.ui.views_3.0.0/\n[22] was not resolved.\n!SUBENTRY 1 org.eclipse.osgi Oct 06, 2004 16:52:17.254\n!MESSAGE Missing required bundle org.eclipse.help_0.0.0.\n!SUBENTRY 1 org.eclipse.osgi Oct 06, 2004 16:52:17.254\n!MESSAGE Missing required bundle org.eclipse.ui_0.0.0.\n\n!ENTRY org.eclipse.osgi Oct 06, 2004 16:52:17.255\n!MESSAGE Bundle update@/home/mvelope/eclipse/plugins/org.eclipse.pde.ui_3.0.0/\n[23] was not resolved.\n!SUBENTRY 1 org.eclipse.osgi Oct 06, 2004 16:52:17.255\n!MESSAGE Missing required bundle org.eclipse.ui.ide_0.0.0.\n!SUBENTRY 1 org.eclipse.osgi Oct 06, 2004 16:52:17.255\n!MESSAGE Missing required bundle org.eclipse.ui.views_0.0.0.\n!SUBENTRY 1 org.eclipse.osgi Oct 06, 2004 16:52:17.256\n!MESSAGE Missing required bundle org.eclipse.ui.workbench.texteditor_0.0.0.\n!SUBENTRY 1 org.eclipse.osgi Oct 06, 2004 16:52:17.256\n!MESSAGE Missing required bundle org.eclipse.ui.editors_0.0.0.\n!SUBENTRY 1 org.eclipse.osgi Oct 06, 2004 16:52:17.256\n!MESSAGE Missing required bundle org.eclipse.debug.ui_0.0.0.\n!SUBENTRY 1 org.eclipse.osgi Oct 06, 2004 16:52:17.260\n!MESSAGE Missing required bundle org.eclipse.help.base_0.0.0.\n\n!SUBENTRY 1 org.eclipse.osgi Oct 06, 2004 16:52:17.260\n!MESSAGE Missing required bundle org.eclipse.jdt.debug.ui_0.0.0.\n!SUBENTRY 1 org.eclipse.osgi Oct 06, 2004 16:52:17.262\n!MESSAGE Missing required bundle org.eclipse.jdt.ui_0.0.0.\n!SUBENTRY 1 org.eclipse.osgi Oct 06, 2004 16:52:17.262\n!MESSAGE Missing required bundle org.eclipse.search_0.0.0.\n!SUBENTRY 1 org.eclipse.osgi Oct 06, 2004 16:52:17.262\n!MESSAGE Missing required bundle org.eclipse.ui_0.0.0.\n!SUBENTRY 1 org.eclipse.osgi Oct 06, 2004 16:52:17.268\n!MESSAGE Missing required bundle org.eclipse.ui.forms_0.0.0.\n!SUBENTRY 1 org.eclipse.osgi Oct 06, 2004 16:52:17.268\n!MESSAGE Missing required bundle org.eclipse.ant.ui_0.0.0.\n!SUBENTRY 1 org.eclipse.osgi Oct 06, 2004 16:52:17.269\n!MESSAGE Missing required bundle org.eclipse.jdt.junit_0.0.0.\n!SUBENTRY 1 org.eclipse.osgi Oct 06, 2004 16:52:17.270\n!MESSAGE Missing required bundle org.eclipse.ui.intro_0.0.0.\n!SUBENTRY 1 org.eclipse.osgi Oct 06, 2004 16:52:17.270\n!MESSAGE Missing required bundle org.eclipse.ui.cheatsheets_0.0.0.\n\n!ENTRY org.eclipse.osgi Oct 06, 2004 16:52:17.270\n!MESSAGE Bundle update@/home/mvelope/eclipse/plugins/org.eclipse.ui.ide_3.0.0/\n[26] was not resolved.\n!SUBENTRY 1 org.eclipse.osgi Oct 06, 2004 16:52:17.271\n!MESSAGE Missing required bundle org.eclipse.help_0.0.0.\n!SUBENTRY 1 org.eclipse.osgi Oct 06, 2004 16:52:17.271\n!MESSAGE Missing required bundle org.eclipse.ui_0.0.0.\n!SUBENTRY 1 org.eclipse.osgi Oct 06, 2004 16:52:17.271\n!MESSAGE Missing required bundle org.eclipse.ui.views_0.0.0.\n!SUBENTRY 1 org.eclipse.osgi Oct 06, 2004 16:52:17.271\n!MESSAGE Missing required bundle org.eclipse.update.ui_0.0.0.\n\n!ENTRY org.eclipse.osgi Oct 06, 2004 16:52:17.272\n!MESSAGE Bundle\nupdate@/home/mvelope/eclipse/plugins/org.eclipse.ui.externaltools_3.0.0/ [28]\nwas not resolved\n.\n!SUBENTRY 1 org.eclipse.osgi Oct 06, 2004 16:52:17.272\n!MESSAGE Missing optionally required bundle org.eclipse.ui.ide_0.0.0.\n\n!SUBENTRY 1 org.eclipse.osgi Oct 06, 2004 16:52:17.272\n!MESSAGE Missing optionally required bundle org.eclipse.ui.views_0.0.0.\n!SUBENTRY 1 org.eclipse.osgi Oct 06, 2004 16:52:17.273\n!MESSAGE Missing optionally required bundle\norg.eclipse.ui.workbench.texteditor_0.0.0.\n!SUBENTRY 1 org.eclipse.osgi Oct 06, 2004 16:52:17.273\n!MESSAGE Missing optionally required bundle org.eclipse.ui.editors_0.0.0.\n!SUBENTRY 1 org.eclipse.osgi Oct 06, 2004 16:52:17.273\n!MESSAGE Missing required bundle org.eclipse.ui_0.0.0.\n!SUBENTRY 1 org.eclipse.osgi Oct 06, 2004 16:52:17.273\n!MESSAGE Missing required bundle org.eclipse.debug.ui_0.0.0.\n\n!ENTRY org.eclipse.osgi Oct 06, 2004 16:52:17.273\n!MESSAGE Bundle\nupdate@/home/mvelope/eclipse/plugins/org.eclipse.pde.doc.user_3.0.0/ [30] was\nnot resolved.\n!SUBENTRY 1 org.eclipse.osgi Oct 06, 2004 16:52:17.275\n!MESSAGE Missing required bundle org.eclipse.help_0.0.0.\n\n!ENTRY org.eclipse.osgi Oct 06, 2004 16:52:17.280\n!MESSAGE Bundle update@/home/mvelope/eclipse/plugins/org.eclipse.help.ide_3.0.0/\n[31] was not resolved.\n!SUBENTRY 1 org.eclipse.osgi Oct 06, 2004 16:52:17.280\n!MESSAGE Missing required bundle org.eclipse.help.base_0.0.0.\n!SUBENTRY 1 org.eclipse.osgi Oct 06, 2004 16:52:17.280\n!MESSAGE Missing required bundle org.eclipse.help.ui_0.0.0.\n!SUBENTRY 1 org.eclipse.osgi Oct 06, 2004 16:52:17.281\n!MESSAGE Missing required bundle org.eclipse.search_0.0.0.\n!SUBENTRY 1 org.eclipse.osgi Oct 06, 2004 16:52:17.281\n!MESSAGE Missing required bundle org.eclipse.ui_0.0.0.\n!SUBENTRY 1 org.eclipse.osgi Oct 06, 2004 16:52:17.287\n!MESSAGE Missing required bundle org.eclipse.ui.ide_0.0.0.\n\n!ENTRY org.eclipse.osgi Oct 06, 2004 16:52:17.288\n!MESSAGE Bundle\nupdate@/home/mvelope/eclipse/plugins/org.eclipse.ltk.ui.refactoring_3.0.0/ [32]\nwas not resolv\ned.\n!SUBENTRY 1 org.eclipse.osgi Oct 06, 2004 16:52:17.288\n!MESSAGE Missing required bundle org.eclipse.ui_0.0.0.\n!SUBENTRY 1 org.eclipse.osgi Oct 06, 2004 16:52:17.288\n\nMESSAGE Missing required bundle org.eclipse.compare_0.0.0.\n!SUBENTRY 1 org.eclipse.osgi Oct 06, 2004 16:52:17.288\n!MESSAGE Missing required bundle org.eclipse.ui.workbench.texteditor_0.0.0.\n\n!ENTRY org.eclipse.osgi Oct 06, 2004 16:52:17.289\n!MESSAGE Bundle update@/home/mvelope/eclipse/plugins/org.eclipse.ant.ui_3.0.0/\n[33] was not resolved.\n!SUBENTRY 1 org.eclipse.osgi Oct 06, 2004 16:52:17.289\n!MESSAGE Missing optionally required bundle org.eclipse.ui.ide_0.0.0.\n!SUBENTRY 1 org.eclipse.osgi Oct 06, 2004 16:52:17.289\n!MESSAGE Missing optionally required bundle org.eclipse.ui.views_0.0.0.\n!SUBENTRY 1 org.eclipse.osgi Oct 06, 2004 16:52:17.289\n!MESSAGE Missing optionally required bundle\norg.eclipse.ui.workbench.texteditor_0.0.0.\n!SUBENTRY 1 org.eclipse.osgi Oct 06, 2004 16:52:17.289\n!MESSAGE Missing optionally required bundle org.eclipse.ui.editors_0.0.0.\n!SUBENTRY 1 org.eclipse.osgi Oct 06, 2004 16:52:17.289\n!MESSAGE Missing required bundle org.eclipse.ui.externaltools_0.0.0.\n!SUBENTRY 1 org.eclipse.osgi Oct 06, 2004 16:52:17.290\n!MESSAGE Missing required bundle org.eclipse.ui_0.0.0.\n!SUBENTRY 1 org.eclipse.osgi Oct 06, 2004 16:52:17.290\n!MESSAGE Missing required bundle org.eclipse.ui.console_0.0.0.\n!SUBENTRY 1 org.eclipse.osgi Oct 06, 2004 16:52:17.290\n!MESSAGE Missing required bundle org.eclipse.debug.ui_0.0.0.\n!SUBENTRY 1 org.eclipse.osgi Oct 06, 2004 16:52:17.290\n!MESSAGE Missing required bundle org.eclipse.jdt.ui_0.0.0.\n!SUBENTRY 1 org.eclipse.osgi Oct 06, 2004 16:52:17.290\n!MESSAGE Missing required bundle org.eclipse.jdt.debug.ui_0.0.0.\n\n!ENTRY org.eclipse.osgi Oct 06, 2004 16:52:17.293\n!MESSAGE Bundle update@/home/mvelope/eclipse/plugins/org.eclipse.compare_3.0.0/\n[35] was not resolved.\n!SUBENTRY 1 org.eclipse.osgi Oct 06, 2004 16:52:17.295\n!MESSAGE Missing required bundle org.eclipse.ui_0.0.0.\n!SUBENTRY 1 org.eclipse.osgi Oct 06, 2004 16:52:17.295\n!MESSAGE Missing required bundle org.eclipse.ui.ide_0.0.0.\n!SUBENTRY 1 org.eclipse.osgi Oct 06, 2004 16:52:17.295\n!MESSAGE Missing required bundle org.eclipse.ui.views_0.0.0.\n\n!SUBENTRY 1 org.eclipse.osgi Oct 06, 2004 16:52:17.295\n!MESSAGE Missing required bundle org.eclipse.ui.workbench.texteditor_0.0.0.\n\n!ENTRY org.eclipse.osgi Oct 06, 2004 16:52:17.296\n!MESSAGE Bundle\nupdate@/home/mvelope/eclipse/plugins/org.eclipse.pde.runtime_3.0.0/ [37] was not\nresolved.\n!SUBENTRY 1 org.eclipse.osgi Oct 06, 2004 16:52:17.296\n!MESSAGE Missing required bundle org.eclipse.ui_0.0.0.\n!SUBENTRY 1 org.eclipse.osgi Oct 06, 2004 16:52:17.296\n!MESSAGE Missing required bundle org.eclipse.ui.views_0.0.0.\n\n!ENTRY org.eclipse.osgi Oct 06, 2004 16:52:17.297\n!MESSAGE Bundle\nupdate@/home/mvelope/eclipse/plugins/org.eclipse.update.ui_3.0.0/ [43] was not\nresolved.\n!SUBENTRY 1 org.eclipse.osgi Oct 06, 2004 16:52:17.297\n!MESSAGE Missing required bundle org.eclipse.ui_0.0.0.\n!SUBENTRY 1 org.eclipse.osgi Oct 06, 2004 16:52:17.297\n!MESSAGE Missing required bundle org.eclipse.help.base_0.0.0.\n!SUBENTRY 1 org.eclipse.osgi Oct 06, 2004 16:52:17.298\n!MESSAGE Missing required bundle org.eclipse.ui.forms_0.0.0.\n\n!ENTRY org.eclipse.osgi Oct 06, 2004 16:52:17.298\n!MESSAGE Bundle\nupdate@/home/mvelope/eclipse/plugins/org.eclipse.help.webapp_3.0.0/ [44] was not\nresolved.\n!SUBENTRY 1 org.eclipse.osgi Oct 06, 2004 16:52:17.298\n!MESSAGE Missing required bundle org.eclipse.help.base_0.0.0.\n\n!ENTRY org.eclipse.osgi Oct 06, 2004 16:52:17.299\n!MESSAGE Bundle\nupdate@/home/mvelope/eclipse/plugins/org.eclipse.team.cvs.ssh2_3.0.0/ [46] was\nnot resolved.\n!SUBENTRY 1 org.eclipse.osgi Oct 06, 2004 16:52:17.299\n!MESSAGE Missing required bundle org.eclipse.ui_0.0.0.\n!SUBENTRY 1 org.eclipse.osgi Oct 06, 2004 16:52:17.299\n!MESSAGE Missing required bundle org.eclipse.team.cvs.ssh_0.0.0.\n\n!ENTRY org.eclipse.osgi Oct 06, 2004 16:52:17.300\n!MESSAGE Bundle update@/home/mvelope/eclipse/plugins/org.eclipse.help.ui_3.0.0/\n[47] was not resolved.\n!SUBENTRY 1 org.eclipse.osgi Oct 06, 2004 16:52:17.300\n!MESSAGE Missing required bundle org.eclipse.help.base_0.0.0.\n\n!SUBENTRY 1 org.eclipse.osgi Oct 06, 2004 16:52:17.300\n!MESSAGE Missing required bundle org.eclipse.ui_0.0.0.\n\n!ENTRY org.eclipse.osgi Oct 06, 2004 16:52:17.301\n!MESSAGE Bundle update@/home/mvelope/eclipse/plugins/org.eclipse.search_3.0.0/\n[50] was not resolved.\n!SUBENTRY 1 org.eclipse.osgi Oct 06, 2004 16:52:17.301\n!MESSAGE Missing required bundle org.eclipse.ui_0.0.0.\n!SUBENTRY 1 org.eclipse.osgi Oct 06, 2004 16:52:17.301\n!MESSAGE Missing required bundle org.eclipse.ui.ide_0.0.0.\n!SUBENTRY 1 org.eclipse.osgi Oct 06, 2004 16:52:17.302\n!MESSAGE Missing required bundle org.eclipse.ui.workbench.texteditor_0.0.0.\n!SUBENTRY 1 org.eclipse.osgi Oct 06, 2004 16:52:17.302\n!MESSAGE Missing required bundle org.eclipse.ui.editors_0.0.0.\n\n!ENTRY org.eclipse.osgi Oct 06, 2004 16:52:17.304\n!MESSAGE Bundle\nupdate@/home/mvelope/eclipse/plugins/org.eclipse.ui.console_3.0.0/ [52] was not\nresolved.\n!SUBENTRY 1 org.eclipse.osgi Oct 06, 2004 16:52:17.304\n!MESSAGE Missing required bundle org.eclipse.ui_0.0.0.\n!SUBENTRY 1 org.eclipse.osgi Oct 06, 2004 16:52:17.304\n!MESSAGE Missing required bundle org.eclipse.help_0.0.0.\n!SUBENTRY 1 org.eclipse.osgi Oct 06, 2004 16:52:17.304\n!MESSAGE Missing required bundle org.eclipse.ui.workbench.texteditor_0.0.0.\n\n!ENTRY org.eclipse.osgi Oct 06, 2004 16:52:17.307\n!MESSAGE Bundle update@/home/mvelope/eclipse/plugins/org.eclipse.ui_3.0.0/ [55]\nwas not resolved.\n!SUBENTRY 1 org.eclipse.osgi Oct 06, 2004 16:52:17.307\n!MESSAGE Missing required bundle org.eclipse.help_0.0.0.\n!SUBENTRY 1 org.eclipse.osgi Oct 06, 2004 16:52:17.307\n!MESSAGE Missing required bundle org.eclipse.ui.workbench_0.0.0.\n\n!ENTRY org.eclipse.osgi Oct 06, 2004 16:52:17.308\n!MESSAGE Bundle\nupdate@/home/mvelope/eclipse/plugins/org.eclipse.team.cvs.ui_3.0.0/ [56] was not\nresolved.\n!SUBENTRY 1 org.eclipse.osgi Oct 06, 2004 16:52:17.308\n!MESSAGE Missing optionally required bundle org.eclipse.ui.ide_0.0.0.\n!SUBENTRY 1 org.eclipse.osgi Oct 06, 2004 16:52:17.308\n\n!MESSAGE Missing optionally required bundle org.eclipse.ui.views_0.0.0.\n!SUBENTRY 1 org.eclipse.osgi Oct 06, 2004 16:52:17.308\n!MESSAGE Missing optionally required bundle\norg.eclipse.ui.workbench.texteditor_0.0.0.\n!SUBENTRY 1 org.eclipse.osgi Oct 06, 2004 16:52:17.308\n!MESSAGE Missing optionally required bundle org.eclipse.ui.editors_0.0.0.\n!SUBENTRY 1 org.eclipse.osgi Oct 06, 2004 16:52:17.308\n!MESSAGE Missing required bundle org.eclipse.ui_0.0.0.\n!SUBENTRY 1 org.eclipse.osgi Oct 06, 2004 16:52:17.308\n!MESSAGE Missing required bundle org.eclipse.ui.console_0.0.0.\n!SUBENTRY 1 org.eclipse.osgi Oct 06, 2004 16:52:17.308\n!MESSAGE Missing required bundle org.eclipse.team.ui_0.0.0.\n!SUBENTRY 1 org.eclipse.osgi Oct 06, 2004 16:52:17.309\n!MESSAGE Missing required bundle org.eclipse.compare_0.0.0.\n\n!ENTRY org.eclipse.osgi Oct 06, 2004 16:52:17.309\n!MESSAGE Bundle\nupdate@/home/mvelope/eclipse/plugins/org.eclipse.ui.presentations.r21_3.0.0/\n[57] was not reso\nlved.\n!SUBENTRY 1 org.eclipse.osgi Oct 06, 2004 16:52:17.309\n!MESSAGE Missing required bundle org.eclipse.ui_0.0.0.\n\n!ENTRY org.eclipse.osgi Oct 06, 2004 16:52:17.310\n!MESSAGE Bundle update@/home/mvelope/eclipse/plugins/org.eclipse.team.ui_3.0.0/\n[67] was not resolved.\n!SUBENTRY 1 org.eclipse.osgi Oct 06, 2004 16:52:17.310\n!MESSAGE Missing optionally required bundle org.eclipse.ui.ide_0.0.0.\n!SUBENTRY 1 org.eclipse.osgi Oct 06, 2004 16:52:17.310\n!MESSAGE Missing optionally required bundle org.eclipse.ui.views_0.0.0.\n!SUBENTRY 1 org.eclipse.osgi Oct 06, 2004 16:52:17.310\n!MESSAGE Missing optionally required bundle\norg.eclipse.ui.workbench.texteditor_0.0.0.\n!SUBENTRY 1 org.eclipse.osgi Oct 06, 2004 16:52:17.310\n!MESSAGE Missing optionally required bundle org.eclipse.ui.editors_0.0.0.\n!SUBENTRY 1 org.eclipse.osgi Oct 06, 2004 16:52:17.310\n!MESSAGE Missing required bundle org.eclipse.ui_0.0.0.\n!SUBENTRY 1 org.eclipse.osgi Oct 06, 2004 16:52:17.310\n!MESSAGE Missing required bundle org.eclipse.compare_0.0.0.\n!SUBENTRY 1 org.eclipse.osgi Oct 06, 2004 16:52:17.311\n!MESSAGE Missing required bundle org.eclipse.ui.forms_0.0.0.\n\n!ENTRY org.eclipse.osgi Oct 06, 2004 16:52:17.312\n!MESSAGE Bundle\nupdate@/home/mvelope/eclipse/plugins/org.eclipse.jdt.junit_3.0.0/ [68] was not\nresolved.\n!SUBENTRY 1 org.eclipse.osgi Oct 06, 2004 16:52:17.312\n!MESSAGE Missing required bundle org.eclipse.ui.ide_0.0.0.\n!SUBENTRY 1 org.eclipse.osgi Oct 06, 2004 16:52:17.312\n!MESSAGE Missing required bundle org.eclipse.ui.views_0.0.0.\n!SUBENTRY 1 org.eclipse.osgi Oct 06, 2004 16:52:17.312\n!MESSAGE Missing required bundle org.eclipse.ui.workbench.texteditor_0.0.0.\n!SUBENTRY 1 org.eclipse.osgi Oct 06, 2004 16:52:17.313\n!MESSAGE Missing required bundle org.eclipse.ui.editors_0.0.0.\n!SUBENTRY 1 org.eclipse.osgi Oct 06, 2004 16:52:17.313\n!MESSAGE Missing required bundle org.eclipse.ui_0.0.0.\n!SUBENTRY 1 org.eclipse.osgi Oct 06, 2004 16:52:17.313\n!MESSAGE Missing required bundle org.eclipse.debug.ui_0.0.0.\n!SUBENTRY 1 org.eclipse.osgi Oct 06, 2004 16:52:17.313\n!MESSAGE Missing required bundle org.eclipse.jdt.ui_0.0.0.\n!SUBENTRY 1 org.eclipse.osgi Oct 06, 2004 16:52:17.313\n!MESSAGE Missing required bundle org.eclipse.jdt.debug.ui_0.0.0.\n!SUBENTRY 1 org.eclipse.osgi Oct 06, 2004 16:52:17.313\n!MESSAGE Missing required bundle org.eclipse.compare_0.0.0.\n\n!ENTRY org.eclipse.osgi Oct 06, 2004 16:52:17.314\n!MESSAGE Bundle\nupdate@/home/mvelope/eclipse/plugins/org.eclipse.ui.editors_3.0.0/ [69] was not\nresolved.\n!SUBENTRY 1 org.eclipse.osgi Oct 06, 2004 16:52:17.314\n!MESSAGE Missing required bundle org.eclipse.ui.ide_0.0.0.\n!SUBENTRY 1 org.eclipse.osgi Oct 06, 2004 16:52:17.314\n!MESSAGE Missing required bundle org.eclipse.ui.workbench.texteditor_0.0.0.\n!SUBENTRY 1 org.eclipse.osgi Oct 06, 2004 16:52:17.314\n!MESSAGE Missing required bundle org.eclipse.ui_0.0.0.\n\n!ENTRY org.eclipse.osgi Oct 06, 2004 16:52:17.315\n!MESSAGE Bundle\nupdate@/home/mvelope/eclipse/plugins/org.eclipse.ui.workbench.texteditor_3.0.0/\n[74] was not resolved.\n\n!MESSAGE Missing required bundle org.eclipse.ui_0.0.0.\n\n!ENTRY org.eclipse.osgi Oct 06, 2004 16:52:17.315\n!MESSAGE Bundle\nupdate@/home/mvelope/eclipse/plugins/org.eclipse.ui.workbench.texteditor_3.0.0/\n[74] was not r\nesolved.\n!SUBENTRY 1 org.eclipse.osgi Oct 06, 2004 16:52:17.315\n!MESSAGE Missing required bundle org.eclipse.ui_0.0.0.\n\n!ENTRY org.eclipse.osgi Oct 06, 2004 16:52:17.317\n!MESSAGE Bundle\nupdate@/home/mvelope/eclipse/plugins/org.eclipse.ui.cheatsheets_3.0.0/ [75] was\nnot resolved.\n!SUBENTRY 1 org.eclipse.osgi Oct 06, 2004 16:52:17.318\n!MESSAGE Missing required bundle org.eclipse.ui_0.0.0.\n!SUBENTRY 1 org.eclipse.osgi Oct 06, 2004 16:52:17.318\n!MESSAGE Missing required bundle org.eclipse.ui.forms_0.0.0.\n!SUBENTRY 1 org.eclipse.osgi Oct 06, 2004 16:52:17.318\n!MESSAGE Missing required bundle org.eclipse.help_0.0.0.\n\n!ENTRY org.eclipse.osgi Oct 06, 2004 16:52:17.318\n!MESSAGE Bundle\nupdate@/home/mvelope/eclipse/plugins/org.eclipse.platform.doc.isv_3.0.0/ [76]\nwas not resolved\n.\n!SUBENTRY 1 org.eclipse.osgi Oct 06, 2004 16:52:17.318\n!MESSAGE Missing required bundle org.eclipse.help_0.0.0.\n!SUBENTRY 1 org.eclipse.osgi Oct 06, 2004 16:52:17.318\n!MESSAGE Missing required bundle org.eclipse.ui_0.0.0.\n\n!ENTRY org.eclipse.osgi Oct 06, 2004 16:52:17.319\n!MESSAGE Bundle\nupdate@/home/mvelope/eclipse/plugins/org.eclipse.ui.workbench.compatibility_3.0.0/\n[78] was no\nt resolved.\n!SUBENTRY 1 org.eclipse.osgi Oct 06, 2004 16:52:17.319\n!MESSAGE Missing host org.eclipse.ui.workbench_[3.0.0,4.0.0).\n\n!ENTRY org.eclipse.osgi Oct 06, 2004 16:52:17.319\n!MESSAGE Bundle update@/home/mvelope/eclipse/plugins/org.eclipse.ui.forms_3.0.0/\n[81] was not resolved.\n!SUBENTRY 1 org.eclipse.osgi Oct 06, 2004 16:52:17.320\n!MESSAGE Missing required bundle org.eclipse.ui_0.0.0.",
    "*** Bug 75707 has been marked as a duplicate of this bug. ***",
    "Can you tell me what build you downloaded?  Was it the full SDK, an RCP build,\netc?  From that log it almost looks like the entire build wasn\u0027t installed. \nPunting to core for comment on the log.",
    "concur on log analysis.  Looks like something wrong on the installation.  \nOriginator should reinstall and try again.  Please reopen if you still have a \nproblem."
  ],
  "commentCreationDates": [
    "2004-10-06T13:46:59+02:00",
    "2004-10-06T14:12:50+02:00",
    "2004-10-07T02:13:53+02:00",
    "2004-10-07T17:34:36+02:00"
  ],
  "traces": [
    {
      "exceptionType": "java.lang.RuntimeException",
      "message": "Application \"org.eclipse.ui.ide.workbench\" could not be found in the registry. The  applications available are: org.eclipse.ant.core.antRunner, org.eclipse.pde.build.BuildScriptGenerator, org.e clipse.pde.build.FetchScriptGenerator, org.eclipse.update.core.standaloneUpdate, org.eclipse.pde.junit.runtime .uitestapplication, org.eclipse.pde.junit.runtime.legacyUItestapplication, org.eclipse.pde.junit.runtime.coret estapplication.",
      "elements": [
        {
          "method": "org.eclipse.core.internal.runtime.PlatformActivator$1.run",
          "source": "PlatformActivator.java:325"
        },
        {
          "method": "org.eclipse.core.runtime.adaptor.EclipseStarter.run",
          "source": "EclipseStarter.java:273"
        },
        {
          "method": "org.eclipse.core.runtime.adaptor.EclipseStarter.run",
          "source": "EclipseStarter.java:129"
        },
        {
          "method": "sun.reflect.NativeMethodAccessorImpl.invoke0",
          "source": "Native Method"
        },
        {
          "method": "sun.reflect.NativeMethodAccessorImpl.invoke",
          "source": "NativeMethodAccessorImpl.java:39"
        },
        {
          "method": "sun.reflect.DelegatingMethodAccessorImpl.invoke",
          "source": "DelegatingMethodAccessorImpl.java:25"
        },
        {
          "method": "java.lang.reflect.Method.invoke",
          "source": "Method.java:324"
        },
        {
          "method": "org.eclipse.core.launcher.Main.basicRun",
          "source": "Main.java:183"
        },
        {
          "method": "org.eclipse.core.launcher.Main.run",
          "source": "Main.java:644"
        },
        {
          "method": "org.eclipse.core.launcher.Main.main",
          "source": "Main.java:628"
        }
      ],
      "number": 0,
      "commentIndex": 0,
      "bugId": "75706",
      "date": "2004-10-06T13:46:59+02:00",
      "product": "Platform",
      "component": "Runtime",
      "severity": "blocker"
    }
  ],
  "groupId": "75706",
  "bugId": "75706",
  "date": "2004-10-06T13:46:59+02:00",
  "product": "Platform",
  "component": "Runtime",
  "severity": "blocker"
}