{
  "comments": [
    "build i1005\n\nI had a workspace from i0928 and I downloaded and installed build i1005. On\nfirst startup, I got the following in my log file. I was also prompted with an\nError dialog saying that the workbench layout could not be restored. It reset\nall my customized perspectives, closed all my editors, and left only the\nResource perspective open.\n\nI believe the editor on top was on a class file in an external library. (whose\nlocation would have changed when I did the upgrade)\n\nosgi\u003e !SESSION Oct 06, 2004 14:06:43.626\n---------------------------------------------\neclipse.buildId\u003dI200410050800\njava.fullversion\u003dJ2RE 1.4.2 IBM J9 2.2 Windows XP x86-32 j9n142-20040915 (JIT\nenabled)\nJ9VM - 20040914_1123_lHdSMR\nJIT  - r7_level20040912_1800\nBootLoader constants: OS\u003dwin32, ARCH\u003dx86, WS\u003dwin32, NL\u003den_US\nCommand-line arguments: -showlocation\n\n!ENTRY org.eclipse.ui 4 4 Oct 06, 2004 14:06:43.636\n!MESSAGE Exception creating editor: The classfile is not on the classpath\nException creating editor: The classfile is not on the classpath\n\n!ENTRY org.eclipse.core.runtime 4 2 Oct 06, 2004 14:06:43.686\n!MESSAGE Problems occurred when invoking code from plug-in:\n\"org.eclipse.core.runtime\".\n!STACK 0\norg.eclipse.jface.util.Assert$AssertionFailedException: Assertion failed:\n        at org.eclipse.jface.util.Assert.isTrue(Assert.java:174)\n        at org.eclipse.jface.util.Assert.isTrue(Assert.java:159)\n        at\norg.eclipse.ui.internal.presentations.newapi.PresentablePartFolder.getTab(PresentablePartFolder.java:376)\n        at\norg.eclipse.ui.internal.presentations.newapi.PresentablePartFolder.select(PresentablePartFolder.java:275)\n        at\norg.eclipse.ui.internal.presentations.newapi.LeftToRightTabOrder.select(LeftToRightTabOrder.java:65)\n        at\norg.eclipse.ui.internal.presentations.newapi.TabbedStackPresentation.selectPart(TabbedStackPresentation.java:378)\n        at\norg.eclipse.ui.internal.PartStack.refreshPresentationSelection(PartStack.java:1025)\n        at org.eclipse.ui.internal.PartStack.setSelection(PartStack.java:999)\n        at org.eclipse.ui.internal.PartStack.showPart(PartStack.java:1174)\n        at org.eclipse.ui.internal.PartStack.add(PartStack.java:359)\n        at org.eclipse.ui.internal.EditorStack.add(EditorStack.java:109)\n        at\norg.eclipse.ui.internal.EditorSashContainer.addEditor(EditorSashContainer.java:63)\n        at\norg.eclipse.ui.internal.EditorAreaHelper.openEditor(EditorAreaHelper.java:281)\n        at org.eclipse.ui.internal.EditorManager$4.run(EditorManager.java:787)\n        at org.eclipse.swt.custom.BusyIndicator.showWhile(BusyIndicator.java:69)\n        at\norg.eclipse.ui.internal.EditorManager.createEditorTab(EditorManager.java:773)\n        at\norg.eclipse.ui.internal.EditorManager.restoreEditorState(EditorManager.java:1721)\n        at\norg.eclipse.ui.internal.EditorManager.restoreState(EditorManager.java:999)\n        at\norg.eclipse.ui.internal.WorkbenchPage.restoreState(WorkbenchPage.java:2474)\n        at\norg.eclipse.ui.internal.WorkbenchWindow.restoreState(WorkbenchWindow.java:1606)\n        at org.eclipse.ui.internal.Workbench.restoreState(Workbench.java:1290)\n        at org.eclipse.ui.internal.Workbench.access$10(Workbench.java:1246)\n        at org.eclipse.ui.internal.Workbench$13.run(Workbench.java:1150)\n        at\norg.eclipse.core.internal.runtime.InternalPlatform.run(InternalPlatform.java:616)\n        at org.eclipse.core.runtime.Platform.run(Platform.java:747)\n        at org.eclipse.ui.internal.Workbench.restoreState(Workbench.java:1084)\n        at\norg.eclipse.ui.internal.WorkbenchConfigurer.restoreState(WorkbenchConfigurer.java:171)\n        at\norg.eclipse.ui.application.WorkbenchAdvisor.openWindows(WorkbenchAdvisor.java:655)\n        at org.eclipse.ui.internal.Workbench.init(Workbench.java:860)\n        at org.eclipse.ui.internal.Workbench.runUI(Workbench.java:1391)\n        at\norg.eclipse.ui.internal.Workbench.createAndRunWorkbench(Workbench.java:271)\n        at org.eclipse.ui.PlatformUI.createAndRunWorkbench(PlatformUI.java:144)\n        at org.eclipse.ui.internal.ide.IDEApplication.run(IDEApplication.java:102)\n        at\norg.eclipse.core.internal.runtime.PlatformActivator$1.run(PlatformActivator.java:335)\n        at\norg.eclipse.core.runtime.adaptor.EclipseStarter.run(EclipseStarter.java:273)\n        at\norg.eclipse.core.runtime.adaptor.EclipseStarter.run(EclipseStarter.java:129)\n        at sun.reflect.NativeMethodAccessorImpl.invoke0(Native Method)\n        at\nsun.reflect.NativeMethodAccessorImpl.invoke(NativeMethodAccessorImpl.java:85)\n        at\nsun.reflect.NativeMethodAccessorImpl.invoke(NativeMethodAccessorImpl.java:58)\n        at\nsun.reflect.DelegatingMethodAccessorImpl.invoke(DelegatingMethodAccessorImpl.java:60)\n        at java.lang.reflect.Method.invoke(Method.java:391)\n        at org.eclipse.core.launcher.Main.basicRun(Main.java:185)\n        at org.eclipse.core.launcher.Main.run(Main.java:684)\n        at org.eclipse.core.launcher.Main.main(Main.java:668)",
    "fixed by the patch to bug 87468"
  ],
  "commentCreationDates": [
    "2004-10-06T20:19:17+02:00",
    "2005-03-12T09:07:27+01:00"
  ],
  "traces": [
    {
      "exceptionType": "org.eclipse.jface.util.Assert$AssertionFailedException",
      "message": "Assertion failed:",
      "elements": [
        {
          "method": "org.eclipse.jface.util.Assert.isTrue",
          "source": "Assert.java:174"
        },
        {
          "method": "org.eclipse.jface.util.Assert.isTrue",
          "source": "Assert.java:159"
        },
        {
          "method": "org.eclipse.ui.internal.presentations.newapi.PresentablePartFolder.getTab",
          "source": "PresentablePartFolder.java:376"
        },
        {
          "method": "org.eclipse.ui.internal.presentations.newapi.PresentablePartFolder.select",
          "source": "PresentablePartFolder.java:275"
        },
        {
          "method": "org.eclipse.ui.internal.presentations.newapi.LeftToRightTabOrder.select",
          "source": "LeftToRightTabOrder.java:65"
        },
        {
          "method": "org.eclipse.ui.internal.presentations.newapi.TabbedStackPresentation.selectPart",
          "source": "TabbedStackPresentation.java:378"
        },
        {
          "method": "org.eclipse.ui.internal.PartStack.refreshPresentationSelection",
          "source": "PartStack.java:1025"
        },
        {
          "method": "org.eclipse.ui.internal.PartStack.setSelection",
          "source": "PartStack.java:999"
        },
        {
          "method": "org.eclipse.ui.internal.PartStack.showPart",
          "source": "PartStack.java:1174"
        },
        {
          "method": "org.eclipse.ui.internal.PartStack.add",
          "source": "PartStack.java:359"
        },
        {
          "method": "org.eclipse.ui.internal.EditorStack.add",
          "source": "EditorStack.java:109"
        },
        {
          "method": "org.eclipse.ui.internal.EditorSashContainer.addEditor",
          "source": "EditorSashContainer.java:63"
        },
        {
          "method": "org.eclipse.ui.internal.EditorAreaHelper.openEditor",
          "source": "EditorAreaHelper.java:281"
        },
        {
          "method": "org.eclipse.ui.internal.EditorManager$4.run",
          "source": "EditorManager.java:787"
        },
        {
          "method": "org.eclipse.swt.custom.BusyIndicator.showWhile",
          "source": "BusyIndicator.java:69"
        },
        {
          "method": "org.eclipse.ui.internal.EditorManager.createEditorTab",
          "source": "EditorManager.java:773"
        },
        {
          "method": "org.eclipse.ui.internal.EditorManager.restoreEditorState",
          "source": "EditorManager.java:1721"
        },
        {
          "method": "org.eclipse.ui.internal.EditorManager.restoreState",
          "source": "EditorManager.java:999"
        },
        {
          "method": "org.eclipse.ui.internal.WorkbenchPage.restoreState",
          "source": "WorkbenchPage.java:2474"
        },
        {
          "method": "org.eclipse.ui.internal.WorkbenchWindow.restoreState",
          "source": "WorkbenchWindow.java:1606"
        },
        {
          "method": "org.eclipse.ui.internal.Workbench.restoreState",
          "source": "Workbench.java:1290"
        },
        {
          "method": "org.eclipse.ui.internal.Workbench.access$10",
          "source": "Workbench.java:1246"
        },
        {
          "method": "org.eclipse.ui.internal.Workbench$13.run",
          "source": "Workbench.java:1150"
        },
        {
          "method": "org.eclipse.core.internal.runtime.InternalPlatform.run",
          "source": "InternalPlatform.java:616"
        },
        {
          "method": "org.eclipse.core.runtime.Platform.run",
          "source": "Platform.java:747"
        },
        {
          "method": "org.eclipse.ui.internal.Workbench.restoreState",
          "source": "Workbench.java:1084"
        },
        {
          "method": "org.eclipse.ui.internal.WorkbenchConfigurer.restoreState",
          "source": "WorkbenchConfigurer.java:171"
        },
        {
          "method": "org.eclipse.ui.application.WorkbenchAdvisor.openWindows",
          "source": "WorkbenchAdvisor.java:655"
        },
        {
          "method": "org.eclipse.ui.internal.Workbench.init",
          "source": "Workbench.java:860"
        },
        {
          "method": "org.eclipse.ui.internal.Workbench.runUI",
          "source": "Workbench.java:1391"
        },
        {
          "method": "org.eclipse.ui.internal.Workbench.createAndRunWorkbench",
          "source": "Workbench.java:271"
        },
        {
          "method": "org.eclipse.ui.PlatformUI.createAndRunWorkbench",
          "source": "PlatformUI.java:144"
        },
        {
          "method": "org.eclipse.ui.internal.ide.IDEApplication.run",
          "source": "IDEApplication.java:102"
        },
        {
          "method": "org.eclipse.core.internal.runtime.PlatformActivator$1.run",
          "source": "PlatformActivator.java:335"
        },
        {
          "method": "org.eclipse.core.runtime.adaptor.EclipseStarter.run",
          "source": "EclipseStarter.java:273"
        },
        {
          "method": "org.eclipse.core.runtime.adaptor.EclipseStarter.run",
          "source": "EclipseStarter.java:129"
        },
        {
          "method": "sun.reflect.NativeMethodAccessorImpl.invoke0",
          "source": "Native Method"
        },
        {
          "method": "sun.reflect.NativeMethodAccessorImpl.invoke",
          "source": "NativeMethodAccessorImpl.java:85"
        },
        {
          "method": "sun.reflect.NativeMethodAccessorImpl.invoke",
          "source": "NativeMethodAccessorImpl.java:58"
        },
        {
          "method": "sun.reflect.DelegatingMethodAccessorImpl.invoke",
          "source": "DelegatingMethodAccessorImpl.java:60"
        },
        {
          "method": "java.lang.reflect.Method.invoke",
          "source": "Method.java:391"
        },
        {
          "method": "org.eclipse.core.launcher.Main.basicRun",
          "source": "Main.java:185"
        },
        {
          "method": "org.eclipse.core.launcher.Main.run",
          "source": "Main.java:684"
        },
        {
          "method": "org.eclipse.core.launcher.Main.main",
          "source": "Main.java:668"
        }
      ],
      "number": 0,
      "commentIndex": 0,
      "bugId": "75722",
      "date": "2004-10-06T20:19:17+02:00",
      "product": "Platform",
      "component": "UI",
      "severity": "normal"
    }
  ],
  "groupId": "75722",
  "bugId": "75722",
  "date": "2004-10-06T20:19:17+02:00",
  "product": "Platform",
  "component": "UI",
  "severity": "normal"
}