{
  "comments": [
    "I was messing around with a PDE project (migrating to 3.1 among other things)\nand wanted to recreate the build.xml file.\n\nSo, I backed up my build.xml file and deleted it.  I right-clicked the\nplugin.xml file and selected \"Create Ant Build File\".  In doing this, I got an\nerror dialog that said \"Unable to write script /home/ewies/project/build.xml\". \nWhen I did \"touch build.xml\" to create a dummy file (to test permissions, or\nsomething), the command completed without an error, but the resulting build\nscript was empty.\n\nAfter looking at the stack trace in the error log, I saw which plugin and dove\ninto the CVS source.  It ended up that I had the \"custom\" flag set in my\nbuild.properties file.  I had some custom ant commands in my project and had\nforgotten that the flag was set.\n\nI deleted build.xml again and removed the flag and all worked fine.\n\nTo make a long story short, I had to do some digging around to figure out what\nwas wrong.  A more verbose error message would be useful.  There is already an\nerror dialog for this specific failure mode  (see the callstack below), it just\nneeds to be more verbose -- something akin to \"Could not open /path/build.xml\nwhile updating project with custom build enabled.\"?\n\nCheers,\nEvan\n\n\nRelevant stack frames:\n!ENTRY org.eclipse.pde.build 4 7 Oct 05, 2004 14:55:00.925\n!MESSAGE Could not write script /home/ewies/bb/utils/sif/build.xml.\n!STACK 0\njava.io.FileNotFoundException: /home/ewies/bb/utils/sif/build.xml (No such file\nor directory)\n\tat java.io.FileInputStream.open(Native Method)\n\tat java.io.FileInputStream.\u003cinit\u003e(FileInputStream.java:106)\n\tat\norg.eclipse.pde.internal.build.builder.AbstractBuildScriptGenerator.readFile(AbstractBuildScriptGenerator.java:142)\n\tat\norg.eclipse.pde.internal.build.builder.AbstractBuildScriptGenerator.updateVersion(AbstractBuildScriptGenerator.java:180)\n\tat\norg.eclipse.pde.internal.build.builder.ModelBuildScriptGenerator.updateExistingScript(ModelBuildScriptGenerator.java:893)\n\tat\norg.eclipse.pde.internal.build.builder.ModelBuildScriptGenerator.generate(ModelBuildScriptGenerator.java:125)",
    "Fixed in HEAD."
  ],
  "commentCreationDates": [
    "2004-10-07T00:41:21+02:00",
    "2005-03-10T21:06:59+01:00"
  ],
  "traces": [
    {
      "exceptionType": "java.io.FileNotFoundException",
      "message": "/home/ewies/bb/utils/sif/build.xml (No such file or directory)",
      "elements": [
        {
          "method": "java.io.FileInputStream.open",
          "source": "Native Method"
        },
        {
          "method": "java.io.FileInputStream.\u003cinit\u003e",
          "source": "FileInputStream.java:106"
        },
        {
          "method": "org.eclipse.pde.internal.build.builder.AbstractBuildScriptGenerator.readFile",
          "source": "AbstractBuildScriptGenerator.java:142"
        },
        {
          "method": "org.eclipse.pde.internal.build.builder.AbstractBuildScriptGenerator.updateVersion",
          "source": "AbstractBuildScriptGenerator.java:180"
        },
        {
          "method": "org.eclipse.pde.internal.build.builder.ModelBuildScriptGenerator.updateExistingScript",
          "source": "ModelBuildScriptGenerator.java:893"
        },
        {
          "method": "org.eclipse.pde.internal.build.builder.ModelBuildScriptGenerator.generate",
          "source": "ModelBuildScriptGenerator.java:125"
        }
      ],
      "number": 0,
      "commentIndex": 0,
      "bugId": "75752",
      "date": "2004-10-07T00:41:21+02:00",
      "product": "PDE",
      "component": "Build",
      "severity": "enhancement"
    }
  ],
  "groupId": "75752",
  "bugId": "75752",
  "date": "2004-10-07T00:41:21+02:00",
  "product": "PDE",
  "component": "Build",
  "severity": "enhancement"
}