{
  "comments": [
    "!SESSION Oct 14, 2004 12:22:52.857\neclipse.buildId\u003dI200409300800\njava.version\u003d1.4.2_05\njava.vendor\u003dSun Microsystems Inc.\nBootLoader constants: OS\u003dwin32, ARCH\u003dx86, WS\u003dwin32, NL\u003den_GB\nCommand-line arguments: -J-Xmx512m\n\n!ENTRY org.eclipse.ui 4 4 Oct 14, 2004 12:22:52.857\n!MESSAGE Unhandled event loop exception\n\n!ENTRY org.eclipse.ui 4 0 Oct 14, 2004 12:22:52.857\n!MESSAGE java.lang.NullPointerException\n!STACK 0\njava.lang.NullPointerException\n        at\norg.eclipse.jdt.internal.ui.text.correction.UnimplementedMethodsCompletionProposal.evalUnimplementedMethods(UnimplementedMethodsCompletionP\nroposal.java:198)\n        at\norg.eclipse.jdt.internal.ui.text.correction.UnimplementedMethodsCompletionProposal.getRewrite(UnimplementedMethodsCompletionProposal.java:7\n3)\n        at\norg.eclipse.jdt.internal.ui.text.correction.ASTRewriteCorrectionProposal.addEdits(ASTRewriteCorrectionProposal.java:61)\n        at\norg.eclipse.jdt.internal.ui.text.correction.CUCorrectionProposal.initializeTextChange(CUCorrectionProposal.java:135)\n        at\norg.eclipse.jdt.internal.ui.text.correction.CUCorrectionProposal.performChange(CUCorrectionProposal.java:258)\n        at\norg.eclipse.jdt.internal.ui.text.correction.CUCorrectionProposal.apply(CUCorrectionProposal.java:289)\n        at\norg.eclipse.jface.text.contentassist.CompletionProposalPopup.insertProposal(CompletionProposalPopup.java:420)\n        at\norg.eclipse.jface.text.contentassist.CompletionProposalPopup.selectProposalWithMask(CompletionProposalPopup.java:362)\n        at\norg.eclipse.jface.text.contentassist.CompletionProposalPopup.verifyKey(CompletionProposalPopup.java:720)\n        at\norg.eclipse.jface.text.contentassist.ContentAssistant$InternalListener.verifyKey(ContentAssistant.java:622)\n        at\norg.eclipse.jface.text.TextViewer$VerifyKeyListenersManager.verifyKey(TextViewer.java:404)\n        at\norg.eclipse.swt.custom.StyledTextListener.handleEvent(StyledTextListener.java:55)\n        at org.eclipse.swt.widgets.EventTable.sendEvent(EventTable.java:82)\n        at org.eclipse.swt.widgets.Widget.sendEvent(Widget.java:796)\n        at org.eclipse.swt.widgets.Widget.sendEvent(Widget.java:820)\n        at org.eclipse.swt.widgets.Widget.sendEvent(Widget.java:805)\n        at org.eclipse.swt.widgets.Widget.notifyListeners(Widget.java:613)\n        at org.eclipse.swt.custom.StyledText.handleKeyDown(StyledText.java:5000)\n        at org.eclipse.swt.custom.StyledText$7.handleEvent(StyledText.java:4747)\n        at org.eclipse.swt.widgets.EventTable.sendEvent(EventTable.java:82)\n        at org.eclipse.swt.widgets.Widget.sendEvent(Widget.java:796)\n        at org.eclipse.swt.widgets.Widget.sendEvent(Widget.java:820)\n        at org.eclipse.swt.widgets.Widget.sendEvent(Widget.java:805)\n        at org.eclipse.swt.widgets.Control.sendKeyEvent(Control.java:1736)\n        at org.eclipse.swt.widgets.Control.sendKeyEvent(Control.java:1732)\n        at org.eclipse.swt.widgets.Control.WM_CHAR(Control.java:3073)\n        at org.eclipse.swt.widgets.Control.windowProc(Control.java:2975)\n        at org.eclipse.swt.widgets.Display.windowProc(Display.java:3351)\n        at org.eclipse.swt.internal.win32.OS.DispatchMessageW(Native Method)\n        at org.eclipse.swt.internal.win32.OS.DispatchMessage(OS.java:1488)\n        at org.eclipse.swt.widgets.Display.readAndDispatch(Display.java:2441)\n        at org.eclipse.ui.internal.Workbench.runEventLoop(Workbench.java:1443)\n        at org.eclipse.ui.internal.Workbench.runUI(Workbench.java:1414)\n        at\norg.eclipse.ui.internal.Workbench.createAndRunWorkbench(Workbench.java:271)\n        at org.eclipse.ui.PlatformUI.createAndRunWorkbench(PlatformUI.java:144)\n        at org.eclipse.ui.internal.ide.IDEApplication.run(IDEApplication.java:102)\n        at\norg.eclipse.core.internal.runtime.PlatformActivator$1.run(PlatformActivator.java:335)\n        at\norg.eclipse.core.runtime.adaptor.EclipseStarter.run(EclipseStarter.java:273)\n        at\norg.eclipse.core.runtime.adaptor.EclipseStarter.run(EclipseStarter.java:129)\n        at sun.reflect.NativeMethodAccessorImpl.invoke0(Native Method)\n        at\nsun.reflect.NativeMethodAccessorImpl.invoke(NativeMethodAccessorImpl.java:39)\n        at\nsun.reflect.DelegatingMethodAccessorImpl.invoke(DelegatingMethodAccessorImpl.java:25)\n        at java.lang.reflect.Method.invoke(Method.java:324)\n        at org.eclipse.core.launcher.Main.basicRun(Main.java:185)\n        at org.eclipse.core.launcher.Main.run(Main.java:704)\n        at org.eclipse.core.launcher.Main.main(Main.java:688)",
    "fixed \u003e 20041014",
    "Thanks Martin.",
    "Oh, what I forgot to ask; do you have this reproducable?\nI fixed the bug that the quick fix shows up even if the type has no type \nbinding. Maybe it\u0027s also a bug in jdt.core that there is no type binding",
    "I\u0027ll see if I can reproduce it and report back if I do.\n\nChanning"
  ],
  "commentCreationDates": [
    "2004-10-14T13:37:36+02:00",
    "2004-10-14T18:55:55+02:00",
    "2004-10-14T23:15:23+02:00",
    "2004-10-15T12:57:03+02:00",
    "2004-10-15T13:00:24+02:00"
  ],
  "traces": [
    {
      "exceptionType": "java.lang.NullPointerException",
      "elements": [
        {
          "method": "org.eclipse.jdt.internal.ui.text.correction.UnimplementedMethodsCompletionProposal.evalUnimplementedMethods",
          "source": "UnimplementedMethodsCompletionP roposal.java:198"
        },
        {
          "method": "org.eclipse.jdt.internal.ui.text.correction.UnimplementedMethodsCompletionProposal.getRewrite",
          "source": "UnimplementedMethodsCompletionProposal.java:7 3"
        },
        {
          "method": "org.eclipse.jdt.internal.ui.text.correction.ASTRewriteCorrectionProposal.addEdits",
          "source": "ASTRewriteCorrectionProposal.java:61"
        },
        {
          "method": "org.eclipse.jdt.internal.ui.text.correction.CUCorrectionProposal.initializeTextChange",
          "source": "CUCorrectionProposal.java:135"
        },
        {
          "method": "org.eclipse.jdt.internal.ui.text.correction.CUCorrectionProposal.performChange",
          "source": "CUCorrectionProposal.java:258"
        },
        {
          "method": "org.eclipse.jdt.internal.ui.text.correction.CUCorrectionProposal.apply",
          "source": "CUCorrectionProposal.java:289"
        },
        {
          "method": "org.eclipse.jface.text.contentassist.CompletionProposalPopup.insertProposal",
          "source": "CompletionProposalPopup.java:420"
        },
        {
          "method": "org.eclipse.jface.text.contentassist.CompletionProposalPopup.selectProposalWithMask",
          "source": "CompletionProposalPopup.java:362"
        },
        {
          "method": "org.eclipse.jface.text.contentassist.CompletionProposalPopup.verifyKey",
          "source": "CompletionProposalPopup.java:720"
        },
        {
          "method": "org.eclipse.jface.text.contentassist.ContentAssistant$InternalListener.verifyKey",
          "source": "ContentAssistant.java:622"
        },
        {
          "method": "org.eclipse.jface.text.TextViewer$VerifyKeyListenersManager.verifyKey",
          "source": "TextViewer.java:404"
        },
        {
          "method": "org.eclipse.swt.custom.StyledTextListener.handleEvent",
          "source": "StyledTextListener.java:55"
        },
        {
          "method": "org.eclipse.swt.widgets.EventTable.sendEvent",
          "source": "EventTable.java:82"
        },
        {
          "method": "org.eclipse.swt.widgets.Widget.sendEvent",
          "source": "Widget.java:796"
        },
        {
          "method": "org.eclipse.swt.widgets.Widget.sendEvent",
          "source": "Widget.java:820"
        },
        {
          "method": "org.eclipse.swt.widgets.Widget.sendEvent",
          "source": "Widget.java:805"
        },
        {
          "method": "org.eclipse.swt.widgets.Widget.notifyListeners",
          "source": "Widget.java:613"
        },
        {
          "method": "org.eclipse.swt.custom.StyledText.handleKeyDown",
          "source": "StyledText.java:5000"
        },
        {
          "method": "org.eclipse.swt.custom.StyledText$7.handleEvent",
          "source": "StyledText.java:4747"
        },
        {
          "method": "org.eclipse.swt.widgets.EventTable.sendEvent",
          "source": "EventTable.java:82"
        },
        {
          "method": "org.eclipse.swt.widgets.Widget.sendEvent",
          "source": "Widget.java:796"
        },
        {
          "method": "org.eclipse.swt.widgets.Widget.sendEvent",
          "source": "Widget.java:820"
        },
        {
          "method": "org.eclipse.swt.widgets.Widget.sendEvent",
          "source": "Widget.java:805"
        },
        {
          "method": "org.eclipse.swt.widgets.Control.sendKeyEvent",
          "source": "Control.java:1736"
        },
        {
          "method": "org.eclipse.swt.widgets.Control.sendKeyEvent",
          "source": "Control.java:1732"
        },
        {
          "method": "org.eclipse.swt.widgets.Control.WM_CHAR",
          "source": "Control.java:3073"
        },
        {
          "method": "org.eclipse.swt.widgets.Control.windowProc",
          "source": "Control.java:2975"
        },
        {
          "method": "org.eclipse.swt.widgets.Display.windowProc",
          "source": "Display.java:3351"
        },
        {
          "method": "org.eclipse.swt.internal.win32.OS.DispatchMessageW",
          "source": "Native Method"
        },
        {
          "method": "org.eclipse.swt.internal.win32.OS.DispatchMessage",
          "source": "OS.java:1488"
        },
        {
          "method": "org.eclipse.swt.widgets.Display.readAndDispatch",
          "source": "Display.java:2441"
        },
        {
          "method": "org.eclipse.ui.internal.Workbench.runEventLoop",
          "source": "Workbench.java:1443"
        },
        {
          "method": "org.eclipse.ui.internal.Workbench.runUI",
          "source": "Workbench.java:1414"
        },
        {
          "method": "org.eclipse.ui.internal.Workbench.createAndRunWorkbench",
          "source": "Workbench.java:271"
        },
        {
          "method": "org.eclipse.ui.PlatformUI.createAndRunWorkbench",
          "source": "PlatformUI.java:144"
        },
        {
          "method": "org.eclipse.ui.internal.ide.IDEApplication.run",
          "source": "IDEApplication.java:102"
        },
        {
          "method": "org.eclipse.core.internal.runtime.PlatformActivator$1.run",
          "source": "PlatformActivator.java:335"
        },
        {
          "method": "org.eclipse.core.runtime.adaptor.EclipseStarter.run",
          "source": "EclipseStarter.java:273"
        },
        {
          "method": "org.eclipse.core.runtime.adaptor.EclipseStarter.run",
          "source": "EclipseStarter.java:129"
        },
        {
          "method": "sun.reflect.NativeMethodAccessorImpl.invoke0",
          "source": "Native Method"
        },
        {
          "method": "sun.reflect.NativeMethodAccessorImpl.invoke",
          "source": "NativeMethodAccessorImpl.java:39"
        },
        {
          "method": "sun.reflect.DelegatingMethodAccessorImpl.invoke",
          "source": "DelegatingMethodAccessorImpl.java:25"
        },
        {
          "method": "java.lang.reflect.Method.invoke",
          "source": "Method.java:324"
        },
        {
          "method": "org.eclipse.core.launcher.Main.basicRun",
          "source": "Main.java:185"
        },
        {
          "method": "org.eclipse.core.launcher.Main.run",
          "source": "Main.java:704"
        },
        {
          "method": "org.eclipse.core.launcher.Main.main",
          "source": "Main.java:688"
        }
      ],
      "number": 0,
      "commentIndex": 0,
      "bugId": "76242",
      "date": "2004-10-14T13:37:36+02:00",
      "product": "JDT",
      "component": "Text",
      "severity": "normal"
    }
  ],
  "groupId": "76242",
  "bugId": "76242",
  "date": "2004-10-14T13:37:36+02:00",
  "product": "JDT",
  "component": "Text",
  "severity": "normal"
}