{
  "comments": [
    "This does not seem urgent, I don\u0027t think there are any bad side effects, but I \nsaw the following exception logged while shutting down the latest RAD build \n(built on 3.0.1).\n\nClass cast exceptions within eclipse code should never happen, right?\n\n!ENTRY org.eclipse.core.runtime 4 2 Oct 12, 2004 19:06:23.627\n!MESSAGE Problems occurred when invoking code from plug-\nin: \"org.eclipse.core.runtime\".\n!STACK 0\njava.lang.ClassCastException: org/eclipse/ui/internal/EditorActionBars \nincompatible with org/eclipse/ui/internal/ViewActionBars\n        at org.eclipse.ui.internal.ViewFactory.destroyView(Unknown Source)\n        at org.eclipse.ui.internal.ViewFactory.releaseView(Unknown Source)\n        at org.eclipse.ui.internal.Perspective.dispose(Unknown Source)\n        at org.eclipse.ui.internal.WorkbenchPage.dispose(Unknown Source)\n        at org.eclipse.ui.internal.WorkbenchWindow.closeAllPages(Unknown \nSource)\n        at org.eclipse.ui.internal.WorkbenchWindow.hardClose(Unknown Source)\n        at org.eclipse.ui.internal.WorkbenchWindow.busyClose(Unknown Source)\n        at org.eclipse.ui.internal.WorkbenchWindow.access$0(Unknown Source)\n        at org.eclipse.ui.internal.WorkbenchWindow$1.run(Unknown Source)\n        at org.eclipse.swt.custom.BusyIndicator.showWhile(Unknown Source)\n        at org.eclipse.ui.internal.WorkbenchWindow.close(Unknown Source)\n        at org.eclipse.jface.window.WindowManager.close(Unknown Source)\n        at org.eclipse.ui.internal.Workbench$10.run(Unknown Source)\n        at org.eclipse.core.internal.runtime.InternalPlatform.run(Unknown \nSource)\n        at org.eclipse.core.runtime.Platform.run(Unknown Source)\n        at org.eclipse.ui.internal.Workbench.busyClose(Unknown Source)\n        at org.eclipse.ui.internal.Workbench.access$8(Unknown Source)\n        at org.eclipse.ui.internal.Workbench$12.run(Unknown Source)\n        at org.eclipse.swt.custom.BusyIndicator.showWhile(Unknown Source)\n        at org.eclipse.ui.internal.Workbench.close(Unknown Source)\n        at org.eclipse.ui.internal.Workbench.close(Unknown Source)\n        at org.eclipse.ui.internal.WorkbenchWindow.busyClose(Unknown Source)\n        at org.eclipse.ui.internal.WorkbenchWindow.access$0(Unknown Source)\n        at org.eclipse.ui.internal.WorkbenchWindow$1.run(Unknown Source)\n        at org.eclipse.swt.custom.BusyIndicator.showWhile(Unknown Source)\n        at org.eclipse.ui.internal.WorkbenchWindow.close(Unknown Source)\n        at org.eclipse.jface.window.Window.handleShellCloseEvent(Unknown \nSource)\n        at org.eclipse.jface.window.Window$2.shellClosed(Unknown Source)\n        at org.eclipse.swt.widgets.TypedListener.handleEvent(Unknown Source)\n        at org.eclipse.swt.widgets.EventTable.sendEvent(Unknown Source)\n        at org.eclipse.swt.widgets.Widget.sendEvent(Unknown Source)\n        at org.eclipse.swt.widgets.Widget.sendEvent(Unknown Source)\n        at org.eclipse.swt.widgets.Widget.sendEvent(Unknown Source)\n        at org.eclipse.swt.widgets.Decorations.WM_CLOSE(Unknown Source)\n        at org.eclipse.swt.widgets.Control.windowProc(Unknown Source)\n        at org.eclipse.swt.widgets.Decorations.windowProc(Unknown Source)\n        at org.eclipse.swt.widgets.Display.windowProc(Unknown Source)\n        at org.eclipse.swt.internal.win32.OS.DefWindowProcW(Native Method)\n        at org.eclipse.swt.internal.win32.OS.DefWindowProc(Unknown Source)\n        at org.eclipse.swt.widgets.Shell.callWindowProc(Unknown Source)\n        at org.eclipse.swt.widgets.Control.windowProc(Unknown Source)\n        at org.eclipse.swt.widgets.Decorations.windowProc(Unknown Source)\n        at org.eclipse.swt.widgets.Display.windowProc(Unknown Source)\n        at org.eclipse.swt.internal.win32.OS.DefWindowProcW(Native Method)\n        at org.eclipse.swt.internal.win32.OS.DefWindowProc(Unknown Source)\n        at org.eclipse.swt.widgets.Shell.callWindowProc(Unknown Source)\n        at org.eclipse.swt.widgets.Control.windowProc(Unknown Source)\n        at org.eclipse.swt.widgets.Decorations.windowProc(Unknown Source)\n        at org.eclipse.swt.widgets.Display.windowProc(Unknown Source)\n        at org.eclipse.swt.internal.win32.OS.DispatchMessageW(Native Method)\n        at org.eclipse.swt.internal.win32.OS.DispatchMessage(Unknown Source)\n        at org.eclipse.swt.widgets.Display.readAndDispatch(Unknown Source)\n        at org.eclipse.ui.internal.Workbench.runEventLoop(Unknown Source)\n        at org.eclipse.ui.internal.Workbench.runUI(Unknown Source)\n        at org.eclipse.ui.internal.Workbench.createAndRunWorkbench(Unknown \nSource)\n        at org.eclipse.ui.PlatformUI.createAndRunWorkbench(Unknown Source)\n        at org.eclipse.ui.internal.ide.IDEApplication.run(Unknown Source)\n        at org.eclipse.core.internal.runtime.PlatformActivator$1.run(Unknown \nSource)\n        at org.eclipse.core.runtime.adaptor.EclipseStarter.run\n(EclipseStarter.java:273)\n        at org.eclipse.core.runtime.adaptor.EclipseStarter.run\n(EclipseStarter.java:129)\n        at sun.reflect.NativeMethodAccessorImpl.invoke0(Native Method)\n        at sun.reflect.NativeMethodAccessorImpl.invoke\n(NativeMethodAccessorImpl.java:85)\n        at sun.reflect.NativeMethodAccessorImpl.invoke\n(NativeMethodAccessorImpl.java:58)\n        at sun.reflect.DelegatingMethodAccessorImpl.invoke\n(DelegatingMethodAccessorImpl.java:60)\n        at java.lang.reflect.Method.invoke(Method.java:391)\n        at org.eclipse.core.launcher.Main.basicRun(Main.java:185)\n        at org.eclipse.core.launcher.Main.run(Main.java:684)\n        at org.eclipse.core.launcher.Main.main(Main.java:668)",
    "\n\n*** This bug has been marked as a duplicate of 75051 ***",
    "Which views did you have open (across all perspectives)?\nDo any of them do anything weird like changing their site.\nSee bug 75051 for more details, and reply there.\n\n"
  ],
  "commentCreationDates": [
    "2004-10-16T14:52:04+02:00",
    "2004-10-19T14:05:48+02:00",
    "2004-10-20T18:18:14+02:00"
  ],
  "traces": [
    {
      "exceptionType": "java.lang.ClassCastException",
      "message": "org/eclipse/ui/internal/EditorActionBars  incompatible with org/eclipse/ui/internal/ViewActionBars",
      "elements": [
        {
          "method": "org.eclipse.ui.internal.ViewFactory.destroyView",
          "source": "Unknown Source"
        },
        {
          "method": "org.eclipse.ui.internal.ViewFactory.releaseView",
          "source": "Unknown Source"
        },
        {
          "method": "org.eclipse.ui.internal.Perspective.dispose",
          "source": "Unknown Source"
        },
        {
          "method": "org.eclipse.ui.internal.WorkbenchPage.dispose",
          "source": "Unknown Source"
        },
        {
          "method": "org.eclipse.ui.internal.WorkbenchWindow.closeAllPages",
          "source": "Unknown  Source"
        },
        {
          "method": "org.eclipse.ui.internal.WorkbenchWindow.hardClose",
          "source": "Unknown Source"
        },
        {
          "method": "org.eclipse.ui.internal.WorkbenchWindow.busyClose",
          "source": "Unknown Source"
        },
        {
          "method": "org.eclipse.ui.internal.WorkbenchWindow.access$0",
          "source": "Unknown Source"
        },
        {
          "method": "org.eclipse.ui.internal.WorkbenchWindow$1.run",
          "source": "Unknown Source"
        },
        {
          "method": "org.eclipse.swt.custom.BusyIndicator.showWhile",
          "source": "Unknown Source"
        },
        {
          "method": "org.eclipse.ui.internal.WorkbenchWindow.close",
          "source": "Unknown Source"
        },
        {
          "method": "org.eclipse.jface.window.WindowManager.close",
          "source": "Unknown Source"
        },
        {
          "method": "org.eclipse.ui.internal.Workbench$10.run",
          "source": "Unknown Source"
        },
        {
          "method": "org.eclipse.core.internal.runtime.InternalPlatform.run",
          "source": "Unknown  Source"
        },
        {
          "method": "org.eclipse.core.runtime.Platform.run",
          "source": "Unknown Source"
        },
        {
          "method": "org.eclipse.ui.internal.Workbench.busyClose",
          "source": "Unknown Source"
        },
        {
          "method": "org.eclipse.ui.internal.Workbench.access$8",
          "source": "Unknown Source"
        },
        {
          "method": "org.eclipse.ui.internal.Workbench$12.run",
          "source": "Unknown Source"
        },
        {
          "method": "org.eclipse.swt.custom.BusyIndicator.showWhile",
          "source": "Unknown Source"
        },
        {
          "method": "org.eclipse.ui.internal.Workbench.close",
          "source": "Unknown Source"
        },
        {
          "method": "org.eclipse.ui.internal.Workbench.close",
          "source": "Unknown Source"
        },
        {
          "method": "org.eclipse.ui.internal.WorkbenchWindow.busyClose",
          "source": "Unknown Source"
        },
        {
          "method": "org.eclipse.ui.internal.WorkbenchWindow.access$0",
          "source": "Unknown Source"
        },
        {
          "method": "org.eclipse.ui.internal.WorkbenchWindow$1.run",
          "source": "Unknown Source"
        },
        {
          "method": "org.eclipse.swt.custom.BusyIndicator.showWhile",
          "source": "Unknown Source"
        },
        {
          "method": "org.eclipse.ui.internal.WorkbenchWindow.close",
          "source": "Unknown Source"
        },
        {
          "method": "org.eclipse.jface.window.Window.handleShellCloseEvent",
          "source": "Unknown  Source"
        },
        {
          "method": "org.eclipse.jface.window.Window$2.shellClosed",
          "source": "Unknown Source"
        },
        {
          "method": "org.eclipse.swt.widgets.TypedListener.handleEvent",
          "source": "Unknown Source"
        },
        {
          "method": "org.eclipse.swt.widgets.EventTable.sendEvent",
          "source": "Unknown Source"
        },
        {
          "method": "org.eclipse.swt.widgets.Widget.sendEvent",
          "source": "Unknown Source"
        },
        {
          "method": "org.eclipse.swt.widgets.Widget.sendEvent",
          "source": "Unknown Source"
        },
        {
          "method": "org.eclipse.swt.widgets.Widget.sendEvent",
          "source": "Unknown Source"
        },
        {
          "method": "org.eclipse.swt.widgets.Decorations.WM_CLOSE",
          "source": "Unknown Source"
        },
        {
          "method": "org.eclipse.swt.widgets.Control.windowProc",
          "source": "Unknown Source"
        },
        {
          "method": "org.eclipse.swt.widgets.Decorations.windowProc",
          "source": "Unknown Source"
        },
        {
          "method": "org.eclipse.swt.widgets.Display.windowProc",
          "source": "Unknown Source"
        },
        {
          "method": "org.eclipse.swt.internal.win32.OS.DefWindowProcW",
          "source": "Native Method"
        },
        {
          "method": "org.eclipse.swt.internal.win32.OS.DefWindowProc",
          "source": "Unknown Source"
        },
        {
          "method": "org.eclipse.swt.widgets.Shell.callWindowProc",
          "source": "Unknown Source"
        },
        {
          "method": "org.eclipse.swt.widgets.Control.windowProc",
          "source": "Unknown Source"
        },
        {
          "method": "org.eclipse.swt.widgets.Decorations.windowProc",
          "source": "Unknown Source"
        },
        {
          "method": "org.eclipse.swt.widgets.Display.windowProc",
          "source": "Unknown Source"
        },
        {
          "method": "org.eclipse.swt.internal.win32.OS.DefWindowProcW",
          "source": "Native Method"
        },
        {
          "method": "org.eclipse.swt.internal.win32.OS.DefWindowProc",
          "source": "Unknown Source"
        },
        {
          "method": "org.eclipse.swt.widgets.Shell.callWindowProc",
          "source": "Unknown Source"
        },
        {
          "method": "org.eclipse.swt.widgets.Control.windowProc",
          "source": "Unknown Source"
        },
        {
          "method": "org.eclipse.swt.widgets.Decorations.windowProc",
          "source": "Unknown Source"
        },
        {
          "method": "org.eclipse.swt.widgets.Display.windowProc",
          "source": "Unknown Source"
        },
        {
          "method": "org.eclipse.swt.internal.win32.OS.DispatchMessageW",
          "source": "Native Method"
        },
        {
          "method": "org.eclipse.swt.internal.win32.OS.DispatchMessage",
          "source": "Unknown Source"
        },
        {
          "method": "org.eclipse.swt.widgets.Display.readAndDispatch",
          "source": "Unknown Source"
        },
        {
          "method": "org.eclipse.ui.internal.Workbench.runEventLoop",
          "source": "Unknown Source"
        },
        {
          "method": "org.eclipse.ui.internal.Workbench.runUI",
          "source": "Unknown Source"
        },
        {
          "method": "org.eclipse.ui.internal.Workbench.createAndRunWorkbench",
          "source": "Unknown  Source"
        },
        {
          "method": "org.eclipse.ui.PlatformUI.createAndRunWorkbench",
          "source": "Unknown Source"
        },
        {
          "method": "org.eclipse.ui.internal.ide.IDEApplication.run",
          "source": "Unknown Source"
        },
        {
          "method": "org.eclipse.core.internal.runtime.PlatformActivator$1.run",
          "source": "Unknown  Source"
        },
        {
          "method": "org.eclipse.core.runtime.adaptor.EclipseStarter.run",
          "source": "EclipseStarter.java:273"
        },
        {
          "method": "org.eclipse.core.runtime.adaptor.EclipseStarter.run",
          "source": "EclipseStarter.java:129"
        },
        {
          "method": "sun.reflect.NativeMethodAccessorImpl.invoke0",
          "source": "Native Method"
        },
        {
          "method": "sun.reflect.NativeMethodAccessorImpl.invoke",
          "source": "NativeMethodAccessorImpl.java:85"
        },
        {
          "method": "sun.reflect.NativeMethodAccessorImpl.invoke",
          "source": "NativeMethodAccessorImpl.java:58"
        },
        {
          "method": "sun.reflect.DelegatingMethodAccessorImpl.invoke",
          "source": "DelegatingMethodAccessorImpl.java:60"
        },
        {
          "method": "java.lang.reflect.Method.invoke",
          "source": "Method.java:391"
        },
        {
          "method": "org.eclipse.core.launcher.Main.basicRun",
          "source": "Main.java:185"
        },
        {
          "method": "org.eclipse.core.launcher.Main.run",
          "source": "Main.java:684"
        },
        {
          "method": "org.eclipse.core.launcher.Main.main",
          "source": "Main.java:668"
        }
      ],
      "number": 0,
      "commentIndex": 0,
      "bugId": "76418",
      "duplicateId": "75051",
      "date": "2004-10-16T14:52:04+02:00",
      "product": "Platform",
      "component": "UI",
      "severity": "normal"
    }
  ],
  "groupId": "75051",
  "bugId": "76418",
  "duplicateId": "75051",
  "date": "2004-10-16T14:52:04+02:00",
  "product": "Platform",
  "component": "UI",
  "severity": "normal"
}