{
  "comments": [
    "Under Solaris the Eclipse default CVS protocol not set to pserver.\nI forgot to change it to pserver.\nWith it not set to pserver, attempting CVS operations resulted in Eclipse\nfailing with a JVM crash.",
    "What was it set to? What is the stack trace from the crash?",
    "I do not understand your action here.  Is this resolved, or do you need a stack \ntrace?",
    "Sorry, RESOLVED REMIND is a place holder for bugs tht are awaiting feedback \nfrom the reporter. Please provide the stack trace and the connection method \nthat caused the failure. Without them, we cannot proceed.",
    "The connection type was the default Eclipse gave me on Solaris - extssh\nThe stack trace is below.\nThis is the one I showed you where Eclipse dies when you are right clicking\nin the CVS window.\n\n-bash-2.05b$ cat hs_err_pid5029.log \n\nAn unexpected exception has been detected in native code outside the VM.\nUnexpected Signal : 11 occurred at PC\u003d0xF0B34FC0\nFunction\u003dXFilterEvent+0x24\nLibrary\u003d/usr/openwin/lib/libX11.so.4\n\nCurrent Java thread:\n        at org.eclipse.swt.internal.motif.OS.XtDispatchEvent(Native Method)\n        at\norg.eclipse.swt.widgets.Display.readAndDispatch(Display.java:2640)\n        at\norg.eclipse.ui.internal.Workbench.runEventLoop(Workbench.java:1377)\n        at org.eclipse.ui.internal.Workbench.runUI(Workbench.java:1348)\n        at\norg.eclipse.ui.internal.Workbench.createAndRunWorkbench(Workbench.java:254)\n        at\norg.eclipse.ui.PlatformUI.createAndRunWorkbench(PlatformUI.java:141)\n        at\norg.eclipse.ui.internal.ide.IDEApplication.run(IDEApplication.java:96)\n        at\norg.eclipse.core.internal.runtime.PlatformActivator$1.run(PlatformActivator.\njava:335)\n        at\norg.eclipse.core.runtime.adaptor.EclipseStarter.run(EclipseStarter.java:273)\n        at\norg.eclipse.core.runtime.adaptor.EclipseStarter.run(EclipseStarter.java:129)\n        at sun.reflect.NativeMethodAccessorImpl.invoke0(Native Method)\n        at\nsun.reflect.NativeMethodAccessorImpl.invoke(NativeMethodAccessorImpl.java:39\n)\n        at\nsun.reflect.DelegatingMethodAccessorImpl.invoke(DelegatingMethodAccessorImpl\n.java:25)\n        at java.lang.reflect.Method.invoke(Method.java:324)\n        at org.eclipse.core.launcher.Main.basicRun(Main.java:185)\n        at org.eclipse.core.launcher.Main.run(Main.java:704)\n        at org.eclipse.core.launcher.Main.main(Main.java:688)\n\nDynamic libraries:\n0x10000         /usr/j2se/bin/java\n0xff350000      /usr/lib/libthread.so.1\n0xff390000      /usr/lib/libdl.so.1\n0xff200000      /usr/lib/libc.so.1\n0xff330000      /usr/platform/SUNW,Sun-Blade-100/lib/libc_psr.so.1\n0xfe000000      /usr/j2se/jre/lib/sparc/client/libjvm.so\n0xff2e0000      /usr/lib/libCrun.so.1\n0xff1e0000      /usr/lib/libsocket.so.1\n0xff100000      /usr/lib/libnsl.so.1\n0xff0d0000      /usr/lib/libm.so.1\n0xff310000      /usr/lib/libw.so.1\n0xff0b0000      /usr/lib/libmp.so.2\n0xff080000      /usr/j2se/jre/lib/sparc/native_threads/libhpi.so\n0xff050000      /usr/j2se/jre/lib/sparc/libverify.so\n0xfe7c0000      /usr/j2se/jre/lib/sparc/libjava.so\n0xff030000      /usr/j2se/jre/lib/sparc/libzip.so\n0xfc470000      /usr/j2se/jre/lib/sparc/libnet.so\n0xfdf90000      /usr/j2se/jre/lib/sparc/libnio.so\n0xfdee0000      /usr/lib/librt.so.1\n0xfc450000      /usr/lib/libaio.so.1\n0xfa290000\n/usr/eclipse/plugins/org.eclipse.swt.motif_3.0.1/os/solaris/sparc/libswt-mot\nif-3063.so\n0xf0c00000      /usr/lib/libXm.so.4\n0xfa190000      /usr/openwin/lib/libXt.so.4\n0xf0b00000      /usr/openwin/lib/libX11.so.4\n0xfa0e0000      /usr/openwin/lib/libXp.so.1\n0xfa0c0000      /usr/openwin/lib/libXtst.so.1\n0xfa0a0000      /usr/openwin/lib/libSM.so.6\n0xfa070000      /usr/openwin/lib/libICE.so.6\n0xfa040000      /usr/openwin/lib/libXext.so.0\n0xfa010000      /usr/openwin/lib/libdga.so.1\n0xf1fd0000      /usr/lib//liblayout.so\n\nLocal Time \u003d Wed Oct  6 17:12:40 2004\nElapsed Time \u003d 429\n#\n# The exception above was detected in native code outside the VM\n#\n# Java VM: Java HotSpot(TM) Client VM (1.4.1_02-b06 mixed mode)\n#\n-bash-2.05b$\n",
    "Reopening",
    "Failure seems to be coming from SWT. Moving to SWT for comment.",
    "I can reproduce this in 3.0.1 and the 3.1 stream, happens on Solaris 8 only.\n",
    "This problem happens on Debian, kernel 2.6 with the latest 3.1 SDKs (JDK  \n1.4.2_07, Eclipse SDK 3.1.I20050202-0800) too:  \n  \nEclipse alerts this:  \n  \nJVM terminated. Exit code\u003d255  \n/usr/bin/java  \n-Djava.endorsed.dirs\u003d/appz/eclipse-jars/org.xerces_2.6.2  \n-jar /usr/local/eclipse3.1I050202/eclipse/startup.jar  \n-os linux  \n-ws gtk  \n-arch x86  \n-launcher /usr/local/eclipse3.1I050202/eclipse/eclipse  \n-name Eclipse  \n-showsplash 600  \n-exitdata 3680006  \n-data /home/nboldt/workspace  \n-vm /usr/bin/java  \n-vmargs  \n-Djava.endorsed.dirs\u003d/appz/eclipse-jars/org.xerces_2.6.2  \n-jar /usr/local/eclipse3.1I050202/eclipse/startup.jar   \n   \nAnd to console I get this:  \n   \n# HotSpot Virtual Machine Error, Internal Error   \n# Please report this error at   \n# http://java.sun.com/cgi-bin/bugreport.cgi   \n#   \n# Java VM: Java HotSpot(TM) Client VM (1.4.2_07-b05 mixed mode)   \n#   \n# Error ID: 43113F32554E54494D45110E4350500308   \n#   \n# Problematic Thread: prio\u003d1 tid\u003d0x0805bce0 nid\u003d0x3326 runnable   \n#   \n   \nHeap at VM Abort:   \nHeap   \n def new generation   total 1280K, used 343K [0x45290000, 0x453f0000,   \n0x45770000)   \n  eden space 1152K,  26% used [0x45290000, 0x452db1b0, 0x453b0000)   \n  from space 128K,  33% used [0x453d0000, 0x453daac0, 0x453f0000)   \n  to   space 128K,   0% used [0x453b0000, 0x453b0000, 0x453d0000)   \n tenured generation   total 16008K, used 11613K [0x45770000, 0x46712000,   \n0x49290000)   \n   the space 16008K,  72% used [0x45770000, 0x462c75e8, 0x462c7600,   \n0x46712000)   \n compacting perm gen  total 19712K, used 19683K [0x49290000, 0x4a5d0000,   \n0x4d290000)   \n   the space 19712K,  99% used [0x49290000, 0x4a5c8da0, 0x4a5c8e00,   \n0x4a5d0000)   \n[error occured during error reporting]   \n  \nThe .log contains: \n \n!SESSION 2005-02-09 14:38:55.113 \n----------------------------------------------- \neclipse.buildId\u003dI20050202-0800 \njava.version\u003d1.4.2_07 \njava.vendor\u003dSun Microsystems Inc. \nBootLoader constants: OS\u003dlinux, ARCH\u003dx86, WS\u003dgtk, NL\u003den_US \nCommand-line arguments:  -os linux -ws gtk -arch x86 \n-data /home/nboldt/workspace \n \n!ENTRY org.eclipse.team.cvs.ui 4 0 2005-02-09 14:38:55.115 \n!MESSAGE Internal error \n!STACK 1 \norg.eclipse.team.internal.ccvs.core.CVSException: Only the following methods \nare supported: extssh, pserver, ext \n at \norg.eclipse.team.internal.ccvs.core.connection.CVSRepositoryLocation.fromProperties(CVSRepositoryLocation.java:212) \n at \norg.eclipse.team.internal.ccvs.ui.repo.CVSRepositoryPropertiesPage.validateFields(CVSRepositoryPropertiesPage.java:527) \n at \norg.eclipse.team.internal.ccvs.ui.repo.CVSRepositoryPropertiesPage.updateWidgetEnablements(CVSRepositoryPropertiesPage.java:490) \n at \norg.eclipse.team.internal.ccvs.ui.repo.CVSRepositoryPropertiesPage$3.handleEvent(CVSRepositoryPropertiesPage.java:177) \n at org.eclipse.swt.widgets.EventTable.sendEvent(EventTable.java:82) \n at org.eclipse.swt.widgets.Widget.sendEvent(Widget.java:1007) \n at org.eclipse.swt.widgets.Widget.sendEvent(Widget.java:1031) \n at org.eclipse.swt.widgets.Widget.sendEvent(Widget.java:1012) \n at org.eclipse.swt.widgets.Combo.gtk_changed(Combo.java:863) \n at org.eclipse.swt.widgets.Widget.windowProc(Widget.java:1304) \n at org.eclipse.swt.widgets.Display.windowProc(Display.java:3259) \n at org.eclipse.swt.internal.gtk.OS._gtk_main_do_event(Native Method) \n at org.eclipse.swt.internal.gtk.OS.gtk_main_do_event(OS.java:4660) \n at org.eclipse.swt.widgets.Display.eventProc(Display.java:926) \n at org.eclipse.swt.internal.gtk.OS._g_main_context_iteration(Native \nMethod) \n at \norg.eclipse.swt.internal.gtk.OS.g_main_context_iteration(OS.java:1104) \n at org.eclipse.swt.widgets.Display.readAndDispatch(Display.java:2419) \n at org.eclipse.jface.window.Window.runEventLoop(Window.java:718) \n at org.eclipse.jface.window.Window.open(Window.java:696) \n at \norg.eclipse.ui.dialogs.PropertyDialogAction.run(PropertyDialogAction.java:140) \n at org.eclipse.jface.action.Action.runWithEvent(Action.java:989) \n at \norg.eclipse.jface.action.ActionContributionItem.handleWidgetSelection(ActionContributionItem.java:557) \n at org.eclipse.jface.action.ActionContributionItem.access$2\n(ActionContributionItem.java:507) \n at \norg.eclipse.jface.action.ActionContributionItem$6.handleEvent(ActionContributionItem.java:421) \n at org.eclipse.swt.widgets.EventTable.sendEvent(EventTable.java:82) \n at org.eclipse.swt.widgets.Widget.sendEvent(Widget.java:1007) \n at \norg.eclipse.swt.widgets.Display.runDeferredEvents(Display.java:2722) \n at org.eclipse.swt.widgets.Display.readAndDispatch(Display.java:2421) \n at org.eclipse.ui.internal.Workbench.runEventLoop(Workbench.java:1585) \n at org.eclipse.ui.internal.Workbench.runUI(Workbench.java:1551) \n at \norg.eclipse.ui.internal.Workbench.createAndRunWorkbench(Workbench.java:290) \n at \norg.eclipse.ui.PlatformUI.createAndRunWorkbench(PlatformUI.java:144) \n at \norg.eclipse.ui.internal.ide.IDEApplication.run(IDEApplication.java:102) \n at \norg.eclipse.core.internal.runtime.PlatformActivator$1.run(PlatformActivator.java:227) \n at \norg.eclipse.core.runtime.adaptor.EclipseStarter.run(EclipseStarter.java:276) \n at \norg.eclipse.core.runtime.adaptor.EclipseStarter.run(EclipseStarter.java:131) \n at sun.reflect.NativeMethodAccessorImpl.invoke0(Native Method) \n at \nsun.reflect.NativeMethodAccessorImpl.invoke(NativeMethodAccessorImpl.java:39) \n at \nsun.reflect.DelegatingMethodAccessorImpl.invoke(DelegatingMethodAccessorImpl.java:25) \n at java.lang.reflect.Method.invoke(Method.java:324) \n at org.eclipse.core.launcher.Main.basicRun(Main.java:261) \n at org.eclipse.core.launcher.Main.run(Main.java:817) \n at org.eclipse.core.launcher.Main.main(Main.java:801) \n!SUBENTRY 1 org.eclipse.team.cvs.core 4 -6 2005-02-09 14:38:55.118 \n!MESSAGE Only the following methods are supported: extssh, pserver, ext \n ",
    "Nick your problem is different, and I notice that you\u0027re running with gtk not \nmotif.  If you have steps that reproduce this reliably then please log a new \nreport with Platform - SWT, thanks.\n",
    "test snippet:\n\npublic static void main(String[] args) {\n\tfinal Display display \u003d new Display();\n\tShell shell \u003d new Shell(display);\n\tshell.setBounds(10,10,200,200);\n\tComposite composite \u003d new Composite(shell, SWT.BORDER);\n\tcomposite.setBounds(10,10,100,100);\n\tcomposite.addListener(SWT.MouseDown, new Listener() {\n\t\tpublic void handleEvent(Event event) {\n\t\t\tlong start \u003d System.currentTimeMillis();\n\t\t\tlong current \u003d start;\n\t\t\twhile (current - start \u003c 50) {\t/* dispatch for at \nleast 50ms */\n\t\t\t\tif (!display.readAndDispatch()) display.sleep();\n\t\t\t\tcurrent \u003d System.currentTimeMillis();\n\t\t\t}\n\t\t}\n\t});\n\tMenu menu \u003d new Menu(shell, SWT.POP_UP);\n\tcomposite.setMenu(menu);\n\tnew MenuItem(menu, SWT.NONE);\n\tshell.open();\n\twhile (!shell.isDisposed()) {\n\t\tif (!display.readAndDispatch()) display.sleep();\n\t}\n\tdisplay.dispose();\n}\n",
    "fixed \u003e 0505 with SSQ\n"
  ],
  "commentCreationDates": [
    "2004-10-20T08:02:10+02:00",
    "2004-10-20T15:19:02+02:00",
    "2004-10-20T16:13:28+02:00",
    "2004-10-20T16:46:25+02:00",
    "2004-10-20T18:23:54+02:00",
    "2004-10-20T18:33:01+02:00",
    "2004-10-20T18:33:39+02:00",
    "2004-10-21T22:26:41+02:00",
    "2005-02-09T19:44:40+01:00",
    "2005-02-09T20:50:06+01:00",
    "2005-05-05T20:47:32+02:00",
    "2005-05-05T20:48:16+02:00"
  ],
  "traces": [
    {
      "exceptionType": "org.eclipse.team.internal.ccvs.core.CVSException",
      "message": "Only the following methods  are supported: extssh, pserver, ext",
      "elements": [
        {
          "method": "org.eclipse.team.internal.ccvs.core.connection.CVSRepositoryLocation.fromProperties",
          "source": "CVSRepositoryLocation.java:212"
        },
        {
          "method": "org.eclipse.team.internal.ccvs.ui.repo.CVSRepositoryPropertiesPage.validateFields",
          "source": "CVSRepositoryPropertiesPage.java:527"
        },
        {
          "method": "org.eclipse.team.internal.ccvs.ui.repo.CVSRepositoryPropertiesPage.updateWidgetEnablements",
          "source": "CVSRepositoryPropertiesPage.java:490"
        },
        {
          "method": "org.eclipse.team.internal.ccvs.ui.repo.CVSRepositoryPropertiesPage$3.handleEvent",
          "source": "CVSRepositoryPropertiesPage.java:177"
        },
        {
          "method": "org.eclipse.swt.widgets.EventTable.sendEvent",
          "source": "EventTable.java:82"
        },
        {
          "method": "org.eclipse.swt.widgets.Widget.sendEvent",
          "source": "Widget.java:1007"
        },
        {
          "method": "org.eclipse.swt.widgets.Widget.sendEvent",
          "source": "Widget.java:1031"
        },
        {
          "method": "org.eclipse.swt.widgets.Widget.sendEvent",
          "source": "Widget.java:1012"
        },
        {
          "method": "org.eclipse.swt.widgets.Combo.gtk_changed",
          "source": "Combo.java:863"
        },
        {
          "method": "org.eclipse.swt.widgets.Widget.windowProc",
          "source": "Widget.java:1304"
        },
        {
          "method": "org.eclipse.swt.widgets.Display.windowProc",
          "source": "Display.java:3259"
        },
        {
          "method": "org.eclipse.swt.internal.gtk.OS._gtk_main_do_event",
          "source": "Native Method"
        },
        {
          "method": "org.eclipse.swt.internal.gtk.OS.gtk_main_do_event",
          "source": "OS.java:4660"
        },
        {
          "method": "org.eclipse.swt.widgets.Display.eventProc",
          "source": "Display.java:926"
        },
        {
          "method": "org.eclipse.swt.internal.gtk.OS._g_main_context_iteration",
          "source": "Native  Method"
        },
        {
          "method": "org.eclipse.swt.internal.gtk.OS.g_main_context_iteration",
          "source": "OS.java:1104"
        },
        {
          "method": "org.eclipse.swt.widgets.Display.readAndDispatch",
          "source": "Display.java:2419"
        },
        {
          "method": "org.eclipse.jface.window.Window.runEventLoop",
          "source": "Window.java:718"
        },
        {
          "method": "org.eclipse.jface.window.Window.open",
          "source": "Window.java:696"
        },
        {
          "method": "org.eclipse.ui.dialogs.PropertyDialogAction.run",
          "source": "PropertyDialogAction.java:140"
        },
        {
          "method": "org.eclipse.jface.action.Action.runWithEvent",
          "source": "Action.java:989"
        },
        {
          "method": "org.eclipse.jface.action.ActionContributionItem.handleWidgetSelection",
          "source": "ActionContributionItem.java:557"
        },
        {
          "method": "org.eclipse.jface.action.ActionContributionItem.access$2",
          "source": "ActionContributionItem.java:507"
        },
        {
          "method": "org.eclipse.jface.action.ActionContributionItem$6.handleEvent",
          "source": "ActionContributionItem.java:421"
        },
        {
          "method": "org.eclipse.swt.widgets.EventTable.sendEvent",
          "source": "EventTable.java:82"
        },
        {
          "method": "org.eclipse.swt.widgets.Widget.sendEvent",
          "source": "Widget.java:1007"
        },
        {
          "method": "org.eclipse.swt.widgets.Display.runDeferredEvents",
          "source": "Display.java:2722"
        },
        {
          "method": "org.eclipse.swt.widgets.Display.readAndDispatch",
          "source": "Display.java:2421"
        },
        {
          "method": "org.eclipse.ui.internal.Workbench.runEventLoop",
          "source": "Workbench.java:1585"
        },
        {
          "method": "org.eclipse.ui.internal.Workbench.runUI",
          "source": "Workbench.java:1551"
        },
        {
          "method": "org.eclipse.ui.internal.Workbench.createAndRunWorkbench",
          "source": "Workbench.java:290"
        },
        {
          "method": "org.eclipse.ui.PlatformUI.createAndRunWorkbench",
          "source": "PlatformUI.java:144"
        },
        {
          "method": "org.eclipse.ui.internal.ide.IDEApplication.run",
          "source": "IDEApplication.java:102"
        },
        {
          "method": "org.eclipse.core.internal.runtime.PlatformActivator$1.run",
          "source": "PlatformActivator.java:227"
        },
        {
          "method": "org.eclipse.core.runtime.adaptor.EclipseStarter.run",
          "source": "EclipseStarter.java:276"
        },
        {
          "method": "org.eclipse.core.runtime.adaptor.EclipseStarter.run",
          "source": "EclipseStarter.java:131"
        },
        {
          "method": "sun.reflect.NativeMethodAccessorImpl.invoke0",
          "source": "Native Method"
        },
        {
          "method": "sun.reflect.NativeMethodAccessorImpl.invoke",
          "source": "NativeMethodAccessorImpl.java:39"
        },
        {
          "method": "sun.reflect.DelegatingMethodAccessorImpl.invoke",
          "source": "DelegatingMethodAccessorImpl.java:25"
        },
        {
          "method": "java.lang.reflect.Method.invoke",
          "source": "Method.java:324"
        },
        {
          "method": "org.eclipse.core.launcher.Main.basicRun",
          "source": "Main.java:261"
        },
        {
          "method": "org.eclipse.core.launcher.Main.run",
          "source": "Main.java:817"
        },
        {
          "method": "org.eclipse.core.launcher.Main.main",
          "source": "Main.java:801"
        }
      ],
      "number": 0,
      "commentIndex": 8,
      "bugId": "76628",
      "date": "2005-02-09T19:44:40+01:00",
      "product": "Platform",
      "component": "SWT",
      "severity": "normal"
    }
  ],
  "groupId": "76628",
  "bugId": "76628",
  "date": "2004-10-20T08:02:10+02:00",
  "product": "Platform",
  "component": "SWT",
  "severity": "normal"
}