{
  "comments": [
    "I\u0027ve installed eclipse 3.01 for Solaris in my home directory for evaluation.\nI installed this from the following zip file:\n\neclipse-SDK-3.0.1-solaris-motif.zip \n\nI\u0027m running on Solaris 9 with the following environment settings:\n\nexport JAVA_HOME\u003d/opt/jdk1.4.2_04\nexport PATH\u003d$JAVA_HOME/bin:$PATH\n\nThen I do the following:\n\ncd ~/eclipse\neclipse -Xmx256M\n\nI see the splash screen, followed by a popup which states:\n\n\"An error has occurred.  See the log file: \u003chome-\ndir\u003e/configuration/1098742437488.log\"\n\nThe content of that file is shown below.\nAfter clicking \"OK\" eclipse exits.\n\nReid Madsen\n\n::::::::::::::\nconfiguration/1098742437488.log\n::::::::::::::\n!SESSION Oct 25, 2004 17:13:59.230 --------------------------------------------\n-\neclipse.buildId\u003dM200409161125\njava.version\u003d1.4.2_04\njava.vendor\u003dSun Microsystems Inc.\nBootLoader constants: OS\u003dsolaris, ARCH\u003dsparc, WS\u003dmotif, NL\u003den\nCommand-line arguments: -Xmx512m\n\n!ENTRY org.eclipse.osgi Oct 25, 2004 17:13:59.233\n!MESSAGE Application error\n!STACK 1\njava.lang.IllegalArgumentException: Argument cannot be null\n        at org.eclipse.swt.SWT.error(SWT.java:2677)\n        at org.eclipse.swt.SWT.error(SWT.java:2616)\n        at org.eclipse.swt.SWT.error(SWT.java:2587)\n        at org.eclipse.swt.graphics.Font.\u003cinit\u003e(Font.java:106)\n        at org.eclipse.jface.resource.FontRegistry.calculateDefaultFont\n(FontRegistry.java:412)\n        at org.eclipse.jface.resource.FontRegistry.defaultFontRecord\n(FontRegistry.java:430)\n        at org.eclipse.jface.resource.FontRegistry.getFontRecord\n(FontRegistry.java:519)\n        at org.eclipse.jface.resource.FontRegistry.get(FontRegistry.java:472)\n        at org.eclipse.jface.resource.JFaceResources.getDialogFont\n(JFaceResources.java:182)\n        at org.eclipse.jface.dialogs.Dialog.initializeDialogUnits\n(Dialog.java:778)\n        at org.eclipse.jface.dialogs.TitleAreaDialog.createContents\n(TitleAreaDialog.java:93)\n        at org.eclipse.jface.window.Window.create(Window.java:348)\n        at org.eclipse.jface.dialogs.Dialog.create(Dialog.java:925)\n        at org.eclipse.jface.window.Window.open(Window.java:637)\n        at org.eclipse.ui.internal.ide.ChooseWorkspaceDialog.prompt\n(ChooseWorkspaceDialog.java:65)\n        at org.eclipse.ui.internal.ide.IDEApplication.promptForWorkspace\n(IDEApplication.java:314)\n        at org.eclipse.ui.internal.ide.IDEApplication.checkInstanceLocation\n(IDEApplication.java:219)\n        at org.eclipse.ui.internal.ide.IDEApplication.run\n(IDEApplication.java:83)\n        at org.eclipse.core.internal.runtime.PlatformActivator$1.run\n(PlatformActivator.java:335)\n        at org.eclipse.core.runtime.adaptor.EclipseStarter.run\n(EclipseStarter.java:273)\n        at org.eclipse.core.runtime.adaptor.EclipseStarter.run\n(EclipseStarter.java:129)\n        at sun.reflect.NativeMethodAccessorImpl.invoke0(Native Method)\n        at sun.reflect.NativeMethodAccessorImpl.invoke\n(NativeMethodAccessorImpl.java:39)\n        at sun.reflect.DelegatingMethodAccessorImpl.invoke\n(DelegatingMethodAccessorImpl.java:25)\n        at java.lang.reflect.Method.invoke(Method.java:324)\n        at org.eclipse.core.launcher.Main.basicRun(Main.java:185)\n        at org.eclipse.core.launcher.Main.run(Main.java:704)\n        at org.eclipse.core.launcher.Main.main(Main.java:688)",
    "\n\n*** This bug has been marked as a duplicate of 76456 ***"
  ],
  "commentCreationDates": [
    "2004-10-26T01:33:08+02:00",
    "2004-10-26T15:48:45+02:00"
  ],
  "traces": [
    {
      "exceptionType": "java.lang.IllegalArgumentException",
      "message": "Argument cannot be null",
      "elements": [
        {
          "method": "org.eclipse.swt.SWT.error",
          "source": "SWT.java:2677"
        },
        {
          "method": "org.eclipse.swt.SWT.error",
          "source": "SWT.java:2616"
        },
        {
          "method": "org.eclipse.swt.SWT.error",
          "source": "SWT.java:2587"
        },
        {
          "method": "org.eclipse.swt.graphics.Font.\u003cinit\u003e",
          "source": "Font.java:106"
        },
        {
          "method": "org.eclipse.jface.resource.FontRegistry.calculateDefaultFont",
          "source": "FontRegistry.java:412"
        },
        {
          "method": "org.eclipse.jface.resource.FontRegistry.defaultFontRecord",
          "source": "FontRegistry.java:430"
        },
        {
          "method": "org.eclipse.jface.resource.FontRegistry.getFontRecord",
          "source": "FontRegistry.java:519"
        },
        {
          "method": "org.eclipse.jface.resource.FontRegistry.get",
          "source": "FontRegistry.java:472"
        },
        {
          "method": "org.eclipse.jface.resource.JFaceResources.getDialogFont",
          "source": "JFaceResources.java:182"
        },
        {
          "method": "org.eclipse.jface.dialogs.Dialog.initializeDialogUnits",
          "source": "Dialog.java:778"
        },
        {
          "method": "org.eclipse.jface.dialogs.TitleAreaDialog.createContents",
          "source": "TitleAreaDialog.java:93"
        },
        {
          "method": "org.eclipse.jface.window.Window.create",
          "source": "Window.java:348"
        },
        {
          "method": "org.eclipse.jface.dialogs.Dialog.create",
          "source": "Dialog.java:925"
        },
        {
          "method": "org.eclipse.jface.window.Window.open",
          "source": "Window.java:637"
        },
        {
          "method": "org.eclipse.ui.internal.ide.ChooseWorkspaceDialog.prompt",
          "source": "ChooseWorkspaceDialog.java:65"
        },
        {
          "method": "org.eclipse.ui.internal.ide.IDEApplication.promptForWorkspace",
          "source": "IDEApplication.java:314"
        },
        {
          "method": "org.eclipse.ui.internal.ide.IDEApplication.checkInstanceLocation",
          "source": "IDEApplication.java:219"
        },
        {
          "method": "org.eclipse.ui.internal.ide.IDEApplication.run",
          "source": "IDEApplication.java:83"
        },
        {
          "method": "org.eclipse.core.internal.runtime.PlatformActivator$1.run",
          "source": "PlatformActivator.java:335"
        },
        {
          "method": "org.eclipse.core.runtime.adaptor.EclipseStarter.run",
          "source": "EclipseStarter.java:273"
        },
        {
          "method": "org.eclipse.core.runtime.adaptor.EclipseStarter.run",
          "source": "EclipseStarter.java:129"
        },
        {
          "method": "sun.reflect.NativeMethodAccessorImpl.invoke0",
          "source": "Native Method"
        },
        {
          "method": "sun.reflect.NativeMethodAccessorImpl.invoke",
          "source": "NativeMethodAccessorImpl.java:39"
        },
        {
          "method": "sun.reflect.DelegatingMethodAccessorImpl.invoke",
          "source": "DelegatingMethodAccessorImpl.java:25"
        },
        {
          "method": "java.lang.reflect.Method.invoke",
          "source": "Method.java:324"
        },
        {
          "method": "org.eclipse.core.launcher.Main.basicRun",
          "source": "Main.java:185"
        },
        {
          "method": "org.eclipse.core.launcher.Main.run",
          "source": "Main.java:704"
        },
        {
          "method": "org.eclipse.core.launcher.Main.main",
          "source": "Main.java:688"
        }
      ],
      "number": 0,
      "commentIndex": 0,
      "bugId": "76985",
      "duplicateId": "76456",
      "date": "2004-10-26T01:33:08+02:00",
      "product": "Platform",
      "component": "UI",
      "severity": "blocker"
    }
  ],
  "groupId": "76456",
  "bugId": "76985",
  "duplicateId": "76456",
  "date": "2004-10-26T01:33:08+02:00",
  "product": "Platform",
  "component": "UI",
  "severity": "blocker"
}