{
  "comments": [
    "I get \"org.eclipse.swt.SWTError: No more handles\"\nwhen having done some work inside Eclipse or at startup.\n\nI see that there are many bug reports with this error message. \nI have got it more and more often the last days, and today \nI wasn\u0027t even able to open my workspace. I get a beautiful \nerror message and the workspace is taken beautifully down, \nsaving its settings and everything. No crash in the ordinary sense. \nThe log dump is enclosed. However beautiful, I cannot do my work.\nAs I read about the other cases I read an answer that this is an OS \nproblem, Eclipse cannot do anything but exit. Well, I tried to exit \nall other applications up and running, there were actually quite a \nfew of them at the time, and the problem disappeared. My workspace \nis not particulary big. I have lots of memory (1.5GB).\n\nMay I get a comment to a question asked: As a former amateur \nWindows developer, I seem to remember that \"out of handles\" is a \nresource problem not necessarily associated to memory supply. \nThe number of handles is limited. Is that the case in Win2K as well?\nWhen you say that it is an OS problem, couldn\u0027t that be true and \nfalse at the same time? Couldn\u0027t the problem be Eclipse\u0027s use of SWT? \nOr the SWT\u0027s design itself? If handles are allocated all the time a \ncontrol is in some way \"defined\", the number of handles \nallocated could be excessive. I think there are many ways to solve \nthis problem. I know of applications that don\u0027t allocate handles before they \nare \nactually needed, e.g. when the user clicks on what looks like a control.\nA screen could just be a bitmap with what looks like a lot of controls on \nit. But that is an illusion. The control looking thing is not created as \na control until the user clicks on it. In this way the \nhandles are used more carefully and sparsely.\nI mean, I have often a lot of big applications up and going nowadays, \nbut I never get into a similar problem. Actually this problem I haven\u0027t \nencountered since back in the Win95 days. \nSo I suggest there is something intrinsic to Eclipse and/or \nSWT, caused by the way they (mis)use Windows resources.\nI would be delighted if someone could reject my suspicion.\n\nEnvironment:\n------------\nWin2K SP4 w/latest updates\nj2sdk1.4.2_06\n1.5 GB memory\n300 GB unused HD\n\n.log:\n-----\n!SESSION Oct 26, 2004 09:00:46.390 ---------------------------------------------\neclipse.buildId\u003dM200409161125\njava.version\u003d1.4.2_06\njava.vendor\u003dSun Microsystems Inc.\nBootLoader constants: OS\u003dwin32, ARCH\u003dx86, WS\u003dwin32, NL\u003den_US\nCommand-line arguments: -showlocation\n\n!ENTRY org.eclipse.ui 4 4 Oct 26, 2004 09:00:46.390\n!MESSAGE Unhandled event loop exception\n\n!ENTRY org.eclipse.ui 4 0 Oct 26, 2004 09:00:46.515\n!MESSAGE No more handles\n!STACK 0\norg.eclipse.swt.SWTError: No more handles\n\tat org.eclipse.swt.SWT.error(SWT.java:2717)\n\tat org.eclipse.swt.graphics.Image.init(Image.java:1366)\n\tat org.eclipse.swt.graphics.Image.\u003cinit\u003e(Image.java:161)\n\tat org.eclipse.swt.custom.StyledText.performPaint(StyledText.java:5676)\n\tat org.eclipse.swt.custom.StyledText.handlePaint(StyledText.java:5072)\n\tat org.eclipse.swt.custom.StyledText$7.handleEvent(StyledText.java:4752)\n\tat org.eclipse.swt.widgets.EventTable.sendEvent(EventTable.java:82)\n\tat org.eclipse.swt.widgets.Widget.sendEvent(Widget.java:796)\n\tat org.eclipse.swt.widgets.Widget.sendEvent(Widget.java:820)\n\tat org.eclipse.swt.widgets.Widget.sendEvent(Widget.java:805)\n\tat org.eclipse.swt.widgets.Composite.WM_PAINT(Composite.java:803)\n\tat org.eclipse.swt.widgets.Control.windowProc(Control.java:3020)\n\tat org.eclipse.swt.widgets.Display.windowProc(Display.java:3338)\n\tat org.eclipse.swt.internal.win32.OS.DispatchMessageW(Native Method)\n\tat org.eclipse.swt.internal.win32.OS.DispatchMessage(OS.java:1473)\n\tat org.eclipse.swt.widgets.Display.readAndDispatch(Display.java:2429)\n\tat org.eclipse.ui.internal.Workbench.runEventLoop(Workbench.java:1377)\n\tat org.eclipse.ui.internal.Workbench.runUI(Workbench.java:1348)\n\tat org.eclipse.ui.internal.Workbench.createAndRunWorkbench\n(Workbench.java:254)\n\tat org.eclipse.ui.PlatformUI.createAndRunWorkbench(PlatformUI.java:141)\n\tat org.eclipse.ui.internal.ide.IDEApplication.run\n(IDEApplication.java:96)\n\tat org.eclipse.core.internal.runtime.PlatformActivator$1.run\n(PlatformActivator.java:335)\n\tat org.eclipse.core.runtime.adaptor.EclipseStarter.run\n(EclipseStarter.java:273)\n\tat org.eclipse.core.runtime.adaptor.EclipseStarter.run\n(EclipseStarter.java:129)\n\tat sun.reflect.NativeMethodAccessorImpl.invoke0(Native Method)\n\tat sun.reflect.NativeMethodAccessorImpl.invoke\n(NativeMethodAccessorImpl.java:39)\n\tat sun.reflect.DelegatingMethodAccessorImpl.invoke\n(DelegatingMethodAccessorImpl.java:25)\n\tat java.lang.reflect.Method.invoke(Method.java:324)\n\tat org.eclipse.core.launcher.Main.basicRun(Main.java:185)\n\tat org.eclipse.core.launcher.Main.run(Main.java:704)\n\tat org.eclipse.core.launcher.Main.main(Main.java:688)",
    "The \"no more handles\" error is usually seen when the application is leaking \nresources such as GDI objects.\n\nDo you have a plain Eclipse SDK installation or do you have additional plugins \ninstalled?\n\nYou can find out who is leaking resources using the Sleak tool:\n\nhttp://dev.eclipse.org/viewcvs/index.cgi/%7Echeckout%7E/platform-swt-\nhome/dev.html#tools\n\nIt is part of the SWT design that applications must manage their own \nresources.  The reasons and philosphy are described here:\n\nhttp://www.eclipse.org/articles/swt-design-2/swt-design-2.html\n\nWe do not intend to change this design decision.  Closing this bug report as \nWONTFIX.  Please identify plugins that are leaking and report bugs against the \nowners of those plugins."
  ],
  "commentCreationDates": [
    "2004-10-26T10:34:34+02:00",
    "2004-10-26T17:07:06+02:00"
  ],
  "traces": [
    {
      "exceptionType": "org.eclipse.swt.SWTError",
      "message": "No more handles",
      "elements": [
        {
          "method": "org.eclipse.swt.SWT.error",
          "source": "SWT.java:2717"
        },
        {
          "method": "org.eclipse.swt.graphics.Image.init",
          "source": "Image.java:1366"
        },
        {
          "method": "org.eclipse.swt.graphics.Image.\u003cinit\u003e",
          "source": "Image.java:161"
        },
        {
          "method": "org.eclipse.swt.custom.StyledText.performPaint",
          "source": "StyledText.java:5676"
        },
        {
          "method": "org.eclipse.swt.custom.StyledText.handlePaint",
          "source": "StyledText.java:5072"
        },
        {
          "method": "org.eclipse.swt.custom.StyledText$7.handleEvent",
          "source": "StyledText.java:4752"
        },
        {
          "method": "org.eclipse.swt.widgets.EventTable.sendEvent",
          "source": "EventTable.java:82"
        },
        {
          "method": "org.eclipse.swt.widgets.Widget.sendEvent",
          "source": "Widget.java:796"
        },
        {
          "method": "org.eclipse.swt.widgets.Widget.sendEvent",
          "source": "Widget.java:820"
        },
        {
          "method": "org.eclipse.swt.widgets.Widget.sendEvent",
          "source": "Widget.java:805"
        },
        {
          "method": "org.eclipse.swt.widgets.Composite.WM_PAINT",
          "source": "Composite.java:803"
        },
        {
          "method": "org.eclipse.swt.widgets.Control.windowProc",
          "source": "Control.java:3020"
        },
        {
          "method": "org.eclipse.swt.widgets.Display.windowProc",
          "source": "Display.java:3338"
        },
        {
          "method": "org.eclipse.swt.internal.win32.OS.DispatchMessageW",
          "source": "Native Method"
        },
        {
          "method": "org.eclipse.swt.internal.win32.OS.DispatchMessage",
          "source": "OS.java:1473"
        },
        {
          "method": "org.eclipse.swt.widgets.Display.readAndDispatch",
          "source": "Display.java:2429"
        },
        {
          "method": "org.eclipse.ui.internal.Workbench.runEventLoop",
          "source": "Workbench.java:1377"
        },
        {
          "method": "org.eclipse.ui.internal.Workbench.runUI",
          "source": "Workbench.java:1348"
        },
        {
          "method": "org.eclipse.ui.internal.Workbench.createAndRunWorkbench",
          "source": "Workbench.java:254"
        },
        {
          "method": "org.eclipse.ui.PlatformUI.createAndRunWorkbench",
          "source": "PlatformUI.java:141"
        },
        {
          "method": "org.eclipse.ui.internal.ide.IDEApplication.run",
          "source": "IDEApplication.java:96"
        },
        {
          "method": "org.eclipse.core.internal.runtime.PlatformActivator$1.run",
          "source": "PlatformActivator.java:335"
        },
        {
          "method": "org.eclipse.core.runtime.adaptor.EclipseStarter.run",
          "source": "EclipseStarter.java:273"
        },
        {
          "method": "org.eclipse.core.runtime.adaptor.EclipseStarter.run",
          "source": "EclipseStarter.java:129"
        },
        {
          "method": "sun.reflect.NativeMethodAccessorImpl.invoke0",
          "source": "Native Method"
        },
        {
          "method": "sun.reflect.NativeMethodAccessorImpl.invoke",
          "source": "NativeMethodAccessorImpl.java:39"
        },
        {
          "method": "sun.reflect.DelegatingMethodAccessorImpl.invoke",
          "source": "DelegatingMethodAccessorImpl.java:25"
        },
        {
          "method": "java.lang.reflect.Method.invoke",
          "source": "Method.java:324"
        },
        {
          "method": "org.eclipse.core.launcher.Main.basicRun",
          "source": "Main.java:185"
        },
        {
          "method": "org.eclipse.core.launcher.Main.run",
          "source": "Main.java:704"
        },
        {
          "method": "org.eclipse.core.launcher.Main.main",
          "source": "Main.java:688"
        }
      ],
      "number": 0,
      "commentIndex": 0,
      "bugId": "76997",
      "date": "2004-10-26T10:34:34+02:00",
      "product": "Platform",
      "component": "SWT",
      "severity": "major"
    }
  ],
  "groupId": "76997",
  "bugId": "76997",
  "date": "2004-10-26T10:34:34+02:00",
  "product": "Platform",
  "component": "SWT",
  "severity": "major"
}