{
  "comments": [
    "I am trying to get an existing C++ project into eclipse under Linux, but  I keep\ngetting an error message saying \"Project cannot be created\" \"Reason: Errors\noccurred while refreshing resources with the local file system\"\n\nWhen I look at the details it says \":n is an invalid resource name.\".\n\nI\u0027m using Eclipse 3.0.1 on Redhat Linux 8.0 with Java 1.5.0.\n\nI can create a project from a subdirectory but not from the top where I want to\ncreate it. I also tried creating a Simple project and the results were the same,\nso it is not specific to the C/C++ support.\n\nI also tried Eclipse on Windows via a Samba share and it worked fine.\n\nFrom the .log:\n!SESSION Oct 27, 2004 15:33:28.249 ---------------------------------------------\neclipse.buildId\u003dM200409161125\njava.version\u003d1.5.0\njava.vendor\u003dSun Microsystems Inc.\nBootLoader constants: OS\u003dlinux, ARCH\u003dx86, WS\u003dgtk, NL\u003den_AU\n\n!ENTRY org.eclipse.cdt.ui 4 4 Oct 27, 2004 15:33:28.252\n!MESSAGE Error\n!STACK 1\norg.eclipse.core.internal.resources.ResourceException: Errors occurred while ref\nreshing resources with the local file system.\n        at org.eclipse.core.internal.localstore.FileSystemResourceManager.refres\nhResource(FileSystemResourceManager.java:625)\n        at org.eclipse.core.internal.localstore.FileSystemResourceManager.refres\nh(FileSystemResourceManager.java:609)\n        at org.eclipse.core.internal.resources.Resource.refreshLocal(Resource.ja\nva:1228)\n        at org.eclipse.core.internal.resources.Project.open(Project.java:787)\n        at org.eclipse.cdt.core.CCorePlugin$3.run(CCorePlugin.java:702)\n        at org.eclipse.core.internal.resources.Workspace.run(Workspace.java:1673\n)\n        at org.eclipse.cdt.core.CCorePlugin.createCProject(CCorePlugin.java:686)\n        at org.eclipse.cdt.ui.wizards.NewCProjectWizard.createNewProject(NewCPro\njectWizard.java:300)\n        at org.eclipse.cdt.ui.wizards.NewCProjectWizard.doRun(NewCProjectWizard.\njava:259)\n        at org.eclipse.cdt.make.ui.wizards.NewMakeProjectWizard.doRun(NewMakePro\njectWizard.java:51)\n        at org.eclipse.cdt.make.ui.wizards.NewMakeCCProjectWizard.doRun(NewMakeC\nCProjectWizard.java:49)\n        at org.eclipse.cdt.ui.wizards.NewCProjectWizard$1.run(NewCProjectWizard.\njava:220)\n        at org.eclipse.ui.actions.WorkspaceModifyDelegatingOperation.execute(Wor\nkspaceModifyDelegatingOperation.java:67)\n        at org.eclipse.ui.actions.WorkspaceModifyOperation$1.run(WorkspaceModify\nOperation.java:91)\n        at org.eclipse.core.internal.resources.Workspace.run(Workspace.java:1673\n)\n        at org.eclipse.ui.actions.WorkspaceModifyOperation.run(WorkspaceModifyOp\neration.java:105)\n        at org.eclipse.jface.operation.ModalContext.runInCurrentThread(ModalCont\next.java:303)\n        at org.eclipse.jface.operation.ModalContext.run(ModalContext.java:253)\n        at org.eclipse.jface.wizard.WizardDialog.run(WizardDialog.java:752)\n        at org.eclipse.cdt.ui.wizards.NewCProjectWizard.invokeRunnable(NewCProje\nctWizard.java:238)\n        at org.eclipse.cdt.ui.wizards.NewCProjectWizard.performFinish(NewCProjec\ntWizard.java:161)\n        at org.eclipse.jface.wizard.WizardDialog.finishPressed(WizardDialog.java\n:609)\n        at org.eclipse.jface.wizard.WizardDialog.buttonPressed(WizardDialog.java\n:305)\n        at org.eclipse.jface.dialogs.Dialog$2.widgetSelected(Dialog.java:506)\n        at org.eclipse.swt.widgets.TypedListener.handleEvent(TypedListener.java:\n89)\n        at org.eclipse.swt.widgets.EventTable.sendEvent(EventTable.java:82)\n        at org.eclipse.swt.widgets.Widget.sendEvent(Widget.java:954)\n        at org.eclipse.swt.widgets.Display.runDeferredEvents(Display.java:2595)\n        at org.eclipse.jface.window.Window.runEventLoop(Window.java:668)\n        at org.eclipse.jface.window.Window.open(Window.java:648)\n        at org.eclipse.ui.actions.NewProjectAction.run(NewProjectAction.java:111\n)\n        at org.eclipse.jface.action.Action.runWithEvent(Action.java:881)\n        at org.eclipse.jface.action.ActionContributionItem.handleWidgetSelection\n(ActionContributionItem.java:915)\n        at org.eclipse.jface.action.ActionContributionItem.access$2(ActionContri\nbutionItem.java:866)\n        at org.eclipse.jface.action.ActionContributionItem$7.handleEvent(ActionC\nontributionItem.java:785)\n        at org.eclipse.swt.widgets.EventTable.sendEvent(EventTable.java:82)\n        at org.eclipse.swt.widgets.Widget.sendEvent(Widget.java:954)\n        at org.eclipse.swt.widgets.Display.runDeferredEvents(Display.java:2595)\n        at org.eclipse.swt.widgets.Display.readAndDispatch(Display.java:2298)\n        at org.eclipse.ui.internal.Workbench.runEventLoop(Workbench.java:1377)\n        at org.eclipse.ui.internal.Workbench.runUI(Workbench.java:1348)\n        at org.eclipse.ui.internal.Workbench.createAndRunWorkbench(Workbench.jav\na:254)\n        at org.eclipse.ui.PlatformUI.createAndRunWorkbench(PlatformUI.java:141)\n        at org.eclipse.ui.internal.ide.IDEApplication.run(IDEApplication.java:96\n)\n        at org.eclipse.core.internal.runtime.PlatformActivator$1.run(PlatformAct\nivator.java:335)\n        at org.eclipse.core.runtime.adaptor.EclipseStarter.run(EclipseStarter.ja\nva:273)\n        at org.eclipse.core.runtime.adaptor.EclipseStarter.run(EclipseStarter.ja\nva:129)\n        at sun.reflect.NativeMethodAccessorImpl.invoke0(Native Method)\n        at sun.reflect.NativeMethodAccessorImpl.invoke(NativeMethodAccessorImpl.\njava:39)\n        at sun.reflect.DelegatingMethodAccessorImpl.invoke(DelegatingMethodAcces\nsorImpl.java:25)\n        at java.lang.reflect.Method.invoke(Method.java:585)\n        at org.eclipse.core.launcher.Main.basicRun(Main.java:185)\n        at org.eclipse.core.launcher.Main.run(Main.java:704)\n        at org.eclipse.core.launcher.Main.main(Main.java:688)\n!SUBENTRY 1 org.eclipse.core.resources 4 271 Oct 27, 2004 15:33:28.255\n!MESSAGE Errors occurred while refreshing resources with the local file system.\n!SUBENTRY 2 org.eclipse.core.resources 4 278 Oct 27, 2004 15:33:28.255\n!MESSAGE :n is an invalid resource name.",
    "Eclipse now allows for resources with a colon in the name. Please try a more\nrecent build. Thanks.\n\n*** This bug has been marked as a duplicate of 24152 ***"
  ],
  "commentCreationDates": [
    "2004-10-28T02:07:10+02:00",
    "2004-10-28T17:22:56+02:00"
  ],
  "traces": [
    {
      "exceptionType": "org.eclipse.core.internal.resources.ResourceException",
      "message": "Errors occurred while ref reshing resources with the local file system.",
      "elements": [
        {
          "method": "org.eclipse.core.internal.localstore.FileSystemResourceManager.refreshResource",
          "source": "FileSystemResourceManager.java:625"
        },
        {
          "method": "org.eclipse.core.internal.localstore.FileSystemResourceManager.refresh",
          "source": "FileSystemResourceManager.java:609"
        },
        {
          "method": "org.eclipse.core.internal.resources.Resource.refreshLocal",
          "source": "Resource.ja va:1228"
        },
        {
          "method": "org.eclipse.core.internal.resources.Project.open",
          "source": "Project.java:787"
        },
        {
          "method": "org.eclipse.cdt.core.CCorePlugin$3.run",
          "source": "CCorePlugin.java:702"
        },
        {
          "method": "org.eclipse.core.internal.resources.Workspace.run",
          "source": "Workspace.java:1673 "
        },
        {
          "method": "org.eclipse.cdt.core.CCorePlugin.createCProject",
          "source": "CCorePlugin.java:686"
        },
        {
          "method": "org.eclipse.cdt.ui.wizards.NewCProjectWizard.createNewProject",
          "source": "NewCPro jectWizard.java:300"
        },
        {
          "method": "org.eclipse.cdt.ui.wizards.NewCProjectWizard.doRun",
          "source": "NewCProjectWizard. java:259"
        },
        {
          "method": "org.eclipse.cdt.make.ui.wizards.NewMakeProjectWizard.doRun",
          "source": "NewMakePro jectWizard.java:51"
        },
        {
          "method": "org.eclipse.cdt.make.ui.wizards.NewMakeCCProjectWizard.doRun",
          "source": "NewMakeC CProjectWizard.java:49"
        },
        {
          "method": "org.eclipse.cdt.ui.wizards.NewCProjectWizard$1.run",
          "source": "NewCProjectWizard. java:220"
        },
        {
          "method": "org.eclipse.ui.actions.WorkspaceModifyDelegatingOperation.execute",
          "source": "Wor kspaceModifyDelegatingOperation.java:67"
        },
        {
          "method": "org.eclipse.ui.actions.WorkspaceModifyOperation$1.run",
          "source": "WorkspaceModify Operation.java:91"
        },
        {
          "method": "org.eclipse.core.internal.resources.Workspace.run",
          "source": "Workspace.java:1673 "
        },
        {
          "method": "org.eclipse.ui.actions.WorkspaceModifyOperation.run",
          "source": "WorkspaceModifyOp eration.java:105"
        },
        {
          "method": "org.eclipse.jface.operation.ModalContext.runInCurrentThread",
          "source": "ModalCont ext.java:303"
        },
        {
          "method": "org.eclipse.jface.operation.ModalContext.run",
          "source": "ModalContext.java:253"
        },
        {
          "method": "org.eclipse.jface.wizard.WizardDialog.run",
          "source": "WizardDialog.java:752"
        },
        {
          "method": "org.eclipse.cdt.ui.wizards.NewCProjectWizard.invokeRunnable",
          "source": "NewCProje ctWizard.java:238"
        },
        {
          "method": "org.eclipse.cdt.ui.wizards.NewCProjectWizard.performFinish",
          "source": "NewCProjec tWizard.java:161"
        },
        {
          "method": "org.eclipse.jface.wizard.WizardDialog.finishPressed",
          "source": "WizardDialog.java :609"
        },
        {
          "method": "org.eclipse.jface.wizard.WizardDialog.buttonPressed",
          "source": "WizardDialog.java :305"
        },
        {
          "method": "org.eclipse.jface.dialogs.Dialog$2.widgetSelected",
          "source": "Dialog.java:506"
        },
        {
          "method": "org.eclipse.swt.widgets.TypedListener.handleEvent",
          "source": "TypedListener.java: 89"
        },
        {
          "method": "org.eclipse.swt.widgets.EventTable.sendEvent",
          "source": "EventTable.java:82"
        },
        {
          "method": "org.eclipse.swt.widgets.Widget.sendEvent",
          "source": "Widget.java:954"
        },
        {
          "method": "org.eclipse.swt.widgets.Display.runDeferredEvents",
          "source": "Display.java:2595"
        },
        {
          "method": "org.eclipse.jface.window.Window.runEventLoop",
          "source": "Window.java:668"
        },
        {
          "method": "org.eclipse.jface.window.Window.open",
          "source": "Window.java:648"
        },
        {
          "method": "org.eclipse.ui.actions.NewProjectAction.run",
          "source": "NewProjectAction.java:111 "
        },
        {
          "method": "org.eclipse.jface.action.Action.runWithEvent",
          "source": "Action.java:881"
        },
        {
          "method": "org.eclipse.jface.action.ActionContributionItem.handleWidgetSelection",
          "source": "ActionContributionItem.java:915"
        },
        {
          "method": "org.eclipse.jface.action.ActionContributionItem.access$2",
          "source": "ActionContri butionItem.java:866"
        },
        {
          "method": "org.eclipse.jface.action.ActionContributionItem$7.handleEvent",
          "source": "ActionC ontributionItem.java:785"
        },
        {
          "method": "org.eclipse.swt.widgets.EventTable.sendEvent",
          "source": "EventTable.java:82"
        },
        {
          "method": "org.eclipse.swt.widgets.Widget.sendEvent",
          "source": "Widget.java:954"
        },
        {
          "method": "org.eclipse.swt.widgets.Display.runDeferredEvents",
          "source": "Display.java:2595"
        },
        {
          "method": "org.eclipse.swt.widgets.Display.readAndDispatch",
          "source": "Display.java:2298"
        },
        {
          "method": "org.eclipse.ui.internal.Workbench.runEventLoop",
          "source": "Workbench.java:1377"
        },
        {
          "method": "org.eclipse.ui.internal.Workbench.runUI",
          "source": "Workbench.java:1348"
        },
        {
          "method": "org.eclipse.ui.internal.Workbench.createAndRunWorkbench",
          "source": "Workbench.jav a:254"
        },
        {
          "method": "org.eclipse.ui.PlatformUI.createAndRunWorkbench",
          "source": "PlatformUI.java:141"
        },
        {
          "method": "org.eclipse.ui.internal.ide.IDEApplication.run",
          "source": "IDEApplication.java:96 "
        },
        {
          "method": "org.eclipse.core.internal.runtime.PlatformActivator$1.run",
          "source": "PlatformAct ivator.java:335"
        },
        {
          "method": "org.eclipse.core.runtime.adaptor.EclipseStarter.run",
          "source": "EclipseStarter.ja va:273"
        },
        {
          "method": "org.eclipse.core.runtime.adaptor.EclipseStarter.run",
          "source": "EclipseStarter.ja va:129"
        },
        {
          "method": "sun.reflect.NativeMethodAccessorImpl.invoke0",
          "source": "Native Method"
        },
        {
          "method": "sun.reflect.NativeMethodAccessorImpl.invoke",
          "source": "NativeMethodAccessorImpl. java:39"
        },
        {
          "method": "sun.reflect.DelegatingMethodAccessorImpl.invoke",
          "source": "DelegatingMethodAcces sorImpl.java:25"
        },
        {
          "method": "java.lang.reflect.Method.invoke",
          "source": "Method.java:585"
        },
        {
          "method": "org.eclipse.core.launcher.Main.basicRun",
          "source": "Main.java:185"
        },
        {
          "method": "org.eclipse.core.launcher.Main.run",
          "source": "Main.java:704"
        },
        {
          "method": "org.eclipse.core.launcher.Main.main",
          "source": "Main.java:688"
        }
      ],
      "number": 0,
      "commentIndex": 0,
      "bugId": "77162",
      "duplicateId": "24152",
      "date": "2004-10-28T02:07:10+02:00",
      "product": "Platform",
      "component": "Resources",
      "severity": "normal"
    }
  ],
  "groupId": "24152",
  "bugId": "77162",
  "duplicateId": "24152",
  "date": "2004-10-28T02:07:10+02:00",
  "product": "Platform",
  "component": "Resources",
  "severity": "normal"
}