{
  "comments": [
    "3.1M3 first candidate build\n\n- run eclipse with the examples\n- Window -\u003e Show View -\u003e Other...\n- select SWT Examples - Browser Demo, OK\n- the following error is spewed:\n\norg.eclipse.swt.SWTError: No more handles\n        at org.eclipse.swt.SWT.error(SWT.java:2723)\n        at org.eclipse.swt.SWT.error(SWT.java:2622)\n        at org.eclipse.swt.SWT.error(SWT.java:2593)\n        at org.eclipse.swt.browser.Browser.\u003cinit\u003e(Browser.java:118)\n        at\norg.eclipse.swt.examples.browser.demos.views.PawnTab.\u003cinit\u003e(PawnTab.jav\na:61)\n        at\norg.eclipse.swt.examples.browser.demos.views.BrowserDemoView.createPart\nControl(BrowserDemoView.java:32)\n        at org.eclipse.ui.internal.PartPane$2.run(PartPane.java:142)\n        at\norg.eclipse.core.internal.runtime.InternalPlatform.run(InternalPlatform\n.java:616)\n        at org.eclipse.core.runtime.Platform.run(Platform.java:747)\n        at\norg.eclipse.ui.internal.PartPane.doCreateChildControl(PartPane.java:138\n)\n        at\norg.eclipse.ui.internal.ViewPane.doCreateChildControl(ViewPane.java:135\n)\n        at\norg.eclipse.ui.internal.PartPane.createChildControl(PartPane.java:343)\n        at org.eclipse.ui.internal.PartPane.createControl(PartPane.java:212)\n        at org.eclipse.ui.internal.ViewPane.createControl(ViewPane.java:124)\n        at org.eclipse.ui.internal.ViewFactory$1.run(ViewFactory.java:392)\n        at\norg.eclipse.core.internal.runtime.InternalPlatform.run(InternalPlatform\n.java:616)\n        at org.eclipse.core.runtime.Platform.run(Platform.java:747)\n        at\norg.eclipse.ui.internal.ViewFactory.busyRestoreView(ViewFactory.java:28\n4)\n        at org.eclipse.ui.internal.ViewFactory$2.run(ViewFactory.java:578)\n        at org.eclipse.swt.custom.BusyIndicator.showWhile(BusyIndicator.java:69)\n        at org.eclipse.ui.internal.ViewFactory.restoreView(ViewFactory.java:575)\n        at org.eclipse.ui.internal.Perspective.showView(Perspective.java:1697)\n        at\norg.eclipse.ui.internal.WorkbenchPage.busyShowView(WorkbenchPage.java:7\n95)\n        at\norg.eclipse.ui.internal.WorkbenchPage.access$9(WorkbenchPage.java:778)\n        at org.eclipse.ui.internal.WorkbenchPage$13.run(WorkbenchPage.java:3105)\n        at org.eclipse.swt.custom.BusyIndicator.showWhile(BusyIndicator.java:69)\n        at\norg.eclipse.ui.internal.WorkbenchPage.showView(WorkbenchPage.java:3102)\n        at\norg.eclipse.ui.internal.WorkbenchPage.showView(WorkbenchPage.java:3081)\n        at org.eclipse.ui.internal.ShowViewMenu.showOther(ShowViewMenu.java:209)\n        at org.eclipse.ui.internal.ShowViewMenu$2.run(ShowViewMenu.java:71)\n        at org.eclipse.jface.action.Action.runWithEvent(Action.java:988)\n        at\norg.eclipse.jface.action.ActionContributionItem.handleWidgetSelection(A\nctionContributionItem.java:946)\n        at\norg.eclipse.jface.action.ActionContributionItem.access$2(ActionContribu\ntionItem.java:896)\n        at\norg.eclipse.jface.action.ActionContributionItem$7.handleEvent(ActionCon\ntributionItem.java:810)\n        at org.eclipse.swt.widgets.EventTable.sendEvent(EventTable.java:82)\n        at org.eclipse.swt.widgets.Widget.sendEvent(Widget.java:734)\n        at org.eclipse.swt.widgets.Display.runDeferredEvents(Display.java:2949)\n        at org.eclipse.swt.widgets.Display.readAndDispatch(Display.java:2649)\n        at org.eclipse.ui.internal.Workbench.runEventLoop(Workbench.java:1527)\n        at org.eclipse.ui.internal.Workbench.runUI(Workbench.java:1498)\n        at\norg.eclipse.ui.internal.Workbench.createAndRunWorkbench(Workbench.java:\n276)\n        at org.eclipse.ui.PlatformUI.createAndRunWorkbench(PlatformUI.java:144)\n        at\norg.eclipse.ui.internal.ide.IDEApplication.run(IDEApplication.java:102)\n        at\norg.eclipse.core.internal.runtime.PlatformActivator$1.run(PlatformActiv\nator.java:335)\n        at\norg.eclipse.core.runtime.adaptor.EclipseStarter.run(EclipseStarter.java\n:273)\n        at\norg.eclipse.core.runtime.adaptor.EclipseStarter.run(EclipseStarter.java\n:129)\n        at sun.reflect.NativeMethodAccessorImpl.invoke0(Native Method)\n        at\nsun.reflect.NativeMethodAccessorImpl.invoke(NativeMethodAccessorImpl.ja\nva:39)\n        at\nsun.reflect.DelegatingMethodAccessorImpl.invoke(DelegatingMethodAccesso\nrImpl.java:25)\n        at java.lang.reflect.Method.invoke(Method.java:324)\n        at org.eclipse.core.launcher.Main.basicRun(Main.java:185)\n        at org.eclipse.core.launcher.Main.run(Main.java:704)\n        at org.eclipse.core.launcher.Main.main(Main.java:688)\norg.eclipse.swt.SWTError: No more handles\n        at org.eclipse.swt.SWT.error(SWT.java:2723)\n        at org.eclipse.swt.SWT.error(SWT.java:2622)\n        at org.eclipse.swt.SWT.error(SWT.java:2593)\n        at org.eclipse.swt.browser.Browser.\u003cinit\u003e(Browser.java:118)\n        at\norg.eclipse.swt.examples.browser.demos.views.EditorTab.\u003cinit\u003e(EditorTab\n.java:53)\n        at\norg.eclipse.swt.examples.browser.demos.views.BrowserDemoView.createPart\nControl(BrowserDemoView.java:35)\n        at org.eclipse.ui.internal.PartPane$2.run(PartPane.java:142)\n        at\norg.eclipse.core.internal.runtime.InternalPlatform.run(InternalPlatform\n.java:616)\n        at org.eclipse.core.runtime.Platform.run(Platform.java:747)\n        at\norg.eclipse.ui.internal.PartPane.doCreateChildControl(PartPane.java:138\n)\n        at\norg.eclipse.ui.internal.ViewPane.doCreateChildControl(ViewPane.java:135\n)\n        at\norg.eclipse.ui.internal.PartPane.createChildControl(PartPane.java:343)\n        at org.eclipse.ui.internal.PartPane.createControl(PartPane.java:212)\n        at org.eclipse.ui.internal.ViewPane.createControl(ViewPane.java:124)\n        at org.eclipse.ui.internal.ViewFactory$1.run(ViewFactory.java:392)\n        at\norg.eclipse.core.internal.runtime.InternalPlatform.run(InternalPlatform\n.java:616)\n        at org.eclipse.core.runtime.Platform.run(Platform.java:747)\n        at\norg.eclipse.ui.internal.ViewFactory.busyRestoreView(ViewFactory.java:28\n4)\n        at org.eclipse.ui.internal.ViewFactory$2.run(ViewFactory.java:578)\n        at org.eclipse.swt.custom.BusyIndicator.showWhile(BusyIndicator.java:69)\n        at org.eclipse.ui.internal.ViewFactory.restoreView(ViewFactory.java:575)\n        at org.eclipse.ui.internal.Perspective.showView(Perspective.java:1697)\n        at\norg.eclipse.ui.internal.WorkbenchPage.busyShowView(WorkbenchPage.java:7\n95)\n        at\norg.eclipse.ui.internal.WorkbenchPage.access$9(WorkbenchPage.java:778)\n        at org.eclipse.ui.internal.WorkbenchPage$13.run(WorkbenchPage.java:3105)\n        at org.eclipse.swt.custom.BusyIndicator.showWhile(BusyIndicator.java:69)\n        at\norg.eclipse.ui.internal.WorkbenchPage.showView(WorkbenchPage.java:3102)\n        at\norg.eclipse.ui.internal.WorkbenchPage.showView(WorkbenchPage.java:3081)\n        at org.eclipse.ui.internal.ShowViewMenu.showOther(ShowViewMenu.java:209)\n        at org.eclipse.ui.internal.ShowViewMenu$2.run(ShowViewMenu.java:71)\n        at org.eclipse.jface.action.Action.runWithEvent(Action.java:988)\n        at\norg.eclipse.jface.action.ActionContributionItem.handleWidgetSelection(A\nctionContributionItem.java:946)\n        at\norg.eclipse.jface.action.ActionContributionItem.access$2(ActionContribu\ntionItem.java:896)\n        at\norg.eclipse.jface.action.ActionContributionItem$7.handleEvent(ActionCon\ntributionItem.java:810)\n        at org.eclipse.swt.widgets.EventTable.sendEvent(EventTable.java:82)\n        at org.eclipse.swt.widgets.Widget.sendEvent(Widget.java:734)\n        at org.eclipse.swt.widgets.Display.runDeferredEvents(Display.java:2949)\n        at org.eclipse.swt.widgets.Display.readAndDispatch(Display.java:2649)\n        at org.eclipse.ui.internal.Workbench.runEventLoop(Workbench.java:1527)\n        at org.eclipse.ui.internal.Workbench.runUI(Workbench.java:1498)\n        at\norg.eclipse.ui.internal.Workbench.createAndRunWorkbench(Workbench.java:\n276)\n        at org.eclipse.ui.PlatformUI.createAndRunWorkbench(PlatformUI.java:144)\n        at\norg.eclipse.ui.internal.ide.IDEApplication.run(IDEApplication.java:102)\n        at\norg.eclipse.core.internal.runtime.PlatformActivator$1.run(PlatformActiv\nator.java:335)\n        at\norg.eclipse.core.runtime.adaptor.EclipseStarter.run(EclipseStarter.java\n:273)\n        at\norg.eclipse.core.runtime.adaptor.EclipseStarter.run(EclipseStarter.java\n:129)\n        at sun.reflect.NativeMethodAccessorImpl.invoke0(Native Method)\n        at\nsun.reflect.NativeMethodAccessorImpl.invoke(NativeMethodAccessorImpl.ja\nva:39)\n        at\nsun.reflect.DelegatingMethodAccessorImpl.invoke(DelegatingMethodAccesso\nrImpl.java:25)\n        at java.lang.reflect.Method.invoke(Method.java:324)\n        at org.eclipse.core.launcher.Main.basicRun(Main.java:185)\n        at org.eclipse.core.launcher.Main.run(Main.java:704)\n        at org.eclipse.core.launcher.Main.main(Main.java:688)",
    "fixed \u003ev20041104"
  ],
  "commentCreationDates": [
    "2004-11-02T17:36:55+01:00",
    "2004-11-04T21:34:32+01:00"
  ],
  "traces": [
    {
      "exceptionType": "org.eclipse.swt.SWTError",
      "message": "No more handles",
      "elements": [
        {
          "method": "org.eclipse.swt.SWT.error",
          "source": "SWT.java:2723"
        },
        {
          "method": "org.eclipse.swt.SWT.error",
          "source": "SWT.java:2622"
        },
        {
          "method": "org.eclipse.swt.SWT.error",
          "source": "SWT.java:2593"
        },
        {
          "method": "org.eclipse.swt.browser.Browser.\u003cinit\u003e",
          "source": "Browser.java:118"
        },
        {
          "method": "org.eclipse.swt.examples.browser.demos.views.PawnTab.\u003cinit\u003e",
          "source": "PawnTab.jav a:61"
        },
        {
          "method": "org.eclipse.swt.examples.browser.demos.views.BrowserDemoView.createPartControl",
          "source": "BrowserDemoView.java:32"
        },
        {
          "method": "org.eclipse.ui.internal.PartPane$2.run",
          "source": "PartPane.java:142"
        },
        {
          "method": "org.eclipse.core.internal.runtime.InternalPlatform.run",
          "source": "InternalPlatform .java:616"
        },
        {
          "method": "org.eclipse.core.runtime.Platform.run",
          "source": "Platform.java:747"
        },
        {
          "method": "org.eclipse.ui.internal.PartPane.doCreateChildControl",
          "source": "PartPane.java:138 "
        },
        {
          "method": "org.eclipse.ui.internal.ViewPane.doCreateChildControl",
          "source": "ViewPane.java:135 "
        },
        {
          "method": "org.eclipse.ui.internal.PartPane.createChildControl",
          "source": "PartPane.java:343"
        },
        {
          "method": "org.eclipse.ui.internal.PartPane.createControl",
          "source": "PartPane.java:212"
        },
        {
          "method": "org.eclipse.ui.internal.ViewPane.createControl",
          "source": "ViewPane.java:124"
        },
        {
          "method": "org.eclipse.ui.internal.ViewFactory$1.run",
          "source": "ViewFactory.java:392"
        },
        {
          "method": "org.eclipse.core.internal.runtime.InternalPlatform.run",
          "source": "InternalPlatform .java:616"
        },
        {
          "method": "org.eclipse.core.runtime.Platform.run",
          "source": "Platform.java:747"
        },
        {
          "method": "org.eclipse.ui.internal.ViewFactory.busyRestoreView",
          "source": "ViewFactory.java:28 4"
        },
        {
          "method": "org.eclipse.ui.internal.ViewFactory$2.run",
          "source": "ViewFactory.java:578"
        },
        {
          "method": "org.eclipse.swt.custom.BusyIndicator.showWhile",
          "source": "BusyIndicator.java:69"
        },
        {
          "method": "org.eclipse.ui.internal.ViewFactory.restoreView",
          "source": "ViewFactory.java:575"
        },
        {
          "method": "org.eclipse.ui.internal.Perspective.showView",
          "source": "Perspective.java:1697"
        },
        {
          "method": "org.eclipse.ui.internal.WorkbenchPage.busyShowView",
          "source": "WorkbenchPage.java:7 95"
        },
        {
          "method": "org.eclipse.ui.internal.WorkbenchPage.access$9",
          "source": "WorkbenchPage.java:778"
        },
        {
          "method": "org.eclipse.ui.internal.WorkbenchPage$13.run",
          "source": "WorkbenchPage.java:3105"
        },
        {
          "method": "org.eclipse.swt.custom.BusyIndicator.showWhile",
          "source": "BusyIndicator.java:69"
        },
        {
          "method": "org.eclipse.ui.internal.WorkbenchPage.showView",
          "source": "WorkbenchPage.java:3102"
        },
        {
          "method": "org.eclipse.ui.internal.WorkbenchPage.showView",
          "source": "WorkbenchPage.java:3081"
        },
        {
          "method": "org.eclipse.ui.internal.ShowViewMenu.showOther",
          "source": "ShowViewMenu.java:209"
        },
        {
          "method": "org.eclipse.ui.internal.ShowViewMenu$2.run",
          "source": "ShowViewMenu.java:71"
        },
        {
          "method": "org.eclipse.jface.action.Action.runWithEvent",
          "source": "Action.java:988"
        },
        {
          "method": "org.eclipse.jface.action.ActionContributionItem.handleWidgetSelection",
          "source": "A ctionContributionItem.java:946"
        },
        {
          "method": "org.eclipse.jface.action.ActionContributionItem.access$2",
          "source": "ActionContribu tionItem.java:896"
        },
        {
          "method": "org.eclipse.jface.action.ActionContributionItem$7.handleEvent",
          "source": "ActionCon tributionItem.java:810"
        },
        {
          "method": "org.eclipse.swt.widgets.EventTable.sendEvent",
          "source": "EventTable.java:82"
        },
        {
          "method": "org.eclipse.swt.widgets.Widget.sendEvent",
          "source": "Widget.java:734"
        },
        {
          "method": "org.eclipse.swt.widgets.Display.runDeferredEvents",
          "source": "Display.java:2949"
        },
        {
          "method": "org.eclipse.swt.widgets.Display.readAndDispatch",
          "source": "Display.java:2649"
        },
        {
          "method": "org.eclipse.ui.internal.Workbench.runEventLoop",
          "source": "Workbench.java:1527"
        },
        {
          "method": "org.eclipse.ui.internal.Workbench.runUI",
          "source": "Workbench.java:1498"
        },
        {
          "method": "org.eclipse.ui.internal.Workbench.createAndRunWorkbench",
          "source": "Workbench.java: 276"
        },
        {
          "method": "org.eclipse.ui.PlatformUI.createAndRunWorkbench",
          "source": "PlatformUI.java:144"
        },
        {
          "method": "org.eclipse.ui.internal.ide.IDEApplication.run",
          "source": "IDEApplication.java:102"
        },
        {
          "method": "org.eclipse.core.internal.runtime.PlatformActivator$1.run",
          "source": "PlatformActiv ator.java:335"
        },
        {
          "method": "org.eclipse.core.runtime.adaptor.EclipseStarter.run",
          "source": "EclipseStarter.java :273"
        },
        {
          "method": "org.eclipse.core.runtime.adaptor.EclipseStarter.run",
          "source": "EclipseStarter.java :129"
        },
        {
          "method": "sun.reflect.NativeMethodAccessorImpl.invoke0",
          "source": "Native Method"
        },
        {
          "method": "sun.reflect.NativeMethodAccessorImpl.invoke",
          "source": "NativeMethodAccessorImpl.ja va:39"
        },
        {
          "method": "sun.reflect.DelegatingMethodAccessorImpl.invoke",
          "source": "DelegatingMethodAccesso rImpl.java:25"
        },
        {
          "method": "java.lang.reflect.Method.invoke",
          "source": "Method.java:324"
        },
        {
          "method": "org.eclipse.core.launcher.Main.basicRun",
          "source": "Main.java:185"
        },
        {
          "method": "org.eclipse.core.launcher.Main.run",
          "source": "Main.java:704"
        },
        {
          "method": "org.eclipse.core.launcher.Main.main",
          "source": "Main.java:688"
        }
      ],
      "number": 0,
      "commentIndex": 0,
      "bugId": "77493",
      "date": "2004-11-02T17:36:55+01:00",
      "product": "Platform",
      "component": "SWT",
      "severity": "normal"
    },
    {
      "exceptionType": "org.eclipse.swt.SWTError",
      "message": "No more handles",
      "elements": [
        {
          "method": "org.eclipse.swt.SWT.error",
          "source": "SWT.java:2723"
        },
        {
          "method": "org.eclipse.swt.SWT.error",
          "source": "SWT.java:2622"
        },
        {
          "method": "org.eclipse.swt.SWT.error",
          "source": "SWT.java:2593"
        },
        {
          "method": "org.eclipse.swt.browser.Browser.\u003cinit\u003e",
          "source": "Browser.java:118"
        },
        {
          "method": "org.eclipse.swt.examples.browser.demos.views.EditorTab.\u003cinit\u003e",
          "source": "EditorTab .java:53"
        },
        {
          "method": "org.eclipse.swt.examples.browser.demos.views.BrowserDemoView.createPartControl",
          "source": "BrowserDemoView.java:35"
        },
        {
          "method": "org.eclipse.ui.internal.PartPane$2.run",
          "source": "PartPane.java:142"
        },
        {
          "method": "org.eclipse.core.internal.runtime.InternalPlatform.run",
          "source": "InternalPlatform .java:616"
        },
        {
          "method": "org.eclipse.core.runtime.Platform.run",
          "source": "Platform.java:747"
        },
        {
          "method": "org.eclipse.ui.internal.PartPane.doCreateChildControl",
          "source": "PartPane.java:138 "
        },
        {
          "method": "org.eclipse.ui.internal.ViewPane.doCreateChildControl",
          "source": "ViewPane.java:135 "
        },
        {
          "method": "org.eclipse.ui.internal.PartPane.createChildControl",
          "source": "PartPane.java:343"
        },
        {
          "method": "org.eclipse.ui.internal.PartPane.createControl",
          "source": "PartPane.java:212"
        },
        {
          "method": "org.eclipse.ui.internal.ViewPane.createControl",
          "source": "ViewPane.java:124"
        },
        {
          "method": "org.eclipse.ui.internal.ViewFactory$1.run",
          "source": "ViewFactory.java:392"
        },
        {
          "method": "org.eclipse.core.internal.runtime.InternalPlatform.run",
          "source": "InternalPlatform .java:616"
        },
        {
          "method": "org.eclipse.core.runtime.Platform.run",
          "source": "Platform.java:747"
        },
        {
          "method": "org.eclipse.ui.internal.ViewFactory.busyRestoreView",
          "source": "ViewFactory.java:28 4"
        },
        {
          "method": "org.eclipse.ui.internal.ViewFactory$2.run",
          "source": "ViewFactory.java:578"
        },
        {
          "method": "org.eclipse.swt.custom.BusyIndicator.showWhile",
          "source": "BusyIndicator.java:69"
        },
        {
          "method": "org.eclipse.ui.internal.ViewFactory.restoreView",
          "source": "ViewFactory.java:575"
        },
        {
          "method": "org.eclipse.ui.internal.Perspective.showView",
          "source": "Perspective.java:1697"
        },
        {
          "method": "org.eclipse.ui.internal.WorkbenchPage.busyShowView",
          "source": "WorkbenchPage.java:7 95"
        },
        {
          "method": "org.eclipse.ui.internal.WorkbenchPage.access$9",
          "source": "WorkbenchPage.java:778"
        },
        {
          "method": "org.eclipse.ui.internal.WorkbenchPage$13.run",
          "source": "WorkbenchPage.java:3105"
        },
        {
          "method": "org.eclipse.swt.custom.BusyIndicator.showWhile",
          "source": "BusyIndicator.java:69"
        },
        {
          "method": "org.eclipse.ui.internal.WorkbenchPage.showView",
          "source": "WorkbenchPage.java:3102"
        },
        {
          "method": "org.eclipse.ui.internal.WorkbenchPage.showView",
          "source": "WorkbenchPage.java:3081"
        },
        {
          "method": "org.eclipse.ui.internal.ShowViewMenu.showOther",
          "source": "ShowViewMenu.java:209"
        },
        {
          "method": "org.eclipse.ui.internal.ShowViewMenu$2.run",
          "source": "ShowViewMenu.java:71"
        },
        {
          "method": "org.eclipse.jface.action.Action.runWithEvent",
          "source": "Action.java:988"
        },
        {
          "method": "org.eclipse.jface.action.ActionContributionItem.handleWidgetSelection",
          "source": "A ctionContributionItem.java:946"
        },
        {
          "method": "org.eclipse.jface.action.ActionContributionItem.access$2",
          "source": "ActionContribu tionItem.java:896"
        },
        {
          "method": "org.eclipse.jface.action.ActionContributionItem$7.handleEvent",
          "source": "ActionCon tributionItem.java:810"
        },
        {
          "method": "org.eclipse.swt.widgets.EventTable.sendEvent",
          "source": "EventTable.java:82"
        },
        {
          "method": "org.eclipse.swt.widgets.Widget.sendEvent",
          "source": "Widget.java:734"
        },
        {
          "method": "org.eclipse.swt.widgets.Display.runDeferredEvents",
          "source": "Display.java:2949"
        },
        {
          "method": "org.eclipse.swt.widgets.Display.readAndDispatch",
          "source": "Display.java:2649"
        },
        {
          "method": "org.eclipse.ui.internal.Workbench.runEventLoop",
          "source": "Workbench.java:1527"
        },
        {
          "method": "org.eclipse.ui.internal.Workbench.runUI",
          "source": "Workbench.java:1498"
        },
        {
          "method": "org.eclipse.ui.internal.Workbench.createAndRunWorkbench",
          "source": "Workbench.java: 276"
        },
        {
          "method": "org.eclipse.ui.PlatformUI.createAndRunWorkbench",
          "source": "PlatformUI.java:144"
        },
        {
          "method": "org.eclipse.ui.internal.ide.IDEApplication.run",
          "source": "IDEApplication.java:102"
        },
        {
          "method": "org.eclipse.core.internal.runtime.PlatformActivator$1.run",
          "source": "PlatformActiv ator.java:335"
        },
        {
          "method": "org.eclipse.core.runtime.adaptor.EclipseStarter.run",
          "source": "EclipseStarter.java :273"
        },
        {
          "method": "org.eclipse.core.runtime.adaptor.EclipseStarter.run",
          "source": "EclipseStarter.java :129"
        },
        {
          "method": "sun.reflect.NativeMethodAccessorImpl.invoke0",
          "source": "Native Method"
        },
        {
          "method": "sun.reflect.NativeMethodAccessorImpl.invoke",
          "source": "NativeMethodAccessorImpl.ja va:39"
        },
        {
          "method": "sun.reflect.DelegatingMethodAccessorImpl.invoke",
          "source": "DelegatingMethodAccesso rImpl.java:25"
        },
        {
          "method": "java.lang.reflect.Method.invoke",
          "source": "Method.java:324"
        },
        {
          "method": "org.eclipse.core.launcher.Main.basicRun",
          "source": "Main.java:185"
        },
        {
          "method": "org.eclipse.core.launcher.Main.run",
          "source": "Main.java:704"
        },
        {
          "method": "org.eclipse.core.launcher.Main.main",
          "source": "Main.java:688"
        }
      ],
      "number": 1,
      "commentIndex": 0,
      "bugId": "77493",
      "date": "2004-11-02T17:36:55+01:00",
      "product": "Platform",
      "component": "SWT",
      "severity": "normal"
    }
  ],
  "groupId": "77493",
  "bugId": "77493",
  "date": "2004-11-02T17:36:55+01:00",
  "product": "Platform",
  "component": "SWT",
  "severity": "normal"
}