{
  "comments": [
    "Hallo,\n\nI made some tests with CDT 2.1 RC0 and detected the following problem. \n\nWe use Eclipse / CDT on a PC with windows XP using cygwin and the Gnu tools to \ncreate applications for a small realtime kernel in a host / target environment. \nIn this scenario we also make a remote connection to a debug server on our \nrealtime target. This worked well before. \n\nNow with the actual release we receive an error, when we want to start the \ndebug session:\n\n!SUBENTRY 1 org.eclipse.cdt.launch 4 107 Nov 03, 2004 15:54:17.679\n!MESSAGE Program not Binary\n!STACK 0\njava.io.FileNotFoundException: Program not Binary\n\tat org.eclipse.cdt.launch.AbstractCLaunchDelegate.verifyBinary\n(AbstractCLaunchDelegate.java:747)\n\tat org.eclipse.cdt.launch.internal.LocalRunLaunchDelegate.launch\n(LocalRunLaunchDelegate.java:58)\n\tat org.eclipse.debug.internal.core.LaunchConfiguration.launch\n(LaunchConfiguration.java:569)\n\tat org.eclipse.debug.internal.core.LaunchConfiguration.launch\n(LaunchConfiguration.java:150)\n\tat org.eclipse.debug.internal.ui.DebugUIPlugin.buildAndLaunch\n(DebugUIPlugin.java:792)\n\tat org.eclipse.debug.internal.ui.DebugUIPlugin$6.run\n(DebugUIPlugin.java:955)\n\tat org.eclipse.core.internal.jobs.Worker.run(Worker.java:66)\n\nThe binary parser is set to gnu elf / elf. Our executable is a relocatable i386-\nelf file. This file will be interpreted correctly when we look at it using the \nCDT navigation window. I also created a new project - but the same results. \nSomething must have changed with this release.\n\nIf necessary I can provide additional information (object files).\n\nRegards. Manfred.",
    "Launching problem.",
    "Can you debug this method to dig further, I don\u0027t see anything obvious. If your\nbinaries show up in the C/C++ Project view as binaries, then the launch should\ndetect them as such.",
    "please verify."
  ],
  "commentCreationDates": [
    "2004-11-03T15:19:49+01:00",
    "2004-11-09T22:07:31+01:00",
    "2004-11-10T15:23:24+01:00",
    "2004-11-22T21:50:57+01:00"
  ],
  "traces": [
    {
      "exceptionType": "java.io.FileNotFoundException",
      "message": "Program not Binary",
      "elements": [
        {
          "method": "org.eclipse.cdt.launch.AbstractCLaunchDelegate.verifyBinary",
          "source": "AbstractCLaunchDelegate.java:747"
        },
        {
          "method": "org.eclipse.cdt.launch.internal.LocalRunLaunchDelegate.launch",
          "source": "LocalRunLaunchDelegate.java:58"
        },
        {
          "method": "org.eclipse.debug.internal.core.LaunchConfiguration.launch",
          "source": "LaunchConfiguration.java:569"
        },
        {
          "method": "org.eclipse.debug.internal.core.LaunchConfiguration.launch",
          "source": "LaunchConfiguration.java:150"
        },
        {
          "method": "org.eclipse.debug.internal.ui.DebugUIPlugin.buildAndLaunch",
          "source": "DebugUIPlugin.java:792"
        },
        {
          "method": "org.eclipse.debug.internal.ui.DebugUIPlugin$6.run",
          "source": "DebugUIPlugin.java:955"
        },
        {
          "method": "org.eclipse.core.internal.jobs.Worker.run",
          "source": "Worker.java:66"
        }
      ],
      "number": 0,
      "commentIndex": 0,
      "bugId": "77643",
      "date": "2004-11-03T15:19:49+01:00",
      "product": "CDT",
      "component": "cdt-launch",
      "severity": "normal"
    }
  ],
  "groupId": "77643",
  "bugId": "77643",
  "date": "2004-11-03T15:19:49+01:00",
  "product": "CDT",
  "component": "cdt-launch",
  "severity": "normal"
}