{
  "comments": [
    "The Linux-GTK implementation of SWT does not appear to release all OS resources\nwhen disposing an org.eclipse.swt.printing.Printer object.\n\nThe following code snippet results in a \"No more handles\" SWT error:\n\n\tDisplay.getDefault().syncExec(new Runnable() {\n\t\tpublic void run() {\n\t\t\tfor (int i \u003d 0; i \u003c 100; i++) {\n\t\t\t\tPrinter printer \u003d new Printer();\n\t\t\t\tprinter.dispose();\n\t\t\t}\n\t\t}\n\t});\n\nThe stack trace looks like:\n\norg.eclipse.swt.SWTError: No more handles\n\tat org.eclipse.swt.SWT.error(SWT.java:2717)\n\tat org.eclipse.swt.SWT.error(SWT.java:2616)\n\tat org.eclipse.swt.SWT.error(SWT.java:2587)\n\tat org.eclipse.swt.printing.Printer.\u003cinit\u003e(Printer.java:100)\n\tat org.eclipse.swt.printing.Printer.\u003cinit\u003e(Printer.java:77)\n\tat com.example.MyPlugin$1.run(PetalUIPlugin.java:106)\n\tat org.eclipse.swt.widgets.Synchronizer.syncExec(Synchronizer.java:135)\n\tat org.eclipse.ui.internal.UISynchronizer.syncExec(UISynchronizer.java:25)\n\tat org.eclipse.swt.widgets.Display.syncExec(Display.java:3022)\n\tat com.example.MyPlugin.doStartup(PetalUIPlugin.java:102)\n        ...\n\nThis code manifests no problems on Windows platforms.\n\nConfiguration:\n\nPlatform:  Intel x86 32-bit dual-processor\nOS:        RedHat Linux 9 (Shrike)\nWS:        GTK\nEclipse:   3.0.1\nJVM:       java version \"1.4.2\"\n           IBM J9SE VM (build 2.2, J2RE 1.4.2 IBM J9 2.2 Linux x86-32\n               j9xia32142-2040917 (JIT enabled)\n           J9VM - 20040916_0910_1HdSMR\n           JIT  - r7_level20040915_1801",
    "Printing is not implemented on GTK.",
    "\n\n*** This bug has been marked as a duplicate of 24796 ***"
  ],
  "commentCreationDates": [
    "2004-11-03T17:12:52+01:00",
    "2004-11-04T15:36:05+01:00",
    "2004-11-04T15:36:51+01:00"
  ],
  "traces": [
    {
      "exceptionType": "org.eclipse.swt.SWTError",
      "message": "No more handles",
      "elements": [
        {
          "method": "org.eclipse.swt.SWT.error",
          "source": "SWT.java:2717"
        },
        {
          "method": "org.eclipse.swt.SWT.error",
          "source": "SWT.java:2616"
        },
        {
          "method": "org.eclipse.swt.SWT.error",
          "source": "SWT.java:2587"
        },
        {
          "method": "org.eclipse.swt.printing.Printer.\u003cinit\u003e",
          "source": "Printer.java:100"
        },
        {
          "method": "org.eclipse.swt.printing.Printer.\u003cinit\u003e",
          "source": "Printer.java:77"
        },
        {
          "method": "com.example.MyPlugin$1.run",
          "source": "PetalUIPlugin.java:106"
        },
        {
          "method": "org.eclipse.swt.widgets.Synchronizer.syncExec",
          "source": "Synchronizer.java:135"
        },
        {
          "method": "org.eclipse.ui.internal.UISynchronizer.syncExec",
          "source": "UISynchronizer.java:25"
        },
        {
          "method": "org.eclipse.swt.widgets.Display.syncExec",
          "source": "Display.java:3022"
        },
        {
          "method": "com.example.MyPlugin.doStartup",
          "source": "PetalUIPlugin.java:102"
        }
      ],
      "number": 0,
      "commentIndex": 0,
      "bugId": "77695",
      "duplicateId": "24796",
      "date": "2004-11-03T17:12:52+01:00",
      "product": "Platform",
      "component": "SWT",
      "severity": "normal"
    }
  ],
  "groupId": "24796",
  "bugId": "77695",
  "duplicateId": "24796",
  "date": "2004-11-03T17:12:52+01:00",
  "product": "Platform",
  "component": "SWT",
  "severity": "normal"
}