{
  "comments": [
    "I200411022000\n\nNot sure what triggered that, but I remember having seen it on an earlier session:\n\njava.lang.IllegalArgumentException: Attempted to beginRule: R/, does not match o\nuter scope rule: L/Test2/src/test5/A.java\n        at org.eclipse.core.internal.runtime.Assert.isLegal(Assert.java:58)\n        at org.eclipse.core.internal.jobs.ThreadJob.illegalPush(ThreadJob.java:1\n06)\n        at org.eclipse.core.internal.jobs.ThreadJob.push(ThreadJob.java:200)\n        at org.eclipse.core.internal.jobs.ImplicitJobs.begin(ImplicitJobs.java:5\n8)\n        at org.eclipse.core.internal.jobs.JobManager.beginRule(JobManager.java:1\n83)\n        at org.eclipse.core.internal.resources.WorkManager.checkIn(WorkManager.j\nava:95)\n        at org.eclipse.core.internal.resources.Workspace.prepareOperation(Worksp\nace.java:1631)\n        at org.eclipse.core.internal.events.AutoBuildJob.doBuild(AutoBuildJob.ja\nva:138)\n        at org.eclipse.core.internal.events.AutoBuildJob.run(AutoBuildJob.java:2\n03)\n        at org.eclipse.core.internal.jobs.Worker.run(Worker.java:66)",
    "\n\n*** This bug has been marked as a duplicate of 77640 ***"
  ],
  "commentCreationDates": [
    "2004-11-03T17:21:48+01:00",
    "2004-11-03T17:24:10+01:00"
  ],
  "traces": [
    {
      "exceptionType": "java.lang.IllegalArgumentException",
      "message": "Attempted to beginRule: R/, does not match o uter scope rule: L/Test2/src/test5/A.java",
      "elements": [
        {
          "method": "org.eclipse.core.internal.runtime.Assert.isLegal",
          "source": "Assert.java:58"
        },
        {
          "method": "org.eclipse.core.internal.jobs.ThreadJob.illegalPush",
          "source": "ThreadJob.java:1 06"
        },
        {
          "method": "org.eclipse.core.internal.jobs.ThreadJob.push",
          "source": "ThreadJob.java:200"
        },
        {
          "method": "org.eclipse.core.internal.jobs.ImplicitJobs.begin",
          "source": "ImplicitJobs.java:5 8"
        },
        {
          "method": "org.eclipse.core.internal.jobs.JobManager.beginRule",
          "source": "JobManager.java:1 83"
        },
        {
          "method": "org.eclipse.core.internal.resources.WorkManager.checkIn",
          "source": "WorkManager.j ava:95"
        },
        {
          "method": "org.eclipse.core.internal.resources.Workspace.prepareOperation",
          "source": "Worksp ace.java:1631"
        },
        {
          "method": "org.eclipse.core.internal.events.AutoBuildJob.doBuild",
          "source": "AutoBuildJob.ja va:138"
        },
        {
          "method": "org.eclipse.core.internal.events.AutoBuildJob.run",
          "source": "AutoBuildJob.java:2 03"
        },
        {
          "method": "org.eclipse.core.internal.jobs.Worker.run",
          "source": "Worker.java:66"
        }
      ],
      "number": 0,
      "commentIndex": 0,
      "bugId": "77699",
      "duplicateId": "77640",
      "date": "2004-11-03T17:21:48+01:00",
      "product": "Platform",
      "component": "Resources",
      "severity": "normal"
    }
  ],
  "groupId": "77640",
  "bugId": "77699",
  "duplicateId": "77640",
  "date": "2004-11-03T17:21:48+01:00",
  "product": "Platform",
  "component": "Resources",
  "severity": "normal"
}