{
  "comments": [
    "I200411022000, Motif, Solaris.\n\nI tried opening several external files.  The first couple did not open, and did\nnot display an error dialog.  The following was printed to the console (but not\nto the log):\n\n\n\norg.eclipse.ui.PartInitException[0]: java.lang.IllegalArgumentException: Path\nmust include project and resource name: /.mailcap\n        at org.eclipse.core.internal.utils.Assert.isLegal(Assert.java:58)\n        at\norg.eclipse.core.internal.resources.Workspace.newResource(Workspace.java:1519)\n        at\norg.eclipse.core.internal.resources.Container.getFile(Container.java:124)\n        at\norg.eclipse.search2.internal.ui.text.PositionTracker.bufferCreated(PositionTracker.java:241)\n        at\norg.eclipse.core.internal.filebuffers.TextFileBufferManager.fireBufferCreated(TextFileBufferManager.java:370)\n        at\norg.eclipse.core.internal.filebuffers.TextFileBufferManager.connect(TextFileBufferManager.java:88)\n        at\norg.eclipse.ui.editors.text.TextFileDocumentProvider.createFileInfo(TextFileDocumentProvider.java:541)\n        at\norg.eclipse.ui.editors.text.TextFileDocumentProvider.connect(TextFileDocumentProvider.java:462)\n        at\norg.eclipse.ui.texteditor.AbstractTextEditor.doSetInput(AbstractTextEditor.java:2871)\n        at\norg.eclipse.ui.texteditor.StatusTextEditor.doSetInput(StatusTextEditor.java:173)\n        at\norg.eclipse.ui.texteditor.AbstractDecoratedTextEditor.doSetInput(AbstractDecoratedTextEditor.java:1142)\n        at\norg.eclipse.ui.editors.text.TextEditor.doSetInput(TextEditor.java:262)\n        at\norg.eclipse.ui.texteditor.AbstractTextEditor$15.run(AbstractTextEditor.java:2235)\n        at\norg.eclipse.jface.operation.ModalContext.runInCurrentThread(ModalContext.java:322)\n        at org.eclipse.jface.operation.ModalContext.run(ModalContext.java:269)\n        at\norg.eclipse.jface.window.ApplicationWindow$1.run(ApplicationWindow.java:624)\n        at org.eclipse.swt.custom.BusyIndicator.showWhile(BusyIndicator.java:69)\n        at\norg.eclipse.jface.window.ApplicationWindow.run(ApplicationWindow.java:621)\n        at\norg.eclipse.ui.internal.WorkbenchWindow.run(WorkbenchWindow.java:1919)\n        at\norg.eclipse.ui.texteditor.AbstractTextEditor.internalInit(AbstractTextEditor.java:2249)\n        at\norg.eclipse.ui.texteditor.AbstractTextEditor.init(AbstractTextEditor.java:2267)\n        at\norg.eclipse.ui.internal.EditorManager.createSite(EditorManager.java:815)\n        at\norg.eclipse.ui.internal.EditorManager.openInternalEditor(EditorManager.java:894)\n        at\norg.eclipse.ui.internal.EditorManager.openEditorFromDescriptor(EditorManager.java:647)\n        at\norg.eclipse.ui.internal.EditorManager.openEditor(EditorManager.java:633)\n        at\norg.eclipse.ui.internal.WorkbenchPage.busyOpenEditorBatched(WorkbenchPage.java:2279)\n        at\norg.eclipse.ui.internal.WorkbenchPage.busyOpenEditor(WorkbenchPage.java:2211)\n        at\norg.eclipse.ui.internal.WorkbenchPage.access$6(WorkbenchPage.java:2203)\n        at org.eclipse.ui.internal.WorkbenchPage$9.run(WorkbenchPage.java:2189)\n        at org.eclipse.swt.custom.BusyIndicator.showWhile(BusyIndicator.java:69)\n        at\norg.eclipse.ui.internal.WorkbenchPage.openEditor(WorkbenchPage.java:2184)\n        at\norg.eclipse.ui.internal.WorkbenchPage.openEditor(WorkbenchPage.java:2169)\n        at\norg.eclipse.ui.internal.editors.text.OpenExternalFileAction.run(OpenExternalFileAction.java:115)\n        at\norg.eclipse.ui.internal.editors.text.OpenExternalFileAction.run(OpenExternalFileAction.java:87)\n        at\norg.eclipse.ui.internal.PluginAction.runWithEvent(PluginAction.java:298)\n        at\norg.eclipse.ui.internal.WWinPluginAction.runWithEvent(WWinPluginAction.java:221)\n        at\norg.eclipse.jface.action.ActionContributionItem.handleWidgetSelection(ActionContributionItem.java:946)\n        at\norg.eclipse.jface.action.ActionContributionItem.access$2(ActionContributionItem.java:896)\n        at\norg.eclipse.jface.action.ActionContributionItem$7.handleEvent(ActionContributionItem.java:810)\n        at org.eclipse.swt.widgets.EventTable.sendEvent(EventTable.java:82)\n        at org.eclipse.swt.widgets.Widget.sendEvent(Widget.java:734)\n        at org.eclipse.swt.widgets.Display.runDeferredEvents(Display.java:2949)\n        at org.eclipse.swt.widgets.Display.readAndDispatch(Display.java:2649)\n        at org.eclipse.ui.internal.Workbench.runEventLoop(Workbench.java:1527)\n        at org.eclipse.ui.internal.Workbench.runUI(Workbench.java:1498)\n        at\norg.eclipse.ui.internal.Workbench.createAndRunWorkbench(Workbench.java:276)\n        at org.eclipse.ui.PlatformUI.createAndRunWorkbench(PlatformUI.java:144)\n        at\norg.eclipse.ui.internal.ide.IDEApplication.run(IDEApplication.java:102)\n        at\norg.eclipse.core.internal.runtime.PlatformActivator$1.run(PlatformActivator.java:335)\n        at\norg.eclipse.core.runtime.adaptor.EclipseStarter.run(EclipseStarter.java:273)\n        at\norg.eclipse.core.runtime.adaptor.EclipseStarter.run(EclipseStarter.java:129)\n        at sun.reflect.NativeMethodAccessorImpl.invoke0(Native Method)\n        at\nsun.reflect.NativeMethodAccessorImpl.invoke(NativeMethodAccessorImpl.java:39)\n        at\nsun.reflect.DelegatingMethodAccessorImpl.invoke(DelegatingMethodAccessorImpl.java:25)\n        at java.lang.reflect.Method.invoke(Method.java:324)\n        at org.eclipse.core.launcher.Main.basicRun(Main.java:185)\n        at org.eclipse.core.launcher.Main.run(Main.java:704)\n        at org.eclipse.core.launcher.Main.main(Main.java:688)\norg.eclipse.ui.PartInitException[0]: java.lang.IllegalArgumentException: Path\nmust include project and resource name: /.bash_history\n        at org.eclipse.core.internal.utils.Assert.isLegal(Assert.java:58)\n        at\norg.eclipse.core.internal.resources.Workspace.newResource(Workspace.java:1519)\n        at\norg.eclipse.core.internal.resources.Container.getFile(Container.java:124)\n        at\norg.eclipse.search2.internal.ui.text.PositionTracker.bufferCreated(PositionTracker.java:241)\n        at\norg.eclipse.core.internal.filebuffers.TextFileBufferManager.fireBufferCreated(TextFileBufferManager.java:370)\n        at\norg.eclipse.core.internal.filebuffers.TextFileBufferManager.connect(TextFileBufferManager.java:88)\n        at\norg.eclipse.ui.editors.text.TextFileDocumentProvider.createFileInfo(TextFileDocumentProvider.java:541)\n        at\norg.eclipse.ui.editors.text.TextFileDocumentProvider.connect(TextFileDocumentProvider.java:462)\n        at\norg.eclipse.ui.texteditor.AbstractTextEditor.doSetInput(AbstractTextEditor.java:2871)\n        at\norg.eclipse.ui.texteditor.StatusTextEditor.doSetInput(StatusTextEditor.java:173)\n        at\norg.eclipse.ui.texteditor.AbstractDecoratedTextEditor.doSetInput(AbstractDecoratedTextEditor.java:1142)\n        at\norg.eclipse.ui.editors.text.TextEditor.doSetInput(TextEditor.java:262)\n        at\norg.eclipse.ui.texteditor.AbstractTextEditor$15.run(AbstractTextEditor.java:2235)\n        at\norg.eclipse.jface.operation.ModalContext.runInCurrentThread(ModalContext.java:322)\n        at org.eclipse.jface.operation.ModalContext.run(ModalContext.java:269)\n        at\norg.eclipse.jface.window.ApplicationWindow$1.run(ApplicationWindow.java:624)\n        at org.eclipse.swt.custom.BusyIndicator.showWhile(BusyIndicator.java:69)\n        at\norg.eclipse.jface.window.ApplicationWindow.run(ApplicationWindow.java:621)\n        at\norg.eclipse.ui.internal.WorkbenchWindow.run(WorkbenchWindow.java:1919)\n        at\norg.eclipse.ui.texteditor.AbstractTextEditor.internalInit(AbstractTextEditor.java:2249)\n        at\norg.eclipse.ui.texteditor.AbstractTextEditor.init(AbstractTextEditor.java:2267)\n        at\norg.eclipse.ui.internal.EditorManager.createSite(EditorManager.java:815)\n        at\norg.eclipse.ui.internal.EditorManager.openInternalEditor(EditorManager.java:894)\n        at\norg.eclipse.ui.internal.EditorManager.openEditorFromDescriptor(EditorManager.java:647)\n        at\norg.eclipse.ui.internal.EditorManager.openEditor(EditorManager.java:633)\n        at\norg.eclipse.ui.internal.WorkbenchPage.busyOpenEditorBatched(WorkbenchPage.java:2279)\n        at\norg.eclipse.ui.internal.WorkbenchPage.busyOpenEditor(WorkbenchPage.java:2211)\n        at\norg.eclipse.ui.internal.WorkbenchPage.access$6(WorkbenchPage.java:2203)\n        at org.eclipse.ui.internal.WorkbenchPage$9.run(WorkbenchPage.java:2189)\n        at org.eclipse.swt.custom.BusyIndicator.showWhile(BusyIndicator.java:69)\n        at\norg.eclipse.ui.internal.WorkbenchPage.openEditor(WorkbenchPage.java:2184)\n        at\norg.eclipse.ui.internal.WorkbenchPage.openEditor(WorkbenchPage.java:2169)\n        at\norg.eclipse.ui.internal.editors.text.OpenExternalFileAction.run(OpenExternalFileAction.java:115)\n        at\norg.eclipse.ui.internal.editors.text.OpenExternalFileAction.run(OpenExternalFileAction.java:87)\n        at\norg.eclipse.ui.internal.PluginAction.runWithEvent(PluginAction.java:298)\n        at\norg.eclipse.ui.internal.WWinPluginAction.runWithEvent(WWinPluginAction.java:221)\n        at\norg.eclipse.jface.action.ActionContributionItem.handleWidgetSelection(ActionContributionItem.java:946)\n        at\norg.eclipse.jface.action.ActionContributionItem.access$2(ActionContributionItem.java:896)\n        at\norg.eclipse.jface.action.ActionContributionItem$7.handleEvent(ActionContributionItem.java:810)\n        at org.eclipse.swt.widgets.EventTable.sendEvent(EventTable.java:82)\n        at org.eclipse.swt.widgets.Widget.sendEvent(Widget.java:734)\n        at org.eclipse.swt.widgets.Display.runDeferredEvents(Display.java:2949)\n        at org.eclipse.swt.widgets.Display.readAndDispatch(Display.java:2649)\n        at org.eclipse.ui.internal.Workbench.runEventLoop(Workbench.java:1527)\n        at org.eclipse.ui.internal.Workbench.runUI(Workbench.java:1498)\n        at\norg.eclipse.ui.internal.Workbench.createAndRunWorkbench(Workbench.java:276)\n        at org.eclipse.ui.PlatformUI.createAndRunWorkbench(PlatformUI.java:144)\n        at\norg.eclipse.ui.internal.ide.IDEApplication.run(IDEApplication.java:102)\n        at\norg.eclipse.core.internal.runtime.PlatformActivator$1.run(PlatformActivator.java:335)\n        at\norg.eclipse.core.runtime.adaptor.EclipseStarter.run(EclipseStarter.java:273)\n        at\norg.eclipse.core.runtime.adaptor.EclipseStarter.run(EclipseStarter.java:129)\n        at sun.reflect.NativeMethodAccessorImpl.invoke0(Native Method)\n        at\nsun.reflect.NativeMethodAccessorImpl.invoke(NativeMethodAccessorImpl.java:39)\n        at\nsun.reflect.DelegatingMethodAccessorImpl.invoke(DelegatingMethodAccessorImpl.java:25)\n        at java.lang.reflect.Method.invoke(Method.java:324)\n        at org.eclipse.core.launcher.Main.basicRun(Main.java:185)\n        at org.eclipse.core.launcher.Main.run(Main.java:704)\n        at org.eclipse.core.launcher.Main.main(Main.java:688)",
    "As the exception states, you can\u0027t create an IFile on a path with onely one\nsegment. Moving to platform text.",
    "Also happens under WinXP.\n\nThis is a bug in Search: it calls IContainer.getFile(IPath) which specs that the \npath must have at least 2 segments.\n",
    "The problem is provisorily fixed and released into I200411040800. The correct\nfix needs to be put in place for 3.1 M4 (see bug 77807).",
    "OK. Verified in I200411040800."
  ],
  "commentCreationDates": [
    "2004-11-03T19:47:58+01:00",
    "2004-11-03T20:18:14+01:00",
    "2004-11-04T08:44:35+01:00",
    "2004-11-04T15:35:46+01:00",
    "2004-11-04T16:00:49+01:00"
  ],
  "traces": [
    {
      "exceptionType": "java.lang.IllegalArgumentException",
      "message": "Path must include project and resource name: /.mailcap",
      "elements": [
        {
          "method": "org.eclipse.core.internal.utils.Assert.isLegal",
          "source": "Assert.java:58"
        },
        {
          "method": "org.eclipse.core.internal.resources.Workspace.newResource",
          "source": "Workspace.java:1519"
        },
        {
          "method": "org.eclipse.core.internal.resources.Container.getFile",
          "source": "Container.java:124"
        },
        {
          "method": "org.eclipse.search2.internal.ui.text.PositionTracker.bufferCreated",
          "source": "PositionTracker.java:241"
        },
        {
          "method": "org.eclipse.core.internal.filebuffers.TextFileBufferManager.fireBufferCreated",
          "source": "TextFileBufferManager.java:370"
        },
        {
          "method": "org.eclipse.core.internal.filebuffers.TextFileBufferManager.connect",
          "source": "TextFileBufferManager.java:88"
        },
        {
          "method": "org.eclipse.ui.editors.text.TextFileDocumentProvider.createFileInfo",
          "source": "TextFileDocumentProvider.java:541"
        },
        {
          "method": "org.eclipse.ui.editors.text.TextFileDocumentProvider.connect",
          "source": "TextFileDocumentProvider.java:462"
        },
        {
          "method": "org.eclipse.ui.texteditor.AbstractTextEditor.doSetInput",
          "source": "AbstractTextEditor.java:2871"
        },
        {
          "method": "org.eclipse.ui.texteditor.StatusTextEditor.doSetInput",
          "source": "StatusTextEditor.java:173"
        },
        {
          "method": "org.eclipse.ui.texteditor.AbstractDecoratedTextEditor.doSetInput",
          "source": "AbstractDecoratedTextEditor.java:1142"
        },
        {
          "method": "org.eclipse.ui.editors.text.TextEditor.doSetInput",
          "source": "TextEditor.java:262"
        },
        {
          "method": "org.eclipse.ui.texteditor.AbstractTextEditor$15.run",
          "source": "AbstractTextEditor.java:2235"
        },
        {
          "method": "org.eclipse.jface.operation.ModalContext.runInCurrentThread",
          "source": "ModalContext.java:322"
        },
        {
          "method": "org.eclipse.jface.operation.ModalContext.run",
          "source": "ModalContext.java:269"
        },
        {
          "method": "org.eclipse.jface.window.ApplicationWindow$1.run",
          "source": "ApplicationWindow.java:624"
        },
        {
          "method": "org.eclipse.swt.custom.BusyIndicator.showWhile",
          "source": "BusyIndicator.java:69"
        },
        {
          "method": "org.eclipse.jface.window.ApplicationWindow.run",
          "source": "ApplicationWindow.java:621"
        },
        {
          "method": "org.eclipse.ui.internal.WorkbenchWindow.run",
          "source": "WorkbenchWindow.java:1919"
        },
        {
          "method": "org.eclipse.ui.texteditor.AbstractTextEditor.internalInit",
          "source": "AbstractTextEditor.java:2249"
        },
        {
          "method": "org.eclipse.ui.texteditor.AbstractTextEditor.init",
          "source": "AbstractTextEditor.java:2267"
        },
        {
          "method": "org.eclipse.ui.internal.EditorManager.createSite",
          "source": "EditorManager.java:815"
        },
        {
          "method": "org.eclipse.ui.internal.EditorManager.openInternalEditor",
          "source": "EditorManager.java:894"
        },
        {
          "method": "org.eclipse.ui.internal.EditorManager.openEditorFromDescriptor",
          "source": "EditorManager.java:647"
        },
        {
          "method": "org.eclipse.ui.internal.EditorManager.openEditor",
          "source": "EditorManager.java:633"
        },
        {
          "method": "org.eclipse.ui.internal.WorkbenchPage.busyOpenEditorBatched",
          "source": "WorkbenchPage.java:2279"
        },
        {
          "method": "org.eclipse.ui.internal.WorkbenchPage.busyOpenEditor",
          "source": "WorkbenchPage.java:2211"
        },
        {
          "method": "org.eclipse.ui.internal.WorkbenchPage.access$6",
          "source": "WorkbenchPage.java:2203"
        },
        {
          "method": "org.eclipse.ui.internal.WorkbenchPage$9.run",
          "source": "WorkbenchPage.java:2189"
        },
        {
          "method": "org.eclipse.swt.custom.BusyIndicator.showWhile",
          "source": "BusyIndicator.java:69"
        },
        {
          "method": "org.eclipse.ui.internal.WorkbenchPage.openEditor",
          "source": "WorkbenchPage.java:2184"
        },
        {
          "method": "org.eclipse.ui.internal.WorkbenchPage.openEditor",
          "source": "WorkbenchPage.java:2169"
        },
        {
          "method": "org.eclipse.ui.internal.editors.text.OpenExternalFileAction.run",
          "source": "OpenExternalFileAction.java:115"
        },
        {
          "method": "org.eclipse.ui.internal.editors.text.OpenExternalFileAction.run",
          "source": "OpenExternalFileAction.java:87"
        },
        {
          "method": "org.eclipse.ui.internal.PluginAction.runWithEvent",
          "source": "PluginAction.java:298"
        },
        {
          "method": "org.eclipse.ui.internal.WWinPluginAction.runWithEvent",
          "source": "WWinPluginAction.java:221"
        },
        {
          "method": "org.eclipse.jface.action.ActionContributionItem.handleWidgetSelection",
          "source": "ActionContributionItem.java:946"
        },
        {
          "method": "org.eclipse.jface.action.ActionContributionItem.access$2",
          "source": "ActionContributionItem.java:896"
        },
        {
          "method": "org.eclipse.jface.action.ActionContributionItem$7.handleEvent",
          "source": "ActionContributionItem.java:810"
        },
        {
          "method": "org.eclipse.swt.widgets.EventTable.sendEvent",
          "source": "EventTable.java:82"
        },
        {
          "method": "org.eclipse.swt.widgets.Widget.sendEvent",
          "source": "Widget.java:734"
        },
        {
          "method": "org.eclipse.swt.widgets.Display.runDeferredEvents",
          "source": "Display.java:2949"
        },
        {
          "method": "org.eclipse.swt.widgets.Display.readAndDispatch",
          "source": "Display.java:2649"
        },
        {
          "method": "org.eclipse.ui.internal.Workbench.runEventLoop",
          "source": "Workbench.java:1527"
        },
        {
          "method": "org.eclipse.ui.internal.Workbench.runUI",
          "source": "Workbench.java:1498"
        },
        {
          "method": "org.eclipse.ui.internal.Workbench.createAndRunWorkbench",
          "source": "Workbench.java:276"
        },
        {
          "method": "org.eclipse.ui.PlatformUI.createAndRunWorkbench",
          "source": "PlatformUI.java:144"
        },
        {
          "method": "org.eclipse.ui.internal.ide.IDEApplication.run",
          "source": "IDEApplication.java:102"
        },
        {
          "method": "org.eclipse.core.internal.runtime.PlatformActivator$1.run",
          "source": "PlatformActivator.java:335"
        },
        {
          "method": "org.eclipse.core.runtime.adaptor.EclipseStarter.run",
          "source": "EclipseStarter.java:273"
        },
        {
          "method": "org.eclipse.core.runtime.adaptor.EclipseStarter.run",
          "source": "EclipseStarter.java:129"
        },
        {
          "method": "sun.reflect.NativeMethodAccessorImpl.invoke0",
          "source": "Native Method"
        },
        {
          "method": "sun.reflect.NativeMethodAccessorImpl.invoke",
          "source": "NativeMethodAccessorImpl.java:39"
        },
        {
          "method": "sun.reflect.DelegatingMethodAccessorImpl.invoke",
          "source": "DelegatingMethodAccessorImpl.java:25"
        },
        {
          "method": "java.lang.reflect.Method.invoke",
          "source": "Method.java:324"
        },
        {
          "method": "org.eclipse.core.launcher.Main.basicRun",
          "source": "Main.java:185"
        },
        {
          "method": "org.eclipse.core.launcher.Main.run",
          "source": "Main.java:704"
        },
        {
          "method": "org.eclipse.core.launcher.Main.main",
          "source": "Main.java:688"
        }
      ],
      "number": 0,
      "commentIndex": 0,
      "bugId": "77741",
      "date": "2004-11-03T19:47:58+01:00",
      "product": "Platform",
      "component": "Search",
      "severity": "normal"
    },
    {
      "exceptionType": "java.lang.IllegalArgumentException",
      "message": "Path must include project and resource name: /.bash_history",
      "elements": [
        {
          "method": "org.eclipse.core.internal.utils.Assert.isLegal",
          "source": "Assert.java:58"
        },
        {
          "method": "org.eclipse.core.internal.resources.Workspace.newResource",
          "source": "Workspace.java:1519"
        },
        {
          "method": "org.eclipse.core.internal.resources.Container.getFile",
          "source": "Container.java:124"
        },
        {
          "method": "org.eclipse.search2.internal.ui.text.PositionTracker.bufferCreated",
          "source": "PositionTracker.java:241"
        },
        {
          "method": "org.eclipse.core.internal.filebuffers.TextFileBufferManager.fireBufferCreated",
          "source": "TextFileBufferManager.java:370"
        },
        {
          "method": "org.eclipse.core.internal.filebuffers.TextFileBufferManager.connect",
          "source": "TextFileBufferManager.java:88"
        },
        {
          "method": "org.eclipse.ui.editors.text.TextFileDocumentProvider.createFileInfo",
          "source": "TextFileDocumentProvider.java:541"
        },
        {
          "method": "org.eclipse.ui.editors.text.TextFileDocumentProvider.connect",
          "source": "TextFileDocumentProvider.java:462"
        },
        {
          "method": "org.eclipse.ui.texteditor.AbstractTextEditor.doSetInput",
          "source": "AbstractTextEditor.java:2871"
        },
        {
          "method": "org.eclipse.ui.texteditor.StatusTextEditor.doSetInput",
          "source": "StatusTextEditor.java:173"
        },
        {
          "method": "org.eclipse.ui.texteditor.AbstractDecoratedTextEditor.doSetInput",
          "source": "AbstractDecoratedTextEditor.java:1142"
        },
        {
          "method": "org.eclipse.ui.editors.text.TextEditor.doSetInput",
          "source": "TextEditor.java:262"
        },
        {
          "method": "org.eclipse.ui.texteditor.AbstractTextEditor$15.run",
          "source": "AbstractTextEditor.java:2235"
        },
        {
          "method": "org.eclipse.jface.operation.ModalContext.runInCurrentThread",
          "source": "ModalContext.java:322"
        },
        {
          "method": "org.eclipse.jface.operation.ModalContext.run",
          "source": "ModalContext.java:269"
        },
        {
          "method": "org.eclipse.jface.window.ApplicationWindow$1.run",
          "source": "ApplicationWindow.java:624"
        },
        {
          "method": "org.eclipse.swt.custom.BusyIndicator.showWhile",
          "source": "BusyIndicator.java:69"
        },
        {
          "method": "org.eclipse.jface.window.ApplicationWindow.run",
          "source": "ApplicationWindow.java:621"
        },
        {
          "method": "org.eclipse.ui.internal.WorkbenchWindow.run",
          "source": "WorkbenchWindow.java:1919"
        },
        {
          "method": "org.eclipse.ui.texteditor.AbstractTextEditor.internalInit",
          "source": "AbstractTextEditor.java:2249"
        },
        {
          "method": "org.eclipse.ui.texteditor.AbstractTextEditor.init",
          "source": "AbstractTextEditor.java:2267"
        },
        {
          "method": "org.eclipse.ui.internal.EditorManager.createSite",
          "source": "EditorManager.java:815"
        },
        {
          "method": "org.eclipse.ui.internal.EditorManager.openInternalEditor",
          "source": "EditorManager.java:894"
        },
        {
          "method": "org.eclipse.ui.internal.EditorManager.openEditorFromDescriptor",
          "source": "EditorManager.java:647"
        },
        {
          "method": "org.eclipse.ui.internal.EditorManager.openEditor",
          "source": "EditorManager.java:633"
        },
        {
          "method": "org.eclipse.ui.internal.WorkbenchPage.busyOpenEditorBatched",
          "source": "WorkbenchPage.java:2279"
        },
        {
          "method": "org.eclipse.ui.internal.WorkbenchPage.busyOpenEditor",
          "source": "WorkbenchPage.java:2211"
        },
        {
          "method": "org.eclipse.ui.internal.WorkbenchPage.access$6",
          "source": "WorkbenchPage.java:2203"
        },
        {
          "method": "org.eclipse.ui.internal.WorkbenchPage$9.run",
          "source": "WorkbenchPage.java:2189"
        },
        {
          "method": "org.eclipse.swt.custom.BusyIndicator.showWhile",
          "source": "BusyIndicator.java:69"
        },
        {
          "method": "org.eclipse.ui.internal.WorkbenchPage.openEditor",
          "source": "WorkbenchPage.java:2184"
        },
        {
          "method": "org.eclipse.ui.internal.WorkbenchPage.openEditor",
          "source": "WorkbenchPage.java:2169"
        },
        {
          "method": "org.eclipse.ui.internal.editors.text.OpenExternalFileAction.run",
          "source": "OpenExternalFileAction.java:115"
        },
        {
          "method": "org.eclipse.ui.internal.editors.text.OpenExternalFileAction.run",
          "source": "OpenExternalFileAction.java:87"
        },
        {
          "method": "org.eclipse.ui.internal.PluginAction.runWithEvent",
          "source": "PluginAction.java:298"
        },
        {
          "method": "org.eclipse.ui.internal.WWinPluginAction.runWithEvent",
          "source": "WWinPluginAction.java:221"
        },
        {
          "method": "org.eclipse.jface.action.ActionContributionItem.handleWidgetSelection",
          "source": "ActionContributionItem.java:946"
        },
        {
          "method": "org.eclipse.jface.action.ActionContributionItem.access$2",
          "source": "ActionContributionItem.java:896"
        },
        {
          "method": "org.eclipse.jface.action.ActionContributionItem$7.handleEvent",
          "source": "ActionContributionItem.java:810"
        },
        {
          "method": "org.eclipse.swt.widgets.EventTable.sendEvent",
          "source": "EventTable.java:82"
        },
        {
          "method": "org.eclipse.swt.widgets.Widget.sendEvent",
          "source": "Widget.java:734"
        },
        {
          "method": "org.eclipse.swt.widgets.Display.runDeferredEvents",
          "source": "Display.java:2949"
        },
        {
          "method": "org.eclipse.swt.widgets.Display.readAndDispatch",
          "source": "Display.java:2649"
        },
        {
          "method": "org.eclipse.ui.internal.Workbench.runEventLoop",
          "source": "Workbench.java:1527"
        },
        {
          "method": "org.eclipse.ui.internal.Workbench.runUI",
          "source": "Workbench.java:1498"
        },
        {
          "method": "org.eclipse.ui.internal.Workbench.createAndRunWorkbench",
          "source": "Workbench.java:276"
        },
        {
          "method": "org.eclipse.ui.PlatformUI.createAndRunWorkbench",
          "source": "PlatformUI.java:144"
        },
        {
          "method": "org.eclipse.ui.internal.ide.IDEApplication.run",
          "source": "IDEApplication.java:102"
        },
        {
          "method": "org.eclipse.core.internal.runtime.PlatformActivator$1.run",
          "source": "PlatformActivator.java:335"
        },
        {
          "method": "org.eclipse.core.runtime.adaptor.EclipseStarter.run",
          "source": "EclipseStarter.java:273"
        },
        {
          "method": "org.eclipse.core.runtime.adaptor.EclipseStarter.run",
          "source": "EclipseStarter.java:129"
        },
        {
          "method": "sun.reflect.NativeMethodAccessorImpl.invoke0",
          "source": "Native Method"
        },
        {
          "method": "sun.reflect.NativeMethodAccessorImpl.invoke",
          "source": "NativeMethodAccessorImpl.java:39"
        },
        {
          "method": "sun.reflect.DelegatingMethodAccessorImpl.invoke",
          "source": "DelegatingMethodAccessorImpl.java:25"
        },
        {
          "method": "java.lang.reflect.Method.invoke",
          "source": "Method.java:324"
        },
        {
          "method": "org.eclipse.core.launcher.Main.basicRun",
          "source": "Main.java:185"
        },
        {
          "method": "org.eclipse.core.launcher.Main.run",
          "source": "Main.java:704"
        },
        {
          "method": "org.eclipse.core.launcher.Main.main",
          "source": "Main.java:688"
        }
      ],
      "number": 1,
      "commentIndex": 0,
      "bugId": "77741",
      "date": "2004-11-03T19:47:58+01:00",
      "product": "Platform",
      "component": "Search",
      "severity": "normal"
    }
  ],
  "groupId": "77741",
  "bugId": "77741",
  "date": "2004-11-03T19:47:58+01:00",
  "product": "Platform",
  "component": "Search",
  "severity": "normal"
}