{
  "comments": [
    "I\u0027ve noticed that some of my enums fail to parse within Eclipse (3.1 11/2/04\nintegration build).  After opening or while moving the cursor around within an\noffending file, I repeatedly get a dialog stating:\n\u0027An internal error occurred during: \"Java AST creation\".\u0027\n\nAssociated with this error I get following exception in the error log:\njava.lang.ClassCastException: org.eclipse.jdt.internal.compiler.ast.TypeDeclaration\n\tat org.eclipse.jdt.core.dom.ASTConverter.lookupScope(ASTConverter.java:3416)\n\tat org.eclipse.jdt.core.dom.ASTConverter.lookupForScopes(ASTConverter.java:3344)\n\tat org.eclipse.jdt.core.dom.ASTConverter.convert(ASTConverter.java:1319)\n\tat\norg.eclipse.jdt.core.dom.CompilationUnitResolver.convert(CompilationUnitResolver.java:219)\n\tat org.eclipse.jdt.core.dom.ASTParser.internalCreateAST(ASTParser.java:743)\n\tat org.eclipse.jdt.core.dom.ASTParser.createAST(ASTParser.java:574)\n\tat\norg.eclipse.jdt.internal.ui.javaeditor.ASTProvider.createAST(ASTProvider.java:563)\n\tat org.eclipse.jdt.internal.ui.javaeditor.ASTProvider.getAST(ASTProvider.java:492)\n\tat\norg.eclipse.jdt.internal.ui.viewsupport.SelectionListenerWithASTManager$PartListenerGroup.calculateASTandInform(SelectionListenerWithASTManager.java:165)\n\tat\norg.eclipse.jdt.internal.ui.viewsupport.SelectionListenerWithASTManager$3.run(SelectionListenerWithASTManager.java:142)\n\tat org.eclipse.core.internal.jobs.Worker.run(Worker.java:66)\n\n\nI believe the error occurs when an enum references static vars defined in other\ntypes from within its static initializer (there may be other cases).  I\u0027ve\nmanaged to come up with a reproducible test case, which I\u0027ve pasted below.  Put\nthe two type definitions in two separate .java files in a project.  Then open\nTest.java.  After opening, click somewhere within the body of the enum.  This\nshould reproduce the error.\n\npublic enum Test {\n    VAL_A;\n\n    private static final String VAL_A_LABEL;\n\n    static {\n        VAL_A_LABEL \u003d Test2.value;\n    }\n}\n\npublic class Test2 {   \n    public static final String value \u003d \"foo\";\n}",
    "I will investigate.",
    "Fix is ready. Need to run all the tests before releasing it.",
    "All tests are green (JDT/Core tests + JDT/UI tests).",
    "Fixed and released in HEAD.\nRegression test added.",
    "Ok for M3",
    "Verified for 3.1 M3 with build I200411040800."
  ],
  "commentCreationDates": [
    "2004-11-03T22:03:41+01:00",
    "2004-11-03T23:09:47+01:00",
    "2004-11-03T23:26:44+01:00",
    "2004-11-04T04:13:03+01:00",
    "2004-11-04T04:13:22+01:00",
    "2004-11-04T10:32:58+01:00",
    "2004-11-04T16:10:04+01:00"
  ],
  "traces": [
    {
      "exceptionType": "java.lang.ClassCastException",
      "message": "org.eclipse.jdt.internal.compiler.ast.TypeDeclaration",
      "elements": [
        {
          "method": "org.eclipse.jdt.core.dom.ASTConverter.lookupScope",
          "source": "ASTConverter.java:3416"
        },
        {
          "method": "org.eclipse.jdt.core.dom.ASTConverter.lookupForScopes",
          "source": "ASTConverter.java:3344"
        },
        {
          "method": "org.eclipse.jdt.core.dom.ASTConverter.convert",
          "source": "ASTConverter.java:1319"
        },
        {
          "method": "org.eclipse.jdt.core.dom.CompilationUnitResolver.convert",
          "source": "CompilationUnitResolver.java:219"
        },
        {
          "method": "org.eclipse.jdt.core.dom.ASTParser.internalCreateAST",
          "source": "ASTParser.java:743"
        },
        {
          "method": "org.eclipse.jdt.core.dom.ASTParser.createAST",
          "source": "ASTParser.java:574"
        },
        {
          "method": "org.eclipse.jdt.internal.ui.javaeditor.ASTProvider.createAST",
          "source": "ASTProvider.java:563"
        },
        {
          "method": "org.eclipse.jdt.internal.ui.javaeditor.ASTProvider.getAST",
          "source": "ASTProvider.java:492"
        },
        {
          "method": "org.eclipse.jdt.internal.ui.viewsupport.SelectionListenerWithASTManager$PartListenerGroup.calculateASTandInform",
          "source": "SelectionListenerWithASTManager.java:165"
        },
        {
          "method": "org.eclipse.jdt.internal.ui.viewsupport.SelectionListenerWithASTManager$3.run",
          "source": "SelectionListenerWithASTManager.java:142"
        },
        {
          "method": "org.eclipse.core.internal.jobs.Worker.run",
          "source": "Worker.java:66"
        }
      ],
      "number": 0,
      "commentIndex": 0,
      "bugId": "77772",
      "date": "2004-11-03T22:03:41+01:00",
      "product": "JDT",
      "component": "Core",
      "severity": "critical"
    }
  ],
  "groupId": "77772",
  "bugId": "77772",
  "date": "2004-11-03T22:03:41+01:00",
  "product": "JDT",
  "component": "Core",
  "severity": "critical"
}