{
  "comments": [
    "While declaring an attribute read-only (no set method is expected to be\ngenerated), using the Ecore parameter (isChangeable\u003dFalse), the following\nException was encountered during deserialization:\njava.lang.IllegalArgumentException: The feature \u0027serverType\u0027 is not a valid\nchangeable feature\n      at \norg.eclipse.emf.ecore.impl.BasicEObjectImpl.eDynamicSet(BasicEObjectImpl.java:515)\n      at\ncom.ibm.db.models.db2.luw.impl.LUWGenericServerImpl.eSet(LUWGenericServerImpl.java:281)\n      at\norg.eclipse.emf.ecore.xmi.impl.XMLHelperImpl.setValue(XMLHelperImpl.java:768)\n[...]\n\nWe need to be able to generate code through EMF for read-only attributes\n(isChangeable\u003dFalse) that are not expected to have any set\u003cAttribName\u003e() method\nbeing generated. That should not have an impact on being able to deserialize the\nobject (i.e. while default isTransient\u003dFalse). Otherwise it forces EMF clients\nto implement a custom serialization. This expectation is similar to default JDK\nserialization/deserialization which does happen consistently even from read-only\nattributes. The usage of a private attribute proposed through the forum does not\nfit our needs as we need to have an accessor for this attribute, but no modifier.",
    "The implementation described in the bugzilla 75926 will allow you remove the set\naccessor from the interface while keeping the feature \"changeable\".\n\n*** This bug has been marked as a duplicate of 75926 ***"
  ],
  "commentCreationDates": [
    "2004-11-05T16:36:24+01:00",
    "2004-11-05T20:42:10+01:00"
  ],
  "traces": [
    {
      "exceptionType": "java.lang.IllegalArgumentException",
      "message": "The feature \u0027serverType\u0027 is not a valid changeable feature",
      "elements": [
        {
          "method": "org.eclipse.emf.ecore.impl.BasicEObjectImpl.eDynamicSet",
          "source": "BasicEObjectImpl.java:515"
        },
        {
          "method": "com.ibm.db.models.db2.luw.impl.LUWGenericServerImpl.eSet",
          "source": "LUWGenericServerImpl.java:281"
        },
        {
          "method": "org.eclipse.emf.ecore.xmi.impl.XMLHelperImpl.setValue",
          "source": "XMLHelperImpl.java:768"
        }
      ],
      "number": 0,
      "commentIndex": 0,
      "bugId": "77963",
      "duplicateId": "75926",
      "date": "2004-11-05T16:36:24+01:00",
      "product": "EMF",
      "component": "Core",
      "severity": "critical"
    }
  ],
  "groupId": "75926",
  "bugId": "77963",
  "duplicateId": "75926",
  "date": "2004-11-05T16:36:24+01:00",
  "product": "EMF",
  "component": "Core",
  "severity": "critical"
}