{
  "comments": [
    "I see the following stack trace dumped to the console every time I save a Java\nsource file in the editor:\n\njava.lang.NullPointerException\n        at java.lang.SecurityManager.checkRead(SecurityManager.java:900)\n        at java.io.FileInputStream.\u003cinit\u003e(FileInputStream.java(Inlined Compiled\nCode))\n        at\norg.eclipse.jdt.internal.core.index.DiskIndex.readCategoryTable(DiskIndex.java(Compiled\nCode))\n        at\norg.eclipse.jdt.internal.core.index.DiskIndex.mergeCategory(DiskIndex.java(Compiled\nCode))\n        at\norg.eclipse.jdt.internal.core.index.DiskIndex.mergeCategories(DiskIndex.java:352)\n        at\norg.eclipse.jdt.internal.core.index.DiskIndex.mergeWith(DiskIndex.java(Compiled\nCode))\n        at org.eclipse.jdt.internal.core.index.Index.save(Index.java:171)\n        at\norg.eclipse.jdt.internal.core.search.indexing.IndexManager.saveIndex(IndexManager.java:506)\n        at\norg.eclipse.jdt.internal.core.search.indexing.SaveIndex.execute(SaveIndex.java:40)\n        at\norg.eclipse.jdt.internal.core.search.processing.JobManager.run(JobManager.java:361)\n        at java.lang.Thread.run(Thread.java:568)",
    "Kent, this seems to be another case where the file name is null.",
    "Tessa: what VM are you using?",
    "IBM\u0027s 1.4.1 JDK:\n\njava version \"1.4.1\"\nJava(TM) 2 Runtime Environment, Standard Edition (build 1.4.1)\nClassic VM (build 1.4.1, J2RE 1.4.1 IBM build cxia321411-20040301 (JIT enabled:\njitc))\n",
    "This was caused by a VM bug with IBM build cxia321411-20040301 (JIT enabled: \njitc). There are newer versions of this VM available - you should switch.\n\n*** This bug has been marked as a duplicate of 66836 ***"
  ],
  "commentCreationDates": [
    "2004-11-10T20:58:30+01:00",
    "2004-11-10T22:54:27+01:00",
    "2004-11-11T14:50:40+01:00",
    "2004-11-11T15:17:07+01:00",
    "2004-11-11T16:23:15+01:00"
  ],
  "traces": [
    {
      "exceptionType": "java.lang.NullPointerException",
      "elements": [
        {
          "method": "java.lang.SecurityManager.checkRead",
          "source": "SecurityManager.java:900"
        },
        {
          "method": "java.io.FileInputStream.\u003cinit\u003e",
          "source": "FileInputStream.java(Inlined Compiled Code)"
        },
        {
          "method": "org.eclipse.jdt.internal.core.index.DiskIndex.readCategoryTable",
          "source": "DiskIndex.java(Compiled Code)"
        },
        {
          "method": "org.eclipse.jdt.internal.core.index.DiskIndex.mergeCategory",
          "source": "DiskIndex.java(Compiled Code)"
        },
        {
          "method": "org.eclipse.jdt.internal.core.index.DiskIndex.mergeCategories",
          "source": "DiskIndex.java:352"
        },
        {
          "method": "org.eclipse.jdt.internal.core.index.DiskIndex.mergeWith",
          "source": "DiskIndex.java(Compiled Code)"
        },
        {
          "method": "org.eclipse.jdt.internal.core.index.Index.save",
          "source": "Index.java:171"
        },
        {
          "method": "org.eclipse.jdt.internal.core.search.indexing.IndexManager.saveIndex",
          "source": "IndexManager.java:506"
        },
        {
          "method": "org.eclipse.jdt.internal.core.search.indexing.SaveIndex.execute",
          "source": "SaveIndex.java:40"
        },
        {
          "method": "org.eclipse.jdt.internal.core.search.processing.JobManager.run",
          "source": "JobManager.java:361"
        },
        {
          "method": "java.lang.Thread.run",
          "source": "Thread.java:568"
        }
      ],
      "number": 0,
      "commentIndex": 0,
      "bugId": "78339",
      "duplicateId": "66836",
      "date": "2004-11-10T20:58:30+01:00",
      "product": "JDT",
      "component": "Core",
      "severity": "normal"
    }
  ],
  "groupId": "66836",
  "bugId": "78339",
  "duplicateId": "66836",
  "date": "2004-11-10T20:58:30+01:00",
  "product": "JDT",
  "component": "Core",
  "severity": "normal"
}