{
  "comments": [
    "Running with -registrycache on, I got the following error in the log file this \nmorning.  The platform correctly reverted to parsing the registry and there were \nno other startup errors (I didn\u0027t even notice anything had gone wrong until \nlater).  I might have terminated the workbench without normal shutdown last \nnight.\n\n  \u003cstatus\n     plugin-id\u003d\"org.eclipse.core.runtime\"\n     severity\u003d\"ERROR\"\n     message\u003d\"Problems encountered loading the plug-in registry.\"\n     code\u003d\"1\"\u003e\n    \u003cstatus\n       plugin-id\u003d\"org.eclipse.core.runtime\"\n       severity\u003d\"ERROR\"\n       message\u003d\"Unable to create input stream for registry cache.\"\n       code\u003d\"2\"\u003e\n      \u003cexception\n         message\u003d\"d:\\eclipse\\test\\.metadata\\.registry.bak (The system cannot \nfind the file specified)\"\n         trace\u003d\"\njava.io.FileNotFoundException: d:\\eclipse\\test\\.metadata\\.registry.bak (The \nsystem cannot find the file specified)\n\tat java.io.FileInputStream.open(Native Method)\n\tat java.io.FileInputStream.\u0026lt;init\u0026gt;(FileInputStream.java:70)\n\tat java.io.FileInputStream.\u0026lt;init\u0026gt;(FileInputStream.java:101)\n\tat \norg.eclipse.core.internal.runtime.SafeFileInputStream.getInputStream(SafeFileInp\nutStream.java:37)\n\tat \norg.eclipse.core.internal.runtime.SafeFileInputStream.\u0026lt;init\u0026gt;(SafeFileInput\nStream.java:28)\n\tat \norg.eclipse.core.internal.runtime.InternalPlatform.loadRegistry(InternalPlatform\n.java:665)\n\tat \norg.eclipse.core.internal.runtime.InternalPlatform.loaderStartup(InternalPlatfor\nm.java:587)\n\tat java.lang.reflect.Method.invoke(Native Method)\n\tat \norg.eclipse.core.internal.boot.InternalBootLoader.startup(InternalBootLoader.jav\na:978)\n\tat \norg.eclipse.core.internal.boot.InternalBootLoader.run(InternalBootLoader.java:86\n6)\n\tat org.eclipse.core.boot.BootLoader.run(BootLoader.java:321)\n\tat java.lang.reflect.Method.invoke(Native Method)\n\tat org.eclipse.core.launcher.Main.basicRun(Main.java:151)\n\tat org.eclipse.core.launcher.Main.run(Main.java:502)\n\tat org.eclipse.core.launcher.UIMain.main(UIMain.java:52)\n\"\u003e\n      \u003c/exception\u003e\n    \u003c/status\u003e\n  \u003c/status\u003e",
    "This error message typically appears when you first set the -registrycache \noption (the first time, we try to read the registry from a cache file which \ndoesn\u0027t exist).  Now, we determine that the cache file exists before we try to \nread from it.\n\n"
  ],
  "commentCreationDates": [
    "2002-01-17T15:51:45+01:00",
    "2002-01-17T16:51:12+01:00"
  ],
  "traces": [
    {
      "exceptionType": "java.io.FileNotFoundException",
      "message": "d:\\eclipse\\test\\.metadata\\.registry.bak (The  system cannot find the file specified)",
      "elements": [
        {
          "method": "java.io.FileInputStream.open",
          "source": "Native Method"
        }
      ],
      "number": 0,
      "commentIndex": 0,
      "bugId": "7843",
      "date": "2002-01-17T15:51:45+01:00",
      "product": "Platform",
      "component": "Resources",
      "severity": "normal"
    }
  ],
  "groupId": "7843",
  "bugId": "7843",
  "date": "2002-01-17T15:51:45+01:00",
  "product": "Platform",
  "component": "Resources",
  "severity": "normal"
}