{
  "comments": [
    "I20041112-gtk\n\nI added a classpath variable to my source lookup settings in a launch config.\nThen I got the exception below. Please dispatch to Core if you think that it\u0027s\nnot you...\n\nThe classpatch variable contained this string:\n\n${ECLIPSE_HOME}/plugins/org.eclipse.motif_3.0.0/ws/motif\n\n!ENTRY org.eclipse.core.runtime 4 2 2004-11-15 18:43:17.650\n!MESSAGE Problems occurred when invoking code from plug-in:\n\"org.eclipse.core.runtime\".\n!STACK 0\norg.eclipse.jdt.internal.core.Assert$AssertionFailedException: Assertion failed;\nPath for IClasspathEntry must be absolute\n        at org.eclipse.jdt.internal.core.Assert.isTrue(Assert.java:89)\n        at org.eclipse.jdt.core.JavaCore.newLibraryEntry(JavaCore.java:3033)\n        at org.eclipse.jdt.core.JavaCore.newLibraryEntry(JavaCore.java:2906)\n        at\norg.eclipse.jdt.launching.JavaRuntime.newArchiveRuntimeClasspathEntry(JavaRuntime.java:541)\n        at\norg.eclipse.jdt.launching.sourcelookup.containers.ClasspathVariableSourceContainer.createSourceContainers(ClasspathVariableSourceContainer.java:64)\n        at\norg.eclipse.debug.core.sourcelookup.containers.CompositeSourceContainer.getSourceContainers(CompositeSourceContainer.java:126)\n        at\norg.eclipse.debug.core.sourcelookup.containers.CompositeSourceContainer.findSourceElements(CompositeSourceContainer.java:45)\n        at\norg.eclipse.debug.core.sourcelookup.AbstractSourceLookupParticipant.findSourceElements(AbstractSourceLookupParticipant.java:60)\n        at\norg.eclipse.debug.core.sourcelookup.AbstractSourceLookupDirector$SourceLookupQuery.run(AbstractSourceLookupDirector.java:125)\n        at\norg.eclipse.core.internal.runtime.InternalPlatform.run(InternalPlatform.java:616)\n        at org.eclipse.core.runtime.Platform.run(Platform.java:747)\n        at\norg.eclipse.debug.core.sourcelookup.AbstractSourceLookupDirector.doSourceLookup(AbstractSourceLookupDirector.java:443)\n        at\norg.eclipse.debug.core.sourcelookup.AbstractSourceLookupDirector.getSourceElement(AbstractSourceLookupDirector.java:692)\n        at\norg.eclipse.debug.core.sourcelookup.AbstractSourceLookupDirector.getSourceElement(AbstractSourceLookupDirector.java:431)\n        at\norg.eclipse.debug.internal.ui.views.launch.LaunchView.lookupEditorInput(LaunchView.java:616)\n        at\norg.eclipse.debug.internal.ui.views.launch.LaunchView.openEditorForStackFrame(LaunchView.java:687)\n        at\norg.eclipse.debug.internal.ui.views.launch.LaunchView.showEditorForCurrentSelection(LaunchView.java:595)\n        at\norg.eclipse.debug.internal.ui.views.launch.LaunchView.selectionChanged(LaunchView.java:467)\n        at\norg.eclipse.jface.viewers.StructuredViewer$3.run(StructuredViewer.java:636)\n        at\norg.eclipse.core.internal.runtime.InternalPlatform.run(InternalPlatform.java:616)\n        at org.eclipse.core.runtime.Platform.run(Platform.java:747)\n        at\norg.eclipse.jface.viewers.StructuredViewer.firePostSelectionChanged(StructuredViewer.java:634)\n        at\norg.eclipse.jface.viewers.StructuredViewer.setSelection(StructuredViewer.java:1305)\n        at\norg.eclipse.debug.internal.ui.views.launch.LaunchViewer$SelectionJob.runInUIThread(LaunchViewer.java:90)\n        at org.eclipse.ui.progress.UIJob$1.run(UIJob.java:96)\n        at org.eclipse.swt.widgets.RunnableLock.run(RunnableLock.java:35)\n        at\norg.eclipse.swt.widgets.Synchronizer.runAsyncMessages(Synchronizer.java:118)\n        at org.eclipse.swt.widgets.Display.runAsyncMessages(Display.java:2647)\n        at org.eclipse.swt.widgets.Display.readAndDispatch(Display.java:2372)\n        at org.eclipse.ui.internal.Workbench.runEventLoop(Workbench.java:1537)\n        at org.eclipse.ui.internal.Workbench.runUI(Workbench.java:1508)\n        at\norg.eclipse.ui.internal.Workbench.createAndRunWorkbench(Workbench.java:277)\n        at org.eclipse.ui.PlatformUI.createAndRunWorkbench(PlatformUI.java:144)\n        at org.eclipse.ui.internal.ide.IDEApplication.run(IDEApplication.java:102)\n        at\norg.eclipse.core.internal.runtime.PlatformActivator$1.run(PlatformActivator.java:335)\n        at\norg.eclipse.core.runtime.adaptor.EclipseStarter.run(EclipseStarter.java:273)\n        at\norg.eclipse.core.runtime.adaptor.EclipseStarter.run(EclipseStarter.java:129)\n        at sun.reflect.NativeMethodAccessorImpl.invoke0(Native Method)\n        at\nsun.reflect.NativeMethodAccessorImpl.invoke(NativeMethodAccessorImpl.java:39)\n        at\nsun.reflect.DelegatingMethodAccessorImpl.invoke(DelegatingMethodAccessorImpl.java:25)\n        at java.lang.reflect.Method.invoke(Method.java:585)\n        at org.eclipse.core.launcher.Main.basicRun(Main.java:185)\n        at org.eclipse.core.launcher.Main.run(Main.java:710)\n        at org.eclipse.core.launcher.Main.main(Main.java:694)",
    "I am unable to reproduce the problem. Can you give steps?",
    "ok, I do have steps:\n\n1) on the Java\u003eBuild Path\u003eClasspath Variables preference page: create a new\nclasspath variable as described in comment 0\n\n-\u003e note that when adding the variable, the dialog tells me that the \"Path does\nnot exist\", presumeably because it cannot resolve the used ECLIPSE_HOME variable?\n\n2) open a runtime launch config dialog, select the \u0027Source\u0027 tab\n3) press \u0027Add\u0027 to add a source lookup path\n4) choose \u0027Java classpath variable\u0027 and select the variable created in step 1\n\n-\u003e a new entry is added to the list of source lookup paths\n-\u003e everything as expected so far\n\n5) expand the variable\n\n-\u003e this is where I get the exception",
    "Looks like it\u0027s just an invalid classpath variable - you were warned ;-)\nmoving to JDT Core for comment. ",
    "Actually it is not an invalid classpath variable, but a misused of JDT Core API.\nJDT Debug is calling JavaCore#newLibraryEntry(IPath, IPath, IPath) with a\nrelative path \"${ECLIPSE_HOME}/plugins/org.eclipse.motif_3.0.0/ws/motif\" as the\nfirst argument.\n\nJDT Debug should check that the path is absolute before passing it to\nnewLibrary(...)\n\nMoving to JDT Debug for comment",
    "I am unable to reproduce. The dialog no longer allows me to add in invalid \nvariable such as \"${ECLIPSE_HOME}\". I have to specify \"ECLISPE_HOME\", and then \nit works.",
    "Reproducable with the steps given in comment 2 and 3.1-RC2. Reopening.",
    "(In reply to comment #5)\n\u003e I am unable to reproduce. The dialog no longer allows me to add in invalid \n\u003e variable such as \"${ECLIPSE_HOME}\". I have to specify \"ECLISPE_HOME\", and then \n\u003e it works.\n\nDarinw, which dialog are you referring to here?",
    "Ah - from the buildpath page I can set the name to \"${...}\". However, I will \nhave to test on Linux, as it still does not cause this exception on Windows.",
    "Darin, you want to set the classpath variable name to TEST and its value to\n${ECLIPSE_HOME}/plugins/org.eclipse.motif_3.0.0/ws/motif. Then add the classpath\nvariable TEST on the source lookup page. This should behave the same on any\nplatform since the path ${ECLIPSE_HOME}/plugins/org.eclipse.motif_3.0.0/ws/motif\nis not absolute (it doesn\u0027t start with a slash).",
    "Deferred"
  ],
  "commentCreationDates": [
    "2004-11-15T17:52:04+01:00",
    "2004-11-15T18:49:34+01:00",
    "2004-11-17T14:24:02+01:00",
    "2005-05-04T19:50:52+02:00",
    "2005-06-13T11:21:19+02:00",
    "2005-06-13T16:58:08+02:00",
    "2005-06-13T17:30:25+02:00",
    "2005-06-13T17:34:22+02:00",
    "2005-06-13T17:49:04+02:00",
    "2005-06-14T12:33:30+02:00",
    "2005-06-17T18:06:28+02:00"
  ],
  "traces": [
    {
      "exceptionType": "org.eclipse.jdt.internal.core.Assert$AssertionFailedException",
      "message": "Assertion failed; Path for IClasspathEntry must be absolute",
      "elements": [
        {
          "method": "org.eclipse.jdt.internal.core.Assert.isTrue",
          "source": "Assert.java:89"
        },
        {
          "method": "org.eclipse.jdt.core.JavaCore.newLibraryEntry",
          "source": "JavaCore.java:3033"
        },
        {
          "method": "org.eclipse.jdt.core.JavaCore.newLibraryEntry",
          "source": "JavaCore.java:2906"
        },
        {
          "method": "org.eclipse.jdt.launching.JavaRuntime.newArchiveRuntimeClasspathEntry",
          "source": "JavaRuntime.java:541"
        },
        {
          "method": "org.eclipse.jdt.launching.sourcelookup.containers.ClasspathVariableSourceContainer.createSourceContainers",
          "source": "ClasspathVariableSourceContainer.java:64"
        },
        {
          "method": "org.eclipse.debug.core.sourcelookup.containers.CompositeSourceContainer.getSourceContainers",
          "source": "CompositeSourceContainer.java:126"
        },
        {
          "method": "org.eclipse.debug.core.sourcelookup.containers.CompositeSourceContainer.findSourceElements",
          "source": "CompositeSourceContainer.java:45"
        },
        {
          "method": "org.eclipse.debug.core.sourcelookup.AbstractSourceLookupParticipant.findSourceElements",
          "source": "AbstractSourceLookupParticipant.java:60"
        },
        {
          "method": "org.eclipse.debug.core.sourcelookup.AbstractSourceLookupDirector$SourceLookupQuery.run",
          "source": "AbstractSourceLookupDirector.java:125"
        },
        {
          "method": "org.eclipse.core.internal.runtime.InternalPlatform.run",
          "source": "InternalPlatform.java:616"
        },
        {
          "method": "org.eclipse.core.runtime.Platform.run",
          "source": "Platform.java:747"
        },
        {
          "method": "org.eclipse.debug.core.sourcelookup.AbstractSourceLookupDirector.doSourceLookup",
          "source": "AbstractSourceLookupDirector.java:443"
        },
        {
          "method": "org.eclipse.debug.core.sourcelookup.AbstractSourceLookupDirector.getSourceElement",
          "source": "AbstractSourceLookupDirector.java:692"
        },
        {
          "method": "org.eclipse.debug.core.sourcelookup.AbstractSourceLookupDirector.getSourceElement",
          "source": "AbstractSourceLookupDirector.java:431"
        },
        {
          "method": "org.eclipse.debug.internal.ui.views.launch.LaunchView.lookupEditorInput",
          "source": "LaunchView.java:616"
        },
        {
          "method": "org.eclipse.debug.internal.ui.views.launch.LaunchView.openEditorForStackFrame",
          "source": "LaunchView.java:687"
        },
        {
          "method": "org.eclipse.debug.internal.ui.views.launch.LaunchView.showEditorForCurrentSelection",
          "source": "LaunchView.java:595"
        },
        {
          "method": "org.eclipse.debug.internal.ui.views.launch.LaunchView.selectionChanged",
          "source": "LaunchView.java:467"
        },
        {
          "method": "org.eclipse.jface.viewers.StructuredViewer$3.run",
          "source": "StructuredViewer.java:636"
        },
        {
          "method": "org.eclipse.core.internal.runtime.InternalPlatform.run",
          "source": "InternalPlatform.java:616"
        },
        {
          "method": "org.eclipse.core.runtime.Platform.run",
          "source": "Platform.java:747"
        },
        {
          "method": "org.eclipse.jface.viewers.StructuredViewer.firePostSelectionChanged",
          "source": "StructuredViewer.java:634"
        },
        {
          "method": "org.eclipse.jface.viewers.StructuredViewer.setSelection",
          "source": "StructuredViewer.java:1305"
        },
        {
          "method": "org.eclipse.debug.internal.ui.views.launch.LaunchViewer$SelectionJob.runInUIThread",
          "source": "LaunchViewer.java:90"
        },
        {
          "method": "org.eclipse.ui.progress.UIJob$1.run",
          "source": "UIJob.java:96"
        },
        {
          "method": "org.eclipse.swt.widgets.RunnableLock.run",
          "source": "RunnableLock.java:35"
        },
        {
          "method": "org.eclipse.swt.widgets.Synchronizer.runAsyncMessages",
          "source": "Synchronizer.java:118"
        },
        {
          "method": "org.eclipse.swt.widgets.Display.runAsyncMessages",
          "source": "Display.java:2647"
        },
        {
          "method": "org.eclipse.swt.widgets.Display.readAndDispatch",
          "source": "Display.java:2372"
        },
        {
          "method": "org.eclipse.ui.internal.Workbench.runEventLoop",
          "source": "Workbench.java:1537"
        },
        {
          "method": "org.eclipse.ui.internal.Workbench.runUI",
          "source": "Workbench.java:1508"
        },
        {
          "method": "org.eclipse.ui.internal.Workbench.createAndRunWorkbench",
          "source": "Workbench.java:277"
        },
        {
          "method": "org.eclipse.ui.PlatformUI.createAndRunWorkbench",
          "source": "PlatformUI.java:144"
        },
        {
          "method": "org.eclipse.ui.internal.ide.IDEApplication.run",
          "source": "IDEApplication.java:102"
        },
        {
          "method": "org.eclipse.core.internal.runtime.PlatformActivator$1.run",
          "source": "PlatformActivator.java:335"
        },
        {
          "method": "org.eclipse.core.runtime.adaptor.EclipseStarter.run",
          "source": "EclipseStarter.java:273"
        },
        {
          "method": "org.eclipse.core.runtime.adaptor.EclipseStarter.run",
          "source": "EclipseStarter.java:129"
        },
        {
          "method": "sun.reflect.NativeMethodAccessorImpl.invoke0",
          "source": "Native Method"
        },
        {
          "method": "sun.reflect.NativeMethodAccessorImpl.invoke",
          "source": "NativeMethodAccessorImpl.java:39"
        },
        {
          "method": "sun.reflect.DelegatingMethodAccessorImpl.invoke",
          "source": "DelegatingMethodAccessorImpl.java:25"
        },
        {
          "method": "java.lang.reflect.Method.invoke",
          "source": "Method.java:585"
        },
        {
          "method": "org.eclipse.core.launcher.Main.basicRun",
          "source": "Main.java:185"
        },
        {
          "method": "org.eclipse.core.launcher.Main.run",
          "source": "Main.java:710"
        },
        {
          "method": "org.eclipse.core.launcher.Main.main",
          "source": "Main.java:694"
        }
      ],
      "number": 0,
      "commentIndex": 0,
      "bugId": "78638",
      "date": "2004-11-15T17:52:04+01:00",
      "product": "JDT",
      "component": "Debug",
      "severity": "normal"
    }
  ],
  "groupId": "78638",
  "bugId": "78638",
  "date": "2004-11-15T17:52:04+01:00",
  "product": "JDT",
  "component": "Debug",
  "severity": "normal"
}