{
  "comments": [
    "I200411160944 \n \nI\u0027m not sure what caused this, but it might have been \"Remove from View\" with \nthe commit sets turned on.  When I tried that, the item wouldn\u0027t actually \ndisappear until I turned commit sets off and then on again. \n \n \n \n!ENTRY org.eclipse.ui 4 4 2004-11-16 14:53:53.510 \n!MESSAGE *** SWT nested exception \n \n!ENTRY org.eclipse.ui 4 0 2004-11-16 14:53:53.511 \n!MESSAGE java.lang.ArrayStoreException \n!STACK 0 \njava.lang.ArrayStoreException \n        at java.util.ArrayList.toArray(ArrayList.java:337) \n        at \norg.eclipse.team.internal.ui.synchronize.CompressedFoldersModelProvider.handleResourceRemovals(CompressedFoldersModelProvider.java:291) \n        at \norg.eclipse.team.internal.ui.synchronize.AbstractSynchronizeModelProvider.handleChanges(AbstractSynchronizeModelProvider.java:654) \n        at \norg.eclipse.team.internal.ui.synchronize.SynchronizeModelProvider.handleChanges(SynchronizeModelProvider.java:202) \n        at \norg.eclipse.team.internal.ui.synchronize.SynchronizeModelUpdateHandler$3.run(SynchronizeModelUpdateHandler.java:514) \n        at \norg.eclipse.team.internal.ui.synchronize.SynchronizeModelUpdateHandler.internalRunViewUpdate(SynchronizeModelUpdateHandler.java:587) \n        at \norg.eclipse.team.internal.ui.synchronize.SynchronizeModelUpdateHandler.access$1\n(SynchronizeModelUpdateHandler.java:575) \n        at \norg.eclipse.team.internal.ui.synchronize.SynchronizeModelUpdateHandler$5.run(SynchronizeModelUpdateHandler.java:554) \n        at \norg.eclipse.swt.custom.BusyIndicator.showWhile(BusyIndicator.java:69) \n        at \norg.eclipse.team.internal.ui.synchronize.SynchronizeModelUpdateHandler$4.run(SynchronizeModelUpdateHandler.java:552) \n        at \norg.eclipse.ui.internal.UILockListener.doPendingWork(UILockListener.java:145) \n        at org.eclipse.ui.internal.UISynchronizer$1.run(UISynchronizer.java:36) \n        at org.eclipse.swt.widgets.RunnableLock.run(RunnableLock.java:35) \n        at \norg.eclipse.swt.widgets.Synchronizer.runAsyncMessages(Synchronizer.java:118) \n        at org.eclipse.swt.widgets.Display.runAsyncMessages(Display.java:2647) \n        at org.eclipse.swt.widgets.Display.readAndDispatch(Display.java:2372) \n        at org.eclipse.ui.internal.Workbench.runEventLoop(Workbench.java:1573) \n        at org.eclipse.ui.internal.Workbench.runUI(Workbench.java:1544) \n        at \norg.eclipse.ui.internal.Workbench.createAndRunWorkbench(Workbench.java:279) \n        at org.eclipse.ui.PlatformUI.createAndRunWorkbench(PlatformUI.java:144) \n        at \norg.eclipse.ui.internal.ide.IDEApplication.run(IDEApplication.java:102) \n        at \norg.eclipse.core.internal.runtime.PlatformActivator$1.run(PlatformActivator.java:220) \n        at \norg.eclipse.core.runtime.adaptor.EclipseStarter.run(EclipseStarter.java:273) \n        at \norg.eclipse.core.runtime.adaptor.EclipseStarter.run(EclipseStarter.java:129) \n        at sun.reflect.NativeMethodAccessorImpl.invoke0(Native Method) \n        at \nsun.reflect.NativeMethodAccessorImpl.invoke(NativeMethodAccessorImpl.java:85) \n        at \nsun.reflect.NativeMethodAccessorImpl.invoke(NativeMethodAccessorImpl.java:58) \n        at \nsun.reflect.DelegatingMethodAccessorImpl.invoke(DelegatingMethodAccessorImpl.java:60) \n        at java.lang.reflect.Method.invoke(Method.java:391) \n        at org.eclipse.core.launcher.Main.basicRun(Main.java:185) \n        at org.eclipse.core.launcher.Main.run(Main.java:684) \n        at org.eclipse.core.launcher.Main.main(Main.java:668)",
    "Fix released to HEAD"
  ],
  "commentCreationDates": [
    "2004-11-16T21:23:23+01:00",
    "2004-11-22T19:42:00+01:00"
  ],
  "traces": [
    {
      "exceptionType": "java.lang.ArrayStoreException",
      "elements": [
        {
          "method": "java.util.ArrayList.toArray",
          "source": "ArrayList.java:337"
        },
        {
          "method": "org.eclipse.team.internal.ui.synchronize.CompressedFoldersModelProvider.handleResourceRemovals",
          "source": "CompressedFoldersModelProvider.java:291"
        },
        {
          "method": "org.eclipse.team.internal.ui.synchronize.AbstractSynchronizeModelProvider.handleChanges",
          "source": "AbstractSynchronizeModelProvider.java:654"
        },
        {
          "method": "org.eclipse.team.internal.ui.synchronize.SynchronizeModelProvider.handleChanges",
          "source": "SynchronizeModelProvider.java:202"
        },
        {
          "method": "org.eclipse.team.internal.ui.synchronize.SynchronizeModelUpdateHandler$3.run",
          "source": "SynchronizeModelUpdateHandler.java:514"
        },
        {
          "method": "org.eclipse.team.internal.ui.synchronize.SynchronizeModelUpdateHandler.internalRunViewUpdate",
          "source": "SynchronizeModelUpdateHandler.java:587"
        },
        {
          "method": "org.eclipse.team.internal.ui.synchronize.SynchronizeModelUpdateHandler.access$1",
          "source": "SynchronizeModelUpdateHandler.java:575"
        },
        {
          "method": "org.eclipse.team.internal.ui.synchronize.SynchronizeModelUpdateHandler$5.run",
          "source": "SynchronizeModelUpdateHandler.java:554"
        },
        {
          "method": "org.eclipse.swt.custom.BusyIndicator.showWhile",
          "source": "BusyIndicator.java:69"
        },
        {
          "method": "org.eclipse.team.internal.ui.synchronize.SynchronizeModelUpdateHandler$4.run",
          "source": "SynchronizeModelUpdateHandler.java:552"
        },
        {
          "method": "org.eclipse.ui.internal.UILockListener.doPendingWork",
          "source": "UILockListener.java:145"
        },
        {
          "method": "org.eclipse.ui.internal.UISynchronizer$1.run",
          "source": "UISynchronizer.java:36"
        },
        {
          "method": "org.eclipse.swt.widgets.RunnableLock.run",
          "source": "RunnableLock.java:35"
        },
        {
          "method": "org.eclipse.swt.widgets.Synchronizer.runAsyncMessages",
          "source": "Synchronizer.java:118"
        },
        {
          "method": "org.eclipse.swt.widgets.Display.runAsyncMessages",
          "source": "Display.java:2647"
        },
        {
          "method": "org.eclipse.swt.widgets.Display.readAndDispatch",
          "source": "Display.java:2372"
        },
        {
          "method": "org.eclipse.ui.internal.Workbench.runEventLoop",
          "source": "Workbench.java:1573"
        },
        {
          "method": "org.eclipse.ui.internal.Workbench.runUI",
          "source": "Workbench.java:1544"
        },
        {
          "method": "org.eclipse.ui.internal.Workbench.createAndRunWorkbench",
          "source": "Workbench.java:279"
        },
        {
          "method": "org.eclipse.ui.PlatformUI.createAndRunWorkbench",
          "source": "PlatformUI.java:144"
        },
        {
          "method": "org.eclipse.ui.internal.ide.IDEApplication.run",
          "source": "IDEApplication.java:102"
        },
        {
          "method": "org.eclipse.core.internal.runtime.PlatformActivator$1.run",
          "source": "PlatformActivator.java:220"
        },
        {
          "method": "org.eclipse.core.runtime.adaptor.EclipseStarter.run",
          "source": "EclipseStarter.java:273"
        },
        {
          "method": "org.eclipse.core.runtime.adaptor.EclipseStarter.run",
          "source": "EclipseStarter.java:129"
        },
        {
          "method": "sun.reflect.NativeMethodAccessorImpl.invoke0",
          "source": "Native Method"
        },
        {
          "method": "sun.reflect.NativeMethodAccessorImpl.invoke",
          "source": "NativeMethodAccessorImpl.java:85"
        },
        {
          "method": "sun.reflect.NativeMethodAccessorImpl.invoke",
          "source": "NativeMethodAccessorImpl.java:58"
        },
        {
          "method": "sun.reflect.DelegatingMethodAccessorImpl.invoke",
          "source": "DelegatingMethodAccessorImpl.java:60"
        },
        {
          "method": "java.lang.reflect.Method.invoke",
          "source": "Method.java:391"
        },
        {
          "method": "org.eclipse.core.launcher.Main.basicRun",
          "source": "Main.java:185"
        },
        {
          "method": "org.eclipse.core.launcher.Main.run",
          "source": "Main.java:684"
        },
        {
          "method": "org.eclipse.core.launcher.Main.main",
          "source": "Main.java:668"
        }
      ],
      "number": 0,
      "commentIndex": 0,
      "bugId": "78793",
      "date": "2004-11-16T21:23:23+01:00",
      "product": "Platform",
      "component": "Team",
      "severity": "normal"
    }
  ],
  "groupId": "78793",
  "bugId": "78793",
  "date": "2004-11-16T21:23:23+01:00",
  "product": "Platform",
  "component": "Team",
  "severity": "normal"
}