{
  "comments": [
    "class TestSuper0 {\n  void foo() {\n  }\n}\n\npublic class TestSuper extends TestSuper0 {\n  public static void main(String[] args) {\n    new TestSuper().foo();\n  }\n  void foo() {\n    System.out.println();  // \u003c-- breakpoint\n  }\n}\n\nDebug to the breakpoint, evaluate \u0027super.foo()\u0027 :\n\n!ENTRY org.eclipse.ui 4 0 2004-11-17 14:57:46.915\n!MESSAGE Array index out of range: -1\n!STACK 0\njava.lang.ArrayIndexOutOfBoundsException: Array index out of range: -1\n        at\norg.eclipse.jdt.internal.debug.eval.ast.engine.ASTInstructionCompiler.visit(ASTInstructionCompiler.java:2995)\n        at\norg.eclipse.jdt.core.dom.SuperMethodInvocation.accept0(SuperMethodInvocation.java:236)\n        at org.eclipse.jdt.core.dom.ASTNode.accept(ASTNode.java:2450)\n        at org.eclipse.jdt.core.dom.ASTNode.acceptChild(ASTNode.java:2497)\n        at\norg.eclipse.jdt.core.dom.ExpressionStatement.accept0(ExpressionStatement.java:143)\n        at org.eclipse.jdt.core.dom.ASTNode.accept(ASTNode.java:2450)\n        at org.eclipse.jdt.core.dom.ASTNode.acceptChildren(ASTNode.java:2520)\n        at org.eclipse.jdt.core.dom.Block.accept0(Block.java:135)\n        at org.eclipse.jdt.core.dom.ASTNode.accept(ASTNode.java:2450)\n        at org.eclipse.jdt.core.dom.ASTNode.acceptChild(ASTNode.java:2497)\n        at\norg.eclipse.jdt.core.dom.MethodDeclaration.accept0(MethodDeclaration.java:504)\n        at org.eclipse.jdt.core.dom.ASTNode.accept(ASTNode.java:2450)\n        at org.eclipse.jdt.core.dom.ASTNode.acceptChildren(ASTNode.java:2520)\n        at\norg.eclipse.jdt.core.dom.TypeDeclaration.accept0(TypeDeclaration.java:486)\n        at org.eclipse.jdt.core.dom.ASTNode.accept(ASTNode.java:2450)\n        at org.eclipse.jdt.core.dom.ASTNode.acceptChildren(ASTNode.java:2520)\n        at\norg.eclipse.jdt.core.dom.CompilationUnit.accept0(CompilationUnit.java:291)\n        at org.eclipse.jdt.core.dom.ASTNode.accept(ASTNode.java:2450)\n        at\norg.eclipse.jdt.internal.debug.eval.ast.engine.ASTEvaluationEngine.createExpressionFromAST(ASTEvaluationEngine.java:275)\n        at\norg.eclipse.jdt.internal.debug.eval.ast.engine.ASTEvaluationEngine.getCompiledExpression(ASTEvaluationEngine.java:158)\n        at\norg.eclipse.jdt.internal.debug.eval.ast.engine.ASTEvaluationEngine.evaluate(ASTEvaluationEngine.java:75)\n        at\norg.eclipse.jdt.internal.debug.ui.actions.EvaluateAction.run(EvaluateAction.java:243)\n        at\norg.eclipse.jdt.internal.debug.ui.actions.DisplayAction.run(DisplayAction.java:104)\n        at\norg.eclipse.jdt.internal.debug.ui.actions.EvaluateAction.run(EvaluateAction.java:564)\n        at org.eclipse.ui.internal.PluginAction.runWithEvent(PluginAction.java:298)\n        at\norg.eclipse.ui.internal.WWinPluginAction.runWithEvent(WWinPluginAction.java:221)\n        at org.eclipse.ui.commands.ActionHandler.execute(ActionHandler.java:188)\n        at org.eclipse.ui.internal.commands.Command.execute(Command.java:130)\n        at\norg.eclipse.ui.internal.keys.WorkbenchKeyboard.executeCommand(WorkbenchKeyboard.java:445)\n        at\norg.eclipse.ui.internal.keys.WorkbenchKeyboard.press(WorkbenchKeyboard.java:724)\n        at\norg.eclipse.ui.internal.keys.WorkbenchKeyboard.processKeyEvent(WorkbenchKeyboard.java:767)\n        at\norg.eclipse.ui.internal.keys.WorkbenchKeyboard.filterKeySequenceBindings(WorkbenchKeyboard.java:536)\n        at\norg.eclipse.ui.internal.keys.WorkbenchKeyboard.access$2(WorkbenchKeyboard.java:479)\n        at\norg.eclipse.ui.internal.keys.WorkbenchKeyboard$1.handleEvent(WorkbenchKeyboard.java:221)\n        at org.eclipse.swt.widgets.EventTable.sendEvent(EventTable.java:82)\n        at org.eclipse.swt.widgets.Display.filterEvent(Display.java:1060)\n        at org.eclipse.swt.widgets.Widget.sendEvent(Widget.java:990)\n        at org.eclipse.swt.widgets.Widget.sendEvent(Widget.java:1015)\n        at org.eclipse.swt.widgets.Widget.sendEvent(Widget.java:1000)\n        at org.eclipse.swt.widgets.Widget.sendKeyEvent(Widget.java:1027)\n        at org.eclipse.swt.widgets.Widget.gtk_key_press_event(Widget.java:595)\n        at org.eclipse.swt.widgets.Control.gtk_key_press_event(Control.java:1870)\n        at org.eclipse.swt.widgets.Composite.gtk_key_press_event(Composite.java:522)\n        at org.eclipse.swt.widgets.Widget.windowProc(Widget.java:1327)\n        at org.eclipse.swt.widgets.Display.windowProc(Display.java:3222)\n        at org.eclipse.swt.internal.gtk.OS.gtk_main_do_event(Native Method)\n        at org.eclipse.swt.widgets.Display.eventProc(Display.java:903)\n        at org.eclipse.swt.internal.gtk.OS.g_main_context_iteration(Native Method)\n        at org.eclipse.swt.widgets.Display.readAndDispatch(Display.java:2367)\n        at org.eclipse.ui.internal.Workbench.runEventLoop(Workbench.java:1573)\n        at org.eclipse.ui.internal.Workbench.runUI(Workbench.java:1544)\n        at\norg.eclipse.ui.internal.Workbench.createAndRunWorkbench(Workbench.java:279)\n        at org.eclipse.ui.PlatformUI.createAndRunWorkbench(PlatformUI.java:144)\n        at org.eclipse.ui.internal.ide.IDEApplication.run(IDEApplication.java:102)\n        at\norg.eclipse.core.internal.runtime.PlatformActivator$1.run(PlatformActivator.java:220)\n        at\norg.eclipse.core.runtime.adaptor.EclipseStarter.run(EclipseStarter.java:273)\n        at\norg.eclipse.core.runtime.adaptor.EclipseStarter.run(EclipseStarter.java:129)\n        at sun.reflect.NativeMethodAccessorImpl.invoke0(Native Method)\n        at\nsun.reflect.NativeMethodAccessorImpl.invoke(NativeMethodAccessorImpl.java:85)\n        at\nsun.reflect.NativeMethodAccessorImpl.invoke(NativeMethodAccessorImpl.java:58)\n        at\nsun.reflect.DelegatingMethodAccessorImpl.invoke(DelegatingMethodAccessorImpl.java:60)\n        at java.lang.reflect.Method.invoke(Method.java:391)\n        at org.eclipse.core.launcher.Main.basicRun(Main.java:185)\n        at org.eclipse.core.launcher.Main.run(Main.java:684)\n        at org.eclipse.core.launcher.Main.main(Main.java:668)",
    "Fixed.\nThis bug was introduce while adding the support for varargs methods, it was the\nlittle brother of bug 76860.\n\nChanges in ASTInstructionCompiler#visit(SuperMethodInvocation).",
    "Please verify, Darin W.",
    "Verified."
  ],
  "commentCreationDates": [
    "2004-11-17T23:00:40+01:00",
    "2004-11-17T23:06:49+01:00",
    "2004-11-17T23:08:05+01:00",
    "2004-11-22T20:37:37+01:00"
  ],
  "traces": [
    {
      "exceptionType": "java.lang.ArrayIndexOutOfBoundsException",
      "message": "Array index out of range: -1",
      "elements": [
        {
          "method": "org.eclipse.jdt.internal.debug.eval.ast.engine.ASTInstructionCompiler.visit",
          "source": "ASTInstructionCompiler.java:2995"
        },
        {
          "method": "org.eclipse.jdt.core.dom.SuperMethodInvocation.accept0",
          "source": "SuperMethodInvocation.java:236"
        },
        {
          "method": "org.eclipse.jdt.core.dom.ASTNode.accept",
          "source": "ASTNode.java:2450"
        },
        {
          "method": "org.eclipse.jdt.core.dom.ASTNode.acceptChild",
          "source": "ASTNode.java:2497"
        },
        {
          "method": "org.eclipse.jdt.core.dom.ExpressionStatement.accept0",
          "source": "ExpressionStatement.java:143"
        },
        {
          "method": "org.eclipse.jdt.core.dom.ASTNode.accept",
          "source": "ASTNode.java:2450"
        },
        {
          "method": "org.eclipse.jdt.core.dom.ASTNode.acceptChildren",
          "source": "ASTNode.java:2520"
        },
        {
          "method": "org.eclipse.jdt.core.dom.Block.accept0",
          "source": "Block.java:135"
        },
        {
          "method": "org.eclipse.jdt.core.dom.ASTNode.accept",
          "source": "ASTNode.java:2450"
        },
        {
          "method": "org.eclipse.jdt.core.dom.ASTNode.acceptChild",
          "source": "ASTNode.java:2497"
        },
        {
          "method": "org.eclipse.jdt.core.dom.MethodDeclaration.accept0",
          "source": "MethodDeclaration.java:504"
        },
        {
          "method": "org.eclipse.jdt.core.dom.ASTNode.accept",
          "source": "ASTNode.java:2450"
        },
        {
          "method": "org.eclipse.jdt.core.dom.ASTNode.acceptChildren",
          "source": "ASTNode.java:2520"
        },
        {
          "method": "org.eclipse.jdt.core.dom.TypeDeclaration.accept0",
          "source": "TypeDeclaration.java:486"
        },
        {
          "method": "org.eclipse.jdt.core.dom.ASTNode.accept",
          "source": "ASTNode.java:2450"
        },
        {
          "method": "org.eclipse.jdt.core.dom.ASTNode.acceptChildren",
          "source": "ASTNode.java:2520"
        },
        {
          "method": "org.eclipse.jdt.core.dom.CompilationUnit.accept0",
          "source": "CompilationUnit.java:291"
        },
        {
          "method": "org.eclipse.jdt.core.dom.ASTNode.accept",
          "source": "ASTNode.java:2450"
        },
        {
          "method": "org.eclipse.jdt.internal.debug.eval.ast.engine.ASTEvaluationEngine.createExpressionFromAST",
          "source": "ASTEvaluationEngine.java:275"
        },
        {
          "method": "org.eclipse.jdt.internal.debug.eval.ast.engine.ASTEvaluationEngine.getCompiledExpression",
          "source": "ASTEvaluationEngine.java:158"
        },
        {
          "method": "org.eclipse.jdt.internal.debug.eval.ast.engine.ASTEvaluationEngine.evaluate",
          "source": "ASTEvaluationEngine.java:75"
        },
        {
          "method": "org.eclipse.jdt.internal.debug.ui.actions.EvaluateAction.run",
          "source": "EvaluateAction.java:243"
        },
        {
          "method": "org.eclipse.jdt.internal.debug.ui.actions.DisplayAction.run",
          "source": "DisplayAction.java:104"
        },
        {
          "method": "org.eclipse.jdt.internal.debug.ui.actions.EvaluateAction.run",
          "source": "EvaluateAction.java:564"
        },
        {
          "method": "org.eclipse.ui.internal.PluginAction.runWithEvent",
          "source": "PluginAction.java:298"
        },
        {
          "method": "org.eclipse.ui.internal.WWinPluginAction.runWithEvent",
          "source": "WWinPluginAction.java:221"
        },
        {
          "method": "org.eclipse.ui.commands.ActionHandler.execute",
          "source": "ActionHandler.java:188"
        },
        {
          "method": "org.eclipse.ui.internal.commands.Command.execute",
          "source": "Command.java:130"
        },
        {
          "method": "org.eclipse.ui.internal.keys.WorkbenchKeyboard.executeCommand",
          "source": "WorkbenchKeyboard.java:445"
        },
        {
          "method": "org.eclipse.ui.internal.keys.WorkbenchKeyboard.press",
          "source": "WorkbenchKeyboard.java:724"
        },
        {
          "method": "org.eclipse.ui.internal.keys.WorkbenchKeyboard.processKeyEvent",
          "source": "WorkbenchKeyboard.java:767"
        },
        {
          "method": "org.eclipse.ui.internal.keys.WorkbenchKeyboard.filterKeySequenceBindings",
          "source": "WorkbenchKeyboard.java:536"
        },
        {
          "method": "org.eclipse.ui.internal.keys.WorkbenchKeyboard.access$2",
          "source": "WorkbenchKeyboard.java:479"
        },
        {
          "method": "org.eclipse.ui.internal.keys.WorkbenchKeyboard$1.handleEvent",
          "source": "WorkbenchKeyboard.java:221"
        },
        {
          "method": "org.eclipse.swt.widgets.EventTable.sendEvent",
          "source": "EventTable.java:82"
        },
        {
          "method": "org.eclipse.swt.widgets.Display.filterEvent",
          "source": "Display.java:1060"
        },
        {
          "method": "org.eclipse.swt.widgets.Widget.sendEvent",
          "source": "Widget.java:990"
        },
        {
          "method": "org.eclipse.swt.widgets.Widget.sendEvent",
          "source": "Widget.java:1015"
        },
        {
          "method": "org.eclipse.swt.widgets.Widget.sendEvent",
          "source": "Widget.java:1000"
        },
        {
          "method": "org.eclipse.swt.widgets.Widget.sendKeyEvent",
          "source": "Widget.java:1027"
        },
        {
          "method": "org.eclipse.swt.widgets.Widget.gtk_key_press_event",
          "source": "Widget.java:595"
        },
        {
          "method": "org.eclipse.swt.widgets.Control.gtk_key_press_event",
          "source": "Control.java:1870"
        },
        {
          "method": "org.eclipse.swt.widgets.Composite.gtk_key_press_event",
          "source": "Composite.java:522"
        },
        {
          "method": "org.eclipse.swt.widgets.Widget.windowProc",
          "source": "Widget.java:1327"
        },
        {
          "method": "org.eclipse.swt.widgets.Display.windowProc",
          "source": "Display.java:3222"
        },
        {
          "method": "org.eclipse.swt.internal.gtk.OS.gtk_main_do_event",
          "source": "Native Method"
        },
        {
          "method": "org.eclipse.swt.widgets.Display.eventProc",
          "source": "Display.java:903"
        },
        {
          "method": "org.eclipse.swt.internal.gtk.OS.g_main_context_iteration",
          "source": "Native Method"
        },
        {
          "method": "org.eclipse.swt.widgets.Display.readAndDispatch",
          "source": "Display.java:2367"
        },
        {
          "method": "org.eclipse.ui.internal.Workbench.runEventLoop",
          "source": "Workbench.java:1573"
        },
        {
          "method": "org.eclipse.ui.internal.Workbench.runUI",
          "source": "Workbench.java:1544"
        },
        {
          "method": "org.eclipse.ui.internal.Workbench.createAndRunWorkbench",
          "source": "Workbench.java:279"
        },
        {
          "method": "org.eclipse.ui.PlatformUI.createAndRunWorkbench",
          "source": "PlatformUI.java:144"
        },
        {
          "method": "org.eclipse.ui.internal.ide.IDEApplication.run",
          "source": "IDEApplication.java:102"
        },
        {
          "method": "org.eclipse.core.internal.runtime.PlatformActivator$1.run",
          "source": "PlatformActivator.java:220"
        },
        {
          "method": "org.eclipse.core.runtime.adaptor.EclipseStarter.run",
          "source": "EclipseStarter.java:273"
        },
        {
          "method": "org.eclipse.core.runtime.adaptor.EclipseStarter.run",
          "source": "EclipseStarter.java:129"
        },
        {
          "method": "sun.reflect.NativeMethodAccessorImpl.invoke0",
          "source": "Native Method"
        },
        {
          "method": "sun.reflect.NativeMethodAccessorImpl.invoke",
          "source": "NativeMethodAccessorImpl.java:85"
        },
        {
          "method": "sun.reflect.NativeMethodAccessorImpl.invoke",
          "source": "NativeMethodAccessorImpl.java:58"
        },
        {
          "method": "sun.reflect.DelegatingMethodAccessorImpl.invoke",
          "source": "DelegatingMethodAccessorImpl.java:60"
        },
        {
          "method": "java.lang.reflect.Method.invoke",
          "source": "Method.java:391"
        },
        {
          "method": "org.eclipse.core.launcher.Main.basicRun",
          "source": "Main.java:185"
        },
        {
          "method": "org.eclipse.core.launcher.Main.run",
          "source": "Main.java:684"
        },
        {
          "method": "org.eclipse.core.launcher.Main.main",
          "source": "Main.java:668"
        }
      ],
      "number": 0,
      "commentIndex": 0,
      "bugId": "78900",
      "date": "2004-11-17T23:00:40+01:00",
      "product": "JDT",
      "component": "Debug",
      "severity": "normal"
    }
  ],
  "groupId": "78900",
  "bugId": "78900",
  "date": "2004-11-17T23:00:40+01:00",
  "product": "JDT",
  "component": "Debug",
  "severity": "normal"
}