{
  "comments": [
    "I200411170800, GTK+ 2.4.9, IBM VM 1.4.2 \n \nI\u0027m not sure, but I believe I was replacing a file with code from head.  I then \ngot this exception in the log. \n \n \n!ENTRY org.eclipse.core.runtime 4 2 2004-11-22 11:41:18.31 \n!MESSAGE An internal error occurred during: \"Override indicator installation \njob \n\". \n!STACK 0 \njava.lang.IllegalArgumentException \n        at \norg.eclipse.jdt.core.dom.CompilationUnitResolver.parse(CompilationUni \ntResolver.java:323) \n        at \norg.eclipse.jdt.core.dom.ASTParser.internalCreateAST(ASTParser.java:7 \n37) \n        at org.eclipse.jdt.core.dom.ASTParser.createAST(ASTParser.java:574) \n        at \norg.eclipse.jdt.internal.ui.javaeditor.ASTProvider.createAST(ASTProvi \nder.java:565) \n        at \norg.eclipse.jdt.internal.ui.javaeditor.ASTProvider.getAST(ASTProvider \n.java:494) \n        at \norg.eclipse.jdt.internal.ui.javaeditor.JavaEditor$8.run(JavaEditor.ja \nva:4023) \n        at org.eclipse.core.internal.jobs.Worker.run(Worker.java:66)",
    "This is what happened if the source unit is null.\nMove to JDT/UI for investigation. Need to find out how the unit can be null.",
    "It\u0027s not the source which is null but the element that no longer exists. If\nthere\u0027s no source an IllegalStateException is correctly thrown. Reading the API\nfor createAST(...) I expect the same to happened when the element no longer exists:\n\n\t * @exception IllegalStateException if the settings provided\n\t * are insufficient, contradictory, or otherwise unsupported\n\nAnother solution would be to spec to throw a JavaModelException.isDoesNotExist()\nbut throwing an IllegalArgumentException seems not appropriate.",
    "Found a path that led to a sourceUnit equals to null.\nI added a check that throws a IllegalStateException if the sourceUnit is null\n(the element doesn\u0027t exist anymore or if a JavaModelException has be thrown\ntrying to get the source).\nCould not build a reproducable test case.\nFixed and released in HEAD.",
    "Sometimes we compute the AST in a background job. A possible test could be to\nsuspend such a job (e.g. by putting a breakpoint into ASTProvider.createsAST)\nthen delete the CU and resume the job which creates the AST.",
    "The case where the source unit could be null is attempting to create an AST on\nan IClassFile that doesn\u0027t exist. \n\nVerified (in I20041214-2000) that ASTParser#internalCreateAST(IProgressMonitor)\ncorrectly throws an IllegalStateException if the IClassFile doesn\u0027t exist."
  ],
  "commentCreationDates": [
    "2004-11-24T15:41:12+01:00",
    "2004-11-24T16:47:42+01:00",
    "2004-11-25T15:49:36+01:00",
    "2004-11-25T21:32:05+01:00",
    "2004-11-26T09:12:35+01:00",
    "2004-12-15T16:56:02+01:00"
  ],
  "traces": [
    {
      "exceptionType": "java.lang.IllegalArgumentException",
      "elements": [
        {
          "method": "org.eclipse.jdt.core.dom.CompilationUnitResolver.parse",
          "source": "CompilationUni  tResolver.java:323"
        },
        {
          "method": "org.eclipse.jdt.core.dom.ASTParser.internalCreateAST",
          "source": "ASTParser.java:7  37"
        },
        {
          "method": "org.eclipse.jdt.core.dom.ASTParser.createAST",
          "source": "ASTParser.java:574"
        },
        {
          "method": "org.eclipse.jdt.internal.ui.javaeditor.ASTProvider.createAST",
          "source": "ASTProvi  der.java:565"
        },
        {
          "method": "org.eclipse.jdt.internal.ui.javaeditor.ASTProvider.getAST",
          "source": "ASTProvider  .java:494"
        },
        {
          "method": "org.eclipse.jdt.internal.ui.javaeditor.JavaEditor$8.run",
          "source": "JavaEditor.ja  va:4023"
        },
        {
          "method": "org.eclipse.core.internal.jobs.Worker.run",
          "source": "Worker.java:66"
        }
      ],
      "number": 0,
      "commentIndex": 0,
      "bugId": "79395",
      "date": "2004-11-24T15:41:12+01:00",
      "product": "JDT",
      "component": "Core",
      "severity": "normal"
    }
  ],
  "groupId": "79395",
  "bugId": "79395",
  "date": "2004-11-24T15:41:12+01:00",
  "product": "JDT",
  "component": "Core",
  "severity": "normal"
}