{
  "comments": [
    "Hallo,\n\nI tried to set up a remote debug session with the new CDT 2.1 RC 3 update.\nThe previous launching problem (CDT debug launch did not understand a\nrelocatable executable) is resolved. However, one step further, I\nencountered a new problem. During startup of the debug session the gdb is\nlaunched (I see this process in the process list of Windows XP), but it\nseems that no connection is established between gdb and CDT. The .log file\nshows the following message:\n\n!ENTRY org.eclipse.cdt.debug.core 4 1000 Nov 24, 2004 13:12:24.511\n!MESSAGE Internal error logged from CDI Debug: \n!STACK 0\norg.eclipse.cdt.debug.core.cdi.CDIException: No registers.[]\n\tat\norg.eclipse.cdt.debug.mi.core.cdi.model.Target.getCThreads(Target.java:298)\n\tat\norg.eclipse.cdt.debug.mi.core.cdi.model.Target.getThreads(Target.java:319)\n\tat\norg.eclipse.cdt.debug.internal.core.model.CDebugTarget.refreshThreads(CDebug\nTarget.java:590)\n\tat\norg.eclipse.cdt.debug.internal.core.model.CDebugTarget.handleSuspendedEvent(\nCDebugTarget.java:1097)\n\tat\norg.eclipse.cdt.debug.internal.core.model.CDebugTarget.handleDebugEvents(CDe\nbugTarget.java:892)\n\tat\norg.eclipse.cdt.debug.mi.core.cdi.EventManager.fireEvents(EventManager.java:\n253)\n\tat\norg.eclipse.cdt.debug.mi.core.cdi.EventManager.update(EventManager.java:221)\n\tat java.util.Observable.notifyObservers(Unknown Source)\n\tat\norg.eclipse.cdt.debug.mi.core.MISession.notifyObservers(MISession.java:532)\n\tat\norg.eclipse.cdt.debug.mi.core.EventThread.run(EventThread.java:46)\n\nIn the various debug windows you can see the messages:\n\ninfo threads\nNo stack.\nDon\u0027t know how to run.  Try \"help target\".\nThe program being debugged is not being run.\n\nGDB Server (11/24/04 1:43 PM) (Suspended) \u003cDon\u0027t know how to run. Try ....\u003e\n\nI tried to look at the MI protocol between CDT and Gdb and enabled the debug\nmode in the .options file. However, due to the different startup with CDT\n2.1 I don\u0027t see any MI messages at all. As far as I can see, no\ncommunication between gdb and the (remote) gdbserver was established.\n\nmy configuration: Windows XP with cygwin, gdb 6.2.1 (but also with 5.3), \n\nRegards.\n\nManfred.",
    "Manfred, have you been able to make it work?\n\nThanks.",
    "(In reply to comment #1)\n\u003e Manfred, have you been able to make it work?\n\u003e Thanks.\n\nHallo Mikhail, \n\nAs far as I remember, this issue was resolved with a following update of\nthe CDT release. Currently we use CDT 2.1.1, which works (so far) fine.\n\nHow is the procedure to close the bug report?\n\nRegards. Manfred.\n\n",
    "Marking as fixed. \n",
    "Considering the comment from Manfred as a verification.",
    "Closing."
  ],
  "commentCreationDates": [
    "2004-11-25T12:51:36+01:00",
    "2005-05-06T19:49:21+02:00",
    "2005-05-10T17:49:45+02:00",
    "2005-05-10T17:50:44+02:00",
    "2005-05-10T17:53:12+02:00",
    "2005-05-10T17:53:24+02:00"
  ],
  "traces": [
    {
      "exceptionType": "org.eclipse.cdt.debug.core.cdi.CDIException",
      "message": "No registers.[]",
      "elements": [
        {
          "method": "org.eclipse.cdt.debug.mi.core.cdi.model.Target.getCThreads",
          "source": "Target.java:298"
        },
        {
          "method": "org.eclipse.cdt.debug.mi.core.cdi.model.Target.getThreads",
          "source": "Target.java:319"
        },
        {
          "method": "org.eclipse.cdt.debug.internal.core.model.CDebugTarget.refreshThreads",
          "source": "CDebug Target.java:590"
        },
        {
          "method": "org.eclipse.cdt.debug.internal.core.model.CDebugTarget.handleSuspendedEvent",
          "source": " CDebugTarget.java:1097"
        },
        {
          "method": "org.eclipse.cdt.debug.internal.core.model.CDebugTarget.handleDebugEvents",
          "source": "CDe bugTarget.java:892"
        },
        {
          "method": "org.eclipse.cdt.debug.mi.core.cdi.EventManager.fireEvents",
          "source": "EventManager.java: 253"
        },
        {
          "method": "org.eclipse.cdt.debug.mi.core.cdi.EventManager.update",
          "source": "EventManager.java:221"
        },
        {
          "method": "java.util.Observable.notifyObservers",
          "source": "Unknown Source"
        },
        {
          "method": "org.eclipse.cdt.debug.mi.core.MISession.notifyObservers",
          "source": "MISession.java:532"
        },
        {
          "method": "org.eclipse.cdt.debug.mi.core.EventThread.run",
          "source": "EventThread.java:46"
        }
      ],
      "number": 0,
      "commentIndex": 0,
      "bugId": "79482",
      "date": "2004-11-25T12:51:36+01:00",
      "product": "CDT",
      "component": "cdt-debug",
      "severity": "normal"
    }
  ],
  "groupId": "79482",
  "bugId": "79482",
  "date": "2004-11-25T12:51:36+01:00",
  "product": "CDT",
  "component": "cdt-debug",
  "severity": "normal"
}