{
  "comments": [
    "~\u003e which ajc\n/cygdrive/c/aspectj1.2.1/bin/ajc\n~\u003e ajc -version\nAspectJ Compiler 1.2.1 built on Friday Nov 5, 2004 at 12:30:41 GMT\n~\u003e cat AspectTest.java\naspect AspectTest {\n        pointcut calls(String str): call(*.new(String)) \u0026\u0026 args(str);\n        declare warning: calls(str) : \"not statically determinable, trying anyway\";\n}\n~\u003e ajc AspectTest.java\nC:\\Documents and Settings\\Macneil Shonle\\AspectTest.java [error] Internal\ncompiler error\norg.aspectj.weaver.BCException: illegal change to pointcut declaration:\ncalls(\u003cnothing\u003e)\n        at\norg.aspectj.weaver.patterns.ReferencePointcut.concretize1(ReferencePointcut.java:268)\n        at org.aspectj.weaver.patterns.Pointcut.concretize(Pointcut.java:167)\n        at org.aspectj.weaver.patterns.Pointcut.concretize(Pointcut.java:154)\n        at org.aspectj.weaver.Checker.concretize(Checker.java:35)\n        at\norg.aspectj.weaver.CrosscuttingMembers.addShadowMunger(CrosscuttingMembers.java:78)\n        at\norg.aspectj.weaver.CrosscuttingMembers.addDeclare(CrosscuttingMembers.java:102)\n        at\norg.aspectj.weaver.CrosscuttingMembers.addDeclares(CrosscuttingMembers.java:92)\n        at\norg.aspectj.weaver.CrosscuttingMembersSet.addAdviceLikeDeclares(CrosscuttingMembersSet.java:68)\n        at\norg.aspectj.ajdt.internal.compiler.lookup.AjLookupEnvironment.addAdviceLikeDeclares(AjLookupEnvironment.java:163)\n        at\norg.aspectj.ajdt.internal.compiler.lookup.AjLookupEnvironment.completeTypeBindings(AjLookupEnvironment.java:138)\n        at\norg.aspectj.org.eclipse.jdt.internal.compiler.Compiler.beginToCompile(Compiler.java:331)\n        at\norg.aspectj.org.eclipse.jdt.internal.compiler.Compiler.compile(Compiler.java:348)\n        at\norg.aspectj.ajdt.internal.core.builder.AjBuildManager.performCompilation(AjBuildManager.java:680)\n        at\norg.aspectj.ajdt.internal.core.builder.AjBuildManager.doBuild(AjBuildManager.java:168)\n        at\norg.aspectj.ajdt.internal.core.builder.AjBuildManager.batchBuild(AjBuildManager.java:102)\n        at org.aspectj.ajdt.ajc.AjdtCommand.doCommand(AjdtCommand.java:109)\n        at org.aspectj.ajdt.ajc.AjdtCommand.runCommand(AjdtCommand.java:60)\n        at org.aspectj.tools.ajc.Main.run(Main.java:291)\n        at org.aspectj.tools.ajc.Main.runMain(Main.java:227)\n        at org.aspectj.tools.ajc.Main.main(Main.java:80)\n\n(no source information available)\nC:\\Documents and Settings\\Macneil Shonle\\AspectTest.java:3 [error] bad parameter\nto pointcut reference\ndeclare warning: calls(str) : \"not statically determinable, trying anyway\";\n                 ^^^^^^^^\nC:\\Documents and Settings\\Macneil Shonle\\AspectTest.java:3 [warning] no match\nfor this type name: str [Xlint:invalidAbsoluteTypeName]\ndeclare warning: calls(str) : \"not statically determinable, trying anyway\";\n                       ^\nABORT\n        \nException thrown from AspectJ 1.2.1\n\nThis might be logged as a bug already -- find current bugs at\n  http://bugs.eclipse.org/bugs/buglist.cgi?product\u003dAspectJ\u0026component\u003dCompiler\n\nBugs for exceptions thrown have titles File:line from the top stack, \ne.g., \"SomeFile.java:243\"\n\nIf you don\u0027t find the exception below in a bug, please add a new bug\nat http://bugs.eclipse.org/bugs/enter_bug.cgi?product\u003dAspectJ\nTo make the bug a priority, please include a test program\nthat can reproduce this exception.\nillegal change to pointcut declaration: calls(\u003cnothing\u003e)\nillegal change to pointcut declaration: calls(\u003cnothing\u003e)\norg.aspectj.weaver.BCException: illegal change to pointcut declaration:\ncalls(\u003cnothing\u003e)\n        at\norg.aspectj.weaver.patterns.ReferencePointcut.concretize1(ReferencePointcut.java:268)\n        at org.aspectj.weaver.patterns.Pointcut.concretize(Pointcut.java:167)\n        at org.aspectj.weaver.patterns.Pointcut.concretize(Pointcut.java:154)\n        at org.aspectj.weaver.Checker.concretize(Checker.java:35)\n        at\norg.aspectj.weaver.CrosscuttingMembers.addShadowMunger(CrosscuttingMembers.java:78)\n        at\norg.aspectj.weaver.CrosscuttingMembers.addDeclare(CrosscuttingMembers.java:102)\n        at\norg.aspectj.weaver.CrosscuttingMembers.addDeclares(CrosscuttingMembers.java:92)\n        at\norg.aspectj.weaver.CrosscuttingMembersSet.addAdviceLikeDeclares(CrosscuttingMembersSet.java:68)\n        at\norg.aspectj.ajdt.internal.compiler.lookup.AjLookupEnvironment.addAdviceLikeDeclares(AjLookupEnvironment.java:163)\n        at\norg.aspectj.ajdt.internal.compiler.lookup.AjLookupEnvironment.completeTypeBindings(AjLookupEnvironment.java:138)\n        at\norg.aspectj.org.eclipse.jdt.internal.compiler.Compiler.beginToCompile(Compiler.java:331)\n        at\norg.aspectj.org.eclipse.jdt.internal.compiler.Compiler.compile(Compiler.java:348)\n        at\norg.aspectj.ajdt.internal.core.builder.AjBuildManager.performCompilation(AjBuildManager.java:680)\n        at\norg.aspectj.ajdt.internal.core.builder.AjBuildManager.doBuild(AjBuildManager.java:168)\n        at\norg.aspectj.ajdt.internal.core.builder.AjBuildManager.batchBuild(AjBuildManager.java:102)\n        at org.aspectj.ajdt.ajc.AjdtCommand.doCommand(AjdtCommand.java:109)\n        at org.aspectj.ajdt.ajc.AjdtCommand.runCommand(AjdtCommand.java:60)\n        at org.aspectj.tools.ajc.Main.run(Main.java:291)\n        at org.aspectj.tools.ajc.Main.runMain(Main.java:227)\n        at org.aspectj.tools.ajc.Main.main(Main.java:80)\n\nDumping to ajcore.20041125.132911.022.txt\n\n1 fail|abort, 2 errors, 1 warning\nSignal 127",
    "this needs to be fixed in aj5m3. The bug arises when calls(str) is used in the\ndeow (rather than calls(String) which produces the correct error message).",
    "compiler now handles this gracefully and emits the appropriate error messages."
  ],
  "commentCreationDates": [
    "2004-11-25T21:31:26+01:00",
    "2005-03-23T14:03:24+01:00",
    "2005-08-19T21:52:59+02:00"
  ],
  "traces": [
    {
      "exceptionType": "org.aspectj.weaver.BCException",
      "message": "illegal change to pointcut declaration: calls(\u003cnothing\u003e)",
      "elements": [
        {
          "method": "org.aspectj.weaver.patterns.ReferencePointcut.concretize1",
          "source": "ReferencePointcut.java:268"
        },
        {
          "method": "org.aspectj.weaver.patterns.Pointcut.concretize",
          "source": "Pointcut.java:167"
        },
        {
          "method": "org.aspectj.weaver.patterns.Pointcut.concretize",
          "source": "Pointcut.java:154"
        },
        {
          "method": "org.aspectj.weaver.Checker.concretize",
          "source": "Checker.java:35"
        },
        {
          "method": "org.aspectj.weaver.CrosscuttingMembers.addShadowMunger",
          "source": "CrosscuttingMembers.java:78"
        },
        {
          "method": "org.aspectj.weaver.CrosscuttingMembers.addDeclare",
          "source": "CrosscuttingMembers.java:102"
        },
        {
          "method": "org.aspectj.weaver.CrosscuttingMembers.addDeclares",
          "source": "CrosscuttingMembers.java:92"
        },
        {
          "method": "org.aspectj.weaver.CrosscuttingMembersSet.addAdviceLikeDeclares",
          "source": "CrosscuttingMembersSet.java:68"
        },
        {
          "method": "org.aspectj.ajdt.internal.compiler.lookup.AjLookupEnvironment.addAdviceLikeDeclares",
          "source": "AjLookupEnvironment.java:163"
        },
        {
          "method": "org.aspectj.ajdt.internal.compiler.lookup.AjLookupEnvironment.completeTypeBindings",
          "source": "AjLookupEnvironment.java:138"
        },
        {
          "method": "org.aspectj.org.eclipse.jdt.internal.compiler.Compiler.beginToCompile",
          "source": "Compiler.java:331"
        },
        {
          "method": "org.aspectj.org.eclipse.jdt.internal.compiler.Compiler.compile",
          "source": "Compiler.java:348"
        },
        {
          "method": "org.aspectj.ajdt.internal.core.builder.AjBuildManager.performCompilation",
          "source": "AjBuildManager.java:680"
        },
        {
          "method": "org.aspectj.ajdt.internal.core.builder.AjBuildManager.doBuild",
          "source": "AjBuildManager.java:168"
        },
        {
          "method": "org.aspectj.ajdt.internal.core.builder.AjBuildManager.batchBuild",
          "source": "AjBuildManager.java:102"
        },
        {
          "method": "org.aspectj.ajdt.ajc.AjdtCommand.doCommand",
          "source": "AjdtCommand.java:109"
        },
        {
          "method": "org.aspectj.ajdt.ajc.AjdtCommand.runCommand",
          "source": "AjdtCommand.java:60"
        },
        {
          "method": "org.aspectj.tools.ajc.Main.run",
          "source": "Main.java:291"
        },
        {
          "method": "org.aspectj.tools.ajc.Main.runMain",
          "source": "Main.java:227"
        },
        {
          "method": "org.aspectj.tools.ajc.Main.main",
          "source": "Main.java:80"
        }
      ],
      "number": 0,
      "commentIndex": 0,
      "bugId": "79523",
      "date": "2004-11-25T21:31:26+01:00",
      "product": "AspectJ",
      "component": "Compiler",
      "severity": "normal"
    },
    {
      "exceptionType": "org.aspectj.weaver.BCException",
      "message": "illegal change to pointcut declaration: calls(\u003cnothing\u003e)",
      "elements": [
        {
          "method": "org.aspectj.weaver.patterns.ReferencePointcut.concretize1",
          "source": "ReferencePointcut.java:268"
        },
        {
          "method": "org.aspectj.weaver.patterns.Pointcut.concretize",
          "source": "Pointcut.java:167"
        },
        {
          "method": "org.aspectj.weaver.patterns.Pointcut.concretize",
          "source": "Pointcut.java:154"
        },
        {
          "method": "org.aspectj.weaver.Checker.concretize",
          "source": "Checker.java:35"
        },
        {
          "method": "org.aspectj.weaver.CrosscuttingMembers.addShadowMunger",
          "source": "CrosscuttingMembers.java:78"
        },
        {
          "method": "org.aspectj.weaver.CrosscuttingMembers.addDeclare",
          "source": "CrosscuttingMembers.java:102"
        },
        {
          "method": "org.aspectj.weaver.CrosscuttingMembers.addDeclares",
          "source": "CrosscuttingMembers.java:92"
        },
        {
          "method": "org.aspectj.weaver.CrosscuttingMembersSet.addAdviceLikeDeclares",
          "source": "CrosscuttingMembersSet.java:68"
        },
        {
          "method": "org.aspectj.ajdt.internal.compiler.lookup.AjLookupEnvironment.addAdviceLikeDeclares",
          "source": "AjLookupEnvironment.java:163"
        },
        {
          "method": "org.aspectj.ajdt.internal.compiler.lookup.AjLookupEnvironment.completeTypeBindings",
          "source": "AjLookupEnvironment.java:138"
        },
        {
          "method": "org.aspectj.org.eclipse.jdt.internal.compiler.Compiler.beginToCompile",
          "source": "Compiler.java:331"
        },
        {
          "method": "org.aspectj.org.eclipse.jdt.internal.compiler.Compiler.compile",
          "source": "Compiler.java:348"
        },
        {
          "method": "org.aspectj.ajdt.internal.core.builder.AjBuildManager.performCompilation",
          "source": "AjBuildManager.java:680"
        },
        {
          "method": "org.aspectj.ajdt.internal.core.builder.AjBuildManager.doBuild",
          "source": "AjBuildManager.java:168"
        },
        {
          "method": "org.aspectj.ajdt.internal.core.builder.AjBuildManager.batchBuild",
          "source": "AjBuildManager.java:102"
        },
        {
          "method": "org.aspectj.ajdt.ajc.AjdtCommand.doCommand",
          "source": "AjdtCommand.java:109"
        },
        {
          "method": "org.aspectj.ajdt.ajc.AjdtCommand.runCommand",
          "source": "AjdtCommand.java:60"
        },
        {
          "method": "org.aspectj.tools.ajc.Main.run",
          "source": "Main.java:291"
        },
        {
          "method": "org.aspectj.tools.ajc.Main.runMain",
          "source": "Main.java:227"
        },
        {
          "method": "org.aspectj.tools.ajc.Main.main",
          "source": "Main.java:80"
        }
      ],
      "number": 1,
      "commentIndex": 0,
      "bugId": "79523",
      "date": "2004-11-25T21:31:26+01:00",
      "product": "AspectJ",
      "component": "Compiler",
      "severity": "normal"
    }
  ],
  "groupId": "79523",
  "bugId": "79523",
  "date": "2004-11-25T21:31:26+01:00",
  "product": "AspectJ",
  "component": "Compiler",
  "severity": "normal"
}