{
  "comments": [
    "build i2004-11-24\n\nJust noticed this in my log file...sorry no steps. At one point I had been in\nthe plug-in manifest editor and I was trying to create a new extension to an\nextension point (and open the relative schema doc). Perhaps it was during this\noperation?\n\n\nosgi\u003e !SESSION 2004-11-26 15:24:10.53\n------------------------------------------------\neclipse.buildId\u003dI200411240800\njava.fullversion\u003dJ2RE 1.4.2 IBM J9 2.2 Windows XP x86-32 j9n142-20040915 (JIT\nenabled)\nJ9VM - 20040914_1123_lHdSMR\nJIT  - r7_level20040912_1800\nBootLoader constants: OS\u003dwin32, ARCH\u003dx86, WS\u003dwin32, NL\u003den_CA\nFramework arguments:  -showlocation\nCommand-line arguments:  -os win32 -ws win32 -arch x86 -data\n\\eclipse\\target\\head\\plugins\\ -showlocation -consoleLog -console\n\n!ENTRY org.eclipse.core.runtime 4 2 2004-11-26 15:25:52.490\n!MESSAGE Problems occurred when invoking code from plug-in:\n\"org.eclipse.core.runtime\".\n!STACK 0\njava.lang.ClassCastException:\norg/eclipse/pde/internal/core/plugin/WorkspaceExtensionsModel incompatible with\norg/eclipse/pde/core/plugin/IPluginModel\nBase\n        at org.eclipse.pde.internal.ui.search.ManifestEditorOpener.open(Unknown\nSource)\n        at\norg.eclipse.pde.internal.ui.search.PluginSearchResultPage.showMatch(Unknown Source)\n        at org.eclipse.search.ui.text.AbstractTextSearchViewPage$9.run(Unknown\nSource)\n        at org.eclipse.core.internal.runtime.InternalPlatform.run(Unknown Source)\n        at org.eclipse.core.runtime.Platform.run(Unknown Source)\n        at\norg.eclipse.search.ui.text.AbstractTextSearchViewPage.showMatch(Unknown Source)\n        at\norg.eclipse.search.ui.text.AbstractTextSearchViewPage.showCurrentMatch(Unknown\nSource)\n        at\norg.eclipse.search.ui.text.AbstractTextSearchViewPage.gotoNextMatch(Unknown Source)\n        at\norg.eclipse.search.ui.text.AbstractTextSearchViewPage.handleOpen(Unknown Source)\n        at org.eclipse.search.ui.text.AbstractTextSearchViewPage$6.open(Unknown\nSource)\n        at org.eclipse.jface.viewers.StructuredViewer$2.run(Unknown Source)\n        at org.eclipse.core.internal.runtime.InternalPlatform.run(Unknown Source)\n        at org.eclipse.core.runtime.Platform.run(Unknown Source)\n        at org.eclipse.jface.viewers.StructuredViewer.fireOpen(Unknown Source)\n        at org.eclipse.jface.viewers.StructuredViewer.handleOpen(Unknown Source)\n        at org.eclipse.jface.viewers.StructuredViewer$6.handleOpen(Unknown Source)\n        at org.eclipse.jface.util.OpenStrategy.fireOpenEvent(Unknown Source)\n        at org.eclipse.jface.util.OpenStrategy.access$2(Unknown Source)\n        at org.eclipse.jface.util.OpenStrategy$1.mouseSelectItem(Unknown Source)\n        at org.eclipse.jface.util.OpenStrategy$1.handleEvent(Unknown Source)\n        at org.eclipse.swt.widgets.EventTable.sendEvent(Unknown Source)\n        at org.eclipse.swt.widgets.Widget.sendEvent(Unknown Source)\n        at org.eclipse.swt.widgets.Display.runDeferredEvents(Unknown Source)\n        at org.eclipse.swt.widgets.Display.readAndDispatch(Unknown Source)\n        at org.eclipse.ui.internal.Workbench.runEventLoop(Unknown Source)\n        at org.eclipse.ui.internal.Workbench.runUI(Unknown Source)\n        at org.eclipse.ui.internal.Workbench.createAndRunWorkbench(Unknown Source)\n        at org.eclipse.ui.PlatformUI.createAndRunWorkbench(Unknown Source)\n        at org.eclipse.ui.internal.ide.IDEApplication.run(Unknown Source)\n        at org.eclipse.core.internal.runtime.PlatformActivator$1.run(Unknown Source)\n        at\norg.eclipse.core.runtime.adaptor.EclipseStarter.run(EclipseStarter.java:273)\n        at\norg.eclipse.core.runtime.adaptor.EclipseStarter.run(EclipseStarter.java:129)\n        at sun.reflect.NativeMethodAccessorImpl.invoke0(Native Method)\n        at\nsun.reflect.NativeMethodAccessorImpl.invoke(NativeMethodAccessorImpl.java:85)\n        at\nsun.reflect.NativeMethodAccessorImpl.invoke(NativeMethodAccessorImpl.java:58)\n        at\nsun.reflect.DelegatingMethodAccessorImpl.invoke(DelegatingMethodAccessorImpl.java:60)\n        at java.lang.reflect.Method.invoke(Method.java:391)\n        at org.eclipse.core.launcher.Main.basicRun(Main.java:185)\n        at org.eclipse.core.launcher.Main.run(Main.java:684)\n        at org.eclipse.core.launcher.Main.main(Main.java:668)",
    "Pretty useless stack trace with no line numbers ;-)\nLuckily I am psychic and I think I know what happened.",
    "Good thing....I hear that after 30 your psychic abilities dwindle.... :-)",
    "\"you hear\"?  don\u0027t you mean \"you remember\"? :-)",
    "Memory is another thing that goes...",
    "Fixed.\nThe problem was occurring when you double-click on a search hit that maps to a \nworkspace plugin that has a manifest.mf/plugin.xml combo, like the \ncore.runtime plugin for example."
  ],
  "commentCreationDates": [
    "2004-11-26T21:43:31+01:00",
    "2004-11-26T21:53:28+01:00",
    "2004-11-26T21:55:14+01:00",
    "2004-11-26T22:02:18+01:00",
    "2004-11-26T22:39:29+01:00",
    "2004-11-29T23:47:39+01:00"
  ],
  "traces": [
    {
      "exceptionType": "java.lang.ClassCastException",
      "message": "org/eclipse/pde/internal/core/plugin/WorkspaceExtensionsModel incompatible with org/eclipse/pde/core/plugin/IPluginModel Base",
      "elements": [
        {
          "method": "org.eclipse.pde.internal.ui.search.ManifestEditorOpener.open",
          "source": "Unknown Source"
        },
        {
          "method": "org.eclipse.pde.internal.ui.search.PluginSearchResultPage.showMatch",
          "source": "Unknown Source"
        },
        {
          "method": "org.eclipse.search.ui.text.AbstractTextSearchViewPage$9.run",
          "source": "Unknown Source"
        },
        {
          "method": "org.eclipse.core.internal.runtime.InternalPlatform.run",
          "source": "Unknown Source"
        },
        {
          "method": "org.eclipse.core.runtime.Platform.run",
          "source": "Unknown Source"
        },
        {
          "method": "org.eclipse.search.ui.text.AbstractTextSearchViewPage.showMatch",
          "source": "Unknown Source"
        },
        {
          "method": "org.eclipse.search.ui.text.AbstractTextSearchViewPage.showCurrentMatch",
          "source": "Unknown Source"
        },
        {
          "method": "org.eclipse.search.ui.text.AbstractTextSearchViewPage.gotoNextMatch",
          "source": "Unknown Source"
        },
        {
          "method": "org.eclipse.search.ui.text.AbstractTextSearchViewPage.handleOpen",
          "source": "Unknown Source"
        },
        {
          "method": "org.eclipse.search.ui.text.AbstractTextSearchViewPage$6.open",
          "source": "Unknown Source"
        },
        {
          "method": "org.eclipse.jface.viewers.StructuredViewer$2.run",
          "source": "Unknown Source"
        },
        {
          "method": "org.eclipse.core.internal.runtime.InternalPlatform.run",
          "source": "Unknown Source"
        },
        {
          "method": "org.eclipse.core.runtime.Platform.run",
          "source": "Unknown Source"
        },
        {
          "method": "org.eclipse.jface.viewers.StructuredViewer.fireOpen",
          "source": "Unknown Source"
        },
        {
          "method": "org.eclipse.jface.viewers.StructuredViewer.handleOpen",
          "source": "Unknown Source"
        },
        {
          "method": "org.eclipse.jface.viewers.StructuredViewer$6.handleOpen",
          "source": "Unknown Source"
        },
        {
          "method": "org.eclipse.jface.util.OpenStrategy.fireOpenEvent",
          "source": "Unknown Source"
        },
        {
          "method": "org.eclipse.jface.util.OpenStrategy.access$2",
          "source": "Unknown Source"
        },
        {
          "method": "org.eclipse.jface.util.OpenStrategy$1.mouseSelectItem",
          "source": "Unknown Source"
        },
        {
          "method": "org.eclipse.jface.util.OpenStrategy$1.handleEvent",
          "source": "Unknown Source"
        },
        {
          "method": "org.eclipse.swt.widgets.EventTable.sendEvent",
          "source": "Unknown Source"
        },
        {
          "method": "org.eclipse.swt.widgets.Widget.sendEvent",
          "source": "Unknown Source"
        },
        {
          "method": "org.eclipse.swt.widgets.Display.runDeferredEvents",
          "source": "Unknown Source"
        },
        {
          "method": "org.eclipse.swt.widgets.Display.readAndDispatch",
          "source": "Unknown Source"
        },
        {
          "method": "org.eclipse.ui.internal.Workbench.runEventLoop",
          "source": "Unknown Source"
        },
        {
          "method": "org.eclipse.ui.internal.Workbench.runUI",
          "source": "Unknown Source"
        },
        {
          "method": "org.eclipse.ui.internal.Workbench.createAndRunWorkbench",
          "source": "Unknown Source"
        },
        {
          "method": "org.eclipse.ui.PlatformUI.createAndRunWorkbench",
          "source": "Unknown Source"
        },
        {
          "method": "org.eclipse.ui.internal.ide.IDEApplication.run",
          "source": "Unknown Source"
        },
        {
          "method": "org.eclipse.core.internal.runtime.PlatformActivator$1.run",
          "source": "Unknown Source"
        },
        {
          "method": "org.eclipse.core.runtime.adaptor.EclipseStarter.run",
          "source": "EclipseStarter.java:273"
        },
        {
          "method": "org.eclipse.core.runtime.adaptor.EclipseStarter.run",
          "source": "EclipseStarter.java:129"
        },
        {
          "method": "sun.reflect.NativeMethodAccessorImpl.invoke0",
          "source": "Native Method"
        },
        {
          "method": "sun.reflect.NativeMethodAccessorImpl.invoke",
          "source": "NativeMethodAccessorImpl.java:85"
        },
        {
          "method": "sun.reflect.NativeMethodAccessorImpl.invoke",
          "source": "NativeMethodAccessorImpl.java:58"
        },
        {
          "method": "sun.reflect.DelegatingMethodAccessorImpl.invoke",
          "source": "DelegatingMethodAccessorImpl.java:60"
        },
        {
          "method": "java.lang.reflect.Method.invoke",
          "source": "Method.java:391"
        },
        {
          "method": "org.eclipse.core.launcher.Main.basicRun",
          "source": "Main.java:185"
        },
        {
          "method": "org.eclipse.core.launcher.Main.run",
          "source": "Main.java:684"
        },
        {
          "method": "org.eclipse.core.launcher.Main.main",
          "source": "Main.java:668"
        }
      ],
      "number": 0,
      "commentIndex": 0,
      "bugId": "79600",
      "date": "2004-11-26T21:43:31+01:00",
      "product": "PDE",
      "component": "UI",
      "severity": "normal"
    }
  ],
  "groupId": "79600",
  "bugId": "79600",
  "date": "2004-11-26T21:43:31+01:00",
  "product": "PDE",
  "component": "UI",
  "severity": "normal"
}