{
  "comments": [
    "Over our latest long run (3 days with 20 users I believe) we saw several\ninstances of the exception listed below.  To make a long story short, it turns\nout that this is caused from the DateFormat class not being thread safe.  \n[11/27/04 10:38:58:232 EST]   b421fd SessionContex E Exception is:\njava.lang.NumberFormatException: For input string: \"\"\n        at\njava.lang.NumberFormatException.forInputString(NumberFormatException.java:48)\n        at java.lang.Long.parseLong(Long.java:415)\n        at java.lang.Long.parseLong(Long.java:452)\n        at java.text.DigitList.getLong(DigitList.java:149)\n        at java.text.DecimalFormat.parse(DecimalFormat.java:1068)\n        at java.text.SimpleDateFormat.subParse(SimpleDateFormat.java:1705)\n        at java.text.SimpleDateFormat.parse(SimpleDateFormat.java:1156)\n        at java.text.DateFormat.parse(DateFormat.java:333)\n        at\norg.eclipse.emf.ecore.impl.EcoreFactoryImpl.createEDateFromString(EcoreFactoryImpl.java:426)\n        at\norg.eclipse.emf.ecore.impl.EcoreFactoryImpl.createFromString(EcoreFactoryImpl.java:108)\n        at\norg.eclipse.emf.ecore.xmi.impl.XMLHelperImpl.createFromString(XMLHelperImpl.java:1090)\n        at\norg.eclipse.emf.ecore.xmi.impl.XMLHelperImpl.setValue(XMLHelperImpl.java:768)\n        at\norg.eclipse.emf.ecore.xmi.impl.XMLHandler.setFeatureValue(XMLHandler.java:1729)\n        at\norg.eclipse.emf.ecore.xmi.impl.XMLHandler.setAttribValue(XMLHandler.java:1788)\n        at\norg.eclipse.emf.ecore.xmi.impl.SAXXMLHandler.handleObjectAttribs(SAXXMLHandler.java:145)\n        at\norg.eclipse.emf.ecore.xmi.impl.XMLHandler.createObjectFromFactory(XMLHandler.java:1346)\n        at\norg.eclipse.emf.ecore.sdo.util.DataGraphResourceFactoryImpl$1.createObjectFromFactory(DataGraphResourceFactoryImpl.java:451)\n        at\norg.eclipse.emf.ecore.xmi.impl.XMLHandler.createObjectFromFeatureType(XMLHandler.java:1318)\n        at\norg.eclipse.emf.ecore.xmi.impl.XMLHandler.createObject(XMLHandler.java:1213)\n        at\norg.eclipse.emf.ecore.xmi.impl.XMLHandler.handleFeature(XMLHandler.java:1022)\n        at\norg.eclipse.emf.ecore.sdo.util.DataGraphResourceFactoryImpl$1.handleFeature(DataGraphResourceFactoryImpl.java:393)\n        at\norg.eclipse.emf.ecore.xmi.impl.XMLHandler.processElement(XMLHandler.java:448)\n        at\norg.eclipse.emf.ecore.xmi.impl.XMLHandler.startElement(XMLHandler.java:431)\n        at\norg.eclipse.emf.ecore.xmi.impl.SAXWrapper.startElement(SAXWrapper.java:75)\n        at org.apache.xerces.parsers.AbstractSAXParser.startElement(Unknown Source)\n        at\norg.apache.xerces.parsers.AbstractXMLDocumentParser.emptyElement(Unknown Source)\n        at\norg.apache.xerces.impl.XMLDocumentFragmentScannerImpl.scanStartElement(Unknown\nSource)\n        at\norg.apache.xerces.impl.XMLDocumentFragmentScannerImpl$FragmentContentDispatcher.dispatch(Unknown\nSource)\n        at\norg.apache.xerces.impl.XMLDocumentFragmentScannerImpl.scanDocument(Unknown Source)\n        at org.apache.xerces.parsers.XML11Configuration.parse(Unknown Source)\n        at org.apache.xerces.parsers.XML11Configuration.parse(Unknown Source)\n        at org.apache.xerces.parsers.XMLParser.parse(Unknown Source)\n        at org.apache.xerces.parsers.AbstractSAXParser.parse(Unknown Source)\n        at javax.xml.parsers.SAXParser.parse(Unknown Source)\n        at org.eclipse.emf.ecore.xmi.impl.XMLLoadImpl.load(XMLLoadImpl.java:129)\n        at\norg.eclipse.emf.ecore.xmi.impl.XMLResourceImpl.doLoad(XMLResourceImpl.java:155)\n        at\norg.eclipse.emf.ecore.resource.impl.ResourceImpl.load(ResourceImpl.java:888)\n        at\norg.eclipse.emf.ecore.sdo.impl.EDataGraphImpl$EDataGraphExternalizable.readExternal(EDataGraphImpl.java:560)\n        at java.io.ObjectInputStream.readExternalData(ObjectInputStream.java:1686)\n        at java.io.ObjectInputStream.readOrdinaryObject(ObjectInputStream.java:1644)\n        at java.io.ObjectInputStream.readObject0(ObjectInputStream.java:1274)\n        at java.io.ObjectInputStream.readObject(ObjectInputStream.java:324)\n        at\norg.eclipse.emf.ecore.sdo.impl.EDataGraphImpl$EDataObjectExternalizable.readExternal(EDataGraphImpl.java:612)\n        at java.io.ObjectInputStream.readExternalData(ObjectInputStream.java:1686)\n        at java.io.ObjectInputStream.readOrdinaryObject(ObjectInputStream.java:1644)\n        at java.io.ObjectInputStream.readObject0(ObjectInputStream.java:1274)\n        at java.io.ObjectInputStream.defaultReadFields(ObjectInputStream.java:1845)\n        at java.io.ObjectInputStream.readSerialData(ObjectInputStream.java:1769)\n        at java.io.ObjectInputStream.readOrdinaryObject(ObjectInputStream.java:1646)\n        at java.io.ObjectInputStream.readObject0(ObjectInputStream.java:1274)\n        at java.io.ObjectInputStream.readObject(ObjectInputStream.java:324)\n        at java.util.HashMap.readObject(HashMap.java:1006)\n        at sun.reflect.GeneratedMethodAccessor15.invoke(Unknown Source)\n        at\nsun.reflect.DelegatingMethodAccessorImpl.invoke(DelegatingMethodAccessorImpl.java:25)\n        at java.lang.reflect.Method.invoke(Method.java:324)\n        at java.io.ObjectStreamClass.invokeReadObject(ObjectStreamClass.java:838)\n        at java.io.ObjectInputStream.readSerialData(ObjectInputStream.java:1746)",
    "The SimpleDataFormat instances in EFactoryImpl.EDATA_FORMATS aren\u0027t thread safe,\nso a fix has been applied to make those instances thread safe.",
    "Fixed in Build 2.1.0.I200412091159."
  ],
  "commentCreationDates": [
    "2004-12-01T20:00:44+01:00",
    "2004-12-03T12:07:44+01:00",
    "2004-12-09T18:20:47+01:00"
  ],
  "traces": [
    {
      "exceptionType": "java.lang.NumberFormatException",
      "message": "For input string: \"\"",
      "elements": [
        {
          "method": "java.lang.NumberFormatException.forInputString",
          "source": "NumberFormatException.java:48"
        },
        {
          "method": "java.lang.Long.parseLong",
          "source": "Long.java:415"
        },
        {
          "method": "java.lang.Long.parseLong",
          "source": "Long.java:452"
        },
        {
          "method": "java.text.DigitList.getLong",
          "source": "DigitList.java:149"
        },
        {
          "method": "java.text.DecimalFormat.parse",
          "source": "DecimalFormat.java:1068"
        },
        {
          "method": "java.text.SimpleDateFormat.subParse",
          "source": "SimpleDateFormat.java:1705"
        },
        {
          "method": "java.text.SimpleDateFormat.parse",
          "source": "SimpleDateFormat.java:1156"
        },
        {
          "method": "java.text.DateFormat.parse",
          "source": "DateFormat.java:333"
        },
        {
          "method": "org.eclipse.emf.ecore.impl.EcoreFactoryImpl.createEDateFromString",
          "source": "EcoreFactoryImpl.java:426"
        },
        {
          "method": "org.eclipse.emf.ecore.impl.EcoreFactoryImpl.createFromString",
          "source": "EcoreFactoryImpl.java:108"
        },
        {
          "method": "org.eclipse.emf.ecore.xmi.impl.XMLHelperImpl.createFromString",
          "source": "XMLHelperImpl.java:1090"
        },
        {
          "method": "org.eclipse.emf.ecore.xmi.impl.XMLHelperImpl.setValue",
          "source": "XMLHelperImpl.java:768"
        },
        {
          "method": "org.eclipse.emf.ecore.xmi.impl.XMLHandler.setFeatureValue",
          "source": "XMLHandler.java:1729"
        },
        {
          "method": "org.eclipse.emf.ecore.xmi.impl.XMLHandler.setAttribValue",
          "source": "XMLHandler.java:1788"
        },
        {
          "method": "org.eclipse.emf.ecore.xmi.impl.SAXXMLHandler.handleObjectAttribs",
          "source": "SAXXMLHandler.java:145"
        },
        {
          "method": "org.eclipse.emf.ecore.xmi.impl.XMLHandler.createObjectFromFactory",
          "source": "XMLHandler.java:1346"
        },
        {
          "method": "org.eclipse.emf.ecore.sdo.util.DataGraphResourceFactoryImpl$1.createObjectFromFactory",
          "source": "DataGraphResourceFactoryImpl.java:451"
        },
        {
          "method": "org.eclipse.emf.ecore.xmi.impl.XMLHandler.createObjectFromFeatureType",
          "source": "XMLHandler.java:1318"
        },
        {
          "method": "org.eclipse.emf.ecore.xmi.impl.XMLHandler.createObject",
          "source": "XMLHandler.java:1213"
        },
        {
          "method": "org.eclipse.emf.ecore.xmi.impl.XMLHandler.handleFeature",
          "source": "XMLHandler.java:1022"
        },
        {
          "method": "org.eclipse.emf.ecore.sdo.util.DataGraphResourceFactoryImpl$1.handleFeature",
          "source": "DataGraphResourceFactoryImpl.java:393"
        },
        {
          "method": "org.eclipse.emf.ecore.xmi.impl.XMLHandler.processElement",
          "source": "XMLHandler.java:448"
        },
        {
          "method": "org.eclipse.emf.ecore.xmi.impl.XMLHandler.startElement",
          "source": "XMLHandler.java:431"
        },
        {
          "method": "org.eclipse.emf.ecore.xmi.impl.SAXWrapper.startElement",
          "source": "SAXWrapper.java:75"
        },
        {
          "method": "org.apache.xerces.parsers.AbstractSAXParser.startElement",
          "source": "Unknown Source"
        },
        {
          "method": "org.apache.xerces.parsers.AbstractXMLDocumentParser.emptyElement",
          "source": "Unknown Source"
        },
        {
          "method": "org.apache.xerces.impl.XMLDocumentFragmentScannerImpl.scanStartElement",
          "source": "Unknown Source"
        },
        {
          "method": "org.apache.xerces.impl.XMLDocumentFragmentScannerImpl$FragmentContentDispatcher.dispatch",
          "source": "Unknown Source"
        },
        {
          "method": "org.apache.xerces.impl.XMLDocumentFragmentScannerImpl.scanDocument",
          "source": "Unknown Source"
        },
        {
          "method": "org.apache.xerces.parsers.XML11Configuration.parse",
          "source": "Unknown Source"
        },
        {
          "method": "org.apache.xerces.parsers.XML11Configuration.parse",
          "source": "Unknown Source"
        },
        {
          "method": "org.apache.xerces.parsers.XMLParser.parse",
          "source": "Unknown Source"
        },
        {
          "method": "org.apache.xerces.parsers.AbstractSAXParser.parse",
          "source": "Unknown Source"
        },
        {
          "method": "javax.xml.parsers.SAXParser.parse",
          "source": "Unknown Source"
        },
        {
          "method": "org.eclipse.emf.ecore.xmi.impl.XMLLoadImpl.load",
          "source": "XMLLoadImpl.java:129"
        },
        {
          "method": "org.eclipse.emf.ecore.xmi.impl.XMLResourceImpl.doLoad",
          "source": "XMLResourceImpl.java:155"
        },
        {
          "method": "org.eclipse.emf.ecore.resource.impl.ResourceImpl.load",
          "source": "ResourceImpl.java:888"
        },
        {
          "method": "org.eclipse.emf.ecore.sdo.impl.EDataGraphImpl$EDataGraphExternalizable.readExternal",
          "source": "EDataGraphImpl.java:560"
        },
        {
          "method": "java.io.ObjectInputStream.readExternalData",
          "source": "ObjectInputStream.java:1686"
        },
        {
          "method": "java.io.ObjectInputStream.readOrdinaryObject",
          "source": "ObjectInputStream.java:1644"
        },
        {
          "method": "java.io.ObjectInputStream.readObject0",
          "source": "ObjectInputStream.java:1274"
        },
        {
          "method": "java.io.ObjectInputStream.readObject",
          "source": "ObjectInputStream.java:324"
        },
        {
          "method": "org.eclipse.emf.ecore.sdo.impl.EDataGraphImpl$EDataObjectExternalizable.readExternal",
          "source": "EDataGraphImpl.java:612"
        },
        {
          "method": "java.io.ObjectInputStream.readExternalData",
          "source": "ObjectInputStream.java:1686"
        },
        {
          "method": "java.io.ObjectInputStream.readOrdinaryObject",
          "source": "ObjectInputStream.java:1644"
        },
        {
          "method": "java.io.ObjectInputStream.readObject0",
          "source": "ObjectInputStream.java:1274"
        },
        {
          "method": "java.io.ObjectInputStream.defaultReadFields",
          "source": "ObjectInputStream.java:1845"
        },
        {
          "method": "java.io.ObjectInputStream.readSerialData",
          "source": "ObjectInputStream.java:1769"
        },
        {
          "method": "java.io.ObjectInputStream.readOrdinaryObject",
          "source": "ObjectInputStream.java:1646"
        },
        {
          "method": "java.io.ObjectInputStream.readObject0",
          "source": "ObjectInputStream.java:1274"
        },
        {
          "method": "java.io.ObjectInputStream.readObject",
          "source": "ObjectInputStream.java:324"
        },
        {
          "method": "java.util.HashMap.readObject",
          "source": "HashMap.java:1006"
        },
        {
          "method": "sun.reflect.GeneratedMethodAccessor15.invoke",
          "source": "Unknown Source"
        },
        {
          "method": "sun.reflect.DelegatingMethodAccessorImpl.invoke",
          "source": "DelegatingMethodAccessorImpl.java:25"
        },
        {
          "method": "java.lang.reflect.Method.invoke",
          "source": "Method.java:324"
        },
        {
          "method": "java.io.ObjectStreamClass.invokeReadObject",
          "source": "ObjectStreamClass.java:838"
        },
        {
          "method": "java.io.ObjectInputStream.readSerialData",
          "source": "ObjectInputStream.java:1746"
        }
      ],
      "number": 0,
      "commentIndex": 0,
      "bugId": "79922",
      "date": "2004-12-01T20:00:44+01:00",
      "product": "EMF",
      "component": "Core",
      "severity": "normal"
    }
  ],
  "groupId": "79922",
  "bugId": "79922",
  "date": "2004-12-01T20:00:44+01:00",
  "product": "EMF",
  "component": "Core",
  "severity": "normal"
}