{
  "comments": [
    "Searching for other types, including java.lang exceptions work. Marking \nRuntimeException in code however fails. This is what appears in the log: \n \nENTRY org.eclipse.core.runtime 4 2 2004-12-02 10:53:05.620 \n!MESSAGE An internal error occurred during: \"Java Search\". \n!STACK 0 \njava.lang.StringIndexOutOfBoundsException: String index out of range: -1 \n        at java.lang.String.substring(String.java:1768) \n        at \norg.eclipse.jdt.internal.core.search.matching.PossibleMatch.getQualifiedName(PossibleMatch.java:109) \n        at \norg.eclipse.jdt.internal.core.search.matching.PossibleMatch.\u003cinit\u003e(PossibleMatch.java:41) \n        at \norg.eclipse.jdt.internal.core.search.matching.MatchLocator.locateMatches(MatchLocator.java:924) \n        at \norg.eclipse.jdt.internal.core.search.JavaSearchParticipant.locateMatches(JavaSearchParticipant.java:94) \n        at \norg.eclipse.jdt.internal.core.search.SearchBasicEngine.findMatches(SearchBasicEngine.java:196) \n        at \norg.eclipse.jdt.internal.core.search.SearchBasicEngine.search(SearchBasicEngine.java:382) \n        at \norg.eclipse.jdt.core.search.SearchEngine.search(SearchEngine.java:512) \n        at \norg.eclipse.jdt.internal.ui.search.JavaSearchQuery.run(JavaSearchQuery.java:125) \n        at \norg.eclipse.search2.internal.ui.InternalSearchUI$InternalSearchJob.run(InternalSearchUI.java:85) \n        at org.eclipse.core.internal.jobs.Worker.run(Worker.java:66) \n \nI\u0027m using 3.1M3",
    "\n\n*** This bug has been marked as a duplicate of 73784 ***"
  ],
  "commentCreationDates": [
    "2004-12-02T10:08:58+01:00",
    "2004-12-02T11:46:05+01:00"
  ],
  "traces": [
    {
      "exceptionType": "java.lang.StringIndexOutOfBoundsException",
      "message": "String index out of range: -1",
      "elements": [
        {
          "method": "java.lang.String.substring",
          "source": "String.java:1768"
        },
        {
          "method": "org.eclipse.jdt.internal.core.search.matching.PossibleMatch.getQualifiedName",
          "source": "PossibleMatch.java:109"
        },
        {
          "method": "org.eclipse.jdt.internal.core.search.matching.PossibleMatch.\u003cinit\u003e",
          "source": "PossibleMatch.java:41"
        },
        {
          "method": "org.eclipse.jdt.internal.core.search.matching.MatchLocator.locateMatches",
          "source": "MatchLocator.java:924"
        },
        {
          "method": "org.eclipse.jdt.internal.core.search.JavaSearchParticipant.locateMatches",
          "source": "JavaSearchParticipant.java:94"
        },
        {
          "method": "org.eclipse.jdt.internal.core.search.SearchBasicEngine.findMatches",
          "source": "SearchBasicEngine.java:196"
        },
        {
          "method": "org.eclipse.jdt.internal.core.search.SearchBasicEngine.search",
          "source": "SearchBasicEngine.java:382"
        },
        {
          "method": "org.eclipse.jdt.core.search.SearchEngine.search",
          "source": "SearchEngine.java:512"
        },
        {
          "method": "org.eclipse.jdt.internal.ui.search.JavaSearchQuery.run",
          "source": "JavaSearchQuery.java:125"
        },
        {
          "method": "org.eclipse.search2.internal.ui.InternalSearchUI$InternalSearchJob.run",
          "source": "InternalSearchUI.java:85"
        },
        {
          "method": "org.eclipse.core.internal.jobs.Worker.run",
          "source": "Worker.java:66"
        }
      ],
      "number": 0,
      "commentIndex": 0,
      "bugId": "79975",
      "duplicateId": "73784",
      "date": "2004-12-02T10:08:58+01:00",
      "product": "JDT",
      "component": "Core",
      "severity": "normal"
    }
  ],
  "groupId": "73784",
  "bugId": "79975",
  "duplicateId": "73784",
  "date": "2004-12-02T10:08:58+01:00",
  "product": "JDT",
  "component": "Core",
  "severity": "normal"
}