{
  "comments": [
    "Found the following in the console:\n\njava.lang.NullPointerException\n        at\norg.eclipse.jdt.internal.compiler.lookup.MethodBinding.signature(MethodBinding.java:630)\n        at\norg.eclipse.jdt.internal.compiler.lookup.MethodBinding.computeUniqueKey(MethodBinding.java:290)\n        at\norg.eclipse.jdt.internal.compiler.lookup.MethodBinding.computeUniqueKey(MethodBinding.java:278)\n        at org.eclipse.jdt.core.dom.MethodBinding.getKey(MethodBinding.java:286)\n        at\norg.eclipse.jdt.core.dom.DefaultBindingResolver.resolveMethod(DefaultBindingResolver.java:628)\n        at\norg.eclipse.jdt.core.dom.MethodDeclaration.resolveBinding(MethodDeclaration.java:875)\n        at org.eclipse.jdt.core.dom.ASTConverter.convert(ASTConverter.java:624)\n        at\norg.eclipse.jdt.core.dom.ASTConverter.buildBodyDeclarations(ASTConverter.java:175)\n        at org.eclipse.jdt.core.dom.ASTConverter.convert(ASTConverter.java:2478)\n        at\norg.eclipse.jdt.core.dom.ASTConverter.buildBodyDeclarations(ASTConverter.java:180)\n        at org.eclipse.jdt.core.dom.ASTConverter.convert(ASTConverter.java:2478)\n        at org.eclipse.jdt.core.dom.ASTConverter.convert(ASTConverter.java:1226)\n        at org.eclipse.jdt.core.dom.AST.convertCompilationUnit(AST.java:259)\n        at\norg.eclipse.jdt.internal.core.ReconcileWorkingCopyOperation.executeOperation(ReconcileWorkingCopyOperation.java:83)\n        at\norg.eclipse.jdt.internal.core.JavaModelOperation.run(JavaModelOperation.java:700)\n        at\norg.eclipse.jdt.internal.core.JavaModelOperation.runOperation(JavaModelOperation.java:739)\n        at\norg.eclipse.jdt.internal.core.CompilationUnit.reconcile(CompilationUnit.java:1105)\n        at\norg.eclipse.jdt.internal.ui.text.java.JavaReconcilingStrategy.reconcile(JavaReconcilingStrategy.java:91)\n        at\norg.eclipse.jdt.internal.ui.text.java.JavaReconcilingStrategy.reconcile(JavaReconcilingStrategy.java:133)\n        at\norg.eclipse.jdt.internal.ui.text.CompositeReconcilingStrategy.reconcile(CompositeReconcilingStrategy.java:86)\n        at\norg.eclipse.jdt.internal.ui.text.JavaCompositeReconcilingStrategy.reconcile(JavaCompositeReconcilingStrategy.java:96)\n        at\norg.eclipse.jface.text.reconciler.MonoReconciler.process(MonoReconciler.java:75)\n        at\norg.eclipse.jdt.internal.ui.text.JavaReconciler.process(JavaReconciler.java:318)\n        at\norg.eclipse.jface.text.reconciler.AbstractReconciler$BackgroundThread.run(AbstractReconciler.java:204)\n\nFile open in editor was PackageExplorerPerfTest from HEAD.",
    "Seems like a method with no return type... ",
    "Could not reproduce. Added null check in MethodBinding#signature() and\ngenericSignature()",
    "Verified added code for 3.1 M4 using build I200412142000.\n"
  ],
  "commentCreationDates": [
    "2004-12-02T18:42:35+01:00",
    "2004-12-03T00:28:01+01:00",
    "2004-12-08T15:17:28+01:00",
    "2004-12-15T12:33:16+01:00"
  ],
  "traces": [
    {
      "exceptionType": "java.lang.NullPointerException",
      "elements": [
        {
          "method": "org.eclipse.jdt.internal.compiler.lookup.MethodBinding.signature",
          "source": "MethodBinding.java:630"
        },
        {
          "method": "org.eclipse.jdt.internal.compiler.lookup.MethodBinding.computeUniqueKey",
          "source": "MethodBinding.java:290"
        },
        {
          "method": "org.eclipse.jdt.internal.compiler.lookup.MethodBinding.computeUniqueKey",
          "source": "MethodBinding.java:278"
        },
        {
          "method": "org.eclipse.jdt.core.dom.MethodBinding.getKey",
          "source": "MethodBinding.java:286"
        },
        {
          "method": "org.eclipse.jdt.core.dom.DefaultBindingResolver.resolveMethod",
          "source": "DefaultBindingResolver.java:628"
        },
        {
          "method": "org.eclipse.jdt.core.dom.MethodDeclaration.resolveBinding",
          "source": "MethodDeclaration.java:875"
        },
        {
          "method": "org.eclipse.jdt.core.dom.ASTConverter.convert",
          "source": "ASTConverter.java:624"
        },
        {
          "method": "org.eclipse.jdt.core.dom.ASTConverter.buildBodyDeclarations",
          "source": "ASTConverter.java:175"
        },
        {
          "method": "org.eclipse.jdt.core.dom.ASTConverter.convert",
          "source": "ASTConverter.java:2478"
        },
        {
          "method": "org.eclipse.jdt.core.dom.ASTConverter.buildBodyDeclarations",
          "source": "ASTConverter.java:180"
        },
        {
          "method": "org.eclipse.jdt.core.dom.ASTConverter.convert",
          "source": "ASTConverter.java:2478"
        },
        {
          "method": "org.eclipse.jdt.core.dom.ASTConverter.convert",
          "source": "ASTConverter.java:1226"
        },
        {
          "method": "org.eclipse.jdt.core.dom.AST.convertCompilationUnit",
          "source": "AST.java:259"
        },
        {
          "method": "org.eclipse.jdt.internal.core.ReconcileWorkingCopyOperation.executeOperation",
          "source": "ReconcileWorkingCopyOperation.java:83"
        },
        {
          "method": "org.eclipse.jdt.internal.core.JavaModelOperation.run",
          "source": "JavaModelOperation.java:700"
        },
        {
          "method": "org.eclipse.jdt.internal.core.JavaModelOperation.runOperation",
          "source": "JavaModelOperation.java:739"
        },
        {
          "method": "org.eclipse.jdt.internal.core.CompilationUnit.reconcile",
          "source": "CompilationUnit.java:1105"
        },
        {
          "method": "org.eclipse.jdt.internal.ui.text.java.JavaReconcilingStrategy.reconcile",
          "source": "JavaReconcilingStrategy.java:91"
        },
        {
          "method": "org.eclipse.jdt.internal.ui.text.java.JavaReconcilingStrategy.reconcile",
          "source": "JavaReconcilingStrategy.java:133"
        },
        {
          "method": "org.eclipse.jdt.internal.ui.text.CompositeReconcilingStrategy.reconcile",
          "source": "CompositeReconcilingStrategy.java:86"
        },
        {
          "method": "org.eclipse.jdt.internal.ui.text.JavaCompositeReconcilingStrategy.reconcile",
          "source": "JavaCompositeReconcilingStrategy.java:96"
        },
        {
          "method": "org.eclipse.jface.text.reconciler.MonoReconciler.process",
          "source": "MonoReconciler.java:75"
        },
        {
          "method": "org.eclipse.jdt.internal.ui.text.JavaReconciler.process",
          "source": "JavaReconciler.java:318"
        },
        {
          "method": "org.eclipse.jface.text.reconciler.AbstractReconciler$BackgroundThread.run",
          "source": "AbstractReconciler.java:204"
        }
      ],
      "number": 0,
      "commentIndex": 0,
      "bugId": "80045",
      "date": "2004-12-02T18:42:35+01:00",
      "product": "JDT",
      "component": "Core",
      "severity": "normal"
    }
  ],
  "groupId": "80045",
  "bugId": "80045",
  "date": "2004-12-02T18:42:35+01:00",
  "product": "JDT",
  "component": "Core",
  "severity": "normal"
}