{
  "comments": [
    "reported by Christof Marti:\n\nrunning performance tests on 3.0 resulted in the following NPE.\nIt seems that AllTypesCache.getAllTypes can return null and that AllTypesCache.getTypes() doesn\u0027t \ncheck for this.\n\n\njava.lang.NullPointerException\nat org.eclipse.jdt.internal.corext.util.AllTypesCache.getTypes(AllTypesCache.java:246)\nat \norg.eclipse.jdt.text.tests.performance.EditorTestHelper.joinBackgroundActivities(EditorTestHelper.java:\n243)\nat org.eclipse.jdt.text.tests.performance.PerformanceTestSetup.setUp(PerformanceTestSetup.java:76)\nat junit.extensions.TestSetup$1.protect(TestSetup.java:18)\nat junit.extensions.TestSetup.run(TestSetup.java:23)\nat junit.extensions.TestDecorator.basicRun(TestDecorator.java:22)\nat junit.extensions.TestDecorator.run(TestDecorator.java:28)\nat org.eclipse.jdt.text.tests.performance.CloseWorkbenchDecorator.run(CloseWorkbenchDecorator.java:\n31)\nat org.eclipse.test.EclipseTestRunner.run(EclipseTestRunner.java:320)\nat org.eclipse.test.EclipseTestRunner.run(EclipseTestRunner.java:196)\nat org.eclipse.test.UITestApplication$3.run(UITestApplication.java:188)\nat org.eclipse.swt.widgets.RunnableLock.run(RunnableLock.java:35)\nat org.eclipse.swt.widgets.Synchronizer.runAsyncMessages(Synchronizer.java:106)\nat org.eclipse.swt.widgets.Display.runAsyncMessages(Display.java:2749)\nat org.eclipse.swt.widgets.Display.readAndDispatch(Display.java:2434)\nat org.eclipse.ui.internal.Workbench.runEventLoop(Workbench.java:1377)\nat org.eclipse.ui.internal.Workbench.runUI(Workbench.java:1348)\nat org.eclipse.ui.internal.Workbench.createAndRunWorkbench(Workbench.java:254)\nat org.eclipse.ui.PlatformUI.createAndRunWorkbench(PlatformUI.java:141)\nat org.eclipse.ui.internal.ide.IDEApplication.run(IDEApplication.java:96)\nat org.eclipse.test.UITestApplication.runApplication(UITestApplication.java:131)\nat org.eclipse.test.UITestApplication.run(UITestApplication.java:58)\nat org.eclipse.core.internal.runtime.PlatformActivator$1.run(PlatformActivator.java:335)\nat org.eclipse.core.runtime.adaptor.EclipseStarter.run(EclipseStarter.java:273)\nat org.eclipse.core.runtime.adaptor.EclipseStarter.run(EclipseStarter.java:129)\nat sun.reflect.NativeMethodAccessorImpl.invoke0(Native Method)\nat sun.reflect.NativeMethodAccessorImpl.invoke(NativeMethodAccessorImpl.java:39)\nat sun.reflect.DelegatingMethodAccessorImpl.invoke(DelegatingMethodAccessorImpl.java:25)\nat org.eclipse.core.launcher.Main.basicRun(Main.java:183)\nat org.eclipse.core.launcher.Main.run(Main.java:644)\nat org.eclipse.core.launcher.Main.main(Main.java:628)",
    "The only reason for AllTypesCache.getAllTypes() to return null is a JavaModelException in \nSearchEngine().searchAllTypeNames(). However, if this happens an entry should be written to the log.\n",
    "Created an attachment (id\u003d16450)\nPatch for AllTypesCache\n",
    "Attempting to complete the picture, the exception below was found in the log.\nThe \"SWTException: Device is disposed\" exception could come from the fact that\nthere is a \"Workbench.close()\" call in the JDT/Text tests at the end of the\ntest-suite, which is a workaround for bug 71362.\n\n     [java] java.lang.InterruptedException\n     [java] \tat java.lang.Object.wait(Native Method)\n     [java] \tat\norg.eclipse.jdt.internal.corext.util.AllTypesCache.getAllTypes(AllTypesCache.java:303)\n     [java] \tat\norg.eclipse.jdt.internal.corext.util.AllTypesCache.getTypes(AllTypesCache.java:240)\n     [java] \tat\norg.eclipse.jdt.text.tests.performance.EditorTestHelper.joinBackgroundActivities(EditorTestHelper.java:243)\n     [java] \tat\norg.eclipse.jdt.text.tests.performance.PerformanceTestSetup.setUp(PerformanceTestSetup.java:76)\n     [java] \tat junit.extensions.TestSetup$1.protect(TestSetup.java:18)\n     [java] \tat junit.framework.TestResult.runProtected(TestResult.java:124)\n     [java] \tat junit.extensions.TestSetup.run(TestSetup.java:23)\n     [java] \tat junit.extensions.TestDecorator.basicRun(TestDecorator.java:22)\n     [java] \tat junit.extensions.TestDecorator.run(TestDecorator.java:28)\n     [java] \tat\norg.eclipse.jdt.text.tests.performance.CloseWorkbenchDecorator.run(CloseWorkbenchDecorator.java:31)\n     [java] \tat org.eclipse.test.EclipseTestRunner.run(EclipseTestRunner.java:320)\n     [java] \tat org.eclipse.test.EclipseTestRunner.run(EclipseTestRunner.java:196)\n     [java] \tat org.eclipse.test.UITestApplication$3.run(UITestApplication.java:188)\n     [java] \tat org.eclipse.swt.widgets.RunnableLock.run(RunnableLock.java:35)\n     [java] \tat\norg.eclipse.swt.widgets.Synchronizer.runAsyncMessages(Synchronizer.java:106)\n     [java] \tat org.eclipse.swt.widgets.Display.runAsyncMessages(Display.java:2749)\n     [java] \tat org.eclipse.swt.widgets.Display.readAndDispatch(Display.java:2434)\n     [java] \tat org.eclipse.ui.internal.Workbench.runEventLoop(Workbench.java:1377)\n     [java] \tat org.eclipse.ui.internal.Workbench.runUI(Workbench.java:1348)\n     [java] \tat\norg.eclipse.ui.internal.Workbench.createAndRunWorkbench(Workbench.java:254)\n     [java] \tat org.eclipse.ui.PlatformUI.createAndRunWorkbench(PlatformUI.java:141)\n     [java] \tat\norg.eclipse.ui.internal.ide.IDEApplication.run(IDEApplication.java:96)\n     [java] \tat\norg.eclipse.test.UITestApplication.runApplication(UITestApplication.java:131)\n     [java] \tat org.eclipse.test.UITestApplication.run(UITestApplication.java:58)\n     [java] \tat\norg.eclipse.core.internal.runtime.PlatformActivator$1.run(PlatformActivator.java:335)\n     [java] \tat\norg.eclipse.core.runtime.adaptor.EclipseStarter.run(EclipseStarter.java:273)\n     [java] \tat\norg.eclipse.core.runtime.adaptor.EclipseStarter.run(EclipseStarter.java:129)\n     [java] \tat sun.reflect.NativeMethodAccessorImpl.invoke0(Native Method)\n     [java] \tat\nsun.reflect.NativeMethodAccessorImpl.invoke(NativeMethodAccessorImpl.java:39)\n     [java] \tat\nsun.reflect.DelegatingMethodAccessorImpl.invoke(DelegatingMethodAccessorImpl.java:25)\n     [java] \tat java.lang.reflect.Method.invoke(Method.java:324)\n     [java] \tat org.eclipse.core.launcher.Main.basicRun(Main.java:183)\n     [java] \tat org.eclipse.core.launcher.Main.run(Main.java:644)\n     [java] \tat org.eclipse.core.launcher.Main.main(Main.java:628)\n     [java] org.eclipse.swt.SWTException: Device is disposed\n     [java] \tat org.eclipse.swt.SWT.error(SWT.java:2691)\n     [java] \tat org.eclipse.swt.SWT.error(SWT.java:2616)\n     [java] \tat org.eclipse.swt.SWT.error(SWT.java:2587)\n     [java] \tat org.eclipse.swt.widgets.Display.error(Display.java:736)\n     [java] \tat org.eclipse.swt.widgets.Display.syncExec(Display.java:3095)\n     [java] \tat\norg.eclipse.ui.internal.testing.WorkbenchTestable.testingFinished(WorkbenchTestable.java:93)\n     [java] \tat\norg.eclipse.test.UITestApplication.runTests(UITestApplication.java:194)\n     [java] \tat\norg.eclipse.ui.internal.testing.WorkbenchTestable$1.run(WorkbenchTestable.java:56)\n     [java] \tat java.lang.Thread.run(Thread.java:534)\n",
    "Andre, can you please comment on the state of this bug.",
    "I\u0027ve applied the patch on 2004/12/8 but forgot to mark the bug as fixed."
  ],
  "commentCreationDates": [
    "2004-12-07T17:56:36+01:00",
    "2004-12-08T09:01:53+01:00",
    "2004-12-08T09:58:15+01:00",
    "2004-12-13T09:32:19+01:00",
    "2005-03-21T21:53:13+01:00",
    "2005-03-21T22:35:26+01:00"
  ],
  "traces": [
    {
      "exceptionType": "java.lang.NullPointerException",
      "elements": [
        {
          "method": "org.eclipse.jdt.internal.corext.util.AllTypesCache.getTypes",
          "source": "AllTypesCache.java:246"
        },
        {
          "method": "org.eclipse.jdt.text.tests.performance.EditorTestHelper.joinBackgroundActivities",
          "source": "EditorTestHelper.java: 243"
        },
        {
          "method": "org.eclipse.jdt.text.tests.performance.PerformanceTestSetup.setUp",
          "source": "PerformanceTestSetup.java:76"
        },
        {
          "method": "junit.extensions.TestSetup$1.protect",
          "source": "TestSetup.java:18"
        },
        {
          "method": "junit.extensions.TestSetup.run",
          "source": "TestSetup.java:23"
        },
        {
          "method": "junit.extensions.TestDecorator.basicRun",
          "source": "TestDecorator.java:22"
        },
        {
          "method": "junit.extensions.TestDecorator.run",
          "source": "TestDecorator.java:28"
        },
        {
          "method": "org.eclipse.jdt.text.tests.performance.CloseWorkbenchDecorator.run",
          "source": "CloseWorkbenchDecorator.java: 31"
        },
        {
          "method": "org.eclipse.test.EclipseTestRunner.run",
          "source": "EclipseTestRunner.java:320"
        },
        {
          "method": "org.eclipse.test.EclipseTestRunner.run",
          "source": "EclipseTestRunner.java:196"
        },
        {
          "method": "org.eclipse.test.UITestApplication$3.run",
          "source": "UITestApplication.java:188"
        },
        {
          "method": "org.eclipse.swt.widgets.RunnableLock.run",
          "source": "RunnableLock.java:35"
        },
        {
          "method": "org.eclipse.swt.widgets.Synchronizer.runAsyncMessages",
          "source": "Synchronizer.java:106"
        },
        {
          "method": "org.eclipse.swt.widgets.Display.runAsyncMessages",
          "source": "Display.java:2749"
        },
        {
          "method": "org.eclipse.swt.widgets.Display.readAndDispatch",
          "source": "Display.java:2434"
        },
        {
          "method": "org.eclipse.ui.internal.Workbench.runEventLoop",
          "source": "Workbench.java:1377"
        },
        {
          "method": "org.eclipse.ui.internal.Workbench.runUI",
          "source": "Workbench.java:1348"
        },
        {
          "method": "org.eclipse.ui.internal.Workbench.createAndRunWorkbench",
          "source": "Workbench.java:254"
        },
        {
          "method": "org.eclipse.ui.PlatformUI.createAndRunWorkbench",
          "source": "PlatformUI.java:141"
        },
        {
          "method": "org.eclipse.ui.internal.ide.IDEApplication.run",
          "source": "IDEApplication.java:96"
        },
        {
          "method": "org.eclipse.test.UITestApplication.runApplication",
          "source": "UITestApplication.java:131"
        },
        {
          "method": "org.eclipse.test.UITestApplication.run",
          "source": "UITestApplication.java:58"
        },
        {
          "method": "org.eclipse.core.internal.runtime.PlatformActivator$1.run",
          "source": "PlatformActivator.java:335"
        },
        {
          "method": "org.eclipse.core.runtime.adaptor.EclipseStarter.run",
          "source": "EclipseStarter.java:273"
        },
        {
          "method": "org.eclipse.core.runtime.adaptor.EclipseStarter.run",
          "source": "EclipseStarter.java:129"
        },
        {
          "method": "sun.reflect.NativeMethodAccessorImpl.invoke0",
          "source": "Native Method"
        },
        {
          "method": "sun.reflect.NativeMethodAccessorImpl.invoke",
          "source": "NativeMethodAccessorImpl.java:39"
        },
        {
          "method": "sun.reflect.DelegatingMethodAccessorImpl.invoke",
          "source": "DelegatingMethodAccessorImpl.java:25"
        },
        {
          "method": "org.eclipse.core.launcher.Main.basicRun",
          "source": "Main.java:183"
        },
        {
          "method": "org.eclipse.core.launcher.Main.run",
          "source": "Main.java:644"
        },
        {
          "method": "org.eclipse.core.launcher.Main.main",
          "source": "Main.java:628"
        }
      ],
      "number": 0,
      "commentIndex": 0,
      "bugId": "80393",
      "date": "2004-12-07T17:56:36+01:00",
      "product": "JDT",
      "component": "UI",
      "severity": "normal"
    },
    {
      "exceptionType": "SWTException",
      "message": "Device is disposed\" exception could come from the fact that there is a \"Workbench.close()\" call in the JDT/Text tests at the end of the test-suite, which is a workaround for bug 71362.       [java] java.lang.InterruptedException      [java]",
      "elements": [
        {
          "method": "java.lang.Object.wait",
          "source": "Native Method"
        }
      ],
      "number": 1,
      "commentIndex": 3,
      "bugId": "80393",
      "date": "2004-12-13T09:32:19+01:00",
      "product": "JDT",
      "component": "UI",
      "severity": "normal"
    },
    {
      "exceptionType": "org.eclipse.swt.SWTException",
      "message": "Device is disposed      [java]",
      "elements": [
        {
          "method": "org.eclipse.swt.SWT.error",
          "source": "SWT.java:2691"
        }
      ],
      "number": 2,
      "commentIndex": 3,
      "bugId": "80393",
      "date": "2004-12-13T09:32:19+01:00",
      "product": "JDT",
      "component": "UI",
      "severity": "normal"
    }
  ],
  "groupId": "80393",
  "bugId": "80393",
  "date": "2004-12-07T17:56:36+01:00",
  "product": "JDT",
  "component": "UI",
  "severity": "normal"
}