{
  "comments": [
    "With the changes for bug 80332, an NPE is generated if the preference page is\nopen before any Java apps were launch in debug mode.\n\n!ENTRY org.eclipse.core.runtime 4 2 2004-12-13 13:51:27.77\n!MESSAGE Problems occurred when invoking code from plug-in:\n\"org.eclipse.core.runtime\".\n!STACK 0\njava.lang.NullPointerException\n        at\norg.eclipse.jdt.internal.debug.core.logicalstructures.JavaLogicalStructures.getJavaLogicalStructures(JavaLogicalStructures.java)\n        at\norg.eclipse.jdt.internal.debug.ui.JavaLogicalStructuresPreferencePage$LogicalStructuresListViewerContentProvider.\u003cinit\u003e(JavaLogicalStructuresPreferencePage.java:94)\n        at\norg.eclipse.jdt.internal.debug.ui.JavaLogicalStructuresPreferencePage.createContents(JavaLogicalStructuresPreferencePage.java:222)\n        at\norg.eclipse.jface.preference.PreferencePage.createControl(PreferencePage.java:413)\n        at\norg.eclipse.jface.preference.PreferencePage.createControl(PreferencePage.java:378)\n        at\norg.eclipse.ui.internal.dialogs.WorkbenchPreferenceDialog.createPageControl(WorkbenchPreferenceDialog.java:994)\n        at\norg.eclipse.jface.preference.PreferenceDialog$13.run(PreferenceDialog.java:1116)\n        at\norg.eclipse.core.internal.runtime.InternalPlatform.run(InternalPlatform.java:1044)\n        at org.eclipse.core.runtime.Platform.run(Platform.java:747)\n        at\norg.eclipse.jface.preference.PreferenceDialog.showPage(PreferenceDialog.java:1110)\n        at\norg.eclipse.ui.internal.dialogs.WorkbenchPreferenceDialog.showPage(WorkbenchPreferenceDialog.java:782)\n        at\norg.eclipse.jface.preference.PreferenceDialog$9.selectionChanged(PreferenceDialog.java:619)\n        at\norg.eclipse.jface.viewers.StructuredViewer$3.run(StructuredViewer.java:681)\n        at\norg.eclipse.core.internal.runtime.InternalPlatform.run(InternalPlatform.java:1044)\n        at org.eclipse.core.runtime.Platform.run(Platform.java:747)\n        at\norg.eclipse.jface.viewers.StructuredViewer.firePostSelectionChanged(StructuredViewer.java:679)\n        at\norg.eclipse.jface.viewers.StructuredViewer.handlePostSelect(StructuredViewer.java:950)\n        at\norg.eclipse.jface.viewers.StructuredViewer$5.widgetSelected(StructuredViewer.java:970)\n        at\norg.eclipse.jface.util.OpenStrategy.firePostSelectionEvent(OpenStrategy.java:231)\n        at org.eclipse.jface.util.OpenStrategy.access$4(OpenStrategy.java:226)\n        at org.eclipse.jface.util.OpenStrategy$3.run(OpenStrategy.java:392)\n        at org.eclipse.swt.widgets.RunnableLock.run(RunnableLock.java:35)\n        at\norg.eclipse.swt.widgets.Synchronizer.runAsyncMessages(Synchronizer.java:118)\n[...]",
    "Fixed in JavaLogicalStructures. The static initializer was not declared as \u0027static\u0027.",
    "Please verify, Darin W.",
    "Verified."
  ],
  "commentCreationDates": [
    "2004-12-13T21:55:22+01:00",
    "2004-12-13T21:56:50+01:00",
    "2004-12-13T21:57:10+01:00",
    "2004-12-13T22:04:11+01:00"
  ],
  "traces": [
    {
      "exceptionType": "java.lang.NullPointerException",
      "elements": [
        {
          "method": "org.eclipse.jdt.internal.debug.core.logicalstructures.JavaLogicalStructures.getJavaLogicalStructures",
          "source": "JavaLogicalStructures.java"
        },
        {
          "method": "org.eclipse.jdt.internal.debug.ui.JavaLogicalStructuresPreferencePage$LogicalStructuresListViewerContentProvider.\u003cinit\u003e",
          "source": "JavaLogicalStructuresPreferencePage.java:94"
        },
        {
          "method": "org.eclipse.jdt.internal.debug.ui.JavaLogicalStructuresPreferencePage.createContents",
          "source": "JavaLogicalStructuresPreferencePage.java:222"
        },
        {
          "method": "org.eclipse.jface.preference.PreferencePage.createControl",
          "source": "PreferencePage.java:413"
        },
        {
          "method": "org.eclipse.jface.preference.PreferencePage.createControl",
          "source": "PreferencePage.java:378"
        },
        {
          "method": "org.eclipse.ui.internal.dialogs.WorkbenchPreferenceDialog.createPageControl",
          "source": "WorkbenchPreferenceDialog.java:994"
        },
        {
          "method": "org.eclipse.jface.preference.PreferenceDialog$13.run",
          "source": "PreferenceDialog.java:1116"
        },
        {
          "method": "org.eclipse.core.internal.runtime.InternalPlatform.run",
          "source": "InternalPlatform.java:1044"
        },
        {
          "method": "org.eclipse.core.runtime.Platform.run",
          "source": "Platform.java:747"
        },
        {
          "method": "org.eclipse.jface.preference.PreferenceDialog.showPage",
          "source": "PreferenceDialog.java:1110"
        },
        {
          "method": "org.eclipse.ui.internal.dialogs.WorkbenchPreferenceDialog.showPage",
          "source": "WorkbenchPreferenceDialog.java:782"
        },
        {
          "method": "org.eclipse.jface.preference.PreferenceDialog$9.selectionChanged",
          "source": "PreferenceDialog.java:619"
        },
        {
          "method": "org.eclipse.jface.viewers.StructuredViewer$3.run",
          "source": "StructuredViewer.java:681"
        },
        {
          "method": "org.eclipse.core.internal.runtime.InternalPlatform.run",
          "source": "InternalPlatform.java:1044"
        },
        {
          "method": "org.eclipse.core.runtime.Platform.run",
          "source": "Platform.java:747"
        },
        {
          "method": "org.eclipse.jface.viewers.StructuredViewer.firePostSelectionChanged",
          "source": "StructuredViewer.java:679"
        },
        {
          "method": "org.eclipse.jface.viewers.StructuredViewer.handlePostSelect",
          "source": "StructuredViewer.java:950"
        },
        {
          "method": "org.eclipse.jface.viewers.StructuredViewer$5.widgetSelected",
          "source": "StructuredViewer.java:970"
        },
        {
          "method": "org.eclipse.jface.util.OpenStrategy.firePostSelectionEvent",
          "source": "OpenStrategy.java:231"
        },
        {
          "method": "org.eclipse.jface.util.OpenStrategy.access$4",
          "source": "OpenStrategy.java:226"
        },
        {
          "method": "org.eclipse.jface.util.OpenStrategy$3.run",
          "source": "OpenStrategy.java:392"
        },
        {
          "method": "org.eclipse.swt.widgets.RunnableLock.run",
          "source": "RunnableLock.java:35"
        },
        {
          "method": "org.eclipse.swt.widgets.Synchronizer.runAsyncMessages",
          "source": "Synchronizer.java:118"
        }
      ],
      "number": 0,
      "commentIndex": 0,
      "bugId": "80879",
      "date": "2004-12-13T21:55:22+01:00",
      "product": "JDT",
      "component": "Debug",
      "severity": "normal"
    }
  ],
  "groupId": "80879",
  "bugId": "80879",
  "date": "2004-12-13T21:55:22+01:00",
  "product": "JDT",
  "component": "Debug",
  "severity": "normal"
}