{
  "comments": [
    "Using pde build scripts fails when building application between 0:00 and 9:59.\nFollowing error message appears:\n\u003eTarget `229\u0027 does not exist in this project.\u003c\nwhere number is a current time (02:29).\n\nError message disapears when time is between 10:00 and 23:59\n\n\nThe full stack trace of the problem.\nApache Ant version 1.6.2 compiled on July 16 2004\nBuildfile:\nC:\\Work\\java\\eclipse3\\plugins\\org.eclipse.pde.build_3.0.1\\scripts\\build.xml\nparsing buildfile\nC:\\Work\\java\\eclipse3\\plugins\\org.eclipse.pde.build_3.0.1\\scripts\\build.xml with\nURI \u003d file:///C:/Work/java/eclipse3/plugins/org.ecl\nipse.pde.build_3.0.1/scripts/build.xml\nProject base dir set to:\nC:\\Work\\java\\eclipse3\\plugins\\org.eclipse.pde.build_3.0.1\\scripts\n [property] Loading C:\\wielkadupa\\build.properties\n\nBUILD FAILED\nTarget `229\u0027 does not exist in this project.\n        at org.apache.tools.ant.Project.tsort(Project.java:1665)\n        at org.apache.tools.ant.Project.topoSort(Project.java:1587)\n        at org.apache.tools.ant.Project.executeTarget(Project.java:1191)\n        at org.apache.tools.ant.Project.executeTargets(Project.java:1062)\n        at\norg.eclipse.ant.internal.core.ant.InternalAntRunner.run(InternalAntRunner.java:633)\n        at\norg.eclipse.ant.internal.core.ant.InternalAntRunner.run(InternalAntRunner.java:539)\n        at sun.reflect.NativeMethodAccessorImpl.invoke0(Native Method)\n        at\nsun.reflect.NativeMethodAccessorImpl.invoke(NativeMethodAccessorImpl.java:39)\n        at\nsun.reflect.DelegatingMethodAccessorImpl.invoke(DelegatingMethodAccessorImpl.java:25)\n        at java.lang.reflect.Method.invoke(Method.java:324)\n        at org.eclipse.ant.core.AntRunner.run(AntRunner.java:488)\n        at\norg.eclipse.core.internal.runtime.PlatformActivator$1.run(PlatformActivator.java:335)\n        at\norg.eclipse.core.runtime.adaptor.EclipseStarter.run(EclipseStarter.java:273)\n        at\norg.eclipse.core.runtime.adaptor.EclipseStarter.run(EclipseStarter.java:129)\n        at sun.reflect.NativeMethodAccessorImpl.invoke0(Native Method)\n        at\nsun.reflect.NativeMethodAccessorImpl.invoke(NativeMethodAccessorImpl.java:39)\n        at\nsun.reflect.DelegatingMethodAccessorImpl.invoke(DelegatingMethodAccessorImpl.java:25)\n        at java.lang.reflect.Method.invoke(Method.java:324)\n        at org.eclipse.core.launcher.Main.basicRun(Main.java:185)\n        at org.eclipse.core.launcher.Main.run(Main.java:704)\n        at org.eclipse.core.launcher.Main.main(Main.java:688)\n\nTotal time: 0 seconds\n!SESSION gru 14, 2004 02:29:55.953 ---------------------------------------------\neclipse.buildId\u003dM200409161125\njava.version\u003d1.4.2_04\njava.vendor\u003dSun Microsystems Inc.\nBootLoader constants: OS\u003dwin32, ARCH\u003dx86, WS\u003dwin32, NL\u003dpl_PL\nCommand-line arguments: -application org.eclipse.ant.core.antRunner\n-DbaseLocation\u003dC:\\Work\\java\\eclipse3 -Dbuilder\u003dc:\\wielkadupa -Dtimestamp\u003d2-144-20\n229 -DbuildDirectory\u003dc:\\wielkadupa\\build\n-DsourceDir\u003dC:\\RepCapWrokingSet\\Implementation\\AutoBuild\\TemplateEditor\\..\\..\\Sources\n-verbose\n\n!ENTRY org.eclipse.osgi gru 14, 2004 02:29:56.00\n!MESSAGE Application error\n!STACK 1\njava.lang.reflect.InvocationTargetException\n        at sun.reflect.NativeMethodAccessorImpl.invoke0(Native Method)\n        at\nsun.reflect.NativeMethodAccessorImpl.invoke(NativeMethodAccessorImpl.java:39)\n        at\nsun.reflect.DelegatingMethodAccessorImpl.invoke(DelegatingMethodAccessorImpl.java:25)\n        at java.lang.reflect.Method.invoke(Method.java:324)\n        at org.eclipse.ant.core.AntRunner.run(AntRunner.java:488)\n        at\norg.eclipse.core.internal.runtime.PlatformActivator$1.run(PlatformActivator.java:335)\n        at\norg.eclipse.core.runtime.adaptor.EclipseStarter.run(EclipseStarter.java:273)\n        at\norg.eclipse.core.runtime.adaptor.EclipseStarter.run(EclipseStarter.java:129)\n        at sun.reflect.NativeMethodAccessorImpl.invoke0(Native Method)\n        at\nsun.reflect.NativeMethodAccessorImpl.invoke(NativeMethodAccessorImpl.java:39)\n        at\nsun.reflect.DelegatingMethodAccessorImpl.invoke(DelegatingMethodAccessorImpl.java:25)\n        at java.lang.reflect.Method.invoke(Method.java:324)\n        at org.eclipse.core.launcher.Main.basicRun(Main.java:185)\n        at org.eclipse.core.launcher.Main.run(Main.java:704)\n        at org.eclipse.core.launcher.Main.main(Main.java:688)\nCaused by: Target `229\u0027 does not exist in this project.\n        at org.apache.tools.ant.Project.tsort(Project.java:1665)\n        at org.apache.tools.ant.Project.topoSort(Project.java:1587)\n        at org.apache.tools.ant.Project.executeTarget(Project.java:1191)\n        at org.apache.tools.ant.Project.executeTargets(Project.java:1062)\n        at\norg.eclipse.ant.internal.core.ant.InternalAntRunner.run(InternalAntRunner.java:633)\n        at\norg.eclipse.ant.internal.core.ant.InternalAntRunner.run(InternalAntRunner.java:539)\n        ... 15 more\nRoot exception:\nTarget `229\u0027 does not exist in this project.\n        at org.apache.tools.ant.Project.tsort(Project.java:1665)\n        at org.apache.tools.ant.Project.topoSort(Project.java:1587)\n        at org.apache.tools.ant.Project.executeTarget(Project.java:1191)\n        at org.apache.tools.ant.Project.executeTargets(Project.java:1062)\n        at\norg.eclipse.ant.internal.core.ant.InternalAntRunner.run(InternalAntRunner.java:633)\n        at\norg.eclipse.ant.internal.core.ant.InternalAntRunner.run(InternalAntRunner.java:539)\n        at sun.reflect.NativeMethodAccessorImpl.invoke0(Native Method)\n        at\nsun.reflect.NativeMethodAccessorImpl.invoke(NativeMethodAccessorImpl.java:39)\n        at\nsun.reflect.DelegatingMethodAccessorImpl.invoke(DelegatingMethodAccessorImpl.java:25)\n        at java.lang.reflect.Method.invoke(Method.java:324)\n        at org.eclipse.ant.core.AntRunner.run(AntRunner.java:488)\n        at\norg.eclipse.core.internal.runtime.PlatformActivator$1.run(PlatformActivator.java:335)\n        at\norg.eclipse.core.runtime.adaptor.EclipseStarter.run(EclipseStarter.java:273)\n        at\norg.eclipse.core.runtime.adaptor.EclipseStarter.run(EclipseStarter.java:129)\n        at sun.reflect.NativeMethodAccessorImpl.invoke0(Native Method)\n        at\nsun.reflect.NativeMethodAccessorImpl.invoke(NativeMethodAccessorImpl.java:39)\n        at\nsun.reflect.DelegatingMethodAccessorImpl.invoke(DelegatingMethodAccessorImpl.java:25)\n        at java.lang.reflect.Method.invoke(Method.java:324)\n        at org.eclipse.core.launcher.Main.basicRun(Main.java:185)\n        at org.eclipse.core.launcher.Main.run(Main.java:704)\n        at org.eclipse.core.launcher.Main.main(Main.java:688)",
    "Could you attach the build.xml containing the 229 target?",
    "Hi,\n\nWe are building the application in followin way:\n\nThe directory structure of our AutoBuild looks in following way:\nAutobuild \u003cDIR\u003e\n|---build \u003cDIR\u003e\n    |---fetch_[our_pluginname].xml \u003cfile\u003e\n|---build.bat \u003cfile\u003e\n|---build.properties \u003cfile\u003e\n|---customTargets.xml \u003cfile\u003e\n\nWe are starting build process by calling following line from the build.bat file.\n\njava -cp %ECLIPSE_HOME_DIR%\\startup.jar org.eclipse.core.launcher.Main -\napplication org.eclipse.ant.core.antRunner -DbaseLocation\u003d%ECLIPSE_HOME_DIR% -\nDbuilder\u003d%BUILD_DIR% -Dtimestamp\u003d%TIMESTAMP% -DbuildDirectory\u003d%BUILD_DIR%\n\\build -DsourceDir\u003d%SOURCE_DIR% -verbose -consolelog %ANT_TASKS%\n\nThe build.properties file differs from the \n\u003ceclipse_plugins\u003e/org.eclipse.pde.build_3.0.1/scripts/build-template.properties \nby following elements (Only different properties are listed below):\n\n# buildDirectory\nbuildId\u003d${timestamp}//The same error occures with buildId\u003dTestIdentifier\n#baseLocation\nbaseos\u003dwin32\nbasews\u003dwin32\nbasearch\u003dx86\n#bootclasspath\njavaSource\u003d1.4\n\n\nThe customTargets.xml file is almost the same as the file \n\u003ceclipse_plugins\u003e/org.eclipse.pde.build_3.0.1/scripts/customTargets-template.xml\nthe only difference is the allElements target which looks as below:\n\u003ctarget name\u003d\"allElements\"\u003e\n\t\u003cant antfile\u003d\"${genericTargets}\" target\u003d\"${target}\" \u003e\n\t\t\u003cproperty name\u003d\"type\" value\u003d\"\u003cfeature\u003e\" /\u003e\n\t\t\u003cproperty name\u003d\"id\" value\u003d\"\u003celement.id\u003e\" /\u003e\n\t\u003c/ant\u003e\n\u003c/target\u003e\n\n\nthe fetch_[plugin_name].xml has following content:\n\u003cproject name\u003d\"FetchScript\" default\u003d\"fetch\"\u003e\n\t\u003cproperty name\u003d\"quiet\" value\u003d\"true\"/\u003e\n\n\t\u003ctarget name\u003d\"fetch\"\u003e\n\t\t\u003cantcall target\u003d\"fetch.element\"/\u003e\n\t\t\u003cantcall target\u003d\"fetch.plugins\"/\u003e\n\t\t\u003cantcall target\u003d\"fetch.recursively\"/\u003e\n\t\u003c/target\u003e\n\t\u003ctarget name\u003d\"fetch.element\" if\u003d\"featureOnly\"\u003e\n\t\t\u003ccopy todir\u003d\"${buildDirectory}/features\"\u003e\n\t\t\t\u003cfileset dir\u003d\"${sourceDir}/features\"/\u003e\n\t\t\u003c/copy\u003e\n\t\u003c/target\u003e\n\t\u003ctarget name\u003d\"fetch.plugins\" if\u003d\"featureAndPlugins\"\u003e\n\t\t\u003ccopy todir\u003d\"${buildDirectory}/plugins\"\u003e\n\t\t\t\u003cfileset dir\u003d\"${sourceDir}/plugins\"/\u003e\t\t\n\t\t\u003c/copy\u003e\n\t\u003c/target\u003e\n\t\u003ctarget name\u003d\"fetch.recursively\" if\u003d\"featuresRecursively\"\u003e\n\t\u003c/target\u003e\n\n\u003c/project\u003e\n",
    "Please provide the build.xml that contains a reference to the time.\n(for example in the stack trace I see Caused by: Target `229\u0027 does not exist in\nthis project). Without it I can\u0027t do anything.",
    "Note as well that our nightly build are running at 00:10 and the integration\nbuild at 08:00",
    "Hi,\n\nWe DO NOT have any build.xml which have reference to the time. That is also\nstrange to me.\n\nWe are using your build.xml file, from the org.eclipse.pde.build_3.0.1, it looks\nas follows (please take a look at the bat command i\u0027ve posted before):\n\n\u003cproject name\u003d\"Build All Elements\" default\u003d\"main\"\u003e\n\n\u003c!-- \u003d\u003d\u003d\u003d\u003d\u003d\u003d\u003d\u003d\u003d\u003d\u003d\u003d\u003d\u003d\u003d\u003d\u003d\u003d\u003d\u003d\u003d\u003d\u003d\u003d\u003d\u003d\u003d\u003d\u003d\u003d\u003d\u003d\u003d\u003d\u003d\u003d\u003d\u003d\u003d\u003d\u003d\u003d\u003d\u003d\u003d\u003d\u003d\u003d\u003d\u003d\u003d\u003d\u003d\u003d\u003d\u003d\u003d\u003d\u003d\u003d\u003d\u003d\u003d\u003d\u003d\u003d\u003d\u003d --\u003e\n\u003c!-- Global properties.  See the build.properties for information on --\u003e\n\u003c!-- the properties which callers can control. --\u003e\n\u003c!-- \u003d\u003d\u003d\u003d\u003d\u003d\u003d\u003d\u003d\u003d\u003d\u003d\u003d\u003d\u003d\u003d\u003d\u003d\u003d\u003d\u003d\u003d\u003d\u003d\u003d\u003d\u003d\u003d\u003d\u003d\u003d\u003d\u003d\u003d\u003d\u003d\u003d\u003d\u003d\u003d\u003d\u003d\u003d\u003d\u003d\u003d\u003d\u003d\u003d\u003d\u003d\u003d\u003d\u003d\u003d\u003d\u003d\u003d\u003d\u003d\u003d\u003d\u003d\u003d\u003d\u003d\u003d\u003d\u003d --\u003e\n\u003cproperty name\u003d\"builderDirectory\" location\u003d\"${builder}\"/\u003e\n\u003cproperty name\u003d\"buildProperties\" location\u003d\"${builder}/build.properties\"/\u003e\n\u003cproperty file\u003d\"${buildProperties}\"/\u003e\n\u003cproperty name\u003d\"customTargets\" location\u003d\"${builderDirectory}/customTargets.xml\"/\u003e\n\u003cproperty name\u003d\"genericTargets\" location\u003d\"genericTargets.xml\"/\u003e\n\n\u003c!-- \u003d\u003d\u003d\u003d\u003d\u003d\u003d\u003d\u003d\u003d\u003d\u003d\u003d\u003d\u003d\u003d\u003d\u003d\u003d\u003d\u003d\u003d\u003d\u003d\u003d\u003d\u003d\u003d\u003d\u003d\u003d\u003d\u003d\u003d\u003d\u003d\u003d\u003d\u003d\u003d\u003d\u003d\u003d\u003d\u003d\u003d\u003d\u003d\u003d\u003d\u003d\u003d\u003d\u003d\u003d\u003d\u003d\u003d\u003d\u003d\u003d\u003d\u003d\u003d\u003d\u003d\u003d\u003d\u003d --\u003e\n\u003c!-- main entry point to setup, fetch, generate, build etc. Use --\u003e\n\u003c!-- the customTargets.xml to modify the build behaviour. --\u003e\n\u003c!-- \u003d\u003d\u003d\u003d\u003d\u003d\u003d\u003d\u003d\u003d\u003d\u003d\u003d\u003d\u003d\u003d\u003d\u003d\u003d\u003d\u003d\u003d\u003d\u003d\u003d\u003d\u003d\u003d\u003d\u003d\u003d\u003d\u003d\u003d\u003d\u003d\u003d\u003d\u003d\u003d\u003d\u003d\u003d\u003d\u003d\u003d\u003d\u003d\u003d\u003d\u003d\u003d\u003d\u003d\u003d\u003d\u003d\u003d\u003d\u003d\u003d\u003d\u003d\u003d\u003d\u003d\u003d\u003d\u003d --\u003e\n\n\u003c!-- ******* add in the descriptions for each of the top level targets to teh\ntarget decl --\u003e\n\u003ctarget name\u003d\"main\" description\u003d\"the main build target\"\u003e\t\n  \t\u003cantcall target\u003d\"preBuild\" /\u003e \n \t\u003cantcall target\u003d\"fetch\" /\u003e\n\t\u003cantcall target\u003d\"generate\" /\u003e \n\t\u003cantcall target\u003d\"process\" /\u003e \n\t\u003cantcall target\u003d\"assemble\" /\u003e\n\t\u003cantcall target\u003d\"postBuild\" /\u003e\n\u003c/target\u003e\n\n\u003c!-- \u003d\u003d\u003d\u003d\u003d\u003d\u003d\u003d\u003d\u003d\u003d\u003d\u003d\u003d\u003d\u003d\u003d\u003d\u003d\u003d\u003d\u003d\u003d\u003d\u003d\u003d\u003d\u003d\u003d\u003d\u003d\u003d\u003d\u003d\u003d\u003d\u003d\u003d\u003d\u003d\u003d\u003d\u003d\u003d\u003d\u003d\u003d\u003d\u003d\u003d\u003d\u003d\u003d\u003d\u003d\u003d\u003d\u003d\u003d\u003d\u003d\u003d\u003d\u003d\u003d\u003d\u003d\u003d\u003d --\u003e\n\u003c!-- Steps to do before starting the build.  Typical setup includes --\u003e\n\u003c!-- fetching the map files and building the directory.  --\u003e\n\u003c!-- \u003d\u003d\u003d\u003d\u003d\u003d\u003d\u003d\u003d\u003d\u003d\u003d\u003d\u003d\u003d\u003d\u003d\u003d\u003d\u003d\u003d\u003d\u003d\u003d\u003d\u003d\u003d\u003d\u003d\u003d\u003d\u003d\u003d\u003d\u003d\u003d\u003d\u003d\u003d\u003d\u003d\u003d\u003d\u003d\u003d\u003d\u003d\u003d\u003d\u003d\u003d\u003d\u003d\u003d\u003d\u003d\u003d\u003d\u003d\u003d\u003d\u003d\u003d\u003d\u003d\u003d\u003d\u003d\u003d --\u003e\n\u003ctarget name\u003d\"preBuild\"\u003e\n\t\u003cmkdir dir\u003d\"${buildDirectory}\" /\u003e\n\t\u003cant antfile\u003d\"${customTargets}\" target\u003d\"preSetup\" /\u003e \n\t\u003cant antfile\u003d\"${customTargets}\" target\u003d\"getMapFiles\" /\u003e \n\t\u003cconcat destfile\u003d\"${buildDirectory}/directory.txt\" fixlastline\u003d\"yes\"\u003e\n\t\t\u003cfileset dir\u003d\"${buildDirectory}\" includes\u003d\"maps/**/*.map\"/\u003e\n\t\u003c/concat\u003e\n\t\u003cant antfile\u003d\"${customTargets}\" target\u003d\"postSetup\" /\u003e\n\u003c/target\u003e\n\n\u003c!-- \u003d\u003d\u003d\u003d\u003d\u003d\u003d\u003d\u003d\u003d\u003d\u003d\u003d\u003d\u003d\u003d\u003d\u003d\u003d\u003d\u003d\u003d\u003d\u003d\u003d\u003d\u003d\u003d\u003d\u003d\u003d\u003d\u003d\u003d\u003d\u003d\u003d\u003d\u003d\u003d\u003d\u003d\u003d\u003d\u003d\u003d\u003d\u003d\u003d\u003d\u003d\u003d\u003d\u003d\u003d\u003d\u003d\u003d\u003d\u003d\u003d\u003d\u003d\u003d\u003d\u003d\u003d\u003d\u003d --\u003e\n\u003c!-- Fetch the elements identified in the customTargets --\u003e\n\u003c!-- \u003d\u003d\u003d\u003d\u003d\u003d\u003d\u003d\u003d\u003d\u003d\u003d\u003d\u003d\u003d\u003d\u003d\u003d\u003d\u003d\u003d\u003d\u003d\u003d\u003d\u003d\u003d\u003d\u003d\u003d\u003d\u003d\u003d\u003d\u003d\u003d\u003d\u003d\u003d\u003d\u003d\u003d\u003d\u003d\u003d\u003d\u003d\u003d\u003d\u003d\u003d\u003d\u003d\u003d\u003d\u003d\u003d\u003d\u003d\u003d\u003d\u003d\u003d\u003d\u003d\u003d\u003d\u003d\u003d --\u003e\n\u003ctarget name\u003d\"fetch\"\u003e\n\t\u003cant antfile\u003d\"${customTargets}\" target\u003d\"preFetch\"/\u003e\n\t\u003c!-- Generates and then execute the fetch scripts for each build element--\u003e\n\t\u003cant antfile\u003d\"${customTargets}\" target\u003d\"allElements\"\u003e\n\t\t\u003cproperty name\u003d\"target\" value\u003d\"fetchElement\" /\u003e\n\t\u003c/ant\u003e\n\t\n\t\u003cant antfile\u003d\"${customTargets}\" target\u003d\"postFetch\"/\u003e\n\u003c/target\u003e\n\n\u003c!-- \u003d\u003d\u003d\u003d\u003d\u003d\u003d\u003d\u003d\u003d\u003d\u003d\u003d\u003d\u003d\u003d\u003d\u003d\u003d\u003d\u003d\u003d\u003d\u003d\u003d\u003d\u003d\u003d\u003d\u003d\u003d\u003d\u003d\u003d\u003d\u003d\u003d\u003d\u003d\u003d\u003d\u003d\u003d\u003d\u003d\u003d\u003d\u003d\u003d\u003d\u003d\u003d\u003d\u003d\u003d\u003d\u003d\u003d\u003d\u003d\u003d\u003d\u003d\u003d\u003d\u003d\u003d\u003d\u003d --\u003e\n\u003c!-- Generate the build scripts for each element identified in the customTargets --\u003e\n\u003c!-- \u003d\u003d\u003d\u003d\u003d\u003d\u003d\u003d\u003d\u003d\u003d\u003d\u003d\u003d\u003d\u003d\u003d\u003d\u003d\u003d\u003d\u003d\u003d\u003d\u003d\u003d\u003d\u003d\u003d\u003d\u003d\u003d\u003d\u003d\u003d\u003d\u003d\u003d\u003d\u003d\u003d\u003d\u003d\u003d\u003d\u003d\u003d\u003d\u003d\u003d\u003d\u003d\u003d\u003d\u003d\u003d\u003d\u003d\u003d\u003d\u003d\u003d\u003d\u003d\u003d\u003d\u003d\u003d\u003d --\u003e\n\u003ctarget name\u003d\"generate\"\u003e\n\t\u003cant antfile\u003d\"${customTargets}\" target\u003d\"preGenerate\"/\u003e\n\t\u003c!-- Generate the build.xml for each build element--\u003e\n\t\u003cant antfile\u003d\"${customTargets}\" target\u003d\"allElements\"\u003e\n\t\t\u003cproperty name\u003d\"target\" value\u003d\"generateScript\" /\u003e\n\t\u003c/ant\u003e\n\t\u003cant antfile\u003d\"${customTargets}\" target\u003d\"postGenerate\"/\u003e\t\n\u003c/target\u003e\n\n\u003c!-- \u003d\u003d\u003d\u003d\u003d\u003d\u003d\u003d\u003d\u003d\u003d\u003d\u003d\u003d\u003d\u003d\u003d\u003d\u003d\u003d\u003d\u003d\u003d\u003d\u003d\u003d\u003d\u003d\u003d\u003d\u003d\u003d\u003d\u003d\u003d\u003d\u003d\u003d\u003d\u003d\u003d\u003d\u003d\u003d\u003d\u003d\u003d\u003d\u003d\u003d\u003d\u003d\u003d\u003d\u003d\u003d\u003d\u003d\u003d\u003d\u003d\u003d\u003d\u003d\u003d\u003d\u003d\u003d\u003d --\u003e\n\u003c!-- Run the build scripts for each element identified in the customTargets --\u003e\n\u003c!-- \u003d\u003d\u003d\u003d\u003d\u003d\u003d\u003d\u003d\u003d\u003d\u003d\u003d\u003d\u003d\u003d\u003d\u003d\u003d\u003d\u003d\u003d\u003d\u003d\u003d\u003d\u003d\u003d\u003d\u003d\u003d\u003d\u003d\u003d\u003d\u003d\u003d\u003d\u003d\u003d\u003d\u003d\u003d\u003d\u003d\u003d\u003d\u003d\u003d\u003d\u003d\u003d\u003d\u003d\u003d\u003d\u003d\u003d\u003d\u003d\u003d\u003d\u003d\u003d\u003d\u003d\u003d\u003d\u003d --\u003e\n\u003ctarget name\u003d\"process\"\u003e\n\t\u003c!-- Run custom tasks before processing, i.e. creating source build zip files --\u003e\n\t\u003cant antfile\u003d\"${customTargets}\" target\u003d\"preProcess\" /\u003e\n\n\t\u003c!-- Process all of the build elements--\u003e\n\t\u003cant antfile\u003d\"${customTargets}\" target\u003d\"allElements\"\u003e\n\t\t\u003cproperty name\u003d\"target\" value\u003d\"processElement\" /\u003e\n\t\u003c/ant\u003e\n\n\t\u003c!-- Run custom tasks after compiling, i.e. reporting compile errors --\u003e\n\t\u003cant antfile\u003d\"${customTargets}\" target\u003d\"postProcess\" /\u003e\n\u003c/target\u003e\n\n\u003c!-- \u003d\u003d\u003d\u003d\u003d\u003d\u003d\u003d\u003d\u003d\u003d\u003d\u003d\u003d\u003d\u003d\u003d\u003d\u003d\u003d\u003d\u003d\u003d\u003d\u003d\u003d\u003d\u003d\u003d\u003d\u003d\u003d\u003d\u003d\u003d\u003d\u003d\u003d\u003d\u003d\u003d\u003d\u003d\u003d\u003d\u003d\u003d\u003d\u003d\u003d\u003d\u003d\u003d\u003d\u003d\u003d\u003d\u003d\u003d\u003d\u003d\u003d\u003d\u003d\u003d\u003d\u003d\u003d\u003d --\u003e\n\u003c!-- Assemble the build elements into final distributions --\u003e\n\u003c!-- \u003d\u003d\u003d\u003d\u003d\u003d\u003d\u003d\u003d\u003d\u003d\u003d\u003d\u003d\u003d\u003d\u003d\u003d\u003d\u003d\u003d\u003d\u003d\u003d\u003d\u003d\u003d\u003d\u003d\u003d\u003d\u003d\u003d\u003d\u003d\u003d\u003d\u003d\u003d\u003d\u003d\u003d\u003d\u003d\u003d\u003d\u003d\u003d\u003d\u003d\u003d\u003d\u003d\u003d\u003d\u003d\u003d\u003d\u003d\u003d\u003d\u003d\u003d\u003d\u003d\u003d\u003d\u003d\u003d --\u003e\n\u003ctarget name\u003d\"assemble\"\u003e\n\t\u003cant antfile\u003d\"${customTargets}\" target\u003d\"preAssemble\"/\u003e\n\t\u003cant antfile\u003d\"${customTargets}\" target\u003d\"allElements\"\u003e\n\t\t\u003cproperty name\u003d\"target\" value\u003d\"assembleElement\"/\u003e\n\t\u003c/ant\u003e\n\t\u003cant antfile\u003d\"${customTargets}\" target\u003d\"postAssemble\"/\u003e\t\n\u003c/target\u003e\n\n\u003c!-- \u003d\u003d\u003d\u003d\u003d\u003d\u003d\u003d\u003d\u003d\u003d\u003d\u003d\u003d\u003d\u003d\u003d\u003d\u003d\u003d\u003d\u003d\u003d\u003d\u003d\u003d\u003d\u003d\u003d\u003d\u003d\u003d\u003d\u003d\u003d\u003d\u003d\u003d\u003d\u003d\u003d\u003d\u003d\u003d\u003d\u003d\u003d\u003d\u003d\u003d\u003d\u003d\u003d\u003d\u003d\u003d\u003d\u003d\u003d\u003d\u003d\u003d\u003d\u003d\u003d\u003d\u003d\u003d\u003d --\u003e\n\u003c!-- Do any steps required after the build (e.g., posting, testing, ...) --\u003e\n\u003c!-- \u003d\u003d\u003d\u003d\u003d\u003d\u003d\u003d\u003d\u003d\u003d\u003d\u003d\u003d\u003d\u003d\u003d\u003d\u003d\u003d\u003d\u003d\u003d\u003d\u003d\u003d\u003d\u003d\u003d\u003d\u003d\u003d\u003d\u003d\u003d\u003d\u003d\u003d\u003d\u003d\u003d\u003d\u003d\u003d\u003d\u003d\u003d\u003d\u003d\u003d\u003d\u003d\u003d\u003d\u003d\u003d\u003d\u003d\u003d\u003d\u003d\u003d\u003d\u003d\u003d\u003d\u003d\u003d\u003d --\u003e\n\u003ctarget name\u003d\"postBuild\"\u003e\n\t\u003cant antfile\u003d\"${customTargets}\" target\u003d\"postBuild\" /\u003e\n\u003c/target\u003e\n\n\u003c!-- \u003d\u003d\u003d\u003d\u003d\u003d\u003d\u003d\u003d\u003d\u003d\u003d\u003d\u003d\u003d\u003d\u003d\u003d\u003d\u003d\u003d\u003d\u003d\u003d\u003d\u003d\u003d\u003d\u003d\u003d\u003d\u003d\u003d\u003d\u003d\u003d\u003d\u003d\u003d\u003d\u003d\u003d\u003d\u003d\u003d\u003d\u003d\u003d\u003d\u003d\u003d\u003d\u003d\u003d\u003d\u003d\u003d\u003d\u003d\u003d\u003d\u003d\u003d\u003d\u003d\u003d\u003d\u003d\u003d --\u003e\n\u003c!-- Clean the build elements.  This target is here as an entry --\u003e\n\u003c!-- point to the customTargets.  It is not called directly in the normal --\u003e\n\u003c!-- course of events. --\u003e\n\u003c!-- \u003d\u003d\u003d\u003d\u003d\u003d\u003d\u003d\u003d\u003d\u003d\u003d\u003d\u003d\u003d\u003d\u003d\u003d\u003d\u003d\u003d\u003d\u003d\u003d\u003d\u003d\u003d\u003d\u003d\u003d\u003d\u003d\u003d\u003d\u003d\u003d\u003d\u003d\u003d\u003d\u003d\u003d\u003d\u003d\u003d\u003d\u003d\u003d\u003d\u003d\u003d\u003d\u003d\u003d\u003d\u003d\u003d\u003d\u003d\u003d\u003d\u003d\u003d\u003d\u003d\u003d\u003d\u003d\u003d --\u003e\n\u003ctarget name\u003d\"clean\"\u003e\n  \u003cant antfile\u003d\"${customTargets}\" target\u003d\"allElements\"\u003e\n     \u003cproperty name\u003d\"target\" value\u003d\"cleanElement\"/\u003e\n  \u003c/ant\u003e\n\u003c/target\u003e\n\n\u003c/project\u003e\n\n\nps. The error occures at the very beginning of the building process, so there\nare no plugins\u0027 build.xml files generated.",
    "Hi,\nWe\u0027ve found out the problem, and it\u0027s located in our build file. the time stamp \nproperty was incorreclty set inside the build command, because of such time it \nwas set to \u0027-Dtimestamp\u003d2-144-20 229\u0027 and here is the \"bug\".\n\nSorry for the problem.\n"
  ],
  "commentCreationDates": [
    "2004-12-14T11:50:52+01:00",
    "2004-12-14T14:16:29+01:00",
    "2004-12-14T15:55:24+01:00",
    "2004-12-14T16:17:06+01:00",
    "2004-12-14T16:41:48+01:00",
    "2004-12-14T20:04:21+01:00",
    "2004-12-15T14:09:57+01:00"
  ],
  "traces": [
    {
      "exceptionType": "java.lang.reflect.InvocationTargetException",
      "elements": [
        {
          "method": "sun.reflect.NativeMethodAccessorImpl.invoke0",
          "source": "Native Method"
        },
        {
          "method": "sun.reflect.NativeMethodAccessorImpl.invoke",
          "source": "NativeMethodAccessorImpl.java:39"
        },
        {
          "method": "sun.reflect.DelegatingMethodAccessorImpl.invoke",
          "source": "DelegatingMethodAccessorImpl.java:25"
        },
        {
          "method": "java.lang.reflect.Method.invoke",
          "source": "Method.java:324"
        },
        {
          "method": "org.eclipse.ant.core.AntRunner.run",
          "source": "AntRunner.java:488"
        },
        {
          "method": "org.eclipse.core.internal.runtime.PlatformActivator$1.run",
          "source": "PlatformActivator.java:335"
        },
        {
          "method": "org.eclipse.core.runtime.adaptor.EclipseStarter.run",
          "source": "EclipseStarter.java:273"
        },
        {
          "method": "org.eclipse.core.runtime.adaptor.EclipseStarter.run",
          "source": "EclipseStarter.java:129"
        },
        {
          "method": "sun.reflect.NativeMethodAccessorImpl.invoke0",
          "source": "Native Method"
        },
        {
          "method": "sun.reflect.NativeMethodAccessorImpl.invoke",
          "source": "NativeMethodAccessorImpl.java:39"
        },
        {
          "method": "sun.reflect.DelegatingMethodAccessorImpl.invoke",
          "source": "DelegatingMethodAccessorImpl.java:25"
        },
        {
          "method": "java.lang.reflect.Method.invoke",
          "source": "Method.java:324"
        },
        {
          "method": "org.eclipse.core.launcher.Main.basicRun",
          "source": "Main.java:185"
        },
        {
          "method": "org.eclipse.core.launcher.Main.run",
          "source": "Main.java:704"
        },
        {
          "method": "org.eclipse.core.launcher.Main.main",
          "source": "Main.java:688"
        }
      ],
      "number": 0,
      "commentIndex": 0,
      "bugId": "80921",
      "date": "2004-12-14T11:50:52+01:00",
      "product": "PDE",
      "component": "Build",
      "severity": "critical"
    }
  ],
  "groupId": "80921",
  "bugId": "80921",
  "date": "2004-12-14T11:50:52+01:00",
  "product": "PDE",
  "component": "Build",
  "severity": "critical"
}