{
  "comments": [
    "Using 200412140800, I got the following exception:\n\njava.lang.NullPointerException\n\tat\norg.eclipse.jdt.internal.codeassist.SelectionEngine.selectFrom(SelectionEngine.java:795)\n\tat\norg.eclipse.jdt.internal.codeassist.SelectionEngine.select(SelectionEngine.java:714)\n\tat org.eclipse.jdt.internal.core.Openable.codeSelect(Openable.java:140)\n\tat\norg.eclipse.jdt.internal.core.CompilationUnit.codeSelect(CompilationUnit.java:300)\n\tat\norg.eclipse.jdt.internal.core.CompilationUnit.codeSelect(CompilationUnit.java:294)\n\tat\norg.eclipse.jdt.internal.ui.javaeditor.JavaElementHyperlinkDetector.detectHyperlinks(JavaElementHyperlinkDetector.java:73)\n\tat\norg.eclipse.jface.text.hyperlink.HyperlinkManager.findHyperlinks(HyperlinkManager.java:235)\n\tat\norg.eclipse.jface.text.hyperlink.HyperlinkManager.mouseMove(HyperlinkManager.java:422)\n\tat org.eclipse.swt.widgets.TypedListener.handleEvent(TypedListener.java:144)\n\tat org.eclipse.swt.widgets.EventTable.sendEvent(EventTable.java:82)\n\tat org.eclipse.swt.widgets.Widget.sendEvent(Widget.java:833)\n\tat org.eclipse.swt.widgets.Display.runDeferredEvents(Display.java:2803)\n\tat org.eclipse.swt.widgets.Display.readAndDispatch(Display.java:2448)\n\tat org.eclipse.ui.internal.Workbench.runEventLoop(Workbench.java:1569)\n\tat org.eclipse.ui.internal.Workbench.runUI(Workbench.java:1540)\n\tat org.eclipse.ui.internal.Workbench.createAndRunWorkbench(Workbench.java:285)\n\tat org.eclipse.ui.PlatformUI.createAndRunWorkbench(PlatformUI.java:144)\n\tat org.eclipse.ui.internal.ide.IDEApplication.run(IDEApplication.java:102)\n\tat\norg.eclipse.core.internal.runtime.PlatformActivator$1.run(PlatformActivator.java:220)\n\tat org.eclipse.core.runtime.adaptor.EclipseStarter.run(EclipseStarter.java:273)\n\tat org.eclipse.core.runtime.adaptor.EclipseStarter.run(EclipseStarter.java:129)\n\tat sun.reflect.NativeMethodAccessorImpl.invoke0(Native Method)\n\tat sun.reflect.NativeMethodAccessorImpl.invoke(NativeMethodAccessorImpl.java:85)\n\tat sun.reflect.NativeMethodAccessorImpl.invoke(NativeMethodAccessorImpl.java:58)\n\tat\nsun.reflect.DelegatingMethodAccessorImpl.invoke(DelegatingMethodAccessorImpl.java:60)\n\tat java.lang.reflect.Method.invoke(Method.java:391)\n\tat org.eclipse.core.launcher.Main.basicRun(Main.java:185)\n\tat org.eclipse.core.launcher.Main.run(Main.java:684)\n\tat org.eclipse.core.launcher.Main.main(Main.java:668)\n\n\nSteps to reproduce:\n\n1) Create a new Java project\n2) Set the compiler compliance to 1.5\n3) Create a new compilation unit that contains:\npublic class ShortcutIfElse {\n\n    public ShortcutIfElse() { }\n\t\n    public Integer[] getTypes() {\n        List\u003cInteger\u003e list \u003d new ArrayList\u003cInteger\u003e();\n        return list \u003d\u003d null \n            ? new Integer[0] \n            : list.toArray(new Integer[list.size()]);\n    }\n\n    public static void main(String[] args) {\n        Class clazz \u003d null;\n        try {\n            clazz \u003d Class.forName(\"ShortcutIfElse\");\n        } catch (Throwable e) {\n            e.printStackTrace();\n        }\n    }\n}\nArrayList and List are reported as errors.\n3) Code assist behind ArrayList to add a import.\n4) Do the same for List and you should get the NPE.",
    "Null check added.\nFixed and released in HEAD.\nRegression test added in org.eclipse.jdt.core.tests.model.ResolveTests_1_5.test0086",
    "Reopen to assign",
    "Null check added.\nFixed and released in HEAD.\nRegression test added in org.eclipse.jdt.core.tests.model.ResolveTests_1_5.test0086",
    "Verified in 200412141600"
  ],
  "commentCreationDates": [
    "2004-12-14T17:40:01+01:00",
    "2004-12-14T19:15:44+01:00",
    "2004-12-14T19:16:08+01:00",
    "2004-12-14T19:17:00+01:00",
    "2004-12-15T04:30:12+01:00"
  ],
  "traces": [
    {
      "exceptionType": "java.lang.NullPointerException",
      "elements": [
        {
          "method": "org.eclipse.jdt.internal.codeassist.SelectionEngine.selectFrom",
          "source": "SelectionEngine.java:795"
        },
        {
          "method": "org.eclipse.jdt.internal.codeassist.SelectionEngine.select",
          "source": "SelectionEngine.java:714"
        },
        {
          "method": "org.eclipse.jdt.internal.core.Openable.codeSelect",
          "source": "Openable.java:140"
        },
        {
          "method": "org.eclipse.jdt.internal.core.CompilationUnit.codeSelect",
          "source": "CompilationUnit.java:300"
        },
        {
          "method": "org.eclipse.jdt.internal.core.CompilationUnit.codeSelect",
          "source": "CompilationUnit.java:294"
        },
        {
          "method": "org.eclipse.jdt.internal.ui.javaeditor.JavaElementHyperlinkDetector.detectHyperlinks",
          "source": "JavaElementHyperlinkDetector.java:73"
        },
        {
          "method": "org.eclipse.jface.text.hyperlink.HyperlinkManager.findHyperlinks",
          "source": "HyperlinkManager.java:235"
        },
        {
          "method": "org.eclipse.jface.text.hyperlink.HyperlinkManager.mouseMove",
          "source": "HyperlinkManager.java:422"
        },
        {
          "method": "org.eclipse.swt.widgets.TypedListener.handleEvent",
          "source": "TypedListener.java:144"
        },
        {
          "method": "org.eclipse.swt.widgets.EventTable.sendEvent",
          "source": "EventTable.java:82"
        },
        {
          "method": "org.eclipse.swt.widgets.Widget.sendEvent",
          "source": "Widget.java:833"
        },
        {
          "method": "org.eclipse.swt.widgets.Display.runDeferredEvents",
          "source": "Display.java:2803"
        },
        {
          "method": "org.eclipse.swt.widgets.Display.readAndDispatch",
          "source": "Display.java:2448"
        },
        {
          "method": "org.eclipse.ui.internal.Workbench.runEventLoop",
          "source": "Workbench.java:1569"
        },
        {
          "method": "org.eclipse.ui.internal.Workbench.runUI",
          "source": "Workbench.java:1540"
        },
        {
          "method": "org.eclipse.ui.internal.Workbench.createAndRunWorkbench",
          "source": "Workbench.java:285"
        },
        {
          "method": "org.eclipse.ui.PlatformUI.createAndRunWorkbench",
          "source": "PlatformUI.java:144"
        },
        {
          "method": "org.eclipse.ui.internal.ide.IDEApplication.run",
          "source": "IDEApplication.java:102"
        },
        {
          "method": "org.eclipse.core.internal.runtime.PlatformActivator$1.run",
          "source": "PlatformActivator.java:220"
        },
        {
          "method": "org.eclipse.core.runtime.adaptor.EclipseStarter.run",
          "source": "EclipseStarter.java:273"
        },
        {
          "method": "org.eclipse.core.runtime.adaptor.EclipseStarter.run",
          "source": "EclipseStarter.java:129"
        },
        {
          "method": "sun.reflect.NativeMethodAccessorImpl.invoke0",
          "source": "Native Method"
        },
        {
          "method": "sun.reflect.NativeMethodAccessorImpl.invoke",
          "source": "NativeMethodAccessorImpl.java:85"
        },
        {
          "method": "sun.reflect.NativeMethodAccessorImpl.invoke",
          "source": "NativeMethodAccessorImpl.java:58"
        },
        {
          "method": "sun.reflect.DelegatingMethodAccessorImpl.invoke",
          "source": "DelegatingMethodAccessorImpl.java:60"
        },
        {
          "method": "java.lang.reflect.Method.invoke",
          "source": "Method.java:391"
        },
        {
          "method": "org.eclipse.core.launcher.Main.basicRun",
          "source": "Main.java:185"
        },
        {
          "method": "org.eclipse.core.launcher.Main.run",
          "source": "Main.java:684"
        },
        {
          "method": "org.eclipse.core.launcher.Main.main",
          "source": "Main.java:668"
        }
      ],
      "number": 0,
      "commentIndex": 0,
      "bugId": "80957",
      "date": "2004-12-14T17:40:01+01:00",
      "product": "JDT",
      "component": "Core",
      "severity": "normal"
    }
  ],
  "groupId": "80957",
  "bugId": "80957",
  "date": "2004-12-14T17:40:01+01:00",
  "product": "JDT",
  "component": "Core",
  "severity": "normal"
}