{
  "comments": [
    "Not sure if this was reproducable but I:\n\n- changed some of my project-specific compiler preferences\n- it prompted me for a rebuild\n- I waited a bit but then hit Cancel on the pref page\n- I got the \"job blocked\" dialog and cancelled the auto-build job\n- noticed this in my log file\n\nosgi\u003e !SESSION 2004-12-15 14:29:45.461\n-----------------------------------------------\neclipse.buildId\u003dI20041214-2000\njava.fullversion\u003dJ2RE 1.4.2 IBM J9 2.2 Windows XP x86-32 j9n142-20040915 (JIT\nenabled)\nJ9VM - 20040914_1123_lHdSMR\nJIT  - r7_level20040912_1800\nBootLoader constants: OS\u003dwin32, ARCH\u003dx86, WS\u003dwin32, NL\u003den_CA\nFramework arguments:  -showlocation\nCommand-line arguments:  -os win32 -ws win32 -arch x86 -data\n\\eclipse\\target\\head\\plugins\\ -showlocation -consoleLog -console\n\n!ENTRY org.eclipse.core.runtime 4 0 2004-12-15 14:29:45.461\n!MESSAGE org.eclipse.swt.SWTException: Widget is disposed\n!STACK 0\norg.eclipse.swt.SWTException: Widget is disposed\n        at org.eclipse.swt.SWT.error(Unknown Source)\n        at org.eclipse.swt.SWT.error(Unknown Source)\n        at org.eclipse.swt.SWT.error(Unknown Source)\n        at org.eclipse.swt.widgets.Widget.error(Unknown Source)\n        at org.eclipse.swt.widgets.Widget.getDisplay(Unknown Source)\n        at org.eclipse.jface.dialogs.IconAndMessageDialog.getSWTImage(Unknown\nSource)\n        at\norg.eclipse.jface.dialogs.IconAndMessageDialog.getQuestionImage(Unknown Source)\n        at org.eclipse.jface.dialogs.MessageDialog.\u003cinit\u003e(Unknown Source)\n        at\norg.eclipse.jdt.internal.ui.preferences.OptionsConfigurationBlock.performOk(Unknown\nSource)\n        at\norg.eclipse.jdt.internal.ui.preferences.ProblemSeveritiesPreferencePage.performOk(Unknown\nSource)\n        at org.eclipse.jface.preference.PreferenceDialog$12.run(Unknown Source)\n        at org.eclipse.core.internal.runtime.InternalPlatform.run(Unknown Source)\n        at org.eclipse.core.runtime.Platform.run(Unknown Source)\n        at org.eclipse.jface.preference.PreferenceDialog.okPressed(Unknown Source)\n        at org.eclipse.jface.preference.PreferenceDialog.buttonPressed(Unknown\nSource)\n        at org.eclipse.jface.dialogs.Dialog$2.widgetSelected(Unknown Source)\n        at org.eclipse.swt.widgets.TypedListener.handleEvent(Unknown Source)\n        at org.eclipse.swt.widgets.EventTable.sendEvent(Unknown Source)\n        at org.eclipse.swt.widgets.Widget.sendEvent(Unknown Source)\n        at org.eclipse.swt.widgets.Display.runDeferredEvents(Unknown Source)\n        at org.eclipse.swt.widgets.Display.readAndDispatch(Unknown Source)\n        at org.eclipse.jface.window.Window.runEventLoop(Unknown Source)\n        at org.eclipse.jface.window.Window.open(Unknown Source)\n        at org.eclipse.ui.dialogs.PropertyDialogAction.run(Unknown Source)\n        at org.eclipse.jface.action.Action.runWithEvent(Unknown Source)\n        at\norg.eclipse.jface.action.ActionContributionItem.handleWidgetSelection(Unknown\nSource)\n        at org.eclipse.jface.action.ActionContributionItem.access$2(Unknown Source)\n        at org.eclipse.jface.action.ActionContributionItem$6.handleEvent(Unknown\nSource)\n        at org.eclipse.swt.widgets.EventTable.sendEvent(Unknown Source)\n        at org.eclipse.swt.widgets.Widget.sendEvent(Unknown Source)\n        at org.eclipse.swt.widgets.Display.runDeferredEvents(Unknown Source)\n        at org.eclipse.swt.widgets.Display.readAndDispatch(Unknown Source)\n        at org.eclipse.ui.internal.Workbench.runEventLoop(Unknown Source)\n        at org.eclipse.ui.internal.Workbench.runUI(Unknown Source)\n        at org.eclipse.ui.internal.Workbench.createAndRunWorkbench(Unknown Source)\n        at org.eclipse.ui.PlatformUI.createAndRunWorkbench(Unknown Source)\n        at org.eclipse.ui.internal.ide.IDEApplication.run(Unknown Source)\n        at org.eclipse.core.internal.runtime.PlatformActivator$1.run(Unknown Source)\n        at\norg.eclipse.core.runtime.adaptor.EclipseStarter.run(EclipseStarter.java:273)\n        at\norg.eclipse.core.runtime.adaptor.EclipseStarter.run(EclipseStarter.java:129)\n        at sun.reflect.NativeMethodAccessorImpl.invoke0(Native Method)\n        at\nsun.reflect.NativeMethodAccessorImpl.invoke(NativeMethodAccessorImpl.java:85)\n        at\nsun.reflect.NativeMethodAccessorImpl.invoke(NativeMethodAccessorImpl.java:58)\n        at\nsun.reflect.DelegatingMethodAccessorImpl.invoke(DelegatingMethodAccessorImpl.java:60)\n        at java.lang.reflect.Method.invoke(Method.java:391)\n        at org.eclipse.core.launcher.Main.basicRun(Main.java:185)\n        at org.eclipse.core.launcher.Main.run(Main.java:684)\n        at org.eclipse.core.launcher.Main.main(Main.java:668)",
    "Martin, can you please investigate and judge if critical for M4.",
    "not for M4",
    "could not reproduce anymore in 20050324"
  ],
  "commentCreationDates": [
    "2004-12-15T19:35:33+01:00",
    "2004-12-15T21:37:11+01:00",
    "2004-12-16T10:26:51+01:00",
    "2005-03-24T17:32:13+01:00"
  ],
  "traces": [
    {
      "exceptionType": "org.eclipse.swt.SWTException",
      "message": "Widget is disposed",
      "elements": [
        {
          "method": "org.eclipse.swt.SWT.error",
          "source": "Unknown Source"
        },
        {
          "method": "org.eclipse.swt.SWT.error",
          "source": "Unknown Source"
        },
        {
          "method": "org.eclipse.swt.SWT.error",
          "source": "Unknown Source"
        },
        {
          "method": "org.eclipse.swt.widgets.Widget.error",
          "source": "Unknown Source"
        },
        {
          "method": "org.eclipse.swt.widgets.Widget.getDisplay",
          "source": "Unknown Source"
        },
        {
          "method": "org.eclipse.jface.dialogs.IconAndMessageDialog.getSWTImage",
          "source": "Unknown Source"
        },
        {
          "method": "org.eclipse.jface.dialogs.IconAndMessageDialog.getQuestionImage",
          "source": "Unknown Source"
        },
        {
          "method": "org.eclipse.jface.dialogs.MessageDialog.\u003cinit\u003e",
          "source": "Unknown Source"
        },
        {
          "method": "org.eclipse.jdt.internal.ui.preferences.OptionsConfigurationBlock.performOk",
          "source": "Unknown Source"
        },
        {
          "method": "org.eclipse.jdt.internal.ui.preferences.ProblemSeveritiesPreferencePage.performOk",
          "source": "Unknown Source"
        },
        {
          "method": "org.eclipse.jface.preference.PreferenceDialog$12.run",
          "source": "Unknown Source"
        },
        {
          "method": "org.eclipse.core.internal.runtime.InternalPlatform.run",
          "source": "Unknown Source"
        },
        {
          "method": "org.eclipse.core.runtime.Platform.run",
          "source": "Unknown Source"
        },
        {
          "method": "org.eclipse.jface.preference.PreferenceDialog.okPressed",
          "source": "Unknown Source"
        },
        {
          "method": "org.eclipse.jface.preference.PreferenceDialog.buttonPressed",
          "source": "Unknown Source"
        },
        {
          "method": "org.eclipse.jface.dialogs.Dialog$2.widgetSelected",
          "source": "Unknown Source"
        },
        {
          "method": "org.eclipse.swt.widgets.TypedListener.handleEvent",
          "source": "Unknown Source"
        },
        {
          "method": "org.eclipse.swt.widgets.EventTable.sendEvent",
          "source": "Unknown Source"
        },
        {
          "method": "org.eclipse.swt.widgets.Widget.sendEvent",
          "source": "Unknown Source"
        },
        {
          "method": "org.eclipse.swt.widgets.Display.runDeferredEvents",
          "source": "Unknown Source"
        },
        {
          "method": "org.eclipse.swt.widgets.Display.readAndDispatch",
          "source": "Unknown Source"
        },
        {
          "method": "org.eclipse.jface.window.Window.runEventLoop",
          "source": "Unknown Source"
        },
        {
          "method": "org.eclipse.jface.window.Window.open",
          "source": "Unknown Source"
        },
        {
          "method": "org.eclipse.ui.dialogs.PropertyDialogAction.run",
          "source": "Unknown Source"
        },
        {
          "method": "org.eclipse.jface.action.Action.runWithEvent",
          "source": "Unknown Source"
        },
        {
          "method": "org.eclipse.jface.action.ActionContributionItem.handleWidgetSelection",
          "source": "Unknown Source"
        },
        {
          "method": "org.eclipse.jface.action.ActionContributionItem.access$2",
          "source": "Unknown Source"
        },
        {
          "method": "org.eclipse.jface.action.ActionContributionItem$6.handleEvent",
          "source": "Unknown Source"
        },
        {
          "method": "org.eclipse.swt.widgets.EventTable.sendEvent",
          "source": "Unknown Source"
        },
        {
          "method": "org.eclipse.swt.widgets.Widget.sendEvent",
          "source": "Unknown Source"
        },
        {
          "method": "org.eclipse.swt.widgets.Display.runDeferredEvents",
          "source": "Unknown Source"
        },
        {
          "method": "org.eclipse.swt.widgets.Display.readAndDispatch",
          "source": "Unknown Source"
        },
        {
          "method": "org.eclipse.ui.internal.Workbench.runEventLoop",
          "source": "Unknown Source"
        },
        {
          "method": "org.eclipse.ui.internal.Workbench.runUI",
          "source": "Unknown Source"
        },
        {
          "method": "org.eclipse.ui.internal.Workbench.createAndRunWorkbench",
          "source": "Unknown Source"
        },
        {
          "method": "org.eclipse.ui.PlatformUI.createAndRunWorkbench",
          "source": "Unknown Source"
        },
        {
          "method": "org.eclipse.ui.internal.ide.IDEApplication.run",
          "source": "Unknown Source"
        },
        {
          "method": "org.eclipse.core.internal.runtime.PlatformActivator$1.run",
          "source": "Unknown Source"
        },
        {
          "method": "org.eclipse.core.runtime.adaptor.EclipseStarter.run",
          "source": "EclipseStarter.java:273"
        },
        {
          "method": "org.eclipse.core.runtime.adaptor.EclipseStarter.run",
          "source": "EclipseStarter.java:129"
        },
        {
          "method": "sun.reflect.NativeMethodAccessorImpl.invoke0",
          "source": "Native Method"
        },
        {
          "method": "sun.reflect.NativeMethodAccessorImpl.invoke",
          "source": "NativeMethodAccessorImpl.java:85"
        },
        {
          "method": "sun.reflect.NativeMethodAccessorImpl.invoke",
          "source": "NativeMethodAccessorImpl.java:58"
        },
        {
          "method": "sun.reflect.DelegatingMethodAccessorImpl.invoke",
          "source": "DelegatingMethodAccessorImpl.java:60"
        },
        {
          "method": "java.lang.reflect.Method.invoke",
          "source": "Method.java:391"
        },
        {
          "method": "org.eclipse.core.launcher.Main.basicRun",
          "source": "Main.java:185"
        },
        {
          "method": "org.eclipse.core.launcher.Main.run",
          "source": "Main.java:684"
        },
        {
          "method": "org.eclipse.core.launcher.Main.main",
          "source": "Main.java:668"
        }
      ],
      "number": 0,
      "commentIndex": 0,
      "bugId": "81291",
      "date": "2004-12-15T19:35:33+01:00",
      "product": "JDT",
      "component": "UI",
      "severity": "normal"
    }
  ],
  "groupId": "81291",
  "bugId": "81291",
  "date": "2004-12-15T19:35:33+01:00",
  "product": "JDT",
  "component": "UI",
  "severity": "normal"
}