{
  "comments": [
    "Hi,\n\nI use Eclipse 3.1M3 and CDT RC7 on WinXP SP1 , 3.0Gz,\n512MB ram\n\nOne of my project  gives an error when i open it and\nrebuild it.\n\nBinary Search Thread\n\nAn error occured while traversing resource.\n\nI tried to choose different binary parsers but nothing\nchanged. In my \nother projects, PE Windows Binary Parser is selected\nand everythings are ok.\n\nThe difference of that project is linking with wsock32\nlibrary.\n\n\nHere is the log file :\n\n!ENTRY org.eclipse.core.resources 4 566 2004-12-16\n13:49:30.671\n!MESSAGE An error occurred while traversing resources.\n!STACK 0\njava.lang.ArrayIndexOutOfBoundsException: -1694695938\n    at\norg.eclipse.cdt.utils.coff.PE.getAttribute(PE.java:493)\n    at \norg.eclipse.cdt.utils.coff.parser.PEParser.getBinary(PEParser.java:50)\n    at \norg.eclipse.cdt.internal.core.model.CModelManager.createBinaryFile(CModelManager.java:577)\n    at \norg.eclipse.cdt.internal.core.model.BinaryRunner.addChildIfBinary(BinaryRunner.java:116)\n    at \norg.eclipse.cdt.internal.core.model.BinaryRunner$Visitor.visit(BinaryRunner.java:141)\n    at \norg.eclipse.core.internal.resources.Resource$2.visit(Resource.java:108)\n    at \norg.eclipse.core.internal.resources.Resource$1.visitElement(Resource.java:55)\n    at \norg.eclipse.core.internal.watson.ElementTreeIterator.doIteration(ElementTreeIterator.java:81)\n    at \norg.eclipse.core.internal.watson.ElementTreeIterator.doIteration(ElementTreeIterator.java:85)\n    at \norg.eclipse.core.internal.watson.ElementTreeIterator.doIteration(ElementTreeIterator.java:85)\n    at \norg.eclipse.core.internal.watson.ElementTreeIterator.doIteration(ElementTreeIterator.java:85)\n    at \norg.eclipse.core.internal.watson.ElementTreeIterator.doIteration(ElementTreeIterator.java:85)\n    at \norg.eclipse.core.internal.watson.ElementTreeIterator.iterate(ElementTreeIterator.java:126)\n    at\norg.eclipse.core.internal.resources.Resource.accept(Resource.java:65)\n    at \norg.eclipse.core.internal.resources.Resource.accept(Resource.java:110)\n    at\norg.eclipse.core.internal.resources.Resource.accept(Resource.java:85)\n    at \norg.eclipse.cdt.internal.core.model.BinaryRunner$1.run(BinaryRunner.java:59)\n    at\norg.eclipse.core.internal.jobs.Worker.run(Worker.java:66)\n\n\nCC Vural",
    "Compiler is cygwin gcc 3.3.3",
    "Created an attachment (id\u003d16749)\nCDT has problem with this EXE file\n"
  ],
  "commentCreationDates": [
    "2004-12-16T13:30:12+01:00",
    "2004-12-16T13:31:22+01:00",
    "2004-12-18T10:03:37+01:00"
  ],
  "traces": [
    {
      "exceptionType": "java.lang.ArrayIndexOutOfBoundsException",
      "message": "-1694695938",
      "elements": [
        {
          "method": "org.eclipse.cdt.utils.coff.PE.getAttribute",
          "source": "PE.java:493"
        },
        {
          "method": "org.eclipse.cdt.utils.coff.parser.PEParser.getBinary",
          "source": "PEParser.java:50"
        },
        {
          "method": "org.eclipse.cdt.internal.core.model.CModelManager.createBinaryFile",
          "source": "CModelManager.java:577"
        },
        {
          "method": "org.eclipse.cdt.internal.core.model.BinaryRunner.addChildIfBinary",
          "source": "BinaryRunner.java:116"
        },
        {
          "method": "org.eclipse.cdt.internal.core.model.BinaryRunner$Visitor.visit",
          "source": "BinaryRunner.java:141"
        },
        {
          "method": "org.eclipse.core.internal.resources.Resource$2.visit",
          "source": "Resource.java:108"
        },
        {
          "method": "org.eclipse.core.internal.resources.Resource$1.visitElement",
          "source": "Resource.java:55"
        },
        {
          "method": "org.eclipse.core.internal.watson.ElementTreeIterator.doIteration",
          "source": "ElementTreeIterator.java:81"
        },
        {
          "method": "org.eclipse.core.internal.watson.ElementTreeIterator.doIteration",
          "source": "ElementTreeIterator.java:85"
        },
        {
          "method": "org.eclipse.core.internal.watson.ElementTreeIterator.doIteration",
          "source": "ElementTreeIterator.java:85"
        },
        {
          "method": "org.eclipse.core.internal.watson.ElementTreeIterator.doIteration",
          "source": "ElementTreeIterator.java:85"
        },
        {
          "method": "org.eclipse.core.internal.watson.ElementTreeIterator.doIteration",
          "source": "ElementTreeIterator.java:85"
        },
        {
          "method": "org.eclipse.core.internal.watson.ElementTreeIterator.iterate",
          "source": "ElementTreeIterator.java:126"
        },
        {
          "method": "org.eclipse.core.internal.resources.Resource.accept",
          "source": "Resource.java:65"
        },
        {
          "method": "org.eclipse.core.internal.resources.Resource.accept",
          "source": "Resource.java:110"
        },
        {
          "method": "org.eclipse.core.internal.resources.Resource.accept",
          "source": "Resource.java:85"
        },
        {
          "method": "org.eclipse.cdt.internal.core.model.BinaryRunner$1.run",
          "source": "BinaryRunner.java:59"
        },
        {
          "method": "org.eclipse.core.internal.jobs.Worker.run",
          "source": "Worker.java:66"
        }
      ],
      "number": 0,
      "commentIndex": 0,
      "bugId": "81388",
      "date": "2004-12-16T13:30:12+01:00",
      "product": "CDT",
      "component": "cdt-build",
      "severity": "normal"
    }
  ],
  "groupId": "81388",
  "bugId": "81388",
  "date": "2004-12-16T13:30:12+01:00",
  "product": "CDT",
  "component": "cdt-build",
  "severity": "normal"
}