{
  "comments": [
    "Found in log testing 10/17 version. Actually ... I was wondering why I could \nsee this in PDE Schema validation messages (after loading released projects)\n.... I suggest you turn that checking on my default. \n\nI\u0027m putting as \"major P2\" since this is one of the exit criteria, though, \nfrankly, I don\u0027t know what function is lost, so if no function lost, you might\nargue the severity and priority is not so high (but still ... a \"clean\" import\nwas one of the exit criteria every one\u0027s looking at). \n\n!MESSAGE Plug-in org.eclipse.jst.j2ee.ejb was unable to load class\norg.eclipse.jst.j2ee.internal.ejb.deployables.EJBDeployableObjectAdapter.\n!STACK 0\njava.lang.ClassNotFoundException:\norg.eclipse.jst.j2ee.internal.ejb.deployables.EJBDeployableObjectAdapter\n        at\norg.eclipse.osgi.framework.internal.core.BundleLoader.findClass(BundleLoader.java:404)\n        at\norg.eclipse.osgi.framework.adaptor.core.AbstractClassLoader.loadClass(AbstractClassLoader.java:93)\n        at java.lang.ClassLoader.loadClass(ClassLoader.java:560)\n        at\norg.eclipse.osgi.framework.internal.core.BundleLoader.loadClass(BundleLoader.java:307)\n        at\norg.eclipse.osgi.framework.internal.core.BundleHost.loadClass(BundleHost.java:332)\n        at\norg.eclipse.osgi.framework.internal.core.AbstractBundle.loadClass(AbstractBundle.java:1315)\n        at\norg.eclipse.core.internal.registry.ConfigurationElement.createExecutableExtension(ConfigurationElement.java:161)\n        at\norg.eclipse.core.internal.registry.ConfigurationElement.createExecutableExtension(ConfigurationElement.java:151)\n        at\norg.eclipse.core.internal.registry.ConfigurationElement.createExecutableExtension(ConfigurationElement.java:138)\n        at\norg.eclipse.core.internal.registry.ConfigurationElementHandle.createExecutableExtension(ConfigurationElementHandle.java:48)\n        at\norg.eclipse.wst.server.core.internal.ModuleArtifactAdapter.getDelegate(ModuleArtifactAdapter.java:69)\n        at\norg.eclipse.wst.server.core.internal.ModuleArtifactAdapter.getModuleObject(ModuleArtifactAdapter.java:82)\n        at\norg.eclipse.wst.server.core.ServerUtil.getModuleObjects(ServerUtil.java:258)\n        at\norg.eclipse.wst.server.ui.internal.actions.RunOnServerActionDelegate.run(RunOnServerActionDelegate.java:136)\n        at\norg.eclipse.wst.server.ui.internal.actions.RunOnServerActionDelegate.run(RunOnServerActionDelegate.java:461)\n        at\norg.eclipse.wst.server.ui.internal.ServerLaunchShortcut.launch(ServerLaunchShortcut.java:42)\n        at\norg.eclipse.debug.internal.ui.launchConfigurations.LaunchShortcutExtension.launch(LaunchShortcutExtension.java:395)\n        at\norg.eclipse.debug.internal.ui.actions.LaunchShortcutAction.run(LaunchShortcutAction.java:62)\n        at org.eclipse.jface.action.Action.runWithEvent(Action.java:989)\n        at\norg.eclipse.jface.action.ActionContributionItem.handleWidgetSelection(ActionContributionItem.java:555)\n        at\norg.eclipse.jface.action.ActionContributionItem.access$2(ActionContributionItem.java:505)\n        at\norg.eclipse.jface.action.ActionContributionItem$6.handleEvent(ActionContributionItem.java:419)\n        at org.eclipse.swt.widgets.EventTable.sendEvent(EventTable.java:82)",
    "Found this exception when trying \u0027Run On Server\u0027 action for some web resource \n(as a stacktrace suggests too). Action is not working.\n\nTested with \u0027I20041218\u0027.",
    "This is a duplicate of 80002\n\n*** This bug has been marked as a duplicate of 80002 ***",
    "closed"
  ],
  "commentCreationDates": [
    "2004-12-18T02:05:50+01:00",
    "2004-12-19T05:12:10+01:00",
    "2004-12-20T14:23:26+01:00",
    "2005-04-09T22:45:13+02:00"
  ],
  "traces": [
    {
      "exceptionType": "java.lang.ClassNotFoundException",
      "message": "org.eclipse.jst.j2ee.internal.ejb.deployables.EJBDeployableObjectAdapter",
      "elements": [
        {
          "method": "org.eclipse.osgi.framework.internal.core.BundleLoader.findClass",
          "source": "BundleLoader.java:404"
        },
        {
          "method": "org.eclipse.osgi.framework.adaptor.core.AbstractClassLoader.loadClass",
          "source": "AbstractClassLoader.java:93"
        },
        {
          "method": "java.lang.ClassLoader.loadClass",
          "source": "ClassLoader.java:560"
        },
        {
          "method": "org.eclipse.osgi.framework.internal.core.BundleLoader.loadClass",
          "source": "BundleLoader.java:307"
        },
        {
          "method": "org.eclipse.osgi.framework.internal.core.BundleHost.loadClass",
          "source": "BundleHost.java:332"
        },
        {
          "method": "org.eclipse.osgi.framework.internal.core.AbstractBundle.loadClass",
          "source": "AbstractBundle.java:1315"
        },
        {
          "method": "org.eclipse.core.internal.registry.ConfigurationElement.createExecutableExtension",
          "source": "ConfigurationElement.java:161"
        },
        {
          "method": "org.eclipse.core.internal.registry.ConfigurationElement.createExecutableExtension",
          "source": "ConfigurationElement.java:151"
        },
        {
          "method": "org.eclipse.core.internal.registry.ConfigurationElement.createExecutableExtension",
          "source": "ConfigurationElement.java:138"
        },
        {
          "method": "org.eclipse.core.internal.registry.ConfigurationElementHandle.createExecutableExtension",
          "source": "ConfigurationElementHandle.java:48"
        },
        {
          "method": "org.eclipse.wst.server.core.internal.ModuleArtifactAdapter.getDelegate",
          "source": "ModuleArtifactAdapter.java:69"
        },
        {
          "method": "org.eclipse.wst.server.core.internal.ModuleArtifactAdapter.getModuleObject",
          "source": "ModuleArtifactAdapter.java:82"
        },
        {
          "method": "org.eclipse.wst.server.core.ServerUtil.getModuleObjects",
          "source": "ServerUtil.java:258"
        },
        {
          "method": "org.eclipse.wst.server.ui.internal.actions.RunOnServerActionDelegate.run",
          "source": "RunOnServerActionDelegate.java:136"
        },
        {
          "method": "org.eclipse.wst.server.ui.internal.actions.RunOnServerActionDelegate.run",
          "source": "RunOnServerActionDelegate.java:461"
        },
        {
          "method": "org.eclipse.wst.server.ui.internal.ServerLaunchShortcut.launch",
          "source": "ServerLaunchShortcut.java:42"
        },
        {
          "method": "org.eclipse.debug.internal.ui.launchConfigurations.LaunchShortcutExtension.launch",
          "source": "LaunchShortcutExtension.java:395"
        },
        {
          "method": "org.eclipse.debug.internal.ui.actions.LaunchShortcutAction.run",
          "source": "LaunchShortcutAction.java:62"
        },
        {
          "method": "org.eclipse.jface.action.Action.runWithEvent",
          "source": "Action.java:989"
        },
        {
          "method": "org.eclipse.jface.action.ActionContributionItem.handleWidgetSelection",
          "source": "ActionContributionItem.java:555"
        },
        {
          "method": "org.eclipse.jface.action.ActionContributionItem.access$2",
          "source": "ActionContributionItem.java:505"
        },
        {
          "method": "org.eclipse.jface.action.ActionContributionItem$6.handleEvent",
          "source": "ActionContributionItem.java:419"
        },
        {
          "method": "org.eclipse.swt.widgets.EventTable.sendEvent",
          "source": "EventTable.java:82"
        }
      ],
      "number": 0,
      "commentIndex": 0,
      "bugId": "81578",
      "duplicateId": "80002",
      "date": "2004-12-18T02:05:50+01:00",
      "product": "Web Tools",
      "component": "jst.ejb",
      "severity": "major"
    }
  ],
  "groupId": "80002",
  "bugId": "81578",
  "duplicateId": "80002",
  "date": "2004-12-18T02:05:50+01:00",
  "product": "Web Tools",
  "component": "jst.ejb",
  "severity": "major"
}