{
  "comments": [
    "notes:\n    \u003cNote by yanlingz (Zhang, Yan Ling *CONTRACTOR*), 2004/11/10 06:13:52, seq:\n1 rel: 0  action: open\u003e\nhere is the code snippet:\nBOXMLSerializer boXMLSerializer \u003d (BOXMLSerializer)\nlocateService(SERVICE_BOXMLSERIALIZER);\nDataObject employee \u003d\nhelper.create(typeService.getType(\"http://www.scm.com/EmployeeTypes\",\"Employee\"));\nemployee.setDate(\"hiredate\",new Date());\n\n              try {\n                     ByteArrayOutputStream bos \u003d new ByteArrayOutputStream();\n                     boXMLSerializer.saveDataObject(employee,bos);\n                     String content \u003d new String(bos.toByteArray());\n                     System.out.println(content);\n                     ByteArrayInputStream bis \u003d new\nByteArrayInputStream(bos.toByteArray());                     \n                     DataObject retrievedDO \u003d boXMLSerializer.loadDataObject(bis);\n                     bis.close();\n                     bos.close();\n                     return retrievedDO;\n              } catch (Exception e) {\n                     e.printStackTrace();\n              } \n\nSure, we defined hiredate as \"xs:date\" type, when we run this with driver,\nexception is thrown. \nThe outputs is followed:\n\n\u003c?xml version\u003d\"1.0\" encoding\u003d\"ASCII\"?\u003e\n\u003ctypes:Employee xmlns:types\u003d\"http://www.scm.com/EmployeeTypes\"\u003e\n  \u003ctypes:hiredate\u003eWed Nov 10 20:10:19 CST 2004\u003c/types:hiredate\u003e\n\u003c/types:Employee\u003e\n\norg.eclipse.emf.ecore.xml.type.InvalidDatatypeValueException: Year separator is\nmissing or misplaced\n       at\norg.eclipse.emf.ecore.xml.type.internal.XMLCalendar.getYearMonth(XMLCalendar.java:440)\n       at\norg.eclipse.emf.ecore.xml.type.internal.XMLCalendar.getDate(XMLCalendar.java:410)\n       at\norg.eclipse.emf.ecore.xml.type.internal.XMLCalendar.parseDate(XMLCalendar.java:1042)\n       at\norg.eclipse.emf.ecore.xml.type.internal.XMLCalendar.\u003cinit\u003e(XMLCalendar.java:159)\n       at\norg.eclipse.emf.ecore.xml.type.impl.XMLTypeFactoryImpl.createDateFromString(XMLTypeFactoryImpl.java:694)\n       at\norg.eclipse.emf.ecore.xml.type.impl.XMLTypeFactoryImpl.createFromString(XMLTypeFactoryImpl.java:95)\n       at\norg.eclipse.emf.ecore.xmi.impl.XMLHelperImpl.createFromString(XMLHelperImpl.java:1090)\n       at\norg.eclipse.emf.ecore.xmi.impl.XMLHelperImpl.setValue(XMLHelperImpl.java:768)\n       at\norg.eclipse.emf.ecore.xmi.impl.XMLHandler.setFeatureValue(XMLHandler.java:1729)\n       at\norg.eclipse.emf.ecore.xmi.impl.XMLHandler.setFeatureValue(XMLHandler.java:1719)\n       at org.eclipse.emf.ecore.xmi.impl.XMLHandler.endElement(XMLHandler.java:830)\n       at org.eclipse.emf.ecore.xmi.impl.SAXWrapper.endElement(SAXWrapper.java:80)\n       at org.apache.xerces.parsers.AbstractSAXParser.endElement(Unknown Source)\n       at\norg.apache.xerces.impl.XMLDocumentFragmentScannerImpl.scanEndElement(Unknown Source)\n       at\norg.apache.xerces.impl.XMLDocumentFragmentScannerImpl$FragmentContentDispatcher.dispatch(Unknown\nSource)\n       at\norg.apache.xerces.impl.XMLDocumentFragmentScannerImpl.scanDocument(Unknown Source)\n       at org.apache.xerces.parsers.XML11Configuration.parse(Unknown Source)\n       at org.apache.xerces.parsers.XML11Configuration.parse(Unknown Source)\n       at org.apache.xerces.parsers.XMLParser.parse(Unknown Source)\n       at org.apache.xerces.parsers.AbstractSAXParser.parse(Unknown Source)\n       at javax.xml.parsers.SAXParser.parse(Unknown Source)\n       at org.eclipse.emf.ecore.xmi.impl.XMLLoadImpl.load(XMLLoadImpl.java:129)\n       at\norg.eclipse.emf.ecore.xmi.impl.XMLResourceImpl.doLoad(XMLResourceImpl.java:155)\n       at extension.model.resource.XML.XmlResource.doLoad(XmlResource.java:49)\n       at\norg.eclipse.emf.ecore.resource.impl.ResourceImpl.load(ResourceImpl.java:888)\n       at extension.model.resource.ResourceX.load(ResourceX.java:672)\n       at com.ibm.wbi.model.ObjectResource.load(ObjectResource.java:111)\n       at com.ibm.wbi.bo.impl.XmlSerializer.readDataObject(XmlSerializer.java:36)\n       at com.ibm.wbi.bo.impl.XmlSerializer.loadDataObject(XmlSerializer.java:102)\n       at sun.reflect.NativeMethodAccessorImpl.invoke0(Native Method)\n       at\nsun.reflect.NativeMethodAccessorImpl.invoke(NativeMethodAccessorImpl.java:85)\n       at\nsun.reflect.NativeMethodAccessorImpl.invoke(NativeMethodAccessorImpl.java:58)\n       at\nsun.reflect.DelegatingMethodAccessorImpl.invoke(DelegatingMethodAccessorImpl.java:60)\n       at java.lang.reflect.Method.invoke(Method.java:391)\n       at\ncom.ibm.ws.jservice.java.JavaReflectionAdapter.invoke(JavaReflectionAdapter.java:99)\n       at\ncom.ibm.ws.jservice.java.JavaImplementationHandler.invokeSync(JavaImplementationHandler.java:250)\n       at\ncom.ibm.ws.jservice.java.JavaImplementationHandler.processMessage(JavaImplementationHandler.java:81)\n       at\ncom.ibm.ws.jservice.handler.impl.ExtensionMessageHandlerImpl.processMessage(ExtensionMessageHandlerImpl.java:68)\n       at\ncom.ibm.ws.jservice.scdl.extensions.impl.ManagedImplementationExtensionImpl.processMessage(ManagedImplementationExtensionImpl.java:71)\n       at\ncom.ibm.ws.jservice.handler.impl.MessageDispatcherImpl.processMessage(MessageDispatcherImpl.java:175)\n       at\ncom.ibm.ws.jservice.handler.impl.ProxyInvocationHandlerImpl.processMessage(ProxyInvocationHandlerImpl.java:633)\n       at\ncom.ibm.ws.jservice.handler.impl.ProxyInvocationHandlerImpl.invoke(ProxyInvocationHandlerImpl.java:724)\n       at\ncom.ibm.ws.jservice.handler.impl.ProxyInvocationHandlerImpl.invoke(ProxyInvocationHandlerImpl.java:748)\n       at\ncom.ibm.ws.jservice.handler.impl.ProxyInvocationHandlerImpl.invoke(ProxyInvocationHandlerImpl.java:482)\n       at $Proxy3.loadDataObject(Unknown Source)\n       at clientside.tBOF.BOFHelper.xmlSerialize(BOFHelper.java:438)\n       at clientside.tBOF.BOFHelper.main(BOFHelper.java:1046)\n\n    \u003cNote by zlainwala (Kulkarni, Zeenat), 2004/11/15 15:13:09, seq: 2 rel: 0 \naction: assign\u003e\nOld Owner: zlainwala\nNew Owner: gchen\n\n\n\n\n\n    \u003cNote by kjwillia (Williams, Kevin J.             ), 2004/11/17 19:53:15,\nseq: 7 rel: 0  action: return\u003e\nPlease provide a simple example and stack trace.\n\n    \u003cNote by yanlingz (Zhang, Yan Ling *CONTRACTOR*), 2004/11/17 20:51:07, seq:\n8 rel: 0  action: reopen\u003e\nSymptoms or statement of problem:\nAttribute with \"xs:date\"  desiralization is failed by exception\n\nConsole output with Exception:\n\u003c?xml version\u003d\"1.0\" encoding\u003d\"ASCII\"?\u003e\n\u003ctypes:Employee xmlns:types\u003d\"http://www.scm.com/EmployeeTypes\"\u003e\n  \u003ctypes:hiredate\u003eThu Nov 18 10:41:46 CST 2004\u003c/types:hiredate\u003e\n\u003c/types:Employee\u003e\norg.eclipse.emf.ecore.xml.type.InvalidDatatypeValueException: Year separator is\nmissing or misplaced\n       at\norg.eclipse.emf.ecore.xml.type.internal.XMLCalendar.getYearMonth(XMLCalendar.java:440)\n       at\norg.eclipse.emf.ecore.xml.type.internal.XMLCalendar.getDate(XMLCalendar.java:410)\n       at\norg.eclipse.emf.ecore.xml.type.internal.XMLCalendar.parseDate(XMLCalendar.java:1042)\n       at\norg.eclipse.emf.ecore.xml.type.internal.XMLCalendar.\u003cinit\u003e(XMLCalendar.java:159)\n       at\norg.eclipse.emf.ecore.xml.type.impl.XMLTypeFactoryImpl.createDateFromString(XMLTypeFactoryImpl.java:694)\n       at\norg.eclipse.emf.ecore.xml.type.impl.XMLTypeFactoryImpl.createFromString(XMLTypeFactoryImpl.java:95)\n       at\norg.eclipse.emf.ecore.xmi.impl.XMLHelperImpl.createFromString(XMLHelperImpl.java:1090)\n       at\norg.eclipse.emf.ecore.xmi.impl.XMLHelperImpl.setValue(XMLHelperImpl.java:768)\n       at\norg.eclipse.emf.ecore.xmi.impl.XMLHandler.setFeatureValue(XMLHandler.java:1729)\n       at\norg.eclipse.emf.ecore.xmi.impl.XMLHandler.setFeatureValue(XMLHandler.java:1719)\n       at org.eclipse.emf.ecore.xmi.impl.XMLHandler.endElement(XMLHandler.java:830)\n       at org.eclipse.emf.ecore.xmi.impl.SAXWrapper.endElement(SAXWrapper.java:80)\n       at org.apache.xerces.parsers.AbstractSAXParser.endElement(Unknown Source)\n       at\norg.apache.xerces.impl.XMLDocumentFragmentScannerImpl.scanEndElement(Unknown Source)\n       at\norg.apache.xerces.impl.XMLDocumentFragmentScannerImpl$FragmentContentDispatcher.dispatch(Unknown\nSource)\n       at\norg.apache.xerces.impl.XMLDocumentFragmentScannerImpl.scanDocument(Unknown Source)\n       at org.apache.xerces.parsers.XML11Configuration.parse(Unknown Source)\n       at org.apache.xerces.parsers.XML11Configuration.parse(Unknown Source)\n       at org.apache.xerces.parsers.XMLParser.parse(Unknown Source)\n       at org.apache.xerces.parsers.AbstractSAXParser.parse(Unknown Source)\n       at javax.xml.parsers.SAXParser.parse(Unknown Source)\n       at org.eclipse.emf.ecore.xmi.impl.XMLLoadImpl.load(XMLLoadImpl.java:129)\n       at\norg.eclipse.emf.ecore.xmi.impl.XMLResourceImpl.doLoad(XMLResourceImpl.java:155)\n       at extension.model.resource.XML.XmlResource.doLoad(XmlResource.java:71)\n       at\norg.eclipse.emf.ecore.resource.impl.ResourceImpl.load(ResourceImpl.java:888)\n       at extension.model.resource.ResourceX.load(ResourceX.java:902)\n       at com.ibm.wbi.model.ObjectResource.load(ObjectResource.java:134)\n       at com.ibm.wbi.bo.impl.XmlSerializer.readDataObject(XmlSerializer.java:57)\n       at com.ibm.wbi.bo.impl.XmlSerializer.loadDataObject(XmlSerializer.java:123)\n       at sun.reflect.NativeMethodAccessorImpl.invoke0(Native Method)\n       at\nsun.reflect.NativeMethodAccessorImpl.invoke(NativeMethodAccessorImpl.java:85)\n       at\nsun.reflect.NativeMethodAccessorImpl.invoke(NativeMethodAccessorImpl.java:58)\n       at\nsun.reflect.DelegatingMethodAccessorImpl.invoke(DelegatingMethodAccessorImpl.java:60)\n       at java.lang.reflect.Method.invoke(Method.java:391)\n       at\ncom.ibm.ws.jservice.java.JavaReflectionAdapter.invoke(JavaReflectionAdapter.java:99)\n       at\ncom.ibm.ws.jservice.java.JavaImplementationHandler.invokeSync(JavaImplementationHandler.java:251)\n       at\ncom.ibm.ws.jservice.java.JavaImplementationHandler.processMessage(JavaImplementationHandler.java:82)\n       at\ncom.ibm.ws.jservice.handler.impl.ExtensionMessageHandlerImpl.processMessage(ExtensionMessageHandlerImpl.java:68)\n       at\ncom.ibm.ws.jservice.scdl.extensions.impl.ManagedImplementationExtensionImpl.processMessage(ManagedImplementationExtensionImpl.java:71)\n       at\ncom.ibm.ws.jservice.handler.impl.MessageDispatcherImpl.processMessage(MessageDispatcherImpl.java:175)\n       at\ncom.ibm.ws.jservice.handler.impl.ProxyInvocationHandlerImpl.processMessage(ProxyInvocationHandlerImpl.java:633)\n       at\ncom.ibm.ws.jservice.handler.impl.ProxyInvocationHandlerImpl.invoke(ProxyInvocationHandlerImpl.java:724)\n       at\ncom.ibm.ws.jservice.handler.impl.ProxyInvocationHandlerImpl.invoke(ProxyInvocationHandlerImpl.java:748)\n       at\ncom.ibm.ws.jservice.handler.impl.ProxyInvocationHandlerImpl.invoke(ProxyInvocationHandlerImpl.java:482)!!!!!!!!!!!!!BG\n\n       at $Proxy3.loadDataObject(Unknown Source)\n       at jts.diamond.test.bo.BOFHelper.main(BOFHelper.java:1289)\n\nHere is the sample code:\n       BOXMLSerializer boXMLSerializer \u003d (BOXMLSerializer)\nlocateService(SERVICE_BOXMLSERIALIZER);\n       DataObject employee \u003d\nhelper.create(typeService.getType(\"http://www.scm.com/EmployeeTypes\",\"Employee\"));\n       employee.setDate(\"hiredate\",new Date());\n\n       try {\n              ByteArrayOutputStream bos \u003d new ByteArrayOutputStream();\n              boXMLSerializer.saveDataObject(employee,bos);\n              String content \u003d new String(bos.toByteArray());\n              System.out.println(content);\n              ByteArrayInputStream bis \u003d new\nByteArrayInputStream(bos.toByteArray());                     \n              DataObject retrievedDO \u003d boXMLSerializer.loadDataObject(bis);\n              bis.close();\n              bos.close();\n       } catch (Exception e) {\n              e.printStackTrace();\n       } \n              \nWe have definied hiredate as \"xs:date\" type\n\n\n\n\nDescription of steps to reproduce the problem:\n1.Load BO definition files\n2. Retrieve a BOFactory\n3. Create a Company Business Graph\n4. Create a Company from the Company Business Graph\n5. Set the ID for the Company BO\n6. Set the name for the Company BO\n7. Create a child department BO from this company BO\n8. Set the ID for the child department BO\n9. Set the name for the child department BO\n10. Create a child employee from this child department BO\n11.Set ID,IC, name, manager and address(city, street, number) ,\nhiredate,birthday,salary,dutyTime,blogsrc,isActive for the employee\n12.Serialize the BO\n13.Retrieve the BO and verify \n\n  \n\nDifference between expected and actual results:\nexpected:The BO should be retrieved with right data.\nactual: Exception was thrown and the retrieved BO is null\n\nDid this test case previously execute successfully?\nNo.\n\nLocation of trace/dump information or test case files:\n\n\n\n\n    \u003cNote by yanlingz (Zhang, Yan Ling *CONTRACTOR*), 2004/11/28 19:56:36, seq:\n9 rel: 0  action: modify\u003e\nOld Abstract: Attribute with \"xs:date\"  desiralization is failed by exception\nNew Abstract: WBI-Attr with \"xs:date\"  desiralization is failed by exception\n\n\n\n    \u003cNote by kjwillia (Williams, Kevin J.             ), 2004/12/01 14:52:25,\nseq: 10 rel: 0  action: note\u003e\nComment from Steve Brodsky ...\n\n\"Most likely the user does not have the right instance class for dates.  Either\nthey have to use the one \nspecified by the EMF mapping or they have to modify the XSD converter to use\nsome other mapping such as \nSDO 1.1.\"\n\n\n\n\nFollow-up comment by Ed Merks ...\n\n\"Steve,\n\nI\u0027m assuming that the model started as an XML Schema and that xsd:date was\nmapped to XMLTypePackage.getDate:\n\n  /**\n   * Returns the meta object for data type \u0027{@link java.lang.Object \u003cem\u003eDate\u003c/em\u003e}\u0027.\n   * \u003c!-- begin-user-doc --\u003e\n   * \u003c!-- end-user-doc --\u003e\n   * @return the meta object for data type \u0027\u003cem\u003eDate\u003c/em\u003e\u0027.\n   * @see java.lang.Object\n   * @model instanceClass\u003d\"java.lang.Object\"\n   * @generated\n   */\n  EDataType getDate();\n\nSince that type is declared to be java.lang.Object (to hide the internal\nimplementation class that will \neventually be replaced by XMLGregorianCalendar) assigning a java.util.Date to\nthe feature will not be \nnoticed as a type error.  And since the serialization is done like this:\n\n  public String convertDateToString(EDataType eDataType, Object instanceValue)\n  {\n    return instanceValue \u003d\u003d null ? null : instanceValue.toString();\n  }\n\nthe java.util.Date object is converted to a String okay, but not to a form that\nconforms to xsd:date.\n\nOne way to \"fix\" this would be to check for java.util.Date in the above method\nand serialize it in a way \nthat conforms to xsd:date (as does the EDate type in the Ecore package), but\nthat\u0027s kind of a hack, and \ncode that relies on this will break when java.lang.Object becomes\nXMLGregorianCalendar and java.util.Date \nmay not longer be assigned.\n\nA better way to handle this is for setDate and getDate to do conversion to and\nfrom other \"Date\" types.  \nIn this case, it would convert the Date to our internal XMLCalendar and back. \n(It would probably be nice \nand consistent for getString and setString to work for dates too, but 1.0 didn\u0027t\nspecify that.)   The ideal \nsolution for this particular scenario would be for the xsd:date to have mapped\nto the less precise EDate \ntype in Ecore rather than the 100% precise Date type in XMLType, but I think we\nshould leave changes to \nthe mapping to be based on the 1.1 spec, not to fix 1.0 problems.\"\n\n    \u003cNote by yanlingz (Zhang, Yan Ling *CONTRACTOR*), 2004/12/02 00:18:31, seq:\n11 rel: 0  action: note\u003e\nCan you give me the sample of how to use XMLTypePackage.getDate, the similiar with\nxsd:time and xsd:dateTime\n\n    \u003cNote by yanlingz (Zhang, Yan Ling *CONTRACTOR*), 2004/12/03 02:51:00, seq:\n12 rel: 0  action: note\u003e\ni have tried XMLTypePackage, here is the code snippet:\n\n            employee \u003d\nhelper.create(typeService.getType(\"http://www.scm.com/EmployeeTypes\",\"Employee\"));\n           employee.set(\"hiredate\", XMLTypePackage.eINSTANCE.getDate());       \n          \n\n           try {\n                  ByteArrayOutputStream bos \u003d new ByteArrayOutputStream();\n                  boXMLSerializer.saveDataObject(employee,bos);\n                  String content \u003d new String(bos.toByteArray());\n                  System.out.println(content);\n                  ByteArrayInputStream bis \u003d new\nByteArrayInputStream(bos.toByteArray());                     \n                  DataObject retrievedDO \u003d boXMLSerializer.loadDataObject(bis);\n                  bis.close();\n                  bos.close();\n                                \n          } catch (Exception e) {\n                  e.printStackTrace();\n          } \n\nthe same exception is thrown like:\n\norg.eclipse.emf.ecore.xml.type.InvalidDatatypeValueException: Year separator is\nmissing or misplaced\n       at\norg.eclipse.emf.ecore.xml.type.internal.XMLCalendar.getYearMonth(XMLCalendar.java:440)\n       at\norg.eclipse.emf.ecore.xml.type.internal.XMLCalendar.getDate(XMLCalendar.java:410)\n       at\norg.eclipse.emf.ecore.xml.type.internal.XMLCalendar.parseDate(XMLCalendar.java:1042)\n       at\norg.eclipse.emf.ecore.xml.type.internal.XMLCalendar.\u003cinit\u003e(XMLCalendar.java:159)\n       at\norg.eclipse.emf.ecore.xml.type.impl.XMLTypeFactoryImpl.createDateFromString(XMLTypeFactoryImpl.java:694)\n       at\norg.eclipse.emf.ecore.xml.type.impl.XMLTypeFactoryImpl.createFromString(XMLTypeFactoryImpl.java:95)\n       at\norg.eclipse.emf.ecore.xmi.impl.XMLHelperImpl.createFromString(XMLHelperImpl.java:1090)\n       at\norg.eclipse.emf.ecore.xmi.impl.XMLHelperImpl.setValue(XMLHelperImpl.java:768)\n       at\norg.eclipse.emf.ecore.xmi.impl.XMLHandler.setFeatureValue(XMLHandler.java:1729)\n       at\norg.eclipse.emf.ecore.xmi.impl.XMLHandler.setFeatureValue(XMLHandler.java:1719)\n       at org.eclipse.emf.ecore.xmi.impl.XMLHandler.endElement(XMLHandler.java:830)\n       at org.eclipse.emf.ecore.xmi.impl.SAXWrapper.endElement(SAXWrapper.java:80)\n       at org.apache.xerces.parsers.AbstractSAXParser.endElement(Unknown Source)\n       at\norg.apache.xerces.impl.XMLDocumentFragmentScannerImpl.scanEndElement(Unknown Source)\n       at\norg.apache.xerces.impl.XMLDocumentFragmentScannerImpl$FragmentContentDispatcher.dispatch(Unknown\nSource)\n       at\norg.apache.xerces.impl.XMLDocumentFragmentScannerImpl.scanDocument(Unknown Source)\n       at org.apache.xerces.parsers.XML11Configuration.parse(Unknown Source)\n       at org.apache.xerces.parsers.XML11Configuration.parse(Unknown Source)\n       at org.apache.xerces.parsers.XMLParser.parse(Unknown Source)\n       at org.apache.xerces.parsers.AbstractSAXParser.parse(Unknown Source)\n       at javax.xml.parsers.SAXParser.parse(Unknown Source)\n       at org.eclipse.emf.ecore.xmi.impl.XMLLoadImpl.load(XMLLoadImpl.java:129)\n       at\norg.eclipse.emf.ecore.xmi.impl.XMLResourceImpl.doLoad(XMLResourceImpl.java:155)\n       at extension.model.resource.XML.XmlResource.doLoad(XmlResource.java:71)\n       at\norg.eclipse.emf.ecore.resource.impl.ResourceImpl.load(ResourceImpl.java:888)\n       at extension.model.resource.ResourceX.load(ResourceX.java:898)\n       at com.ibm.wbi.model.ObjectResource.load(ObjectResource.java:131)\n       at com.ibm.wbi.bo.impl.XmlSerializer.readDataObject(XmlSerializer.java:57)\n       at com.ibm.wbi.bo.impl.XmlSerializer.loadDataObject(XmlSerializer.java:137)\n       at sun.reflect.NativeMethodAccessorImpl.invoke0(Native Method)\n       at\nsun.reflect.NativeMethodAccessorImpl.invoke(NativeMethodAccessorImpl.java:85)\n       at\nsun.reflect.NativeMethodAccessorImpl.invoke(NativeMethodAccessorImpl.java:58)\n       at\nsun.reflect.DelegatingMethodAccessorImpl.invoke(DelegatingMethodAccessorImpl.java:60)\n       at java.lang.reflect.Method.invoke(Method.java:391)\n       at\ncom.ibm.ws.jservice.java.JavaReflectionAdapter.invoke(JavaReflectionAdapter.java:99)\n       at\ncom.ibm.ws.jservice.java.JavaImplementationHandler.invokeSync(JavaImplementationHandler.java:251)\n       at\ncom.ibm.ws.jservice.java.JavaImplementationHandler.processMessage(JavaImplementationHandler.java:82)\n       at\ncom.ibm.ws.jservice.handler.impl.ExtensionMessageHandlerImpl.processMessage(ExtensionMessageHandlerImpl.java:68)\n       at\ncom.ibm.ws.jservice.scdl.extensions.impl.ManagedImplementationExtensionImpl.processMessage(ManagedImplementationExtensionImpl.java:70)\n       at\ncom.ibm.ws.jservice.handler.impl.MessageDispatcherImpl.processMessage(MessageDispatcherImpl.java:175)\n       at\ncom.ibm.ws.jservice.handler.impl.ProxyInvocationHandlerImpl.processMessage(ProxyInvocationHandlerImpl.java:633)\n       at\ncom.ibm.ws.jservice.handler.impl.ProxyInvocationHandlerImpl.invoke(ProxyInvocationHandlerImpl.java:724)\n       at\ncom.ibm.ws.jservice.handler.impl.ProxyInvocationHandlerImpl.invoke(ProxyInvocationHandlerImpl.java:748)\n       at\ncom.ibm.ws.jservice.handler.impl.ProxyInvocationHandlerImpl.invoke(ProxyInvocationHandlerImpl.java:482)\n       at $Proxy3.loadDataObject(Unknown Source)\n\nso could you pls give me detail information on how to use this correctly?\n\n------------\nYan,\n\nThe problem appears to be that XML Schema wants the time zone to look like\n+08:00 not just +0800.  Something like this should help to put the \":\" in the\nresult:\n\n    SimpleDateFormat xmlSchemaDateTimeFormat \u003d \n      new SimpleDateFormat(\"HH:mm:ss\u0027.\u0027SSSZ\")\n      {\n        public StringBuffer format(Date date, StringBuffer toAppendTo,\nFieldPosition pos)\n        {\n          StringBuffer result \u003d super.format(date, toAppendTo, pos);\n          result.insert(result.length() - 2, \":\");\n          return result;\n        }\n      };\n    String x \u003d xmlSchemaDateTimeFormat.format(new Date());\n    System.err.println(\"##\" +\nEcoreUtil.createFromString(XMLTypePackage.eINSTANCE.getTime(), x));\n\n\nEd Merks\n--------------\n\nAnother comment from ED ...\n\nEven if the spec doesn\u0027t specify converting between XMLGegorianCalendard and\njava.util.Date, we still should.",
    "[plan pri\u003d1 est\u003d1w/]",
    "Fix in CVS.\nRun JUnit test org.eclipse.emf.test.sdo.DateTest and step in for details.",
    "Fixed in 2.1.0 I200506091102",
    "(In reply to comment #3)\n\u003e Fixed in 2.1.0 I200506091102\n\nThis fix is also needed in the 2.0.1 stream."
  ],
  "commentCreationDates": [
    "2004-12-21T19:28:04+01:00",
    "2005-02-18T12:41:24+01:00",
    "2005-06-08T22:49:28+02:00",
    "2005-06-09T21:40:54+02:00",
    "2005-12-21T19:26:17+01:00"
  ],
  "traces": [
    {
      "exceptionType": "org.eclipse.emf.ecore.xml.type.InvalidDatatypeValueException",
      "message": "Year separator is missing or misplaced",
      "elements": [
        {
          "method": "org.eclipse.emf.ecore.xml.type.internal.XMLCalendar.getYearMonth",
          "source": "XMLCalendar.java:440"
        },
        {
          "method": "org.eclipse.emf.ecore.xml.type.internal.XMLCalendar.getDate",
          "source": "XMLCalendar.java:410"
        },
        {
          "method": "org.eclipse.emf.ecore.xml.type.internal.XMLCalendar.parseDate",
          "source": "XMLCalendar.java:1042"
        },
        {
          "method": "org.eclipse.emf.ecore.xml.type.internal.XMLCalendar.\u003cinit\u003e",
          "source": "XMLCalendar.java:159"
        },
        {
          "method": "org.eclipse.emf.ecore.xml.type.impl.XMLTypeFactoryImpl.createDateFromString",
          "source": "XMLTypeFactoryImpl.java:694"
        },
        {
          "method": "org.eclipse.emf.ecore.xml.type.impl.XMLTypeFactoryImpl.createFromString",
          "source": "XMLTypeFactoryImpl.java:95"
        },
        {
          "method": "org.eclipse.emf.ecore.xmi.impl.XMLHelperImpl.createFromString",
          "source": "XMLHelperImpl.java:1090"
        },
        {
          "method": "org.eclipse.emf.ecore.xmi.impl.XMLHelperImpl.setValue",
          "source": "XMLHelperImpl.java:768"
        },
        {
          "method": "org.eclipse.emf.ecore.xmi.impl.XMLHandler.setFeatureValue",
          "source": "XMLHandler.java:1729"
        },
        {
          "method": "org.eclipse.emf.ecore.xmi.impl.XMLHandler.setFeatureValue",
          "source": "XMLHandler.java:1719"
        },
        {
          "method": "org.eclipse.emf.ecore.xmi.impl.XMLHandler.endElement",
          "source": "XMLHandler.java:830"
        },
        {
          "method": "org.eclipse.emf.ecore.xmi.impl.SAXWrapper.endElement",
          "source": "SAXWrapper.java:80"
        },
        {
          "method": "org.apache.xerces.parsers.AbstractSAXParser.endElement",
          "source": "Unknown Source"
        },
        {
          "method": "org.apache.xerces.impl.XMLDocumentFragmentScannerImpl.scanEndElement",
          "source": "Unknown Source"
        },
        {
          "method": "org.apache.xerces.impl.XMLDocumentFragmentScannerImpl$FragmentContentDispatcher.dispatch",
          "source": "Unknown Source"
        },
        {
          "method": "org.apache.xerces.impl.XMLDocumentFragmentScannerImpl.scanDocument",
          "source": "Unknown Source"
        },
        {
          "method": "org.apache.xerces.parsers.XML11Configuration.parse",
          "source": "Unknown Source"
        },
        {
          "method": "org.apache.xerces.parsers.XML11Configuration.parse",
          "source": "Unknown Source"
        },
        {
          "method": "org.apache.xerces.parsers.XMLParser.parse",
          "source": "Unknown Source"
        },
        {
          "method": "org.apache.xerces.parsers.AbstractSAXParser.parse",
          "source": "Unknown Source"
        },
        {
          "method": "javax.xml.parsers.SAXParser.parse",
          "source": "Unknown Source"
        },
        {
          "method": "org.eclipse.emf.ecore.xmi.impl.XMLLoadImpl.load",
          "source": "XMLLoadImpl.java:129"
        },
        {
          "method": "org.eclipse.emf.ecore.xmi.impl.XMLResourceImpl.doLoad",
          "source": "XMLResourceImpl.java:155"
        },
        {
          "method": "extension.model.resource.XML.XmlResource.doLoad",
          "source": "XmlResource.java:49"
        },
        {
          "method": "org.eclipse.emf.ecore.resource.impl.ResourceImpl.load",
          "source": "ResourceImpl.java:888"
        },
        {
          "method": "extension.model.resource.ResourceX.load",
          "source": "ResourceX.java:672"
        },
        {
          "method": "com.ibm.wbi.model.ObjectResource.load",
          "source": "ObjectResource.java:111"
        },
        {
          "method": "com.ibm.wbi.bo.impl.XmlSerializer.readDataObject",
          "source": "XmlSerializer.java:36"
        },
        {
          "method": "com.ibm.wbi.bo.impl.XmlSerializer.loadDataObject",
          "source": "XmlSerializer.java:102"
        },
        {
          "method": "sun.reflect.NativeMethodAccessorImpl.invoke0",
          "source": "Native Method"
        },
        {
          "method": "sun.reflect.NativeMethodAccessorImpl.invoke",
          "source": "NativeMethodAccessorImpl.java:85"
        },
        {
          "method": "sun.reflect.NativeMethodAccessorImpl.invoke",
          "source": "NativeMethodAccessorImpl.java:58"
        },
        {
          "method": "sun.reflect.DelegatingMethodAccessorImpl.invoke",
          "source": "DelegatingMethodAccessorImpl.java:60"
        },
        {
          "method": "java.lang.reflect.Method.invoke",
          "source": "Method.java:391"
        },
        {
          "method": "com.ibm.ws.jservice.java.JavaReflectionAdapter.invoke",
          "source": "JavaReflectionAdapter.java:99"
        },
        {
          "method": "com.ibm.ws.jservice.java.JavaImplementationHandler.invokeSync",
          "source": "JavaImplementationHandler.java:250"
        },
        {
          "method": "com.ibm.ws.jservice.java.JavaImplementationHandler.processMessage",
          "source": "JavaImplementationHandler.java:81"
        },
        {
          "method": "com.ibm.ws.jservice.handler.impl.ExtensionMessageHandlerImpl.processMessage",
          "source": "ExtensionMessageHandlerImpl.java:68"
        },
        {
          "method": "com.ibm.ws.jservice.scdl.extensions.impl.ManagedImplementationExtensionImpl.processMessage",
          "source": "ManagedImplementationExtensionImpl.java:71"
        },
        {
          "method": "com.ibm.ws.jservice.handler.impl.MessageDispatcherImpl.processMessage",
          "source": "MessageDispatcherImpl.java:175"
        },
        {
          "method": "com.ibm.ws.jservice.handler.impl.ProxyInvocationHandlerImpl.processMessage",
          "source": "ProxyInvocationHandlerImpl.java:633"
        },
        {
          "method": "com.ibm.ws.jservice.handler.impl.ProxyInvocationHandlerImpl.invoke",
          "source": "ProxyInvocationHandlerImpl.java:724"
        },
        {
          "method": "com.ibm.ws.jservice.handler.impl.ProxyInvocationHandlerImpl.invoke",
          "source": "ProxyInvocationHandlerImpl.java:748"
        },
        {
          "method": "com.ibm.ws.jservice.handler.impl.ProxyInvocationHandlerImpl.invoke",
          "source": "ProxyInvocationHandlerImpl.java:482"
        }
      ],
      "number": 0,
      "commentIndex": 0,
      "bugId": "81752",
      "date": "2004-12-21T19:28:04+01:00",
      "product": "EMF",
      "component": "SDO",
      "severity": "normal"
    },
    {
      "exceptionType": "org.eclipse.emf.ecore.xml.type.InvalidDatatypeValueException",
      "message": "Year separator is missing or misplaced",
      "elements": [
        {
          "method": "org.eclipse.emf.ecore.xml.type.internal.XMLCalendar.getYearMonth",
          "source": "XMLCalendar.java:440"
        },
        {
          "method": "org.eclipse.emf.ecore.xml.type.internal.XMLCalendar.getDate",
          "source": "XMLCalendar.java:410"
        },
        {
          "method": "org.eclipse.emf.ecore.xml.type.internal.XMLCalendar.parseDate",
          "source": "XMLCalendar.java:1042"
        },
        {
          "method": "org.eclipse.emf.ecore.xml.type.internal.XMLCalendar.\u003cinit\u003e",
          "source": "XMLCalendar.java:159"
        },
        {
          "method": "org.eclipse.emf.ecore.xml.type.impl.XMLTypeFactoryImpl.createDateFromString",
          "source": "XMLTypeFactoryImpl.java:694"
        },
        {
          "method": "org.eclipse.emf.ecore.xml.type.impl.XMLTypeFactoryImpl.createFromString",
          "source": "XMLTypeFactoryImpl.java:95"
        },
        {
          "method": "org.eclipse.emf.ecore.xmi.impl.XMLHelperImpl.createFromString",
          "source": "XMLHelperImpl.java:1090"
        },
        {
          "method": "org.eclipse.emf.ecore.xmi.impl.XMLHelperImpl.setValue",
          "source": "XMLHelperImpl.java:768"
        },
        {
          "method": "org.eclipse.emf.ecore.xmi.impl.XMLHandler.setFeatureValue",
          "source": "XMLHandler.java:1729"
        },
        {
          "method": "org.eclipse.emf.ecore.xmi.impl.XMLHandler.setFeatureValue",
          "source": "XMLHandler.java:1719"
        },
        {
          "method": "org.eclipse.emf.ecore.xmi.impl.XMLHandler.endElement",
          "source": "XMLHandler.java:830"
        },
        {
          "method": "org.eclipse.emf.ecore.xmi.impl.SAXWrapper.endElement",
          "source": "SAXWrapper.java:80"
        },
        {
          "method": "org.apache.xerces.parsers.AbstractSAXParser.endElement",
          "source": "Unknown Source"
        },
        {
          "method": "org.apache.xerces.impl.XMLDocumentFragmentScannerImpl.scanEndElement",
          "source": "Unknown Source"
        },
        {
          "method": "org.apache.xerces.impl.XMLDocumentFragmentScannerImpl$FragmentContentDispatcher.dispatch",
          "source": "Unknown Source"
        },
        {
          "method": "org.apache.xerces.impl.XMLDocumentFragmentScannerImpl.scanDocument",
          "source": "Unknown Source"
        },
        {
          "method": "org.apache.xerces.parsers.XML11Configuration.parse",
          "source": "Unknown Source"
        },
        {
          "method": "org.apache.xerces.parsers.XML11Configuration.parse",
          "source": "Unknown Source"
        },
        {
          "method": "org.apache.xerces.parsers.XMLParser.parse",
          "source": "Unknown Source"
        },
        {
          "method": "org.apache.xerces.parsers.AbstractSAXParser.parse",
          "source": "Unknown Source"
        },
        {
          "method": "javax.xml.parsers.SAXParser.parse",
          "source": "Unknown Source"
        },
        {
          "method": "org.eclipse.emf.ecore.xmi.impl.XMLLoadImpl.load",
          "source": "XMLLoadImpl.java:129"
        },
        {
          "method": "org.eclipse.emf.ecore.xmi.impl.XMLResourceImpl.doLoad",
          "source": "XMLResourceImpl.java:155"
        },
        {
          "method": "extension.model.resource.XML.XmlResource.doLoad",
          "source": "XmlResource.java:71"
        },
        {
          "method": "org.eclipse.emf.ecore.resource.impl.ResourceImpl.load",
          "source": "ResourceImpl.java:888"
        },
        {
          "method": "extension.model.resource.ResourceX.load",
          "source": "ResourceX.java:902"
        },
        {
          "method": "com.ibm.wbi.model.ObjectResource.load",
          "source": "ObjectResource.java:134"
        },
        {
          "method": "com.ibm.wbi.bo.impl.XmlSerializer.readDataObject",
          "source": "XmlSerializer.java:57"
        },
        {
          "method": "com.ibm.wbi.bo.impl.XmlSerializer.loadDataObject",
          "source": "XmlSerializer.java:123"
        },
        {
          "method": "sun.reflect.NativeMethodAccessorImpl.invoke0",
          "source": "Native Method"
        },
        {
          "method": "sun.reflect.NativeMethodAccessorImpl.invoke",
          "source": "NativeMethodAccessorImpl.java:85"
        },
        {
          "method": "sun.reflect.NativeMethodAccessorImpl.invoke",
          "source": "NativeMethodAccessorImpl.java:58"
        },
        {
          "method": "sun.reflect.DelegatingMethodAccessorImpl.invoke",
          "source": "DelegatingMethodAccessorImpl.java:60"
        },
        {
          "method": "java.lang.reflect.Method.invoke",
          "source": "Method.java:391"
        },
        {
          "method": "com.ibm.ws.jservice.java.JavaReflectionAdapter.invoke",
          "source": "JavaReflectionAdapter.java:99"
        },
        {
          "method": "com.ibm.ws.jservice.java.JavaImplementationHandler.invokeSync",
          "source": "JavaImplementationHandler.java:251"
        },
        {
          "method": "com.ibm.ws.jservice.java.JavaImplementationHandler.processMessage",
          "source": "JavaImplementationHandler.java:82"
        },
        {
          "method": "com.ibm.ws.jservice.handler.impl.ExtensionMessageHandlerImpl.processMessage",
          "source": "ExtensionMessageHandlerImpl.java:68"
        },
        {
          "method": "com.ibm.ws.jservice.scdl.extensions.impl.ManagedImplementationExtensionImpl.processMessage",
          "source": "ManagedImplementationExtensionImpl.java:71"
        },
        {
          "method": "com.ibm.ws.jservice.handler.impl.MessageDispatcherImpl.processMessage",
          "source": "MessageDispatcherImpl.java:175"
        },
        {
          "method": "com.ibm.ws.jservice.handler.impl.ProxyInvocationHandlerImpl.processMessage",
          "source": "ProxyInvocationHandlerImpl.java:633"
        },
        {
          "method": "com.ibm.ws.jservice.handler.impl.ProxyInvocationHandlerImpl.invoke",
          "source": "ProxyInvocationHandlerImpl.java:724"
        },
        {
          "method": "com.ibm.ws.jservice.handler.impl.ProxyInvocationHandlerImpl.invoke",
          "source": "ProxyInvocationHandlerImpl.java:748"
        },
        {
          "method": "com.ibm.ws.jservice.handler.impl.ProxyInvocationHandlerImpl.invoke",
          "source": "ProxyInvocationHandlerImpl.java:482"
        }
      ],
      "number": 1,
      "commentIndex": 0,
      "bugId": "81752",
      "date": "2004-12-21T19:28:04+01:00",
      "product": "EMF",
      "component": "SDO",
      "severity": "normal"
    },
    {
      "exceptionType": "org.eclipse.emf.ecore.xml.type.InvalidDatatypeValueException",
      "message": "Year separator is missing or misplaced",
      "elements": [
        {
          "method": "org.eclipse.emf.ecore.xml.type.internal.XMLCalendar.getYearMonth",
          "source": "XMLCalendar.java:440"
        },
        {
          "method": "org.eclipse.emf.ecore.xml.type.internal.XMLCalendar.getDate",
          "source": "XMLCalendar.java:410"
        },
        {
          "method": "org.eclipse.emf.ecore.xml.type.internal.XMLCalendar.parseDate",
          "source": "XMLCalendar.java:1042"
        },
        {
          "method": "org.eclipse.emf.ecore.xml.type.internal.XMLCalendar.\u003cinit\u003e",
          "source": "XMLCalendar.java:159"
        },
        {
          "method": "org.eclipse.emf.ecore.xml.type.impl.XMLTypeFactoryImpl.createDateFromString",
          "source": "XMLTypeFactoryImpl.java:694"
        },
        {
          "method": "org.eclipse.emf.ecore.xml.type.impl.XMLTypeFactoryImpl.createFromString",
          "source": "XMLTypeFactoryImpl.java:95"
        },
        {
          "method": "org.eclipse.emf.ecore.xmi.impl.XMLHelperImpl.createFromString",
          "source": "XMLHelperImpl.java:1090"
        },
        {
          "method": "org.eclipse.emf.ecore.xmi.impl.XMLHelperImpl.setValue",
          "source": "XMLHelperImpl.java:768"
        },
        {
          "method": "org.eclipse.emf.ecore.xmi.impl.XMLHandler.setFeatureValue",
          "source": "XMLHandler.java:1729"
        },
        {
          "method": "org.eclipse.emf.ecore.xmi.impl.XMLHandler.setFeatureValue",
          "source": "XMLHandler.java:1719"
        },
        {
          "method": "org.eclipse.emf.ecore.xmi.impl.XMLHandler.endElement",
          "source": "XMLHandler.java:830"
        },
        {
          "method": "org.eclipse.emf.ecore.xmi.impl.SAXWrapper.endElement",
          "source": "SAXWrapper.java:80"
        },
        {
          "method": "org.apache.xerces.parsers.AbstractSAXParser.endElement",
          "source": "Unknown Source"
        },
        {
          "method": "org.apache.xerces.impl.XMLDocumentFragmentScannerImpl.scanEndElement",
          "source": "Unknown Source"
        },
        {
          "method": "org.apache.xerces.impl.XMLDocumentFragmentScannerImpl$FragmentContentDispatcher.dispatch",
          "source": "Unknown Source"
        },
        {
          "method": "org.apache.xerces.impl.XMLDocumentFragmentScannerImpl.scanDocument",
          "source": "Unknown Source"
        },
        {
          "method": "org.apache.xerces.parsers.XML11Configuration.parse",
          "source": "Unknown Source"
        },
        {
          "method": "org.apache.xerces.parsers.XML11Configuration.parse",
          "source": "Unknown Source"
        },
        {
          "method": "org.apache.xerces.parsers.XMLParser.parse",
          "source": "Unknown Source"
        },
        {
          "method": "org.apache.xerces.parsers.AbstractSAXParser.parse",
          "source": "Unknown Source"
        },
        {
          "method": "javax.xml.parsers.SAXParser.parse",
          "source": "Unknown Source"
        },
        {
          "method": "org.eclipse.emf.ecore.xmi.impl.XMLLoadImpl.load",
          "source": "XMLLoadImpl.java:129"
        },
        {
          "method": "org.eclipse.emf.ecore.xmi.impl.XMLResourceImpl.doLoad",
          "source": "XMLResourceImpl.java:155"
        },
        {
          "method": "extension.model.resource.XML.XmlResource.doLoad",
          "source": "XmlResource.java:71"
        },
        {
          "method": "org.eclipse.emf.ecore.resource.impl.ResourceImpl.load",
          "source": "ResourceImpl.java:888"
        },
        {
          "method": "extension.model.resource.ResourceX.load",
          "source": "ResourceX.java:898"
        },
        {
          "method": "com.ibm.wbi.model.ObjectResource.load",
          "source": "ObjectResource.java:131"
        },
        {
          "method": "com.ibm.wbi.bo.impl.XmlSerializer.readDataObject",
          "source": "XmlSerializer.java:57"
        },
        {
          "method": "com.ibm.wbi.bo.impl.XmlSerializer.loadDataObject",
          "source": "XmlSerializer.java:137"
        },
        {
          "method": "sun.reflect.NativeMethodAccessorImpl.invoke0",
          "source": "Native Method"
        },
        {
          "method": "sun.reflect.NativeMethodAccessorImpl.invoke",
          "source": "NativeMethodAccessorImpl.java:85"
        },
        {
          "method": "sun.reflect.NativeMethodAccessorImpl.invoke",
          "source": "NativeMethodAccessorImpl.java:58"
        },
        {
          "method": "sun.reflect.DelegatingMethodAccessorImpl.invoke",
          "source": "DelegatingMethodAccessorImpl.java:60"
        },
        {
          "method": "java.lang.reflect.Method.invoke",
          "source": "Method.java:391"
        },
        {
          "method": "com.ibm.ws.jservice.java.JavaReflectionAdapter.invoke",
          "source": "JavaReflectionAdapter.java:99"
        },
        {
          "method": "com.ibm.ws.jservice.java.JavaImplementationHandler.invokeSync",
          "source": "JavaImplementationHandler.java:251"
        },
        {
          "method": "com.ibm.ws.jservice.java.JavaImplementationHandler.processMessage",
          "source": "JavaImplementationHandler.java:82"
        },
        {
          "method": "com.ibm.ws.jservice.handler.impl.ExtensionMessageHandlerImpl.processMessage",
          "source": "ExtensionMessageHandlerImpl.java:68"
        },
        {
          "method": "com.ibm.ws.jservice.scdl.extensions.impl.ManagedImplementationExtensionImpl.processMessage",
          "source": "ManagedImplementationExtensionImpl.java:70"
        },
        {
          "method": "com.ibm.ws.jservice.handler.impl.MessageDispatcherImpl.processMessage",
          "source": "MessageDispatcherImpl.java:175"
        },
        {
          "method": "com.ibm.ws.jservice.handler.impl.ProxyInvocationHandlerImpl.processMessage",
          "source": "ProxyInvocationHandlerImpl.java:633"
        },
        {
          "method": "com.ibm.ws.jservice.handler.impl.ProxyInvocationHandlerImpl.invoke",
          "source": "ProxyInvocationHandlerImpl.java:724"
        },
        {
          "method": "com.ibm.ws.jservice.handler.impl.ProxyInvocationHandlerImpl.invoke",
          "source": "ProxyInvocationHandlerImpl.java:748"
        },
        {
          "method": "com.ibm.ws.jservice.handler.impl.ProxyInvocationHandlerImpl.invoke",
          "source": "ProxyInvocationHandlerImpl.java:482"
        }
      ],
      "number": 2,
      "commentIndex": 0,
      "bugId": "81752",
      "date": "2004-12-21T19:28:04+01:00",
      "product": "EMF",
      "component": "SDO",
      "severity": "normal"
    }
  ],
  "groupId": "81752",
  "bugId": "81752",
  "date": "2004-12-21T19:28:04+01:00",
  "product": "EMF",
  "component": "SDO",
  "severity": "normal"
}