{
  "comments": [
    "If create a project with same name but different case in Eclipse you will get \nan error message on creation and exceptions in log when press finish button in \nProject wizard.\nWill be nice if the project with same name (\u0026 different case) will be detected \nand error will be displayed on Project wizard label (as ghappen when the name \nis the same and same case) and Next/Finish button should be disabled.\n\nSteps:\n1. Create a Java project named a\n2. Try to create another java project named A\nActual: when press Finish button you get an error message and exceptions in log \n(see below)\n\nSee below the error log:\n\n!ENTRY org.eclipse.jdt.ui 4 10001 Dec 22, 2004 15:45:08.818\n!MESSAGE Internal Error\n!STACK 1\norg.eclipse.core.internal.resources.ResourceException: A resource exists with a \ndifferent case: /iii.\n\tat org.eclipse.core.internal.resources.Resource.checkDoesNotExist\n(Unknown Source)\n\tat org.eclipse.core.internal.resources.Project.create(Unknown Source)\n\tat \norg.eclipse.jdt.internal.ui.wizards.buildpaths.BuildPathsBlock.createProject\n(Unknown Source)\n\tat \norg.eclipse.jdt.ui.wizards.JavaCapabilityConfigurationPage.createProject\n(Unknown Source)\n\tat \norg.eclipse.jdt.internal.ui.wizards.JavaProjectWizardSecondPage.updateProject\n(Unknown Source)\n\tat org.eclipse.jdt.internal.ui.wizards.JavaProjectWizardSecondPage$1.run\n(Unknown Source)\n\tat org.eclipse.ui.actions.WorkspaceModifyDelegatingOperation.execute\n(Unknown Source)\n\tat org.eclipse.ui.actions.WorkspaceModifyOperation$1.run(Unknown Source)\n\tat org.eclipse.core.internal.resources.Workspace.run(Unknown Source)\n\tat org.eclipse.ui.actions.WorkspaceModifyOperation.run(Unknown Source)\n\tat org.eclipse.jface.operation.ModalContext$ModalContextThread.run\n(Unknown Source)\n!SUBENTRY 1 org.eclipse.core.resources 4 275 Dec 22, 2004 15:45:08.828\n!MESSAGE A resource exists with a different case: /a.",
    "Martin, can you please comment.",
    "Resource core doesn\u0027t offer API to find out if a project of a certain name (or\nresource in general) can be created. We therefore can\u0027t warn users in the wizard\n but have to let them run into a error dialog.\n\nWe did some workarounds in the case of the new package or new type wizard, but\nfor projects we can\u0027t as the New project wizard also would accept existing\nlocations.",
    "\n\n*** This bug has been marked as a duplicate of 76954 ***"
  ],
  "commentCreationDates": [
    "2004-12-22T20:50:56+01:00",
    "2004-12-23T10:13:39+01:00",
    "2004-12-23T10:33:56+01:00",
    "2004-12-23T15:37:05+01:00"
  ],
  "traces": [
    {
      "exceptionType": "org.eclipse.core.internal.resources.ResourceException",
      "message": "A resource exists with a  different case: /iii.",
      "elements": [
        {
          "method": "org.eclipse.core.internal.resources.Resource.checkDoesNotExist",
          "source": "Unknown Source"
        },
        {
          "method": "org.eclipse.core.internal.resources.Project.create",
          "source": "Unknown Source"
        },
        {
          "method": "org.eclipse.jdt.internal.ui.wizards.buildpaths.BuildPathsBlock.createProject",
          "source": "Unknown Source"
        },
        {
          "method": "org.eclipse.jdt.ui.wizards.JavaCapabilityConfigurationPage.createProject",
          "source": "Unknown Source"
        },
        {
          "method": "org.eclipse.jdt.internal.ui.wizards.JavaProjectWizardSecondPage.updateProject",
          "source": "Unknown Source"
        },
        {
          "method": "org.eclipse.jdt.internal.ui.wizards.JavaProjectWizardSecondPage$1.run",
          "source": "Unknown Source"
        },
        {
          "method": "org.eclipse.ui.actions.WorkspaceModifyDelegatingOperation.execute",
          "source": "Unknown Source"
        },
        {
          "method": "org.eclipse.ui.actions.WorkspaceModifyOperation$1.run",
          "source": "Unknown Source"
        },
        {
          "method": "org.eclipse.core.internal.resources.Workspace.run",
          "source": "Unknown Source"
        },
        {
          "method": "org.eclipse.ui.actions.WorkspaceModifyOperation.run",
          "source": "Unknown Source"
        },
        {
          "method": "org.eclipse.jface.operation.ModalContext$ModalContextThread.run",
          "source": "Unknown Source"
        }
      ],
      "number": 0,
      "commentIndex": 0,
      "bugId": "81822",
      "duplicateId": "76954",
      "date": "2004-12-22T20:50:56+01:00",
      "product": "Platform",
      "component": "Resources",
      "severity": "normal"
    }
  ],
  "groupId": "76954",
  "bugId": "81822",
  "duplicateId": "76954",
  "date": "2004-12-22T20:50:56+01:00",
  "product": "Platform",
  "component": "Resources",
  "severity": "normal"
}