{
  "comments": [
    "Version: 3.1.0\nBuild id: 200412210800\n\nEMF 2.1.0\n\nI found this while playing with WebTools 1.0 M2, but it is reproducible with a\nsimple EMF example.\n\nTest:\n1. Create a new EMF project\n2. Create an example ECore model (any type will do)\n3. Open the model it created.  Should display in the standard model editor\n4. Right click on the title of the editor.  CCE should appear in the log\n\n\nException from the log:\n\njava.lang.ClassCastException\n    at org.eclipse.emf.common.ui.ViewerPane.showTitleLabelMenu(ViewerPane.java:585)\n    at org.eclipse.emf.common.ui.ViewerPane.access$1(ViewerPane.java:580)\n    at org.eclipse.emf.common.ui.ViewerPane$5.mouseDown(ViewerPane.java:348)\n    at org.eclipse.swt.widgets.TypedListener.handleEvent(TypedListener.java:132)\n    at org.eclipse.swt.widgets.EventTable.sendEvent(EventTable.java:82)\n    at org.eclipse.swt.widgets.Widget.sendEvent(Widget.java:833)\n    at org.eclipse.swt.widgets.Display.runDeferredEvents(Display.java:2809)\n    at org.eclipse.swt.widgets.Display.readAndDispatch(Display.java:2454)\n    at org.eclipse.ui.internal.Workbench.runEventLoop(Workbench.java:1569)\n    at org.eclipse.ui.internal.Workbench.runUI(Workbench.java:1540)\n    at org.eclipse.ui.internal.Workbench.createAndRunWorkbench(Workbench.java:285)\n    at org.eclipse.ui.PlatformUI.createAndRunWorkbench(PlatformUI.java:144)\n    at org.eclipse.ui.internal.ide.IDEApplication.run(IDEApplication.java:102)\n    at\norg.eclipse.core.internal.runtime.PlatformActivator$1.run(PlatformActivator.java:220)\n    at org.eclipse.core.runtime.adaptor.EclipseStarter.run(EclipseStarter.java:273)\n    at org.eclipse.core.runtime.adaptor.EclipseStarter.run(EclipseStarter.java:129)\n    at sun.reflect.NativeMethodAccessorImpl.invoke0(Native Method)\n    at sun.reflect.NativeMethodAccessorImpl.invoke(Unknown Source)\n    at sun.reflect.DelegatingMethodAccessorImpl.invoke(Unknown Source)\n    at java.lang.reflect.Method.invoke(Unknown Source)\n    at org.eclipse.core.launcher.Main.basicRun(Main.java:185)\n    at org.eclipse.core.launcher.Main.run(Main.java:710)\n    at org.eclipse.core.launcher.Main.main(Main.java:694)",
    "There seems to be a CTabFolder there now.  I\u0027ve committed changes to handle\neither SashForm or CTabFolder.",
    "Changes committed to Build 2.1.0.I200501041213"
  ],
  "commentCreationDates": [
    "2004-12-29T05:35:30+01:00",
    "2004-12-29T18:32:09+01:00",
    "2005-01-04T18:18:06+01:00"
  ],
  "traces": [
    {
      "exceptionType": "java.lang.ClassCastException",
      "elements": [
        {
          "method": "org.eclipse.emf.common.ui.ViewerPane.showTitleLabelMenu",
          "source": "ViewerPane.java:585"
        },
        {
          "method": "org.eclipse.emf.common.ui.ViewerPane.access$1",
          "source": "ViewerPane.java:580"
        },
        {
          "method": "org.eclipse.emf.common.ui.ViewerPane$5.mouseDown",
          "source": "ViewerPane.java:348"
        },
        {
          "method": "org.eclipse.swt.widgets.TypedListener.handleEvent",
          "source": "TypedListener.java:132"
        },
        {
          "method": "org.eclipse.swt.widgets.EventTable.sendEvent",
          "source": "EventTable.java:82"
        },
        {
          "method": "org.eclipse.swt.widgets.Widget.sendEvent",
          "source": "Widget.java:833"
        },
        {
          "method": "org.eclipse.swt.widgets.Display.runDeferredEvents",
          "source": "Display.java:2809"
        },
        {
          "method": "org.eclipse.swt.widgets.Display.readAndDispatch",
          "source": "Display.java:2454"
        },
        {
          "method": "org.eclipse.ui.internal.Workbench.runEventLoop",
          "source": "Workbench.java:1569"
        },
        {
          "method": "org.eclipse.ui.internal.Workbench.runUI",
          "source": "Workbench.java:1540"
        },
        {
          "method": "org.eclipse.ui.internal.Workbench.createAndRunWorkbench",
          "source": "Workbench.java:285"
        },
        {
          "method": "org.eclipse.ui.PlatformUI.createAndRunWorkbench",
          "source": "PlatformUI.java:144"
        },
        {
          "method": "org.eclipse.ui.internal.ide.IDEApplication.run",
          "source": "IDEApplication.java:102"
        },
        {
          "method": "org.eclipse.core.internal.runtime.PlatformActivator$1.run",
          "source": "PlatformActivator.java:220"
        },
        {
          "method": "org.eclipse.core.runtime.adaptor.EclipseStarter.run",
          "source": "EclipseStarter.java:273"
        },
        {
          "method": "org.eclipse.core.runtime.adaptor.EclipseStarter.run",
          "source": "EclipseStarter.java:129"
        },
        {
          "method": "sun.reflect.NativeMethodAccessorImpl.invoke0",
          "source": "Native Method"
        },
        {
          "method": "sun.reflect.NativeMethodAccessorImpl.invoke",
          "source": "Unknown Source"
        },
        {
          "method": "sun.reflect.DelegatingMethodAccessorImpl.invoke",
          "source": "Unknown Source"
        },
        {
          "method": "java.lang.reflect.Method.invoke",
          "source": "Unknown Source"
        },
        {
          "method": "org.eclipse.core.launcher.Main.basicRun",
          "source": "Main.java:185"
        },
        {
          "method": "org.eclipse.core.launcher.Main.run",
          "source": "Main.java:710"
        },
        {
          "method": "org.eclipse.core.launcher.Main.main",
          "source": "Main.java:694"
        }
      ],
      "number": 0,
      "commentIndex": 0,
      "bugId": "81977",
      "date": "2004-12-29T05:35:30+01:00",
      "product": "EMF",
      "component": "Edit",
      "severity": "minor"
    }
  ],
  "groupId": "81977",
  "bugId": "81977",
  "date": "2004-12-29T05:35:30+01:00",
  "product": "EMF",
  "component": "Edit",
  "severity": "minor"
}