{
  "comments": [
    "Exact Version is 3.1M2.\nDon\u0027t know how to reproduce.\nEclipse has to be restarted after this.\n\n!MESSAGE Problems occurred when invoking code from plug-\nin: \"org.eclipse.core.runtime\".\n!STACK 0\njava.lang.NullPointerException\n        at org.eclipse.jface.text.SequentialRewriteTextStore.get\n(SequentialRewriteTextStore.java:136)\n        at org.eclipse.jface.text.AbstractDocument.get\n(AbstractDocument.java:905)\n        at org.eclipse.jface.text.TextSelection.getText(TextSelection.java:142)\n        at \norg.eclipse.debug.internal.ui.stringsubstitution.SelectedResourceManager.select\nionChanged(SelectedResourceManager.java:169)\n        at \norg.eclipse.debug.internal.ui.stringsubstitution.SelectedResourceManager.window\nActivated(SelectedResourceManager.java:106)\n        at org.eclipse.ui.internal.Workbench$6.run(Workbench.java:389)\n        at org.eclipse.core.internal.runtime.InternalPlatform.run\n(InternalPlatform.java:616)\n        at org.eclipse.core.runtime.Platform.run(Platform.java:747)\n        at org.eclipse.ui.internal.Workbench.fireWindowActivated\n(Workbench.java:387)\n        at org.eclipse.ui.internal.WorkbenchWindow$5.shellActivated\n(WorkbenchWindow.java:2200)\n        at org.eclipse.swt.widgets.TypedListener.handleEvent\n(TypedListener.java:163)\n        at org.eclipse.swt.widgets.EventTable.sendEvent(EventTable.java:82)\n        at org.eclipse.swt.widgets.Widget.sendEvent(Widget.java:973)\n        at org.eclipse.swt.widgets.Widget.sendEvent(Widget.java:997)\n        at org.eclipse.swt.widgets.Widget.sendEvent(Widget.java:978)\n        at org.eclipse.swt.widgets.Shell.gtk_focus_in_event(Shell.java:789)\n        at org.eclipse.swt.widgets.Widget.windowProc(Widget.java:1226)\n        at org.eclipse.swt.widgets.Display.windowProc(Display.java:3166)\n        at org.eclipse.swt.internal.gtk.OS.gtk_main_do_event(Native Method)\n        at org.eclipse.swt.widgets.Display.eventProc(Display.java:902)\n        at org.eclipse.swt.internal.gtk.OS.gtk_main_iteration(Native Method)\n        at org.eclipse.swt.widgets.Display.readAndDispatch(Display.java:2361)\n        at org.eclipse.jface.window.Window.runEventLoop(Window.java:706)\n        at org.eclipse.jface.window.Window.open(Window.java:684)\n        at org.eclipse.jface.dialogs.MessageDialog.openError\n(MessageDialog.java:319)\n        at org.eclipse.jface.util.SafeRunnable.handleException\n(SafeRunnable.java:53)\n        at org.eclipse.core.internal.runtime.InternalPlatform.handleException\n(InternalPlatform.java:350)\n        at org.eclipse.core.internal.runtime.InternalPlatform.run\n(InternalPlatform.java:618)\n        at org.eclipse.core.runtime.Platform.run(Platform.java:747)\n        at org.eclipse.ui.internal.Workbench.fireWindowActivated\n(Workbench.java:387)\n        at org.eclipse.ui.internal.WorkbenchWindow$5.shellActivated\n(WorkbenchWindow.java:2200)\n        at org.eclipse.swt.widgets.TypedListener.handleEvent\n(TypedListener.java:163)\n        at org.eclipse.swt.widgets.EventTable.sendEvent(EventTable.java:82)\n        at org.eclipse.swt.widgets.Widget.sendEvent(Widget.java:973)\n        at org.eclipse.swt.widgets.Widget.sendEvent(Widget.java:997)\n        at org.eclipse.swt.widgets.Widget.sendEvent(Widget.java:978)\n        at org.eclipse.swt.widgets.Shell.gtk_focus_in_event(Shell.java:789)\n        at org.eclipse.swt.widgets.Widget.windowProc(Widget.java:1226)\n        at org.eclipse.swt.widgets.Display.windowProc(Display.java:3166)\n        at org.eclipse.swt.internal.gtk.OS.gtk_main_do_event(Native Method)\n        at org.eclipse.swt.widgets.Display.eventProc(Display.java:902)\n        at org.eclipse.swt.internal.gtk.OS.gtk_main_iteration(Native Method)\n        at org.eclipse.swt.widgets.Display.readAndDispatch(Display.java:2361)\n        at org.eclipse.jface.window.Window.runEventLoop(Window.java:706)\n        at org.eclipse.jface.window.Window.open(Window.java:684)\n        at org.eclipse.jface.dialogs.MessageDialog.openError\n(MessageDialog.java:319)\n        at org.eclipse.jface.util.SafeRunnable.handleException\n(SafeRunnable.java:53)\n        at org.eclipse.core.internal.runtime.InternalPlatform.handleException\n(InternalPlatform.java:350)\n        at org.eclipse.core.internal.runtime.InternalPlatform.run\n(InternalPlatform.java:618)\n        at org.eclipse.core.runtime.Platform.run(Platform.java:747)\n        at org.eclipse.ui.internal.Workbench.fireWindowActivated\n(Workbench.java:387)\n        at org.eclipse.ui.internal.WorkbenchWindow$5.shellActivated\n(WorkbenchWindow.java:2200)\n        at org.eclipse.swt.widgets.TypedListener.handleEvent\n(TypedListener.java:163)\n        at org.eclipse.swt.widgets.EventTable.sendEvent(EventTable.java:82)\n        at org.eclipse.swt.widgets.Widget.sendEvent(Widget.java:973)\n        at org.eclipse.swt.widgets.Widget.sendEvent(Widget.java:997)\n        at org.eclipse.swt.widgets.Widget.sendEvent(Widget.java:978)\n        at org.eclipse.swt.widgets.Shell.gtk_focus_in_event(Shell.java:789)\n        at org.eclipse.swt.widgets.Widget.windowProc(Widget.java:1226)\n        at org.eclipse.swt.widgets.Display.windowProc(Display.java:3166)\n        at org.eclipse.swt.internal.gtk.OS.gtk_main_do_event(Native Method)\n        at org.eclipse.swt.widgets.Display.eventProc(Display.java:902)\n        at org.eclipse.swt.internal.gtk.OS.gtk_main_iteration(Native Method)\n        at org.eclipse.swt.widgets.Display.readAndDispatch(Display.java:2361)\n        at org.eclipse.jface.window.Window.runEventLoop(Window.java:706)\n        at org.eclipse.jface.window.Window.open(Window.java:684)\n        at org.eclipse.jface.dialogs.MessageDialog.openError\n(MessageDialog.java:319)\n        at org.eclipse.jface.util.SafeRunnable.handleException\n(SafeRunnable.java:53)\n        at org.eclipse.core.internal.runtime.InternalPlatform.handleException\n(InternalPlatform.java:350)\n        at org.eclipse.core.internal.runtime.InternalPlatform.run\n(InternalPlatform.java:618)\n        at org.eclipse.core.runtime.Platform.run(Platform.java:747)\n        at org.eclipse.ui.internal.Workbench.fireWindowActivated\n(Workbench.java:387)\n        at org.eclipse.ui.internal.WorkbenchWindow$5.shellActivated\n(WorkbenchWindow.java:2200)\n        at org.eclipse.swt.widgets.TypedListener.handleEvent\n(TypedListener.java:163)\n        at org.eclipse.swt.widgets.EventTable.sendEvent(EventTable.java:82)\n        at org.eclipse.swt.widgets.Widget.sendEvent(Widget.java:973)\n        at org.eclipse.swt.widgets.Widget.sendEvent(Widget.java:997)\n        at org.eclipse.swt.widgets.Widget.sendEvent(Widget.java:978)\n        at org.eclipse.swt.widgets.Shell.gtk_focus_in_event(Shell.java:789)\n        at org.eclipse.swt.widgets.Widget.windowProc(Widget.java:1226)\n        at org.eclipse.swt.widgets.Display.windowProc(Display.java:3166)\n        at org.eclipse.swt.internal.gtk.OS.gtk_main_do_event(Native Method)\n        at org.eclipse.swt.widgets.Display.eventProc(Display.java:902)\n        at org.eclipse.swt.internal.gtk.OS.gtk_main_iteration(Native Method)\n        at org.eclipse.swt.widgets.Display.readAndDispatch(Display.java:2361)\n        at org.eclipse.jface.window.Window.runEventLoop(Window.java:706)\n        at org.eclipse.jface.window.Window.open(Window.java:684)\n        at org.eclipse.jface.dialogs.MessageDialog.openError\n(MessageDialog.java:319)\n        at org.eclipse.jface.util.SafeRunnable.handleException\n(SafeRunnable.java:53)\n        at org.eclipse.core.internal.runtime.InternalPlatform.handleException\n(InternalPlatform.java:350)\n        at org.eclipse.core.internal.runtime.InternalPlatform.run\n(InternalPlatform.java:618)\n        at org.eclipse.core.runtime.Platform.run(Platform.java:747)\n        at org.eclipse.ui.internal.Workbench.fireWindowActivated\n(Workbench.java:387)\n        at org.eclipse.ui.internal.WorkbenchWindow$5.shellActivated\n(WorkbenchWindow.java:2200)\n        at org.eclipse.swt.widgets.TypedListener.handleEvent\n(TypedListener.java:163)\n        at org.eclipse.swt.widgets.EventTable.sendEvent(EventTable.java:82)\n        at org.eclipse.swt.widgets.Widget.sendEvent(Widget.java:973)\n        at org.eclipse.swt.widgets.Widget.sendEvent(Widget.java:997)\n        at org.eclipse.swt.widgets.Widget.sendEvent(Widget.java:978)\n        at org.eclipse.swt.widgets.Shell.gtk_focus_in_event(Shell.java:789)\n        at org.eclipse.swt.widgets.Widget.windowProc(Widget.java:1226)\n        at org.eclipse.swt.widgets.Display.windowProc(Display.java:3166)\n        at org.eclipse.swt.internal.gtk.OS.gtk_main_do_event(Native Method)\n        at org.eclipse.swt.widgets.Display.eventProc(Display.java:902)\n        at org.eclipse.swt.internal.gtk.OS.gtk_main_iteration(Native Method)\n        at org.eclipse.swt.widgets.Display.readAndDispatch(Display.java:2361)\n        at org.eclipse.ui.internal.Workbench.runEventLoop(Workbench.java:1443)\n        at org.eclipse.ui.internal.Workbench.runUI(Workbench.java:1414)\n        at org.eclipse.ui.internal.Workbench.createAndRunWorkbench\n(Workbench.java:271)\n        at org.eclipse.ui.PlatformUI.createAndRunWorkbench(PlatformUI.java:144)\n        at org.eclipse.ui.internal.ide.IDEApplication.run\n(IDEApplication.java:102)\n        at org.eclipse.core.internal.runtime.PlatformActivator$1.run\n(PlatformActivator.java:335)\n        at org.eclipse.core.runtime.adaptor.EclipseStarter.run\n(EclipseStarter.java:273)\n        at org.eclipse.core.runtime.adaptor.EclipseStarter.run\n(EclipseStarter.java:129)\n        at sun.reflect.NativeMethodAccessorImpl.invoke0(Native Method)\n        at sun.reflect.NativeMethodAccessorImpl.invoke\n(NativeMethodAccessorImpl.java:39)\n        at sun.reflect.DelegatingMethodAccessorImpl.invoke\n(DelegatingMethodAccessorImpl.java:25)\n        at java.lang.reflect.Method.invoke(Method.java:324)\n        at org.eclipse.core.launcher.Main.basicRun(Main.java:185)\n        at org.eclipse.core.launcher.Main.run(Main.java:704)\n        at org.eclipse.core.launcher.Main.main(Main.java:688)",
    "*** Bug 82321 has been marked as a duplicate of this bug. ***",
    "Sorry but we need more info to track this down.\nDid you install additional plug-ins?",
    "I have CDT 2.0.2 installed",
    "Get rid of deprecated state.",
    "."
  ],
  "commentCreationDates": [
    "2005-01-06T14:26:06+01:00",
    "2005-01-06T14:49:13+01:00",
    "2005-01-06T16:20:24+01:00",
    "2005-01-09T06:38:21+01:00",
    "2007-06-22T15:59:17+02:00",
    "2007-06-22T16:04:32+02:00"
  ],
  "traces": [
    {
      "exceptionType": "java.lang.NullPointerException",
      "elements": [
        {
          "method": "org.eclipse.jface.text.SequentialRewriteTextStore.get",
          "source": "SequentialRewriteTextStore.java:136"
        },
        {
          "method": "org.eclipse.jface.text.AbstractDocument.get",
          "source": "AbstractDocument.java:905"
        },
        {
          "method": "org.eclipse.jface.text.TextSelection.getText",
          "source": "TextSelection.java:142"
        },
        {
          "method": "org.eclipse.debug.internal.ui.stringsubstitution.SelectedResourceManager.selectionChanged",
          "source": "SelectedResourceManager.java:169"
        },
        {
          "method": "org.eclipse.debug.internal.ui.stringsubstitution.SelectedResourceManager.windowActivated",
          "source": "SelectedResourceManager.java:106"
        },
        {
          "method": "org.eclipse.ui.internal.Workbench$6.run",
          "source": "Workbench.java:389"
        },
        {
          "method": "org.eclipse.core.internal.runtime.InternalPlatform.run",
          "source": "InternalPlatform.java:616"
        },
        {
          "method": "org.eclipse.core.runtime.Platform.run",
          "source": "Platform.java:747"
        },
        {
          "method": "org.eclipse.ui.internal.Workbench.fireWindowActivated",
          "source": "Workbench.java:387"
        },
        {
          "method": "org.eclipse.ui.internal.WorkbenchWindow$5.shellActivated",
          "source": "WorkbenchWindow.java:2200"
        },
        {
          "method": "org.eclipse.swt.widgets.TypedListener.handleEvent",
          "source": "TypedListener.java:163"
        },
        {
          "method": "org.eclipse.swt.widgets.EventTable.sendEvent",
          "source": "EventTable.java:82"
        },
        {
          "method": "org.eclipse.swt.widgets.Widget.sendEvent",
          "source": "Widget.java:973"
        },
        {
          "method": "org.eclipse.swt.widgets.Widget.sendEvent",
          "source": "Widget.java:997"
        },
        {
          "method": "org.eclipse.swt.widgets.Widget.sendEvent",
          "source": "Widget.java:978"
        },
        {
          "method": "org.eclipse.swt.widgets.Shell.gtk_focus_in_event",
          "source": "Shell.java:789"
        },
        {
          "method": "org.eclipse.swt.widgets.Widget.windowProc",
          "source": "Widget.java:1226"
        },
        {
          "method": "org.eclipse.swt.widgets.Display.windowProc",
          "source": "Display.java:3166"
        },
        {
          "method": "org.eclipse.swt.internal.gtk.OS.gtk_main_do_event",
          "source": "Native Method"
        },
        {
          "method": "org.eclipse.swt.widgets.Display.eventProc",
          "source": "Display.java:902"
        },
        {
          "method": "org.eclipse.swt.internal.gtk.OS.gtk_main_iteration",
          "source": "Native Method"
        },
        {
          "method": "org.eclipse.swt.widgets.Display.readAndDispatch",
          "source": "Display.java:2361"
        },
        {
          "method": "org.eclipse.jface.window.Window.runEventLoop",
          "source": "Window.java:706"
        },
        {
          "method": "org.eclipse.jface.window.Window.open",
          "source": "Window.java:684"
        },
        {
          "method": "org.eclipse.jface.dialogs.MessageDialog.openError",
          "source": "MessageDialog.java:319"
        },
        {
          "method": "org.eclipse.jface.util.SafeRunnable.handleException",
          "source": "SafeRunnable.java:53"
        },
        {
          "method": "org.eclipse.core.internal.runtime.InternalPlatform.handleException",
          "source": "InternalPlatform.java:350"
        },
        {
          "method": "org.eclipse.core.internal.runtime.InternalPlatform.run",
          "source": "InternalPlatform.java:618"
        },
        {
          "method": "org.eclipse.core.runtime.Platform.run",
          "source": "Platform.java:747"
        },
        {
          "method": "org.eclipse.ui.internal.Workbench.fireWindowActivated",
          "source": "Workbench.java:387"
        },
        {
          "method": "org.eclipse.ui.internal.WorkbenchWindow$5.shellActivated",
          "source": "WorkbenchWindow.java:2200"
        },
        {
          "method": "org.eclipse.swt.widgets.TypedListener.handleEvent",
          "source": "TypedListener.java:163"
        },
        {
          "method": "org.eclipse.swt.widgets.EventTable.sendEvent",
          "source": "EventTable.java:82"
        },
        {
          "method": "org.eclipse.swt.widgets.Widget.sendEvent",
          "source": "Widget.java:973"
        },
        {
          "method": "org.eclipse.swt.widgets.Widget.sendEvent",
          "source": "Widget.java:997"
        },
        {
          "method": "org.eclipse.swt.widgets.Widget.sendEvent",
          "source": "Widget.java:978"
        },
        {
          "method": "org.eclipse.swt.widgets.Shell.gtk_focus_in_event",
          "source": "Shell.java:789"
        },
        {
          "method": "org.eclipse.swt.widgets.Widget.windowProc",
          "source": "Widget.java:1226"
        },
        {
          "method": "org.eclipse.swt.widgets.Display.windowProc",
          "source": "Display.java:3166"
        },
        {
          "method": "org.eclipse.swt.internal.gtk.OS.gtk_main_do_event",
          "source": "Native Method"
        },
        {
          "method": "org.eclipse.swt.widgets.Display.eventProc",
          "source": "Display.java:902"
        },
        {
          "method": "org.eclipse.swt.internal.gtk.OS.gtk_main_iteration",
          "source": "Native Method"
        },
        {
          "method": "org.eclipse.swt.widgets.Display.readAndDispatch",
          "source": "Display.java:2361"
        },
        {
          "method": "org.eclipse.jface.window.Window.runEventLoop",
          "source": "Window.java:706"
        },
        {
          "method": "org.eclipse.jface.window.Window.open",
          "source": "Window.java:684"
        },
        {
          "method": "org.eclipse.jface.dialogs.MessageDialog.openError",
          "source": "MessageDialog.java:319"
        },
        {
          "method": "org.eclipse.jface.util.SafeRunnable.handleException",
          "source": "SafeRunnable.java:53"
        },
        {
          "method": "org.eclipse.core.internal.runtime.InternalPlatform.handleException",
          "source": "InternalPlatform.java:350"
        },
        {
          "method": "org.eclipse.core.internal.runtime.InternalPlatform.run",
          "source": "InternalPlatform.java:618"
        },
        {
          "method": "org.eclipse.core.runtime.Platform.run",
          "source": "Platform.java:747"
        },
        {
          "method": "org.eclipse.ui.internal.Workbench.fireWindowActivated",
          "source": "Workbench.java:387"
        },
        {
          "method": "org.eclipse.ui.internal.WorkbenchWindow$5.shellActivated",
          "source": "WorkbenchWindow.java:2200"
        },
        {
          "method": "org.eclipse.swt.widgets.TypedListener.handleEvent",
          "source": "TypedListener.java:163"
        },
        {
          "method": "org.eclipse.swt.widgets.EventTable.sendEvent",
          "source": "EventTable.java:82"
        },
        {
          "method": "org.eclipse.swt.widgets.Widget.sendEvent",
          "source": "Widget.java:973"
        },
        {
          "method": "org.eclipse.swt.widgets.Widget.sendEvent",
          "source": "Widget.java:997"
        },
        {
          "method": "org.eclipse.swt.widgets.Widget.sendEvent",
          "source": "Widget.java:978"
        },
        {
          "method": "org.eclipse.swt.widgets.Shell.gtk_focus_in_event",
          "source": "Shell.java:789"
        },
        {
          "method": "org.eclipse.swt.widgets.Widget.windowProc",
          "source": "Widget.java:1226"
        },
        {
          "method": "org.eclipse.swt.widgets.Display.windowProc",
          "source": "Display.java:3166"
        },
        {
          "method": "org.eclipse.swt.internal.gtk.OS.gtk_main_do_event",
          "source": "Native Method"
        },
        {
          "method": "org.eclipse.swt.widgets.Display.eventProc",
          "source": "Display.java:902"
        },
        {
          "method": "org.eclipse.swt.internal.gtk.OS.gtk_main_iteration",
          "source": "Native Method"
        },
        {
          "method": "org.eclipse.swt.widgets.Display.readAndDispatch",
          "source": "Display.java:2361"
        },
        {
          "method": "org.eclipse.jface.window.Window.runEventLoop",
          "source": "Window.java:706"
        },
        {
          "method": "org.eclipse.jface.window.Window.open",
          "source": "Window.java:684"
        },
        {
          "method": "org.eclipse.jface.dialogs.MessageDialog.openError",
          "source": "MessageDialog.java:319"
        },
        {
          "method": "org.eclipse.jface.util.SafeRunnable.handleException",
          "source": "SafeRunnable.java:53"
        },
        {
          "method": "org.eclipse.core.internal.runtime.InternalPlatform.handleException",
          "source": "InternalPlatform.java:350"
        },
        {
          "method": "org.eclipse.core.internal.runtime.InternalPlatform.run",
          "source": "InternalPlatform.java:618"
        },
        {
          "method": "org.eclipse.core.runtime.Platform.run",
          "source": "Platform.java:747"
        },
        {
          "method": "org.eclipse.ui.internal.Workbench.fireWindowActivated",
          "source": "Workbench.java:387"
        },
        {
          "method": "org.eclipse.ui.internal.WorkbenchWindow$5.shellActivated",
          "source": "WorkbenchWindow.java:2200"
        },
        {
          "method": "org.eclipse.swt.widgets.TypedListener.handleEvent",
          "source": "TypedListener.java:163"
        },
        {
          "method": "org.eclipse.swt.widgets.EventTable.sendEvent",
          "source": "EventTable.java:82"
        },
        {
          "method": "org.eclipse.swt.widgets.Widget.sendEvent",
          "source": "Widget.java:973"
        },
        {
          "method": "org.eclipse.swt.widgets.Widget.sendEvent",
          "source": "Widget.java:997"
        },
        {
          "method": "org.eclipse.swt.widgets.Widget.sendEvent",
          "source": "Widget.java:978"
        },
        {
          "method": "org.eclipse.swt.widgets.Shell.gtk_focus_in_event",
          "source": "Shell.java:789"
        },
        {
          "method": "org.eclipse.swt.widgets.Widget.windowProc",
          "source": "Widget.java:1226"
        },
        {
          "method": "org.eclipse.swt.widgets.Display.windowProc",
          "source": "Display.java:3166"
        },
        {
          "method": "org.eclipse.swt.internal.gtk.OS.gtk_main_do_event",
          "source": "Native Method"
        },
        {
          "method": "org.eclipse.swt.widgets.Display.eventProc",
          "source": "Display.java:902"
        },
        {
          "method": "org.eclipse.swt.internal.gtk.OS.gtk_main_iteration",
          "source": "Native Method"
        },
        {
          "method": "org.eclipse.swt.widgets.Display.readAndDispatch",
          "source": "Display.java:2361"
        },
        {
          "method": "org.eclipse.jface.window.Window.runEventLoop",
          "source": "Window.java:706"
        },
        {
          "method": "org.eclipse.jface.window.Window.open",
          "source": "Window.java:684"
        },
        {
          "method": "org.eclipse.jface.dialogs.MessageDialog.openError",
          "source": "MessageDialog.java:319"
        },
        {
          "method": "org.eclipse.jface.util.SafeRunnable.handleException",
          "source": "SafeRunnable.java:53"
        },
        {
          "method": "org.eclipse.core.internal.runtime.InternalPlatform.handleException",
          "source": "InternalPlatform.java:350"
        },
        {
          "method": "org.eclipse.core.internal.runtime.InternalPlatform.run",
          "source": "InternalPlatform.java:618"
        },
        {
          "method": "org.eclipse.core.runtime.Platform.run",
          "source": "Platform.java:747"
        },
        {
          "method": "org.eclipse.ui.internal.Workbench.fireWindowActivated",
          "source": "Workbench.java:387"
        },
        {
          "method": "org.eclipse.ui.internal.WorkbenchWindow$5.shellActivated",
          "source": "WorkbenchWindow.java:2200"
        },
        {
          "method": "org.eclipse.swt.widgets.TypedListener.handleEvent",
          "source": "TypedListener.java:163"
        },
        {
          "method": "org.eclipse.swt.widgets.EventTable.sendEvent",
          "source": "EventTable.java:82"
        },
        {
          "method": "org.eclipse.swt.widgets.Widget.sendEvent",
          "source": "Widget.java:973"
        },
        {
          "method": "org.eclipse.swt.widgets.Widget.sendEvent",
          "source": "Widget.java:997"
        },
        {
          "method": "org.eclipse.swt.widgets.Widget.sendEvent",
          "source": "Widget.java:978"
        },
        {
          "method": "org.eclipse.swt.widgets.Shell.gtk_focus_in_event",
          "source": "Shell.java:789"
        },
        {
          "method": "org.eclipse.swt.widgets.Widget.windowProc",
          "source": "Widget.java:1226"
        },
        {
          "method": "org.eclipse.swt.widgets.Display.windowProc",
          "source": "Display.java:3166"
        },
        {
          "method": "org.eclipse.swt.internal.gtk.OS.gtk_main_do_event",
          "source": "Native Method"
        },
        {
          "method": "org.eclipse.swt.widgets.Display.eventProc",
          "source": "Display.java:902"
        },
        {
          "method": "org.eclipse.swt.internal.gtk.OS.gtk_main_iteration",
          "source": "Native Method"
        },
        {
          "method": "org.eclipse.swt.widgets.Display.readAndDispatch",
          "source": "Display.java:2361"
        },
        {
          "method": "org.eclipse.ui.internal.Workbench.runEventLoop",
          "source": "Workbench.java:1443"
        },
        {
          "method": "org.eclipse.ui.internal.Workbench.runUI",
          "source": "Workbench.java:1414"
        },
        {
          "method": "org.eclipse.ui.internal.Workbench.createAndRunWorkbench",
          "source": "Workbench.java:271"
        },
        {
          "method": "org.eclipse.ui.PlatformUI.createAndRunWorkbench",
          "source": "PlatformUI.java:144"
        },
        {
          "method": "org.eclipse.ui.internal.ide.IDEApplication.run",
          "source": "IDEApplication.java:102"
        },
        {
          "method": "org.eclipse.core.internal.runtime.PlatformActivator$1.run",
          "source": "PlatformActivator.java:335"
        },
        {
          "method": "org.eclipse.core.runtime.adaptor.EclipseStarter.run",
          "source": "EclipseStarter.java:273"
        },
        {
          "method": "org.eclipse.core.runtime.adaptor.EclipseStarter.run",
          "source": "EclipseStarter.java:129"
        },
        {
          "method": "sun.reflect.NativeMethodAccessorImpl.invoke0",
          "source": "Native Method"
        },
        {
          "method": "sun.reflect.NativeMethodAccessorImpl.invoke",
          "source": "NativeMethodAccessorImpl.java:39"
        },
        {
          "method": "sun.reflect.DelegatingMethodAccessorImpl.invoke",
          "source": "DelegatingMethodAccessorImpl.java:25"
        },
        {
          "method": "java.lang.reflect.Method.invoke",
          "source": "Method.java:324"
        },
        {
          "method": "org.eclipse.core.launcher.Main.basicRun",
          "source": "Main.java:185"
        },
        {
          "method": "org.eclipse.core.launcher.Main.run",
          "source": "Main.java:704"
        },
        {
          "method": "org.eclipse.core.launcher.Main.main",
          "source": "Main.java:688"
        }
      ],
      "number": 0,
      "commentIndex": 0,
      "bugId": "82320",
      "date": "2005-01-06T14:26:06+01:00",
      "product": "Platform",
      "component": "Text",
      "severity": "normal"
    }
  ],
  "groupId": "82320",
  "bugId": "82320",
  "date": "2005-01-06T14:26:06+01:00",
  "product": "Platform",
  "component": "Text",
  "severity": "normal"
}