{
  "comments": [
    "When trying to build james.apache.org v2.2.0 in eclipse I get the below error\nand the project does not build.\nWhen building with ant on the cygwin command-line, all appears to be fine. What\nam I doing wrong?\n\n\u003c\u003c!ENTRY org.eclipse.jdt.core 4 4 Jan 08, 2005 17:39:11.623\n!MESSAGE JavaBuilder handling ImageBuilderInternalException while building: sPop2\n!STACK 1\norg.eclipse.core.internal.resources.ResourceException: A resource exists with a\ndifferent case: /sPop2/bin/org/apache/ja\nmes/imapserver/IMAPServer.xinfo.\n        at\norg.eclipse.core.internal.resources.Resource.checkDoesNotExist(Resource.java:280)\n        at\norg.eclipse.core.internal.resources.Resource.checkCopyRequirements(Resource.java:213)\n        at\norg.eclipse.core.internal.resources.Resource.assertCopyRequirements(Resource.java:136)\n        at org.eclipse.core.internal.resources.Resource.copy(Resource.java:540)\n        at\norg.eclipse.jdt.internal.core.builder.BatchImageBuilder$4.visit(BatchImageBuilder.java:226)\n        at\norg.eclipse.core.internal.resources.Resource$1.visitElement(Resource.java:55)\n        at\norg.eclipse.core.internal.watson.ElementTreeIterator.doIteration(ElementTreeIterator.java:78)\n        at\norg.eclipse.core.internal.watson.ElementTreeIterator.doIteration(ElementTreeIterator.java:82)\n        at\norg.eclipse.core.internal.watson.ElementTreeIterator.doIteration(ElementTreeIterator.java:82)\n        at\norg.eclipse.core.internal.watson.ElementTreeIterator.doIteration(ElementTreeIterator.java:82)\n        at\norg.eclipse.core.internal.watson.ElementTreeIterator.doIteration(ElementTreeIterator.java:82)\n        at\norg.eclipse.core.internal.watson.ElementTreeIterator.doIteration(ElementTreeIterator.java:82)\n        at\norg.eclipse.core.internal.watson.ElementTreeIterator.iterate(ElementTreeIterator.java:123)\n        at org.eclipse.core.internal.resources.Resource.accept(Resource.java:65)\n        at\norg.eclipse.jdt.internal.core.builder.BatchImageBuilder.copyExtraResourcesBack(BatchImageBuilder.java:197)\n        at\norg.eclipse.jdt.internal.core.builder.BatchImageBuilder.cleanOutputFolders(BatchImageBuilder.java:130)\n        at\norg.eclipse.jdt.internal.core.builder.BatchImageBuilder.build(BatchImageBuilder.java:35)\n        at\norg.eclipse.jdt.internal.core.builder.JavaBuilder.buildAll(JavaBuilder.java:213)\n        at\norg.eclipse.jdt.internal.core.builder.JavaBuilder.build(JavaBuilder.java:141)\n        at\norg.eclipse.core.internal.events.BuildManager$2.run(BuildManager.java:570)\n        at\norg.eclipse.core.internal.runtime.InternalPlatform.run(InternalPlatform.java:616)\n        at org.eclipse.core.runtime.Platform.run(Platform.java:747)\n        at\norg.eclipse.core.internal.events.BuildManager.basicBuild(BuildManager.java:159)\n        at\norg.eclipse.core.internal.events.BuildManager.basicBuild(BuildManager.java:251)\n        at\norg.eclipse.core.internal.events.BuildManager.basicBuild(BuildManager.java:204)\n        at\norg.eclipse.core.internal.events.BuildManager$1.run(BuildManager.java:231)\n        at\norg.eclipse.core.internal.runtime.InternalPlatform.run(InternalPlatform.java:616)\n        at org.eclipse.core.runtime.Platform.run(Platform.java:747)\n        at\norg.eclipse.core.internal.events.BuildManager.basicBuild(BuildManager.java:234)\n        at\norg.eclipse.core.internal.events.BuildManager.build(BuildManager.java:330)\n        at org.eclipse.core.internal.resources.Project.build(Project.java:105)\n!ENTRY org.eclipse.jdt.core 4 4 Jan 08, 2005 17:39:11.623\n!MESSAGE JavaBuilder handling ImageBuilderInternalException while building: sPop2\n!STACK 1\norg.eclipse.core.internal.resources.ResourceException: A resource exists with a\ndifferent case: /sPop2/bin/org/apache/ja\nmes/imapserver/IMAPServer.xinfo.\n        at\norg.eclipse.core.internal.resources.Resource.checkDoesNotExist(Resource.java:280)\n        at\norg.eclipse.core.internal.resources.Resource.checkCopyRequirements(Resource.java:213)\n        at\norg.eclipse.core.internal.resources.Resource.assertCopyRequirements(Resource.java:136)\n        at org.eclipse.core.internal.resources.Resource.copy(Resource.java:540)\n        at\norg.eclipse.jdt.internal.core.builder.BatchImageBuilder$4.visit(BatchImageBuilder.java:226)\n        at\norg.eclipse.core.internal.resources.Resource$1.visitElement(Resource.java:55)\n        at\norg.eclipse.core.internal.watson.ElementTreeIterator.doIteration(ElementTreeIterator.java:78)\n        at\norg.eclipse.core.internal.watson.ElementTreeIterator.doIteration(ElementTreeIterator.java:82)\n        at\norg.eclipse.core.internal.watson.ElementTreeIterator.doIteration(ElementTreeIterator.java:82)\n        at\norg.eclipse.core.internal.watson.ElementTreeIterator.doIteration(ElementTreeIterator.java:82)\n        at\norg.eclipse.core.internal.watson.ElementTreeIterator.doIteration(ElementTreeIterator.java:82)\n        at\norg.eclipse.core.internal.watson.ElementTreeIterator.doIteration(ElementTreeIterator.java:82)\n        at\norg.eclipse.core.internal.watson.ElementTreeIterator.iterate(ElementTreeIterator.java:123)\n        at org.eclipse.core.internal.resources.Resource.accept(Resource.java:65)\n        at\norg.eclipse.jdt.internal.core.builder.BatchImageBuilder.copyExtraResourcesBack(BatchImageBuilder.java:197)\n        at\norg.eclipse.jdt.internal.core.builder.BatchImageBuilder.cleanOutputFolders(BatchImageBuilder.java:130)\n        at\norg.eclipse.jdt.internal.core.builder.BatchImageBuilder.build(BatchImageBuilder.java:35)\n        at\norg.eclipse.jdt.internal.core.builder.JavaBuilder.buildAll(JavaBuilder.java:213)\n        at\norg.eclipse.jdt.internal.core.builder.JavaBuilder.build(JavaBuilder.java:141)\n        at\norg.eclipse.core.internal.events.BuildManager$2.run(BuildManager.java:570)\n        at\norg.eclipse.core.internal.runtime.InternalPlatform.run(InternalPlatform.java:616)\n        at org.eclipse.core.runtime.Platform.run(Platform.java:747)\n        at\norg.eclipse.core.internal.events.BuildManager.basicBuild(BuildManager.java:159)\n        at\norg.eclipse.core.internal.events.BuildManager.basicBuild(BuildManager.java:251)\n        at\norg.eclipse.core.internal.events.BuildManager.basicBuild(BuildManager.java:204)\n        at\norg.eclipse.core.internal.events.BuildManager$1.run(BuildManager.java:231)\n        at\norg.eclipse.core.internal.runtime.InternalPlatform.run(InternalPlatform.java:616)\n        at org.eclipse.core.runtime.Platform.run(Platform.java:747)\n        at\norg.eclipse.core.internal.events.BuildManager.basicBuild(BuildManager.java:234)\n        at\norg.eclipse.core.internal.events.BuildManager.build(BuildManager.java:330)\n        at org.eclipse.core.internal.resources.Project.build(Project.java:105)\n        at org.eclipse.ui.actions.BuildAction.invokeOperation(BuildAction.java:169)\n        at org.eclipse.ui.actions.WorkspaceAction.execute(WorkspaceAction.java:127)\n        at org.eclipse.ui.actions.WorkspaceAction$2.run(WorkspaceAction.java:370)\n        at org.eclipse.core.internal.jobs.Worker.run(Worker.java:66)\n!SUBENTRY 1 org.eclipse.core.resources 4 275 Jan 08, 2005 17:39:11.623\n!MESSAGE A resource exists with a different case:\n/sPop2/bin/org/apache/james/imapserver/IMAPServer.xinfo.\n\nthrowing out a few src dirs (src/proposal) did help, but if that is what needs \nto be done, it would be great if the error message gave a hint into this direction.",
    "Deferring post 3.1"
  ],
  "commentCreationDates": [
    "2005-01-08T18:20:38+01:00",
    "2005-04-07T15:44:25+02:00"
  ],
  "traces": [
    {
      "exceptionType": "org.eclipse.core.internal.resources.ResourceException",
      "message": "A resource exists with a different case: /sPop2/bin/org/apache/ja mes/imapserver/IMAPServer.xinfo.",
      "elements": [
        {
          "method": "org.eclipse.core.internal.resources.Resource.checkDoesNotExist",
          "source": "Resource.java:280"
        },
        {
          "method": "org.eclipse.core.internal.resources.Resource.checkCopyRequirements",
          "source": "Resource.java:213"
        },
        {
          "method": "org.eclipse.core.internal.resources.Resource.assertCopyRequirements",
          "source": "Resource.java:136"
        },
        {
          "method": "org.eclipse.core.internal.resources.Resource.copy",
          "source": "Resource.java:540"
        },
        {
          "method": "org.eclipse.jdt.internal.core.builder.BatchImageBuilder$4.visit",
          "source": "BatchImageBuilder.java:226"
        },
        {
          "method": "org.eclipse.core.internal.resources.Resource$1.visitElement",
          "source": "Resource.java:55"
        },
        {
          "method": "org.eclipse.core.internal.watson.ElementTreeIterator.doIteration",
          "source": "ElementTreeIterator.java:78"
        },
        {
          "method": "org.eclipse.core.internal.watson.ElementTreeIterator.doIteration",
          "source": "ElementTreeIterator.java:82"
        },
        {
          "method": "org.eclipse.core.internal.watson.ElementTreeIterator.doIteration",
          "source": "ElementTreeIterator.java:82"
        },
        {
          "method": "org.eclipse.core.internal.watson.ElementTreeIterator.doIteration",
          "source": "ElementTreeIterator.java:82"
        },
        {
          "method": "org.eclipse.core.internal.watson.ElementTreeIterator.doIteration",
          "source": "ElementTreeIterator.java:82"
        },
        {
          "method": "org.eclipse.core.internal.watson.ElementTreeIterator.doIteration",
          "source": "ElementTreeIterator.java:82"
        },
        {
          "method": "org.eclipse.core.internal.watson.ElementTreeIterator.iterate",
          "source": "ElementTreeIterator.java:123"
        },
        {
          "method": "org.eclipse.core.internal.resources.Resource.accept",
          "source": "Resource.java:65"
        },
        {
          "method": "org.eclipse.jdt.internal.core.builder.BatchImageBuilder.copyExtraResourcesBack",
          "source": "BatchImageBuilder.java:197"
        },
        {
          "method": "org.eclipse.jdt.internal.core.builder.BatchImageBuilder.cleanOutputFolders",
          "source": "BatchImageBuilder.java:130"
        },
        {
          "method": "org.eclipse.jdt.internal.core.builder.BatchImageBuilder.build",
          "source": "BatchImageBuilder.java:35"
        },
        {
          "method": "org.eclipse.jdt.internal.core.builder.JavaBuilder.buildAll",
          "source": "JavaBuilder.java:213"
        },
        {
          "method": "org.eclipse.jdt.internal.core.builder.JavaBuilder.build",
          "source": "JavaBuilder.java:141"
        },
        {
          "method": "org.eclipse.core.internal.events.BuildManager$2.run",
          "source": "BuildManager.java:570"
        },
        {
          "method": "org.eclipse.core.internal.runtime.InternalPlatform.run",
          "source": "InternalPlatform.java:616"
        },
        {
          "method": "org.eclipse.core.runtime.Platform.run",
          "source": "Platform.java:747"
        },
        {
          "method": "org.eclipse.core.internal.events.BuildManager.basicBuild",
          "source": "BuildManager.java:159"
        },
        {
          "method": "org.eclipse.core.internal.events.BuildManager.basicBuild",
          "source": "BuildManager.java:251"
        },
        {
          "method": "org.eclipse.core.internal.events.BuildManager.basicBuild",
          "source": "BuildManager.java:204"
        },
        {
          "method": "org.eclipse.core.internal.events.BuildManager$1.run",
          "source": "BuildManager.java:231"
        },
        {
          "method": "org.eclipse.core.internal.runtime.InternalPlatform.run",
          "source": "InternalPlatform.java:616"
        },
        {
          "method": "org.eclipse.core.runtime.Platform.run",
          "source": "Platform.java:747"
        },
        {
          "method": "org.eclipse.core.internal.events.BuildManager.basicBuild",
          "source": "BuildManager.java:234"
        },
        {
          "method": "org.eclipse.core.internal.events.BuildManager.build",
          "source": "BuildManager.java:330"
        },
        {
          "method": "org.eclipse.core.internal.resources.Project.build",
          "source": "Project.java:105"
        }
      ],
      "number": 0,
      "commentIndex": 0,
      "bugId": "82423",
      "date": "2005-01-08T18:20:38+01:00",
      "product": "JDT",
      "component": "Core",
      "severity": "normal"
    },
    {
      "exceptionType": "org.eclipse.core.internal.resources.ResourceException",
      "message": "A resource exists with a different case: /sPop2/bin/org/apache/ja mes/imapserver/IMAPServer.xinfo.",
      "elements": [
        {
          "method": "org.eclipse.core.internal.resources.Resource.checkDoesNotExist",
          "source": "Resource.java:280"
        },
        {
          "method": "org.eclipse.core.internal.resources.Resource.checkCopyRequirements",
          "source": "Resource.java:213"
        },
        {
          "method": "org.eclipse.core.internal.resources.Resource.assertCopyRequirements",
          "source": "Resource.java:136"
        },
        {
          "method": "org.eclipse.core.internal.resources.Resource.copy",
          "source": "Resource.java:540"
        },
        {
          "method": "org.eclipse.jdt.internal.core.builder.BatchImageBuilder$4.visit",
          "source": "BatchImageBuilder.java:226"
        },
        {
          "method": "org.eclipse.core.internal.resources.Resource$1.visitElement",
          "source": "Resource.java:55"
        },
        {
          "method": "org.eclipse.core.internal.watson.ElementTreeIterator.doIteration",
          "source": "ElementTreeIterator.java:78"
        },
        {
          "method": "org.eclipse.core.internal.watson.ElementTreeIterator.doIteration",
          "source": "ElementTreeIterator.java:82"
        },
        {
          "method": "org.eclipse.core.internal.watson.ElementTreeIterator.doIteration",
          "source": "ElementTreeIterator.java:82"
        },
        {
          "method": "org.eclipse.core.internal.watson.ElementTreeIterator.doIteration",
          "source": "ElementTreeIterator.java:82"
        },
        {
          "method": "org.eclipse.core.internal.watson.ElementTreeIterator.doIteration",
          "source": "ElementTreeIterator.java:82"
        },
        {
          "method": "org.eclipse.core.internal.watson.ElementTreeIterator.doIteration",
          "source": "ElementTreeIterator.java:82"
        },
        {
          "method": "org.eclipse.core.internal.watson.ElementTreeIterator.iterate",
          "source": "ElementTreeIterator.java:123"
        },
        {
          "method": "org.eclipse.core.internal.resources.Resource.accept",
          "source": "Resource.java:65"
        },
        {
          "method": "org.eclipse.jdt.internal.core.builder.BatchImageBuilder.copyExtraResourcesBack",
          "source": "BatchImageBuilder.java:197"
        },
        {
          "method": "org.eclipse.jdt.internal.core.builder.BatchImageBuilder.cleanOutputFolders",
          "source": "BatchImageBuilder.java:130"
        },
        {
          "method": "org.eclipse.jdt.internal.core.builder.BatchImageBuilder.build",
          "source": "BatchImageBuilder.java:35"
        },
        {
          "method": "org.eclipse.jdt.internal.core.builder.JavaBuilder.buildAll",
          "source": "JavaBuilder.java:213"
        },
        {
          "method": "org.eclipse.jdt.internal.core.builder.JavaBuilder.build",
          "source": "JavaBuilder.java:141"
        },
        {
          "method": "org.eclipse.core.internal.events.BuildManager$2.run",
          "source": "BuildManager.java:570"
        },
        {
          "method": "org.eclipse.core.internal.runtime.InternalPlatform.run",
          "source": "InternalPlatform.java:616"
        },
        {
          "method": "org.eclipse.core.runtime.Platform.run",
          "source": "Platform.java:747"
        },
        {
          "method": "org.eclipse.core.internal.events.BuildManager.basicBuild",
          "source": "BuildManager.java:159"
        },
        {
          "method": "org.eclipse.core.internal.events.BuildManager.basicBuild",
          "source": "BuildManager.java:251"
        },
        {
          "method": "org.eclipse.core.internal.events.BuildManager.basicBuild",
          "source": "BuildManager.java:204"
        },
        {
          "method": "org.eclipse.core.internal.events.BuildManager$1.run",
          "source": "BuildManager.java:231"
        },
        {
          "method": "org.eclipse.core.internal.runtime.InternalPlatform.run",
          "source": "InternalPlatform.java:616"
        },
        {
          "method": "org.eclipse.core.runtime.Platform.run",
          "source": "Platform.java:747"
        },
        {
          "method": "org.eclipse.core.internal.events.BuildManager.basicBuild",
          "source": "BuildManager.java:234"
        },
        {
          "method": "org.eclipse.core.internal.events.BuildManager.build",
          "source": "BuildManager.java:330"
        },
        {
          "method": "org.eclipse.core.internal.resources.Project.build",
          "source": "Project.java:105"
        },
        {
          "method": "org.eclipse.ui.actions.BuildAction.invokeOperation",
          "source": "BuildAction.java:169"
        },
        {
          "method": "org.eclipse.ui.actions.WorkspaceAction.execute",
          "source": "WorkspaceAction.java:127"
        },
        {
          "method": "org.eclipse.ui.actions.WorkspaceAction$2.run",
          "source": "WorkspaceAction.java:370"
        },
        {
          "method": "org.eclipse.core.internal.jobs.Worker.run",
          "source": "Worker.java:66"
        }
      ],
      "number": 1,
      "commentIndex": 0,
      "bugId": "82423",
      "date": "2005-01-08T18:20:38+01:00",
      "product": "JDT",
      "component": "Core",
      "severity": "normal"
    }
  ],
  "groupId": "82423",
  "bugId": "82423",
  "date": "2005-01-08T18:20:38+01:00",
  "product": "JDT",
  "component": "Core",
  "severity": "normal"
}