{
  "comments": [
    "At seemingly random times I get the \u0027xxx is not a child of folder yyy\u0027 error  \nmessage from Eclipse team. The server is a windows cvs server (using pserver \nto connect), and I\u0027ve only seen it happen on binary resources. \n \nHere is a full log of my console. My current Eclipse version is 3.1M4. If  \nanyone has any idea how to get around this please tell me! I\u0027m kind of dead in  \nthe water right now :) \n \nRoot /cvs/moelleryoung \nCMD\u003e cvs version \nversion \nM Concurrent Versions System (CVSNT) 2.0.58d (client/server) \nok \nRESULT\u003e Status OK: org.eclipse.team.cvs.core code\u003d0 ok null \nCMD\u003e cvs -n update -d \"/MyJSDebug\" \nGlobal_option -n \nArgument -d \nDirectory . \n/cvs/xxx/MyJSDebug \nEntry /.classpath/1.1/// \nUnchanged .classpath \nEntry /.cvsignore/1.1/// \nUnchanged .cvsignore \nEntry /.project/1.1/// \nUnchanged .project \nEntry /build.properties/1.1/// \nUnchanged build.properties \nEntry /plugin.xml/1.2/// \nUnchanged plugin.xml \nDirectory icons \n/cvs/moelleryoung/MyJSDebug/icons \nEntry /sample.gif/1.1//-kb/ \nUnchanged sample.gif \nDirectory src \n/cvs/moelleryoung/MyJSDebug/src \nDirectory src/com \n/cvs/moelleryoung/MyJSDebug/src/com \nDirectory src/com/my \n/cvs/moelleryoung/MyJSDebug/src/com/my \nDirectory src/com/my/jsdebug \n/cvs/moelleryoung/MyJSDebug/src/com/my/jsdebug \nEntry /MyJSDebugPlugin.java/1.1/// \nUnchanged MyJSDebugPlugin.java \nDirectory src/com/my/jsdebug/debugger \n/cvs/moelleryoung/MyJSDebug/src/com/my/jsdebug/debugger \nEntry /JSExecutorListener.java/1.1/// \nUnchanged JSExecutorListener.java \nEntry /JavaScriptExecutor.java/1.2/// \nUnchanged JavaScriptExecutor.java \nDirectory src/com/my/jsdebug/debugger/actions \n/cvs/moelleryoung/MyJSDebug/src/com/my/jsdebug/debugger/actions \nEntry /ExecuteJavaScript.java/1.1/// \nUnchanged ExecuteJavaScript.java \nDirectory src/com/my/jsdebug/test \n/cvs/moelleryoung/MyJSDebug/src/com/my/jsdebug/test \nEntry /BreakTester.java/1.2/// \nUnchanged BreakTester.java \nArgument . \nDirectory . \n/cvs/moelleryoung/MyJSDebug \nupdate \nE cvs server: Updating . \nMT +updated \nMT text U \nMT fname plugin.xml \nMT newline \nMT -updated \nE cvs server: Updating icons \nE cvs server: Updating icons/dtool16 \nMT +updated \nMT text U \nMT fname icons/dtool16/debug_exc.gif \nMT newline \nMT -updated \nMT +updated \nMT text U \nMT fname icons/dtool16/rem_all_co.gif \nMT newline \nMT -updated \nMT +updated \nMT text U \nMT fname icons/dtool16/rem_co.gif \nMT newline \nMT -updated \nMT +updated \nMT text U \nMT fname icons/dtool16/resume_co.gif \nMT newline \nMT -updated \nMT +updated \nMT text U \nMT fname icons/dtool16/run_exc.gif \nMT newline \nMT -updated \nMT +updated \nMT text U \nMT fname icons/dtool16/suspend_co.gif \nMT newline \nMT -updated \nMT +updated \nMT text U \nMT fname icons/dtool16/terminate_all_co.gif \nMT newline \nMT -updated \nMT +updated \nMT text U \nMT fname icons/dtool16/terminate_co.gif \nMT newline \nMT -updated \nMT +updated \nMT text U \nMT fname icons/dtool16/watch_exp.gif \nMT newline \nMT -updated \nE cvs server: Updating icons/etool16 \nMT +updated \nMT text U \nMT fname icons/etool16/debug_exc.gif \nMT newline \nMT -updated \nMT +updated \nMT text U \nMT fname icons/etool16/rem_all_co.gif \nMT newline \nMT -updated \nMT +updated \nMT text U \nMT fname icons/etool16/rem_co.gif \nMT newline \nMT -updated \nMT +updated \nMT text U \nMT fname icons/etool16/resume_co.gif \nMT newline \nMT -updated \nMT +updated \nMT text U \nMT fname icons/etool16/run_exc.gif \nMT newline \nMT -updated \nMT +updated \nMT text U \nMT fname icons/etool16/suspend_co.gif \nMT newline \nMT -updated \nMT +updated \nMT text U \nMT fname icons/etool16/terminate_all_co.gif \nMT newline \nMT -updated \nMT +updated \nMT text U \nMT fname icons/etool16/terminate_co.gif \nMT newline \nMT -updated \nMT +updated \nMT text U \nMT fname icons/etool16/watch_exp.gif \nMT newline \nMT -updated \nE cvs server: Updating src \nE cvs server: Updating src/com \nE cvs server: Updating src/com/my \nE cvs server: Updating src/com/my/jsdebug \nMT +updated \nMT text U \nMT fname src/com/my/jsdebug/MyJSDebugPlugin.java \nMT newline \nMT -updated \nMT +updated \nMT text U \nMT fname src/com/my/jsdebug/MyJSDebugPluginImageRegistry.java \nMT newline \nMT -updated \nE cvs server: Updating src/com/my/jsdebug/debugger \nMT +updated \nMT text U \nMT fname src/com/my/jsdebug/debugger/JSExecutionManager.java \nMT newline \nMT -updated \nMT +updated \nMT text U \nMT fname src/com/my/jsdebug/debugger/JSExecutionManagerListener.java \nMT newline \nMT -updated \nMT +updated \nMT text U \nMT fname src/com/my/jsdebug/debugger/JSExecutorListener.java \nMT newline \nMT -updated \nMT +updated \nMT text U \nMT fname src/com/my/jsdebug/debugger/JavaScriptExecutor.java \nMT newline \nMT -updated \nE cvs server: Updating src/com/my/jsdebug/debugger/actions \nMT +updated \nMT text U \nMT fname src/com/my/jsdebug/debugger/actions/ExecuteJavaScript.java \nMT newline \nMT -updated \nE cvs server: Updating src/com/my/jsdebug/debugger/views \nMT +updated \nMT text U \nMT fname src/com/my/jsdebug/debugger/views/ExecutionOutput.java \nMT newline \nMT -updated \nE cvs server: Updating src/com/my/jsdebug/test \nMT +updated \nMT text U \nMT fname src/com/my/jsdebug/test/BreakTester.java \nMT newline \nMT -updated \nok \nRESULT\u003e Status OK: org.eclipse.team.cvs.core code\u003d0 ok null \nI LOVE YOU \nValid-responses ok error M E Checked-in Valid-requests Template Set-sticky MT  \nCl \near-static-directory Module-expansion Set-static-directory Clear-sticky New- \nentr \ny Merged Removed Updated Remove-entry Update-existing Copy-file Created  \nNotified \n Mod-time \nvalid-requests \nValid-requests Root Valid-responses valid-requests Directory Max-dotdot \nStatic- \nd \nirectory Sticky Entry EntryExtra Kopt Checkin-time Modified Is-modified  \nUseUncha \nnged Unchanged Notify NotifyUser Questionable Utf8 Argument Argumentx  \nGlobal_opt \nion Gzip-stream wrapper-sendme-rcsOptions Set Rename VirtualRepository expand- \nmo \ndules ci co chown setowner chacl2 lsacl passwd info update diff log rlog add  \nrem \nove update-patches status ls rls rdiff tag rtag import admin export history  \nrele \nase watch-on watch-off watch-add watch-remove watchers editors init annotate  \nran \nnotate noop version Rootless-stream-modification Kerberos-encrypt Gssapi- \nencrypt \n Protocol-encrypt Gssapi-authenticate Protocol-authenticate read-cvsrc read- \ncvsr \nc2 read-cvsignore read-cvswrappers Error-If-Reader server-codepage client- \nversio \nn       Can-Rename Valid-RcsOptions \nok \nRoot /cvs/moelleryoung \nCMD\u003e cvs  \nstatus \"plugin.xml\" \"icons/dtool16/debug_exc.gif\" \"icons/dtool16/rem_al \nl_co.gif\" \"icons/dtool16/rem_co.gif\" \"icons/dtool16/resume_co.gif\" \n\"icons/dtool \n1 \n6/run_exc.gif\" \"icons/dtool16/suspend_co.gif\" \n\"icons/dtool16/terminate_all_co.g \ni \nf\" \"icons/dtool16/terminate_co.gif\" \"icons/dtool16/watch_exp.gif\" \n\"icons/etool1 \n6 \n/debug_exc.gif\" \"icons/etool16/rem_all_co.gif\" \"icons/etool16/rem_co.gif\" \n\"icon \ns \n/etool16/resume_co.gif\" \"icons/etool16/run_exc.gif\" \n\"icons/etool16/suspend_co.g \ni \nf\" \"icons/etool16/terminate_all_co.gif\" \"icons/etool16/terminate_co.gif\" \n\"icons \n/ \netool16/watch_exp.gif\" \"src/com/my/jsdebug/MyJSDebugPlugin.java\" \n\"src/com/my/js \nd \nebug/MyJSDebugPluginImageRegistry.java\" \n\"src/com/my/jsdebug/debugger/JSExecutio \nn \nManager.java\" \"src/com/my/jsdebug/debugger/JSExecutionManagerListener.java\" \n\"sr \nc \n/com/my/jsdebug/debugger/JSExecutorListener.java\" \n\"src/com/my/jsdebug/debugger/ \nJ \navaScriptExecutor.java\" \n\"src/com/my/jsdebug/debugger/actions/ExecuteJavaScript. \nj \nava\" \"src/com/my/jsdebug/debugger/views/ExecutionOutput.java\" \n\"src/com/my/jsdeb \nu \ng/test/BreakTester.java\" \nRESULT\u003e org.eclipse.team.internal.ccvs.core.CVSException: Resource  \nicons/dtool16 \n/debug_exc.gif is not a child of folder MyJSDebug \n \n!ENTRY org.eclipse.team.core 4 0 2005-01-18 10:02:09.231 \n!MESSAGE Problems reported while synchronizing CVS Workspace. 0 of 1 resources  \nw \nere synchronized. \n!SUBENTRY 1 org.eclipse.team.core 4 0 2005-01-18 10:02:09.247 \n!MESSAGE An error occurred synchronizing /MyJSDebug: Resource  \nicons/dtool16/debu \ng_exc.gif is not a child of folder MyJSDebug \n!STACK 1 \norg.eclipse.team.internal.ccvs.core.CVSException: Resource  \nicons/dtool16/debug_e \nxc.gif is not a child of folder MyJSDebug \n        at org.eclipse.team.internal.ccvs.core.resources.RemoteFolder.getChild \n(R \nemoteFolder.java:346) \n        at  \norg.eclipse.team.internal.ccvs.core.client.Command.computeWorkResourc \nes(Command.java:224) \n        at org.eclipse.team.internal.ccvs.core.client.Command.doExecute \n(Command. \njava:385) \n        at org.eclipse.team.internal.ccvs.core.client.Command$1.run \n(Command.java \n:320) \n        at org.eclipse.team.internal.ccvs.core.resources.RemoteFolder.run \n(Remote \nFolder.java:463) \n        at org.eclipse.team.internal.ccvs.core.client.Command.execute \n(Command.ja \nva:332) \n        at  \norg.eclipse.team.internal.ccvs.core.resources.RemoteFolderTreeBuilder \n.fetchFileRevisions(RemoteFolderTreeBuilder.java:720) \n        at  \norg.eclipse.team.internal.ccvs.core.resources.RemoteFolderTreeBuilder \n.fetchFileRevisions(RemoteFolderTreeBuilder.java:280) \n        at  \norg.eclipse.team.internal.ccvs.core.resources.RemoteFolderTreeBuilder \n.buildTree(RemoteFolderTreeBuilder.java:175) \n        at  \norg.eclipse.team.internal.ccvs.core.resources.RemoteFolderTreeBuilder \n.buildRemoteTree(RemoteFolderTreeBuilder.java:138) \n        at  \norg.eclipse.team.internal.ccvs.core.resources.CVSWorkspaceRoot.getRem \noteTree(CVSWorkspaceRoot.java:230) \n        at  \norg.eclipse.team.internal.ccvs.core.syncinfo.CVSResourceVariantTree.f \netchVariant(CVSResourceVariantTree.java:79) \n        at org.eclipse.team.core.variants.AbstractResourceVariantTree.refresh \n(Ab \nstractResourceVariantTree.java:94) \n        at  \norg.eclipse.team.internal.ccvs.core.syncinfo.CVSResourceVariantTree.r \nefresh(CVSResourceVariantTree.java:308) \n        at org.eclipse.team.core.variants.AbstractResourceVariantTree.refresh \n(Ab \nstractResourceVariantTree.java:63) \n        at \norg.eclipse.team.core.variants.ResourceVariantTreeSubscriber.refresh \n( \nResourceVariantTreeSubscriber.java:158) \n        at \norg.eclipse.team.core.variants.ResourceVariantTreeSubscriber.refresh \n( \nResourceVariantTreeSubscriber.java:123) \n        at org.eclipse.team.internal.ui.synchronize.RefreshSubscriberJob.run \n(Ref \nreshSubscriberJob.java:340) \n        at org.eclipse.core.internal.jobs.Worker.run(Worker.java:66) \n!SUBENTRY 2 org.eclipse.team.cvs.core 4 1000 2005-01-18 10:02:09.247 \n!MESSAGE Resource icons/dtool16/debug_exc.gif is not a child of folder  \nMyJSDebug",
    "Lowering Severity - I can run cvs manually on command line to get around the \nproblem. Still a little annoying :) ",
    "There\u0027s not mush we can do unless we can reproduce it. If you can come up with \na set of steps that will reproduce the problem, please add them to this bug \nand reopen it.",
    "Our usual practice is to move bugs to the RESOLVED REMIND state when there is not enough information provided to address the reported issue and more information has been requested. This bug has been in the RESOLVED REMIND state for quite some time so it is being CLOSED. If you can provide the requested information or you otherwise feel that this is still an issue, please reopen the bug. If you are unable to open it due to a lack or permissions, please add a comment to the bug stating that you would like to have the request reconsidered.  I applogize for this blanket approach to bug screening but there are just to many bugs in the REMIND state for us to effectively triage them. Your help in this matter is appreciated."
  ],
  "commentCreationDates": [
    "2005-01-18T16:29:17+01:00",
    "2005-01-18T16:57:03+01:00",
    "2005-01-26T16:46:43+01:00",
    "2006-10-20T12:18:36+02:00"
  ],
  "traces": [
    {
      "exceptionType": "org.eclipse.team.internal.ccvs.core.CVSException",
      "message": "Resource   icons/dtool16/debug_e  xc.gif is not a child of folder MyJSDebug",
      "elements": [
        {
          "method": "org.eclipse.team.internal.ccvs.core.resources.RemoteFolder.getChild",
          "source": "R  emoteFolder.java:346"
        },
        {
          "method": "org.eclipse.team.internal.ccvs.core.client.Command.computeWorkResources",
          "source": "Command.java:224"
        },
        {
          "method": "org.eclipse.team.internal.ccvs.core.client.Command.doExecute",
          "source": "Command.  java:385"
        },
        {
          "method": "org.eclipse.team.internal.ccvs.core.client.Command$1.run",
          "source": "Command.java  :320"
        },
        {
          "method": "org.eclipse.team.internal.ccvs.core.resources.RemoteFolder.run",
          "source": "Remote  Folder.java:463"
        },
        {
          "method": "org.eclipse.team.internal.ccvs.core.client.Command.execute",
          "source": "Command.ja  va:332"
        },
        {
          "method": "org.eclipse.team.internal.ccvs.core.resources.RemoteFolderTreeBuilder.fetchFileRevisions",
          "source": "RemoteFolderTreeBuilder.java:720"
        },
        {
          "method": "org.eclipse.team.internal.ccvs.core.resources.RemoteFolderTreeBuilder.fetchFileRevisions",
          "source": "RemoteFolderTreeBuilder.java:280"
        },
        {
          "method": "org.eclipse.team.internal.ccvs.core.resources.RemoteFolderTreeBuilder.buildTree",
          "source": "RemoteFolderTreeBuilder.java:175"
        },
        {
          "method": "org.eclipse.team.internal.ccvs.core.resources.RemoteFolderTreeBuilder.buildRemoteTree",
          "source": "RemoteFolderTreeBuilder.java:138"
        },
        {
          "method": "org.eclipse.team.internal.ccvs.core.resources.CVSWorkspaceRoot.getRemoteTree",
          "source": "CVSWorkspaceRoot.java:230"
        },
        {
          "method": "org.eclipse.team.internal.ccvs.core.syncinfo.CVSResourceVariantTree.fetchVariant",
          "source": "CVSResourceVariantTree.java:79"
        },
        {
          "method": "org.eclipse.team.core.variants.AbstractResourceVariantTree.refresh",
          "source": "Ab  stractResourceVariantTree.java:94"
        },
        {
          "method": "org.eclipse.team.internal.ccvs.core.syncinfo.CVSResourceVariantTree.refresh",
          "source": "CVSResourceVariantTree.java:308"
        },
        {
          "method": "org.eclipse.team.core.variants.AbstractResourceVariantTree.refresh",
          "source": "Ab  stractResourceVariantTree.java:63"
        },
        {
          "method": "org.eclipse.team.core.variants.ResourceVariantTreeSubscriber.refresh",
          "source": "  ResourceVariantTreeSubscriber.java:158"
        },
        {
          "method": "org.eclipse.team.core.variants.ResourceVariantTreeSubscriber.refresh",
          "source": "  ResourceVariantTreeSubscriber.java:123"
        },
        {
          "method": "org.eclipse.team.internal.ui.synchronize.RefreshSubscriberJob.run",
          "source": "Ref  reshSubscriberJob.java:340"
        },
        {
          "method": "org.eclipse.core.internal.jobs.Worker.run",
          "source": "Worker.java:66"
        }
      ],
      "number": 0,
      "commentIndex": 0,
      "bugId": "83110",
      "date": "2005-01-18T16:29:17+01:00",
      "product": "Platform",
      "component": "CVS",
      "severity": "normal"
    }
  ],
  "groupId": "83110",
  "bugId": "83110",
  "date": "2005-01-18T16:29:17+01:00",
  "product": "Platform",
  "component": "CVS",
  "severity": "normal"
}