{
  "comments": [
    "Build 3.1 20050126\n\nAfter upgrading to 20050125, I am quite often seeing hangs during debug process\n(after hitting a breakpoint, some step action causes a freeze).\nThere doesn\u0027t seem to be a specific pattern. Usually terminating/restarting\nwould work.\n\norg.eclipse.jdi.TimeoutException: Timeout occurred while waiting for packet 104515\n        at\norg.eclipse.jdi.internal.connect.PacketReceiveManager.getReply(PacketReceiveManager.java:160)\n        at\norg.eclipse.jdi.internal.connect.PacketReceiveManager.getReply(PacketReceiveManager.java:169)\n        at org.eclipse.jdi.internal.MirrorImpl.requestVM(MirrorImpl.java:174)\n        at org.eclipse.jdi.internal.MirrorImpl.requestVM(MirrorImpl.java:192)\n        at\norg.eclipse.jdi.internal.ThreadReferenceImpl.frames(ThreadReferenceImpl.java:187)\n        at\norg.eclipse.jdi.internal.ThreadReferenceImpl.frame(ThreadReferenceImpl.java:140)\n        at\norg.eclipse.jdt.internal.debug.core.model.JDIThread.getUnderlyingFrame(JDIThread.java:575)\n        at\norg.eclipse.jdt.internal.debug.core.model.JDIStackFrame.getUnderlyingStackFrame(JDIStackFrame.java:1000)\n        at\norg.eclipse.jdt.internal.debug.core.model.JDIStackFrame.getUnderlyingMethod(JDIStackFrame.java:228)\n        at\norg.eclipse.jdt.internal.debug.core.model.JDIStackFrame.isNative(JDIStackFrame.java:793)\n        at\norg.eclipse.jdt.internal.debug.core.model.JDIStackFrame.supportsDropToFrame(JDIStackFrame.java:584)\n        at\norg.eclipse.jdt.internal.debug.ui.actions.DropToFrameButton.selectionChanged(DropToFrameButton.java:62)\n        at\norg.eclipse.ui.internal.PluginAction.refreshEnablement(PluginAction.java:195)\n        at\norg.eclipse.ui.internal.PluginAction.selectionChanged(PluginAction.java:267)\n        at\norg.eclipse.ui.internal.PluginAction.selectionChanged(PluginAction.java:278)\n        at org.eclipse.jface.viewers.Viewer$2.run(Viewer.java:163)\n        at\norg.eclipse.core.internal.runtime.InternalPlatform.run(InternalPlatform.java:1051)\n        at org.eclipse.core.runtime.Platform.run(Platform.java:747)\n        at org.eclipse.jface.viewers.Viewer.fireSelectionChanged(Viewer.java:161)\n        at\norg.eclipse.jface.viewers.StructuredViewer.updateSelection(StructuredViewer.java:1676)\n        at\norg.eclipse.jface.viewers.StructuredViewer.setSelection(StructuredViewer.java:1358)\n        at\norg.eclipse.debug.internal.ui.views.RemoteTreeViewer.deferSelection(RemoteTreeViewer.java:305)\n        at\norg.eclipse.debug.internal.ui.views.launch.LaunchViewEventHandler.doHandleSuspendThreadEvent(LaunchViewEventHandler.java:237)\n        at\norg.eclipse.debug.internal.ui.views.launch.LaunchViewEventHandler.doHandleSuspendEvent(LaunchViewEventHandler.java:204)\n        at\norg.eclipse.debug.internal.ui.views.launch.LaunchViewEventHandler.doHandleDebugEvents(LaunchViewEventHandler.java:123)\n        at\norg.eclipse.debug.internal.ui.views.AbstractDebugEventHandler$EventProcessingJob.runInUIThread(AbstractDebugEventHandler.java:103)\n        at org.eclipse.ui.progress.UIJob$1.run(UIJob.java:96)\n        at org.eclipse.swt.widgets.RunnableLock.run(RunnableLock.java:35)\n        at\norg.eclipse.swt.widgets.Synchronizer.runAsyncMessages(Synchronizer.java:118)\n        at org.eclipse.swt.widgets.Display.runAsyncMessages(Display.java:2854)\n        at org.eclipse.swt.widgets.Display.readAndDispatch(Display.java:2518)\n        at org.eclipse.ui.internal.Workbench.runEventLoop(Workbench.java:1584)\n        at org.eclipse.ui.internal.Workbench.runUI(Workbench.java:1550)\n        at\norg.eclipse.ui.internal.Workbench.createAndRunWorkbench(Workbench.java:288)\n        at org.eclipse.ui.PlatformUI.createAndRunWorkbench(PlatformUI.java:144)\n        at org.eclipse.ui.internal.ide.IDEApplication.run(IDEApplication.java:102)\n        at\norg.eclipse.core.internal.runtime.PlatformActivator$1.run(PlatformActivator.java:225)\n        at\norg.eclipse.core.runtime.adaptor.EclipseStarter.run(EclipseStarter.java:274)\n        at\norg.eclipse.core.runtime.adaptor.EclipseStarter.run(EclipseStarter.java:129)\n        at sun.reflect.NativeMethodAccessorImpl.invoke0(Native Method)\n        at\nsun.reflect.NativeMethodAccessorImpl.invoke(NativeMethodAccessorImpl.java:39)\n        at\nsun.reflect.DelegatingMethodAccessorImpl.invoke(DelegatingMethodAccessorImpl.java:25)\n        at java.lang.reflect.Method.invoke(Method.java:324)\n        at org.eclipse.core.launcher.Main.basicRun(Main.java:255)\n        at org.eclipse.core.launcher.Main.run(Main.java:811)\n        at org.eclipse.core.launcher.Main.main(Main.java:795)",
    "The action should update in the background to avoid blocking the UI thread.",
    "filed bug 85966 to handle selectionChanged() in background thread.",
    "Phillippe, Are you still getting these Timeouts? \nI suspect this may be the same as bug #87144.",
    "*** Bug 89064 has been marked as a duplicate of this bug. ***",
    "*** Bug 84495 has been marked as a duplicate of this bug. ***",
    "*** Bug 85842 has been marked as a duplicate of this bug. ***",
    "*** Bug 87144 has been marked as a duplicate of this bug. ***",
    "*** Bug 88197 has been marked as a duplicate of this bug. ***",
    "*** Bug 81653 has been marked as a duplicate of this bug. ***",
    "Another example timeout:\n\norg.eclipse.jdi.TimeoutException: Timeout occurred while waiting for packet \n11567. RemainingTime: 0 Received: 46 Received Queue: [5830 5831 5832 5833 5834 \n5835 5836 5837 5838 5839 5840 5841 5842 5843 10814 10815 10816 10817 10818 \n10819 10820 10821 10822 10823 10824 10825 10826 10827 10828 10829 10830 10831 \n10832 10833 10834 10835 10836 10837 10838 10839 10840 10841 10842 10843 10844 \n10845 ]\n\tat org.eclipse.jdi.internal.connect.PacketReceiveManager.getReply\n(PacketReceiveManager.java:175)\n\tat org.eclipse.jdi.internal.connect.PacketReceiveManager.getReply\n(PacketReceiveManager.java:185)\n\tat org.eclipse.jdi.internal.MirrorImpl.requestVM(MirrorImpl.java:174)\n\tat org.eclipse.jdi.internal.MirrorImpl.requestVM(MirrorImpl.java:192)\n\tat org.eclipse.jdi.internal.ThreadReferenceImpl.frames\n(ThreadReferenceImpl.java:187)\n\tat org.eclipse.jdi.internal.ThreadReferenceImpl.frames\n(ThreadReferenceImpl.java:171)\n\tat \norg.eclipse.jdt.internal.debug.core.model.JDIThread.getUnderlyingFrames\n(JDIThread.java:500)\n\tat \norg.eclipse.jdt.internal.debug.core.model.JDIThread.computeStackFrames\n(JDIThread.java:412)\n\tat \norg.eclipse.jdt.internal.debug.core.model.JDIThread.computeStackFrames\n(JDIThread.java:476)\n\tat \norg.eclipse.jdt.internal.debug.core.model.JDIStackFrame.supportsDropToFrame\n(JDIStackFrame.java:573)\n\tat \norg.eclipse.jdt.internal.debug.core.model.JDIStackFrame.canDropToFrame\n(JDIStackFrame.java:544)\n\tat \norg.eclipse.debug.internal.ui.actions.DropToFrameActionDelegate.isEnabledFor\n(DropToFrameActionDelegate.java:81)\n\tat \norg.eclipse.debug.internal.ui.actions.AbstractDebugActionDelegate.getEnableStat\neForSelection(AbstractDebugActionDelegate.java:392)\n\tat \norg.eclipse.debug.internal.ui.actions.AbstractDebugActionDelegate.update\n(AbstractDebugActionDelegate.java:244)\n\tat \norg.eclipse.debug.internal.ui.actions.DropToFrameActionDelegate.access$0\n(DropToFrameActionDelegate.java:1)\n\tat \norg.eclipse.debug.internal.ui.actions.DropToFrameActionDelegate$UpdateJob.run\n(DropToFrameActionDelegate.java:43)\n\tat org.eclipse.core.internal.jobs.Worker.run(Worker.java:67)\n",
    "Proposals:\n\n* We should throw away responses for requests that have timed out.\n* We should serialize label jobs from the same target to avoid having mulitple \njobs attempting to retrieve labels at once for the same target\n\n",
    "haven\u0027t seen any Timeouts (or new bug reports) for a while.\nChanged PacketReceiveManager to maintain a list of packets that have timed out so that those packets \ncan be thrown out when/if they are eventually received. Also reduced the error message back to a \nreasonable size\nChanges to ConnectMessages.properties and PacketReceiveManager",
    "Darin, please verify",
    "Verified.",
    "Also see bug 94452. We have a potential fix for 3.1.1."
  ],
  "commentCreationDates": [
    "2005-01-28T15:40:39+01:00",
    "2005-01-28T19:27:25+01:00",
    "2005-02-21T17:23:27+01:00",
    "2005-03-15T15:53:28+01:00",
    "2005-03-24T23:33:44+01:00",
    "2005-04-04T20:18:56+02:00",
    "2005-04-04T20:54:36+02:00",
    "2005-04-04T21:38:03+02:00",
    "2005-04-04T21:57:19+02:00",
    "2005-04-04T22:49:06+02:00",
    "2005-04-05T21:11:36+02:00",
    "2005-04-18T20:35:36+02:00",
    "2005-05-03T23:27:49+02:00",
    "2005-05-03T23:28:11+02:00",
    "2005-05-09T18:53:23+02:00",
    "2005-06-23T16:45:19+02:00"
  ],
  "traces": [
    {
      "exceptionType": "org.eclipse.jdi.TimeoutException",
      "message": "Timeout occurred while waiting for packet 104515",
      "elements": [
        {
          "method": "org.eclipse.jdi.internal.connect.PacketReceiveManager.getReply",
          "source": "PacketReceiveManager.java:160"
        },
        {
          "method": "org.eclipse.jdi.internal.connect.PacketReceiveManager.getReply",
          "source": "PacketReceiveManager.java:169"
        },
        {
          "method": "org.eclipse.jdi.internal.MirrorImpl.requestVM",
          "source": "MirrorImpl.java:174"
        },
        {
          "method": "org.eclipse.jdi.internal.MirrorImpl.requestVM",
          "source": "MirrorImpl.java:192"
        },
        {
          "method": "org.eclipse.jdi.internal.ThreadReferenceImpl.frames",
          "source": "ThreadReferenceImpl.java:187"
        },
        {
          "method": "org.eclipse.jdi.internal.ThreadReferenceImpl.frame",
          "source": "ThreadReferenceImpl.java:140"
        },
        {
          "method": "org.eclipse.jdt.internal.debug.core.model.JDIThread.getUnderlyingFrame",
          "source": "JDIThread.java:575"
        },
        {
          "method": "org.eclipse.jdt.internal.debug.core.model.JDIStackFrame.getUnderlyingStackFrame",
          "source": "JDIStackFrame.java:1000"
        },
        {
          "method": "org.eclipse.jdt.internal.debug.core.model.JDIStackFrame.getUnderlyingMethod",
          "source": "JDIStackFrame.java:228"
        },
        {
          "method": "org.eclipse.jdt.internal.debug.core.model.JDIStackFrame.isNative",
          "source": "JDIStackFrame.java:793"
        },
        {
          "method": "org.eclipse.jdt.internal.debug.core.model.JDIStackFrame.supportsDropToFrame",
          "source": "JDIStackFrame.java:584"
        },
        {
          "method": "org.eclipse.jdt.internal.debug.ui.actions.DropToFrameButton.selectionChanged",
          "source": "DropToFrameButton.java:62"
        },
        {
          "method": "org.eclipse.ui.internal.PluginAction.refreshEnablement",
          "source": "PluginAction.java:195"
        },
        {
          "method": "org.eclipse.ui.internal.PluginAction.selectionChanged",
          "source": "PluginAction.java:267"
        },
        {
          "method": "org.eclipse.ui.internal.PluginAction.selectionChanged",
          "source": "PluginAction.java:278"
        },
        {
          "method": "org.eclipse.jface.viewers.Viewer$2.run",
          "source": "Viewer.java:163"
        },
        {
          "method": "org.eclipse.core.internal.runtime.InternalPlatform.run",
          "source": "InternalPlatform.java:1051"
        },
        {
          "method": "org.eclipse.core.runtime.Platform.run",
          "source": "Platform.java:747"
        },
        {
          "method": "org.eclipse.jface.viewers.Viewer.fireSelectionChanged",
          "source": "Viewer.java:161"
        },
        {
          "method": "org.eclipse.jface.viewers.StructuredViewer.updateSelection",
          "source": "StructuredViewer.java:1676"
        },
        {
          "method": "org.eclipse.jface.viewers.StructuredViewer.setSelection",
          "source": "StructuredViewer.java:1358"
        },
        {
          "method": "org.eclipse.debug.internal.ui.views.RemoteTreeViewer.deferSelection",
          "source": "RemoteTreeViewer.java:305"
        },
        {
          "method": "org.eclipse.debug.internal.ui.views.launch.LaunchViewEventHandler.doHandleSuspendThreadEvent",
          "source": "LaunchViewEventHandler.java:237"
        },
        {
          "method": "org.eclipse.debug.internal.ui.views.launch.LaunchViewEventHandler.doHandleSuspendEvent",
          "source": "LaunchViewEventHandler.java:204"
        },
        {
          "method": "org.eclipse.debug.internal.ui.views.launch.LaunchViewEventHandler.doHandleDebugEvents",
          "source": "LaunchViewEventHandler.java:123"
        },
        {
          "method": "org.eclipse.debug.internal.ui.views.AbstractDebugEventHandler$EventProcessingJob.runInUIThread",
          "source": "AbstractDebugEventHandler.java:103"
        },
        {
          "method": "org.eclipse.ui.progress.UIJob$1.run",
          "source": "UIJob.java:96"
        },
        {
          "method": "org.eclipse.swt.widgets.RunnableLock.run",
          "source": "RunnableLock.java:35"
        },
        {
          "method": "org.eclipse.swt.widgets.Synchronizer.runAsyncMessages",
          "source": "Synchronizer.java:118"
        },
        {
          "method": "org.eclipse.swt.widgets.Display.runAsyncMessages",
          "source": "Display.java:2854"
        },
        {
          "method": "org.eclipse.swt.widgets.Display.readAndDispatch",
          "source": "Display.java:2518"
        },
        {
          "method": "org.eclipse.ui.internal.Workbench.runEventLoop",
          "source": "Workbench.java:1584"
        },
        {
          "method": "org.eclipse.ui.internal.Workbench.runUI",
          "source": "Workbench.java:1550"
        },
        {
          "method": "org.eclipse.ui.internal.Workbench.createAndRunWorkbench",
          "source": "Workbench.java:288"
        },
        {
          "method": "org.eclipse.ui.PlatformUI.createAndRunWorkbench",
          "source": "PlatformUI.java:144"
        },
        {
          "method": "org.eclipse.ui.internal.ide.IDEApplication.run",
          "source": "IDEApplication.java:102"
        },
        {
          "method": "org.eclipse.core.internal.runtime.PlatformActivator$1.run",
          "source": "PlatformActivator.java:225"
        },
        {
          "method": "org.eclipse.core.runtime.adaptor.EclipseStarter.run",
          "source": "EclipseStarter.java:274"
        },
        {
          "method": "org.eclipse.core.runtime.adaptor.EclipseStarter.run",
          "source": "EclipseStarter.java:129"
        },
        {
          "method": "sun.reflect.NativeMethodAccessorImpl.invoke0",
          "source": "Native Method"
        },
        {
          "method": "sun.reflect.NativeMethodAccessorImpl.invoke",
          "source": "NativeMethodAccessorImpl.java:39"
        },
        {
          "method": "sun.reflect.DelegatingMethodAccessorImpl.invoke",
          "source": "DelegatingMethodAccessorImpl.java:25"
        },
        {
          "method": "java.lang.reflect.Method.invoke",
          "source": "Method.java:324"
        },
        {
          "method": "org.eclipse.core.launcher.Main.basicRun",
          "source": "Main.java:255"
        },
        {
          "method": "org.eclipse.core.launcher.Main.run",
          "source": "Main.java:811"
        },
        {
          "method": "org.eclipse.core.launcher.Main.main",
          "source": "Main.java:795"
        }
      ],
      "number": 0,
      "commentIndex": 0,
      "bugId": "83937",
      "date": "2005-01-28T15:40:39+01:00",
      "product": "JDT",
      "component": "Debug",
      "severity": "normal"
    },
    {
      "exceptionType": "org.eclipse.jdi.TimeoutException",
      "message": "Timeout occurred while waiting for packet  11567. RemainingTime: 0 Received: 46 Received Queue: [5830 5831 5832 5833 5834  5835 5836 5837 5838 5839 5840 5841 5842 5843 10814 10815 10816 10817 10818  10819 10820 10821 10822 10823 10824 10825 10826 10827 10828 10829 10830 10831  10832 10833 10834 10835 10836 10837 10838 10839 10840 10841 10842 10843 10844  10845 ]",
      "elements": [
        {
          "method": "org.eclipse.jdi.internal.connect.PacketReceiveManager.getReply",
          "source": "PacketReceiveManager.java:175"
        },
        {
          "method": "org.eclipse.jdi.internal.connect.PacketReceiveManager.getReply",
          "source": "PacketReceiveManager.java:185"
        },
        {
          "method": "org.eclipse.jdi.internal.MirrorImpl.requestVM",
          "source": "MirrorImpl.java:174"
        },
        {
          "method": "org.eclipse.jdi.internal.MirrorImpl.requestVM",
          "source": "MirrorImpl.java:192"
        },
        {
          "method": "org.eclipse.jdi.internal.ThreadReferenceImpl.frames",
          "source": "ThreadReferenceImpl.java:187"
        },
        {
          "method": "org.eclipse.jdi.internal.ThreadReferenceImpl.frames",
          "source": "ThreadReferenceImpl.java:171"
        },
        {
          "method": "org.eclipse.jdt.internal.debug.core.model.JDIThread.getUnderlyingFrames",
          "source": "JDIThread.java:500"
        },
        {
          "method": "org.eclipse.jdt.internal.debug.core.model.JDIThread.computeStackFrames",
          "source": "JDIThread.java:412"
        },
        {
          "method": "org.eclipse.jdt.internal.debug.core.model.JDIThread.computeStackFrames",
          "source": "JDIThread.java:476"
        },
        {
          "method": "org.eclipse.jdt.internal.debug.core.model.JDIStackFrame.supportsDropToFrame",
          "source": "JDIStackFrame.java:573"
        },
        {
          "method": "org.eclipse.jdt.internal.debug.core.model.JDIStackFrame.canDropToFrame",
          "source": "JDIStackFrame.java:544"
        },
        {
          "method": "org.eclipse.debug.internal.ui.actions.DropToFrameActionDelegate.isEnabledFor",
          "source": "DropToFrameActionDelegate.java:81"
        },
        {
          "method": "org.eclipse.debug.internal.ui.actions.AbstractDebugActionDelegate.getEnableStateForSelection",
          "source": "AbstractDebugActionDelegate.java:392"
        },
        {
          "method": "org.eclipse.debug.internal.ui.actions.AbstractDebugActionDelegate.update",
          "source": "AbstractDebugActionDelegate.java:244"
        },
        {
          "method": "org.eclipse.debug.internal.ui.actions.DropToFrameActionDelegate.access$0",
          "source": "DropToFrameActionDelegate.java:1"
        },
        {
          "method": "org.eclipse.debug.internal.ui.actions.DropToFrameActionDelegate$UpdateJob.run",
          "source": "DropToFrameActionDelegate.java:43"
        },
        {
          "method": "org.eclipse.core.internal.jobs.Worker.run",
          "source": "Worker.java:67"
        }
      ],
      "number": 1,
      "commentIndex": 10,
      "bugId": "83937",
      "date": "2005-04-05T21:11:36+02:00",
      "product": "JDT",
      "component": "Debug",
      "severity": "normal"
    }
  ],
  "groupId": "83937",
  "bugId": "83937",
  "date": "2005-01-28T15:40:39+01:00",
  "product": "JDT",
  "component": "Debug",
  "severity": "normal"
}