{
  "comments": [
    "I encountered a NullPointerException:\n\njava.lang.NullPointerException\n        at\norg.aspectj.weaver.ResolvedTypeX.isConvertableFrom(ResolvedTypeX.java:131)\n        at org.aspectj.weaver.bcel.Utility.appendConversion(Utility.java:241)\n        at org.aspectj.weaver.bcel.BcelVar.appendLoadAndConvert(BcelVar.java:61)\n        at org.aspectj.weaver.bcel.BcelAdvice.getAdviceArgSetup(BcelAdvice.java:314)\n        at\norg.aspectj.weaver.bcel.BcelAdvice.getAdviceInstructions(BcelAdvice.java:270)\n        at\norg.aspectj.weaver.bcel.BcelShadow.weaveAfterReturning(BcelShadow.java:1380)\n        at org.aspectj.weaver.bcel.BcelAdvice.implementOn(BcelAdvice.java:138)\n        at org.aspectj.weaver.Shadow.implementMungers(Shadow.java:451)\n        at org.aspectj.weaver.Shadow.implement(Shadow.java:334)\n        at\norg.aspectj.weaver.bcel.BcelClassWeaver.implement(BcelClassWeaver.java:1157)\n        at org.aspectj.weaver.bcel.BcelClassWeaver.weave(BcelClassWeaver.java:362)\n        at org.aspectj.weaver.bcel.BcelClassWeaver.weave(BcelClassWeaver.java:83)\n        at org.aspectj.weaver.bcel.BcelWeaver.weave(BcelWeaver.java:742)\n        at org.aspectj.weaver.bcel.BcelWeaver.weaveWithoutDump(BcelWeaver.java:707)\n        at org.aspectj.weaver.bcel.BcelWeaver.weaveAndNotify(BcelWeaver.java:634)\n        at org.aspectj.weaver.bcel.BcelWeaver.weave(BcelWeaver.java:565)\n        at\norg.aspectj.ajdt.internal.compiler.AjCompilerAdapter.weave(AjCompilerAdapter.java:243)\n        at\norg.aspectj.ajdt.internal.compiler.AjCompilerAdapter.afterCompiling(AjCompilerAdapter.java:118)\n        at\norg.aspectj.org.eclipse.jdt.internal.compiler.Compiler.compile(Compiler.java:383)\n        at\norg.aspectj.ajdt.internal.core.builder.AjBuildManager.performCompilation(AjBuildManager.java:682)\n        at\norg.aspectj.ajdt.internal.core.builder.AjBuildManager.doBuild(AjBuildManager.java:168)\n        at\norg.aspectj.ajdt.internal.core.builder.AjBuildManager.batchBuild(AjBuildManager.java:102)\n        at org.aspectj.ajdt.ajc.AjdtCommand.doCommand(AjdtCommand.java:109)\n        at org.aspectj.ajdt.ajc.AjdtCommand.runCommand(AjdtCommand.java:60)\n        at org.aspectj.tools.ajc.Main.run(Main.java:291)\n        at org.aspectj.tools.ajc.Main.runMain(Main.java:227)\n        at org.aspectj.tools.ajc.Main.main(Main.java:80)",
    "Created an attachment (id\u003d17551)\nSource-tree that triggers the bug\n\nRun ./compile to trigger the bug. It fails on compiling TestMain.java. I\nsuspect it has something to do with Trace.java, since that\u0027s the only file\nthat\u0027s been changed between compiles (the after returning rules have been\nadded). (Note that I\u0027m new to AspectJ/AOP, so I may behave stupidly in my\nprogram ;-)\n\nOther aspects are in CalculateSum.java and CheckColours.java. There\u0027s a dump in\nthe ZIP-file too.\n\nThe code requires Java 5 features (enums), so that\u0027s why some stuff is compiled\nwith javac.\n",
    "Also, I\u0027m using javac 1.5.0 and ajc 1.5.0 M1.\n\nsjoerd@cicero:~$ ajc -version  \nAspectJ Compiler 1.5.0 M1 built on Friday Dec 10, 2004 at 15:10:44 GMT\nsjoerd@cicero:~$ javac -version\njavac 1.5.0\n",
    "If in the following code ...\n\n  after (CarComponent c) returning (boolean match): target (c) \u0026\u0026 traceCol () {\n    System.out.println (\"Leaving \" + c + \": \" + match);\n  }\n\n... \"(boolean match)\" is left out, the code compiles (well, if you don\u0027t use\nmatch later on). But that doesn\u0027t allow me to use the match variable, which of\ncourse I do want :-) Empty parentheses do work, different types or names don\u0027t.\n\nI worked around the problem by using (how appropriate) the around () advice.\n",
    "for verification and fixing if needed in aj5m3...",
    "Reassigning to Andrew for investigation.  It is likely due to \u0027boolean\u0027 since\nthey are represented as a special kind of ResolvedTypeX and have only been\nreferenced in the isConvertableFrom code since I wrote the autoboxing changes\nfor 1.5.0.",
    "Already fixed as bug 85097 - closing as dup - fix available in 1.5.0M2.\n\n*** This bug has been marked as a duplicate of 85097 ***"
  ],
  "commentCreationDates": [
    "2005-01-28T14:04:08+01:00",
    "2005-01-28T14:09:19+01:00",
    "2005-01-28T14:11:59+01:00",
    "2005-01-28T15:10:08+01:00",
    "2005-03-23T14:27:51+01:00",
    "2005-04-11T18:17:50+02:00",
    "2005-04-12T12:09:36+02:00"
  ],
  "traces": [
    {
      "exceptionType": "java.lang.NullPointerException",
      "elements": [
        {
          "method": "org.aspectj.weaver.ResolvedTypeX.isConvertableFrom",
          "source": "ResolvedTypeX.java:131"
        },
        {
          "method": "org.aspectj.weaver.bcel.Utility.appendConversion",
          "source": "Utility.java:241"
        },
        {
          "method": "org.aspectj.weaver.bcel.BcelVar.appendLoadAndConvert",
          "source": "BcelVar.java:61"
        },
        {
          "method": "org.aspectj.weaver.bcel.BcelAdvice.getAdviceArgSetup",
          "source": "BcelAdvice.java:314"
        },
        {
          "method": "org.aspectj.weaver.bcel.BcelAdvice.getAdviceInstructions",
          "source": "BcelAdvice.java:270"
        },
        {
          "method": "org.aspectj.weaver.bcel.BcelShadow.weaveAfterReturning",
          "source": "BcelShadow.java:1380"
        },
        {
          "method": "org.aspectj.weaver.bcel.BcelAdvice.implementOn",
          "source": "BcelAdvice.java:138"
        },
        {
          "method": "org.aspectj.weaver.Shadow.implementMungers",
          "source": "Shadow.java:451"
        },
        {
          "method": "org.aspectj.weaver.Shadow.implement",
          "source": "Shadow.java:334"
        },
        {
          "method": "org.aspectj.weaver.bcel.BcelClassWeaver.implement",
          "source": "BcelClassWeaver.java:1157"
        },
        {
          "method": "org.aspectj.weaver.bcel.BcelClassWeaver.weave",
          "source": "BcelClassWeaver.java:362"
        },
        {
          "method": "org.aspectj.weaver.bcel.BcelClassWeaver.weave",
          "source": "BcelClassWeaver.java:83"
        },
        {
          "method": "org.aspectj.weaver.bcel.BcelWeaver.weave",
          "source": "BcelWeaver.java:742"
        },
        {
          "method": "org.aspectj.weaver.bcel.BcelWeaver.weaveWithoutDump",
          "source": "BcelWeaver.java:707"
        },
        {
          "method": "org.aspectj.weaver.bcel.BcelWeaver.weaveAndNotify",
          "source": "BcelWeaver.java:634"
        },
        {
          "method": "org.aspectj.weaver.bcel.BcelWeaver.weave",
          "source": "BcelWeaver.java:565"
        },
        {
          "method": "org.aspectj.ajdt.internal.compiler.AjCompilerAdapter.weave",
          "source": "AjCompilerAdapter.java:243"
        },
        {
          "method": "org.aspectj.ajdt.internal.compiler.AjCompilerAdapter.afterCompiling",
          "source": "AjCompilerAdapter.java:118"
        },
        {
          "method": "org.aspectj.org.eclipse.jdt.internal.compiler.Compiler.compile",
          "source": "Compiler.java:383"
        },
        {
          "method": "org.aspectj.ajdt.internal.core.builder.AjBuildManager.performCompilation",
          "source": "AjBuildManager.java:682"
        },
        {
          "method": "org.aspectj.ajdt.internal.core.builder.AjBuildManager.doBuild",
          "source": "AjBuildManager.java:168"
        },
        {
          "method": "org.aspectj.ajdt.internal.core.builder.AjBuildManager.batchBuild",
          "source": "AjBuildManager.java:102"
        },
        {
          "method": "org.aspectj.ajdt.ajc.AjdtCommand.doCommand",
          "source": "AjdtCommand.java:109"
        },
        {
          "method": "org.aspectj.ajdt.ajc.AjdtCommand.runCommand",
          "source": "AjdtCommand.java:60"
        },
        {
          "method": "org.aspectj.tools.ajc.Main.run",
          "source": "Main.java:291"
        },
        {
          "method": "org.aspectj.tools.ajc.Main.runMain",
          "source": "Main.java:227"
        },
        {
          "method": "org.aspectj.tools.ajc.Main.main",
          "source": "Main.java:80"
        }
      ],
      "number": 0,
      "commentIndex": 0,
      "bugId": "83930",
      "duplicateId": "85097",
      "date": "2005-01-28T14:04:08+01:00",
      "product": "AspectJ",
      "component": "Compiler",
      "severity": "normal"
    }
  ],
  "groupId": "85097",
  "bugId": "83930",
  "duplicateId": "85097",
  "date": "2005-01-28T14:04:08+01:00",
  "product": "AspectJ",
  "component": "Compiler",
  "severity": "normal"
}