{
  "comments": [
    "I know you have addressed variants of this problem but as root on a Linux box \n(Redhat Enterprise Linux 3.0 with JDK 1.5.0 and Eclipse 3.0.1) I am able to \nrun Eclipse fine but as a user, I got the following error. I tried the -vmargs \nthat helps with the ignore file locking, but that didn\u0027t help either. Would \nyou guys know what might be wrong?\n\n!SESSION Jan 31, 2005 18:50:33.489 --------------------------------------------\n-\neclipse.buildId\u003dM200409161125\njava.version\u003d1.5.0\njava.vendor\u003dSun Microsystems Inc.\nBootLoader constants: OS\u003dlinux, ARCH\u003damd64, WS\u003dgtk, NL\u003den_US\nCommand-line arguments: ./eclipse -Dorg.eclipse.core.runtime.ignoreLockFile\n\n!ENTRY \ninitial@reference:file:/usr/local/eclipse/plugins/org.eclipse.core.runtime_3.0.\n1/ 0 0 Jan 31, 2\n005 18:50:33.499\n!MESSAGE FrameworkEvent.ERROR\n!STACK 0\norg.osgi.framework.BundleException: Exception in \norg.eclipse.core.internal.runtime.PlatformActivator.s\ntart() of bundle org.eclipse.core.runtime.\n        at \norg.eclipse.osgi.framework.internal.core.BundleContextImpl.startActivator\n(BundleContextImpl\n.java:975)\n        at org.eclipse.osgi.framework.internal.core.BundleContextImpl.start\n(BundleContextImpl.java:937\n)\n        at org.eclipse.osgi.framework.internal.core.BundleHost.startWorker\n(BundleHost.java:421)\n        at org.eclipse.osgi.framework.internal.core.AbstractBundle.resume\n(AbstractBundle.java:366)\n        at org.eclipse.osgi.framework.internal.core.Framework.resumeBundle\n(Framework.java:999)\n        at \norg.eclipse.osgi.framework.internal.core.StartLevelManager.resumeBundles\n(StartLevelManager.\njava:577)\n        at org.eclipse.osgi.framework.internal.core.StartLevelManager.incFWSL\n(StartLevelManager.java:4\n88)\n        at \norg.eclipse.osgi.framework.internal.core.StartLevelManager.doSetStartLevel\n(StartLevelManage\nr.java:273)\n        at \norg.eclipse.osgi.framework.internal.core.StartLevelManager.dispatchEvent\n(StartLevelManager.\njava:444)\n        at org.eclipse.osgi.framework.eventmgr.EventManager.dispatchEvent\n(EventManager.java:186)\n        at org.eclipse.osgi.framework.eventmgr.EventThread.run\n(EventThread.java:104)\nCaused by: java.io.IOException: An error occurred while locking \nfile \"/home/suhit/.eclipse/org.eclipse\n.platform_3.0.1/configuration/org.eclipse.core.runtime/.manager/.fileTableLock\"\n: \"Input/output error\".\n A probably reason is that the file system or Runtime Environment does not \nsupport file locking. You m\nay want to choose a different location, or disable file locking (using the \nosgi.locking property), but\n this can cause data corruption.\n        at org.eclipse.core.runtime.adaptor.Locker_JavaNio.lock\n(Locker_JavaNio.java:42)\n        at org.eclipse.osgi.service.datalocation.FileManager.lock\n(FileManager.java:219)\n        at org.eclipse.osgi.service.datalocation.FileManager.open\n(FileManager.java:423)\n        at \norg.eclipse.core.internal.runtime.InternalPlatform.initializeRuntimeFileManager\n(InternalPla\ntform.java:391)\n        at org.eclipse.core.internal.runtime.InternalPlatform.start\n(InternalPlatform.java:384)\n        at \norg.eclipse.core.internal.runtime.PlatformActivator.startInternalPlatform\n(PlatformActivator\n.java:251)\n        at org.eclipse.core.internal.runtime.PlatformActivator.start\n(PlatformActivator.java:64)\n        at org.eclipse.osgi.framework.internal.core.BundleContextImpl$1.run\n(BundleContextImpl.java:958\n)\n        at java.security.AccessController.doPrivileged(Native Method)\n        at \norg.eclipse.osgi.framework.internal.core.BundleContextImpl.startActivator\n(BundleContextImpl\n.java:954)\n        ... 10 more\nRoot exception:\njava.io.IOException: An error occurred while locking \nfile \"/home/suhit/.eclipse/org.eclipse.platform_3\n.0.1/configuration/org.eclipse.core.runtime/.manager/.fileTableLock\": \"Input/ou\ntput error\". A probably\n reason is that the file system or Runtime Environment does not support file \nlocking. You may want to \nchoose a different location, or disable file locking (using the osgi.locking \nproperty), but this can c\nause data corruption.\n        at org.eclipse.core.runtime.adaptor.Locker_JavaNio.lock\n(Locker_JavaNio.java:42)\n        at org.eclipse.osgi.service.datalocation.FileManager.lock\n(FileManager.java:219)\n        at org.eclipse.osgi.service.datalocation.FileManager.open\n(FileManager.java:423)\n        at \norg.eclipse.core.internal.runtime.InternalPlatform.initializeRuntimeFileManager\n(InternalPla\ntform.java:391)\n        at org.eclipse.core.internal.runtime.InternalPlatform.start\n(InternalPlatform.java:384)\n        at \norg.eclipse.core.internal.runtime.PlatformActivator.startInternalPlatform\n(PlatformActivator\n.java:251)\n[suhit@compute1 configuration]$ cd\n[suhit@compute1 suhit]$ eclipse ./eclipse -vm /usr/java/jdk1.5.0/bin/java -\nvmargs -Dorg.eclipse.core.runtime.ignoreLockFile\n[suhit@compute1 suhit]$ eclipse ./eclipse -vmargs -\nDorg.eclipse.core.runtime.ignoreLockFile\n[suhit@compute1 suhit]$ \n[suhit@compute1 suhit]$ ./eclipse -vmargs -\nDorg.eclipse.core.runtime.ignoreLockFile\n-bash: ./eclipse: No such file or directory\n[suhit@compute1 suhit]$ eclipse -vmargs -\nDorg.eclipse.core.runtime.ignoreLockFile\n[suhit@compute1 suhit]$ eclipse -vm /usr/java/jdk1.5.0/bin/java -vmargs -\nDorg.eclipse.core.runtime.ignoreLockFile\n[suhit@compute1 suhit]$ eclipse -date ~/temp/eclipse-workspace\n[suhit@compute1 suhit]$ cd .eclipse/\n[suhit@compute1 .eclipse]$ ls\norg.eclipse.platform_3.0.1\n[suhit@compute1 .eclipse]$ cd org.eclipse.platform_3.0.1/\n[suhit@compute1 org.eclipse.platform_3.0.1]$ cd configuration/\n[suhit@compute1 configuration]$ ls\n1107214700609.log  1107215432819.log  1107215556639.log  1107215620164.log  \norg.eclipse.core.runtime\n1107215335337.log  1107215546460.log  1107215605695.log  1107215755292.log  \norg.eclipse.osgi\n[suhit@compute1 configuration]$ less 1107215432819.log \n!SESSION Jan 31, 2005 18:50:33.489 --------------------------------------------\n-\neclipse.buildId\u003dM200409161125\njava.version\u003d1.5.0\njava.vendor\u003dSun Microsystems Inc.\nBootLoader constants: OS\u003dlinux, ARCH\u003damd64, WS\u003dgtk, NL\u003den_US\nCommand-line arguments: ./eclipse -Dorg.eclipse.core.runtime.ignoreLockFile\n\n!ENTRY \ninitial@reference:file:/usr/local/eclipse/plugins/org.eclipse.core.runtime_3.0.\n1/ 0 0 Jan 31, 2\n005 18:50:33.499\n!MESSAGE FrameworkEvent.ERROR\n!STACK 0\norg.osgi.framework.BundleException: Exception in \norg.eclipse.core.internal.runtime.PlatformActivator.s\ntart() of bundle org.eclipse.core.runtime.\n        at \norg.eclipse.osgi.framework.internal.core.BundleContextImpl.startActivator\n(BundleContextImpl\n.java:975)\n        at org.eclipse.osgi.framework.internal.core.BundleContextImpl.start\n(BundleContextImpl.java:937\n)\n        at org.eclipse.osgi.framework.internal.core.BundleHost.startWorker\n(BundleHost.java:421)\n        at org.eclipse.osgi.framework.internal.core.AbstractBundle.resume\n(AbstractBundle.java:366)\n        at org.eclipse.osgi.framework.internal.core.Framework.resumeBundle\n(Framework.java:999)\n        at \norg.eclipse.osgi.framework.internal.core.StartLevelManager.resumeBundles\n(StartLevelManager.\njava:577)\n        at org.eclipse.osgi.framework.internal.core.StartLevelManager.incFWSL\n(StartLevelManager.java:4\n88)\n        at \norg.eclipse.osgi.framework.internal.core.StartLevelManager.doSetStartLevel\n(StartLevelManage\nr.java:273)\n        at \norg.eclipse.osgi.framework.internal.core.StartLevelManager.dispatchEvent\n(StartLevelManager.\njava:444)\n        at org.eclipse.osgi.framework.eventmgr.EventManager.dispatchEvent\n(EventManager.java:186)\n        at org.eclipse.osgi.framework.eventmgr.EventThread.run\n(EventThread.java:104)\nCaused by: java.io.IOException: An error occurred while locking \nfile \"/home/suhit/.eclipse/org.eclipse\n.platform_3.0.1/configuration/org.eclipse.core.runtime/.manager/.fileTableLock\"\n: \"Input/output error\".\n A probably reason is that the file system or Runtime Environment does not \nsupport file locking. You m\nay want to choose a different location, or disable file locking (using the \nosgi.locking property), but\n this can cause data corruption.\n        at org.eclipse.core.runtime.adaptor.Locker_JavaNio.lock\n(Locker_JavaNio.java:42)\n        at org.eclipse.osgi.service.datalocation.FileManager.lock\n(FileManager.java:219)\n        at org.eclipse.osgi.service.datalocation.FileManager.open\n(FileManager.java:423)\n        at \norg.eclipse.core.internal.runtime.InternalPlatform.initializeRuntimeFileManager\n(InternalPla\ntform.java:391)\n        at org.eclipse.core.internal.runtime.InternalPlatform.start\n(InternalPlatform.java:384)\n        at \norg.eclipse.core.internal.runtime.PlatformActivator.startInternalPlatform\n(PlatformActivator\n.java:251)\n        at org.eclipse.core.internal.runtime.PlatformActivator.start\n(PlatformActivator.java:64)\n        at org.eclipse.osgi.framework.internal.core.BundleContextImpl$1.run\n(BundleContextImpl.java:958\n)\n        at java.security.AccessController.doPrivileged(Native Method)\n        at \norg.eclipse.osgi.framework.internal.core.BundleContextImpl.startActivator\n(BundleContextImpl\n.java:954)\n        ... 10 more\nRoot exception:\njava.io.IOException: An error occurred while locking \nfile \"/home/suhit/.eclipse/org.eclipse.platform_3\n.0.1/configuration/org.eclipse.core.runtime/.manager/.fileTableLock\": \"Input/ou\ntput error\". A probably\n reason is that the file system or Runtime Environment does not support file \nlocking. You may want to \nchoose a different location, or disable file locking (using the osgi.locking \nproperty), but this can c\nause data corruption.\n        at org.eclipse.core.runtime.adaptor.Locker_JavaNio.lock\n(Locker_JavaNio.java:42)\n        at org.eclipse.osgi.service.datalocation.FileManager.lock\n(FileManager.java:219)\n        at org.eclipse.osgi.service.datalocation.FileManager.open\n(FileManager.java:423)\n        at \norg.eclipse.core.internal.runtime.InternalPlatform.initializeRuntimeFileManager\n(InternalPla\ntform.java:391)\n        at org.eclipse.core.internal.runtime.InternalPlatform.start\n(InternalPlatform.java:384)\n        at \norg.eclipse.core.internal.runtime.PlatformActivator.startInternalPlatform\n(PlatformActivator\n.java:251)\n        at org.eclipse.core.internal.runtime.PlatformActivator.start\n(PlatformActivator.java:64)\n        at org.eclipse.osgi.framework.internal.core.BundleContextImpl$1.run\n(BundleContextImpl.java:958\n)\n        at java.security.AccessController.doPrivileged(Native Method)\n        at \norg.eclipse.osgi.framework.internal.core.BundleContextImpl.startActivator\n(BundleContextImpl\n.java:954)\n        at org.eclipse.osgi.framework.internal.core.BundleContextImpl.start\n(BundleContextImpl.java:937\n)\n        at org.eclipse.osgi.framework.internal.core.BundleHost.startWorker\n(BundleHost.java:421)\n        at org.eclipse.osgi.framework.internal.core.AbstractBundle.resume\n(AbstractBundle.java:366)\n        at org.eclipse.osgi.framework.internal.core.Framework.resumeBundle\n(Framework.java:999)\n        at \norg.eclipse.osgi.framework.internal.core.StartLevelManager.resumeBundles\n(StartLevelManager.\njava:577)\n        at org.eclipse.osgi.framework.internal.core.StartLevelManager.incFWSL\n(StartLevelManager.java:4\n88)\n        at \norg.eclipse.osgi.framework.internal.core.StartLevelManager.doSetStartLevel\n(StartLevelManage\nr.java:273)\n        at \norg.eclipse.osgi.framework.internal.core.StartLevelManager.dispatchEvent\n(StartLevelManager.\njava:444)\n        at org.eclipse.osgi.framework.eventmgr.EventManager.dispatchEvent\n(EventManager.java:186)\n        at org.eclipse.osgi.framework.eventmgr.EventThread.run\n(EventThread.java:104)\n\n!ENTRY \ninitial@reference:file:/usr/local/eclipse/plugins/org.eclipse.update.configurat\nor_3.0.0/ 0 0 Ja\nn 31, 2005 18:50:33.509\n!MESSAGE FrameworkEvent.ERROR\n!STACK 0\norg.osgi.framework.BundleException: Exception in \norg.eclipse.update.internal.configurator.Configuratio\nnActivator.start() of bundle org.eclipse.update.configurator.\n        at \norg.eclipse.osgi.framework.internal.core.BundleContextImpl.startActivator\n(BundleContextImpl\n.java:975)\n        at org.eclipse.osgi.framework.internal.core.BundleContextImpl.start\n(BundleContextImpl.java:937\n)\n        at org.eclipse.osgi.framework.internal.core.BundleHost.startWorker\n(BundleHost.java:421)\n        at org.eclipse.osgi.framework.internal.core.AbstractBundle.resume\n(AbstractBundle.java:366)\n        at org.eclipse.osgi.framework.internal.core.Framework.resumeBundle\n(Framework.java:999)\n        at \norg.eclipse.osgi.framework.internal.core.StartLevelManager.resumeBundles\n(StartLevelManager.\njava:577)\n        at org.eclipse.osgi.framework.internal.core.StartLevelManager.incFWSL\n(StartLevelManager.java:4\n88)\n        at \norg.eclipse.osgi.framework.internal.core.StartLevelManager.doSetStartLevel\n(StartLevelManage\nr.java:273)\n        at \norg.eclipse.osgi.framework.internal.core.StartLevelManager.dispatchEvent\n(StartLevelManager.\njava:444)\n        at org.eclipse.osgi.framework.eventmgr.EventManager.dispatchEvent\n(EventManager.java:186)\n        at org.eclipse.osgi.framework.eventmgr.EventThread.run\n(EventThread.java:104)\nCaused by: java.lang.Exception: Cannot initialize the Update Configurator\n        at \norg.eclipse.update.internal.configurator.ConfigurationActivator.initialize\n(ConfigurationAct\nivator.java:93)\n        at \norg.eclipse.update.internal.configurator.ConfigurationActivator.start\n(ConfigurationActivato\nr.java:71)\n        at org.eclipse.osgi.framework.internal.core.BundleContextImpl$1.run\n(BundleContextImpl.java:958\n)\n        at java.security.AccessController.doPrivileged(Native Method)\n        at \norg.eclipse.osgi.framework.internal.core.BundleContextImpl.startActivator\n(BundleContextImpl\n.java:954)\n        ... 10 more\nRoot exception:\njava.lang.Exception: Cannot initialize the Update Configurator\n        at \norg.eclipse.update.internal.configurator.ConfigurationActivator.initialize\n(ConfigurationAct\nivator.java:93)\n        at \norg.eclipse.update.internal.configurator.ConfigurationActivator.start\n(ConfigurationActivato\nr.java:71)\n        at org.eclipse.osgi.framework.internal.core.BundleContextImpl$1.run\n(BundleContextImpl.java:958\n)\n        at java.security.AccessController.doPrivileged(Native Method)\n        at \norg.eclipse.osgi.framework.internal.core.BundleContextImpl.startActivator\n(BundleContextImpl\n.java:954)\n        at org.eclipse.osgi.framework.internal.core.BundleContextImpl.start\n(BundleContextImpl.java:937\n)\n        at org.eclipse.osgi.framework.internal.core.BundleHost.startWorker\n(BundleHost.java:421)\n        at org.eclipse.osgi.framework.internal.core.AbstractBundle.resume\n(AbstractBundle.java:366)\n        at org.eclipse.osgi.framework.internal.core.Framework.resumeBundle\n(Framework.java:999)\n        at \norg.eclipse.osgi.framework.internal.core.StartLevelManager.resumeBundles\n(StartLevelManager.\njava:577)\n        at org.eclipse.osgi.framework.internal.core.StartLevelManager.incFWSL\n(StartLevelManager.java:4\n88)\n        at \norg.eclipse.osgi.framework.internal.core.StartLevelManager.doSetStartLevel\n(StartLevelManage\nr.java:273)\n        at \norg.eclipse.osgi.framework.internal.core.StartLevelManager.dispatchEvent\n(StartLevelManager.\njava:444)\n        at org.eclipse.osgi.framework.eventmgr.EventManager.dispatchEvent\n(EventManager.java:186)\n        at org.eclipse.osgi.framework.eventmgr.EventThread.run\n(EventThread.java:104)\n\n!ENTRY org.eclipse.osgi Jan 31, 2005 18:50:33.519\n!MESSAGE Startup error\n!STACK 1\njava.lang.IllegalStateException: Bundle \ninitial@reference:file:/usr/local/eclipse/plugins/org.eclipse.\ncore.runtime_3.0.1/ [1] is not active.\n        at org.eclipse.core.runtime.adaptor.EclipseStarter.ensureBundlesActive\n(EclipseStarter.java:303\n)\n        at org.eclipse.core.runtime.adaptor.EclipseStarter.startup\n(EclipseStarter.java:227)\n        at org.eclipse.core.runtime.adaptor.EclipseStarter.run\n(EclipseStarter.java:127)\n        at sun.reflect.NativeMethodAccessorImpl.invoke0(Native Method)\n        at sun.reflect.NativeMethodAccessorImpl.invoke\n(NativeMethodAccessorImpl.java:39)\n        at sun.reflect.DelegatingMethodAccessorImpl.invoke\n(DelegatingMethodAccessorImpl.java:25)\n        at java.lang.reflect.Method.invoke(Method.java:585)\n        at org.eclipse.core.launcher.Main.basicRun(Main.java:185)\n        at org.eclipse.core.launcher.Main.run(Main.java:704)\n        at org.eclipse.core.launcher.Main.main(Main.java:688)",
    "As per bug 44735 comment 37, the system property to disable file locking using\njava.nio now is (and has been since the 3.0 release):\n\n-Dosgi.locking\u003dnone\n\n*** This bug has been marked as a duplicate of 44735 ***"
  ],
  "commentCreationDates": [
    "2005-02-01T00:09:31+01:00",
    "2005-02-01T14:56:56+01:00"
  ],
  "traces": [
    {
      "exceptionType": "org.osgi.framework.BundleException",
      "message": "Exception in  org.eclipse.core.internal.runtime.PlatformActivator.s tart() of bundle org.eclipse.core.runtime.",
      "elements": [
        {
          "method": "org.eclipse.osgi.framework.internal.core.BundleContextImpl.startActivator",
          "source": "BundleContextImpl .java:975"
        },
        {
          "method": "org.eclipse.osgi.framework.internal.core.BundleContextImpl.start",
          "source": "BundleContextImpl.java:937 "
        },
        {
          "method": "org.eclipse.osgi.framework.internal.core.BundleHost.startWorker",
          "source": "BundleHost.java:421"
        },
        {
          "method": "org.eclipse.osgi.framework.internal.core.AbstractBundle.resume",
          "source": "AbstractBundle.java:366"
        },
        {
          "method": "org.eclipse.osgi.framework.internal.core.Framework.resumeBundle",
          "source": "Framework.java:999"
        },
        {
          "method": "org.eclipse.osgi.framework.internal.core.StartLevelManager.resumeBundles",
          "source": "StartLevelManager. java:577"
        },
        {
          "method": "org.eclipse.osgi.framework.internal.core.StartLevelManager.incFWSL",
          "source": "StartLevelManager.java:4 88"
        },
        {
          "method": "org.eclipse.osgi.framework.internal.core.StartLevelManager.doSetStartLevel",
          "source": "StartLevelManage r.java:273"
        },
        {
          "method": "org.eclipse.osgi.framework.internal.core.StartLevelManager.dispatchEvent",
          "source": "StartLevelManager. java:444"
        },
        {
          "method": "org.eclipse.osgi.framework.eventmgr.EventManager.dispatchEvent",
          "source": "EventManager.java:186"
        },
        {
          "method": "org.eclipse.osgi.framework.eventmgr.EventThread.run",
          "source": "EventThread.java:104"
        }
      ],
      "causedBy": {
        "exceptionType": "java.io.IOException",
        "message": "An error occurred while locking  file \"/home/suhit/.eclipse/org.eclipse .platform_3.0.1/configuration/org.eclipse.core.runtime/.manager/.fileTableLock\" : \"Input/output error\".  A probably reason is that the file system or Runtime Environment does not  support file locking. You m ay want to choose a different location, or disable file locking (using the  osgi.locking property), but  this can cause data corruption.",
        "elements": [
          {
            "method": "org.eclipse.core.runtime.adaptor.Locker_JavaNio.lock",
            "source": "Locker_JavaNio.java:42"
          },
          {
            "method": "org.eclipse.osgi.service.datalocation.FileManager.lock",
            "source": "FileManager.java:219"
          },
          {
            "method": "org.eclipse.osgi.service.datalocation.FileManager.open",
            "source": "FileManager.java:423"
          },
          {
            "method": "org.eclipse.core.internal.runtime.InternalPlatform.initializeRuntimeFileManager",
            "source": "InternalPla tform.java:391"
          },
          {
            "method": "org.eclipse.core.internal.runtime.InternalPlatform.start",
            "source": "InternalPlatform.java:384"
          },
          {
            "method": "org.eclipse.core.internal.runtime.PlatformActivator.startInternalPlatform",
            "source": "PlatformActivator .java:251"
          },
          {
            "method": "org.eclipse.core.internal.runtime.PlatformActivator.start",
            "source": "PlatformActivator.java:64"
          },
          {
            "method": "org.eclipse.osgi.framework.internal.core.BundleContextImpl$1.run",
            "source": "BundleContextImpl.java:958 "
          },
          {
            "method": "java.security.AccessController.doPrivileged",
            "source": "Native Method"
          },
          {
            "method": "org.eclipse.osgi.framework.internal.core.BundleContextImpl.startActivator",
            "source": "BundleContextImpl .java:954"
          }
        ],
        "number": 0,
        "commentIndex": 0
      },
      "number": 0,
      "commentIndex": 0,
      "bugId": "84106",
      "duplicateId": "44735",
      "date": "2005-02-01T00:09:31+01:00",
      "product": "Platform",
      "component": "Runtime",
      "severity": "normal"
    },
    {
      "exceptionType": "java.io.IOException",
      "message": "An error occurred while locking  file \"/home/suhit/.eclipse/org.eclipse.platform_3 .0.1/configuration/org.eclipse.core.runtime/.manager/.fileTableLock\": \"Input/ou tput error\". A probably  reason is that the file system or Runtime Environment does not support file  locking. You may want to  choose a different location, or disable file locking (using the osgi.locking  property), but this can c ause data corruption.",
      "elements": [
        {
          "method": "org.eclipse.core.runtime.adaptor.Locker_JavaNio.lock",
          "source": "Locker_JavaNio.java:42"
        },
        {
          "method": "org.eclipse.osgi.service.datalocation.FileManager.lock",
          "source": "FileManager.java:219"
        },
        {
          "method": "org.eclipse.osgi.service.datalocation.FileManager.open",
          "source": "FileManager.java:423"
        },
        {
          "method": "org.eclipse.core.internal.runtime.InternalPlatform.initializeRuntimeFileManager",
          "source": "InternalPla tform.java:391"
        },
        {
          "method": "org.eclipse.core.internal.runtime.InternalPlatform.start",
          "source": "InternalPlatform.java:384"
        },
        {
          "method": "org.eclipse.core.internal.runtime.PlatformActivator.startInternalPlatform",
          "source": "PlatformActivator .java:251"
        }
      ],
      "number": 1,
      "commentIndex": 0,
      "bugId": "84106",
      "duplicateId": "44735",
      "date": "2005-02-01T00:09:31+01:00",
      "product": "Platform",
      "component": "Runtime",
      "severity": "normal"
    },
    {
      "exceptionType": "org.osgi.framework.BundleException",
      "message": "Exception in  org.eclipse.core.internal.runtime.PlatformActivator.s tart() of bundle org.eclipse.core.runtime.",
      "elements": [
        {
          "method": "org.eclipse.osgi.framework.internal.core.BundleContextImpl.startActivator",
          "source": "BundleContextImpl .java:975"
        },
        {
          "method": "org.eclipse.osgi.framework.internal.core.BundleContextImpl.start",
          "source": "BundleContextImpl.java:937 "
        },
        {
          "method": "org.eclipse.osgi.framework.internal.core.BundleHost.startWorker",
          "source": "BundleHost.java:421"
        },
        {
          "method": "org.eclipse.osgi.framework.internal.core.AbstractBundle.resume",
          "source": "AbstractBundle.java:366"
        },
        {
          "method": "org.eclipse.osgi.framework.internal.core.Framework.resumeBundle",
          "source": "Framework.java:999"
        },
        {
          "method": "org.eclipse.osgi.framework.internal.core.StartLevelManager.resumeBundles",
          "source": "StartLevelManager. java:577"
        },
        {
          "method": "org.eclipse.osgi.framework.internal.core.StartLevelManager.incFWSL",
          "source": "StartLevelManager.java:4 88"
        },
        {
          "method": "org.eclipse.osgi.framework.internal.core.StartLevelManager.doSetStartLevel",
          "source": "StartLevelManage r.java:273"
        },
        {
          "method": "org.eclipse.osgi.framework.internal.core.StartLevelManager.dispatchEvent",
          "source": "StartLevelManager. java:444"
        },
        {
          "method": "org.eclipse.osgi.framework.eventmgr.EventManager.dispatchEvent",
          "source": "EventManager.java:186"
        },
        {
          "method": "org.eclipse.osgi.framework.eventmgr.EventThread.run",
          "source": "EventThread.java:104"
        }
      ],
      "causedBy": {
        "exceptionType": "java.io.IOException",
        "message": "An error occurred while locking  file \"/home/suhit/.eclipse/org.eclipse .platform_3.0.1/configuration/org.eclipse.core.runtime/.manager/.fileTableLock\" : \"Input/output error\".  A probably reason is that the file system or Runtime Environment does not  support file locking. You m ay want to choose a different location, or disable file locking (using the  osgi.locking property), but  this can cause data corruption.",
        "elements": [
          {
            "method": "org.eclipse.core.runtime.adaptor.Locker_JavaNio.lock",
            "source": "Locker_JavaNio.java:42"
          },
          {
            "method": "org.eclipse.osgi.service.datalocation.FileManager.lock",
            "source": "FileManager.java:219"
          },
          {
            "method": "org.eclipse.osgi.service.datalocation.FileManager.open",
            "source": "FileManager.java:423"
          },
          {
            "method": "org.eclipse.core.internal.runtime.InternalPlatform.initializeRuntimeFileManager",
            "source": "InternalPla tform.java:391"
          },
          {
            "method": "org.eclipse.core.internal.runtime.InternalPlatform.start",
            "source": "InternalPlatform.java:384"
          },
          {
            "method": "org.eclipse.core.internal.runtime.PlatformActivator.startInternalPlatform",
            "source": "PlatformActivator .java:251"
          },
          {
            "method": "org.eclipse.core.internal.runtime.PlatformActivator.start",
            "source": "PlatformActivator.java:64"
          },
          {
            "method": "org.eclipse.osgi.framework.internal.core.BundleContextImpl$1.run",
            "source": "BundleContextImpl.java:958 "
          },
          {
            "method": "java.security.AccessController.doPrivileged",
            "source": "Native Method"
          },
          {
            "method": "org.eclipse.osgi.framework.internal.core.BundleContextImpl.startActivator",
            "source": "BundleContextImpl .java:954"
          }
        ],
        "number": 0,
        "commentIndex": 0
      },
      "number": 2,
      "commentIndex": 0,
      "bugId": "84106",
      "duplicateId": "44735",
      "date": "2005-02-01T00:09:31+01:00",
      "product": "Platform",
      "component": "Runtime",
      "severity": "normal"
    },
    {
      "exceptionType": "java.io.IOException",
      "message": "An error occurred while locking  file \"/home/suhit/.eclipse/org.eclipse.platform_3 .0.1/configuration/org.eclipse.core.runtime/.manager/.fileTableLock\": \"Input/ou tput error\". A probably  reason is that the file system or Runtime Environment does not support file  locking. You may want to  choose a different location, or disable file locking (using the osgi.locking  property), but this can c ause data corruption.",
      "elements": [
        {
          "method": "org.eclipse.core.runtime.adaptor.Locker_JavaNio.lock",
          "source": "Locker_JavaNio.java:42"
        },
        {
          "method": "org.eclipse.osgi.service.datalocation.FileManager.lock",
          "source": "FileManager.java:219"
        },
        {
          "method": "org.eclipse.osgi.service.datalocation.FileManager.open",
          "source": "FileManager.java:423"
        },
        {
          "method": "org.eclipse.core.internal.runtime.InternalPlatform.initializeRuntimeFileManager",
          "source": "InternalPla tform.java:391"
        },
        {
          "method": "org.eclipse.core.internal.runtime.InternalPlatform.start",
          "source": "InternalPlatform.java:384"
        },
        {
          "method": "org.eclipse.core.internal.runtime.PlatformActivator.startInternalPlatform",
          "source": "PlatformActivator .java:251"
        },
        {
          "method": "org.eclipse.core.internal.runtime.PlatformActivator.start",
          "source": "PlatformActivator.java:64"
        },
        {
          "method": "org.eclipse.osgi.framework.internal.core.BundleContextImpl$1.run",
          "source": "BundleContextImpl.java:958 "
        },
        {
          "method": "java.security.AccessController.doPrivileged",
          "source": "Native Method"
        },
        {
          "method": "org.eclipse.osgi.framework.internal.core.BundleContextImpl.startActivator",
          "source": "BundleContextImpl .java:954"
        },
        {
          "method": "org.eclipse.osgi.framework.internal.core.BundleContextImpl.start",
          "source": "BundleContextImpl.java:937 "
        },
        {
          "method": "org.eclipse.osgi.framework.internal.core.BundleHost.startWorker",
          "source": "BundleHost.java:421"
        },
        {
          "method": "org.eclipse.osgi.framework.internal.core.AbstractBundle.resume",
          "source": "AbstractBundle.java:366"
        },
        {
          "method": "org.eclipse.osgi.framework.internal.core.Framework.resumeBundle",
          "source": "Framework.java:999"
        },
        {
          "method": "org.eclipse.osgi.framework.internal.core.StartLevelManager.resumeBundles",
          "source": "StartLevelManager. java:577"
        },
        {
          "method": "org.eclipse.osgi.framework.internal.core.StartLevelManager.incFWSL",
          "source": "StartLevelManager.java:4 88"
        },
        {
          "method": "org.eclipse.osgi.framework.internal.core.StartLevelManager.doSetStartLevel",
          "source": "StartLevelManage r.java:273"
        },
        {
          "method": "org.eclipse.osgi.framework.internal.core.StartLevelManager.dispatchEvent",
          "source": "StartLevelManager. java:444"
        },
        {
          "method": "org.eclipse.osgi.framework.eventmgr.EventManager.dispatchEvent",
          "source": "EventManager.java:186"
        },
        {
          "method": "org.eclipse.osgi.framework.eventmgr.EventThread.run",
          "source": "EventThread.java:104"
        }
      ],
      "number": 3,
      "commentIndex": 0,
      "bugId": "84106",
      "duplicateId": "44735",
      "date": "2005-02-01T00:09:31+01:00",
      "product": "Platform",
      "component": "Runtime",
      "severity": "normal"
    },
    {
      "exceptionType": "org.osgi.framework.BundleException",
      "message": "Exception in  org.eclipse.update.internal.configurator.Configuratio nActivator.start() of bundle org.eclipse.update.configurator.",
      "elements": [
        {
          "method": "org.eclipse.osgi.framework.internal.core.BundleContextImpl.startActivator",
          "source": "BundleContextImpl .java:975"
        },
        {
          "method": "org.eclipse.osgi.framework.internal.core.BundleContextImpl.start",
          "source": "BundleContextImpl.java:937 "
        },
        {
          "method": "org.eclipse.osgi.framework.internal.core.BundleHost.startWorker",
          "source": "BundleHost.java:421"
        },
        {
          "method": "org.eclipse.osgi.framework.internal.core.AbstractBundle.resume",
          "source": "AbstractBundle.java:366"
        },
        {
          "method": "org.eclipse.osgi.framework.internal.core.Framework.resumeBundle",
          "source": "Framework.java:999"
        },
        {
          "method": "org.eclipse.osgi.framework.internal.core.StartLevelManager.resumeBundles",
          "source": "StartLevelManager. java:577"
        },
        {
          "method": "org.eclipse.osgi.framework.internal.core.StartLevelManager.incFWSL",
          "source": "StartLevelManager.java:4 88"
        },
        {
          "method": "org.eclipse.osgi.framework.internal.core.StartLevelManager.doSetStartLevel",
          "source": "StartLevelManage r.java:273"
        },
        {
          "method": "org.eclipse.osgi.framework.internal.core.StartLevelManager.dispatchEvent",
          "source": "StartLevelManager. java:444"
        },
        {
          "method": "org.eclipse.osgi.framework.eventmgr.EventManager.dispatchEvent",
          "source": "EventManager.java:186"
        },
        {
          "method": "org.eclipse.osgi.framework.eventmgr.EventThread.run",
          "source": "EventThread.java:104"
        }
      ],
      "causedBy": {
        "exceptionType": "java.lang.Exception",
        "message": "Cannot initialize the Update Configurator",
        "elements": [
          {
            "method": "org.eclipse.update.internal.configurator.ConfigurationActivator.initialize",
            "source": "ConfigurationAct ivator.java:93"
          },
          {
            "method": "org.eclipse.update.internal.configurator.ConfigurationActivator.start",
            "source": "ConfigurationActivato r.java:71"
          },
          {
            "method": "org.eclipse.osgi.framework.internal.core.BundleContextImpl$1.run",
            "source": "BundleContextImpl.java:958 "
          },
          {
            "method": "java.security.AccessController.doPrivileged",
            "source": "Native Method"
          },
          {
            "method": "org.eclipse.osgi.framework.internal.core.BundleContextImpl.startActivator",
            "source": "BundleContextImpl .java:954"
          }
        ],
        "number": 0,
        "commentIndex": 0
      },
      "number": 4,
      "commentIndex": 0,
      "bugId": "84106",
      "duplicateId": "44735",
      "date": "2005-02-01T00:09:31+01:00",
      "product": "Platform",
      "component": "Runtime",
      "severity": "normal"
    },
    {
      "exceptionType": "java.lang.Exception",
      "message": "Cannot initialize the Update Configurator",
      "elements": [
        {
          "method": "org.eclipse.update.internal.configurator.ConfigurationActivator.initialize",
          "source": "ConfigurationAct ivator.java:93"
        },
        {
          "method": "org.eclipse.update.internal.configurator.ConfigurationActivator.start",
          "source": "ConfigurationActivato r.java:71"
        },
        {
          "method": "org.eclipse.osgi.framework.internal.core.BundleContextImpl$1.run",
          "source": "BundleContextImpl.java:958 "
        },
        {
          "method": "java.security.AccessController.doPrivileged",
          "source": "Native Method"
        },
        {
          "method": "org.eclipse.osgi.framework.internal.core.BundleContextImpl.startActivator",
          "source": "BundleContextImpl .java:954"
        },
        {
          "method": "org.eclipse.osgi.framework.internal.core.BundleContextImpl.start",
          "source": "BundleContextImpl.java:937 "
        },
        {
          "method": "org.eclipse.osgi.framework.internal.core.BundleHost.startWorker",
          "source": "BundleHost.java:421"
        },
        {
          "method": "org.eclipse.osgi.framework.internal.core.AbstractBundle.resume",
          "source": "AbstractBundle.java:366"
        },
        {
          "method": "org.eclipse.osgi.framework.internal.core.Framework.resumeBundle",
          "source": "Framework.java:999"
        },
        {
          "method": "org.eclipse.osgi.framework.internal.core.StartLevelManager.resumeBundles",
          "source": "StartLevelManager. java:577"
        },
        {
          "method": "org.eclipse.osgi.framework.internal.core.StartLevelManager.incFWSL",
          "source": "StartLevelManager.java:4 88"
        },
        {
          "method": "org.eclipse.osgi.framework.internal.core.StartLevelManager.doSetStartLevel",
          "source": "StartLevelManage r.java:273"
        },
        {
          "method": "org.eclipse.osgi.framework.internal.core.StartLevelManager.dispatchEvent",
          "source": "StartLevelManager. java:444"
        },
        {
          "method": "org.eclipse.osgi.framework.eventmgr.EventManager.dispatchEvent",
          "source": "EventManager.java:186"
        },
        {
          "method": "org.eclipse.osgi.framework.eventmgr.EventThread.run",
          "source": "EventThread.java:104"
        }
      ],
      "number": 5,
      "commentIndex": 0,
      "bugId": "84106",
      "duplicateId": "44735",
      "date": "2005-02-01T00:09:31+01:00",
      "product": "Platform",
      "component": "Runtime",
      "severity": "normal"
    },
    {
      "exceptionType": "java.lang.IllegalStateException",
      "message": "Bundle  initial@reference:file:/usr/local/eclipse/plugins/org.eclipse. core.runtime_3.0.1/ [1] is not active.",
      "elements": [
        {
          "method": "org.eclipse.core.runtime.adaptor.EclipseStarter.ensureBundlesActive",
          "source": "EclipseStarter.java:303 "
        },
        {
          "method": "org.eclipse.core.runtime.adaptor.EclipseStarter.startup",
          "source": "EclipseStarter.java:227"
        },
        {
          "method": "org.eclipse.core.runtime.adaptor.EclipseStarter.run",
          "source": "EclipseStarter.java:127"
        },
        {
          "method": "sun.reflect.NativeMethodAccessorImpl.invoke0",
          "source": "Native Method"
        },
        {
          "method": "sun.reflect.NativeMethodAccessorImpl.invoke",
          "source": "NativeMethodAccessorImpl.java:39"
        },
        {
          "method": "sun.reflect.DelegatingMethodAccessorImpl.invoke",
          "source": "DelegatingMethodAccessorImpl.java:25"
        },
        {
          "method": "java.lang.reflect.Method.invoke",
          "source": "Method.java:585"
        },
        {
          "method": "org.eclipse.core.launcher.Main.basicRun",
          "source": "Main.java:185"
        },
        {
          "method": "org.eclipse.core.launcher.Main.run",
          "source": "Main.java:704"
        },
        {
          "method": "org.eclipse.core.launcher.Main.main",
          "source": "Main.java:688"
        }
      ],
      "number": 6,
      "commentIndex": 0,
      "bugId": "84106",
      "duplicateId": "44735",
      "date": "2005-02-01T00:09:31+01:00",
      "product": "Platform",
      "component": "Runtime",
      "severity": "normal"
    }
  ],
  "groupId": "44735",
  "bugId": "84106",
  "duplicateId": "44735",
  "date": "2005-02-01T00:09:31+01:00",
  "product": "Platform",
  "component": "Runtime",
  "severity": "normal"
}