{
  "comments": [
    "Just noticed this exception in my log file. (second exception is interesting) I\n*think* it may have happened when I was debugging and I clicked on a\njava.util.Properties object in the Variables view and it didn\u0027t print anything.\n\n!SESSION 2005-02-02 13:19:27.557 -----------------------------------------------\neclipse.buildId\u003dI20050202-0800\njava.fullversion\u003dJ2RE 1.4.2 IBM J9 2.2 Windows XP x86-32 j9n142-20040915 (JIT\nenabled)\nJ9VM - 20040914_1123_lHdSMR\nJIT  - r7_level20040912_1800\nBootLoader constants: OS\u003dwin32, ARCH\u003dx86, WS\u003dwin32, NL\u003den_CA\nFramework arguments:  -showlocation\nCommand-line arguments:  -os win32 -ws win32 -arch x86 -debug -data\n\\eclipse\\target\\head\\plugins\\ -showlocation -consoleLog -console\n\n!ENTRY org.eclipse.jdt.launching 4 120 2005-02-02 13:19:27.567\n!MESSAGE Cannot connect to VM\n!STACK 0\njava.net.SocketException: socket closed\n        at java.net.PlainSocketImpl.socketAccept(Native Method)\n        at java.net.PlainSocketImpl.accept(PlainSocketImpl.java:379)\n        at java.net.ServerSocket.implAccept(ServerSocket.java:471)\n        at java.net.ServerSocket.accept(ServerSocket.java:442)\n        at\norg.eclipse.jdi.internal.connect.SocketTransportService.accept(SocketTransportService.java:91)\n        at\norg.eclipse.jdi.internal.connect.SocketTransportImpl.accept(SocketTransportImpl.java:56)\n        at\norg.eclipse.jdi.internal.connect.SocketListeningConnectorImpl.accept(SocketListeningConnectorImpl.java:128)\n        at\norg.eclipse.jdt.internal.launching.StandardVMDebugger$ConnectRunnable.run(StandardVMDebugger.java:78)\n        at java.lang.Thread.run(Thread.java:813)\n\n!ENTRY org.eclipse.jdt.debug 4 120 2005-02-02 13:25:12.272\n!MESSAGE Exception processing async thread queue\n!SUBENTRY 1 org.eclipse.jdt.debug 4 120 2005-02-02 13:25:12.272\n!MESSAGE Exception processing async thread queue\n!STACK 0\njava.lang.ArrayIndexOutOfBoundsException\n        at java.util.ArrayList.get(ArrayList.java:358)\n        at\norg.eclipse.jdt.internal.debug.eval.ast.instructions.InstructionSequence.getInstruction(InstructionSequence.java:104)\n        at\norg.eclipse.jdt.internal.debug.eval.ast.engine.ASTInstructionCompiler.endVisit(ASTInstructionCompiler.java:993)\n        at org.eclipse.jdt.core.dom.ForStatement.accept0(ForStatement.java:230)\n        at org.eclipse.jdt.core.dom.ASTNode.accept(ASTNode.java:2450)\n        at org.eclipse.jdt.core.dom.ASTNode.acceptChildren(ASTNode.java:2520)\n        at org.eclipse.jdt.core.dom.Block.accept0(Block.java:135)\n        at org.eclipse.jdt.core.dom.ASTNode.accept(ASTNode.java:2450)\n        at org.eclipse.jdt.core.dom.ASTNode.acceptChild(ASTNode.java:2497)\n        at\norg.eclipse.jdt.core.dom.MethodDeclaration.accept0(MethodDeclaration.java:503)\n        at org.eclipse.jdt.core.dom.ASTNode.accept(ASTNode.java:2450)\n        at org.eclipse.jdt.core.dom.ASTNode.acceptChildren(ASTNode.java:2520)\n        at\norg.eclipse.jdt.core.dom.TypeDeclaration.accept0(TypeDeclaration.java:477)\n        at org.eclipse.jdt.core.dom.ASTNode.accept(ASTNode.java:2450)\n        at org.eclipse.jdt.core.dom.ASTNode.acceptChildren(ASTNode.java:2520)\n        at\norg.eclipse.jdt.core.dom.CompilationUnit.accept0(CompilationUnit.java:291)\n        at org.eclipse.jdt.core.dom.ASTNode.accept(ASTNode.java:2450)\n        at\norg.eclipse.jdt.internal.debug.eval.ast.engine.ASTEvaluationEngine.createExpressionFromAST(ASTEvaluationEngine.java:283)\n        at\norg.eclipse.jdt.internal.debug.eval.ast.engine.ASTEvaluationEngine.getCompiledExpression(ASTEvaluationEngine.java:230)\n        at\norg.eclipse.jdt.internal.debug.eval.ast.engine.ASTEvaluationEngine.getCompiledExpression(ASTEvaluationEngine.java:200)\n        at\norg.eclipse.jdt.internal.debug.ui.JavaDetailFormattersManager.getCompiledExpression(JavaDetailFormattersManager.java:295)\n        at\norg.eclipse.jdt.internal.debug.ui.JavaDetailFormattersManager.resolveFormatter(JavaDetailFormattersManager.java:162)\n        at\norg.eclipse.jdt.internal.debug.ui.JavaDetailFormattersManager.access$0(JavaDetailFormattersManager.java:150)\n        at\norg.eclipse.jdt.internal.debug.ui.JavaDetailFormattersManager$4.run(JavaDetailFormattersManager.java:138)\n        at\norg.eclipse.jdt.internal.debug.core.model.JDIThread$ThreadJob.run(JDIThread.java:2531)\n        at org.eclipse.core.internal.jobs.Worker.run(Worker.java:66)",
    "From the stack trace, it looks like you have a detail formatter defined with a\nfor loop in its code. Is it possible to get info about this detail formatter ?",
    "Hey, I forgot all about that. Here it is. It is defined against the\njava.util.HashMap type.\n\nint max \u003d size() - 1;\nStringBuffer buf \u003d new StringBuffer();\nIterator it \u003d entrySet().iterator();\n\nbuf.append(\"{\");\nfor (int i \u003d 0; i \u003c\u003d max; i++) {\n    Map.Entry e \u003d (Map.Entry) (it.next());\n        Object key \u003d e.getKey();\n        Object value \u003d e.getValue();\n        buf.append((key   \u003d\u003d this ? \"(this Map)\" : key) + \"\u003d\" +\n                   (value \u003d\u003d this ? \"(this Map)\" : value));\n\n    if (i \u003c max)\n\tbuf.append(\",\\n\");\n}\nbuf.append(\"}\");\nreturn buf.toString();",
    "Fixed.\nThere was a problem in the autoboxing support, the case of string concatenation\nwith an Object as parameter was no correctly managed.\nA simpler test case is the evaluation of :\n\"test\" + new Object()\n\nASTInstruction compiler - modified to correctly indicate if an instruction has\nbeen added to outbox a value.",
    "Please verify, Darin W.",
    "Verified."
  ],
  "commentCreationDates": [
    "2005-02-02T19:17:03+01:00",
    "2005-02-02T19:42:50+01:00",
    "2005-02-02T19:51:58+01:00",
    "2005-02-03T21:33:58+01:00",
    "2005-02-03T21:34:35+01:00",
    "2005-02-07T17:35:56+01:00"
  ],
  "traces": [
    {
      "exceptionType": "java.net.SocketException",
      "message": "socket closed",
      "elements": [
        {
          "method": "java.net.PlainSocketImpl.socketAccept",
          "source": "Native Method"
        },
        {
          "method": "java.net.PlainSocketImpl.accept",
          "source": "PlainSocketImpl.java:379"
        },
        {
          "method": "java.net.ServerSocket.implAccept",
          "source": "ServerSocket.java:471"
        },
        {
          "method": "java.net.ServerSocket.accept",
          "source": "ServerSocket.java:442"
        },
        {
          "method": "org.eclipse.jdi.internal.connect.SocketTransportService.accept",
          "source": "SocketTransportService.java:91"
        },
        {
          "method": "org.eclipse.jdi.internal.connect.SocketTransportImpl.accept",
          "source": "SocketTransportImpl.java:56"
        },
        {
          "method": "org.eclipse.jdi.internal.connect.SocketListeningConnectorImpl.accept",
          "source": "SocketListeningConnectorImpl.java:128"
        },
        {
          "method": "org.eclipse.jdt.internal.launching.StandardVMDebugger$ConnectRunnable.run",
          "source": "StandardVMDebugger.java:78"
        },
        {
          "method": "java.lang.Thread.run",
          "source": "Thread.java:813"
        }
      ],
      "number": 0,
      "commentIndex": 0,
      "bugId": "84259",
      "date": "2005-02-02T19:17:03+01:00",
      "product": "JDT",
      "component": "Debug",
      "severity": "normal"
    },
    {
      "exceptionType": "java.lang.ArrayIndexOutOfBoundsException",
      "elements": [
        {
          "method": "java.util.ArrayList.get",
          "source": "ArrayList.java:358"
        },
        {
          "method": "org.eclipse.jdt.internal.debug.eval.ast.instructions.InstructionSequence.getInstruction",
          "source": "InstructionSequence.java:104"
        },
        {
          "method": "org.eclipse.jdt.internal.debug.eval.ast.engine.ASTInstructionCompiler.endVisit",
          "source": "ASTInstructionCompiler.java:993"
        },
        {
          "method": "org.eclipse.jdt.core.dom.ForStatement.accept0",
          "source": "ForStatement.java:230"
        },
        {
          "method": "org.eclipse.jdt.core.dom.ASTNode.accept",
          "source": "ASTNode.java:2450"
        },
        {
          "method": "org.eclipse.jdt.core.dom.ASTNode.acceptChildren",
          "source": "ASTNode.java:2520"
        },
        {
          "method": "org.eclipse.jdt.core.dom.Block.accept0",
          "source": "Block.java:135"
        },
        {
          "method": "org.eclipse.jdt.core.dom.ASTNode.accept",
          "source": "ASTNode.java:2450"
        },
        {
          "method": "org.eclipse.jdt.core.dom.ASTNode.acceptChild",
          "source": "ASTNode.java:2497"
        },
        {
          "method": "org.eclipse.jdt.core.dom.MethodDeclaration.accept0",
          "source": "MethodDeclaration.java:503"
        },
        {
          "method": "org.eclipse.jdt.core.dom.ASTNode.accept",
          "source": "ASTNode.java:2450"
        },
        {
          "method": "org.eclipse.jdt.core.dom.ASTNode.acceptChildren",
          "source": "ASTNode.java:2520"
        },
        {
          "method": "org.eclipse.jdt.core.dom.TypeDeclaration.accept0",
          "source": "TypeDeclaration.java:477"
        },
        {
          "method": "org.eclipse.jdt.core.dom.ASTNode.accept",
          "source": "ASTNode.java:2450"
        },
        {
          "method": "org.eclipse.jdt.core.dom.ASTNode.acceptChildren",
          "source": "ASTNode.java:2520"
        },
        {
          "method": "org.eclipse.jdt.core.dom.CompilationUnit.accept0",
          "source": "CompilationUnit.java:291"
        },
        {
          "method": "org.eclipse.jdt.core.dom.ASTNode.accept",
          "source": "ASTNode.java:2450"
        },
        {
          "method": "org.eclipse.jdt.internal.debug.eval.ast.engine.ASTEvaluationEngine.createExpressionFromAST",
          "source": "ASTEvaluationEngine.java:283"
        },
        {
          "method": "org.eclipse.jdt.internal.debug.eval.ast.engine.ASTEvaluationEngine.getCompiledExpression",
          "source": "ASTEvaluationEngine.java:230"
        },
        {
          "method": "org.eclipse.jdt.internal.debug.eval.ast.engine.ASTEvaluationEngine.getCompiledExpression",
          "source": "ASTEvaluationEngine.java:200"
        },
        {
          "method": "org.eclipse.jdt.internal.debug.ui.JavaDetailFormattersManager.getCompiledExpression",
          "source": "JavaDetailFormattersManager.java:295"
        },
        {
          "method": "org.eclipse.jdt.internal.debug.ui.JavaDetailFormattersManager.resolveFormatter",
          "source": "JavaDetailFormattersManager.java:162"
        },
        {
          "method": "org.eclipse.jdt.internal.debug.ui.JavaDetailFormattersManager.access$0",
          "source": "JavaDetailFormattersManager.java:150"
        },
        {
          "method": "org.eclipse.jdt.internal.debug.ui.JavaDetailFormattersManager$4.run",
          "source": "JavaDetailFormattersManager.java:138"
        },
        {
          "method": "org.eclipse.jdt.internal.debug.core.model.JDIThread$ThreadJob.run",
          "source": "JDIThread.java:2531"
        },
        {
          "method": "org.eclipse.core.internal.jobs.Worker.run",
          "source": "Worker.java:66"
        }
      ],
      "number": 1,
      "commentIndex": 0,
      "bugId": "84259",
      "date": "2005-02-02T19:17:03+01:00",
      "product": "JDT",
      "component": "Debug",
      "severity": "normal"
    }
  ],
  "groupId": "84259",
  "bugId": "84259",
  "date": "2005-02-02T19:17:03+01:00",
  "product": "JDT",
  "component": "Debug",
  "severity": "normal"
}