{
  "comments": [
    "Reported by Geert Vermeiren:\n\nHi,\n\nSame problem occurs on my machine. I\u0027m running linux-gtk(2.4.x) on amd64. In\naddition to the exception in the original report, I get an error dialog when\nclicking the Help preferences:\n\"Could not accept changes - The currently displayed page contains invalid \nvalues\". \nAfter activating another prefs page, then re-activating the help prefs, the \npage\nappears, \"The selection determines...\" but no controls are available on the\npage. Both \u0027mozilla\u0027 and \u0027firefox\u0027 are available as browsers on my system.\n\nIn .log I found:\n\n!SESSION 2005-01-28 20:16:41.298 ----------------------------------------------\n-\neclipse.buildId\u003dI20041216-2000\njava.version\u003d1.5.0_01\njava.vendor\u003dSun Microsystems Inc.\nBootLoader constants: OS\u003dlinux, ARCH\u003damd64, WS\u003dgtk, NL\u003den_US\nCommand-line arguments:  -os linux -ws gtk -arch amd64\n\n!ENTRY org.eclipse.core.runtime 4 2 2005-01-28 20:16:41.299\n!MESSAGE Problems occurred when invoking code from plug-in:\n\"org.eclipse.core.runtime\".\n!STACK 0\njava.lang.NoClassDefFoundError: org/eclipse/swt/internal/mozilla/nsEmbedString\n        at org.eclipse.swt.browser.Browser.\u003cinit\u003e(Browser.java:143)\n        at\norg.eclipse.help.ui.internal.browser.embedded.EmbeddedBrowserFactory.test\n(EmbeddedBrowserFactory.java:69)\n        at\norg.eclipse.help.ui.internal.browser.embedded.EmbeddedBrowserFactory.isAvailabl\ne(EmbeddedBrowserFactory.java:49)\n        at\norg.eclipse.help.internal.browser.BrowserManager.createBrowserDescriptors\n(BrowserManager.java:215)\n        at\norg.eclipse.help.internal.browser.BrowserManager.init(BrowserManager.java:75)\n        at\norg.eclipse.help.internal.browser.BrowserManager.isEmbeddedBrowserPresent\n(BrowserManager.java:385)\n        at\norg.eclipse.help.ui.internal.browser.BrowsersPreferencePage.createContents\n(BrowsersPreferencePage.java:58)\n        at\norg.eclipse.jface.preference.PreferencePage.createControl\n(PreferencePage.java:425)\n        at\norg.eclipse.jface.preference.PreferencePage.createControl\n(PreferencePage.java:390)\n        at\norg.eclipse.ui.internal.dialogs.WorkbenchPreferenceDialog.createPageControl\n(WorkbenchPreferenceDialog.java:1044)\n        at\norg.eclipse.jface.preference.PreferenceDialog$13.run\n(PreferenceDialog.java:1132)\n        at\norg.eclipse.core.internal.runtime.InternalPlatform.run\n(InternalPlatform.java:1061)\n        at org.eclipse.core.runtime.Platform.run(Platform.java:747)\n        at\norg.eclipse.jface.preference.PreferenceDialog.showPage\n(PreferenceDialog.java:1126)\n        at\norg.eclipse.ui.internal.dialogs.WorkbenchPreferenceDialog.showPage\n(WorkbenchPreferenceDialog.java:818)\n        at\norg.eclipse.jface.preference.PreferenceDialog$9.selectionChanged\n(PreferenceDialog.java:628)\n        at\norg.eclipse.jface.viewers.StructuredViewer$3.run(StructuredViewer.java:681)\n        at\norg.eclipse.core.internal.runtime.InternalPlatform.run\n(InternalPlatform.java:1061)\n        at org.eclipse.core.runtime.Platform.run(Platform.java:747)\n        at\norg.eclipse.jface.viewers.StructuredViewer.firePostSelectionChanged\n(StructuredViewer.java:679)\n        at\norg.eclipse.jface.viewers.StructuredViewer.handlePostSelect\n(StructuredViewer.java:950)\n        at\norg.eclipse.jface.viewers.StructuredViewer$5.widgetSelected\n(StructuredViewer.java:970)\n        at\norg.eclipse.jface.util.OpenStrategy.firePostSelectionEvent\n(OpenStrategy.java:231)\n        at org.eclipse.jface.util.OpenStrategy.access$4(OpenStrategy.java:226)\n        at org.eclipse.jface.util.OpenStrategy$3.run(OpenStrategy.java:392)\n        at org.eclipse.swt.widgets.RunnableLock.run(RunnableLock.java:35)\n        at\norg.eclipse.swt.widgets.Synchronizer.runAsyncMessages(Synchronizer.java:118)\n        at org.eclipse.swt.widgets.Display.runAsyncMessages(Display.java:2695)\n        at org.eclipse.swt.widgets.Display.readAndDispatch(Display.java:2420)\n        at org.eclipse.jface.window.Window.runEventLoop(Window.java:718)\n        at org.eclipse.jface.window.Window.open(Window.java:696)\n        at\norg.eclipse.ui.internal.OpenPreferencesAction.run\n(OpenPreferencesAction.java:64)\n        at org.eclipse.jface.action.Action.runWithEvent(Action.java:989)\n        at\norg.eclipse.jface.action.ActionContributionItem.handleWidgetSelection\n(ActionContributionItem.java:555)\n        at\norg.eclipse.jface.action.ActionContributionItem.access$2\n(ActionContributionItem.java:505)\n        at\norg.eclipse.jface.action.ActionContributionItem$6.handleEvent\n(ActionContributionItem.java:419)\n        at org.eclipse.swt.widgets.EventTable.sendEvent(EventTable.java:82)\n        at org.eclipse.swt.widgets.Widget.sendEvent(Widget.java:1002)\n        at org.eclipse.swt.widgets.Display.runDeferredEvents(Display.java:2718)\n        at org.eclipse.swt.widgets.Display.readAndDispatch(Display.java:2417)\n        at org.eclipse.ui.internal.Workbench.runEventLoop(Workbench.java:1575)\n        at org.eclipse.ui.internal.Workbench.runUI(Workbench.java:1541)\n        at\norg.eclipse.ui.internal.Workbench.createAndRunWorkbench(Workbench.java:287)\n        at org.eclipse.ui.PlatformUI.createAndRunWorkbench(PlatformUI.java:144)\n        at org.eclipse.ui.internal.ide.IDEApplication.run\n(IDEApplication.java:102)\n        at\norg.eclipse.core.internal.runtime.PlatformActivator$1.run\n(PlatformActivator.java:220)\n        at\norg.eclipse.core.runtime.adaptor.EclipseStarter.run(EclipseStarter.java:274)\n        at\norg.eclipse.core.runtime.adaptor.EclipseStarter.run(EclipseStarter.java:129)\n        at sun.reflect.NativeMethodAccessorImpl.invoke0(Native Method)\n        at\nsun.reflect.NativeMethodAccessorImpl.invoke(NativeMethodAccessorImpl.java:39)\n        at\nsun.reflect.DelegatingMethodAccessorImpl.invoke\n(DelegatingMethodAccessorImpl.java:25)\n        at java.lang.reflect.Method.invoke(Method.java:585)\n        at org.eclipse.core.launcher.Main.basicRun(Main.java:255)\n        at org.eclipse.core.launcher.Main.run(Main.java:811)\n        at org.eclipse.core.launcher.Main.main(Main.java:795)",
    "Geert:\nWhat is your linux distribution?\nWhich Mozilla is installed? (you can get the version by typing about: in the \nMozilla URL entry.\n\nAre you using the 64 bit version of Eclipse or the regular 32 bit Linux GTK \nEclipse?\n\nThanks!",
    "Hi Christophe,\n\nHere\u0027s the info:\n\nlinux Fedora Core 3 for amd64\ntwo browsers are installed:\nfirefox 1.0 (Mozilla/5.0 (X11; U; Linux x86_64; en-US; rv:1.7.5) Gecko/20041110\nFirefox/1.0)\nmozilla 1.7.3 (Mozilla/5.0 (X11; U; Linux x86_64; en-US; rv:1.7.3) Gecko/20041020)\n\n!SESSION 2005-02-04 09:42:24.467 \neclipse.buildId\u003dI20041216-2000\njava.version\u003d1.5.0_01\njava.vendor\u003dSun Microsystems Inc.\nBootLoader constants: OS\u003dlinux, ARCH\u003damd64, WS\u003dgtk, NL\u003den_US\nCommand-line arguments:  -os linux -ws gtk -arch amd64\n\nIf you need additional info, or want me to run some tests, let me know, I\u0027d be\nglad to help.\n\nbr,\n\nGeert",
    "If you need to get things working, here what to do so that the Browser does \nnot show up:\n\ncsh\nsetenv MOZILLA_FIVE_HOME EMPTY\neclipse\n\nThis will cause the SWT Browser to not find any Mozilla build. And Eclipse \nshould be usable to you.\n\nTo help us understand more:\n\n1. Which build of Eclipse are you using? Go to Help \u003e About Eclipse Platform \u003e \nbuild id\n\n2. Can you paste the output of the following:\n- start Mozilla\n- type the following in the Mozilla URL bar (without the \nquotes): \"build.config\"\nJust to verify it is a GTK2 64 build.\n\n\nThis is weird. nsEmbedString should be in the swt-mozilla.jar under the \norg.eclipse.swt.gtk64 fragment. In case you were running 3.0, can you try a \nrecent integration build (today\u0027s one for example)? I would have expected a \ndifferent kind of error.\n\n\n\n",
    "build-id: I20050202-0800\n\nTyping build.config at the url of mozilla just says \u0027www.build.config\u0027 not found :-)\n\nabout: in the url gives me\nMozilla/5.0 (X11; U; Linux x86_64; en-US; rv:1.7.3) Gecko/20041020\nPretty sure it\u0027s the correct version as it was installed with Fedora\n\nAnyway, I tried looking at the error-log, clicking the button from the eclipse\nabout-box. Guess what? Mozilla opened showing me .log (apparently it uses\nanother way of opening mozilla)\n\n!SESSION 2005-02-11 18:49:07.69 ------------------------------------------------\neclipse.buildId\u003dI20050202-0800\njava.version\u003d1.5.0_01\njava.vendor\u003dSun Microsystems Inc.\nBootLoader constants: OS\u003dlinux, ARCH\u003dx86_64, WS\u003dgtk, NL\u003den_US\nCommand-line arguments:  -os linux -ws gtk -arch x86_64\n\n!ENTRY org.eclipse.ui 4 4 2005-02-11 18:49:07.70\n!MESSAGE Unhandled event loop exception\n\n!ENTRY org.eclipse.ui 4 0 2005-02-11 18:49:07.71\n!MESSAGE org/eclipse/swt/internal/mozilla/nsEmbedString\n!STACK 0\njava.lang.NoClassDefFoundError: org/eclipse/swt/internal/mozilla/nsEmbedString\n\tat org.eclipse.swt.browser.Browser.\u003cinit\u003e(Browser.java:143)\n\tat\norg.eclipse.help.ui.internal.browser.embedded.EmbeddedBrowserFactory.test(EmbeddedBrowserFactory.java:69)\n\tat\norg.eclipse.help.ui.internal.browser.embedded.EmbeddedBrowserFactory.isAvailable(EmbeddedBrowserFactory.java:49)\n\nThe exception happened as I tried viewing help (Help \u003e Help Contents) after startup.",
    "Thanks. Sorry, it was: \"about:buildconfig\", not build.config.\n\nTo be able to use Eclipse until this issue is resolved, please do this:\ncsh\nsetenv MOZILLA_FIVE_HOME EMPTY\neclipse\n\nThat causes the SWT Browser widget to not find/embed your Mozilla and to not \nthrow that exception.\n\n\u003e apparently it uses another way of opening mozilla)\nYes in that case it\u0027s launching an external Mozilla.\n",
    "Indeed, the setenv thing does the trick. \n\nThe build.config ;-)\n\nabout:buildconfig\n\nBuild platform\ntarget\nx86_64-unknown-linux-gnu\n\nBuild tools\nCompiler \tVersion \tCompiler flags\ngcc \tgcc version 3.4.2 20041017 (Red Hat 3.4.2-6) \t-Wall -W -Wno-unused\n-Wpointer-arith -Wcast-align -Wno-long-long -pedantic -g -pthread -pipe\nc++ \tgcc version 3.4.2 20041017 (Red Hat 3.4.2-6) \t-fno-rtti -fno-exceptions\n-Wall -Wconversion -Wpointer-arith -Wcast-align -Woverloaded-virtual -Wsynth\n-Wno-ctor-dtor-privacy -Wno-non-virtual-dtor -Wno-long-long -pedantic -g\n-fshort-wchar -pthread -pipe -I/usr/X11R6/include\n\nConfigure arguments\n--prefix\u003d/usr --libdir\u003d/usr/lib64 --enable-optimize\u003d-O2 --disable-debug\n--with-default-mozilla-five-home\u003d/usr/lib64/mozilla-1.7.3 --disable-strip-libs\n--disable-tests --enable-xinerama --enable-nspr-autoconf\n--enable-extensions\u003ddefault,irc --without-mng --enable-crypto --disable-xprint\n--without-system-nspr --with-system-zlib --with-system-png --with-system-jpeg\n--enable-default-toolkit\u003dgtk2 --disable-freetype2 --enable-xft --enable-pango\n--mandir\u003d/usr/share/man \n",
    "Additionally, after setting the environment thingie, the help-prefs page is back\nto normal too. I see 3 external browsers (mozilla, firefox which I installed\nmanually, and \u0027custom\u0027). Without setenv the list was empty.",
    "*** Bug 86760 has been marked as a duplicate of this bug. ***",
    "*** Bug 88391 has been marked as a duplicate of this bug. ***",
    "Fixed. AMD64 Browser will simply throw a NO MORE HANDLES, Browser is not \nsupported for 3.1 on that platform. This will let the build work fine without \nthe Browser functionality.\n\nThe swt-mozilla native library is no longer built for AMD64. The problem is \nthat we currently need to build against Mozilla 1.4 to be upward compatible, \nhowever there are no standard out of the box Mozilla 1.4 64 bit compliant \nsources. At the moment every distribution has their own set of patches to \nworkaround 64 bit issues. As an experiment, I tried to build our library \nagainst a 1.7.5 patched from Gentoo but that has proven to be causing trouble \nand not very useful since it was not working with most other 64 bit Mozilla \nbuilds.\n64 bit Browser support can be revisited if a future version of the Browser is \nimplemented on top of GtkMozembed or when major Linux distributions switched \nto a standard 64 bit 1.7 version of Mozilla.",
    "How about some instructions for those of us willing to brave these issues? I\ntried doing this myself. Here is what I did:\n\ncd\n~/eclipse-3.1/plugins/org.eclipse.platform.source.linux.gtk.x86_64_3.1.0/src/org.eclipse.swt.gtk.linux.x86_64_3.1.0/\n\nmkdir src\ncd src\nunzip ../src.zip\nvi make_linux.mak\n\nA the diff with the changes:\n\n--- src/make_linux.mak  2005-05-13 14:40:30.000000000 -0700\n+++ crap/make_linux.mak 2005-05-19 00:13:01.725435072 -0700\n@@ -50,6 +50,7 @@\n # Uncomment for Native Stats tool\n #NATIVE_STATS \u003d -DNATIVE_STATS\n \n+MOZILLA_FIVE_HOME\u003d/opt/mozilla64\n MOZILLACFLAGS \u003d -O \\\n        -DXPCOM_GLUE\u003d1 \\\n        -DMOZILLA_STRICT_API\u003d1 \\\n@@ -62,6 +63,10 @@\n        -I./ \\\n        -I$(JAVA_HOME)/include \\\n        -I$(JAVA_HOME)/include/linux \\\n+       -I$(MOZILLA_FIVE_HOME)/include/xpcom \\\n+       -I$(MOZILLA_FIVE_HOME)/include/nspr \\\n+       -I$(MOZILLA_FIVE_HOME)/include/embed_base \\\n+       -I$(MOZILLA_FIVE_HOME)/include/string \\\n        ${GECKO_INCLUDES} \\\n        ${SWT_PTR_CFLAGS}\n        \n@@ -86,7 +91,7 @@\n LIBS \u003d -shared -fpic -s\n \n \n-all: make_swt make_atk make_gnome make_awt\n+all: make_swt make_atk make_gnome make_awt make_mozilla\n \n #\n # SWT libs\n\nmake -f make_linux.mak\ncp libswt*.so ~/eclipse-3.1/configuration/org.eclipse.osgi/bundles/41/1/.cp/\n\n(It seems eclipse 3.1 extracts the .so files from a jar and creates an arbitrary\ndirectory to put them in. This is that directory on my machine, so I put these\nfiles here)\n\nI then run eclipse with MOZILLA_FIVE_HOME\u003d/opt/mozilla64 (the default mozilla on\nmy machine is 32 bit. I keep a 64 bit mozilla here for eclipse only). I get this:\n\njava.lang.UnsatisfiedLinkError:\n/home/primus/eclipse-3.1/configuration/org.eclipse.osgi/bundles/41/1/.cp/libswt-pi-gtk-3135.so:\n/home/primus/eclipse-3.1/configuration/org.eclipse.osgi/bundles/41/1/.cp/libswt-pi-gtk-3135.so:\nundefined symbol: XTestFakeButtonEvent\n\nIf I don\u0027t replace the two library files that come from the eclipse jar file, I\nget this:\n\norg.eclipse.swt.SWTError: No more handles (java.lang.UnsatisfiedLinkError: no\nswt-mozilla-gtk-3135 in java.library.path)\n\nSo I then do a bunch of stracing and try to find where it\u0027s looking for the said\nfile. It actually finds it in the bundles/41/1/.cp directory, but refuses to use\nit. I then copy it to /opt/mozilla64, and symlink it to libswt-mozilla-gtk.so,\nand it find it. Which then yields:\n\norg.eclipse.swt.SWTError: No more handles (java.lang.UnsatisfiedLinkError:\n/opt/mozilla64/libswt-mozilla-gtk-3135.so:\n/opt/mozilla64/libswt-mozilla-gtk-3135.so: undefined symbol: _ZN4nsID5ParseEPKc)\n\nThis is in libxpcom.so, which is found in /opt/mozilla64. I then for this to be\nloaded with LD_PRELOAD. This gets me this:\n\norg.eclipse.swt.SWTError: No more handles (java.lang.UnsatisfiedLinkError:\n/opt/mozilla64/libswt-mozilla-gtk-3135.so:\n/opt/mozilla64/libswt-mozilla-gtk-3135.so: undefined symbol: NS_InitEmbedding)\n\nSeeing the pattern here? It seems this libswt-mozilla-gtk can\u0027t or won\u0027t resolve\nits dependent libraries. Anyhow, that symbol is found in libgtkembedmoz.so. I\ntry to LD_PRELOAD this too, which then causes java to simply crash.\n\nI guess I\u0027d just like to know what I did wrong, if anything. How can I force the\nlibswt-mozilla-gtk.so to resolve its libraries? Is there a way to do this?\nShould I just give up? I\u0027d _really_ like the embedded browser in eclipse 3.1 on\namd64.\n\nBTW, the embeded browser in 3.1M6 on Linux amd64 works fine for me.\n\nThoughts?",
    "Also, is there a bug report report to track the issue of getting a stable \nMozilla build against which we can compile?  This bug report is closed but the \nissue is not fully resolved.",
    "This bug report is a bit confusing.  All of the stack traces on this bug are for\nNoClassDefFound errors, which indicates a problem in the Java side and not with\nthe compiled mozilla code or the version of mozilla on the target machine.  This\nindicates a bug either with the build, or with the class loader.  I believe that\nthese problems are resolved by the new build strategy for 3.1 which puts all of\nthe SWT Java code in a single jar.\n\nSince:\n\n  1. It is a pain to build the mozilla library for amd64 users that want it\n  2. There are no reported crashes from incompatible mozilla builds\n  3. amd64 is still an \"early access\" platform for Eclipse\n  4. Users are asking for embedded mozilla support\n  5. It\u0027s easy to disable if it is causing problems (unset MOZILLA_FIVE_HOME)\n\nI think we should just re-enable it in our builds.",
    "*** Bug 96405 has been marked as a duplicate of this bug. ***",
    "Please re-enabled for RC2. Request done per Billy Biggs request on IRC.",
    "I have added the mozilla library for AMD64.\nUnfortunately, I did not make it in time for the warm up RC2 build at noon \ntoday but it will be in for the next build - which will be at 4PM today.",
    "I have compiled the eclipse 3.1 final on amd64 against mozilla 1.7.8 and the\nembedded browser works nicely after patching a few files here and there (all\nrequired changes have been entered as bugs here).\n\nBefore compiling remember to delete all the .so files so that you can be sure\nthat the ones distributed with the source package are not used.",
    "Tested and works on Fedora Core 4 Java 1.5.0_04 x86_64,  stock mozilla 1.7.10\nRPMS, and eclipse 3.1  Only had to install the compat-libstdc++33 for x86_64 to\nprovide libstdc++.so.5.  \n\njust set \nexport MOZILLA_FIVE_HOME\u003d/usr/lib64/mozilla-1.7.10\nexport LD_LIBRARY_PATH\u003d\"$MOZILLA_FIVE_HOME:$LD_LIBRARY_PATH\"\n\nin my eclipse wrapper startup script. ",
    "I\u0027m seeing 3.2.2 crashes with\n\n/usr/bin/java: symbol lookup error: /opt/eclipse64/configuration/org.eclipse.osgi/bundles/518/1/.cp/libswt-mozilla-gcc3-gtk-3236.so: undefined symbol: NS_InitEmbedding\n\n\n",
    "re: comment 19\n\na fix is available for this, see https://bugs.eclipse.org/bugs/show_bug.cgi?id\u003d174547#c8\n",
    "Closing, this was fixed quite a while ago.\n"
  ],
  "commentCreationDates": [
    "2005-02-08T13:57:52+01:00",
    "2005-02-08T14:02:26+01:00",
    "2005-02-08T19:29:10+01:00",
    "2005-02-08T20:13:14+01:00",
    "2005-02-11T18:04:30+01:00",
    "2005-02-11T18:35:16+01:00",
    "2005-02-11T18:50:12+01:00",
    "2005-02-11T18:54:07+01:00",
    "2005-02-27T02:29:43+01:00",
    "2005-03-17T22:33:02+01:00",
    "2005-04-13T17:41:05+02:00",
    "2005-05-20T00:26:45+02:00",
    "2005-05-31T13:37:17+02:00",
    "2005-06-01T17:43:55+02:00",
    "2005-06-01T17:45:07+02:00",
    "2005-06-09T03:43:27+02:00",
    "2005-06-09T19:40:24+02:00",
    "2005-06-29T22:40:34+02:00",
    "2005-08-19T00:29:33+02:00",
    "2007-05-04T17:23:09+02:00",
    "2007-05-07T18:28:25+02:00",
    "2007-08-28T18:46:24+02:00"
  ],
  "traces": [
    {
      "exceptionType": "java.lang.NoClassDefFoundError",
      "message": "org/eclipse/swt/internal/mozilla/nsEmbedString",
      "elements": [
        {
          "method": "org.eclipse.swt.browser.Browser.\u003cinit\u003e",
          "source": "Browser.java:143"
        },
        {
          "method": "org.eclipse.help.ui.internal.browser.embedded.EmbeddedBrowserFactory.test",
          "source": "EmbeddedBrowserFactory.java:69"
        },
        {
          "method": "org.eclipse.help.ui.internal.browser.embedded.EmbeddedBrowserFactory.isAvailable",
          "source": "EmbeddedBrowserFactory.java:49"
        },
        {
          "method": "org.eclipse.help.internal.browser.BrowserManager.createBrowserDescriptors",
          "source": "BrowserManager.java:215"
        },
        {
          "method": "org.eclipse.help.internal.browser.BrowserManager.init",
          "source": "BrowserManager.java:75"
        },
        {
          "method": "org.eclipse.help.internal.browser.BrowserManager.isEmbeddedBrowserPresent",
          "source": "BrowserManager.java:385"
        },
        {
          "method": "org.eclipse.help.ui.internal.browser.BrowsersPreferencePage.createContents",
          "source": "BrowsersPreferencePage.java:58"
        },
        {
          "method": "org.eclipse.jface.preference.PreferencePage.createControl",
          "source": "PreferencePage.java:425"
        },
        {
          "method": "org.eclipse.jface.preference.PreferencePage.createControl",
          "source": "PreferencePage.java:390"
        },
        {
          "method": "org.eclipse.ui.internal.dialogs.WorkbenchPreferenceDialog.createPageControl",
          "source": "WorkbenchPreferenceDialog.java:1044"
        },
        {
          "method": "org.eclipse.jface.preference.PreferenceDialog$13.run",
          "source": "PreferenceDialog.java:1132"
        },
        {
          "method": "org.eclipse.core.internal.runtime.InternalPlatform.run",
          "source": "InternalPlatform.java:1061"
        },
        {
          "method": "org.eclipse.core.runtime.Platform.run",
          "source": "Platform.java:747"
        },
        {
          "method": "org.eclipse.jface.preference.PreferenceDialog.showPage",
          "source": "PreferenceDialog.java:1126"
        },
        {
          "method": "org.eclipse.ui.internal.dialogs.WorkbenchPreferenceDialog.showPage",
          "source": "WorkbenchPreferenceDialog.java:818"
        },
        {
          "method": "org.eclipse.jface.preference.PreferenceDialog$9.selectionChanged",
          "source": "PreferenceDialog.java:628"
        },
        {
          "method": "org.eclipse.jface.viewers.StructuredViewer$3.run",
          "source": "StructuredViewer.java:681"
        },
        {
          "method": "org.eclipse.core.internal.runtime.InternalPlatform.run",
          "source": "InternalPlatform.java:1061"
        },
        {
          "method": "org.eclipse.core.runtime.Platform.run",
          "source": "Platform.java:747"
        },
        {
          "method": "org.eclipse.jface.viewers.StructuredViewer.firePostSelectionChanged",
          "source": "StructuredViewer.java:679"
        },
        {
          "method": "org.eclipse.jface.viewers.StructuredViewer.handlePostSelect",
          "source": "StructuredViewer.java:950"
        },
        {
          "method": "org.eclipse.jface.viewers.StructuredViewer$5.widgetSelected",
          "source": "StructuredViewer.java:970"
        },
        {
          "method": "org.eclipse.jface.util.OpenStrategy.firePostSelectionEvent",
          "source": "OpenStrategy.java:231"
        },
        {
          "method": "org.eclipse.jface.util.OpenStrategy.access$4",
          "source": "OpenStrategy.java:226"
        },
        {
          "method": "org.eclipse.jface.util.OpenStrategy$3.run",
          "source": "OpenStrategy.java:392"
        },
        {
          "method": "org.eclipse.swt.widgets.RunnableLock.run",
          "source": "RunnableLock.java:35"
        },
        {
          "method": "org.eclipse.swt.widgets.Synchronizer.runAsyncMessages",
          "source": "Synchronizer.java:118"
        },
        {
          "method": "org.eclipse.swt.widgets.Display.runAsyncMessages",
          "source": "Display.java:2695"
        },
        {
          "method": "org.eclipse.swt.widgets.Display.readAndDispatch",
          "source": "Display.java:2420"
        },
        {
          "method": "org.eclipse.jface.window.Window.runEventLoop",
          "source": "Window.java:718"
        },
        {
          "method": "org.eclipse.jface.window.Window.open",
          "source": "Window.java:696"
        },
        {
          "method": "org.eclipse.ui.internal.OpenPreferencesAction.run",
          "source": "OpenPreferencesAction.java:64"
        },
        {
          "method": "org.eclipse.jface.action.Action.runWithEvent",
          "source": "Action.java:989"
        },
        {
          "method": "org.eclipse.jface.action.ActionContributionItem.handleWidgetSelection",
          "source": "ActionContributionItem.java:555"
        },
        {
          "method": "org.eclipse.jface.action.ActionContributionItem.access$2",
          "source": "ActionContributionItem.java:505"
        },
        {
          "method": "org.eclipse.jface.action.ActionContributionItem$6.handleEvent",
          "source": "ActionContributionItem.java:419"
        },
        {
          "method": "org.eclipse.swt.widgets.EventTable.sendEvent",
          "source": "EventTable.java:82"
        },
        {
          "method": "org.eclipse.swt.widgets.Widget.sendEvent",
          "source": "Widget.java:1002"
        },
        {
          "method": "org.eclipse.swt.widgets.Display.runDeferredEvents",
          "source": "Display.java:2718"
        },
        {
          "method": "org.eclipse.swt.widgets.Display.readAndDispatch",
          "source": "Display.java:2417"
        },
        {
          "method": "org.eclipse.ui.internal.Workbench.runEventLoop",
          "source": "Workbench.java:1575"
        },
        {
          "method": "org.eclipse.ui.internal.Workbench.runUI",
          "source": "Workbench.java:1541"
        },
        {
          "method": "org.eclipse.ui.internal.Workbench.createAndRunWorkbench",
          "source": "Workbench.java:287"
        },
        {
          "method": "org.eclipse.ui.PlatformUI.createAndRunWorkbench",
          "source": "PlatformUI.java:144"
        },
        {
          "method": "org.eclipse.ui.internal.ide.IDEApplication.run",
          "source": "IDEApplication.java:102"
        },
        {
          "method": "org.eclipse.core.internal.runtime.PlatformActivator$1.run",
          "source": "PlatformActivator.java:220"
        },
        {
          "method": "org.eclipse.core.runtime.adaptor.EclipseStarter.run",
          "source": "EclipseStarter.java:274"
        },
        {
          "method": "org.eclipse.core.runtime.adaptor.EclipseStarter.run",
          "source": "EclipseStarter.java:129"
        },
        {
          "method": "sun.reflect.NativeMethodAccessorImpl.invoke0",
          "source": "Native Method"
        },
        {
          "method": "sun.reflect.NativeMethodAccessorImpl.invoke",
          "source": "NativeMethodAccessorImpl.java:39"
        },
        {
          "method": "sun.reflect.DelegatingMethodAccessorImpl.invoke",
          "source": "DelegatingMethodAccessorImpl.java:25"
        },
        {
          "method": "java.lang.reflect.Method.invoke",
          "source": "Method.java:585"
        },
        {
          "method": "org.eclipse.core.launcher.Main.basicRun",
          "source": "Main.java:255"
        },
        {
          "method": "org.eclipse.core.launcher.Main.run",
          "source": "Main.java:811"
        },
        {
          "method": "org.eclipse.core.launcher.Main.main",
          "source": "Main.java:795"
        }
      ],
      "number": 0,
      "commentIndex": 0,
      "bugId": "84673",
      "date": "2005-02-08T13:57:52+01:00",
      "product": "Platform",
      "component": "SWT",
      "severity": "normal"
    },
    {
      "exceptionType": "java.lang.NoClassDefFoundError",
      "message": "org/eclipse/swt/internal/mozilla/nsEmbedString",
      "elements": [
        {
          "method": "org.eclipse.swt.browser.Browser.\u003cinit\u003e",
          "source": "Browser.java:143"
        },
        {
          "method": "org.eclipse.help.ui.internal.browser.embedded.EmbeddedBrowserFactory.test",
          "source": "EmbeddedBrowserFactory.java:69"
        },
        {
          "method": "org.eclipse.help.ui.internal.browser.embedded.EmbeddedBrowserFactory.isAvailable",
          "source": "EmbeddedBrowserFactory.java:49"
        }
      ],
      "number": 1,
      "commentIndex": 4,
      "bugId": "84673",
      "date": "2005-02-11T18:04:30+01:00",
      "product": "Platform",
      "component": "SWT",
      "severity": "normal"
    }
  ],
  "groupId": "84673",
  "bugId": "84673",
  "date": "2005-02-08T13:57:52+01:00",
  "product": "Platform",
  "component": "SWT",
  "severity": "normal"
}