{
  "comments": [
    "I20050208-0800\n\nI think I was saving a file and hittinc Ctrl-O for the quick outline when I got\na dialog saying there was an error in the log.\n\n!ENTRY org.eclipse.ui 4 0 2005-02-10 11:27:08.863\n!MESSAGE Widget is disposed\n!STACK 0\norg.eclipse.swt.SWTException: Widget is disposed\n        at org.eclipse.swt.SWT.error(SWT.java:2839)\n        at org.eclipse.swt.SWT.error(SWT.java:2762)\n        at org.eclipse.swt.SWT.error(SWT.java:2733)\n        at org.eclipse.swt.widgets.Widget.error(Widget.java:399)\n        at org.eclipse.swt.widgets.Widget.checkWidget(Widget.java:335)\n        at org.eclipse.swt.widgets.Widget.getData(Widget.java:425)\n        at\norg.eclipse.jdt.internal.ui.viewsupport.ProblemTableViewer.doUpdateItem(ProblemTableViewer.java:75)\n        at\norg.eclipse.jdt.internal.ui.viewsupport.ResourceToItemsMapper.updateItem(ResourceToItemsMapper.java:73)\n        at\norg.eclipse.jdt.internal.ui.viewsupport.ResourceToItemsMapper.resourceChanged(ResourceToItemsMapper.java:67)\n        at\norg.eclipse.jdt.internal.ui.viewsupport.ProblemTableViewer.handleLabelProviderChanged(ProblemTableViewer.java:123)\n        at\norg.eclipse.jdt.internal.ui.search.JavaSearchResultPage$3.handleLabelProviderChanged(JavaSearchResultPage.java:393)\n        at\norg.eclipse.jface.viewers.ContentViewer$1.labelProviderChanged(ContentViewer.java:74)\n        at\norg.eclipse.jdt.ui.ProblemsLabelDecorator.fireProblemsChanged(ProblemsLabelDecorator.java:357)\n        at\norg.eclipse.jdt.ui.ProblemsLabelDecorator.access$0(ProblemsLabelDecorator.java:352)\n        at\norg.eclipse.jdt.ui.ProblemsLabelDecorator$1.problemsChanged(ProblemsLabelDecorator.java:332)\n        at\norg.eclipse.jdt.internal.ui.viewsupport.ProblemMarkerManager$1.run(ProblemMarkerManager.java:176)\n        at org.eclipse.swt.widgets.RunnableLock.run(RunnableLock.java:35)\n        at\norg.eclipse.swt.widgets.Synchronizer.runAsyncMessages(Synchronizer.java:118)\n        at org.eclipse.swt.widgets.Display.runAsyncMessages(Display.java:2699)\n        at org.eclipse.swt.widgets.Display.readAndDispatch(Display.java:2424)\n        at org.eclipse.ui.internal.Workbench.runEventLoop(Workbench.java:1622)\n        at org.eclipse.ui.internal.Workbench.runUI(Workbench.java:1588)\n        at\norg.eclipse.ui.internal.Workbench.createAndRunWorkbench(Workbench.java:299)\n        at org.eclipse.ui.PlatformUI.createAndRunWorkbench(PlatformUI.java:144)\n        at org.eclipse.ui.internal.ide.IDEApplication.run(IDEApplication.java:102)\n        at\norg.eclipse.core.internal.runtime.PlatformActivator$1.run(PlatformActivator.java:227)\n        at\norg.eclipse.core.runtime.adaptor.EclipseStarter.run(EclipseStarter.java:281)\n        at\norg.eclipse.core.runtime.adaptor.EclipseStarter.run(EclipseStarter.java:131)\n        at sun.reflect.NativeMethodAccessorImpl.invoke0(Native Method)\n        at\nsun.reflect.NativeMethodAccessorImpl.invoke(NativeMethodAccessorImpl.java:39)\n        at\nsun.reflect.DelegatingMethodAccessorImpl.invoke(DelegatingMethodAccessorImpl.java:25)\n        at java.lang.reflect.Method.invoke(Method.java:324)\n        at org.eclipse.core.launcher.Main.basicRun(Main.java:261)\n        at org.eclipse.core.launcher.Main.run(Main.java:817)\n        at org.eclipse.core.launcher.Main.main(Main.java:801)",
    "\n\n*** This bug has been marked as a duplicate of 84747 ***"
  ],
  "commentCreationDates": [
    "2005-02-10T16:31:32+01:00",
    "2005-02-10T16:57:53+01:00"
  ],
  "traces": [
    {
      "exceptionType": "org.eclipse.swt.SWTException",
      "message": "Widget is disposed",
      "elements": [
        {
          "method": "org.eclipse.swt.SWT.error",
          "source": "SWT.java:2839"
        },
        {
          "method": "org.eclipse.swt.SWT.error",
          "source": "SWT.java:2762"
        },
        {
          "method": "org.eclipse.swt.SWT.error",
          "source": "SWT.java:2733"
        },
        {
          "method": "org.eclipse.swt.widgets.Widget.error",
          "source": "Widget.java:399"
        },
        {
          "method": "org.eclipse.swt.widgets.Widget.checkWidget",
          "source": "Widget.java:335"
        },
        {
          "method": "org.eclipse.swt.widgets.Widget.getData",
          "source": "Widget.java:425"
        },
        {
          "method": "org.eclipse.jdt.internal.ui.viewsupport.ProblemTableViewer.doUpdateItem",
          "source": "ProblemTableViewer.java:75"
        },
        {
          "method": "org.eclipse.jdt.internal.ui.viewsupport.ResourceToItemsMapper.updateItem",
          "source": "ResourceToItemsMapper.java:73"
        },
        {
          "method": "org.eclipse.jdt.internal.ui.viewsupport.ResourceToItemsMapper.resourceChanged",
          "source": "ResourceToItemsMapper.java:67"
        },
        {
          "method": "org.eclipse.jdt.internal.ui.viewsupport.ProblemTableViewer.handleLabelProviderChanged",
          "source": "ProblemTableViewer.java:123"
        },
        {
          "method": "org.eclipse.jdt.internal.ui.search.JavaSearchResultPage$3.handleLabelProviderChanged",
          "source": "JavaSearchResultPage.java:393"
        },
        {
          "method": "org.eclipse.jface.viewers.ContentViewer$1.labelProviderChanged",
          "source": "ContentViewer.java:74"
        },
        {
          "method": "org.eclipse.jdt.ui.ProblemsLabelDecorator.fireProblemsChanged",
          "source": "ProblemsLabelDecorator.java:357"
        },
        {
          "method": "org.eclipse.jdt.ui.ProblemsLabelDecorator.access$0",
          "source": "ProblemsLabelDecorator.java:352"
        },
        {
          "method": "org.eclipse.jdt.ui.ProblemsLabelDecorator$1.problemsChanged",
          "source": "ProblemsLabelDecorator.java:332"
        },
        {
          "method": "org.eclipse.jdt.internal.ui.viewsupport.ProblemMarkerManager$1.run",
          "source": "ProblemMarkerManager.java:176"
        },
        {
          "method": "org.eclipse.swt.widgets.RunnableLock.run",
          "source": "RunnableLock.java:35"
        },
        {
          "method": "org.eclipse.swt.widgets.Synchronizer.runAsyncMessages",
          "source": "Synchronizer.java:118"
        },
        {
          "method": "org.eclipse.swt.widgets.Display.runAsyncMessages",
          "source": "Display.java:2699"
        },
        {
          "method": "org.eclipse.swt.widgets.Display.readAndDispatch",
          "source": "Display.java:2424"
        },
        {
          "method": "org.eclipse.ui.internal.Workbench.runEventLoop",
          "source": "Workbench.java:1622"
        },
        {
          "method": "org.eclipse.ui.internal.Workbench.runUI",
          "source": "Workbench.java:1588"
        },
        {
          "method": "org.eclipse.ui.internal.Workbench.createAndRunWorkbench",
          "source": "Workbench.java:299"
        },
        {
          "method": "org.eclipse.ui.PlatformUI.createAndRunWorkbench",
          "source": "PlatformUI.java:144"
        },
        {
          "method": "org.eclipse.ui.internal.ide.IDEApplication.run",
          "source": "IDEApplication.java:102"
        },
        {
          "method": "org.eclipse.core.internal.runtime.PlatformActivator$1.run",
          "source": "PlatformActivator.java:227"
        },
        {
          "method": "org.eclipse.core.runtime.adaptor.EclipseStarter.run",
          "source": "EclipseStarter.java:281"
        },
        {
          "method": "org.eclipse.core.runtime.adaptor.EclipseStarter.run",
          "source": "EclipseStarter.java:131"
        },
        {
          "method": "sun.reflect.NativeMethodAccessorImpl.invoke0",
          "source": "Native Method"
        },
        {
          "method": "sun.reflect.NativeMethodAccessorImpl.invoke",
          "source": "NativeMethodAccessorImpl.java:39"
        },
        {
          "method": "sun.reflect.DelegatingMethodAccessorImpl.invoke",
          "source": "DelegatingMethodAccessorImpl.java:25"
        },
        {
          "method": "java.lang.reflect.Method.invoke",
          "source": "Method.java:324"
        },
        {
          "method": "org.eclipse.core.launcher.Main.basicRun",
          "source": "Main.java:261"
        },
        {
          "method": "org.eclipse.core.launcher.Main.run",
          "source": "Main.java:817"
        },
        {
          "method": "org.eclipse.core.launcher.Main.main",
          "source": "Main.java:801"
        }
      ],
      "number": 0,
      "commentIndex": 0,
      "bugId": "84909",
      "duplicateId": "84747",
      "date": "2005-02-10T16:31:32+01:00",
      "product": "JDT",
      "component": "UI",
      "severity": "normal"
    }
  ],
  "groupId": "84747",
  "bugId": "84909",
  "duplicateId": "84747",
  "date": "2005-02-10T16:31:32+01:00",
  "product": "JDT",
  "component": "UI",
  "severity": "normal"
}