{
  "comments": [
    "20020123/Linux\n\nBoot URL:\n    file:/home/eclipse/20020123/eclipse/plugins/org.eclipse.core.boot/boot.jar\n\nR2.0 startup mode activated\n\nInstall URL: file:/home/eclipse/20020123/eclipse/\nDebug-Options: file:/home/eclipse/20020123/eclipse/.options\n\njava.lang.reflect.InvocationTargetException: java.lang.UnsupportedOperationExcep\ntion\n        at java.util.AbstractList.remove(AbstractList.java:176)\n        at java.util.AbstractList$Itr.remove(AbstractList.java:439)\n        at java.util.AbstractCollection.remove(AbstractCollection.java:261)\n        at org.eclipse.core.internal.boot.PlatformConfiguration$SiteEntry.getPlu\ngins(PlatformConfiguration.java:184)\n        at org.eclipse.core.internal.boot.PlatformConfiguration$SiteEntry.comput\nePluginsChangeStamp(PlatformConfiguration.java:343)\n        at org.eclipse.core.internal.boot.PlatformConfiguration$SiteEntry.getPlu\nginsChangeStamp(PlatformConfiguration.java:216)\n        at org.eclipse.core.internal.boot.PlatformConfiguration.computePluginsCh\nangeStamp(PlatformConfiguration.java:827)\n        at org.eclipse.core.internal.boot.PlatformConfiguration.computeChangeSta\nmp(PlatformConfiguration.java:802)\n        at org.eclipse.core.internal.boot.PlatformConfiguration.\u003cinit\u003e(PlatformC\nonfiguration.java:476)\n        at org.eclipse.core.internal.boot.PlatformConfiguration.startup(Platform\nConf\nException launching the Eclipse Platform UI:\n\niguration.java:685)\n        at org.eclipse.core.internal.boot.InternalBootLoader.initialize(Internal\nBootLoader.java:583)\n        at org.eclipse.core.internal.boot.InternalBootLoader.startup(InternalBoo\ntLoader.java:973)\n        at org.eclipse.core.internal.boot.InternalBootLoader.run(InternalBootLoa\nder.java:866)\n        at org.eclipse.core.boot.BootLoader.run(BootLoader.java:321)\n        at java.lang.reflect.Method.invoke(Native Method)\n        at org.eclipse.core.launcher.Main.basicRun(Main.java:151)\n        at org.eclipse.core.launcher.Main.run(Main.java:502)\n        at org.eclipse.core.launcher.UIMain.main(UIMain.java:52)",
    "\n\n*** This bug has been marked as a duplicate of 8620 ***"
  ],
  "commentCreationDates": [
    "2002-01-25T18:25:09+01:00",
    "2002-01-28T20:58:53+01:00"
  ],
  "traces": [
    {
      "exceptionType": "java.lang.reflect.InvocationTargetException",
      "message": "java.lang.UnsupportedOperationExcep tion",
      "elements": [
        {
          "method": "java.util.AbstractList.remove",
          "source": "AbstractList.java:176"
        },
        {
          "method": "java.util.AbstractList$Itr.remove",
          "source": "AbstractList.java:439"
        },
        {
          "method": "java.util.AbstractCollection.remove",
          "source": "AbstractCollection.java:261"
        },
        {
          "method": "org.eclipse.core.internal.boot.PlatformConfiguration$SiteEntry.getPlugins",
          "source": "PlatformConfiguration.java:184"
        },
        {
          "method": "org.eclipse.core.internal.boot.PlatformConfiguration$SiteEntry.computePluginsChangeStamp",
          "source": "PlatformConfiguration.java:343"
        },
        {
          "method": "org.eclipse.core.internal.boot.PlatformConfiguration$SiteEntry.getPluginsChangeStamp",
          "source": "PlatformConfiguration.java:216"
        },
        {
          "method": "org.eclipse.core.internal.boot.PlatformConfiguration.computePluginsChangeStamp",
          "source": "PlatformConfiguration.java:827"
        },
        {
          "method": "org.eclipse.core.internal.boot.PlatformConfiguration.computeChangeStamp",
          "source": "PlatformConfiguration.java:802"
        },
        {
          "method": "org.eclipse.core.internal.boot.PlatformConfiguration.\u003cinit\u003e",
          "source": "PlatformC onfiguration.java:476"
        },
        {
          "method": "org.eclipse.core.internal.boot.PlatformConfiguration.startup",
          "source": "Platform Conf Exception launching the Eclipse Platform UI:  iguration.java:685"
        },
        {
          "method": "org.eclipse.core.internal.boot.InternalBootLoader.initialize",
          "source": "Internal BootLoader.java:583"
        },
        {
          "method": "org.eclipse.core.internal.boot.InternalBootLoader.startup",
          "source": "InternalBoo tLoader.java:973"
        },
        {
          "method": "org.eclipse.core.internal.boot.InternalBootLoader.run",
          "source": "InternalBootLoa der.java:866"
        },
        {
          "method": "org.eclipse.core.boot.BootLoader.run",
          "source": "BootLoader.java:321"
        },
        {
          "method": "java.lang.reflect.Method.invoke",
          "source": "Native Method"
        },
        {
          "method": "org.eclipse.core.launcher.Main.basicRun",
          "source": "Main.java:151"
        },
        {
          "method": "org.eclipse.core.launcher.Main.run",
          "source": "Main.java:502"
        },
        {
          "method": "org.eclipse.core.launcher.UIMain.main",
          "source": "UIMain.java:52"
        }
      ],
      "number": 0,
      "commentIndex": 0,
      "bugId": "8496",
      "duplicateId": "8620",
      "date": "2002-01-25T18:25:09+01:00",
      "product": "Platform",
      "component": "Update",
      "severity": "normal"
    }
  ],
  "groupId": "8620",
  "bugId": "8496",
  "duplicateId": "8620",
  "date": "2002-01-25T18:25:09+01:00",
  "product": "Platform",
  "component": "Update",
  "severity": "normal"
}