{
  "comments": [
    "write this:\n\n  Vector3f[][][]  normals \u003d new Vector3f[][][2];\n\nas soon as the semi-colon is written, a dialog appears saying something bad. \nwhen the dialog is closed, it reappears.  Eclipse could only be closed by asking\nthe OS to close it and then electing NOT TO SAVE the buffer containing the\nerror.  the following was found in the log:\n\n!ENTRY org.eclipse.core.runtime 4 2 Feb 13, 2005 14:08:16.388\n!MESSAGE An internal error occurred during: \"Java AST creation\".\n!STACK 0\njava.lang.NullPointerException\n        at\norg.eclipse.jdt.internal.compiler.problem.ProblemReporter.incorrectLocationForEmptyDimension(ProblemReporter.java:1573)\n        at\norg.eclipse.jdt.internal.compiler.ast.ArrayAllocationExpression.resolveType(ArrayAllocationExpression.java:132)\n        at\norg.eclipse.jdt.internal.compiler.ast.LocalDeclaration.resolve(LocalDeclaration.java:190)\n        at\norg.eclipse.jdt.internal.compiler.ast.AbstractMethodDeclaration.resolveStatements(AbstractMethodDeclaration.java:400)\n        at\norg.eclipse.jdt.internal.compiler.ast.ConstructorDeclaration.resolveStatements(ConstructorDeclaration.java:424)\n        at\norg.eclipse.jdt.internal.compiler.ast.AbstractMethodDeclaration.resolve(AbstractMethodDeclaration.java:378)\n        at\norg.eclipse.jdt.internal.compiler.ast.TypeDeclaration.resolve(TypeDeclaration.java:940)\n        at\norg.eclipse.jdt.internal.compiler.ast.TypeDeclaration.resolve(TypeDeclaration.java:989)\n        at\norg.eclipse.jdt.internal.compiler.ast.CompilationUnitDeclaration.resolve(CompilationUnitDeclaration.java:280)\n        at org.eclipse.jdt.core.dom.CompilationUnitResolver.resolve(CompilationU",
    "\n\n*** This bug has been marked as a duplicate of 80597 ***"
  ],
  "commentCreationDates": [
    "2005-02-13T14:53:09+01:00",
    "2005-02-13T16:57:32+01:00"
  ],
  "traces": [
    {
      "exceptionType": "java.lang.NullPointerException",
      "elements": [
        {
          "method": "org.eclipse.jdt.internal.compiler.problem.ProblemReporter.incorrectLocationForEmptyDimension",
          "source": "ProblemReporter.java:1573"
        },
        {
          "method": "org.eclipse.jdt.internal.compiler.ast.ArrayAllocationExpression.resolveType",
          "source": "ArrayAllocationExpression.java:132"
        },
        {
          "method": "org.eclipse.jdt.internal.compiler.ast.LocalDeclaration.resolve",
          "source": "LocalDeclaration.java:190"
        },
        {
          "method": "org.eclipse.jdt.internal.compiler.ast.AbstractMethodDeclaration.resolveStatements",
          "source": "AbstractMethodDeclaration.java:400"
        },
        {
          "method": "org.eclipse.jdt.internal.compiler.ast.ConstructorDeclaration.resolveStatements",
          "source": "ConstructorDeclaration.java:424"
        },
        {
          "method": "org.eclipse.jdt.internal.compiler.ast.AbstractMethodDeclaration.resolve",
          "source": "AbstractMethodDeclaration.java:378"
        },
        {
          "method": "org.eclipse.jdt.internal.compiler.ast.TypeDeclaration.resolve",
          "source": "TypeDeclaration.java:940"
        },
        {
          "method": "org.eclipse.jdt.internal.compiler.ast.TypeDeclaration.resolve",
          "source": "TypeDeclaration.java:989"
        },
        {
          "method": "org.eclipse.jdt.internal.compiler.ast.CompilationUnitDeclaration.resolve",
          "source": "CompilationUnitDeclaration.java:280"
        }
      ],
      "number": 0,
      "commentIndex": 0,
      "bugId": "85106",
      "duplicateId": "80597",
      "date": "2005-02-13T14:53:09+01:00",
      "product": "JDT",
      "component": "Core",
      "severity": "normal"
    }
  ],
  "groupId": "80597",
  "bugId": "85106",
  "duplicateId": "80597",
  "date": "2005-02-13T14:53:09+01:00",
  "product": "JDT",
  "component": "Core",
  "severity": "normal"
}