{
  "comments": [
    "Dear Eclipse folks,\n\nI had a previous installation of Eclipse 2.x and removed the eclipse \ninstallation dir as well as the workspace dir. After upgrading to 3.0.1 I get \nthe following error after the splash screen. Env is Solaris 9 with Gnome 2.0.\n\nRunning with \"-vm /usr/j2sdk1.4.2_04/bin/java\" (which used to run Eclipse 2.x \nperfectly well) didn\u0027t help either.\n\nexample$ eclipse -debug           \nStart VM: /usr/bin/java\n-cp /opt/eclipse/startup.jar org.eclipse.core.launcher.Main\n-os solaris\n-ws motif\n-arch sparc\n-showsplash /opt/eclipse/eclipse -showsplash 600\n-exitdata /opt/eclipse/eclipse -exitdata 2e1001\n-debug\n-vm /usr/bin/java\n-vmargs\n-cp /opt/eclipse/startup.jar org.eclipse.core.launcher.Main \nInstall location:\n    file:/opt/eclipse/\nConfiguration file:\n    file:/opt/eclipse/configuration/config.ini loaded\nConfiguration location:\n    file:/opt/eclipse/configuration/\nConfiguration file:\n    file:/opt/eclipse/configuration/config.ini loaded\nFramework located:\n    file:/opt/eclipse/plugins/org.eclipse.osgi_3.0.1/\nLoading framework classpath from:\n    file:/opt/eclipse/plugins/org.eclipse.osgi_3.0.1/eclipse.properties\nFramework classpath:\n    file:/opt/eclipse/plugins/org.eclipse.osgi_3.0.1/core.jar\n    file:/opt/eclipse/plugins/org.eclipse.osgi_3.0.1/console.jar\n    file:/opt/eclipse/plugins/org.eclipse.osgi_3.0.1/osgi.jar\n    file:/opt/eclipse/plugins/org.eclipse.osgi_3.0.1/resolver.jar\n    file:/opt/eclipse/plugins/org.eclipse.osgi_3.0.1/defaultAdaptor.jar\n    file:/opt/eclipse/plugins/org.eclipse.osgi_3.0.1/eclipseAdaptor.jar\nSplash location:\n    /opt/eclipse/plugins/org.eclipse.platform_3.0.1/splash.bmp\nDebug options:\n    file:/home/alex/.options loaded\njava.io.IOException: The FrameworkAdaptor object could not perform the operation\n        at org.eclipse.osgi.framework.internal.defaultadaptor.DefaultAdaptor.\ninitializeStorage(DefaultAdaptor.java:267)\n        at org.eclipse.osgi.framework.internal.core.Framework.\ninitialize(Framework.java:115)\n        at org.eclipse.osgi.framework.internal.core.Framework.\u003cinit\u003e(Framework.\njava:95)\n        at org.eclipse.osgi.framework.internal.core.OSGi.createFramework(OSGi.\njava:90)\n        at org.eclipse.osgi.framework.internal.core.OSGi.\u003cinit\u003e(OSGi.java:31)\n        at org.eclipse.core.runtime.adaptor.EclipseStarter.\nstartup(EclipseStarter.java:215)\n        at org.eclipse.core.runtime.adaptor.EclipseStarter.run(EclipseStarter.\njava:127)\n        at sun.reflect.NativeMethodAccessorImpl.invoke0(Native Method)\n        at sun.reflect.NativeMethodAccessorImpl.invoke(Unknown Source)\n        at sun.reflect.DelegatingMethodAccessorImpl.invoke(Unknown Source)\n        at java.lang.reflect.Method.invoke(Unknown Source)\n        at org.eclipse.core.launcher.Main.basicRun(Main.java:185)\n        at org.eclipse.core.launcher.Main.run(Main.java:704)\n        at org.eclipse.core.launcher.Main.main(Main.java:688)\n!SESSION Feb 16, 2005 00:53:49.903 ---------------------------------------------\neclipse.buildId\u003dM200409161125\njava.version\u003d1.5.0_01\njava.vendor\u003dSun Microsystems Inc.\nBootLoader constants: OS\u003dsolaris, ARCH\u003dsparc, WS\u003dmotif, NL\u003den\n\n!ENTRY org.eclipse.osgi Feb 16, 2005 00:53:49.923\n!MESSAGE Startup error\n!STACK 1\njava.lang.RuntimeException: The FrameworkAdaptor object could not perform the \noperation\n        at org.eclipse.osgi.framework.internal.core.Framework.\ninitialize(Framework.java:119)\n        at org.eclipse.osgi.framework.internal.core.Framework.\u003cinit\u003e(Framework.\njava:95)\n        at org.eclipse.osgi.framework.internal.core.OSGi.createFramework(OSGi.\njava:90)\n        at org.eclipse.osgi.framework.internal.core.OSGi.\u003cinit\u003e(OSGi.java:31)\n        at org.eclipse.core.runtime.adaptor.EclipseStarter.\nstartup(EclipseStarter.java:215)\n        at org.eclipse.core.runtime.adaptor.EclipseStarter.run(EclipseStarter.\njava:127)\n        at sun.reflect.NativeMethodAccessorImpl.invoke0(Native Method)\n        at sun.reflect.NativeMethodAccessorImpl.invoke(Unknown Source)\n        at sun.reflect.DelegatingMethodAccessorImpl.invoke(Unknown Source)\n        at java.lang.reflect.Method.invoke(Unknown Source)\n        at org.eclipse.core.launcher.Main.basicRun(Main.java:185)\n        at org.eclipse.core.launcher.Main.run(Main.java:704)\n        at org.eclipse.core.launcher.Main.main(Main.java:688)",
    "Um, turns out to be a permissions issue...\n\nThe directory \u003ceclipse-dir\u003e/configuration and its contents must be writable by \nthe user(s) running eclipse.\n",
    "Should be RESOLVED/INVALID.",
    "Closing."
  ],
  "commentCreationDates": [
    "2005-02-16T00:02:34+01:00",
    "2005-02-16T00:20:26+01:00",
    "2005-02-16T14:54:24+01:00",
    "2005-02-16T14:55:19+01:00"
  ],
  "traces": [
    {
      "exceptionType": "java.io.IOException",
      "message": "The FrameworkAdaptor object could not perform the operation",
      "elements": [
        {
          "method": "org.eclipse.osgi.framework.internal.defaultadaptor.DefaultAdaptor.initializeStorage",
          "source": "DefaultAdaptor.java:267"
        },
        {
          "method": "org.eclipse.osgi.framework.internal.core.Framework.initialize",
          "source": "Framework.java:115"
        },
        {
          "method": "org.eclipse.osgi.framework.internal.core.Framework.\u003cinit\u003e",
          "source": "Framework. java:95"
        },
        {
          "method": "org.eclipse.osgi.framework.internal.core.OSGi.createFramework",
          "source": "OSGi. java:90"
        },
        {
          "method": "org.eclipse.osgi.framework.internal.core.OSGi.\u003cinit\u003e",
          "source": "OSGi.java:31"
        },
        {
          "method": "org.eclipse.core.runtime.adaptor.EclipseStarter.startup",
          "source": "EclipseStarter.java:215"
        },
        {
          "method": "org.eclipse.core.runtime.adaptor.EclipseStarter.run",
          "source": "EclipseStarter. java:127"
        },
        {
          "method": "sun.reflect.NativeMethodAccessorImpl.invoke0",
          "source": "Native Method"
        },
        {
          "method": "sun.reflect.NativeMethodAccessorImpl.invoke",
          "source": "Unknown Source"
        },
        {
          "method": "sun.reflect.DelegatingMethodAccessorImpl.invoke",
          "source": "Unknown Source"
        },
        {
          "method": "java.lang.reflect.Method.invoke",
          "source": "Unknown Source"
        },
        {
          "method": "org.eclipse.core.launcher.Main.basicRun",
          "source": "Main.java:185"
        },
        {
          "method": "org.eclipse.core.launcher.Main.run",
          "source": "Main.java:704"
        },
        {
          "method": "org.eclipse.core.launcher.Main.main",
          "source": "Main.java:688"
        }
      ],
      "number": 0,
      "commentIndex": 0,
      "bugId": "85354",
      "date": "2005-02-16T00:02:34+01:00",
      "product": "Platform",
      "component": "Runtime",
      "severity": "normal"
    },
    {
      "exceptionType": "java.lang.RuntimeException",
      "message": "The FrameworkAdaptor object could not perform the  operation",
      "elements": [
        {
          "method": "org.eclipse.osgi.framework.internal.core.Framework.initialize",
          "source": "Framework.java:119"
        },
        {
          "method": "org.eclipse.osgi.framework.internal.core.Framework.\u003cinit\u003e",
          "source": "Framework. java:95"
        },
        {
          "method": "org.eclipse.osgi.framework.internal.core.OSGi.createFramework",
          "source": "OSGi. java:90"
        },
        {
          "method": "org.eclipse.osgi.framework.internal.core.OSGi.\u003cinit\u003e",
          "source": "OSGi.java:31"
        },
        {
          "method": "org.eclipse.core.runtime.adaptor.EclipseStarter.startup",
          "source": "EclipseStarter.java:215"
        },
        {
          "method": "org.eclipse.core.runtime.adaptor.EclipseStarter.run",
          "source": "EclipseStarter. java:127"
        },
        {
          "method": "sun.reflect.NativeMethodAccessorImpl.invoke0",
          "source": "Native Method"
        },
        {
          "method": "sun.reflect.NativeMethodAccessorImpl.invoke",
          "source": "Unknown Source"
        },
        {
          "method": "sun.reflect.DelegatingMethodAccessorImpl.invoke",
          "source": "Unknown Source"
        },
        {
          "method": "java.lang.reflect.Method.invoke",
          "source": "Unknown Source"
        },
        {
          "method": "org.eclipse.core.launcher.Main.basicRun",
          "source": "Main.java:185"
        },
        {
          "method": "org.eclipse.core.launcher.Main.run",
          "source": "Main.java:704"
        },
        {
          "method": "org.eclipse.core.launcher.Main.main",
          "source": "Main.java:688"
        }
      ],
      "number": 1,
      "commentIndex": 0,
      "bugId": "85354",
      "date": "2005-02-16T00:02:34+01:00",
      "product": "Platform",
      "component": "Runtime",
      "severity": "normal"
    }
  ],
  "groupId": "85354",
  "bugId": "85354",
  "date": "2005-02-16T00:02:34+01:00",
  "product": "Platform",
  "component": "Runtime",
  "severity": "normal"
}