{
  "comments": [
    "AK (6/5/01 7:07:04 PM)\n\tnote: i use internet explorer 2.0\n\n\t1. open the getting started page\n\t2. hit the Workbench User Guide link\n\t3. note: no busy cursor ! \u003c\u003cBUG 1\n\t4. an error message show up saying that i don\u0027t have a correct version of ie installed.\n\t\tbut it does not tell me which version _is_ correct. \u003c\u003c BUG 2\n\t5. i get the following walkback in the console \u003c\u003c BUG 3\n\n\t\t\nCheck to see if the correct version of Internet Explorer is installed on your sy\nstem.\norg.eclipse.swt.SWTException: Class ID not found in registry result \u003d -214722100\n5\n        at org.eclipse.swt.ole.win32.OLE.error(OLE.java:304)\n        at org.eclipse.swt.ole.win32.OleClientSite.getClassID(OleClientSite.java\n:631)\n        at org.eclipse.swt.ole.win32.OleControlSite.\u003cinit\u003e(OleControlSite.java:8\n0)\n        at org.eclipse.help.internal.ui.win32.HelpControlSite.\u003cinit\u003e(HelpControl\nSite.java:28)\n        at org.eclipse.help.internal.ui.win32.WebBrowser.\u003cinit\u003e(WebBrowser.java:\n102)\n        at org.eclipse.help.internal.ui.win32.BrowserFactory.createBrowser(Brows\nerFactory.java:27)\n        at org.eclipse.help.internal.ui.HTMLHelpViewer.createControl(HTMLHelpVie\nwer.java:56)\n        at org.eclipse.help.internal.ui.HTMLHelpViewer.\u003cinit\u003e(HTMLHelpViewer.jav\na:35)\n        at org.eclipse.help.internal.ui.EmbeddedHelpView.createPartControl(Embed\ndedHelpView.java:107)\n        at org.eclipse.ui.internal.PartPane$2.run(PartPane.java:54)\n        at org.eclipse.core.internal.runtime.InternalPlatform.run(InternalPlatfo\nrm.java(Compiled Code))\n        at org.eclipse.core.runtime.Platform.run(Platform.java(Compiled Code))\n        at org.eclipse.ui.internal.PartPane.createChildControl(PartPane.java:52)\n\n        at org.eclipse.ui.internal.PartPane.createControl(PartPane.java:96)\n        at org.eclipse.ui.internal.ViewPane.createControl(ViewPane.java:108)\n        at org.eclipse.ui.internal.PartSashContainer.createControl(PartSashConta\niner.java:163)\n        at org.eclipse.ui.internal.PerspectivePresentation.activate(PerspectiveP\nresentation.java:78)\n        at org.eclipse.ui.internal.Perspective.onActivate(Perspective.java:499)\n        at org.eclipse.ui.internal.WorkbenchPage.onActivate(WorkbenchPage.java:8\n27)\n        at org.eclipse.ui.internal.WorkbenchWindow$5.run(WorkbenchWindow.java:87\n2)\n        at org.eclipse.swt.custom.BusyIndicator.showWhile(BusyIndicator.java(Com\npiled Code))\n        at org.eclipse.ui.internal.WorkbenchWindow.setActivePage(WorkbenchWindow\n.java:860)\n        at org.eclipse.ui.internal.WorkbenchWindow.busyOpenPage(WorkbenchWindow.\njava:281)\n        at org.eclipse.ui.internal.WorkbenchWindow.access$6(WorkbenchWindow.java\n:269)\n        at org.eclipse.ui.internal.WorkbenchWindow$4.run(WorkbenchWindow.java:64\n1)\n        at org.eclipse.swt.custom.BusyIndicator.showWhile(BusyIndicator.java(Com\npiled Code))\n        at org.eclipse.ui.internal.WorkbenchWindow.openPage(WorkbenchWindow.java\n:638)\n        at org.eclipse.help.internal.ui.DefaultHelp.getHelpViewInHelpPerspective\n(DefaultHelp.java:223)\n        at org.eclipse.help.internal.ui.DefaultHelp.getHelpViewInCurrentPerpecti\nve(DefaultHelp.java:167)\n        at org.eclipse.help.internal.ui.DefaultHelp.displayHelp(DefaultHelp.java\n:132)\n        at org.eclipse.ui.internal.dialogs.WelcomeItem.openHelpTopic(WelcomeItem\n.java:91)\n        at org.eclipse.ui.internal.dialogs.WelcomeItem.access$0(WelcomeItem.java\n:88)\n        at org.eclipse.ui.internal.dialogs.WelcomeItem$1.run(WelcomeItem.java:13\n1)\n        at org.eclipse.swt.custom.BusyIndicator.showWhile(BusyIndicator.java(Com\npiled Code))\n        at org.eclipse.ui.internal.dialogs.WelcomeItem.triggerLinkAt(WelcomeItem\n.java:129)\n        at org.eclipse.ui.internal.dialogs.WelcomeEditor$1.mouseUp(WelcomeEditor\n.java:71)\n        at org.eclipse.swt.widgets.TypedListener.handleEvent(TypedListener.java(\nCompiled Code))\n        at org.eclipse.swt.widgets.Widget.notifyListeners(Widget.java(Compiled C\node))\n        at org.eclipse.swt.widgets.Widget.notifyListeners(Widget.java(Compiled C\node))\n        at org.eclipse.swt.widgets.Display.runDeferredEvents(Display.java(Compil\ned Code))\n        at org.eclipse.swt.widgets.Display.readAndDispatch(Display.java(Compiled\n Code))\n        at org.eclipse.ui.internal.Workbench.runEventLoop(Workbench.java(Compile\nd Code))\n        at org.eclipse.ui.internal.Workbench.run(Workbench.java:620)\n        at org.eclipse.core.internal.boot.InternalBootLoader.run(InternalBootLoa\nder.java:815)\n        at org.eclipse.core.boot.BootLoader.run(BootLoader.java:285)\n        at java.lang.reflect.Method.invoke(Native Method)\n        at org.eclipse.core.launcher.Main.basicRun(Main.java:69)\n        at org.eclipse.core.launcher.Main.run(Main.java:311)\n        at org.eclipse.core.launcher.Main.main(Main.java:198)\n\nNOTES:\nEG (6/5/2001 9:18:48 AM)\n\tmoving to ITPUI\n\nKH (6/5/2001 3:25:25 PM)\n\tMoving to TOR\n\n\tMF (6/7/01 3:47:46 PM)\n\t\tOK. \n\t\tFor bug 1, I *do* get the hour glass. So can you please be more specific if you are doing some \n\t\tspecial steps?\n\n\t\tFor bug 2: I have added the IE version to the pop-up message.\n\n\t\tFor bug 3: yes, we do stack dump, but we stack dump to our own .log file, not console.\n\t\tNote that we are using the Platform\u0027s \"log\" object, and the platform by default has a global\n\t\tlog listener, that will listen to us. \n\t\tSo the only way that I can see where you will see us stack dumping to the console, it would be if\n\t\tyou have started the platform with logging directed to standard out. \n\t\tAnd even then, it is *not* us stack dumping, we would still be logging to our .log file in this \n\t\tscenario. It is the platform that is listening to us, and deciding to use standard out instead.\n\n\t\tSo the point is, can you please let us know if you had platform logging directed to standard\n\t\tout ?\n\n\n\tMF (6/7/01 4:52:12 PM)\n\t\tBug2: fixed in build \u003e 0.119",
    "PRODUCT VERSION:\n\t118\n\n",
    "It was fixed in 1.0"
  ],
  "commentCreationDates": [
    "2001-10-11T03:49:02+02:00",
    "2001-10-24T12:27:08+02:00",
    "2002-04-22T20:19:19+02:00"
  ],
  "traces": [
    {
      "exceptionType": "org.eclipse.swt.SWTException",
      "message": "Class ID not found in registry result \u003d -214722100 5",
      "elements": [
        {
          "method": "org.eclipse.swt.ole.win32.OLE.error",
          "source": "OLE.java:304"
        },
        {
          "method": "org.eclipse.swt.ole.win32.OleClientSite.getClassID",
          "source": "OleClientSite.java :631"
        },
        {
          "method": "org.eclipse.swt.ole.win32.OleControlSite.\u003cinit\u003e",
          "source": "OleControlSite.java:8 0"
        },
        {
          "method": "org.eclipse.help.internal.ui.win32.HelpControlSite.\u003cinit\u003e",
          "source": "HelpControl Site.java:28"
        },
        {
          "method": "org.eclipse.help.internal.ui.win32.WebBrowser.\u003cinit\u003e",
          "source": "WebBrowser.java: 102"
        },
        {
          "method": "org.eclipse.help.internal.ui.win32.BrowserFactory.createBrowser",
          "source": "Brows erFactory.java:27"
        },
        {
          "method": "org.eclipse.help.internal.ui.HTMLHelpViewer.createControl",
          "source": "HTMLHelpVie wer.java:56"
        },
        {
          "method": "org.eclipse.help.internal.ui.HTMLHelpViewer.\u003cinit\u003e",
          "source": "HTMLHelpViewer.jav a:35"
        },
        {
          "method": "org.eclipse.help.internal.ui.EmbeddedHelpView.createPartControl",
          "source": "Embed dedHelpView.java:107"
        },
        {
          "method": "org.eclipse.ui.internal.PartPane$2.run",
          "source": "PartPane.java:54"
        },
        {
          "method": "org.eclipse.core.internal.runtime.InternalPlatform.run",
          "source": "InternalPlatfo rm.java(Compiled Code)"
        },
        {
          "method": "org.eclipse.core.runtime.Platform.run",
          "source": "Platform.java(Compiled Code)"
        },
        {
          "method": "org.eclipse.ui.internal.PartPane.createChildControl",
          "source": "PartPane.java:52"
        },
        {
          "method": "org.eclipse.ui.internal.PartPane.createControl",
          "source": "PartPane.java:96"
        },
        {
          "method": "org.eclipse.ui.internal.ViewPane.createControl",
          "source": "ViewPane.java:108"
        },
        {
          "method": "org.eclipse.ui.internal.PartSashContainer.createControl",
          "source": "PartSashConta iner.java:163"
        },
        {
          "method": "org.eclipse.ui.internal.PerspectivePresentation.activate",
          "source": "PerspectiveP resentation.java:78"
        },
        {
          "method": "org.eclipse.ui.internal.Perspective.onActivate",
          "source": "Perspective.java:499"
        },
        {
          "method": "org.eclipse.ui.internal.WorkbenchPage.onActivate",
          "source": "WorkbenchPage.java:8 27"
        },
        {
          "method": "org.eclipse.ui.internal.WorkbenchWindow$5.run",
          "source": "WorkbenchWindow.java:87 2"
        },
        {
          "method": "org.eclipse.swt.custom.BusyIndicator.showWhile",
          "source": "BusyIndicator.java(Com piled Code)"
        },
        {
          "method": "org.eclipse.ui.internal.WorkbenchWindow.setActivePage",
          "source": "WorkbenchWindow .java:860"
        },
        {
          "method": "org.eclipse.ui.internal.WorkbenchWindow.busyOpenPage",
          "source": "WorkbenchWindow. java:281"
        },
        {
          "method": "org.eclipse.ui.internal.WorkbenchWindow.access$6",
          "source": "WorkbenchWindow.java :269"
        },
        {
          "method": "org.eclipse.ui.internal.WorkbenchWindow$4.run",
          "source": "WorkbenchWindow.java:64 1"
        },
        {
          "method": "org.eclipse.swt.custom.BusyIndicator.showWhile",
          "source": "BusyIndicator.java(Com piled Code)"
        },
        {
          "method": "org.eclipse.ui.internal.WorkbenchWindow.openPage",
          "source": "WorkbenchWindow.java :638"
        },
        {
          "method": "org.eclipse.help.internal.ui.DefaultHelp.getHelpViewInHelpPerspective",
          "source": "DefaultHelp.java:223"
        },
        {
          "method": "org.eclipse.help.internal.ui.DefaultHelp.getHelpViewInCurrentPerpective",
          "source": "DefaultHelp.java:167"
        },
        {
          "method": "org.eclipse.help.internal.ui.DefaultHelp.displayHelp",
          "source": "DefaultHelp.java :132"
        },
        {
          "method": "org.eclipse.ui.internal.dialogs.WelcomeItem.openHelpTopic",
          "source": "WelcomeItem .java:91"
        },
        {
          "method": "org.eclipse.ui.internal.dialogs.WelcomeItem.access$0",
          "source": "WelcomeItem.java :88"
        },
        {
          "method": "org.eclipse.ui.internal.dialogs.WelcomeItem$1.run",
          "source": "WelcomeItem.java:13 1"
        },
        {
          "method": "org.eclipse.swt.custom.BusyIndicator.showWhile",
          "source": "BusyIndicator.java(Com piled Code)"
        },
        {
          "method": "org.eclipse.ui.internal.dialogs.WelcomeItem.triggerLinkAt",
          "source": "WelcomeItem .java:129"
        },
        {
          "method": "org.eclipse.ui.internal.dialogs.WelcomeEditor$1.mouseUp",
          "source": "WelcomeEditor .java:71"
        },
        {
          "method": "org.eclipse.swt.widgets.TypedListener.handleEvent",
          "source": "TypedListener.java( Compiled Code)"
        },
        {
          "method": "org.eclipse.swt.widgets.Widget.notifyListeners",
          "source": "Widget.java(Compiled C ode)"
        },
        {
          "method": "org.eclipse.swt.widgets.Widget.notifyListeners",
          "source": "Widget.java(Compiled C ode)"
        },
        {
          "method": "org.eclipse.swt.widgets.Display.runDeferredEvents",
          "source": "Display.java(Compil ed Code)"
        },
        {
          "method": "org.eclipse.swt.widgets.Display.readAndDispatch",
          "source": "Display.java(Compiled  Code)"
        },
        {
          "method": "org.eclipse.ui.internal.Workbench.runEventLoop",
          "source": "Workbench.java(Compile d Code)"
        },
        {
          "method": "org.eclipse.ui.internal.Workbench.run",
          "source": "Workbench.java:620"
        },
        {
          "method": "org.eclipse.core.internal.boot.InternalBootLoader.run",
          "source": "InternalBootLoa der.java:815"
        },
        {
          "method": "org.eclipse.core.boot.BootLoader.run",
          "source": "BootLoader.java:285"
        },
        {
          "method": "java.lang.reflect.Method.invoke",
          "source": "Native Method"
        },
        {
          "method": "org.eclipse.core.launcher.Main.basicRun",
          "source": "Main.java:69"
        },
        {
          "method": "org.eclipse.core.launcher.Main.run",
          "source": "Main.java:311"
        },
        {
          "method": "org.eclipse.core.launcher.Main.main",
          "source": "Main.java:198"
        }
      ],
      "number": 0,
      "commentIndex": 0,
      "bugId": "857",
      "date": "2001-10-11T03:49:02+02:00",
      "product": "Platform",
      "component": "User Assistance",
      "severity": "normal"
    }
  ],
  "groupId": "857",
  "bugId": "857",
  "date": "2001-10-11T03:49:02+02:00",
  "product": "Platform",
  "component": "User Assistance",
  "severity": "normal"
}