{
  "comments": [
    "AspectJ produces stack traces including munged member names that confuse JDT\nwhen clicking in the console to navigate to the appropriate line (it attempts to\ninterpret the class name).  Perhaps the parser could be corrected, or a hint\ntaken from the file/line number at the end of the trace line.  For example, in\nthe following, JDT attempts to find the class \"util.OneAsMany.ajc\" when parsing \n\"util.OneAsMany.ajc$around$util_OneAsMany$1$b32733c6(OneAsMany.java:101)\"\n\ncreating testContext\nException in thread \"main\" java.lang.Error: testContext not closed\n\tat\naunit.samples.ManageTestContext.ajc$around$aunit_samples_ManageTestContext$2$ae3f2067(Run.java:110)\n\tat util.OneAsMany.ajc$around$util_OneAsMany$1$b32733c6(OneAsMany.java:101)\n\tat aunit.samples.Runner.run(Run.java:1)\n\tat aunit.samples.Run.main(Run.java:26)",
    "Deferred"
  ],
  "commentCreationDates": [
    "2005-02-18T07:40:11+01:00",
    "2005-04-04T20:53:28+02:00"
  ],
  "traces": [
    {
      "exceptionType": "java.lang.Error",
      "message": "testContext not closed",
      "elements": [
        {
          "method": "aunit.samples.ManageTestContext.ajc$around$aunit_samples_ManageTestContext$2$ae3f2067",
          "source": "Run.java:110"
        },
        {
          "method": "util.OneAsMany.ajc$around$util_OneAsMany$1$b32733c6",
          "source": "OneAsMany.java:101"
        },
        {
          "method": "aunit.samples.Runner.run",
          "source": "Run.java:1"
        },
        {
          "method": "aunit.samples.Run.main",
          "source": "Run.java:26"
        }
      ],
      "number": 0,
      "commentIndex": 0,
      "bugId": "85795",
      "date": "2005-02-18T07:40:11+01:00",
      "product": "JDT",
      "component": "Debug",
      "severity": "normal"
    }
  ],
  "groupId": "85795",
  "bugId": "85795",
  "date": "2005-02-18T07:40:11+01:00",
  "product": "JDT",
  "component": "Debug",
  "severity": "normal"
}