{
  "comments": [
    "Build 20020125\n\nI installed a new VM on the \"Installed JREs\" preference page.  I then checked it \noff as the default and clicked ok.  I got an internal error dialog (stack \nattached).  I was installing IBM JRE 1.3.0 sr10a.  I have not been able to \nreproduce it.  I realize the runnable being exec\u0027ed doesn\u0027t necessarily \noriginate from JDT debug, but that\u0027s the only lead I have to go on so far.  The \ntop of the stack is:\n\norg.eclipse.swt.SWTException: Failed to execute runnable \n(java.lang.NullPointerException)\n\tat org.eclipse.swt.SWT.error(SWT.java:1887)\n\tat \norg.eclipse.swt.widgets.Synchronizer.runAsyncMessages(Synchronizer.java:96)\n\tat org.eclipse.swt.widgets.Display.runAsyncMessages(Display.java:1390)\n\tat org.eclipse.swt.widgets.Display.readAndDispatch(Display.java(Compiled \nCode))\n\tat \norg.eclipse.jface.operation.ModalContext$ModalContextThread.block(ModalContext.j\nava:133)\n\tat org.eclipse.jface.operation.ModalContext.run(ModalContext.java:258)\n\tat \norg.eclipse.jface.dialogs.ProgressMonitorDialog.run(ProgressMonitorDialog.java:3\n35)\n\tat \norg.eclipse.jdt.internal.debug.ui.launcher.VMPreferencePage.updateDefaultVMInsta\nll(VMPreferencePage.java:400)",
    "Created an attachment (id\u003d275)\nLog file showing stack traces\n",
    "Unable to reproduce."
  ],
  "commentCreationDates": [
    "2002-01-28T16:12:21+01:00",
    "2002-01-28T16:12:42+01:00",
    "2002-02-28T17:41:18+01:00"
  ],
  "traces": [
    {
      "exceptionType": "org.eclipse.swt.SWTException",
      "message": "Failed to execute runnable  (java.lang.NullPointerException)",
      "elements": [
        {
          "method": "org.eclipse.swt.SWT.error",
          "source": "SWT.java:1887"
        },
        {
          "method": "org.eclipse.swt.widgets.Synchronizer.runAsyncMessages",
          "source": "Synchronizer.java:96"
        },
        {
          "method": "org.eclipse.swt.widgets.Display.runAsyncMessages",
          "source": "Display.java:1390"
        },
        {
          "method": "org.eclipse.swt.widgets.Display.readAndDispatch",
          "source": "Display.java(Compiled  Code)"
        },
        {
          "method": "org.eclipse.jface.operation.ModalContext$ModalContextThread.block",
          "source": "ModalContext.j ava:133"
        },
        {
          "method": "org.eclipse.jface.operation.ModalContext.run",
          "source": "ModalContext.java:258"
        },
        {
          "method": "org.eclipse.jface.dialogs.ProgressMonitorDialog.run",
          "source": "ProgressMonitorDialog.java:3 35"
        },
        {
          "method": "org.eclipse.jdt.internal.debug.ui.launcher.VMPreferencePage.updateDefaultVMInstall",
          "source": "VMPreferencePage.java:400"
        }
      ],
      "number": 0,
      "commentIndex": 0,
      "bugId": "8596",
      "date": "2002-01-28T16:12:21+01:00",
      "product": "JDT",
      "component": "Debug",
      "severity": "normal"
    }
  ],
  "groupId": "8596",
  "bugId": "8596",
  "date": "2002-01-28T16:12:21+01:00",
  "product": "JDT",
  "component": "Debug",
  "severity": "normal"
}