{
  "comments": [
    "I\u0027m on SLES 9.0 (in case that matters for URL or something).\n\nIn a JSP file if I hover over\n\n\u003cscript src\u003d\"test.jsp\"\u003e\n\nI\u0027m getting this:\n\n!ENTRY org.eclipse.ui 4 0 2005-02-22 13:38:46.708\n!MESSAGE URI is not absolute\n!STACK 0\njava.lang.IllegalArgumentException: URI is not absolute\n        at java.io.File.\u003cinit\u003e(File.java:319)\n        at\norg.eclipse.jst.jsp.ui.internal.hyperlink.XMLHyperlinkDetector.isValidURI(XMLHyperlinkDetector.java:418)\n        at\norg.eclipse.jst.jsp.ui.internal.hyperlink.XMLHyperlinkDetector.detectHyperlinks(XMLHyperlinkDetector.java:79)\n        at\norg.eclipse.jface.text.hyperlink.HyperlinkManager.findHyperlinks(HyperlinkManager.java:235)\n        at\norg.eclipse.jface.text.hyperlink.HyperlinkManager.mouseMove(HyperlinkManager.java:422)\n        at org.eclipse.swt.widgets.TypedListener.handleEvent(TypedListener.java:144)\n        at org.eclipse.swt.widgets.EventTable.sendEvent(EventTable.java:82)\n        at org.eclipse.swt.widgets.Widget.sendEvent(Widget.java:1009)\n        at org.eclipse.swt.widgets.Display.runDeferredEvents(Display.java:2728)\n        at org.eclipse.swt.widgets.Display.readAndDispatch(Display.java:2427)\n        at org.eclipse.ui.internal.Workbench.runEventLoop(Workbench.java:1612)\n        at org.eclipse.ui.internal.Workbench.runUI(Workbench.java:1578)\n        at\norg.eclipse.ui.internal.Workbench.createAndRunWorkbench(Workbench.java:293)\n        at org.eclipse.ui.PlatformUI.createAndRunWorkbench(PlatformUI.java:144)\n        at org.eclipse.ui.internal.ide.IDEApplication.run(IDEApplication.java:102)\n        at\norg.eclipse.core.internal.runtime.PlatformActivator$1.run(PlatformActivator.java:228)\n        at\norg.eclipse.core.runtime.adaptor.EclipseStarter.run(EclipseStarter.java:333)\n        at\norg.eclipse.core.runtime.adaptor.EclipseStarter.run(EclipseStarter.java:150)\n        at sun.reflect.NativeMethodAccessorImpl.invoke0(Native Method)\n        at\nsun.reflect.NativeMethodAccessorImpl.invoke(NativeMethodAccessorImpl.java:39)\n        at\nsun.reflect.DelegatingMethodAccessorImpl.invoke(DelegatingMethodAccessorImpl.java:25)\n        at java.lang.reflect.Method.invoke(Method.java:324)\n        at org.eclipse.core.launcher.Main.invokeFramework(Main.java:268)\n        at org.eclipse.core.launcher.Main.basicRun(Main.java:260)\n        at org.eclipse.core.launcher.Main.run(Main.java:887)\n        at org.eclipse.core.launcher.Main.main(Main.java:871)\nURI is not absolute",
    "in isValidURI, instead of checking for \nif (uri.isAbsolute())\n  file \u003d new File(uri);\n\nit was checking\nif (!uri.isAbsolute())\n  file \u003d new File(uri);\n",
    "Created an attachment (id\u003d18319)\norg.eclipse.wst.xml.ui.patch\n",
    "Created an attachment (id\u003d18320)\norg.eclipse.wst.html.ui.patch\n",
    "Created an attachment (id\u003d18321)\norg.eclipse.wst.html.ui.patch\n",
    "Created an attachment (id\u003d18322)\norg.eclipse.jst.jsp.ui.patch\n",
    "Thanks Amy, I\u0027ve committed to head and will release for next I-build. ",
    "verified, closing.",
    "I thought I closed this awhile back but apparently not."
  ],
  "commentCreationDates": [
    "2005-02-22T22:14:48+01:00",
    "2005-02-25T16:59:06+01:00",
    "2005-02-25T19:35:46+01:00",
    "2005-02-25T19:42:25+01:00",
    "2005-02-25T19:42:36+01:00",
    "2005-02-25T19:44:03+01:00",
    "2005-03-10T04:36:48+01:00",
    "2005-06-21T15:24:09+02:00",
    "2005-07-08T16:48:13+02:00"
  ],
  "traces": [
    {
      "exceptionType": "java.lang.IllegalArgumentException",
      "message": "URI is not absolute",
      "elements": [
        {
          "method": "java.io.File.\u003cinit\u003e",
          "source": "File.java:319"
        },
        {
          "method": "org.eclipse.jst.jsp.ui.internal.hyperlink.XMLHyperlinkDetector.isValidURI",
          "source": "XMLHyperlinkDetector.java:418"
        },
        {
          "method": "org.eclipse.jst.jsp.ui.internal.hyperlink.XMLHyperlinkDetector.detectHyperlinks",
          "source": "XMLHyperlinkDetector.java:79"
        },
        {
          "method": "org.eclipse.jface.text.hyperlink.HyperlinkManager.findHyperlinks",
          "source": "HyperlinkManager.java:235"
        },
        {
          "method": "org.eclipse.jface.text.hyperlink.HyperlinkManager.mouseMove",
          "source": "HyperlinkManager.java:422"
        },
        {
          "method": "org.eclipse.swt.widgets.TypedListener.handleEvent",
          "source": "TypedListener.java:144"
        },
        {
          "method": "org.eclipse.swt.widgets.EventTable.sendEvent",
          "source": "EventTable.java:82"
        },
        {
          "method": "org.eclipse.swt.widgets.Widget.sendEvent",
          "source": "Widget.java:1009"
        },
        {
          "method": "org.eclipse.swt.widgets.Display.runDeferredEvents",
          "source": "Display.java:2728"
        },
        {
          "method": "org.eclipse.swt.widgets.Display.readAndDispatch",
          "source": "Display.java:2427"
        },
        {
          "method": "org.eclipse.ui.internal.Workbench.runEventLoop",
          "source": "Workbench.java:1612"
        },
        {
          "method": "org.eclipse.ui.internal.Workbench.runUI",
          "source": "Workbench.java:1578"
        },
        {
          "method": "org.eclipse.ui.internal.Workbench.createAndRunWorkbench",
          "source": "Workbench.java:293"
        },
        {
          "method": "org.eclipse.ui.PlatformUI.createAndRunWorkbench",
          "source": "PlatformUI.java:144"
        },
        {
          "method": "org.eclipse.ui.internal.ide.IDEApplication.run",
          "source": "IDEApplication.java:102"
        },
        {
          "method": "org.eclipse.core.internal.runtime.PlatformActivator$1.run",
          "source": "PlatformActivator.java:228"
        },
        {
          "method": "org.eclipse.core.runtime.adaptor.EclipseStarter.run",
          "source": "EclipseStarter.java:333"
        },
        {
          "method": "org.eclipse.core.runtime.adaptor.EclipseStarter.run",
          "source": "EclipseStarter.java:150"
        },
        {
          "method": "sun.reflect.NativeMethodAccessorImpl.invoke0",
          "source": "Native Method"
        },
        {
          "method": "sun.reflect.NativeMethodAccessorImpl.invoke",
          "source": "NativeMethodAccessorImpl.java:39"
        },
        {
          "method": "sun.reflect.DelegatingMethodAccessorImpl.invoke",
          "source": "DelegatingMethodAccessorImpl.java:25"
        },
        {
          "method": "java.lang.reflect.Method.invoke",
          "source": "Method.java:324"
        },
        {
          "method": "org.eclipse.core.launcher.Main.invokeFramework",
          "source": "Main.java:268"
        },
        {
          "method": "org.eclipse.core.launcher.Main.basicRun",
          "source": "Main.java:260"
        },
        {
          "method": "org.eclipse.core.launcher.Main.run",
          "source": "Main.java:887"
        },
        {
          "method": "org.eclipse.core.launcher.Main.main",
          "source": "Main.java:871"
        }
      ],
      "number": 0,
      "commentIndex": 0,
      "bugId": "86209",
      "date": "2005-02-22T22:14:48+01:00",
      "product": "Web Tools",
      "component": "jst.jsp",
      "severity": "normal"
    }
  ],
  "groupId": "86209",
  "bugId": "86209",
  "date": "2005-02-22T22:14:48+01:00",
  "product": "Web Tools",
  "component": "jst.jsp",
  "severity": "normal"
}