{
  "comments": [
    "When i click to  expand the tree in  ANT View to get:\n- a long time wait  \u003e 1 minute (My system si 1G dual G5) \n- the log file report the follow null pointer exception during the operation:\n\n\n!SESSION Feb 24, 2005 10:55:21.288 ---------------------------------------------\neclipse.buildId\u003dM200409161125\njava.version\u003d1.4.2_05\njava.vendor\u003dApple Computer, Inc.\nBootLoader constants: OS\u003dmacosx, ARCH\u003dppc, WS\u003dcarbon, NL\u003den_US\nCommand-line arguments: -keyring /Users/pch/.eclipse_keyring -showlocation\n\n!ENTRY org.eclipse.jdt.launching 4 4 Feb 24, 2005 10:55:21.588\n!MESSAGE Failed to retrieve default libraries for /System/Library/Frameworks/JavaVM.framework/\nVersions/1.4.2/Home\n\n!ENTRY org.eclipse.debug.core 4 120 Feb 24, 2005 10:56:35.395\n!MESSAGE Error logged from Debug Core: \n!STACK 0\njava.lang.NullPointerException\n        at java.io.BufferedInputStream.read(BufferedInputStream.java:279)\n        at java.io.FilterInputStream.read(FilterInputStream.java:90)\n        at org.eclipse.debug.internal.core.OutputStreamMonitor.read(OutputStreamMonitor.java:132)\n        at org.eclipse.debug.internal.core.OutputStreamMonitor.access$1(OutputStreamMonitor.java:124)\n        at org.eclipse.debug.internal.core.OutputStreamMonitor$1.run(OutputStreamMonitor.java:177)\n        at java.lang.Thread.run(Thread.java:552)",
    "sorry for this fake bug.. was my ENV with some wrong path... "
  ],
  "commentCreationDates": [
    "2005-02-24T10:09:02+01:00",
    "2005-02-24T10:26:08+01:00"
  ],
  "traces": [
    {
      "exceptionType": "java.lang.NullPointerException",
      "elements": [
        {
          "method": "java.io.BufferedInputStream.read",
          "source": "BufferedInputStream.java:279"
        },
        {
          "method": "java.io.FilterInputStream.read",
          "source": "FilterInputStream.java:90"
        },
        {
          "method": "org.eclipse.debug.internal.core.OutputStreamMonitor.read",
          "source": "OutputStreamMonitor.java:132"
        },
        {
          "method": "org.eclipse.debug.internal.core.OutputStreamMonitor.access$1",
          "source": "OutputStreamMonitor.java:124"
        },
        {
          "method": "org.eclipse.debug.internal.core.OutputStreamMonitor$1.run",
          "source": "OutputStreamMonitor.java:177"
        },
        {
          "method": "java.lang.Thread.run",
          "source": "Thread.java:552"
        }
      ],
      "number": 0,
      "commentIndex": 0,
      "bugId": "86448",
      "date": "2005-02-24T10:09:02+01:00",
      "product": "JDT",
      "component": "Debug",
      "severity": "normal"
    }
  ],
  "groupId": "86448",
  "bugId": "86448",
  "date": "2005-02-24T10:09:02+01:00",
  "product": "JDT",
  "component": "Debug",
  "severity": "normal"
}