{
  "comments": [
    "Hi, I just installed Eclipse 3.1M5a with no 3rd party plug-ins on an AMD64\nrunning 64-bit with IBM\u0027s JDK 1.4.2 and Gtk+ 2.6.2.\n\nI opened a workspace I last used with version 3.0.1 of Eclipse and found out\nthat the key bindings had changed. I realized that the mapping had switched back\nfrom Emacs to Default, so I selected Emacs again; after this, some keys started\nbehaving as expected (e.g., keyboard navigation keys as Ctrl+N, Ctrl+P, etc) but\nothers didn\u0027t.\n\nHere, I reset all key combinations with \"Restore Defaults.\" So I had to manually\nrestore my old configuration. I tried to assign Ctrl+/ to Edit/Undo, but upon\nreopening the key binding editor the key combination shows up as unassigned (it\nused to be bound to Toggle Comment). If I press it in the Java editor it still\ntoggles the comment instead of performing what I chose to, and of course this is\ndoubly incorrect as it\u0027s not bound to the Toggle Comment function anymore.\n\nSame thing happened with Ctrl+Y (paste) and Ctrl+W (Emacs: cut, current\nbehavior: apparently close current editor, even though it\u0027s not showed a such).\n\nAnything else of interest I can provide? Eclipse is not outputing anything to\nthe standard output or error.",
    "There are two separate bugs here.\n\nI cannot reproduce the switching back to Default.  Do you have any additional\nplug-ins installed?\n\nThe \"Ctrl+/\" problem should be fixed in I20050301-1230.  Could you try to\nreproduce with that integration build, and let me know?",
    "Hi Douglas,\n\nI tried to run that integration build (I got it from\nhttp://download.eclipse.org/eclipse/downloads/drops/I-Daniela_2-200503011230/index.php)\nbut I cannot get it to run. It points me to a log file at:\n/opt/eclipse-3.1-I20050301-1230/configuration/1109784415922.log. Which contains\nthe following error message:\n!SESSION 2005-03-02 12:26:58.456 ----------------------------------------------\\-\neclipse.buildId\u003dI20050301-1230\njava.fullversion\u003dJ2RE 1.4.2 IBM J9 2.2 Linux amd64-64 j9xa641420-20040916a (JIT\\\nenabled)\nJ9VM - 20040916_0916_LHdSMr\nJIT  - r7_level20040915_1801\nBootLoader constants: OS\u003dlinux, ARCH\u003dx86_64, WS\u003dgtk, NL\u003des_AR\nCommand-line arguments:  -os linux -ws gtk -arch x86_64 -debug\nfile:/home/jkohe\\n/.eclipse.options\n\n!ENTRY org.eclipse.osgi 2005-03-02 12:26:58.457\n!MESSAGE Application error\n!STACK 1\njava.lang.NoSuchMethodError: org/eclipse/swt/widgets/Display.setDirectionProc(J\\J)J\n        at org.eclipse.swt.internal.Callback.bind(Native Method)\n        at org.eclipse.swt.internal.Callback.\u003cinit\u003e(Callback.java:123)\n        at org.eclipse.swt.internal.Callback.\u003cinit\u003e(Callback.java:78)\n        at org.eclipse.swt.internal.Callback.\u003cinit\u003e(Callback.java:60)\n        at org.eclipse.swt.widgets.Display.initializeCallbacks(Display.java:195\\2)\n        at org.eclipse.swt.widgets.Display.init(Display.java:1894)\n        at org.eclipse.swt.graphics.Device.\u003cinit\u003e(Device.java:124)\n        at org.eclipse.swt.widgets.Display.\u003cinit\u003e(Display.java:419)\n        at org.eclipse.swt.widgets.Display.\u003cinit\u003e(Display.java:415)\n        at org.eclipse.ui.internal.Workbench.createDisplay(Workbench.java:313)\n        at org.eclipse.ui.PlatformUI.createDisplay(PlatformUI.java:155)\n        at\norg.eclipse.ui.internal.ide.IDEApplication.createDisplay(IDEApplicat\\ion.java:127)\n        at org.eclipse.ui.internal.ide.IDEApplication.run(IDEApplication.java:7\\8)\n        at\norg.eclipse.core.internal.runtime.PlatformActivator$1.run(PlatformAc\\tivator.java:228)\n        at\norg.eclipse.core.runtime.adaptor.EclipseStarter.run(EclipseStarter.j\\ava:338)\n        at\norg.eclipse.core.runtime.adaptor.EclipseStarter.run(EclipseStarter.j\\ava:151)\n        at sun.reflect.NativeMethodAccessorImpl.invoke0(Native Method)\n        at\nsun.reflect.NativeMethodAccessorImpl.invoke(NativeMethodAccessorImpl\\.java:85)\n        at\nsun.reflect.NativeMethodAccessorImpl.invoke(NativeMethodAccessorImpl\\.java:58)\n        at\nsun.reflect.DelegatingMethodAccessorImpl.invoke(DelegatingMethodAcce\\ssorImpl.java:60)\n        at java.lang.reflect.Method.invoke(Method.java:391)\n        at org.eclipse.core.launcher.Main.invokeFramework(Main.java:268)\n        at org.eclipse.core.launcher.Main.basicRun(Main.java:260)\n        at org.eclipse.core.launcher.Main.run(Main.java:887)\n        at org.eclipse.core.launcher.Main.main(Main.java:871)\n\nWhat should I do now?\n\nBack to your question, I don\u0027t have any plug-ins installed, I just uncompressed\nthe Eclipse 3.1M5a tarball and used it to run a 3.0.1 workspace. The workspace\nreferenced a few non-essential plug-ins (SYSDEO\u0027s Tomcat, sqlexplorer and\nfindbugs). I\u0027ll try to reproduce it along with the other bug as soon as I\u0027m able\nto run one of the integration builds.",
    "I\u0027ve filed this other bug as Bug 87010.  Until we resolve that, I guess we can\u0027t\ndo much more about this bug.",
    "Can you please try again with next week\u0027s integration build, and let me know? \nI20040308-0800 or later....",
    "Thanks Douglas, I\u0027ll make it a point to test that build.",
    "It works for me now in I20050308-1510. The keybindings I had set in the 3.0\nworkspace were all recognized (including the Emacs global setting) and adding a\nnew key binding for the \"Go To Line\" action resulted in a working key binding.\n\nThanks!",
    "I\u0027m not sure when this was fixed -- removing the milestone."
  ],
  "commentCreationDates": [
    "2005-03-01T18:10:23+01:00",
    "2005-03-02T11:45:56+01:00",
    "2005-03-02T17:33:51+01:00",
    "2005-03-02T17:43:19+01:00",
    "2005-03-02T18:45:39+01:00",
    "2005-03-02T19:46:26+01:00",
    "2005-03-09T17:30:24+01:00",
    "2005-06-09T21:26:24+02:00"
  ],
  "traces": [
    {
      "exceptionType": "java.lang.NoSuchMethodError",
      "message": "org/eclipse/swt/widgets/Display.setDirectionProc(J\\J)J",
      "elements": [
        {
          "method": "org.eclipse.swt.internal.Callback.bind",
          "source": "Native Method"
        },
        {
          "method": "org.eclipse.swt.internal.Callback.\u003cinit\u003e",
          "source": "Callback.java:123"
        },
        {
          "method": "org.eclipse.swt.internal.Callback.\u003cinit\u003e",
          "source": "Callback.java:78"
        },
        {
          "method": "org.eclipse.swt.internal.Callback.\u003cinit\u003e",
          "source": "Callback.java:60"
        },
        {
          "method": "org.eclipse.swt.widgets.Display.initializeCallbacks",
          "source": "Display.java:195\\2"
        },
        {
          "method": "org.eclipse.swt.widgets.Display.init",
          "source": "Display.java:1894"
        },
        {
          "method": "org.eclipse.swt.graphics.Device.\u003cinit\u003e",
          "source": "Device.java:124"
        },
        {
          "method": "org.eclipse.swt.widgets.Display.\u003cinit\u003e",
          "source": "Display.java:419"
        },
        {
          "method": "org.eclipse.swt.widgets.Display.\u003cinit\u003e",
          "source": "Display.java:415"
        },
        {
          "method": "org.eclipse.ui.internal.Workbench.createDisplay",
          "source": "Workbench.java:313"
        },
        {
          "method": "org.eclipse.ui.PlatformUI.createDisplay",
          "source": "PlatformUI.java:155"
        },
        {
          "method": "org.eclipse.ui.internal.ide.IDEApplication.createDisplay",
          "source": "IDEApplicat\\ion.java:127"
        },
        {
          "method": "org.eclipse.ui.internal.ide.IDEApplication.run",
          "source": "IDEApplication.java:7\\8"
        },
        {
          "method": "org.eclipse.core.internal.runtime.PlatformActivator$1.run",
          "source": "PlatformAc\\tivator.java:228"
        },
        {
          "method": "org.eclipse.core.runtime.adaptor.EclipseStarter.run",
          "source": "EclipseStarter.j\\ava:338"
        },
        {
          "method": "org.eclipse.core.runtime.adaptor.EclipseStarter.run",
          "source": "EclipseStarter.j\\ava:151"
        },
        {
          "method": "sun.reflect.NativeMethodAccessorImpl.invoke0",
          "source": "Native Method"
        },
        {
          "method": "sun.reflect.NativeMethodAccessorImpl.invoke",
          "source": "NativeMethodAccessorImpl\\.java:85"
        },
        {
          "method": "sun.reflect.NativeMethodAccessorImpl.invoke",
          "source": "NativeMethodAccessorImpl\\.java:58"
        },
        {
          "method": "sun.reflect.DelegatingMethodAccessorImpl.invoke",
          "source": "DelegatingMethodAcce\\ssorImpl.java:60"
        },
        {
          "method": "java.lang.reflect.Method.invoke",
          "source": "Method.java:391"
        },
        {
          "method": "org.eclipse.core.launcher.Main.invokeFramework",
          "source": "Main.java:268"
        },
        {
          "method": "org.eclipse.core.launcher.Main.basicRun",
          "source": "Main.java:260"
        },
        {
          "method": "org.eclipse.core.launcher.Main.run",
          "source": "Main.java:887"
        },
        {
          "method": "org.eclipse.core.launcher.Main.main",
          "source": "Main.java:871"
        }
      ],
      "number": 0,
      "commentIndex": 2,
      "bugId": "86926",
      "date": "2005-03-02T17:33:51+01:00",
      "product": "Platform",
      "component": "UI",
      "severity": "normal"
    }
  ],
  "groupId": "86926",
  "bugId": "86926",
  "date": "2005-03-01T18:10:23+01:00",
  "product": "Platform",
  "component": "UI",
  "severity": "normal"
}