{
  "comments": [
    "When working with a user on Bug 86926, he got the following exception.  I\u0027m not\nsure if it\u0027s just a corrupt download/install or something more significant.\n\n\nI tried to run that integration build (I got it from\nhttp://download.eclipse.org/eclipse/downloads/drops/I-Daniela_2-200503011230/index.php)\nbut I cannot get it to run. It points me to a log file at:\n/opt/eclipse-3.1-I20050301-1230/configuration/1109784415922.log. Which contains\nthe following error message:\n!SESSION 2005-03-02 12:26:58.456 ----------------------------------------------\\-\neclipse.buildId\u003dI20050301-1230\njava.fullversion\u003dJ2RE 1.4.2 IBM J9 2.2 Linux amd64-64 j9xa641420-20040916a (JIT\\\nenabled)\nJ9VM - 20040916_0916_LHdSMr\nJIT  - r7_level20040915_1801\nBootLoader constants: OS\u003dlinux, ARCH\u003dx86_64, WS\u003dgtk, NL\u003des_AR\nCommand-line arguments:  -os linux -ws gtk -arch x86_64 -debug\nfile:/home/jkohe\\n/.eclipse.options\n\n!ENTRY org.eclipse.osgi 2005-03-02 12:26:58.457\n!MESSAGE Application error\n!STACK 1\njava.lang.NoSuchMethodError: org/eclipse/swt/widgets/Display.setDirectionProc(J\\J)J\n        at org.eclipse.swt.internal.Callback.bind(Native Method)\n        at org.eclipse.swt.internal.Callback.\u003cinit\u003e(Callback.java:123)\n        at org.eclipse.swt.internal.Callback.\u003cinit\u003e(Callback.java:78)\n        at org.eclipse.swt.internal.Callback.\u003cinit\u003e(Callback.java:60)\n        at org.eclipse.swt.widgets.Display.initializeCallbacks(Display.java:195\\2)\n        at org.eclipse.swt.widgets.Display.init(Display.java:1894)\n        at org.eclipse.swt.graphics.Device.\u003cinit\u003e(Device.java:124)\n        at org.eclipse.swt.widgets.Display.\u003cinit\u003e(Display.java:419)\n        at org.eclipse.swt.widgets.Display.\u003cinit\u003e(Display.java:415)\n        at org.eclipse.ui.internal.Workbench.createDisplay(Workbench.java:313)\n        at org.eclipse.ui.PlatformUI.createDisplay(PlatformUI.java:155)\n        at\norg.eclipse.ui.internal.ide.IDEApplication.createDisplay(IDEApplicat\\ion.java:127)\n        at org.eclipse.ui.internal.ide.IDEApplication.run(IDEApplication.java:7\\8)\n        at\norg.eclipse.core.internal.runtime.PlatformActivator$1.run(PlatformAc\\tivator.java:228)\n        at\norg.eclipse.core.runtime.adaptor.EclipseStarter.run(EclipseStarter.j\\ava:338)\n        at\norg.eclipse.core.runtime.adaptor.EclipseStarter.run(EclipseStarter.j\\ava:151)\n        at sun.reflect.NativeMethodAccessorImpl.invoke0(Native Method)\n        at\nsun.reflect.NativeMethodAccessorImpl.invoke(NativeMethodAccessorImpl\\.java:85)\n        at\nsun.reflect.NativeMethodAccessorImpl.invoke(NativeMethodAccessorImpl\\.java:58)\n        at\nsun.reflect.DelegatingMethodAccessorImpl.invoke(DelegatingMethodAcce\\ssorImpl.java:60)\n        at java.lang.reflect.Method.invoke(Method.java:391)\n        at org.eclipse.core.launcher.Main.invokeFramework(Main.java:268)\n        at org.eclipse.core.launcher.Main.basicRun(Main.java:260)\n        at org.eclipse.core.launcher.Main.run(Main.java:887)\n        at org.eclipse.core.launcher.Main.main(Main.java:871)",
    "Could you check two things?  One, could you try downloading the build again to\nmake sure the download wasn\u0027t corrupted.  Two, could you make sure that the\ninstall was unzipped into a new directory (i.e., not on top of an existing install).",
    "Did someone forget to use int /*long*/ widget instead of int widget?\n\nint setDirectionProc (int widget, int direction) {\n        OS.gtk_widget_set_direction (widget, direction);\n        if (OS.GTK_IS_CONTAINER (widget)) {\n                OS.gtk_container_forall (widget, setDirectionProc, direction);\n        }\n        return 0;\n}",
    "I did. ",
    "fixed in head \u003e 20050302",
    "Deja vu. I just tried I20050308-0835 to see if 86926 had been fixed and got the\nsame error than last time. I completely removed the old integration build and\nI\u0027m 100% sure that the installation is clean. There are no plug-ins installed,\njust the SDK.\n\nI cannot reopen this issue here, but I hope that when you get this message you will.\n\n!SESSION 2005-03-08 13:11:25.103\n-----------------------------------------------eclipse.buildId\u003dI20050308-0835\njava.fullversion\u003dJ2RE 1.4.2 IBM J9 2.2 Linux amd64-64 j9xa64142sr1a-20050225\n(JIT enabled)\nJ9VM - 20050224_1940_LHdSMr\nJIT  - r7_level20050120_1805\nBootLoader constants: OS\u003dlinux, ARCH\u003dx86_64, WS\u003dgtk, NL\u003des_AR\nCommand-line arguments:  -os linux -ws gtk -arch x86_64 -debug\nfile:/home/jkohen/.eclipse.options\n\n!ENTRY org.eclipse.osgi 2005-03-08 13:11:25.103\n!MESSAGE Application error\n!STACK 1\njava.lang.NoSuchMethodError: org/eclipse/swt/widgets/Display.setDirectionProc(JJ)J\n        at org.eclipse.swt.internal.Callback.bind(Native Method)\n        at org.eclipse.swt.internal.Callback.\u003cinit\u003e(Callback.java:123)\n        at org.eclipse.swt.internal.Callback.\u003cinit\u003e(Callback.java:78)\n        at org.eclipse.swt.internal.Callback.\u003cinit\u003e(Callback.java:60)\n        at org.eclipse.swt.widgets.Display.initializeCallbacks(Display.java:1989)\n        at org.eclipse.swt.widgets.Display.init(Display.java:1931)\n        at org.eclipse.swt.graphics.Device.\u003cinit\u003e(Device.java:124)\n        at org.eclipse.swt.widgets.Display.\u003cinit\u003e(Display.java:419)\n        at org.eclipse.swt.widgets.Display.\u003cinit\u003e(Display.java:415)\n        at org.eclipse.ui.internal.Workbench.createDisplay(Workbench.java:323)\n        at org.eclipse.ui.PlatformUI.createDisplay(PlatformUI.java:155)\n        at\norg.eclipse.ui.internal.ide.IDEApplication.createDisplay(IDEApplication.java:128)\n        at org.eclipse.ui.internal.ide.IDEApplication.run(IDEApplication.java:79)\n        at\norg.eclipse.core.internal.runtime.PlatformActivator$1.run(PlatformActivator.java:228)\n        at\norg.eclipse.core.runtime.adaptor.EclipseStarter.run(EclipseStarter.java:338)\n        at\norg.eclipse.core.runtime.adaptor.EclipseStarter.run(EclipseStarter.java:151)\n        at sun.reflect.NativeMethodAccessorImpl.invoke0(Native Method)\n        at\nsun.reflect.NativeMethodAccessorImpl.invoke(NativeMethodAccessorImpl.java:85)\n        at\nsun.reflect.NativeMethodAccessorImpl.invoke(NativeMethodAccessorImpl.java:58)\n        at\nsun.reflect.DelegatingMethodAccessorImpl.invoke(DelegatingMethodAccessorImpl.java:60)\n        at java.lang.reflect.Method.invoke(Method.java:391)\n        at org.eclipse.core.launcher.Main.invokeFramework(Main.java:268)\n        at org.eclipse.core.launcher.Main.basicRun(Main.java:260)\n        at org.eclipse.core.launcher.Main.run(Main.java:887)\n        at org.eclipse.core.launcher.Main.main(Main.java:871)\n",
    "Felipe, did the fix not make it into the build?",
    "The change was incomplete. Every argument in a calback must be int /*long*/, \nincluding the return value. I\u0027ve released it in HEAD.\n\nint /*long*/ setDirectionProc (int /*long*/ widget, int /*long*/ direction)",
    "When\u0027s the next integration build, so I can try to reproduce both bug #87010 and\nbug #86926?",
    "I think this integration build is being rebuilt for this fix (and others), so it\nmight be later today...",
    "Yes - a rebuild I200503081510 was requested and the fix should make its way \nthrough the final integration build. Closing for now..."
  ],
  "commentCreationDates": [
    "2005-03-02T17:41:39+01:00",
    "2005-03-02T17:42:39+01:00",
    "2005-03-02T17:50:13+01:00",
    "2005-03-02T18:20:01+01:00",
    "2005-03-02T18:40:11+01:00",
    "2005-03-08T18:15:58+01:00",
    "2005-03-08T18:43:11+01:00",
    "2005-03-08T18:44:27+01:00",
    "2005-03-08T18:49:52+01:00",
    "2005-03-08T19:40:52+01:00",
    "2005-03-08T20:20:10+01:00"
  ],
  "traces": [
    {
      "exceptionType": "java.lang.NoSuchMethodError",
      "message": "org/eclipse/swt/widgets/Display.setDirectionProc(J\\J)J",
      "elements": [
        {
          "method": "org.eclipse.swt.internal.Callback.bind",
          "source": "Native Method"
        },
        {
          "method": "org.eclipse.swt.internal.Callback.\u003cinit\u003e",
          "source": "Callback.java:123"
        },
        {
          "method": "org.eclipse.swt.internal.Callback.\u003cinit\u003e",
          "source": "Callback.java:78"
        },
        {
          "method": "org.eclipse.swt.internal.Callback.\u003cinit\u003e",
          "source": "Callback.java:60"
        },
        {
          "method": "org.eclipse.swt.widgets.Display.initializeCallbacks",
          "source": "Display.java:195\\2"
        },
        {
          "method": "org.eclipse.swt.widgets.Display.init",
          "source": "Display.java:1894"
        },
        {
          "method": "org.eclipse.swt.graphics.Device.\u003cinit\u003e",
          "source": "Device.java:124"
        },
        {
          "method": "org.eclipse.swt.widgets.Display.\u003cinit\u003e",
          "source": "Display.java:419"
        },
        {
          "method": "org.eclipse.swt.widgets.Display.\u003cinit\u003e",
          "source": "Display.java:415"
        },
        {
          "method": "org.eclipse.ui.internal.Workbench.createDisplay",
          "source": "Workbench.java:313"
        },
        {
          "method": "org.eclipse.ui.PlatformUI.createDisplay",
          "source": "PlatformUI.java:155"
        },
        {
          "method": "org.eclipse.ui.internal.ide.IDEApplication.createDisplay",
          "source": "IDEApplicat\\ion.java:127"
        },
        {
          "method": "org.eclipse.ui.internal.ide.IDEApplication.run",
          "source": "IDEApplication.java:7\\8"
        },
        {
          "method": "org.eclipse.core.internal.runtime.PlatformActivator$1.run",
          "source": "PlatformAc\\tivator.java:228"
        },
        {
          "method": "org.eclipse.core.runtime.adaptor.EclipseStarter.run",
          "source": "EclipseStarter.j\\ava:338"
        },
        {
          "method": "org.eclipse.core.runtime.adaptor.EclipseStarter.run",
          "source": "EclipseStarter.j\\ava:151"
        },
        {
          "method": "sun.reflect.NativeMethodAccessorImpl.invoke0",
          "source": "Native Method"
        },
        {
          "method": "sun.reflect.NativeMethodAccessorImpl.invoke",
          "source": "NativeMethodAccessorImpl\\.java:85"
        },
        {
          "method": "sun.reflect.NativeMethodAccessorImpl.invoke",
          "source": "NativeMethodAccessorImpl\\.java:58"
        },
        {
          "method": "sun.reflect.DelegatingMethodAccessorImpl.invoke",
          "source": "DelegatingMethodAcce\\ssorImpl.java:60"
        },
        {
          "method": "java.lang.reflect.Method.invoke",
          "source": "Method.java:391"
        },
        {
          "method": "org.eclipse.core.launcher.Main.invokeFramework",
          "source": "Main.java:268"
        },
        {
          "method": "org.eclipse.core.launcher.Main.basicRun",
          "source": "Main.java:260"
        },
        {
          "method": "org.eclipse.core.launcher.Main.run",
          "source": "Main.java:887"
        },
        {
          "method": "org.eclipse.core.launcher.Main.main",
          "source": "Main.java:871"
        }
      ],
      "number": 0,
      "commentIndex": 0,
      "bugId": "87010",
      "date": "2005-03-02T17:41:39+01:00",
      "product": "Platform",
      "component": "SWT",
      "severity": "normal"
    },
    {
      "exceptionType": "java.lang.NoSuchMethodError",
      "message": "org/eclipse/swt/widgets/Display.setDirectionProc(JJ)J",
      "elements": [
        {
          "method": "org.eclipse.swt.internal.Callback.bind",
          "source": "Native Method"
        },
        {
          "method": "org.eclipse.swt.internal.Callback.\u003cinit\u003e",
          "source": "Callback.java:123"
        },
        {
          "method": "org.eclipse.swt.internal.Callback.\u003cinit\u003e",
          "source": "Callback.java:78"
        },
        {
          "method": "org.eclipse.swt.internal.Callback.\u003cinit\u003e",
          "source": "Callback.java:60"
        },
        {
          "method": "org.eclipse.swt.widgets.Display.initializeCallbacks",
          "source": "Display.java:1989"
        },
        {
          "method": "org.eclipse.swt.widgets.Display.init",
          "source": "Display.java:1931"
        },
        {
          "method": "org.eclipse.swt.graphics.Device.\u003cinit\u003e",
          "source": "Device.java:124"
        },
        {
          "method": "org.eclipse.swt.widgets.Display.\u003cinit\u003e",
          "source": "Display.java:419"
        },
        {
          "method": "org.eclipse.swt.widgets.Display.\u003cinit\u003e",
          "source": "Display.java:415"
        },
        {
          "method": "org.eclipse.ui.internal.Workbench.createDisplay",
          "source": "Workbench.java:323"
        },
        {
          "method": "org.eclipse.ui.PlatformUI.createDisplay",
          "source": "PlatformUI.java:155"
        },
        {
          "method": "org.eclipse.ui.internal.ide.IDEApplication.createDisplay",
          "source": "IDEApplication.java:128"
        },
        {
          "method": "org.eclipse.ui.internal.ide.IDEApplication.run",
          "source": "IDEApplication.java:79"
        },
        {
          "method": "org.eclipse.core.internal.runtime.PlatformActivator$1.run",
          "source": "PlatformActivator.java:228"
        },
        {
          "method": "org.eclipse.core.runtime.adaptor.EclipseStarter.run",
          "source": "EclipseStarter.java:338"
        },
        {
          "method": "org.eclipse.core.runtime.adaptor.EclipseStarter.run",
          "source": "EclipseStarter.java:151"
        },
        {
          "method": "sun.reflect.NativeMethodAccessorImpl.invoke0",
          "source": "Native Method"
        },
        {
          "method": "sun.reflect.NativeMethodAccessorImpl.invoke",
          "source": "NativeMethodAccessorImpl.java:85"
        },
        {
          "method": "sun.reflect.NativeMethodAccessorImpl.invoke",
          "source": "NativeMethodAccessorImpl.java:58"
        },
        {
          "method": "sun.reflect.DelegatingMethodAccessorImpl.invoke",
          "source": "DelegatingMethodAccessorImpl.java:60"
        },
        {
          "method": "java.lang.reflect.Method.invoke",
          "source": "Method.java:391"
        },
        {
          "method": "org.eclipse.core.launcher.Main.invokeFramework",
          "source": "Main.java:268"
        },
        {
          "method": "org.eclipse.core.launcher.Main.basicRun",
          "source": "Main.java:260"
        },
        {
          "method": "org.eclipse.core.launcher.Main.run",
          "source": "Main.java:887"
        },
        {
          "method": "org.eclipse.core.launcher.Main.main",
          "source": "Main.java:871"
        }
      ],
      "number": 1,
      "commentIndex": 5,
      "bugId": "87010",
      "date": "2005-03-08T18:15:58+01:00",
      "product": "Platform",
      "component": "SWT",
      "severity": "normal"
    }
  ],
  "groupId": "87010",
  "bugId": "87010",
  "date": "2005-03-02T17:41:39+01:00",
  "product": "Platform",
  "component": "SWT",
  "severity": "normal"
}