{
  "comments": [
    "btw, this is on 3.1M5A, both win32 and linux.\n\nNot sure what causes the exception, but it should be handled without the search\nfailing.\n\njava.nio.charset.IllegalCharsetNameException: (db encoding)\n        at java.nio.charset.Charset.checkName(Charset.java:285)\n        at java.nio.charset.Charset.lookup2(Charset.java:459)\n        at java.nio.charset.Charset.lookup(Charset.java:438)\n        at java.nio.charset.Charset.forName(Charset.java:497)\n        at\norg.eclipse.search.internal.core.text.TextSearchVisitor.visit(TextSearchVisitor.java:191)\n        at\norg.eclipse.core.internal.resources.Resource$1.visitElement(Resource.java:52)\n        at\norg.eclipse.core.internal.watson.ElementTreeIterator.doIteration(ElementTreeIterator.java:81)\n        at\norg.eclipse.core.internal.watson.ElementTreeIterator.doIteration(ElementTreeIterator.java:85)\n        at\norg.eclipse.core.internal.watson.ElementTreeIterator.doIteration(ElementTreeIterator.java:85)\n        at\norg.eclipse.core.internal.watson.ElementTreeIterator.doIteration(ElementTreeIterator.java:85)\n        at\norg.eclipse.core.internal.watson.ElementTreeIterator.doIteration(ElementTreeIterator.java:85)\n        at\norg.eclipse.core.internal.watson.ElementTreeIterator.doIteration(ElementTreeIterator.java:85)\n        at\norg.eclipse.core.internal.watson.ElementTreeIterator.iterate(ElementTreeIterator.java:126)\n        at org.eclipse.core.internal.resources.Resource.accept(Resource.java:62)\n        at\norg.eclipse.search.internal.core.text.TextSearchVisitor.process(TextSearchVisitor.java:105)\n        at\norg.eclipse.search.internal.core.text.TextSearchEngine.search(TextSearchEngine.java:76)\n        at\norg.eclipse.search.internal.core.text.TextSearchEngine.search(TextSearchEngine.java:47)\n        at\norg.eclipse.search.internal.ui.text.FileSearchQuery.run(FileSearchQuery.java:82)\n        at\norg.eclipse.search2.internal.ui.InternalSearchUI$InternalSearchJob.run(InternalSearchUI.java:93)\n        at org.eclipse.core.internal.jobs.Worker.run(Worker.java:67)",
    "Search does only fail for the file with the problem. All other files will be\nsearched and you get the problem(s) reported in the end.\n\nI don\u0027t think we can do better than that. It\u0027s not possible to read a file if\nits encoding is unknown to us.\n\nReopen if you observe something else.",
    "Look at the exception.  Unless the code has changed since the 3.1m5a release\nthere\u0027s no way it can work for you - there\u0027s no catch block for the\nIllegalCharsetNameException in TextSearchVisitor.java.  I can\u0027t send you an\nexample file that exhibits this (company confidential and all), but if i add the\ncatch block then it works fine (I can send you the code for the fix if you\nlike).  Frankly, i think its wrong that those functions throw unchecked\nexceptions, but hey its your code base.",
    "You are right. Thanks. I wasn\u0027t aware of the IllegalCharsetNameException.\nfixed \u003e 20050308"
  ],
  "commentCreationDates": [
    "2005-03-04T21:28:06+01:00",
    "2005-03-05T09:01:06+01:00",
    "2005-03-07T21:11:54+01:00",
    "2005-03-08T08:53:49+01:00"
  ],
  "traces": [
    {
      "exceptionType": "java.nio.charset.IllegalCharsetNameException",
      "message": "(db encoding)",
      "elements": [
        {
          "method": "java.nio.charset.Charset.checkName",
          "source": "Charset.java:285"
        },
        {
          "method": "java.nio.charset.Charset.lookup2",
          "source": "Charset.java:459"
        },
        {
          "method": "java.nio.charset.Charset.lookup",
          "source": "Charset.java:438"
        },
        {
          "method": "java.nio.charset.Charset.forName",
          "source": "Charset.java:497"
        },
        {
          "method": "org.eclipse.search.internal.core.text.TextSearchVisitor.visit",
          "source": "TextSearchVisitor.java:191"
        },
        {
          "method": "org.eclipse.core.internal.resources.Resource$1.visitElement",
          "source": "Resource.java:52"
        },
        {
          "method": "org.eclipse.core.internal.watson.ElementTreeIterator.doIteration",
          "source": "ElementTreeIterator.java:81"
        },
        {
          "method": "org.eclipse.core.internal.watson.ElementTreeIterator.doIteration",
          "source": "ElementTreeIterator.java:85"
        },
        {
          "method": "org.eclipse.core.internal.watson.ElementTreeIterator.doIteration",
          "source": "ElementTreeIterator.java:85"
        },
        {
          "method": "org.eclipse.core.internal.watson.ElementTreeIterator.doIteration",
          "source": "ElementTreeIterator.java:85"
        },
        {
          "method": "org.eclipse.core.internal.watson.ElementTreeIterator.doIteration",
          "source": "ElementTreeIterator.java:85"
        },
        {
          "method": "org.eclipse.core.internal.watson.ElementTreeIterator.doIteration",
          "source": "ElementTreeIterator.java:85"
        },
        {
          "method": "org.eclipse.core.internal.watson.ElementTreeIterator.iterate",
          "source": "ElementTreeIterator.java:126"
        },
        {
          "method": "org.eclipse.core.internal.resources.Resource.accept",
          "source": "Resource.java:62"
        },
        {
          "method": "org.eclipse.search.internal.core.text.TextSearchVisitor.process",
          "source": "TextSearchVisitor.java:105"
        },
        {
          "method": "org.eclipse.search.internal.core.text.TextSearchEngine.search",
          "source": "TextSearchEngine.java:76"
        },
        {
          "method": "org.eclipse.search.internal.core.text.TextSearchEngine.search",
          "source": "TextSearchEngine.java:47"
        },
        {
          "method": "org.eclipse.search.internal.ui.text.FileSearchQuery.run",
          "source": "FileSearchQuery.java:82"
        },
        {
          "method": "org.eclipse.search2.internal.ui.InternalSearchUI$InternalSearchJob.run",
          "source": "InternalSearchUI.java:93"
        },
        {
          "method": "org.eclipse.core.internal.jobs.Worker.run",
          "source": "Worker.java:67"
        }
      ],
      "number": 0,
      "commentIndex": 0,
      "bugId": "87187",
      "date": "2005-03-04T21:28:06+01:00",
      "product": "Platform",
      "component": "Search",
      "severity": "normal"
    }
  ],
  "groupId": "87187",
  "bugId": "87187",
  "date": "2005-03-04T21:28:06+01:00",
  "product": "Platform",
  "component": "Search",
  "severity": "normal"
}