{
  "comments": [
    "nightly build n0314\n\nI get the following exception on startup with this nightly build. I have the\ndebug view docked and stacked behind a couple other views. \n\nThere did not seem to be any side effects from this. (I was able to use the view\nwith no problems.\n\n!SESSION 2005-03-14 12:42:38.347 -----------------------------------------------\neclipse.buildId\u003dN20050314-0010\njava.fullversion\u003dJ2RE 1.4.2 IBM J9 2.2 Windows XP x86-32 j9n142-20040915 (JIT\nenabled)\nJ9VM - 20040914_1123_lHdSMR\nJIT  - r7_level20040912_1800\nBootLoader constants: OS\u003dwin32, ARCH\u003dx86, WS\u003dwin32, NL\u003den_CA\nFramework arguments:  -showlocation\nCommand-line arguments:  -os win32 -ws win32 -arch x86 -debug -data\n\\eclipse\\target\\head\\plugins\\ -showlocation -consoleLog -console\n\n!ENTRY org.eclipse.ui 4 0 2005-03-14 12:42:38.377\n!MESSAGE Warning: Detected attempt by view org.eclipse.debug.ui.DebugView to\ncreate itself recursively (this is probably, but not necessarily, a bug)\n!STACK 1\norg.eclipse.ui.PartInitException: Warning: Detected attempt by view\norg.eclipse.debug.ui.DebugView to create itself recursively (this is probably, but\n not necessarily, a bug)\n        at org.eclipse.ui.internal.ViewFactory.busyRestoreView(ViewFactory.java:288)\n        at org.eclipse.ui.internal.ViewFactory$1.run(ViewFactory.java:698)\n        at org.eclipse.swt.custom.BusyIndicator.showWhile(BusyIndicator.java:69)\n        at org.eclipse.ui.internal.ViewFactory.restoreView(ViewFactory.java:695)\n        at\norg.eclipse.ui.internal.ViewFactory$ViewReference.getPart(ViewFactory.java:119)\n        at\norg.eclipse.ui.internal.ViewFactory$ViewReference.getView(ViewFactory.java:172)\n        at org.eclipse.ui.internal.WorkbenchPage.findView(WorkbenchPage.java:1455)\n        at\norg.eclipse.debug.internal.ui.views.launch.LaunchView.createViewer(LaunchView.java:316)\n        at\norg.eclipse.debug.ui.AbstractDebugView$ViewerPage.createControl(AbstractDebugView.java:254)\n        at\norg.eclipse.debug.ui.AbstractDebugView.createDefaultPage(AbstractDebugView.java:342)\n        at org.eclipse.ui.part.PageBookView.createPartControl(PageBookView.java:388)\n        at\norg.eclipse.debug.ui.AbstractDebugView.createPartControl(AbstractDebugView.java:303)\n        at\norg.eclipse.ui.internal.ViewFactory.busyRestoreViewHelper(ViewFactory.java:430)\n        at org.eclipse.ui.internal.ViewFactory.busyRestoreView(ViewFactory.java:299)\n        at org.eclipse.ui.internal.ViewFactory$1.run(ViewFactory.java:698)\n        at org.eclipse.swt.custom.BusyIndicator.showWhile(BusyIndicator.java:69)\n        at org.eclipse.ui.internal.ViewFactory.restoreView(ViewFactory.java:695)\n        at\norg.eclipse.ui.internal.ViewFactory$ViewReference.getPart(ViewFactory.java:119)\n        at\norg.eclipse.ui.internal.ViewFactory$ViewReference.getView(ViewFactory.java:172)\n        at org.eclipse.ui.internal.WorkbenchPage.findView(WorkbenchPage.java:1455)\n        at\norg.eclipse.ui.internal.PagePartSelectionTracker.\u003cinit\u003e(PagePartSelectionTracker.java:59)\n        at\norg.eclipse.ui.internal.PageSelectionService.createPartTracker(PageSelectionService.java:48)\n        at\norg.eclipse.ui.internal.AbstractSelectionService.getPerPartTracker(AbstractSelectionService.java:202)\n        at\norg.eclipse.ui.internal.AbstractSelectionService.addSelectionListener(AbstractSelectionService.java:96)\n        at\norg.eclipse.ui.internal.WorkbenchPage.addSelectionListener(WorkbenchPage.java:652)\n        at\norg.eclipse.ui.internal.WindowPartSelectionTracker.pageOpened(WindowPartSelectionTracker.java:85)\n        at\norg.eclipse.ui.internal.WindowPartSelectionTracker.\u003cinit\u003e(WindowPartSelectionTracker.java:63)\n        at\norg.eclipse.ui.internal.WindowSelectionService.createPartTracker(WindowSelectionService.java:51)\n        at\norg.eclipse.ui.internal.AbstractSelectionService.getPerPartTracker(AbstractSelectionService.java:202)\n        at\norg.eclipse.ui.internal.AbstractSelectionService.addSelectionListener(AbstractSelectionService.java:96)\n        at\norg.eclipse.debug.internal.ui.actions.AbstractDebugActionDelegate.init(AbstractDebugActionDelegate.java:141)\n        at\norg.eclipse.ui.internal.WWinPluginAction.initDelegate(WWinPluginAction.java:180)\n        at\norg.eclipse.ui.internal.PluginAction.createDelegate(PluginAction.java:116)\n        at\norg.eclipse.ui.internal.WWinPluginAction.refreshActionList(WWinPluginAction.java:157)\n        at org.eclipse.ui.plugin.AbstractUIPlugin$1.run(AbstractUIPlugin.java:480)\n        at org.eclipse.swt.widgets.RunnableLock.run(RunnableLock.java:35)\n        at\norg.eclipse.swt.widgets.Synchronizer.runAsyncMessages(Synchronizer.java:118)\n        at org.eclipse.swt.widgets.Display.runAsyncMessages(Display.java:2871)\n        at org.eclipse.swt.widgets.Display.readAndDispatch(Display.java:2530)\n        at org.eclipse.ui.internal.Workbench.runEventLoop(Workbench.java:1514)\n        at org.eclipse.ui.internal.Workbench.runUI(Workbench.java:1478)\n        at\norg.eclipse.ui.internal.Workbench.createAndRunWorkbench(Workbench.java:297)\n        at org.eclipse.ui.PlatformUI.createAndRunWorkbench(PlatformUI.java:143)\n        at org.eclipse.ui.internal.ide.IDEApplication.run(IDEApplication.java:103)\n        at\norg.eclipse.core.internal.runtime.PlatformActivator$1.run(PlatformActivator.java:228)\n        at\norg.eclipse.core.runtime.adaptor.EclipseStarter.run(EclipseStarter.java:338)\n        at\norg.eclipse.core.runtime.adaptor.EclipseStarter.run(EclipseStarter.java:151)\n        at sun.reflect.NativeMethodAccessorImpl.invoke0(Native Method)\n        at\nsun.reflect.NativeMethodAccessorImpl.invoke(NativeMethodAccessorImpl.java:85)\n        at\nsun.reflect.NativeMethodAccessorImpl.invoke(NativeMethodAccessorImpl.java:58)\n        at\nsun.reflect.DelegatingMethodAccessorImpl.invoke(DelegatingMethodAccessorImpl.java:60)\n        at java.lang.reflect.Method.invoke(Method.java:391)\n        at org.eclipse.core.launcher.Main.invokeFramework(Main.java:268)\n        at org.eclipse.core.launcher.Main.basicRun(Main.java:260)\n        at org.eclipse.core.launcher.Main.run(Main.java:887)\n        at org.eclipse.core.launcher.Main.main(Main.java:871)\n!SUBENTRY 1 org.eclipse.ui 4 0 2005-03-14 12:42:38.427\n!MESSAGE Warning: Detected attempt by view org.eclipse.debug.ui.DebugView to\ncreate itself recursively (this is probably, but not necessarily, a bug)",
    "Fixed in LaunchView.\n\nThe view was initializing its \"active\" state when created, but it turns out we \nalso get a perspective changed notificaion that also initializes this state \nwhen the view is created. The code was redundant and can be removed.",
    "Please verify, Kevin.",
    "verified",
    "*** Bug 89060 has been marked as a duplicate of this bug. ***"
  ],
  "commentCreationDates": [
    "2005-03-14T17:49:23+01:00",
    "2005-03-14T18:40:41+01:00",
    "2005-03-14T18:40:56+01:00",
    "2005-03-14T20:39:27+01:00",
    "2005-03-25T03:31:36+01:00"
  ],
  "traces": [
    {
      "exceptionType": "org.eclipse.ui.PartInitException",
      "message": "Warning: Detected attempt by view org.eclipse.debug.ui.DebugView to create itself recursively (this is probably, but  not necessarily, a bug)",
      "elements": [
        {
          "method": "org.eclipse.ui.internal.ViewFactory.busyRestoreView",
          "source": "ViewFactory.java:288"
        },
        {
          "method": "org.eclipse.ui.internal.ViewFactory$1.run",
          "source": "ViewFactory.java:698"
        },
        {
          "method": "org.eclipse.swt.custom.BusyIndicator.showWhile",
          "source": "BusyIndicator.java:69"
        },
        {
          "method": "org.eclipse.ui.internal.ViewFactory.restoreView",
          "source": "ViewFactory.java:695"
        },
        {
          "method": "org.eclipse.ui.internal.ViewFactory$ViewReference.getPart",
          "source": "ViewFactory.java:119"
        },
        {
          "method": "org.eclipse.ui.internal.ViewFactory$ViewReference.getView",
          "source": "ViewFactory.java:172"
        },
        {
          "method": "org.eclipse.ui.internal.WorkbenchPage.findView",
          "source": "WorkbenchPage.java:1455"
        },
        {
          "method": "org.eclipse.debug.internal.ui.views.launch.LaunchView.createViewer",
          "source": "LaunchView.java:316"
        },
        {
          "method": "org.eclipse.debug.ui.AbstractDebugView$ViewerPage.createControl",
          "source": "AbstractDebugView.java:254"
        },
        {
          "method": "org.eclipse.debug.ui.AbstractDebugView.createDefaultPage",
          "source": "AbstractDebugView.java:342"
        },
        {
          "method": "org.eclipse.ui.part.PageBookView.createPartControl",
          "source": "PageBookView.java:388"
        },
        {
          "method": "org.eclipse.debug.ui.AbstractDebugView.createPartControl",
          "source": "AbstractDebugView.java:303"
        },
        {
          "method": "org.eclipse.ui.internal.ViewFactory.busyRestoreViewHelper",
          "source": "ViewFactory.java:430"
        },
        {
          "method": "org.eclipse.ui.internal.ViewFactory.busyRestoreView",
          "source": "ViewFactory.java:299"
        },
        {
          "method": "org.eclipse.ui.internal.ViewFactory$1.run",
          "source": "ViewFactory.java:698"
        },
        {
          "method": "org.eclipse.swt.custom.BusyIndicator.showWhile",
          "source": "BusyIndicator.java:69"
        },
        {
          "method": "org.eclipse.ui.internal.ViewFactory.restoreView",
          "source": "ViewFactory.java:695"
        },
        {
          "method": "org.eclipse.ui.internal.ViewFactory$ViewReference.getPart",
          "source": "ViewFactory.java:119"
        },
        {
          "method": "org.eclipse.ui.internal.ViewFactory$ViewReference.getView",
          "source": "ViewFactory.java:172"
        },
        {
          "method": "org.eclipse.ui.internal.WorkbenchPage.findView",
          "source": "WorkbenchPage.java:1455"
        },
        {
          "method": "org.eclipse.ui.internal.PagePartSelectionTracker.\u003cinit\u003e",
          "source": "PagePartSelectionTracker.java:59"
        },
        {
          "method": "org.eclipse.ui.internal.PageSelectionService.createPartTracker",
          "source": "PageSelectionService.java:48"
        },
        {
          "method": "org.eclipse.ui.internal.AbstractSelectionService.getPerPartTracker",
          "source": "AbstractSelectionService.java:202"
        },
        {
          "method": "org.eclipse.ui.internal.AbstractSelectionService.addSelectionListener",
          "source": "AbstractSelectionService.java:96"
        },
        {
          "method": "org.eclipse.ui.internal.WorkbenchPage.addSelectionListener",
          "source": "WorkbenchPage.java:652"
        },
        {
          "method": "org.eclipse.ui.internal.WindowPartSelectionTracker.pageOpened",
          "source": "WindowPartSelectionTracker.java:85"
        },
        {
          "method": "org.eclipse.ui.internal.WindowPartSelectionTracker.\u003cinit\u003e",
          "source": "WindowPartSelectionTracker.java:63"
        },
        {
          "method": "org.eclipse.ui.internal.WindowSelectionService.createPartTracker",
          "source": "WindowSelectionService.java:51"
        },
        {
          "method": "org.eclipse.ui.internal.AbstractSelectionService.getPerPartTracker",
          "source": "AbstractSelectionService.java:202"
        },
        {
          "method": "org.eclipse.ui.internal.AbstractSelectionService.addSelectionListener",
          "source": "AbstractSelectionService.java:96"
        },
        {
          "method": "org.eclipse.debug.internal.ui.actions.AbstractDebugActionDelegate.init",
          "source": "AbstractDebugActionDelegate.java:141"
        },
        {
          "method": "org.eclipse.ui.internal.WWinPluginAction.initDelegate",
          "source": "WWinPluginAction.java:180"
        },
        {
          "method": "org.eclipse.ui.internal.PluginAction.createDelegate",
          "source": "PluginAction.java:116"
        },
        {
          "method": "org.eclipse.ui.internal.WWinPluginAction.refreshActionList",
          "source": "WWinPluginAction.java:157"
        },
        {
          "method": "org.eclipse.ui.plugin.AbstractUIPlugin$1.run",
          "source": "AbstractUIPlugin.java:480"
        },
        {
          "method": "org.eclipse.swt.widgets.RunnableLock.run",
          "source": "RunnableLock.java:35"
        },
        {
          "method": "org.eclipse.swt.widgets.Synchronizer.runAsyncMessages",
          "source": "Synchronizer.java:118"
        },
        {
          "method": "org.eclipse.swt.widgets.Display.runAsyncMessages",
          "source": "Display.java:2871"
        },
        {
          "method": "org.eclipse.swt.widgets.Display.readAndDispatch",
          "source": "Display.java:2530"
        },
        {
          "method": "org.eclipse.ui.internal.Workbench.runEventLoop",
          "source": "Workbench.java:1514"
        },
        {
          "method": "org.eclipse.ui.internal.Workbench.runUI",
          "source": "Workbench.java:1478"
        },
        {
          "method": "org.eclipse.ui.internal.Workbench.createAndRunWorkbench",
          "source": "Workbench.java:297"
        },
        {
          "method": "org.eclipse.ui.PlatformUI.createAndRunWorkbench",
          "source": "PlatformUI.java:143"
        },
        {
          "method": "org.eclipse.ui.internal.ide.IDEApplication.run",
          "source": "IDEApplication.java:103"
        },
        {
          "method": "org.eclipse.core.internal.runtime.PlatformActivator$1.run",
          "source": "PlatformActivator.java:228"
        },
        {
          "method": "org.eclipse.core.runtime.adaptor.EclipseStarter.run",
          "source": "EclipseStarter.java:338"
        },
        {
          "method": "org.eclipse.core.runtime.adaptor.EclipseStarter.run",
          "source": "EclipseStarter.java:151"
        },
        {
          "method": "sun.reflect.NativeMethodAccessorImpl.invoke0",
          "source": "Native Method"
        },
        {
          "method": "sun.reflect.NativeMethodAccessorImpl.invoke",
          "source": "NativeMethodAccessorImpl.java:85"
        },
        {
          "method": "sun.reflect.NativeMethodAccessorImpl.invoke",
          "source": "NativeMethodAccessorImpl.java:58"
        },
        {
          "method": "sun.reflect.DelegatingMethodAccessorImpl.invoke",
          "source": "DelegatingMethodAccessorImpl.java:60"
        },
        {
          "method": "java.lang.reflect.Method.invoke",
          "source": "Method.java:391"
        },
        {
          "method": "org.eclipse.core.launcher.Main.invokeFramework",
          "source": "Main.java:268"
        },
        {
          "method": "org.eclipse.core.launcher.Main.basicRun",
          "source": "Main.java:260"
        },
        {
          "method": "org.eclipse.core.launcher.Main.run",
          "source": "Main.java:887"
        },
        {
          "method": "org.eclipse.core.launcher.Main.main",
          "source": "Main.java:871"
        }
      ],
      "number": 0,
      "commentIndex": 0,
      "bugId": "87955",
      "date": "2005-03-14T17:49:23+01:00",
      "product": "Platform",
      "component": "Debug",
      "severity": "normal"
    }
  ],
  "groupId": "87955",
  "bugId": "87955",
  "date": "2005-03-14T17:49:23+01:00",
  "product": "Platform",
  "component": "Debug",
  "severity": "normal"
}