{
  "comments": [
    "I\u0027m getting the following log when I tried to start the Eclipse.\nAny idea why? Am I missing something?\n\n!SESSION Mar 15, 2005 10:08:55.14 ----------------------------------------------\neclipse.buildId\u003dM200409161125\njava.fullversion\u003dJ2RE 1.4.2 IBM AIX 5L for PowerPC (64 bit JVM) build\ncaix64142sr1a-20050209 (JIT enabled: jitc)\nBootLoader constants: OS\u003daix, ARCH\u003dppc, WS\u003dmotif, NL\u003den_US\n\n!ENTRY org.eclipse.osgi Mar 15, 2005 10:08:55.18\n!MESSAGE Application error\n!STACK 1\njava.lang.ExceptionInInitializerError\n        at org.eclipse.swt.graphics.Device.\u003cclinit\u003e(Device.java:89)\n        at org.eclipse.ui.internal.Workbench.createDisplay(Workbench.java:268)\n        at org.eclipse.ui.PlatformUI.createDisplay(PlatformUI.java:153)\n        at\norg.eclipse.ui.internal.ide.IDEApplication.createDisplay(IDEApplication.java:122)\n        at org.eclipse.ui.internal.ide.IDEApplication.run(IDEApplication.java:72)\n        at\norg.eclipse.core.internal.runtime.PlatformActivator$1.run(PlatformActivator.java:335)\n        at\norg.eclipse.core.runtime.adaptor.EclipseStarter.run(EclipseStarter.java:273)\n        at\norg.eclipse.core.runtime.adaptor.EclipseStarter.run(EclipseStarter.java:129)\n        at sun.reflect.NativeMethodAccessorImpl.invoke0(Native Method)\n        at\nsun.reflect.NativeMethodAccessorImpl.invoke(NativeMethodAccessorImpl.java:85)\n        at\nsun.reflect.NativeMethodAccessorImpl.invoke(NativeMethodAccessorImpl.java:58)\n        at\nsun.reflect.DelegatingMethodAccessorImpl.invoke(DelegatingMethodAccessorImpl.java:60)\n        at java.lang.reflect.Method.invoke(Method.java:391)\n        at org.eclipse.core.launcher.Main.basicRun(Main.java:185)\n        at org.eclipse.core.launcher.Main.run(Main.java:704)\n        at org.eclipse.core.launcher.Main.main(Main.java:688)\nCaused by: java.lang.NullPointerException\n        at java.lang.ClassLoader.loadLibrary0(ClassLoader.java:2159)\n        at java.lang.ClassLoader.loadLibrary(ClassLoader.java:1976)\n        at java.lang.Runtime.loadLibrary0(Runtime.java:824)\n        at java.lang.System.loadLibrary(System.java:908)\n        at org.eclipse.swt.internal.Library.loadLibrary(Library.java:100)\n        at org.eclipse.swt.internal.motif.OS.\u003cclinit\u003e(OS.java:20)\n        ... 16 more",
    "It works if I use JRE 32 bit version 1.4.2 from IBM\n\n(In reply to comment #0)\n\u003e I\u0027m getting the following log when I tried to start the Eclipse.\n\u003e Any idea why? Am I missing something?\n\u003e \n\u003e !SESSION Mar 15, 2005 10:08:55.14 ----------------------------------------------\n\u003e eclipse.buildId\u003dM200409161125\n\u003e java.fullversion\u003dJ2RE 1.4.2 IBM AIX 5L for PowerPC (64 bit JVM) build\n\u003e caix64142sr1a-20050209 (JIT enabled: jitc)\n\u003e BootLoader constants: OS\u003daix, ARCH\u003dppc, WS\u003dmotif, NL\u003den_US\n\u003e \n\u003e !ENTRY org.eclipse.osgi Mar 15, 2005 10:08:55.18\n\u003e !MESSAGE Application error\n\u003e !STACK 1\n\u003e java.lang.ExceptionInInitializerError\n\u003e         at org.eclipse.swt.graphics.Device.\u003cclinit\u003e(Device.java:89)\n\u003e         at org.eclipse.ui.internal.Workbench.createDisplay(Workbench.java:268)\n\u003e         at org.eclipse.ui.PlatformUI.createDisplay(PlatformUI.java:153)\n\u003e         at\n\u003e org.eclipse.ui.internal.ide.IDEApplication.createDisplay(IDEApplication.java:122)\n\u003e         at org.eclipse.ui.internal.ide.IDEApplication.run(IDEApplication.java:72)\n\u003e         at\n\u003e\norg.eclipse.core.internal.runtime.PlatformActivator$1.run(PlatformActivator.java:335)\n\u003e         at\n\u003e org.eclipse.core.runtime.adaptor.EclipseStarter.run(EclipseStarter.java:273)\n\u003e         at\n\u003e org.eclipse.core.runtime.adaptor.EclipseStarter.run(EclipseStarter.java:129)\n\u003e         at sun.reflect.NativeMethodAccessorImpl.invoke0(Native Method)\n\u003e         at\n\u003e sun.reflect.NativeMethodAccessorImpl.invoke(NativeMethodAccessorImpl.java:85)\n\u003e         at\n\u003e sun.reflect.NativeMethodAccessorImpl.invoke(NativeMethodAccessorImpl.java:58)\n\u003e         at\n\u003e\nsun.reflect.DelegatingMethodAccessorImpl.invoke(DelegatingMethodAccessorImpl.java:60)\n\u003e         at java.lang.reflect.Method.invoke(Method.java:391)\n\u003e         at org.eclipse.core.launcher.Main.basicRun(Main.java:185)\n\u003e         at org.eclipse.core.launcher.Main.run(Main.java:704)\n\u003e         at org.eclipse.core.launcher.Main.main(Main.java:688)\n\u003e Caused by: java.lang.NullPointerException\n\u003e         at java.lang.ClassLoader.loadLibrary0(ClassLoader.java:2159)\n\u003e         at java.lang.ClassLoader.loadLibrary(ClassLoader.java:1976)\n\u003e         at java.lang.Runtime.loadLibrary0(Runtime.java:824)\n\u003e         at java.lang.System.loadLibrary(System.java:908)\n\u003e         at org.eclipse.swt.internal.Library.loadLibrary(Library.java:100)\n\u003e         at org.eclipse.swt.internal.motif.OS.\u003cclinit\u003e(OS.java:20)\n\u003e         ... 16 more\n\n",
    "Though I hadn\u0027t investigated this yet, I was guessing that this might be the \nproblem; bug 46010 has a similar cause on AIX.\n",
    "Changing report status since it\u0027s a jre issue.\n"
  ],
  "commentCreationDates": [
    "2005-03-15T16:43:13+01:00",
    "2005-03-17T11:23:03+01:00",
    "2005-03-17T13:50:15+01:00",
    "2005-04-12T17:48:57+02:00"
  ],
  "traces": [
    {
      "exceptionType": "java.lang.ExceptionInInitializerError",
      "elements": [
        {
          "method": "org.eclipse.swt.graphics.Device.\u003cclinit\u003e",
          "source": "Device.java:89"
        },
        {
          "method": "org.eclipse.ui.internal.Workbench.createDisplay",
          "source": "Workbench.java:268"
        },
        {
          "method": "org.eclipse.ui.PlatformUI.createDisplay",
          "source": "PlatformUI.java:153"
        },
        {
          "method": "org.eclipse.ui.internal.ide.IDEApplication.createDisplay",
          "source": "IDEApplication.java:122"
        },
        {
          "method": "org.eclipse.ui.internal.ide.IDEApplication.run",
          "source": "IDEApplication.java:72"
        },
        {
          "method": "org.eclipse.core.internal.runtime.PlatformActivator$1.run",
          "source": "PlatformActivator.java:335"
        },
        {
          "method": "org.eclipse.core.runtime.adaptor.EclipseStarter.run",
          "source": "EclipseStarter.java:273"
        },
        {
          "method": "org.eclipse.core.runtime.adaptor.EclipseStarter.run",
          "source": "EclipseStarter.java:129"
        },
        {
          "method": "sun.reflect.NativeMethodAccessorImpl.invoke0",
          "source": "Native Method"
        },
        {
          "method": "sun.reflect.NativeMethodAccessorImpl.invoke",
          "source": "NativeMethodAccessorImpl.java:85"
        },
        {
          "method": "sun.reflect.NativeMethodAccessorImpl.invoke",
          "source": "NativeMethodAccessorImpl.java:58"
        },
        {
          "method": "sun.reflect.DelegatingMethodAccessorImpl.invoke",
          "source": "DelegatingMethodAccessorImpl.java:60"
        },
        {
          "method": "java.lang.reflect.Method.invoke",
          "source": "Method.java:391"
        },
        {
          "method": "org.eclipse.core.launcher.Main.basicRun",
          "source": "Main.java:185"
        },
        {
          "method": "org.eclipse.core.launcher.Main.run",
          "source": "Main.java:704"
        },
        {
          "method": "org.eclipse.core.launcher.Main.main",
          "source": "Main.java:688"
        }
      ],
      "causedBy": {
        "exceptionType": "java.lang.NullPointerException",
        "elements": [
          {
            "method": "java.lang.ClassLoader.loadLibrary0",
            "source": "ClassLoader.java:2159"
          },
          {
            "method": "java.lang.ClassLoader.loadLibrary",
            "source": "ClassLoader.java:1976"
          },
          {
            "method": "java.lang.Runtime.loadLibrary0",
            "source": "Runtime.java:824"
          },
          {
            "method": "java.lang.System.loadLibrary",
            "source": "System.java:908"
          },
          {
            "method": "org.eclipse.swt.internal.Library.loadLibrary",
            "source": "Library.java:100"
          },
          {
            "method": "org.eclipse.swt.internal.motif.OS.\u003cclinit\u003e",
            "source": "OS.java:20"
          }
        ],
        "number": 0,
        "commentIndex": 0
      },
      "number": 0,
      "commentIndex": 0,
      "bugId": "88077",
      "date": "2005-03-15T16:43:13+01:00",
      "product": "Platform",
      "component": "SWT",
      "severity": "blocker"
    }
  ],
  "groupId": "88077",
  "bugId": "88077",
  "date": "2005-03-15T16:43:13+01:00",
  "product": "Platform",
  "component": "SWT",
  "severity": "blocker"
}