{
  "comments": [
    "when i try to create web service, I meet the following error message.\nIt seems miss the class. But I can find this class under\neclipse\\plugins\\org.eclipse.wst.wsdl_1.0.0\\lib\\wsdl4j.jar.\n\n\n\nIWAB0014E Unexpected exception occured.\n  javax/wsdl/factory/WSDLFactory\n      java.lang.NoClassDefFoundError: javax/wsdl/factory/WSDLFactory\n      at \norg.eclipse.jst.ws.internal.axis.creation.ui.task.DefaultsForServerJavaWSDLComma\nnd.execute\n\n(DefaultsForServerJavaWSDLCommand.java:128)\n      at \norg.eclipse.wst.command.env.core.fragment.CommandFragmentEngine.runCommand\n\n(CommandFragmentEngine.java:322)\n      at \norg.eclipse.wst.command.env.core.fragment.CommandFragmentEngine.visitTop\n(CommandFragmentEngine.java:288)\n      at \norg.eclipse.wst.command.env.core.fragment.CommandFragmentEngine.moveForwardToNex\ntStop\n\n(CommandFragmentEngine.java:208)\n      at org.eclipse.wst.command.env.ui.widgets.SimpleCommandEngineManager$4.run\n\n(SimpleCommandEngineManager.java:206)\n      at org.eclipse.jface.operation.ModalContext.runInCurrentThread\n(ModalContext.java:344)\n      at org.eclipse.jface.operation.ModalContext.run(ModalContext.java:289)\n      at org.eclipse.jface.wizard.WizardDialog.run(WizardDialog.java:824)\n      at \norg.eclipse.wst.command.env.ui.widgets.SimpleCommandEngineManager.runForwardToNe\nxtStop\n\n(SimpleCommandEngineManager.java:175)\n      at \norg.eclipse.wst.command.internal.env.ui.widgets.WizardPageManager.runForwardToNe\nxtStop\n\n(WizardPageManager.java:69)\n      at \norg.eclipse.wst.command.internal.env.ui.widgets.WizardPageManager.getNextPage\n(WizardPageManager.java:91)\n      at \norg.eclipse.wst.command.internal.env.ui.widgets.SimpleWizardPage.getNextPage\n(SimpleWizardPage.java:123)\n      at org.eclipse.jface.wizard.WizardDialog.nextPressed\n(WizardDialog.java:741)\n      at org.eclipse.jface.wizard.WizardDialog.buttonPressed\n(WizardDialog.java:338)\n      at org.eclipse.jface.dialogs.Dialog$2.widgetSelected(Dialog.java:543)\n      at org.eclipse.swt.widgets.TypedListener.handleEvent\n(TypedListener.java:89)\n      at org.eclipse.swt.widgets.EventTable.sendEvent(EventTable.java:82)\n      at org.eclipse.swt.widgets.Widget.sendEvent(Widget.java:842)\n      at org.eclipse.swt.widgets.Display.runDeferredEvents(Display.java:2908)\n      at org.eclipse.swt.widgets.Display.readAndDispatch(Display.java:2541)\n      at org.eclipse.jface.window.Window.runEventLoop(Window.java:718)\n      at org.eclipse.jface.window.Window.open(Window.java:696)\n      at \norg.eclipse.wst.command.internal.env.ui.widgets.popup.DynamicPopupWizard.run\n(DynamicPopupWizard.java:123)\n      at org.eclipse.ui.internal.PluginAction.runWithEvent\n(PluginAction.java:244)\n      at org.eclipse.jface.action.ActionContributionItem.handleWidgetSelection\n(ActionContributionItem.java:557)\n      at org.eclipse.jface.action.ActionContributionItem.access$2\n(ActionContributionItem.java:507)\n      at org.eclipse.jface.action.ActionContributionItem$6.handleEvent\n(ActionContributionItem.java:421)\n      at org.eclipse.swt.widgets.EventTable.sendEvent(EventTable.java:82)\n      at org.eclipse.swt.widgets.Widget.sendEvent(Widget.java:842)\n      at org.eclipse.swt.widgets.Display.runDeferredEvents(Display.java:2908)\n      at org.eclipse.swt.widgets.Display.readAndDispatch(Display.java:2541)\n      at org.eclipse.ui.internal.Workbench.runEventLoop(Workbench.java:1612)\n      at org.eclipse.ui.internal.Workbench.runUI(Workbench.java:1578)\n      at org.eclipse.ui.internal.Workbench.createAndRunWorkbench\n(Workbench.java:293)\n      at org.eclipse.ui.PlatformUI.createAndRunWorkbench(PlatformUI.java:144)\n      at org.eclipse.ui.internal.ide.IDEApplication.run(IDEApplication.java:102)\n      at org.eclipse.core.internal.runtime.PlatformActivator$1.run\n(PlatformActivator.java:228)\n      at org.eclipse.core.runtime.adaptor.EclipseStarter.run\n(EclipseStarter.java:333)\n      at org.eclipse.core.runtime.adaptor.EclipseStarter.run\n(EclipseStarter.java:150)\n      at sun.reflect.NativeMethodAccessorImpl.invoke0(Native Method)\n      at sun.reflect.NativeMethodAccessorImpl.invoke(Unknown Source)\n      at sun.reflect.DelegatingMethodAccessorImpl.invoke(Unknown Source)\n      at java.lang.reflect.Method.invoke(Unknown Source)\n      at org.eclipse.core.launcher.Main.invokeFramework(Main.java:268)\n      at org.eclipse.core.launcher.Main.basicRun(Main.java:260)\n      at org.eclipse.core.launcher.Main.run(Main.java:887)\n      at org.eclipse.core.launcher.Main.main(Main.java:871)",
    "Are both wsdl4j.jar and qname.jar in org.eclipse.wst.wsdl_1.0.0\\lib, and have \nyou started Eclipse with the \"-clean\" option?",
    "Are both wsdl4j.jar and qname.jar in org.eclipse.wst.wsdl_1.0.0\\lib, and have \nyou started Eclipse with the \"-clean\" option?",
    "Now it is working."
  ],
  "commentCreationDates": [
    "2005-03-18T09:46:13+01:00",
    "2005-03-20T02:18:14+01:00",
    "2005-04-15T05:10:50+02:00",
    "2005-07-13T03:38:04+02:00"
  ],
  "traces": [
    {
      "exceptionType": "java.lang.NoClassDefFoundError",
      "message": "javax/wsdl/factory/WSDLFactory",
      "elements": [
        {
          "method": "org.eclipse.jst.ws.internal.axis.creation.ui.task.DefaultsForServerJavaWSDLCommand.execute",
          "source": "DefaultsForServerJavaWSDLCommand.java:128"
        },
        {
          "method": "org.eclipse.wst.command.env.core.fragment.CommandFragmentEngine.runCommand",
          "source": "CommandFragmentEngine.java:322"
        },
        {
          "method": "org.eclipse.wst.command.env.core.fragment.CommandFragmentEngine.visitTop",
          "source": "CommandFragmentEngine.java:288"
        },
        {
          "method": "org.eclipse.wst.command.env.core.fragment.CommandFragmentEngine.moveForwardToNextStop",
          "source": "CommandFragmentEngine.java:208"
        },
        {
          "method": "org.eclipse.wst.command.env.ui.widgets.SimpleCommandEngineManager$4.run",
          "source": "SimpleCommandEngineManager.java:206"
        },
        {
          "method": "org.eclipse.jface.operation.ModalContext.runInCurrentThread",
          "source": "ModalContext.java:344"
        },
        {
          "method": "org.eclipse.jface.operation.ModalContext.run",
          "source": "ModalContext.java:289"
        },
        {
          "method": "org.eclipse.jface.wizard.WizardDialog.run",
          "source": "WizardDialog.java:824"
        },
        {
          "method": "org.eclipse.wst.command.env.ui.widgets.SimpleCommandEngineManager.runForwardToNextStop",
          "source": "SimpleCommandEngineManager.java:175"
        },
        {
          "method": "org.eclipse.wst.command.internal.env.ui.widgets.WizardPageManager.runForwardToNextStop",
          "source": "WizardPageManager.java:69"
        },
        {
          "method": "org.eclipse.wst.command.internal.env.ui.widgets.WizardPageManager.getNextPage",
          "source": "WizardPageManager.java:91"
        },
        {
          "method": "org.eclipse.wst.command.internal.env.ui.widgets.SimpleWizardPage.getNextPage",
          "source": "SimpleWizardPage.java:123"
        },
        {
          "method": "org.eclipse.jface.wizard.WizardDialog.nextPressed",
          "source": "WizardDialog.java:741"
        },
        {
          "method": "org.eclipse.jface.wizard.WizardDialog.buttonPressed",
          "source": "WizardDialog.java:338"
        },
        {
          "method": "org.eclipse.jface.dialogs.Dialog$2.widgetSelected",
          "source": "Dialog.java:543"
        },
        {
          "method": "org.eclipse.swt.widgets.TypedListener.handleEvent",
          "source": "TypedListener.java:89"
        },
        {
          "method": "org.eclipse.swt.widgets.EventTable.sendEvent",
          "source": "EventTable.java:82"
        },
        {
          "method": "org.eclipse.swt.widgets.Widget.sendEvent",
          "source": "Widget.java:842"
        },
        {
          "method": "org.eclipse.swt.widgets.Display.runDeferredEvents",
          "source": "Display.java:2908"
        },
        {
          "method": "org.eclipse.swt.widgets.Display.readAndDispatch",
          "source": "Display.java:2541"
        },
        {
          "method": "org.eclipse.jface.window.Window.runEventLoop",
          "source": "Window.java:718"
        },
        {
          "method": "org.eclipse.jface.window.Window.open",
          "source": "Window.java:696"
        },
        {
          "method": "org.eclipse.wst.command.internal.env.ui.widgets.popup.DynamicPopupWizard.run",
          "source": "DynamicPopupWizard.java:123"
        },
        {
          "method": "org.eclipse.ui.internal.PluginAction.runWithEvent",
          "source": "PluginAction.java:244"
        },
        {
          "method": "org.eclipse.jface.action.ActionContributionItem.handleWidgetSelection",
          "source": "ActionContributionItem.java:557"
        },
        {
          "method": "org.eclipse.jface.action.ActionContributionItem.access$2",
          "source": "ActionContributionItem.java:507"
        },
        {
          "method": "org.eclipse.jface.action.ActionContributionItem$6.handleEvent",
          "source": "ActionContributionItem.java:421"
        },
        {
          "method": "org.eclipse.swt.widgets.EventTable.sendEvent",
          "source": "EventTable.java:82"
        },
        {
          "method": "org.eclipse.swt.widgets.Widget.sendEvent",
          "source": "Widget.java:842"
        },
        {
          "method": "org.eclipse.swt.widgets.Display.runDeferredEvents",
          "source": "Display.java:2908"
        },
        {
          "method": "org.eclipse.swt.widgets.Display.readAndDispatch",
          "source": "Display.java:2541"
        },
        {
          "method": "org.eclipse.ui.internal.Workbench.runEventLoop",
          "source": "Workbench.java:1612"
        },
        {
          "method": "org.eclipse.ui.internal.Workbench.runUI",
          "source": "Workbench.java:1578"
        },
        {
          "method": "org.eclipse.ui.internal.Workbench.createAndRunWorkbench",
          "source": "Workbench.java:293"
        },
        {
          "method": "org.eclipse.ui.PlatformUI.createAndRunWorkbench",
          "source": "PlatformUI.java:144"
        },
        {
          "method": "org.eclipse.ui.internal.ide.IDEApplication.run",
          "source": "IDEApplication.java:102"
        },
        {
          "method": "org.eclipse.core.internal.runtime.PlatformActivator$1.run",
          "source": "PlatformActivator.java:228"
        },
        {
          "method": "org.eclipse.core.runtime.adaptor.EclipseStarter.run",
          "source": "EclipseStarter.java:333"
        },
        {
          "method": "org.eclipse.core.runtime.adaptor.EclipseStarter.run",
          "source": "EclipseStarter.java:150"
        },
        {
          "method": "sun.reflect.NativeMethodAccessorImpl.invoke0",
          "source": "Native Method"
        },
        {
          "method": "sun.reflect.NativeMethodAccessorImpl.invoke",
          "source": "Unknown Source"
        },
        {
          "method": "sun.reflect.DelegatingMethodAccessorImpl.invoke",
          "source": "Unknown Source"
        },
        {
          "method": "java.lang.reflect.Method.invoke",
          "source": "Unknown Source"
        },
        {
          "method": "org.eclipse.core.launcher.Main.invokeFramework",
          "source": "Main.java:268"
        },
        {
          "method": "org.eclipse.core.launcher.Main.basicRun",
          "source": "Main.java:260"
        },
        {
          "method": "org.eclipse.core.launcher.Main.run",
          "source": "Main.java:887"
        },
        {
          "method": "org.eclipse.core.launcher.Main.main",
          "source": "Main.java:871"
        }
      ],
      "number": 0,
      "commentIndex": 0,
      "bugId": "88431",
      "date": "2005-03-18T09:46:13+01:00",
      "product": "Web Tools",
      "component": "jst.ws",
      "severity": "normal"
    }
  ],
  "groupId": "88431",
  "bugId": "88431",
  "date": "2005-03-18T09:46:13+01:00",
  "product": "Web Tools",
  "component": "jst.ws",
  "severity": "normal"
}