{
  "comments": [
    "- I have a bunch of projects in my workspace including some UI ones and SWT\n- I was doing a full build\n- in the middle of the \"clean\", I turned off auto-build and cancelled the clean\n- then I selected the 2 SWT projects (swt and swt.win32) and selected Close from\nthe context menu\n- projects seemed to close OK but I got the following exception in my log file\n\n!SESSION 2005-03-23 19:00:19.110 -----------------------------------------------\neclipse.buildId\u003dI20050323-1615\njava.fullversion\u003dJ2RE 1.4.2 IBM J9 2.2 Windows XP x86-32 j9n142-20040915 (JIT\nenabled)\nJ9VM - 20040914_1123_lHdSMR\nJIT  - r7_level20040912_1800\nBootLoader constants: OS\u003dwin32, ARCH\u003dx86, WS\u003dwin32, NL\u003den_CA\nFramework arguments:  -showlocation\nCommand-line arguments:  -os win32 -ws win32 -arch x86 -debug -data\n\\eclipse\\target\\head\\plugins\\ -showlocation -consoleLog -console\n\n!ENTRY org.eclipse.core.resources 4 2 2005-03-23 19:00:19.110\n!MESSAGE Problems occurred when invoking code from plug-in:\n\"org.eclipse.core.resources\".\n!STACK 0\njava.lang.IllegalArgumentException: Attempted to beginRule: R/, does not match\nouter scope rule: MultiRule[P/org.eclipse.swt,P/org.eclipse.swt.win32]\n        at org.eclipse.core.internal.runtime.Assert.isLegal(Assert.java:58)\n        at org.eclipse.core.internal.jobs.ThreadJob.illegalPush(ThreadJob.java:107)\n        at org.eclipse.core.internal.jobs.ThreadJob.push(ThreadJob.java:201)\n        at org.eclipse.core.internal.jobs.ImplicitJobs.begin(ImplicitJobs.java:81)\n        at org.eclipse.core.internal.jobs.JobManager.beginRule(JobManager.java:186)\n        at\norg.eclipse.core.internal.resources.WorkManager.checkIn(WorkManager.java:96)\n        at\norg.eclipse.core.internal.resources.Workspace.prepareOperation(Workspace.java:1669)\n        at org.eclipse.core.internal.resources.Workspace.run(Workspace.java:1709)\n        at\norg.eclipse.jdt.internal.core.JavaModelOperation.runOperation(JavaModelOperation.java:771)\n        at\norg.eclipse.jdt.internal.core.JavaProject.setRawClasspath(JavaProject.java:2739)\n        at org.eclipse.jdt.core.JavaCore$3.run(JavaCore.java:4133)\n        at\norg.eclipse.jdt.internal.core.BatchOperation.executeOperation(BatchOperation.java:34)\n        at\norg.eclipse.jdt.internal.core.JavaModelOperation.run(JavaModelOperation.java:710)\n        at org.eclipse.core.internal.resources.Workspace.run(Workspace.java:1714)\n        at org.eclipse.jdt.core.JavaCore.run(JavaCore.java:3946)\n        at org.eclipse.jdt.core.JavaCore.setClasspathContainer(JavaCore.java:4116)\n        at\norg.eclipse.pde.internal.core.SearchablePluginsManager.updateClasspathContainer(SearchablePluginsManager.java:151)\n        at\norg.eclipse.pde.internal.core.SearchablePluginsManager.updateClasspathContainer(SearchablePluginsManager.java:136)\n        at\norg.eclipse.pde.internal.core.PluginModelManager.handleModelsChanged(PluginModelManager.java:274)\n        at\norg.eclipse.pde.internal.core.PluginModelManager.access$0(PluginModelManager.java:191)\n        at\norg.eclipse.pde.internal.core.PluginModelManager$1.modelsChanged(PluginModelManager.java:35)\n        at\norg.eclipse.pde.internal.core.WorkspaceModelManager.fireModelProviderEvent(WorkspaceModelManager.java:732)\n        at\norg.eclipse.pde.internal.core.WorkspaceModelManager.processModelChanges(WorkspaceModelManager.java:726)\n        at\norg.eclipse.pde.internal.core.WorkspaceModelManager.resourceChanged(WorkspaceModelManager.java:399)\n        at\norg.eclipse.core.internal.events.NotificationManager$2.run(NotificationManager.java:275)\n        at\norg.eclipse.core.internal.runtime.InternalPlatform.run(InternalPlatform.java:1015)\n        at org.eclipse.core.runtime.Platform.run(Platform.java:757)\n        at\norg.eclipse.core.internal.events.NotificationManager.notify(NotificationManager.java:269)\n        at\norg.eclipse.core.internal.events.NotificationManager.handleEvent(NotificationManager.java:241)\n        at\norg.eclipse.core.internal.resources.Workspace.broadcastEvent(Workspace.java:195)\n        at org.eclipse.core.internal.resources.Project.close(Project.java:172)\n        at\norg.eclipse.ui.actions.CloseResourceAction.invokeOperation(CloseResourceAction.java:169)\n        at org.eclipse.ui.actions.WorkspaceAction.execute(WorkspaceAction.java:133)\n        at\norg.eclipse.ui.actions.WorkspaceAction$2.runInWorkspace(WorkspaceAction.java:414)\n        at\norg.eclipse.core.internal.resources.InternalWorkspaceJob.run(InternalWorkspaceJob.java:38)\n        at org.eclipse.core.internal.jobs.Worker.run(Worker.java:67)",
    "\n\n*** This bug has been marked as a duplicate of 85846 ***"
  ],
  "commentCreationDates": [
    "2005-03-24T00:02:58+01:00",
    "2005-03-24T07:38:54+01:00"
  ],
  "traces": [
    {
      "exceptionType": "java.lang.IllegalArgumentException",
      "message": "Attempted to beginRule: R/, does not match outer scope rule: MultiRule[P/org.eclipse.swt,P/org.eclipse.swt.win32]",
      "elements": [
        {
          "method": "org.eclipse.core.internal.runtime.Assert.isLegal",
          "source": "Assert.java:58"
        },
        {
          "method": "org.eclipse.core.internal.jobs.ThreadJob.illegalPush",
          "source": "ThreadJob.java:107"
        },
        {
          "method": "org.eclipse.core.internal.jobs.ThreadJob.push",
          "source": "ThreadJob.java:201"
        },
        {
          "method": "org.eclipse.core.internal.jobs.ImplicitJobs.begin",
          "source": "ImplicitJobs.java:81"
        },
        {
          "method": "org.eclipse.core.internal.jobs.JobManager.beginRule",
          "source": "JobManager.java:186"
        },
        {
          "method": "org.eclipse.core.internal.resources.WorkManager.checkIn",
          "source": "WorkManager.java:96"
        },
        {
          "method": "org.eclipse.core.internal.resources.Workspace.prepareOperation",
          "source": "Workspace.java:1669"
        },
        {
          "method": "org.eclipse.core.internal.resources.Workspace.run",
          "source": "Workspace.java:1709"
        },
        {
          "method": "org.eclipse.jdt.internal.core.JavaModelOperation.runOperation",
          "source": "JavaModelOperation.java:771"
        },
        {
          "method": "org.eclipse.jdt.internal.core.JavaProject.setRawClasspath",
          "source": "JavaProject.java:2739"
        },
        {
          "method": "org.eclipse.jdt.core.JavaCore$3.run",
          "source": "JavaCore.java:4133"
        },
        {
          "method": "org.eclipse.jdt.internal.core.BatchOperation.executeOperation",
          "source": "BatchOperation.java:34"
        },
        {
          "method": "org.eclipse.jdt.internal.core.JavaModelOperation.run",
          "source": "JavaModelOperation.java:710"
        },
        {
          "method": "org.eclipse.core.internal.resources.Workspace.run",
          "source": "Workspace.java:1714"
        },
        {
          "method": "org.eclipse.jdt.core.JavaCore.run",
          "source": "JavaCore.java:3946"
        },
        {
          "method": "org.eclipse.jdt.core.JavaCore.setClasspathContainer",
          "source": "JavaCore.java:4116"
        },
        {
          "method": "org.eclipse.pde.internal.core.SearchablePluginsManager.updateClasspathContainer",
          "source": "SearchablePluginsManager.java:151"
        },
        {
          "method": "org.eclipse.pde.internal.core.SearchablePluginsManager.updateClasspathContainer",
          "source": "SearchablePluginsManager.java:136"
        },
        {
          "method": "org.eclipse.pde.internal.core.PluginModelManager.handleModelsChanged",
          "source": "PluginModelManager.java:274"
        },
        {
          "method": "org.eclipse.pde.internal.core.PluginModelManager.access$0",
          "source": "PluginModelManager.java:191"
        },
        {
          "method": "org.eclipse.pde.internal.core.PluginModelManager$1.modelsChanged",
          "source": "PluginModelManager.java:35"
        },
        {
          "method": "org.eclipse.pde.internal.core.WorkspaceModelManager.fireModelProviderEvent",
          "source": "WorkspaceModelManager.java:732"
        },
        {
          "method": "org.eclipse.pde.internal.core.WorkspaceModelManager.processModelChanges",
          "source": "WorkspaceModelManager.java:726"
        },
        {
          "method": "org.eclipse.pde.internal.core.WorkspaceModelManager.resourceChanged",
          "source": "WorkspaceModelManager.java:399"
        },
        {
          "method": "org.eclipse.core.internal.events.NotificationManager$2.run",
          "source": "NotificationManager.java:275"
        },
        {
          "method": "org.eclipse.core.internal.runtime.InternalPlatform.run",
          "source": "InternalPlatform.java:1015"
        },
        {
          "method": "org.eclipse.core.runtime.Platform.run",
          "source": "Platform.java:757"
        },
        {
          "method": "org.eclipse.core.internal.events.NotificationManager.notify",
          "source": "NotificationManager.java:269"
        },
        {
          "method": "org.eclipse.core.internal.events.NotificationManager.handleEvent",
          "source": "NotificationManager.java:241"
        },
        {
          "method": "org.eclipse.core.internal.resources.Workspace.broadcastEvent",
          "source": "Workspace.java:195"
        },
        {
          "method": "org.eclipse.core.internal.resources.Project.close",
          "source": "Project.java:172"
        },
        {
          "method": "org.eclipse.ui.actions.CloseResourceAction.invokeOperation",
          "source": "CloseResourceAction.java:169"
        },
        {
          "method": "org.eclipse.ui.actions.WorkspaceAction.execute",
          "source": "WorkspaceAction.java:133"
        },
        {
          "method": "org.eclipse.ui.actions.WorkspaceAction$2.runInWorkspace",
          "source": "WorkspaceAction.java:414"
        },
        {
          "method": "org.eclipse.core.internal.resources.InternalWorkspaceJob.run",
          "source": "InternalWorkspaceJob.java:38"
        },
        {
          "method": "org.eclipse.core.internal.jobs.Worker.run",
          "source": "Worker.java:67"
        }
      ],
      "number": 0,
      "commentIndex": 0,
      "bugId": "88956",
      "duplicateId": "85846",
      "date": "2005-03-24T00:02:58+01:00",
      "product": "PDE",
      "component": "UI",
      "severity": "normal"
    }
  ],
  "groupId": "85846",
  "bugId": "88956",
  "duplicateId": "85846",
  "date": "2005-03-24T00:02:58+01:00",
  "product": "PDE",
  "component": "UI",
  "severity": "normal"
}