{
  "comments": [
    "build I200503241400 motif linux\n\n1. I selected a project and used Team-\u003eSynchronize with Repository.\n2. In the Synchronize View [in the Synchronize perspective] a had a few conflicts.\n3. I selected one of the conflict files and used \u0027Override and Update\u0027\n\nDurign the processa dialog showed up (some corfimation), I hit yes, after that\nsome other dialog came up, this second dialog had a combo box, the option list\nof this combo box was opening and closing (very fast) non-stop. The dialog was\nso flashy that I couldn\u0027t read anything else.\n\nI could reproduce this problem a couple times but I can\u0027t do it anymore.",
    "Stack trace:\n!ENTRY org.eclipse.ui 4 0 2005-03-24 17:51:58.548\n!MESSAGE Failed to execute runnable\n(org.eclipse.jface.util.Assert$AssertionFailedException: null argument;)\n!STACK 0\norg.eclipse.swt.SWTException: Failed to execute runnable\n(org.eclipse.jface.util.Assert$AssertionFailedException: null argument;)\n        at org.eclipse.swt.SWT.error(SWT.java:2850)\n        at org.eclipse.swt.SWT.error(SWT.java:2773)\n        at\norg.eclipse.swt.widgets.Synchronizer.runAsyncMessages(Synchronizer.java:121)\n        at org.eclipse.swt.widgets.Display.runAsyncMessages(Display.java:2981)\n        at org.eclipse.swt.widgets.Display.readAndDispatch(Display.java:2706)\n        at org.eclipse.jface.window.Window.runEventLoop(Window.java:801)\n        at org.eclipse.jface.window.Window.open(Window.java:779)\n        at org.eclipse.jface.dialogs.ErrorDialog.open(ErrorDialog.java:274)\n        at\norg.eclipse.ui.internal.progress.ErrorNotificationManager.openErrorDialog(ErrorNotificationManager.java:170)\n        at\norg.eclipse.ui.internal.progress.ErrorNotificationManager.access$2(ErrorNotificationManager.java:156)\n        at\norg.eclipse.ui.internal.progress.ErrorNotificationManager$2.runInUIThread(ErrorNotificationManager.java:130)\n        at org.eclipse.ui.progress.UIJob$1.run(UIJob.java:93)\n        at org.eclipse.swt.widgets.RunnableLock.run(RunnableLock.java:35)\n        at\norg.eclipse.swt.widgets.Synchronizer.runAsyncMessages(Synchronizer.java:118)\n        at org.eclipse.swt.widgets.Display.runAsyncMessages(Display.java:2981)\n        at org.eclipse.swt.widgets.Display.readAndDispatch(Display.java:2706)\n        at org.eclipse.ui.internal.Workbench.runEventLoop(Workbench.java:1538)\n        at org.eclipse.ui.internal.Workbench.runUI(Workbench.java:1502)\n        at\norg.eclipse.ui.internal.Workbench.createAndRunWorkbench(Workbench.java:306)\n        at org.eclipse.ui.PlatformUI.createAndRunWorkbench(PlatformUI.java:143)\n        at org.eclipse.ui.internal.ide.IDEApplication.run(IDEApplication.java:103)\n        at\norg.eclipse.core.internal.runtime.PlatformActivator$1.run(PlatformActivator.java:228)\n        at\norg.eclipse.core.runtime.adaptor.EclipseStarter.run(EclipseStarter.java:338)\n        at\norg.eclipse.core.runtime.adaptor.EclipseStarter.run(EclipseStarter.java:151)\n        at sun.reflect.NativeMethodAccessorImpl.invoke0(Native Method)\n        at\nsun.reflect.NativeMethodAccessorImpl.invoke(NativeMethodAccessorImpl.java:39)\n        at\nsun.reflect.DelegatingMethodAccessorImpl.invoke(DelegatingMethodAccessorImpl.java:25)\n        at java.lang.reflect.Method.invoke(Method.java:324)\n        at org.eclipse.core.launcher.Main.invokeFramework(Main.java:268)\n        at org.eclipse.core.launcher.Main.basicRun(Main.java:260)\n        at org.eclipse.core.launcher.Main.run(Main.java:887)\n        at org.eclipse.core.launcher.Main.main(Main.java:871)\nCaused by: org.eclipse.jface.util.Assert$AssertionFailedException: null argument;\n        at org.eclipse.jface.util.Assert.isNotNull(Assert.java:149)\n        at org.eclipse.jface.util.Assert.isNotNull(Assert.java:125)\n        at\norg.eclipse.jface.viewers.StructuredViewer.disassociate(StructuredViewer.java:499)\n        at\norg.eclipse.jface.viewers.TableViewer.internalRefreshAll(TableViewer.java:783)\n        at\norg.eclipse.jface.viewers.TableViewer.internalRefresh(TableViewer.java:710)\n        at\norg.eclipse.jface.viewers.TableViewer.internalRefresh(TableViewer.java:699)\n        at\norg.eclipse.jface.viewers.StructuredViewer$7.run(StructuredViewer.java:1171)\n        at\norg.eclipse.jface.viewers.StructuredViewer.preservingSelection(StructuredViewer.java:1108)\n        at\norg.eclipse.jface.viewers.StructuredViewer.refresh(StructuredViewer.java:1169)\n        at\norg.eclipse.jface.viewers.StructuredViewer.refresh(StructuredViewer.java:1128)\n        at\norg.eclipse.ui.views.markers.internal.TableContentProvider.resync(TableContentProvider.java:254)\n        at\norg.eclipse.ui.views.markers.internal.TableContentProvider.updateViewer(TableContentProvider.java:447)\n        at\norg.eclipse.ui.views.markers.internal.TableContentProvider.access$3(TableContentProvider.java:434)\n        at\norg.eclipse.ui.views.markers.internal.TableContentProvider$WidgetRefreshJob.runInUIThread(TableContentProvider.java:137)\n        at org.eclipse.ui.progress.UIJob$1.run(UIJob.java:93)\n        at org.eclipse.swt.widgets.RunnableLock.run(RunnableLock.java:35)\n        at\norg.eclipse.swt.widgets.Synchronizer.runAsyncMessages(Synchronizer.java:118)\n        ... 29 more\n\nI got hundreds of this same message (11Mb) in my .log.\n\n",
    "The exception you\u0027ve included is coming from the markers view. It looks like \nthere was something wrong in the table viewer. The dialog you saw may have \nbeen the Error Dialog. Moving to UI for comment.",
    "Stefan, note that the motif Table was recently re-written, so it may be causing\nthe viewer grief.  Please have a quick look at this asap and let me know if\nthere\u0027s a problem in the Table.\n",
    "Appears to be TableViewer-related. Tod?",
    "Looks like it might be the table. We are catching UIJob failures at a furious\nrate by the looks of things and are having a hard time logging them",
    "Created an attachment (id\u003d19238)\nflashy dialog screenshot.\n\nIt just happened again. Here is a screenshot of the dialog that keeps blinking\nwhen the problem happens.",
    "This last time I\u0027m not sure if the bug was caused by update from cvs task or by\nthe launching swt task that I also had running. The stacktrace is the same, it\ntook me less than one minute to take the screenshot and close eclipse and it\nstill logged 12Mb in my metadata/.log.\n",
    "On a side note, the error dialog in the screenshot is not properly sized. \nThere was another sizing error on GTK in bug 89203. Did something change on \nGTK that could be causing this?",
    "this is on motif\n",
    "Billy, I saw the words \"GTK\" and \"not properly sized\" in the same sentence, \nyou might be interested.\n",
    "Taking ownership since this is probably a Table problem, though I haven\u0027t been\nable to reproduce it yet.",
    "*** Bug 89410 has been marked as a duplicate of this bug. ***",
    "This causes Eclipse to become unusable, forcing the user to kill it.  Upgrading\nto critical.",
    "Upgrading to blocker.  This is interfering with my ability to complete my test\npass on Linux-Motif.",
    "fixed \u003e 0330"
  ],
  "commentCreationDates": [
    "2005-03-24T23:04:32+01:00",
    "2005-03-24T23:07:14+01:00",
    "2005-03-28T15:59:32+02:00",
    "2005-03-28T17:11:52+02:00",
    "2005-03-28T20:49:47+02:00",
    "2005-03-28T20:58:14+02:00",
    "2005-03-28T20:58:20+02:00",
    "2005-03-28T21:03:17+02:00",
    "2005-03-28T21:22:02+02:00",
    "2005-03-28T21:24:28+02:00",
    "2005-03-28T21:29:12+02:00",
    "2005-03-28T22:40:15+02:00",
    "2005-03-29T21:59:35+02:00",
    "2005-03-29T22:07:09+02:00",
    "2005-03-30T16:25:20+02:00",
    "2005-03-30T19:03:33+02:00"
  ],
  "traces": [
    {
      "exceptionType": "org.eclipse.jface.util.Assert$AssertionFailedException",
      "message": "null argument;)",
      "elements": [
        {
          "method": "org.eclipse.swt.SWT.error",
          "source": "SWT.java:2850"
        },
        {
          "method": "org.eclipse.swt.SWT.error",
          "source": "SWT.java:2773"
        },
        {
          "method": "org.eclipse.swt.widgets.Synchronizer.runAsyncMessages",
          "source": "Synchronizer.java:121"
        },
        {
          "method": "org.eclipse.swt.widgets.Display.runAsyncMessages",
          "source": "Display.java:2981"
        },
        {
          "method": "org.eclipse.swt.widgets.Display.readAndDispatch",
          "source": "Display.java:2706"
        },
        {
          "method": "org.eclipse.jface.window.Window.runEventLoop",
          "source": "Window.java:801"
        },
        {
          "method": "org.eclipse.jface.window.Window.open",
          "source": "Window.java:779"
        },
        {
          "method": "org.eclipse.jface.dialogs.ErrorDialog.open",
          "source": "ErrorDialog.java:274"
        },
        {
          "method": "org.eclipse.ui.internal.progress.ErrorNotificationManager.openErrorDialog",
          "source": "ErrorNotificationManager.java:170"
        },
        {
          "method": "org.eclipse.ui.internal.progress.ErrorNotificationManager.access$2",
          "source": "ErrorNotificationManager.java:156"
        },
        {
          "method": "org.eclipse.ui.internal.progress.ErrorNotificationManager$2.runInUIThread",
          "source": "ErrorNotificationManager.java:130"
        },
        {
          "method": "org.eclipse.ui.progress.UIJob$1.run",
          "source": "UIJob.java:93"
        },
        {
          "method": "org.eclipse.swt.widgets.RunnableLock.run",
          "source": "RunnableLock.java:35"
        },
        {
          "method": "org.eclipse.swt.widgets.Synchronizer.runAsyncMessages",
          "source": "Synchronizer.java:118"
        },
        {
          "method": "org.eclipse.swt.widgets.Display.runAsyncMessages",
          "source": "Display.java:2981"
        },
        {
          "method": "org.eclipse.swt.widgets.Display.readAndDispatch",
          "source": "Display.java:2706"
        },
        {
          "method": "org.eclipse.ui.internal.Workbench.runEventLoop",
          "source": "Workbench.java:1538"
        },
        {
          "method": "org.eclipse.ui.internal.Workbench.runUI",
          "source": "Workbench.java:1502"
        },
        {
          "method": "org.eclipse.ui.internal.Workbench.createAndRunWorkbench",
          "source": "Workbench.java:306"
        },
        {
          "method": "org.eclipse.ui.PlatformUI.createAndRunWorkbench",
          "source": "PlatformUI.java:143"
        },
        {
          "method": "org.eclipse.ui.internal.ide.IDEApplication.run",
          "source": "IDEApplication.java:103"
        },
        {
          "method": "org.eclipse.core.internal.runtime.PlatformActivator$1.run",
          "source": "PlatformActivator.java:228"
        },
        {
          "method": "org.eclipse.core.runtime.adaptor.EclipseStarter.run",
          "source": "EclipseStarter.java:338"
        },
        {
          "method": "org.eclipse.core.runtime.adaptor.EclipseStarter.run",
          "source": "EclipseStarter.java:151"
        },
        {
          "method": "sun.reflect.NativeMethodAccessorImpl.invoke0",
          "source": "Native Method"
        },
        {
          "method": "sun.reflect.NativeMethodAccessorImpl.invoke",
          "source": "NativeMethodAccessorImpl.java:39"
        },
        {
          "method": "sun.reflect.DelegatingMethodAccessorImpl.invoke",
          "source": "DelegatingMethodAccessorImpl.java:25"
        },
        {
          "method": "java.lang.reflect.Method.invoke",
          "source": "Method.java:324"
        },
        {
          "method": "org.eclipse.core.launcher.Main.invokeFramework",
          "source": "Main.java:268"
        },
        {
          "method": "org.eclipse.core.launcher.Main.basicRun",
          "source": "Main.java:260"
        },
        {
          "method": "org.eclipse.core.launcher.Main.run",
          "source": "Main.java:887"
        },
        {
          "method": "org.eclipse.core.launcher.Main.main",
          "source": "Main.java:871"
        }
      ],
      "causedBy": {
        "exceptionType": "org.eclipse.jface.util.Assert$AssertionFailedException",
        "message": "null argument;",
        "elements": [
          {
            "method": "org.eclipse.jface.util.Assert.isNotNull",
            "source": "Assert.java:149"
          },
          {
            "method": "org.eclipse.jface.util.Assert.isNotNull",
            "source": "Assert.java:125"
          },
          {
            "method": "org.eclipse.jface.viewers.StructuredViewer.disassociate",
            "source": "StructuredViewer.java:499"
          },
          {
            "method": "org.eclipse.jface.viewers.TableViewer.internalRefreshAll",
            "source": "TableViewer.java:783"
          },
          {
            "method": "org.eclipse.jface.viewers.TableViewer.internalRefresh",
            "source": "TableViewer.java:710"
          },
          {
            "method": "org.eclipse.jface.viewers.TableViewer.internalRefresh",
            "source": "TableViewer.java:699"
          },
          {
            "method": "org.eclipse.jface.viewers.StructuredViewer$7.run",
            "source": "StructuredViewer.java:1171"
          },
          {
            "method": "org.eclipse.jface.viewers.StructuredViewer.preservingSelection",
            "source": "StructuredViewer.java:1108"
          },
          {
            "method": "org.eclipse.jface.viewers.StructuredViewer.refresh",
            "source": "StructuredViewer.java:1169"
          },
          {
            "method": "org.eclipse.jface.viewers.StructuredViewer.refresh",
            "source": "StructuredViewer.java:1128"
          },
          {
            "method": "org.eclipse.ui.views.markers.internal.TableContentProvider.resync",
            "source": "TableContentProvider.java:254"
          },
          {
            "method": "org.eclipse.ui.views.markers.internal.TableContentProvider.updateViewer",
            "source": "TableContentProvider.java:447"
          },
          {
            "method": "org.eclipse.ui.views.markers.internal.TableContentProvider.access$3",
            "source": "TableContentProvider.java:434"
          },
          {
            "method": "org.eclipse.ui.views.markers.internal.TableContentProvider$WidgetRefreshJob.runInUIThread",
            "source": "TableContentProvider.java:137"
          },
          {
            "method": "org.eclipse.ui.progress.UIJob$1.run",
            "source": "UIJob.java:93"
          },
          {
            "method": "org.eclipse.swt.widgets.RunnableLock.run",
            "source": "RunnableLock.java:35"
          },
          {
            "method": "org.eclipse.swt.widgets.Synchronizer.runAsyncMessages",
            "source": "Synchronizer.java:118"
          }
        ],
        "number": 0,
        "commentIndex": 0
      },
      "number": 0,
      "commentIndex": 1,
      "bugId": "89063",
      "date": "2005-03-24T23:07:14+01:00",
      "product": "Platform",
      "component": "SWT",
      "severity": "blocker"
    }
  ],
  "groupId": "89063",
  "bugId": "89063",
  "date": "2005-03-24T23:04:32+01:00",
  "product": "Platform",
  "component": "SWT",
  "severity": "blocker"
}