{
  "comments": [
    "I was trying to run the test suites for UI with JUnit as a detached view.  I\nclosed the view (or it became hidden somehow) half way through running the\ntests.  When I tried to show the view again I got the following error.\n\n\n!ENTRY org.eclipse.ui 4 0 2005-03-25 17:51:22.39\n!MESSAGE Argument cannot be null\n!STACK 0\njava.lang.IllegalArgumentException: Argument cannot be null\n        at org.eclipse.swt.SWT.error(SWT.java:2834)\n        at org.eclipse.swt.SWT.error(SWT.java:2773)\n        at org.eclipse.swt.SWT.error(SWT.java:2744)\n        at org.eclipse.swt.widgets.Widget.error(Widget.java:393)\n        at org.eclipse.swt.widgets.Control.setParent(Control.java:2996)\n        at org.eclipse.ui.internal.LayoutPart.reparent(LayoutPart.java:250)\n        at org.eclipse.ui.internal.PartPane.reparent(PartPane.java:481)\n        at org.eclipse.ui.internal.ViewPane.reparent(ViewPane.java:499)\n        at org.eclipse.ui.internal.PerspectiveHelper.deactivate(PerspectiveHelpe\nr.java:571)\n        at org.eclipse.ui.internal.Perspective.onDeactivate(Perspective.java:794\n)\n        at org.eclipse.ui.internal.WorkbenchPage.setPerspective(WorkbenchPage.ja\nva:2811)\n        at org.eclipse.ui.internal.WorkbenchPage.busySetPerspective(WorkbenchPag\ne.java:841)\n        at org.eclipse.ui.internal.WorkbenchPage.access$10(WorkbenchPage.java:82\n6)\n        at org.eclipse.ui.internal.WorkbenchPage$13.run(WorkbenchPage.java:2971)\n\n        at org.eclipse.swt.custom.BusyIndicator.showWhile(BusyIndicator.java:69)\n\n        at org.eclipse.ui.internal.WorkbenchPage.setPerspective(WorkbenchPage.ja\nva:2969)\n        at org.eclipse.ui.internal.PerspectiveBarContributionItem.select(Perspec\ntiveBarContributionItem.java:109)\n        at org.eclipse.ui.internal.PerspectiveBarContributionItem$1.widgetSelect\ned(PerspectiveBarContributionItem.java:81)\n        at org.eclipse.swt.widgets.TypedListener.handleEvent(TypedListener.java:\n89)\n        at org.eclipse.swt.widgets.EventTable.sendEvent(EventTable.java:82)\n        at org.eclipse.swt.widgets.Widget.sendEvent(Widget.java:842)\n        at org.eclipse.swt.widgets.Display.runDeferredEvents(Display.java:2894)\n        at org.eclipse.swt.widgets.Display.readAndDispatch(Display.java:2527)\n        at org.eclipse.ui.internal.Workbench.runEventLoop(Workbench.java:1538)\n        at org.eclipse.ui.internal.Workbench.runUI(Workbench.java:1502)\n        at org.eclipse.ui.internal.Workbench.createAndRunWorkbench(Workbench.jav\na:306)\n        at org.eclipse.ui.PlatformUI.createAndRunWorkbench(PlatformUI.java:143)\n        at org.eclipse.ui.internal.ide.IDEApplication.run(IDEApplication.java:10\n3)\n        at org.eclipse.core.internal.runtime.PlatformActivator$1.run(PlatformAct\nivator.java:228)\n        at org.eclipse.core.runtime.adaptor.EclipseStarter.run(EclipseStarter.ja\nva:338)\n        at org.eclipse.core.runtime.adaptor.EclipseStarter.run(EclipseStarter.ja\nva:151)\n        at sun.reflect.NativeMethodAccessorImpl.invoke0(Native Method)\n        at sun.reflect.NativeMethodAccessorImpl.invoke(NativeMethodAccessorImpl.\njava:39)\n        at sun.reflect.DelegatingMethodAccessorImpl.invoke(DelegatingMethodAcces\nsorImpl.java:25)\n        at java.lang.reflect.Method.invoke(Method.java:324)\n        at org.eclipse.core.launcher.Main.invokeFramework(Main.java:268)\n        at org.eclipse.core.launcher.Main.basicRun(Main.java:260)\n        at org.eclipse.core.launcher.Main.run(Main.java:887)\n        at org.eclipse.core.launcher.Main.main(Main.java:871)\nArgument cannot be null",
    "using build \nVersion: 3.1.0\nBuild id: I20050324-1400\n",
    "I wasn\u0027t able to reproduce this in 3.2 so I had a look at the code.\n\nIn 3.1 there used to be a number of paths that disposed part sash containers within the perspective helper.  In 3.2, most of those paths were modified to use setActive(false) instead, which cleaned up references but did not dispose the part sash containers (and so the parent composite isn\u0027t being set to null).\n\nI think it\u0027s safe to say it\u0027s fixed ... and we\u0027ll re-open it or create a new bug if it crops up again.\n\nPW\n"
  ],
  "commentCreationDates": [
    "2005-03-25T22:54:15+01:00",
    "2005-03-25T22:56:07+01:00",
    "2006-02-17T13:58:07+01:00"
  ],
  "traces": [
    {
      "exceptionType": "java.lang.IllegalArgumentException",
      "message": "Argument cannot be null",
      "elements": [
        {
          "method": "org.eclipse.swt.SWT.error",
          "source": "SWT.java:2834"
        },
        {
          "method": "org.eclipse.swt.SWT.error",
          "source": "SWT.java:2773"
        },
        {
          "method": "org.eclipse.swt.SWT.error",
          "source": "SWT.java:2744"
        },
        {
          "method": "org.eclipse.swt.widgets.Widget.error",
          "source": "Widget.java:393"
        },
        {
          "method": "org.eclipse.swt.widgets.Control.setParent",
          "source": "Control.java:2996"
        },
        {
          "method": "org.eclipse.ui.internal.LayoutPart.reparent",
          "source": "LayoutPart.java:250"
        },
        {
          "method": "org.eclipse.ui.internal.PartPane.reparent",
          "source": "PartPane.java:481"
        },
        {
          "method": "org.eclipse.ui.internal.ViewPane.reparent",
          "source": "ViewPane.java:499"
        },
        {
          "method": "org.eclipse.ui.internal.PerspectiveHelper.deactivate",
          "source": "PerspectiveHelpe r.java:571"
        },
        {
          "method": "org.eclipse.ui.internal.Perspective.onDeactivate",
          "source": "Perspective.java:794 "
        },
        {
          "method": "org.eclipse.ui.internal.WorkbenchPage.setPerspective",
          "source": "WorkbenchPage.ja va:2811"
        },
        {
          "method": "org.eclipse.ui.internal.WorkbenchPage.busySetPerspective",
          "source": "WorkbenchPag e.java:841"
        },
        {
          "method": "org.eclipse.ui.internal.WorkbenchPage.access$10",
          "source": "WorkbenchPage.java:82 6"
        },
        {
          "method": "org.eclipse.ui.internal.WorkbenchPage$13.run",
          "source": "WorkbenchPage.java:2971"
        },
        {
          "method": "org.eclipse.swt.custom.BusyIndicator.showWhile",
          "source": "BusyIndicator.java:69"
        },
        {
          "method": "org.eclipse.ui.internal.WorkbenchPage.setPerspective",
          "source": "WorkbenchPage.ja va:2969"
        },
        {
          "method": "org.eclipse.ui.internal.PerspectiveBarContributionItem.select",
          "source": "Perspec tiveBarContributionItem.java:109"
        },
        {
          "method": "org.eclipse.ui.internal.PerspectiveBarContributionItem$1.widgetSelected",
          "source": "PerspectiveBarContributionItem.java:81"
        },
        {
          "method": "org.eclipse.swt.widgets.TypedListener.handleEvent",
          "source": "TypedListener.java: 89"
        },
        {
          "method": "org.eclipse.swt.widgets.EventTable.sendEvent",
          "source": "EventTable.java:82"
        },
        {
          "method": "org.eclipse.swt.widgets.Widget.sendEvent",
          "source": "Widget.java:842"
        },
        {
          "method": "org.eclipse.swt.widgets.Display.runDeferredEvents",
          "source": "Display.java:2894"
        },
        {
          "method": "org.eclipse.swt.widgets.Display.readAndDispatch",
          "source": "Display.java:2527"
        },
        {
          "method": "org.eclipse.ui.internal.Workbench.runEventLoop",
          "source": "Workbench.java:1538"
        },
        {
          "method": "org.eclipse.ui.internal.Workbench.runUI",
          "source": "Workbench.java:1502"
        },
        {
          "method": "org.eclipse.ui.internal.Workbench.createAndRunWorkbench",
          "source": "Workbench.jav a:306"
        },
        {
          "method": "org.eclipse.ui.PlatformUI.createAndRunWorkbench",
          "source": "PlatformUI.java:143"
        },
        {
          "method": "org.eclipse.ui.internal.ide.IDEApplication.run",
          "source": "IDEApplication.java:10 3"
        },
        {
          "method": "org.eclipse.core.internal.runtime.PlatformActivator$1.run",
          "source": "PlatformAct ivator.java:228"
        },
        {
          "method": "org.eclipse.core.runtime.adaptor.EclipseStarter.run",
          "source": "EclipseStarter.ja va:338"
        },
        {
          "method": "org.eclipse.core.runtime.adaptor.EclipseStarter.run",
          "source": "EclipseStarter.ja va:151"
        },
        {
          "method": "sun.reflect.NativeMethodAccessorImpl.invoke0",
          "source": "Native Method"
        },
        {
          "method": "sun.reflect.NativeMethodAccessorImpl.invoke",
          "source": "NativeMethodAccessorImpl. java:39"
        },
        {
          "method": "sun.reflect.DelegatingMethodAccessorImpl.invoke",
          "source": "DelegatingMethodAcces sorImpl.java:25"
        },
        {
          "method": "java.lang.reflect.Method.invoke",
          "source": "Method.java:324"
        },
        {
          "method": "org.eclipse.core.launcher.Main.invokeFramework",
          "source": "Main.java:268"
        },
        {
          "method": "org.eclipse.core.launcher.Main.basicRun",
          "source": "Main.java:260"
        },
        {
          "method": "org.eclipse.core.launcher.Main.run",
          "source": "Main.java:887"
        },
        {
          "method": "org.eclipse.core.launcher.Main.main",
          "source": "Main.java:871"
        }
      ],
      "number": 0,
      "commentIndex": 0,
      "bugId": "89145",
      "date": "2005-03-25T22:54:15+01:00",
      "product": "Platform",
      "component": "UI",
      "severity": "normal"
    }
  ],
  "groupId": "89145",
  "bugId": "89145",
  "date": "2005-03-25T22:54:15+01:00",
  "product": "Platform",
  "component": "UI",
  "severity": "normal"
}