{
  "comments": [
    "Machine Details:\nSunOS 5.8 Generic_108528-18 sun4u sparc SUNW,Sun-Blade-100\n\nI had run my program containing SWT_AWT using JDK1.5 on the above machine using\nthe latest 3.1M5a build SWT plugin for Motif. \n\nI got the following exception.........\njava.lang.ClassNotFoundException: sun.awt.X11.XEmbeddedFrame\n        at\norg.eclipse.osgi.framework.internal.core.BundleLoader.findClass(BundleLoader.java:404)\n        at\norg.eclipse.osgi.framework.adaptor.core.AbstractClassLoader.loadClass(AbstractClassLoader.java:93)\n        at java.lang.ClassLoader.loadClass(ClassLoader.java:235)\n        at java.lang.ClassLoader.loadClassInternal(ClassLoader.java:302)\n        at java.lang.Class.forName0(Native Method)\n        at java.lang.Class.forName(Class.java:141)\n        at org.eclipse.swt.awt.SWT_AWT.new_Frame(SWT_AWT.java:117)\n        at com.cisco.maui.charts.views.LineChart.\u003cinit\u003e(LineChart.java:77)\n        at\ncom.cisco.maui.charts.views.ChartView.createPartControl(ChartView.java:104)\n        at org.eclipse.ui.internal.PartPane$2.run(PartPane.java:148)\n        at\norg.eclipse.core.internal.runtime.InternalPlatform.run(InternalPlatform.java:1044)\n        at org.eclipse.core.runtime.Platform.run(Platform.java:747)\n        at org.eclipse.ui.internal.PartPane.doCreateChildControl(PartPane.java:144)\n        at org.eclipse.ui.internal.ViewPane.doCreateChildControl(ViewPane.java:135)\n        at org.eclipse.ui.internal.PartPane.createChildControl(PartPane.java:349)\n        at org.eclipse.ui.internal.PartPane.createControl(PartPane.java:218)\n        at org.eclipse.ui.internal.ViewPane.createControl(ViewPane.java:124)\n        at org.eclipse.ui.internal.ViewFactory$1.run(ViewFactory.java:396)\n        at\norg.eclipse.core.internal.runtime.InternalPlatform.run(InternalPlatform.java:1044)\n        at org.eclipse.core.runtime.Platform.run(Platform.java:747)\n        at org.eclipse.ui.internal.ViewFactory.busyRestoreView(ViewFactory.java:287)\n        at org.eclipse.ui.internal.ViewFactory$2.run(ViewFactory.java:582)\n        at org.eclipse.swt.custom.BusyIndicator.showWhile(BusyIndicator.java:69)\n        at org.eclipse.ui.internal.ViewFactory.restoreView(ViewFactory.java:579)\n        at org.eclipse.ui.internal.Perspective.showView(Perspective.java:1705)\n        at\norg.eclipse.ui.internal.WorkbenchPage.busyShowView(WorkbenchPage.java:785)\n        at org.eclipse.ui.internal.WorkbenchPage.access$8(WorkbenchPage.java:768)\n        at org.eclipse.ui.internal.WorkbenchPage$12.run(WorkbenchPage.java:3027)\n        at org.eclipse.swt.custom.BusyIndicator.showWhile(BusyIndicator.java:69)\n        at org.eclipse.ui.internal.WorkbenchPage.showView(WorkbenchPage.java:3024)\n        at org.eclipse.ui.internal.WorkbenchPage.showView(WorkbenchPage.java:3003)\n        at org.eclipse.ui.internal.ShowViewMenu.showOther(ShowViewMenu.java:213)\n        at org.eclipse.ui.internal.ShowViewMenu$2.run(ShowViewMenu.java:72)\n        at org.eclipse.jface.action.Action.runWithEvent(Action.java:989)\n        at\norg.eclipse.jface.action.ActionContributionItem.handleWidgetSelection(ActionContributionItem.java:555)\n        at\norg.eclipse.jface.action.ActionContributionItem.access$2(ActionContributionItem.java:505)\n        at\norg.eclipse.jface.action.ActionContributionItem$6.handleEvent(ActionContributionItem.java:419)\n        at org.eclipse.swt.widgets.EventTable.sendEvent(EventTable.java:82)\n        at org.eclipse.swt.widgets.Widget.sendEvent(Widget.java:740)\n        at org.eclipse.swt.widgets.Display.runDeferredEvents(Display.java:2960)\n        at org.eclipse.swt.widgets.Display.readAndDispatch(Display.java:2660)\n        at org.eclipse.ui.internal.Workbench.runEventLoop(Workbench.java:1569)\n        at org.eclipse.ui.internal.Workbench.runUI(Workbench.java:1540)\n        at\norg.eclipse.ui.internal.Workbench.createAndRunWorkbench(Workbench.java:285)\n        at org.eclipse.ui.PlatformUI.createAndRunWorkbench(PlatformUI.java:144)\n        at com.cisco.nm.aura.AuraApplication.run(AuraApplication.java:32)\n        at\norg.eclipse.core.internal.runtime.PlatformActivator$1.run(PlatformActivator.java:220)\n        at\norg.eclipse.core.runtime.adaptor.EclipseStarter.run(EclipseStarter.java:273)\n        at\norg.eclipse.core.runtime.adaptor.EclipseStarter.run(EclipseStarter.java:129)\n        at sun.reflect.NativeMethodAccessorImpl.invoke0(Native Method)\n        at\nsun.reflect.NativeMethodAccessorImpl.invoke(NativeMethodAccessorImpl.java:39)\n        at\nsun.reflect.DelegatingMethodAccessorImpl.invoke(DelegatingMethodAccessorImpl.java:25)\n        at java.lang.reflect.Method.invoke(Method.java:324)\n        at org.eclipse.core.launcher.Main.basicRun(Main.java:185)\n        at org.eclipse.core.launcher.Main.run(Main.java:710)\n        at org.eclipse.core.launcher.Main.main(Main.java:694)\nsun.awt.X11.XEmbeddedFrame\n\n\nBug 68353 was closed saying SWT_AWT will work on solaris with JDK1.5.\n\nBut still i\u0027m getting the above exception...\n\nPlease do the needful\n\nThanks\nRamakrishnan",
    "SWT_AWT will only work with X11Toolkit. The default toolkit on Solaris 1.5.0 \nis MToolkit. You need to change the default toolkit. Here is a site that shows \nhow you do this.\n\nhttp://java.sun.com/j2se/1.5.0/docs/guide/awt/1.5/xawt.html"
  ],
  "commentCreationDates": [
    "2005-03-28T15:20:00+02:00",
    "2005-03-30T16:35:33+02:00"
  ],
  "traces": [
    {
      "exceptionType": "java.lang.ClassNotFoundException",
      "message": "sun.awt.X11.XEmbeddedFrame",
      "elements": [
        {
          "method": "org.eclipse.osgi.framework.internal.core.BundleLoader.findClass",
          "source": "BundleLoader.java:404"
        },
        {
          "method": "org.eclipse.osgi.framework.adaptor.core.AbstractClassLoader.loadClass",
          "source": "AbstractClassLoader.java:93"
        },
        {
          "method": "java.lang.ClassLoader.loadClass",
          "source": "ClassLoader.java:235"
        },
        {
          "method": "java.lang.ClassLoader.loadClassInternal",
          "source": "ClassLoader.java:302"
        },
        {
          "method": "java.lang.Class.forName0",
          "source": "Native Method"
        },
        {
          "method": "java.lang.Class.forName",
          "source": "Class.java:141"
        },
        {
          "method": "org.eclipse.swt.awt.SWT_AWT.new_Frame",
          "source": "SWT_AWT.java:117"
        },
        {
          "method": "com.cisco.maui.charts.views.LineChart.\u003cinit\u003e",
          "source": "LineChart.java:77"
        },
        {
          "method": "com.cisco.maui.charts.views.ChartView.createPartControl",
          "source": "ChartView.java:104"
        },
        {
          "method": "org.eclipse.ui.internal.PartPane$2.run",
          "source": "PartPane.java:148"
        },
        {
          "method": "org.eclipse.core.internal.runtime.InternalPlatform.run",
          "source": "InternalPlatform.java:1044"
        },
        {
          "method": "org.eclipse.core.runtime.Platform.run",
          "source": "Platform.java:747"
        },
        {
          "method": "org.eclipse.ui.internal.PartPane.doCreateChildControl",
          "source": "PartPane.java:144"
        },
        {
          "method": "org.eclipse.ui.internal.ViewPane.doCreateChildControl",
          "source": "ViewPane.java:135"
        },
        {
          "method": "org.eclipse.ui.internal.PartPane.createChildControl",
          "source": "PartPane.java:349"
        },
        {
          "method": "org.eclipse.ui.internal.PartPane.createControl",
          "source": "PartPane.java:218"
        },
        {
          "method": "org.eclipse.ui.internal.ViewPane.createControl",
          "source": "ViewPane.java:124"
        },
        {
          "method": "org.eclipse.ui.internal.ViewFactory$1.run",
          "source": "ViewFactory.java:396"
        },
        {
          "method": "org.eclipse.core.internal.runtime.InternalPlatform.run",
          "source": "InternalPlatform.java:1044"
        },
        {
          "method": "org.eclipse.core.runtime.Platform.run",
          "source": "Platform.java:747"
        },
        {
          "method": "org.eclipse.ui.internal.ViewFactory.busyRestoreView",
          "source": "ViewFactory.java:287"
        },
        {
          "method": "org.eclipse.ui.internal.ViewFactory$2.run",
          "source": "ViewFactory.java:582"
        },
        {
          "method": "org.eclipse.swt.custom.BusyIndicator.showWhile",
          "source": "BusyIndicator.java:69"
        },
        {
          "method": "org.eclipse.ui.internal.ViewFactory.restoreView",
          "source": "ViewFactory.java:579"
        },
        {
          "method": "org.eclipse.ui.internal.Perspective.showView",
          "source": "Perspective.java:1705"
        },
        {
          "method": "org.eclipse.ui.internal.WorkbenchPage.busyShowView",
          "source": "WorkbenchPage.java:785"
        },
        {
          "method": "org.eclipse.ui.internal.WorkbenchPage.access$8",
          "source": "WorkbenchPage.java:768"
        },
        {
          "method": "org.eclipse.ui.internal.WorkbenchPage$12.run",
          "source": "WorkbenchPage.java:3027"
        },
        {
          "method": "org.eclipse.swt.custom.BusyIndicator.showWhile",
          "source": "BusyIndicator.java:69"
        },
        {
          "method": "org.eclipse.ui.internal.WorkbenchPage.showView",
          "source": "WorkbenchPage.java:3024"
        },
        {
          "method": "org.eclipse.ui.internal.WorkbenchPage.showView",
          "source": "WorkbenchPage.java:3003"
        },
        {
          "method": "org.eclipse.ui.internal.ShowViewMenu.showOther",
          "source": "ShowViewMenu.java:213"
        },
        {
          "method": "org.eclipse.ui.internal.ShowViewMenu$2.run",
          "source": "ShowViewMenu.java:72"
        },
        {
          "method": "org.eclipse.jface.action.Action.runWithEvent",
          "source": "Action.java:989"
        },
        {
          "method": "org.eclipse.jface.action.ActionContributionItem.handleWidgetSelection",
          "source": "ActionContributionItem.java:555"
        },
        {
          "method": "org.eclipse.jface.action.ActionContributionItem.access$2",
          "source": "ActionContributionItem.java:505"
        },
        {
          "method": "org.eclipse.jface.action.ActionContributionItem$6.handleEvent",
          "source": "ActionContributionItem.java:419"
        },
        {
          "method": "org.eclipse.swt.widgets.EventTable.sendEvent",
          "source": "EventTable.java:82"
        },
        {
          "method": "org.eclipse.swt.widgets.Widget.sendEvent",
          "source": "Widget.java:740"
        },
        {
          "method": "org.eclipse.swt.widgets.Display.runDeferredEvents",
          "source": "Display.java:2960"
        },
        {
          "method": "org.eclipse.swt.widgets.Display.readAndDispatch",
          "source": "Display.java:2660"
        },
        {
          "method": "org.eclipse.ui.internal.Workbench.runEventLoop",
          "source": "Workbench.java:1569"
        },
        {
          "method": "org.eclipse.ui.internal.Workbench.runUI",
          "source": "Workbench.java:1540"
        },
        {
          "method": "org.eclipse.ui.internal.Workbench.createAndRunWorkbench",
          "source": "Workbench.java:285"
        },
        {
          "method": "org.eclipse.ui.PlatformUI.createAndRunWorkbench",
          "source": "PlatformUI.java:144"
        },
        {
          "method": "com.cisco.nm.aura.AuraApplication.run",
          "source": "AuraApplication.java:32"
        },
        {
          "method": "org.eclipse.core.internal.runtime.PlatformActivator$1.run",
          "source": "PlatformActivator.java:220"
        },
        {
          "method": "org.eclipse.core.runtime.adaptor.EclipseStarter.run",
          "source": "EclipseStarter.java:273"
        },
        {
          "method": "org.eclipse.core.runtime.adaptor.EclipseStarter.run",
          "source": "EclipseStarter.java:129"
        },
        {
          "method": "sun.reflect.NativeMethodAccessorImpl.invoke0",
          "source": "Native Method"
        },
        {
          "method": "sun.reflect.NativeMethodAccessorImpl.invoke",
          "source": "NativeMethodAccessorImpl.java:39"
        },
        {
          "method": "sun.reflect.DelegatingMethodAccessorImpl.invoke",
          "source": "DelegatingMethodAccessorImpl.java:25"
        },
        {
          "method": "java.lang.reflect.Method.invoke",
          "source": "Method.java:324"
        },
        {
          "method": "org.eclipse.core.launcher.Main.basicRun",
          "source": "Main.java:185"
        },
        {
          "method": "org.eclipse.core.launcher.Main.run",
          "source": "Main.java:710"
        },
        {
          "method": "org.eclipse.core.launcher.Main.main",
          "source": "Main.java:694"
        }
      ],
      "number": 0,
      "commentIndex": 0,
      "bugId": "89216",
      "date": "2005-03-28T15:20:00+02:00",
      "product": "Platform",
      "component": "SWT",
      "severity": "normal"
    }
  ],
  "groupId": "89216",
  "bugId": "89216",
  "date": "2005-03-28T15:20:00+02:00",
  "product": "Platform",
  "component": "SWT",
  "severity": "normal"
}