{
  "comments": [
    "Hello.\nFollowing error i receive at some starts of eclipse.\nIt\u0027s not at every start, just at all 3th to 5th start.\nI use 20020129, but the problem exists since 20020122 or earlier.\n\n/usr/local/eclipse-gtk/eclipse -ws gtk -debug -data $HOME/ -vm\n/usr/lib/jreb/bin/java\n\n\nBoot URL:\n    file:/usr/local/eclipse-gtk/plugins/org.eclipse.core.boot/boot.jar\nInstall URL: file:/usr/local/eclipse-gtk/\nDebug-Options: file:/usr/local/eclipse-gtk/.options\nRead registry cache: 307ms\nOS: linux WS: gtk NL: de_DE ARCH: i386\norg.eclipse.swt.SWTError: Unspecified error\n        at org.eclipse.swt.SWT.error(SWT.java:1912)\n        at org.eclipse.swt.SWT.error(SWT.java:1819)\n        at\norg.eclipse.swt.graphics.DefaultGtkStyle.loadDefaultFont(DefaultGtkStyle.java:97)\n        at org.eclipse.swt.graphics.GC.\u003cinit\u003e(GC.java:83)\n        at org.eclipse.swt.custom.CTabFolder.updateArrowBar(CTabFolder.java:1352)\n        at org.eclipse.swt.custom.CTabFolder.layoutButtons(CTabFolder.java:669)\n        at org.eclipse.swt.custom.CTabFolder.layoutItems(CTabFolder.java:798)\n        at org.eclipse.swt.custom.CTabItem.setText(CTabItem.java:410)\n        at\norg.eclipse.ui.internal.EditorWorkbook.updateEditorTab(EditorWorkbook.java:755)\n        at org.eclipse.ui.internal.EditorWorkbook.createTab(EditorWorkbook.java:241)\n        at org.eclipse.ui.internal.EditorWorkbook.createTab(EditorWorkbook.java:231)\n        at\norg.eclipse.ui.internal.EditorWorkbook.createPage(EditorWorkbook.java:213)\n        at\norg.eclipse.ui.internal.EditorWorkbook.createControl(EditorWorkbook.java:179)\n        at\norg.eclipse.ui.internal.PartSashContainer.createControl(PartSashContainer.java:172)\n        at\norg.eclipse.ui.internal.PartSashContainer.createControl(PartSashContainer.java:172)\n        at\norg.eclipse.ui.internal.PerspectivePresentation.activate(PerspectivePresentation.java:80)\n        at org.eclipse.ui.internal.Perspective.onActivate(Perspective.java:511)\n        at org.eclipse.ui.internal.WorkbenchPage.onActivate(WorkbenchPage.java:1030)\n        at org.eclipse.ui.internal.WorkbenchWindow$5.run(WorkbenchWindow.java:893)\n        at org.eclipse.swt.custom.BusyIndicator.showWhile(BusyIndicator.java:56)\n       at\norg.eclipse.ui.internal.WorkbenchWindow.setActivePage(WorkbenchWindow.java:881)\n        at\norg.eclipse.ui.internal.WorkbenchWindow.restoreState(WorkbenchWindow.java:794)\n        at org.eclipse.ui.internal.Workbench.restoreState(Workbench.java:811)\n        at org.eclipse.ui.internal.Workbench$5.run(Workbench.java:557)\n        at\norg.eclipse.core.internal.runtime.InternalPlatform.run(InternalPlatform.java:832)\n        at org.eclipse.core.runtime.Platform.run(Platform.java:395)\n        at\norg.eclipse.ui.internal.Workbench.openPreviousWorkbenchState(Workbench.java:541)\n        at org.eclipse.ui.internal.Workbench.openWindows(Workbench.java:598)\n        at org.eclipse.ui.internal.Workbench.init(Workbench.java:441)\n        at org.eclipse.ui.internal.Workbench.run(Workbench.java:831)\n        at\norg.eclipse.core.internal.boot.InternalBootLoader.run(InternalBootLoader.java:895)\n        at org.eclipse.core.boot.BootLoader.run(BootLoader.java:321)\n        at sun.reflect.NativeMethodAccessorImpl.invoke0(Native Method)\n        at\nsun.reflect.NativeMethodAccessorImpl.invoke(NativeMethodAccessorImpl.java:39)\n        at\nsun.reflect.DelegatingMethodAccessorImpl.invoke(DelegatingMethodAccessorImpl.java:25)\n        at java.lang.reflect.Method.invoke(Method.java:324)\n        at org.eclipse.core.launcher.Main.basicRun(Main.java:151)\n        at org.eclipse.core.launcher.Main.run(Main.java:502)\n        at org.eclipse.core.launcher.Main.main(Main.java:362)\nWrote registry: 216ms",
    "Perhaps related to problems in Bug 8785? Reserving comment until Bug 8785 is \nresolved.\n",
    "Bug 8785 has been fixed. \n\nPlease confirm that this is still a problem in integration build 2002-02-05.\n",
    "Created an attachment (id\u003d307)\nlog with the messages at start\n",
    "Created an attachment (id\u003d308)\nlogfile with debug-options\n",
    "The problem exists also with 20020205.\nI have append two logfiles from eclipse-start.\nThe first (debug-1.20020205) is with debug-option debug\u003dtrue\n\nThe second (debug-2.20020205) is with debug-options\nloader/debug\u003dtrue\nloader/debug/actions\u003dtrue\nloader/debug/failure\u003dtrue\n\nSorry, in the second logfile just the end of the startmessages, but my \nconsole-buffer is too short for all messages.\n\nI can\u0027t say, when i become the problem and when start eclipse without \nproblem.\nexample: \ni start 5 times, 5 times with error\ni start 3 times, 3 times without error\ni start 4 times, 2 times with error, 2 without ",
    "Finding the library has been fixed in 20020205 (see related Bug 8785). \nUser is still getting this SWTError though.\nMoving to Platform/SWT for comment.\n",
    "The problem is still exists in 200200215",
    "The way fonts work in SWT on GTK1.2, is temporary, and is being rewritten for \n2.0 (yes, Pango).  This means bugs like this will be fixed in the 2.0 branch - \nit\u0027s just not worth writing more temporary code.",
    "Post 2.0. Re-opening bug reports for review.",
    "The whole gtk2 branch is free of this bug by design."
  ],
  "commentCreationDates": [
    "2002-02-01T16:52:39+01:00",
    "2002-02-01T19:12:27+01:00",
    "2002-02-05T15:08:41+01:00",
    "2002-02-05T23:22:03+01:00",
    "2002-02-05T23:22:36+01:00",
    "2002-02-05T23:29:14+01:00",
    "2002-02-05T23:31:55+01:00",
    "2002-02-20T14:08:06+01:00",
    "2002-02-27T23:34:23+01:00",
    "2002-09-10T16:25:24+02:00",
    "2002-09-10T19:27:13+02:00"
  ],
  "traces": [
    {
      "exceptionType": "org.eclipse.swt.SWTError",
      "message": "Unspecified error",
      "elements": [
        {
          "method": "org.eclipse.swt.SWT.error",
          "source": "SWT.java:1912"
        },
        {
          "method": "org.eclipse.swt.SWT.error",
          "source": "SWT.java:1819"
        },
        {
          "method": "org.eclipse.swt.graphics.DefaultGtkStyle.loadDefaultFont",
          "source": "DefaultGtkStyle.java:97"
        },
        {
          "method": "org.eclipse.swt.graphics.GC.\u003cinit\u003e",
          "source": "GC.java:83"
        },
        {
          "method": "org.eclipse.swt.custom.CTabFolder.updateArrowBar",
          "source": "CTabFolder.java:1352"
        },
        {
          "method": "org.eclipse.swt.custom.CTabFolder.layoutButtons",
          "source": "CTabFolder.java:669"
        },
        {
          "method": "org.eclipse.swt.custom.CTabFolder.layoutItems",
          "source": "CTabFolder.java:798"
        },
        {
          "method": "org.eclipse.swt.custom.CTabItem.setText",
          "source": "CTabItem.java:410"
        },
        {
          "method": "org.eclipse.ui.internal.EditorWorkbook.updateEditorTab",
          "source": "EditorWorkbook.java:755"
        },
        {
          "method": "org.eclipse.ui.internal.EditorWorkbook.createTab",
          "source": "EditorWorkbook.java:241"
        },
        {
          "method": "org.eclipse.ui.internal.EditorWorkbook.createTab",
          "source": "EditorWorkbook.java:231"
        },
        {
          "method": "org.eclipse.ui.internal.EditorWorkbook.createPage",
          "source": "EditorWorkbook.java:213"
        },
        {
          "method": "org.eclipse.ui.internal.EditorWorkbook.createControl",
          "source": "EditorWorkbook.java:179"
        },
        {
          "method": "org.eclipse.ui.internal.PartSashContainer.createControl",
          "source": "PartSashContainer.java:172"
        },
        {
          "method": "org.eclipse.ui.internal.PartSashContainer.createControl",
          "source": "PartSashContainer.java:172"
        },
        {
          "method": "org.eclipse.ui.internal.PerspectivePresentation.activate",
          "source": "PerspectivePresentation.java:80"
        },
        {
          "method": "org.eclipse.ui.internal.Perspective.onActivate",
          "source": "Perspective.java:511"
        },
        {
          "method": "org.eclipse.ui.internal.WorkbenchPage.onActivate",
          "source": "WorkbenchPage.java:1030"
        },
        {
          "method": "org.eclipse.ui.internal.WorkbenchWindow$5.run",
          "source": "WorkbenchWindow.java:893"
        },
        {
          "method": "org.eclipse.swt.custom.BusyIndicator.showWhile",
          "source": "BusyIndicator.java:56"
        },
        {
          "method": "org.eclipse.ui.internal.WorkbenchWindow.setActivePage",
          "source": "WorkbenchWindow.java:881"
        },
        {
          "method": "org.eclipse.ui.internal.WorkbenchWindow.restoreState",
          "source": "WorkbenchWindow.java:794"
        },
        {
          "method": "org.eclipse.ui.internal.Workbench.restoreState",
          "source": "Workbench.java:811"
        },
        {
          "method": "org.eclipse.ui.internal.Workbench$5.run",
          "source": "Workbench.java:557"
        },
        {
          "method": "org.eclipse.core.internal.runtime.InternalPlatform.run",
          "source": "InternalPlatform.java:832"
        },
        {
          "method": "org.eclipse.core.runtime.Platform.run",
          "source": "Platform.java:395"
        },
        {
          "method": "org.eclipse.ui.internal.Workbench.openPreviousWorkbenchState",
          "source": "Workbench.java:541"
        },
        {
          "method": "org.eclipse.ui.internal.Workbench.openWindows",
          "source": "Workbench.java:598"
        },
        {
          "method": "org.eclipse.ui.internal.Workbench.init",
          "source": "Workbench.java:441"
        },
        {
          "method": "org.eclipse.ui.internal.Workbench.run",
          "source": "Workbench.java:831"
        },
        {
          "method": "org.eclipse.core.internal.boot.InternalBootLoader.run",
          "source": "InternalBootLoader.java:895"
        },
        {
          "method": "org.eclipse.core.boot.BootLoader.run",
          "source": "BootLoader.java:321"
        },
        {
          "method": "sun.reflect.NativeMethodAccessorImpl.invoke0",
          "source": "Native Method"
        },
        {
          "method": "sun.reflect.NativeMethodAccessorImpl.invoke",
          "source": "NativeMethodAccessorImpl.java:39"
        },
        {
          "method": "sun.reflect.DelegatingMethodAccessorImpl.invoke",
          "source": "DelegatingMethodAccessorImpl.java:25"
        },
        {
          "method": "java.lang.reflect.Method.invoke",
          "source": "Method.java:324"
        },
        {
          "method": "org.eclipse.core.launcher.Main.basicRun",
          "source": "Main.java:151"
        },
        {
          "method": "org.eclipse.core.launcher.Main.run",
          "source": "Main.java:502"
        },
        {
          "method": "org.eclipse.core.launcher.Main.main",
          "source": "Main.java:362"
        }
      ],
      "number": 0,
      "commentIndex": 0,
      "bugId": "8933",
      "date": "2002-02-01T16:52:39+01:00",
      "product": "Platform",
      "component": "SWT",
      "severity": "normal"
    }
  ],
  "groupId": "8933",
  "bugId": "8933",
  "date": "2002-02-01T16:52:39+01:00",
  "product": "Platform",
  "component": "SWT",
  "severity": "normal"
}