{
  "comments": [
    "I20050329-0010\n\n- Enable preference Team \u003e CVS \u003e Refresh tags when comparing ...\n- From a CVS project\u0027s context menu, choose Compare With \u003e Another Branch or\nVersion...\n- Before the \"Refereshing Tags...\" message disappears, press the Cancel button\n\norg.eclipse.swt.SWTException: Widget is disposed\n        at org.eclipse.swt.SWT.error(SWT.java:2860)\n        at org.eclipse.swt.SWT.error(SWT.java:2783)\n        at org.eclipse.swt.SWT.error(SWT.java:2754)\n        at org.eclipse.swt.widgets.Widget.error(Widget.java:393)\n        at org.eclipse.swt.widgets.Widget.checkWidget(Widget.java:295)\n        at org.eclipse.swt.widgets.Control.setCursor(Control.java:2047)\n        at\norg.eclipse.team.internal.ccvs.ui.tags.TagSelectionDialog$6.run(TagSelectionDialog.java:314)\n        at org.eclipse.swt.widgets.RunnableLock.run(RunnableLock.java:35)\n        at\norg.eclipse.swt.widgets.Synchronizer.runAsyncMessages(Synchronizer.java:118)\n        at org.eclipse.swt.widgets.Display.runAsyncMessages(Display.java:2871)\n        at org.eclipse.swt.widgets.Display.readAndDispatch(Display.java:2530)\n        at org.eclipse.ui.internal.Workbench.runEventLoop(Workbench.java:1570)\n        at org.eclipse.ui.internal.Workbench.runUI(Workbench.java:1534)\n        at\norg.eclipse.ui.internal.Workbench.createAndRunWorkbench(Workbench.java:306)\n        at org.eclipse.ui.PlatformUI.createAndRunWorkbench(PlatformUI.java:143)\n        at org.eclipse.ui.internal.ide.IDEApplication.run(IDEApplication.java:103)\n        at\norg.eclipse.core.internal.runtime.PlatformActivator$1.run(PlatformActivator.java:228)\n        at\norg.eclipse.core.runtime.adaptor.EclipseStarter.run(EclipseStarter.java:338)\n        at\norg.eclipse.core.runtime.adaptor.EclipseStarter.run(EclipseStarter.java:151)\n        at sun.reflect.NativeMethodAccessorImpl.invoke0(Native Method)\n        at\nsun.reflect.NativeMethodAccessorImpl.invoke(NativeMethodAccessorImpl.java:39)\n        at\nsun.reflect.DelegatingMethodAccessorImpl.invoke(DelegatingMethodAccessorImpl.java:25)\n        at java.lang.reflect.Method.invoke(Method.java:585)\n        at org.eclipse.core.launcher.Main.invokeFramework(Main.java:268)\n        at org.eclipse.core.launcher.Main.basicRun(Main.java:260)\n        at org.eclipse.core.launcher.Main.run(Main.java:887)\n        at org.eclipse.core.launcher.Main.main(Main.java:871)",
    "Fix released to HEAD. It\u0027s safe enough to put into M6 if we decide to but I\u0027l \nmark it M7 for now.",
    "Verified"
  ],
  "commentCreationDates": [
    "2005-03-30T08:03:21+02:00",
    "2005-03-30T16:01:50+02:00",
    "2005-05-10T16:33:45+02:00"
  ],
  "traces": [
    {
      "exceptionType": "org.eclipse.swt.SWTException",
      "message": "Widget is disposed",
      "elements": [
        {
          "method": "org.eclipse.swt.SWT.error",
          "source": "SWT.java:2860"
        },
        {
          "method": "org.eclipse.swt.SWT.error",
          "source": "SWT.java:2783"
        },
        {
          "method": "org.eclipse.swt.SWT.error",
          "source": "SWT.java:2754"
        },
        {
          "method": "org.eclipse.swt.widgets.Widget.error",
          "source": "Widget.java:393"
        },
        {
          "method": "org.eclipse.swt.widgets.Widget.checkWidget",
          "source": "Widget.java:295"
        },
        {
          "method": "org.eclipse.swt.widgets.Control.setCursor",
          "source": "Control.java:2047"
        },
        {
          "method": "org.eclipse.team.internal.ccvs.ui.tags.TagSelectionDialog$6.run",
          "source": "TagSelectionDialog.java:314"
        },
        {
          "method": "org.eclipse.swt.widgets.RunnableLock.run",
          "source": "RunnableLock.java:35"
        },
        {
          "method": "org.eclipse.swt.widgets.Synchronizer.runAsyncMessages",
          "source": "Synchronizer.java:118"
        },
        {
          "method": "org.eclipse.swt.widgets.Display.runAsyncMessages",
          "source": "Display.java:2871"
        },
        {
          "method": "org.eclipse.swt.widgets.Display.readAndDispatch",
          "source": "Display.java:2530"
        },
        {
          "method": "org.eclipse.ui.internal.Workbench.runEventLoop",
          "source": "Workbench.java:1570"
        },
        {
          "method": "org.eclipse.ui.internal.Workbench.runUI",
          "source": "Workbench.java:1534"
        },
        {
          "method": "org.eclipse.ui.internal.Workbench.createAndRunWorkbench",
          "source": "Workbench.java:306"
        },
        {
          "method": "org.eclipse.ui.PlatformUI.createAndRunWorkbench",
          "source": "PlatformUI.java:143"
        },
        {
          "method": "org.eclipse.ui.internal.ide.IDEApplication.run",
          "source": "IDEApplication.java:103"
        },
        {
          "method": "org.eclipse.core.internal.runtime.PlatformActivator$1.run",
          "source": "PlatformActivator.java:228"
        },
        {
          "method": "org.eclipse.core.runtime.adaptor.EclipseStarter.run",
          "source": "EclipseStarter.java:338"
        },
        {
          "method": "org.eclipse.core.runtime.adaptor.EclipseStarter.run",
          "source": "EclipseStarter.java:151"
        },
        {
          "method": "sun.reflect.NativeMethodAccessorImpl.invoke0",
          "source": "Native Method"
        },
        {
          "method": "sun.reflect.NativeMethodAccessorImpl.invoke",
          "source": "NativeMethodAccessorImpl.java:39"
        },
        {
          "method": "sun.reflect.DelegatingMethodAccessorImpl.invoke",
          "source": "DelegatingMethodAccessorImpl.java:25"
        },
        {
          "method": "java.lang.reflect.Method.invoke",
          "source": "Method.java:585"
        },
        {
          "method": "org.eclipse.core.launcher.Main.invokeFramework",
          "source": "Main.java:268"
        },
        {
          "method": "org.eclipse.core.launcher.Main.basicRun",
          "source": "Main.java:260"
        },
        {
          "method": "org.eclipse.core.launcher.Main.run",
          "source": "Main.java:887"
        },
        {
          "method": "org.eclipse.core.launcher.Main.main",
          "source": "Main.java:871"
        }
      ],
      "number": 0,
      "commentIndex": 0,
      "bugId": "89462",
      "date": "2005-03-30T08:03:21+02:00",
      "product": "Platform",
      "component": "CVS",
      "severity": "minor"
    }
  ],
  "groupId": "89462",
  "bugId": "89462",
  "date": "2005-03-30T08:03:21+02:00",
  "product": "Platform",
  "component": "CVS",
  "severity": "minor"
}