{
  "comments": [
    "I20050329-2000\n\nI found this in the console (was not in the log; I\u0027ll file a bug for jdt.text\nthat this should be logged). I was experimenting with 1.5 code when this\nhappened. Sorry, no steps to reproduce.\n\nException in thread \"Text Viewer Hover Presenter\" java.lang.ArrayStoreException\n        at java.lang.System.arraycopy(Native Method)\n        at\norg.eclipse.jdt.internal.codeassist.SelectionEngine.acceptType(SelectionEngine.java:211)\n        at\norg.eclipse.jdt.internal.core.SearchableEnvironment$2.acceptType(SearchableEnvironment.java:276)\n        at\norg.eclipse.jdt.internal.core.search.BasicSearchEngine$1.acceptIndexMatch(BasicSearchEngine.java:524)\n        at\norg.eclipse.jdt.internal.core.search.matching.InternalSearchPattern.acceptMatch(InternalSearchPattern.java:44)\n        at\norg.eclipse.jdt.internal.core.search.matching.InternalSearchPattern.findIndexMatches(InternalSearchPattern.java:75)\n        at\norg.eclipse.jdt.internal.core.search.matching.MatchLocator.findIndexMatches(MatchLocator.java:308)\n        at\norg.eclipse.jdt.internal.core.search.PatternSearchJob.search(PatternSearchJob.java:111)\n        at\norg.eclipse.jdt.internal.core.search.PatternSearchJob.execute(PatternSearchJob.java:64)\n        at\norg.eclipse.jdt.internal.core.search.processing.JobManager.performConcurrentJob(JobManager.java:260)\n        at\norg.eclipse.jdt.internal.core.search.BasicSearchEngine.searchAllTypeNames(BasicSearchEngine.java:535)\n        at\norg.eclipse.jdt.internal.core.SearchableEnvironment.findTypes(SearchableEnvironment.java:280)\n        at\norg.eclipse.jdt.internal.codeassist.SelectionEngine.select(SelectionEngine.java:670)\n        at org.eclipse.jdt.internal.core.Openable.codeSelect(Openable.java:140)\n        at\norg.eclipse.jdt.internal.core.CompilationUnit.codeSelect(CompilationUnit.java:313)\n        at\norg.eclipse.jdt.internal.core.CompilationUnit.codeSelect(CompilationUnit.java:307)\n        at\norg.eclipse.jdt.internal.ui.text.java.hover.AbstractJavaEditorTextHover.getHoverInfo(AbstractJavaEditorTextHover.java:108)\n        at\norg.eclipse.jdt.internal.ui.text.java.hover.BestMatchHover.getHoverInfo(BestMatchHover.java:102)\n        at\norg.eclipse.jdt.internal.ui.text.java.hover.JavaEditorTextHoverProxy.getHoverInfo(JavaEditorTextHoverProxy.java:69)\n        at\norg.eclipse.jface.text.TextViewerHoverManager$4.run(TextViewerHoverManager.java:160)",
    "Fixed\n\nThe line 211 of SelectionEngine must be\n\nSystem.arraycopy(this.acceptedClassesModifiers, 0, this.acceptedClassesModifiers\n\u003d new int[newLength], 0, length);\n\ninstead of\n\nSystem.arraycopy(this.acceptedClasses, 0, this.acceptedClassesModifiers \u003d new\nint[newLength], 0, length);",
    "Verified in I20050331-0800"
  ],
  "commentCreationDates": [
    "2005-03-30T10:08:33+02:00",
    "2005-03-30T11:14:43+02:00",
    "2005-03-31T18:17:38+02:00"
  ],
  "traces": [
    {
      "exceptionType": "java.lang.ArrayStoreException",
      "elements": [
        {
          "method": "java.lang.System.arraycopy",
          "source": "Native Method"
        },
        {
          "method": "org.eclipse.jdt.internal.codeassist.SelectionEngine.acceptType",
          "source": "SelectionEngine.java:211"
        },
        {
          "method": "org.eclipse.jdt.internal.core.SearchableEnvironment$2.acceptType",
          "source": "SearchableEnvironment.java:276"
        },
        {
          "method": "org.eclipse.jdt.internal.core.search.BasicSearchEngine$1.acceptIndexMatch",
          "source": "BasicSearchEngine.java:524"
        },
        {
          "method": "org.eclipse.jdt.internal.core.search.matching.InternalSearchPattern.acceptMatch",
          "source": "InternalSearchPattern.java:44"
        },
        {
          "method": "org.eclipse.jdt.internal.core.search.matching.InternalSearchPattern.findIndexMatches",
          "source": "InternalSearchPattern.java:75"
        },
        {
          "method": "org.eclipse.jdt.internal.core.search.matching.MatchLocator.findIndexMatches",
          "source": "MatchLocator.java:308"
        },
        {
          "method": "org.eclipse.jdt.internal.core.search.PatternSearchJob.search",
          "source": "PatternSearchJob.java:111"
        },
        {
          "method": "org.eclipse.jdt.internal.core.search.PatternSearchJob.execute",
          "source": "PatternSearchJob.java:64"
        },
        {
          "method": "org.eclipse.jdt.internal.core.search.processing.JobManager.performConcurrentJob",
          "source": "JobManager.java:260"
        },
        {
          "method": "org.eclipse.jdt.internal.core.search.BasicSearchEngine.searchAllTypeNames",
          "source": "BasicSearchEngine.java:535"
        },
        {
          "method": "org.eclipse.jdt.internal.core.SearchableEnvironment.findTypes",
          "source": "SearchableEnvironment.java:280"
        },
        {
          "method": "org.eclipse.jdt.internal.codeassist.SelectionEngine.select",
          "source": "SelectionEngine.java:670"
        },
        {
          "method": "org.eclipse.jdt.internal.core.Openable.codeSelect",
          "source": "Openable.java:140"
        },
        {
          "method": "org.eclipse.jdt.internal.core.CompilationUnit.codeSelect",
          "source": "CompilationUnit.java:313"
        },
        {
          "method": "org.eclipse.jdt.internal.core.CompilationUnit.codeSelect",
          "source": "CompilationUnit.java:307"
        },
        {
          "method": "org.eclipse.jdt.internal.ui.text.java.hover.AbstractJavaEditorTextHover.getHoverInfo",
          "source": "AbstractJavaEditorTextHover.java:108"
        },
        {
          "method": "org.eclipse.jdt.internal.ui.text.java.hover.BestMatchHover.getHoverInfo",
          "source": "BestMatchHover.java:102"
        },
        {
          "method": "org.eclipse.jdt.internal.ui.text.java.hover.JavaEditorTextHoverProxy.getHoverInfo",
          "source": "JavaEditorTextHoverProxy.java:69"
        },
        {
          "method": "org.eclipse.jface.text.TextViewerHoverManager$4.run",
          "source": "TextViewerHoverManager.java:160"
        }
      ],
      "number": 0,
      "commentIndex": 0,
      "bugId": "89477",
      "date": "2005-03-30T10:08:33+02:00",
      "product": "JDT",
      "component": "Core",
      "severity": "normal"
    }
  ],
  "groupId": "89477",
  "bugId": "89477",
  "date": "2005-03-30T10:08:33+02:00",
  "product": "JDT",
  "component": "Core",
  "severity": "normal"
}