{
  "comments": [
    "I had org.eclipse.swt in my workspace, but it was closed.  When I opened the\nproject this is what occurred:\n\n!SESSION 2005-03-30 10:05:06.14 ------------------------------------------------\neclipse.buildId\u003dI20050330-0500\njava.version\u003d1.4.2_06\njava.vendor\u003dSun Microsystems Inc.\nBootLoader constants: OS\u003dlinux, ARCH\u003dx86, WS\u003dgtk, NL\u003den_US\nCommand-line arguments:  -os linux -ws gtk -arch x86 -debug\n\n!ENTRY org.eclipse.ui.ide 4 4 2005-03-30 10:05:06.14\n!MESSAGE Core exception while testing project persistent property\n\n!ENTRY org.eclipse.ui.ide 4 4 2005-03-30 10:05:06.50\n!MESSAGE Core exception while testing project persistent property\n!STACK 1 \norg.eclipse.core.internal.resources.ResourceException: Resource /org.eclipse.swt\nis not open.\n        at\norg.eclipse.core.internal.resources.Project.checkAccessible(Project.java:127)\n        at\norg.eclipse.core.internal.resources.Resource.getPersistentProperty(Resource.java:924)\n        at\norg.eclipse.ui.internal.ide.model.ProjectPersistentPropertyTester.test(ProjectPersistentPropertyTester.java:68)\n        at org.eclipse.core.internal.expressions.Property.test(Property.java:52)\n        at\norg.eclipse.core.internal.expressions.TestExpression.evaluate(TestExpression.java:57)\n        at\norg.eclipse.core.internal.expressions.CompositeExpression.evaluateAnd(CompositeExpression.java:47)\n        at\norg.eclipse.core.internal.expressions.AdaptExpression.evaluate(AdaptExpression.java:58)\n        at\norg.eclipse.core.internal.expressions.CompositeExpression.evaluateAnd(CompositeExpression.java:47)\n        at\norg.eclipse.core.internal.expressions.EnablementExpression.evaluate(EnablementExpression.java:29)\n        at\norg.eclipse.ui.internal.ObjectActionContributor$ObjectContribution.isApplicableTo(ObjectActionContributor.java:337)\n        at\norg.eclipse.ui.internal.ObjectActionContributor.isApplicableTo(ObjectActionContributor.java:208)\n        at\norg.eclipse.ui.internal.ObjectContributorManager.isApplicableTo(ObjectContributorManager.java:274)\n        at\norg.eclipse.ui.internal.ObjectActionContributorManager.contributeObjectActions(ObjectActionContributorManager.java:124)\n        at\norg.eclipse.ui.internal.PopupMenuExtender.addObjectActions(PopupMenuExtender.java:201)\n        at\norg.eclipse.ui.internal.PopupMenuExtender.menuAboutToShow(PopupMenuExtender.java:226)\n        at\norg.eclipse.jface.action.MenuManager.fireAboutToShow(MenuManager.java:285)\n        at\norg.eclipse.jface.action.MenuManager.handleAboutToShow(MenuManager.java:372)\n        at org.eclipse.jface.action.MenuManager.access$0(MenuManager.java:369)\n        at org.eclipse.jface.action.MenuManager$2.menuShown(MenuManager.java:386)\n        at org.eclipse.swt.widgets.TypedListener.handleEvent(TypedListener.java:116)\n        at org.eclipse.swt.widgets.EventTable.sendEvent(EventTable.java:82)\n        at org.eclipse.swt.widgets.Widget.sendEvent(Widget.java:1012)\n        at org.eclipse.swt.widgets.Widget.sendEvent(Widget.java:1036)\n        at org.eclipse.swt.widgets.Widget.sendEvent(Widget.java:1017)\n        at org.eclipse.swt.widgets.Menu._setVisible(Menu.java:175)\n        at org.eclipse.swt.widgets.Display.runPopups(Display.java:2804)\n        at org.eclipse.swt.widgets.Display.readAndDispatch(Display.java:2469)\n        at org.eclipse.ui.internal.Workbench.runEventLoop(Workbench.java:1570)\n        at org.eclipse.ui.internal.Workbench.runUI(Workbench.java:1534)\n        at\norg.eclipse.ui.internal.Workbench.createAndRunWorkbench(Workbench.java:306)\n        at org.eclipse.ui.PlatformUI.createAndRunWorkbench(PlatformUI.java:143)\n        at org.eclipse.ui.internal.ide.IDEApplication.run(IDEApplication.java:103)\n        at\norg.eclipse.core.internal.runtime.PlatformActivator$1.run(PlatformActivator.java:228)\n        at\norg.eclipse.core.runtime.adaptor.EclipseStarter.run(EclipseStarter.java:338)\n        at\norg.eclipse.core.runtime.adaptor.EclipseStarter.run(EclipseStarter.java:151)\n        at sun.reflect.NativeMethodAccessorImpl.invoke0(Native Method)\n        at\nsun.reflect.NativeMethodAccessorImpl.invoke(NativeMethodAccessorImpl.java:39)\n        at\nsun.reflect.DelegatingMethodAccessorImpl.invoke(DelegatingMethodAccessorImpl.java:25)\n        at java.lang.reflect.Method.invoke(Method.java:324)\n        at org.eclipse.core.launcher.Main.invokeFramework(Main.java:268)\n        at org.eclipse.core.launcher.Main.basicRun(Main.java:260)\n        at org.eclipse.core.launcher.Main.run(Main.java:887)\n        at org.eclipse.core.launcher.Main.main(Main.java:871)\n!SUBENTRY 1 org.eclipse.core.resources 4 372 2005-03-30 10:05:06.51\n!MESSAGE Resource /org.eclipse.swt is not open.",
    "I had the same problem with build i0330-0500.",
    "*** Bug 89560 has been marked as a duplicate of this bug. ***",
    "\n\n*** This bug has been marked as a duplicate of 89504 ***"
  ],
  "commentCreationDates": [
    "2005-03-30T16:08:54+02:00",
    "2005-03-30T16:14:07+02:00",
    "2005-03-30T16:15:28+02:00",
    "2005-03-30T16:26:16+02:00"
  ],
  "traces": [
    {
      "exceptionType": "org.eclipse.core.internal.resources.ResourceException",
      "message": "Resource /org.eclipse.swt is not open.",
      "elements": [
        {
          "method": "org.eclipse.core.internal.resources.Project.checkAccessible",
          "source": "Project.java:127"
        },
        {
          "method": "org.eclipse.core.internal.resources.Resource.getPersistentProperty",
          "source": "Resource.java:924"
        },
        {
          "method": "org.eclipse.ui.internal.ide.model.ProjectPersistentPropertyTester.test",
          "source": "ProjectPersistentPropertyTester.java:68"
        },
        {
          "method": "org.eclipse.core.internal.expressions.Property.test",
          "source": "Property.java:52"
        },
        {
          "method": "org.eclipse.core.internal.expressions.TestExpression.evaluate",
          "source": "TestExpression.java:57"
        },
        {
          "method": "org.eclipse.core.internal.expressions.CompositeExpression.evaluateAnd",
          "source": "CompositeExpression.java:47"
        },
        {
          "method": "org.eclipse.core.internal.expressions.AdaptExpression.evaluate",
          "source": "AdaptExpression.java:58"
        },
        {
          "method": "org.eclipse.core.internal.expressions.CompositeExpression.evaluateAnd",
          "source": "CompositeExpression.java:47"
        },
        {
          "method": "org.eclipse.core.internal.expressions.EnablementExpression.evaluate",
          "source": "EnablementExpression.java:29"
        },
        {
          "method": "org.eclipse.ui.internal.ObjectActionContributor$ObjectContribution.isApplicableTo",
          "source": "ObjectActionContributor.java:337"
        },
        {
          "method": "org.eclipse.ui.internal.ObjectActionContributor.isApplicableTo",
          "source": "ObjectActionContributor.java:208"
        },
        {
          "method": "org.eclipse.ui.internal.ObjectContributorManager.isApplicableTo",
          "source": "ObjectContributorManager.java:274"
        },
        {
          "method": "org.eclipse.ui.internal.ObjectActionContributorManager.contributeObjectActions",
          "source": "ObjectActionContributorManager.java:124"
        },
        {
          "method": "org.eclipse.ui.internal.PopupMenuExtender.addObjectActions",
          "source": "PopupMenuExtender.java:201"
        },
        {
          "method": "org.eclipse.ui.internal.PopupMenuExtender.menuAboutToShow",
          "source": "PopupMenuExtender.java:226"
        },
        {
          "method": "org.eclipse.jface.action.MenuManager.fireAboutToShow",
          "source": "MenuManager.java:285"
        },
        {
          "method": "org.eclipse.jface.action.MenuManager.handleAboutToShow",
          "source": "MenuManager.java:372"
        },
        {
          "method": "org.eclipse.jface.action.MenuManager.access$0",
          "source": "MenuManager.java:369"
        },
        {
          "method": "org.eclipse.jface.action.MenuManager$2.menuShown",
          "source": "MenuManager.java:386"
        },
        {
          "method": "org.eclipse.swt.widgets.TypedListener.handleEvent",
          "source": "TypedListener.java:116"
        },
        {
          "method": "org.eclipse.swt.widgets.EventTable.sendEvent",
          "source": "EventTable.java:82"
        },
        {
          "method": "org.eclipse.swt.widgets.Widget.sendEvent",
          "source": "Widget.java:1012"
        },
        {
          "method": "org.eclipse.swt.widgets.Widget.sendEvent",
          "source": "Widget.java:1036"
        },
        {
          "method": "org.eclipse.swt.widgets.Widget.sendEvent",
          "source": "Widget.java:1017"
        },
        {
          "method": "org.eclipse.swt.widgets.Menu._setVisible",
          "source": "Menu.java:175"
        },
        {
          "method": "org.eclipse.swt.widgets.Display.runPopups",
          "source": "Display.java:2804"
        },
        {
          "method": "org.eclipse.swt.widgets.Display.readAndDispatch",
          "source": "Display.java:2469"
        },
        {
          "method": "org.eclipse.ui.internal.Workbench.runEventLoop",
          "source": "Workbench.java:1570"
        },
        {
          "method": "org.eclipse.ui.internal.Workbench.runUI",
          "source": "Workbench.java:1534"
        },
        {
          "method": "org.eclipse.ui.internal.Workbench.createAndRunWorkbench",
          "source": "Workbench.java:306"
        },
        {
          "method": "org.eclipse.ui.PlatformUI.createAndRunWorkbench",
          "source": "PlatformUI.java:143"
        },
        {
          "method": "org.eclipse.ui.internal.ide.IDEApplication.run",
          "source": "IDEApplication.java:103"
        },
        {
          "method": "org.eclipse.core.internal.runtime.PlatformActivator$1.run",
          "source": "PlatformActivator.java:228"
        },
        {
          "method": "org.eclipse.core.runtime.adaptor.EclipseStarter.run",
          "source": "EclipseStarter.java:338"
        },
        {
          "method": "org.eclipse.core.runtime.adaptor.EclipseStarter.run",
          "source": "EclipseStarter.java:151"
        },
        {
          "method": "sun.reflect.NativeMethodAccessorImpl.invoke0",
          "source": "Native Method"
        },
        {
          "method": "sun.reflect.NativeMethodAccessorImpl.invoke",
          "source": "NativeMethodAccessorImpl.java:39"
        },
        {
          "method": "sun.reflect.DelegatingMethodAccessorImpl.invoke",
          "source": "DelegatingMethodAccessorImpl.java:25"
        },
        {
          "method": "java.lang.reflect.Method.invoke",
          "source": "Method.java:324"
        },
        {
          "method": "org.eclipse.core.launcher.Main.invokeFramework",
          "source": "Main.java:268"
        },
        {
          "method": "org.eclipse.core.launcher.Main.basicRun",
          "source": "Main.java:260"
        },
        {
          "method": "org.eclipse.core.launcher.Main.run",
          "source": "Main.java:887"
        },
        {
          "method": "org.eclipse.core.launcher.Main.main",
          "source": "Main.java:871"
        }
      ],
      "number": 0,
      "commentIndex": 0,
      "bugId": "89558",
      "duplicateId": "89504",
      "date": "2005-03-30T16:08:54+02:00",
      "product": "Platform",
      "component": "UI",
      "severity": "normal"
    }
  ],
  "groupId": "89504",
  "bugId": "89558",
  "duplicateId": "89504",
  "date": "2005-03-30T16:08:54+02:00",
  "product": "Platform",
  "component": "UI",
  "severity": "normal"
}