{
  "comments": [
    "I20050330-0500\n\n* created a watch expression for \"fFull\" being populated in a loop:\n\n        for (int i\u003d 0; i \u003c 100; i++)\n            fFull.addElement(new Integer(i));\n\n* Turned on logical structures in the expressions view\n* Holding down the step over key results in some exceptions like:\n\n\norg.eclipse.debug.core.DebugException: Evaluation failed - thread not \nsuspended.\n\tat \norg.eclipse.jdt.internal.debug.core.model.JDIDebugElement.throwDebugException\n(JDIDebugElement.java:200)\n\tat \norg.eclipse.jdt.internal.debug.core.model.JDIDebugElement.requestFailed\n(JDIDebugElement.java:158)\n\tat org.eclipse.jdt.internal.debug.core.model.JDIThread.runEvaluation\n(JDIThread.java:548)\n\tat \norg.eclipse.jdt.internal.debug.eval.ast.engine.ASTEvaluationEngine$EvalRunnable\n.run(ASTEvaluationEngine.java:389)\n\tat org.eclipse.jdt.internal.debug.core.model.JDIThread$ThreadJob.run\n(JDIThread.java:2417)\n\tat org.eclipse.core.internal.jobs.Worker.run(Worker.java:67)",
    "Note that the watch item \"fFull\" needs to be expanded for this to happen (i.e. \nshowing children)",
    "No longer a problem - error message appears as child of watch expression now."
  ],
  "commentCreationDates": [
    "2005-03-30T18:22:08+02:00",
    "2005-03-30T18:23:21+02:00",
    "2005-05-19T04:42:10+02:00"
  ],
  "traces": [
    {
      "exceptionType": "org.eclipse.debug.core.DebugException",
      "message": "Evaluation failed - thread not  suspended.",
      "elements": [
        {
          "method": "org.eclipse.jdt.internal.debug.core.model.JDIDebugElement.throwDebugException",
          "source": "JDIDebugElement.java:200"
        },
        {
          "method": "org.eclipse.jdt.internal.debug.core.model.JDIDebugElement.requestFailed",
          "source": "JDIDebugElement.java:158"
        },
        {
          "method": "org.eclipse.jdt.internal.debug.core.model.JDIThread.runEvaluation",
          "source": "JDIThread.java:548"
        },
        {
          "method": "org.eclipse.jdt.internal.debug.eval.ast.engine.ASTEvaluationEngine$EvalRunnable.run",
          "source": "ASTEvaluationEngine.java:389"
        },
        {
          "method": "org.eclipse.jdt.internal.debug.core.model.JDIThread$ThreadJob.run",
          "source": "JDIThread.java:2417"
        },
        {
          "method": "org.eclipse.core.internal.jobs.Worker.run",
          "source": "Worker.java:67"
        }
      ],
      "number": 0,
      "commentIndex": 0,
      "bugId": "89613",
      "date": "2005-03-30T18:22:08+02:00",
      "product": "JDT",
      "component": "Debug",
      "severity": "normal"
    }
  ],
  "groupId": "89613",
  "bugId": "89613",
  "date": "2005-03-30T18:22:08+02:00",
  "product": "JDT",
  "component": "Debug",
  "severity": "normal"
}