{
  "comments": [
    "M6\n\nFound the following in the console window after having recognized that the \neditor now longer correctly updated errors on typing:\n\njava.util.ConcurrentModificationException\n        at java.util.AbstractList$Itr.checkForComodification\n(AbstractList.java:462)\n        at java.util.AbstractList$Itr.next(AbstractList.java:433)\n        at java.util.AbstractCollection.remove(AbstractCollection.java:268)\n        at org.eclipse.jface.text.AbstractDocument.removeDocumentListener\n(AbstractDocument.java:288)\n        at \norg.eclipse.core.internal.filebuffers.DocumentInputStream.releaseDocument\n(DocumentInputStream.java:176)\n        at org.eclipse.core.internal.filebuffers.DocumentInputStream.close\n(DocumentInputStream.java:152)\n        at \norg.eclipse.core.internal.filebuffers.ResourceTextFileBuffer.getContentType\n(ResourceTextFileBuffer.java:184)\n        at org.eclipse.ui.editors.text.TextFileDocumentProvider.getContentType\n(TextFileDocumentProvider.java:1155)\n        at \norg.eclipse.jdt.internal.ui.text.spelling.JavaSpellingReconcileStrategy.getCont\nentType(JavaSpellingReconcileStrategy.java:164)\n        at \norg.eclipse.jdt.internal.ui.text.spelling.JavaSpellingReconcileStrategy.reconci\nle(JavaSpellingReconcileStrategy.java:146)\n        at \norg.eclipse.jdt.internal.ui.text.CompositeReconcilingStrategy.reconcile\n(CompositeReconcilingStrategy.java:86)\n        at \norg.eclipse.jdt.internal.ui.text.JavaCompositeReconcilingStrategy.reconcile\n(JavaCompositeReconcilingStrategy.java:94)\n        at org.eclipse.jface.text.reconciler.MonoReconciler.process\n(MonoReconciler.java:75)\n        at org.eclipse.jdt.internal.ui.text.JavaReconciler.process\n(JavaReconciler.java:318)\n        at \norg.eclipse.jface.text.reconciler.AbstractReconciler$BackgroundThread.run\n(AbstractReconciler.java:204)\n\nNo reproducible steps yet.",
    "Document listener handling is done in AbstractDocument which is not thread-safe.",
    "*** Bug 96209 has been marked as a duplicate of this bug. ***",
    "Moving target to 3.2.",
    "*** Bug 124938 has been marked as a duplicate of this bug. ***",
    "Fixed in HEAD.\nAvailable in builds \u003e N20060404-0010.",
    "Verified in code of N20060426-0010 that AbstractDocument now uses org.eclipse.core.runtime.ListenerList."
  ],
  "commentCreationDates": [
    "2005-04-07T13:00:36+02:00",
    "2005-04-07T17:01:07+02:00",
    "2005-05-22T18:52:10+02:00",
    "2005-06-16T14:04:07+02:00",
    "2006-01-24T08:00:31+01:00",
    "2006-04-04T12:32:32+02:00",
    "2006-04-26T18:55:19+02:00"
  ],
  "traces": [
    {
      "exceptionType": "java.util.ConcurrentModificationException",
      "elements": [
        {
          "method": "java.util.AbstractList$Itr.checkForComodification",
          "source": "AbstractList.java:462"
        },
        {
          "method": "java.util.AbstractList$Itr.next",
          "source": "AbstractList.java:433"
        },
        {
          "method": "java.util.AbstractCollection.remove",
          "source": "AbstractCollection.java:268"
        },
        {
          "method": "org.eclipse.jface.text.AbstractDocument.removeDocumentListener",
          "source": "AbstractDocument.java:288"
        },
        {
          "method": "org.eclipse.core.internal.filebuffers.DocumentInputStream.releaseDocument",
          "source": "DocumentInputStream.java:176"
        },
        {
          "method": "org.eclipse.core.internal.filebuffers.DocumentInputStream.close",
          "source": "DocumentInputStream.java:152"
        },
        {
          "method": "org.eclipse.core.internal.filebuffers.ResourceTextFileBuffer.getContentType",
          "source": "ResourceTextFileBuffer.java:184"
        },
        {
          "method": "org.eclipse.ui.editors.text.TextFileDocumentProvider.getContentType",
          "source": "TextFileDocumentProvider.java:1155"
        },
        {
          "method": "org.eclipse.jdt.internal.ui.text.spelling.JavaSpellingReconcileStrategy.getContentType",
          "source": "JavaSpellingReconcileStrategy.java:164"
        },
        {
          "method": "org.eclipse.jdt.internal.ui.text.spelling.JavaSpellingReconcileStrategy.reconcile",
          "source": "JavaSpellingReconcileStrategy.java:146"
        },
        {
          "method": "org.eclipse.jdt.internal.ui.text.CompositeReconcilingStrategy.reconcile",
          "source": "CompositeReconcilingStrategy.java:86"
        },
        {
          "method": "org.eclipse.jdt.internal.ui.text.JavaCompositeReconcilingStrategy.reconcile",
          "source": "JavaCompositeReconcilingStrategy.java:94"
        },
        {
          "method": "org.eclipse.jface.text.reconciler.MonoReconciler.process",
          "source": "MonoReconciler.java:75"
        },
        {
          "method": "org.eclipse.jdt.internal.ui.text.JavaReconciler.process",
          "source": "JavaReconciler.java:318"
        },
        {
          "method": "org.eclipse.jface.text.reconciler.AbstractReconciler$BackgroundThread.run",
          "source": "AbstractReconciler.java:204"
        }
      ],
      "number": 0,
      "commentIndex": 0,
      "bugId": "90590",
      "date": "2005-04-07T13:00:36+02:00",
      "product": "JDT",
      "component": "Text",
      "severity": "major"
    }
  ],
  "groupId": "90590",
  "bugId": "90590",
  "date": "2005-04-07T13:00:36+02:00",
  "product": "JDT",
  "component": "Text",
  "severity": "major"
}