{
  "comments": [
    "build i0405\nreleng tools v3.1.0\n\nI tried to release some code with this build I nothing happened. I checked my\nlog file and noticed the following stack trace:\n\n!SESSION 2005-04-12 17:06:27.883 -----------------------------------------------\neclipse.buildId\u003dI20050405-0800\njava.fullversion\u003dJ2RE 1.4.2 IBM J9 2.2 Windows XP x86-32 j9n142-20040915 (JIT\nenabled)\nJ9VM - 20040914_1123_lHdSMR\nJIT  - r7_level20040912_1800\nBootLoader constants: OS\u003dwin32, ARCH\u003dx86, WS\u003dwin32, NL\u003den_CA\nFramework arguments:  -showlocation\nCommand-line arguments:  -os win32 -ws win32 -arch x86 -debug -data\n\\eclipse\\target\\head\\plugins\\ -showlocation -consoleLog -console\n\n!ENTRY org.eclipse.ui 4 4 2005-04-12 17:06:27.893\n!MESSAGE Unhandled event loop exception\nUnhandled event loop exception\nReason:\n\n!ENTRY org.eclipse.ui 4 0 2005-04-12 17:06:27.893\n!MESSAGE org.eclipse.ui.internal.dialogs.ContainerCheckedTreeViewer\n!STACK 0\njava.lang.NoClassDefFoundError:\norg.eclipse.ui.internal.dialogs.ContainerCheckedTreeViewer\n        at java.lang.Class.verifyImpl(Native Method)\n        at java.lang.Class.verify(Class.java:253)\n        at java.lang.Class.initialize(Class.java:315)\n        at org.eclipse.releng.tools.ReleaseWizard.addPages(ReleaseWizard.java:132)\n        at\norg.eclipse.jface.wizard.WizardDialog.createContents(WizardDialog.java:499)\n        at org.eclipse.jface.window.Window.create(Window.java:418)\n        at org.eclipse.jface.dialogs.Dialog.create(Dialog.java:996)\n        at org.eclipse.jface.window.Window.open(Window.java:770)\n        at org.eclipse.releng.tools.ReleaseWizard.execute(ReleaseWizard.java:118)\n        at\norg.eclipse.releng.tools.TagAndReleaseAction.execute(TagAndReleaseAction.java:37)\n        at\norg.eclipse.team.internal.ccvs.ui.actions.CVSAction.run(CVSAction.java:117)\n        at\norg.eclipse.ui.actions.ActionDelegate.runWithEvent(ActionDelegate.java:70)\n        at org.eclipse.ui.internal.PluginAction.runWithEvent(PluginAction.java:236)\n        at\norg.eclipse.jface.action.ActionContributionItem.handleWidgetSelection(ActionContributionItem.java:538)\n        at\norg.eclipse.jface.action.ActionContributionItem.access$2(ActionContributionItem.java:488)\n        at\norg.eclipse.jface.action.ActionContributionItem$5.handleEvent(ActionContributionItem.java:400)\n        at org.eclipse.swt.widgets.EventTable.sendEvent(EventTable.java:82)\n        at org.eclipse.swt.widgets.Widget.sendEvent(Widget.java:842)\n        at org.eclipse.swt.widgets.Display.runDeferredEvents(Display.java:2894)\n        at org.eclipse.swt.widgets.Display.readAndDispatch(Display.java:2527)\n        at org.eclipse.ui.internal.Workbench.runEventLoop(Workbench.java:1570)\n        at org.eclipse.ui.internal.Workbench.runUI(Workbench.java:1534)\n        at\norg.eclipse.ui.internal.Workbench.createAndRunWorkbench(Workbench.java:306)\n        at org.eclipse.ui.PlatformUI.createAndRunWorkbench(PlatformUI.java:143)\n        at org.eclipse.ui.internal.ide.IDEApplication.run(IDEApplication.java:103)\n        at\norg.eclipse.core.internal.runtime.PlatformActivator$1.run(PlatformActivator.java:228)\n        at\norg.eclipse.core.runtime.adaptor.EclipseStarter.run(EclipseStarter.java:344)\n        at\norg.eclipse.core.runtime.adaptor.EclipseStarter.run(EclipseStarter.java:156)\n        at sun.reflect.NativeMethodAccessorImpl.invoke0(Native Method)\n        at\nsun.reflect.NativeMethodAccessorImpl.invoke(NativeMethodAccessorImpl.java:85)\n        at\nsun.reflect.NativeMethodAccessorImpl.invoke(NativeMethodAccessorImpl.java:58)\n        at\nsun.reflect.DelegatingMethodAccessorImpl.invoke(DelegatingMethodAccessorImpl.java:60)\n        at java.lang.reflect.Method.invoke(Method.java:391)\n        at org.eclipse.core.launcher.Main.invokeFramework(Main.java:315)\n        at org.eclipse.core.launcher.Main.basicRun(Main.java:268)\n        at org.eclipse.core.launcher.Main.run(Main.java:947)\n        at org.eclipse.core.launcher.Main.main(Main.java:931)\norg.eclipse.ui.internal.dialogs.ContainerCheckedTreeViewer",
    "The plugin has changed this week.\n\n*** This bug has been marked as a duplicate of 85164 ***"
  ],
  "commentCreationDates": [
    "2005-04-12T23:10:34+02:00",
    "2005-04-12T23:20:41+02:00"
  ],
  "traces": [
    {
      "exceptionType": "java.lang.NoClassDefFoundError",
      "message": "org.eclipse.ui.internal.dialogs.ContainerCheckedTreeViewer",
      "elements": [
        {
          "method": "java.lang.Class.verifyImpl",
          "source": "Native Method"
        },
        {
          "method": "java.lang.Class.verify",
          "source": "Class.java:253"
        },
        {
          "method": "java.lang.Class.initialize",
          "source": "Class.java:315"
        },
        {
          "method": "org.eclipse.releng.tools.ReleaseWizard.addPages",
          "source": "ReleaseWizard.java:132"
        },
        {
          "method": "org.eclipse.jface.wizard.WizardDialog.createContents",
          "source": "WizardDialog.java:499"
        },
        {
          "method": "org.eclipse.jface.window.Window.create",
          "source": "Window.java:418"
        },
        {
          "method": "org.eclipse.jface.dialogs.Dialog.create",
          "source": "Dialog.java:996"
        },
        {
          "method": "org.eclipse.jface.window.Window.open",
          "source": "Window.java:770"
        },
        {
          "method": "org.eclipse.releng.tools.ReleaseWizard.execute",
          "source": "ReleaseWizard.java:118"
        },
        {
          "method": "org.eclipse.releng.tools.TagAndReleaseAction.execute",
          "source": "TagAndReleaseAction.java:37"
        },
        {
          "method": "org.eclipse.team.internal.ccvs.ui.actions.CVSAction.run",
          "source": "CVSAction.java:117"
        },
        {
          "method": "org.eclipse.ui.actions.ActionDelegate.runWithEvent",
          "source": "ActionDelegate.java:70"
        },
        {
          "method": "org.eclipse.ui.internal.PluginAction.runWithEvent",
          "source": "PluginAction.java:236"
        },
        {
          "method": "org.eclipse.jface.action.ActionContributionItem.handleWidgetSelection",
          "source": "ActionContributionItem.java:538"
        },
        {
          "method": "org.eclipse.jface.action.ActionContributionItem.access$2",
          "source": "ActionContributionItem.java:488"
        },
        {
          "method": "org.eclipse.jface.action.ActionContributionItem$5.handleEvent",
          "source": "ActionContributionItem.java:400"
        },
        {
          "method": "org.eclipse.swt.widgets.EventTable.sendEvent",
          "source": "EventTable.java:82"
        },
        {
          "method": "org.eclipse.swt.widgets.Widget.sendEvent",
          "source": "Widget.java:842"
        },
        {
          "method": "org.eclipse.swt.widgets.Display.runDeferredEvents",
          "source": "Display.java:2894"
        },
        {
          "method": "org.eclipse.swt.widgets.Display.readAndDispatch",
          "source": "Display.java:2527"
        },
        {
          "method": "org.eclipse.ui.internal.Workbench.runEventLoop",
          "source": "Workbench.java:1570"
        },
        {
          "method": "org.eclipse.ui.internal.Workbench.runUI",
          "source": "Workbench.java:1534"
        },
        {
          "method": "org.eclipse.ui.internal.Workbench.createAndRunWorkbench",
          "source": "Workbench.java:306"
        },
        {
          "method": "org.eclipse.ui.PlatformUI.createAndRunWorkbench",
          "source": "PlatformUI.java:143"
        },
        {
          "method": "org.eclipse.ui.internal.ide.IDEApplication.run",
          "source": "IDEApplication.java:103"
        },
        {
          "method": "org.eclipse.core.internal.runtime.PlatformActivator$1.run",
          "source": "PlatformActivator.java:228"
        },
        {
          "method": "org.eclipse.core.runtime.adaptor.EclipseStarter.run",
          "source": "EclipseStarter.java:344"
        },
        {
          "method": "org.eclipse.core.runtime.adaptor.EclipseStarter.run",
          "source": "EclipseStarter.java:156"
        },
        {
          "method": "sun.reflect.NativeMethodAccessorImpl.invoke0",
          "source": "Native Method"
        },
        {
          "method": "sun.reflect.NativeMethodAccessorImpl.invoke",
          "source": "NativeMethodAccessorImpl.java:85"
        },
        {
          "method": "sun.reflect.NativeMethodAccessorImpl.invoke",
          "source": "NativeMethodAccessorImpl.java:58"
        },
        {
          "method": "sun.reflect.DelegatingMethodAccessorImpl.invoke",
          "source": "DelegatingMethodAccessorImpl.java:60"
        },
        {
          "method": "java.lang.reflect.Method.invoke",
          "source": "Method.java:391"
        },
        {
          "method": "org.eclipse.core.launcher.Main.invokeFramework",
          "source": "Main.java:315"
        },
        {
          "method": "org.eclipse.core.launcher.Main.basicRun",
          "source": "Main.java:268"
        },
        {
          "method": "org.eclipse.core.launcher.Main.run",
          "source": "Main.java:947"
        },
        {
          "method": "org.eclipse.core.launcher.Main.main",
          "source": "Main.java:931"
        }
      ],
      "number": 0,
      "commentIndex": 0,
      "bugId": "91210",
      "duplicateId": "85164",
      "date": "2005-04-12T23:10:34+02:00",
      "product": "Platform",
      "component": "Releng",
      "severity": "normal"
    }
  ],
  "groupId": "85164",
  "bugId": "91210",
  "duplicateId": "85164",
  "date": "2005-04-12T23:10:34+02:00",
  "product": "Platform",
  "component": "Releng",
  "severity": "normal"
}