{
  "comments": [
    "I have created a UI contributing plugin with a ViewPart, a help plugin, and a \nfeature plugin tying them together.  I then created an Update Site plugin, \nattached the feature plugin, defined a category, and clicked \"Build All\".  This \nis what I get.  If I delete the Update Site project and regenerate it, it seems \nto work until I increment the versions of my plugins and feature, then I get \nthis error again:\n\n\nAn internal error occurred during: \"PDE Export\".\njava.lang.IllegalArgumentException: Attempted to beginRule: R/, does not match \nouter scope rule: MultiRule\n[P/com.iwaysoftware.ibsexp.update,org.eclipse.pde.internal.ui.wizards.exports.Fe\natureExportJob$SchedulingRule@d72782]\norg.eclipse.core.internal.runtime.Assert.isLegal(Assert.java:58)\norg.eclipse.core.internal.jobs.ThreadJob.illegalPush(ThreadJob.java:106)\norg.eclipse.core.internal.jobs.ThreadJob.push(ThreadJob.java:200)\norg.eclipse.core.internal.jobs.ImplicitJobs.begin(ImplicitJobs.java:80)\norg.eclipse.core.internal.jobs.JobManager.beginRule(JobManager.java:170)\norg.eclipse.core.internal.resources.WorkManager.checkIn(WorkManager.java:95)\norg.eclipse.core.internal.resources.Workspace.prepareOperation\n(Workspace.java:1628)\norg.eclipse.core.internal.resources.Resource.refreshLocal(Resource.java:1224)\norg.eclipse.pde.internal.ui.build.BuildSiteJob.refresh(BuildSiteJob.java:53)\norg.eclipse.pde.internal.ui.build.BuildSiteJob.run(BuildSiteJob.java:42)\norg.eclipse.core.internal.jobs.Worker.run(Worker.java:66)",
    "I have more information regarding this bug:\n\n1) 3.1M5\u0027s \"Build All\" works with no errors.  But this may be because my 3.1M5 \ninstance does not use VSS (see #2).\n2) This is related to the Visual Source Safe plugin.  (org.vssplugin_1.6.0)\n  The error ONLY occurs for projects that are associated with a directory in \nVSS.  If I remove the VSS connection, the PDE Build works fine.  If I \nreassociate the project with VSS, it fails.  I\u0027ve tried marking files \nread/write, checking out all the files, etc. with no effect.\n\nSo for now my workaround is to deassociate VSS with my update site project \nevery time I want to release a build.",
    "We have no control over what behavior add-on non-SDK plugins exhibit.\n\nplease reopen if you can reproduce on Eclipse-proper.  Thanks.",
    "Ok, I have the same problem, with another repository provider - I\u0027m using \nPerforce.\nThe error could be reproduced, if one first create:\n1) plugin project\n2) feature project for this plugin\n3) update site for feature project\nIf none of projects are connected to team provider, \"build all\" works perfectly.\nThen I have connected all three projects to Perforce, incremented plugin and \nfeature versions and got during \"build all\" the same error:\n\njava.lang.IllegalArgumentException: Attempted to beginRule: R/, does not match \nouter scope rule: MultiRule[P/ALUpdateSite,org.eclipse.pde.internal.ui.build.\nFeatureExportJob$SchedulingRule@9bfaff]\n\tat org.eclipse.core.internal.runtime.Assert.isLegal(Assert.java:58)\n\tat org.eclipse.core.internal.jobs.ThreadJob.illegalPush(ThreadJob.java:\n117)\n\tat org.eclipse.core.internal.jobs.ThreadJob.push(ThreadJob.java:211)\n\tat org.eclipse.core.internal.jobs.ImplicitJobs.begin(ImplicitJobs.java:81)\n\tat org.eclipse.core.internal.jobs.JobManager.beginRule(JobManager.java:\n190)\n\tat org.eclipse.core.internal.resources.WorkManager.checkIn(WorkManager.\njava:96)\n\tat org.eclipse.core.internal.resources.Workspace.\nprepareOperation(Workspace.java:1674)\n\tat org.eclipse.core.internal.resources.Resource.refreshLocal(Resource.\njava:1240)\n\tat org.eclipse.pde.internal.ui.build.BuildSiteJob.run(BuildSiteJob.java:\n81)\n\tat org.eclipse.core.internal.jobs.Worker.run(Worker.java:76)\n\n\neclipse.buildId\u003dI20050617-1618\njava.version\u003d1.5.0_05\n\nThe workaround for me was the same as for Ken in comment 1 - I have disconnected \nthe update site from team provider and then \"build all\" was working again.\n\nI think the problem is related not only to Visual Source Safe plugin (I\u0027m using \nPerforce), so please consider that this is a bug in PDE."
  ],
  "commentCreationDates": [
    "2005-04-12T23:38:51+02:00",
    "2005-04-13T16:05:16+02:00",
    "2005-05-26T08:52:39+02:00",
    "2005-09-22T08:50:10+02:00"
  ],
  "traces": [
    {
      "exceptionType": "java.lang.IllegalArgumentException",
      "message": "Attempted to beginRule: R/, does not match  outer scope rule: MultiRule[P/ALUpdateSite,org.eclipse.pde.internal.ui.build. FeatureExportJob$SchedulingRule@9bfaff]",
      "elements": [
        {
          "method": "org.eclipse.core.internal.runtime.Assert.isLegal",
          "source": "Assert.java:58"
        },
        {
          "method": "org.eclipse.core.internal.jobs.ThreadJob.illegalPush",
          "source": "ThreadJob.java: 117"
        },
        {
          "method": "org.eclipse.core.internal.jobs.ThreadJob.push",
          "source": "ThreadJob.java:211"
        },
        {
          "method": "org.eclipse.core.internal.jobs.ImplicitJobs.begin",
          "source": "ImplicitJobs.java:81"
        },
        {
          "method": "org.eclipse.core.internal.jobs.JobManager.beginRule",
          "source": "JobManager.java: 190"
        },
        {
          "method": "org.eclipse.core.internal.resources.WorkManager.checkIn",
          "source": "WorkManager. java:96"
        },
        {
          "method": "org.eclipse.core.internal.resources.Workspace.prepareOperation",
          "source": "Workspace.java:1674"
        },
        {
          "method": "org.eclipse.core.internal.resources.Resource.refreshLocal",
          "source": "Resource. java:1240"
        },
        {
          "method": "org.eclipse.pde.internal.ui.build.BuildSiteJob.run",
          "source": "BuildSiteJob.java: 81"
        },
        {
          "method": "org.eclipse.core.internal.jobs.Worker.run",
          "source": "Worker.java:76"
        }
      ],
      "number": 0,
      "commentIndex": 3,
      "bugId": "91216",
      "date": "2005-09-22T08:50:10+02:00",
      "product": "PDE",
      "component": "UI",
      "severity": "normal"
    }
  ],
  "groupId": "91216",
  "bugId": "91216",
  "date": "2005-04-12T23:38:51+02:00",
  "product": "PDE",
  "component": "UI",
  "severity": "normal"
}