{
  "comments": [
    "Build 20020129\n\n1) Started with a project (a plugin with source) that was in sync\n2) In the filesystem, I slammed the project contents, replacing with a binary \nversion of the same plugin (so most files/folders in the projects are replaced\n3) In the navigator, refreshed from local\n\nNow, whenever I try to do anything CVS-related on this project, I get internal \nerrors (for example, when I do CVS-\u003eSynchronize).  Here is a sample from the log \nfile:\n\nLog: Tue Feb 05 12:51:27 EST 2002\n4 org.eclipse.team.ui 1 Internal error\norg.eclipse.team.core.TeamException: Error retrieving remote resource tree. \nParent is not managed\n\tat \norg.eclipse.team.ccvs.core.CVSTeamProvider.getRemoteSyncTree(CVSTeamProvider.jav\na:631)\n\tat \norg.eclipse.team.internal.ccvs.ui.sync.CVSSyncCompareInput.createSyncElements(CV\nSSyncCompareInput.java:64)\n\tat \norg.eclipse.team.ui.sync.SyncCompareInput.prepareInput(SyncCompareInput.java:200\n)\n\tat \norg.eclipse.compare.CompareEditorInput.run(CompareEditorInput.java:288)\n\tat \norg.eclipse.jface.operation.ModalContext$ModalContextThread.run(ModalContext.jav\na:98)",
    "\n\n*** This bug has been marked as a duplicate of 9189 ***"
  ],
  "commentCreationDates": [
    "2002-02-05T17:53:05+01:00",
    "2002-02-07T15:44:51+01:00"
  ],
  "traces": [
    {
      "exceptionType": "org.eclipse.team.core.TeamException",
      "message": "Error retrieving remote resource tree.  Parent is not managed",
      "elements": [
        {
          "method": "org.eclipse.team.ccvs.core.CVSTeamProvider.getRemoteSyncTree",
          "source": "CVSTeamProvider.jav a:631"
        },
        {
          "method": "org.eclipse.team.internal.ccvs.ui.sync.CVSSyncCompareInput.createSyncElements",
          "source": "CV SSyncCompareInput.java:64"
        },
        {
          "method": "org.eclipse.team.ui.sync.SyncCompareInput.prepareInput",
          "source": "SyncCompareInput.java:200 "
        },
        {
          "method": "org.eclipse.compare.CompareEditorInput.run",
          "source": "CompareEditorInput.java:288"
        },
        {
          "method": "org.eclipse.jface.operation.ModalContext$ModalContextThread.run",
          "source": "ModalContext.jav a:98"
        }
      ],
      "number": 0,
      "commentIndex": 0,
      "bugId": "9123",
      "duplicateId": "9189",
      "date": "2002-02-05T17:53:05+01:00",
      "product": "Platform",
      "component": "Team",
      "severity": "normal"
    }
  ],
  "groupId": "9189",
  "bugId": "9123",
  "duplicateId": "9189",
  "date": "2002-02-05T17:53:05+01:00",
  "product": "Platform",
  "component": "Team",
  "severity": "normal"
}