{
  "comments": [
    "when the archivesFormat parameter to the eclipse.buildScript task is missing a\nNPE during build is thrown (see below). However, when specifying the\narchivesFormat the build script cannot be used with Eclipse 3.0 anymore (we have\na build setup that compiles our plugins for both 3.0 and 3.1 with version\nspecific extensions). Maybe there could be a reasonable default for the\narchivesProperty so no NPE occurs (e.g. \"*,*,*-antZip\")\n\njava.lang.NullPointerException\n        at\norg.eclipse.pde.internal.build.AssembleScriptGenerator.generateAssembleConfigFileTargetCall(AssembleScriptGenerator.java:61)\n        at\norg.eclipse.pde.internal.build.AssembleScriptGenerator.generateMainTarget(AssembleScriptGenerator.java:54)\n        at\norg.eclipse.pde.internal.build.AssembleScriptGenerator.generate(AssembleScriptGenerator.java:43)\n        at\norg.eclipse.pde.internal.build.BuildScriptGenerator.generateAssembleScripts(BuildScriptGenerator.java:184)\n        at\norg.eclipse.pde.internal.build.BuildScriptGenerator.generateFeatures(BuildScriptGenerator.java:160)\n        at\norg.eclipse.pde.internal.build.BuildScriptGenerator.generate(BuildScriptGenerator.java:79)\n        at\norg.eclipse.pde.internal.build.tasks.BuildScriptGeneratorTask.run(BuildScriptGeneratorTask.java:77)\n        at\norg.eclipse.pde.internal.build.tasks.BuildScriptGeneratorTask.execute(BuildScriptGeneratorTask.java:70)\n        at org.apache.tools.ant.UnknownElement.execute(UnknownElement.java:275)\n        at org.apache.tools.ant.Task.perform(Task.java:364)\n        at org.apache.tools.ant.Target.execute(Target.java:341)\n        at org.apache.tools.ant.Target.performTasks(Target.java:369)\n        at org.apache.tools.ant.Project.executeTarget(Project.java:1214)\n        at org.apache.tools.ant.Project.executeTargets(Project.java:1062)\n        at\norg.eclipse.ant.internal.core.ant.InternalAntRunner.run(InternalAntRunner.java:685)\n        at\norg.eclipse.ant.internal.core.ant.InternalAntRunner.run(InternalAntRunner.java:571)\n        at sun.reflect.NativeMethodAccessorImpl.invoke0(Native Method)\n        at sun.reflect.NativeMethodAccessorImpl.invoke(Unknown Source)\n        at sun.reflect.DelegatingMethodAccessorImpl.invoke(Unknown Source)\n        at java.lang.reflect.Method.invoke(Unknown Source)\n        at org.eclipse.ant.core.AntRunner.run(AntRunner.java:493)\n        at\norg.eclipse.core.internal.runtime.PlatformActivator$1.run(PlatformActivator.java:228)\n        at\norg.eclipse.core.runtime.adaptor.EclipseStarter.run(EclipseStarter.java:344)\n        at\norg.eclipse.core.runtime.adaptor.EclipseStarter.run(EclipseStarter.java:156)\n        at sun.reflect.NativeMethodAccessorImpl.invoke0(Native Method)\n        at sun.reflect.NativeMethodAccessorImpl.invoke(Unknown Source)\n        at sun.reflect.DelegatingMethodAccessorImpl.invoke(Unknown Source)\n        at java.lang.reflect.Method.invoke(Unknown Source)\n        at org.eclipse.core.launcher.Main.invokeFramework(Main.java:315)\n        at org.eclipse.core.launcher.Main.basicRun(Main.java:268)\n        at org.eclipse.core.launcher.Main.run(Main.java:942)\n        at org.eclipse.core.launcher.Main.main(Main.java:926)",
    "\n\n*** This bug has been marked as a duplicate of 90398 ***"
  ],
  "commentCreationDates": [
    "2005-04-13T11:53:12+02:00",
    "2005-04-13T14:49:35+02:00"
  ],
  "traces": [
    {
      "exceptionType": "java.lang.NullPointerException",
      "elements": [
        {
          "method": "org.eclipse.pde.internal.build.AssembleScriptGenerator.generateAssembleConfigFileTargetCall",
          "source": "AssembleScriptGenerator.java:61"
        },
        {
          "method": "org.eclipse.pde.internal.build.AssembleScriptGenerator.generateMainTarget",
          "source": "AssembleScriptGenerator.java:54"
        },
        {
          "method": "org.eclipse.pde.internal.build.AssembleScriptGenerator.generate",
          "source": "AssembleScriptGenerator.java:43"
        },
        {
          "method": "org.eclipse.pde.internal.build.BuildScriptGenerator.generateAssembleScripts",
          "source": "BuildScriptGenerator.java:184"
        },
        {
          "method": "org.eclipse.pde.internal.build.BuildScriptGenerator.generateFeatures",
          "source": "BuildScriptGenerator.java:160"
        },
        {
          "method": "org.eclipse.pde.internal.build.BuildScriptGenerator.generate",
          "source": "BuildScriptGenerator.java:79"
        },
        {
          "method": "org.eclipse.pde.internal.build.tasks.BuildScriptGeneratorTask.run",
          "source": "BuildScriptGeneratorTask.java:77"
        },
        {
          "method": "org.eclipse.pde.internal.build.tasks.BuildScriptGeneratorTask.execute",
          "source": "BuildScriptGeneratorTask.java:70"
        },
        {
          "method": "org.apache.tools.ant.UnknownElement.execute",
          "source": "UnknownElement.java:275"
        },
        {
          "method": "org.apache.tools.ant.Task.perform",
          "source": "Task.java:364"
        },
        {
          "method": "org.apache.tools.ant.Target.execute",
          "source": "Target.java:341"
        },
        {
          "method": "org.apache.tools.ant.Target.performTasks",
          "source": "Target.java:369"
        },
        {
          "method": "org.apache.tools.ant.Project.executeTarget",
          "source": "Project.java:1214"
        },
        {
          "method": "org.apache.tools.ant.Project.executeTargets",
          "source": "Project.java:1062"
        },
        {
          "method": "org.eclipse.ant.internal.core.ant.InternalAntRunner.run",
          "source": "InternalAntRunner.java:685"
        },
        {
          "method": "org.eclipse.ant.internal.core.ant.InternalAntRunner.run",
          "source": "InternalAntRunner.java:571"
        },
        {
          "method": "sun.reflect.NativeMethodAccessorImpl.invoke0",
          "source": "Native Method"
        },
        {
          "method": "sun.reflect.NativeMethodAccessorImpl.invoke",
          "source": "Unknown Source"
        },
        {
          "method": "sun.reflect.DelegatingMethodAccessorImpl.invoke",
          "source": "Unknown Source"
        },
        {
          "method": "java.lang.reflect.Method.invoke",
          "source": "Unknown Source"
        },
        {
          "method": "org.eclipse.ant.core.AntRunner.run",
          "source": "AntRunner.java:493"
        },
        {
          "method": "org.eclipse.core.internal.runtime.PlatformActivator$1.run",
          "source": "PlatformActivator.java:228"
        },
        {
          "method": "org.eclipse.core.runtime.adaptor.EclipseStarter.run",
          "source": "EclipseStarter.java:344"
        },
        {
          "method": "org.eclipse.core.runtime.adaptor.EclipseStarter.run",
          "source": "EclipseStarter.java:156"
        },
        {
          "method": "sun.reflect.NativeMethodAccessorImpl.invoke0",
          "source": "Native Method"
        },
        {
          "method": "sun.reflect.NativeMethodAccessorImpl.invoke",
          "source": "Unknown Source"
        },
        {
          "method": "sun.reflect.DelegatingMethodAccessorImpl.invoke",
          "source": "Unknown Source"
        },
        {
          "method": "java.lang.reflect.Method.invoke",
          "source": "Unknown Source"
        },
        {
          "method": "org.eclipse.core.launcher.Main.invokeFramework",
          "source": "Main.java:315"
        },
        {
          "method": "org.eclipse.core.launcher.Main.basicRun",
          "source": "Main.java:268"
        },
        {
          "method": "org.eclipse.core.launcher.Main.run",
          "source": "Main.java:942"
        },
        {
          "method": "org.eclipse.core.launcher.Main.main",
          "source": "Main.java:926"
        }
      ],
      "number": 0,
      "commentIndex": 0,
      "bugId": "91253",
      "duplicateId": "90398",
      "date": "2005-04-13T11:53:12+02:00",
      "product": "PDE",
      "component": "Build",
      "severity": "normal"
    }
  ],
  "groupId": "90398",
  "bugId": "91253",
  "duplicateId": "90398",
  "date": "2005-04-13T11:53:12+02:00",
  "product": "PDE",
  "component": "Build",
  "severity": "normal"
}