{
  "comments": [
    "I was working on a JUnit plug-in test.  What I usually do is from a suite of \ntests, I click on one of them in the JUnit view and just run that one \nindividual test, and keep using the \"run last test\" button while I work on it.\n\nOne of the times when I ran the test I got this assertion failure to the \nconsole after the test completed:\n\norg.eclipse.core.internal.runtime.AssertionFailedException: assertion failed: \nThe application has not been initialized.\n\tat org.eclipse.core.internal.runtime.Assert.isTrue(Assert.java:107)\n\tat org.eclipse.core.internal.runtime.InternalPlatform.assertInitialized\n(InternalPlatform.java:218)\n\tat org.eclipse.core.internal.runtime.InternalPlatform.log\n(InternalPlatform.java:822)\n\tat org.eclipse.core.internal.jobs.ImplicitJobs.endJob\n(ImplicitJobs.java:128)\n\tat org.eclipse.core.internal.jobs.WorkerPool.endJob(WorkerPool.java:96)\n\tat org.eclipse.core.internal.jobs.Worker.run(Worker.java:83)",
    "\n\n*** This bug has been marked as a duplicate of 91291 ***"
  ],
  "commentCreationDates": [
    "2005-04-13T21:13:51+02:00",
    "2005-04-13T21:16:32+02:00"
  ],
  "traces": [
    {
      "exceptionType": "org.eclipse.core.internal.runtime.AssertionFailedException",
      "message": "assertion failed:  The application has not been initialized.",
      "elements": [
        {
          "method": "org.eclipse.core.internal.runtime.Assert.isTrue",
          "source": "Assert.java:107"
        },
        {
          "method": "org.eclipse.core.internal.runtime.InternalPlatform.assertInitialized",
          "source": "InternalPlatform.java:218"
        },
        {
          "method": "org.eclipse.core.internal.runtime.InternalPlatform.log",
          "source": "InternalPlatform.java:822"
        },
        {
          "method": "org.eclipse.core.internal.jobs.ImplicitJobs.endJob",
          "source": "ImplicitJobs.java:128"
        },
        {
          "method": "org.eclipse.core.internal.jobs.WorkerPool.endJob",
          "source": "WorkerPool.java:96"
        },
        {
          "method": "org.eclipse.core.internal.jobs.Worker.run",
          "source": "Worker.java:83"
        }
      ],
      "number": 0,
      "commentIndex": 0,
      "bugId": "91337",
      "duplicateId": "91291",
      "date": "2005-04-13T21:13:51+02:00",
      "product": "Platform",
      "component": "Runtime",
      "severity": "normal"
    }
  ],
  "groupId": "91291",
  "bugId": "91337",
  "duplicateId": "91291",
  "date": "2005-04-13T21:13:51+02:00",
  "product": "Platform",
  "component": "Runtime",
  "severity": "normal"
}