{
  "comments": [
    "The flexible project wizard (launched from new EAR) is not displaying validation\nwarnings. e.g. \"You must enter a proejct name\", \"that is not a valid project\nname\", etc.  Also if you enter a . there are null pointers when attempting to\nvalidate the path:\n\n!ENTRY org.eclipse.ui 4 0 2005-04-15 10:36:57.908\n!MESSAGE Path for project must have only one segment.\n!STACK 0\njava.lang.IllegalArgumentException: Path for project must have only one segment.\n        at org.eclipse.core.internal.utils.Assert.isLegal(Assert.java:60)\n        at\norg.eclipse.core.internal.resources.WorkspaceRoot.getProject(WorkspaceRoot.java:133)\n        at\norg.eclipse.jem.util.emf.workbench.ProjectUtilities.getProject(ProjectUtilities.java:723)\n        at\norg.eclipse.jst.j2ee.application.internal.operations.FlexibleProjectCreationDataModel.validateProjectName(Fle\nxibleProjectCreationDataModel.java:70)\n        at\norg.eclipse.jst.j2ee.application.internal.operations.FlexibleProjectCreationDataModel.doValidateProperty(Flex\nibleProjectCreationDataModel.java:62)\n        at\norg.eclipse.wst.common.frameworks.internal.operations.WTPOperationDataModel.validateProperty(WTPOperationData\nModel.java:949)\n        at\norg.eclipse.wst.common.frameworks.internal.ui.WTPWizardPage.validateProperty(WTPWizardPage.java:306)\n        at\norg.eclipse.wst.common.frameworks.internal.ui.WTPWizardPage.validateControlsBase(WTPWizardPage.java:292)\n        at\norg.eclipse.wst.common.frameworks.internal.ui.WTPWizardPage.validatePage(WTPWizardPage.java:269)\n        at\norg.eclipse.wst.common.frameworks.internal.ui.WTPWizardPage.validatePage(WTPWizardPage.java:262)\n        at\norg.eclipse.wst.common.frameworks.internal.ui.WTPWizardPage.propertyChanged(WTPWizardPage.java:361)\n        at\norg.eclipse.wst.common.frameworks.internal.operations.WTPOperationDataModel.notifyListeners(WTPOperationDataM\nodel.java:817)\n        at\norg.eclipse.wst.common.frameworks.internal.operations.WTPOperationDataModel.notifyListeners(WTPOperationDataM\nodel.java:802)\n        at\norg.eclipse.wst.common.frameworks.internal.operations.WTPOperationDataModel.internalSetProperty(WTPOperationD\nataModel.java:763)\n        at\norg.eclipse.wst.common.frameworks.internal.operations.WTPOperationDataModel.setProperty(WTPOperationDataModel\n.java:741)\n        at\norg.eclipse.wst.common.frameworks.internal.ui.WTPDataModelSynchHelper.setProperty(WTPDataModelSynchHelper.jav\na:176)\n        at\norg.eclipse.wst.common.frameworks.internal.ui.WTPDataModelSynchHelper$ModifyTextListener.modifyText(WTPDataMo\ndelSynchHelper.java:69)\n        at\norg.eclipse.swt.widgets.TypedListener.handleEvent(TypedListener.java(Compiled Code))\n        at org.eclipse.swt.widgets.EventTable.sendEvent(EventTable.java(Compiled\nCode))\n        at org.eclipse.swt.widgets.Widget.sendEvent(Widget.java(Inlined Compiled\nCode))\n        at org.eclipse.swt.widgets.Widget.sendEvent(Widget.java(Compiled Code))\n        at org.eclipse.swt.widgets.Widget.sendEvent(Widget.java(Compiled Code))\n        at org.eclipse.swt.widgets.Text.wmCommandChild(Text.java:2019)\n        at org.eclipse.swt.widgets.Control.WM_COMMAND(Control.java:3155)\n        at org.eclipse.swt.widgets.Control.windowProc(Control.java(Compiled Code))\n        at org.eclipse.swt.widgets.Display.windowProc(Display.java(Compiled Code))\n        at org.eclipse.swt.internal.win32.OS.CallWindowProcW(Native Method)\n        at org.eclipse.swt.internal.win32.OS.CallWindowProc(OS.java(Inlined\nCompiled Code))\n        at org.eclipse.swt.widgets.Text.callWindowProc(Text.java(Compiled Code))\n        at org.eclipse.swt.widgets.Control.windowProc(Control.java(Compiled Code))\n        at org.eclipse.swt.widgets.Text.windowProc(Text.java(Compiled Code))\n        at org.eclipse.swt.widgets.Display.windowProc(Display.java(Compiled Code))\n        at org.eclipse.swt.internal.win32.OS.DispatchMessageW(Native Method)",
    "Fixed",
    "There are still a few more problems here.  \"You must enter a proejct name\" (or\nsomething to the effect) should be displayed if there is no project name entered\n(but not when the wizard first shows up).  Also, the wizard thinks whitespace is\nvalild.",
    "Just assigning to specific component based on abstract.",
    "attempting to set back to previous assigned owner after changing component",
    "Fixed",
    "This is still broken.  try entering ... for the project name and hitting finish.",
    "Project name ending with periods is a bug from base eclipse, i have opened \na defect  https://bugs.eclipse.org/bugs/show_bug.cgi?id\u003d97712",
    "Changed Version field given new release numbering.\n",
    "closing"
  ],
  "commentCreationDates": [
    "2005-04-15T16:40:41+02:00",
    "2005-04-19T22:42:38+02:00",
    "2005-04-22T17:56:20+02:00",
    "2005-04-24T07:06:58+02:00",
    "2005-04-24T20:30:04+02:00",
    "2005-06-13T15:47:34+02:00",
    "2005-06-14T19:22:35+02:00",
    "2005-06-14T20:36:03+02:00",
    "2005-06-15T07:32:10+02:00",
    "2005-06-16T18:59:53+02:00"
  ],
  "traces": [
    {
      "exceptionType": "java.lang.IllegalArgumentException",
      "message": "Path for project must have only one segment.",
      "elements": [
        {
          "method": "org.eclipse.core.internal.utils.Assert.isLegal",
          "source": "Assert.java:60"
        },
        {
          "method": "org.eclipse.core.internal.resources.WorkspaceRoot.getProject",
          "source": "WorkspaceRoot.java:133"
        },
        {
          "method": "org.eclipse.jem.util.emf.workbench.ProjectUtilities.getProject",
          "source": "ProjectUtilities.java:723"
        },
        {
          "method": "org.eclipse.jst.j2ee.application.internal.operations.FlexibleProjectCreationDataModel.validateProjectName",
          "source": "Fle xibleProjectCreationDataModel.java:70"
        },
        {
          "method": "org.eclipse.jst.j2ee.application.internal.operations.FlexibleProjectCreationDataModel.doValidateProperty",
          "source": "Flex ibleProjectCreationDataModel.java:62"
        },
        {
          "method": "org.eclipse.wst.common.frameworks.internal.operations.WTPOperationDataModel.validateProperty",
          "source": "WTPOperationData Model.java:949"
        },
        {
          "method": "org.eclipse.wst.common.frameworks.internal.ui.WTPWizardPage.validateProperty",
          "source": "WTPWizardPage.java:306"
        },
        {
          "method": "org.eclipse.wst.common.frameworks.internal.ui.WTPWizardPage.validateControlsBase",
          "source": "WTPWizardPage.java:292"
        },
        {
          "method": "org.eclipse.wst.common.frameworks.internal.ui.WTPWizardPage.validatePage",
          "source": "WTPWizardPage.java:269"
        },
        {
          "method": "org.eclipse.wst.common.frameworks.internal.ui.WTPWizardPage.validatePage",
          "source": "WTPWizardPage.java:262"
        },
        {
          "method": "org.eclipse.wst.common.frameworks.internal.ui.WTPWizardPage.propertyChanged",
          "source": "WTPWizardPage.java:361"
        },
        {
          "method": "org.eclipse.wst.common.frameworks.internal.operations.WTPOperationDataModel.notifyListeners",
          "source": "WTPOperationDataM odel.java:817"
        },
        {
          "method": "org.eclipse.wst.common.frameworks.internal.operations.WTPOperationDataModel.notifyListeners",
          "source": "WTPOperationDataM odel.java:802"
        },
        {
          "method": "org.eclipse.wst.common.frameworks.internal.operations.WTPOperationDataModel.internalSetProperty",
          "source": "WTPOperationD ataModel.java:763"
        },
        {
          "method": "org.eclipse.wst.common.frameworks.internal.operations.WTPOperationDataModel.setProperty",
          "source": "WTPOperationDataModel .java:741"
        },
        {
          "method": "org.eclipse.wst.common.frameworks.internal.ui.WTPDataModelSynchHelper.setProperty",
          "source": "WTPDataModelSynchHelper.jav a:176"
        },
        {
          "method": "org.eclipse.wst.common.frameworks.internal.ui.WTPDataModelSynchHelper$ModifyTextListener.modifyText",
          "source": "WTPDataMo delSynchHelper.java:69"
        },
        {
          "method": "org.eclipse.swt.widgets.TypedListener.handleEvent",
          "source": "TypedListener.java(Compiled Code)"
        },
        {
          "method": "org.eclipse.swt.widgets.EventTable.sendEvent",
          "source": "EventTable.java(Compiled Code)"
        },
        {
          "method": "org.eclipse.swt.widgets.Widget.sendEvent",
          "source": "Widget.java(Inlined Compiled Code)"
        },
        {
          "method": "org.eclipse.swt.widgets.Widget.sendEvent",
          "source": "Widget.java(Compiled Code)"
        },
        {
          "method": "org.eclipse.swt.widgets.Widget.sendEvent",
          "source": "Widget.java(Compiled Code)"
        },
        {
          "method": "org.eclipse.swt.widgets.Text.wmCommandChild",
          "source": "Text.java:2019"
        },
        {
          "method": "org.eclipse.swt.widgets.Control.WM_COMMAND",
          "source": "Control.java:3155"
        },
        {
          "method": "org.eclipse.swt.widgets.Control.windowProc",
          "source": "Control.java(Compiled Code)"
        },
        {
          "method": "org.eclipse.swt.widgets.Display.windowProc",
          "source": "Display.java(Compiled Code)"
        },
        {
          "method": "org.eclipse.swt.internal.win32.OS.CallWindowProcW",
          "source": "Native Method"
        },
        {
          "method": "org.eclipse.swt.internal.win32.OS.CallWindowProc",
          "source": "OS.java(Inlined Compiled Code)"
        },
        {
          "method": "org.eclipse.swt.widgets.Text.callWindowProc",
          "source": "Text.java(Compiled Code)"
        },
        {
          "method": "org.eclipse.swt.widgets.Control.windowProc",
          "source": "Control.java(Compiled Code)"
        },
        {
          "method": "org.eclipse.swt.widgets.Text.windowProc",
          "source": "Text.java(Compiled Code)"
        },
        {
          "method": "org.eclipse.swt.widgets.Display.windowProc",
          "source": "Display.java(Compiled Code)"
        },
        {
          "method": "org.eclipse.swt.internal.win32.OS.DispatchMessageW",
          "source": "Native Method"
        }
      ],
      "number": 0,
      "commentIndex": 0,
      "bugId": "91541",
      "date": "2005-04-15T16:40:41+02:00",
      "product": "Web Tools",
      "component": "jst.j2ee",
      "severity": "normal"
    }
  ],
  "groupId": "91541",
  "bugId": "91541",
  "date": "2005-04-15T16:40:41+02:00",
  "product": "Web Tools",
  "component": "jst.j2ee",
  "severity": "normal"
}