{
  "comments": [
    "Using Mac OS X 10.3.8\n\n\n!ENTRY org.eclipse.osgi Apr 16, 2005 12:16:30.966\n!MESSAGE Application error\n!STACK 1\njava.lang.NoClassDefFoundError: org/eclipse/core/resources/IProject\n        at\norg.eclipse.ui.internal.ide.model.WorkbenchAdapterFactory.\u003cinit\u003e(WorkbenchAdapterFactory.java:26)\n        at\norg.eclipse.ui.internal.ide.model.WorkbenchAdapterBuilder.registerAdapters(WorkbenchAdapterBuilder.java:33)\n        at\norg.eclipse.ui.internal.ide.IDEWorkbenchAdvisor.initialize(IDEWorkbenchAdvisor.java:155)\n        at\norg.eclipse.ui.application.WorkbenchAdvisor.internalBasicInitialize(WorkbenchAdvisor.java:165)\n        at org.eclipse.ui.internal.Workbench.init(Workbench.java:789)\n        at org.eclipse.ui.internal.Workbench.runUI(Workbench.java:1325)\n        at\norg.eclipse.ui.internal.Workbench.createAndRunWorkbench(Workbench.java:254)\n        at org.eclipse.ui.PlatformUI.createAndRunWorkbench(PlatformUI.java:141)\n        at org.eclipse.ui.internal.ide.IDEApplication.run(IDEApplication.java:96)\n        at\norg.eclipse.core.internal.runtime.PlatformActivator$1.run(PlatformActivator.java:335)\n        at\norg.eclipse.core.runtime.adaptor.EclipseStarter.run(EclipseStarter.java:273)\n        at\norg.eclipse.core.runtime.adaptor.EclipseStarter.run(EclipseStarter.java:129)\n        at sun.reflect.NativeMethodAccessorImpl.invoke0(Native Method)\n        at\nsun.reflect.NativeMethodAccessorImpl.invoke(NativeMethodAccessorImpl.java:39)\n        at\nsun.reflect.DelegatingMethodAccessorImpl.invoke(DelegatingMethodAccessorImpl.java:25)\n        at java.lang.reflect.Method.invoke(Method.java:324)\n        at org.eclipse.core.launcher.Main.basicRun(Main.java:185)\n        at org.eclipse.core.launcher.Main.run(Main.java:704)\n        at org.eclipse.core.launcher.Main.main(Main.java:688)",
    "Correction: This bug is in version 3.0.2 but there is no Version choice for that\nhere in bugzilla.",
    "It looks like I have been able to work around this by creating a new workspace\nand copying projects of .metadata/.plugins/org.eclipse.core.resources/.projects\nover.\n\nI now consider that this issue is more of the error message being rather\nunhelpful, at least to me, so I\u0027m lowering the sevrity to minor. It\u0027s more than\npossible that someone with more experience would be able to tell just what went\nwrong from the error.",
    "Is that the only information in your log file?  Please attach the entire\nworkspace/.metadata/.log file if still available.  The NoClassDefFoundError was\nlikely caused by the owning plugin (org.eclipse.core.resource) failing to start.\n That fail should also be recorded in the log.",
    "Requested details not provided; closing."
  ],
  "commentCreationDates": [
    "2005-04-16T21:19:16+02:00",
    "2005-04-16T21:28:09+02:00",
    "2005-04-17T04:39:18+02:00",
    "2005-04-18T17:13:29+02:00",
    "2005-05-02T17:28:47+02:00"
  ],
  "traces": [
    {
      "exceptionType": "java.lang.NoClassDefFoundError",
      "message": "org/eclipse/core/resources/IProject",
      "elements": [
        {
          "method": "org.eclipse.ui.internal.ide.model.WorkbenchAdapterFactory.\u003cinit\u003e",
          "source": "WorkbenchAdapterFactory.java:26"
        },
        {
          "method": "org.eclipse.ui.internal.ide.model.WorkbenchAdapterBuilder.registerAdapters",
          "source": "WorkbenchAdapterBuilder.java:33"
        },
        {
          "method": "org.eclipse.ui.internal.ide.IDEWorkbenchAdvisor.initialize",
          "source": "IDEWorkbenchAdvisor.java:155"
        },
        {
          "method": "org.eclipse.ui.application.WorkbenchAdvisor.internalBasicInitialize",
          "source": "WorkbenchAdvisor.java:165"
        },
        {
          "method": "org.eclipse.ui.internal.Workbench.init",
          "source": "Workbench.java:789"
        },
        {
          "method": "org.eclipse.ui.internal.Workbench.runUI",
          "source": "Workbench.java:1325"
        },
        {
          "method": "org.eclipse.ui.internal.Workbench.createAndRunWorkbench",
          "source": "Workbench.java:254"
        },
        {
          "method": "org.eclipse.ui.PlatformUI.createAndRunWorkbench",
          "source": "PlatformUI.java:141"
        },
        {
          "method": "org.eclipse.ui.internal.ide.IDEApplication.run",
          "source": "IDEApplication.java:96"
        },
        {
          "method": "org.eclipse.core.internal.runtime.PlatformActivator$1.run",
          "source": "PlatformActivator.java:335"
        },
        {
          "method": "org.eclipse.core.runtime.adaptor.EclipseStarter.run",
          "source": "EclipseStarter.java:273"
        },
        {
          "method": "org.eclipse.core.runtime.adaptor.EclipseStarter.run",
          "source": "EclipseStarter.java:129"
        },
        {
          "method": "sun.reflect.NativeMethodAccessorImpl.invoke0",
          "source": "Native Method"
        },
        {
          "method": "sun.reflect.NativeMethodAccessorImpl.invoke",
          "source": "NativeMethodAccessorImpl.java:39"
        },
        {
          "method": "sun.reflect.DelegatingMethodAccessorImpl.invoke",
          "source": "DelegatingMethodAccessorImpl.java:25"
        },
        {
          "method": "java.lang.reflect.Method.invoke",
          "source": "Method.java:324"
        },
        {
          "method": "org.eclipse.core.launcher.Main.basicRun",
          "source": "Main.java:185"
        },
        {
          "method": "org.eclipse.core.launcher.Main.run",
          "source": "Main.java:704"
        },
        {
          "method": "org.eclipse.core.launcher.Main.main",
          "source": "Main.java:688"
        }
      ],
      "number": 0,
      "commentIndex": 0,
      "bugId": "91659",
      "date": "2005-04-16T21:19:16+02:00",
      "product": "Platform",
      "component": "Resources",
      "severity": "minor"
    }
  ],
  "groupId": "91659",
  "bugId": "91659",
  "date": "2005-04-16T21:19:16+02:00",
  "product": "Platform",
  "component": "Resources",
  "severity": "minor"
}