{
  "comments": [
    "Found in 3.1M6.  The following classes/interfaces, each in separate files:\n\npublic interface A\u003c K extends A.BK\u003c S \u003e, S extends A.BS \u003e\n{\n    public interface BS extends Serializable { }\n    public interface BK\u003c SS \u003e extends Serializable {\n        public void put( SS a );\n    }\n    \n    public P\u003c K, S \u003e getP( );\n}\n\npublic class P\u003c K extends A.BK\u003c S \u003e, S extends A.BS \u003e\n{\n    K k;\n    S s;\n    \n    public void put( )\n    {\n        k.put( s );\n    }\n}\n\npublic class C\u003c T \u003e implements A\u003c C.K, C.S \u003e\n{\n    public static class K implements A.BK\u003c C.S \u003e {\n        public void put( S a )\n        {\n        }\n    }\n    protected static class S implements A.BS { }\n    \n    public P\u003c K, S \u003e getP( )\n    {\n        return null;\n    }\n}\n\nCompile without error under javac, as well as with a full-build after a clean. \nWhen auto-built however they generate spurious bound mismatch errors.\n\nFurther, though these small examples do NOT generate it, a larger project with\nsimilar code caused an NPE during every auto-build:\n\nWarning 2005-04-17 13:21:45.78 java.lang.NullPointerException encountered while\nrunning Java Builder.\njava.lang.NullPointerException\nat\norg.eclipse.jdt.internal.compiler.ast.QualifiedAllocationExpression.resolveType(QualifiedAllocationExpression.java:239)\nat\norg.eclipse.jdt.internal.compiler.ast.MessageSend.resolveType(MessageSend.java:291)\nat org.eclipse.jdt.internal.compiler.ast.Expression.resolve(Expression.java:780)\nat\norg.eclipse.jdt.internal.compiler.ast.AbstractMethodDeclaration.resolveStatements(AbstractMethodDeclaration.java:415)\nat\norg.eclipse.jdt.internal.compiler.ast.MethodDeclaration.resolveStatements(MethodDeclaration.java:167)\nat\norg.eclipse.jdt.internal.compiler.ast.AbstractMethodDeclaration.resolve(AbstractMethodDeclaration.java:393)\nat\norg.eclipse.jdt.internal.compiler.ast.TypeDeclaration.resolve(TypeDeclaration.java:1061)\nat\norg.eclipse.jdt.internal.compiler.ast.TypeDeclaration.resolve(TypeDeclaration.java:1110)\nat\norg.eclipse.jdt.internal.compiler.ast.CompilationUnitDeclaration.resolve(CompilationUnitDeclaration.java:300)\nat org.eclipse.jdt.internal.compiler.Compiler.process(Compiler.java:510)\nat org.eclipse.jdt.internal.compiler.Compiler.compile(Compiler.java:335)\nat\norg.eclipse.jdt.internal.core.builder.AbstractImageBuilder.compile(AbstractImageBuilder.java:239)\nat\norg.eclipse.jdt.internal.core.builder.AbstractImageBuilder.compile(AbstractImageBuilder.java:189)\nat\norg.eclipse.jdt.internal.core.builder.IncrementalImageBuilder.build(IncrementalImageBuilder.java:113)\nat\norg.eclipse.jdt.internal.core.builder.JavaBuilder.buildDeltas(JavaBuilder.java:223)\nat org.eclipse.jdt.internal.core.builder.JavaBuilder.build(JavaBuilder.java:151)\nat org.eclipse.core.internal.events.BuildManager$2.run(BuildManager.java:581)\nat\norg.eclipse.core.internal.runtime.InternalPlatform.run(InternalPlatform.java:1021)\nat org.eclipse.core.runtime.Platform.run(Platform.java:757)\nat org.eclipse.core.internal.events.BuildManager.basicBuild(BuildManager.java:160)\nat org.eclipse.core.internal.events.BuildManager.basicBuild(BuildManager.java:198)\nat org.eclipse.core.internal.events.BuildManager$1.run(BuildManager.java:227)\nat\norg.eclipse.core.internal.runtime.InternalPlatform.run(InternalPlatform.java:1021)\nat org.eclipse.core.runtime.Platform.run(Platform.java:757)\nat org.eclipse.core.internal.events.BuildManager.basicBuild(BuildManager.java:230)\nat\norg.eclipse.core.internal.events.BuildManager.basicBuildLoop(BuildManager.java:249)\nat org.eclipse.core.internal.events.BuildManager.build(BuildManager.java:278)\nat org.eclipse.core.internal.events.AutoBuildJob.doBuild(AutoBuildJob.java:139)\nat org.eclipse.core.internal.events.AutoBuildJob.run(AutoBuildJob.java:200)\nat org.eclipse.core.internal.jobs.Worker.run(Worker.java:67)\n\nThis NPE stopped occuring after a restart of Eclipse.\n\nAlso the errors reported would be corrupt: a bound mismatch error was reported\nwith a line number of 0, and another (which only appeared in the editor, not the\nproblem view) would have a nonsensical description of \"implements\nsome.class.method\".  I believe the 0-line error then prevented the type from\nbeing compiled at all, resulting in a huge number of \"cannot be resolved\" errors.",
    "Your guess is right. Dup.\nAdded GenericTypeTest#test611\n\n*** This bug has been marked as a duplicate of 90881 ***",
    "I downloaded I20050414-1107 and the bound error is still present; I assume the\nfix didn\u0027t make it into that I-build.  Will it make the next I-build or should I\njust wait until the bug is marked verified?",
    "It isn\u0027t released to HEAD yet, as it is part of a group of changes which are\nbeing worked on at once (near capture conversion).\nIt should be released soon (understand during this week, but likely after the\nnext integration build)."
  ],
  "commentCreationDates": [
    "2005-04-17T23:19:31+02:00",
    "2005-04-18T09:25:37+02:00",
    "2005-04-18T20:50:54+02:00",
    "2005-04-18T21:19:21+02:00"
  ],
  "traces": [
    {
      "exceptionType": "java.lang.NullPointerException",
      "elements": [
        {
          "method": "org.eclipse.jdt.internal.compiler.ast.QualifiedAllocationExpression.resolveType",
          "source": "QualifiedAllocationExpression.java:239"
        },
        {
          "method": "org.eclipse.jdt.internal.compiler.ast.MessageSend.resolveType",
          "source": "MessageSend.java:291"
        },
        {
          "method": "org.eclipse.jdt.internal.compiler.ast.Expression.resolve",
          "source": "Expression.java:780"
        },
        {
          "method": "org.eclipse.jdt.internal.compiler.ast.AbstractMethodDeclaration.resolveStatements",
          "source": "AbstractMethodDeclaration.java:415"
        },
        {
          "method": "org.eclipse.jdt.internal.compiler.ast.MethodDeclaration.resolveStatements",
          "source": "MethodDeclaration.java:167"
        },
        {
          "method": "org.eclipse.jdt.internal.compiler.ast.AbstractMethodDeclaration.resolve",
          "source": "AbstractMethodDeclaration.java:393"
        },
        {
          "method": "org.eclipse.jdt.internal.compiler.ast.TypeDeclaration.resolve",
          "source": "TypeDeclaration.java:1061"
        },
        {
          "method": "org.eclipse.jdt.internal.compiler.ast.TypeDeclaration.resolve",
          "source": "TypeDeclaration.java:1110"
        },
        {
          "method": "org.eclipse.jdt.internal.compiler.ast.CompilationUnitDeclaration.resolve",
          "source": "CompilationUnitDeclaration.java:300"
        },
        {
          "method": "org.eclipse.jdt.internal.compiler.Compiler.process",
          "source": "Compiler.java:510"
        },
        {
          "method": "org.eclipse.jdt.internal.compiler.Compiler.compile",
          "source": "Compiler.java:335"
        },
        {
          "method": "org.eclipse.jdt.internal.core.builder.AbstractImageBuilder.compile",
          "source": "AbstractImageBuilder.java:239"
        },
        {
          "method": "org.eclipse.jdt.internal.core.builder.AbstractImageBuilder.compile",
          "source": "AbstractImageBuilder.java:189"
        },
        {
          "method": "org.eclipse.jdt.internal.core.builder.IncrementalImageBuilder.build",
          "source": "IncrementalImageBuilder.java:113"
        },
        {
          "method": "org.eclipse.jdt.internal.core.builder.JavaBuilder.buildDeltas",
          "source": "JavaBuilder.java:223"
        },
        {
          "method": "org.eclipse.jdt.internal.core.builder.JavaBuilder.build",
          "source": "JavaBuilder.java:151"
        },
        {
          "method": "org.eclipse.core.internal.events.BuildManager$2.run",
          "source": "BuildManager.java:581"
        },
        {
          "method": "org.eclipse.core.internal.runtime.InternalPlatform.run",
          "source": "InternalPlatform.java:1021"
        },
        {
          "method": "org.eclipse.core.runtime.Platform.run",
          "source": "Platform.java:757"
        },
        {
          "method": "org.eclipse.core.internal.events.BuildManager.basicBuild",
          "source": "BuildManager.java:160"
        },
        {
          "method": "org.eclipse.core.internal.events.BuildManager.basicBuild",
          "source": "BuildManager.java:198"
        },
        {
          "method": "org.eclipse.core.internal.events.BuildManager$1.run",
          "source": "BuildManager.java:227"
        },
        {
          "method": "org.eclipse.core.internal.runtime.InternalPlatform.run",
          "source": "InternalPlatform.java:1021"
        },
        {
          "method": "org.eclipse.core.runtime.Platform.run",
          "source": "Platform.java:757"
        },
        {
          "method": "org.eclipse.core.internal.events.BuildManager.basicBuild",
          "source": "BuildManager.java:230"
        },
        {
          "method": "org.eclipse.core.internal.events.BuildManager.basicBuildLoop",
          "source": "BuildManager.java:249"
        },
        {
          "method": "org.eclipse.core.internal.events.BuildManager.build",
          "source": "BuildManager.java:278"
        },
        {
          "method": "org.eclipse.core.internal.events.AutoBuildJob.doBuild",
          "source": "AutoBuildJob.java:139"
        },
        {
          "method": "org.eclipse.core.internal.events.AutoBuildJob.run",
          "source": "AutoBuildJob.java:200"
        },
        {
          "method": "org.eclipse.core.internal.jobs.Worker.run",
          "source": "Worker.java:67"
        }
      ],
      "number": 0,
      "commentIndex": 0,
      "bugId": "91696",
      "duplicateId": "90881",
      "date": "2005-04-17T23:19:31+02:00",
      "product": "JDT",
      "component": "Core",
      "severity": "normal"
    }
  ],
  "groupId": "90881",
  "bugId": "91696",
  "duplicateId": "90881",
  "date": "2005-04-17T23:19:31+02:00",
  "product": "JDT",
  "component": "Core",
  "severity": "normal"
}