{
  "comments": [
    "JDT/Core HEAD from 04/19\n\nAfter patching with JDT/Core, and restarting workspace (multi-window) I got the\nfollowing deadlock (thread dump).\n\njava.lang.ClassCircularityError: org/eclipse/pde/internal/core/WorkspaceModelManager\n        at org.eclipse.pde.internal.core.PDECore.initializeModels(PDECore.java:376)\n        at org.eclipse.pde.internal.core.PDECore.getModelManager(PDECore.java:301)\n        at\norg.eclipse.pde.internal.core.RequiredPluginsInitializer.initialize(RequiredPluginsInitializer.java:36)\n        at\norg.eclipse.jdt.internal.core.JavaModelManager.initializeContainer(JavaModelManager.java:1416)\n        at\norg.eclipse.jdt.internal.core.JavaModelManager.getClasspathContainer(JavaModelManager.java:971)\n        at org.eclipse.jdt.core.JavaCore.getClasspathContainer(JavaCore.java:1304)\n        at\norg.eclipse.jdt.internal.core.JavaProject.getResolvedClasspath(JavaProject.java:2065)\n        at\norg.eclipse.jdt.internal.core.JavaProject.getResolvedClasspath(JavaProject.java:1973)\n        at\norg.eclipse.jdt.internal.core.JavaProject.isOnClasspath(JavaProject.java:2251)\n        at\norg.eclipse.jdt.internal.ui.javaeditor.CompilationUnitDocumentProvider$CompilationUnitAnnotationModel.internalBeginReporting(CompilationUnitDocumentP\nrovider.java:467)\n        at\norg.eclipse.jdt.internal.ui.javaeditor.CompilationUnitDocumentProvider$CompilationUnitAnnotationModel.beginReportingSequence(CompilationUnitDocumentP\nrovider.java:457)\n        at\norg.eclipse.jdt.internal.ui.text.JavaCompositeReconcilingStrategy.initialReconcile(JavaCompositeReconcilingStrategy.java:119)\n        at\norg.eclipse.jface.text.reconciler.MonoReconciler.initialProcess(MonoReconciler.java:103)\n        at\norg.eclipse.jdt.internal.ui.text.JavaReconciler.initialProcess(JavaReconciler.java:307)\n        at\norg.eclipse.jface.text.reconciler.AbstractReconciler$BackgroundThread.run(AbstractReconciler.java:170)\nFull thread dump Java HotSpot(TM) Client VM (1.4.2_08-b03 mixed mode):\n\n\"org.eclipse.jdt.internal.ui.text.JavaReconciler\" daemon prio\u003d2 tid\u003d0x033f2a48\nnid\u003d0xc88 waiting for monitor entry [541f000..541fd8c]\n        at\norg.eclipse.jdt.internal.ui.text.java.JavaReconcilingStrategy.reconcile(JavaReconcilingStrategy.java:90)\n        - waiting to lock \u003c0x168fa708\u003e (a\norg.eclipse.jdt.internal.core.CompilationUnit)\n        at\norg.eclipse.jdt.internal.ui.text.java.JavaReconcilingStrategy.initialReconcile(JavaReconcilingStrategy.java:160)\n        at\norg.eclipse.jdt.internal.ui.text.CompositeReconcilingStrategy.initialReconcile(CompositeReconcilingStrategy.java:114)\n        at\norg.eclipse.jdt.internal.ui.text.JavaCompositeReconcilingStrategy.initialReconcile(JavaCompositeReconcilingStrategy.java:120)\n        at\norg.eclipse.jface.text.reconciler.MonoReconciler.initialProcess(MonoReconciler.java:103)\n        at\norg.eclipse.jdt.internal.ui.text.JavaReconciler.initialProcess(JavaReconciler.java:307)\n        - locked \u003c0x179bacd0\u003e (a java.lang.Object)\n        at\norg.eclipse.jface.text.reconciler.AbstractReconciler$BackgroundThread.run(AbstractReconciler.java:170)\n\n\"org.eclipse.jdt.internal.ui.text.JavaReconciler\" daemon prio\u003d2 tid\u003d0x033d6b00\nnid\u003d0xc60 in Object.wait() [52af000..52afd8c]\n        at java.lang.Object.wait(Native Method)\n        - waiting on \u003c0x17475aa8\u003e (a\norg.eclipse.jface.text.reconciler.DirtyRegionQueue)\n        at\norg.eclipse.jface.text.reconciler.AbstractReconciler$BackgroundThread.run(AbstractReconciler.java:176)\n        - locked \u003c0x17475aa8\u003e (a org.eclipse.jface.text.reconciler.DirtyRegionQueue)\n\n\"org.eclipse.jdt.internal.ui.text.JavaReconciler\" daemon prio\u003d2 tid\u003d0x041dcd88\nnid\u003d0xd60 in Object.wait() [4f4f000..4f4fd8c]\n        at java.lang.Object.wait(Native Method)\n        - waiting on \u003c0x17b3c308\u003e (a org.eclipse.core.internal.jobs.ThreadJob)\n        at org.eclipse.core.internal.jobs.ThreadJob.joinRun(ThreadJob.java:160)\n        - locked \u003c0x17b3c308\u003e (a org.eclipse.core.internal.jobs.ThreadJob)\n        at org.eclipse.core.internal.jobs.ImplicitJobs.begin(ImplicitJobs.java:88)\n        at org.eclipse.core.internal.jobs.JobManager.beginRule(JobManager.java:186)\n        at\norg.eclipse.core.internal.resources.WorkManager.checkIn(WorkManager.java:96)\n        at\norg.eclipse.core.internal.resources.Workspace.prepareOperation(Workspace.java:1669)\n        at org.eclipse.core.internal.resources.Workspace.run(Workspace.java:1709)\n        at\norg.eclipse.jdt.internal.core.JavaModelOperation.runOperation(JavaModelOperation.java:782)\n        at\norg.eclipse.jdt.internal.core.JavaProject.setRawClasspath(JavaProject.java:2771)\n        at org.eclipse.jdt.core.JavaCore$3.run(JavaCore.java:3830)\n        at\norg.eclipse.jdt.internal.core.BatchOperation.executeOperation(BatchOperation.java:39)\n        at\norg.eclipse.jdt.internal.core.JavaModelOperation.run(JavaModelOperation.java:718)\n        at org.eclipse.core.internal.resources.Workspace.run(Workspace.java:1714)\n        at org.eclipse.jdt.core.JavaCore.run(JavaCore.java:3639)\n        at org.eclipse.jdt.core.JavaCore.setClasspathContainer(JavaCore.java:3813)\n        at\norg.eclipse.pde.internal.core.ModelEntry.updateClasspathContainer(ModelEntry.java:110)\n        at\norg.eclipse.pde.internal.core.RequiredPluginsInitializer.initialize(RequiredPluginsInitializer.java:40)\n        at\norg.eclipse.jdt.internal.core.JavaModelManager.initializeContainer(JavaModelManager.java:1416)\n        at\norg.eclipse.jdt.internal.core.JavaModelManager.getClasspathContainer(JavaModelManager.java:971)\n        at org.eclipse.jdt.core.JavaCore.getClasspathContainer(JavaCore.java:1304)\n        at\norg.eclipse.jdt.internal.core.JavaProject.getResolvedClasspath(JavaProject.java:2065)\n        at\norg.eclipse.jdt.internal.core.JavaProject.getResolvedClasspath(JavaProject.java:1973)\n        at\norg.eclipse.jdt.internal.core.JavaProject.computePackageFragmentRoots(JavaProject.java:574)\n        at\norg.eclipse.jdt.internal.core.JavaProject.computePackageFragmentRoots(JavaProject.java:647)\n        at\norg.eclipse.jdt.internal.core.JavaProject.computePackageFragmentRoots(JavaProject.java:608)\n        at\norg.eclipse.jdt.internal.core.JavaProject.getAllPackageFragmentRoots(JavaProject.java:1338)\n        at\norg.eclipse.jdt.internal.core.JavaProjectElementInfo.getAllPackageFragmentRoots(JavaProjectElementInfo.java:172)\n        at\norg.eclipse.jdt.internal.core.JavaProjectElementInfo.newNameLookup(JavaProjectElementInfo.java:255)\n        - locked \u003c0x17174fc8\u003e (a\norg.eclipse.jdt.internal.core.JavaProjectElementInfo)\n        at\norg.eclipse.jdt.internal.core.JavaProject.newNameLookup(JavaProject.java:2363)\n        at\norg.eclipse.jdt.internal.core.SearchableEnvironment.\u003cinit\u003e(SearchableEnvironment.java:60)\n        at\norg.eclipse.jdt.internal.core.SearchableEnvironment.\u003cinit\u003e(SearchableEnvironment.java:74)\n        at\norg.eclipse.jdt.internal.core.CancelableNameEnvironment.\u003cinit\u003e(CancelableNameEnvironment.java:26)\n        at\norg.eclipse.jdt.internal.core.CompilationUnitProblemFinder.process(CompilationUnitProblemFinder.java:148)\n        at\norg.eclipse.jdt.internal.core.CompilationUnitProblemFinder.process(CompilationUnitProblemFinder.java:214)\n        at\norg.eclipse.jdt.internal.core.ReconcileWorkingCopyOperation.executeOperation(ReconcileWorkingCopyOperation.java:79)\n        at\norg.eclipse.jdt.internal.core.JavaModelOperation.run(JavaModelOperation.java:718)\n        at\norg.eclipse.jdt.internal.core.JavaModelOperation.runOperation(JavaModelOperation.java:777)\n        at\norg.eclipse.jdt.internal.core.CompilationUnit.reconcile(CompilationUnit.java:1080)\n        at\norg.eclipse.jdt.internal.ui.text.java.JavaReconcilingStrategy.reconcile(JavaReconcilingStrategy.java:91)\n        - locked \u003c0x168fa708\u003e (a org.eclipse.jdt.internal.core.CompilationUnit)\n        at\norg.eclipse.jdt.internal.ui.text.java.JavaReconcilingStrategy.initialReconcile(JavaReconcilingStrategy.java:160)\n        at\norg.eclipse.jdt.internal.ui.text.CompositeReconcilingStrategy.initialReconcile(CompositeReconcilingStrategy.java:114)\n        at\norg.eclipse.jdt.internal.ui.text.JavaCompositeReconcilingStrategy.initialReconcile(JavaCompositeReconcilingStrategy.java:120)\n        at\norg.eclipse.jface.text.reconciler.MonoReconciler.initialProcess(MonoReconciler.java:103)\n        at\norg.eclipse.jdt.internal.ui.text.JavaReconciler.initialProcess(JavaReconciler.java:307)\n        - locked \u003c0x16b29418\u003e (a java.lang.Object)\n        at\norg.eclipse.jface.text.reconciler.AbstractReconciler$BackgroundThread.run(AbstractReconciler.java:170)\n\n\"org.eclipse.jdt.internal.ui.text.JavaReconciler\" daemon prio\u003d2 tid\u003d0x042aca38\nnid\u003d0xdbc in Object.wait() [504f000..504fd8c]\n        at java.lang.Object.wait(Native Method)\n        - waiting on \u003c0x17b3c4a8\u003e (a org.eclipse.core.internal.jobs.ThreadJob)\n        at org.eclipse.core.internal.jobs.ThreadJob.joinRun(ThreadJob.java:160)\n        - locked \u003c0x17b3c4a8\u003e (a org.eclipse.core.internal.jobs.ThreadJob)\n        at org.eclipse.core.internal.jobs.ImplicitJobs.begin(ImplicitJobs.java:88)\n        at org.eclipse.core.internal.jobs.JobManager.beginRule(JobManager.java:186)\n        at\norg.eclipse.core.internal.resources.WorkManager.checkIn(WorkManager.java:96)\n        at\norg.eclipse.core.internal.resources.Workspace.prepareOperation(Workspace.java:1669)\n        at org.eclipse.core.internal.resources.Workspace.run(Workspace.java:1709)\n        at\norg.eclipse.jdt.internal.core.JavaModelOperation.runOperation(JavaModelOperation.java:782)\n        at\norg.eclipse.jdt.internal.core.JavaProject.setRawClasspath(JavaProject.java:2771)\n        at org.eclipse.jdt.core.JavaCore$3.run(JavaCore.java:3830)\n        at\norg.eclipse.jdt.internal.core.BatchOperation.executeOperation(BatchOperation.java:39)\n        at\norg.eclipse.jdt.internal.core.JavaModelOperation.run(JavaModelOperation.java:718)\n        at org.eclipse.core.internal.resources.Workspace.run(Workspace.java:1714)\n        at org.eclipse.jdt.core.JavaCore.run(JavaCore.java:3639)\n        at org.eclipse.jdt.core.JavaCore.setClasspathContainer(JavaCore.java:3813)\n        at\norg.eclipse.pde.internal.core.ModelEntry.updateClasspathContainer(ModelEntry.java:110)\n        at\norg.eclipse.pde.internal.core.RequiredPluginsInitializer.initialize(RequiredPluginsInitializer.java:40)\n        at\norg.eclipse.jdt.internal.core.JavaModelManager.initializeContainer(JavaModelManager.java:1416)\n        at\norg.eclipse.jdt.internal.core.JavaModelManager.getClasspathContainer(JavaModelManager.java:971)\n        at org.eclipse.jdt.core.JavaCore.getClasspathContainer(JavaCore.java:1304)\n        at\norg.eclipse.jdt.internal.core.JavaProject.getResolvedClasspath(JavaProject.java:2065)\n        at\norg.eclipse.jdt.internal.core.JavaProject.getResolvedClasspath(JavaProject.java:1973)\n        at\norg.eclipse.jdt.internal.core.JavaProject.isOnClasspath(JavaProject.java:2251)\n        at\norg.eclipse.jdt.internal.ui.javaeditor.CompilationUnitDocumentProvider$CompilationUnitAnnotationModel.internalBeginReporting(CompilationUnitDocumentP\nrovider.java:467)\n        at\norg.eclipse.jdt.internal.ui.javaeditor.CompilationUnitDocumentProvider$CompilationUnitAnnotationModel.beginReportingSequence(CompilationUnitDocumentP\nrovider.java:457)\n        at\norg.eclipse.jdt.internal.ui.text.JavaCompositeReconcilingStrategy.initialReconcile(JavaCompositeReconcilingStrategy.java:119)\n        at\norg.eclipse.jface.text.reconciler.MonoReconciler.initialProcess(MonoReconciler.java:103)\n        at\norg.eclipse.jdt.internal.ui.text.JavaReconciler.initialProcess(JavaReconciler.java:307)\n        - locked \u003c0x164db338\u003e (a java.lang.Object)\n        at\norg.eclipse.jface.text.reconciler.AbstractReconciler$BackgroundThread.run(AbstractReconciler.java:170)\n\n\"Java indexing\" daemon prio\u003d4 tid\u003d0x03482010 nid\u003d0x57c in Object.wait()\n[4e4f000..4e4fd8c]\n        at java.lang.Object.wait(Native Method)\n        - waiting on \u003c0x16105ee0\u003e (a\norg.eclipse.jdt.internal.core.search.indexing.IndexManager)\n        at java.lang.Object.wait(Object.java:429)\n        at\norg.eclipse.jdt.internal.core.search.processing.JobManager.run(JobManager.java:346)\n        - locked \u003c0x16105ee0\u003e (a\norg.eclipse.jdt.internal.core.search.indexing.IndexManager)\n        at java.lang.Thread.run(Thread.java:534)\n\n\"Worker-0\" prio\u003d5 tid\u003d0x00a74808 nid\u003d0xb74 in Object.wait() [4c1f000..4c1fd8c]\n        at java.lang.Object.wait(Native Method)\n        - waiting on \u003c0x128a77c8\u003e (a org.eclipse.core.internal.jobs.WorkerPool)\n        at org.eclipse.core.internal.jobs.WorkerPool.sleep(WorkerPool.java:168)\n        - locked \u003c0x128a77c8\u003e (a org.eclipse.core.internal.jobs.WorkerPool)\n        at org.eclipse.core.internal.jobs.WorkerPool.startJob(WorkerPool.java:200)\n        at org.eclipse.core.internal.jobs.Worker.run(Worker.java:60)\n\n\"Start Level Event Dispatcher\" daemon prio\u003d5 tid\u003d0x034d2958 nid\u003d0xdc0 in\nObject.wait() [3fcf000..3fcfd8c]\n        at java.lang.Object.wait(Native Method)\n        - waiting on \u003c0x127dcbb0\u003e (a\norg.eclipse.osgi.framework.eventmgr.EventThread)\n        at java.lang.Object.wait(Object.java:429)\n        at\norg.eclipse.osgi.framework.eventmgr.EventThread.getNextEvent(EventThread.java:162)\n        - locked \u003c0x127dcbb0\u003e (a org.eclipse.osgi.framework.eventmgr.EventThread)\n        at org.eclipse.osgi.framework.eventmgr.EventThread.run(EventThread.java:100)\n\n\"OSGi Console\" prio\u003d5 tid\u003d0x034bda50 nid\u003d0xac8 runnable [3ecf000..3ecfd8c]\n        at java.io.FileInputStream.readBytes(Native Method)\n        at java.io.FileInputStream.read(FileInputStream.java:194)\n        at java.io.BufferedInputStream.read1(BufferedInputStream.java:220)\n        at java.io.BufferedInputStream.read(BufferedInputStream.java:277)\n        - locked \u003c0x127806a0\u003e (a java.io.BufferedInputStream)\n        at sun.nio.cs.StreamDecoder$CharsetSD.readBytes(StreamDecoder.java:408)\n        at sun.nio.cs.StreamDecoder$CharsetSD.implRead(StreamDecoder.java:450)\n        at sun.nio.cs.StreamDecoder.read(StreamDecoder.java:182)\n        - locked \u003c0x127db208\u003e (a java.io.InputStreamReader)\n        at java.io.InputStreamReader.read(InputStreamReader.java:167)\n        at java.io.BufferedReader.fill(BufferedReader.java:136)\n        at java.io.BufferedReader.readLine(BufferedReader.java:299)\n        - locked \u003c0x127db208\u003e (a java.io.InputStreamReader)\n        at java.io.BufferedReader.readLine(BufferedReader.java:362)\n        at\norg.eclipse.osgi.framework.internal.core.FrameworkConsole.console(FrameworkConsole.java:273)\n        at\norg.eclipse.osgi.framework.internal.core.FrameworkConsole.console(FrameworkConsole.java:237)\n        at\norg.eclipse.osgi.framework.internal.core.FrameworkConsole.run(FrameworkConsole.java:208)\n        at java.lang.Thread.run(Thread.java:534)\n\n\"Framework Event Dispatcher\" daemon prio\u003d5 tid\u003d0x034a1470 nid\u003d0xf3c in\nObject.wait() [3dcf000..3dcfd8c]\n        at java.lang.Object.wait(Native Method)\n        - waiting on \u003c0x163bfed8\u003e (a org.eclipse.swt.widgets.RunnableLock)\n        at java.lang.Object.wait(Object.java:429)\n        at org.eclipse.swt.widgets.Synchronizer.syncExec(Synchronizer.java:164)\n        - locked \u003c0x163bfed8\u003e (a org.eclipse.swt.widgets.RunnableLock)\n        at org.eclipse.ui.internal.UISynchronizer.syncExec(UISynchronizer.java:28)\n        at org.eclipse.swt.widgets.Display.syncExec(Display.java:3220)\n        at\norg.eclipse.ui.internal.AbstractWorkingSetManager.firePropertyChange(AbstractWorkingSetManager.java:281)\n        at\norg.eclipse.ui.internal.AbstractWorkingSetManager.getUpdater(AbstractWorkingSetManager.java:526)\n        at\norg.eclipse.ui.internal.AbstractWorkingSetManager.bundleChanged(AbstractWorkingSetManager.java:487)\n        - locked \u003c0x15fa6268\u003e (a org.eclipse.ui.internal.WorkingSetManager)\n        at\norg.eclipse.osgi.framework.internal.core.BundleContextImpl.dispatchEvent(BundleContextImpl.java:1205)\n        at\norg.eclipse.osgi.framework.eventmgr.EventManager.dispatchEvent(EventManager.java:186)\n        at org.eclipse.osgi.framework.eventmgr.EventThread.run(EventThread.java:104)\n\n\"State Data Manager\" daemon prio\u003d5 tid\u003d0x00a24848 nid\u003d0xa40 waiting on condition\n[3ccf000..3ccfd8c]\n        at java.lang.Thread.sleep(Native Method)\n        at\norg.eclipse.osgi.internal.resolver.StateManager.run(StateManager.java:187)\n        at java.lang.Thread.run(Thread.java:534)\n\n\"Signal Dispatcher\" daemon prio\u003d10 tid\u003d0x00a49808 nid\u003d0xa44 waiting on condition\n[0..0]\n\n\"YJP CPU Sampler\" daemon prio\u003d5 tid\u003d0x00a237f0 nid\u003d0x8ec runnable [0..0]\n\n\"YJP RequestServer\" daemon prio\u003d5 tid\u003d0x00a11e68 nid\u003d0xf5c runnable\n[369f000..369fd8c]\n        at java.net.PlainSocketImpl.socketAccept(Native Method)\n        at java.net.PlainSocketImpl.accept(PlainSocketImpl.java:353)\n        - locked \u003c0x1277da28\u003e (a java.net.PlainSocketImpl)\n        at java.net.ServerSocket.implAccept(ServerSocket.java:448)\n        at java.net.ServerSocket.accept(ServerSocket.java:419)\n        at com.yourkit.runtime.RequestServer.startServerImpl(RequestServer.java:236)\n        at com.yourkit.runtime.RequestServer.access$000(RequestServer.java:17)\n        at com.yourkit.runtime.RequestServer$1.run(RequestServer.java:61)\n\n\"Finalizer\" daemon prio\u003d9 tid\u003d0x00a1f0b0 nid\u003d0xd80 in Object.wait()\n[2f9f000..2f9fd8c]\n        at java.lang.Object.wait(Native Method)\n        - waiting on \u003c0x1277db50\u003e (a java.lang.ref.ReferenceQueue$Lock)\n        at java.lang.ref.ReferenceQueue.remove(ReferenceQueue.java:111)\n        - locked \u003c0x1277db50\u003e (a java.lang.ref.ReferenceQueue$Lock)\n        at java.lang.ref.ReferenceQueue.remove(ReferenceQueue.java:127)\n        at java.lang.ref.Finalizer$FinalizerThread.run(Finalizer.java:159)\n\n\"Reference Handler\" daemon prio\u003d10 tid\u003d0x00a13688 nid\u003d0xaf0 in Object.wait()\n[2e9f000..2e9fd8c]\n        at java.lang.Object.wait(Native Method)\n        - waiting on \u003c0x1277dbb8\u003e (a java.lang.ref.Reference$Lock)\n        at java.lang.Object.wait(Object.java:429)\n        at java.lang.ref.Reference$ReferenceHandler.run(Reference.java:115)\n        - locked \u003c0x1277dbb8\u003e (a java.lang.ref.Reference$Lock)\n\n\"main\" prio\u003d7 tid\u003d0x00036008 nid\u003d0xf84 waiting for monitor entry [7e000..7fc38]\n        at\norg.eclipse.jdt.internal.core.JavaProjectElementInfo.resetCaches(JavaProjectElementInfo.java:264)\n        - waiting to lock \u003c0x17174fc8\u003e (a\norg.eclipse.jdt.internal.core.JavaProjectElementInfo)\n        at\norg.eclipse.jdt.internal.core.JavaProject.updatePackageFragmentRoots(JavaProject.java:2933)\n        at\norg.eclipse.jdt.internal.core.SetClasspathOperation.executeOperation(SetClasspathOperation.java:261)\n        at\norg.eclipse.jdt.internal.core.JavaModelOperation.run(JavaModelOperation.java:718)\n        at org.eclipse.core.internal.resources.Workspace.run(Workspace.java:1714)\n        at\norg.eclipse.jdt.internal.core.JavaModelOperation.runOperation(JavaModelOperation.java:782)\n        at\norg.eclipse.jdt.internal.core.JavaProject.setRawClasspath(JavaProject.java:2771)\n        at\norg.eclipse.jdt.internal.core.SetClasspathOperation$5.run(SetClasspathOperation.java:684)\n        at\norg.eclipse.jdt.internal.core.JavaModelOperation.runPostActions(JavaModelOperation.java:804)\n        at\norg.eclipse.jdt.internal.core.JavaModelOperation.run(JavaModelOperation.java:721)\n        at org.eclipse.core.internal.resources.Workspace.run(Workspace.java:1714)\n        at org.eclipse.jdt.core.JavaCore.run(JavaCore.java:3639)\n        at org.eclipse.jdt.core.JavaCore.setClasspathContainer(JavaCore.java:3813)\n        at\norg.eclipse.pde.internal.core.ModelEntry.updateClasspathContainer(ModelEntry.java:110)\n        at\norg.eclipse.pde.internal.core.RequiredPluginsInitializer.initialize(RequiredPluginsInitializer.java:40)\n        at\norg.eclipse.jdt.internal.core.JavaModelManager.initializeContainer(JavaModelManager.java:1416)\n        at\norg.eclipse.jdt.internal.core.JavaModelManager.getClasspathContainer(JavaModelManager.java:971)\n        at org.eclipse.jdt.core.JavaCore.getClasspathContainer(JavaCore.java:1304)\n        at\norg.eclipse.jdt.internal.core.JavaProject.getResolvedClasspath(JavaProject.java:2065)\n        at\norg.eclipse.jdt.internal.core.JavaProject.getResolvedClasspath(JavaProject.java:1973)\n        at\norg.eclipse.jdt.internal.core.JavaProject.computePackageFragmentRoots(JavaProject.java:574)\n        at\norg.eclipse.jdt.internal.core.JavaProject.computePackageFragmentRoots(JavaProject.java:647)\n        at\norg.eclipse.jdt.internal.core.JavaProject.computePackageFragmentRoots(JavaProject.java:608)\n        at\norg.eclipse.jdt.internal.core.JavaProject.getAllPackageFragmentRoots(JavaProject.java:1338)\n        at\norg.eclipse.jdt.internal.core.JavaProject.getAllPackageFragmentRoots(JavaProject.java:1333)\n        at\norg.eclipse.jdt.internal.core.JavaProject.findPackageFragmentRoot0(JavaProject.java:1094)\n        at\norg.eclipse.jdt.internal.core.JavaProject.findPackageFragmentRoot(JavaProject.java:1085)\n        at\norg.eclipse.jdt.ui.StandardJavaElementContentProvider.getResources(StandardJavaElementContentProvider.java:297)\n        at\norg.eclipse.jdt.ui.StandardJavaElementContentProvider.getChildren(StandardJavaElementContentProvider.java:176)\n        at\norg.eclipse.jdt.internal.ui.packageview.PackageExplorerContentProvider.getChildren(PackageExplorerContentProvider.java:158)\n        at\norg.eclipse.jdt.ui.StandardJavaElementContentProvider.hasChildren(StandardJavaElementContentProvider.java:221)\n        at\norg.eclipse.jface.viewers.AbstractTreeViewer.isExpandable(AbstractTreeViewer.java:1259)\n        at\norg.eclipse.jdt.internal.ui.viewsupport.ProblemTreeViewer.isExpandable(ProblemTreeViewer.java:159)\n        at\norg.eclipse.jdt.internal.ui.packageview.PackageExplorerPart$PackageExplorerProblemTreeViewer.isExpandable(PackageExplorerPart.java:293)\n        at\norg.eclipse.jface.viewers.AbstractTreeViewer.updatePlus(AbstractTreeViewer.java:1721)\n        at\norg.eclipse.jface.viewers.AbstractTreeViewer.createTreeItem(AbstractTreeViewer.java:433)\n        at\norg.eclipse.jface.viewers.AbstractTreeViewer$1.run(AbstractTreeViewer.java:411)\n        at org.eclipse.swt.custom.BusyIndicator.showWhile(BusyIndicator.java:69)\n        at\norg.eclipse.jface.viewers.AbstractTreeViewer.createChildren(AbstractTreeViewer.java:391)\n        at\norg.eclipse.jface.viewers.AbstractTreeViewer.internalExpand(AbstractTreeViewer.java:971)\n        at\norg.eclipse.jface.viewers.AbstractTreeViewer.internalExpand(AbstractTreeViewer.java:968)\n        at\norg.eclipse.jface.viewers.AbstractTreeViewer.setSelectionToWidget(AbstractTreeViewer.java:1494)\n        at\norg.eclipse.jface.viewers.StructuredViewer.setSelectionToWidget(StructuredViewer.java:1484)\n        at\norg.eclipse.jdt.internal.ui.packageview.PackageExplorerPart$PackageExplorerProblemTreeViewer.setSelectionToWidget(PackageExplorerPart.java:599)\n        at\norg.eclipse.jface.viewers.StructuredViewer.setSelection(StructuredViewer.java:1440)\n        at\norg.eclipse.jdt.internal.ui.packageview.PackageExplorerPart.showInput(PackageExplorerPart.java:1446)\n        at\norg.eclipse.jdt.internal.ui.packageview.PackageExplorerPart.editorActivated(PackageExplorerPart.java:1411)\n        at\norg.eclipse.jdt.internal.ui.packageview.PackageExplorerPart$1.partActivated(PackageExplorerPart.java:210)\n        at org.eclipse.ui.internal.PartListenerList$1.run(PartListenerList.java:72)\n        at\norg.eclipse.core.internal.runtime.InternalPlatform.run(InternalPlatform.java:1021)\n        at org.eclipse.core.runtime.Platform.run(Platform.java:757)\n        at\norg.eclipse.ui.internal.PartListenerList.fireEvent(PartListenerList.java:58)\n        at\norg.eclipse.ui.internal.PartListenerList.firePartActivated(PartListenerList.java:70)\n        at\norg.eclipse.ui.internal.WorkbenchPage.firePartActivated(WorkbenchPage.java:1488)\n        at org.eclipse.ui.internal.WorkbenchPage.onActivate(WorkbenchPage.java:2140)\n        at org.eclipse.ui.internal.WorkbenchWindow$5.run(WorkbenchWindow.java:2350)\n        at org.eclipse.swt.custom.BusyIndicator.showWhile(BusyIndicator.java:69)\n        at\norg.eclipse.ui.internal.WorkbenchWindow.setActivePage(WorkbenchWindow.java:2336)\n        at\norg.eclipse.ui.internal.WorkbenchWindow.restoreState(WorkbenchWindow.java:1858)\n        at org.eclipse.ui.internal.Workbench.restoreState(Workbench.java:1408)\n        at org.eclipse.ui.internal.Workbench.access$9(Workbench.java:1358)\n        at org.eclipse.ui.internal.Workbench$14.run(Workbench.java:1241)\n        at\norg.eclipse.core.internal.runtime.InternalPlatform.run(InternalPlatform.java:1021)\n        at org.eclipse.core.runtime.Platform.run(Platform.java:757)\n        at org.eclipse.ui.internal.Workbench.restoreState(Workbench.java:1185)\n        at\norg.eclipse.ui.internal.WorkbenchConfigurer.restoreState(WorkbenchConfigurer.java:173)\n        at\norg.eclipse.ui.application.WorkbenchAdvisor.openWindows(WorkbenchAdvisor.java:712)\n        at org.eclipse.ui.internal.Workbench.init(Workbench.java:962)\n        at org.eclipse.ui.internal.Workbench.runUI(Workbench.java:1510)\n        at\norg.eclipse.ui.internal.Workbench.createAndRunWorkbench(Workbench.java:306)\n        at org.eclipse.ui.PlatformUI.createAndRunWorkbench(PlatformUI.java:143)\n        at org.eclipse.ui.internal.ide.IDEApplication.run(IDEApplication.java:103)\n        at\norg.eclipse.core.internal.runtime.PlatformActivator$1.run(PlatformActivator.java:228)\n        at\norg.eclipse.core.runtime.adaptor.EclipseStarter.run(EclipseStarter.java:344)\n        at\norg.eclipse.core.runtime.adaptor.EclipseStarter.run(EclipseStarter.java:156)\n        at sun.reflect.NativeMethodAccessorImpl.invoke0(Native Method)\n        at\nsun.reflect.NativeMethodAccessorImpl.invoke(NativeMethodAccessorImpl.java:39)\n        at\nsun.reflect.DelegatingMethodAccessorImpl.invoke(DelegatingMethodAccessorImpl.java:25)\n        at java.lang.reflect.Method.invoke(Method.java:324)\n        at org.eclipse.core.launcher.Main.invokeFramework(Main.java:316)\n        at org.eclipse.core.launcher.Main.basicRun(Main.java:269)\n        at org.eclipse.core.launcher.Main.run(Main.java:948)\n        at org.eclipse.core.launcher.Main.main(Main.java:932)\n\n\"VM Thread\" prio\u003d5 tid\u003d0x009cafd8 nid\u003d0xe80 runnable\n\n\"VM Periodic Task Thread\" prio\u003d10 tid\u003d0x00a11288 nid\u003d0x634 waiting on condition\n\"Suspend Checker Thread\" prio\u003d10 tid\u003d0x00a0bba0 nid\u003d0x23c runnable",
    "Ignoring initial classloader circularity (could be a PDE issue), problem comes\nfrom interference between one editor reconciling while package explorer is being\nrendered.\n\nReconcile\n - lock on projectElementInfo (to compute namelookup)\n - initializes classpath\n - calls out client CP initializer\n - execute operation which needs resource lock --\u003e WAIT\n\nMain (pkg explorer)\n - takes resource lock\n - initializes classpath \n - attempt to lock on projectElementInfo to reset pkg fragment roots cache\n - DEADLOCK\n\n",
    "No 3rd party code should run within our projectElementInfo lock. \nProposal is to stop synchronizing namelookup creation.",
    "Changed JavaProjectElementInfo to use a member class (ProjectCache) to store the\nallPackageFragmentRootsCache, allPackageFragmentsCache, and\npathToResolvedEntries. This cache is reset at once (by nulling the projectCache\nfield), and it is initialized at once (in getProjectCache()). No need to\nsynchronize these methods any longer.",
    "Verified for 3.1 M7 using build I20050509-2010 + jdt.core HEAD.",
    "*** Bug 84162 has been marked as a duplicate of this bug. ***"
  ],
  "commentCreationDates": [
    "2005-04-19T11:59:56+02:00",
    "2005-04-19T12:04:04+02:00",
    "2005-04-19T12:04:51+02:00",
    "2005-04-19T13:13:40+02:00",
    "2005-05-11T17:06:04+02:00",
    "2005-05-12T12:22:21+02:00"
  ],
  "traces": [
    {
      "exceptionType": "java.lang.ClassCircularityError",
      "message": "org/eclipse/pde/internal/core/WorkspaceModelManager",
      "elements": [
        {
          "method": "org.eclipse.pde.internal.core.PDECore.initializeModels",
          "source": "PDECore.java:376"
        },
        {
          "method": "org.eclipse.pde.internal.core.PDECore.getModelManager",
          "source": "PDECore.java:301"
        },
        {
          "method": "org.eclipse.pde.internal.core.RequiredPluginsInitializer.initialize",
          "source": "RequiredPluginsInitializer.java:36"
        },
        {
          "method": "org.eclipse.jdt.internal.core.JavaModelManager.initializeContainer",
          "source": "JavaModelManager.java:1416"
        },
        {
          "method": "org.eclipse.jdt.internal.core.JavaModelManager.getClasspathContainer",
          "source": "JavaModelManager.java:971"
        },
        {
          "method": "org.eclipse.jdt.core.JavaCore.getClasspathContainer",
          "source": "JavaCore.java:1304"
        },
        {
          "method": "org.eclipse.jdt.internal.core.JavaProject.getResolvedClasspath",
          "source": "JavaProject.java:2065"
        },
        {
          "method": "org.eclipse.jdt.internal.core.JavaProject.getResolvedClasspath",
          "source": "JavaProject.java:1973"
        },
        {
          "method": "org.eclipse.jdt.internal.core.JavaProject.isOnClasspath",
          "source": "JavaProject.java:2251"
        },
        {
          "method": "org.eclipse.jdt.internal.ui.javaeditor.CompilationUnitDocumentProvider$CompilationUnitAnnotationModel.internalBeginReporting",
          "source": "CompilationUnitDocumentP rovider.java:467"
        },
        {
          "method": "org.eclipse.jdt.internal.ui.javaeditor.CompilationUnitDocumentProvider$CompilationUnitAnnotationModel.beginReportingSequence",
          "source": "CompilationUnitDocumentP rovider.java:457"
        },
        {
          "method": "org.eclipse.jdt.internal.ui.text.JavaCompositeReconcilingStrategy.initialReconcile",
          "source": "JavaCompositeReconcilingStrategy.java:119"
        },
        {
          "method": "org.eclipse.jface.text.reconciler.MonoReconciler.initialProcess",
          "source": "MonoReconciler.java:103"
        },
        {
          "method": "org.eclipse.jdt.internal.ui.text.JavaReconciler.initialProcess",
          "source": "JavaReconciler.java:307"
        },
        {
          "method": "org.eclipse.jface.text.reconciler.AbstractReconciler$BackgroundThread.run",
          "source": "AbstractReconciler.java:170"
        }
      ],
      "number": 0,
      "commentIndex": 0,
      "bugId": "91861",
      "date": "2005-04-19T11:59:56+02:00",
      "product": "JDT",
      "component": "Core",
      "severity": "normal"
    }
  ],
  "groupId": "91861",
  "bugId": "91861",
  "date": "2005-04-19T11:59:56+02:00",
  "product": "JDT",
  "component": "Core",
  "severity": "normal"
}