{
  "comments": [
    "Follow the test case \n\nhttp://www.eclipse.org/webtools/jst/components/j2ee/scenarios/migration_webm3_t\nutorial.html\n\nuntil  step 4, the  project was  shown in the \"Other  projects\" group, right \nclick the project  and  ypu will get the following error\n\n\n\njava.lang.IllegalArgumentException: Group not found: common-menu-edit-delete\n        at org.eclipse.jface.action.ContributionManager.addToGroup\n(ContributionManager.java:124)\n        at org.eclipse.jface.action.ContributionManager.appendToGroup\n(ContributionManager.java:131)\n        at \norg.eclipse.jst.j2ee.navigator.internal.J2EEActionProvider.fillContextMenu\n(J2EEActionProvider.java:121)\n        at \norg.eclipse.wst.common.navigator.internal.provisional.views.NavigatorActionServ\nice.addContentDescriptorMenu(NavigatorActionService.java:190)\n        at \norg.eclipse.wst.common.navigator.internal.provisional.views.NavigatorActionServ\nice.fillContextMenu(NavigatorActionService.java:146)\n        at \norg.eclipse.wst.common.navigator.internal.provisional.views.CommonNavigatorMana\nger.fillContextMenu(CommonNavigatorManager.java:127)\n        at \norg.eclipse.wst.common.navigator.internal.provisional.views.CommonNavigatorMana\nger$1.menuAboutToShow(CommonNavigatorManager.java:144)\n        at org.eclipse.jface.action.MenuManager.fireAboutToShow\n(MenuManager.java:285)\n        at org.eclipse.jface.action.MenuManager.handleAboutToShow\n(MenuManager.java:372)\n        at org.eclipse.jface.action.MenuManager.access$0(MenuManager.java:369)\n        at org.eclipse.jface.action.MenuManager$2.menuShown\n(MenuManager.java:386)\n        at org.eclipse.swt.widgets.TypedListener.handleEvent\n(TypedListener.java:116)\n        at org.eclipse.swt.widgets.EventTable.sendEvent(EventTable.java:82)\n        at org.eclipse.swt.widgets.Widget.sendEvent(Widget.java:842)\n        at org.eclipse.swt.widgets.Widget.sendEvent(Widget.java:866)\n        at org.eclipse.swt.widgets.Widget.sendEvent(Widget.java:847)\n        at org.eclipse.swt.widgets.Control.WM_INITMENUPOPUP(Control.java:3327)\n        at org.eclipse.swt.widgets.Control.windowProc(Control.java:3055)\n        at org.eclipse.swt.widgets.Decorations.windowProc\n(Decorations.java:1493)\n        at org.eclipse.swt.widgets.Display.windowProc(Display.java:3466)\n        at org.eclipse.swt.internal.win32.OS.TrackPopupMenu(Native Method)\n        at org.eclipse.swt.widgets.Menu._setVisible(Menu.java:225)\n        at org.eclipse.swt.widgets.Display.runPopups(Display.java:2920)\n        at org.eclipse.swt.widgets.Display.readAndDispatch(Display.java:2521)\n        at org.eclipse.ui.internal.Workbench.runEventLoop(Workbench.java:1570)\n        at org.eclipse.ui.internal.Workbench.runUI(Workbench.java:1534)\n        at org.eclipse.ui.internal.Workbench.createAndRunWorkbench\n(Workbench.java:306)\n        at org.eclipse.ui.PlatformUI.createAndRunWorkbench(PlatformUI.java:143)\n        at org.eclipse.ui.internal.ide.IDEApplication.run\n(IDEApplication.java:103)\n        at org.eclipse.core.internal.runtime.PlatformActivator$1.run\n(PlatformActivator.java:228)\n        at org.eclipse.core.runtime.adaptor.EclipseStarter.run\n(EclipseStarter.java:344)\n        at org.eclipse.core.runtime.adaptor.EclipseStarter.run\n(EclipseStarter.java:156)\n        at sun.reflect.NativeMethodAccessorImpl.invoke0(Native Method)\n        at sun.reflect.NativeMethodAccessorImpl.invoke(Unknown Source)\n        at sun.reflect.DelegatingMethodAccessorImpl.invoke(Unknown Source)\n        at java.lang.reflect.Method.invoke(Unknown Source)\n        at org.eclipse.core.launcher.Main.invokeFramework(Main.java:315)\n        at org.eclipse.core.launcher.Main.basicRun(Main.java:268)\n        at org.eclipse.core.launcher.Main.run(Main.java:942)\n        at org.eclipse.core.launcher.Main.main(Main.java:926)",
    "could not reproduce",
    "Tested on 04/22 build"
  ],
  "commentCreationDates": [
    "2005-04-19T17:20:06+02:00",
    "2005-04-20T21:28:46+02:00",
    "2005-04-22T22:15:21+02:00"
  ],
  "traces": [
    {
      "exceptionType": "java.lang.IllegalArgumentException",
      "message": "Group not found: common-menu-edit-delete",
      "elements": [
        {
          "method": "org.eclipse.jface.action.ContributionManager.addToGroup",
          "source": "ContributionManager.java:124"
        },
        {
          "method": "org.eclipse.jface.action.ContributionManager.appendToGroup",
          "source": "ContributionManager.java:131"
        },
        {
          "method": "org.eclipse.jst.j2ee.navigator.internal.J2EEActionProvider.fillContextMenu",
          "source": "J2EEActionProvider.java:121"
        },
        {
          "method": "org.eclipse.wst.common.navigator.internal.provisional.views.NavigatorActionService.addContentDescriptorMenu",
          "source": "NavigatorActionService.java:190"
        },
        {
          "method": "org.eclipse.wst.common.navigator.internal.provisional.views.NavigatorActionService.fillContextMenu",
          "source": "NavigatorActionService.java:146"
        },
        {
          "method": "org.eclipse.wst.common.navigator.internal.provisional.views.CommonNavigatorManager.fillContextMenu",
          "source": "CommonNavigatorManager.java:127"
        },
        {
          "method": "org.eclipse.wst.common.navigator.internal.provisional.views.CommonNavigatorManager$1.menuAboutToShow",
          "source": "CommonNavigatorManager.java:144"
        },
        {
          "method": "org.eclipse.jface.action.MenuManager.fireAboutToShow",
          "source": "MenuManager.java:285"
        },
        {
          "method": "org.eclipse.jface.action.MenuManager.handleAboutToShow",
          "source": "MenuManager.java:372"
        },
        {
          "method": "org.eclipse.jface.action.MenuManager.access$0",
          "source": "MenuManager.java:369"
        },
        {
          "method": "org.eclipse.jface.action.MenuManager$2.menuShown",
          "source": "MenuManager.java:386"
        },
        {
          "method": "org.eclipse.swt.widgets.TypedListener.handleEvent",
          "source": "TypedListener.java:116"
        },
        {
          "method": "org.eclipse.swt.widgets.EventTable.sendEvent",
          "source": "EventTable.java:82"
        },
        {
          "method": "org.eclipse.swt.widgets.Widget.sendEvent",
          "source": "Widget.java:842"
        },
        {
          "method": "org.eclipse.swt.widgets.Widget.sendEvent",
          "source": "Widget.java:866"
        },
        {
          "method": "org.eclipse.swt.widgets.Widget.sendEvent",
          "source": "Widget.java:847"
        },
        {
          "method": "org.eclipse.swt.widgets.Control.WM_INITMENUPOPUP",
          "source": "Control.java:3327"
        },
        {
          "method": "org.eclipse.swt.widgets.Control.windowProc",
          "source": "Control.java:3055"
        },
        {
          "method": "org.eclipse.swt.widgets.Decorations.windowProc",
          "source": "Decorations.java:1493"
        },
        {
          "method": "org.eclipse.swt.widgets.Display.windowProc",
          "source": "Display.java:3466"
        },
        {
          "method": "org.eclipse.swt.internal.win32.OS.TrackPopupMenu",
          "source": "Native Method"
        },
        {
          "method": "org.eclipse.swt.widgets.Menu._setVisible",
          "source": "Menu.java:225"
        },
        {
          "method": "org.eclipse.swt.widgets.Display.runPopups",
          "source": "Display.java:2920"
        },
        {
          "method": "org.eclipse.swt.widgets.Display.readAndDispatch",
          "source": "Display.java:2521"
        },
        {
          "method": "org.eclipse.ui.internal.Workbench.runEventLoop",
          "source": "Workbench.java:1570"
        },
        {
          "method": "org.eclipse.ui.internal.Workbench.runUI",
          "source": "Workbench.java:1534"
        },
        {
          "method": "org.eclipse.ui.internal.Workbench.createAndRunWorkbench",
          "source": "Workbench.java:306"
        },
        {
          "method": "org.eclipse.ui.PlatformUI.createAndRunWorkbench",
          "source": "PlatformUI.java:143"
        },
        {
          "method": "org.eclipse.ui.internal.ide.IDEApplication.run",
          "source": "IDEApplication.java:103"
        },
        {
          "method": "org.eclipse.core.internal.runtime.PlatformActivator$1.run",
          "source": "PlatformActivator.java:228"
        },
        {
          "method": "org.eclipse.core.runtime.adaptor.EclipseStarter.run",
          "source": "EclipseStarter.java:344"
        },
        {
          "method": "org.eclipse.core.runtime.adaptor.EclipseStarter.run",
          "source": "EclipseStarter.java:156"
        },
        {
          "method": "sun.reflect.NativeMethodAccessorImpl.invoke0",
          "source": "Native Method"
        },
        {
          "method": "sun.reflect.NativeMethodAccessorImpl.invoke",
          "source": "Unknown Source"
        },
        {
          "method": "sun.reflect.DelegatingMethodAccessorImpl.invoke",
          "source": "Unknown Source"
        },
        {
          "method": "java.lang.reflect.Method.invoke",
          "source": "Unknown Source"
        },
        {
          "method": "org.eclipse.core.launcher.Main.invokeFramework",
          "source": "Main.java:315"
        },
        {
          "method": "org.eclipse.core.launcher.Main.basicRun",
          "source": "Main.java:268"
        },
        {
          "method": "org.eclipse.core.launcher.Main.run",
          "source": "Main.java:942"
        },
        {
          "method": "org.eclipse.core.launcher.Main.main",
          "source": "Main.java:926"
        }
      ],
      "number": 0,
      "commentIndex": 0,
      "bugId": "91906",
      "date": "2005-04-19T17:20:06+02:00",
      "product": "Web Tools",
      "component": "jst.j2ee",
      "severity": "major"
    }
  ],
  "groupId": "91906",
  "bugId": "91906",
  "date": "2005-04-19T17:20:06+02:00",
  "product": "Web Tools",
  "component": "jst.j2ee",
  "severity": "major"
}