{
  "comments": [
    "I20050419-1200\n\nUnclear how this occurred. Was self-hosting on this build, and noticed the\nfollowing in log. \nCould this be a consequence of us becoming more lazy, and exposing latent issues ?\n\n!ENTRY org.eclipse.ui.workbench 4 2 2005-04-20 12:57:08.418\n!MESSAGE Problems occurred when invoking code from plug-in:\n\"org.eclipse.ui.workbench\".\n!STACK 0\njava.lang.IllegalArgumentException: Attempted to beginRule: R/, does not match\nouter scope rule: org.eclipse.ui.internal.decorators.DecorationScheduler$1@a32604\n\n        at org.eclipse.core.internal.runtime.Assert.isLegal(Assert.java:58)\n        at org.eclipse.core.internal.jobs.ThreadJob.illegalPush(ThreadJob.java:107)\n        at org.eclipse.core.internal.jobs.ThreadJob.push(ThreadJob.java:201)\n        at org.eclipse.core.internal.jobs.ImplicitJobs.begin(ImplicitJobs.java:81)\n        at org.eclipse.core.internal.jobs.JobManager.beginRule(JobManager.java:187)\n        at\norg.eclipse.core.internal.resources.WorkManager.checkIn(WorkManager.java:96)\n        at\norg.eclipse.core.internal.resources.Workspace.prepareOperation(Workspace.java:1671)\n        at org.eclipse.core.internal.resources.Workspace.run(Workspace.java:1711)\n        at\norg.eclipse.jdt.internal.core.JavaModelOperation.runOperation(JavaModelOperation.java:782)\n        at\norg.eclipse.jdt.internal.core.JavaProject.setRawClasspath(JavaProject.java:2778)\n        at org.eclipse.jdt.core.JavaCore$3.run(JavaCore.java:3841)\n        at\norg.eclipse.jdt.internal.core.BatchOperation.executeOperation(BatchOperation.java:39)\n        at\norg.eclipse.jdt.internal.core.JavaModelOperation.run(JavaModelOperation.java:718)\n        at org.eclipse.core.internal.resources.Workspace.run(Workspace.java:1716)\n        at org.eclipse.jdt.core.JavaCore.run(JavaCore.java:3650)\n        at org.eclipse.jdt.core.JavaCore.setClasspathContainer(JavaCore.java:3824)\n        at\norg.eclipse.pde.internal.core.ModelEntry.updateClasspathContainer(ModelEntry.java:110)\n        at\norg.eclipse.pde.internal.core.RequiredPluginsInitializer.initialize(RequiredPluginsInitializer.java:40)\n        at\norg.eclipse.jdt.internal.core.JavaModelManager.initializeContainer(JavaModelManager.java:1416)\n        at\norg.eclipse.jdt.internal.core.JavaModelManager.getClasspathContainer(JavaModelManager.java:971)\n        at org.eclipse.jdt.core.JavaCore.getClasspathContainer(JavaCore.java:1309)\n        at\norg.eclipse.jdt.internal.core.JavaProject.getResolvedClasspath(JavaProject.java:2065)\n        at\norg.eclipse.jdt.internal.core.JavaProject.getResolvedClasspath(JavaProject.java:1973)\n        at\norg.eclipse.jdt.internal.core.DeltaProcessingState.initializeRoots(DeltaProcessingState.java:260)\n        at\norg.eclipse.jdt.internal.core.JavaModelOperation.run(JavaModelOperation.java:715)\n        at org.eclipse.core.internal.resources.Workspace.run(Workspace.java:1716)\n        at org.eclipse.jdt.core.JavaCore.run(JavaCore.java:3650)\n        at org.eclipse.jdt.core.JavaCore.setClasspathContainer(JavaCore.java:3824)\n        at\norg.eclipse.pde.internal.core.ModelEntry.updateClasspathContainer(ModelEntry.java:110)\n        at\norg.eclipse.pde.internal.core.RequiredPluginsInitializer.initialize(RequiredPluginsInitializer.java:40)\n        at\norg.eclipse.jdt.internal.core.JavaModelManager.initializeContainer(JavaModelManager.java:1416)\n        at\norg.eclipse.jdt.internal.core.JavaModelManager.getClasspathContainer(JavaModelManager.java:971)\n        at org.eclipse.jdt.core.JavaCore.getClasspathContainer(JavaCore.java:1309)\n        at\norg.eclipse.jdt.internal.core.JavaProject.getResolvedClasspath(JavaProject.java:2065)\n        at\norg.eclipse.jdt.internal.core.JavaProject.getResolvedClasspath(JavaProject.java:1973)\n        at\norg.eclipse.jdt.internal.core.JavaProject.isOnClasspath(JavaProject.java:2251)\n        at\norg.eclipse.jdt.ui.OverrideIndicatorLabelDecorator.computeAdornmentFlags(OverrideIndicatorLabelDecorator.java:123)\n        at\norg.eclipse.jdt.ui.OverrideIndicatorLabelDecorator.decorate(OverrideIndicatorLabelDecorator.java:251)\n        at\norg.eclipse.ui.internal.decorators.LightweightDecoratorDefinition.decorate(LightweightDecoratorDefinition.java:220)\n        at\norg.eclipse.ui.internal.decorators.LightweightDecoratorManager$LightweightRunnable.run(LightweightDecoratorManager.java:65)\n        at\norg.eclipse.core.internal.runtime.InternalPlatform.run(InternalPlatform.java:1026)\n        at org.eclipse.core.runtime.Platform.run(Platform.java:757)\n        at\norg.eclipse.ui.internal.decorators.LightweightDecoratorManager.decorate(LightweightDecoratorManager.java:287)\n        at\norg.eclipse.ui.internal.decorators.LightweightDecoratorManager.getDecorations(LightweightDecoratorManager.java:273)\n        at\norg.eclipse.ui.internal.decorators.DecorationScheduler$2.run(DecorationScheduler.java:326)\n        at org.eclipse.core.internal.jobs.Worker.run(Worker.java:67)\n\n!ENTRY org.eclipse.ui 4 4 2005-04-20 12:57:08.418\n!MESSAGE Exception in Decorator\nException in Decorator\nReason:\n\n!ENTRY org.eclipse.ui 4 4 2005-04-20 12:57:08.418\n!MESSAGE Attempted to beginRule: R/, does not match outer scope rule:\norg.eclipse.ui.internal.decorators.DecorationScheduler$1@a32604\n!STACK 0\njava.lang.IllegalArgumentException: Attempted to beginRule: R/, does not match\nouter scope rule: org.eclipse.ui.internal.decorators.DecorationScheduler$1@a32604\n\n        at org.eclipse.core.internal.runtime.Assert.isLegal(Assert.java:58)\n        at org.eclipse.core.internal.jobs.ThreadJob.illegalPush(ThreadJob.java:107)\n        at org.eclipse.core.internal.jobs.ThreadJob.push(ThreadJob.java:201)\n        at org.eclipse.core.internal.jobs.ImplicitJobs.begin(ImplicitJobs.java:81)\n        at org.eclipse.core.internal.jobs.JobManager.beginRule(JobManager.java:187)\n        at\norg.eclipse.core.internal.resources.WorkManager.checkIn(WorkManager.java:96)\n        at\norg.eclipse.core.internal.resources.Workspace.prepareOperation(Workspace.java:1671)\n        at org.eclipse.core.internal.resources.Workspace.run(Workspace.java:1711)\n        at\norg.eclipse.jdt.internal.core.JavaModelOperation.runOperation(JavaModelOperation.java:782)\n        at\norg.eclipse.jdt.internal.core.JavaProject.setRawClasspath(JavaProject.java:2778)\n        at org.eclipse.jdt.core.JavaCore$3.run(JavaCore.java:3841)\n        at\norg.eclipse.jdt.internal.core.BatchOperation.executeOperation(BatchOperation.java:39)\n        at\norg.eclipse.jdt.internal.core.JavaModelOperation.run(JavaModelOperation.java:718)\n        at org.eclipse.core.internal.resources.Workspace.run(Workspace.java:1716)\n        at org.eclipse.jdt.core.JavaCore.run(JavaCore.java:3650)\n        at org.eclipse.jdt.core.JavaCore.setClasspathContainer(JavaCore.java:3824)\n        at\norg.eclipse.pde.internal.core.ModelEntry.updateClasspathContainer(ModelEntry.java:110)\n        at\norg.eclipse.pde.internal.core.RequiredPluginsInitializer.initialize(RequiredPluginsInitializer.java:40)\n        at\norg.eclipse.jdt.internal.core.JavaModelManager.initializeContainer(JavaModelManager.java:1416)\n        at\norg.eclipse.jdt.internal.core.JavaModelManager.getClasspathContainer(JavaModelManager.java:971)\n        at org.eclipse.jdt.core.JavaCore.getClasspathContainer(JavaCore.java:1309)\n        at\norg.eclipse.jdt.internal.core.JavaProject.getResolvedClasspath(JavaProject.java:2065)\n        at\norg.eclipse.jdt.internal.core.JavaProject.getResolvedClasspath(JavaProject.java:1973)\n        at\norg.eclipse.jdt.internal.core.DeltaProcessingState.initializeRoots(DeltaProcessingState.java:260)\n        at\norg.eclipse.jdt.internal.core.JavaModelOperation.run(JavaModelOperation.java:715)\n        at org.eclipse.core.internal.resources.Workspace.run(Workspace.java:1716)\n        at org.eclipse.jdt.core.JavaCore.run(JavaCore.java:3650)\n        at org.eclipse.jdt.core.JavaCore.setClasspathContainer(JavaCore.java:3824)\n        at\norg.eclipse.pde.internal.core.ModelEntry.updateClasspathContainer(ModelEntry.java:110)\n        at\norg.eclipse.pde.internal.core.RequiredPluginsInitializer.initialize(RequiredPluginsInitializer.java:40)\n        at\norg.eclipse.jdt.internal.core.JavaModelManager.initializeContainer(JavaModelManager.java:1416)\n        at\norg.eclipse.jdt.internal.core.JavaModelManager.getClasspathContainer(JavaModelManager.java:971)\n        at org.eclipse.jdt.core.JavaCore.getClasspathContainer(JavaCore.java:1309)\n        at\norg.eclipse.jdt.internal.core.JavaProject.getResolvedClasspath(JavaProject.java:2065)\n        at\norg.eclipse.jdt.internal.core.JavaProject.getResolvedClasspath(JavaProject.java:1973)\n        at\norg.eclipse.jdt.internal.core.JavaProject.isOnClasspath(JavaProject.java:2251)\n        at\norg.eclipse.jdt.ui.OverrideIndicatorLabelDecorator.computeAdornmentFlags(OverrideIndicatorLabelDecorator.java:123)\n        at\norg.eclipse.jdt.ui.OverrideIndicatorLabelDecorator.decorate(OverrideIndicatorLabelDecorator.java:251)\n        at\norg.eclipse.ui.internal.decorators.LightweightDecoratorDefinition.decorate(LightweightDecoratorDefinition.java:220)\n        at\norg.eclipse.ui.internal.decorators.LightweightDecoratorManager$LightweightRunnable.run(LightweightDecoratorManager.java:65)\n        at\norg.eclipse.core.internal.runtime.InternalPlatform.run(InternalPlatform.java:1026)\n        at org.eclipse.core.runtime.Platform.run(Platform.java:757)\n        at\norg.eclipse.ui.internal.decorators.LightweightDecoratorManager.decorate(LightweightDecoratorManager.java:287)\n        at\norg.eclipse.ui.internal.decorators.LightweightDecoratorManager.getDecorations(LightweightDecoratorManager.java:273)\n        at\norg.eclipse.ui.internal.decorators.DecorationScheduler$2.run(DecorationScheduler.java:326)\n        at org.eclipse.core.internal.jobs.Worker.run(Worker.java:67)\nAttempted to beginRule: R/, does not match outer scope rule:\norg.eclipse.ui.internal.decorators.DecorationScheduler$1@a32604",
    "Probably a dup of bug 86628.",
    "Problem occurs when some decorator from JDT/UI asks a question which triggered\nclasspath initialization (during which we take the workspace lock eagerly).\n\nPlatform-ui locked on its own decoration rule; then we want to lock on\nworkspace, and our rule get blamed for containment issues.\n\nSuspecting the logic in platform layer to be invalid:\nThreadJob#push(ISchedulingRule) should not check for:\n//check for containment last because we don\u0027t want to fail again on endRule\nif (baseRule !\u003d null \u0026\u0026 rule !\u003d null \u0026\u0026 !baseRule.contains(rule))\n  illegalPush(rule, baseRule);\n}\n\nbut rather:\n\n//check for containment last because we don\u0027t want to fail again on endRule\nif (baseRule !\u003d null \u0026\u0026 rule !\u003d null \u0026\u0026 rule.contains(baseRule))\n  illegalPush(rule, baseRule);\n}\n\nThis would allow disjoint locks to perform whithout causing any grief.",
    "\n\n*** This bug has been marked as a duplicate of 86628 ***"
  ],
  "commentCreationDates": [
    "2005-04-20T13:40:59+02:00",
    "2005-04-21T12:12:21+02:00",
    "2005-04-21T13:10:04+02:00",
    "2005-04-21T13:17:05+02:00"
  ],
  "traces": [
    {
      "exceptionType": "java.lang.IllegalArgumentException",
      "message": "Attempted to beginRule: R/, does not match outer scope rule: org.eclipse.ui.internal.decorators.DecorationScheduler$1@a32604",
      "elements": [
        {
          "method": "org.eclipse.core.internal.runtime.Assert.isLegal",
          "source": "Assert.java:58"
        },
        {
          "method": "org.eclipse.core.internal.jobs.ThreadJob.illegalPush",
          "source": "ThreadJob.java:107"
        },
        {
          "method": "org.eclipse.core.internal.jobs.ThreadJob.push",
          "source": "ThreadJob.java:201"
        },
        {
          "method": "org.eclipse.core.internal.jobs.ImplicitJobs.begin",
          "source": "ImplicitJobs.java:81"
        },
        {
          "method": "org.eclipse.core.internal.jobs.JobManager.beginRule",
          "source": "JobManager.java:187"
        },
        {
          "method": "org.eclipse.core.internal.resources.WorkManager.checkIn",
          "source": "WorkManager.java:96"
        },
        {
          "method": "org.eclipse.core.internal.resources.Workspace.prepareOperation",
          "source": "Workspace.java:1671"
        },
        {
          "method": "org.eclipse.core.internal.resources.Workspace.run",
          "source": "Workspace.java:1711"
        },
        {
          "method": "org.eclipse.jdt.internal.core.JavaModelOperation.runOperation",
          "source": "JavaModelOperation.java:782"
        },
        {
          "method": "org.eclipse.jdt.internal.core.JavaProject.setRawClasspath",
          "source": "JavaProject.java:2778"
        },
        {
          "method": "org.eclipse.jdt.core.JavaCore$3.run",
          "source": "JavaCore.java:3841"
        },
        {
          "method": "org.eclipse.jdt.internal.core.BatchOperation.executeOperation",
          "source": "BatchOperation.java:39"
        },
        {
          "method": "org.eclipse.jdt.internal.core.JavaModelOperation.run",
          "source": "JavaModelOperation.java:718"
        },
        {
          "method": "org.eclipse.core.internal.resources.Workspace.run",
          "source": "Workspace.java:1716"
        },
        {
          "method": "org.eclipse.jdt.core.JavaCore.run",
          "source": "JavaCore.java:3650"
        },
        {
          "method": "org.eclipse.jdt.core.JavaCore.setClasspathContainer",
          "source": "JavaCore.java:3824"
        },
        {
          "method": "org.eclipse.pde.internal.core.ModelEntry.updateClasspathContainer",
          "source": "ModelEntry.java:110"
        },
        {
          "method": "org.eclipse.pde.internal.core.RequiredPluginsInitializer.initialize",
          "source": "RequiredPluginsInitializer.java:40"
        },
        {
          "method": "org.eclipse.jdt.internal.core.JavaModelManager.initializeContainer",
          "source": "JavaModelManager.java:1416"
        },
        {
          "method": "org.eclipse.jdt.internal.core.JavaModelManager.getClasspathContainer",
          "source": "JavaModelManager.java:971"
        },
        {
          "method": "org.eclipse.jdt.core.JavaCore.getClasspathContainer",
          "source": "JavaCore.java:1309"
        },
        {
          "method": "org.eclipse.jdt.internal.core.JavaProject.getResolvedClasspath",
          "source": "JavaProject.java:2065"
        },
        {
          "method": "org.eclipse.jdt.internal.core.JavaProject.getResolvedClasspath",
          "source": "JavaProject.java:1973"
        },
        {
          "method": "org.eclipse.jdt.internal.core.DeltaProcessingState.initializeRoots",
          "source": "DeltaProcessingState.java:260"
        },
        {
          "method": "org.eclipse.jdt.internal.core.JavaModelOperation.run",
          "source": "JavaModelOperation.java:715"
        },
        {
          "method": "org.eclipse.core.internal.resources.Workspace.run",
          "source": "Workspace.java:1716"
        },
        {
          "method": "org.eclipse.jdt.core.JavaCore.run",
          "source": "JavaCore.java:3650"
        },
        {
          "method": "org.eclipse.jdt.core.JavaCore.setClasspathContainer",
          "source": "JavaCore.java:3824"
        },
        {
          "method": "org.eclipse.pde.internal.core.ModelEntry.updateClasspathContainer",
          "source": "ModelEntry.java:110"
        },
        {
          "method": "org.eclipse.pde.internal.core.RequiredPluginsInitializer.initialize",
          "source": "RequiredPluginsInitializer.java:40"
        },
        {
          "method": "org.eclipse.jdt.internal.core.JavaModelManager.initializeContainer",
          "source": "JavaModelManager.java:1416"
        },
        {
          "method": "org.eclipse.jdt.internal.core.JavaModelManager.getClasspathContainer",
          "source": "JavaModelManager.java:971"
        },
        {
          "method": "org.eclipse.jdt.core.JavaCore.getClasspathContainer",
          "source": "JavaCore.java:1309"
        },
        {
          "method": "org.eclipse.jdt.internal.core.JavaProject.getResolvedClasspath",
          "source": "JavaProject.java:2065"
        },
        {
          "method": "org.eclipse.jdt.internal.core.JavaProject.getResolvedClasspath",
          "source": "JavaProject.java:1973"
        },
        {
          "method": "org.eclipse.jdt.internal.core.JavaProject.isOnClasspath",
          "source": "JavaProject.java:2251"
        },
        {
          "method": "org.eclipse.jdt.ui.OverrideIndicatorLabelDecorator.computeAdornmentFlags",
          "source": "OverrideIndicatorLabelDecorator.java:123"
        },
        {
          "method": "org.eclipse.jdt.ui.OverrideIndicatorLabelDecorator.decorate",
          "source": "OverrideIndicatorLabelDecorator.java:251"
        },
        {
          "method": "org.eclipse.ui.internal.decorators.LightweightDecoratorDefinition.decorate",
          "source": "LightweightDecoratorDefinition.java:220"
        },
        {
          "method": "org.eclipse.ui.internal.decorators.LightweightDecoratorManager$LightweightRunnable.run",
          "source": "LightweightDecoratorManager.java:65"
        },
        {
          "method": "org.eclipse.core.internal.runtime.InternalPlatform.run",
          "source": "InternalPlatform.java:1026"
        },
        {
          "method": "org.eclipse.core.runtime.Platform.run",
          "source": "Platform.java:757"
        },
        {
          "method": "org.eclipse.ui.internal.decorators.LightweightDecoratorManager.decorate",
          "source": "LightweightDecoratorManager.java:287"
        },
        {
          "method": "org.eclipse.ui.internal.decorators.LightweightDecoratorManager.getDecorations",
          "source": "LightweightDecoratorManager.java:273"
        },
        {
          "method": "org.eclipse.ui.internal.decorators.DecorationScheduler$2.run",
          "source": "DecorationScheduler.java:326"
        },
        {
          "method": "org.eclipse.core.internal.jobs.Worker.run",
          "source": "Worker.java:67"
        }
      ],
      "number": 0,
      "commentIndex": 0,
      "bugId": "92057",
      "duplicateId": "86628",
      "date": "2005-04-20T13:40:59+02:00",
      "product": "JDT",
      "component": "Core",
      "severity": "normal"
    },
    {
      "exceptionType": "java.lang.IllegalArgumentException",
      "message": "Attempted to beginRule: R/, does not match outer scope rule: org.eclipse.ui.internal.decorators.DecorationScheduler$1@a32604",
      "elements": [
        {
          "method": "org.eclipse.core.internal.runtime.Assert.isLegal",
          "source": "Assert.java:58"
        },
        {
          "method": "org.eclipse.core.internal.jobs.ThreadJob.illegalPush",
          "source": "ThreadJob.java:107"
        },
        {
          "method": "org.eclipse.core.internal.jobs.ThreadJob.push",
          "source": "ThreadJob.java:201"
        },
        {
          "method": "org.eclipse.core.internal.jobs.ImplicitJobs.begin",
          "source": "ImplicitJobs.java:81"
        },
        {
          "method": "org.eclipse.core.internal.jobs.JobManager.beginRule",
          "source": "JobManager.java:187"
        },
        {
          "method": "org.eclipse.core.internal.resources.WorkManager.checkIn",
          "source": "WorkManager.java:96"
        },
        {
          "method": "org.eclipse.core.internal.resources.Workspace.prepareOperation",
          "source": "Workspace.java:1671"
        },
        {
          "method": "org.eclipse.core.internal.resources.Workspace.run",
          "source": "Workspace.java:1711"
        },
        {
          "method": "org.eclipse.jdt.internal.core.JavaModelOperation.runOperation",
          "source": "JavaModelOperation.java:782"
        },
        {
          "method": "org.eclipse.jdt.internal.core.JavaProject.setRawClasspath",
          "source": "JavaProject.java:2778"
        },
        {
          "method": "org.eclipse.jdt.core.JavaCore$3.run",
          "source": "JavaCore.java:3841"
        },
        {
          "method": "org.eclipse.jdt.internal.core.BatchOperation.executeOperation",
          "source": "BatchOperation.java:39"
        },
        {
          "method": "org.eclipse.jdt.internal.core.JavaModelOperation.run",
          "source": "JavaModelOperation.java:718"
        },
        {
          "method": "org.eclipse.core.internal.resources.Workspace.run",
          "source": "Workspace.java:1716"
        },
        {
          "method": "org.eclipse.jdt.core.JavaCore.run",
          "source": "JavaCore.java:3650"
        },
        {
          "method": "org.eclipse.jdt.core.JavaCore.setClasspathContainer",
          "source": "JavaCore.java:3824"
        },
        {
          "method": "org.eclipse.pde.internal.core.ModelEntry.updateClasspathContainer",
          "source": "ModelEntry.java:110"
        },
        {
          "method": "org.eclipse.pde.internal.core.RequiredPluginsInitializer.initialize",
          "source": "RequiredPluginsInitializer.java:40"
        },
        {
          "method": "org.eclipse.jdt.internal.core.JavaModelManager.initializeContainer",
          "source": "JavaModelManager.java:1416"
        },
        {
          "method": "org.eclipse.jdt.internal.core.JavaModelManager.getClasspathContainer",
          "source": "JavaModelManager.java:971"
        },
        {
          "method": "org.eclipse.jdt.core.JavaCore.getClasspathContainer",
          "source": "JavaCore.java:1309"
        },
        {
          "method": "org.eclipse.jdt.internal.core.JavaProject.getResolvedClasspath",
          "source": "JavaProject.java:2065"
        },
        {
          "method": "org.eclipse.jdt.internal.core.JavaProject.getResolvedClasspath",
          "source": "JavaProject.java:1973"
        },
        {
          "method": "org.eclipse.jdt.internal.core.DeltaProcessingState.initializeRoots",
          "source": "DeltaProcessingState.java:260"
        },
        {
          "method": "org.eclipse.jdt.internal.core.JavaModelOperation.run",
          "source": "JavaModelOperation.java:715"
        },
        {
          "method": "org.eclipse.core.internal.resources.Workspace.run",
          "source": "Workspace.java:1716"
        },
        {
          "method": "org.eclipse.jdt.core.JavaCore.run",
          "source": "JavaCore.java:3650"
        },
        {
          "method": "org.eclipse.jdt.core.JavaCore.setClasspathContainer",
          "source": "JavaCore.java:3824"
        },
        {
          "method": "org.eclipse.pde.internal.core.ModelEntry.updateClasspathContainer",
          "source": "ModelEntry.java:110"
        },
        {
          "method": "org.eclipse.pde.internal.core.RequiredPluginsInitializer.initialize",
          "source": "RequiredPluginsInitializer.java:40"
        },
        {
          "method": "org.eclipse.jdt.internal.core.JavaModelManager.initializeContainer",
          "source": "JavaModelManager.java:1416"
        },
        {
          "method": "org.eclipse.jdt.internal.core.JavaModelManager.getClasspathContainer",
          "source": "JavaModelManager.java:971"
        },
        {
          "method": "org.eclipse.jdt.core.JavaCore.getClasspathContainer",
          "source": "JavaCore.java:1309"
        },
        {
          "method": "org.eclipse.jdt.internal.core.JavaProject.getResolvedClasspath",
          "source": "JavaProject.java:2065"
        },
        {
          "method": "org.eclipse.jdt.internal.core.JavaProject.getResolvedClasspath",
          "source": "JavaProject.java:1973"
        },
        {
          "method": "org.eclipse.jdt.internal.core.JavaProject.isOnClasspath",
          "source": "JavaProject.java:2251"
        },
        {
          "method": "org.eclipse.jdt.ui.OverrideIndicatorLabelDecorator.computeAdornmentFlags",
          "source": "OverrideIndicatorLabelDecorator.java:123"
        },
        {
          "method": "org.eclipse.jdt.ui.OverrideIndicatorLabelDecorator.decorate",
          "source": "OverrideIndicatorLabelDecorator.java:251"
        },
        {
          "method": "org.eclipse.ui.internal.decorators.LightweightDecoratorDefinition.decorate",
          "source": "LightweightDecoratorDefinition.java:220"
        },
        {
          "method": "org.eclipse.ui.internal.decorators.LightweightDecoratorManager$LightweightRunnable.run",
          "source": "LightweightDecoratorManager.java:65"
        },
        {
          "method": "org.eclipse.core.internal.runtime.InternalPlatform.run",
          "source": "InternalPlatform.java:1026"
        },
        {
          "method": "org.eclipse.core.runtime.Platform.run",
          "source": "Platform.java:757"
        },
        {
          "method": "org.eclipse.ui.internal.decorators.LightweightDecoratorManager.decorate",
          "source": "LightweightDecoratorManager.java:287"
        },
        {
          "method": "org.eclipse.ui.internal.decorators.LightweightDecoratorManager.getDecorations",
          "source": "LightweightDecoratorManager.java:273"
        },
        {
          "method": "org.eclipse.ui.internal.decorators.DecorationScheduler$2.run",
          "source": "DecorationScheduler.java:326"
        },
        {
          "method": "org.eclipse.core.internal.jobs.Worker.run",
          "source": "Worker.java:67"
        }
      ],
      "number": 1,
      "commentIndex": 0,
      "bugId": "92057",
      "duplicateId": "86628",
      "date": "2005-04-20T13:40:59+02:00",
      "product": "JDT",
      "component": "Core",
      "severity": "normal"
    }
  ],
  "groupId": "86628",
  "bugId": "92057",
  "duplicateId": "86628",
  "date": "2005-04-20T13:40:59+02:00",
  "product": "JDT",
  "component": "Core",
  "severity": "normal"
}