{
  "comments": [
    "The UML 1.4 Diagram Interchange meta-model uses MOF StructureType elements to\ndescribe elements like \"Point\", \"Dimension\", etc. When running a transformation\nthat copies such elements in debug mode, I get (ERROR: null). On the command\nline, the following is shown (everything above the \"ERROR\" line is \u0027normal\u0027):\n\nStrange !!! This method is not good: public static\norg.mda.asm.nativeimpl.ASMOclParametrizedType\norg.mda.asm.nativeimpl.ASMOclParametrizedType.getASMOclParametrizedType(java.lang.String,org.mda.asm.nativeimpl.ASMOclType,org.mda.asm.nativeimpl.ASMOclType)\nParameter: 1\n        \u003d\u003eWriteTo\nParameter: 2\n        \u003d\u003edebug\nTrying to connect to remote debuggee\nInitializing MDR...\n[org.netbeans.mdr.Logger] Metamodel specific JMI class org.omg.uml.UmlPackage\nnot found. Using bytecode generation to create it.\nConnected.\n********************************* ERROR *********************************\njava.lang.Exception\n        at org.mda.asm.NetworkDebugger.error(NetworkDebugger.java:146)\n        at org.mda.asm.StackFrame.printStackTrace(StackFrame.java:76)\n        at org.mda.asm.StackFrame.printStackTrace(StackFrame.java:68)\n        at org.mda.asm.ASMOperation.exec(ASMOperation.java:150)\n        at org.mda.asm.ASMOperation.realExec(ASMOperation.java:211)\n        at org.mda.asm.ASMOperation.realExec(ASMOperation.java:269)\n        at org.mda.asm.ASMOperation.exec(ASMOperation.java:148)\n        at org.mda.asm.ASMOperation.realExec(ASMOperation.java:211)\n        at org.mda.asm.ASMOperation.exec(ASMOperation.java:148)\n        at org.mda.asm.ASMInterpreter.\u003cinit\u003e(ASMInterpreter.java:257)\n        at org.atl.eclipse.engine.AtlLauncher.launch(AtlLauncher.java:89)\n        at org.atl.eclipse.engine.AtlLauncher.debug(AtlLauncher.java:64)\n        at\norg.atl.eclipse.adt.launching.AtlLaunchConfigurationDelegate.runAtlLauncher(AtlLaunchConfigurationDelegate.java:194)\n        at\norg.atl.eclipse.adt.launching.AtlLaunchConfigurationDelegate.runAtlLauncher(AtlLaunchConfigurationDelegate.java:147)\n        at\norg.atl.eclipse.adt.launching.AtlLaunchConfigurationDelegate.runAtlLauncher(AtlLaunchConfigurationDelegate.java:130)\n        at\norg.atl.eclipse.adt.launching.AtlLaunchConfigurationDelegate.runAtlLauncher(AtlLaunchConfigurationDelegate.java:112)\n        at\norg.atl.eclipse.adt.launching.AtlLaunchConfigurationDelegate.access$0(AtlLaunchConfigurationDelegate.java:101)\n        at\norg.atl.eclipse.adt.launching.AtlLaunchConfigurationDelegate$1.run(AtlLaunchConfigurationDelegate.java:79)\n\nI\u0027ve used the DIModelCopy.atl transformation on the BreakoutModel.xmi model with\nthe M2_DiagramInterchangeModel.xmi meta-model for my test. All can be found here:\n\nhttp://ssel.vub.ac.be/viewcvs/viewcvs.py/svn-gen/UML1CaseStudies/?rev\u003d886#dirlist\n\n-- or --\n\nsvn co -r 886 http://ssel.vub.ac.be/svn-gen/UML1CaseStudies"
  ],
  "commentCreationDates": [
    "2005-04-21T10:01:19+02:00"
  ],
  "traces": [
    {
      "exceptionType": "java.lang.Exception",
      "elements": [
        {
          "method": "org.mda.asm.NetworkDebugger.error",
          "source": "NetworkDebugger.java:146"
        },
        {
          "method": "org.mda.asm.StackFrame.printStackTrace",
          "source": "StackFrame.java:76"
        },
        {
          "method": "org.mda.asm.StackFrame.printStackTrace",
          "source": "StackFrame.java:68"
        },
        {
          "method": "org.mda.asm.ASMOperation.exec",
          "source": "ASMOperation.java:150"
        },
        {
          "method": "org.mda.asm.ASMOperation.realExec",
          "source": "ASMOperation.java:211"
        },
        {
          "method": "org.mda.asm.ASMOperation.realExec",
          "source": "ASMOperation.java:269"
        },
        {
          "method": "org.mda.asm.ASMOperation.exec",
          "source": "ASMOperation.java:148"
        },
        {
          "method": "org.mda.asm.ASMOperation.realExec",
          "source": "ASMOperation.java:211"
        },
        {
          "method": "org.mda.asm.ASMOperation.exec",
          "source": "ASMOperation.java:148"
        },
        {
          "method": "org.mda.asm.ASMInterpreter.\u003cinit\u003e",
          "source": "ASMInterpreter.java:257"
        },
        {
          "method": "org.atl.eclipse.engine.AtlLauncher.launch",
          "source": "AtlLauncher.java:89"
        },
        {
          "method": "org.atl.eclipse.engine.AtlLauncher.debug",
          "source": "AtlLauncher.java:64"
        },
        {
          "method": "org.atl.eclipse.adt.launching.AtlLaunchConfigurationDelegate.runAtlLauncher",
          "source": "AtlLaunchConfigurationDelegate.java:194"
        },
        {
          "method": "org.atl.eclipse.adt.launching.AtlLaunchConfigurationDelegate.runAtlLauncher",
          "source": "AtlLaunchConfigurationDelegate.java:147"
        },
        {
          "method": "org.atl.eclipse.adt.launching.AtlLaunchConfigurationDelegate.runAtlLauncher",
          "source": "AtlLaunchConfigurationDelegate.java:130"
        },
        {
          "method": "org.atl.eclipse.adt.launching.AtlLaunchConfigurationDelegate.runAtlLauncher",
          "source": "AtlLaunchConfigurationDelegate.java:112"
        },
        {
          "method": "org.atl.eclipse.adt.launching.AtlLaunchConfigurationDelegate.access$0",
          "source": "AtlLaunchConfigurationDelegate.java:101"
        },
        {
          "method": "org.atl.eclipse.adt.launching.AtlLaunchConfigurationDelegate$1.run",
          "source": "AtlLaunchConfigurationDelegate.java:79"
        }
      ],
      "number": 0,
      "commentIndex": 0,
      "bugId": "92188",
      "date": "2005-04-21T10:01:19+02:00",
      "product": "GMT",
      "component": "ATL",
      "severity": "normal"
    }
  ],
  "groupId": "92188",
  "bugId": "92188",
  "date": "2005-04-21T10:01:19+02:00",
  "product": "GMT",
  "component": "ATL",
  "severity": "normal"
}