{
  "comments": [
    "Hi,\nI\u0027m getting the following error when building my targets on CDT 2.1.0 and \n2.1.1 (I dont get any of these exceptions in the previous version 2.0.2 of CDT)\nThis error is found only on HP-UX. There is no problem in Linux and Windows. I \ncreate a target using Create Make Target and build the target using Build Make \nTarget.\n\njava.lang.UnsatisfiedLinkError: no spawner in java.library.path\n        at java.lang.ClassLoader.loadLibrary(ClassLoader.java:1516)\n        at java.lang.Runtime.loadLibrary0(Runtime.java:788)\n        at java.lang.System.loadLibrary(System.java:834)\n        at org.eclipse.cdt.utils.spawner.ProcessFactory.\u003cinit\u003e\n(ProcessFactory.java:35)\n        at org.eclipse.cdt.utils.spawner.ProcessFactory.getFactory\n(ProcessFactory.java:47)\n        at org.eclipse.cdt.utils.spawner.EnvironmentReader.getEnvVars\n(EnvironmentReader.java:49)\n        at org.eclipse.cdt.core.CommandLauncher.getEnvironment\n(CommandLauncher.java:67)\n        at org.eclipse.cdt.make.core.MakeBuilder.invokeMake\n(MakeBuilder.java:147)\n        at org.eclipse.cdt.make.core.MakeBuilder.build(MakeBuilder.java:76)\n        at org.eclipse.core.internal.events.BuildManager$2.run\n(BuildManager.java:570)\n        at org.eclipse.core.internal.runtime.InternalPlatform.run\n(InternalPlatform.java:616)\n        at org.eclipse.core.runtime.Platform.run(Platform.java:747)\n        at org.eclipse.core.internal.events.BuildManager.basicBuild\n(BuildManager.java:159)\n        at org.eclipse.core.internal.events.BuildManager.basicBuild\n(BuildManager.java:251)\n        at org.eclipse.core.internal.events.BuildManager.build\n(BuildManager.java:348)\n        at org.eclipse.core.internal.resources.Project.build(Project.java:81)\n        at org.eclipse.cdt.make.internal.core.MakeTarget$1.run\n(MakeTarget.java:160)\n        at org.eclipse.core.internal.resources.Workspace.run\n(Workspace.java:1673)\n        at org.eclipse.core.internal.resources.Workspace.run\n(Workspace.java:1693)\n        at org.eclipse.cdt.make.internal.core.MakeTarget.build\n(MakeTarget.java:173)\n        at org.eclipse.cdt.make.ui.TargetBuild$2.run(TargetBuild.java:94)\n        at org.eclipse.core.internal.resources.Workspace.run\n(Workspace.java:1673)\n        at org.eclipse.core.internal.resources.Workspace.run\n(Workspace.java:1693)\n        at org.eclipse.cdt.make.ui.TargetBuild$1.run(TargetBuild.java:97)\n        at org.eclipse.core.internal.jobs.Worker.run(Worker.java:66)"
  ],
  "commentCreationDates": [
    "2005-04-21T09:58:06+02:00"
  ],
  "traces": [
    {
      "exceptionType": "java.lang.UnsatisfiedLinkError",
      "message": "no spawner in java.library.path",
      "elements": [
        {
          "method": "java.lang.ClassLoader.loadLibrary",
          "source": "ClassLoader.java:1516"
        },
        {
          "method": "java.lang.Runtime.loadLibrary0",
          "source": "Runtime.java:788"
        },
        {
          "method": "java.lang.System.loadLibrary",
          "source": "System.java:834"
        },
        {
          "method": "org.eclipse.cdt.utils.spawner.ProcessFactory.\u003cinit\u003e",
          "source": "ProcessFactory.java:35"
        },
        {
          "method": "org.eclipse.cdt.utils.spawner.ProcessFactory.getFactory",
          "source": "ProcessFactory.java:47"
        },
        {
          "method": "org.eclipse.cdt.utils.spawner.EnvironmentReader.getEnvVars",
          "source": "EnvironmentReader.java:49"
        },
        {
          "method": "org.eclipse.cdt.core.CommandLauncher.getEnvironment",
          "source": "CommandLauncher.java:67"
        },
        {
          "method": "org.eclipse.cdt.make.core.MakeBuilder.invokeMake",
          "source": "MakeBuilder.java:147"
        },
        {
          "method": "org.eclipse.cdt.make.core.MakeBuilder.build",
          "source": "MakeBuilder.java:76"
        },
        {
          "method": "org.eclipse.core.internal.events.BuildManager$2.run",
          "source": "BuildManager.java:570"
        },
        {
          "method": "org.eclipse.core.internal.runtime.InternalPlatform.run",
          "source": "InternalPlatform.java:616"
        },
        {
          "method": "org.eclipse.core.runtime.Platform.run",
          "source": "Platform.java:747"
        },
        {
          "method": "org.eclipse.core.internal.events.BuildManager.basicBuild",
          "source": "BuildManager.java:159"
        },
        {
          "method": "org.eclipse.core.internal.events.BuildManager.basicBuild",
          "source": "BuildManager.java:251"
        },
        {
          "method": "org.eclipse.core.internal.events.BuildManager.build",
          "source": "BuildManager.java:348"
        },
        {
          "method": "org.eclipse.core.internal.resources.Project.build",
          "source": "Project.java:81"
        },
        {
          "method": "org.eclipse.cdt.make.internal.core.MakeTarget$1.run",
          "source": "MakeTarget.java:160"
        },
        {
          "method": "org.eclipse.core.internal.resources.Workspace.run",
          "source": "Workspace.java:1673"
        },
        {
          "method": "org.eclipse.core.internal.resources.Workspace.run",
          "source": "Workspace.java:1693"
        },
        {
          "method": "org.eclipse.cdt.make.internal.core.MakeTarget.build",
          "source": "MakeTarget.java:173"
        },
        {
          "method": "org.eclipse.cdt.make.ui.TargetBuild$2.run",
          "source": "TargetBuild.java:94"
        },
        {
          "method": "org.eclipse.core.internal.resources.Workspace.run",
          "source": "Workspace.java:1673"
        },
        {
          "method": "org.eclipse.core.internal.resources.Workspace.run",
          "source": "Workspace.java:1693"
        },
        {
          "method": "org.eclipse.cdt.make.ui.TargetBuild$1.run",
          "source": "TargetBuild.java:97"
        },
        {
          "method": "org.eclipse.core.internal.jobs.Worker.run",
          "source": "Worker.java:66"
        }
      ],
      "number": 0,
      "commentIndex": 0,
      "bugId": "92187",
      "date": "2005-04-21T09:58:06+02:00",
      "product": "CDT",
      "component": "cdt-build",
      "severity": "major"
    }
  ],
  "groupId": "92187",
  "bugId": "92187",
  "date": "2005-04-21T09:58:06+02:00",
  "product": "CDT",
  "component": "cdt-build",
  "severity": "major"
}