{
  "comments": [
    "This happens in today\u0027s build 20050420_1434.  \n\nAfter creating a new test (Junit or URL), when finish, Error message box popup.\nAlso get the error message box when double click on the test in test navigator.\nHere\u0027s the stacktrace:\norg.eclipse.jface.util.Assert$AssertionFailedException: null argument;\n\tat org.eclipse.jface.util.Assert.isNotNull(Assert.java:139)\n\tat org.eclipse.jface.util.Assert.isNotNull(Assert.java:116)\n\tat\norg.eclipse.jface.viewers.StructuredSelection.\u003cinit\u003e(StructuredSelection.java:61)\n\tat\norg.eclipse.hyades.test.ui.internal.navigator.TestNavigator.selectionChanged(TestNavigator.java:845)\n\nAs a result of not getting the proxy for test, Report... context menu is not\navailable after the test executed twice or more.  and because report is not\navailable from anywhere else, this feature is currently not available in 3.3. \nThus making it major.",
    "\n\n*** This bug has been marked as a duplicate of 92160 ***",
    "Sorry about this, I was refreshing my old web page and accidentally submitted a\nnew request."
  ],
  "commentCreationDates": [
    "2005-04-21T17:03:50+02:00",
    "2005-04-21T17:14:06+02:00",
    "2005-04-21T17:18:54+02:00"
  ],
  "traces": [
    {
      "exceptionType": "org.eclipse.jface.util.Assert$AssertionFailedException",
      "message": "null argument;",
      "elements": [
        {
          "method": "org.eclipse.jface.util.Assert.isNotNull",
          "source": "Assert.java:139"
        },
        {
          "method": "org.eclipse.jface.util.Assert.isNotNull",
          "source": "Assert.java:116"
        },
        {
          "method": "org.eclipse.jface.viewers.StructuredSelection.\u003cinit\u003e",
          "source": "StructuredSelection.java:61"
        },
        {
          "method": "org.eclipse.hyades.test.ui.internal.navigator.TestNavigator.selectionChanged",
          "source": "TestNavigator.java:845"
        }
      ],
      "number": 0,
      "commentIndex": 0,
      "bugId": "92234",
      "duplicateId": "92160",
      "date": "2005-04-21T17:03:50+02:00",
      "product": "Hyades",
      "component": "UI",
      "severity": "major"
    }
  ],
  "groupId": "92160",
  "bugId": "92234",
  "duplicateId": "92160",
  "date": "2005-04-21T17:03:50+02:00",
  "product": "Hyades",
  "component": "UI",
  "severity": "major"
}