{
  "comments": [
    "I\u0027ve seen errors similar to the one below when I try creating a second Web\nModule in a Flexible project using the wizard.\n\n\n*** ERROR ***: Fri Apr 22 10:56:37 EDT 2005    Component Type is null for the\nmodule: EEE in project: GGG\n\n*** ERROR ***: Fri Apr 22 10:56:37 EDT 2005    Component Type is null for the\nmodule: EEE in project: GGG\n\n*** ERROR ***: Fri Apr 22 10:56:37 EDT 2005    Component Type is null for the\nmodule: EEE in project: GGG\n\n*** ERROR ***: Fri Apr 22 10:56:37 EDT 2005    Component Type is null for the\nmodule: EEE in project: GGG\n\n*** ERROR ***: Fri Apr 22 10:56:37 EDT 2005   \njava.lang.reflect.InvocationTargetException\n        at\norg.eclipse.jface.operation.ModalContext.runInCurrentThread(ModalContext.java:357)\n        at org.eclipse.jface.operation.ModalContext.run(ModalContext.java:291)\n        at org.eclipse.jface.wizard.WizardDialog.run(WizardDialog.java:830)\n        at\norg.eclipse.wst.common.frameworks.internal.ui.WTPWizard.performFinish(WTPWizard.java:242)\n        at\norg.eclipse.jface.wizard.WizardDialog.finishPressed(WizardDialog.java:676)\n        at\norg.eclipse.jface.wizard.WizardDialog.buttonPressed(WizardDialog.java:349)\n        at org.eclipse.jface.dialogs.Dialog$2.widgetSelected(Dialog.java:556)\n        at\norg.eclipse.swt.widgets.TypedListener.handleEvent(TypedListener.java(Compiled Code))\n        at org.eclipse.swt.widgets.EventTable.sendEvent(EventTable.java(Compiled\nCode))\n        at org.eclipse.swt.widgets.Widget.sendEvent(Widget.java(Inlined Compiled\nCode))\n        at\norg.eclipse.swt.widgets.Display.runDeferredEvents(Display.java(Compiled Code))\n        at org.eclipse.swt.widgets.Display.readAndDispatch(Display.java(Compiled\nCode))\n        at org.eclipse.jface.window.Window.runEventLoop(Window.java(Compiled Code))\n        at org.eclipse.jface.window.Window.open(Window.java:781)\n        at\norg.eclipse.wst.common.navigator.internal.actions.WizardShortcutAction.run(WizardShortcutAction.java:114)\n        at org.eclipse.jface.action.Action.runWithEvent(Action.java:996)\n        at\norg.eclipse.jface.action.ActionContributionItem.handleWidgetSelection(ActionContributionItem.java:538)\n        at\norg.eclipse.jface.action.ActionContributionItem.access$2(ActionContributionItem.java:488)\n        at\norg.eclipse.jface.action.ActionContributionItem$5.handleEvent(ActionContributionItem.java:400)\n        at org.eclipse.swt.widgets.EventTable.sendEvent(EventTable.java(Compiled\nCode))\n        at org.eclipse.swt.widgets.Widget.sendEvent(Widget.java(Inlined Compiled\nCode))\n        at\norg.eclipse.swt.widgets.Display.runDeferredEvents(Display.java(Compiled Code))\n        at org.eclipse.swt.widgets.Display.readAndDispatch(Display.java(Compiled\nCode))\n        at\norg.eclipse.ui.internal.Workbench.runEventLoop(Workbench.java(Compiled Code))\n        at org.eclipse.ui.internal.Workbench.runUI(Workbench.java:1534)\n        at\norg.eclipse.ui.internal.Workbench.createAndRunWorkbench(Workbench.java:306)\n        at org.eclipse.ui.PlatformUI.createAndRunWorkbench(PlatformUI.java:143)\n        at org.eclipse.ui.internal.ide.IDEApplication.run(IDEApplication.java:103)\n        at\norg.eclipse.core.internal.runtime.PlatformActivator$1.run(PlatformActivator.java:228)\n        at\norg.eclipse.core.runtime.adaptor.EclipseStarter.run(EclipseStarter.java:344)\n        at\norg.eclipse.core.runtime.adaptor.EclipseStarter.run(EclipseStarter.java:156)\n        at sun.reflect.NativeMethodAccessorImpl.invoke0(Native Method)\n        at\nsun.reflect.NativeMethodAccessorImpl.invoke(NativeMethodAccessorImpl.java:85)\n        at\nsun.reflect.NativeMethodAccessorImpl.invoke(NativeMethodAccessorImpl.java:58)\n        at\nsun.reflect.DelegatingMethodAccessorImpl.invoke(DelegatingMethodAccessorImpl.java:60)\n        at java.lang.reflect.Method.invoke(Method.java:391)\n        at org.eclipse.core.launcher.Main.invokeFramework(Main.java:315)\n        at org.eclipse.core.launcher.Main.basicRun(Main.java:268)\n        at org.eclipse.core.launcher.Main.run(Main.java:942)\n        at org.eclipse.core.launcher.Main.main(Main.java:926)\n    Caused by: java.lang.IllegalArgumentException: Path must include project and\nresource name: /GGG\n        at org.eclipse.core.internal.utils.Assert.isLegal(Assert.java(Inlined\nCompiled Code))\n        at\norg.eclipse.core.internal.resources.Workspace.newResource(Workspace.java(Compiled\nCode))\n        at\norg.eclipse.core.internal.resources.Container.getFolder(Container.java:139)\n        at\norg.eclipse.wst.common.componentcore.internal.resources.VirtualFolder.create(VirtualFolder.java:57)\n        at\norg.eclipse.jst.j2ee.internal.web.archive.operations.WebComponentCreationOperation.createAndLinkJ2EEComponent\ns(WebComponentCreationOperation.java:69)\n        at\norg.eclipse.jst.j2ee.application.internal.operations.J2EEComponentCreationOperation.execute(J2EEComponentCrea\ntionOperation.java:75)\n        at\norg.eclipse.jst.j2ee.internal.web.archive.operations.WebComponentCreationOperation.execute(WebComponentCreati\nonOperation.java:110)\n        at\norg.eclipse.wst.common.frameworks.internal.operations.WTPOperation.doRun(WTPOperation.java:306)\n        at\norg.eclipse.wst.common.frameworks.internal.operations.WTPOperation$1.run(WTPOperation.java:230)\n        at org.eclipse.core.internal.resources.Workspace.run(Workspace.java:1714)\n        at org.eclipse.core.internal.resources.Workspace.run(Workspace.java:1734)\n        at\norg.eclipse.wst.common.frameworks.internal.operations.WTPOperation.run(WTPOperation.java:248)\n        at\norg.eclipse.wst.common.frameworks.internal.ui.RunnableWithProgressWrapper.run(RunnableWithProgressWrapper.jav\na:64)\n        at\norg.eclipse.jface.operation.ModalContext.runInCurrentThread(ModalContext.java:346)\n        ... 39 more",
    "Just assigning to specific component based on abstract.",
    "tested on M4  I build",
    "verified",
    "Changed Version field given new release numbering.\n"
  ],
  "commentCreationDates": [
    "2005-04-22T17:16:08+02:00",
    "2005-04-24T07:07:00+02:00",
    "2005-05-04T19:17:05+02:00",
    "2005-06-14T19:12:25+02:00",
    "2005-06-15T07:33:01+02:00"
  ],
  "traces": [
    {
      "exceptionType": "java.lang.reflect.InvocationTargetException",
      "elements": [
        {
          "method": "org.eclipse.jface.operation.ModalContext.runInCurrentThread",
          "source": "ModalContext.java:357"
        },
        {
          "method": "org.eclipse.jface.operation.ModalContext.run",
          "source": "ModalContext.java:291"
        },
        {
          "method": "org.eclipse.jface.wizard.WizardDialog.run",
          "source": "WizardDialog.java:830"
        },
        {
          "method": "org.eclipse.wst.common.frameworks.internal.ui.WTPWizard.performFinish",
          "source": "WTPWizard.java:242"
        },
        {
          "method": "org.eclipse.jface.wizard.WizardDialog.finishPressed",
          "source": "WizardDialog.java:676"
        },
        {
          "method": "org.eclipse.jface.wizard.WizardDialog.buttonPressed",
          "source": "WizardDialog.java:349"
        },
        {
          "method": "org.eclipse.jface.dialogs.Dialog$2.widgetSelected",
          "source": "Dialog.java:556"
        },
        {
          "method": "org.eclipse.swt.widgets.TypedListener.handleEvent",
          "source": "TypedListener.java(Compiled Code)"
        },
        {
          "method": "org.eclipse.swt.widgets.EventTable.sendEvent",
          "source": "EventTable.java(Compiled Code)"
        },
        {
          "method": "org.eclipse.swt.widgets.Widget.sendEvent",
          "source": "Widget.java(Inlined Compiled Code)"
        },
        {
          "method": "org.eclipse.swt.widgets.Display.runDeferredEvents",
          "source": "Display.java(Compiled Code)"
        },
        {
          "method": "org.eclipse.swt.widgets.Display.readAndDispatch",
          "source": "Display.java(Compiled Code)"
        },
        {
          "method": "org.eclipse.jface.window.Window.runEventLoop",
          "source": "Window.java(Compiled Code)"
        },
        {
          "method": "org.eclipse.jface.window.Window.open",
          "source": "Window.java:781"
        },
        {
          "method": "org.eclipse.wst.common.navigator.internal.actions.WizardShortcutAction.run",
          "source": "WizardShortcutAction.java:114"
        },
        {
          "method": "org.eclipse.jface.action.Action.runWithEvent",
          "source": "Action.java:996"
        },
        {
          "method": "org.eclipse.jface.action.ActionContributionItem.handleWidgetSelection",
          "source": "ActionContributionItem.java:538"
        },
        {
          "method": "org.eclipse.jface.action.ActionContributionItem.access$2",
          "source": "ActionContributionItem.java:488"
        },
        {
          "method": "org.eclipse.jface.action.ActionContributionItem$5.handleEvent",
          "source": "ActionContributionItem.java:400"
        },
        {
          "method": "org.eclipse.swt.widgets.EventTable.sendEvent",
          "source": "EventTable.java(Compiled Code)"
        },
        {
          "method": "org.eclipse.swt.widgets.Widget.sendEvent",
          "source": "Widget.java(Inlined Compiled Code)"
        },
        {
          "method": "org.eclipse.swt.widgets.Display.runDeferredEvents",
          "source": "Display.java(Compiled Code)"
        },
        {
          "method": "org.eclipse.swt.widgets.Display.readAndDispatch",
          "source": "Display.java(Compiled Code)"
        },
        {
          "method": "org.eclipse.ui.internal.Workbench.runEventLoop",
          "source": "Workbench.java(Compiled Code)"
        },
        {
          "method": "org.eclipse.ui.internal.Workbench.runUI",
          "source": "Workbench.java:1534"
        },
        {
          "method": "org.eclipse.ui.internal.Workbench.createAndRunWorkbench",
          "source": "Workbench.java:306"
        },
        {
          "method": "org.eclipse.ui.PlatformUI.createAndRunWorkbench",
          "source": "PlatformUI.java:143"
        },
        {
          "method": "org.eclipse.ui.internal.ide.IDEApplication.run",
          "source": "IDEApplication.java:103"
        },
        {
          "method": "org.eclipse.core.internal.runtime.PlatformActivator$1.run",
          "source": "PlatformActivator.java:228"
        },
        {
          "method": "org.eclipse.core.runtime.adaptor.EclipseStarter.run",
          "source": "EclipseStarter.java:344"
        },
        {
          "method": "org.eclipse.core.runtime.adaptor.EclipseStarter.run",
          "source": "EclipseStarter.java:156"
        },
        {
          "method": "sun.reflect.NativeMethodAccessorImpl.invoke0",
          "source": "Native Method"
        },
        {
          "method": "sun.reflect.NativeMethodAccessorImpl.invoke",
          "source": "NativeMethodAccessorImpl.java:85"
        },
        {
          "method": "sun.reflect.NativeMethodAccessorImpl.invoke",
          "source": "NativeMethodAccessorImpl.java:58"
        },
        {
          "method": "sun.reflect.DelegatingMethodAccessorImpl.invoke",
          "source": "DelegatingMethodAccessorImpl.java:60"
        },
        {
          "method": "java.lang.reflect.Method.invoke",
          "source": "Method.java:391"
        },
        {
          "method": "org.eclipse.core.launcher.Main.invokeFramework",
          "source": "Main.java:315"
        },
        {
          "method": "org.eclipse.core.launcher.Main.basicRun",
          "source": "Main.java:268"
        },
        {
          "method": "org.eclipse.core.launcher.Main.run",
          "source": "Main.java:942"
        },
        {
          "method": "org.eclipse.core.launcher.Main.main",
          "source": "Main.java:926"
        }
      ],
      "causedBy": {
        "exceptionType": "java.lang.IllegalArgumentException",
        "message": "Path must include project and resource name: /GGG",
        "elements": [
          {
            "method": "org.eclipse.core.internal.utils.Assert.isLegal",
            "source": "Assert.java(Inlined Compiled Code)"
          },
          {
            "method": "org.eclipse.core.internal.resources.Workspace.newResource",
            "source": "Workspace.java(Compiled Code)"
          },
          {
            "method": "org.eclipse.core.internal.resources.Container.getFolder",
            "source": "Container.java:139"
          },
          {
            "method": "org.eclipse.wst.common.componentcore.internal.resources.VirtualFolder.create",
            "source": "VirtualFolder.java:57"
          },
          {
            "method": "org.eclipse.jst.j2ee.internal.web.archive.operations.WebComponentCreationOperation.createAndLinkJ2EEComponents",
            "source": "WebComponentCreationOperation.java:69"
          },
          {
            "method": "org.eclipse.jst.j2ee.application.internal.operations.J2EEComponentCreationOperation.execute",
            "source": "J2EEComponentCrea tionOperation.java:75"
          },
          {
            "method": "org.eclipse.jst.j2ee.internal.web.archive.operations.WebComponentCreationOperation.execute",
            "source": "WebComponentCreati onOperation.java:110"
          },
          {
            "method": "org.eclipse.wst.common.frameworks.internal.operations.WTPOperation.doRun",
            "source": "WTPOperation.java:306"
          },
          {
            "method": "org.eclipse.wst.common.frameworks.internal.operations.WTPOperation$1.run",
            "source": "WTPOperation.java:230"
          },
          {
            "method": "org.eclipse.core.internal.resources.Workspace.run",
            "source": "Workspace.java:1714"
          },
          {
            "method": "org.eclipse.core.internal.resources.Workspace.run",
            "source": "Workspace.java:1734"
          },
          {
            "method": "org.eclipse.wst.common.frameworks.internal.operations.WTPOperation.run",
            "source": "WTPOperation.java:248"
          },
          {
            "method": "org.eclipse.wst.common.frameworks.internal.ui.RunnableWithProgressWrapper.run",
            "source": "RunnableWithProgressWrapper.jav a:64"
          },
          {
            "method": "org.eclipse.jface.operation.ModalContext.runInCurrentThread",
            "source": "ModalContext.java:346"
          }
        ],
        "number": 0,
        "commentIndex": 0
      },
      "number": 0,
      "commentIndex": 0,
      "bugId": "92388",
      "date": "2005-04-22T17:16:08+02:00",
      "product": "Web Tools",
      "component": "jst.j2ee",
      "severity": "normal"
    }
  ],
  "groupId": "92388",
  "bugId": "92388",
  "date": "2005-04-22T17:16:08+02:00",
  "product": "Web Tools",
  "component": "jst.j2ee",
  "severity": "normal"
}