{
  "comments": [
    "I upgraded Eclipse and found that it was not working after the upgrade. \n\nSo i decided to do the quick fix and installed a clean 3.0 version i had still\non my hard disk - eclipse-SDK-3.0-win32.zip.\nI started up, everything worked fine, then i upgraded to 3.0.2 from within the\napplication. The upgrade installed, eclipse restarted and produced this error\nmessage:\n\"An error has occurred. See log file...\"\n\nI thought this worthy of filing because it should be reproducable anywhere. I\ntook a clean, unchanged 3.0 install and upgraded, following the recommended\nsteps. I chose all the default values in all dialogs.\n\nLog file as follows:\n!SESSION Apr 24, 2005 17:00:22.875 ---------------------------------------------\neclipse.buildId\u003dI200406251208\njava.version\u003d1.4.2_07\njava.vendor\u003dSun Microsystems Inc.\nBootLoader constants: OS\u003dwin32, ARCH\u003dx86, WS\u003dwin32, NL\u003den_US\n\n!ENTRY org.eclipse.osgi Apr 24, 2005 17:00:22.875\n!MESSAGE Application error\n!STACK 1\njava.lang.RuntimeException: No application id has been found.\n\tat\norg.eclipse.core.internal.runtime.PlatformActivator$1.run(PlatformActivator.java:313)\n\tat org.eclipse.core.runtime.adaptor.EclipseStarter.run(EclipseStarter.java:273)\n\tat org.eclipse.core.runtime.adaptor.EclipseStarter.run(EclipseStarter.java:129)\n\tat sun.reflect.NativeMethodAccessorImpl.invoke0(Native Method)\n\tat sun.reflect.NativeMethodAccessorImpl.invoke(Unknown Source)\n\tat sun.reflect.DelegatingMethodAccessorImpl.invoke(Unknown Source)\n\tat java.lang.reflect.Method.invoke(Unknown Source)\n\tat org.eclipse.core.launcher.Main.basicRun(Main.java:183)\n\tat org.eclipse.core.launcher.Main.run(Main.java:644)\n\tat org.eclipse.core.launcher.Main.main(Main.java:628)\n\n!ENTRY org.eclipse.osgi Apr 24, 2005 17:00:22.875\n!MESSAGE Bundle update@/c:/eclipse/plugins/org.eclipse.compare_3.0.0/ [7] was\nnot resolved.\n\n!ENTRY org.eclipse.osgi Apr 24, 2005 17:00:22.875\n!MESSAGE Bundle\nupdate@/c:/eclipse/plugins/org.eclipse.core.resources.win32_3.0.0/ [11] was not\nresolved.\n\n!ENTRY org.eclipse.osgi Apr 24, 2005 17:00:22.890\n!MESSAGE Bundle update@/c:/eclipse/plugins/org.eclipse.help.ide_3.0.0/ [20] was\nnot resolved.\n\n!ENTRY org.eclipse.osgi Apr 24, 2005 17:00:22.890\n!MESSAGE Bundle update@/c:/eclipse/plugins/org.eclipse.team.core_3.0.0/ [59] was\nnot resolved.\n\n!ENTRY org.eclipse.osgi Apr 24, 2005 17:00:22.890\n!MESSAGE Bundle update@/c:/eclipse/plugins/org.eclipse.team.cvs.ssh2_3.0.0/ [61]\nwas not resolved.\n\n!ENTRY org.eclipse.osgi Apr 24, 2005 17:00:22.890\n!MESSAGE Bundle update@/c:/eclipse/plugins/org.eclipse.team.cvs.ssh_3.0.0/ [62]\nwas not resolved.\n\n!ENTRY org.eclipse.osgi Apr 24, 2005 17:00:22.890\n!MESSAGE Bundle update@/c:/eclipse/plugins/org.eclipse.tomcat_4.1.30/ [66] was\nnot resolved.\n\n!ENTRY org.eclipse.osgi Apr 24, 2005 17:00:22.890\n!MESSAGE Bundle update@/c:/eclipse/plugins/org.eclipse.ui.console_3.0.0/ [68]\nwas not resolved.\n\n!ENTRY org.eclipse.osgi Apr 24, 2005 17:00:22.890\n!MESSAGE Bundle update@/c:/eclipse/plugins/org.eclipse.ui.forms_3.0.0/ [71] was\nnot resolved.\n\n!ENTRY org.eclipse.osgi Apr 24, 2005 17:00:22.890\n!MESSAGE Bundle update@/c:/eclipse/plugins/org.eclipse.ui.views_3.0.0/ [75] was\nnot resolved.\n\n!ENTRY org.eclipse.osgi Apr 24, 2005 17:00:22.890\n!MESSAGE Bundle\nupdate@/c:/eclipse/plugins/org.eclipse.ui.workbench.compatibility_3.0.0/ [77]\nwas not resolved.\n\n!ENTRY org.eclipse.osgi Apr 24, 2005 17:00:22.890\n!MESSAGE Bundle update@/c:/eclipse/plugins/org.eclipse.update.core.win32_3.0.0/\n[82] was not resolved.\n\n!ENTRY org.eclipse.osgi Apr 24, 2005 17:00:22.890\n!MESSAGE Bundle update@/c:/eclipse/plugins/org.eclipse.ant.ui_3.0.2/ [87] was\nnot resolved.\n!SUBENTRY 1 org.eclipse.osgi Apr 24, 2005 17:00:22.906\n!MESSAGE Missing optionally required bundle org.eclipse.ui.ide_0.0.0.\n!SUBENTRY 1 org.eclipse.osgi Apr 24, 2005 17:00:22.906\n!MESSAGE Missing optionally required bundle org.eclipse.ui.views_0.0.0.\n!SUBENTRY 1 org.eclipse.osgi Apr 24, 2005 17:00:22.906\n!MESSAGE Missing optionally required bundle org.eclipse.jface.text_0.0.0.\n!SUBENTRY 1 org.eclipse.osgi Apr 24, 2005 17:00:22.906\n!MESSAGE Missing optionally required bundle\norg.eclipse.ui.workbench.texteditor_0.0.0.\n!SUBENTRY 1 org.eclipse.osgi Apr 24, 2005 17:00:22.906\n!MESSAGE Missing optionally required bundle org.eclipse.ui.editors_0.0.0.\n!SUBENTRY 1 org.eclipse.osgi Apr 24, 2005 17:00:22.906\n!MESSAGE Missing required bundle org.apache.ant_0.0.0.\n!SUBENTRY 1 org.eclipse.osgi Apr 24, 2005 17:00:22.906\n!MESSAGE Missing required bundle org.eclipse.core.resources_0.0.0.\n!SUBENTRY 1 org.eclipse.osgi Apr 24, 2005 17:00:22.906\n!MESSAGE Missing required bundle org.eclipse.core.filebuffers_0.0.0.\n!SUBENTRY 1 org.eclipse.osgi Apr 24, 2005 17:00:22.906\n!MESSAGE Missing required bundle org.eclipse.ui.externaltools_0.0.0.\n!SUBENTRY 1 org.eclipse.osgi Apr 24, 2005 17:00:22.906\n!MESSAGE Missing required bundle org.eclipse.ui_0.0.0.\n!SUBENTRY 1 org.eclipse.osgi Apr 24, 2005 17:00:22.906\n!MESSAGE Missing required bundle org.eclipse.ui.console_0.0.0.\n!SUBENTRY 1 org.eclipse.osgi Apr 24, 2005 17:00:22.906\n!MESSAGE Missing required bundle org.eclipse.debug.core_0.0.0.\n!SUBENTRY 1 org.eclipse.osgi Apr 24, 2005 17:00:22.906\n!MESSAGE Missing required bundle org.eclipse.debug.ui_0.0.0.\n!SUBENTRY 1 org.eclipse.osgi Apr 24, 2005 17:00:22.906\n!MESSAGE Missing required bundle org.eclipse.jdt.ui_0.0.0.\n!SUBENTRY 1 org.eclipse.osgi Apr 24, 2005 17:00:22.906\n!MESSAGE Missing required bundle org.eclipse.jdt.debug.ui_0.0.0.\n!SUBENTRY 1 org.eclipse.osgi Apr 24, 2005 17:00:22.906\n!MESSAGE Missing required bundle org.eclipse.jdt.launching_0.0.0.\n!SUBENTRY 1 org.eclipse.osgi Apr 24, 2005 17:00:22.906\n!MESSAGE Missing required bundle org.eclipse.jdt.core_0.0.0.\n\n!ENTRY org.eclipse.osgi Apr 24, 2005 17:00:22.906\n!MESSAGE Bundle update@/c:/eclipse/plugins/org.eclipse.jdt.core_3.0.2/ [88] was\nnot resolved.\n!SUBENTRY 1 org.eclipse.osgi Apr 24, 2005 17:00:22.906\n!MESSAGE Missing required bundle org.eclipse.core.resources_0.0.0.\n!SUBENTRY 1 org.eclipse.osgi Apr 24, 2005 17:00:22.906\n!MESSAGE Missing required bundle org.eclipse.text_0.0.0.\n!SUBENTRY 1 org.eclipse.osgi Apr 24, 2005 17:00:22.906\n!MESSAGE Missing optionally required bundle org.apache.ant_0.0.0.\n!SUBENTRY 1 org.eclipse.osgi Apr 24, 2005 17:00:22.906\n!MESSAGE Missing optionally required bundle org.eclipse.team.core_0.0.0.\n\n!ENTRY org.eclipse.osgi Apr 24, 2005 17:00:22.906\n!MESSAGE Bundle update@/c:/eclipse/plugins/org.eclipse.jdt.debug.ui_3.0.2/ [89]\nwas not resolved.\n!SUBENTRY 1 org.eclipse.osgi Apr 24, 2005 17:00:22.906\n!MESSAGE Missing required bundle org.eclipse.ui.ide_0.0.0.\n!SUBENTRY 1 org.eclipse.osgi Apr 24, 2005 17:00:22.906\n!MESSAGE Missing required bundle org.eclipse.jface.text_0.0.0.\n!SUBENTRY 1 org.eclipse.osgi Apr 24, 2005 17:00:22.906\n!MESSAGE Missing required bundle org.eclipse.ui.workbench.texteditor_0.0.0.\n!SUBENTRY 1 org.eclipse.osgi Apr 24, 2005 17:00:22.906\n!MESSAGE Missing required bundle org.eclipse.ui.editors_0.0.0.\n!SUBENTRY 1 org.eclipse.osgi Apr 24, 2005 17:00:22.906\n!MESSAGE Missing required bundle org.eclipse.ui_0.0.0.\n!SUBENTRY 1 org.eclipse.osgi Apr 24, 2005 17:00:22.906\n!MESSAGE Missing required bundle org.eclipse.core.filebuffers_0.0.0.\n!SUBENTRY 1 org.eclipse.osgi Apr 24, 2005 17:00:22.906\n!MESSAGE Missing required bundle org.eclipse.core.resources_0.0.0.\n!SUBENTRY 1 org.eclipse.osgi Apr 24, 2005 17:00:22.906\n!MESSAGE Missing required bundle org.eclipse.jdt.core_0.0.0.\n!SUBENTRY 1 org.eclipse.osgi Apr 24, 2005 17:00:22.906\n!MESSAGE Missing required bundle org.eclipse.debug.core_0.0.0.\n!SUBENTRY 1 org.eclipse.osgi Apr 24, 2005 17:00:22.906\n!MESSAGE Missing required bundle org.eclipse.debug.ui_0.0.0.\n!SUBENTRY 1 org.eclipse.osgi Apr 24, 2005 17:00:22.906\n!MESSAGE Missing required bundle org.eclipse.jdt.debug_0.0.0.\n!SUBENTRY 1 org.eclipse.osgi Apr 24, 2005 17:00:22.906\n!MESSAGE Missing required bundle org.eclipse.jdt.launching_0.0.0.\n!SUBENTRY 1 org.eclipse.osgi Apr 24, 2005 17:00:22.906\n!MESSAGE Missing required bundle org.eclipse.jdt.ui_0.0.0.\n!SUBENTRY 1 org.eclipse.osgi Apr 24, 2005 17:00:22.906\n!MESSAGE Missing required bundle org.eclipse.ltk.core.refactoring_0.0.0.\n\n!ENTRY org.eclipse.osgi Apr 24, 2005 17:00:22.906\n!MESSAGE Bundle update@/c:/eclipse/plugins/org.eclipse.jdt.debug_3.0.2/ [90] was\nnot resolved.\n!SUBENTRY 1 org.eclipse.osgi Apr 24, 2005 17:00:22.906\n!MESSAGE Missing required bundle org.eclipse.core.resources_0.0.0.\n!SUBENTRY 1 org.eclipse.osgi Apr 24, 2005 17:00:22.906\n!MESSAGE Missing required bundle org.eclipse.debug.core_0.0.0.\n!SUBENTRY 1 org.eclipse.osgi Apr 24, 2005 17:00:22.906\n!MESSAGE Missing required bundle org.eclipse.jdt.core_0.0.0.\n\n!ENTRY org.eclipse.osgi Apr 24, 2005 17:00:22.906\n!MESSAGE Bundle update@/c:/eclipse/plugins/org.eclipse.jdt.junit_3.0.1/ [94] was\nnot resolved.\n!SUBENTRY 1 org.eclipse.osgi Apr 24, 2005 17:00:22.906\n!MESSAGE Missing required bundle org.eclipse.ui.ide_0.0.0.\n!SUBENTRY 1 org.eclipse.osgi Apr 24, 2005 17:00:22.906\n!MESSAGE Missing required bundle org.eclipse.ui.views_0.0.0.\n!SUBENTRY 1 org.eclipse.osgi Apr 24, 2005 17:00:22.906\n!MESSAGE Missing required bundle org.eclipse.jface.text_0.0.0.\n!SUBENTRY 1 org.eclipse.osgi Apr 24, 2005 17:00:22.921\n!MESSAGE Missing required bundle org.eclipse.ui.workbench.texteditor_0.0.0.\n!SUBENTRY 1 org.eclipse.osgi Apr 24, 2005 17:00:22.921\n!MESSAGE Missing required bundle org.eclipse.ui.editors_0.0.0.\n!SUBENTRY 1 org.eclipse.osgi Apr 24, 2005 17:00:22.921\n!MESSAGE Missing required bundle org.eclipse.ui_0.0.0.\n!SUBENTRY 1 org.eclipse.osgi Apr 24, 2005 17:00:22.921\n!MESSAGE Missing required bundle org.eclipse.core.resources_0.0.0.\n!SUBENTRY 1 org.eclipse.osgi Apr 24, 2005 17:00:22.921\n!MESSAGE Missing required bundle org.eclipse.debug.core_0.0.0.\n!SUBENTRY 1 org.eclipse.osgi Apr 24, 2005 17:00:22.921\n!MESSAGE Missing required bundle org.eclipse.debug.ui_0.0.0.\n!SUBENTRY 1 org.eclipse.osgi Apr 24, 2005 17:00:22.921\n!MESSAGE Missing required bundle org.eclipse.jdt.core_0.0.0.\n!SUBENTRY 1 org.eclipse.osgi Apr 24, 2005 17:00:22.921\n!MESSAGE Missing required bundle org.eclipse.jdt.ui_0.0.0.\n!SUBENTRY 1 org.eclipse.osgi Apr 24, 2005 17:00:22.921\n!MESSAGE Missing required bundle org.eclipse.jdt.launching_0.0.0.\n!SUBENTRY 1 org.eclipse.osgi Apr 24, 2005 17:00:22.921\n!MESSAGE Missing required bundle org.eclipse.jdt.debug.ui_0.0.0.\n!SUBENTRY 1 org.eclipse.osgi Apr 24, 2005 17:00:22.921\n!MESSAGE Missing required bundle org.eclipse.compare_0.0.0.\n!SUBENTRY 1 org.eclipse.osgi Apr 24, 2005 17:00:22.921\n!MESSAGE Missing required bundle org.eclipse.ltk.core.refactoring_0.0.0.\n\n!ENTRY org.eclipse.osgi Apr 24, 2005 17:00:22.921\n!MESSAGE Bundle update@/c:/eclipse/plugins/org.eclipse.jdt.launching_3.0.2/ [95]\nwas not resolved.\n!SUBENTRY 1 org.eclipse.osgi Apr 24, 2005 17:00:22.921\n!MESSAGE Missing required bundle org.eclipse.core.resources_0.0.0.\n!SUBENTRY 1 org.eclipse.osgi Apr 24, 2005 17:00:22.921\n!MESSAGE Missing required bundle org.eclipse.jdt.core_0.0.0.\n!SUBENTRY 1 org.eclipse.osgi Apr 24, 2005 17:00:22.921\n!MESSAGE Missing required bundle org.eclipse.debug.core_0.0.0.\n!SUBENTRY 1 org.eclipse.osgi Apr 24, 2005 17:00:22.921\n!MESSAGE Missing required bundle org.eclipse.jdt.debug_0.0.0.\n\n!ENTRY org.eclipse.osgi Apr 24, 2005 17:00:22.921\n!MESSAGE Bundle update@/c:/eclipse/plugins/org.eclipse.jdt.ui_3.0.2/ [97] was\nnot resolved.\n!SUBENTRY 1 org.eclipse.osgi Apr 24, 2005 17:00:22.921\n!MESSAGE Missing required bundle org.eclipse.ui_0.0.0.\n!SUBENTRY 1 org.eclipse.osgi Apr 24, 2005 17:00:22.921\n!MESSAGE Missing required bundle org.eclipse.ui.console_0.0.0.\n!SUBENTRY 1 org.eclipse.osgi Apr 24, 2005 17:00:22.921\n!MESSAGE Missing required bundle org.eclipse.core.resources_0.0.0.\n!SUBENTRY 1 org.eclipse.osgi Apr 24, 2005 17:00:22.921\n!MESSAGE Missing required bundle org.eclipse.jdt.core_0.0.0.\n!SUBENTRY 1 org.eclipse.osgi Apr 24, 2005 17:00:22.921\n!MESSAGE Missing required bundle org.eclipse.search_0.0.0.\n!SUBENTRY 1 org.eclipse.osgi Apr 24, 2005 17:00:22.921\n!MESSAGE Missing required bundle org.eclipse.debug.core_0.0.0.\n!SUBENTRY 1 org.eclipse.osgi Apr 24, 2005 17:00:22.921\n!MESSAGE Missing required bundle org.eclipse.debug.ui_0.0.0.\n!SUBENTRY 1 org.eclipse.osgi Apr 24, 2005 17:00:22.921\n!MESSAGE Missing required bundle org.eclipse.jdt.launching_0.0.0.\n!SUBENTRY 1 org.eclipse.osgi Apr 24, 2005 17:00:22.921\n!MESSAGE Missing required bundle org.eclipse.compare_0.0.0.\n!SUBENTRY 1 org.eclipse.osgi Apr 24, 2005 17:00:22.921\n!MESSAGE Missing required bundle org.eclipse.team.core_0.0.0.\n!SUBENTRY 1 org.eclipse.osgi Apr 24, 2005 17:00:22.921\n!MESSAGE Missing required bundle org.eclipse.core.filebuffers_0.0.0.\n!SUBENTRY 1 org.eclipse.osgi Apr 24, 2005 17:00:22.921\n!MESSAGE Missing required bundle org.eclipse.jface.text_0.0.0.\n!SUBENTRY 1 org.eclipse.osgi Apr 24, 2005 17:00:22.921\n!MESSAGE Missing required bundle org.eclipse.ui.workbench.texteditor_0.0.0.\n!SUBENTRY 1 org.eclipse.osgi Apr 24, 2005 17:00:22.921\n!MESSAGE Missing required bundle org.eclipse.ui.ide_0.0.0.\n!SUBENTRY 1 org.eclipse.osgi Apr 24, 2005 17:00:22.921\n!MESSAGE Missing required bundle org.eclipse.ui.views_0.0.0.\n!SUBENTRY 1 org.eclipse.osgi Apr 24, 2005 17:00:22.921\n!MESSAGE Missing required bundle org.eclipse.ui.editors_0.0.0.\n!SUBENTRY 1 org.eclipse.osgi Apr 24, 2005 17:00:22.921\n!MESSAGE Missing required bundle org.eclipse.ltk.core.refactoring_0.0.0.\n!SUBENTRY 1 org.eclipse.osgi Apr 24, 2005 17:00:22.921\n!MESSAGE Missing required bundle org.eclipse.ltk.ui.refactoring_0.0.0.\n\n!ENTRY org.eclipse.osgi Apr 24, 2005 17:00:22.921\n!MESSAGE Bundle update@/c:/eclipse/plugins/org.eclipse.jdt_3.0.2/ [98] was not\nresolved.\n!SUBENTRY 1 org.eclipse.osgi Apr 24, 2005 17:00:22.921\n!MESSAGE Missing required bundle org.eclipse.ui.intro_0.0.0.\n!SUBENTRY 1 org.eclipse.osgi Apr 24, 2005 17:00:22.921\n!MESSAGE Missing required bundle org.eclipse.ui.cheatsheets_0.0.0.\n\n!ENTRY org.eclipse.osgi Apr 24, 2005 17:00:22.921\n!MESSAGE Bundle\nupdate@/c:/eclipse/plugins/org.eclipse.ltk.core.refactoring_3.0.1/ [99] was not\nresolved.\n!SUBENTRY 1 org.eclipse.osgi Apr 24, 2005 17:00:22.937\n!MESSAGE Missing required bundle org.eclipse.core.filebuffers_0.0.0.\n!SUBENTRY 1 org.eclipse.osgi Apr 24, 2005 17:00:22.937\n!MESSAGE Missing required bundle org.eclipse.core.resources_0.0.0.\n!SUBENTRY 1 org.eclipse.osgi Apr 24, 2005 17:00:22.937\n!MESSAGE Missing required bundle org.eclipse.text_0.0.0.\n\n!ENTRY org.eclipse.osgi Apr 24, 2005 17:00:22.937\n!MESSAGE Bundle update@/c:/eclipse/plugins/org.eclipse.ltk.ui.refactoring_3.0.1/\n[100] was not resolved.\n!SUBENTRY 1 org.eclipse.osgi Apr 24, 2005 17:00:22.937\n!MESSAGE Missing required bundle org.eclipse.core.filebuffers_0.0.0.\n!SUBENTRY 1 org.eclipse.osgi Apr 24, 2005 17:00:22.937\n!MESSAGE Missing required bundle org.eclipse.core.resources_0.0.0.\n!SUBENTRY 1 org.eclipse.osgi Apr 24, 2005 17:00:22.937\n!MESSAGE Missing required bundle org.eclipse.text_0.0.0.\n!SUBENTRY 1 org.eclipse.osgi Apr 24, 2005 17:00:22.937\n!MESSAGE Missing required bundle org.eclipse.ltk.core.refactoring_0.0.0.\n!SUBENTRY 1 org.eclipse.osgi Apr 24, 2005 17:00:22.937\n!MESSAGE Missing required bundle org.eclipse.jdt.core_0.0.0.\n!SUBENTRY 1 org.eclipse.osgi Apr 24, 2005 17:00:22.937\n!MESSAGE Missing required bundle org.eclipse.jface.text_0.0.0.\n!SUBENTRY 1 org.eclipse.osgi Apr 24, 2005 17:00:22.937\n!MESSAGE Missing required bundle org.eclipse.ui_0.0.0.\n!SUBENTRY 1 org.eclipse.osgi Apr 24, 2005 17:00:22.937\n!MESSAGE Missing required bundle org.eclipse.compare_0.0.0.\n!SUBENTRY 1 org.eclipse.osgi Apr 24, 2005 17:00:22.937\n!MESSAGE Missing required bundle org.eclipse.ui.workbench.texteditor_0.0.0.\n\n!ENTRY org.eclipse.osgi Apr 24, 2005 17:00:22.937\n!MESSAGE Bundle update@/c:/eclipse/plugins/org.eclipse.pde.build_3.0.1/ [101]\nwas not resolved.\n!SUBENTRY 1 org.eclipse.osgi Apr 24, 2005 17:00:22.937\n!MESSAGE Missing required bundle org.eclipse.update.core_0.0.0.\n!SUBENTRY 1 org.eclipse.osgi Apr 24, 2005 17:00:22.937\n!MESSAGE Missing required bundle org.apache.ant_0.0.0.\n\n!ENTRY org.eclipse.osgi Apr 24, 2005 17:00:22.937\n!MESSAGE Bundle update@/c:/eclipse/plugins/org.eclipse.pde.core_3.0.2/ [102] was\nnot resolved.\n!SUBENTRY 1 org.eclipse.osgi Apr 24, 2005 17:00:22.937\n!MESSAGE Missing required bundle org.eclipse.core.resources_0.0.0.\n!SUBENTRY 1 org.eclipse.osgi Apr 24, 2005 17:00:22.937\n!MESSAGE Missing required bundle org.eclipse.jdt.core_0.0.0.\n!SUBENTRY 1 org.eclipse.osgi Apr 24, 2005 17:00:22.937\n!MESSAGE Missing required bundle org.eclipse.team.core_0.0.0.\n\n!ENTRY org.eclipse.osgi Apr 24, 2005 17:00:22.937\n!MESSAGE Bundle update@/c:/eclipse/plugins/org.eclipse.pde.runtime_3.0.1/ [103]\nwas not resolved.\n!SUBENTRY 1 org.eclipse.osgi Apr 24, 2005 17:00:22.937\n!MESSAGE Missing required bundle org.eclipse.ui_0.0.0.\n!SUBENTRY 1 org.eclipse.osgi Apr 24, 2005 17:00:22.937\n!MESSAGE Missing required bundle org.eclipse.ui.views_0.0.0.\n\n!ENTRY org.eclipse.osgi Apr 24, 2005 17:00:22.937\n!MESSAGE Bundle update@/c:/eclipse/plugins/org.eclipse.pde.ui_3.0.2/ [105] was\nnot resolved.\n!SUBENTRY 1 org.eclipse.osgi Apr 24, 2005 17:00:22.937\n!MESSAGE Missing required bundle org.eclipse.ui.ide_0.0.0.\n!SUBENTRY 1 org.eclipse.osgi Apr 24, 2005 17:00:22.937\n!MESSAGE Missing required bundle org.eclipse.ui.views_0.0.0.\n!SUBENTRY 1 org.eclipse.osgi Apr 24, 2005 17:00:22.937\n!MESSAGE Missing required bundle org.eclipse.jface.text_0.0.0.\n!SUBENTRY 1 org.eclipse.osgi Apr 24, 2005 17:00:22.937\n!MESSAGE Missing required bundle org.eclipse.ui.workbench.texteditor_0.0.0.\n!SUBENTRY 1 org.eclipse.osgi Apr 24, 2005 17:00:22.937\n!MESSAGE Missing required bundle org.eclipse.ui.editors_0.0.0.\n!SUBENTRY 1 org.eclipse.osgi Apr 24, 2005 17:00:22.937\n!MESSAGE Missing required bundle org.eclipse.core.resources_0.0.0.\n!SUBENTRY 1 org.eclipse.osgi Apr 24, 2005 17:00:22.937\n!MESSAGE Missing required bundle org.eclipse.debug.core_0.0.0.\n!SUBENTRY 1 org.eclipse.osgi Apr 24, 2005 17:00:22.937\n!MESSAGE Missing required bundle org.eclipse.debug.ui_0.0.0.\n!SUBENTRY 1 org.eclipse.osgi Apr 24, 2005 17:00:22.937\n!MESSAGE Missing required bundle org.eclipse.help.base_0.0.0.\n!SUBENTRY 1 org.eclipse.osgi Apr 24, 2005 17:00:22.937\n!MESSAGE Missing required bundle org.eclipse.jdt.core_0.0.0.\n!SUBENTRY 1 org.eclipse.osgi Apr 24, 2005 17:00:22.937\n!MESSAGE Missing required bundle org.eclipse.jdt.debug.ui_0.0.0.\n!SUBENTRY 1 org.eclipse.osgi Apr 24, 2005 17:00:22.937\n!MESSAGE Missing required bundle org.eclipse.jdt.launching_0.0.0.\n!SUBENTRY 1 org.eclipse.osgi Apr 24, 2005 17:00:22.937\n!MESSAGE Missing required bundle org.eclipse.jdt.ui_0.0.0.\n!SUBENTRY 1 org.eclipse.osgi Apr 24, 2005 17:00:22.937\n!MESSAGE Missing required bundle org.eclipse.pde_0.0.0.\n!SUBENTRY 1 org.eclipse.osgi Apr 24, 2005 17:00:22.953\n!MESSAGE Missing required bundle org.eclipse.pde.build_0.0.0.\n!SUBENTRY 1 org.eclipse.osgi Apr 24, 2005 17:00:22.953\n!MESSAGE Missing required bundle org.eclipse.search_0.0.0.\n!SUBENTRY 1 org.eclipse.osgi Apr 24, 2005 17:00:22.953\n!MESSAGE Missing required bundle org.eclipse.team.core_0.0.0.\n!SUBENTRY 1 org.eclipse.osgi Apr 24, 2005 17:00:22.953\n!MESSAGE Missing required bundle org.eclipse.ui_0.0.0.\n!SUBENTRY 1 org.eclipse.osgi Apr 24, 2005 17:00:22.953\n!MESSAGE Missing required bundle org.eclipse.update.core_0.0.0.\n!SUBENTRY 1 org.eclipse.osgi Apr 24, 2005 17:00:22.953\n!MESSAGE Missing required bundle org.eclipse.ui.forms_0.0.0.\n!SUBENTRY 1 org.eclipse.osgi Apr 24, 2005 17:00:22.953\n!MESSAGE Missing required bundle org.eclipse.ant.ui_0.0.0.\n!SUBENTRY 1 org.eclipse.osgi Apr 24, 2005 17:00:22.953\n!MESSAGE Missing required bundle org.eclipse.jdt.junit_0.0.0.\n!SUBENTRY 1 org.eclipse.osgi Apr 24, 2005 17:00:22.953\n!MESSAGE Missing required bundle org.eclipse.ui.intro_0.0.0.\n!SUBENTRY 1 org.eclipse.osgi Apr 24, 2005 17:00:22.953\n!MESSAGE Missing required bundle org.eclipse.ui.cheatsheets_0.0.0.\n\n!ENTRY org.eclipse.osgi Apr 24, 2005 17:00:22.953\n!MESSAGE Bundle update@/c:/eclipse/plugins/org.eclipse.pde_3.0.1/ [106] was not\nresolved.\n!SUBENTRY 1 org.eclipse.osgi Apr 24, 2005 17:00:22.953\n!MESSAGE Missing required bundle org.eclipse.pde.core_0.0.0.\n!SUBENTRY 1 org.eclipse.osgi Apr 24, 2005 17:00:22.953\n!MESSAGE Missing required bundle org.eclipse.core.resources_0.0.0.\n!SUBENTRY 1 org.eclipse.osgi Apr 24, 2005 17:00:22.953\n!MESSAGE Missing required bundle org.eclipse.jdt.core_0.0.0.\n!SUBENTRY 1 org.eclipse.osgi Apr 24, 2005 17:00:22.953\n!MESSAGE Missing required bundle org.eclipse.text_0.0.0.\n!SUBENTRY 1 org.eclipse.osgi Apr 24, 2005 17:00:22.953\n!MESSAGE Missing optionally required bundle org.eclipse.ui.intro_0.0.0.\n!SUBENTRY 1 org.eclipse.osgi Apr 24, 2005 17:00:22.953\n!MESSAGE Missing optionally required bundle org.eclipse.ui.cheatsheets_0.0.0.\n\n!ENTRY org.eclipse.osgi Apr 24, 2005 17:00:22.953\n!MESSAGE Bundle update@/c:/eclipse/plugins/org.eclipse.platform.doc.isv_3.0.1/\n[107] was not resolved.\n!SUBENTRY 1 org.eclipse.osgi Apr 24, 2005 17:00:22.953\n!MESSAGE Missing required bundle org.eclipse.ui_0.0.0.\n\n!ENTRY org.eclipse.osgi Apr 24, 2005 17:00:22.953\n!MESSAGE Bundle update@/c:/eclipse/plugins/org.eclipse.sdk_3.0.2/ [110] was not\nresolved.\n!SUBENTRY 1 org.eclipse.osgi Apr 24, 2005 17:00:22.953\n!MESSAGE Missing required bundle org.eclipse.ui_0.0.0.",
    "this bug has been fixed in 3.0.2.\nTo recover, download the sdk zip, unzip it on top, and restart eclipse with -\nclean."
  ],
  "commentCreationDates": [
    "2005-04-24T12:13:09+02:00",
    "2005-04-24T21:53:14+02:00"
  ],
  "traces": [
    {
      "exceptionType": "java.lang.RuntimeException",
      "message": "No application id has been found.",
      "elements": [
        {
          "method": "org.eclipse.core.internal.runtime.PlatformActivator$1.run",
          "source": "PlatformActivator.java:313"
        },
        {
          "method": "org.eclipse.core.runtime.adaptor.EclipseStarter.run",
          "source": "EclipseStarter.java:273"
        },
        {
          "method": "org.eclipse.core.runtime.adaptor.EclipseStarter.run",
          "source": "EclipseStarter.java:129"
        },
        {
          "method": "sun.reflect.NativeMethodAccessorImpl.invoke0",
          "source": "Native Method"
        },
        {
          "method": "sun.reflect.NativeMethodAccessorImpl.invoke",
          "source": "Unknown Source"
        },
        {
          "method": "sun.reflect.DelegatingMethodAccessorImpl.invoke",
          "source": "Unknown Source"
        },
        {
          "method": "java.lang.reflect.Method.invoke",
          "source": "Unknown Source"
        },
        {
          "method": "org.eclipse.core.launcher.Main.basicRun",
          "source": "Main.java:183"
        },
        {
          "method": "org.eclipse.core.launcher.Main.run",
          "source": "Main.java:644"
        },
        {
          "method": "org.eclipse.core.launcher.Main.main",
          "source": "Main.java:628"
        }
      ],
      "number": 0,
      "commentIndex": 0,
      "bugId": "92510",
      "date": "2005-04-24T12:13:09+02:00",
      "product": "Platform",
      "component": "Update",
      "severity": "normal"
    }
  ],
  "groupId": "92510",
  "bugId": "92510",
  "date": "2005-04-24T12:13:09+02:00",
  "product": "Platform",
  "component": "Update",
  "severity": "normal"
}