{
  "comments": [
    "Tested in eclipse 3.1 M6\n\nIf a testcase override the getName() method, returning a meaningful name instead\nof the method name, the junit runner uses this name when trying to re-run the\ntest and fails.\n\nSteps to reproduce:\n- add the following testcase\n\npublic class NamedTest extends junit.framework.TestCase\n{\n    public void testSomething()\n    {\n    }\n    public String getName()\n    {\n        return \"A meaningful name, useful when the test is included in a suite.\";\n    }\n}\n\n\nRun the testcase with Run as -\u003e Junit test.\nNow the overridden method name is shown in junit hierarchy page: right click on\nthe method and select \"Run\": the test runner fails with the following exception:\n\njunit.framework.AssertionFailedError: Method \"A meaningful name, useful when the\ntest is included in a suite.\" not found\n\tat junit.framework.Assert.fail(Assert.java:47)\n\tat junit.framework.TestCase.runTest(TestCase.java:147)\n\tat junit.framework.TestCase.runBare(TestCase.java:127)\n\tat junit.framework.TestResult$1.protect(TestResult.java:106)\n\tat junit.framework.TestResult.runProtected(TestResult.java:124)\n\tat junit.framework.TestResult.run(TestResult.java:109)\n\tat junit.framework.TestCase.run(TestCase.java:118)\n\tat\norg.eclipse.jdt.internal.junit.runner.RemoteTestRunner.runTests(RemoteTestRunner.java:474)\n\tat\norg.eclipse.jdt.internal.junit.runner.RemoteTestRunner.run(RemoteTestRunner.java:342)\n\tat\norg.eclipse.jdt.internal.junit.runner.RemoteTestRunner.main(RemoteTestRunner.java:194)\n\n\nExpected behaviour: the junit runner should use the real method name when\nrerunning tests, and not the name returned by getName()",
    "Created an attachment (id\u003d20290)\nscreenshot\n",
    "This is a known issue that unfortunately cannot be fixed without support from\nthe JUnit framework. The workaround is to not override getName(). \n",
    "Marking as later then."
  ],
  "commentCreationDates": [
    "2005-04-25T10:57:50+02:00",
    "2005-04-25T11:00:18+02:00",
    "2005-04-25T18:09:17+02:00",
    "2005-04-26T00:47:16+02:00"
  ],
  "traces": [
    {
      "exceptionType": "junit.framework.AssertionFailedError",
      "message": "Method \"A meaningful name, useful when the test is included in a suite.\" not found",
      "elements": [
        {
          "method": "junit.framework.Assert.fail",
          "source": "Assert.java:47"
        },
        {
          "method": "junit.framework.TestCase.runTest",
          "source": "TestCase.java:147"
        },
        {
          "method": "junit.framework.TestCase.runBare",
          "source": "TestCase.java:127"
        },
        {
          "method": "junit.framework.TestResult$1.protect",
          "source": "TestResult.java:106"
        },
        {
          "method": "junit.framework.TestResult.runProtected",
          "source": "TestResult.java:124"
        },
        {
          "method": "junit.framework.TestResult.run",
          "source": "TestResult.java:109"
        },
        {
          "method": "junit.framework.TestCase.run",
          "source": "TestCase.java:118"
        },
        {
          "method": "org.eclipse.jdt.internal.junit.runner.RemoteTestRunner.runTests",
          "source": "RemoteTestRunner.java:474"
        },
        {
          "method": "org.eclipse.jdt.internal.junit.runner.RemoteTestRunner.run",
          "source": "RemoteTestRunner.java:342"
        },
        {
          "method": "org.eclipse.jdt.internal.junit.runner.RemoteTestRunner.main",
          "source": "RemoteTestRunner.java:194"
        }
      ],
      "number": 0,
      "commentIndex": 0,
      "bugId": "92557",
      "date": "2005-04-25T10:57:50+02:00",
      "product": "JDT",
      "component": "UI",
      "severity": "normal"
    }
  ],
  "groupId": "92557",
  "bugId": "92557",
  "date": "2005-04-25T10:57:50+02:00",
  "product": "JDT",
  "component": "UI",
  "severity": "normal"
}