{
  "comments": [
    "Per discussion with Richard. In some cases, the workbench will hang when \ncreating a new WSDL file. To reproduce:\n\n1. Start with a new workspace\n2. Create a Tomcat 5.0.2.8 targetted J2EE Web module. Use the same name for \nyour project and module (not sure whether this will make any difference).\n3. Make sure you switch to the J2EE perspective when prompted.\n4. Launch the new WSDL wizard to create a new WSDL file (default settings)\n5. Eclipse hangs...\n\nHere\u0027s the trace. Richard, I\u0027m opening this bug against the wst.wsdl component \nsince this is where the bug was found. Re-assign if neccessary, thanks.\n\n!ENTRY org.eclipse.wst.wsdl 2 0 2005-04-21 18:27:32.189\n!MESSAGE Document root element is missing.\n!STACK 0\norg.xml.sax.SAXParseException: Document root element is missing.\n        at org.apache.crimson.parser.Parser2.fatal(Unknown Source)\n        at org.apache.crimson.parser.Parser2.fatal(Unknown Source)\n        at org.apache.crimson.parser.Parser2.parseInternal(Unknown Source)\n        at org.apache.crimson.parser.Parser2.parse(Unknown Source)\n        at org.apache.crimson.parser.XMLReaderImpl.parse(Unknown Source)\n        at org.apache.crimson.jaxp.DocumentBuilderImpl.parse(Unknown Source)\n        at javax.xml.parsers.DocumentBuilder.parse(Unknown Source)\n        at org.eclipse.wst.wsdl.util.WSDLResourceImpl.getDocument\n(WSDLResourceIm\npl.java:263)\n        at org.eclipse.wst.wsdl.util.WSDLResourceImpl.doLoad\n(WSDLResourceImpl.ja\nva:183)\n        at org.eclipse.emf.ecore.resource.impl.ResourceImpl.load\n(ResourceImpl.ja\nva:977)\n        at org.eclipse.emf.ecore.resource.impl.ResourceImpl.load\n(ResourceImpl.ja\nva:832)\n        at org.eclipse.emf.ecore.resource.impl.ResourceSetImpl.demandLoad\n(Resour\nceSetImpl.java:249)\n        at \norg.eclipse.jem.internal.util.emf.workbench.ProjectResourceSetImpl.de\nmandLoad(ProjectResourceSetImpl.java:83)\n        at org.eclipse.emf.ecore.resource.impl.ResourceSetImpl.demandLoadHelper\n(\nResourceSetImpl.java:264)\n        at org.eclipse.emf.ecore.resource.impl.ResourceSetImpl.getResource\n(Resou\nrceSetImpl.java:349)\n        at \norg.eclipse.jem.internal.util.emf.workbench.ProjectResourceSetImpl.ge\ntResource(ProjectResourceSetImpl.java:262)\n        at \norg.eclipse.jem.util.emf.workbench.WorkbenchResourceHelperBase.getRes\nource(WorkbenchResourceHelperBase.java:446)\n        at \norg.eclipse.jem.util.emf.workbench.WorkbenchResourceHelperBase.getRes\nource(WorkbenchResourceHelperBase.java:418)\n        at \norg.eclipse.jst.j2ee.internal.webservices.WebServicesManager.addedWsd\nl(WebServicesManager.java:804)\n        at org.eclipse.jst.j2ee.internal.webservices.WebServicesManager.visit\n(We\nbServicesManager.java:793)\n        at org.eclipse.core.internal.events.ResourceDelta.accept\n(ResourceDelta.j\nava:68)\n        at org.eclipse.core.internal.events.ResourceDelta.accept\n(ResourceDelta.j\nava:77)\n        at org.eclipse.core.internal.events.ResourceDelta.accept\n(ResourceDelta.j\nava:77)",
    "I would change this bug\u0027s priority to 2 (but bugzilla wouldn\u0027t allow me) given \nthat user has no way out beside killing the workbench. However, I wouldn\u0027t \nconsider this a blocker just yet because there\u0027s an easy workaround, which is \nto avoid the J2EE perspective before creating the WSDL file.",
    "We\u0027re seeing a problem when we attempt to import a wsil or wsdl file in the \nJ2EE perspective.\nIt appears we\u0027re hitting an infinite loop in CommonWorkingSetViewer.java in \nmethod remove(Object[] elements).  Line 192\n\nWe\u0027re also hitting this infinite loop when finishing the New WSDL Wizard.\n\nI\u0027m using the I20050419 and I20050421 Integration driver.\n",
    "The defect was fixed on 04/25 round 5:00 pm yesterday. I verified on the\nyesterday\u0027s 04/24  nightly build.\n",
    "Verified with I20040624",
    "Closing already verified defects"
  ],
  "commentCreationDates": [
    "2005-04-26T00:16:53+02:00",
    "2005-04-26T00:20:21+02:00",
    "2005-04-26T17:26:26+02:00",
    "2005-04-26T19:45:10+02:00",
    "2005-06-27T21:22:17+02:00",
    "2005-07-26T20:03:14+02:00"
  ],
  "traces": [
    {
      "exceptionType": "org.xml.sax.SAXParseException",
      "message": "Document root element is missing.",
      "elements": [
        {
          "method": "org.apache.crimson.parser.Parser2.fatal",
          "source": "Unknown Source"
        },
        {
          "method": "org.apache.crimson.parser.Parser2.fatal",
          "source": "Unknown Source"
        },
        {
          "method": "org.apache.crimson.parser.Parser2.parseInternal",
          "source": "Unknown Source"
        },
        {
          "method": "org.apache.crimson.parser.Parser2.parse",
          "source": "Unknown Source"
        },
        {
          "method": "org.apache.crimson.parser.XMLReaderImpl.parse",
          "source": "Unknown Source"
        },
        {
          "method": "org.apache.crimson.jaxp.DocumentBuilderImpl.parse",
          "source": "Unknown Source"
        },
        {
          "method": "javax.xml.parsers.DocumentBuilder.parse",
          "source": "Unknown Source"
        },
        {
          "method": "org.eclipse.wst.wsdl.util.WSDLResourceImpl.getDocument",
          "source": "WSDLResourceIm pl.java:263"
        },
        {
          "method": "org.eclipse.wst.wsdl.util.WSDLResourceImpl.doLoad",
          "source": "WSDLResourceImpl.ja va:183"
        },
        {
          "method": "org.eclipse.emf.ecore.resource.impl.ResourceImpl.load",
          "source": "ResourceImpl.ja va:977"
        },
        {
          "method": "org.eclipse.emf.ecore.resource.impl.ResourceImpl.load",
          "source": "ResourceImpl.ja va:832"
        },
        {
          "method": "org.eclipse.emf.ecore.resource.impl.ResourceSetImpl.demandLoad",
          "source": "Resour ceSetImpl.java:249"
        },
        {
          "method": "org.eclipse.jem.internal.util.emf.workbench.ProjectResourceSetImpl.demandLoad",
          "source": "ProjectResourceSetImpl.java:83"
        },
        {
          "method": "org.eclipse.emf.ecore.resource.impl.ResourceSetImpl.demandLoadHelper",
          "source": " ResourceSetImpl.java:264"
        },
        {
          "method": "org.eclipse.emf.ecore.resource.impl.ResourceSetImpl.getResource",
          "source": "Resou rceSetImpl.java:349"
        },
        {
          "method": "org.eclipse.jem.internal.util.emf.workbench.ProjectResourceSetImpl.getResource",
          "source": "ProjectResourceSetImpl.java:262"
        },
        {
          "method": "org.eclipse.jem.util.emf.workbench.WorkbenchResourceHelperBase.getResource",
          "source": "WorkbenchResourceHelperBase.java:446"
        },
        {
          "method": "org.eclipse.jem.util.emf.workbench.WorkbenchResourceHelperBase.getResource",
          "source": "WorkbenchResourceHelperBase.java:418"
        },
        {
          "method": "org.eclipse.jst.j2ee.internal.webservices.WebServicesManager.addedWsdl",
          "source": "WebServicesManager.java:804"
        },
        {
          "method": "org.eclipse.jst.j2ee.internal.webservices.WebServicesManager.visit",
          "source": "We bServicesManager.java:793"
        },
        {
          "method": "org.eclipse.core.internal.events.ResourceDelta.accept",
          "source": "ResourceDelta.j ava:68"
        },
        {
          "method": "org.eclipse.core.internal.events.ResourceDelta.accept",
          "source": "ResourceDelta.j ava:77"
        },
        {
          "method": "org.eclipse.core.internal.events.ResourceDelta.accept",
          "source": "ResourceDelta.j ava:77"
        }
      ],
      "number": 0,
      "commentIndex": 0,
      "bugId": "92665",
      "date": "2005-04-26T00:16:53+02:00",
      "product": "Web Tools",
      "component": "wst.wsdl",
      "severity": "major"
    }
  ],
  "groupId": "92665",
  "bugId": "92665",
  "date": "2005-04-26T00:16:53+02:00",
  "product": "Web Tools",
  "component": "wst.wsdl",
  "severity": "major"
}