{
  "comments": [
    "When deploying the birt viewer - by copying the birt-viewer directory to the \ntomcat webapps directory - you get the following stack trace dump when \nrestarting tomcat:\n\nApr 27, 2005 10:43:06 AM org.apache.commons.digester.Digester error\nSEVERE: Parse Error at line 296 column 11: The content of element type \n\n\"web-app\"\n must match \n\n\"(icon?,display-name?,description?,distributable?,context-param*,ser\nvlet*,servlet-mapping*,session-config?,mime-mapping*,welcome-file-list?\n\n,error-pa\nge*,taglib*,resource-ref*,security-constraint*,login-config?,security-r\n\nole*,env-\nentry*,ejb-ref*)\".\norg.xml.sax.SAXParseException: The content of element type \"web-app\" \n\nmust match\n\"(icon?,display-name?,description?,distributable?,context-param*,servle\n\nt*,servle\nt-mapping*,session-config?,mime-mapping*,welcome-file-list?,error-page*\n\n,taglib*,\nresource-ref*,security-constraint*,login-config?,security-role*,env-ent\n\nry*,ejb-r\nef*)\".\n        at \n\norg.apache.xerces.util.ErrorHandlerWrapper.createSAXParseException(Un\nknown Source)\n        at org.apache.xerces.util.ErrorHandlerWrapper.error(Unknown \n\nSource)\n        at org.apache.xerces.impl.XMLErrorReporter.reportError(Unknown \n\nSource)\n        at org.apache.xerces.impl.XMLErrorReporter.reportError(Unknown \n\nSource)\n        at \n\norg.apache.xerces.impl.dtd.XMLDTDValidator.handleEndElement(Unknown S\nource)\n        at \n\norg.apache.xerces.impl.dtd.XMLDTDValidator.endElement(Unknown Source)\n        at \n\norg.apache.xerces.impl.XMLDocumentFragmentScannerImpl.scanEndElement(\nUnknown Source)\n        at \n\norg.apache.xerces.impl.XMLDocumentFragmentScannerImpl$FragmentContent\nDispatcher.dispatch(Unknown Source)\n        at \n\norg.apache.xerces.impl.XMLDocumentFragmentScannerImpl.scanDocument(Un\nknown Source)\n        at org.apache.xerces.parsers.XML11Configuration.parse(Unknown \n\nSource)\n        at org.apache.xerces.parsers.DTDConfiguration.parse(Unknown \n\nSource)\n        at org.apache.xerces.parsers.XMLParser.parse(Unknown Source)\n        at org.apache.xerces.parsers.AbstractSAXParser.parse(Unknown \n\nSource)\n        at \n\norg.apache.commons.digester.Digester.parse(Digester.java:1548)\n        at \n\norg.apache.catalina.startup.ContextConfig.applicationConfig(ContextCo\nnfig.java:282)\n        at \n\norg.apache.catalina.startup.ContextConfig.start(ContextConfig.java:63\n9)\n        at \n\norg.apache.catalina.startup.ContextConfig.lifecycleEvent(ContextConfi\ng.java:243)\n        at \n\norg.apache.catalina.util.LifecycleSupport.fireLifecycleEvent(Lifecycl\neSupport.java:166)\n        at \n\norg.apache.catalina.core.StandardContext.start(StandardContext.java:3\n568)\n        at \n\norg.apache.catalina.core.ContainerBase.addChildInternal(ContainerBase\n.java:821)\n        at \n\norg.apache.catalina.core.ContainerBase.addChild(ContainerBase.java:807)\n        at \n\norg.apache.catalina.core.StandardHost.addChild(StandardHost.java:579)\n\n        at \n\norg.apache.catalina.core.StandardHostDeployer.install(StandardHostDep\nloyer.java:307)\n        at \n\norg.apache.catalina.core.StandardHost.install(StandardHost.java:772)\n        at \n\norg.apache.catalina.startup.HostConfig.deployDirectories(HostConfig.j\nava:559)\n        at \n\norg.apache.catalina.startup.HostConfig.deployApps(HostConfig.java:401\n)\n        at \n\norg.apache.catalina.startup.HostConfig.start(HostConfig.java:718)\n        at \n\norg.apache.catalina.startup.HostConfig.lifecycleEvent(HostConfig.java\n:358)\n        at \n\norg.apache.catalina.util.LifecycleSupport.fireLifecycleEvent(Lifecycl\neSupport.java:166)\n        at \n\norg.apache.catalina.core.ContainerBase.start(ContainerBase.java:1196)\n\n        at \n\norg.apache.catalina.core.StandardHost.start(StandardHost.java:738)\n        at \n\norg.apache.catalina.core.ContainerBase.start(ContainerBase.java:1188)\n\n        at \n\norg.apache.catalina.core.StandardEngine.start(StandardEngine.java:347\n)\n        at \n\norg.apache.catalina.core.StandardService.start(StandardService.java:4\n97)\n        at \n\norg.apache.catalina.core.StandardServer.start(StandardServer.java:219\n0)\n        at \n\norg.apache.catalina.startup.Catalina.start(Catalina.java:512)\n        at \n\norg.apache.catalina.startup.Catalina.execute(Catalina.java:400)\n        at \n\norg.apache.catalina.startup.Catalina.process(Catalina.java:180)\n        at sun.reflect.NativeMethodAccessorImpl.invoke0(Native Method)\n        at \n\nsun.reflect.NativeMethodAccessorImpl.invoke(NativeMethodAccessorImpl.\njava:39)\n        at \n\nsun.reflect.DelegatingMethodAccessorImpl.invoke(DelegatingMethodAcces\nsorImpl.java:25)\n        at java.lang.reflect.Method.invoke(Method.java:324)\n        at \n\norg.apache.catalina.startup.Bootstrap.main(Bootstrap.java:203)\nApr 27, 2005 10:43:06 AM org.apache.coyote.http11.Http11Protocol start\nINFO: Starting Coyote HTTP/1.1 on port 8080\nApr 27, 2005 10:43:06 AM org.apache.jk.common.ChannelSocket init\nINFO: JK2: ajp13 listening on /0.0.0.0:8009\nApr 27, 2005 10:43:06 AM org.apache.jk.server.JkMain start\nINFO: Jk running ID\u003d0 time\u003d0/63  \n\nconfig\u003dc:\\jakarta-tomcat-4.1.27\\conf\\jk2.proper\nties\nApr 27, 2005 10:43:22 AM \n\norg.apache.struts.util.PropertyMessageResources \u003cinit\u003e\nINFO: Initializing, \n\nconfig\u003d\u0027org.apache.struts.taglib.html.LocalStrings\u0027, returnN\null\u003dtrue\nApr 27, 2005 10:43:22 AM \n\norg.apache.struts.util.PropertyMessageResources \u003cinit\u003e\nINFO: Initializing, config\u003d\u0027org.apache.struts.util.LocalStrings\u0027, \n\nreturnNull\u003dtru\ne\nApr 27, 2005 10:43:22 AM \n\norg.apache.struts.util.PropertyMessageResources \u003cinit\u003e\nINFO: Initializing, \n\nconfig\u003d\u0027org.apache.struts.taglib.bean.LocalStrings\u0027, returnN\null\u003dtrue\nApr 27, 2005 10:43:22 AM \n\norg.apache.struts.util.PropertyMessageResources \u003cinit\u003e\nINFO: Initializing, \n\nconfig\u003d\u0027org.apache.struts.taglib.html.LocalStrings\u0027, returnN\null\u003dtrue\nApr 27, 2005 10:43:25 AM \n\norg.apache.struts.util.PropertyMessageResources \u003cinit\u003e\nINFO: Initializing, \n\nconfig\u003d\u0027org.apache.struts.taglib.html.LocalStrings\u0027, returnN\null\u003dtrue\nApr 27, 2005 10:43:25 AM \n\norg.apache.struts.util.PropertyMessageResources \u003cinit\u003e\nINFO: Initializing, \n\nconfig\u003d\u0027org.apache.struts.taglib.html.LocalStrings\u0027, returnN\null\u003dtrue",
    "This is caused by generated web.xml containing multiple server definition and\nmappings. Their orders are mixed.\n\nThis is obselete in the latest release since we remove the jsp pre-compile,\nwhich generated web.xml dynamically.",
    "Verified in build 20051222"
  ],
  "commentCreationDates": [
    "2005-04-27T18:18:58+02:00",
    "2005-05-14T01:47:00+02:00",
    "2005-12-22T08:57:37+01:00"
  ],
  "traces": [
    {
      "exceptionType": "org.xml.sax.SAXParseException",
      "message": "The content of element type \"web-app\"   must match \"(icon?,display-name?,description?,distributable?,context-param*,servle  t*,servle t-mapping*,session-config?,mime-mapping*,welcome-file-list?,error-page*  ,taglib*, resource-ref*,security-constraint*,login-config?,security-role*,env-ent  ry*,ejb-r ef*)\".",
      "elements": [
        {
          "method": "org.apache.xerces.util.ErrorHandlerWrapper.createSAXParseException",
          "source": "Un known Source"
        },
        {
          "method": "org.apache.xerces.util.ErrorHandlerWrapper.error",
          "source": "Unknown   Source"
        },
        {
          "method": "org.apache.xerces.impl.XMLErrorReporter.reportError",
          "source": "Unknown   Source"
        },
        {
          "method": "org.apache.xerces.impl.XMLErrorReporter.reportError",
          "source": "Unknown   Source"
        },
        {
          "method": "org.apache.xerces.impl.dtd.XMLDTDValidator.handleEndElement",
          "source": "Unknown S ource"
        },
        {
          "method": "org.apache.xerces.impl.dtd.XMLDTDValidator.endElement",
          "source": "Unknown Source"
        },
        {
          "method": "org.apache.xerces.impl.XMLDocumentFragmentScannerImpl.scanEndElement",
          "source": " Unknown Source"
        },
        {
          "method": "org.apache.xerces.impl.XMLDocumentFragmentScannerImpl$FragmentContentDispatcher.dispatch",
          "source": "Unknown Source"
        },
        {
          "method": "org.apache.xerces.impl.XMLDocumentFragmentScannerImpl.scanDocument",
          "source": "Un known Source"
        },
        {
          "method": "org.apache.xerces.parsers.XML11Configuration.parse",
          "source": "Unknown   Source"
        },
        {
          "method": "org.apache.xerces.parsers.DTDConfiguration.parse",
          "source": "Unknown   Source"
        },
        {
          "method": "org.apache.xerces.parsers.XMLParser.parse",
          "source": "Unknown Source"
        },
        {
          "method": "org.apache.xerces.parsers.AbstractSAXParser.parse",
          "source": "Unknown   Source"
        },
        {
          "method": "org.apache.commons.digester.Digester.parse",
          "source": "Digester.java:1548"
        },
        {
          "method": "org.apache.catalina.startup.ContextConfig.applicationConfig",
          "source": "ContextCo nfig.java:282"
        },
        {
          "method": "org.apache.catalina.startup.ContextConfig.start",
          "source": "ContextConfig.java:63 9"
        },
        {
          "method": "org.apache.catalina.startup.ContextConfig.lifecycleEvent",
          "source": "ContextConfi g.java:243"
        },
        {
          "method": "org.apache.catalina.util.LifecycleSupport.fireLifecycleEvent",
          "source": "Lifecycl eSupport.java:166"
        },
        {
          "method": "org.apache.catalina.core.StandardContext.start",
          "source": "StandardContext.java:3 568"
        },
        {
          "method": "org.apache.catalina.core.ContainerBase.addChildInternal",
          "source": "ContainerBase .java:821"
        },
        {
          "method": "org.apache.catalina.core.ContainerBase.addChild",
          "source": "ContainerBase.java:807"
        },
        {
          "method": "org.apache.catalina.core.StandardHost.addChild",
          "source": "StandardHost.java:579"
        },
        {
          "method": "org.apache.catalina.core.StandardHostDeployer.install",
          "source": "StandardHostDep loyer.java:307"
        },
        {
          "method": "org.apache.catalina.core.StandardHost.install",
          "source": "StandardHost.java:772"
        },
        {
          "method": "org.apache.catalina.startup.HostConfig.deployDirectories",
          "source": "HostConfig.j ava:559"
        },
        {
          "method": "org.apache.catalina.startup.HostConfig.deployApps",
          "source": "HostConfig.java:401 "
        },
        {
          "method": "org.apache.catalina.startup.HostConfig.start",
          "source": "HostConfig.java:718"
        },
        {
          "method": "org.apache.catalina.startup.HostConfig.lifecycleEvent",
          "source": "HostConfig.java :358"
        },
        {
          "method": "org.apache.catalina.util.LifecycleSupport.fireLifecycleEvent",
          "source": "Lifecycl eSupport.java:166"
        },
        {
          "method": "org.apache.catalina.core.ContainerBase.start",
          "source": "ContainerBase.java:1196"
        },
        {
          "method": "org.apache.catalina.core.StandardHost.start",
          "source": "StandardHost.java:738"
        },
        {
          "method": "org.apache.catalina.core.ContainerBase.start",
          "source": "ContainerBase.java:1188"
        },
        {
          "method": "org.apache.catalina.core.StandardEngine.start",
          "source": "StandardEngine.java:347 "
        },
        {
          "method": "org.apache.catalina.core.StandardService.start",
          "source": "StandardService.java:4 97"
        },
        {
          "method": "org.apache.catalina.core.StandardServer.start",
          "source": "StandardServer.java:219 0"
        },
        {
          "method": "org.apache.catalina.startup.Catalina.start",
          "source": "Catalina.java:512"
        },
        {
          "method": "org.apache.catalina.startup.Catalina.execute",
          "source": "Catalina.java:400"
        },
        {
          "method": "org.apache.catalina.startup.Catalina.process",
          "source": "Catalina.java:180"
        },
        {
          "method": "sun.reflect.NativeMethodAccessorImpl.invoke0",
          "source": "Native Method"
        },
        {
          "method": "sun.reflect.NativeMethodAccessorImpl.invoke",
          "source": "NativeMethodAccessorImpl. java:39"
        },
        {
          "method": "sun.reflect.DelegatingMethodAccessorImpl.invoke",
          "source": "DelegatingMethodAcces sorImpl.java:25"
        },
        {
          "method": "java.lang.reflect.Method.invoke",
          "source": "Method.java:324"
        },
        {
          "method": "org.apache.catalina.startup.Bootstrap.main",
          "source": "Bootstrap.java:203"
        }
      ],
      "number": 0,
      "commentIndex": 0,
      "bugId": "92941",
      "date": "2005-04-27T18:18:58+02:00",
      "product": "BIRT",
      "component": "Report",
      "severity": "normal"
    }
  ],
  "groupId": "92941",
  "bugId": "92941",
  "date": "2005-04-27T18:18:58+02:00",
  "product": "BIRT",
  "component": "Report",
  "severity": "normal"
}