{
  "comments": [
    "!SESSION 2005-04-28 11:25:42.906 ----------------------------------------------\n-\neclipse.buildId\u003dI20041216-2000\njava.version\u003d1.5.0_02\njava.vendor\u003dSun Microsystems Inc.\nBootLoader constants: OS\u003dwin32, ARCH\u003dx86, WS\u003dwin32, NL\u003dru_RU\nCommand-line arguments:  -os win32 -ws win32 -arch x86 -data \n\\\\darksite\\mike\\eclipse\n\n!ENTRY org.eclipse.osgi 2005-04-28 11:25:42.906\n!MESSAGE An error occured while automatically activating bundle \norg.eclipse.core.resources (15).\n!STACK 0\norg.osgi.framework.BundleException: Exception in \norg.eclipse.core.internal.compatibility.PluginActivator.start() of bundle \norg.eclipse.core.resources.\n        at \norg.eclipse.osgi.framework.internal.core.BundleContextImpl.startActivator\n(BundleContextImpl.java:975)\n        at org.eclipse.osgi.framework.internal.core.BundleContextImpl.start\n(BundleContextImpl.java:937)\n        at org.eclipse.osgi.framework.internal.core.BundleHost.startWorker\n(BundleHost.java:417)\n        at org.eclipse.osgi.framework.internal.core.AbstractBundle.start\n(AbstractBundle.java:293)\n        at org.eclipse.core.runtime.adaptor.EclipseClassLoader.findLocalClass\n(EclipseClassLoader.java:110)\n        at org.eclipse.osgi.framework.internal.core.BundleLoader.findLocalClass\n(BundleLoader.java:371)\n        at org.eclipse.osgi.framework.internal.core.BundleLoader.requireClass\n(BundleLoader.java:336)\n        at \norg.eclipse.osgi.framework.internal.core.BundleLoader.findRequiredClass\n(BundleLoader.java:914)\n        at org.eclipse.osgi.framework.internal.core.BundleLoader.findClass\n(BundleLoader.java:399)\n        at \norg.eclipse.osgi.framework.adaptor.core.AbstractClassLoader.loadClass\n(AbstractClassLoader.java:93)\n        at java.lang.ClassLoader.loadClass(Unknown Source)\n        at java.lang.ClassLoader.loadClassInternal(Unknown Source)\n        at org.eclipse.ui.internal.ide.model.WorkbenchAdapterFactory.\u003cinit\u003e\n(WorkbenchAdapterFactory.java:33)\n        at \norg.eclipse.ui.internal.ide.model.WorkbenchAdapterBuilder.registerAdapters\n(WorkbenchAdapterBuilder.java:33)\n        at org.eclipse.ui.internal.ide.IDEWorkbenchAdvisor.initialize\n(IDEWorkbenchAdvisor.java:173)\n        at org.eclipse.ui.application.WorkbenchAdvisor.internalBasicInitialize\n(WorkbenchAdvisor.java:167)\n        at org.eclipse.ui.internal.Workbench.init(Workbench.java:852)\n        at org.eclipse.ui.internal.Workbench.runUI(Workbench.java:1516)\n        at org.eclipse.ui.internal.Workbench.createAndRunWorkbench\n(Workbench.java:285)\n        at org.eclipse.ui.PlatformUI.createAndRunWorkbench(PlatformUI.java:144)\n        at org.eclipse.ui.internal.ide.IDEApplication.run\n(IDEApplication.java:102)\n        at org.eclipse.core.internal.runtime.PlatformActivator$1.run\n(PlatformActivator.java:220)\n        at org.eclipse.core.runtime.adaptor.EclipseStarter.run\n(EclipseStarter.java:273)\n        at org.eclipse.core.runtime.adaptor.EclipseStarter.run\n(EclipseStarter.java:129)\n        at sun.reflect.NativeMethodAccessorImpl.invoke0(Native Method)\n        at sun.reflect.NativeMethodAccessorImpl.invoke(Unknown Source)\n        at sun.reflect.DelegatingMethodAccessorImpl.invoke(Unknown Source)\n        at java.lang.reflect.Method.invoke(Unknown Source)\n        at org.eclipse.core.launcher.Main.basicRun(Main.java:185)\n        at org.eclipse.core.launcher.Main.run(Main.java:710)\n        at org.eclipse.core.launcher.Main.main(Main.java:694)\nCaused by: java.lang.IndexOutOfBoundsException: Index: 458761, Size: 5\n        at java.util.ArrayList.RangeCheck(Unknown Source)\n        at java.util.ArrayList.get(Unknown Source)\n        at org.eclipse.core.internal.resources.MarkerReader_3.readMarkerInfo\n(MarkerReader_3.java:134)\n        at org.eclipse.core.internal.resources.MarkerReader_3.read\n(MarkerReader_3.java:69)\n        at org.eclipse.core.internal.resources.MarkerReader.read\n(MarkerReader.java:49)\n        at org.eclipse.core.internal.resources.MarkerManager.restoreFromSave\n(MarkerManager.java:449)\n        at org.eclipse.core.internal.resources.MarkerManager.restore\n(MarkerManager.java:434)\n        at org.eclipse.core.internal.resources.SaveManager.restoreMarkers\n(SaveManager.java:633)\n        at org.eclipse.core.internal.resources.SaveManager.restore\n(SaveManager.java:558)\n        at org.eclipse.core.internal.resources.SaveManager.startup\n(SaveManager.java:1241)\n        at org.eclipse.core.internal.resources.Workspace.startup\n(Workspace.java:1822)\n        at org.eclipse.core.internal.resources.Workspace.open\n(Workspace.java:1601)\n        at org.eclipse.core.resources.ResourcesPlugin.startup\n(ResourcesPlugin.java:357)\n        at org.eclipse.core.internal.compatibility.PluginActivator.start\n(PluginActivator.java:56)\n        at org.eclipse.osgi.framework.internal.core.BundleContextImpl$1.run\n(BundleContextImpl.java:958)\n        at java.security.AccessController.doPrivileged(Native Method)\n        at \norg.eclipse.osgi.framework.internal.core.BundleContextImpl.startActivator\n(BundleContextImpl.java:954)\n        ... 30 more\nRoot exception:\njava.lang.IndexOutOfBoundsException: Index: 458761, Size: 5\n        at java.util.ArrayList.RangeCheck(Unknown Source)\n        at java.util.ArrayList.get(Unknown Source)\n        at org.eclipse.core.internal.resources.MarkerReader_3.readMarkerInfo\n(MarkerReader_3.java:134)\n        at org.eclipse.core.internal.resources.MarkerReader_3.read\n(MarkerReader_3.java:69)\n        at org.eclipse.core.internal.resources.MarkerReader.read\n(MarkerReader.java:49)\n        at org.eclipse.core.internal.resources.MarkerManager.restoreFromSave\n(MarkerManager.java:449)\n        at org.eclipse.core.internal.resources.MarkerManager.restore\n(MarkerManager.java:434)\n        at org.eclipse.core.internal.resources.SaveManager.restoreMarkers\n(SaveManager.java:633)\n        at org.eclipse.core.internal.resources.SaveManager.restore\n(SaveManager.java:558)\n        at org.eclipse.core.internal.resources.SaveManager.startup\n(SaveManager.java:1241)\n        at org.eclipse.core.internal.resources.Workspace.startup\n(Workspace.java:1822)\n        at org.eclipse.core.internal.resources.Workspace.open\n(Workspace.java:1601)\n        at org.eclipse.core.resources.ResourcesPlugin.startup\n(ResourcesPlugin.java:357)\n        at org.eclipse.core.internal.compatibility.PluginActivator.start\n(PluginActivator.java:56)\n        at org.eclipse.osgi.framework.internal.core.BundleContextImpl$1.run\n(BundleContextImpl.java:958)\n        at java.security.AccessController.doPrivileged(Native Method)\n        at \norg.eclipse.osgi.framework.internal.core.BundleContextImpl.startActivator\n(BundleContextImpl.java:954)\n        at org.eclipse.osgi.framework.internal.core.BundleContextImpl.start\n(BundleContextImpl.java:937)\n        at org.eclipse.osgi.framework.internal.core.BundleHost.startWorker\n(BundleHost.java:417)\n        at org.eclipse.osgi.framework.internal.core.AbstractBundle.start\n(AbstractBundle.java:293)\n        at org.eclipse.core.runtime.adaptor.EclipseClassLoader.findLocalClass\n(EclipseClassLoader.java:110)\n        at org.eclipse.osgi.framework.internal.core.BundleLoader.findLocalClass\n(BundleLoader.java:371)\n        at org.eclipse.osgi.framework.internal.core.BundleLoader.requireClass\n(BundleLoader.java:336)\n        at \norg.eclipse.osgi.framework.internal.core.BundleLoader.findRequiredClass\n(BundleLoader.java:914)\n        at org.eclipse.osgi.framework.internal.core.BundleLoader.findClass\n(BundleLoader.java:399)\n        at \norg.eclipse.osgi.framework.adaptor.core.AbstractClassLoader.loadClass\n(AbstractClassLoader.java:93)\n        at java.lang.ClassLoader.loadClass(Unknown Source)\n        at java.lang.ClassLoader.loadClassInternal(Unknown Source)\n        at org.eclipse.ui.internal.ide.model.WorkbenchAdapterFactory.\u003cinit\u003e\n(WorkbenchAdapterFactory.java:33)\n        at \norg.eclipse.ui.internal.ide.model.WorkbenchAdapterBuilder.registerAdapters\n(WorkbenchAdapterBuilder.java:33)\n        at org.eclipse.ui.internal.ide.IDEWorkbenchAdvisor.initialize\n(IDEWorkbenchAdvisor.java:173)\n        at org.eclipse.ui.application.WorkbenchAdvisor.internalBasicInitialize\n(WorkbenchAdvisor.java:167)\n        at org.eclipse.ui.internal.Workbench.init(Workbench.java:852)\n        at org.eclipse.ui.internal.Workbench.runUI(Workbench.java:1516)\n        at org.eclipse.ui.internal.Workbench.createAndRunWorkbench\n(Workbench.java:285)\n        at org.eclipse.ui.PlatformUI.createAndRunWorkbench(PlatformUI.java:144)\n        at org.eclipse.ui.internal.ide.IDEApplication.run\n(IDEApplication.java:102)\n        at org.eclipse.core.internal.runtime.PlatformActivator$1.run\n(PlatformActivator.java:220)\n        at org.eclipse.core.runtime.adaptor.EclipseStarter.run\n(EclipseStarter.java:273)\n        at org.eclipse.core.runtime.adaptor.EclipseStarter.run\n(EclipseStarter.java:129)\n        at sun.reflect.NativeMethodAccessorImpl.invoke0(Native Method)\n        at sun.reflect.NativeMethodAccessorImpl.invoke(Unknown Source)\n        at sun.reflect.DelegatingMethodAccessorImpl.invoke(Unknown Source)\n        at java.lang.reflect.Method.invoke(Unknown Source)\n        at org.eclipse.core.launcher.Main.basicRun(Main.java:185)\n        at org.eclipse.core.launcher.Main.run(Main.java:710)\n        at org.eclipse.core.launcher.Main.main(Main.java:694)\n\n!ENTRY org.eclipse.osgi 2005-04-28 11:25:42.984\n!MESSAGE Application error\n!STACK 1\njava.lang.NoClassDefFoundError: org/eclipse/core/resources/IProject\n        at org.eclipse.ui.internal.ide.model.WorkbenchAdapterFactory.\u003cinit\u003e\n(WorkbenchAdapterFactory.java:33)\n        at \norg.eclipse.ui.internal.ide.model.WorkbenchAdapterBuilder.registerAdapters\n(WorkbenchAdapterBuilder.java:33)\n        at org.eclipse.ui.internal.ide.IDEWorkbenchAdvisor.initialize\n(IDEWorkbenchAdvisor.java:173)\n        at org.eclipse.ui.application.WorkbenchAdvisor.internalBasicInitialize\n(WorkbenchAdvisor.java:167)\n        at org.eclipse.ui.internal.Workbench.init(Workbench.java:852)\n        at org.eclipse.ui.internal.Workbench.runUI(Workbench.java:1516)\n        at org.eclipse.ui.internal.Workbench.createAndRunWorkbench\n(Workbench.java:285)\n        at org.eclipse.ui.PlatformUI.createAndRunWorkbench(PlatformUI.java:144)\n        at org.eclipse.ui.internal.ide.IDEApplication.run\n(IDEApplication.java:102)\n        at org.eclipse.core.internal.runtime.PlatformActivator$1.run\n(PlatformActivator.java:220)\n        at org.eclipse.core.runtime.adaptor.EclipseStarter.run\n(EclipseStarter.java:273)\n        at org.eclipse.core.runtime.adaptor.EclipseStarter.run\n(EclipseStarter.java:129)\n        at sun.reflect.NativeMethodAccessorImpl.invoke0(Native Method)\n        at sun.reflect.NativeMethodAccessorImpl.invoke(Unknown Source)\n        at sun.reflect.DelegatingMethodAccessorImpl.invoke(Unknown Source)\n        at java.lang.reflect.Method.invoke(Unknown Source)\n        at org.eclipse.core.launcher.Main.basicRun(Main.java:185)\n        at org.eclipse.core.launcher.Main.run(Main.java:710)\n        at org.eclipse.core.launcher.Main.main(Main.java:694)",
    "One of your metadata files was corrupt.  If you look in your log from the\nsession before the crash, it might yield some clues about what caused the failure.\n\nIn any case, corruption of this metadata file, whether caused by an Eclipse\nproblem or a local file system problem, should not prevent Eclipse from\nstarting. I will fix the startup code to catch this exception and recover more\ngracefully.",
    "Fix released.  Note that there is not enough information here to figure out how\nthe workspace metadata became corrupt.  If you find more information in the log\nfrom the session before the crash that might point at the cause of failure,\nplease attach the log file here (use the \"Create a New Attachment\" link above).\n\nThe fix I have released makes sure we are still able to start the platform when\nthe marker file is corrupt.  The error will be written to the log and existing\nmarkers (problems, breakpoints, bookmarks, etc), will be lost.",
    "File corruption occures while \"out of space\" on my HDD. I suppose that it was\nnot problem witn Eclipse. But I nevertheless send my .log file. Me be it will be\nuseful.",
    "Created an attachment (id\u003d20654)\nLog file of Eclipse with broken file structure\n"
  ],
  "commentCreationDates": [
    "2005-04-28T09:38:36+02:00",
    "2005-05-02T17:21:56+02:00",
    "2005-05-02T20:36:20+02:00",
    "2005-05-03T22:48:46+02:00",
    "2005-05-03T22:51:40+02:00"
  ],
  "traces": [
    {
      "exceptionType": "org.osgi.framework.BundleException",
      "message": "Exception in  org.eclipse.core.internal.compatibility.PluginActivator.start() of bundle  org.eclipse.core.resources.",
      "elements": [
        {
          "method": "org.eclipse.osgi.framework.internal.core.BundleContextImpl.startActivator",
          "source": "BundleContextImpl.java:975"
        },
        {
          "method": "org.eclipse.osgi.framework.internal.core.BundleContextImpl.start",
          "source": "BundleContextImpl.java:937"
        },
        {
          "method": "org.eclipse.osgi.framework.internal.core.BundleHost.startWorker",
          "source": "BundleHost.java:417"
        },
        {
          "method": "org.eclipse.osgi.framework.internal.core.AbstractBundle.start",
          "source": "AbstractBundle.java:293"
        },
        {
          "method": "org.eclipse.core.runtime.adaptor.EclipseClassLoader.findLocalClass",
          "source": "EclipseClassLoader.java:110"
        },
        {
          "method": "org.eclipse.osgi.framework.internal.core.BundleLoader.findLocalClass",
          "source": "BundleLoader.java:371"
        },
        {
          "method": "org.eclipse.osgi.framework.internal.core.BundleLoader.requireClass",
          "source": "BundleLoader.java:336"
        },
        {
          "method": "org.eclipse.osgi.framework.internal.core.BundleLoader.findRequiredClass",
          "source": "BundleLoader.java:914"
        },
        {
          "method": "org.eclipse.osgi.framework.internal.core.BundleLoader.findClass",
          "source": "BundleLoader.java:399"
        },
        {
          "method": "org.eclipse.osgi.framework.adaptor.core.AbstractClassLoader.loadClass",
          "source": "AbstractClassLoader.java:93"
        },
        {
          "method": "java.lang.ClassLoader.loadClass",
          "source": "Unknown Source"
        },
        {
          "method": "java.lang.ClassLoader.loadClassInternal",
          "source": "Unknown Source"
        },
        {
          "method": "org.eclipse.ui.internal.ide.model.WorkbenchAdapterFactory.\u003cinit\u003e",
          "source": "WorkbenchAdapterFactory.java:33"
        },
        {
          "method": "org.eclipse.ui.internal.ide.model.WorkbenchAdapterBuilder.registerAdapters",
          "source": "WorkbenchAdapterBuilder.java:33"
        },
        {
          "method": "org.eclipse.ui.internal.ide.IDEWorkbenchAdvisor.initialize",
          "source": "IDEWorkbenchAdvisor.java:173"
        },
        {
          "method": "org.eclipse.ui.application.WorkbenchAdvisor.internalBasicInitialize",
          "source": "WorkbenchAdvisor.java:167"
        },
        {
          "method": "org.eclipse.ui.internal.Workbench.init",
          "source": "Workbench.java:852"
        },
        {
          "method": "org.eclipse.ui.internal.Workbench.runUI",
          "source": "Workbench.java:1516"
        },
        {
          "method": "org.eclipse.ui.internal.Workbench.createAndRunWorkbench",
          "source": "Workbench.java:285"
        },
        {
          "method": "org.eclipse.ui.PlatformUI.createAndRunWorkbench",
          "source": "PlatformUI.java:144"
        },
        {
          "method": "org.eclipse.ui.internal.ide.IDEApplication.run",
          "source": "IDEApplication.java:102"
        },
        {
          "method": "org.eclipse.core.internal.runtime.PlatformActivator$1.run",
          "source": "PlatformActivator.java:220"
        },
        {
          "method": "org.eclipse.core.runtime.adaptor.EclipseStarter.run",
          "source": "EclipseStarter.java:273"
        },
        {
          "method": "org.eclipse.core.runtime.adaptor.EclipseStarter.run",
          "source": "EclipseStarter.java:129"
        },
        {
          "method": "sun.reflect.NativeMethodAccessorImpl.invoke0",
          "source": "Native Method"
        },
        {
          "method": "sun.reflect.NativeMethodAccessorImpl.invoke",
          "source": "Unknown Source"
        },
        {
          "method": "sun.reflect.DelegatingMethodAccessorImpl.invoke",
          "source": "Unknown Source"
        },
        {
          "method": "java.lang.reflect.Method.invoke",
          "source": "Unknown Source"
        },
        {
          "method": "org.eclipse.core.launcher.Main.basicRun",
          "source": "Main.java:185"
        },
        {
          "method": "org.eclipse.core.launcher.Main.run",
          "source": "Main.java:710"
        },
        {
          "method": "org.eclipse.core.launcher.Main.main",
          "source": "Main.java:694"
        }
      ],
      "causedBy": {
        "exceptionType": "java.lang.IndexOutOfBoundsException",
        "message": "Index: 458761, Size: 5",
        "elements": [
          {
            "method": "java.util.ArrayList.RangeCheck",
            "source": "Unknown Source"
          },
          {
            "method": "java.util.ArrayList.get",
            "source": "Unknown Source"
          },
          {
            "method": "org.eclipse.core.internal.resources.MarkerReader_3.readMarkerInfo",
            "source": "MarkerReader_3.java:134"
          },
          {
            "method": "org.eclipse.core.internal.resources.MarkerReader_3.read",
            "source": "MarkerReader_3.java:69"
          },
          {
            "method": "org.eclipse.core.internal.resources.MarkerReader.read",
            "source": "MarkerReader.java:49"
          },
          {
            "method": "org.eclipse.core.internal.resources.MarkerManager.restoreFromSave",
            "source": "MarkerManager.java:449"
          },
          {
            "method": "org.eclipse.core.internal.resources.MarkerManager.restore",
            "source": "MarkerManager.java:434"
          },
          {
            "method": "org.eclipse.core.internal.resources.SaveManager.restoreMarkers",
            "source": "SaveManager.java:633"
          },
          {
            "method": "org.eclipse.core.internal.resources.SaveManager.restore",
            "source": "SaveManager.java:558"
          },
          {
            "method": "org.eclipse.core.internal.resources.SaveManager.startup",
            "source": "SaveManager.java:1241"
          },
          {
            "method": "org.eclipse.core.internal.resources.Workspace.startup",
            "source": "Workspace.java:1822"
          },
          {
            "method": "org.eclipse.core.internal.resources.Workspace.open",
            "source": "Workspace.java:1601"
          },
          {
            "method": "org.eclipse.core.resources.ResourcesPlugin.startup",
            "source": "ResourcesPlugin.java:357"
          },
          {
            "method": "org.eclipse.core.internal.compatibility.PluginActivator.start",
            "source": "PluginActivator.java:56"
          },
          {
            "method": "org.eclipse.osgi.framework.internal.core.BundleContextImpl$1.run",
            "source": "BundleContextImpl.java:958"
          },
          {
            "method": "java.security.AccessController.doPrivileged",
            "source": "Native Method"
          },
          {
            "method": "org.eclipse.osgi.framework.internal.core.BundleContextImpl.startActivator",
            "source": "BundleContextImpl.java:954"
          }
        ],
        "number": 0,
        "commentIndex": 0
      },
      "number": 0,
      "commentIndex": 0,
      "bugId": "93069",
      "date": "2005-04-28T09:38:36+02:00",
      "product": "Platform",
      "component": "Resources",
      "severity": "normal"
    },
    {
      "exceptionType": "java.lang.IndexOutOfBoundsException",
      "message": "Index: 458761, Size: 5",
      "elements": [
        {
          "method": "java.util.ArrayList.RangeCheck",
          "source": "Unknown Source"
        },
        {
          "method": "java.util.ArrayList.get",
          "source": "Unknown Source"
        },
        {
          "method": "org.eclipse.core.internal.resources.MarkerReader_3.readMarkerInfo",
          "source": "MarkerReader_3.java:134"
        },
        {
          "method": "org.eclipse.core.internal.resources.MarkerReader_3.read",
          "source": "MarkerReader_3.java:69"
        },
        {
          "method": "org.eclipse.core.internal.resources.MarkerReader.read",
          "source": "MarkerReader.java:49"
        },
        {
          "method": "org.eclipse.core.internal.resources.MarkerManager.restoreFromSave",
          "source": "MarkerManager.java:449"
        },
        {
          "method": "org.eclipse.core.internal.resources.MarkerManager.restore",
          "source": "MarkerManager.java:434"
        },
        {
          "method": "org.eclipse.core.internal.resources.SaveManager.restoreMarkers",
          "source": "SaveManager.java:633"
        },
        {
          "method": "org.eclipse.core.internal.resources.SaveManager.restore",
          "source": "SaveManager.java:558"
        },
        {
          "method": "org.eclipse.core.internal.resources.SaveManager.startup",
          "source": "SaveManager.java:1241"
        },
        {
          "method": "org.eclipse.core.internal.resources.Workspace.startup",
          "source": "Workspace.java:1822"
        },
        {
          "method": "org.eclipse.core.internal.resources.Workspace.open",
          "source": "Workspace.java:1601"
        },
        {
          "method": "org.eclipse.core.resources.ResourcesPlugin.startup",
          "source": "ResourcesPlugin.java:357"
        },
        {
          "method": "org.eclipse.core.internal.compatibility.PluginActivator.start",
          "source": "PluginActivator.java:56"
        },
        {
          "method": "org.eclipse.osgi.framework.internal.core.BundleContextImpl$1.run",
          "source": "BundleContextImpl.java:958"
        },
        {
          "method": "java.security.AccessController.doPrivileged",
          "source": "Native Method"
        },
        {
          "method": "org.eclipse.osgi.framework.internal.core.BundleContextImpl.startActivator",
          "source": "BundleContextImpl.java:954"
        },
        {
          "method": "org.eclipse.osgi.framework.internal.core.BundleContextImpl.start",
          "source": "BundleContextImpl.java:937"
        },
        {
          "method": "org.eclipse.osgi.framework.internal.core.BundleHost.startWorker",
          "source": "BundleHost.java:417"
        },
        {
          "method": "org.eclipse.osgi.framework.internal.core.AbstractBundle.start",
          "source": "AbstractBundle.java:293"
        },
        {
          "method": "org.eclipse.core.runtime.adaptor.EclipseClassLoader.findLocalClass",
          "source": "EclipseClassLoader.java:110"
        },
        {
          "method": "org.eclipse.osgi.framework.internal.core.BundleLoader.findLocalClass",
          "source": "BundleLoader.java:371"
        },
        {
          "method": "org.eclipse.osgi.framework.internal.core.BundleLoader.requireClass",
          "source": "BundleLoader.java:336"
        },
        {
          "method": "org.eclipse.osgi.framework.internal.core.BundleLoader.findRequiredClass",
          "source": "BundleLoader.java:914"
        },
        {
          "method": "org.eclipse.osgi.framework.internal.core.BundleLoader.findClass",
          "source": "BundleLoader.java:399"
        },
        {
          "method": "org.eclipse.osgi.framework.adaptor.core.AbstractClassLoader.loadClass",
          "source": "AbstractClassLoader.java:93"
        },
        {
          "method": "java.lang.ClassLoader.loadClass",
          "source": "Unknown Source"
        },
        {
          "method": "java.lang.ClassLoader.loadClassInternal",
          "source": "Unknown Source"
        },
        {
          "method": "org.eclipse.ui.internal.ide.model.WorkbenchAdapterFactory.\u003cinit\u003e",
          "source": "WorkbenchAdapterFactory.java:33"
        },
        {
          "method": "org.eclipse.ui.internal.ide.model.WorkbenchAdapterBuilder.registerAdapters",
          "source": "WorkbenchAdapterBuilder.java:33"
        },
        {
          "method": "org.eclipse.ui.internal.ide.IDEWorkbenchAdvisor.initialize",
          "source": "IDEWorkbenchAdvisor.java:173"
        },
        {
          "method": "org.eclipse.ui.application.WorkbenchAdvisor.internalBasicInitialize",
          "source": "WorkbenchAdvisor.java:167"
        },
        {
          "method": "org.eclipse.ui.internal.Workbench.init",
          "source": "Workbench.java:852"
        },
        {
          "method": "org.eclipse.ui.internal.Workbench.runUI",
          "source": "Workbench.java:1516"
        },
        {
          "method": "org.eclipse.ui.internal.Workbench.createAndRunWorkbench",
          "source": "Workbench.java:285"
        },
        {
          "method": "org.eclipse.ui.PlatformUI.createAndRunWorkbench",
          "source": "PlatformUI.java:144"
        },
        {
          "method": "org.eclipse.ui.internal.ide.IDEApplication.run",
          "source": "IDEApplication.java:102"
        },
        {
          "method": "org.eclipse.core.internal.runtime.PlatformActivator$1.run",
          "source": "PlatformActivator.java:220"
        },
        {
          "method": "org.eclipse.core.runtime.adaptor.EclipseStarter.run",
          "source": "EclipseStarter.java:273"
        },
        {
          "method": "org.eclipse.core.runtime.adaptor.EclipseStarter.run",
          "source": "EclipseStarter.java:129"
        },
        {
          "method": "sun.reflect.NativeMethodAccessorImpl.invoke0",
          "source": "Native Method"
        },
        {
          "method": "sun.reflect.NativeMethodAccessorImpl.invoke",
          "source": "Unknown Source"
        },
        {
          "method": "sun.reflect.DelegatingMethodAccessorImpl.invoke",
          "source": "Unknown Source"
        },
        {
          "method": "java.lang.reflect.Method.invoke",
          "source": "Unknown Source"
        },
        {
          "method": "org.eclipse.core.launcher.Main.basicRun",
          "source": "Main.java:185"
        },
        {
          "method": "org.eclipse.core.launcher.Main.run",
          "source": "Main.java:710"
        },
        {
          "method": "org.eclipse.core.launcher.Main.main",
          "source": "Main.java:694"
        }
      ],
      "number": 1,
      "commentIndex": 0,
      "bugId": "93069",
      "date": "2005-04-28T09:38:36+02:00",
      "product": "Platform",
      "component": "Resources",
      "severity": "normal"
    },
    {
      "exceptionType": "java.lang.NoClassDefFoundError",
      "message": "org/eclipse/core/resources/IProject",
      "elements": [
        {
          "method": "org.eclipse.ui.internal.ide.model.WorkbenchAdapterFactory.\u003cinit\u003e",
          "source": "WorkbenchAdapterFactory.java:33"
        },
        {
          "method": "org.eclipse.ui.internal.ide.model.WorkbenchAdapterBuilder.registerAdapters",
          "source": "WorkbenchAdapterBuilder.java:33"
        },
        {
          "method": "org.eclipse.ui.internal.ide.IDEWorkbenchAdvisor.initialize",
          "source": "IDEWorkbenchAdvisor.java:173"
        },
        {
          "method": "org.eclipse.ui.application.WorkbenchAdvisor.internalBasicInitialize",
          "source": "WorkbenchAdvisor.java:167"
        },
        {
          "method": "org.eclipse.ui.internal.Workbench.init",
          "source": "Workbench.java:852"
        },
        {
          "method": "org.eclipse.ui.internal.Workbench.runUI",
          "source": "Workbench.java:1516"
        },
        {
          "method": "org.eclipse.ui.internal.Workbench.createAndRunWorkbench",
          "source": "Workbench.java:285"
        },
        {
          "method": "org.eclipse.ui.PlatformUI.createAndRunWorkbench",
          "source": "PlatformUI.java:144"
        },
        {
          "method": "org.eclipse.ui.internal.ide.IDEApplication.run",
          "source": "IDEApplication.java:102"
        },
        {
          "method": "org.eclipse.core.internal.runtime.PlatformActivator$1.run",
          "source": "PlatformActivator.java:220"
        },
        {
          "method": "org.eclipse.core.runtime.adaptor.EclipseStarter.run",
          "source": "EclipseStarter.java:273"
        },
        {
          "method": "org.eclipse.core.runtime.adaptor.EclipseStarter.run",
          "source": "EclipseStarter.java:129"
        },
        {
          "method": "sun.reflect.NativeMethodAccessorImpl.invoke0",
          "source": "Native Method"
        },
        {
          "method": "sun.reflect.NativeMethodAccessorImpl.invoke",
          "source": "Unknown Source"
        },
        {
          "method": "sun.reflect.DelegatingMethodAccessorImpl.invoke",
          "source": "Unknown Source"
        },
        {
          "method": "java.lang.reflect.Method.invoke",
          "source": "Unknown Source"
        },
        {
          "method": "org.eclipse.core.launcher.Main.basicRun",
          "source": "Main.java:185"
        },
        {
          "method": "org.eclipse.core.launcher.Main.run",
          "source": "Main.java:710"
        },
        {
          "method": "org.eclipse.core.launcher.Main.main",
          "source": "Main.java:694"
        }
      ],
      "number": 2,
      "commentIndex": 0,
      "bugId": "93069",
      "date": "2005-04-28T09:38:36+02:00",
      "product": "Platform",
      "component": "Resources",
      "severity": "normal"
    }
  ],
  "groupId": "93069",
  "bugId": "93069",
  "date": "2005-04-28T09:38:36+02:00",
  "product": "Platform",
  "component": "Resources",
  "severity": "normal"
}