{
  "comments": [
    "in i0426\n\nI\u0027m running with a framework fragment installed (CDS).  This shows up as a \nbundle that does not have a manifest.  Nor does it have a plugin.xml or \nfragment.xml.  Whne I start Eclipse I get the follwoing in my log\n\nRoot exception:\norg.eclipse.osgi.service.pluginconversion.PluginConversionException: Could not \nfind a plugin.xml or a fragment.xml in d:\n\\i0426\\eclipse\\plugins\\com.ibm.cds_1.0.1.\n        at org.eclipse.core.runtime.adaptor.PluginConverterImpl.fillPluginInfo\n(PluginConverterImpl.java:92)\n        at org.eclipse.core.runtime.adaptor.PluginConverterImpl.convertManifest\n(PluginConverterImpl.java:688)\n        at org.eclipse.core.runtime.adaptor.EclipseBundleData.generateManifest\n(EclipseBundleData.java:256)\n        at org.eclipse.core.runtime.adaptor.EclipseBundleData.loadManifest\n(EclipseBundleData.java:214)\n        at org.eclipse.core.runtime.adaptor.EclipseBundleData.getManifest\n(EclipseBundleData.java:182)\n        at org.eclipse.core.runtime.adaptor.EclipseBundleData.loadFromManifest\n(EclipseBundleData.java:302)\n        at \norg.eclipse.osgi.framework.adaptor.core.AbstractBundleData.initializeNewBundle\n(AbstractBundleData.java:506)\n        at \norg.eclipse.osgi.framework.adaptor.core.AbstractFrameworkAdaptor$1.begin\n(AbstractFrameworkAdaptor.java:723)\n        at \norg.eclipse.osgi.framework.internal.core.Framework.installWorkerPrivileged\n(Framework.java:797)\n        at org.eclipse.osgi.framework.internal.core.Framework$2.run\n(Framework.java:713)\n        at java.security.AccessController.doPrivileged\n(AccessController.java:195)\n        at org.eclipse.osgi.framework.internal.core.Framework.installWorker\n(Framework.java:764)\n        at org.eclipse.osgi.framework.internal.core.Framework.installBundle\n(Framework.java:708)\n        at \norg.eclipse.osgi.framework.internal.core.BundleContextImpl.installBundle\n(BundleContextImpl.java:221)\n        at org.eclipse.core.runtime.adaptor.EclipseStarter.installBundles\n(EclipseStarter.java:915)\n        at org.eclipse.core.runtime.adaptor.EclipseStarter.loadBasicBundles\n(EclipseStarter.java:512)\n        at org.eclipse.core.runtime.adaptor.EclipseStarter.startup\n(EclipseStarter.java:282)\n        at org.eclipse.core.runtime.adaptor.EclipseStarter.run\n(EclipseStarter.java:154)\n        at sun.reflect.NativeMethodAccessorImpl.invoke0(Native Method)\n        at sun.reflect.NativeMethodAccessorImpl.invoke\n(NativeMethodAccessorImpl.java:85)\n        at sun.reflect.NativeMethodAccessorImpl.invoke\n(NativeMethodAccessorImpl.java:58)\n        at sun.reflect.DelegatingMethodAccessorImpl.invoke\n(DelegatingMethodAccessorImpl.java:60)\n        at java.lang.reflect.Method.invoke(Method.java:391)\n        at org.eclipse.core.launcher.Main.invokeFramework(Main.java:319)\n        at org.eclipse.core.launcher.Main.basicRun(Main.java:272)\n        at org.eclipse.core.launcher.Main.run(Main.java:951)\n        at org.eclipse.core.launcher.Main.main(Main.java:935)\n\nThe exception likely should not happening at all.  Technically speaking it is \nnot an error to install a bundle with no manifest (or plugin/fragment.xml).  It \nis somewhat pathalogical but the framework likely handles it.  The error we are \ngetting here is because the converter *really* wants to run (there is no \nmanifest) and there is are no xml files to convert.\n\nIn debug mode perhaps we would report more information (e.g., \"installed a \nbundle with no manifest\")",
    "How do you have a framework fragment with out a bundle manifest?  You need to \nat least specify:\n\nBundle-SymbolicName: cds\nFragment-Host: org.eclipse.osgi\n\nI do agree that the PluginConverter should not fail in this case.  But you \nwill likely have other issues.  I\u0027m pretty sure you need at least a Bundle-\nSymbolicName to be included in a feature, right?",
    "yes and no.  the fragment needs a manifest to go in a feature but features are \nnot required.  So I can install bundles without features and without a \nmanifest.  As I say, it is pathological but it shouldn\u0027t fail.",
    "Let\u0027s see if we can do a two line fix for RC2.",
    "defer",
    "releasing bug ownership.\n\nI looked into this fix but it turns out to be more that a two line fix.  There \nare several places in the converter which expect a valid manifest to be \ngenerated.  If we do not bail with a PluginConverterException then there are \nseveral places (both in the converter impl and clients) that will need to \nchange to prevent NPEs.",
    "No intention of fixing this right now. Will need a convincing use case in order to change PluginConvertor code."
  ],
  "commentCreationDates": [
    "2005-04-29T03:05:24+02:00",
    "2005-04-29T15:01:43+02:00",
    "2005-04-29T16:53:29+02:00",
    "2005-05-31T22:47:35+02:00",
    "2005-06-07T21:16:32+02:00",
    "2005-06-07T21:54:14+02:00",
    "2007-03-27T22:38:32+02:00"
  ],
  "traces": [
    {
      "exceptionType": "org.eclipse.osgi.service.pluginconversion.PluginConversionException",
      "message": "Could not  find a plugin.xml or a fragment.xml in d: \\i0426\\eclipse\\plugins\\com.ibm.cds_1.0.1.",
      "elements": [
        {
          "method": "org.eclipse.core.runtime.adaptor.PluginConverterImpl.fillPluginInfo",
          "source": "PluginConverterImpl.java:92"
        },
        {
          "method": "org.eclipse.core.runtime.adaptor.PluginConverterImpl.convertManifest",
          "source": "PluginConverterImpl.java:688"
        },
        {
          "method": "org.eclipse.core.runtime.adaptor.EclipseBundleData.generateManifest",
          "source": "EclipseBundleData.java:256"
        },
        {
          "method": "org.eclipse.core.runtime.adaptor.EclipseBundleData.loadManifest",
          "source": "EclipseBundleData.java:214"
        },
        {
          "method": "org.eclipse.core.runtime.adaptor.EclipseBundleData.getManifest",
          "source": "EclipseBundleData.java:182"
        },
        {
          "method": "org.eclipse.core.runtime.adaptor.EclipseBundleData.loadFromManifest",
          "source": "EclipseBundleData.java:302"
        },
        {
          "method": "org.eclipse.osgi.framework.adaptor.core.AbstractBundleData.initializeNewBundle",
          "source": "AbstractBundleData.java:506"
        },
        {
          "method": "org.eclipse.osgi.framework.adaptor.core.AbstractFrameworkAdaptor$1.begin",
          "source": "AbstractFrameworkAdaptor.java:723"
        },
        {
          "method": "org.eclipse.osgi.framework.internal.core.Framework.installWorkerPrivileged",
          "source": "Framework.java:797"
        },
        {
          "method": "org.eclipse.osgi.framework.internal.core.Framework$2.run",
          "source": "Framework.java:713"
        },
        {
          "method": "java.security.AccessController.doPrivileged",
          "source": "AccessController.java:195"
        },
        {
          "method": "org.eclipse.osgi.framework.internal.core.Framework.installWorker",
          "source": "Framework.java:764"
        },
        {
          "method": "org.eclipse.osgi.framework.internal.core.Framework.installBundle",
          "source": "Framework.java:708"
        },
        {
          "method": "org.eclipse.osgi.framework.internal.core.BundleContextImpl.installBundle",
          "source": "BundleContextImpl.java:221"
        },
        {
          "method": "org.eclipse.core.runtime.adaptor.EclipseStarter.installBundles",
          "source": "EclipseStarter.java:915"
        },
        {
          "method": "org.eclipse.core.runtime.adaptor.EclipseStarter.loadBasicBundles",
          "source": "EclipseStarter.java:512"
        },
        {
          "method": "org.eclipse.core.runtime.adaptor.EclipseStarter.startup",
          "source": "EclipseStarter.java:282"
        },
        {
          "method": "org.eclipse.core.runtime.adaptor.EclipseStarter.run",
          "source": "EclipseStarter.java:154"
        },
        {
          "method": "sun.reflect.NativeMethodAccessorImpl.invoke0",
          "source": "Native Method"
        },
        {
          "method": "sun.reflect.NativeMethodAccessorImpl.invoke",
          "source": "NativeMethodAccessorImpl.java:85"
        },
        {
          "method": "sun.reflect.NativeMethodAccessorImpl.invoke",
          "source": "NativeMethodAccessorImpl.java:58"
        },
        {
          "method": "sun.reflect.DelegatingMethodAccessorImpl.invoke",
          "source": "DelegatingMethodAccessorImpl.java:60"
        },
        {
          "method": "java.lang.reflect.Method.invoke",
          "source": "Method.java:391"
        },
        {
          "method": "org.eclipse.core.launcher.Main.invokeFramework",
          "source": "Main.java:319"
        },
        {
          "method": "org.eclipse.core.launcher.Main.basicRun",
          "source": "Main.java:272"
        },
        {
          "method": "org.eclipse.core.launcher.Main.run",
          "source": "Main.java:951"
        },
        {
          "method": "org.eclipse.core.launcher.Main.main",
          "source": "Main.java:935"
        }
      ],
      "number": 0,
      "commentIndex": 0,
      "bugId": "93207",
      "date": "2005-04-29T03:05:24+02:00",
      "product": "Platform",
      "component": "Runtime",
      "severity": "normal"
    }
  ],
  "groupId": "93207",
  "bugId": "93207",
  "date": "2005-04-29T03:05:24+02:00",
  "product": "Platform",
  "component": "Runtime",
  "severity": "normal"
}