{
  "comments": [
    "Using build I20050426-1700.\n\nWhile exiting my workspace I got following exception:\n!ENTRY org.eclipse.ui.workbench 4 2 2005-04-29 10:40:17.127\n!MESSAGE Problems occurred when invoking code from plug-in:\n\"org.eclipse.ui.workbench\".\n!STACK 0\njava.lang.ClassCastException: org.apache.crimson.tree.TextNode\n        at org.eclipse.ui.XMLMemento$DOMWriter.save(XMLMemento.java:430)\n        at org.eclipse.ui.XMLMemento$DOMWriter.save(XMLMemento.java:430)\n        at org.eclipse.ui.XMLMemento$DOMWriter.save(XMLMemento.java:430)\n        at org.eclipse.ui.XMLMemento$DOMWriter.save(XMLMemento.java:430)\n        at org.eclipse.ui.XMLMemento$DOMWriter.save(XMLMemento.java:430)\n        at org.eclipse.ui.XMLMemento$DOMWriter.save(XMLMemento.java:430)\n        at org.eclipse.ui.XMLMemento.save(XMLMemento.java:404)\n        at org.eclipse.ui.internal.Workbench.saveMementoToFile(Workbench.java:1618)\n        at org.eclipse.ui.internal.Workbench.access$4(Workbench.java:1609)\n        at org.eclipse.ui.internal.Workbench$9.run(Workbench.java:500)\n        at\norg.eclipse.core.internal.runtime.InternalPlatform.run(InternalPlatform.java:1026)\n        at org.eclipse.core.runtime.Platform.run(Platform.java:757)\n        at org.eclipse.ui.internal.Workbench.busyClose(Workbench.java:496)\n        at org.eclipse.ui.internal.Workbench.access$6(Workbench.java:461)\n        at org.eclipse.ui.internal.Workbench$12.run(Workbench.java:644)\n        at org.eclipse.swt.custom.BusyIndicator.showWhile(BusyIndicator.java:69)\n        at org.eclipse.ui.internal.Workbench.close(Workbench.java:642)\n        at org.eclipse.ui.internal.Workbench.close(Workbench.java:617)\n        at org.eclipse.ui.internal.QuitAction.run(QuitAction.java:57)\n        at org.eclipse.jface.action.Action.runWithEvent(Action.java:996)\n        at\norg.eclipse.jface.action.ActionContributionItem.handleWidgetSelection(ActionContributionItem.java:538)\n        at\norg.eclipse.jface.action.ActionContributionItem.access$2(ActionContributionItem.java:488)\n        at\norg.eclipse.jface.action.ActionContributionItem$5.handleEvent(ActionContributionItem.java:400)\n        at org.eclipse.swt.widgets.EventTable.sendEvent(EventTable.java:82)\n        at org.eclipse.swt.widgets.Widget.sendEvent(Widget.java:842)\n        at org.eclipse.swt.widgets.Display.runDeferredEvents(Display.java:2900)\n        at org.eclipse.swt.widgets.Display.readAndDispatch(Display.java:2533)\n        at org.eclipse.ui.internal.Workbench.runEventLoop(Workbench.java:1569)\n        at org.eclipse.ui.internal.Workbench.runUI(Workbench.java:1533)\n        at\norg.eclipse.ui.internal.Workbench.createAndRunWorkbench(Workbench.java:306)\n        at org.eclipse.ui.PlatformUI.createAndRunWorkbench(PlatformUI.java:143)\n        at org.eclipse.ui.internal.ide.IDEApplication.run(IDEApplication.java:103)\n        at\norg.eclipse.core.internal.runtime.PlatformActivator$1.run(PlatformActivator.java:228)\n        at\norg.eclipse.core.runtime.adaptor.EclipseStarter.run(EclipseStarter.java:345)\n        at\norg.eclipse.core.runtime.adaptor.EclipseStarter.run(EclipseStarter.java:158)\n        at sun.reflect.NativeMethodAccessorImpl.invoke0(Native Method)\n        at\nsun.reflect.NativeMethodAccessorImpl.invoke(NativeMethodAccessorImpl.java:39)\n        at\nsun.reflect.DelegatingMethodAccessorImpl.invoke(DelegatingMethodAccessorImpl.java:25)\n        at java.lang.reflect.Method.invoke(Method.java:324)\n        at org.eclipse.core.launcher.Main.invokeFramework(Main.java:319)\n        at org.eclipse.core.launcher.Main.basicRun(Main.java:272)\n        at org.eclipse.core.launcher.Main.run(Main.java:951)\n        at org.eclipse.core.launcher.Main.main(Main.java:935)",
    "Nick, would this have anything to do with the Foundation changes that were made?",
    "Looks like it.  I\u0027ll have a look.\n",
    "XMLMemento.DOMWriter is not properly handling text nodes, which can be put in\nthe memento using XMLMemento.putTextData(String).\n",
    "And the Display view does this.\n",
    "Fixed.  It turns out it\u0027s non-trivial to handle a Text node and nice line breaks\nand indenting at the same time, without corrupting the text value.\nThe DOMWriter has been fixed up to support this, but I\u0027ve disabled indenting to\nbe closer to R3.0 behaviour (line breaks, but no indenting).\n\nFiled bug 93262 to do some regression tests.\n",
    "*** Bug 93412 has been marked as a duplicate of this bug. ***",
    "Verified that the regression tests pass in I20050513-0010.\n"
  ],
  "commentCreationDates": [
    "2005-04-29T10:43:33+02:00",
    "2005-04-29T14:17:28+02:00",
    "2005-04-29T15:13:51+02:00",
    "2005-04-29T15:16:26+02:00",
    "2005-04-29T15:16:48+02:00",
    "2005-04-29T18:13:30+02:00",
    "2005-05-02T17:01:48+02:00",
    "2005-05-13T19:29:56+02:00"
  ],
  "traces": [
    {
      "exceptionType": "java.lang.ClassCastException",
      "message": "org.apache.crimson.tree.TextNode",
      "elements": [
        {
          "method": "org.eclipse.ui.XMLMemento$DOMWriter.save",
          "source": "XMLMemento.java:430"
        },
        {
          "method": "org.eclipse.ui.XMLMemento$DOMWriter.save",
          "source": "XMLMemento.java:430"
        },
        {
          "method": "org.eclipse.ui.XMLMemento$DOMWriter.save",
          "source": "XMLMemento.java:430"
        },
        {
          "method": "org.eclipse.ui.XMLMemento$DOMWriter.save",
          "source": "XMLMemento.java:430"
        },
        {
          "method": "org.eclipse.ui.XMLMemento$DOMWriter.save",
          "source": "XMLMemento.java:430"
        },
        {
          "method": "org.eclipse.ui.XMLMemento$DOMWriter.save",
          "source": "XMLMemento.java:430"
        },
        {
          "method": "org.eclipse.ui.XMLMemento.save",
          "source": "XMLMemento.java:404"
        },
        {
          "method": "org.eclipse.ui.internal.Workbench.saveMementoToFile",
          "source": "Workbench.java:1618"
        },
        {
          "method": "org.eclipse.ui.internal.Workbench.access$4",
          "source": "Workbench.java:1609"
        },
        {
          "method": "org.eclipse.ui.internal.Workbench$9.run",
          "source": "Workbench.java:500"
        },
        {
          "method": "org.eclipse.core.internal.runtime.InternalPlatform.run",
          "source": "InternalPlatform.java:1026"
        },
        {
          "method": "org.eclipse.core.runtime.Platform.run",
          "source": "Platform.java:757"
        },
        {
          "method": "org.eclipse.ui.internal.Workbench.busyClose",
          "source": "Workbench.java:496"
        },
        {
          "method": "org.eclipse.ui.internal.Workbench.access$6",
          "source": "Workbench.java:461"
        },
        {
          "method": "org.eclipse.ui.internal.Workbench$12.run",
          "source": "Workbench.java:644"
        },
        {
          "method": "org.eclipse.swt.custom.BusyIndicator.showWhile",
          "source": "BusyIndicator.java:69"
        },
        {
          "method": "org.eclipse.ui.internal.Workbench.close",
          "source": "Workbench.java:642"
        },
        {
          "method": "org.eclipse.ui.internal.Workbench.close",
          "source": "Workbench.java:617"
        },
        {
          "method": "org.eclipse.ui.internal.QuitAction.run",
          "source": "QuitAction.java:57"
        },
        {
          "method": "org.eclipse.jface.action.Action.runWithEvent",
          "source": "Action.java:996"
        },
        {
          "method": "org.eclipse.jface.action.ActionContributionItem.handleWidgetSelection",
          "source": "ActionContributionItem.java:538"
        },
        {
          "method": "org.eclipse.jface.action.ActionContributionItem.access$2",
          "source": "ActionContributionItem.java:488"
        },
        {
          "method": "org.eclipse.jface.action.ActionContributionItem$5.handleEvent",
          "source": "ActionContributionItem.java:400"
        },
        {
          "method": "org.eclipse.swt.widgets.EventTable.sendEvent",
          "source": "EventTable.java:82"
        },
        {
          "method": "org.eclipse.swt.widgets.Widget.sendEvent",
          "source": "Widget.java:842"
        },
        {
          "method": "org.eclipse.swt.widgets.Display.runDeferredEvents",
          "source": "Display.java:2900"
        },
        {
          "method": "org.eclipse.swt.widgets.Display.readAndDispatch",
          "source": "Display.java:2533"
        },
        {
          "method": "org.eclipse.ui.internal.Workbench.runEventLoop",
          "source": "Workbench.java:1569"
        },
        {
          "method": "org.eclipse.ui.internal.Workbench.runUI",
          "source": "Workbench.java:1533"
        },
        {
          "method": "org.eclipse.ui.internal.Workbench.createAndRunWorkbench",
          "source": "Workbench.java:306"
        },
        {
          "method": "org.eclipse.ui.PlatformUI.createAndRunWorkbench",
          "source": "PlatformUI.java:143"
        },
        {
          "method": "org.eclipse.ui.internal.ide.IDEApplication.run",
          "source": "IDEApplication.java:103"
        },
        {
          "method": "org.eclipse.core.internal.runtime.PlatformActivator$1.run",
          "source": "PlatformActivator.java:228"
        },
        {
          "method": "org.eclipse.core.runtime.adaptor.EclipseStarter.run",
          "source": "EclipseStarter.java:345"
        },
        {
          "method": "org.eclipse.core.runtime.adaptor.EclipseStarter.run",
          "source": "EclipseStarter.java:158"
        },
        {
          "method": "sun.reflect.NativeMethodAccessorImpl.invoke0",
          "source": "Native Method"
        },
        {
          "method": "sun.reflect.NativeMethodAccessorImpl.invoke",
          "source": "NativeMethodAccessorImpl.java:39"
        },
        {
          "method": "sun.reflect.DelegatingMethodAccessorImpl.invoke",
          "source": "DelegatingMethodAccessorImpl.java:25"
        },
        {
          "method": "java.lang.reflect.Method.invoke",
          "source": "Method.java:324"
        },
        {
          "method": "org.eclipse.core.launcher.Main.invokeFramework",
          "source": "Main.java:319"
        },
        {
          "method": "org.eclipse.core.launcher.Main.basicRun",
          "source": "Main.java:272"
        },
        {
          "method": "org.eclipse.core.launcher.Main.run",
          "source": "Main.java:951"
        },
        {
          "method": "org.eclipse.core.launcher.Main.main",
          "source": "Main.java:935"
        }
      ],
      "number": 0,
      "commentIndex": 0,
      "bugId": "93238",
      "date": "2005-04-29T10:43:33+02:00",
      "product": "Platform",
      "component": "UI",
      "severity": "critical"
    }
  ],
  "groupId": "93238",
  "bugId": "93238",
  "date": "2005-04-29T10:43:33+02:00",
  "product": "Platform",
  "component": "UI",
  "severity": "critical"
}