{
  "comments": [
    "On Linux Power PC machine, eclipse fails to launch with the log entry below. \nYou must start eclipse with -Dosgi.locking \u003dnone.  I have mentioned this in the\ndownload clickthrough, however, it should be fixed because setting any VM args\non the command line wipes out any default VM args set by eclipse.\n\n!SESSION 2005-04-29 14:09:53.103 -----------------------------------------------\neclipse.buildId\u003dI20050426-1700\njava.fullversion\u003dJ2RE 1.4.2 IBM build cxppc32142sr1a-20050209 (JIT enabled: jitc)\nBootLoader constants: OS\u003dlinux, ARCH\u003dppc, WS\u003dgtk, NL\u003den_US\nFramework arguments:  -showlocation\nCommand-line arguments:  -os linux -ws gtk -arch ppc -showlocation -debug\n\n!ENTRY initial@reference:file:plugins/org.eclipse.core.runtime_3.1.0.jar/ 0 0\n2005-04-29 14:09:54.176\n!MESSAGE FrameworkEvent.ERROR\n!STACK 0\norg.osgi.framework.BundleException: Exception in\norg.eclipse.core.internal.runtime.PlatformActivator.start() of bundle\norg.eclipse.core.runtime.\n        at\norg.eclipse.osgi.framework.internal.core.BundleContextImpl.startActivator(BundleContextImpl.java:1013)\n        at\norg.eclipse.osgi.framework.internal.core.BundleContextImpl.start(BundleContextImpl.java:969)\n        at\norg.eclipse.osgi.framework.internal.core.BundleHost.startWorker(BundleHost.java:321)\n        at\norg.eclipse.osgi.framework.internal.core.AbstractBundle.resume(AbstractBundle.java:339)\n        at\norg.eclipse.osgi.framework.internal.core.Framework.resumeBundle(Framework.java:1000)\n        at\norg.eclipse.osgi.framework.internal.core.StartLevelManager.resumeBundles(StartLevelManager.java:576)\n        at\norg.eclipse.osgi.framework.internal.core.StartLevelManager.incFWSL(StartLevelManager.java:498)\n        at\norg.eclipse.osgi.framework.internal.core.StartLevelManager.doSetStartLevel(StartLevelManager.java:275)\n        at\norg.eclipse.osgi.framework.internal.core.StartLevelManager.dispatchEvent(StartLevelManager.java:458)\n        at\norg.eclipse.osgi.framework.eventmgr.EventManager.dispatchEvent(EventManager.java:186)\n        at org.eclipse.osgi.framework.eventmgr.EventThread.run(EventThread.java:104)\nCaused by: java.io.IOException: An error occurred while locking file\n\"/bluebird/teamswt/torres/linux/gtk_ppc/eclipse/configuration/org.eclipse.core.runtime/.manager/.fileTableLock\":\n\"No locks available\". A probable reason is that the file system or Runtime\nEnvironment does not support file locking for that location. Please choose a\ndifferent location, or disable file locking (using the osgi.locking property).\n        at\norg.eclipse.core.runtime.adaptor.Locker_JavaNio.lock(Locker_JavaNio.java:43)\n        at\norg.eclipse.osgi.service.datalocation.FileManager.lock(FileManager.java:356)\n        at\norg.eclipse.osgi.service.datalocation.FileManager.open(FileManager.java:652)\n        at\norg.eclipse.core.internal.runtime.InternalPlatform.initializeRuntimeFileManager(InternalPlatform.java:774)\n        at\norg.eclipse.core.internal.runtime.InternalPlatform.start(InternalPlatform.java:1088)\n        at\norg.eclipse.core.internal.runtime.PlatformActivator.startInternalPlatform(PlatformActivator.java:144)\n        at\norg.eclipse.core.internal.runtime.PlatformActivator.start(PlatformActivator.java:60)\n        at\norg.eclipse.osgi.framework.internal.core.BundleContextImpl$2.run(BundleContextImpl.java:994)\n        at java.security.AccessController.doPrivileged1(Native Method)\n        at java.security.AccessController.doPrivileged(AccessController.java:351)\n        at\norg.eclipse.osgi.framework.internal.core.BundleContextImpl.startActivator(BundleContextImpl.java:988)\n        ... 10 more\nRoot exception:\njava.io.IOException: An error occurred while locking file\n\"/bluebird/teamswt/torres/linux/gtk_ppc/eclipse/configuration/org.eclipse.core.runtime/.manager/.fileTableLock\":\n\"No locks available\". A probable reason is that the file system or Runtime\nEnvironment does not support file locking for that location. Please choose a\ndifferent location, or disable file locking (using the osgi.locking property).\n        at\norg.eclipse.core.runtime.adaptor.Locker_JavaNio.lock(Locker_JavaNio.java:43)\n        at\norg.eclipse.osgi.service.datalocation.FileManager.lock(FileManager.java:356)\n        at\norg.eclipse.osgi.service.datalocation.FileManager.open(FileManager.java:652)\n        at\norg.eclipse.core.internal.runtime.InternalPlatform.initializeRuntimeFileManager(InternalPlatform.java:774)\n        at\norg.eclipse.core.internal.runtime.InternalPlatform.start(InternalPlatform.java:1088)\n        at\norg.eclipse.core.internal.runtime.PlatformActivator.startInternalPlatform(PlatformActivator.java:144)\n        at\norg.eclipse.core.internal.runtime.PlatformActivator.start(PlatformActivator.java:60)\n        at\norg.eclipse.osgi.framework.internal.core.BundleContextImpl$2.run(BundleContextImpl.java:994)\n        at java.security.AccessController.doPrivileged1(Native Method)\n        at java.security.AccessController.doPrivileged(AccessController.java:351)\n        at\norg.eclipse.osgi.framework.internal.core.BundleContextImpl.startActivator(BundleContextImpl.java:988)\n        at\norg.eclipse.osgi.framework.internal.core.BundleContextImpl.start(BundleContextImpl.java:969)\n        at\norg.eclipse.osgi.framework.internal.core.BundleHost.startWorker(BundleHost.java:321)\n        at\norg.eclipse.osgi.framework.internal.core.AbstractBundle.resume(AbstractBundle.java:339)\n        at\norg.eclipse.osgi.framework.internal.core.Framework.resumeBundle(Framework.java:1000)\n        at\norg.eclipse.osgi.framework.internal.core.StartLevelManager.resumeBundles(StartLevelManager.java:576)\n        at\norg.eclipse.osgi.framework.internal.core.StartLevelManager.incFWSL(StartLevelManager.java:498)\n        at\norg.eclipse.osgi.framework.internal.core.StartLevelManager.doSetStartLevel(StartLevelManager.java:275)\n        at\norg.eclipse.osgi.framework.internal.core.StartLevelManager.dispatchEvent(StartLevelManager.java:458)\n        at\norg.eclipse.osgi.framework.eventmgr.EventManager.dispatchEvent(EventManager.java:186)\n        at org.eclipse.osgi.framework.eventmgr.EventThread.run(EventThread.java:104)\n\n!ENTRY initial@reference:file:plugins/org.eclipse.update.configurator_3.1.0.jar/\n0 0 2005-04-29 14:09:54.209\n!MESSAGE FrameworkEvent.ERROR\n!STACK 0\norg.osgi.framework.BundleException: Exception in\norg.eclipse.update.internal.configurator.ConfigurationActivator.start() of\nbundle org.eclipse.update.configurator.\n        at\norg.eclipse.osgi.framework.internal.core.BundleContextImpl.startActivator(BundleContextImpl.java:1013)\n        at\norg.eclipse.osgi.framework.internal.core.BundleContextImpl.start(BundleContextImpl.java:969)\n        at\norg.eclipse.osgi.framework.internal.core.BundleHost.startWorker(BundleHost.java:321)\n        at\norg.eclipse.osgi.framework.internal.core.AbstractBundle.resume(AbstractBundle.java:339)\n        at\norg.eclipse.osgi.framework.internal.core.Framework.resumeBundle(Framework.java:1000)\n        at\norg.eclipse.osgi.framework.internal.core.StartLevelManager.resumeBundles(StartLevelManager.java:576)\n        at\norg.eclipse.osgi.framework.internal.core.StartLevelManager.incFWSL(StartLevelManager.java:498)\n        at\norg.eclipse.osgi.framework.internal.core.StartLevelManager.doSetStartLevel(StartLevelManager.java:275)\n        at\norg.eclipse.osgi.framework.internal.core.StartLevelManager.dispatchEvent(StartLevelManager.java:458)\n        at\norg.eclipse.osgi.framework.eventmgr.EventManager.dispatchEvent(EventManager.java:186)\n        at org.eclipse.osgi.framework.eventmgr.EventThread.run(EventThread.java:104)\nCaused by: java.lang.Exception: Cannot initialize the Update Configurator\n        at\norg.eclipse.update.internal.configurator.ConfigurationActivator.initialize(ConfigurationActivator.java:94)\n        at\norg.eclipse.update.internal.configurator.ConfigurationActivator.start(ConfigurationActivator.java:72)\n        at\norg.eclipse.osgi.framework.internal.core.BundleContextImpl$2.run(BundleContextImpl.java:994)\n        at java.security.AccessController.doPrivileged1(Native Method)\n        at java.security.AccessController.doPrivileged(AccessController.java:351)\n        at\norg.eclipse.osgi.framework.internal.core.BundleContextImpl.startActivator(BundleContextImpl.java:988)\n        ... 10 more\nRoot exception:\njava.lang.Exception: Cannot initialize the Update Configurator\n        at\norg.eclipse.update.internal.configurator.ConfigurationActivator.initialize(ConfigurationActivator.java:94)\n        at\norg.eclipse.update.internal.configurator.ConfigurationActivator.start(ConfigurationActivator.java:72)\n        at\norg.eclipse.osgi.framework.internal.core.BundleContextImpl$2.run(BundleContextImpl.java:994)\n        at java.security.AccessController.doPrivileged1(Native Method)\n        at java.security.AccessController.doPrivileged(AccessController.java:351)\n        at\norg.eclipse.osgi.framework.internal.core.BundleContextImpl.startActivator(BundleContextImpl.java:988)\n        at\norg.eclipse.osgi.framework.internal.core.BundleContextImpl.start(BundleContextImpl.java:969)\n        at\norg.eclipse.osgi.framework.internal.core.BundleHost.startWorker(BundleHost.java:321)\n        at\norg.eclipse.osgi.framework.internal.core.AbstractBundle.resume(AbstractBundle.java:339)\n        at\norg.eclipse.osgi.framework.internal.core.Framework.resumeBundle(Framework.java:1000)\n        at\norg.eclipse.osgi.framework.internal.core.StartLevelManager.resumeBundles(StartLevelManager.java:576)\n        at\norg.eclipse.osgi.framework.internal.core.StartLevelManager.incFWSL(StartLevelManager.java:498)\n        at\norg.eclipse.osgi.framework.internal.core.StartLevelManager.doSetStartLevel(StartLevelManager.java:275)\n        at\norg.eclipse.osgi.framework.internal.core.StartLevelManager.dispatchEvent(StartLevelManager.java:458)\n        at\norg.eclipse.osgi.framework.eventmgr.EventManager.dispatchEvent(EventManager.java:186)\n        at org.eclipse.osgi.framework.eventmgr.EventThread.run(EventThread.java:104)\n\n!ENTRY org.eclipse.osgi 2005-04-29 14:09:54.216\n!MESSAGE Startup error\n!STACK 1\njava.lang.IllegalStateException: Bundle\ninitial@reference:file:plugins/org.eclipse.core.runtime_3.1.0.jar/ [1] is not\nactive.\n        at\norg.eclipse.core.runtime.adaptor.EclipseStarter.ensureBundlesActive(EclipseStarter.java:379)\n        at\norg.eclipse.core.runtime.adaptor.EclipseStarter.startup(EclipseStarter.java:289)\n        at\norg.eclipse.core.runtime.adaptor.EclipseStarter.run(EclipseStarter.java:154)\n        at sun.reflect.NativeMethodAccessorImpl.invoke0(Native Method)\n        at\nsun.reflect.NativeMethodAccessorImpl.invoke(NativeMethodAccessorImpl.java:85)\n        at\nsun.reflect.NativeMethodAccessorImpl.invoke(NativeMethodAccessorImpl.java:58)\n        at\nsun.reflect.DelegatingMethodAccessorImpl.invoke(DelegatingMethodAccessorImpl.java:60)\n        at java.lang.reflect.Method.invoke(Method.java:391)\n        at org.eclipse.core.launcher.Main.invokeFramework(Main.java:319)\n        at org.eclipse.core.launcher.Main.basicRun(Main.java:272)\n        at org.eclipse.core.launcher.Main.run(Main.java:951)\n        at org.eclipse.core.launcher.Main.main(Main.java:935)",
    "We cannot fix the problem with locking itself. This is usually caused by a bad\nNFS configuration. Running Eclipse on this machine having configuration area (or\ninstall) and workspace locally should work, otherwise it would prove it to be a\nVM limitation.\n\nThe best we can do is if it is a OS/platform specific problem, then that drop\u0027s\neclipse.ini could have locking disabled by default.",
    "Just as another data point...\n\nI did not need this command line arg to launch Eclipse on my box (SLES 9 SP1). \nI am not using NFS.",
    "There is not much we can do about the locking problem, and the command line is\nexpected to override default options set by eclipse.ini.\n\n*** This bug has been marked as a duplicate of 44735 ***"
  ],
  "commentCreationDates": [
    "2005-04-29T21:01:40+02:00",
    "2005-04-29T21:13:42+02:00",
    "2005-05-03T16:00:51+02:00",
    "2005-05-03T17:24:26+02:00"
  ],
  "traces": [
    {
      "exceptionType": "org.osgi.framework.BundleException",
      "message": "Exception in org.eclipse.core.internal.runtime.PlatformActivator.start() of bundle org.eclipse.core.runtime.",
      "elements": [
        {
          "method": "org.eclipse.osgi.framework.internal.core.BundleContextImpl.startActivator",
          "source": "BundleContextImpl.java:1013"
        },
        {
          "method": "org.eclipse.osgi.framework.internal.core.BundleContextImpl.start",
          "source": "BundleContextImpl.java:969"
        },
        {
          "method": "org.eclipse.osgi.framework.internal.core.BundleHost.startWorker",
          "source": "BundleHost.java:321"
        },
        {
          "method": "org.eclipse.osgi.framework.internal.core.AbstractBundle.resume",
          "source": "AbstractBundle.java:339"
        },
        {
          "method": "org.eclipse.osgi.framework.internal.core.Framework.resumeBundle",
          "source": "Framework.java:1000"
        },
        {
          "method": "org.eclipse.osgi.framework.internal.core.StartLevelManager.resumeBundles",
          "source": "StartLevelManager.java:576"
        },
        {
          "method": "org.eclipse.osgi.framework.internal.core.StartLevelManager.incFWSL",
          "source": "StartLevelManager.java:498"
        },
        {
          "method": "org.eclipse.osgi.framework.internal.core.StartLevelManager.doSetStartLevel",
          "source": "StartLevelManager.java:275"
        },
        {
          "method": "org.eclipse.osgi.framework.internal.core.StartLevelManager.dispatchEvent",
          "source": "StartLevelManager.java:458"
        },
        {
          "method": "org.eclipse.osgi.framework.eventmgr.EventManager.dispatchEvent",
          "source": "EventManager.java:186"
        },
        {
          "method": "org.eclipse.osgi.framework.eventmgr.EventThread.run",
          "source": "EventThread.java:104"
        }
      ],
      "causedBy": {
        "exceptionType": "java.io.IOException",
        "message": "An error occurred while locking file \"/bluebird/teamswt/torres/linux/gtk_ppc/eclipse/configuration/org.eclipse.core.runtime/.manager/.fileTableLock\": \"No locks available\". A probable reason is that the file system or Runtime Environment does not support file locking for that location. Please choose a different location, or disable file locking (using the osgi.locking property).",
        "elements": [
          {
            "method": "org.eclipse.core.runtime.adaptor.Locker_JavaNio.lock",
            "source": "Locker_JavaNio.java:43"
          },
          {
            "method": "org.eclipse.osgi.service.datalocation.FileManager.lock",
            "source": "FileManager.java:356"
          },
          {
            "method": "org.eclipse.osgi.service.datalocation.FileManager.open",
            "source": "FileManager.java:652"
          },
          {
            "method": "org.eclipse.core.internal.runtime.InternalPlatform.initializeRuntimeFileManager",
            "source": "InternalPlatform.java:774"
          },
          {
            "method": "org.eclipse.core.internal.runtime.InternalPlatform.start",
            "source": "InternalPlatform.java:1088"
          },
          {
            "method": "org.eclipse.core.internal.runtime.PlatformActivator.startInternalPlatform",
            "source": "PlatformActivator.java:144"
          },
          {
            "method": "org.eclipse.core.internal.runtime.PlatformActivator.start",
            "source": "PlatformActivator.java:60"
          },
          {
            "method": "org.eclipse.osgi.framework.internal.core.BundleContextImpl$2.run",
            "source": "BundleContextImpl.java:994"
          },
          {
            "method": "java.security.AccessController.doPrivileged1",
            "source": "Native Method"
          },
          {
            "method": "java.security.AccessController.doPrivileged",
            "source": "AccessController.java:351"
          },
          {
            "method": "org.eclipse.osgi.framework.internal.core.BundleContextImpl.startActivator",
            "source": "BundleContextImpl.java:988"
          }
        ],
        "number": 0,
        "commentIndex": 0
      },
      "number": 0,
      "commentIndex": 0,
      "bugId": "93312",
      "duplicateId": "44735",
      "date": "2005-04-29T21:01:40+02:00",
      "product": "Platform",
      "component": "Runtime",
      "severity": "normal"
    },
    {
      "exceptionType": "java.io.IOException",
      "message": "An error occurred while locking file \"/bluebird/teamswt/torres/linux/gtk_ppc/eclipse/configuration/org.eclipse.core.runtime/.manager/.fileTableLock\": \"No locks available\". A probable reason is that the file system or Runtime Environment does not support file locking for that location. Please choose a different location, or disable file locking (using the osgi.locking property).",
      "elements": [
        {
          "method": "org.eclipse.core.runtime.adaptor.Locker_JavaNio.lock",
          "source": "Locker_JavaNio.java:43"
        },
        {
          "method": "org.eclipse.osgi.service.datalocation.FileManager.lock",
          "source": "FileManager.java:356"
        },
        {
          "method": "org.eclipse.osgi.service.datalocation.FileManager.open",
          "source": "FileManager.java:652"
        },
        {
          "method": "org.eclipse.core.internal.runtime.InternalPlatform.initializeRuntimeFileManager",
          "source": "InternalPlatform.java:774"
        },
        {
          "method": "org.eclipse.core.internal.runtime.InternalPlatform.start",
          "source": "InternalPlatform.java:1088"
        },
        {
          "method": "org.eclipse.core.internal.runtime.PlatformActivator.startInternalPlatform",
          "source": "PlatformActivator.java:144"
        },
        {
          "method": "org.eclipse.core.internal.runtime.PlatformActivator.start",
          "source": "PlatformActivator.java:60"
        },
        {
          "method": "org.eclipse.osgi.framework.internal.core.BundleContextImpl$2.run",
          "source": "BundleContextImpl.java:994"
        },
        {
          "method": "java.security.AccessController.doPrivileged1",
          "source": "Native Method"
        },
        {
          "method": "java.security.AccessController.doPrivileged",
          "source": "AccessController.java:351"
        },
        {
          "method": "org.eclipse.osgi.framework.internal.core.BundleContextImpl.startActivator",
          "source": "BundleContextImpl.java:988"
        },
        {
          "method": "org.eclipse.osgi.framework.internal.core.BundleContextImpl.start",
          "source": "BundleContextImpl.java:969"
        },
        {
          "method": "org.eclipse.osgi.framework.internal.core.BundleHost.startWorker",
          "source": "BundleHost.java:321"
        },
        {
          "method": "org.eclipse.osgi.framework.internal.core.AbstractBundle.resume",
          "source": "AbstractBundle.java:339"
        },
        {
          "method": "org.eclipse.osgi.framework.internal.core.Framework.resumeBundle",
          "source": "Framework.java:1000"
        },
        {
          "method": "org.eclipse.osgi.framework.internal.core.StartLevelManager.resumeBundles",
          "source": "StartLevelManager.java:576"
        },
        {
          "method": "org.eclipse.osgi.framework.internal.core.StartLevelManager.incFWSL",
          "source": "StartLevelManager.java:498"
        },
        {
          "method": "org.eclipse.osgi.framework.internal.core.StartLevelManager.doSetStartLevel",
          "source": "StartLevelManager.java:275"
        },
        {
          "method": "org.eclipse.osgi.framework.internal.core.StartLevelManager.dispatchEvent",
          "source": "StartLevelManager.java:458"
        },
        {
          "method": "org.eclipse.osgi.framework.eventmgr.EventManager.dispatchEvent",
          "source": "EventManager.java:186"
        },
        {
          "method": "org.eclipse.osgi.framework.eventmgr.EventThread.run",
          "source": "EventThread.java:104"
        }
      ],
      "number": 1,
      "commentIndex": 0,
      "bugId": "93312",
      "duplicateId": "44735",
      "date": "2005-04-29T21:01:40+02:00",
      "product": "Platform",
      "component": "Runtime",
      "severity": "normal"
    },
    {
      "exceptionType": "org.osgi.framework.BundleException",
      "message": "Exception in org.eclipse.update.internal.configurator.ConfigurationActivator.start() of bundle org.eclipse.update.configurator.",
      "elements": [
        {
          "method": "org.eclipse.osgi.framework.internal.core.BundleContextImpl.startActivator",
          "source": "BundleContextImpl.java:1013"
        },
        {
          "method": "org.eclipse.osgi.framework.internal.core.BundleContextImpl.start",
          "source": "BundleContextImpl.java:969"
        },
        {
          "method": "org.eclipse.osgi.framework.internal.core.BundleHost.startWorker",
          "source": "BundleHost.java:321"
        },
        {
          "method": "org.eclipse.osgi.framework.internal.core.AbstractBundle.resume",
          "source": "AbstractBundle.java:339"
        },
        {
          "method": "org.eclipse.osgi.framework.internal.core.Framework.resumeBundle",
          "source": "Framework.java:1000"
        },
        {
          "method": "org.eclipse.osgi.framework.internal.core.StartLevelManager.resumeBundles",
          "source": "StartLevelManager.java:576"
        },
        {
          "method": "org.eclipse.osgi.framework.internal.core.StartLevelManager.incFWSL",
          "source": "StartLevelManager.java:498"
        },
        {
          "method": "org.eclipse.osgi.framework.internal.core.StartLevelManager.doSetStartLevel",
          "source": "StartLevelManager.java:275"
        },
        {
          "method": "org.eclipse.osgi.framework.internal.core.StartLevelManager.dispatchEvent",
          "source": "StartLevelManager.java:458"
        },
        {
          "method": "org.eclipse.osgi.framework.eventmgr.EventManager.dispatchEvent",
          "source": "EventManager.java:186"
        },
        {
          "method": "org.eclipse.osgi.framework.eventmgr.EventThread.run",
          "source": "EventThread.java:104"
        }
      ],
      "causedBy": {
        "exceptionType": "java.lang.Exception",
        "message": "Cannot initialize the Update Configurator",
        "elements": [
          {
            "method": "org.eclipse.update.internal.configurator.ConfigurationActivator.initialize",
            "source": "ConfigurationActivator.java:94"
          },
          {
            "method": "org.eclipse.update.internal.configurator.ConfigurationActivator.start",
            "source": "ConfigurationActivator.java:72"
          },
          {
            "method": "org.eclipse.osgi.framework.internal.core.BundleContextImpl$2.run",
            "source": "BundleContextImpl.java:994"
          },
          {
            "method": "java.security.AccessController.doPrivileged1",
            "source": "Native Method"
          },
          {
            "method": "java.security.AccessController.doPrivileged",
            "source": "AccessController.java:351"
          },
          {
            "method": "org.eclipse.osgi.framework.internal.core.BundleContextImpl.startActivator",
            "source": "BundleContextImpl.java:988"
          }
        ],
        "number": 0,
        "commentIndex": 0
      },
      "number": 2,
      "commentIndex": 0,
      "bugId": "93312",
      "duplicateId": "44735",
      "date": "2005-04-29T21:01:40+02:00",
      "product": "Platform",
      "component": "Runtime",
      "severity": "normal"
    },
    {
      "exceptionType": "java.lang.Exception",
      "message": "Cannot initialize the Update Configurator",
      "elements": [
        {
          "method": "org.eclipse.update.internal.configurator.ConfigurationActivator.initialize",
          "source": "ConfigurationActivator.java:94"
        },
        {
          "method": "org.eclipse.update.internal.configurator.ConfigurationActivator.start",
          "source": "ConfigurationActivator.java:72"
        },
        {
          "method": "org.eclipse.osgi.framework.internal.core.BundleContextImpl$2.run",
          "source": "BundleContextImpl.java:994"
        },
        {
          "method": "java.security.AccessController.doPrivileged1",
          "source": "Native Method"
        },
        {
          "method": "java.security.AccessController.doPrivileged",
          "source": "AccessController.java:351"
        },
        {
          "method": "org.eclipse.osgi.framework.internal.core.BundleContextImpl.startActivator",
          "source": "BundleContextImpl.java:988"
        },
        {
          "method": "org.eclipse.osgi.framework.internal.core.BundleContextImpl.start",
          "source": "BundleContextImpl.java:969"
        },
        {
          "method": "org.eclipse.osgi.framework.internal.core.BundleHost.startWorker",
          "source": "BundleHost.java:321"
        },
        {
          "method": "org.eclipse.osgi.framework.internal.core.AbstractBundle.resume",
          "source": "AbstractBundle.java:339"
        },
        {
          "method": "org.eclipse.osgi.framework.internal.core.Framework.resumeBundle",
          "source": "Framework.java:1000"
        },
        {
          "method": "org.eclipse.osgi.framework.internal.core.StartLevelManager.resumeBundles",
          "source": "StartLevelManager.java:576"
        },
        {
          "method": "org.eclipse.osgi.framework.internal.core.StartLevelManager.incFWSL",
          "source": "StartLevelManager.java:498"
        },
        {
          "method": "org.eclipse.osgi.framework.internal.core.StartLevelManager.doSetStartLevel",
          "source": "StartLevelManager.java:275"
        },
        {
          "method": "org.eclipse.osgi.framework.internal.core.StartLevelManager.dispatchEvent",
          "source": "StartLevelManager.java:458"
        },
        {
          "method": "org.eclipse.osgi.framework.eventmgr.EventManager.dispatchEvent",
          "source": "EventManager.java:186"
        },
        {
          "method": "org.eclipse.osgi.framework.eventmgr.EventThread.run",
          "source": "EventThread.java:104"
        }
      ],
      "number": 3,
      "commentIndex": 0,
      "bugId": "93312",
      "duplicateId": "44735",
      "date": "2005-04-29T21:01:40+02:00",
      "product": "Platform",
      "component": "Runtime",
      "severity": "normal"
    },
    {
      "exceptionType": "java.lang.IllegalStateException",
      "message": "Bundle initial@reference:file:plugins/org.eclipse.core.runtime_3.1.0.jar/ [1] is not active.",
      "elements": [
        {
          "method": "org.eclipse.core.runtime.adaptor.EclipseStarter.ensureBundlesActive",
          "source": "EclipseStarter.java:379"
        },
        {
          "method": "org.eclipse.core.runtime.adaptor.EclipseStarter.startup",
          "source": "EclipseStarter.java:289"
        },
        {
          "method": "org.eclipse.core.runtime.adaptor.EclipseStarter.run",
          "source": "EclipseStarter.java:154"
        },
        {
          "method": "sun.reflect.NativeMethodAccessorImpl.invoke0",
          "source": "Native Method"
        },
        {
          "method": "sun.reflect.NativeMethodAccessorImpl.invoke",
          "source": "NativeMethodAccessorImpl.java:85"
        },
        {
          "method": "sun.reflect.NativeMethodAccessorImpl.invoke",
          "source": "NativeMethodAccessorImpl.java:58"
        },
        {
          "method": "sun.reflect.DelegatingMethodAccessorImpl.invoke",
          "source": "DelegatingMethodAccessorImpl.java:60"
        },
        {
          "method": "java.lang.reflect.Method.invoke",
          "source": "Method.java:391"
        },
        {
          "method": "org.eclipse.core.launcher.Main.invokeFramework",
          "source": "Main.java:319"
        },
        {
          "method": "org.eclipse.core.launcher.Main.basicRun",
          "source": "Main.java:272"
        },
        {
          "method": "org.eclipse.core.launcher.Main.run",
          "source": "Main.java:951"
        },
        {
          "method": "org.eclipse.core.launcher.Main.main",
          "source": "Main.java:935"
        }
      ],
      "number": 4,
      "commentIndex": 0,
      "bugId": "93312",
      "duplicateId": "44735",
      "date": "2005-04-29T21:01:40+02:00",
      "product": "Platform",
      "component": "Runtime",
      "severity": "normal"
    }
  ],
  "groupId": "44735",
  "bugId": "93312",
  "duplicateId": "44735",
  "date": "2005-04-29T21:01:40+02:00",
  "product": "Platform",
  "component": "Runtime",
  "severity": "normal"
}