{
  "comments": [
    "For this code with 3.1M6 I get continue AST exceptions --\n\n  Requesting Java AST from selection (Time of error: ....) An internal error \noccurred during: \"Requesting Java AST from selection\".\n\nAnd when I try and build get this error.\nSeverity\tDescription\tResource\tIn Folder\tLocation\n\tCreation Time\n2\tInternal compiler error\njava.lang.NullPointerException\n\tat org.eclipse.jdt.internal.compiler.lookup.Scope.convertToRawType\n(Scope.java:492)\n\tat org.eclipse.jdt.internal.compiler.ast.TypeReference.resolveType\n(TypeReference.java:150)\n\tat \norg.eclipse.jdt.internal.compiler.ast.TypeReference.resolveTypeArgument\n(TypeReference.java:158)\n\tat \norg.eclipse.jdt.internal.compiler.ast.ParameterizedQualifiedTypeReference.intern\nalResolveType(ParameterizedQualifiedTypeReference.java:161)\n\tat \norg.eclipse.jdt.internal.compiler.ast.ParameterizedQualifiedTypeReference.resolv\neType(ParameterizedQualifiedTypeReference.java:288)\n\tat \norg.eclipse.jdt.internal.compiler.ast.TypeReference.resolveTypeArgument\n(TypeReference.java:158)\n\tat \norg.eclipse.jdt.internal.compiler.ast.ParameterizedQualifiedTypeReference.intern\nalResolveType(ParameterizedQualifiedTypeReference.java:161)\n\tat \norg.eclipse.jdt.internal.compiler.ast.ParameterizedQualifiedTypeReference.resolv\neType(ParameterizedQualifiedTypeReference.java:288)\n\tat org.eclipse.jdt.internal.compiler.ast.TypeReference.resolveSuperType\n(TypeReference.java:104)\n\tat org.eclipse.jdt.internal.compiler.lookup.ClassScope.findSupertype\n(ClassScope.java:1050)\n\tat org.eclipse.jdt.internal.compiler.lookup.ClassScope.connectSuperclass\n(ClassScope.java:719)\n\tat \norg.eclipse.jdt.internal.compiler.lookup.ClassScope.connectTypeHierarchy\n(ClassScope.java:856)\n\tat \norg.eclipse.jdt.internal.compiler.lookup.CompilationUnitScope.connectTypeHierarc\nhy(CompilationUnitScope.java:243)\n\tat \norg.eclipse.jdt.internal.compiler.lookup.LookupEnvironment.completeTypeBindings\n(LookupEnvironment.java:195)\n\tat org.eclipse.jdt.internal.compiler.Compiler.beginToCompile\n(Compiler.java:307)\n\tat org.eclipse.jdt.internal.compiler.Compiler.compile(Compiler.java:321)\n\tat org.eclipse.jdt.internal.core.builder.AbstractImageBuilder.compile\n(AbstractImageBuilder.java:239)\n\tat org.eclipse.jdt.internal.core.builder.AbstractImageBuilder.compile\n(AbstractImageBuilder.java:189)\n\tat org.eclipse.jdt.internal.core.builder.BatchImageBuilder.build\n(BatchImageBuilder.java:49)\n\tat org.eclipse.jdt.internal.core.builder.JavaBuilder.buildAll\n(JavaBuilder.java:212)\n\tat org.eclipse.jdt.internal.core.builder.JavaBuilder.build\n(JavaBuilder.java:135)\n\tat org.eclipse.core.internal.events.BuildManager$2.run\n(BuildManager.java:581)\n\tat org.eclipse.core.internal.runtime.InternalPlatform.run\n(InternalPlatform.java:1021)\n\tat org.eclipse.core.runtime.Platform.run(Platform.java:757)\n\tat org.eclipse.core.internal.events.BuildManager.basicBuild\n(BuildManager.java:160)\n\tat org.eclipse.core.internal.events.BuildManager.basicBuild\n(BuildManager.java:198)\n\tat org.eclipse.core.internal.events.BuildManager$1.run\n(BuildManager.java:227)\n\tat org.eclipse.core.internal.runtime.InternalPlatform.run\n(InternalPlatform.java:1021)\n\tat org.eclipse.core.runtime.Platform.run(Platform.java:757)\n\tat org.eclipse.core.internal.events.BuildManager.basicBuild\n(BuildManager.java:230)\n\tat org.eclipse.core.internal.events.BuildManager.basicBuildLoop\n(BuildManager.java:249)\n\tat org.eclipse.core.internal.events.BuildManager.build\n(BuildManager.java:278)\n\tat org.eclipse.core.internal.resources.Workspace.build\n(Workspace.java:211)\n\tat org.eclipse.ui.actions.GlobalBuildAction$1.run\n(GlobalBuildAction.java:183)\n\tat org.eclipse.core.internal.jobs.Worker.run(Worker.java:67)\n\tTest.java\tFooey/src\tline 0\tMay 3, 2005 6:18:53 AM\nand this problem when building.\n\n% cat Test.java\nimport java.util.concurrent.BlockingQueue;\n\n/**\n * @author \u003ca href\u003d\"mailto:foo@bar.com\"\u003eMia\u003c/a\u003e\n */\npublic class Test\n{\n    static interface X\u003cS, L\u003e\n    {\n        /**\n         * @param a\n         * @param b\n         */\n        void call(L a, S b);\n    }\n    static interface Y\u003cS, L\u003e\n    {\n        /**\n         * @param a\n         */\n        void addX(final X\u003cS, L\u003e a);\n\n        /**\n         * @param a\n         */\n        void removeX(final X\u003cS, L\u003e a);\n    }\n    static final class Pair\u003cT, V\u003e\n    {\n        T first;\n\n        V second;\n    }\n    static class Bar\u003cP\u003e\n    {\n        Bar(final BlockingQueue\u003cP\u003e a)\n        {\n\n        }\n    }\n}\n\nfinal class Foo\u003cS, L\u003e extends Test.Bar\u003cTest.Pair\u003cL[], S\u003e\u003e implements Test.X\u003cS, \nL\u003e\n{\n    Foo(final BlockingQueue\u003cTest.Pair\u003cL[], S\u003e\u003e in)\n    {\n        super(in);\n    }\n\n    public void call(L a, S b)\n    {\n\n    }\n}",
    "Cannot reproduce in latest, likely addressed when reworking raw conversion.\nAdded GenericTypeTest#test638."
  ],
  "commentCreationDates": [
    "2005-05-03T05:49:31+02:00",
    "2005-05-09T13:56:35+02:00"
  ],
  "traces": [
    {
      "exceptionType": "java.lang.NullPointerException",
      "elements": [
        {
          "method": "org.eclipse.jdt.internal.compiler.lookup.Scope.convertToRawType",
          "source": "Scope.java:492"
        },
        {
          "method": "org.eclipse.jdt.internal.compiler.ast.TypeReference.resolveType",
          "source": "TypeReference.java:150"
        },
        {
          "method": "org.eclipse.jdt.internal.compiler.ast.TypeReference.resolveTypeArgument",
          "source": "TypeReference.java:158"
        },
        {
          "method": "org.eclipse.jdt.internal.compiler.ast.ParameterizedQualifiedTypeReference.internalResolveType",
          "source": "ParameterizedQualifiedTypeReference.java:161"
        },
        {
          "method": "org.eclipse.jdt.internal.compiler.ast.ParameterizedQualifiedTypeReference.resolveType",
          "source": "ParameterizedQualifiedTypeReference.java:288"
        },
        {
          "method": "org.eclipse.jdt.internal.compiler.ast.TypeReference.resolveTypeArgument",
          "source": "TypeReference.java:158"
        },
        {
          "method": "org.eclipse.jdt.internal.compiler.ast.ParameterizedQualifiedTypeReference.internalResolveType",
          "source": "ParameterizedQualifiedTypeReference.java:161"
        },
        {
          "method": "org.eclipse.jdt.internal.compiler.ast.ParameterizedQualifiedTypeReference.resolveType",
          "source": "ParameterizedQualifiedTypeReference.java:288"
        },
        {
          "method": "org.eclipse.jdt.internal.compiler.ast.TypeReference.resolveSuperType",
          "source": "TypeReference.java:104"
        },
        {
          "method": "org.eclipse.jdt.internal.compiler.lookup.ClassScope.findSupertype",
          "source": "ClassScope.java:1050"
        },
        {
          "method": "org.eclipse.jdt.internal.compiler.lookup.ClassScope.connectSuperclass",
          "source": "ClassScope.java:719"
        },
        {
          "method": "org.eclipse.jdt.internal.compiler.lookup.ClassScope.connectTypeHierarchy",
          "source": "ClassScope.java:856"
        },
        {
          "method": "org.eclipse.jdt.internal.compiler.lookup.CompilationUnitScope.connectTypeHierarchy",
          "source": "CompilationUnitScope.java:243"
        },
        {
          "method": "org.eclipse.jdt.internal.compiler.lookup.LookupEnvironment.completeTypeBindings",
          "source": "LookupEnvironment.java:195"
        },
        {
          "method": "org.eclipse.jdt.internal.compiler.Compiler.beginToCompile",
          "source": "Compiler.java:307"
        },
        {
          "method": "org.eclipse.jdt.internal.compiler.Compiler.compile",
          "source": "Compiler.java:321"
        },
        {
          "method": "org.eclipse.jdt.internal.core.builder.AbstractImageBuilder.compile",
          "source": "AbstractImageBuilder.java:239"
        },
        {
          "method": "org.eclipse.jdt.internal.core.builder.AbstractImageBuilder.compile",
          "source": "AbstractImageBuilder.java:189"
        },
        {
          "method": "org.eclipse.jdt.internal.core.builder.BatchImageBuilder.build",
          "source": "BatchImageBuilder.java:49"
        },
        {
          "method": "org.eclipse.jdt.internal.core.builder.JavaBuilder.buildAll",
          "source": "JavaBuilder.java:212"
        },
        {
          "method": "org.eclipse.jdt.internal.core.builder.JavaBuilder.build",
          "source": "JavaBuilder.java:135"
        },
        {
          "method": "org.eclipse.core.internal.events.BuildManager$2.run",
          "source": "BuildManager.java:581"
        },
        {
          "method": "org.eclipse.core.internal.runtime.InternalPlatform.run",
          "source": "InternalPlatform.java:1021"
        },
        {
          "method": "org.eclipse.core.runtime.Platform.run",
          "source": "Platform.java:757"
        },
        {
          "method": "org.eclipse.core.internal.events.BuildManager.basicBuild",
          "source": "BuildManager.java:160"
        },
        {
          "method": "org.eclipse.core.internal.events.BuildManager.basicBuild",
          "source": "BuildManager.java:198"
        },
        {
          "method": "org.eclipse.core.internal.events.BuildManager$1.run",
          "source": "BuildManager.java:227"
        },
        {
          "method": "org.eclipse.core.internal.runtime.InternalPlatform.run",
          "source": "InternalPlatform.java:1021"
        },
        {
          "method": "org.eclipse.core.runtime.Platform.run",
          "source": "Platform.java:757"
        },
        {
          "method": "org.eclipse.core.internal.events.BuildManager.basicBuild",
          "source": "BuildManager.java:230"
        },
        {
          "method": "org.eclipse.core.internal.events.BuildManager.basicBuildLoop",
          "source": "BuildManager.java:249"
        },
        {
          "method": "org.eclipse.core.internal.events.BuildManager.build",
          "source": "BuildManager.java:278"
        },
        {
          "method": "org.eclipse.core.internal.resources.Workspace.build",
          "source": "Workspace.java:211"
        },
        {
          "method": "org.eclipse.ui.actions.GlobalBuildAction$1.run",
          "source": "GlobalBuildAction.java:183"
        },
        {
          "method": "org.eclipse.core.internal.jobs.Worker.run",
          "source": "Worker.java:67"
        }
      ],
      "number": 0,
      "commentIndex": 0,
      "bugId": "93478",
      "date": "2005-05-03T05:49:31+02:00",
      "product": "JDT",
      "component": "Core",
      "severity": "normal"
    }
  ],
  "groupId": "93478",
  "bugId": "93478",
  "date": "2005-05-03T05:49:31+02:00",
  "product": "JDT",
  "component": "Core",
  "severity": "normal"
}