{
  "comments": [
    "Eclipse 20011206 (Linux/2.4.12-ac5/IBM JDK cx130-20010925)\nMachine 800MHz, 256Meg RAM.\n\nworkspace is clean (i.e. no .metadata present)\nFile-\u003eNew-\u003eProject\n\tJava-\u003eJava Project\nNext\n\tName: Emerald\nNext-\u003eLibraries-\u003eAdd external Jar File\n\tName: /usr/local/ovs-tools/java/ftp.jar\nOk\n\t\"An internal error has occured. See error los for more details.\"\n\nCancel-\u003eQuit.\n\nThe Error log in .metadata/.log looks like this: (why is .log\ninvisible? If someone enters .metadata, she will have a reason :-)\n\nLog: Mon Feb 11 14:24:31 GMT+01:00 2002\n4 org.eclipse.core.runtime 0 Unhandled exception caught in event loop.\njava.lang.IllegalArgumentException: \n  at org.eclipse.core.internal.runtime.Assert.isLegal(Assert.java:50)\n  at org.eclipse.core.internal.runtime.Assert.isLegal(Assert.java:35)\n  at org.eclipse.core.runtime.Path.removeFirstSegments(Path.java:691)\n  at\norg.eclipse.jdt.internal.core.JavaProject.canonicalizedPath(JavaProject.java:125)\n  at org.eclipse.jdt.core.JavaCore.newLibraryEntry(JavaCore.java:561)\n  at org.eclipse.jdt.core.JavaCore.getResolvedClasspathEntry(JavaCore.java:402)\n  at\norg.eclipse.jdt.internal.core.JavaProject.projectPrerequisites(JavaProject.java:1485)\n  at\norg.eclipse.jdt.internal.core.JavaProject.hasClasspathCycle(JavaProject.java:1297)\n\nThe jar looks like this:\n\njar tvf /usr/local/ovs-tools/java/ftp.jar\n    68 Mon Feb 26 21:00:00 GMT+01:00 2001 META-INF/MANIFEST.MF\n  7573 Mon Feb 26 21:00:00 GMT+01:00 2001 com/enterprisedt/net/ftp/FTPClient.class\n  2170 Mon Feb 26 20:26:16 GMT+01:00 2001\ncom/enterprisedt/net/ftp/FTPClientTest.class\n  4323 Mon Feb 26 21:00:00 GMT+01:00 2001\ncom/enterprisedt/net/ftp/FTPControlSocket.class\n   424 Mon Feb 26 21:00:00 GMT+01:00 2001\ncom/enterprisedt/net/ftp/FTPException.class\n   635 Mon Feb 26 21:00:00 GMT+01:00 2001\ncom/enterprisedt/net/ftp/FTPTransferType.class\n  2531 Sun Feb 25 16:25:32 GMT+01:00 2001\ncom/enterprisedt/net/ftp/test/FTPClientTest.class\n\nI have been using this file for months (sun jdk 1.3.1 and plain ibm jdk)\nwithout any problems (I doublechecked my CLASSPATH and my build.xml whether is\nanother version).",
    "Moving to JDT/Core. \nDuplicate of Bug 7528?",
    "Closing\n\n*** This bug has been marked as a duplicate of 7528 ***"
  ],
  "commentCreationDates": [
    "2002-02-11T13:44:41+01:00",
    "2002-02-11T13:50:21+01:00",
    "2002-02-11T15:22:34+01:00"
  ],
  "traces": [
    {
      "exceptionType": "java.lang.IllegalArgumentException",
      "message": "",
      "elements": [
        {
          "method": "org.eclipse.core.internal.runtime.Assert.isLegal",
          "source": "Assert.java:50"
        },
        {
          "method": "org.eclipse.core.internal.runtime.Assert.isLegal",
          "source": "Assert.java:35"
        },
        {
          "method": "org.eclipse.core.runtime.Path.removeFirstSegments",
          "source": "Path.java:691"
        },
        {
          "method": "org.eclipse.jdt.internal.core.JavaProject.canonicalizedPath",
          "source": "JavaProject.java:125"
        },
        {
          "method": "org.eclipse.jdt.core.JavaCore.newLibraryEntry",
          "source": "JavaCore.java:561"
        },
        {
          "method": "org.eclipse.jdt.core.JavaCore.getResolvedClasspathEntry",
          "source": "JavaCore.java:402"
        },
        {
          "method": "org.eclipse.jdt.internal.core.JavaProject.projectPrerequisites",
          "source": "JavaProject.java:1485"
        },
        {
          "method": "org.eclipse.jdt.internal.core.JavaProject.hasClasspathCycle",
          "source": "JavaProject.java:1297"
        }
      ],
      "number": 0,
      "commentIndex": 0,
      "bugId": "9386",
      "duplicateId": "7528",
      "date": "2002-02-11T13:44:41+01:00",
      "product": "JDT",
      "component": "Core",
      "severity": "major"
    }
  ],
  "groupId": "7528",
  "bugId": "9386",
  "duplicateId": "7528",
  "date": "2002-02-11T13:44:41+01:00",
  "product": "JDT",
  "component": "Core",
  "severity": "major"
}