{
  "comments": [
    "Build: N20050506-0010\n\n1) I checked out org.eclipse.pde.* into my workspace\n2) After it completed, I tried to open a type hierarchy on the class \"Job\".\n3) I received a flood of error dialogs and \u003e 200KB of error messages in my log file.\n\nFrom looking at the log, it looks like the initial problem is the PDE resource\nchange listener throwing the NPE.  However, this appears to cause damage to the\nJDT core state, possibly causing all the out of bounds exceptions.\n\nLogging against PDE, but there is likely a JDT problem here as well.  I will\nattach the log file, but here is the top of each of the error stack traces.\n\nFirst stack:\n\njava.lang.NullPointerException\n\tat\norg.eclipse.pde.internal.core.WorkspaceModelManager$ModelChange.equals(WorkspaceModelManager.java:52)\n\tat java.util.ArrayList.indexOf(ArrayList.java:245)\n\tat java.util.ArrayList.contains(ArrayList.java:226)\n\tat\norg.eclipse.pde.internal.core.WorkspaceModelManager.handleFileDelta(WorkspaceModelManager.java:206)\n\tat\norg.eclipse.pde.internal.core.WorkspaceModelManager.visit(WorkspaceModelManager.java:477)\n\nSecond stack:\n\njava.lang.ArrayIndexOutOfBoundsException: Array index out of range: 0\n\tat\norg.eclipse.jdt.internal.core.util.BindingKeyParser.parseInnerType(BindingKeyParser.java:629)\n\tat\norg.eclipse.jdt.internal.core.util.BindingKeyParser.parse(BindingKeyParser.java:527)\n\tat\norg.eclipse.jdt.internal.core.util.BindingKeyParser.parse(BindingKeyParser.java:511)\n\tat org.eclipse.jdt.core.BindingKey.isParameterizedType(BindingKey.java:208)",
    "Created an attachment (id\u003d20789)\nLog file\n",
    "I was able to easily reproduce this.  It happens every time I open a type\nhierarchy on \"Job\" in my workspace.  This happens even right after startup, in a\nsession where the NPE from PDE did not occur.  I\u0027m going to move to JDT\n(although the PDE NPE is clearly also a bug).",
    "The NPE in PDE is a dup of bug 91750.\n\nA method could potentially return null and we were not guarding against that.\n",
    "\n\n*** This bug has been marked as a duplicate of 93826 ***"
  ],
  "commentCreationDates": [
    "2005-05-06T22:06:21+02:00",
    "2005-05-06T22:06:44+02:00",
    "2005-05-06T22:17:55+02:00",
    "2005-05-07T03:33:06+02:00",
    "2005-05-09T09:31:42+02:00"
  ],
  "traces": [
    {
      "exceptionType": "java.lang.NullPointerException",
      "elements": [
        {
          "method": "org.eclipse.pde.internal.core.WorkspaceModelManager$ModelChange.equals",
          "source": "WorkspaceModelManager.java:52"
        },
        {
          "method": "java.util.ArrayList.indexOf",
          "source": "ArrayList.java:245"
        },
        {
          "method": "java.util.ArrayList.contains",
          "source": "ArrayList.java:226"
        },
        {
          "method": "org.eclipse.pde.internal.core.WorkspaceModelManager.handleFileDelta",
          "source": "WorkspaceModelManager.java:206"
        },
        {
          "method": "org.eclipse.pde.internal.core.WorkspaceModelManager.visit",
          "source": "WorkspaceModelManager.java:477"
        }
      ],
      "number": 0,
      "commentIndex": 0,
      "bugId": "93995",
      "duplicateId": "93826",
      "date": "2005-05-06T22:06:21+02:00",
      "product": "JDT",
      "component": "Core",
      "severity": "major"
    },
    {
      "exceptionType": "java.lang.ArrayIndexOutOfBoundsException",
      "message": "Array index out of range: 0",
      "elements": [
        {
          "method": "org.eclipse.jdt.internal.core.util.BindingKeyParser.parseInnerType",
          "source": "BindingKeyParser.java:629"
        },
        {
          "method": "org.eclipse.jdt.internal.core.util.BindingKeyParser.parse",
          "source": "BindingKeyParser.java:527"
        },
        {
          "method": "org.eclipse.jdt.internal.core.util.BindingKeyParser.parse",
          "source": "BindingKeyParser.java:511"
        },
        {
          "method": "org.eclipse.jdt.core.BindingKey.isParameterizedType",
          "source": "BindingKey.java:208"
        }
      ],
      "number": 1,
      "commentIndex": 0,
      "bugId": "93995",
      "duplicateId": "93826",
      "date": "2005-05-06T22:06:21+02:00",
      "product": "JDT",
      "component": "Core",
      "severity": "major"
    }
  ],
  "groupId": "93826",
  "bugId": "93995",
  "duplicateId": "93826",
  "date": "2005-05-06T22:06:21+02:00",
  "product": "JDT",
  "component": "Core",
  "severity": "major"
}