{
  "comments": [
    "Zombie JVM may stay alive after RAC is shut down -- subsequent restarts of the \nRAC fail b/c the zombie is hanging on to the port.  The following exception is \nshown when the RAC is restarted:\n\njava.net.BindException: Address already in use: bind\n        at sun.nio.ch.Net.bind(Native Method)\n        at sun.nio.ch.ServerSocketChannelImpl.bind\n(ServerSocketChannelImpl.java:124)\n        at sun.nio.ch.ServerSocketAdaptor.bind(ServerSocketAdaptor.java:86)\n        at sun.nio.ch.ServerSocketAdaptor.bind(ServerSocketAdaptor.java:79)\n        at org.eclipse.hyades.internal.execution.file.FileServerExtended.run\n(FileServerExtended.java:148)\n        at org.eclipse.hyades.internal.execution.file.FileServer.run\n(FileServer.java:61)",
    "Need to verify that the fixes put in this weekend address this problem.",
    "Problem still exists in latest build.  Additional debugging suggests that this \nis the not the file server java process (which we expect to see as dll based \nJVM), but is a NodeImpl launched RAC java process which is somehow hanging on \nto the file transfer port.\n\nI will work to find a fix today and am cautiously optomistic.  Fallback plan \nis to roll back all of the file transfer enhancement, which we would greatly \nprefer not to do.",
    "Fixed and verified.",
    "Closing..."
  ],
  "commentCreationDates": [
    "2005-05-09T05:49:29+02:00",
    "2005-05-09T14:52:16+02:00",
    "2005-05-09T15:58:47+02:00",
    "2005-05-13T13:18:02+02:00",
    "2006-11-16T14:58:34+01:00"
  ],
  "traces": [
    {
      "exceptionType": "java.net.BindException",
      "message": "Address already in use: bind",
      "elements": [
        {
          "method": "sun.nio.ch.Net.bind",
          "source": "Native Method"
        },
        {
          "method": "sun.nio.ch.ServerSocketChannelImpl.bind",
          "source": "ServerSocketChannelImpl.java:124"
        },
        {
          "method": "sun.nio.ch.ServerSocketAdaptor.bind",
          "source": "ServerSocketAdaptor.java:86"
        },
        {
          "method": "sun.nio.ch.ServerSocketAdaptor.bind",
          "source": "ServerSocketAdaptor.java:79"
        },
        {
          "method": "org.eclipse.hyades.internal.execution.file.FileServerExtended.run",
          "source": "FileServerExtended.java:148"
        },
        {
          "method": "org.eclipse.hyades.internal.execution.file.FileServer.run",
          "source": "FileServer.java:61"
        }
      ],
      "number": 0,
      "commentIndex": 0,
      "bugId": "94080",
      "date": "2005-05-09T05:49:29+02:00",
      "product": "Hyades",
      "component": "Exec",
      "severity": "critical"
    }
  ],
  "groupId": "94080",
  "bugId": "94080",
  "date": "2005-05-09T05:49:29+02:00",
  "product": "Hyades",
  "component": "Exec",
  "severity": "critical"
}