{
  "comments": [
    "As of the 3.3.0_20050509_0816 build, running tests on z/OS result in the \nfollowing exception.  \n\njava.lang.ClassNotFoundException:\n        at java.net.URLClassLoader$ClassFinder.run(URLClassLoader.java:846)\n        at java.security.AccessController.doPrivileged1(Native Method)\n        at java.security.AccessController.doPrivileged\n(AccessController.java:388)\n        at java.net.URLClassLoader.findClass(URLClassLoader.java:369)\n        at java.lang.ClassLoader.loadClass(ClassLoader.java:562)\n        at sun.misc.Launcher$AppClassLoader.loadClass(Launcher.java:440)\n        at java.lang.ClassLoader.loadClass(ClassLoader.java:494)\n        at java.lang.Class.forName1(Native Method)\n        at java.lang.Class.forName(Class.java:177)\n        at \norg.eclipse.hyades.internal.execution.core.file.FileServerCommandFactory.createF\nileServerCommand(FileServerCommandFactory.java)\n        at \norg.eclipse.hyades.internal.collection.framework.FileClientHandlerImplExtended.r\nun(FileClientHandlerImplExtended.java:76)\n        at java.lang.Thread.run(Thread.java:568)\nCaused by: java.io.FileNotFoundException: /u/todd/RAC/plugins/.class (EDC5123I \nIs a directory.)\n        at java.io.FileInputStream.open(Native Method)\n        at java.io.FileInputStream.\u003cinit\u003e(FileInputStream.java:123)\n        at sun.misc.URLClassPath$7.getInputStream(URLClassPath.java:970)\n        at sun.misc.Resource.getBytes(Resource.java:74)\n        at java.net.URLClassLoader.defineClass(URLClassLoader.java:470)\n        at java.net.URLClassLoader.access$500(URLClassLoader.java:107)\n        at java.net.URLClassLoader$ClassFinder.run(URLClassLoader.java:844)\n        ... 11 more\norg.eclipse.hyades.internal.execution.core.file.InvalidFileServerCommandExceptio\nn\n        at \norg.eclipse.hyades.internal.execution.core.file.FileServerCommandFactory.createF\nileServerCommand(FileServerCommandFactory.java)\n        at \norg.eclipse.hyades.internal.collection.framework.FileClientHandlerImplExtended.r\nun(FileClientHandlerImplExtended.java:76)\n        at java.lang.Thread.run(Thread.java:568)",
    "Replaced send(String, length) and receiveString(length) with send(byte[]) and \nreceiveBytes(length).  Began passing number of bytes in string passing \nprotocol rather than number of characters.",
    "it works, closing"
  ],
  "commentCreationDates": [
    "2005-05-09T20:43:14+02:00",
    "2005-05-11T23:33:49+02:00",
    "2005-05-12T03:35:29+02:00"
  ],
  "traces": [
    {
      "exceptionType": "java.lang.ClassNotFoundException",
      "message": "",
      "elements": [
        {
          "method": "java.net.URLClassLoader$ClassFinder.run",
          "source": "URLClassLoader.java:846"
        },
        {
          "method": "java.security.AccessController.doPrivileged1",
          "source": "Native Method"
        },
        {
          "method": "java.security.AccessController.doPrivileged",
          "source": "AccessController.java:388"
        },
        {
          "method": "java.net.URLClassLoader.findClass",
          "source": "URLClassLoader.java:369"
        },
        {
          "method": "java.lang.ClassLoader.loadClass",
          "source": "ClassLoader.java:562"
        },
        {
          "method": "sun.misc.Launcher$AppClassLoader.loadClass",
          "source": "Launcher.java:440"
        },
        {
          "method": "java.lang.ClassLoader.loadClass",
          "source": "ClassLoader.java:494"
        },
        {
          "method": "java.lang.Class.forName1",
          "source": "Native Method"
        },
        {
          "method": "java.lang.Class.forName",
          "source": "Class.java:177"
        },
        {
          "method": "org.eclipse.hyades.internal.execution.core.file.FileServerCommandFactory.createFileServerCommand",
          "source": "FileServerCommandFactory.java"
        },
        {
          "method": "org.eclipse.hyades.internal.collection.framework.FileClientHandlerImplExtended.run",
          "source": "FileClientHandlerImplExtended.java:76"
        },
        {
          "method": "java.lang.Thread.run",
          "source": "Thread.java:568"
        }
      ],
      "causedBy": {
        "exceptionType": "java.io.FileNotFoundException",
        "message": "/u/todd/RAC/plugins/.class (EDC5123I  Is a directory.)",
        "elements": [
          {
            "method": "java.io.FileInputStream.open",
            "source": "Native Method"
          },
          {
            "method": "java.io.FileInputStream.\u003cinit\u003e",
            "source": "FileInputStream.java:123"
          },
          {
            "method": "sun.misc.URLClassPath$7.getInputStream",
            "source": "URLClassPath.java:970"
          },
          {
            "method": "sun.misc.Resource.getBytes",
            "source": "Resource.java:74"
          },
          {
            "method": "java.net.URLClassLoader.defineClass",
            "source": "URLClassLoader.java:470"
          },
          {
            "method": "java.net.URLClassLoader.access$500",
            "source": "URLClassLoader.java:107"
          },
          {
            "method": "java.net.URLClassLoader$ClassFinder.run",
            "source": "URLClassLoader.java:844"
          }
        ],
        "number": 0,
        "commentIndex": 0
      },
      "number": 0,
      "commentIndex": 0,
      "bugId": "94176",
      "date": "2005-05-09T20:43:14+02:00",
      "product": "Hyades",
      "component": "Test.common",
      "severity": "blocker"
    }
  ],
  "groupId": "94176",
  "bugId": "94176",
  "date": "2005-05-09T20:43:14+02:00",
  "product": "Hyades",
  "component": "Test.common",
  "severity": "blocker"
}