{
  "comments": [
    "I20050510-0010\n\nWhen using eclipse with OpenSSH_3.9p1, OpenSSL 0.9.7a Feb 19 2003 on Fedora Core\n3 and using -X instead of -Y, eclipse crashes when it tries to get the mouse\npointer relative to the root window.  Using DeviceData.debug \u003d true I got the\nfollowing trace.  Commenting out the call to gdk_window_get_pointer works around\nthe issue for me.\n\norg.eclipse.swt.SWTError: Unspecified error\n        at org.eclipse.swt.graphics.Device.XErrorProc(Device.java:783)\n        at org.eclipse.swt.internal.gtk.OS._gdk_window_get_pointer(Native Method)\n        at org.eclipse.swt.internal.gtk.OS.gdk_window_get_pointer(OS.java:2940)\n        at\norg.eclipse.swt.widgets.Control.gtk_motion_notify_event(Control.java:2028)\n        at org.eclipse.swt.widgets.Widget.windowProc(Widget.java:1354)\n        at org.eclipse.swt.widgets.Display.windowProc(Display.java:3331)\n        at org.eclipse.swt.internal.gtk.OS._gtk_main_do_event(Native Method)",
    "*** Bug 104971 has been marked as a duplicate of this bug. ***",
    "Here are my observations:\n\n- Running Debian Linux box\n- Connecting from a Windows machine w/CygWin SSH and running Xming X server\n- Switched to Java 5.0\n- Now using ssh -Y\n\nWith the combination of these two changes on two different machines(both running\nDebian), I\u0027ve not been able to reproduce the\nlivelock(https://bugs.eclipse.org/bugs/show_bug.cgi?id\u003d104971)",
    "*** Bug 116543 has been marked as a duplicate of this bug. ***"
  ],
  "commentCreationDates": [
    "2005-05-10T20:56:17+02:00",
    "2005-07-25T15:18:02+02:00",
    "2005-07-28T09:33:10+02:00",
    "2005-11-16T02:36:12+01:00"
  ],
  "traces": [
    {
      "exceptionType": "org.eclipse.swt.SWTError",
      "message": "Unspecified error",
      "elements": [
        {
          "method": "org.eclipse.swt.graphics.Device.XErrorProc",
          "source": "Device.java:783"
        },
        {
          "method": "org.eclipse.swt.internal.gtk.OS._gdk_window_get_pointer",
          "source": "Native Method"
        },
        {
          "method": "org.eclipse.swt.internal.gtk.OS.gdk_window_get_pointer",
          "source": "OS.java:2940"
        },
        {
          "method": "org.eclipse.swt.widgets.Control.gtk_motion_notify_event",
          "source": "Control.java:2028"
        },
        {
          "method": "org.eclipse.swt.widgets.Widget.windowProc",
          "source": "Widget.java:1354"
        },
        {
          "method": "org.eclipse.swt.widgets.Display.windowProc",
          "source": "Display.java:3331"
        },
        {
          "method": "org.eclipse.swt.internal.gtk.OS._gtk_main_do_event",
          "source": "Native Method"
        }
      ],
      "number": 0,
      "commentIndex": 0,
      "bugId": "94477",
      "date": "2005-05-10T20:56:17+02:00",
      "product": "Platform",
      "component": "SWT",
      "severity": "normal"
    }
  ],
  "groupId": "94477",
  "bugId": "94477",
  "date": "2005-05-10T20:56:17+02:00",
  "product": "Platform",
  "component": "SWT",
  "severity": "normal"
}