{
  "comments": [
    "While using 3.1M7, I found this in my log.  I am not sure what caused it.\n\nUnable to find Action Set: org.eclipse.ui.edit.text.actionSet.newTextEditor\njava.lang.IllegalArgumentException\n        at org.eclipse.jdt.core.Signature.getReturnType(Signature.java:1595)\n        at org.eclipse.jdt.core.Signature.getReturnType(Signature.java:1611)\n        at org.eclipse.jdt.ui.JavaElementLabels.getMethodLabel(JavaElementLabels\n.java:471)\n        at org.eclipse.jdt.ui.JavaElementLabels.getElementLabel(JavaElementLabel\ns.java:386)\n        at org.eclipse.jdt.ui.JavaElementLabels.getElementLabel(JavaElementLabel\ns.java:363)\n        at org.eclipse.jdt.internal.ui.text.java.hover.JavadocHover.getInfoText(\nJavadocHover.java:143)\n        at org.eclipse.jdt.internal.ui.text.java.hover.JavadocHover.getHoverInfo\n(JavadocHover.java:119)\n        at org.eclipse.jdt.internal.ui.text.java.hover.AbstractJavaEditorTextHov\ner.getHoverInfo(AbstractJavaEditorTextHover.java:120)\n        at org.eclipse.jdt.internal.ui.text.java.hover.BestMatchHover.getHoverIn\nfo(BestMatchHover.java:102)\n        at org.eclipse.jdt.internal.ui.text.java.hover.JavaEditorTextHoverProxy.\ngetHoverInfo(JavaEditorTextHoverProxy.java:69)\n        at org.eclipse.jface.text.TextViewerHoverManager$4.run(TextViewerHoverMa\nnager.java:160)",
    "Billy, you need to rest the perspective(s): this action set which was introduced\nduring 3.1 has gone."
  ],
  "commentCreationDates": [
    "2005-05-19T00:31:45+02:00",
    "2005-05-19T08:23:32+02:00"
  ],
  "traces": [
    {
      "exceptionType": "java.lang.IllegalArgumentException",
      "elements": [
        {
          "method": "org.eclipse.jdt.core.Signature.getReturnType",
          "source": "Signature.java:1595"
        },
        {
          "method": "org.eclipse.jdt.core.Signature.getReturnType",
          "source": "Signature.java:1611"
        },
        {
          "method": "org.eclipse.jdt.ui.JavaElementLabels.getMethodLabel",
          "source": "JavaElementLabels .java:471"
        },
        {
          "method": "org.eclipse.jdt.ui.JavaElementLabels.getElementLabel",
          "source": "JavaElementLabel s.java:386"
        },
        {
          "method": "org.eclipse.jdt.ui.JavaElementLabels.getElementLabel",
          "source": "JavaElementLabel s.java:363"
        },
        {
          "method": "org.eclipse.jdt.internal.ui.text.java.hover.JavadocHover.getInfoText",
          "source": " JavadocHover.java:143"
        },
        {
          "method": "org.eclipse.jdt.internal.ui.text.java.hover.JavadocHover.getHoverInfo",
          "source": "JavadocHover.java:119"
        },
        {
          "method": "org.eclipse.jdt.internal.ui.text.java.hover.AbstractJavaEditorTextHover.getHoverInfo",
          "source": "AbstractJavaEditorTextHover.java:120"
        },
        {
          "method": "org.eclipse.jdt.internal.ui.text.java.hover.BestMatchHover.getHoverInfo",
          "source": "BestMatchHover.java:102"
        },
        {
          "method": "org.eclipse.jdt.internal.ui.text.java.hover.JavaEditorTextHoverProxy.getHoverInfo",
          "source": "JavaEditorTextHoverProxy.java:69"
        },
        {
          "method": "org.eclipse.jface.text.TextViewerHoverManager$4.run",
          "source": "TextViewerHoverMa nager.java:160"
        }
      ],
      "number": 0,
      "commentIndex": 0,
      "bugId": "95874",
      "date": "2005-05-19T00:31:45+02:00",
      "product": "JDT",
      "component": "Text",
      "severity": "normal"
    }
  ],
  "groupId": "95874",
  "bugId": "95874",
  "date": "2005-05-19T00:31:45+02:00",
  "product": "JDT",
  "component": "Text",
  "severity": "normal"
}