{
  "comments": [
    "N20050525-0010\n\nException in thread \"Text Viewer Hover Presenter\" java.lang.ClassCastException:\njava.lang.String\n        at\norg.eclipse.jdt.internal.core.SourceMapper$2.compare(SourceMapper.java:444)\n        at java.util.Arrays.mergeSort(Arrays.java:1284)\n        at java.util.Arrays.sort(Arrays.java:1223)\n        at java.util.Collections.sort(Collections.java:159)\n        at\norg.eclipse.jdt.internal.core.SourceMapper.computeAllRootPaths(SourceMapper.java:442)\n        at\norg.eclipse.jdt.internal.core.SourceMapper.findSource(SourceMapper.java:782)\n        at\norg.eclipse.jdt.internal.core.SourceMapper.findSource(SourceMapper.java:756)\n        at\norg.eclipse.jdt.internal.core.BinaryMethod.getParameterNames(BinaryMethod.java:181)\n        at\norg.eclipse.jdt.ui.JavaElementLabels.getMethodLabel(JavaElementLabels.java:493)\n        at\norg.eclipse.jdt.ui.JavaElementLabels.getElementLabel(JavaElementLabels.java:386)\n        at\norg.eclipse.jdt.ui.JavaElementLabels.getElementLabel(JavaElementLabels.java:363)\n        at\norg.eclipse.jdt.internal.ui.text.java.hover.JavadocHover.getInfoText(JavadocHover.java:142)\n        at\norg.eclipse.jdt.internal.ui.text.java.hover.JavadocHover.getHoverInfo(JavadocHover.java:118)\n        at\norg.eclipse.jdt.internal.ui.text.java.hover.AbstractJavaEditorTextHover.getHoverInfo(AbstractJavaEditorTextHover.java:120)\n        at\norg.eclipse.jdt.internal.ui.text.java.hover.BestMatchHover.getHoverInfo(BestMatchHover.java:102)\n        at\norg.eclipse.jdt.internal.ui.text.java.hover.JavaEditorTextHoverProxy.getHoverInfo(JavaEditorTextHoverProxy.java:69)\n        at\norg.eclipse.jface.text.TextViewerHoverManager$4.run(TextViewerHoverManager.java:160)",
    "I could not reproduce it.\nHowever I changed the code to only put strings into the rootPaths instance\nvariables.\nPlease reopen if you get it again.\nFixed and released in HEAD.",
    "Just another guess: Might have been a concurrency issue that\ncomputeAllRootPaths(..) has been called twice.",
    "Verified for 3.1 RC1 with build I20050527-0010.\n"
  ],
  "commentCreationDates": [
    "2005-05-25T18:50:17+02:00",
    "2005-05-25T21:13:00+02:00",
    "2005-05-26T10:06:22+02:00",
    "2005-05-27T14:27:11+02:00"
  ],
  "traces": [
    {
      "exceptionType": "java.lang.ClassCastException",
      "message": "java.lang.String",
      "elements": [
        {
          "method": "org.eclipse.jdt.internal.core.SourceMapper$2.compare",
          "source": "SourceMapper.java:444"
        },
        {
          "method": "java.util.Arrays.mergeSort",
          "source": "Arrays.java:1284"
        },
        {
          "method": "java.util.Arrays.sort",
          "source": "Arrays.java:1223"
        },
        {
          "method": "java.util.Collections.sort",
          "source": "Collections.java:159"
        },
        {
          "method": "org.eclipse.jdt.internal.core.SourceMapper.computeAllRootPaths",
          "source": "SourceMapper.java:442"
        },
        {
          "method": "org.eclipse.jdt.internal.core.SourceMapper.findSource",
          "source": "SourceMapper.java:782"
        },
        {
          "method": "org.eclipse.jdt.internal.core.SourceMapper.findSource",
          "source": "SourceMapper.java:756"
        },
        {
          "method": "org.eclipse.jdt.internal.core.BinaryMethod.getParameterNames",
          "source": "BinaryMethod.java:181"
        },
        {
          "method": "org.eclipse.jdt.ui.JavaElementLabels.getMethodLabel",
          "source": "JavaElementLabels.java:493"
        },
        {
          "method": "org.eclipse.jdt.ui.JavaElementLabels.getElementLabel",
          "source": "JavaElementLabels.java:386"
        },
        {
          "method": "org.eclipse.jdt.ui.JavaElementLabels.getElementLabel",
          "source": "JavaElementLabels.java:363"
        },
        {
          "method": "org.eclipse.jdt.internal.ui.text.java.hover.JavadocHover.getInfoText",
          "source": "JavadocHover.java:142"
        },
        {
          "method": "org.eclipse.jdt.internal.ui.text.java.hover.JavadocHover.getHoverInfo",
          "source": "JavadocHover.java:118"
        },
        {
          "method": "org.eclipse.jdt.internal.ui.text.java.hover.AbstractJavaEditorTextHover.getHoverInfo",
          "source": "AbstractJavaEditorTextHover.java:120"
        },
        {
          "method": "org.eclipse.jdt.internal.ui.text.java.hover.BestMatchHover.getHoverInfo",
          "source": "BestMatchHover.java:102"
        },
        {
          "method": "org.eclipse.jdt.internal.ui.text.java.hover.JavaEditorTextHoverProxy.getHoverInfo",
          "source": "JavaEditorTextHoverProxy.java:69"
        },
        {
          "method": "org.eclipse.jface.text.TextViewerHoverManager$4.run",
          "source": "TextViewerHoverManager.java:160"
        }
      ],
      "number": 0,
      "commentIndex": 0,
      "bugId": "96642",
      "date": "2005-05-25T18:50:17+02:00",
      "product": "JDT",
      "component": "Core",
      "severity": "normal"
    }
  ],
  "groupId": "96642",
  "bugId": "96642",
  "date": "2005-05-25T18:50:17+02:00",
  "product": "JDT",
  "component": "Core",
  "severity": "normal"
}