{
  "comments": [
    "3.1 M7 on Win XP\n\nI am trying to display or inspect a static variable on a class, something like\n\npublic class Foo {\n  public static void method() {\n    stuff.add(\"123\");\n    stuff.add(\"456\");\n  }\n  private static java.util.Vector stuff \u003d new java.util.Vector();\n}\n\nI have a breakpoint on one of the stuff.add lines.  When I attempt to display or\ninspect stuff, I get the following in the log:\n\n!ENTRY org.eclipse.debug.ui 4 120 2005-05-25 15:46:23.401\n!MESSAGE Error logged from Debug UI: \n!STACK 0\njava.lang.reflect.InvocationTargetException\n        at org.eclipse.jface.operation.ModalContext.run(ModalContext.java:327)\n        at\norg.eclipse.jface.dialogs.ProgressMonitorDialog.run(ProgressMonitorDialog.java:447)\n        at\norg.eclipse.ui.internal.progress.ProgressMonitorJobsDialog.run(ProgressMonitorJobsDialog.java:261)\n        at\norg.eclipse.ui.internal.progress.ProgressManager$3.run(ProgressManager.java:861)\n        at org.eclipse.swt.custom.BusyIndicator.showWhile(BusyIndicator.java:69)\n        at\norg.eclipse.ui.internal.progress.ProgressManager.busyCursorWhile(ProgressManager.java:895)\n        at\norg.eclipse.ui.internal.progress.ProgressManager.busyCursorWhile(ProgressManager.java:871)\n        at\norg.eclipse.jdt.internal.debug.ui.actions.EvaluateAction.run(EvaluateAction.java:275)\n        at\norg.eclipse.jdt.internal.debug.ui.actions.InspectAction.run(InspectAction.java:87)\n        at\norg.eclipse.jdt.internal.debug.ui.actions.EvaluateAction.run(EvaluateAction.java:585)\n        at org.eclipse.ui.internal.PluginAction.runWithEvent(PluginAction.java:246)\n        at\norg.eclipse.jface.action.ActionContributionItem.handleWidgetSelection(ActionContributionItem.java:538)\n        at\norg.eclipse.jface.action.ActionContributionItem.access$2(ActionContributionItem.java:488)\n        at\norg.eclipse.jface.action.ActionContributionItem$5.handleEvent(ActionContributionItem.java:400)\n        at org.eclipse.swt.widgets.EventTable.sendEvent(EventTable.java:82)\n        at org.eclipse.swt.widgets.Widget.sendEvent(Widget.java:842)\n        at org.eclipse.swt.widgets.Display.runDeferredEvents(Display.java:2921)\n        at org.eclipse.swt.widgets.Display.readAndDispatch(Display.java:2554)\n        at org.eclipse.ui.internal.Workbench.runEventLoop(Workbench.java:1601)\n        at org.eclipse.ui.internal.Workbench.runUI(Workbench.java:1565)\n        at\norg.eclipse.ui.internal.Workbench.createAndRunWorkbench(Workbench.java:315)\n        at org.eclipse.ui.PlatformUI.createAndRunWorkbench(PlatformUI.java:143)\n        at org.eclipse.ui.internal.ide.IDEApplication.run(IDEApplication.java:103)\n        at\norg.eclipse.core.internal.runtime.PlatformActivator$1.run(PlatformActivator.java:230)\n        at\norg.eclipse.core.runtime.adaptor.EclipseStarter.run(EclipseStarter.java:371)\n        at\norg.eclipse.core.runtime.adaptor.EclipseStarter.run(EclipseStarter.java:160)\n        at sun.reflect.NativeMethodAccessorImpl.invoke0(Native Method)\n        at\nsun.reflect.NativeMethodAccessorImpl.invoke(NativeMethodAccessorImpl.java:85)\n        at\nsun.reflect.NativeMethodAccessorImpl.invoke(NativeMethodAccessorImpl.java:58)\n        at\nsun.reflect.DelegatingMethodAccessorImpl.invoke(DelegatingMethodAccessorImpl.java:60)\n        at java.lang.reflect.Method.invoke(Method.java:391)\n        at org.eclipse.core.launcher.Main.invokeFramework(Main.java:330)\n        at org.eclipse.core.launcher.Main.basicRun(Main.java:274)\n        at org.eclipse.core.launcher.Main.run(Main.java:977)\n        at org.eclipse.core.launcher.Main.main(Main.java:952)\nCaused by: org.eclipse.swt.SWTException: Invalid thread access\n        at org.eclipse.swt.SWT.error(SWT.java:2940)\n        at org.eclipse.swt.SWT.error(SWT.java:2863)\n        at org.eclipse.swt.SWT.error(SWT.java:2834)\n        at org.eclipse.swt.widgets.Widget.error(Widget.java:393)\n        at org.eclipse.swt.widgets.Shell.\u003cinit\u003e(Shell.java:246)\n        at org.eclipse.swt.widgets.Shell.\u003cinit\u003e(Shell.java:324)\n        at org.eclipse.jface.window.Window.createShell(Window.java:474)\n        at org.eclipse.jface.window.Window.create(Window.java:417)\n        at org.eclipse.jface.dialogs.Dialog.create(Dialog.java:996)\n        at org.eclipse.jface.window.Window.open(Window.java:776)\n        at org.eclipse.jface.dialogs.ErrorDialog.open(ErrorDialog.java:274)\n        at org.eclipse.jface.dialogs.ErrorDialog.openError(ErrorDialog.java:338)\n        at org.eclipse.jface.dialogs.ErrorDialog.openError(ErrorDialog.java:303)\n        at\norg.eclipse.jdt.internal.debug.ui.actions.EvaluateAction.reportError(EvaluateAction.java:515)\n        at\norg.eclipse.jdt.internal.debug.ui.actions.EvaluateAction$1.run(EvaluateAction.java:262)\n        at\norg.eclipse.jface.operation.ModalContext$ModalContextThread.run(ModalContext.java:113)\nRoot exception:\norg.eclipse.swt.SWTException: Invalid thread access\n        at org.eclipse.swt.SWT.error(SWT.java:2940)\n        at org.eclipse.swt.SWT.error(SWT.java:2863)\n        at org.eclipse.swt.SWT.error(SWT.java:2834)\n        at org.eclipse.swt.widgets.Widget.error(Widget.java:393)\n        at org.eclipse.swt.widgets.Shell.\u003cinit\u003e(Shell.java:246)\n        at org.eclipse.swt.widgets.Shell.\u003cinit\u003e(Shell.java:324)\n        at org.eclipse.jface.window.Window.createShell(Window.java:474)\n        at org.eclipse.jface.window.Window.create(Window.java:417)\n        at org.eclipse.jface.dialogs.Dialog.create(Dialog.java:996)\n        at org.eclipse.jface.window.Window.open(Window.java:776)\n        at org.eclipse.jface.dialogs.ErrorDialog.open(ErrorDialog.java:274)\n        at org.eclipse.jface.dialogs.ErrorDialog.openError(ErrorDialog.java:338)\n        at org.eclipse.jface.dialogs.ErrorDialog.openError(ErrorDialog.java:303)\n        at\norg.eclipse.jdt.internal.debug.ui.actions.EvaluateAction.reportError(EvaluateAction.java:515)\n        at\norg.eclipse.jdt.internal.debug.ui.actions.EvaluateAction$1.run(EvaluateAction.java:262)\n        at\norg.eclipse.jface.operation.ModalContext$ModalContextThread.run(ModalContext.java:113)",
    "fixed the invalid thread access in EvaluateAction",
    "Darin, please verify",
    "Modified to use invocation exception to centralize cleanup.\n\nVerified."
  ],
  "commentCreationDates": [
    "2005-05-25T21:52:39+02:00",
    "2005-05-25T22:17:23+02:00",
    "2005-05-25T22:17:44+02:00",
    "2005-05-25T22:28:28+02:00"
  ],
  "traces": [
    {
      "exceptionType": "java.lang.reflect.InvocationTargetException",
      "elements": [
        {
          "method": "org.eclipse.jface.operation.ModalContext.run",
          "source": "ModalContext.java:327"
        },
        {
          "method": "org.eclipse.jface.dialogs.ProgressMonitorDialog.run",
          "source": "ProgressMonitorDialog.java:447"
        },
        {
          "method": "org.eclipse.ui.internal.progress.ProgressMonitorJobsDialog.run",
          "source": "ProgressMonitorJobsDialog.java:261"
        },
        {
          "method": "org.eclipse.ui.internal.progress.ProgressManager$3.run",
          "source": "ProgressManager.java:861"
        },
        {
          "method": "org.eclipse.swt.custom.BusyIndicator.showWhile",
          "source": "BusyIndicator.java:69"
        },
        {
          "method": "org.eclipse.ui.internal.progress.ProgressManager.busyCursorWhile",
          "source": "ProgressManager.java:895"
        },
        {
          "method": "org.eclipse.ui.internal.progress.ProgressManager.busyCursorWhile",
          "source": "ProgressManager.java:871"
        },
        {
          "method": "org.eclipse.jdt.internal.debug.ui.actions.EvaluateAction.run",
          "source": "EvaluateAction.java:275"
        },
        {
          "method": "org.eclipse.jdt.internal.debug.ui.actions.InspectAction.run",
          "source": "InspectAction.java:87"
        },
        {
          "method": "org.eclipse.jdt.internal.debug.ui.actions.EvaluateAction.run",
          "source": "EvaluateAction.java:585"
        },
        {
          "method": "org.eclipse.ui.internal.PluginAction.runWithEvent",
          "source": "PluginAction.java:246"
        },
        {
          "method": "org.eclipse.jface.action.ActionContributionItem.handleWidgetSelection",
          "source": "ActionContributionItem.java:538"
        },
        {
          "method": "org.eclipse.jface.action.ActionContributionItem.access$2",
          "source": "ActionContributionItem.java:488"
        },
        {
          "method": "org.eclipse.jface.action.ActionContributionItem$5.handleEvent",
          "source": "ActionContributionItem.java:400"
        },
        {
          "method": "org.eclipse.swt.widgets.EventTable.sendEvent",
          "source": "EventTable.java:82"
        },
        {
          "method": "org.eclipse.swt.widgets.Widget.sendEvent",
          "source": "Widget.java:842"
        },
        {
          "method": "org.eclipse.swt.widgets.Display.runDeferredEvents",
          "source": "Display.java:2921"
        },
        {
          "method": "org.eclipse.swt.widgets.Display.readAndDispatch",
          "source": "Display.java:2554"
        },
        {
          "method": "org.eclipse.ui.internal.Workbench.runEventLoop",
          "source": "Workbench.java:1601"
        },
        {
          "method": "org.eclipse.ui.internal.Workbench.runUI",
          "source": "Workbench.java:1565"
        },
        {
          "method": "org.eclipse.ui.internal.Workbench.createAndRunWorkbench",
          "source": "Workbench.java:315"
        },
        {
          "method": "org.eclipse.ui.PlatformUI.createAndRunWorkbench",
          "source": "PlatformUI.java:143"
        },
        {
          "method": "org.eclipse.ui.internal.ide.IDEApplication.run",
          "source": "IDEApplication.java:103"
        },
        {
          "method": "org.eclipse.core.internal.runtime.PlatformActivator$1.run",
          "source": "PlatformActivator.java:230"
        },
        {
          "method": "org.eclipse.core.runtime.adaptor.EclipseStarter.run",
          "source": "EclipseStarter.java:371"
        },
        {
          "method": "org.eclipse.core.runtime.adaptor.EclipseStarter.run",
          "source": "EclipseStarter.java:160"
        },
        {
          "method": "sun.reflect.NativeMethodAccessorImpl.invoke0",
          "source": "Native Method"
        },
        {
          "method": "sun.reflect.NativeMethodAccessorImpl.invoke",
          "source": "NativeMethodAccessorImpl.java:85"
        },
        {
          "method": "sun.reflect.NativeMethodAccessorImpl.invoke",
          "source": "NativeMethodAccessorImpl.java:58"
        },
        {
          "method": "sun.reflect.DelegatingMethodAccessorImpl.invoke",
          "source": "DelegatingMethodAccessorImpl.java:60"
        },
        {
          "method": "java.lang.reflect.Method.invoke",
          "source": "Method.java:391"
        },
        {
          "method": "org.eclipse.core.launcher.Main.invokeFramework",
          "source": "Main.java:330"
        },
        {
          "method": "org.eclipse.core.launcher.Main.basicRun",
          "source": "Main.java:274"
        },
        {
          "method": "org.eclipse.core.launcher.Main.run",
          "source": "Main.java:977"
        },
        {
          "method": "org.eclipse.core.launcher.Main.main",
          "source": "Main.java:952"
        }
      ],
      "causedBy": {
        "exceptionType": "org.eclipse.swt.SWTException",
        "message": "Invalid thread access",
        "elements": [
          {
            "method": "org.eclipse.swt.SWT.error",
            "source": "SWT.java:2940"
          },
          {
            "method": "org.eclipse.swt.SWT.error",
            "source": "SWT.java:2863"
          },
          {
            "method": "org.eclipse.swt.SWT.error",
            "source": "SWT.java:2834"
          },
          {
            "method": "org.eclipse.swt.widgets.Widget.error",
            "source": "Widget.java:393"
          },
          {
            "method": "org.eclipse.swt.widgets.Shell.\u003cinit\u003e",
            "source": "Shell.java:246"
          },
          {
            "method": "org.eclipse.swt.widgets.Shell.\u003cinit\u003e",
            "source": "Shell.java:324"
          },
          {
            "method": "org.eclipse.jface.window.Window.createShell",
            "source": "Window.java:474"
          },
          {
            "method": "org.eclipse.jface.window.Window.create",
            "source": "Window.java:417"
          },
          {
            "method": "org.eclipse.jface.dialogs.Dialog.create",
            "source": "Dialog.java:996"
          },
          {
            "method": "org.eclipse.jface.window.Window.open",
            "source": "Window.java:776"
          },
          {
            "method": "org.eclipse.jface.dialogs.ErrorDialog.open",
            "source": "ErrorDialog.java:274"
          },
          {
            "method": "org.eclipse.jface.dialogs.ErrorDialog.openError",
            "source": "ErrorDialog.java:338"
          },
          {
            "method": "org.eclipse.jface.dialogs.ErrorDialog.openError",
            "source": "ErrorDialog.java:303"
          },
          {
            "method": "org.eclipse.jdt.internal.debug.ui.actions.EvaluateAction.reportError",
            "source": "EvaluateAction.java:515"
          },
          {
            "method": "org.eclipse.jdt.internal.debug.ui.actions.EvaluateAction$1.run",
            "source": "EvaluateAction.java:262"
          },
          {
            "method": "org.eclipse.jface.operation.ModalContext$ModalContextThread.run",
            "source": "ModalContext.java:113"
          }
        ],
        "number": 0,
        "commentIndex": 0
      },
      "number": 0,
      "commentIndex": 0,
      "bugId": "96693",
      "date": "2005-05-25T21:52:39+02:00",
      "product": "JDT",
      "component": "Debug",
      "severity": "normal"
    },
    {
      "exceptionType": "org.eclipse.swt.SWTException",
      "message": "Invalid thread access",
      "elements": [
        {
          "method": "org.eclipse.swt.SWT.error",
          "source": "SWT.java:2940"
        },
        {
          "method": "org.eclipse.swt.SWT.error",
          "source": "SWT.java:2863"
        },
        {
          "method": "org.eclipse.swt.SWT.error",
          "source": "SWT.java:2834"
        },
        {
          "method": "org.eclipse.swt.widgets.Widget.error",
          "source": "Widget.java:393"
        },
        {
          "method": "org.eclipse.swt.widgets.Shell.\u003cinit\u003e",
          "source": "Shell.java:246"
        },
        {
          "method": "org.eclipse.swt.widgets.Shell.\u003cinit\u003e",
          "source": "Shell.java:324"
        },
        {
          "method": "org.eclipse.jface.window.Window.createShell",
          "source": "Window.java:474"
        },
        {
          "method": "org.eclipse.jface.window.Window.create",
          "source": "Window.java:417"
        },
        {
          "method": "org.eclipse.jface.dialogs.Dialog.create",
          "source": "Dialog.java:996"
        },
        {
          "method": "org.eclipse.jface.window.Window.open",
          "source": "Window.java:776"
        },
        {
          "method": "org.eclipse.jface.dialogs.ErrorDialog.open",
          "source": "ErrorDialog.java:274"
        },
        {
          "method": "org.eclipse.jface.dialogs.ErrorDialog.openError",
          "source": "ErrorDialog.java:338"
        },
        {
          "method": "org.eclipse.jface.dialogs.ErrorDialog.openError",
          "source": "ErrorDialog.java:303"
        },
        {
          "method": "org.eclipse.jdt.internal.debug.ui.actions.EvaluateAction.reportError",
          "source": "EvaluateAction.java:515"
        },
        {
          "method": "org.eclipse.jdt.internal.debug.ui.actions.EvaluateAction$1.run",
          "source": "EvaluateAction.java:262"
        },
        {
          "method": "org.eclipse.jface.operation.ModalContext$ModalContextThread.run",
          "source": "ModalContext.java:113"
        }
      ],
      "number": 1,
      "commentIndex": 0,
      "bugId": "96693",
      "date": "2005-05-25T21:52:39+02:00",
      "product": "JDT",
      "component": "Debug",
      "severity": "normal"
    }
  ],
  "groupId": "96693",
  "bugId": "96693",
  "date": "2005-05-25T21:52:39+02:00",
  "product": "JDT",
  "component": "Debug",
  "severity": "normal"
}