{
  "comments": [
    "It is possible to get TreeSet\u003cT\u003e.contains(T t) to throw an  \nAbstractMethodError. This occurs on code compiled by Eclipse 3.1.M7 but not  \nfor code compiled by Sun 1.5.0_03 JDK. Can provide code for simple test case  \nif required; however code is roughly as follows:  \n1. Create an interface \u0027Thing\u0027 which extends Comparable\u003cThing\u003e.  \n2. Create an implementation of \u0027Thing\u0027, \u0027ThingImpl\u0027 say which provides an  \n   an implementation of \u0027int compareTo(Thing t)\u0027.  \n3. Create (in a JUnit test case, say) a TreeSet\u003cThing\u003e, create an instance of  \n   ThingImpl and add to the TreeSet.  \n4. Call \u0027contains()\u0027 on the TreeSet, passing the ThingImpl instance previously   \n   added to the set. This should throw an AbstractMethodError with a stack   \n   trace something like below. As stated previously, this does not occur with   \n   code compiled under Sun JDK 1.5.0_03 but does on code compiled by Eclipse   \n   3.1M7. Also occurs when running Eclipse-generated code under Sun JDK so   \n   looks like an Eclipse compiler problem.  \n  \njava.lang.AbstractMethodError: ThingImpl.compareTo(Ljava/lang/Object;)I  \n\tat java.util.TreeMap.compare(TreeMap.java:1093)  \n\tat java.util.TreeMap.getEntry(TreeMap.java:347)  \n\tat java.util.TreeMap.containsKey(TreeMap.java:204)  \n\tat java.util.TreeSet.contains(TreeSet.java:196)  \n\tat ThingTest.testIt(ThingTest.java:24)  \n\tat sun.reflect.NativeMethodAccessorImpl.invoke0(Native Method)  \n\tat  \nsun.reflect.NativeMethodAccessorImpl.invoke(NativeMethodAccessorImpl.java:39)  \n\tat  \nsun.reflect.DelegatingMethodAccessorImpl.invoke(DelegatingMethodAccessorImpl.java:25)  \n\tat java.lang.reflect.Method.invoke(Method.java:585)  \n\tat junit.framework.TestCase.runTest(TestCase.java:154)  \n\tat junit.framework.TestCase.runBare(TestCase.java:127)  \n\tat junit.framework.TestResult$1.protect(TestResult.java:106)  \n\tat junit.framework.TestResult.runProtected(TestResult.java:124)  \n\tat junit.framework.TestResult.run(TestResult.java:109)  \n\tat junit.framework.TestCase.run(TestCase.java:118)  \n\tat junit.framework.TestSuite.runTest(TestSuite.java:208)  \n\tat junit.framework.TestSuite.run(TestSuite.java:203)  \n\tat  \norg.eclipse.jdt.internal.junit.runner.RemoteTestRunner.runTests(RemoteTestRunner.java:474)  \n\tat  \norg.eclipse.jdt.internal.junit.runner.RemoteTestRunner.run(RemoteTestRunner.java:342)  \n\tat  \norg.eclipse.jdt.internal.junit.runner.RemoteTestRunner.main(RemoteTestRunner.java:194)",
    "Created an attachment (id\u003d21804)\nTest case for reporducing problem.\n",
    "This works for me with the latest.\n\nPlease double check with RC1 \u0026 reopen if it fails for you."
  ],
  "commentCreationDates": [
    "2005-05-26T12:24:40+02:00",
    "2005-05-26T12:36:38+02:00",
    "2005-05-26T18:28:55+02:00"
  ],
  "traces": [
    {
      "exceptionType": "java.lang.AbstractMethodError",
      "message": "ThingImpl.compareTo(Ljava/lang/Object;)I",
      "elements": [
        {
          "method": "java.util.TreeMap.compare",
          "source": "TreeMap.java:1093"
        },
        {
          "method": "java.util.TreeMap.getEntry",
          "source": "TreeMap.java:347"
        },
        {
          "method": "java.util.TreeMap.containsKey",
          "source": "TreeMap.java:204"
        },
        {
          "method": "java.util.TreeSet.contains",
          "source": "TreeSet.java:196"
        },
        {
          "method": "ThingTest.testIt",
          "source": "ThingTest.java:24"
        },
        {
          "method": "sun.reflect.NativeMethodAccessorImpl.invoke0",
          "source": "Native Method"
        },
        {
          "method": "sun.reflect.NativeMethodAccessorImpl.invoke",
          "source": "NativeMethodAccessorImpl.java:39"
        },
        {
          "method": "sun.reflect.DelegatingMethodAccessorImpl.invoke",
          "source": "DelegatingMethodAccessorImpl.java:25"
        },
        {
          "method": "java.lang.reflect.Method.invoke",
          "source": "Method.java:585"
        },
        {
          "method": "junit.framework.TestCase.runTest",
          "source": "TestCase.java:154"
        },
        {
          "method": "junit.framework.TestCase.runBare",
          "source": "TestCase.java:127"
        },
        {
          "method": "junit.framework.TestResult$1.protect",
          "source": "TestResult.java:106"
        },
        {
          "method": "junit.framework.TestResult.runProtected",
          "source": "TestResult.java:124"
        },
        {
          "method": "junit.framework.TestResult.run",
          "source": "TestResult.java:109"
        },
        {
          "method": "junit.framework.TestCase.run",
          "source": "TestCase.java:118"
        },
        {
          "method": "junit.framework.TestSuite.runTest",
          "source": "TestSuite.java:208"
        },
        {
          "method": "junit.framework.TestSuite.run",
          "source": "TestSuite.java:203"
        },
        {
          "method": "org.eclipse.jdt.internal.junit.runner.RemoteTestRunner.runTests",
          "source": "RemoteTestRunner.java:474"
        },
        {
          "method": "org.eclipse.jdt.internal.junit.runner.RemoteTestRunner.run",
          "source": "RemoteTestRunner.java:342"
        },
        {
          "method": "org.eclipse.jdt.internal.junit.runner.RemoteTestRunner.main",
          "source": "RemoteTestRunner.java:194"
        }
      ],
      "number": 0,
      "commentIndex": 0,
      "bugId": "96760",
      "date": "2005-05-26T12:24:40+02:00",
      "product": "JDT",
      "component": "Core",
      "severity": "major"
    }
  ],
  "groupId": "96760",
  "bugId": "96760",
  "date": "2005-05-26T12:24:40+02:00",
  "product": "JDT",
  "component": "Core",
  "severity": "major"
}