{
  "comments": [
    "N20050526-0010\n\nIn a new workspace, I added all plugins to Java Search. Then I hit Ctrl+Shift+T.\nAfter the indexes were built and I started typing, a job error message came up:\n\n!ENTRY org.eclipse.core.runtime 4 2 2005-05-26 17:30:20.949\n!MESSAGE An internal error occurred during: \"Searching for all types\".\n!STACK 0\norg.eclipse.swt.SWTException: Invalid thread access\n        at org.eclipse.swt.SWT.error(SWT.java:2940)\n        at org.eclipse.swt.SWT.error(SWT.java:2863)\n        at org.eclipse.swt.SWT.error(SWT.java:2834)\n        at org.eclipse.swt.widgets.Display.error(Display.java:784)\n        at org.eclipse.swt.widgets.Display.checkDevice(Display.java:613)\n        at org.eclipse.swt.widgets.Display.disposeExec(Display.java:729)\n        at\norg.eclipse.jdt.internal.ui.viewsupport.ImageDescriptorRegistry.hookDisplay(ImageDescriptorRegistry.java:85)\n        at\norg.eclipse.jdt.internal.ui.viewsupport.ImageDescriptorRegistry.\u003cinit\u003e(ImageDescriptorRegistry.java:48)\n        at\norg.eclipse.jdt.internal.ui.viewsupport.ImageDescriptorRegistry.\u003cinit\u003e(ImageDescriptorRegistry.java:36)\n        at\norg.eclipse.jdt.internal.ui.JavaPlugin.internalGetImageDescriptorRegistry(JavaPlugin.java:790)\n        at\norg.eclipse.jdt.internal.ui.JavaPlugin.getImageDescriptorRegistry(JavaPlugin.java:342)\n        at\norg.eclipse.jdt.internal.ui.dialogs.TypeInfoViewer$TypeInfoLabelProvider.getImage(TypeInfoViewer.java:333)\n        at\norg.eclipse.jdt.internal.ui.dialogs.TypeInfoViewer$AbstractSearchJob.internalRun(TypeInfoViewer.java:552)\n        at\norg.eclipse.jdt.internal.ui.dialogs.TypeInfoViewer$AbstractSearchJob.doRun(TypeInfoViewer.java:473)\n        at\norg.eclipse.jdt.internal.ui.dialogs.TypeInfoViewer$AbstractJob.run(TypeInfoViewer.java:439)\n        at org.eclipse.core.internal.jobs.Worker.run(Worker.java:67)",
    "I did never show the Java Perspective. To reproduce, you have to switch to the\nDebug perspective (original layout). Then restart eclipse and run \u0027Open Type\u0027.",
    "Fix is trivial. I have to dummy access the registry in the UI thread to make\nsure it is populated.",
    "*** Bug 96870 has been marked as a duplicate of this bug. ***",
    "As said fix is easy. Will attach a patch and we should consider fixing this for RC1.",
    "Created an attachment (id\u003d21864)\nPatch\n",
    "Fixed for RC1.",
    "Verified in I20050527-0900."
  ],
  "commentCreationDates": [
    "2005-05-26T17:36:29+02:00",
    "2005-05-26T17:41:47+02:00",
    "2005-05-26T19:11:38+02:00",
    "2005-05-26T23:51:29+02:00",
    "2005-05-27T00:54:21+02:00",
    "2005-05-27T00:54:59+02:00",
    "2005-05-27T16:17:36+02:00",
    "2005-05-27T19:44:35+02:00"
  ],
  "traces": [
    {
      "exceptionType": "org.eclipse.swt.SWTException",
      "message": "Invalid thread access",
      "elements": [
        {
          "method": "org.eclipse.swt.SWT.error",
          "source": "SWT.java:2940"
        },
        {
          "method": "org.eclipse.swt.SWT.error",
          "source": "SWT.java:2863"
        },
        {
          "method": "org.eclipse.swt.SWT.error",
          "source": "SWT.java:2834"
        },
        {
          "method": "org.eclipse.swt.widgets.Display.error",
          "source": "Display.java:784"
        },
        {
          "method": "org.eclipse.swt.widgets.Display.checkDevice",
          "source": "Display.java:613"
        },
        {
          "method": "org.eclipse.swt.widgets.Display.disposeExec",
          "source": "Display.java:729"
        },
        {
          "method": "org.eclipse.jdt.internal.ui.viewsupport.ImageDescriptorRegistry.hookDisplay",
          "source": "ImageDescriptorRegistry.java:85"
        },
        {
          "method": "org.eclipse.jdt.internal.ui.viewsupport.ImageDescriptorRegistry.\u003cinit\u003e",
          "source": "ImageDescriptorRegistry.java:48"
        },
        {
          "method": "org.eclipse.jdt.internal.ui.viewsupport.ImageDescriptorRegistry.\u003cinit\u003e",
          "source": "ImageDescriptorRegistry.java:36"
        },
        {
          "method": "org.eclipse.jdt.internal.ui.JavaPlugin.internalGetImageDescriptorRegistry",
          "source": "JavaPlugin.java:790"
        },
        {
          "method": "org.eclipse.jdt.internal.ui.JavaPlugin.getImageDescriptorRegistry",
          "source": "JavaPlugin.java:342"
        },
        {
          "method": "org.eclipse.jdt.internal.ui.dialogs.TypeInfoViewer$TypeInfoLabelProvider.getImage",
          "source": "TypeInfoViewer.java:333"
        },
        {
          "method": "org.eclipse.jdt.internal.ui.dialogs.TypeInfoViewer$AbstractSearchJob.internalRun",
          "source": "TypeInfoViewer.java:552"
        },
        {
          "method": "org.eclipse.jdt.internal.ui.dialogs.TypeInfoViewer$AbstractSearchJob.doRun",
          "source": "TypeInfoViewer.java:473"
        },
        {
          "method": "org.eclipse.jdt.internal.ui.dialogs.TypeInfoViewer$AbstractJob.run",
          "source": "TypeInfoViewer.java:439"
        },
        {
          "method": "org.eclipse.core.internal.jobs.Worker.run",
          "source": "Worker.java:67"
        }
      ],
      "number": 0,
      "commentIndex": 0,
      "bugId": "96814",
      "date": "2005-05-26T17:36:29+02:00",
      "product": "JDT",
      "component": "UI",
      "severity": "critical"
    }
  ],
  "groupId": "96814",
  "bugId": "96814",
  "date": "2005-05-26T17:36:29+02:00",
  "product": "JDT",
  "component": "UI",
  "severity": "critical"
}