{
  "comments": [
    "I20050527-0010\n\nUnfortunately I cannot give more concrete steps to reproduce. Just saw this in \nthe log:\n\njava.lang.NullPointerException\n        at \norg.eclipse.jdt.internal.compiler.parser.SourceTypeConverter.parseMemberValue\n(SourceTypeConverter.java:811)\n        at \norg.eclipse.jdt.internal.compiler.parser.SourceTypeConverter.convertAnnotations\n(SourceTypeConverter.java:563)\n\n        at org.eclipse.jdt.internal.compiler.parser.SourceTypeConverter.convert\n(SourceTypeConverter.java:435)\n        at org.eclipse.jdt.internal.compiler.parser.SourceTypeConverter.convert\n(SourceTypeConverter.java:165)\n        at \norg.eclipse.jdt.internal.compiler.parser.SourceTypeConverter.buildCompilationUn\nit(SourceTypeConverter.java:10\n8)\n        at org.eclipse.jdt.internal.core.hierarchy.HierarchyResolver.resolve\n(HierarchyResolver.java:565)\n        at org.eclipse.jdt.internal.core.hierarchy.HierarchyResolver.resolve\n(HierarchyResolver.java:486)\n        at \norg.eclipse.jdt.internal.core.hierarchy.HierarchyBuilder.buildSupertypes\n(HierarchyBuilder.java:119)\n        at \norg.eclipse.jdt.internal.core.hierarchy.IndexBasedHierarchyBuilder.build\n(IndexBasedHierarchyBuilder.java:136)\n\n        at org.eclipse.jdt.internal.core.hierarchy.TypeHierarchy.compute\n(TypeHierarchy.java:320)\n        at org.eclipse.jdt.internal.core.hierarchy.TypeHierarchy.refresh\n(TypeHierarchy.java:1255)\n        at \norg.eclipse.jdt.internal.core.CreateTypeHierarchyOperation.executeOperation\n(CreateTypeHierarchyOperation.java\n:90)\n        at org.eclipse.jdt.internal.core.JavaModelOperation.run\n(JavaModelOperation.java:718)\n        at org.eclipse.jdt.internal.core.JavaModelOperation.runOperation\n(JavaModelOperation.java:777)\n        at org.eclipse.jdt.internal.core.SourceType.newSupertypeHierarchy\n(SourceType.java:671)\n        at org.eclipse.jdt.internal.core.SourceType.newSupertypeHierarchy\n(SourceType.java:623)\n        at \norg.eclipse.jdt.internal.corext.util.SuperTypeHierarchyCache.getTypeHierarchy\n(SuperTypeHierarchyCache.java:88\n)\n        at \norg.eclipse.jdt.internal.corext.util.SuperTypeHierarchyCache.getTypeHierarchy\n(SuperTypeHierarchyCache.java:78\n)\n        at \norg.eclipse.jdt.ui.OverrideIndicatorLabelDecorator.getOverrideIndicators\n(OverrideIndicatorLabelDecorator.java\n:160)\n        at \norg.eclipse.jdt.ui.OverrideIndicatorLabelDecorator.computeAdornmentFlags\n(OverrideIndicatorLabelDecorator.java\n:128)\n        at org.eclipse.jdt.ui.OverrideIndicatorLabelDecorator.decorate\n(OverrideIndicatorLabelDecorator.java:251)\n        at \norg.eclipse.ui.internal.decorators.LightweightDecoratorDefinition.decorate\n(LightweightDecoratorDefinition.jav\na:220)\n        at \norg.eclipse.ui.internal.decorators.LightweightDecoratorManager$LightweightRunna\nble.run(LightweightDecoratorMa\nnager.java:67)\n        at org.eclipse.core.internal.runtime.InternalPlatform.run\n(InternalPlatform.java:1038)\n        at org.eclipse.core.runtime.Platform.run(Platform.java:775)\n        at \norg.eclipse.ui.internal.decorators.LightweightDecoratorManager.decorate\n(LightweightDecoratorManager.java:289)\n\n        at \norg.eclipse.ui.internal.decorators.LightweightDecoratorManager.getDecorations\n(LightweightDecoratorManager.jav\na:275)\n        at org.eclipse.ui.internal.decorators.DecorationScheduler$1.run\n(DecorationScheduler.java:318)\n        at org.eclipse.core.internal.jobs.Worker.run(Worker.java:67)",
    "The NPE can happen only if the field \u0027parser\u0027 is null. Howver it is set to a\nnon-null value 2 lines above, and no other code would set it to null.\nSuspecting a VM problem. What VM are you runinng Eclipse on ?",
    "I was running in an old test workspace with an old vm:\n\njava.fullversion\u003dJ2RE 1.4.2 IBM J9 2.2 Windows XP x86-32 j9n142-20040831 (JIT \nenabled)\nJ9VM - 20040827_2136_lHdSMR\nJIT  - r7_level20040827_1801\n\nIf the other candidates (memberValue and this.unit) are guaranteed to be non-\nnull, close the bug",
    "\u0027memberValue\u0027 and \u0027this.unit\u0027 could not cause a NPE on this line.\nClosing as VM bug.",
    "It happened again in 3.2 RC4 (see bug 142506). After a second look at the code, the NPE can happen if \u0027memberValue\u0027 is null since we\u0027re getting its length.\n\nReopening",
    "*** Bug 150520 has been marked as a duplicate of this bug. ***",
    "This looks like the same bug as this https://bugs.eclipse.org/bugs/show_bug.cgi?id\u003d168088\n\nthe line numbers changed but the call chain is the same",
    "Thanks Scott. This indeed looks like a dup.\n\n*** This bug has been marked as a duplicate of bug 168088 ***"
  ],
  "commentCreationDates": [
    "2005-05-27T16:26:11+02:00",
    "2005-05-27T16:34:49+02:00",
    "2005-05-27T16:42:13+02:00",
    "2005-05-27T17:06:02+02:00",
    "2006-05-19T16:50:25+02:00",
    "2006-07-18T12:49:32+02:00",
    "2007-05-14T22:24:22+02:00",
    "2007-05-15T11:08:00+02:00"
  ],
  "traces": [
    {
      "exceptionType": "java.lang.NullPointerException",
      "elements": [
        {
          "method": "org.eclipse.jdt.internal.compiler.parser.SourceTypeConverter.parseMemberValue",
          "source": "SourceTypeConverter.java:811"
        },
        {
          "method": "org.eclipse.jdt.internal.compiler.parser.SourceTypeConverter.convertAnnotations",
          "source": "SourceTypeConverter.java:563"
        },
        {
          "method": "org.eclipse.jdt.internal.compiler.parser.SourceTypeConverter.convert",
          "source": "SourceTypeConverter.java:435"
        },
        {
          "method": "org.eclipse.jdt.internal.compiler.parser.SourceTypeConverter.convert",
          "source": "SourceTypeConverter.java:165"
        },
        {
          "method": "org.eclipse.jdt.internal.compiler.parser.SourceTypeConverter.buildCompilationUnit",
          "source": "SourceTypeConverter.java:10 8"
        },
        {
          "method": "org.eclipse.jdt.internal.core.hierarchy.HierarchyResolver.resolve",
          "source": "HierarchyResolver.java:565"
        },
        {
          "method": "org.eclipse.jdt.internal.core.hierarchy.HierarchyResolver.resolve",
          "source": "HierarchyResolver.java:486"
        },
        {
          "method": "org.eclipse.jdt.internal.core.hierarchy.HierarchyBuilder.buildSupertypes",
          "source": "HierarchyBuilder.java:119"
        },
        {
          "method": "org.eclipse.jdt.internal.core.hierarchy.IndexBasedHierarchyBuilder.build",
          "source": "IndexBasedHierarchyBuilder.java:136"
        },
        {
          "method": "org.eclipse.jdt.internal.core.hierarchy.TypeHierarchy.compute",
          "source": "TypeHierarchy.java:320"
        },
        {
          "method": "org.eclipse.jdt.internal.core.hierarchy.TypeHierarchy.refresh",
          "source": "TypeHierarchy.java:1255"
        },
        {
          "method": "org.eclipse.jdt.internal.core.CreateTypeHierarchyOperation.executeOperation",
          "source": "CreateTypeHierarchyOperation.java :90"
        },
        {
          "method": "org.eclipse.jdt.internal.core.JavaModelOperation.run",
          "source": "JavaModelOperation.java:718"
        },
        {
          "method": "org.eclipse.jdt.internal.core.JavaModelOperation.runOperation",
          "source": "JavaModelOperation.java:777"
        },
        {
          "method": "org.eclipse.jdt.internal.core.SourceType.newSupertypeHierarchy",
          "source": "SourceType.java:671"
        },
        {
          "method": "org.eclipse.jdt.internal.core.SourceType.newSupertypeHierarchy",
          "source": "SourceType.java:623"
        },
        {
          "method": "org.eclipse.jdt.internal.corext.util.SuperTypeHierarchyCache.getTypeHierarchy",
          "source": "SuperTypeHierarchyCache.java:88 "
        },
        {
          "method": "org.eclipse.jdt.internal.corext.util.SuperTypeHierarchyCache.getTypeHierarchy",
          "source": "SuperTypeHierarchyCache.java:78 "
        },
        {
          "method": "org.eclipse.jdt.ui.OverrideIndicatorLabelDecorator.getOverrideIndicators",
          "source": "OverrideIndicatorLabelDecorator.java :160"
        },
        {
          "method": "org.eclipse.jdt.ui.OverrideIndicatorLabelDecorator.computeAdornmentFlags",
          "source": "OverrideIndicatorLabelDecorator.java :128"
        },
        {
          "method": "org.eclipse.jdt.ui.OverrideIndicatorLabelDecorator.decorate",
          "source": "OverrideIndicatorLabelDecorator.java:251"
        },
        {
          "method": "org.eclipse.ui.internal.decorators.LightweightDecoratorDefinition.decorate",
          "source": "LightweightDecoratorDefinition.jav a:220"
        },
        {
          "method": "org.eclipse.ui.internal.decorators.LightweightDecoratorManager$LightweightRunnable.run",
          "source": "LightweightDecoratorMa nager.java:67"
        },
        {
          "method": "org.eclipse.core.internal.runtime.InternalPlatform.run",
          "source": "InternalPlatform.java:1038"
        },
        {
          "method": "org.eclipse.core.runtime.Platform.run",
          "source": "Platform.java:775"
        },
        {
          "method": "org.eclipse.ui.internal.decorators.LightweightDecoratorManager.decorate",
          "source": "LightweightDecoratorManager.java:289"
        },
        {
          "method": "org.eclipse.ui.internal.decorators.LightweightDecoratorManager.getDecorations",
          "source": "LightweightDecoratorManager.jav a:275"
        },
        {
          "method": "org.eclipse.ui.internal.decorators.DecorationScheduler$1.run",
          "source": "DecorationScheduler.java:318"
        },
        {
          "method": "org.eclipse.core.internal.jobs.Worker.run",
          "source": "Worker.java:67"
        }
      ],
      "number": 0,
      "commentIndex": 0,
      "bugId": "96984",
      "duplicateId": "168088",
      "date": "2005-05-27T16:26:11+02:00",
      "product": "JDT",
      "component": "Core",
      "severity": "normal"
    }
  ],
  "groupId": "168088",
  "bugId": "96984",
  "duplicateId": "168088",
  "date": "2005-05-27T16:26:11+02:00",
  "product": "JDT",
  "component": "Core",
  "severity": "normal"
}