{
  "comments": [
    "the following kind of messages is very often in my log, i\u0027m not sure but the last time it \nhappend the shortcuts stopped working repeatedly (the stop very, very often) -- maybe \nthere\u0027s a tie-in.\n\n!ENTRY org.eclipse.debug.core 4 120 2005-05-29 18:41:23.362\n!MESSAGE Error logged from Debug Core:\n!STACK 0\njava.io.IOException: read error\n        at org.eclipse.cdt.utils.spawner.SpawnerInputStream.read0(Native Method)\n        at org.eclipse.cdt.utils.spawner.SpawnerInputStream.read(SpawnerInputStream.\njava:60)\n        at java.io.BufferedInputStream.read1(BufferedInputStream.java:254)\n        at java.io.BufferedInputStream.read(BufferedInputStream.java:313)\n        at java.io.FilterInputStream.read(FilterInputStream.java:90)\n        at org.eclipse.debug.internal.core.OutputStreamMonitor.\nread(OutputStreamMonitor.java:135)\n        at org.eclipse.debug.internal.core.OutputStreamMonitor.\naccess$1(OutputStreamMonitor.java:126)\n        at org.eclipse.debug.internal.core.OutputStreamMonitor$1.\nrun(OutputStreamMonitor.java:193)\n        at java.lang.Thread.run(Thread.java:595)\n\n!ENTRY org.eclipse.debug.core 4 120 2005-05-29 18:41:23.463\n!MESSAGE Error logged from Debug Core:\n!STACK 0\njava.io.IOException: close error\n        at org.eclipse.cdt.utils.spawner.SpawnerOutputStream.\nclose(SpawnerOutputStream.java:68)\n        at org.eclipse.debug.internal.core.InputStreamMonitor.write(InputStreamMonitor.\njava:109)\n        at org.eclipse.debug.internal.core.InputStreamMonitor$1.run(InputStreamMonitor.\njava:80)\n        at java.lang.Thread.run(Thread.java:595)\n\n!ENTRY org.eclipse.debug.core 4 120 2005-05-29 18:42:07.707\n!MESSAGE Error logged from Debug Core:\n!STACK 0\njava.io.IOException: read error\n        at org.eclipse.cdt.utils.spawner.SpawnerInputStream.read0(Native Method)\n        at org.eclipse.cdt.utils.spawner.SpawnerInputStream.read(SpawnerInputStream.\njava:60)\n        at java.io.BufferedInputStream.read1(BufferedInputStream.java:254)\n        at java.io.BufferedInputStream.read(BufferedInputStream.java:313)\n        at java.io.FilterInputStream.read(FilterInputStream.java:90)\n        at org.eclipse.debug.internal.core.OutputStreamMonitor.\nread(OutputStreamMonitor.java:135)\n        at org.eclipse.debug.internal.core.OutputStreamMonitor.\naccess$1(OutputStreamMonitor.java:126)\n        at org.eclipse.debug.internal.core.OutputStreamMonitor$1.\nrun(OutputStreamMonitor.java:193)\n        at java.lang.Thread.run(Thread.java:595)\n\n!ENTRY org.eclipse.debug.core 4 120 2005-05-29 18:42:07.715\n!MESSAGE Error logged from Debug Core:\n!STACK 0\njava.io.IOException: close error\n        at org.eclipse.cdt.utils.spawner.SpawnerOutputStream.\nclose(SpawnerOutputStream.java:68)\n        at org.eclipse.debug.internal.core.InputStreamMonitor.write(InputStreamMonitor.\njava:109)\n        at org.eclipse.debug.internal.core.InputStreamMonitor$1.run(InputStreamMonitor.\njava:80)\n        at java.lang.Thread.run(Thread.java:595)"
  ],
  "commentCreationDates": [
    "2005-05-30T10:26:47+02:00"
  ],
  "traces": [
    {
      "exceptionType": "java.io.IOException",
      "message": "read error",
      "elements": [
        {
          "method": "org.eclipse.cdt.utils.spawner.SpawnerInputStream.read0",
          "source": "Native Method"
        },
        {
          "method": "org.eclipse.cdt.utils.spawner.SpawnerInputStream.read",
          "source": "SpawnerInputStream. java:60"
        },
        {
          "method": "java.io.BufferedInputStream.read1",
          "source": "BufferedInputStream.java:254"
        },
        {
          "method": "java.io.BufferedInputStream.read",
          "source": "BufferedInputStream.java:313"
        },
        {
          "method": "java.io.FilterInputStream.read",
          "source": "FilterInputStream.java:90"
        },
        {
          "method": "org.eclipse.debug.internal.core.OutputStreamMonitor.read",
          "source": "OutputStreamMonitor.java:135"
        },
        {
          "method": "org.eclipse.debug.internal.core.OutputStreamMonitor.access$1",
          "source": "OutputStreamMonitor.java:126"
        },
        {
          "method": "org.eclipse.debug.internal.core.OutputStreamMonitor$1.run",
          "source": "OutputStreamMonitor.java:193"
        },
        {
          "method": "java.lang.Thread.run",
          "source": "Thread.java:595"
        }
      ],
      "number": 0,
      "commentIndex": 0,
      "bugId": "97178",
      "date": "2005-05-30T10:26:47+02:00",
      "product": "CDT",
      "component": "cdt-core",
      "severity": "normal"
    },
    {
      "exceptionType": "java.io.IOException",
      "message": "close error",
      "elements": [
        {
          "method": "org.eclipse.cdt.utils.spawner.SpawnerOutputStream.close",
          "source": "SpawnerOutputStream.java:68"
        },
        {
          "method": "org.eclipse.debug.internal.core.InputStreamMonitor.write",
          "source": "InputStreamMonitor. java:109"
        },
        {
          "method": "org.eclipse.debug.internal.core.InputStreamMonitor$1.run",
          "source": "InputStreamMonitor. java:80"
        },
        {
          "method": "java.lang.Thread.run",
          "source": "Thread.java:595"
        }
      ],
      "number": 1,
      "commentIndex": 0,
      "bugId": "97178",
      "date": "2005-05-30T10:26:47+02:00",
      "product": "CDT",
      "component": "cdt-core",
      "severity": "normal"
    },
    {
      "exceptionType": "java.io.IOException",
      "message": "read error",
      "elements": [
        {
          "method": "org.eclipse.cdt.utils.spawner.SpawnerInputStream.read0",
          "source": "Native Method"
        },
        {
          "method": "org.eclipse.cdt.utils.spawner.SpawnerInputStream.read",
          "source": "SpawnerInputStream. java:60"
        },
        {
          "method": "java.io.BufferedInputStream.read1",
          "source": "BufferedInputStream.java:254"
        },
        {
          "method": "java.io.BufferedInputStream.read",
          "source": "BufferedInputStream.java:313"
        },
        {
          "method": "java.io.FilterInputStream.read",
          "source": "FilterInputStream.java:90"
        },
        {
          "method": "org.eclipse.debug.internal.core.OutputStreamMonitor.read",
          "source": "OutputStreamMonitor.java:135"
        },
        {
          "method": "org.eclipse.debug.internal.core.OutputStreamMonitor.access$1",
          "source": "OutputStreamMonitor.java:126"
        },
        {
          "method": "org.eclipse.debug.internal.core.OutputStreamMonitor$1.run",
          "source": "OutputStreamMonitor.java:193"
        },
        {
          "method": "java.lang.Thread.run",
          "source": "Thread.java:595"
        }
      ],
      "number": 2,
      "commentIndex": 0,
      "bugId": "97178",
      "date": "2005-05-30T10:26:47+02:00",
      "product": "CDT",
      "component": "cdt-core",
      "severity": "normal"
    },
    {
      "exceptionType": "java.io.IOException",
      "message": "close error",
      "elements": [
        {
          "method": "org.eclipse.cdt.utils.spawner.SpawnerOutputStream.close",
          "source": "SpawnerOutputStream.java:68"
        },
        {
          "method": "org.eclipse.debug.internal.core.InputStreamMonitor.write",
          "source": "InputStreamMonitor. java:109"
        },
        {
          "method": "org.eclipse.debug.internal.core.InputStreamMonitor$1.run",
          "source": "InputStreamMonitor. java:80"
        },
        {
          "method": "java.lang.Thread.run",
          "source": "Thread.java:595"
        }
      ],
      "number": 3,
      "commentIndex": 0,
      "bugId": "97178",
      "date": "2005-05-30T10:26:47+02:00",
      "product": "CDT",
      "component": "cdt-core",
      "severity": "normal"
    }
  ],
  "groupId": "97178",
  "bugId": "97178",
  "date": "2005-05-30T10:26:47+02:00",
  "product": "CDT",
  "component": "cdt-core",
  "severity": "normal"
}