{
  "comments": [
    "Build 20020212\n\nI have a self-hosting workspace, with core + org.eclipse.ui as source, and all \nother projects as binary.  I did a synchronize with stream which triggered an \nincremental build.  This was the first build after upgrading to the latest \ndrop, so it triggered the restoring of builder state.  Sometime during the build \nthe following stack trace appeared on the console.  Note that there was no error \ndialog and nothing in the log, just a stack on the console.  I have not been \nable to reproduce it.\n\njava.lang.ArrayIndexOutOfBoundsException: 3407872\n        at org.eclipse.jdt.internal.core.newbuilder.State.read(State.java(Compil\ned Code))\n        at org.eclipse.jdt.internal.core.newbuilder.JavaBuilder.readState(JavaBu\nilder.java:59)\n        at org.eclipse.jdt.internal.core.JavaModelManager.readState(JavaModelMan\nager.java:846)\n        at org.eclipse.jdt.internal.core.JavaModelManager.getLastBuiltState(Java\nModelManager.java:634)\n        at org.eclipse.jdt.internal.core.newbuilder.JavaBuilder.getLastState(Jav\naBuilder.java:216)\n        at org.eclipse.jdt.internal.core.newbuilder.JavaBuilder.build(JavaBuilde\nr.java:84)\n        at org.eclipse.core.internal.events.BuildManager$2.run(BuildManager.java\n:351)\n        at org.eclipse.core.internal.runtime.InternalPlatform.run(InternalPlatfo\nrm.java:817)\n        at org.eclipse.core.runtime.Platform.run(Platform.java:395)\n        at org.eclipse.core.internal.events.BuildManager.basicBuild(BuildManager\n.java:109)\n        at org.eclipse.core.internal.events.BuildManager.basicBuild(BuildManager\n.java:174)\n        at org.eclipse.core.internal.events.BuildManager.basicBuild(BuildManager\n.java:184)\n        at org.eclipse.core.internal.events.BuildManager$1.run(BuildManager.java\n:133)\n        at org.eclipse.core.internal.runtime.InternalPlatform.run(InternalPlatfo\nrm.java:817)\n        at org.eclipse.core.runtime.Platform.run(Platform.java:395)\n        at org.eclipse.core.internal.events.BuildManager.basicBuild(BuildManager\n.java:147)\n        at org.eclipse.core.internal.events.BuildManager.build(BuildManager.java\n:209)\n        at org.eclipse.core.internal.resources.Workspace.endOperation(Workspace.\njava:701)\n        at org.eclipse.core.internal.resources.Workspace.run(Workspace.java:1237\n)\n        at org.eclipse.ui.actions.WorkspaceModifyOperation.run(WorkspaceModifyOp\neration.java:78)\n        at org.eclipse.jface.operation.ModalContext$ModalContextThread.run(Modal\nContext.java:98)\norg.eclipse.core.runtime.CoreException[2]: java.lang.ArrayIndexOutOfBoundsExcept\nion: 3407872\n        at org.eclipse.jdt.internal.core.newbuilder.State.read(State.java(Compil\ned Code))\n        at org.eclipse.jdt.internal.core.newbuilder.JavaBuilder.readState(JavaBu\nilder.java:59)\n        at org.eclipse.jdt.internal.core.JavaModelManager.readState(JavaModelMan\nager.java:846)\n        at org.eclipse.jdt.internal.core.JavaModelManager.getLastBuiltState(Java\nModelManager.java:634)\n        at org.eclipse.jdt.internal.core.newbuilder.JavaBuilder.getLastState(Jav\naBuilder.java:216)\n        at org.eclipse.jdt.internal.core.newbuilder.JavaBuilder.build(JavaBuilde\nr.java:84)\n        at org.eclipse.core.internal.events.BuildManager$2.run(BuildManager.java\n:351)\n        at org.eclipse.core.internal.runtime.InternalPlatform.run(InternalPlatfo\nrm.java:817)\n        at org.eclipse.core.runtime.Platform.run(Platform.java:395)\n        at org.eclipse.core.internal.events.BuildManager.basicBuild(BuildManager\n.java:109)\n        at org.eclipse.core.internal.events.BuildManager.basicBuild(BuildManager\n.java:174)\n        at org.eclipse.core.internal.events.BuildManager.basicBuild(BuildManager\n.java:184)\n        at org.eclipse.core.internal.events.BuildManager$1.run(BuildManager.java\n:133)\n        at org.eclipse.core.internal.runtime.InternalPlatform.run(InternalPlatfo\nrm.java:817)\n        at org.eclipse.core.runtime.Platform.run(Platform.java:395)\n        at org.eclipse.core.internal.events.BuildManager.basicBuild(BuildManager\n.java:147)\n        at org.eclipse.core.internal.events.BuildManager.build(BuildManager.java\n:209)\n        at org.eclipse.core.internal.resources.Workspace.endOperation(Workspace.\njava:701)\n        at org.eclipse.core.internal.resources.Workspace.run(Workspace.java:1237\n)\n        at org.eclipse.ui.actions.WorkspaceModifyOperation.run(WorkspaceModifyOp\neration.java:78)\n        at org.eclipse.jface.operation.ModalContext$ModalContextThread.run(Modal\nContext.java:98)",
    "Was this your first build after restarting with a 20020212 build ? We had a bug \nin the previous builds which could have caused the built state to be \nincorrectly serialized.\n\n",
    "Yes, this was the first build after restarting with 20020212.",
    "\n\n*** This bug has been marked as a duplicate of 9476 ***"
  ],
  "commentCreationDates": [
    "2002-02-13T18:55:01+01:00",
    "2002-02-13T22:27:24+01:00",
    "2002-02-13T23:22:37+01:00",
    "2002-02-14T16:58:00+01:00"
  ],
  "traces": [
    {
      "exceptionType": "java.lang.ArrayIndexOutOfBoundsException",
      "message": "3407872",
      "elements": [
        {
          "method": "org.eclipse.jdt.internal.core.newbuilder.State.read",
          "source": "State.java(Compil ed Code)"
        },
        {
          "method": "org.eclipse.jdt.internal.core.newbuilder.JavaBuilder.readState",
          "source": "JavaBu ilder.java:59"
        },
        {
          "method": "org.eclipse.jdt.internal.core.JavaModelManager.readState",
          "source": "JavaModelMan ager.java:846"
        },
        {
          "method": "org.eclipse.jdt.internal.core.JavaModelManager.getLastBuiltState",
          "source": "Java ModelManager.java:634"
        },
        {
          "method": "org.eclipse.jdt.internal.core.newbuilder.JavaBuilder.getLastState",
          "source": "Jav aBuilder.java:216"
        },
        {
          "method": "org.eclipse.jdt.internal.core.newbuilder.JavaBuilder.build",
          "source": "JavaBuilde r.java:84"
        },
        {
          "method": "org.eclipse.core.internal.events.BuildManager$2.run",
          "source": "BuildManager.java :351"
        },
        {
          "method": "org.eclipse.core.internal.runtime.InternalPlatform.run",
          "source": "InternalPlatfo rm.java:817"
        },
        {
          "method": "org.eclipse.core.runtime.Platform.run",
          "source": "Platform.java:395"
        },
        {
          "method": "org.eclipse.core.internal.events.BuildManager.basicBuild",
          "source": "BuildManager .java:109"
        },
        {
          "method": "org.eclipse.core.internal.events.BuildManager.basicBuild",
          "source": "BuildManager .java:174"
        },
        {
          "method": "org.eclipse.core.internal.events.BuildManager.basicBuild",
          "source": "BuildManager .java:184"
        },
        {
          "method": "org.eclipse.core.internal.events.BuildManager$1.run",
          "source": "BuildManager.java :133"
        },
        {
          "method": "org.eclipse.core.internal.runtime.InternalPlatform.run",
          "source": "InternalPlatfo rm.java:817"
        },
        {
          "method": "org.eclipse.core.runtime.Platform.run",
          "source": "Platform.java:395"
        },
        {
          "method": "org.eclipse.core.internal.events.BuildManager.basicBuild",
          "source": "BuildManager .java:147"
        },
        {
          "method": "org.eclipse.core.internal.events.BuildManager.build",
          "source": "BuildManager.java :209"
        },
        {
          "method": "org.eclipse.core.internal.resources.Workspace.endOperation",
          "source": "Workspace. java:701"
        },
        {
          "method": "org.eclipse.core.internal.resources.Workspace.run",
          "source": "Workspace.java:1237 "
        },
        {
          "method": "org.eclipse.ui.actions.WorkspaceModifyOperation.run",
          "source": "WorkspaceModifyOp eration.java:78"
        },
        {
          "method": "org.eclipse.jface.operation.ModalContext$ModalContextThread.run",
          "source": "Modal Context.java:98"
        }
      ],
      "number": 0,
      "commentIndex": 0,
      "bugId": "9726",
      "duplicateId": "9476",
      "date": "2002-02-13T18:55:01+01:00",
      "product": "JDT",
      "component": "Core",
      "severity": "normal"
    }
  ],
  "groupId": "9476",
  "bugId": "9726",
  "duplicateId": "9476",
  "date": "2002-02-13T18:55:01+01:00",
  "product": "JDT",
  "component": "Core",
  "severity": "normal"
}