{
  "comments": [
    "Killed a process that was trying to read from System.in and got: \n\njava.io.IOException: Bad file descriptor\nat java.io.FileInputStream.available(Native Method)\nat java.io.BufferedInputStream.read(BufferedInputStream.java:279)\nat java.io.FilterInputStream.read(FilterInputStream.java:90)\nat org.eclipse.debug.internal.core.OutputStreamMonitor.read(OutputStreamMonitor.java:135)\nat org.eclipse.debug.internal.core.OutputStreamMonitor.access$1(OutputStreamMonitor.java:126)\nat org.eclipse.debug.internal.core.OutputStreamMonitor$1.run(OutputStreamMonitor.java:193)\nat java.lang.Thread.run(Thread.java:552)\n\n\nTest Case:\n\npublic class Echo {\n\tpublic static void main(String[] args) throws Exception {\n\t\tbyte[] b \u003d new byte[512];\n\t\tfor (;;) {\n\t\t\tSystem.out.print(\"Enter Text: \");\n\t\t\tint read \u003d System.in.read(b);\n\t\t\tSystem.out.write(b, 0, read);\n\t\t}\n\t}\n}",
    "Can\u0027t reproduce anymore."
  ],
  "commentCreationDates": [
    "2005-05-31T23:03:42+02:00",
    "2005-06-08T18:17:55+02:00"
  ],
  "traces": [
    {
      "exceptionType": "java.io.IOException",
      "message": "Bad file descriptor",
      "elements": [
        {
          "method": "java.io.FileInputStream.available",
          "source": "Native Method"
        },
        {
          "method": "java.io.BufferedInputStream.read",
          "source": "BufferedInputStream.java:279"
        },
        {
          "method": "java.io.FilterInputStream.read",
          "source": "FilterInputStream.java:90"
        },
        {
          "method": "org.eclipse.debug.internal.core.OutputStreamMonitor.read",
          "source": "OutputStreamMonitor.java:135"
        },
        {
          "method": "org.eclipse.debug.internal.core.OutputStreamMonitor.access$1",
          "source": "OutputStreamMonitor.java:126"
        },
        {
          "method": "org.eclipse.debug.internal.core.OutputStreamMonitor$1.run",
          "source": "OutputStreamMonitor.java:193"
        },
        {
          "method": "java.lang.Thread.run",
          "source": "Thread.java:552"
        }
      ],
      "number": 0,
      "commentIndex": 0,
      "bugId": "97735",
      "date": "2005-05-31T23:03:42+02:00",
      "product": "Platform",
      "component": "Debug",
      "severity": "normal"
    }
  ],
  "groupId": "97735",
  "bugId": "97735",
  "date": "2005-05-31T23:03:42+02:00",
  "product": "Platform",
  "component": "Debug",
  "severity": "normal"
}