{
  "comments": [
    "Hello there. I posted about this on the message boards and was told to create a\nbug report.  I\u0027m going to give as much info as possible, though I\u0027m new to\nEclipse so I hope I\u0027m throrough enough.  I\u0027m working on developing cell phone\ngames for the Nokia Series 60 devices.  I\u0027ve installed and am using their\nemulators to run the project. So far everything runs ok, but when I put\nbreakpoints in certain areas I get an internal error while running in Debug\nmode.  Here\u0027s all the details from the Event Details window:\n\nSession Data:\neclipse.buildId\u003dM200503110845\njava.version\u003d1.5.0_03\njava.vendor\u003dSun Microsystems Inc.\nBootLoader constants: OS\u003dwin32, ARCH\u003dx86, WS\u003dwin32, NL\u003den_US\n\nMessage:\nAn internal error occurred during: \"Debug\".\n\n\nException Stack Trace:\njava.lang.IllegalArgumentException\n\tat\norg.eclipse.jdi.internal.GenericSignature.getArgumentsSignature(GenericSignature.java:65)\n\tat org.eclipse.jdi.internal.MethodImpl.argumentTypeSignatures(MethodImpl.java:302)\n\tat org.eclipse.jdi.internal.MethodImpl.argumentTypeNames(MethodImpl.java:278)\n\tat\norg.eclipse.jdt.internal.debug.core.model.JDIStackFrame.getArgumentTypeNames(JDIStackFrame.java:324)\n\tat\norg.eclipse.jdt.internal.debug.ui.JDIModelPresentation.getStackFrameText(JDIModelPresentation.java:1498)\n\tat\norg.eclipse.jdt.internal.debug.ui.JDIModelPresentation.getText(JDIModelPresentation.java:204)\n\tat\norg.eclipse.debug.internal.ui.LazyModelPresentation.getText(LazyModelPresentation.java:101)\n\tat\norg.eclipse.debug.internal.ui.DelegatingModelPresentation.getText(DelegatingModelPresentation.java:158)\n\tat\norg.eclipse.debug.internal.ui.views.DebugViewLabelDecorator$LabelJob.run(DebugViewLabelDecorator.java:326)\n\tat org.eclipse.core.internal.jobs.Worker.run(Worker.java:66)\n\n\nHope that formats ok. It looks like I can still run the Step Over command in the\ndebugger, but it generates the same errror with each step.  Hope this helps. \nFeel free to contact me if you need more info.\nThanks\nMike",
    "\n\n*** This bug has been marked as a duplicate of 88726 ***",
    "I think I mis-directed Mike on the newsgroup. \nI was attempting to indicate that I believe this bug is covered by either bug \n78605 or bug 88726.\n\nMike, could you download Eclipse 3.1 RC1 and see if the problem is fixed?"
  ],
  "commentCreationDates": [
    "2005-06-01T21:42:02+02:00",
    "2005-06-01T21:44:15+02:00",
    "2005-06-01T21:45:05+02:00"
  ],
  "traces": [
    {
      "exceptionType": "java.lang.IllegalArgumentException",
      "elements": [
        {
          "method": "org.eclipse.jdi.internal.GenericSignature.getArgumentsSignature",
          "source": "GenericSignature.java:65"
        },
        {
          "method": "org.eclipse.jdi.internal.MethodImpl.argumentTypeSignatures",
          "source": "MethodImpl.java:302"
        },
        {
          "method": "org.eclipse.jdi.internal.MethodImpl.argumentTypeNames",
          "source": "MethodImpl.java:278"
        },
        {
          "method": "org.eclipse.jdt.internal.debug.core.model.JDIStackFrame.getArgumentTypeNames",
          "source": "JDIStackFrame.java:324"
        },
        {
          "method": "org.eclipse.jdt.internal.debug.ui.JDIModelPresentation.getStackFrameText",
          "source": "JDIModelPresentation.java:1498"
        },
        {
          "method": "org.eclipse.jdt.internal.debug.ui.JDIModelPresentation.getText",
          "source": "JDIModelPresentation.java:204"
        },
        {
          "method": "org.eclipse.debug.internal.ui.LazyModelPresentation.getText",
          "source": "LazyModelPresentation.java:101"
        },
        {
          "method": "org.eclipse.debug.internal.ui.DelegatingModelPresentation.getText",
          "source": "DelegatingModelPresentation.java:158"
        },
        {
          "method": "org.eclipse.debug.internal.ui.views.DebugViewLabelDecorator$LabelJob.run",
          "source": "DebugViewLabelDecorator.java:326"
        },
        {
          "method": "org.eclipse.core.internal.jobs.Worker.run",
          "source": "Worker.java:66"
        }
      ],
      "number": 0,
      "commentIndex": 0,
      "bugId": "97975",
      "duplicateId": "88726",
      "date": "2005-06-01T21:42:02+02:00",
      "product": "JDT",
      "component": "Debug",
      "severity": "major"
    }
  ],
  "groupId": "88726",
  "bugId": "97975",
  "duplicateId": "88726",
  "date": "2005-06-01T21:42:02+02:00",
  "product": "JDT",
  "component": "Debug",
  "severity": "major"
}