{
  "comments": [
    "I realize that Solaris 9 Early Access doesn\u0027t exactly count as an Eclipse\nsupported platform at present, but just as a heads up...  Eclipse dies\nreproducibly on Solaris 9 EA, apparently because of a limitation in SWT\u0027s\nparsing of font descriptors (I think).\n\nThere seem to be multiple ways to tickle this, but one reliable way to \ncrash it is to bring up Eclipse, then in the resource Navigator view\nselect the Menu and then \"Filters...\"\n\nThe configuration that I was using -- Ultra 10 with a Creator3D and 24-bit\ndefault visuals, with Sun JDK 1.3.1 and the stable Eclipse 20020125 build --\nis the same setup that I previously used successfully with Solaris 8;\nas far as I know, the only thing that I changed is the Solaris version.\n\nI also tried both 8-bit visuals (the Eclipse splash screen looks impressively\nawful) and JDK 1.4 Beta 3, but got the same results in all cases -- now that\nI\u0027ve upgraded this box to Solaris 9 EA I can\u0027t run Eclipse on it.  Good thing\nit\u0027s my home machine, where I was only playing around with Eclipse anyway.\n\nHere is a copy of the .metadata/.log file.  Much the same sort of thing gets\nprinted to standard output (or error), and the process exits.\n\nLog: Wed Feb 13 21:09:18 EST 2002\n1 org.eclipse.core.resources 4 Unhandled exception caught in event loop.\nLog: Wed Feb 13 21:09:19 EST 2002\n4 org.eclipse.ui 0 [8.00 0.00 0.00 8.00]\njava.lang.NumberFormatException: [8.00 0.00 0.00 8.00]\n        at java.lang.Integer.parseInt(Integer.java:414)\n        at java.lang.Integer.parseInt(Integer.java:463)\n        at org.eclipse.swt.graphics.FontData.setXlfd(FontData.java:475)\n        at org.eclipse.swt.graphics.FontData.motif_new(FontData.java:335)\n        at org.eclipse.swt.graphics.GC.getFontMetrics(GC.java:1965)\n        at\norg.eclipse.jface.dialogs.Dialog.initializeDialogUnits(Dialog.java:515)\n        at org.eclipse.jface.dialogs.Dialog.createContents(Dialog.java:431)\n        at org.eclipse.jface.window.Window.create(Window.java:237)\n        at org.eclipse.jface.window.Window.open(Window.java:510)\n        at\norg.eclipse.ui.views.navigator.FilterSelectionAction.run(FilterSelectionAction.java:50)\n        at org.eclipse.jface.action.Action.runWithEvent(Action.java:452)\n        at\norg.eclipse.jface.action.ActionContributionItem.handleWidgetSelection(ActionContributionItem.java:407)\n        at\norg.eclipse.jface.action.ActionContributionItem.handleWidgetEvent(ActionContributionItem.java:361)\n        at\norg.eclipse.jface.action.ActionContributionItem.access$0(ActionContributionItem.java:352)\n        at\norg.eclipse.jface.action.ActionContributionItem$ActionListener.handleEvent(ActionContributionItem.java:47)\n        at org.eclipse.swt.widgets.EventTable.sendEvent(EventTable.java:74)\n        at org.eclipse.swt.widgets.Widget.notifyListeners(Widget.java:488)\n        at org.eclipse.swt.widgets.Display.runDeferredEvents(Display.java:1580)\n        at org.eclipse.swt.widgets.Display.readAndDispatch(Display.java:1429)\n        at org.eclipse.ui.internal.Workbench.runEventLoop(Workbench.java:844)\n        at org.eclipse.ui.internal.Workbench.run(Workbench.java:827)\n        at\norg.eclipse.core.internal.boot.InternalBootLoader.run(InternalBootLoader.java:878)\n        at org.eclipse.core.boot.BootLoader.run(BootLoader.java:321)\n        at java.lang.reflect.Method.invoke(Native Method)\n        at org.eclipse.core.launcher.Main.basicRun(Main.java:151)\n        at org.eclipse.core.launcher.Main.run(Main.java:502)\n        at org.eclipse.core.launcher.Main.main(Main.java:362)",
    "KC to investigate. I do not have access to this configuration.",
    "I tried Eclipse 2.0 on a Sun sparc (Ultra 5 ... slow) running Solaris 9 and was \nunable to duplicate the problem. "
  ],
  "commentCreationDates": [
    "2002-02-14T04:06:56+01:00",
    "2002-02-14T17:30:20+01:00",
    "2002-09-10T20:14:05+02:00"
  ],
  "traces": [
    {
      "exceptionType": "java.lang.NumberFormatException",
      "message": "[8.00 0.00 0.00 8.00]",
      "elements": [
        {
          "method": "java.lang.Integer.parseInt",
          "source": "Integer.java:414"
        },
        {
          "method": "java.lang.Integer.parseInt",
          "source": "Integer.java:463"
        },
        {
          "method": "org.eclipse.swt.graphics.FontData.setXlfd",
          "source": "FontData.java:475"
        },
        {
          "method": "org.eclipse.swt.graphics.FontData.motif_new",
          "source": "FontData.java:335"
        },
        {
          "method": "org.eclipse.swt.graphics.GC.getFontMetrics",
          "source": "GC.java:1965"
        },
        {
          "method": "org.eclipse.jface.dialogs.Dialog.initializeDialogUnits",
          "source": "Dialog.java:515"
        },
        {
          "method": "org.eclipse.jface.dialogs.Dialog.createContents",
          "source": "Dialog.java:431"
        },
        {
          "method": "org.eclipse.jface.window.Window.create",
          "source": "Window.java:237"
        },
        {
          "method": "org.eclipse.jface.window.Window.open",
          "source": "Window.java:510"
        },
        {
          "method": "org.eclipse.ui.views.navigator.FilterSelectionAction.run",
          "source": "FilterSelectionAction.java:50"
        },
        {
          "method": "org.eclipse.jface.action.Action.runWithEvent",
          "source": "Action.java:452"
        },
        {
          "method": "org.eclipse.jface.action.ActionContributionItem.handleWidgetSelection",
          "source": "ActionContributionItem.java:407"
        },
        {
          "method": "org.eclipse.jface.action.ActionContributionItem.handleWidgetEvent",
          "source": "ActionContributionItem.java:361"
        },
        {
          "method": "org.eclipse.jface.action.ActionContributionItem.access$0",
          "source": "ActionContributionItem.java:352"
        },
        {
          "method": "org.eclipse.jface.action.ActionContributionItem$ActionListener.handleEvent",
          "source": "ActionContributionItem.java:47"
        },
        {
          "method": "org.eclipse.swt.widgets.EventTable.sendEvent",
          "source": "EventTable.java:74"
        },
        {
          "method": "org.eclipse.swt.widgets.Widget.notifyListeners",
          "source": "Widget.java:488"
        },
        {
          "method": "org.eclipse.swt.widgets.Display.runDeferredEvents",
          "source": "Display.java:1580"
        },
        {
          "method": "org.eclipse.swt.widgets.Display.readAndDispatch",
          "source": "Display.java:1429"
        },
        {
          "method": "org.eclipse.ui.internal.Workbench.runEventLoop",
          "source": "Workbench.java:844"
        },
        {
          "method": "org.eclipse.ui.internal.Workbench.run",
          "source": "Workbench.java:827"
        },
        {
          "method": "org.eclipse.core.internal.boot.InternalBootLoader.run",
          "source": "InternalBootLoader.java:878"
        },
        {
          "method": "org.eclipse.core.boot.BootLoader.run",
          "source": "BootLoader.java:321"
        },
        {
          "method": "java.lang.reflect.Method.invoke",
          "source": "Native Method"
        },
        {
          "method": "org.eclipse.core.launcher.Main.basicRun",
          "source": "Main.java:151"
        },
        {
          "method": "org.eclipse.core.launcher.Main.run",
          "source": "Main.java:502"
        },
        {
          "method": "org.eclipse.core.launcher.Main.main",
          "source": "Main.java:362"
        }
      ],
      "number": 0,
      "commentIndex": 0,
      "bugId": "9803",
      "date": "2002-02-14T04:06:56+01:00",
      "product": "Platform",
      "component": "SWT",
      "severity": "major"
    }
  ],
  "groupId": "9803",
  "bugId": "9803",
  "date": "2002-02-14T04:06:56+01:00",
  "product": "Platform",
  "component": "SWT",
  "severity": "major"
}