{
  "comments": [
    "(Copied from Eclipse.platform news group)\nI ran into the problem using RC1. I launch it on the new workspace. Then switch\ntarget to 3.0.1.\n\n- open preferences\n- select Plugin Development-\u003eTarget Platform\n- set a location to Eclipse 3.0.1 directory\n\n\n Still works fine. Then import plugins into the workspace. \n\n- Select File -\u003e Import -\u003e External Plug-Ins And Fragments\n- check The target platform (as specified in Preferences)\n- click Next\n- click Add All\n- click Finish\n\nAlmost all plugins are error-tagged. The problem is osgi plugin. If I try to\nupdate class paths, I get an error:\n\norg.eclipse.core.runtime.CoreException: Project cannot reference itself:\norg.eclipse.osgi\n    at\norg.eclipse.pde.internal.core.ClasspathComputer.getClasspath(ClasspathComputer.java:68)\n    at\norg.eclipse.pde.internal.core.ClasspathComputer.setClasspath(ClasspathComputer.java:42)\n    at\norg.eclipse.pde.internal.ui.wizards.tools.UpdateClasspathJob.doUpdateClasspath(UpdateClasspathJob.java:55)\n    at\norg.eclipse.pde.internal.ui.wizards.tools.UpdateClasspathJob$UpdateClasspathWorkspaceRunnable.run(UpdateClasspathJob.java:70)\n    at org.eclipse.core.internal.resources.Workspace.run(Workspace.java:1719)\n    at org.eclipse.core.internal.resources.Workspace.run(Workspace.java:1739)\n    at\norg.eclipse.pde.internal.ui.wizards.tools.UpdateClasspathJob.run(UpdateClasspathJob.java:82)\n    at org.eclipse.core.internal.jobs.Worker.run(Worker.java:67)\n\nWorkaround is to exclude osgi and update.configurator plugins from the\nworkspace. It solves previous problem but another one comes up.\n\nI start from scratch. After launching IDE on the new workspace I create launch\nconfiguration for run-time workbench and can launch it succesfully. As soon as I\nimport plugin and fragments (just excluding org.eclipse.osgi and\norg.eclipse.update.configuration as a troublemakers to avoid errors), I lose\nthis ability. Launch (the same launch configuration) fails with the following\ntrace log:\n\njava.lang.RuntimeException: Application \"org.eclipse.ui.ide.workbench\" could not\nbe found in the registry. The applications available are:\norg.eclipse.ant.core.antRunner, org.eclipse.help.base.infocenterApplication,\norg.eclipse.help.base.helpApplication, org.eclipse.help.base.indexTool,\norg.eclipse.pde.build.BuildScriptGenerator,\norg.eclipse.pde.build.FetchScriptGenerator,\norg.eclipse.pde.junit.runtime.uitestapplication,\norg.eclipse.pde.junit.runtime.legacyUItestapplication,\norg.eclipse.pde.junit.runtime.coretestapplication,\norg.eclipse.update.core.standaloneUpdate.\n    at\norg.eclipse.core.internal.runtime.PlatformActivator$1.run(PlatformActivator.java:325)\n    at org.eclipse.core.runtime.adaptor.EclipseStarter.run(EclipseStarter.java:273)\n    at org.eclipse.core.runtime.adaptor.EclipseStarter.run(EclipseStarter.java:129)\n    at sun.reflect.NativeMethodAccessorImpl.invoke0(Native Method)\n    at sun.reflect.NativeMethodAccessorImpl.invoke(Unknown Source)\n    at sun.reflect.DelegatingMethodAccessorImpl.invoke(Unknown Source)\n    at java.lang.reflect.Method.invoke(Unknown Source)\n    at org.eclipse.core.launcher.Main.basicRun(Main.java:185)\n    at org.eclipse.core.launcher.Main.run(Main.java:704)\n    at org.eclipse.core.launcher.Main.main(Main.java:688)\n\n\nThen I remove all the imported stuff expecting that I get this functionality\nback. However the launch fails, just after another error:\n\njava.lang.RuntimeException: No application id has been found.\n    at\norg.eclipse.core.internal.runtime.PlatformActivator$1.run(PlatformActivator.java:313)\n    at org.eclipse.core.runtime.adaptor.EclipseStarter.run(EclipseStarter.java:273)\n    at org.eclipse.core.runtime.adaptor.EclipseStarter.run(EclipseStarter.java:129)\n    at sun.reflect.NativeMethodAccessorImpl.invoke0(Native Method)\n    at sun.reflect.NativeMethodAccessorImpl.invoke(Unknown Source)\n    at sun.reflect.DelegatingMethodAccessorImpl.invoke(Unknown Source)\n    at java.lang.reflect.Method.invoke(Unknown Source)\n    at org.eclipse.core.launcher.Main.basicRun(Main.java:185)\n    at org.eclipse.core.launcher.Main.run(Main.java:704)\n    at org.eclipse.core.launcher.Main.main(Main.java:688)\n\n\nBoth 3.1RC1 and 3.0.1 are dounloaded and fresh installed. If I use workspace\ncreated using another build, it works fine.",
    "However it still not exhausts the list of the problems. I create new workspace,\nthen change target platform and check-out CDT plugins (release 2.1), build it\n(got just one error in plugin.xml: Illegal attribute \u0027targetClass\u0027;I had it with\nprevious milestones and in spite of that error everything worked fine) and try\nto launch once again. Everything is OK, but when I try to open one of CDT\nperspectives, I realize that they are not available any more.  When I check\nPlug-in details (Help-\u003eAbout-\u003ePlugin details...) I don\u0027t see any CDT plugin in\nthe list of available plugins.",
    "The classpath issue will be tracked uner bug 98246.\n\nTom/Jeff, all the errors that appear in this workspace are because the target \nis 3.0.x-based, where the osgi manifest did not list all of its exported \npackages in the manifest.mf.\n\nWhat do we do here?  should we disable access restrictions if the target is \nnot 3.1?  or should the state go the extra mile to find all exported packages \nby a 3.0.x osgi plugin?",
    "Access restrictions are now disabled if target platform \u003e 3.1\nThis will get rid of all errors encountered.\n\nbug 98246 is now fixed too.\n\nAs for the cdt plugins not showing up in the runtime workbench, this is not a \nPDE issue.  They might have been disabled for one reason or another by Update \nor the runtime.  I suggest opening a separate bug report against Runtime or \nUpdate for the cdt problem if the problem persists and if it\u0027s not a user \nerror.",
    "\u003e\u003e Access restrictions are now disabled if target platform \u003e 3.1\n\u003e\u003e This will get rid of all errors encountered.\n\nI assume you mean if target platform \u003c 3.1 (less than 3.1 :)\n",
    "let us hope :-)",
    "I don\u0027t think this is a specific CDT problem. Following the same scenario I\nchecked out my plugins and haven\u0027t seen them as well (in the Plugin Details\nlist). However it works just fine in M7. I did it once again and got even more\nweird picture: C/C++ perspective tag is visible, but neither its views, nor\nC/C++ wizards are available.\nI used jre1.4.2-04, Eclipse3.1RC1, CDT2.1 (this code has been frozen long time\nago), plugin development target Eclipse 3.0.1.\nWould you like I open new bug report, or you prefer to do it yourself?",
    "RC1 has a known issue with Update.  Try the patch from bug 97148 comment 25 or \nN-2006060100.  If the problem persists, please open a bug report.",
    "Yes, I tried N20050606-0010 and found that problem disappeared. Thanks."
  ],
  "commentCreationDates": [
    "2005-06-02T17:04:11+02:00",
    "2005-06-02T17:38:18+02:00",
    "2005-06-03T13:53:52+02:00",
    "2005-06-04T03:15:15+02:00",
    "2005-06-06T04:25:14+02:00",
    "2005-06-06T04:29:21+02:00",
    "2005-06-06T14:49:08+02:00",
    "2005-06-06T14:53:03+02:00",
    "2005-06-06T15:22:50+02:00"
  ],
  "traces": [
    {
      "exceptionType": "org.eclipse.core.runtime.CoreException",
      "message": "Project cannot reference itself: org.eclipse.osgi",
      "elements": [
        {
          "method": "org.eclipse.pde.internal.core.ClasspathComputer.getClasspath",
          "source": "ClasspathComputer.java:68"
        },
        {
          "method": "org.eclipse.pde.internal.core.ClasspathComputer.setClasspath",
          "source": "ClasspathComputer.java:42"
        },
        {
          "method": "org.eclipse.pde.internal.ui.wizards.tools.UpdateClasspathJob.doUpdateClasspath",
          "source": "UpdateClasspathJob.java:55"
        },
        {
          "method": "org.eclipse.pde.internal.ui.wizards.tools.UpdateClasspathJob$UpdateClasspathWorkspaceRunnable.run",
          "source": "UpdateClasspathJob.java:70"
        },
        {
          "method": "org.eclipse.core.internal.resources.Workspace.run",
          "source": "Workspace.java:1719"
        },
        {
          "method": "org.eclipse.core.internal.resources.Workspace.run",
          "source": "Workspace.java:1739"
        },
        {
          "method": "org.eclipse.pde.internal.ui.wizards.tools.UpdateClasspathJob.run",
          "source": "UpdateClasspathJob.java:82"
        },
        {
          "method": "org.eclipse.core.internal.jobs.Worker.run",
          "source": "Worker.java:67"
        }
      ],
      "number": 0,
      "commentIndex": 0,
      "bugId": "98123",
      "date": "2005-06-02T17:04:11+02:00",
      "product": "PDE",
      "component": "UI",
      "severity": "normal"
    },
    {
      "exceptionType": "java.lang.RuntimeException",
      "message": "Application \"org.eclipse.ui.ide.workbench\" could not be found in the registry. The applications available are: org.eclipse.ant.core.antRunner, org.eclipse.help.base.infocenterApplication, org.eclipse.help.base.helpApplication, org.eclipse.help.base.indexTool, org.eclipse.pde.build.BuildScriptGenerator, org.eclipse.pde.build.FetchScriptGenerator, org.eclipse.pde.junit.runtime.uitestapplication, org.eclipse.pde.junit.runtime.legacyUItestapplication, org.eclipse.pde.junit.runtime.coretestapplication, org.eclipse.update.core.standaloneUpdate.",
      "elements": [
        {
          "method": "org.eclipse.core.internal.runtime.PlatformActivator$1.run",
          "source": "PlatformActivator.java:325"
        },
        {
          "method": "org.eclipse.core.runtime.adaptor.EclipseStarter.run",
          "source": "EclipseStarter.java:273"
        },
        {
          "method": "org.eclipse.core.runtime.adaptor.EclipseStarter.run",
          "source": "EclipseStarter.java:129"
        },
        {
          "method": "sun.reflect.NativeMethodAccessorImpl.invoke0",
          "source": "Native Method"
        },
        {
          "method": "sun.reflect.NativeMethodAccessorImpl.invoke",
          "source": "Unknown Source"
        },
        {
          "method": "sun.reflect.DelegatingMethodAccessorImpl.invoke",
          "source": "Unknown Source"
        },
        {
          "method": "java.lang.reflect.Method.invoke",
          "source": "Unknown Source"
        },
        {
          "method": "org.eclipse.core.launcher.Main.basicRun",
          "source": "Main.java:185"
        },
        {
          "method": "org.eclipse.core.launcher.Main.run",
          "source": "Main.java:704"
        },
        {
          "method": "org.eclipse.core.launcher.Main.main",
          "source": "Main.java:688"
        }
      ],
      "number": 1,
      "commentIndex": 0,
      "bugId": "98123",
      "date": "2005-06-02T17:04:11+02:00",
      "product": "PDE",
      "component": "UI",
      "severity": "normal"
    },
    {
      "exceptionType": "java.lang.RuntimeException",
      "message": "No application id has been found.",
      "elements": [
        {
          "method": "org.eclipse.core.internal.runtime.PlatformActivator$1.run",
          "source": "PlatformActivator.java:313"
        },
        {
          "method": "org.eclipse.core.runtime.adaptor.EclipseStarter.run",
          "source": "EclipseStarter.java:273"
        },
        {
          "method": "org.eclipse.core.runtime.adaptor.EclipseStarter.run",
          "source": "EclipseStarter.java:129"
        },
        {
          "method": "sun.reflect.NativeMethodAccessorImpl.invoke0",
          "source": "Native Method"
        },
        {
          "method": "sun.reflect.NativeMethodAccessorImpl.invoke",
          "source": "Unknown Source"
        },
        {
          "method": "sun.reflect.DelegatingMethodAccessorImpl.invoke",
          "source": "Unknown Source"
        },
        {
          "method": "java.lang.reflect.Method.invoke",
          "source": "Unknown Source"
        },
        {
          "method": "org.eclipse.core.launcher.Main.basicRun",
          "source": "Main.java:185"
        },
        {
          "method": "org.eclipse.core.launcher.Main.run",
          "source": "Main.java:704"
        },
        {
          "method": "org.eclipse.core.launcher.Main.main",
          "source": "Main.java:688"
        }
      ],
      "number": 2,
      "commentIndex": 0,
      "bugId": "98123",
      "date": "2005-06-02T17:04:11+02:00",
      "product": "PDE",
      "component": "UI",
      "severity": "normal"
    }
  ],
  "groupId": "98123",
  "bugId": "98123",
  "date": "2005-06-02T17:04:11+02:00",
  "product": "PDE",
  "component": "UI",
  "severity": "normal"
}