{
  "comments": [
    "This is unforuntately not an easy bug to repro, but it is a nasty one. I was\nusing M6 but targetting a RC1 install with WTP integration build I20050601. I\nupgraded to RC1, but continued using the same target platform. Now, when I try\nto run the workspace out of my IDE, I get the following in the log:\n\nESSION 2005-06-07 14:57:33.905 -----------------------------------------------\neclipse.buildId\u003dunknown\njava.version\u003d1.5.0\njava.vendor\u003dSun Microsystems Inc.\nBootLoader constants: OS\u003dwin32, ARCH\u003dx86, WS\u003dwin32, NL\u003den_US\nFramework arguments:  -application org.eclipse.ui.ide.workbench -pdelaunch\nCommand-line arguments:  -application org.eclipse.ui.ide.workbench -data\nC:\\Documents and Settings\\dsomerfi\\runtime-workspace -dev file:C:/Documents and\nSettings/dsomerfi/workspace/.metadata/.plugins/org.eclipse.pde.core/New_configuration/dev.properties\n-pdelaunch -os win32 -ws win32 -arch x86\n\n!ENTRY org.eclipse.osgi 2005-06-07 14:57:34.857\n!MESSAGE Application error\n!STACK 1\njava.lang.RuntimeException: Application \"org.eclipse.ui.ide.workbench\" could not\nbe found in the registry. The applications available are: \u003cNONE\u003e.\n\tat\norg.eclipse.core.internal.runtime.PlatformActivator$1.run(PlatformActivator.java:216)\n\tat org.eclipse.core.runtime.adaptor.EclipseStarter.run(EclipseStarter.java:375)\n\tat org.eclipse.core.runtime.adaptor.EclipseStarter.run(EclipseStarter.java:162)\n\tat sun.reflect.NativeMethodAccessorImpl.invoke0(Native Method)\n\tat sun.reflect.NativeMethodAccessorImpl.invoke(NativeMethodAccessorImpl.java:39)\n\tat\nsun.reflect.DelegatingMethodAccessorImpl.invoke(DelegatingMethodAccessorImpl.java:25)\n\tat java.lang.reflect.Method.invoke(Method.java:585)\n\tat org.eclipse.core.launcher.Main.invokeFramework(Main.java:334)\n\tat org.eclipse.core.launcher.Main.basicRun(Main.java:278)\n\tat org.eclipse.core.launcher.Main.run(Main.java:973)\n\tat org.eclipse.core.launcher.Main.main(Main.java:948)\n\nI have started with a fresh install and it doesn\u0027t do it at first, but then\nstarts doing it. My RC1 install works fine when using itself as the target\nplatform, but won\u0027t work when using any other.\n\nI know this isn\u0027t much of a repro, but it has me at a dead stop. I even killed\nmy workspace and started over and that had me going for a while but it is now\nfailing again.\n\nIf I can send any files to help with the repro, let me know.",
    "Looks like a dup of bug 97148 (there is a patched\norg.eclipse.update.configurator_3.1.0.jar there). If using that patch it still\ndoes not work for you, please reopen.\n\n*** This bug has been marked as a duplicate of 97148 ***"
  ],
  "commentCreationDates": [
    "2005-06-08T00:04:48+02:00",
    "2005-06-08T00:10:53+02:00"
  ],
  "traces": [
    {
      "exceptionType": "java.lang.RuntimeException",
      "message": "Application \"org.eclipse.ui.ide.workbench\" could not be found in the registry. The applications available are: \u003cNONE\u003e.",
      "elements": [
        {
          "method": "org.eclipse.core.internal.runtime.PlatformActivator$1.run",
          "source": "PlatformActivator.java:216"
        },
        {
          "method": "org.eclipse.core.runtime.adaptor.EclipseStarter.run",
          "source": "EclipseStarter.java:375"
        },
        {
          "method": "org.eclipse.core.runtime.adaptor.EclipseStarter.run",
          "source": "EclipseStarter.java:162"
        },
        {
          "method": "sun.reflect.NativeMethodAccessorImpl.invoke0",
          "source": "Native Method"
        },
        {
          "method": "sun.reflect.NativeMethodAccessorImpl.invoke",
          "source": "NativeMethodAccessorImpl.java:39"
        },
        {
          "method": "sun.reflect.DelegatingMethodAccessorImpl.invoke",
          "source": "DelegatingMethodAccessorImpl.java:25"
        },
        {
          "method": "java.lang.reflect.Method.invoke",
          "source": "Method.java:585"
        },
        {
          "method": "org.eclipse.core.launcher.Main.invokeFramework",
          "source": "Main.java:334"
        },
        {
          "method": "org.eclipse.core.launcher.Main.basicRun",
          "source": "Main.java:278"
        },
        {
          "method": "org.eclipse.core.launcher.Main.run",
          "source": "Main.java:973"
        },
        {
          "method": "org.eclipse.core.launcher.Main.main",
          "source": "Main.java:948"
        }
      ],
      "number": 0,
      "commentIndex": 0,
      "bugId": "98849",
      "duplicateId": "97148",
      "date": "2005-06-08T00:04:48+02:00",
      "product": "Platform",
      "component": "Runtime",
      "severity": "critical"
    }
  ],
  "groupId": "97148",
  "bugId": "98849",
  "duplicateId": "97148",
  "date": "2005-06-08T00:04:48+02:00",
  "product": "Platform",
  "component": "Runtime",
  "severity": "critical"
}