{
  "comments": [
    "3.1 RC1 on Win XP\n\nI had two stack which were breakpointed.  Every time I hit F8 (Go), the\nselection which switch and I have a few of the following in my log.\n\n!ENTRY org.eclipse.core.runtime 4 2 2005-06-08 11:36:28.828\n!MESSAGE An internal error occurred during: \"Debug\".\n!STACK 0\njava.lang.ClassCastException\n        at\norg.eclipse.jdt.internal.debug.core.model.JDIStackFrame.getDeclaringType(JDIStackFrame.java:1071)\n        at\norg.eclipse.jdt.internal.debug.ui.JDIModelPresentation.getStackFrameText(JDIModelPresentation.java:1652)\n        at\norg.eclipse.jdt.internal.debug.ui.JDIModelPresentation.getText(JDIModelPresentation.java:214)\n        at\norg.eclipse.debug.internal.ui.LazyModelPresentation.getText(LazyModelPresentation.java:153)\n        at\norg.eclipse.debug.internal.ui.DelegatingModelPresentation.getText(DelegatingModelPresentation.java:156)\n        at\norg.eclipse.debug.internal.ui.views.DebugViewLabelDecorator$LabelJob.run(DebugViewLabelDecorator.java:316)\n        at org.eclipse.core.internal.jobs.Worker.run(Worker.java:67)",
    "\n\n*** This bug has been marked as a duplicate of 96964 ***"
  ],
  "commentCreationDates": [
    "2005-06-08T17:43:27+02:00",
    "2005-06-08T17:54:12+02:00"
  ],
  "traces": [
    {
      "exceptionType": "java.lang.ClassCastException",
      "elements": [
        {
          "method": "org.eclipse.jdt.internal.debug.core.model.JDIStackFrame.getDeclaringType",
          "source": "JDIStackFrame.java:1071"
        },
        {
          "method": "org.eclipse.jdt.internal.debug.ui.JDIModelPresentation.getStackFrameText",
          "source": "JDIModelPresentation.java:1652"
        },
        {
          "method": "org.eclipse.jdt.internal.debug.ui.JDIModelPresentation.getText",
          "source": "JDIModelPresentation.java:214"
        },
        {
          "method": "org.eclipse.debug.internal.ui.LazyModelPresentation.getText",
          "source": "LazyModelPresentation.java:153"
        },
        {
          "method": "org.eclipse.debug.internal.ui.DelegatingModelPresentation.getText",
          "source": "DelegatingModelPresentation.java:156"
        },
        {
          "method": "org.eclipse.debug.internal.ui.views.DebugViewLabelDecorator$LabelJob.run",
          "source": "DebugViewLabelDecorator.java:316"
        },
        {
          "method": "org.eclipse.core.internal.jobs.Worker.run",
          "source": "Worker.java:67"
        }
      ],
      "number": 0,
      "commentIndex": 0,
      "bugId": "98986",
      "duplicateId": "96964",
      "date": "2005-06-08T17:43:27+02:00",
      "product": "JDT",
      "component": "Debug",
      "severity": "normal"
    }
  ],
  "groupId": "96964",
  "bugId": "98986",
  "duplicateId": "96964",
  "date": "2005-06-08T17:43:27+02:00",
  "product": "JDT",
  "component": "Debug",
  "severity": "normal"
}