{
  "comments": [
    "Unfortunately I can\u0027t provide any other information as I have no idea what \ntriggers this exception... I\u0027ve got another project which is quite similar to \nthis and uses the same libraries and that one compiles fine.\n\n     [iajc] java.io.StreamCorruptedException: invalid stream header\n     [iajc]     at java.io.ObjectInputStream.readStreamHeader(ObjectInputStream.\njava:753)\n     [iajc]     at java.io.ObjectInputStream.\u003cinit\u003e(ObjectInputStream.java:268)\n     [iajc]     at org.aspectj.weaver.ResolvedTypeMunger.\nreadSourceLocation(ResolvedTypeMunger.java:153)\n     [iajc]     at org.aspectj.weaver.NewMethodTypeMunger.\nreadMethod(NewMethodTypeMunger.java:47)\n     [iajc]     at org.aspectj.weaver.ResolvedTypeMunger.\nread(ResolvedTypeMunger.java:107)\n     [iajc]     at org.aspectj.weaver.WeaverStateInfo.read(WeaverStateInfo.java:\n106)\n     [iajc]     at org.aspectj.weaver.AjAttribute.read(AjAttribute.java:95)\n     [iajc]     at org.aspectj.weaver.bcel.BcelAttributes.\nreadAjAttributes(BcelAttributes.java:42)\n     [iajc]     at org.aspectj.weaver.bcel.BcelObjectType.\nunpackAspectAttributes(BcelObjectType.java:199)\n     [iajc]     at org.aspectj.weaver.bcel.BcelObjectType.\u003cinit\u003e(BcelObjectType.\njava:103)\n     [iajc]     at org.aspectj.weaver.bcel.BcelWorld.\nmakeBcelObjectType(BcelWorld.java:239)\n     [iajc]     at org.aspectj.weaver.bcel.BcelWorld.\nresolveObjectType(BcelWorld.java:234)\n     [iajc]     at org.aspectj.weaver.World.resolveObjectType(World.java:163)\n     [iajc]     at org.aspectj.weaver.World.resolve(World.java:130)\n     [iajc]     at org.aspectj.weaver.World.resolve(World.java:109)\n     [iajc]     at org.aspectj.ajdt.internal.compiler.lookup.EclipseFactory.\nfromEclipse(EclipseFactory.java:116)\n     [iajc]     at org.aspectj.ajdt.internal.compiler.lookup.\nAjLookupEnvironment.weaveInterTypeDeclarations(AjLookupEnvironment.java:368)\n     [iajc]     at org.aspectj.ajdt.internal.compiler.lookup.\nAjLookupEnvironment.weaveInterTypeDeclarations(AjLookupEnvironment.java:362)\n     [iajc]     at org.aspectj.ajdt.internal.compiler.lookup.\nAjLookupEnvironment.createBinaryTypeFrom(AjLookupEnvironment.java:749)\n     [iajc]     at org.aspectj.org.eclipse.jdt.internal.compiler.lookup.\nLookupEnvironment.createBinaryTypeFrom(LookupEnvironment.java:407)\n     [iajc]     at org.aspectj.org.eclipse.jdt.internal.compiler.Compiler.\naccept(Compiler.java:191)\n     [iajc]     at org.aspectj.org.eclipse.jdt.internal.compiler.lookup.\nLookupEnvironment.askForType(LookupEnvironment.java:137)\n     [iajc]     at org.aspectj.org.eclipse.jdt.internal.compiler.lookup.\nPackageBinding.getTypeOrPackage(PackageBinding.java:178)\n     [iajc]     at org.aspectj.org.eclipse.jdt.internal.compiler.lookup.\nCompilationUnitScope.findImport(CompilationUnitScope.java:388)\n     [iajc]     at org.aspectj.org.eclipse.jdt.internal.compiler.lookup.\nCompilationUnitScope.findSingleImport(CompilationUnitScope.java:441)\n     [iajc]     at org.aspectj.org.eclipse.jdt.internal.compiler.lookup.\nCompilationUnitScope.faultInImports(CompilationUnitScope.java:314)\n     [iajc]     at org.aspectj.org.eclipse.jdt.internal.compiler.lookup.\nCompilationUnitScope.faultInTypes(CompilationUnitScope.java:375)\n     [iajc]     at org.aspectj.org.eclipse.jdt.internal.compiler.Compiler.\nprocess(Compiler.java:500)\n     [iajc]     at org.aspectj.org.eclipse.jdt.internal.compiler.Compiler.\ncompile(Compiler.java:330)\n     [iajc]     at org.aspectj.ajdt.internal.core.builder.AjBuildManager.\nperformCompilation(AjBuildManager.java:727)\n     [iajc]     at org.aspectj.ajdt.internal.core.builder.AjBuildManager.\ndoBuild(AjBuildManager.java:206)\n     [iajc]     at org.aspectj.ajdt.internal.core.builder.AjBuildManager.\nbatchBuild(AjBuildManager.java:140)\n     [iajc]     at org.aspectj.ajdt.ajc.AjdtCommand.doCommand(AjdtCommand.java:\n109)\n     [iajc]     at org.aspectj.ajdt.ajc.AjdtCommand.runCommand(AjdtCommand.java:\n60)\n     [iajc]     at org.aspectj.tools.ajc.Main.run(Main.java:291)\n     [iajc]     at org.aspectj.tools.ajc.Main.runMain(Main.java:227)\n     [iajc]     at org.aspectj.tools.ant.taskdefs.AjcTask.\nexecuteInSameVM(AjcTask.java:1218)\n     [iajc]     at org.aspectj.tools.ant.taskdefs.AjcTask.execute(AjcTask.java:\n988)\n     [iajc]     at org.apache.tools.ant.UnknownElement.execute(UnknownElement.\njava:269)\n     [iajc]     at org.apache.tools.ant.Task.perform(Task.java:364)\n     [iajc]     at org.apache.tools.ant.Target.execute(Target.java:301)\n     [iajc]     at org.apache.tools.ant.Target.performTasks(Target.java:328)\n     [iajc]     at org.apache.tools.ant.Project.executeTarget(Project.java:1215)\n     [iajc]     at org.apache.tools.ant.taskdefs.Ant.execute(Ant.java:383)\n     [iajc]     at org.apache.tools.ant.taskdefs.CallTarget.execute(CallTarget.\njava:107)\n     [iajc]     at org.apache.tools.ant.UnknownElement.execute(UnknownElement.\njava:269)\n     [iajc]     at org.apache.tools.ant.Task.perform(Task.java:364)\n     [iajc]     at org.apache.tools.ant.Target.execute(Target.java:301)\n     [iajc]     at org.apache.tools.ant.Target.performTasks(Target.java:328)\n     [iajc]     at org.apache.tools.ant.Project.executeTarget(Project.java:1215)\n     [iajc]     at org.apache.tools.ant.taskdefs.Ant.execute(Ant.java:383)\n     [iajc]     at org.apache.tools.ant.taskdefs.CallTarget.execute(CallTarget.\njava:107)\n     [iajc]     at org.apache.tools.ant.UnknownElement.execute(UnknownElement.\njava:269)\n     [iajc]     at org.apache.tools.ant.Task.perform(Task.java:364)\n     [iajc]     at org.apache.tools.ant.Target.execute(Target.java:301)\n     [iajc]     at org.apache.tools.ant.Target.performTasks(Target.java:328)\n     [iajc]     at org.apache.tools.ant.Project.executeTarget(Project.java:1215)\n     [iajc]     at org.apache.tools.ant.Project.executeTargets(Project.java:\n1063)\n     [iajc]     at org.apache.tools.ant.Main.runBuild(Main.java:632)\n     [iajc]     at org.apache.tools.ant.Main.startAnt(Main.java:183)\n     [iajc]     at org.apache.tools.ant.launch.Launcher.run(Launcher.java:197)\n     [iajc]     at org.apache.tools.ant.launch.Launcher.main(Launcher.java:56)\n     [iajc] D:\n\\work\\granite\\workspace\\nvsr\\src\\web\\java\\com\\netvisor\\nvsr\\web\\NVSRInstance.\njava [error] Internal compiler error\n     [iajc] org.aspectj.weaver.BCException: malformed org.aspectj.weaver.\nWeaverState attribute java.io.EOFException\n     [iajc]     at org.aspectj.weaver.AjAttribute.read(AjAttribute.java:121)\n     [iajc]     at org.aspectj.weaver.bcel.BcelAttributes.\nreadAjAttributes(BcelAttributes.java:42)\n     [iajc]     at org.aspectj.weaver.bcel.BcelObjectType.\nunpackAspectAttributes(BcelObjectType.java:199)\n     [iajc]     at org.aspectj.weaver.bcel.BcelObjectType.\u003cinit\u003e(BcelObjectType.\njava:103)\n     [iajc]     at org.aspectj.weaver.bcel.BcelWorld.\nmakeBcelObjectType(BcelWorld.java:239)\n     [iajc]     at org.aspectj.weaver.bcel.BcelWorld.\nresolveObjectType(BcelWorld.java:234)\n     [iajc]     at org.aspectj.weaver.World.resolveObjectType(World.java:163)\n     [iajc]     at org.aspectj.weaver.World.resolve(World.java:130)\n     [iajc]     at org.aspectj.weaver.World.resolve(World.java:109)\n     [iajc]     at org.aspectj.ajdt.internal.compiler.lookup.EclipseFactory.\nfromEclipse(EclipseFactory.java:116)\n     [iajc]     at org.aspectj.ajdt.internal.compiler.lookup.\nAjLookupEnvironment.weaveInterTypeDeclarations(AjLookupEnvironment.java:368)\n     [iajc]     at org.aspectj.ajdt.internal.compiler.lookup.\nAjLookupEnvironment.weaveInterTypeDeclarations(AjLookupEnvironment.java:362)\n     [iajc]     at org.aspectj.ajdt.internal.compiler.lookup.\nAjLookupEnvironment.createBinaryTypeFrom(AjLookupEnvironment.java:749)\n     [iajc]     at org.aspectj.org.eclipse.jdt.internal.compiler.lookup.\nLookupEnvironment.createBinaryTypeFrom(LookupEnvironment.java:407)\n     [iajc]     at org.aspectj.org.eclipse.jdt.internal.compiler.Compiler.\naccept(Compiler.java:191)\n     [iajc]     at org.aspectj.org.eclipse.jdt.internal.compiler.lookup.\nLookupEnvironment.askForType(LookupEnvironment.java:137)\n     [iajc]     at org.aspectj.org.eclipse.jdt.internal.compiler.lookup.\nPackageBinding.getTypeOrPackage(PackageBinding.java:178)\n     [iajc]     at org.aspectj.org.eclipse.jdt.internal.compiler.lookup.\nCompilationUnitScope.findImport(CompilationUnitScope.java:388)\n     [iajc]     at org.aspectj.org.eclipse.jdt.internal.compiler.lookup.\nCompilationUnitScope.findSingleImport(CompilationUnitScope.java:441)\n     [iajc]     at org.aspectj.org.eclipse.jdt.internal.compiler.lookup.\nCompilationUnitScope.faultInImports(CompilationUnitScope.java:314)\n     [iajc]     at org.aspectj.org.eclipse.jdt.internal.compiler.lookup.\nCompilationUnitScope.faultInTypes(CompilationUnitScope.java:375)\n     [iajc]     at org.aspectj.org.eclipse.jdt.internal.compiler.Compiler.\nprocess(Compiler.java:500)\n     [iajc]     at org.aspectj.org.eclipse.jdt.internal.compiler.Compiler.\ncompile(Compiler.java:330)\n     [iajc]     at org.aspectj.ajdt.internal.core.builder.AjBuildManager.\nperformCompilation(AjBuildManager.java:727)\n     [iajc]     at org.aspectj.ajdt.internal.core.builder.AjBuildManager.\ndoBuild(AjBuildManager.java:206)\n     [iajc]     at org.aspectj.ajdt.internal.core.builder.AjBuildManager.\nbatchBuild(AjBuildManager.java:140)\n     [iajc]     at org.aspectj.ajdt.ajc.AjdtCommand.doCommand(AjdtCommand.java:\n109)\n     [iajc]     at org.aspectj.ajdt.ajc.AjdtCommand.runCommand(AjdtCommand.java:\n60)\n     [iajc]     at org.aspectj.tools.ajc.Main.run(Main.java:291)\n     [iajc]     at org.aspectj.tools.ajc.Main.runMain(Main.java:227)\n     [iajc]     at org.aspectj.tools.ant.taskdefs.AjcTask.\nexecuteInSameVM(AjcTask.java:1218)\n     [iajc]     at org.aspectj.tools.ant.taskdefs.AjcTask.execute(AjcTask.java:\n988)\n     [iajc]     at org.apache.tools.ant.UnknownElement.execute(UnknownElement.\njava:269)\n     [iajc]     at org.apache.tools.ant.Task.perform(Task.java:364)\n     [iajc]     at org.apache.tools.ant.Target.execute(Target.java:301)\n     [iajc]     at org.apache.tools.ant.Target.performTasks(Target.java:328)\n     [iajc]     at org.apache.tools.ant.Project.executeTarget(Project.java:1215)\n     [iajc]     at org.apache.tools.ant.taskdefs.Ant.execute(Ant.java:383)\n     [iajc]     at org.apache.tools.ant.taskdefs.CallTarget.execute(CallTarget.\njava:107)\n     [iajc]     at org.apache.tools.ant.UnknownElement.execute(UnknownElement.\njava:269)\n     [iajc]     at org.apache.tools.ant.Task.perform(Task.java:364)\n     [iajc]     at org.apache.tools.ant.Target.execute(Target.java:301)\n     [iajc]     at org.apache.tools.ant.Target.performTasks(Target.java:328)\n     [iajc]     at org.apache.tools.ant.Project.executeTarget(Project.java:1215)\n     [iajc]     at org.apache.tools.ant.taskdefs.Ant.execute(Ant.java:383)\n     [iajc]     at org.apache.tools.ant.taskdefs.CallTarget.execute(CallTarget.\njava:107)\n     [iajc]     at org.apache.tools.ant.UnknownElement.execute(UnknownElement.\njava:269)\n     [iajc]     at org.apache.tools.ant.Task.perform(Task.java:364)\n     [iajc]     at org.apache.tools.ant.Target.execute(Target.java:301)\n     [iajc]     at org.apache.tools.ant.Target.performTasks(Target.java:328)\n     [iajc]     at org.apache.tools.ant.Project.executeTarget(Project.java:1215)\n     [iajc]     at org.apache.tools.ant.Project.executeTargets(Project.java:\n1063)\n     [iajc]     at org.apache.tools.ant.Main.runBuild(Main.java:632)\n     [iajc]     at org.apache.tools.ant.Main.startAnt(Main.java:183)\n     [iajc]     at org.apache.tools.ant.launch.Launcher.run(Launcher.java:197)\n     [iajc]     at org.apache.tools.ant.launch.Launcher.main(Launcher.java:56)",
    "appears to be an exact duplicate of bug 99582 where I\u0027ve already appended a comment.\n\n*** This bug has been marked as a duplicate of 99582 ***"
  ],
  "commentCreationDates": [
    "2005-06-13T14:51:38+02:00",
    "2005-06-14T10:43:27+02:00"
  ],
  "traces": [
    {
      "exceptionType": "java.io.StreamCorruptedException",
      "message": "invalid stream header      [iajc]",
      "elements": [
        {
          "method": "java.io.ObjectInputStream.readStreamHeader",
          "source": "ObjectInputStream. java:753"
        }
      ],
      "number": 0,
      "commentIndex": 0,
      "bugId": "99623",
      "duplicateId": "99582",
      "date": "2005-06-13T14:51:38+02:00",
      "product": "AspectJ",
      "component": "Compiler",
      "severity": "normal"
    },
    {
      "exceptionType": "org.aspectj.weaver.BCException",
      "message": "malformed org.aspectj.weaver. WeaverState attribute java.io.EOFException      [iajc]",
      "elements": [
        {
          "method": "org.aspectj.weaver.AjAttribute.read",
          "source": "AjAttribute.java:121"
        }
      ],
      "number": 1,
      "commentIndex": 0,
      "bugId": "99623",
      "duplicateId": "99582",
      "date": "2005-06-13T14:51:38+02:00",
      "product": "AspectJ",
      "component": "Compiler",
      "severity": "normal"
    }
  ],
  "groupId": "99582",
  "bugId": "99623",
  "duplicateId": "99582",
  "date": "2005-06-13T14:51:38+02:00",
  "product": "AspectJ",
  "component": "Compiler",
  "severity": "normal"
}